{
  "type": "Feature",
  "properties": {
    "iso:country":"US",
    "sg:address":"368 Shivers Green Rd",
    "sg:city":"Ridgeway",
    "sg:classifiers":[
        {
            "category":"Social Services",
            "type":"Services"
        }
    ],
    "sg:phone":"+1 803 408 1349",
    "sg:postcode":"29130",
    "sg:province":"SC",
    "sg:tags":[
        "referral"
    ],
    "wof:name":"Office Management Svc",
    "wof:placetype":"venue"
},
  "geometry": {"coordinates":[-80.796587,34.288903],"type":"Point"}
}