{
  "type": "Feature",
  "properties": {
    "iso:country":"US",
    "sg:address":"800 Tec Rd",
    "sg:city":"Cheraw",
    "sg:classifiers":[
        {
            "category":"Building & Trades",
            "subcategory":"Landscaping Services",
            "type":"Services"
        }
    ],
    "sg:phone":"+1 843 921 0809",
    "sg:postcode":"29520",
    "sg:province":"SC",
    "sg:tags":[
        "landscape"
    ],
    "wof:name":"Richard W Furr",
    "wof:placetype":"venue"
},
  "geometry": {"coordinates":[-79.938991,34.6864],"type":"Point"}
}