{
  "type": "Feature",
  "properties": {
    "iso:country":"US",
    "sg:address":"242 Kelley St",
    "sg:city":"Lake City",
    "sg:classifiers":[
        {
            "category":"Shopping",
            "subcategory":"Jewelry",
            "type":"Retail Goods"
        }
    ],
    "sg:phone":"+1 843 394 0833",
    "sg:postcode":"29560",
    "sg:province":"SC",
    "sg:tags":[
        "jeweler"
    ],
    "wof:name":"Friedmans Jewelers",
    "wof:placetype":"venue"
},
  "geometry": {"coordinates":[-79.75732499999999,33.877387],"type":"Point"}
}