{
  "type": "Feature",
  "properties": {
    "addr:full":"3958 Long Ave Exd Conway SC 29526",
    "addr:housenumber":"3958",
    "addr:postcode":"29526",
    "addr:street":"Long Ave Exd",
    "iso:country":"US",
    "sg:address":"3958 Long Ave Exd",
    "sg:city":"Conway",
    "sg:classifiers":[
        {
            "category":"Building & Trades",
            "subcategory":"Construction",
            "type":"Services"
        }
    ],
    "sg:phone":"+1 843 365 7267",
    "sg:postcode":"29526",
    "sg:province":"SC",
    "sg:tags":[
        "home",
        "builder"
    ],
    "wof:name":"Benchmark Construction & Invst",
    "wof:placetype":"venue"
},
  "geometry": {"coordinates":[-79.01260499999999,33.894084],"type":"Point"}
}