{
  "type": "Feature",
  "properties": {
    "addr:full":"422 N Cook St Bennettsville SC 29512",
    "addr:housenumber":"422",
    "addr:postcode":"29512",
    "addr:street":"N Cook St",
    "iso:country":"US",
    "sg:address":"422 N Cook St",
    "sg:city":"Bennettsville",
    "sg:classifiers":[
        {
            "category":"Building & Trades",
            "subcategory":"Plumbing",
            "type":"Services"
        }
    ],
    "sg:phone":"+1 843 479 6291",
    "sg:postcode":"29512",
    "sg:province":"SC",
    "sg:tags":[
        "heat",
        "pump"
    ],
    "wof:name":"Hamer's Heating & Cooling Inc",
    "wof:placetype":"venue"
},
  "geometry": {"coordinates":[-79.672248,34.632421],"type":"Point"}
}