{
  "type": "Feature",
  "properties": {
    "addr:full":"304 E Broad St Hemingway SC 29554",
    "addr:housenumber":"304",
    "addr:postcode":"29554",
    "addr:street":"E Broad St",
    "iso:country":"US",
    "sg:address":"304 E Broad St",
    "sg:city":"Hemingway",
    "sg:classifiers":[
        {
            "category":"Health Services",
            "subcategory":"Chiropractor",
            "type":"Services"
        }
    ],
    "sg:phone":"+1 843 558 0056",
    "sg:postcode":"29554",
    "sg:province":"SC",
    "wof:name":"Hemingway Spinal Care Ctr",
    "wof:placetype":"venue"
},
  "geometry": {"coordinates":[-79.44417900000001,33.753396],"type":"Point"}
}