{
  "type": "Feature",
  "properties": {
    "iso:country":"US",
    "sg:address":"2 Jonagold Ct",
    "sg:city":"Greenville",
    "sg:classifiers":[
        {
            "category":"Real Estate",
            "subcategory":"Real Estate Agent",
            "type":"Services"
        }
    ],
    "sg:phone":"+1 864 289 0458",
    "sg:postcode":"29607",
    "sg:province":"SC",
    "wof:name":"Forrester Chase Homes",
    "wof:placetype":"venue"
},
  "geometry": {"coordinates":[-82.308685,34.810463],"type":"Point"}
}