{
  "type": "Feature",
  "properties": {
    "iso:country":"US",
    "sg:address":"333 Dreher Rd",
    "sg:city":"West Columbia",
    "sg:classifiers":[
        {
            "category":"Wholesale",
            "subcategory":"Tobacco Products",
            "type":"Manufacturing & Wholesale Goods"
        }
    ],
    "sg:phone":"+1 803 791 7000",
    "sg:postcode":"29169",
    "sg:province":"SC",
    "sg:tags":[
        "cigarette",
        "cigar",
        "dealer"
    ],
    "wof:name":"H T Hackney Co",
    "wof:placetype":"venue"
},
  "geometry": {"coordinates":[-81.091644,33.977029],"type":"Point"}
}