{
  "type": "Feature",
  "properties": {
    "iso:country":"US",
    "sg:address":"1328 Broad St",
    "sg:city":"Sumter",
    "sg:classifiers":[
        {
            "category":"Restaurant",
            "type":"Food & Drink"
        }
    ],
    "sg:phone":"+1 803 469 9334",
    "sg:postcode":"29150",
    "sg:province":"SC",
    "wof:name":"Wanthani Bangkok Express",
    "wof:placetype":"venue"
},
  "geometry": {"coordinates":[-80.393089,33.957202],"type":"Point"}
}