{
  "type": "Feature",
  "properties": {
    "iso:country":"US",
    "sg:address":"32 Ann St",
    "sg:city":"Charleston",
    "sg:classifiers":[
        {
            "category":"Government",
            "subcategory":"Office",
            "type":"Public Place"
        }
    ],
    "sg:phone":"+1 843 724 3746",
    "sg:postcode":"29403",
    "sg:province":"SC",
    "sg:tags":[
        "village"
    ],
    "wof:name":"Charleston City Public Info",
    "wof:placetype":"venue"
},
  "geometry": {"coordinates":[-79.937697,32.789801],"type":"Point"}
}