{
  "type": "Feature",
  "properties": {
    "addr:full":"135 Dixie Rd Cheraw SC 29590",
    "addr:housenumber":"135",
    "addr:postcode":"29590",
    "addr:street":"Dixie Rd",
    "iso:country":"US",
    "sg:address":"135 Dixie Rd",
    "sg:city":"Cheraw",
    "sg:classifiers":[
        {
            "category":"Manufacturing",
            "subcategory":"Tools & Machinery",
            "type":"Manufacturing & Wholesale Goods"
        }
    ],
    "sg:phone":"+1 843 537 1940",
    "sg:postcode":"29590",
    "sg:province":"SC",
    "sg:tags":[
        "packaging"
    ],
    "sg:website":"www.brantec.com",
    "wof:name":"Brantec Packaging Machinery",
    "wof:placetype":"venue"
},
  "geometry": {"coordinates":[-79.833302,33.542722],"type":"Point"}
}