{
  "type": "Feature",
  "properties": {
    "addr:full":"1145 Dick Pond Rd Surfside Beach SC 29575",
    "addr:housenumber":"1145",
    "addr:postcode":"29575",
    "addr:street":"Dick Pond Rd",
    "iso:country":"US",
    "sg:address":"1145 Dick Pond Rd",
    "sg:city":"Surfside Beach",
    "sg:classifiers":[
        {
            "category":"Shopping",
            "type":"Retail Goods"
        }
    ],
    "sg:phone":"+1 843 238 2181",
    "sg:postcode":"29575",
    "sg:province":"SC",
    "sg:tags":[
        "pet",
        "shop"
    ],
    "wof:name":"Pet Paradise",
    "wof:placetype":"venue"
},
  "geometry": {"coordinates":[-78.963369,33.630867],"type":"Point"}
}