{
  "type": "Feature",
  "properties": {
    "addr:full":"104 Oley Dr Central SC 29630",
    "addr:housenumber":"104",
    "addr:postcode":"29630",
    "addr:street":"Oley Dr",
    "iso:country":"US",
    "sg:address":"104 Oley Dr",
    "sg:city":"Central",
    "sg:classifiers":[
        {
            "category":"Restaurant",
            "type":"Food & Drink"
        }
    ],
    "sg:phone":"+1 864 653 7485",
    "sg:postcode":"29630",
    "sg:province":"SC",
    "wof:name":"Los Amigos",
    "wof:placetype":"venue"
},
  "geometry": {"coordinates":[-82.846907,34.784445],"type":"Point"}
}