{
  "type": "Feature",
  "properties": {
    "iso:country":"US",
    "sg:address":"6432 Notch Rd",
    "sg:city":"Columbia",
    "sg:classifiers":[
        {
            "category":"Banks & Credit Unions",
            "subcategory":"Bank",
            "type":"Services"
        }
    ],
    "sg:phone":"+1 803 714 6384",
    "sg:postcode":"29223",
    "sg:province":"SC",
    "sg:tags":[
        "company",
        "consumer",
        "loan",
        "finance"
    ],
    "wof:name":"Quick Credit Corp",
    "wof:placetype":"venue"
},
  "geometry": {"coordinates":[-80.96660900000001,34.058167],"type":"Point"}
}