{
  "type": "Feature",
  "properties": {
    "iso:country":"US",
    "sg:address":"5485 Buck Hill Rd",
    "sg:city":"Myrtle Beach",
    "sg:classifiers":[
        {
            "category":"Home & Garden",
            "subcategory":"Home Furnishings",
            "type":"Retail Goods"
        }
    ],
    "sg:phone":"+1 843 293 0827",
    "sg:postcode":"29588",
    "sg:province":"SC",
    "sg:tags":[
        "curtain",
        "made",
        "drapery"
    ],
    "wof:name":"Myrtle Beach Blind & Drapery",
    "wof:placetype":"venue"
},
  "geometry": {"coordinates":[-78.968487,33.683555],"type":"Point"}
}