{
  "type": "Feature",
  "properties": {
    "iso:country":"US",
    "sg:address":"2702 Wise Rd",
    "sg:city":"Conway",
    "sg:classifiers":[
        {
            "category":"Professional",
            "subcategory":"Business Services",
            "type":"Services"
        }
    ],
    "sg:phone":"+1 843 365 9821",
    "sg:postcode":"29526",
    "sg:province":"SC",
    "sg:tags":[
        "notary"
    ],
    "wof:name":"My Mother's Prayers",
    "wof:placetype":"venue"
},
  "geometry": {"coordinates":[-79.039808,33.902088],"type":"Point"}
}