{
  "type": "Feature",
  "properties": {
    "iso:country":"US",
    "sg:address":"1005 Broughton St",
    "sg:city":"Orangeburg",
    "sg:classifiers":[
        {
            "category":"Shopping",
            "subcategory":"Computers & Home Electronics",
            "type":"Retail Goods"
        },
        {
            "category":"Shopping",
            "subcategory":"Musical Instruments",
            "type":"Retail Goods"
        }
    ],
    "sg:phone":"+1 803 516 0090",
    "sg:postcode":"29115",
    "sg:province":"SC",
    "wof:name":"Mark's Music",
    "wof:placetype":"venue"
},
  "geometry": {"coordinates":[-80.86438,33.487762],"type":"Point"}
}