{
  "type": "Feature",
  "properties": {
    "iso:country":"US",
    "sg:address":"4115 US Hwy 52",
    "sg:city":"Coward",
    "sg:classifiers":[
        {
            "category":"Autos & Motor Vehicles",
            "subcategory":"Automobile Sales",
            "type":"Retail Goods"
        }
    ],
    "sg:phone":"+1 843 389 2215",
    "sg:postcode":"29530",
    "sg:province":"SC",
    "sg:tags":[
        "car",
        "dealer"
    ],
    "wof:name":"Carolina Motor Sports",
    "wof:placetype":"venue"
},
  "geometry": {"coordinates":[-79.748722,33.97482],"type":"Point"}
}