{
  "type": "Feature",
  "properties": {
    "addr:full":"103 Applewood Center Pl Seneca SC 29678",
    "addr:housenumber":"103",
    "addr:postcode":"29678",
    "addr:street":"Applewood Center Pl",
    "iso:country":"US",
    "sg:address":"103 Applewood Center Pl",
    "sg:city":"Seneca",
    "sg:classifiers":[
        {
            "category":"Banks & Credit Unions",
            "subcategory":"Bank",
            "type":"Services"
        }
    ],
    "sg:phone":"+1 864 885 1500",
    "sg:postcode":"29678",
    "sg:province":"SC",
    "sg:tags":[
        "financing"
    ],
    "wof:name":"First Franklin Financial Corp",
    "wof:placetype":"venue"
},
  "geometry": {"coordinates":[-82.99226,34.689513],"type":"Point"}
}