{
  "type": "Feature",
  "properties": {
    "iso:country":"US",
    "sg:address":"1770 Camden Hwy",
    "sg:city":"Sumter",
    "sg:classifiers":[
        {
            "category":"Travel",
            "subcategory":"Travel Agent",
            "type":"Entertainment"
        }
    ],
    "sg:phone":"+1 803 469 3660",
    "sg:postcode":"29153",
    "sg:province":"SC",
    "sg:tags":[
        "agency"
    ],
    "wof:name":"Big Time Tours",
    "wof:placetype":"venue"
},
  "geometry": {"coordinates":[-80.392744,33.97138],"type":"Point"}
}