{
  "type": "Feature",
  "properties": {
    "iso:country":"US",
    "sg:address":"28 Stuart St",
    "sg:city":"Seabrook",
    "sg:classifiers":[
        {
            "category":"Building & Trades",
            "subcategory":"Construction",
            "type":"Services"
        }
    ],
    "sg:phone":"+1 843 846 0505",
    "sg:postcode":"29940",
    "sg:province":"SC",
    "sg:tags":[
        "heavy"
    ],
    "wof:name":"Olivers Bshhogging Grading LLC",
    "wof:placetype":"venue"
},
  "geometry": {"coordinates":[-80.772234,32.523527],"type":"Point"}
}