{
  "type": "Feature",
  "properties": {
    "iso:country":"US",
    "sg:address":"207 Whitsett St",
    "sg:city":"Greenville",
    "sg:classifiers":[
        {
            "category":"Real Estate",
            "subcategory":"Real Estate Agent",
            "type":"Services"
        }
    ],
    "sg:phone":"+1 864 232 0019",
    "sg:postcode":"29601",
    "sg:province":"SC",
    "wof:name":"JSI Realty Group",
    "wof:placetype":"venue"
},
  "geometry": {"coordinates":[-82.384507,34.852263],"type":"Point"}
}