{
  "type": "Feature",
  "properties": {
    "addr:full":"4809 Augusta Hwy Leesville SC 29070",
    "addr:housenumber":"4809",
    "addr:postcode":"29070",
    "addr:street":"Augusta Hwy",
    "iso:country":"US",
    "sg:address":"4809 Augusta Hwy",
    "sg:city":"Leesville",
    "sg:classifiers":[
        {
            "category":"Farming",
            "subcategory":"Farm",
            "type":"Manufacturing & Wholesale Goods"
        }
    ],
    "sg:phone":"+1 803 892 2040",
    "sg:postcode":"29070",
    "sg:province":"SC",
    "wof:name":"Wayne P Taylor Family Farms",
    "wof:placetype":"venue"
},
  "geometry": {"coordinates":[-81.420135,33.952369],"type":"Point"}
}