{
  "type": "Feature",
  "properties": {
    "addr:full":"951 Colony Rd Chester SC 29706",
    "addr:housenumber":"951",
    "addr:postcode":"29706",
    "addr:street":"Colony Rd",
    "iso:country":"US",
    "sg:address":"951 Colony Rd",
    "sg:city":"Chester",
    "sg:classifiers":[
        {
            "category":"Retail",
            "subcategory":"Repair Shop",
            "type":"Services"
        }
    ],
    "sg:phone":"+1 803 581 6579",
    "sg:postcode":"29706",
    "sg:province":"SC",
    "sg:tags":[
        "repairing",
        "lawn",
        "mower"
    ],
    "wof:name":"Mc Cree's Small Engines",
    "wof:placetype":"venue"
},
  "geometry": {"coordinates":[-81.184202,34.81118],"type":"Point"}
}