{
  "type": "Feature",
  "properties": {
    "iso:country":"US",
    "sg:address":"310 Lee St",
    "sg:city":"Anderson",
    "sg:classifiers":[
        {
            "category":"Social Services",
            "type":"Services"
        }
    ],
    "sg:phone":"+1 864 224 8586",
    "sg:postcode":"29625",
    "sg:province":"SC",
    "sg:tags":[
        "organization",
        "welfare"
    ],
    "wof:name":"Share Headstart",
    "wof:placetype":"venue"
},
  "geometry": {"coordinates":[-82.657908,34.51564],"type":"Point"}
}