{
  "type": "Feature",
  "properties": {
    "addr:full":"337 Aspen Loop Pawleys Island SC 29585",
    "addr:housenumber":"337",
    "addr:postcode":"29585",
    "addr:street":"Aspen Loop",
    "iso:country":"US",
    "sg:address":"337 Aspen Loop",
    "sg:city":"Pawleys Island",
    "sg:classifiers":[
        {
            "category":"Real Estate",
            "subcategory":"Real Estate Agent",
            "type":"Services"
        }
    ],
    "sg:phone":"+1 843 240 7355",
    "sg:postcode":"29585",
    "sg:province":"SC",
    "wof:name":"Brian Burbage Real Estate",
    "wof:placetype":"venue"
},
  "geometry": {"coordinates":[-79.12584699999999,33.471153],"type":"Point"}
}