{
  "type": "Feature",
  "properties": {
    "iso:country":"US",
    "sg:address":"482 Windy Hill Ln",
    "sg:city":"Lancaster",
    "sg:classifiers":[
        {
            "category":"Building & Trades",
            "subcategory":"Construction",
            "type":"Services"
        }
    ],
    "sg:phone":"+1 803 286 6474",
    "sg:postcode":"29720",
    "sg:province":"SC",
    "sg:tags":[
        "residential",
        "gen",
        "contractor"
    ],
    "wof:name":"Blackmon Construction Co",
    "wof:placetype":"venue"
},
  "geometry": {"coordinates":[-80.66636,34.721177],"type":"Point"}
}