{
  "type": "Feature",
  "properties": {
    "iso:country":"US",
    "sg:address":"731 Broad St",
    "sg:city":"Sumter",
    "sg:classifiers":[
        {
            "category":"Freight",
            "type":"Transportation"
        }
    ],
    "sg:phone":"+1 803 775 9202",
    "sg:postcode":"29150",
    "sg:province":"SC",
    "sg:tags":[
        "special",
        "general"
    ],
    "wof:name":"Sumter Self Storage",
    "wof:placetype":"venue"
},
  "geometry": {"coordinates":[-80.36656000000001,33.941438],"type":"Point"}
}