{
  "type": "Feature",
  "properties": {
    "iso:country":"US",
    "sg:address":"1209 Eisenhower Rd",
    "sg:city":"Rock Hill",
    "sg:classifiers":[
        {
            "category":"Organizations",
            "subcategory":"Religious Organization",
            "type":"Services"
        }
    ],
    "sg:phone":"+1 803 366 7597",
    "sg:postcode":"29730",
    "sg:province":"SC",
    "sg:tags":[
        "church"
    ],
    "sg:website":"www.cpbaptist.info",
    "wof:name":"College Park Baptist Church",
    "wof:placetype":"venue"
},
  "geometry": {"coordinates":[-81.016124,34.951383],"type":"Point"}
}