{
  "type": "Feature",
  "properties": {
    "addr:full":"554 Meeting St West Columbia SC 29169",
    "addr:housenumber":"554",
    "addr:postcode":"29169",
    "addr:street":"Meeting St",
    "iso:country":"US",
    "sg:address":"554 Meeting St",
    "sg:city":"West Columbia",
    "sg:classifiers":[
        {
            "category":"Organizations",
            "subcategory":"Religious Organization",
            "type":"Services"
        }
    ],
    "sg:phone":"+1 803 926 0481",
    "sg:postcode":"29169",
    "sg:province":"SC",
    "sg:tags":[
        "church"
    ],
    "wof:name":"Rhema Christian Ctr",
    "wof:placetype":"venue"
},
  "geometry": {"coordinates":[-81.060091,33.993442],"type":"Point"}
}