{
  "type": "Feature",
  "properties": {
    "addr:full":"2222 Augusta St Greenville SC 29605",
    "addr:housenumber":"2222",
    "addr:postcode":"29605",
    "addr:street":"Augusta St",
    "iso:country":"US",
    "sg:address":"2222 Augusta St",
    "sg:city":"Greenville",
    "sg:classifiers":[
        {
            "category":"Wholesale",
            "subcategory":"Apparel",
            "type":"Manufacturing & Wholesale Goods"
        },
        {
            "category":"Shopping",
            "subcategory":"Shoes",
            "type":"Retail Goods"
        }
    ],
    "sg:phone":"+1 864 271 9750",
    "sg:postcode":"29605",
    "sg:province":"SC",
    "sg:tags":[
        "shoes-wholesale",
        "store",
        "manufacturer"
    ],
    "wof:name":"Muse Shoe Studio",
    "wof:placetype":"venue"
},
  "geometry": {"coordinates":[-82.39261500000001,34.823526],"type":"Point"}
}