{
  "type": "Feature",
  "properties": {
    "addr:full":"684 Edgefield Rd Cowpens SC 29330",
    "addr:housenumber":"684",
    "addr:postcode":"29330",
    "addr:street":"Edgefield Rd",
    "iso:country":"US",
    "sg:address":"684 Edgefield Rd",
    "sg:city":"Cowpens",
    "sg:classifiers":[
        {
            "category":"Building & Trades",
            "subcategory":"Electrical",
            "type":"Services"
        }
    ],
    "sg:phone":"+1 864 463 3872",
    "sg:postcode":"29330",
    "sg:province":"SC",
    "sg:tags":[
        "electrical",
        "contractor"
    ],
    "wof:name":"Als Of Nc Inc",
    "wof:placetype":"venue"
},
  "geometry": {"coordinates":[-81.809557,35.046735],"type":"Point"}
}