{
  "type": "Feature",
  "properties": {
    "iso:country":"US",
    "sg:address":"174 Misty Glen Rd",
    "sg:city":"St George",
    "sg:classifiers":[
        {
            "category":"Utilities",
            "subcategory":"Telephone",
            "type":"Services"
        }
    ],
    "sg:phone":"+1 843 563 8159",
    "sg:postcode":"29477",
    "sg:province":"SC",
    "sg:tags":[
        "telecommunication"
    ],
    "wof:name":"American Tower Corp",
    "wof:placetype":"venue"
},
  "geometry": {"coordinates":[-80.566672,33.265931],"type":"Point"}
}