{
  "type": "Feature",
  "properties": {
    "iso:country":"US",
    "sg:address":"1 New Orleans Rd",
    "sg:city":"Hilton Head Isle",
    "sg:classifiers":[
        {
            "category":"Cinema",
            "subcategory":"Movie Rental",
            "type":"Entertainment"
        }
    ],
    "sg:phone":"+1 843 842 8945",
    "sg:postcode":"29928",
    "sg:province":"SC",
    "sg:tags":[
        "leasing",
        "video",
        "disc",
        "tape"
    ],
    "wof:name":"Blockbuster Video",
    "wof:placetype":"venue"
},
  "geometry": {"coordinates":[-80.755073,32.157283],"type":"Point"}
}