{
  "type": "Feature",
  "properties": {
    "iso:country":"US",
    "sg:address":"431 N Harper St",
    "sg:city":"Laurens",
    "sg:classifiers":[
        {
            "category":"Shopping",
            "type":"Retail Goods"
        }
    ],
    "sg:phone":"+1 864 984 9346",
    "sg:postcode":"29360",
    "sg:province":"SC",
    "sg:tags":[
        "telephone",
        "cellular"
    ],
    "wof:name":"Laurens Cellular & Paging",
    "wof:placetype":"venue"
},
  "geometry": {"coordinates":[-82.00909799999999,34.505908],"type":"Point"}
}