{
  "type": "Feature",
  "properties": {
    "addr:full":"360 Firetower Rd Irmo SC 29063",
    "addr:housenumber":"360",
    "addr:postcode":"29063",
    "addr:street":"Firetower Rd",
    "iso:country":"US",
    "sg:address":"360 Firetower Rd",
    "sg:city":"Irmo",
    "sg:classifiers":[
        {
            "category":"Building & Trades",
            "subcategory":"Construction",
            "type":"Services"
        }
    ],
    "sg:phone":"+1 803 781 3127",
    "sg:postcode":"29063",
    "sg:province":"SC",
    "sg:tags":[
        "excavation",
        "contractor"
    ],
    "wof:name":"Corley Construction",
    "wof:placetype":"venue"
},
  "geometry": {"coordinates":[-81.18056799999999,34.109954],"type":"Point"}
}