{
  "type": "Feature",
  "properties": {
    "addr:full":"107 Westpark Blvd Columbia SC 29210",
    "addr:housenumber":"107",
    "addr:postcode":"29210",
    "addr:street":"Westpark Blvd",
    "iso:country":"US",
    "sg:address":"107 Westpark Blvd",
    "sg:city":"Columbia",
    "sg:classifiers":[
        {
            "category":"Insurance",
            "subcategory":"Insurance Agent",
            "type":"Services"
        }
    ],
    "sg:phone":"+1 803 933 0627",
    "sg:postcode":"29210",
    "sg:province":"SC",
    "wof:name":"Horace Mann Insurance Co",
    "wof:placetype":"venue"
},
  "geometry": {"coordinates":[-81.133083,34.061169],"type":"Point"}
}