{
  "type": "Feature",
  "properties": {
    "iso:country":"US",
    "sg:address":"28 Tidalfield Ct",
    "sg:city":"Pawleys Island",
    "sg:classifiers":[
        {
            "category":"Health Services",
            "subcategory":"Health Practitioner",
            "type":"Services"
        }
    ],
    "sg:phone":"+1 843 235 9800",
    "sg:postcode":"29585",
    "sg:province":"SC",
    "sg:tags":[
        "nutrition",
        "consultant"
    ],
    "wof:name":"Shaklee Nutrition Air Prfctn",
    "wof:placetype":"venue"
},
  "geometry": {"coordinates":[-79.14412900000001,33.460764],"type":"Point"}
}