{
  "type": "Feature",
  "properties": {
    "addr:full":"12087 Wells Hwy Seneca SC 29678",
    "addr:housenumber":"12087",
    "addr:postcode":"29678",
    "addr:street":"Wells Hwy",
    "iso:country":"US",
    "sg:address":"12087 Wells Hwy",
    "sg:city":"Seneca",
    "sg:classifiers":[
        {
            "category":"Wholesale",
            "subcategory":"Durable Goods & Equipment",
            "type":"Manufacturing & Wholesale Goods"
        }
    ],
    "sg:phone":"+1 864 882 5642",
    "sg:postcode":"29678",
    "sg:province":"SC",
    "sg:tags":[
        "importer"
    ],
    "wof:name":"Rochester Imports",
    "wof:placetype":"venue"
},
  "geometry": {"coordinates":[-82.980092,34.667795],"type":"Point"}
}