{
  "type": "Feature",
  "properties": {
    "iso:country":"US",
    "sg:address":"2043 S Church St Exd",
    "sg:city":"Spartanburg",
    "sg:classifiers":[
        {
            "category":"Food & Beverages",
            "subcategory":"Fruits & Vegetables",
            "type":"Retail Goods"
        }
    ],
    "sg:phone":"+1 864 582 5337",
    "sg:postcode":"29306",
    "sg:province":"SC",
    "sg:tags":[
        "produce"
    ],
    "wof:name":"Mr Produce",
    "wof:placetype":"venue"
},
  "geometry": {"coordinates":[-81.936059,34.92089],"type":"Point"}
}