{
  "type": "Feature",
  "properties": {
    "addr:full":"10696 Old White Horse Rd Travelers Rest SC 29690",
    "addr:housenumber":"10696",
    "addr:postcode":"29690",
    "addr:street":"Old White Horse Rd",
    "iso:country":"US",
    "sg:address":"10696 Old White Horse Rd",
    "sg:city":"Travelers Rest",
    "sg:classifiers":[
        {
            "category":"Professional",
            "subcategory":"Advertising",
            "type":"Services"
        }
    ],
    "sg:phone":"+1 864 834 5177",
    "sg:postcode":"29690",
    "sg:province":"SC",
    "sg:tags":[
        "distribution"
    ],
    "wof:name":"SCDI",
    "wof:placetype":"venue"
},
  "geometry": {"coordinates":[-82.474119,34.951439],"type":"Point"}
}