{
  "type": "Feature",
  "properties": {
    "iso:country":"US",
    "sg:address":"1705 Edge Dr",
    "sg:city":"North Myrtle Bch",
    "sg:classifiers":[
        {
            "category":"Recreation",
            "type":"Entertainment"
        }
    ],
    "sg:phone":"+1 843 272 3657",
    "sg:postcode":"29582",
    "sg:province":"SC",
    "sg:tags":[
        "aquarium"
    ],
    "wof:name":"World Marine Aquarium Mntnc",
    "wof:placetype":"venue"
},
  "geometry": {"coordinates":[-78.702843,33.810658],"type":"Point"}
}