{
  "type": "Feature",
  "properties": {
    "iso:country":"US",
    "sg:address":"1020 Powdersville Rd",
    "sg:city":"Easley",
    "sg:classifiers":[
        {
            "category":"Restaurant",
            "type":"Food & Drink"
        }
    ],
    "sg:phone":"+1 864 442 1400",
    "sg:postcode":"29642",
    "sg:province":"SC",
    "sg:tags":[
        "eating"
    ],
    "wof:name":"Mutts B B Q Restaurant",
    "wof:placetype":"venue"
},
  "geometry": {"coordinates":[-82.54928,34.812516],"type":"Point"}
}