{
  "type": "Feature",
  "properties": {
    "iso:country":"US",
    "sg:address":"14 New Orleans Rd",
    "sg:city":"Hilton Head Isle",
    "sg:classifiers":[
        {
            "category":"Autos & Motor Vehicles",
            "subcategory":"Auto Supplies",
            "type":"Retail Goods"
        }
    ],
    "sg:phone":"+1 843 341 9091",
    "sg:postcode":"29928",
    "sg:province":"SC",
    "sg:tags":[
        "automobile",
        "parts"
    ],
    "wof:name":"Auto Parts World",
    "wof:placetype":"venue"
},
  "geometry": {"coordinates":[-80.753054,32.158604],"type":"Point"}
}