{
  "type": "Feature",
  "properties": {
    "iso:country":"US",
    "sg:address":"129 Burton Hill Rd",
    "sg:city":"Beaufort",
    "sg:classifiers":[
        {
            "category":"Building & Trades",
            "subcategory":"Electrical",
            "type":"Services"
        }
    ],
    "sg:phone":"+1 843 522 8880",
    "sg:postcode":"29906",
    "sg:province":"SC",
    "sg:tags":[
        "security",
        "audio",
        "installation",
        "system",
        "contractor"
    ],
    "wof:name":"Bay Street Sound & Security",
    "wof:placetype":"venue"
},
  "geometry": {"coordinates":[-80.717101,32.430816],"type":"Point"}
}