{
  "type": "Feature",
  "properties": {
    "addr:full":"203 Cash Control Rd Newberry SC 29108",
    "addr:housenumber":"203",
    "addr:postcode":"29108",
    "addr:street":"Control Rd",
    "iso:country":"US",
    "sg:address":"203 Cash Control Rd",
    "sg:city":"Newberry",
    "sg:classifiers":[
        {
            "category":"Professional",
            "type":"Services"
        }
    ],
    "sg:phone":"+1 803 405 7260",
    "sg:postcode":"29108",
    "sg:province":"SC",
    "sg:website":"www.insitesupport.com",
    "wof:name":"Insite Support Svc Inc",
    "wof:placetype":"venue"
},
  "geometry": {"coordinates":[-81.569309,34.249625],"type":"Point"}
}