{
  "type": "Feature",
  "properties": {
    "addr:full":"802 S Batesville Rd Greer SC 29650",
    "addr:housenumber":"802",
    "addr:postcode":"29650",
    "addr:street":"S Batesville Rd",
    "iso:country":"US",
    "sg:address":"802 S Batesville Rd",
    "sg:city":"Greer",
    "sg:classifiers":[
        {
            "category":"Personal",
            "subcategory":"Beauty Salon",
            "type":"Services"
        }
    ],
    "sg:phone":"+1 864 801 8014",
    "sg:postcode":"29650",
    "sg:province":"SC",
    "wof:name":"Ivy Salon & Spa",
    "wof:placetype":"venue"
},
  "geometry": {"coordinates":[-82.25713,34.875213],"type":"Point"}
}