{
  "type": "Feature",
  "properties": {
    "iso:country":"US",
    "sg:address":"404 S 3rd St",
    "sg:city":"Florence",
    "sg:classifiers":[
        {
            "category":"Organizations",
            "subcategory":"Religious Organization",
            "type":"Services"
        }
    ],
    "sg:phone":"+1 843 662 0389",
    "sg:postcode":"29506",
    "sg:province":"SC",
    "sg:tags":[
        "church"
    ],
    "wof:name":"Palmetto St Church Of Christ",
    "wof:placetype":"venue"
},
  "geometry": {"coordinates":[-79.741382,34.190328],"type":"Point"}
}