{
  "type": "Feature",
  "properties": {
    "iso:country":"US",
    "sg:address":"102 E Main St",
    "sg:city":"Lake City",
    "sg:classifiers":[
        {
            "category":"Banks & Credit Unions",
            "subcategory":"Investment Brokerage",
            "type":"Services"
        }
    ],
    "sg:phone":"+1 843 374 8786",
    "sg:postcode":"29560",
    "sg:province":"SC",
    "wof:name":"Harold Stuckey Investments",
    "wof:placetype":"venue"
},
  "geometry": {"coordinates":[-79.754472,33.872886],"type":"Point"}
}