{
  "type": "Feature",
  "properties": {
    "iso:country":"US",
    "sg:address":"15 Caldwell St",
    "sg:city":"Sumter",
    "sg:classifiers":[
        {
            "category":"Real Estate",
            "subcategory":"Real Estate Agent",
            "type":"Services"
        }
    ],
    "sg:phone":"+1 803 775 4357",
    "sg:postcode":"29150",
    "sg:province":"SC",
    "sg:tags":[
        "authorities",
        "housing"
    ],
    "wof:name":"Housing Authority Of Sumter",
    "wof:placetype":"venue"
},
  "geometry": {"coordinates":[-80.34166,33.918858],"type":"Point"}
}