{
  "type": "Feature",
  "properties": {
    "addr:full":"3530 Delree St West Columbia SC 29170",
    "addr:housenumber":"3530",
    "addr:postcode":"29170",
    "addr:street":"Delree St",
    "iso:country":"US",
    "sg:address":"3530 Delree St",
    "sg:city":"West Columbia",
    "sg:classifiers":[
        {
            "category":"Autos & Motor Vehicles",
            "subcategory":"Automobile Sales",
            "type":"Retail Goods"
        }
    ],
    "sg:phone":"+1 803 794 2549",
    "sg:postcode":"29170",
    "sg:province":"SC",
    "sg:tags":[
        "used"
    ],
    "wof:name":"Shaws Used Cars",
    "wof:placetype":"venue"
},
  "geometry": {"coordinates":[-81.135256,33.971843],"type":"Point"}
}