{
  "type": "Feature",
  "properties": {
    "addr:full":"128 Inway Dr Columbia SC 29223",
    "addr:housenumber":"128",
    "addr:postcode":"29223",
    "addr:street":"Inway Dr",
    "iso:country":"US",
    "sg:address":"128 Inway Dr",
    "sg:city":"Columbia",
    "sg:classifiers":[
        {
            "category":"Building & Trades",
            "subcategory":"Landscaping Services",
            "type":"Services"
        }
    ],
    "sg:phone":"+1 803 730 1652",
    "sg:postcode":"29223",
    "sg:province":"SC",
    "sg:tags":[
        "landscape",
        "contractor"
    ],
    "wof:name":"Cut-M-Up Lawn Svc",
    "wof:placetype":"venue"
},
  "geometry": {"coordinates":[-80.906977,34.12758],"type":"Point"}
}