{
  "type": "Feature",
  "properties": {
    "addr:full":"1009 Gervais St Columbia SC 29201",
    "addr:housenumber":"1009",
    "addr:postcode":"29201",
    "addr:street":"Gervais St",
    "iso:country":"US",
    "sg:address":"1009 Gervais St",
    "sg:city":"Columbia",
    "sg:classifiers":[
        {
            "category":"Restaurant",
            "type":"Food & Drink"
        }
    ],
    "sg:phone":"+1 803 933 9201",
    "sg:postcode":"29201",
    "sg:province":"SC",
    "sg:tags":[
        "pizza"
    ],
    "sg:website":"www.mellowmushroom.com",
    "wof:name":"Mellow Mushroom",
    "wof:placetype":"venue"
},
  "geometry": {"coordinates":[-81.0355,34.0009],"type":"Point"}
}