{
  "type": "Feature",
  "properties": {
    "iso:country":"US",
    "sg:address":"4200 E North St",
    "sg:city":"Greenville",
    "sg:classifiers":[
        {
            "category":"Health Services",
            "subcategory":"Doctor",
            "type":"Services"
        }
    ],
    "sg:phone":"+1 864 292 2266",
    "sg:postcode":"29615",
    "sg:province":"SC",
    "sg:tags":[
        "physician",
        "surgeon"
    ],
    "sg:website":"www.doctorscare.com",
    "wof:name":"Doctor's Care",
    "wof:placetype":"venue"
},
  "geometry": {"coordinates":[-82.31651599999999,34.879113],"type":"Point"}
}