{
  "type": "Feature",
  "properties": {
    "addr:full":"278 Hook Ln Mt Pleasant SC 29464",
    "addr:housenumber":"278",
    "addr:postcode":"29464",
    "addr:street":"Hook Ln",
    "iso:country":"US",
    "sg:address":"278 Hook Ln",
    "sg:city":"Mt Pleasant",
    "sg:classifiers":[
        {
            "category":"Wholesale",
            "subcategory":"Machinery & Supplies",
            "type":"Manufacturing & Wholesale Goods"
        },
        {
            "category":"Manufacturing",
            "subcategory":"Metals",
            "type":"Manufacturing & Wholesale Goods"
        }
    ],
    "sg:phone":"+1 843 216 0499",
    "sg:postcode":"29464",
    "sg:province":"SC",
    "sg:tags":[
        "valve"
    ],
    "wof:name":"Hora North America Inc",
    "wof:placetype":"venue"
},
  "geometry": {"coordinates":[-79.873271,32.833115],"type":"Point"}
}