{
  "type": "Feature",
  "properties": {
    "addr:full":"145 S Harvin St Sumter SC 29150",
    "addr:housenumber":"145",
    "addr:postcode":"29150",
    "addr:street":"S Harvin St",
    "iso:country":"US",
    "sg:address":"145 S Harvin St",
    "sg:city":"Sumter",
    "sg:classifiers":[
        {
            "category":"Wholesale",
            "subcategory":"Beer",
            "type":"Manufacturing & Wholesale Goods"
        }
    ],
    "sg:phone":"+1 803 775 5346",
    "sg:postcode":"29150",
    "sg:province":"SC",
    "sg:tags":[
        "ale"
    ],
    "wof:name":"Dixie-Central Distributing Co",
    "wof:placetype":"venue"
},
  "geometry": {"coordinates":[-80.34044799999999,33.915837],"type":"Point"}
}