{
  "type": "Feature",
  "properties": {
    "iso:country":"US",
    "sg:address":"145 S Harvin St",
    "sg:city":"Sumter",
    "sg:classifiers":[
        {
            "category":"Wholesale",
            "subcategory":"Beer",
            "type":"Manufacturing & Wholesale Goods"
        }
    ],
    "sg:phone":"+1 803 775 5346",
    "sg:postcode":"29150",
    "sg:province":"SC",
    "sg:tags":[
        "ale"
    ],
    "wof:name":"Dixie-Central Distributing Co",
    "wof:placetype":"venue"
},
  "geometry": {"coordinates":[-80.340448,33.915837],"type":"Point"}
}