{
  "type": "Feature",
  "properties": {
    "iso:country":"US",
    "sg:address":"112 Justin Ln",
    "sg:city":"Central",
    "sg:classifiers":[
        {
            "category":"Building & Trades",
            "subcategory":"Construction",
            "type":"Services"
        }
    ],
    "sg:phone":"+1 864 868 9301",
    "sg:postcode":"29630",
    "sg:province":"SC",
    "sg:tags":[
        "home",
        "builder"
    ],
    "wof:name":"Junior Pilgrim Builders",
    "wof:placetype":"venue"
},
  "geometry": {"coordinates":[-82.791394,34.786626],"type":"Point"}
}