{
  "type": "Feature",
  "properties": {
    "iso:country":"US",
    "sg:address":"2339 Broad St",
    "sg:city":"Camden",
    "sg:classifiers":[
        {
            "category":"Shopping",
            "subcategory":"Pharmacy",
            "type":"Retail Goods"
        }
    ],
    "sg:phone":"+1 803 425 8378",
    "sg:postcode":"29020",
    "sg:province":"SC",
    "sg:website":"www.hawthornesc.com",
    "wof:name":"Hawthorne Camden Pharmacy",
    "wof:placetype":"venue"
},
  "geometry": {"coordinates":[-80.609472,34.270085],"type":"Point"}
}