{
  "type": "Feature",
  "properties": {
    "iso:country":"US",
    "sg:address":"8395 Manse Rd",
    "sg:city":"Edisto Island",
    "sg:classifiers":[
        {
            "category":"Recreation",
            "type":"Entertainment"
        }
    ],
    "sg:phone":"+1 843 869 7733",
    "sg:postcode":"29438",
    "sg:province":"SC",
    "sg:tags":[
        "party",
        "fishing"
    ],
    "wof:name":"Bushwacker Sport Fishing",
    "wof:placetype":"venue"
},
  "geometry": {"coordinates":[-80.319572,32.561383],"type":"Point"}
}