{
  "type": "Feature",
  "properties": {
    "iso:country":"US",
    "sg:address":"116 River St",
    "sg:city":"Belton",
    "sg:classifiers":[
        {
            "category":"Shopping",
            "subcategory":"Department Store",
            "type":"Retail Goods"
        }
    ],
    "sg:phone":"+1 864 338 1063",
    "sg:postcode":"29627",
    "sg:province":"SC",
    "sg:tags":[
        "shop"
    ],
    "wof:name":"Fred's Store",
    "wof:placetype":"venue"
},
  "geometry": {"coordinates":[-82.492124,34.523752],"type":"Point"}
}