{
  "type": "Feature",
  "properties": {
    "addr:full":"129 Ashley Trace Dr Lexington SC 29072",
    "addr:housenumber":"129",
    "addr:postcode":"29072",
    "addr:street":"Ashley Trace Dr",
    "iso:country":"US",
    "sg:address":"129 Ashley Trace Dr",
    "sg:city":"Lexington",
    "sg:classifiers":[
        {
            "category":"Professional",
            "subcategory":"Management & Consulting",
            "type":"Services"
        }
    ],
    "sg:phone":"+1 803 957 5874",
    "sg:postcode":"29072",
    "sg:province":"SC",
    "sg:tags":[
        "consultant",
        "training"
    ],
    "wof:name":"Taylor & Assoc",
    "wof:placetype":"venue"
},
  "geometry": {"coordinates":[-81.19802900000001,34.01158],"type":"Point"}
}