{
  "type": "Feature",
  "properties": {
    "addr:full":"115 W Pearl St Spartanburg SC 29303",
    "addr:housenumber":"115",
    "addr:postcode":"29303",
    "addr:street":"W Pearl St",
    "iso:country":"US",
    "sg:address":"115 W Pearl St",
    "sg:city":"Spartanburg",
    "sg:classifiers":[
        {
            "category":"Shopping",
            "type":"Retail Goods"
        }
    ],
    "sg:phone":"+1 864 582 0046",
    "sg:postcode":"29303",
    "sg:province":"SC",
    "sg:tags":[
        "picture",
        "frame"
    ],
    "wof:name":"R I Designs",
    "wof:placetype":"venue"
},
  "geometry": {"coordinates":[-81.941608,34.960433],"type":"Point"}
}