{
  "type": "Feature",
  "properties": {
    "iso:country":"US",
    "sg:address":"813 E Palmetto St",
    "sg:city":"Florence",
    "sg:classifiers":[
        {
            "category":"Food & Beverages",
            "subcategory":"Groceries & Convenience Stores",
            "type":"Retail Goods"
        }
    ],
    "sg:phone":"+1 843 662 4359",
    "sg:postcode":"29506",
    "sg:province":"SC",
    "sg:tags":[
        "grocer"
    ],
    "wof:name":"Tommy's Thriftway",
    "wof:placetype":"venue"
},
  "geometry": {"coordinates":[-79.756017,34.194383],"type":"Point"}
}