{
  "type": "Feature",
  "properties": {
    "addr:full":"213 Retro Dr Aiken SC 29801",
    "addr:housenumber":"213",
    "addr:postcode":"29801",
    "addr:street":"Retro Dr",
    "iso:country":"US",
    "sg:address":"213 Retro Dr",
    "sg:city":"Aiken",
    "sg:classifiers":[
        {
            "category":"Real Estate",
            "subcategory":"Real Estate Operator",
            "type":"Services"
        }
    ],
    "sg:phone":"+1 803 649 7579",
    "sg:postcode":"29801",
    "sg:province":"SC",
    "sg:tags":[
        "mobile",
        "home",
        "community"
    ],
    "wof:name":"Lamplight Trailer Park",
    "wof:placetype":"venue"
},
  "geometry": {"coordinates":[-81.672119,33.54839],"type":"Point"}
}