{
  "type": "Feature",
  "properties": {
    "iso:country":"US",
    "sg:address":"1605 Timberland Ct",
    "sg:city":"York",
    "sg:classifiers":[
        {
            "category":"Wholesale",
            "subcategory":"Construction Materials",
            "type":"Manufacturing & Wholesale Goods"
        }
    ],
    "sg:phone":"+1 803 628 6044",
    "sg:postcode":"29745",
    "sg:province":"SC",
    "sg:tags":[
        "marble"
    ],
    "sg:website":"www.premiermarble.com",
    "wof:name":"Premier Kitchen & Bath Inc",
    "wof:placetype":"venue"
},
  "geometry": {"coordinates":[-81.181875,34.961556],"type":"Point"}
}