{
  "type": "Feature",
  "properties": {
    "iso:country":"US",
    "sg:address":"1167 Russell St",
    "sg:city":"Orangeburg",
    "sg:classifiers":[
        {
            "category":"Organizations",
            "subcategory":"Religious Organization",
            "type":"Services"
        }
    ],
    "sg:phone":"+1 803 531 9499",
    "sg:postcode":"29115",
    "sg:province":"SC",
    "wof:name":"Empowerment Ministries Sop",
    "wof:placetype":"venue"
},
  "geometry": {"coordinates":[-80.864876,33.489196],"type":"Point"}
}