{
  "type": "Feature",
  "properties": {
    "iso:country":"US",
    "sg:address":"1103 US Hwy 25",
    "sg:city":"Travelers Rest",
    "sg:classifiers":[
        {
            "category":"Autos & Motor Vehicles",
            "subcategory":"Automobile Sales",
            "type":"Retail Goods"
        }
    ],
    "sg:phone":"+1 864 834 0100",
    "sg:postcode":"29690",
    "sg:province":"SC",
    "sg:tags":[
        "body"
    ],
    "wof:name":"New South Mini Warehouses",
    "wof:placetype":"venue"
},
  "geometry": {"coordinates":[-82.41573,35.008385],"type":"Point"}
}