{
  "type": "Feature",
  "properties": {
    "addr:full":"15 Sams Point Rd Beaufort SC 29907",
    "addr:housenumber":"15",
    "addr:postcode":"29907",
    "addr:street":"Sams Point Rd",
    "iso:country":"US",
    "sg:address":"15 Sams Point Rd",
    "sg:city":"Beaufort",
    "sg:classifiers":[
        {
            "category":"Banks & Credit Unions",
            "subcategory":"Bank",
            "type":"Services"
        }
    ],
    "sg:phone":"+1 843 986 0000",
    "sg:postcode":"29907",
    "sg:province":"SC",
    "sg:tags":[
        "loan",
        "real estate"
    ],
    "wof:name":"Crosswind Mortgage Inc",
    "wof:placetype":"venue"
},
  "geometry": {"coordinates":[-80.647941,32.413517],"type":"Point"}
}