{
  "type": "Feature",
  "properties": {
    "addr:full":"668 E Main St Spartanburg SC 29302",
    "addr:housenumber":"668",
    "addr:postcode":"29302",
    "addr:street":"E Main St",
    "iso:country":"US",
    "sg:address":"668 E Main St",
    "sg:city":"Spartanburg",
    "sg:classifiers":[
        {
            "category":"Shopping",
            "subcategory":"Beauty & Cosmetics",
            "type":"Retail Goods"
        }
    ],
    "sg:phone":"+1 864 583 6307",
    "sg:postcode":"29302",
    "sg:province":"SC",
    "sg:tags":[
        "merchandise"
    ],
    "wof:name":"Hair It Is Inc",
    "wof:placetype":"venue"
},
  "geometry": {"coordinates":[-81.91510100000001,34.95521],"type":"Point"}
}