{
  "type": "Feature",
  "properties": {
    "addr:full":"5347 Sunset Blvd Lexington SC 29072",
    "addr:housenumber":"5347",
    "addr:postcode":"29072",
    "addr:street":"Sunset Blvd",
    "iso:country":"US",
    "sg:address":"5347 Sunset Blvd",
    "sg:city":"Lexington",
    "sg:classifiers":[
        {
            "category":"Sports & Exercise",
            "subcategory":"Gym",
            "type":"Entertainment"
        }
    ],
    "sg:phone":"+1 803 359 6400",
    "sg:postcode":"29072",
    "sg:province":"SC",
    "sg:tags":[
        "club",
        "health",
        "studio",
        "gymnasium"
    ],
    "wof:name":"Courtside Fitness Inc",
    "wof:placetype":"venue"
},
  "geometry": {"coordinates":[-81.211051,34.001768],"type":"Point"}
}