{
  "type": "Feature",
  "properties": {
    "addr:full":"319 Old Shealy Rd Chapin SC 29036",
    "addr:housenumber":"319",
    "addr:postcode":"29036",
    "addr:street":"Old Shealy Rd",
    "iso:country":"US",
    "sg:address":"319 Old Shealy Rd",
    "sg:city":"Chapin",
    "sg:classifiers":[
        {
            "category":"Retail",
            "subcategory":"Animal Services",
            "type":"Services"
        }
    ],
    "sg:phone":"+1 803 932 7627",
    "sg:postcode":"29036",
    "sg:province":"SC",
    "sg:tags":[
        "pet",
        "grooming",
        "washing"
    ],
    "wof:name":"Chapin Laundra Pet Grooming",
    "wof:placetype":"venue"
},
  "geometry": {"coordinates":[-81.355318,34.187008],"type":"Point"}
}