{
  "type": "Feature",
  "properties": {
    "addr:full":"7731 Bluff Rd Gadsden SC 29052",
    "addr:housenumber":"7731",
    "addr:postcode":"29052",
    "addr:street":"Bluff Rd",
    "iso:country":"US",
    "sg:address":"7731 Bluff Rd",
    "sg:city":"Gadsden",
    "sg:classifiers":[
        {
            "category":"Government",
            "subcategory":"Post Office",
            "type":"Public Place"
        }
    ],
    "sg:phone":"+1 803 353 0995",
    "sg:postcode":"29052",
    "sg:province":"SC",
    "wof:name":"US Post Office",
    "wof:placetype":"venue"
},
  "geometry": {"coordinates":[-80.769034,33.846323],"type":"Point"}
}