{
  "type": "Feature",
  "properties": {
    "iso:country":"US",
    "sg:address":"3419 Notch Rd",
    "sg:city":"Columbia",
    "sg:classifiers":[
        {
            "category":"Autos & Motor Vehicles",
            "subcategory":"Automobile Sales",
            "type":"Retail Goods"
        }
    ],
    "sg:phone":"+1 803 714 9151",
    "sg:postcode":"29204",
    "sg:province":"SC",
    "sg:tags":[
        "car",
        "dealer"
    ],
    "wof:name":"Columbia Auto Sales & Rental",
    "wof:placetype":"venue"
},
  "geometry": {"coordinates":[-80.99798699999999,34.040525],"type":"Point"}
}