{
  "type": "Feature",
  "properties": {
    "addr:full":"117 Inverness Dr Lexington SC 29072",
    "addr:housenumber":"117",
    "addr:postcode":"29072",
    "addr:street":"Inverness Dr",
    "iso:country":"US",
    "sg:address":"117 Inverness Dr",
    "sg:city":"Lexington",
    "sg:classifiers":[
        {
            "category":"Professional",
            "subcategory":"Engineering",
            "type":"Services"
        }
    ],
    "sg:phone":"+1 803 785 2005",
    "sg:postcode":"29072",
    "sg:province":"SC",
    "sg:tags":[
        "engineer"
    ],
    "wof:name":"Schmoltze Engineering",
    "wof:placetype":"venue"
},
  "geometry": {"coordinates":[-81.291,33.955145],"type":"Point"}
}