{
  "type": "Feature",
  "properties": {
    "iso:country":"US",
    "sg:address":"687 Trask Pkwy",
    "sg:city":"Seabrook",
    "sg:classifiers":[
        {
            "category":"Wholesale",
            "subcategory":"Meat",
            "type":"Manufacturing & Wholesale Goods"
        }
    ],
    "sg:phone":"+1 843 846 6528",
    "sg:postcode":"29940",
    "sg:province":"SC",
    "sg:tags":[
        "packer"
    ],
    "wof:name":"Wild Game Deer Processing",
    "wof:placetype":"venue"
},
  "geometry": {"coordinates":[-80.80423,32.604801],"type":"Point"}
}