{
  "type": "Feature",
  "properties": {
    "iso:country":"US",
    "sg:address":"3565 Boiling Springs Rd",
    "sg:city":"Spartanburg",
    "sg:classifiers":[
        {
            "category":"Personal",
            "type":"Services"
        }
    ],
    "sg:phone":"+1 864 621 8825",
    "sg:postcode":"29316",
    "sg:province":"SC",
    "sg:tags":[
        "therapist",
        "massage"
    ],
    "wof:name":"Bodyworx Therapeutic Massage",
    "wof:placetype":"venue"
},
  "geometry": {"coordinates":[-81.980819,35.044947],"type":"Point"}
}