{
  "type": "Feature",
  "properties": {
    "addr:full":"609 Tee St Little River SC 29566",
    "addr:housenumber":"609",
    "addr:postcode":"29566",
    "addr:street":"Tee St",
    "iso:country":"US",
    "sg:address":"609 Tee St",
    "sg:city":"Little River",
    "sg:classifiers":[
        {
            "category":"Professional",
            "type":"Services"
        }
    ],
    "sg:phone":"+1 843 249 1889",
    "sg:postcode":"29566",
    "sg:province":"SC",
    "sg:tags":[
        "information",
        "fishing"
    ],
    "wof:name":"New Double R Charter Fishing",
    "wof:placetype":"venue"
},
  "geometry": {"coordinates":[-78.64601399999999,33.866229],"type":"Point"}
}