{
  "type": "Feature",
  "properties": {
    "addr:full":"539 Bauskett St Edgefield SC 29824",
    "addr:housenumber":"539",
    "addr:postcode":"29824",
    "addr:street":"Bauskett St",
    "iso:country":"US",
    "sg:address":"539 Bauskett St",
    "sg:city":"Edgefield",
    "sg:classifiers":[
        {
            "category":"Personal",
            "subcategory":"Beauty Salon",
            "type":"Services"
        }
    ],
    "sg:phone":"+1 803 637 5290",
    "sg:postcode":"29824",
    "sg:province":"SC",
    "wof:name":"Linda's Hairstyling",
    "wof:placetype":"venue"
},
  "geometry": {"coordinates":[-81.937528,33.782216],"type":"Point"}
}