{
  "type": "Feature",
  "properties": {
    "addr:full":"1245 Brickle St Orangeburg SC 29118",
    "addr:housenumber":"1245",
    "addr:postcode":"29118",
    "addr:street":"Brickle St",
    "iso:country":"US",
    "sg:address":"1245 Brickle St",
    "sg:city":"Orangeburg",
    "sg:classifiers":[
        {
            "category":"Insurance",
            "subcategory":"Insurance Agent",
            "type":"Services"
        }
    ],
    "sg:phone":"+1 803 536 3700",
    "sg:postcode":"29118",
    "sg:province":"SC",
    "wof:name":"Prudential Insurance Co",
    "wof:placetype":"venue"
},
  "geometry": {"coordinates":[-80.854502,33.522107],"type":"Point"}
}