{
  "type": "Feature",
  "properties": {
    "addr:full":"620 N Main St Greenville SC 29601",
    "addr:housenumber":"620",
    "addr:postcode":"29601",
    "addr:street":"N Main St",
    "iso:country":"US",
    "sg:address":"620 N Main St",
    "sg:city":"Greenville",
    "sg:classifiers":[
        {
            "category":"Professional",
            "subcategory":"Advertising",
            "type":"Services"
        }
    ],
    "sg:phone":"+1 864 235 1227",
    "sg:postcode":"29601",
    "sg:province":"SC",
    "sg:website":"www.metronetworks.com",
    "wof:name":"Metro Networks",
    "wof:placetype":"venue"
},
  "geometry": {"coordinates":[-82.394454,34.860843],"type":"Point"}
}