{
  "type": "Feature",
  "properties": {
    "addr:full":"1807 US Hwy 221 Greenwood SC 29649",
    "addr:housenumber":"1807",
    "addr:postcode":"29649",
    "addr:street":"Us Hwy 221",
    "iso:country":"US",
    "sg:address":"1807 US Hwy 221",
    "sg:city":"Greenwood",
    "sg:classifiers":[
        {
            "category":"Home & Garden",
            "subcategory":"Mobile Homes",
            "type":"Retail Goods"
        }
    ],
    "sg:phone":"+1 864 227 3192",
    "sg:postcode":"29649",
    "sg:province":"SC",
    "wof:name":"Classic Life Style Homes Inc",
    "wof:placetype":"venue"
},
  "geometry": {"coordinates":[-82.130442,34.215897],"type":"Point"}
}