{
  "type": "Feature",
  "properties": {
    "iso:country":"US",
    "sg:address":"110 N Main St",
    "sg:city":"Abbeville",
    "sg:classifiers":[
        {
            "category":"Banks & Credit Unions",
            "subcategory":"Bank",
            "type":"Services"
        }
    ],
    "sg:phone":"+1 864 459 8598",
    "sg:postcode":"29620",
    "sg:province":"SC",
    "sg:tags":[
        "company",
        "consumer",
        "loan",
        "finance"
    ],
    "wof:name":"Delta Credit 42",
    "wof:placetype":"venue"
},
  "geometry": {"coordinates":[-82.379773,34.178598],"type":"Point"}
}