{
  "type": "Feature",
  "properties": {
    "iso:country":"US",
    "sg:address":"2031 Pisgah Rd",
    "sg:city":"North Augusta",
    "sg:classifiers":[
        {
            "category":"Food & Beverages",
            "subcategory":"Groceries & Convenience Stores",
            "type":"Retail Goods"
        }
    ],
    "sg:phone":"+1 803 819 1836",
    "sg:postcode":"29841",
    "sg:province":"SC",
    "wof:name":"Four Seasons Svc Inc",
    "wof:placetype":"venue"
},
  "geometry": {"coordinates":[-81.96570699999999,33.534184],"type":"Point"}
}