{
  "type": "Feature",
  "properties": {
    "iso:country":"US",
    "sg:address":"112 N Main St",
    "sg:city":"Anderson",
    "sg:classifiers":[
        {
            "category":"Bars & Pubs",
            "type":"Food & Drink"
        }
    ],
    "sg:phone":"+1 864 231 0663",
    "sg:postcode":"29621",
    "sg:province":"SC",
    "sg:tags":[
        "bar"
    ],
    "wof:name":"Friends",
    "wof:placetype":"venue"
},
  "geometry": {"coordinates":[-82.650291,34.504052],"type":"Point"}
}