{
  "type": "Feature",
  "properties": {
    "iso:country":"US",
    "sg:address":"1952 Rimini Dr",
    "sg:city":"Georgetown",
    "sg:classifiers":[
        {
            "category":"Building & Trades",
            "subcategory":"Construction",
            "type":"Services"
        }
    ],
    "sg:phone":"+1 843 527 3226",
    "sg:postcode":"29440",
    "sg:province":"SC",
    "sg:tags":[
        "carpentry",
        "contractor"
    ],
    "wof:name":"Woodworking Specialities",
    "wof:placetype":"venue"
},
  "geometry": {"coordinates":[-79.32277000000001,33.505888],"type":"Point"}
}