{
  "type": "Feature",
  "properties": {
    "iso:country":"US",
    "sg:address":"1897 Sam Rittenberg Blvd",
    "sg:city":"Charleston",
    "sg:classifiers":[
        {
            "category":"Professional",
            "subcategory":"Business Services",
            "type":"Services"
        }
    ],
    "sg:phone":"+1 843 766 5458",
    "sg:postcode":"29407",
    "sg:province":"SC",
    "sg:tags":[
        "information",
        "bureau",
        "convention"
    ],
    "wof:name":"Loyal Order Of Moose",
    "wof:placetype":"venue"
},
  "geometry": {"coordinates":[-80.02194799999999,32.798854],"type":"Point"}
}