{
  "type": "Feature",
  "properties": {
    "iso:country":"US",
    "sg:address":"1180 Haywood Rd",
    "sg:city":"Greenville",
    "sg:classifiers":[
        {
            "category":"Real Estate",
            "subcategory":"Real Estate Operator",
            "type":"Services"
        }
    ],
    "sg:phone":"+1 864 288 8093",
    "sg:postcode":"29615",
    "sg:province":"SC",
    "sg:tags":[
        "building",
        "apartment"
    ],
    "wof:name":"Haywood Esttes Rtrment Rsdence",
    "wof:placetype":"venue"
},
  "geometry": {"coordinates":[-82.333867,34.864623],"type":"Point"}
}