{
  "type": "Feature",
  "properties": {
    "iso:country":"US",
    "sg:address":"944 Forest Dr",
    "sg:city":"Lancaster",
    "sg:classifiers":[
        {
            "category":"Building & Trades",
            "subcategory":"Plumbing",
            "type":"Services"
        }
    ],
    "sg:phone":"+1 803 286 8523",
    "sg:postcode":"29720",
    "sg:province":"SC",
    "sg:tags":[
        "contractor"
    ],
    "wof:name":"Blackmon Bckhoe Sptic Tank Svc",
    "wof:placetype":"venue"
},
  "geometry": {"coordinates":[-80.795042,34.726451],"type":"Point"}
}