{
  "type": "Feature",
  "properties": {
    "addr:full":"365 Sha Ln Spartanburg SC 29307",
    "addr:housenumber":"365",
    "addr:postcode":"29307",
    "addr:street":"Sha Ln",
    "iso:country":"US",
    "sg:address":"365 Sha Ln",
    "sg:city":"Spartanburg",
    "sg:classifiers":[
        {
            "category":"Autos & Motor Vehicles",
            "subcategory":"Motorcycle Sales",
            "type":"Retail Goods"
        }
    ],
    "sg:phone":"+1 864 583 8840",
    "sg:postcode":"29307",
    "sg:province":"SC",
    "sg:tags":[
        "scooter"
    ],
    "sg:website":"www.spartanburgharley.com",
    "wof:name":"Harley Davidson-Spartanburg",
    "wof:placetype":"venue"
},
  "geometry": {"coordinates":[-81.894345,35.020245],"type":"Point"}
}