{
  "type": "Feature",
  "properties": {
    "iso:country":"US",
    "sg:address":"907 N Main St",
    "sg:city":"Anderson",
    "sg:classifiers":[
        {
            "category":"Social Services",
            "type":"Services"
        }
    ],
    "sg:phone":"+1 864 226 3438",
    "sg:postcode":"29621",
    "sg:province":"SC",
    "sg:tags":[
        "organization",
        "welfare"
    ],
    "sg:website":"www.foothills.unitedway.org",
    "wof:name":"United Way",
    "wof:placetype":"venue"
},
  "geometry": {"coordinates":[-82.652018,34.510811],"type":"Point"}
}