{
  "type": "Feature",
  "properties": {
    "iso:country":"US",
    "sg:address":"300 Chickenfoot Creek Rd",
    "sg:city":"Woodruff",
    "sg:classifiers":[
        {
            "category":"Organizations",
            "subcategory":"Religious Organization",
            "type":"Services"
        }
    ],
    "sg:phone":"+1 864 433 8512",
    "sg:postcode":"29388",
    "sg:province":"SC",
    "sg:tags":[
        "church"
    ],
    "wof:name":"Green Pond Baptist Church",
    "wof:placetype":"venue"
},
  "geometry": {"coordinates":[-82.079208,34.823562],"type":"Point"}
}