{
  "type": "Feature",
  "properties": {
    "iso:country":"US",
    "sg:address":"1044 Chestnut St",
    "sg:city":"Orangeburg",
    "sg:classifiers":[
        {
            "category":"Shopping",
            "subcategory":"Discount & Variety Stores",
            "type":"Retail Goods"
        }
    ],
    "sg:phone":"+1 803 536 5418",
    "sg:postcode":"29115",
    "sg:province":"SC",
    "wof:name":"Family Dollar Stores",
    "wof:placetype":"venue"
},
  "geometry": {"coordinates":[-80.855357,33.509991],"type":"Point"}
}