{
  "type": "Feature",
  "properties": {
    "addr:full":"1203 Jackson Ave W Hampton SC 29924",
    "addr:housenumber":"1203",
    "addr:postcode":"29924",
    "addr:street":"Jackson Ave W",
    "iso:country":"US",
    "sg:address":"1203 Jackson Ave W",
    "sg:city":"Hampton",
    "sg:classifiers":[
        {
            "category":"Social Services",
            "subcategory":"Child Care",
            "type":"Services"
        }
    ],
    "sg:phone":"+1 803 943 4748",
    "sg:postcode":"29924",
    "sg:province":"SC",
    "wof:name":"Zeigler's Day Care",
    "wof:placetype":"venue"
},
  "geometry": {"coordinates":[-81.121003,32.874278],"type":"Point"}
}