{
  "type": "Feature",
  "properties": {
    "iso:country":"US",
    "sg:address":"836 Packs Mountain Ridge Rd",
    "sg:city":"Taylors",
    "sg:classifiers":[
        {
            "category":"Personal",
            "type":"Services"
        }
    ],
    "sg:phone":"+1 864 895 3690",
    "sg:postcode":"29687",
    "sg:province":"SC",
    "sg:tags":[
        "wedding",
        "chapel"
    ],
    "wof:name":"Mountain View Weddings",
    "wof:placetype":"venue"
},
  "geometry": {"coordinates":[-82.32863500000001,35.063972],"type":"Point"}
}