{
  "type": "Feature",
  "properties": {
    "addr:full":"353 S Harrison Bridge Rd Simpsonville SC 29680",
    "addr:housenumber":"353",
    "addr:postcode":"29680",
    "addr:street":"S Harrison Bridge Rd",
    "iso:country":"US",
    "sg:address":"353 S Harrison Bridge Rd",
    "sg:city":"Simpsonville",
    "sg:classifiers":[
        {
            "category":"Shopping",
            "subcategory":"Department Store",
            "type":"Retail Goods"
        }
    ],
    "sg:phone":"+1 864 228 9304",
    "sg:postcode":"29680",
    "sg:province":"SC",
    "sg:tags":[
        "shop"
    ],
    "sg:website":"www.pier1.com",
    "wof:name":"Pier 1 Imports",
    "wof:placetype":"venue"
},
  "geometry": {"coordinates":[-82.297105,34.674638],"type":"Point"}
}