{
  "type": "Feature",
  "properties": {
    "addr:full":"585 Good Farm Rd Vance SC 29163",
    "addr:housenumber":"585",
    "addr:postcode":"29163",
    "addr:street":"Good Farm Rd",
    "iso:country":"US",
    "sg:address":"585 Good Farm Rd",
    "sg:city":"Vance",
    "sg:classifiers":[
        {
            "category":"Communications",
            "type":"Services"
        }
    ],
    "sg:phone":"+1 803 496 3387",
    "sg:postcode":"29163",
    "sg:province":"SC",
    "wof:name":"Crown Communications",
    "wof:placetype":"venue"
},
  "geometry": {"coordinates":[-80.513464,33.405251],"type":"Point"}
}