{
  "type": "Feature",
  "properties": {
    "addr:full":"144 O'Neil Columbia SC 29223",
    "addr:housenumber":"144",
    "addr:postcode":"29223",
    "addr:street":"O'Neil",
    "iso:country":"US",
    "sg:address":"144 O'Neil",
    "sg:city":"Columbia",
    "sg:classifiers":[
        {
            "category":"Home & Garden",
            "subcategory":"Home Furnishings",
            "type":"Retail Goods"
        },
        {
            "category":"Wholesale",
            "subcategory":"Electrical",
            "type":"Manufacturing & Wholesale Goods"
        }
    ],
    "sg:phone":"+1 803 736 2246",
    "sg:postcode":"29223",
    "sg:province":"SC",
    "sg:tags":[
        "lighting",
        "fixture"
    ],
    "wof:name":"Unique Lighting Center",
    "wof:placetype":"venue"
},
  "geometry": {"coordinates":[-80.949642,34.076012],"type":"Point"}
}