{
  "type": "Feature",
  "properties": {
    "addr:full":"111 Stonemark Ln Columbia SC 29210",
    "addr:housenumber":"111",
    "addr:postcode":"29210",
    "addr:street":"Stonemark Ln",
    "iso:country":"US",
    "sg:address":"111 Stonemark Ln",
    "sg:city":"Columbia",
    "sg:classifiers":[
        {
            "category":"Banks & Credit Unions",
            "subcategory":"Investment Brokerage",
            "type":"Services"
        }
    ],
    "sg:phone":"+1 803 798 4038",
    "sg:postcode":"29210",
    "sg:province":"SC",
    "sg:tags":[
        "marketing",
        "financial"
    ],
    "wof:name":"Primerica",
    "wof:placetype":"venue"
},
  "geometry": {"coordinates":[-81.13527000000001,34.062836],"type":"Point"}
}