{
  "type": "Feature",
  "properties": {
    "iso:country":"US",
    "sg:address":"7740 Augusta Rd",
    "sg:city":"Piedmont",
    "sg:classifiers":[
        {
            "category":"Restaurant",
            "type":"Food & Drink"
        }
    ],
    "sg:phone":"+1 864 277 3141",
    "sg:postcode":"29605",
    "sg:province":"SC",
    "wof:name":"Burns Subs",
    "wof:placetype":"venue"
},
  "geometry": {"coordinates":[-82.390114,34.733888],"type":"Point"}
}