{
  "type": "Feature",
  "properties": {
    "iso:country":"US",
    "sg:address":"235 Timberland Cir",
    "sg:city":"Wellford",
    "sg:classifiers":[
        {
            "category":"Wholesale",
            "subcategory":"Farm Supplies",
            "type":"Manufacturing & Wholesale Goods"
        }
    ],
    "sg:phone":"+1 803 439 7152",
    "sg:postcode":"29385",
    "sg:province":"SC",
    "sg:tags":[
        "material",
        "design",
        "landscape"
    ],
    "wof:name":"Artistic View",
    "wof:placetype":"venue"
},
  "geometry": {"coordinates":[-82.113163,34.978381],"type":"Point"}
}