{
  "type": "Feature",
  "properties": {
    "addr:full":"1742 Nearview Ave Columbia SC 29223",
    "addr:housenumber":"1742",
    "addr:postcode":"29223",
    "addr:street":"Nearview Ave",
    "iso:country":"US",
    "sg:address":"1742 Nearview Ave",
    "sg:city":"Columbia",
    "sg:classifiers":[
        {
            "category":"Banks & Credit Unions",
            "subcategory":"Financial Services",
            "type":"Services"
        }
    ],
    "sg:phone":"+1 803 782 1977",
    "sg:postcode":"29223",
    "sg:province":"SC",
    "sg:tags":[
        "investor",
        "real estate"
    ],
    "wof:name":"So-So Property",
    "wof:placetype":"venue"
},
  "geometry": {"coordinates":[-80.93383900000001,34.050138],"type":"Point"}
}