{
  "type": "Feature",
  "properties": {
    "addr:city":"Charleston",
    "addr:full":"360 Concord St Charleston, Sc 29401",
    "addr:house_number":"360",
    "addr:housenumber":"360",
    "addr:phone":"+1 843-577-7000",
    "addr:postcode":"29401",
    "addr:road":"Concord St",
    "addr:state":"SC",
    "addr:street":"Concord St",
    "iso:country":"US",
    "sg:address":"360 Concord St",
    "sg:city":"Charleston",
    "sg:classifiers":[
        {
            "category":"Museum",
            "type":"Entertainment"
        }
    ],
    "sg:phone":"+1 843 723 9620",
    "sg:postcode":"29401",
    "sg:province":"SC",
    "wof:airports":[
        102531215
    ],
    "wof:name":"American Military Museum",
    "wof:placetype":"venue"
},
  "geometry": {"coordinates":[-79.93729,32.79435],"type":"Point"}
}