{
  "type": "Feature",
  "properties": {
    "iso:country":"US",
    "sg:address":"360 Concord St",
    "sg:city":"Charleston",
    "sg:classifiers":[
        {
            "category":"Museum",
            "type":"Entertainment"
        }
    ],
    "sg:phone":"+1 843 723 9620",
    "sg:postcode":"29401",
    "sg:province":"SC",
    "wof:name":"American Military Museum",
    "wof:placetype":"venue"
},
  "geometry": {"coordinates":[-79.92701700000001,32.791433],"type":"Point"}
}