{
  "type": "Feature",
  "properties": {
    "iso:country":"US",
    "sg:address":"26 S Wise Dr",
    "sg:city":"Sumter",
    "sg:classifiers":[
        {
            "category":"Shopping",
            "subcategory":"Musical Instruments",
            "type":"Retail Goods"
        }
    ],
    "sg:phone":"+1 803 773 0055",
    "sg:postcode":"29150",
    "sg:province":"SC",
    "sg:tags":[
        "music",
        "dealer"
    ],
    "wof:name":"Music & Me",
    "wof:placetype":"venue"
},
  "geometry": {"coordinates":[-80.370662,33.942596],"type":"Point"}
}