{
  "type": "Feature",
  "properties": {
    "iso:country":"US",
    "sg:address":"3506 Sardis Hwy",
    "sg:city":"Timmonsville",
    "sg:classifiers":[
        {
            "category":"Manufacturing",
            "subcategory":"Tools & Machinery",
            "type":"Manufacturing & Wholesale Goods"
        }
    ],
    "sg:phone":"+1 843 346 4891",
    "sg:postcode":"29161",
    "sg:province":"SC",
    "sg:tags":[
        "industrial",
        "mfg"
    ],
    "wof:name":"Sims Machining",
    "wof:placetype":"venue"
},
  "geometry": {"coordinates":[-79.929883,34.037747],"type":"Point"}
}