{
  "type": "Feature",
  "properties": {
    "iso:country":"US",
    "sg:address":"1668 Old Trolley Rd",
    "sg:city":"Summerville",
    "sg:classifiers":[
        {
            "category":"Insurance",
            "subcategory":"Insurance Agent",
            "type":"Services"
        }
    ],
    "sg:phone":"+1 843 873 8970",
    "sg:postcode":"29485",
    "sg:province":"SC",
    "wof:name":"Allstate Insurance",
    "wof:placetype":"venue"
},
  "geometry": {"coordinates":[-80.165215,32.958193],"type":"Point"}
}