{
  "type": "Feature",
  "properties": {
    "addr:full":"224 Barnwell St Columbia SC 29205",
    "addr:housenumber":"224",
    "addr:postcode":"29205",
    "addr:street":"Barnwell St",
    "iso:country":"US",
    "sg:address":"224 Barnwell St",
    "sg:city":"Columbia",
    "sg:classifiers":[
        {
            "category":"Education",
            "subcategory":"Preschool",
            "type":"Public Place"
        },
        {
            "category":"Education",
            "subcategory":"School",
            "type":"Public Place"
        }
    ],
    "sg:phone":"+1 803 648 3311",
    "sg:postcode":"29205",
    "sg:province":"SC",
    "sg:tags":[
        "elementary"
    ],
    "wof:name":"First Presbyterian Church Prschl & Mthr's Mrnng Ot",
    "wof:placetype":"venue"
},
  "geometry": {"coordinates":[-81.01860000000001,33.991199],"type":"Point"}
}