{
  "type": "Feature",
  "properties": {
    "iso:country":"US",
    "sg:address":"1811 W John Paul Jones Rd",
    "sg:city":"Effingham",
    "sg:classifiers":[
        {
            "category":"Building & Trades",
            "subcategory":"Construction",
            "type":"Services"
        }
    ],
    "sg:phone":"+1 843 665 4986",
    "sg:postcode":"29541",
    "sg:province":"SC",
    "sg:tags":[
        "house"
    ],
    "wof:name":"Fowler Builders",
    "wof:placetype":"venue"
},
  "geometry": {"coordinates":[-79.811167,34.110728],"type":"Point"}
}