{
  "type": "Feature",
  "properties": {
    "iso:country":"US",
    "sg:address":"125 Outlet Pointe Blvd",
    "sg:city":"Columbia",
    "sg:classifiers":[
        {
            "category":"Manufacturing",
            "subcategory":"Rubber & Plastics",
            "type":"Manufacturing & Wholesale Goods"
        }
    ],
    "sg:phone":"+1 803 798 1956",
    "sg:postcode":"29210",
    "sg:province":"SC",
    "sg:tags":[
        "product",
        "metal",
        "mfg"
    ],
    "wof:name":"Champion Window Mfg & Sups Co",
    "wof:placetype":"venue"
},
  "geometry": {"coordinates":[-81.125198,34.031585],"type":"Point"}
}