{
  "type": "Feature",
  "properties": {
    "iso:country":"US",
    "sg:address":"4314 Head's Point Ct",
    "sg:city":"Johns Island",
    "sg:classifiers":[
        {
            "category":"Building & Trades",
            "subcategory":"Construction",
            "type":"Services"
        }
    ],
    "sg:phone":"+1 843 768 8404",
    "sg:postcode":"29455",
    "sg:province":"SC",
    "sg:tags":[
        "house"
    ],
    "wof:name":"Haulover Creek Builders",
    "wof:placetype":"venue"
},
  "geometry": {"coordinates":[-80.136531,32.618135],"type":"Point"}
}