{
  "type": "Feature",
  "properties": {
    "addr:full":"2171 Augusta Rd Gloverville SC 29828",
    "addr:housenumber":"2171",
    "addr:postcode":"29828",
    "addr:street":"Augusta Rd",
    "iso:country":"US",
    "sg:address":"2171 Augusta Rd",
    "sg:city":"Gloverville",
    "sg:classifiers":[
        {
            "category":"Restaurant",
            "type":"Food & Drink"
        }
    ],
    "sg:phone":"+1 803 593 2890",
    "sg:postcode":"29828",
    "sg:province":"SC",
    "wof:name":"L & M Cafe",
    "wof:placetype":"venue"
},
  "geometry": {"coordinates":[-81.82794699999999,33.527716],"type":"Point"}
}