{
  "type": "Feature",
  "properties": {
    "addr:full":"1208 Reynolds Ave Greenwood SC 29649",
    "addr:housenumber":"1208",
    "addr:postcode":"29649",
    "addr:street":"Reynolds Ave",
    "iso:country":"US",
    "sg:address":"1208 Reynolds Ave",
    "sg:city":"Greenwood",
    "sg:classifiers":[
        {
            "category":"Shopping",
            "type":"Retail Goods"
        }
    ],
    "sg:phone":"+1 864 223 0981",
    "sg:postcode":"29649",
    "sg:province":"SC",
    "sg:tags":[
        "pet",
        "shop"
    ],
    "wof:name":"World Of Fish & Pets",
    "wof:placetype":"venue"
},
  "geometry": {"coordinates":[-82.147554,34.207852],"type":"Point"}
}