{
  "type": "Feature",
  "properties": {
    "iso:country":"US",
    "sg:address":"1506 Charlton St",
    "sg:city":"Columbia",
    "sg:classifiers":[
        {
            "category":"Organizations",
            "subcategory":"Religious Organization",
            "type":"Services"
        }
    ],
    "sg:phone":"+1 803 333 0515",
    "sg:postcode":"29203",
    "sg:province":"SC",
    "sg:tags":[
        "church"
    ],
    "wof:name":"Greater Love Bible Way Church",
    "wof:placetype":"venue"
},
  "geometry": {"coordinates":[-81.026797,34.044295],"type":"Point"}
}