{
  "type": "Feature",
  "properties": {
    "addr:full":"3011 Broad St Loris SC 29569",
    "addr:housenumber":"3011",
    "addr:postcode":"29569",
    "addr:street":"Broad St",
    "iso:country":"US",
    "sg:address":"3011 Broad St",
    "sg:city":"Loris",
    "sg:classifiers":[
        {
            "category":"Restaurant",
            "type":"Food & Drink"
        }
    ],
    "sg:phone":"+1 843 716 0111",
    "sg:postcode":"29569",
    "sg:province":"SC",
    "wof:name":"Tokyo Express Inc",
    "wof:placetype":"venue"
},
  "geometry": {"coordinates":[-78.892926,34.050982],"type":"Point"}
}