{
  "type": "Feature",
  "properties": {
    "iso:country":"US",
    "sg:address":"100 Morton Ln",
    "sg:city":"Easley",
    "sg:classifiers":[
        {
            "category":"Wholesale",
            "subcategory":"Medical Equipment & Supplies",
            "type":"Manufacturing & Wholesale Goods"
        }
    ],
    "sg:phone":"+1 864 855 3080",
    "sg:postcode":"29642",
    "sg:province":"SC",
    "wof:name":"Carolina Bone & Tissue",
    "wof:placetype":"venue"
},
  "geometry": {"coordinates":[-82.52560699999999,34.82001],"type":"Point"}
}