{
  "type": "Feature",
  "properties": {
    "addr:full":"2719 Edgefield Hwy Trenton SC 29847",
    "addr:housenumber":"2719",
    "addr:postcode":"29847",
    "addr:street":"Edgefield Hwy",
    "iso:country":"US",
    "sg:address":"2719 Edgefield Hwy",
    "sg:city":"Trenton",
    "sg:classifiers":[
        {
            "category":"Real Estate",
            "subcategory":"Real Estate Agent",
            "type":"Services"
        }
    ],
    "sg:phone":"+1 803 648 4004",
    "sg:postcode":"29847",
    "sg:province":"SC",
    "wof:name":"Vikki Crossland Rl Estate",
    "wof:placetype":"venue"
},
  "geometry": {"coordinates":[-81.76522799999999,33.686829],"type":"Point"}
}