{
  "type": "Feature",
  "properties": {
    "addr:full":"1071 Morrison Dr Charleston SC 29403",
    "addr:housenumber":"1071",
    "addr:postcode":"29403",
    "addr:street":"Morrison Dr",
    "iso:country":"US",
    "sg:address":"1071 Morrison Dr",
    "sg:city":"Charleston",
    "sg:classifiers":[
        {
            "category":"Retail",
            "subcategory":"Repair Shop",
            "type":"Services"
        }
    ],
    "sg:phone":"+1 843 723 6915",
    "sg:postcode":"29403",
    "sg:province":"SC",
    "sg:tags":[
        "caning"
    ],
    "wof:name":"Cane Studio",
    "wof:placetype":"venue"
},
  "geometry": {"coordinates":[-79.94778599999999,32.810443],"type":"Point"}
}