{
  "type": "Feature",
  "properties": {
    "addr:full":"104 Commerce Blvd Easley SC 29642",
    "addr:housenumber":"104",
    "addr:postcode":"29642",
    "addr:street":"Commerce Blvd",
    "iso:country":"US",
    "sg:address":"104 Commerce Blvd",
    "sg:city":"Easley",
    "sg:classifiers":[
        {
            "category":"Wholesale",
            "subcategory":"Machinery & Supplies",
            "type":"Manufacturing & Wholesale Goods"
        }
    ],
    "sg:phone":"+1 864 442 9800",
    "sg:postcode":"29642",
    "sg:province":"SC",
    "sg:tags":[
        "textile",
        "parts"
    ],
    "wof:name":"General Textile Svc Co",
    "wof:placetype":"venue"
},
  "geometry": {"coordinates":[-82.532202,34.826185],"type":"Point"}
}