{
  "type": "Feature",
  "properties": {
    "iso:country":"US",
    "sg:address":"127 Armory Rd",
    "sg:city":"Union",
    "sg:classifiers":[
        {
            "category":"Organizations",
            "subcategory":"Religious Organization",
            "type":"Services"
        }
    ],
    "sg:phone":"+1 864 545 6347",
    "sg:postcode":"29364",
    "sg:province":"SC",
    "sg:tags":[
        "church"
    ],
    "wof:name":"Lockhart Freewill Baptist Chr",
    "wof:placetype":"venue"
},
  "geometry": {"coordinates":[-81.484607,34.799706],"type":"Point"}
}