{
  "type": "Feature",
  "properties": {
    "iso:country":"US",
    "sg:address":"202 Hillcrest Dr",
    "sg:city":"Laurens",
    "sg:classifiers":[
        {
            "category":"Retail",
            "subcategory":"Auto Repair",
            "type":"Services"
        }
    ],
    "sg:phone":"+1 864 681 1888",
    "sg:postcode":"29360",
    "sg:province":"SC",
    "sg:tags":[
        "automobile",
        "lubrication"
    ],
    "wof:name":"Valvoline Express Care",
    "wof:placetype":"venue"
},
  "geometry": {"coordinates":[-82.013825,34.505168],"type":"Point"}
}