{
  "type": "Feature",
  "properties": {
    "addr:full":"1427 S Ocean Blvd North Myrtle Bch SC 29582",
    "addr:housenumber":"1427",
    "addr:postcode":"29582",
    "addr:street":"S Ocean Blvd North Myrtle",
    "iso:country":"US",
    "sg:address":"1427 S Ocean Blvd",
    "sg:city":"North Myrtle Bch",
    "sg:classifiers":[
        {
            "category":"Travel",
            "subcategory":"Hotels & Motels",
            "type":"Entertainment"
        }
    ],
    "sg:phone":"+1 843 272 5437",
    "sg:postcode":"29582",
    "sg:province":"SC",
    "wof:name":"Jamaica Ocean Edge Motel",
    "wof:placetype":"venue"
},
  "geometry": {"coordinates":[-78.694067,33.810246],"type":"Point"}
}