{
  "type": "Feature",
  "properties": {
    "iso:country":"US",
    "sg:address":"5015 Hatcher Hill Rd",
    "sg:city":"Wallace",
    "sg:classifiers":[
        {
            "category":"Organizations",
            "subcategory":"Religious Organization",
            "type":"Services"
        }
    ],
    "sg:phone":"+1 843 921 1231",
    "sg:postcode":"29596",
    "sg:province":"SC",
    "sg:tags":[
        "church"
    ],
    "wof:name":"Faith Fellowship Church",
    "wof:placetype":"venue"
},
  "geometry": {"coordinates":[-79.83596,34.763525],"type":"Point"}
}