{
  "type": "Feature",
  "properties": {
    "addr:full":"456 King St Charleston SC 29403",
    "addr:housenumber":"456",
    "addr:postcode":"29403",
    "addr:street":"King St",
    "iso:country":"US",
    "sg:address":"456 King St",
    "sg:city":"Charleston",
    "sg:classifiers":[
        {
            "category":"Railroad",
            "type":"Transportation"
        }
    ],
    "sg:phone":"+1 843 566 8060",
    "sg:postcode":"29403",
    "sg:province":"SC",
    "wof:name":"Norfolk Southern Railway Co",
    "wof:placetype":"venue"
},
  "geometry": {"coordinates":[-79.93836,32.789021],"type":"Point"}
}