{
  "type": "Feature",
  "properties": {
    "addr:full":"123 King St Georgetown SC 29440",
    "addr:housenumber":"123",
    "addr:postcode":"29440",
    "addr:street":"King St",
    "iso:country":"US",
    "sg:address":"123 King St",
    "sg:city":"Georgetown",
    "sg:classifiers":[
        {
            "category":"Shopping",
            "subcategory":"Florist",
            "type":"Retail Goods"
        }
    ],
    "sg:phone":"+1 843 527 9900",
    "sg:postcode":"29440",
    "sg:province":"SC",
    "wof:name":"Indigo Florals & Events",
    "wof:placetype":"venue"
},
  "geometry": {"coordinates":[-79.285124,33.369145],"type":"Point"}
}