{
  "type": "Feature",
  "properties": {
    "iso:country":"US",
    "sg:address":"217 Lake Shire Dr",
    "sg:city":"Lexington",
    "sg:classifiers":[
        {
            "category":"Building & Trades",
            "subcategory":"Plumbing",
            "type":"Services"
        }
    ],
    "sg:phone":"+1 803 957 9028",
    "sg:postcode":"29073",
    "sg:province":"SC",
    "sg:tags":[
        "plumbing",
        "contractor"
    ],
    "wof:name":"Dreher Plumbing Co",
    "wof:placetype":"venue"
},
  "geometry": {"coordinates":[-81.180719,33.952102],"type":"Point"}
}