{
  "type": "Feature",
  "properties": {
    "addr:full":"PO Box 212064 Columbia SC 29221",
    "addr:housenumber":"po",
    "addr:postcode":"29221",
    "addr:street":"Box 212064",
    "iso:country":"US",
    "sg:address":"PO Box 212064",
    "sg:city":"Columbia",
    "sg:classifiers":[
        {
            "category":"Building & Trades",
            "subcategory":"Pest Control",
            "type":"Services"
        }
    ],
    "sg:phone":"+1 803 798 6232",
    "sg:postcode":"29221",
    "sg:province":"SC",
    "wof:name":"Midland Pest Control",
    "wof:placetype":"venue"
},
  "geometry": {"coordinates":[-81.096802,34.040199],"type":"Point"}
}