{
  "type": "Feature",
  "properties": {
    "iso:country":"US",
    "sg:address":"303 Columbia Ave",
    "sg:city":"Lexington",
    "sg:classifiers":[
        {
            "category":"Personal",
            "subcategory":"Beauty Salon",
            "type":"Services"
        }
    ],
    "sg:phone":"+1 803 359 5722",
    "sg:postcode":"29072",
    "sg:province":"SC",
    "wof:name":"Hair Designs By Hope",
    "wof:placetype":"venue"
},
  "geometry": {"coordinates":[-81.245131,33.986896],"type":"Point"}
}