{
  "type": "Feature",
  "properties": {
    "iso:country":"US",
    "sg:address":"140 Cooley Springs Rd",
    "sg:city":"Chesnee",
    "sg:classifiers":[
        {
            "category":"Education",
            "subcategory":"School",
            "type":"Public Place"
        }
    ],
    "sg:phone":"+1 864 592 1211",
    "sg:postcode":"29323",
    "sg:province":"SC",
    "wof:name":"Cooley Springs-Fingerville",
    "wof:placetype":"venue"
},
  "geometry": {"coordinates":[-81.952154,35.139142],"type":"Point"}
}