{
  "type": "Feature",
  "properties": {
    "addr:full":"6322 Rivers Ave Charleston SC 29406",
    "addr:housenumber":"6322",
    "addr:postcode":"29406",
    "addr:street":"Rivers Ave",
    "iso:country":"US",
    "sg:address":"6322 Rivers Ave",
    "sg:city":"Charleston",
    "sg:classifiers":[
        {
            "category":"Restaurant",
            "type":"Food & Drink"
        }
    ],
    "sg:phone":"+1 843 569 6844",
    "sg:postcode":"29406",
    "sg:province":"SC",
    "wof:name":"LA Hacienda Mexican Restaurant",
    "wof:placetype":"venue"
},
  "geometry": {"coordinates":[-80.024035,32.911159],"type":"Point"}
}