{
  "type": "Feature",
  "properties": {
    "iso:country":"US",
    "sg:address":"610 Rose St",
    "sg:city":"Rock Hill",
    "sg:classifiers":[
        {
            "category":"Real Estate",
            "subcategory":"Real Estate Operator",
            "type":"Services"
        }
    ],
    "sg:phone":"+1 803 366 3400",
    "sg:postcode":"29730",
    "sg:province":"SC",
    "sg:tags":[
        "apartment"
    ],
    "wof:name":"University Place Apartments",
    "wof:placetype":"venue"
},
  "geometry": {"coordinates":[-81.03266000000001,34.935698],"type":"Point"}
}