{
  "type": "Feature",
  "properties": {
    "addr:full":"107 Waterlog Ln Bonneau SC 29431",
    "addr:housenumber":"107",
    "addr:postcode":"29431",
    "addr:street":"Waterlog Ln",
    "iso:country":"US",
    "sg:address":"107 Waterlog Ln",
    "sg:city":"Bonneau",
    "sg:classifiers":[
        {
            "category":"Building & Trades",
            "subcategory":"Plumbing",
            "type":"Services"
        }
    ],
    "sg:phone":"+1 843 825 3714",
    "sg:postcode":"29431",
    "sg:province":"SC",
    "sg:tags":[
        "contractor"
    ],
    "wof:name":"Pick S Plumbing",
    "wof:placetype":"venue"
},
  "geometry": {"coordinates":[-79.992396,33.310133],"type":"Point"}
}