{
  "type": "Feature",
  "properties": {
    "iso:country":"US",
    "sg:address":"14323 Ocean Hwy",
    "sg:city":"Pawleys Island",
    "sg:classifiers":[
        {
            "category":"Building & Trades",
            "subcategory":"Construction",
            "type":"Services"
        }
    ],
    "sg:phone":"+1 843 235 9308",
    "sg:postcode":"29585",
    "sg:province":"SC",
    "sg:tags":[
        "contractor"
    ],
    "wof:name":"Sea Spray Homes",
    "wof:placetype":"venue"
},
  "geometry": {"coordinates":[-79.104761,33.471765],"type":"Point"}
}