{
  "type": "Feature",
  "properties": {
    "iso:country":"US",
    "sg:address":"1593 Seawind Dr",
    "sg:city":"Charleston",
    "sg:classifiers":[
        {
            "category":"Shopping",
            "subcategory":"Gifts & Souvenirs",
            "type":"Retail Goods"
        }
    ],
    "sg:phone":"+1 843 769 2270",
    "sg:postcode":"29407",
    "sg:province":"SC",
    "wof:name":"Elegant Expressions Inc",
    "wof:placetype":"venue"
},
  "geometry": {"coordinates":[-80.024851,32.824619],"type":"Point"}
}