{
  "type": "Feature",
  "properties": {
    "iso:country":"US",
    "sg:address":"10093 Southwinds Dr",
    "sg:city":"Fort Mill",
    "sg:classifiers":[
        {
            "category":"Professional",
            "subcategory":"Business Services",
            "type":"Services"
        }
    ],
    "sg:phone":"+1 803 370 0108",
    "sg:postcode":"29707",
    "sg:province":"SC",
    "sg:tags":[
        "embroidery"
    ],
    "wof:name":"A+ Embroidery",
    "wof:placetype":"venue"
},
  "geometry": {"coordinates":[-80.88471,35.014786],"type":"Point"}
}