{
  "type": "Feature",
  "properties": {
    "addr:full":"301 Memorial Dr Seneca SC 29672",
    "addr:housenumber":"301",
    "addr:postcode":"29672",
    "addr:street":"Memorial Dr",
    "iso:country":"US",
    "sg:address":"301 Memorial Dr",
    "sg:city":"Seneca",
    "sg:classifiers":[
        {
            "category":"Shopping",
            "subcategory":"Pharmacy",
            "type":"Retail Goods"
        }
    ],
    "sg:phone":"+1 864 888 2232",
    "sg:postcode":"29672",
    "sg:province":"SC",
    "wof:name":"Mauldins Pharmacy",
    "wof:placetype":"venue"
},
  "geometry": {"coordinates":[-82.988719,34.693998],"type":"Point"}
}