{
  "type": "Feature",
  "properties": {
    "iso:country":"US",
    "sg:address":"220 Stoneridge Dr Suite 402",
    "sg:city":"Columbia",
    "sg:classifiers":[
        {
            "category":"Professional",
            "subcategory":"Accounting & Tax Preparation",
            "type":"Services"
        },
        {
            "category":"Banks & Credit Unions",
            "subcategory":"Financial Services",
            "type":"Services"
        }
    ],
    "sg:phone":"+1 803 477 5973",
    "sg:postcode":"29210",
    "sg:province":"SC",
    "sg:tags":[
        "accountant"
    ],
    "sg:website":"www.AECG.biz",
    "wof:name":"Kirkland Stephen D CPA",
    "wof:placetype":"venue"
},
  "geometry": {"coordinates":[-81.07921399999999,34.014819],"type":"Point"}
}