{
  "type": "Feature",
  "properties": {
    "addr:full":"200 Owens Rd Piedmont SC 29673",
    "addr:housenumber":"200",
    "addr:postcode":"29673",
    "addr:street":"Owens Rd",
    "iso:country":"US",
    "sg:address":"200 Owens Rd",
    "sg:city":"Piedmont",
    "sg:classifiers":[
        {
            "category":"Government",
            "subcategory":"Office",
            "type":"Public Place"
        }
    ],
    "sg:phone":"+1 864 845 3466",
    "sg:postcode":"29673",
    "sg:province":"SC",
    "wof:name":"Greenville County Convenience",
    "wof:placetype":"venue"
},
  "geometry": {"coordinates":[-82.425798,34.678446],"type":"Point"}
}