{
  "type": "Feature",
  "properties": {
    "iso:country":"US",
    "sg:address":"3255 W Oak Hwy",
    "sg:city":"Westminster",
    "sg:classifiers":[
        {
            "category":"Building & Trades",
            "subcategory":"Construction",
            "type":"Services"
        }
    ],
    "sg:phone":"+1 864 647 1555",
    "sg:postcode":"29693",
    "sg:province":"SC",
    "sg:tags":[
        "house"
    ],
    "wof:name":"Massey Builders",
    "wof:placetype":"venue"
},
  "geometry": {"coordinates":[-83.054255,34.624989],"type":"Point"}
}