{
  "type": "Feature",
  "properties": {
    "iso:country":"US",
    "sg:address":"714 Riverdale Dr",
    "sg:city":"Charleston",
    "sg:classifiers":[
        {
            "category":"Organizations",
            "subcategory":"Religious Organization",
            "type":"Services"
        }
    ],
    "sg:phone":"+1 843 571 6655",
    "sg:postcode":"29407",
    "sg:province":"SC",
    "sg:tags":[
        "church"
    ],
    "wof:name":"Lutheran Church-The Redeemer",
    "wof:placetype":"venue"
},
  "geometry": {"coordinates":[-79.983565,32.783243],"type":"Point"}
}