{
  "type": "Feature",
  "properties": {
    "iso:country":"US",
    "sg:address":"1114 Greenlawn Dr",
    "sg:city":"Columbia",
    "sg:classifiers":[
        {
            "category":"Social Services",
            "subcategory":"Child Care",
            "type":"Services"
        }
    ],
    "sg:phone":"+1 803 776 9471",
    "sg:postcode":"29209",
    "sg:province":"SC",
    "wof:name":"Cuddle Care Preschool Inc",
    "wof:placetype":"venue"
},
  "geometry": {"coordinates":[-80.941081,33.974519],"type":"Point"}
}