{
  "type": "Feature",
  "properties": {
    "addr:full":"155 N Williamson Rd Florence SC 29506",
    "addr:housenumber":"155",
    "addr:postcode":"29506",
    "addr:street":"N Williamson Rd",
    "iso:country":"US",
    "sg:address":"155 N Williamson Rd",
    "sg:city":"Florence",
    "sg:classifiers":[
        {
            "category":"Personal",
            "subcategory":"Beauty Salon",
            "type":"Services"
        }
    ],
    "sg:phone":"+1 843 292 0088",
    "sg:postcode":"29506",
    "sg:province":"SC",
    "wof:name":"Beautiful Experience",
    "wof:placetype":"venue"
},
  "geometry": {"coordinates":[-79.70475500000001,34.199036],"type":"Point"}
}