{
  "type": "Feature",
  "properties": {
    "iso:country":"US",
    "sg:address":"1544 Hutton Pl",
    "sg:city":"Charleston",
    "sg:classifiers":[
        {
            "category":"Building & Trades",
            "subcategory":"Construction",
            "type":"Services"
        }
    ],
    "sg:phone":"+1 843 852 0190",
    "sg:postcode":"29407",
    "sg:province":"SC",
    "sg:tags":[
        "home",
        "builder"
    ],
    "wof:name":"Plantation Construction",
    "wof:placetype":"venue"
},
  "geometry": {"coordinates":[-80.015047,32.818144],"type":"Point"}
}