{
  "type": "Feature",
  "properties": {
    "iso:country":"US",
    "sg:address":"1620 Gervais St",
    "sg:city":"Columbia",
    "sg:classifiers":[
        {
            "category":"Professional",
            "subcategory":"Lawyer & Legal Services",
            "type":"Services"
        }
    ],
    "sg:phone":"+1 803 799 9022",
    "sg:postcode":"29201",
    "sg:province":"SC",
    "wof:name":"Massey David E",
    "wof:placetype":"venue"
},
  "geometry": {"coordinates":[-81.025921,34.003178],"type":"Point"}
}