{
  "type": "Feature",
  "properties": {
    "addr:full":"3 Sunderland Dr Greenville SC 29611",
    "addr:housenumber":"3",
    "addr:postcode":"29611",
    "addr:street":"Sunderland Dr",
    "iso:country":"US",
    "sg:address":"3 Sunderland Dr",
    "sg:city":"Greenville",
    "sg:classifiers":[
        {
            "category":"Manufacturing",
            "subcategory":"Metals",
            "type":"Manufacturing & Wholesale Goods"
        }
    ],
    "sg:phone":"+1 864 246 5579",
    "sg:postcode":"29611",
    "sg:province":"SC",
    "sg:tags":[
        "distributor",
        "tool"
    ],
    "wof:name":"Mac Tool Distributor",
    "wof:placetype":"venue"
},
  "geometry": {"coordinates":[-82.46909100000001,34.865128],"type":"Point"}
}