{
  "type": "Feature",
  "properties": {
    "addr:full":"2 Goethe Rd Bluffton SC 29910",
    "addr:housenumber":"2",
    "addr:postcode":"29910",
    "addr:street":"Goethe Rd",
    "iso:country":"US",
    "sg:address":"2 Goethe Rd",
    "sg:city":"Bluffton",
    "sg:classifiers":[
        {
            "category":"Building & Trades",
            "subcategory":"Construction",
            "type":"Services"
        }
    ],
    "sg:phone":"+1 843 815 8373",
    "sg:postcode":"29910",
    "sg:province":"SC",
    "sg:tags":[
        "contractor"
    ],
    "wof:name":"Patlan Drywall",
    "wof:placetype":"venue"
},
  "geometry": {"coordinates":[-80.85480699999999,32.253516],"type":"Point"}
}