{
  "type": "Feature",
  "properties": {
    "iso:country":"US",
    "sg:address":"3821 Saluda Dam Rd",
    "sg:city":"Easley",
    "sg:classifiers":[
        {
            "category":"Organizations",
            "subcategory":"Religious Organization",
            "type":"Services"
        }
    ],
    "sg:phone":"+1 864 295 2360",
    "sg:postcode":"29640",
    "sg:province":"SC",
    "sg:tags":[
        "church"
    ],
    "sg:website":"www.westwoodbaptistchurchsc.com",
    "wof:name":"Westwood Baptist Church",
    "wof:placetype":"venue"
},
  "geometry": {"coordinates":[-82.48864399999999,34.853438],"type":"Point"}
}