{
  "type": "Feature",
  "properties": {
    "iso:country":"US",
    "sg:address":"1281 Ebenezer Rd",
    "sg:city":"Rock Hill",
    "sg:classifiers":[
        {
            "category":"Organizations",
            "subcategory":"Political Organization",
            "type":"Services"
        }
    ],
    "sg:phone":"+1 803 980 6629",
    "sg:postcode":"29732",
    "sg:province":"SC",
    "wof:name":"York County Republican Party",
    "wof:placetype":"venue"
},
  "geometry": {"coordinates":[-81.038775,34.946776],"type":"Point"}
}