{
  "type": "Feature",
  "properties": {
    "addr:full":"219 N Jones Rd Olanta SC 29114",
    "addr:housenumber":"219",
    "addr:postcode":"29114",
    "addr:street":"N Jones Rd",
    "iso:country":"US",
    "sg:address":"219 N Jones Rd",
    "sg:city":"Olanta",
    "sg:classifiers":[
        {
            "category":"Education",
            "subcategory":"School",
            "type":"Public Place"
        }
    ],
    "sg:phone":"+1 843 396 4457",
    "sg:postcode":"29114",
    "sg:province":"SC",
    "wof:name":"Olanta Elementary School",
    "wof:placetype":"venue"
},
  "geometry": {"coordinates":[-79.933555,33.937936],"type":"Point"}
}