{
  "type": "Feature",
  "properties": {
    "iso:country":"US",
    "sg:address":"1105 Oak Harbor Blvd",
    "sg:city":"Isle Of Palms",
    "sg:classifiers":[
        {
            "category":"Building & Trades",
            "subcategory":"Construction",
            "type":"Services"
        }
    ],
    "sg:phone":"+1 843 886 8127",
    "sg:postcode":"29451",
    "sg:province":"SC",
    "sg:tags":[
        "residential"
    ],
    "wof:name":"P & A LLC",
    "wof:placetype":"venue"
},
  "geometry": {"coordinates":[-79.79016900000001,32.787819],"type":"Point"}
}