{
  "type": "Feature",
  "properties": {
    "addr:full":"611 E Wade Hampton Blvd Greer SC 29651",
    "addr:housenumber":"611",
    "addr:postcode":"29651",
    "addr:street":"E Wade Hampton Blvd",
    "iso:country":"US",
    "sg:address":"611 E Wade Hampton Blvd",
    "sg:city":"Greer",
    "sg:classifiers":[
        {
            "category":"Health Services",
            "subcategory":"Chiropractor",
            "type":"Services"
        }
    ],
    "sg:phone":"+1 864 877 2042",
    "sg:postcode":"29651",
    "sg:province":"SC",
    "wof:name":"Carolina Chiropractic",
    "wof:placetype":"venue"
},
  "geometry": {"coordinates":[-82.216521,34.947751],"type":"Point"}
}