{
  "type": "Feature",
  "properties": {
    "addr:full":"421 Bush River Rd Columbia SC 29210",
    "addr:housenumber":"421",
    "addr:postcode":"29210",
    "addr:street":"Bush River Rd",
    "iso:country":"US",
    "sg:address":"421 Bush River Rd",
    "sg:city":"Columbia",
    "sg:classifiers":[
        {
            "category":"Restaurant",
            "type":"Food & Drink"
        }
    ],
    "sg:phone":"+1 803 798 8828",
    "sg:postcode":"29210",
    "sg:province":"SC",
    "sg:tags":[
        "chinese"
    ],
    "wof:name":"Super China Buffett",
    "wof:placetype":"venue"
},
  "geometry": {"coordinates":[-81.0942,34.0308],"type":"Point"}
}