{
  "type": "Feature",
  "properties": {
    "addr:full":"702 38th Ave N Myrtle Beach SC 29577",
    "addr:housenumber":"702",
    "addr:postcode":"29577",
    "addr:street":"38Th Ave N",
    "iso:country":"US",
    "sg:address":"702 38th Ave N",
    "sg:city":"Myrtle Beach",
    "sg:classifiers":[
        {
            "category":"Personal",
            "subcategory":"Barber",
            "type":"Services"
        }
    ],
    "sg:phone":"+1 843 445 9777",
    "sg:postcode":"29577",
    "sg:province":"SC",
    "wof:name":"City Barber Shop",
    "wof:placetype":"venue"
},
  "geometry": {"coordinates":[-78.859911,33.718318],"type":"Point"}
}