{
  "type": "Feature",
  "properties": {
    "addr:full":"853 Stockbridge Dr Fort Mill SC 29708",
    "addr:housenumber":"853",
    "addr:postcode":"29708",
    "addr:street":"Stockbridge Dr",
    "iso:country":"US",
    "sg:address":"853 Stockbridge Dr",
    "sg:city":"Fort Mill",
    "sg:classifiers":[
        {
            "category":"Personal",
            "subcategory":"Beauty Salon",
            "type":"Services"
        }
    ],
    "sg:phone":"+1 803 547 0028",
    "sg:postcode":"29708",
    "sg:province":"SC",
    "wof:name":"Hair Cuttery",
    "wof:placetype":"venue"
},
  "geometry": {"coordinates":[-80.992589,35.062645],"type":"Point"}
}