{
  "type": "Feature",
  "properties": {
    "addr:full":"2018 2nd Loop Rd Florence SC 29501",
    "addr:housenumber":"2018",
    "addr:postcode":"29501",
    "addr:street":"2Nd Loop Rd",
    "iso:country":"US",
    "sg:address":"2018 2nd Loop Rd",
    "sg:city":"Florence",
    "sg:classifiers":[
        {
            "category":"Autos & Motor Vehicles",
            "subcategory":"Automobile Sales",
            "type":"Retail Goods"
        }
    ],
    "sg:phone":"+1 843 662 7756",
    "sg:postcode":"29501",
    "sg:province":"SC",
    "sg:tags":[
        "used"
    ],
    "wof:name":"Snipes Used Cars",
    "wof:placetype":"venue"
},
  "geometry": {"coordinates":[-79.802622,34.172162],"type":"Point"}
}