{
  "type": "Feature",
  "properties": {
    "iso:country":"US",
    "sg:address":"120 Midlands Ct",
    "sg:city":"West Columbia",
    "sg:classifiers":[
        {
            "category":"Health Services",
            "subcategory":"Dentist",
            "type":"Services"
        }
    ],
    "sg:phone":"+1 803 739 0390",
    "sg:postcode":"29169",
    "sg:province":"SC",
    "wof:name":"Powell Sherry DMD",
    "wof:placetype":"venue"
},
  "geometry": {"coordinates":[-81.130925,34.009681],"type":"Point"}
}