{
  "type": "Feature",
  "properties": {
    "iso:country":"US",
    "sg:address":"1206 US Hwy 17 N",
    "sg:city":"Surfside Beach",
    "sg:classifiers":[
        {
            "category":"Restaurant",
            "type":"Food & Drink"
        }
    ],
    "sg:phone":"+1 843 448 1702",
    "sg:postcode":"29575",
    "sg:province":"SC",
    "wof:name":"Shoney's",
    "wof:placetype":"venue"
},
  "geometry": {"coordinates":[-78.972893,33.620932],"type":"Point"}
}