{
  "type": "Feature",
  "properties": {
    "iso:country":"US",
    "sg:address":"1096 McMillan Rd",
    "sg:city":"Greeleyville",
    "sg:phone":"+1 843 426 2887",
    "sg:postcode":"29056",
    "sg:province":"SC",
    "sg:tags":[
        "farm",
        "corn",
        "cotton"
    ],
    "wof:name":"Dixie B Godwin",
    "wof:placetype":"venue"
},
  "geometry": {"coordinates":[-79.951801,33.569142],"type":"Point"}
}