{
  "type": "Feature",
  "properties": {
    "iso:country":"US",
    "sg:address":"1251 Rutherfordton Hwy",
    "sg:city":"Chesnee",
    "sg:classifiers":[
        {
            "category":"Recreation",
            "subcategory":"Amusement Park",
            "type":"Entertainment"
        }
    ],
    "sg:phone":"+1 864 703 9700",
    "sg:postcode":"29323",
    "sg:province":"SC",
    "wof:name":"Quick Silver Amusement",
    "wof:placetype":"venue"
},
  "geometry": {"coordinates":[-81.844511,35.180675],"type":"Point"}
}