{
  "type": "Feature",
  "properties": {
    "addr:full":"4700 S Kings Hwy Myrtle Beach SC 29575",
    "addr:housenumber":"4700",
    "addr:postcode":"29575",
    "addr:street":"S Kings Hwy",
    "iso:country":"US",
    "sg:address":"4700 S Kings Hwy",
    "sg:city":"Myrtle Beach",
    "sg:classifiers":[
        {
            "category":"Retail",
            "subcategory":"Auto Repair",
            "type":"Services"
        }
    ],
    "sg:phone":"+1 843 238 8200",
    "sg:postcode":"29575",
    "sg:province":"SC",
    "sg:tags":[
        "repairing",
        "automobile"
    ],
    "wof:name":"A Plus Auto Glass",
    "wof:placetype":"venue"
},
  "geometry": {"coordinates":[-78.94143800000001,33.646992],"type":"Point"}
}