{
  "type": "Feature",
  "properties": {
    "iso:country":"US",
    "sg:address":"1215 Grove Rd",
    "sg:city":"Greenville",
    "sg:classifiers":[
        {
            "category":"Autos & Motor Vehicles",
            "subcategory":"Automobile Sales",
            "type":"Retail Goods"
        }
    ],
    "sg:phone":"+1 864 467 1649",
    "sg:postcode":"29605",
    "sg:province":"SC",
    "sg:tags":[
        "car",
        "used",
        "dealer"
    ],
    "wof:name":"Jimmy's Auto Sales",
    "wof:placetype":"venue"
},
  "geometry": {"coordinates":[-82.421128,34.808479],"type":"Point"}
}