{
  "type": "Feature",
  "properties": {
    "addr:full":"293 Greystone Blvd Columbia SC 29210",
    "addr:housenumber":"293",
    "addr:postcode":"29210",
    "addr:street":"Greystone Blvd",
    "iso:country":"US",
    "sg:address":"293 Greystone Blvd",
    "sg:city":"Columbia",
    "sg:classifiers":[
        {
            "category":"Health Services",
            "subcategory":"Hospital",
            "type":"Services"
        }
    ],
    "sg:phone":"+1 803 296 5220",
    "sg:postcode":"29210",
    "sg:province":"SC",
    "sg:website":"www.palmettohealth.org",
    "wof:name":"Palmetto Health Richland",
    "wof:placetype":"venue"
},
  "geometry": {"coordinates":[-81.07662000000001,34.019643],"type":"Point"}
}