{
  "type": "Feature",
  "properties": {
    "addr:full":"2868 State Hwy 160 Fort Mill SC 29708",
    "addr:housenumber":"2868",
    "addr:postcode":"29708",
    "addr:street":"State Hwy 160",
    "iso:country":"US",
    "sg:address":"2868 State Hwy 160",
    "sg:city":"Fort Mill",
    "sg:classifiers":[
        {
            "category":"Retail",
            "subcategory":"Laundry & Dry Cleaning",
            "type":"Services"
        }
    ],
    "sg:phone":"+1 803 548 6937",
    "sg:postcode":"29708",
    "sg:province":"SC",
    "sg:tags":[
        "cleaners"
    ],
    "wof:name":"Classic Cleaners",
    "wof:placetype":"venue"
},
  "geometry": {"coordinates":[-80.991619,35.060103],"type":"Point"}
}