{
  "type": "Feature",
  "properties": {
    "addr:full":"305 Church St Conway SC 29527",
    "addr:housenumber":"305",
    "addr:postcode":"29527",
    "addr:street":"Church St",
    "iso:country":"US",
    "sg:address":"305 Church St",
    "sg:city":"Conway",
    "sg:classifiers":[
        {
            "category":"Building & Trades",
            "subcategory":"Plumbing",
            "type":"Services"
        }
    ],
    "sg:phone":"+1 843 488 2243",
    "sg:postcode":"29527",
    "sg:province":"SC",
    "sg:tags":[
        "conditioning",
        "air",
        "system",
        "contractor"
    ],
    "wof:name":"Mercury Heating & Air Cond",
    "wof:placetype":"venue"
},
  "geometry": {"coordinates":[-79.05905799999999,33.830657],"type":"Point"}
}