{
  "type": "Feature",
  "properties": {
    "iso:country":"US",
    "sg:address":"98 Mount Carmel Rd",
    "sg:city":"Walterboro",
    "sg:classifiers":[
        {
            "category":"Professional",
            "subcategory":"Accounting & Tax Preparation",
            "type":"Services"
        }
    ],
    "sg:phone":"+1 843 538 5128",
    "sg:postcode":"29488",
    "sg:province":"SC",
    "sg:tags":[
        "accountant"
    ],
    "wof:name":"Patricia H Saunders CPA",
    "wof:placetype":"venue"
},
  "geometry": {"coordinates":[-80.684998,32.933486],"type":"Point"}
}