{
  "type": "Feature",
  "properties": {
    "addr:full":"2004 Wappoo Dr Charleston SC 29412",
    "addr:housenumber":"2004",
    "addr:postcode":"29412",
    "addr:street":"Wappoo Dr",
    "iso:country":"US",
    "sg:address":"2004 Wappoo Dr",
    "sg:city":"Charleston",
    "sg:classifiers":[
        {
            "category":"Shopping",
            "type":"Retail Goods"
        }
    ],
    "sg:phone":"+1 843 762 3999",
    "sg:postcode":"29412",
    "sg:province":"SC",
    "sg:tags":[
        "flower",
        "artificial"
    ],
    "wof:name":"Lady Tess Everlasting Florals",
    "wof:placetype":"venue"
},
  "geometry": {"coordinates":[-79.98848700000001,32.762352],"type":"Point"}
}