{
  "type": "Feature",
  "properties": {
    "iso:country":"US",
    "sg:address":"2740 State Hwy 101",
    "sg:city":"Greer",
    "sg:classifiers":[
        {
            "category":"Freight",
            "type":"Transportation"
        }
    ],
    "sg:phone":"+1 864 879 4140",
    "sg:postcode":"29651",
    "sg:province":"SC",
    "sg:tags":[
        "operator",
        "trucking"
    ],
    "wof:name":"G & P Trucking Co Inc",
    "wof:placetype":"venue"
},
  "geometry": {"coordinates":[-82.142423,34.864039],"type":"Point"}
}