{
  "type": "Feature",
  "properties": {
    "iso:country":"US",
    "sg:address":"4597 Fish Hatchery Rd",
    "sg:city":"Gaston",
    "sg:classifiers":[
        {
            "category":"Building & Trades",
            "subcategory":"Construction",
            "type":"Services"
        }
    ],
    "sg:phone":"+1 803 755 0338",
    "sg:postcode":"29053",
    "sg:province":"SC",
    "sg:tags":[
        "floor",
        "laying",
        "contractor"
    ],
    "wof:name":"Jimmy C Stukes Hardwood Floors",
    "wof:placetype":"venue"
},
  "geometry": {"coordinates":[-81.183154,33.810713],"type":"Point"}
}