{
  "type": "Feature",
  "properties": {
    "iso:country":"US",
    "sg:address":"1605 Cedar Lane Rd",
    "sg:city":"Greenville",
    "sg:classifiers":[
        {
            "category":"Personal",
            "subcategory":"Beauty Salon",
            "type":"Services"
        }
    ],
    "sg:phone":"+1 864 246 2024",
    "sg:postcode":"29617",
    "sg:province":"SC",
    "wof:name":"Jordan's Hair Co",
    "wof:placetype":"venue"
},
  "geometry": {"coordinates":[-82.44713400000001,34.879178],"type":"Point"}
}