{
  "type": "Feature",
  "properties": {
    "iso:country":"US",
    "sg:address":"220 Riverwood Dr",
    "sg:city":"Salem",
    "sg:classifiers":[
        {
            "category":"Wholesale",
            "subcategory":"Plants",
            "type":"Manufacturing & Wholesale Goods"
        }
    ],
    "sg:phone":"+1 864 944 5764",
    "sg:postcode":"29676",
    "sg:province":"SC",
    "sg:tags":[
        "supply"
    ],
    "wof:name":"Green House",
    "wof:placetype":"venue"
},
  "geometry": {"coordinates":[-82.99590600000001,34.870751],"type":"Point"}
}