{
  "type": "Feature",
  "properties": {
    "iso:country":"US",
    "sg:address":"734 Mayflower Rd",
    "sg:city":"Chapin",
    "sg:classifiers":[
        {
            "category":"Manufacturing",
            "subcategory":"Printing",
            "type":"Manufacturing & Wholesale Goods"
        }
    ],
    "sg:phone":"+1 803 345 6061",
    "sg:postcode":"29036",
    "sg:province":"SC",
    "sg:tags":[
        "commercial"
    ],
    "wof:name":"Direct Display LLC",
    "wof:placetype":"venue"
},
  "geometry": {"coordinates":[-81.367481,34.106073],"type":"Point"}
}