{
  "type": "Feature",
  "properties": {
    "iso:country":"US",
    "sg:address":"101 Verdae Blvd",
    "sg:city":"Greenville",
    "sg:classifiers":[
        {
            "category":"Professional",
            "subcategory":"Management & Consulting",
            "type":"Services"
        },
        {
            "category":"Building & Trades",
            "subcategory":"Landscaping Services",
            "type":"Services"
        }
    ],
    "sg:phone":"+1 864 292 0002",
    "sg:postcode":"29607",
    "sg:province":"SC",
    "sg:tags":[
        "consultant",
        "lighting"
    ],
    "wof:name":"Outdoor Lighting Perspectives",
    "wof:placetype":"venue"
},
  "geometry": {"coordinates":[-82.340667,34.8193],"type":"Point"}
}