{
  "type": "Feature",
  "properties": {
    "addr:full":"275 Harbison Blvd Columbia SC 29212",
    "addr:housenumber":"275",
    "addr:postcode":"29212",
    "addr:street":"Harbison Blvd",
    "iso:country":"US",
    "sg:address":"275 Harbison Blvd",
    "sg:city":"Columbia",
    "sg:classifiers":[
        {
            "category":"Personal",
            "type":"Services"
        }
    ],
    "sg:phone":"+1 803 407 2224",
    "sg:postcode":"29212",
    "sg:province":"SC",
    "sg:tags":[
        "control",
        "weight"
    ],
    "wof:name":"LA Weight Loss Ctr",
    "wof:placetype":"venue"
},
  "geometry": {"coordinates":[-81.15681600000001,34.073674],"type":"Point"}
}