{
  "type": "Feature",
  "properties": {
    "iso:country":"US",
    "sg:address":"631 Cane Branch Rd",
    "sg:city":"Loris",
    "sg:phone":"+1 843 756 6437",
    "sg:postcode":"29569",
    "sg:province":"SC",
    "sg:tags":[
        "farm",
        "tobacco",
        "soybean"
    ],
    "wof:name":"Marcus Gerald",
    "wof:placetype":"venue"
},
  "geometry": {"coordinates":[-78.941565,34.008352],"type":"Point"}
}