{
  "type": "Feature",
  "properties": {
    "iso:country":"US",
    "sg:address":"2423 Montague Ave Exd",
    "sg:city":"Greenwood",
    "sg:classifiers":[
        {
            "category":"Sports & Exercise",
            "subcategory":"Bowling",
            "type":"Entertainment"
        }
    ],
    "sg:phone":"+1 864 223 7676",
    "sg:postcode":"29649",
    "sg:province":"SC",
    "sg:tags":[
        "center"
    ],
    "wof:name":"Expo 300",
    "wof:placetype":"venue"
},
  "geometry": {"coordinates":[-82.20886,34.237997],"type":"Point"}
}