{
  "type": "Feature",
  "properties": {
    "iso:country":"US",
    "sg:address":"2685 Industrial Ave",
    "sg:city":"North Charleston",
    "sg:classifiers":[
        {
            "category":"Retail",
            "subcategory":"Auto Repair",
            "type":"Services"
        }
    ],
    "sg:phone":"+1 843 744 2277",
    "sg:postcode":"29405",
    "sg:province":"SC",
    "sg:tags":[
        "repairing",
        "tire"
    ],
    "wof:name":"Truck Tire Svc Inc",
    "wof:placetype":"venue"
},
  "geometry": {"coordinates":[-80.004623,32.848025],"type":"Point"}
}