{
  "type": "Feature",
  "properties": {
    "iso:country":"US",
    "sg:address":"111 Southland Rd",
    "sg:city":"Gilbert",
    "sg:classifiers":[
        {
            "category":"Freight",
            "type":"Transportation"
        }
    ],
    "sg:phone":"+1 803 892 2523",
    "sg:postcode":"29054",
    "sg:province":"SC",
    "sg:tags":[
        "operator",
        "trucking"
    ],
    "wof:name":"Frank L Dial Jr",
    "wof:placetype":"venue"
},
  "geometry": {"coordinates":[-81.373055,33.965494],"type":"Point"}
}