{
  "type": "Feature",
  "properties": {
    "iso:country":"US",
    "sg:address":"100 McMillan Dr",
    "sg:city":"Spartanburg",
    "sg:classifiers":[
        {
            "category":"Organizations",
            "subcategory":"Community Association",
            "type":"Services"
        }
    ],
    "sg:phone":"+1 864 597 1634",
    "sg:postcode":"29303",
    "sg:province":"SC",
    "sg:tags":[
        "club"
    ],
    "wof:name":"Danz Place Inc",
    "wof:placetype":"venue"
},
  "geometry": {"coordinates":[-81.92904799999999,34.969153],"type":"Point"}
}