{
  "type": "Feature",
  "properties": {
    "addr:full":"3111 US Hwy 301 N Hamer SC 29547",
    "addr:housenumber":"3111",
    "addr:postcode":"29547",
    "addr:street":"Us Hwy 301 N",
    "iso:country":"US",
    "sg:address":"3111 US Hwy 301 N",
    "sg:city":"Hamer",
    "sg:classifiers":[
        {
            "category":"Bars & Pubs",
            "type":"Food & Drink"
        }
    ],
    "sg:phone":"+1 843 774 7770",
    "sg:postcode":"29547",
    "sg:province":"SC",
    "sg:tags":[
        "club",
        "night"
    ],
    "wof:name":"Paradise Lingerie",
    "wof:placetype":"venue"
},
  "geometry": {"coordinates":[-79.32122699999999,34.487337],"type":"Point"}
}