{
  "type": "Feature",
  "properties": {
    "iso:country":"US",
    "sg:address":"14573 State Hwy 19",
    "sg:city":"Nichols",
    "sg:phone":"+1 843 392 9292",
    "sg:postcode":"29581",
    "sg:province":"SC",
    "sg:tags":[
        "farm",
        "tobacco"
    ],
    "wof:name":"Williams Farms",
    "wof:placetype":"venue"
},
  "geometry": {"coordinates":[-79.053511,34.117841],"type":"Point"}
}