{
  "type": "Feature",
  "properties": {
    "iso:country":"US",
    "sg:address":"506 E Main St",
    "sg:city":"Moncks Corner",
    "sg:classifiers":[
        {
            "category":"Autos & Motor Vehicles",
            "subcategory":"Auto Supplies",
            "type":"Retail Goods"
        }
    ],
    "sg:phone":"+1 843 761 8022",
    "sg:postcode":"29461",
    "sg:province":"SC",
    "sg:tags":[
        "automobile",
        "parts"
    ],
    "wof:name":"Hood Auto Parts Inc",
    "wof:placetype":"venue"
},
  "geometry": {"coordinates":[-79.998659,33.192268],"type":"Point"}
}