{
  "type": "Feature",
  "properties": {
    "addr:full":"990 Prosperity Dr Orangeburg SC 29115",
    "addr:housenumber":"990",
    "addr:postcode":"29115",
    "addr:street":"Prosperity Dr",
    "iso:country":"US",
    "sg:address":"990 Prosperity Dr",
    "sg:city":"Orangeburg",
    "sg:classifiers":[
        {
            "category":"Autos & Motor Vehicles",
            "subcategory":"Automobile Sales",
            "type":"Retail Goods"
        }
    ],
    "sg:phone":"+1 803 536 1440",
    "sg:postcode":"29115",
    "sg:province":"SC",
    "sg:tags":[
        "car",
        "used",
        "dealer"
    ],
    "wof:name":"Winn's Auto Sales",
    "wof:placetype":"venue"
},
  "geometry": {"coordinates":[-80.846639,33.447439],"type":"Point"}
}