{
  "type": "Feature",
  "properties": {
    "iso:country":"US",
    "sg:address":"304 Park Rd",
    "sg:city":"Lexington",
    "sg:classifiers":[
        {
            "category":"Manufacturing",
            "subcategory":"Signs",
            "type":"Manufacturing & Wholesale Goods"
        }
    ],
    "sg:phone":"+1 803 996 1100",
    "sg:postcode":"29072",
    "sg:province":"SC",
    "wof:name":"Trojan Signs",
    "wof:placetype":"venue"
},
  "geometry": {"coordinates":[-81.257107,33.990294],"type":"Point"}
}