{
  "type": "Feature",
  "properties": {
    "addr:full":"3531 Maybank Hwy Johns Island SC 29455",
    "addr:housenumber":"3531",
    "addr:postcode":"29455",
    "addr:street":"Maybank Hwy",
    "iso:country":"US",
    "sg:address":"3531 Maybank Hwy",
    "sg:city":"Johns Island",
    "sg:classifiers":[
        {
            "category":"Education",
            "subcategory":"Library",
            "type":"Public Place"
        }
    ],
    "sg:phone":"+1 843 559 1945",
    "sg:postcode":"29455",
    "sg:province":"SC",
    "wof:name":"John's Island Regional Library",
    "wof:placetype":"venue"
},
  "geometry": {"coordinates":[-80.077071,32.723117],"type":"Point"}
}