{
  "type": "Feature",
  "properties": {
    "iso:country":"US",
    "sg:address":"22 Rhetts Bluff Rd",
    "sg:city":"Johns Island",
    "sg:classifiers":[
        {
            "category":"Shopping",
            "subcategory":"Gifts & Souvenirs",
            "type":"Retail Goods"
        }
    ],
    "sg:phone":"+1 843 768 2444",
    "sg:postcode":"29455",
    "sg:province":"SC",
    "wof:name":"Circe",
    "wof:placetype":"venue"
},
  "geometry": {"coordinates":[-80.087065,32.616597],"type":"Point"}
}