{
  "type": "Feature",
  "properties": {
    "iso:country":"US",
    "sg:address":"627 Dacusville Rd",
    "sg:city":"Marietta",
    "sg:classifiers":[
        {
            "category":"Retail",
            "subcategory":"Repair Shop",
            "type":"Services"
        }
    ],
    "sg:phone":"+1 864 836 0786",
    "sg:postcode":"29661",
    "sg:province":"SC",
    "sg:tags":[
        "sharpening"
    ],
    "wof:name":"B & L Sharpening Svc",
    "wof:placetype":"venue"
},
  "geometry": {"coordinates":[-82.52354800000001,34.991424],"type":"Point"}
}