{
  "type": "Feature",
  "properties": {
    "iso:country":"US",
    "sg:address":"301 N 3rd Ave",
    "sg:city":"Dillon",
    "sg:classifiers":[
        {
            "category":"Education",
            "subcategory":"School",
            "type":"Public Place"
        }
    ],
    "sg:phone":"+1 843 774 1212",
    "sg:postcode":"29536",
    "sg:province":"SC",
    "wof:name":"J V Martin Junior High School",
    "wof:placetype":"venue"
},
  "geometry": {"coordinates":[-79.372571,34.421071],"type":"Point"}
}