{
  "type": "Feature",
  "properties": {
    "iso:country":"US",
    "sg:address":"24 Shelter Cove Ln",
    "sg:city":"Hilton Head Isle",
    "sg:classifiers":[
        {
            "category":"Shopping",
            "subcategory":"Clothing, Apparel, & Fashions",
            "type":"Retail Goods"
        }
    ],
    "sg:phone":"+1 843 686 3555",
    "sg:postcode":"29928",
    "sg:province":"SC",
    "sg:tags":[
        "infant",
        "wear"
    ],
    "wof:name":"Gymborree Store",
    "wof:placetype":"venue"
},
  "geometry": {"coordinates":[-80.723457,32.181857],"type":"Point"}
}