{
  "type": "Feature",
  "properties": {
    "addr:full":"100 Verdae Blvd Greenville SC 29607",
    "addr:housenumber":"100",
    "addr:postcode":"29607",
    "addr:street":"Verdae Blvd",
    "iso:country":"US",
    "sg:address":"100 Verdae Blvd",
    "sg:city":"Greenville",
    "sg:classifiers":[
        {
            "category":"Banks & Credit Unions",
            "subcategory":"Bank",
            "type":"Services"
        }
    ],
    "sg:phone":"+1 864 331 6000",
    "sg:postcode":"29607",
    "sg:province":"SC",
    "sg:tags":[
        "mortgage"
    ],
    "sg:website":"www.gmgloans.com",
    "wof:name":"Global Mortgage",
    "wof:placetype":"venue"
},
  "geometry": {"coordinates":[-82.34056699999999,34.819182],"type":"Point"}
}