{
  "type": "Feature",
  "properties": {
    "iso:country":"US",
    "sg:address":"1071 Tiger Blvd",
    "sg:city":"Clemson",
    "sg:classifiers":[
        {
            "category":"Retail",
            "subcategory":"Car Wash",
            "type":"Services"
        }
    ],
    "sg:phone":"+1 864 654 6300",
    "sg:postcode":"29631",
    "sg:province":"SC",
    "sg:tags":[
        "polishing",
        "washing"
    ],
    "wof:name":"Dazzle Car Wash",
    "wof:placetype":"venue"
},
  "geometry": {"coordinates":[-82.849396,34.692754],"type":"Point"}
}