{
  "type": "Feature",
  "properties": {
    "addr:full":"2711 Middleburg Dr Columbia SC 29204",
    "addr:housenumber":"2711",
    "addr:postcode":"29204",
    "addr:street":"Middleburg Dr",
    "iso:country":"US",
    "sg:address":"2711 Middleburg Dr",
    "sg:city":"Columbia",
    "sg:classifiers":[
        {
            "category":"Professional",
            "subcategory":"Computer Services",
            "type":"Services"
        }
    ],
    "sg:phone":"+1 803 256 6123",
    "sg:postcode":"29204",
    "sg:province":"SC",
    "sg:tags":[
        "consultant",
        "designer"
    ],
    "wof:name":"Application Development Group",
    "wof:placetype":"venue"
},
  "geometry": {"coordinates":[-81.001867,34.01584],"type":"Point"}
}