{
  "type": "Feature",
  "properties": {
    "addr:full":"1101 3rd Ave S Myrtle Beach SC 29577",
    "addr:housenumber":"1101",
    "addr:postcode":"29577",
    "addr:street":"3Rd Ave S Myrtle",
    "iso:country":"US",
    "sg:address":"1101 3rd Ave S",
    "sg:city":"Myrtle Beach",
    "sg:classifiers":[
        {
            "category":"Shopping",
            "subcategory":"Hobbies, Toys, & Games",
            "type":"Retail Goods"
        }
    ],
    "sg:phone":"+1 843 916 9381",
    "sg:postcode":"29577",
    "sg:province":"SC",
    "sg:tags":[
        "supply"
    ],
    "wof:name":"Scientific Games Intl Inc",
    "wof:placetype":"venue"
},
  "geometry": {"coordinates":[-78.896609,33.691779],"type":"Point"}
}