{
  "type": "Feature",
  "properties": {
    "iso:country":"US",
    "sg:address":"75 Windham Blvd",
    "sg:city":"Aiken",
    "sg:classifiers":[
        {
            "category":"Manufacturing",
            "subcategory":"Metals",
            "type":"Manufacturing & Wholesale Goods"
        },
        {
            "category":"Building & Trades",
            "subcategory":"Construction",
            "type":"Services"
        }
    ],
    "sg:phone":"+1 803 641 6091",
    "sg:postcode":"29805",
    "sg:province":"SC",
    "sg:tags":[
        "steel",
        "product",
        "wire",
        "mfg",
        "well",
        "water",
        "drilling"
    ],
    "wof:name":"Shinsho American Corporation",
    "wof:placetype":"venue"
},
  "geometry": {"coordinates":[-81.683124,33.657201],"type":"Point"}
}