{
  "type": "Feature",
  "properties": {
    "iso:country":"US",
    "sg:address":"311 Dixie Dr",
    "sg:city":"Anderson",
    "sg:classifiers":[
        {
            "category":"Organizations",
            "subcategory":"Religious Organization",
            "type":"Services"
        }
    ],
    "sg:phone":"+1 864 296 0056",
    "sg:postcode":"29624",
    "sg:province":"SC",
    "sg:tags":[
        "church"
    ],
    "wof:name":"Spiritual Church Of God",
    "wof:placetype":"venue"
},
  "geometry": {"coordinates":[-82.641975,34.47726],"type":"Point"}
}