{
  "type": "Feature",
  "properties": {
    "iso:country":"US",
    "sg:address":"11056 Wilson Blvd",
    "sg:city":"Blythewood",
    "sg:classifiers":[
        {
            "category":"Building & Trades",
            "subcategory":"Construction",
            "type":"Services"
        }
    ],
    "sg:phone":"+1 803 735 1239",
    "sg:postcode":"29016",
    "sg:province":"SC",
    "sg:tags":[
        "house"
    ],
    "wof:name":"Owens Home Repair",
    "wof:placetype":"venue"
},
  "geometry": {"coordinates":[-80.96881500000001,34.228099],"type":"Point"}
}