{
  "type": "Feature",
  "properties": {
    "iso:country":"US",
    "sg:address":"3 Hickory Ln",
    "sg:city":"Hilton Head Isle",
    "sg:classifiers":[
        {
            "category":"Arts & Performance",
            "subcategory":"Theater",
            "type":"Entertainment"
        }
    ],
    "sg:phone":"+1 843 842 5156",
    "sg:postcode":"29928",
    "sg:province":"SC",
    "sg:tags":[
        "entertainer"
    ],
    "wof:name":"H H Rythm & Blues Society",
    "wof:placetype":"venue"
},
  "geometry": {"coordinates":[-80.77072699999999,32.135047],"type":"Point"}
}