{
  "type": "Feature",
  "properties": {
    "iso:country":"US",
    "sg:address":"2572 New Cut Church Rd",
    "sg:city":"Lancaster",
    "sg:classifiers":[
        {
            "category":"Building & Trades",
            "subcategory":"Construction",
            "type":"Services"
        }
    ],
    "sg:phone":"+1 803 286 6141",
    "sg:postcode":"29720",
    "sg:province":"SC",
    "sg:tags":[
        "contractor"
    ],
    "wof:name":"Terry Laney Construction",
    "wof:placetype":"venue"
},
  "geometry": {"coordinates":[-80.669449,34.777474],"type":"Point"}
}