{
  "type": "Feature",
  "properties": {
    "addr:full":"5378 Middle Rd Nichols SC 29581",
    "addr:housenumber":"5378",
    "addr:postcode":"29581",
    "addr:street":"Middle Rd",
    "iso:country":"US",
    "sg:address":"5378 Middle Rd",
    "sg:city":"Nichols",
    "sg:classifiers":[
        {
            "category":"Autos & Motor Vehicles",
            "subcategory":"Automobile Sales",
            "type":"Retail Goods"
        }
    ],
    "sg:phone":"+1 843 526 2374",
    "sg:postcode":"29581",
    "sg:province":"SC",
    "sg:tags":[
        "used"
    ],
    "wof:name":"Humphrey Auto Sales",
    "wof:placetype":"venue"
},
  "geometry": {"coordinates":[-79.167374,34.250593],"type":"Point"}
}