{
  "type": "Feature",
  "properties": {
    "iso:country":"US",
    "sg:address":"3105 Crickentree Ln",
    "sg:city":"Florence",
    "sg:classifiers":[
        {
            "category":"Insurance",
            "subcategory":"Insurance Agent",
            "type":"Services"
        }
    ],
    "sg:phone":"+1 843 229 1678",
    "sg:postcode":"29501",
    "sg:province":"SC",
    "sg:tags":[
        "adjuster"
    ],
    "wof:name":"Palmetto State Adjusters",
    "wof:placetype":"venue"
},
  "geometry": {"coordinates":[-79.83583,34.163198],"type":"Point"}
}