{
  "type": "Feature",
  "properties": {
    "iso:country":"US",
    "sg:address":"3320 Abingdon Rd",
    "sg:city":"Columbia",
    "sg:classifiers":[
        {
            "category":"Organizations",
            "subcategory":"Non-profit Organization",
            "type":"Services"
        }
    ],
    "sg:phone":"+1 803 988 0068",
    "sg:postcode":"29203",
    "sg:province":"SC",
    "sg:tags":[
        "information",
        "alcoholism",
        "treatment"
    ],
    "wof:name":"Oxford House Avondale",
    "wof:placetype":"venue"
},
  "geometry": {"coordinates":[-81.048447,34.032104],"type":"Point"}
}