{
  "type": "Feature",
  "properties": {
    "iso:country":"US",
    "sg:address":"140 Harmon Pond Cir",
    "sg:city":"Gilbert",
    "sg:classifiers":[
        {
            "category":"Building & Trades",
            "subcategory":"Construction",
            "type":"Services"
        }
    ],
    "sg:phone":"+1 803 657 5817",
    "sg:postcode":"29054",
    "sg:province":"SC",
    "sg:tags":[
        "house",
        "nonresidential"
    ],
    "wof:name":"Ballington Builders Inc",
    "wof:placetype":"venue"
},
  "geometry": {"coordinates":[-81.364818,33.834713],"type":"Point"}
}