{
  "type": "Feature",
  "properties": {
    "iso:country":"US",
    "sg:address":"3775 Maybank Hwy",
    "sg:city":"Johns Island",
    "sg:classifiers":[
        {
            "category":"Shopping",
            "subcategory":"Discount & Variety Stores",
            "type":"Retail Goods"
        }
    ],
    "sg:phone":"+1 843 559 3070",
    "sg:postcode":"29455",
    "sg:province":"SC",
    "wof:name":"Family Dollar Stores",
    "wof:placetype":"venue"
},
  "geometry": {"coordinates":[-80.086888,32.716963],"type":"Point"}
}