{
  "type": "Feature",
  "properties": {
    "iso:country":"US",
    "sg:address":"1591 Amelia St",
    "sg:city":"Orangeburg",
    "sg:classifiers":[
        {
            "category":"Health Services",
            "subcategory":"Nursing And Care Facility",
            "type":"Services"
        }
    ],
    "sg:phone":"+1 803 539 0608",
    "sg:postcode":"29115",
    "sg:province":"SC",
    "sg:tags":[
        "home",
        "retirement",
        "community"
    ],
    "wof:name":"Diana-Clarence Residential Cr",
    "wof:placetype":"venue"
},
  "geometry": {"coordinates":[-80.85926499999999,33.494729],"type":"Point"}
}