{
  "type": "Feature",
  "properties": {
    "iso:country":"US",
    "sg:address":"201 Chevy Dr",
    "sg:city":"Fountain Inn",
    "sg:classifiers":[
        {
            "category":"Wholesale",
            "subcategory":"Machinery & Supplies",
            "type":"Manufacturing & Wholesale Goods"
        }
    ],
    "sg:phone":"+1 864 862 2908",
    "sg:postcode":"29644",
    "sg:province":"SC",
    "sg:tags":[
        "equipment",
        "material",
        "handling"
    ],
    "wof:name":"Forklift Equipment Co Inc",
    "wof:placetype":"venue"
},
  "geometry": {"coordinates":[-82.21785,34.68984],"type":"Point"}
}