{
  "type": "Feature",
  "properties": {
    "addr:full":"1914 Woodruff Rd Greenville SC 29607",
    "addr:housenumber":"1914",
    "addr:postcode":"29607",
    "addr:street":"Woodruff Rd",
    "iso:country":"US",
    "sg:address":"1914 Woodruff Rd",
    "sg:city":"Greenville",
    "sg:classifiers":[
        {
            "category":"Sports & Exercise",
            "subcategory":"Gym",
            "type":"Entertainment"
        }
    ],
    "sg:phone":"+1 864 288 1411",
    "sg:postcode":"29607",
    "sg:province":"SC",
    "sg:tags":[
        "club",
        "health",
        "studio",
        "gymnasium"
    ],
    "wof:name":"Power Fitness",
    "wof:placetype":"venue"
},
  "geometry": {"coordinates":[-82.271547,34.819577],"type":"Point"}
}