{
  "type": "Feature",
  "properties": {
    "addr:full":"1001 Bluff Rd Columbia SC 29201",
    "addr:housenumber":"1001",
    "addr:postcode":"29201",
    "addr:street":"Bluff Rd",
    "iso:country":"US",
    "sg:address":"1001 Bluff Rd",
    "sg:city":"Columbia",
    "sg:classifiers":[
        {
            "category":"Wholesale",
            "subcategory":"Fruits & Vegetables",
            "type":"Manufacturing & Wholesale Goods"
        }
    ],
    "sg:phone":"+1 803 771 7625",
    "sg:postcode":"29201",
    "sg:province":"SC",
    "sg:tags":[
        "veggie"
    ],
    "wof:name":"Southern Produce",
    "wof:placetype":"venue"
},
  "geometry": {"coordinates":[-81.021643,33.973128],"type":"Point"}
}