{
  "type": "Feature",
  "properties": {
    "iso:country":"US",
    "sg:address":"4391 W Nixon Cir",
    "sg:city":"Little River",
    "sg:classifiers":[
        {
            "category":"Retail",
            "subcategory":"Auto Repair",
            "type":"Services"
        }
    ],
    "sg:phone":"+1 843 280 2869",
    "sg:postcode":"29566",
    "sg:province":"SC",
    "sg:tags":[
        "wrecker"
    ],
    "wof:name":"Affordable Towing",
    "wof:placetype":"venue"
},
  "geometry": {"coordinates":[-78.658687,33.852946],"type":"Point"}
}