{
  "type": "Feature",
  "properties": {
    "iso:country":"US",
    "sg:address":"709 Meansville Rd",
    "sg:city":"Union",
    "sg:classifiers":[
        {
            "category":"Personal",
            "subcategory":"Beauty Salon",
            "type":"Services"
        }
    ],
    "sg:phone":"+1 864 427 7050",
    "sg:postcode":"29379",
    "sg:province":"SC",
    "wof:name":"Mane Attraction",
    "wof:placetype":"venue"
},
  "geometry": {"coordinates":[-81.657624,34.740213],"type":"Point"}
}