{
  "type": "Feature",
  "properties": {
    "iso:country":"US",
    "sg:address":"528 12th St",
    "sg:city":"West Columbia",
    "sg:classifiers":[
        {
            "category":"Organizations",
            "subcategory":"Religious Organization",
            "type":"Services"
        }
    ],
    "sg:phone":"+1 803 739 0575",
    "sg:postcode":"29169",
    "sg:province":"SC",
    "sg:tags":[
        "church"
    ],
    "wof:name":"Converted Life Worship Ctr",
    "wof:placetype":"venue"
},
  "geometry": {"coordinates":[-81.072076,33.985781],"type":"Point"}
}