{
  "type": "Feature",
  "properties": {
    "iso:country":"US",
    "sg:address":"215 Swampfox Dr",
    "sg:city":"Fort Mill",
    "sg:classifiers":[
        {
            "category":"Shopping",
            "subcategory":"Beauty & Cosmetics",
            "type":"Retail Goods"
        }
    ],
    "sg:phone":"+1 803 547 5364",
    "sg:postcode":"29715",
    "sg:province":"SC",
    "sg:tags":[
        "merchandise"
    ],
    "wof:name":"Independent Beauty Consultant",
    "wof:placetype":"venue"
},
  "geometry": {"coordinates":[-80.905481,35.023849],"type":"Point"}
}