{
  "type": "Feature",
  "properties": {
    "addr:full":"120 Arrowwood Rd Columbia SC 29210",
    "addr:housenumber":"120",
    "addr:postcode":"29210",
    "addr:street":"Arrowwood Rd",
    "iso:country":"US",
    "sg:address":"120 Arrowwood Rd",
    "sg:city":"Columbia",
    "sg:classifiers":[
        {
            "category":"Wholesale",
            "subcategory":"Machinery & Supplies",
            "type":"Manufacturing & Wholesale Goods"
        }
    ],
    "sg:phone":"+1 803 772 3409",
    "sg:postcode":"29210",
    "sg:province":"SC",
    "sg:tags":[
        "equipment",
        "establishment"
    ],
    "wof:name":"Design House",
    "wof:placetype":"venue"
},
  "geometry": {"coordinates":[-81.09599300000001,34.025767],"type":"Point"}
}