{
  "type": "Feature",
  "properties": {
    "iso:country":"US",
    "sg:address":"2125 Airport Rd",
    "sg:city":"Greer",
    "sg:classifiers":[
        {
            "category":"Autos & Motor Vehicles",
            "subcategory":"Auto Supplies",
            "type":"Retail Goods"
        }
    ],
    "sg:phone":"+1 864 848 0601",
    "sg:postcode":"29651",
    "sg:province":"SC",
    "wof:name":"Southern Rods",
    "wof:placetype":"venue"
},
  "geometry": {"coordinates":[-82.212935,34.892615],"type":"Point"}
}