{
  "type": "Feature",
  "properties": {
    "iso:country":"US",
    "sg:address":"1520 Wingate St NE",
    "sg:city":"Orangeburg",
    "sg:classifiers":[
        {
            "category":"Bars & Pubs",
            "type":"Food & Drink"
        }
    ],
    "sg:phone":"+1 803 516 8788",
    "sg:postcode":"29118",
    "sg:province":"SC",
    "wof:name":"Columns Bar & Grill",
    "wof:placetype":"venue"
},
  "geometry": {"coordinates":[-80.865317,33.51813],"type":"Point"}
}