{
  "type": "Feature",
  "properties": {
    "iso:country":"US",
    "sg:address":"305 Lamar Hwy",
    "sg:city":"Darlington",
    "sg:classifiers":[
        {
            "category":"Personal",
            "subcategory":"Beauty Salon",
            "type":"Services"
        }
    ],
    "sg:phone":"+1 843 395 9550",
    "sg:postcode":"29532",
    "sg:province":"SC",
    "sg:tags":[
        "manicuring"
    ],
    "wof:name":"Classic Nails",
    "wof:placetype":"venue"
},
  "geometry": {"coordinates":[-79.888386,34.292934],"type":"Point"}
}