{
  "type": "Feature",
  "properties": {
    "iso:country":"US",
    "sg:address":"676 Fairview Rd",
    "sg:city":"Simpsonville",
    "sg:classifiers":[
        {
            "category":"Shopping",
            "subcategory":"Clothing, Apparel, & Fashions",
            "type":"Retail Goods"
        }
    ],
    "sg:phone":"+1 864 228 2223",
    "sg:postcode":"29680",
    "sg:province":"SC",
    "sg:tags":[
        "infant",
        "wear"
    ],
    "wof:name":"Bargain Babies",
    "wof:placetype":"venue"
},
  "geometry": {"coordinates":[-82.258004,34.705369],"type":"Point"}
}