{
  "type": "Feature",
  "properties": {
    "iso:country":"US",
    "sg:address":"256 Hillview Dr",
    "sg:city":"Graniteville",
    "sg:classifiers":[
        {
            "category":"Building & Trades",
            "subcategory":"Construction",
            "type":"Services"
        }
    ],
    "sg:phone":"+1 803 663 7417",
    "sg:postcode":"29829",
    "sg:province":"SC",
    "sg:tags":[
        "hanging",
        "contractor"
    ],
    "wof:name":"Pearsons Drywall Painting",
    "wof:placetype":"venue"
},
  "geometry": {"coordinates":[-81.827733,33.563561],"type":"Point"}
}