{
  "type": "Feature",
  "properties": {
    "iso:country":"US",
    "sg:address":"102 Republican Rd",
    "sg:city":"Edgefield",
    "sg:classifiers":[
        {
            "category":"Retail",
            "subcategory":"Auto Repair",
            "type":"Services"
        }
    ],
    "sg:phone":"+1 803 279 2788",
    "sg:postcode":"29824",
    "sg:province":"SC",
    "sg:tags":[
        "repairing",
        "automobile"
    ],
    "wof:name":"Lanham's Auto Svc",
    "wof:placetype":"venue"
},
  "geometry": {"coordinates":[-81.99445799999999,33.681763],"type":"Point"}
}