{
  "type": "Feature",
  "properties": {
    "iso:country":"US",
    "sg:address":"949 S Governor Williams Hwy",
    "sg:city":"Darlington",
    "sg:classifiers":[
        {
            "category":"Building & Trades",
            "subcategory":"Equipment Rental",
            "type":"Services"
        }
    ],
    "sg:phone":"+1 843 393 0289",
    "sg:postcode":"29532",
    "sg:province":"SC",
    "sg:tags":[
        "player",
        "recorder",
        "video"
    ],
    "wof:name":"Moviegallery",
    "wof:placetype":"venue"
},
  "geometry": {"coordinates":[-79.86306999999999,34.283419],"type":"Point"}
}