{
  "type": "Feature",
  "properties": {
    "iso:country":"US",
    "sg:address":"2065 Blossom St",
    "sg:city":"Columbia",
    "sg:classifiers":[
        {
            "category":"Organizations",
            "subcategory":"Religious Organization",
            "type":"Services"
        }
    ],
    "sg:phone":"+1 803 254 9048",
    "sg:postcode":"29205",
    "sg:province":"SC",
    "wof:name":"Dharmadhatu Buddhist Ctr",
    "wof:placetype":"venue"
},
  "geometry": {"coordinates":[-81.01539,33.997586],"type":"Point"}
}