{
  "type": "Feature",
  "properties": {
    "iso:country":"US",
    "sg:address":"1206 Red Bank Rd",
    "sg:city":"Goose Creek",
    "sg:classifiers":[
        {
            "category":"Building & Trades",
            "subcategory":"Plumbing",
            "type":"Services"
        }
    ],
    "sg:phone":"+1 843 863 8335",
    "sg:postcode":"29445",
    "sg:province":"SC",
    "sg:tags":[
        "conditioning",
        "air",
        "system",
        "contractor"
    ],
    "wof:name":"Action Heating & Cooling",
    "wof:placetype":"venue"
},
  "geometry": {"coordinates":[-80.012834,32.970841],"type":"Point"}
}