{
  "type": "Feature",
  "properties": {
    "addr:full":"1938 Ashley River Rd Charleston SC 29407",
    "addr:housenumber":"1938",
    "addr:postcode":"29407",
    "addr:street":"Ashley River Rd",
    "iso:country":"US",
    "sg:address":"1938 Ashley River Rd",
    "sg:city":"Charleston",
    "sg:classifiers":[
        {
            "category":"Cinema",
            "subcategory":"Movie Rental",
            "type":"Entertainment"
        }
    ],
    "sg:phone":"+1 843 556 0443",
    "sg:postcode":"29407",
    "sg:province":"SC",
    "sg:tags":[
        "leasing",
        "video",
        "disc",
        "tape"
    ],
    "wof:name":"Hollywood Video",
    "wof:placetype":"venue"
},
  "geometry": {"coordinates":[-80.022886,32.80686],"type":"Point"}
}