{
  "type": "Feature",
  "properties": {
    "iso:country":"US",
    "sg:address":"8 Shad Row",
    "sg:city":"Isle Of Palms",
    "sg:classifiers":[
        {
            "category":"Real Estate",
            "subcategory":"Real Estate Operator",
            "type":"Services"
        }
    ],
    "sg:phone":"+1 843 886 8838",
    "sg:postcode":"29451",
    "sg:province":"SC",
    "sg:tags":[
        "building",
        "nonresidential"
    ],
    "wof:name":"Sea Sands Properties LLC",
    "wof:placetype":"venue"
},
  "geometry": {"coordinates":[-79.745,32.802756],"type":"Point"}
}