{
  "type": "Feature",
  "properties": {
    "iso:country":"US",
    "sg:address":"930 Axtell Dr",
    "sg:city":"Cayce",
    "sg:classifiers":[
        {
            "category":"Personal",
            "subcategory":"Beauty Salon",
            "type":"Services"
        }
    ],
    "sg:phone":"+1 803 739 2007",
    "sg:postcode":"29033",
    "sg:province":"SC",
    "wof:name":"Hair West Of The Vista",
    "wof:placetype":"venue"
},
  "geometry": {"coordinates":[-81.052641,33.985929],"type":"Point"}
}