{
  "type": "Feature",
  "properties": {
    "addr:full":"298 Davis Rd Pelzer SC 29669",
    "addr:housenumber":"298",
    "addr:postcode":"29669",
    "addr:street":"Davis Rd",
    "iso:country":"US",
    "sg:address":"298 Davis Rd",
    "sg:city":"Pelzer",
    "sg:classifiers":[
        {
            "category":"Home & Garden",
            "subcategory":"Home Furnishings",
            "type":"Retail Goods"
        }
    ],
    "sg:phone":"+1 864 243 3840",
    "sg:postcode":"29669",
    "sg:province":"SC",
    "sg:tags":[
        "cutlery"
    ],
    "wof:name":"Skyhawk Cutlery LLC",
    "wof:placetype":"venue"
},
  "geometry": {"coordinates":[-82.364831,34.662286],"type":"Point"}
}