{
  "type": "Feature",
  "properties": {
    "iso:country":"US",
    "sg:address":"260 W Palmetto St",
    "sg:city":"Florence",
    "sg:classifiers":[
        {
            "category":"Restaurant",
            "type":"Food & Drink"
        }
    ],
    "sg:phone":"+1 843 629 9818",
    "sg:postcode":"29501",
    "sg:province":"SC",
    "wof:name":"Bazen's Family Restaurant",
    "wof:placetype":"venue"
},
  "geometry": {"coordinates":[-79.76901100000001,34.193562],"type":"Point"}
}