{
  "type": "Feature",
  "properties": {
    "addr:full":"1770 Mason Cir Murrells Inlet SC 29575",
    "addr:housenumber":"1770",
    "addr:postcode":"29575",
    "addr:street":"Mason Cir",
    "iso:country":"US",
    "sg:address":"1770 Mason Cir",
    "sg:city":"Murrells Inlet",
    "sg:classifiers":[
        {
            "category":"Banks & Credit Unions",
            "subcategory":"Investment Brokerage",
            "type":"Services"
        }
    ],
    "sg:phone":"+1 843 651 4841",
    "sg:postcode":"29575",
    "sg:province":"SC",
    "wof:name":"Oceanside Investments Inc",
    "wof:placetype":"venue"
},
  "geometry": {"coordinates":[-78.988652,33.591143],"type":"Point"}
}