{
  "type": "Feature",
  "properties": {
    "addr:full":"145 Rockwood Dr Greenville SC 29605",
    "addr:housenumber":"145",
    "addr:postcode":"29605",
    "addr:street":"Rockwood Dr",
    "iso:country":"US",
    "sg:address":"145 Rockwood Dr",
    "sg:city":"Greenville",
    "sg:classifiers":[
        {
            "category":"Shopping",
            "subcategory":"Musical Instruments",
            "type":"Retail Goods"
        }
    ],
    "sg:phone":"+1 864 414 3806",
    "sg:postcode":"29605",
    "sg:province":"SC",
    "sg:tags":[
        "piano"
    ],
    "wof:name":"Piano Store",
    "wof:placetype":"venue"
},
  "geometry": {"coordinates":[-82.39193,34.812245],"type":"Point"}
}