{
  "type": "Feature",
  "properties": {
    "iso:country":"US",
    "sg:address":"2044 Wilson Rd",
    "sg:city":"Newberry",
    "sg:classifiers":[
        {
            "category":"Personal",
            "subcategory":"Barber",
            "type":"Services"
        }
    ],
    "sg:phone":"+1 803 321 3284",
    "sg:postcode":"29108",
    "sg:province":"SC",
    "wof:name":"Kasual Kuts",
    "wof:placetype":"venue"
},
  "geometry": {"coordinates":[-81.60687799999999,34.294945],"type":"Point"}
}