{
  "type": "Feature",
  "properties": {
    "iso:country":"US",
    "sg:address":"5001 US Hwy 221 S",
    "sg:city":"Bradley",
    "sg:classifiers":[
        {
            "category":"Food & Beverages",
            "subcategory":"Groceries & Convenience Stores",
            "type":"Retail Goods"
        }
    ],
    "sg:phone":"+1 864 746 6054",
    "sg:postcode":"29819",
    "sg:province":"SC",
    "sg:tags":[
        "grocer"
    ],
    "wof:name":"Steifle Smith Grocery",
    "wof:placetype":"venue"
},
  "geometry": {"coordinates":[-82.245527,34.048072],"type":"Point"}
}