{
  "type": "Feature",
  "properties": {
    "addr:full":"498 State Hwy 90 E Little River SC 29566",
    "addr:housenumber":"498",
    "addr:postcode":"29566",
    "addr:street":"State Hwy 90 E",
    "iso:country":"US",
    "sg:address":"498 State Hwy 90 E",
    "sg:city":"Little River",
    "sg:classifiers":[
        {
            "category":"Real Estate",
            "subcategory":"Developer",
            "type":"Services"
        }
    ],
    "sg:phone":"+1 843 249 1796",
    "sg:postcode":"29566",
    "sg:province":"SC",
    "wof:name":"Ww & Lb Development Co LL",
    "wof:placetype":"venue"
},
  "geometry": {"coordinates":[-78.64840100000001,33.862798],"type":"Point"}
}