{
  "type": "Feature",
  "properties": {
    "iso:country":"US",
    "sg:address":"1202 State Hwy 72 Bus",
    "sg:city":"Greenwood",
    "sg:classifiers":[
        {
            "category":"Home & Garden",
            "subcategory":"Household Appliances",
            "type":"Retail Goods"
        }
    ],
    "sg:phone":"+1 864 223 8222",
    "sg:postcode":"29649",
    "sg:province":"SC",
    "wof:name":"JES Equipment Sales & Svc",
    "wof:placetype":"venue"
},
  "geometry": {"coordinates":[-82.14727999999999,34.208064],"type":"Point"}
}