{
  "type": "Feature",
  "properties": {
    "addr:full":"595 Columbia Rd Winnsboro SC 29180",
    "addr:housenumber":"595",
    "addr:postcode":"29180",
    "addr:street":"Columbia Rd",
    "iso:country":"US",
    "sg:address":"595 Columbia Rd",
    "sg:city":"Winnsboro",
    "sg:classifiers":[
        {
            "category":"Building & Trades",
            "subcategory":"Construction",
            "type":"Services"
        }
    ],
    "sg:phone":"+1 803 635 5014",
    "sg:postcode":"29180",
    "sg:province":"SC",
    "sg:tags":[
        "designer",
        "dealer",
        "pool",
        "swimming"
    ],
    "wof:name":"Deluxe Pools",
    "wof:placetype":"venue"
},
  "geometry": {"coordinates":[-81.08618800000001,34.356605],"type":"Point"}
}