{
  "type": "Feature",
  "properties": {
    "iso:country":"US",
    "sg:address":"911 S 5th St",
    "sg:city":"Easley",
    "sg:classifiers":[
        {
            "category":"Organizations",
            "subcategory":"Religious Organization",
            "type":"Services"
        }
    ],
    "sg:phone":"+1 864 859 9823",
    "sg:postcode":"29640",
    "sg:province":"SC",
    "sg:tags":[
        "church"
    ],
    "wof:name":"Geer Memorial Baptist Church",
    "wof:placetype":"venue"
},
  "geometry": {"coordinates":[-82.604463,34.817549],"type":"Point"}
}