{
  "type": "Feature",
  "properties": {
    "addr:full":"164 Gardner Ln Johns Island SC 29472",
    "addr:housenumber":"164",
    "addr:postcode":"29472",
    "addr:street":"Gardner Ln",
    "iso:country":"US",
    "sg:address":"164 Gardner Ln",
    "sg:city":"Johns Island",
    "sg:classifiers":[
        {
            "category":"Food & Beverages",
            "subcategory":"Liquor & Beverages",
            "type":"Retail Goods"
        }
    ],
    "sg:phone":"+1 843 768 0799",
    "sg:postcode":"29472",
    "sg:province":"SC",
    "wof:name":"B C Liquor & Wines",
    "wof:placetype":"venue"
},
  "geometry": {"coordinates":[-80.38314,33.022364],"type":"Point"}
}