{
  "type": "Feature",
  "properties": {
    "iso:country":"US",
    "sg:address":"2902 Grandview Dr",
    "sg:city":"Simpsonville",
    "sg:classifiers":[
        {
            "category":"Manufacturing",
            "subcategory":"Metals",
            "type":"Manufacturing & Wholesale Goods"
        }
    ],
    "sg:phone":"+1 864 963 5231",
    "sg:postcode":"29680",
    "sg:province":"SC",
    "sg:tags":[
        "product",
        "wire",
        "fabricated"
    ],
    "wof:name":"Ecc Card Clothing Inc",
    "wof:placetype":"venue"
},
  "geometry": {"coordinates":[-82.282835,34.749128],"type":"Point"}
}