{
  "type": "Feature",
  "properties": {
    "iso:country":"US",
    "sg:address":"502 N Pine St",
    "sg:city":"Summerville",
    "sg:classifiers":[
        {
            "category":"Health Services",
            "subcategory":"Doctor",
            "type":"Services"
        }
    ],
    "sg:phone":"+1 843 871 5394",
    "sg:postcode":"29483",
    "sg:province":"SC",
    "sg:tags":[
        "dentist"
    ],
    "wof:name":"Tom Miller DDS",
    "wof:placetype":"venue"
},
  "geometry": {"coordinates":[-80.174362,33.026935],"type":"Point"}
}