{
  "type": "Feature",
  "properties": {
    "iso:country":"US",
    "sg:address":"2426 Wallace Ave",
    "sg:city":"Spartanburg",
    "sg:classifiers":[
        {
            "category":"Retail",
            "subcategory":"Repair Shop",
            "type":"Services"
        }
    ],
    "sg:phone":"+1 864 542 0051",
    "sg:postcode":"29302",
    "sg:province":"SC",
    "sg:tags":[
        "antique",
        "restoring"
    ],
    "wof:name":"South Pine Restorations",
    "wof:placetype":"venue"
},
  "geometry": {"coordinates":[-81.879317,34.936995],"type":"Point"}
}