{
  "type": "Feature",
  "properties": {
    "addr:full":"1761 Bowman Branch Hwy Bowman SC 29018",
    "addr:housenumber":"1761",
    "addr:postcode":"29018",
    "addr:street":"Bowman Branch Hwy",
    "iso:country":"US",
    "sg:address":"1761 Bowman Branch Hwy",
    "sg:city":"Bowman",
    "sg:classifiers":[
        {
            "category":"Home & Garden",
            "subcategory":"Garden Supply",
            "type":"Retail Goods"
        }
    ],
    "sg:phone":"+1 803 829 2626",
    "sg:postcode":"29018",
    "sg:province":"SC",
    "sg:tags":[
        "tree"
    ],
    "wof:name":"Reesville Tree Farm",
    "wof:placetype":"venue"
},
  "geometry": {"coordinates":[-80.7089,33.33242],"type":"Point"}
}