{
  "type": "Feature",
  "properties": {
    "iso:country":"US",
    "sg:address":"10483 Stream Ln",
    "sg:city":"Fort Mill",
    "sg:classifiers":[
        {
            "category":"Professional",
            "subcategory":"Accounting & Tax Preparation",
            "type":"Services"
        }
    ],
    "sg:phone":"+1 803 548 5631",
    "sg:postcode":"29707",
    "sg:province":"SC",
    "sg:tags":[
        "accountant"
    ],
    "wof:name":"Terri Archie CPA",
    "wof:placetype":"venue"
},
  "geometry": {"coordinates":[-80.888408,35.025763],"type":"Point"}
}