{
  "type": "Feature",
  "properties": {
    "iso:country":"US",
    "sg:address":"3480 Clifton Glendale Rd",
    "sg:city":"Spartanburg",
    "sg:classifiers":[
        {
            "category":"Building & Trades",
            "subcategory":"Construction",
            "type":"Services"
        }
    ],
    "sg:phone":"+1 864 579 4666",
    "sg:postcode":"29307",
    "sg:province":"SC",
    "sg:tags":[
        "maker",
        "cabinet"
    ],
    "wof:name":"W & W Wood Shop",
    "wof:placetype":"venue"
},
  "geometry": {"coordinates":[-81.838982,34.954605],"type":"Point"}
}