{
  "type": "Feature",
  "properties": {
    "iso:country":"US",
    "sg:address":"501 Augusta Rd",
    "sg:city":"North Augusta",
    "sg:classifiers":[
        {
            "category":"Building & Trades",
            "subcategory":"Construction",
            "type":"Services"
        }
    ],
    "sg:phone":"+1 803 442 5909",
    "sg:postcode":"29822",
    "sg:province":"SC",
    "sg:tags":[
        "resurfacing",
        "laying",
        "refinishing",
        "floor"
    ],
    "wof:name":"Ranwood Hardwood Floor Fnshng",
    "wof:placetype":"venue"
},
  "geometry": {"coordinates":[-81.89204700000001,33.49671],"type":"Point"}
}