{
  "type": "Feature",
  "properties": {
    "iso:country":"US",
    "sg:address":"612 Saint Andrews Rd",
    "sg:city":"Columbia",
    "sg:classifiers":[
        {
            "category":"Professional",
            "subcategory":"Employment Agencies",
            "type":"Services"
        }
    ],
    "sg:phone":"+1 803 772 1211",
    "sg:postcode":"29210",
    "sg:province":"SC",
    "sg:tags":[
        "help",
        "contractor"
    ],
    "wof:name":"Randstad",
    "wof:placetype":"venue"
},
  "geometry": {"coordinates":[-81.12502499999999,34.045017],"type":"Point"}
}