{
  "type": "Feature",
  "properties": {
    "iso:country":"US",
    "sg:address":"3393 US Hwy 17 Bus",
    "sg:city":"Murrells Inlet",
    "sg:classifiers":[
        {
            "category":"Bars & Pubs",
            "type":"Food & Drink"
        }
    ],
    "sg:phone":"+1 843 651 7960",
    "sg:postcode":"29576",
    "sg:province":"SC",
    "sg:tags":[
        "lounge",
        "cocktail"
    ],
    "wof:name":"Suck Bang & Blow",
    "wof:placetype":"venue"
},
  "geometry": {"coordinates":[-79.02546,33.574994],"type":"Point"}
}