{
  "type": "Feature",
  "properties": {
    "iso:country":"US",
    "sg:address":"3027 Wade Hampton Blvd",
    "sg:city":"Taylors",
    "sg:classifiers":[
        {
            "category":"Shopping",
            "subcategory":"Jewelry",
            "type":"Retail Goods"
        }
    ],
    "sg:phone":"+1 864 244 2352",
    "sg:postcode":"29687",
    "sg:province":"SC",
    "wof:name":"Friedmans Jewelers",
    "wof:placetype":"venue"
},
  "geometry": {"coordinates":[-82.330296,34.906282],"type":"Point"}
}