{
  "type": "Feature",
  "properties": {
    "iso:country":"US",
    "sg:address":"8 E Main St",
    "sg:city":"Taylors",
    "sg:classifiers":[
        {
            "category":"Real Estate",
            "subcategory":"Real Estate Agent",
            "type":"Services"
        }
    ],
    "sg:phone":"+1 864 268 4029",
    "sg:postcode":"29687",
    "sg:province":"SC",
    "wof:name":"Check Springs Real Estate",
    "wof:placetype":"venue"
},
  "geometry": {"coordinates":[-82.29692,34.920551],"type":"Point"}
}