{
  "type": "Feature",
  "properties": {
    "addr:full":"5 Straits Ct Greer SC 29676",
    "addr:housenumber":"5",
    "addr:postcode":"29676",
    "addr:street":"Straits Ct",
    "iso:country":"US",
    "sg:address":"5 Straits Ct",
    "sg:city":"Greer",
    "sg:classifiers":[
        {
            "category":"Professional",
            "type":"Services"
        }
    ],
    "sg:phone":"+1 864 801 4045",
    "sg:postcode":"29676",
    "sg:province":"SC",
    "sg:tags":[
        "establishment"
    ],
    "wof:name":"Riverside Towns",
    "wof:placetype":"venue"
},
  "geometry": {"coordinates":[-82.925319,34.840424],"type":"Point"}
}