{
  "type": "Feature",
  "properties": {
    "iso:country":"US",
    "sg:address":"111 SW Railroad Ave",
    "sg:city":"Latta",
    "sg:classifiers":[
        {
            "category":"Retail",
            "subcategory":"Auto Repair",
            "type":"Services"
        }
    ],
    "sg:phone":"+1 843 752 2139",
    "sg:postcode":"29565",
    "sg:province":"SC",
    "sg:tags":[
        "body",
        "automobile",
        "painting"
    ],
    "wof:name":"L & L Body Shop & Repair Svc",
    "wof:placetype":"venue"
},
  "geometry": {"coordinates":[-79.432923,34.337837],"type":"Point"}
}