{
  "type": "Feature",
  "properties": {
    "addr:full":"205 Lockshire Rd Columbia SC 29212",
    "addr:housenumber":"205",
    "addr:postcode":"29212",
    "addr:street":"Lockshire Rd",
    "iso:country":"US",
    "sg:address":"205 Lockshire Rd",
    "sg:city":"Columbia",
    "sg:classifiers":[
        {
            "category":"Building & Trades",
            "subcategory":"Construction",
            "type":"Services"
        }
    ],
    "sg:phone":"+1 877 775 7234",
    "sg:postcode":"29212",
    "sg:province":"SC",
    "sg:tags":[
        "general",
        "contractor"
    ],
    "wof:name":"Carolina Construction",
    "wof:placetype":"venue"
},
  "geometry": {"coordinates":[-81.160262,34.060528],"type":"Point"}
}