{
  "type": "Feature",
  "properties": {
    "addr:full":"108 Mallard Pt Lexington SC 29072",
    "addr:housenumber":"108",
    "addr:postcode":"29072",
    "addr:street":"Mallard Pt",
    "iso:country":"US",
    "sg:address":"108 Mallard Pt",
    "sg:city":"Lexington",
    "sg:classifiers":[
        {
            "category":"Professional",
            "subcategory":"Business Services",
            "type":"Services"
        }
    ],
    "sg:phone":"+1 803 808 1973",
    "sg:postcode":"29072",
    "sg:province":"SC",
    "sg:tags":[
        "appraiser"
    ],
    "wof:name":"Hutto Appraisal Svc",
    "wof:placetype":"venue"
},
  "geometry": {"coordinates":[-81.32640000000001,34.017349],"type":"Point"}
}