{
  "type": "Feature",
  "properties": {
    "addr:full":"3912 Sandy Point Rd York SC 29745",
    "addr:housenumber":"3912",
    "addr:postcode":"29745",
    "addr:street":"Sandy Point Rd",
    "iso:country":"US",
    "sg:address":"3912 Sandy Point Rd",
    "sg:city":"York",
    "sg:classifiers":[
        {
            "category":"Professional",
            "subcategory":"Management & Consulting",
            "type":"Services"
        }
    ],
    "sg:phone":"+1 803 831 0914",
    "sg:postcode":"29745",
    "sg:province":"SC",
    "sg:tags":[
        "retail",
        "direct",
        "sales"
    ],
    "wof:name":"Ent Distribution",
    "wof:placetype":"venue"
},
  "geometry": {"coordinates":[-81.04878100000001,35.040131],"type":"Point"}
}