{
  "type": "Feature",
  "properties": {
    "addr:full":"20 McPherson Ln Greenville SC 29605",
    "addr:housenumber":"20",
    "addr:postcode":"29605",
    "addr:street":"Mcpherson Ln",
    "iso:country":"US",
    "sg:address":"20 McPherson Ln",
    "sg:city":"Greenville",
    "sg:classifiers":[
        {
            "category":"Insurance",
            "subcategory":"Insurance Agent",
            "type":"Services"
        }
    ],
    "sg:phone":"+1 864 370 0065",
    "sg:postcode":"29605",
    "sg:province":"SC",
    "wof:name":"James E Lipscomb III Agency",
    "wof:placetype":"venue"
},
  "geometry": {"coordinates":[-82.392517,34.82727],"type":"Point"}
}