{
  "type": "Feature",
  "properties": {
    "iso:country":"US",
    "sg:address":"734 Wampler Dr",
    "sg:city":"Charleston",
    "sg:classifiers":[
        {
            "category":"Organizations",
            "subcategory":"Professional Association",
            "type":"Services"
        }
    ],
    "sg:phone":"+1 843 795 6060",
    "sg:postcode":"29412",
    "sg:province":"SC",
    "wof:name":"James Island Yacht Club",
    "wof:placetype":"venue"
},
  "geometry": {"coordinates":[-79.91786500000001,32.753733],"type":"Point"}
}