{
  "type": "Feature",
  "properties": {
    "iso:country":"US",
    "sg:address":"241 McRae St",
    "sg:city":"Columbia",
    "sg:classifiers":[
        {
            "category":"Professional",
            "subcategory":"Detective & Security Services",
            "type":"Services"
        }
    ],
    "sg:phone":"+1 803 765 9263",
    "sg:postcode":"29203",
    "sg:province":"SC",
    "sg:tags":[
        "guard",
        "patrol"
    ],
    "wof:name":"Roosevelt Village Apartments",
    "wof:placetype":"venue"
},
  "geometry": {"coordinates":[-81.063605,34.031791],"type":"Point"}
}