{
  "type": "Feature",
  "properties": {
    "iso:country":"US",
    "sg:address":"218 Albright Rd",
    "sg:city":"Rock Hill",
    "sg:classifiers":[
        {
            "category":"Restaurant",
            "type":"Food & Drink"
        }
    ],
    "sg:phone":"+1 803 329 6659",
    "sg:postcode":"29730",
    "sg:province":"SC",
    "wof:name":"Best Home Cooked Meals",
    "wof:placetype":"venue"
},
  "geometry": {"coordinates":[-81.008664,34.913337],"type":"Point"}
}