{
  "type": "Feature",
  "properties": {
    "iso:country":"US",
    "sg:address":"1446 Thor Dr",
    "sg:city":"Columbia",
    "sg:classifiers":[
        {
            "category":"Building & Trades",
            "subcategory":"Landscaping Services",
            "type":"Services"
        }
    ],
    "sg:phone":"+1 803 772 8649",
    "sg:postcode":"29210",
    "sg:province":"SC",
    "sg:tags":[
        "landscape"
    ],
    "wof:name":"Yardscapes Inc",
    "wof:placetype":"venue"
},
  "geometry": {"coordinates":[-81.082368,34.031892],"type":"Point"}
}