{
  "type": "Feature",
  "properties": {
    "iso:country":"US",
    "sg:address":"269 E Bay St",
    "sg:city":"Charleston",
    "sg:classifiers":[
        {
            "category":"Food & Beverages",
            "subcategory":"Liquor & Beverages",
            "type":"Retail Goods"
        }
    ],
    "sg:phone":"+1 843 958 8466",
    "sg:postcode":"29401",
    "sg:province":"SC",
    "sg:tags":[
        "wine"
    ],
    "wof:name":"Wine & Pine",
    "wof:placetype":"venue"
},
  "geometry": {"coordinates":[-79.92844700000001,32.783697],"type":"Point"}
}