{
  "type": "Feature",
  "properties": {
    "addr:full":"365 Blackstock Rd Enoree SC 29335",
    "addr:housenumber":"365",
    "addr:postcode":"29335",
    "addr:street":"Blackstock Rd",
    "iso:country":"US",
    "sg:address":"365 Blackstock Rd",
    "sg:city":"Enoree",
    "sg:classifiers":[
        {
            "category":"Real Estate",
            "subcategory":"Real Estate Agent",
            "type":"Services"
        }
    ],
    "sg:phone":"+1 864 427 4754",
    "sg:postcode":"29335",
    "sg:province":"SC",
    "wof:name":"Burgess Realty",
    "wof:placetype":"venue"
},
  "geometry": {"coordinates":[-81.833842,34.677637],"type":"Point"}
}