{
  "type": "Feature",
  "properties": {
    "iso:country":"US",
    "sg:address":"1587 Savannah Hwy",
    "sg:city":"Charleston",
    "sg:classifiers":[
        {
            "category":"Building & Trades",
            "subcategory":"Construction",
            "type":"Services"
        }
    ],
    "sg:phone":"+1 843 556 5382",
    "sg:postcode":"29407",
    "sg:province":"SC",
    "sg:tags":[
        "home",
        "improvement"
    ],
    "wof:name":"Curry Brothers Construction Co",
    "wof:placetype":"venue"
},
  "geometry": {"coordinates":[-80.008988,32.785952],"type":"Point"}
}