{
  "type": "Feature",
  "properties": {
    "iso:country":"US",
    "sg:address":"14315 State Hwy 20",
    "sg:city":"Belton",
    "sg:phone":"+1 864 338 7753",
    "sg:postcode":"29627",
    "sg:province":"SC",
    "sg:tags":[
        "product",
        "petroleum"
    ],
    "wof:name":"Marathon Oil Co",
    "wof:placetype":"venue"
},
  "geometry": {"coordinates":[-82.49337300000001,34.54768],"type":"Point"}
}