{
  "type": "Feature",
  "properties": {
    "iso:country":"US",
    "sg:address":"370 College Ave",
    "sg:city":"Clemson",
    "sg:classifiers":[
        {
            "category":"Health Services",
            "subcategory":"Optometrist",
            "type":"Services"
        }
    ],
    "sg:phone":"+1 864 654 7980",
    "sg:postcode":"29631",
    "sg:province":"SC",
    "wof:name":"Eye & Contact Lens Assoc",
    "wof:placetype":"venue"
},
  "geometry": {"coordinates":[-82.837429,34.683724],"type":"Point"}
}