{
  "type": "Feature",
  "properties": {
    "iso:country":"US",
    "sg:address":"111 Hurricane Creek Rd",
    "sg:city":"Piedmont",
    "sg:classifiers":[
        {
            "category":"Utilities",
            "subcategory":"Refuse",
            "type":"Services"
        }
    ],
    "sg:phone":"+1 864 845 7847",
    "sg:postcode":"29673",
    "sg:province":"SC",
    "sg:tags":[
        "garbage",
        "collection"
    ],
    "wof:name":"Parts Place Inc",
    "wof:placetype":"venue"
},
  "geometry": {"coordinates":[-82.503794,34.701092],"type":"Point"}
}