{
  "type": "Feature",
  "properties": {
    "iso:country":"US",
    "sg:address":"7 Charlotte St",
    "sg:city":"Charleston",
    "sg:classifiers":[
        {
            "category":"Professional",
            "subcategory":"Management & Consulting",
            "type":"Services"
        }
    ],
    "sg:phone":"+1 843 579 0500",
    "sg:postcode":"29403",
    "sg:province":"SC",
    "sg:tags":[
        "counselor",
        "public",
        "relations"
    ],
    "wof:name":"Leapfrog Public Relations",
    "wof:placetype":"venue"
},
  "geometry": {"coordinates":[-79.929785,32.790295],"type":"Point"}
}