{
  "type": "Feature",
  "properties": {
    "iso:country":"US",
    "sg:address":"3904 Notch Rd",
    "sg:city":"Columbia",
    "sg:classifiers":[
        {
            "category":"Insurance",
            "subcategory":"Insurance Agent",
            "type":"Services"
        }
    ],
    "sg:phone":"+1 803 786 4405",
    "sg:postcode":"29204",
    "sg:province":"SC",
    "wof:name":"Clark Farley Insurance",
    "wof:placetype":"venue"
},
  "geometry": {"coordinates":[-80.996774,34.040854],"type":"Point"}
}