{
  "type": "Feature",
  "properties": {
    "iso:country":"US",
    "sg:address":"1241 S Pleasantburg Dr",
    "sg:city":"Greenville",
    "sg:classifiers":[
        {
            "category":"Banks & Credit Unions",
            "subcategory":"Bank",
            "type":"Services"
        }
    ],
    "sg:phone":"+1 864 232 2234",
    "sg:postcode":"29605",
    "sg:province":"SC",
    "sg:tags":[
        "loan"
    ],
    "wof:name":"Upstate Check Express",
    "wof:placetype":"venue"
},
  "geometry": {"coordinates":[-82.373381,34.806326],"type":"Point"}
}