{
  "type": "Feature",
  "properties": {
    "iso:country":"US",
    "sg:address":"851 Bettis Academy Rd",
    "sg:city":"Graniteville",
    "sg:classifiers":[
        {
            "category":"Wholesale",
            "subcategory":"Electrical",
            "type":"Manufacturing & Wholesale Goods"
        }
    ],
    "sg:phone":"+1 803 663 9991",
    "sg:postcode":"29829",
    "sg:province":"SC",
    "sg:tags":[
        "control"
    ],
    "wof:name":"Johnson Controls Inc",
    "wof:placetype":"venue"
},
  "geometry": {"coordinates":[-81.85023200000001,33.624287],"type":"Point"}
}