{
  "type": "Feature",
  "properties": {
    "addr:full":"120 W Windsor St Westminster SC 29693",
    "addr:housenumber":"120",
    "addr:postcode":"29693",
    "addr:street":"W Windsor St",
    "iso:country":"US",
    "sg:address":"120 W Windsor St",
    "sg:city":"Westminster",
    "sg:classifiers":[
        {
            "category":"Retail",
            "subcategory":"Laundry & Dry Cleaning",
            "type":"Services"
        }
    ],
    "sg:phone":"+1 864 647 7990",
    "sg:postcode":"29693",
    "sg:province":"SC",
    "wof:name":"Keowee Kleaners",
    "wof:placetype":"venue"
},
  "geometry": {"coordinates":[-83.09792400000001,34.665945],"type":"Point"}
}