{
  "type": "Feature",
  "properties": {
    "addr:full":"4706 White Horse Rd Greenville SC 29611",
    "addr:housenumber":"4706",
    "addr:postcode":"29611",
    "addr:street":"White Horse Rd",
    "iso:country":"US",
    "sg:address":"4706 White Horse Rd",
    "sg:city":"Greenville",
    "sg:classifiers":[
        {
            "category":"Retail",
            "subcategory":"Auto Repair",
            "type":"Services"
        }
    ],
    "sg:phone":"+1 864 269 0510",
    "sg:postcode":"29611",
    "sg:province":"SC",
    "sg:tags":[
        "repairing",
        "automobile"
    ],
    "wof:name":"Ror Lando",
    "wof:placetype":"venue"
},
  "geometry": {"coordinates":[-82.463542,34.865737],"type":"Point"}
}