{
  "type": "Feature",
  "properties": {
    "iso:country":"US",
    "sg:address":"105 E Wesmark Blvd",
    "sg:city":"Sumter",
    "sg:classifiers":[
        {
            "category":"Ice Cream",
            "type":"Food & Drink"
        }
    ],
    "sg:menulink":"http://www.allmenus.com/sc/sumter/230157-marble-slab-creamery/menu/",
    "sg:phone":"+1 803 774 7522",
    "sg:postcode":"29150",
    "sg:province":"SC",
    "sg:tags":[
        "american"
    ],
    "wof:name":"Marble Slab Creamery",
    "wof:placetype":"venue"
},
  "geometry": {"coordinates":[-80.374439,33.953399],"type":"Point"}
}