{
  "type": "Feature",
  "properties": {
    "iso:country":"US",
    "sg:address":"1433 Jeffords St",
    "sg:city":"Charleston",
    "sg:classifiers":[
        {
            "category":"Building & Trades",
            "subcategory":"Construction",
            "type":"Services"
        }
    ],
    "sg:phone":"+1 843 795 7233",
    "sg:postcode":"29412",
    "sg:province":"SC",
    "sg:tags":[
        "general",
        "contractor"
    ],
    "wof:name":"Rice's Construction",
    "wof:placetype":"venue"
},
  "geometry": {"coordinates":[-79.963463,32.714261],"type":"Point"}
}