{
  "type": "Feature",
  "properties": {
    "iso:country":"US",
    "sg:address":"158 Rodeo Dr",
    "sg:city":"Gaffney",
    "sg:classifiers":[
        {
            "category":"Shopping",
            "subcategory":"Discount & Variety Stores",
            "type":"Retail Goods"
        }
    ],
    "sg:phone":"+1 864 812 1204",
    "sg:postcode":"29340",
    "sg:province":"SC",
    "sg:tags":[
        "merchandise",
        "general"
    ],
    "wof:name":"Silverwood Sales",
    "wof:placetype":"venue"
},
  "geometry": {"coordinates":[-81.62568400000001,34.992896],"type":"Point"}
}