{
  "type": "Feature",
  "properties": {
    "addr:full":"8818 Old 6 Hwy Santee SC 29163",
    "addr:housenumber":"8818;6",
    "addr:postcode":"29163",
    "addr:street":"Old;Hwy Santee Sc",
    "iso:country":"US",
    "sg:address":"8818 Old 6 Hwy",
    "sg:city":"Santee",
    "sg:classifiers":[
        {
            "category":"Professional",
            "subcategory":"Lawyer & Legal Services",
            "type":"Services"
        }
    ],
    "sg:phone":"+1 803 854 4417",
    "sg:postcode":"29163",
    "sg:province":"SC",
    "sg:tags":[
        "attorney"
    ],
    "wof:name":"W Scott Palmer",
    "wof:placetype":"venue"
},
  "geometry": {"coordinates":[-80.492177,33.491818],"type":"Point"}
}