{
  "type": "Feature",
  "properties": {
    "addr:full":"920 Frontage Rd Greenville SC 29611",
    "addr:housenumber":"920",
    "addr:postcode":"29611",
    "addr:street":"Frontage Rd",
    "iso:country":"US",
    "sg:address":"920 Frontage Rd",
    "sg:city":"Greenville",
    "sg:classifiers":[
        {
            "category":"Recreation",
            "subcategory":"Arcade",
            "type":"Entertainment"
        }
    ],
    "sg:phone":"+1 864 220 6777",
    "sg:postcode":"29611",
    "sg:province":"SC",
    "sg:tags":[
        "amusement",
        "devices"
    ],
    "wof:name":"Nova Gaming LLC",
    "wof:placetype":"venue"
},
  "geometry": {"coordinates":[-82.31159,34.838617],"type":"Point"}
}