{
  "type": "Feature",
  "properties": {
    "addr:full":"2453 King St Exd North Charleston SC 29405",
    "addr:housenumber":"2453",
    "addr:postcode":"29405",
    "addr:street":"King St Exd",
    "iso:country":"US",
    "sg:address":"2453 King St Exd",
    "sg:city":"North Charleston",
    "sg:classifiers":[
        {
            "category":"Freight",
            "type":"Transportation"
        }
    ],
    "sg:phone":"+1 843 554 0474",
    "sg:postcode":"29405",
    "sg:province":"SC",
    "sg:tags":[
        "warehouse"
    ],
    "wof:name":"Eaton Electrical Inc",
    "wof:placetype":"venue"
},
  "geometry": {"coordinates":[-79.962281,32.838336],"type":"Point"}
}