{
  "type": "Feature",
  "properties": {
    "iso:country":"US",
    "sg:address":"441 Wildlife Rd",
    "sg:city":"Lexington",
    "sg:classifiers":[
        {
            "category":"Building & Trades",
            "subcategory":"Construction",
            "type":"Services"
        }
    ],
    "sg:phone":"+1 803 359 5857",
    "sg:postcode":"29072",
    "sg:province":"SC",
    "sg:tags":[
        "roofing",
        "contractor"
    ],
    "wof:name":"Esslinger Roofing Svc",
    "wof:placetype":"venue"
},
  "geometry": {"coordinates":[-81.255446,33.953253],"type":"Point"}
}