{
  "type": "Feature",
  "properties": {
    "iso:country":"US",
    "sg:address":"101 Bramblewood Dr",
    "sg:city":"Camden",
    "sg:classifiers":[
        {
            "category":"Government",
            "subcategory":"Jail",
            "type":"Public Place"
        }
    ],
    "sg:phone":"+1 803 425 1516",
    "sg:postcode":"29018",
    "sg:province":"SC",
    "sg:tags":[
        "county",
        "govt",
        "institution"
    ],
    "wof:name":"Kershaw County Jail",
    "wof:placetype":"venue"
},
  "geometry": {"coordinates":[-80.676599,33.351618],"type":"Point"}
}