{
  "type": "Feature",
  "properties": {
    "addr:full":"3290 Camp Creek Rd Lancaster SC 29720",
    "addr:housenumber":"3290",
    "addr:postcode":"29720",
    "addr:street":"Camp Creek Rd",
    "iso:country":"US",
    "sg:address":"3290 Camp Creek Rd",
    "sg:city":"Lancaster",
    "sg:classifiers":[
        {
            "category":"Building & Trades",
            "subcategory":"Construction",
            "type":"Services"
        }
    ],
    "sg:phone":"+1 803 285 4219",
    "sg:postcode":"29720",
    "sg:province":"SC",
    "sg:tags":[
        "contractor"
    ],
    "wof:name":"T G Tile",
    "wof:placetype":"venue"
},
  "geometry": {"coordinates":[-80.692632,34.766383],"type":"Point"}
}