{
  "type": "Feature",
  "properties": {
    "iso:country":"US",
    "sg:address":"105 Gulliver St",
    "sg:city":"Fountain Inn",
    "sg:classifiers":[
        {
            "category":"Building & Trades",
            "subcategory":"Landscaping Services",
            "type":"Services"
        }
    ],
    "sg:phone":"+1 864 409 0966",
    "sg:postcode":"29644",
    "sg:province":"SC",
    "wof:name":"B&W Lawn Service LLC",
    "wof:placetype":"venue"
},
  "geometry": {"coordinates":[-82.19748199999999,34.69277],"type":"Point"}
}