{
  "type": "Feature",
  "properties": {
    "iso:country":"US",
    "sg:address":"209 S Cypress St",
    "sg:city":"Mullins",
    "sg:classifiers":[
        {
            "category":"Organizations",
            "subcategory":"Religious Organization",
            "type":"Services"
        }
    ],
    "sg:phone":"+1 843 464 6063",
    "sg:postcode":"29574",
    "sg:province":"SC",
    "sg:tags":[
        "church"
    ],
    "wof:name":"Ellen Chapel Holiness Church",
    "wof:placetype":"venue"
},
  "geometry": {"coordinates":[-79.26153,34.202742],"type":"Point"}
}