{
  "type": "Feature",
  "properties": {
    "iso:country":"US",
    "sg:address":"100 Industrial Dr",
    "sg:city":"Greenville",
    "sg:classifiers":[
        {
            "category":"Wholesale",
            "subcategory":"Machinery & Supplies",
            "type":"Manufacturing & Wholesale Goods"
        }
    ],
    "sg:phone":"+1 864 233 7433",
    "sg:postcode":"29607",
    "sg:province":"SC",
    "sg:tags":[
        "rubber",
        "product"
    ],
    "wof:name":"Dixie Rubber & Plastics Inc",
    "wof:placetype":"venue"
},
  "geometry": {"coordinates":[-82.351263,34.835756],"type":"Point"}
}