{
  "type": "Feature",
  "properties": {
    "addr:full":"7300 Parklane Rd Columbia SC 29223",
    "addr:housenumber":"7300",
    "addr:postcode":"29223",
    "addr:street":"Parklane Rd",
    "iso:country":"US",
    "sg:address":"7300 Parklane Rd",
    "sg:city":"Columbia",
    "sg:classifiers":[
        {
            "category":"Retail",
            "subcategory":"Auto Repair",
            "type":"Services"
        }
    ],
    "sg:phone":"+1 803 736 3635",
    "sg:postcode":"29223",
    "sg:province":"SC",
    "sg:tags":[
        "automobile",
        "lubrication"
    ],
    "wof:name":"Jiffy Lube",
    "wof:placetype":"venue"
},
  "geometry": {"coordinates":[-80.95894199999999,34.072889],"type":"Point"}
}