{
  "type": "Feature",
  "properties": {
    "iso:country":"US",
    "sg:address":"5647 Rivers Ave",
    "sg:city":"North Charleston",
    "sg:classifiers":[
        {
            "category":"Wholesale",
            "subcategory":"Durable Goods & Equipment",
            "type":"Manufacturing & Wholesale Goods"
        }
    ],
    "sg:phone":"+1 843 554 7135",
    "sg:postcode":"29406",
    "sg:province":"SC",
    "sg:tags":[
        "exporter"
    ],
    "wof:name":"Carolina Aquatics",
    "wof:placetype":"venue"
},
  "geometry": {"coordinates":[-80.01634,32.897802],"type":"Point"}
}