{
  "type": "Feature",
  "properties": {
    "addr:full":"1794 Old Pacolet Rd Spartanburg SC 29307",
    "addr:housenumber":"1794",
    "addr:postcode":"29307",
    "addr:street":"Old Pacolet Rd",
    "iso:country":"US",
    "sg:address":"1794 Old Pacolet Rd",
    "sg:city":"Spartanburg",
    "sg:classifiers":[
        {
            "category":"Shopping",
            "subcategory":"Discount & Variety Stores",
            "type":"Retail Goods"
        }
    ],
    "sg:phone":"+1 864 463 3748",
    "sg:postcode":"29307",
    "sg:province":"SC",
    "wof:name":"7 Day Store",
    "wof:placetype":"venue"
},
  "geometry": {"coordinates":[-81.78250800000001,34.994299],"type":"Point"}
}