{
  "type": "Feature",
  "properties": {
    "addr:full":"109 Double Branch Ct West Columbia SC 29169",
    "addr:housenumber":"109",
    "addr:postcode":"29169",
    "addr:street":"Double Branch Ct",
    "iso:country":"US",
    "sg:address":"109 Double Branch Ct",
    "sg:city":"West Columbia",
    "sg:classifiers":[
        {
            "category":"Utilities",
            "subcategory":"Telephone",
            "type":"Services"
        }
    ],
    "sg:phone":"+1 803 361 1160",
    "sg:postcode":"29169",
    "sg:province":"SC",
    "sg:tags":[
        "communications"
    ],
    "wof:name":"Powwowcom LLC",
    "wof:placetype":"venue"
},
  "geometry": {"coordinates":[-81.08909199999999,34.002494],"type":"Point"}
}