{
  "type": "Feature",
  "properties": {
    "addr:full":"349 Floyd Rd Spartanburg SC 29303",
    "addr:housenumber":"349",
    "addr:postcode":"29303",
    "addr:street":"Floyd Rd",
    "iso:country":"US",
    "sg:address":"349 Floyd Rd",
    "sg:city":"Spartanburg",
    "sg:classifiers":[
        {
            "category":"Building & Trades",
            "subcategory":"Landscaping Services",
            "type":"Services"
        }
    ],
    "sg:phone":"+1 864 591 1745",
    "sg:postcode":"29303",
    "sg:province":"SC",
    "wof:name":"Landscape Enterprise",
    "wof:placetype":"venue"
},
  "geometry": {"coordinates":[-81.90168199999999,34.990087],"type":"Point"}
}