{
  "type": "Feature",
  "properties": {
    "addr:full":"2021 W Sumter St Florence SC 29501",
    "addr:housenumber":"2021",
    "addr:postcode":"29501",
    "addr:street":"W Sumter St",
    "iso:country":"US",
    "sg:address":"2021 W Sumter St",
    "sg:city":"Florence",
    "sg:classifiers":[
        {
            "category":"Freight",
            "type":"Transportation"
        }
    ],
    "sg:phone":"+1 843 662 7788",
    "sg:postcode":"29501",
    "sg:province":"SC",
    "sg:tags":[
        "hauling",
        "trucking"
    ],
    "wof:name":"Palmetto Transport Inc",
    "wof:placetype":"venue"
},
  "geometry": {"coordinates":[-79.80613700000001,34.209075],"type":"Point"}
}