{
  "type": "Feature",
  "properties": {
    "addr:full":"2602 W Palmetto St Florence SC 29501",
    "addr:housenumber":"2602",
    "addr:postcode":"29501",
    "addr:street":"W Palmetto St",
    "iso:country":"US",
    "sg:address":"2602 W Palmetto St",
    "sg:city":"Florence",
    "sg:classifiers":[
        {
            "category":"Professional",
            "subcategory":"Accounting & Tax Preparation",
            "type":"Services"
        }
    ],
    "sg:phone":"+1 843 665 8100",
    "sg:postcode":"29501",
    "sg:province":"SC",
    "sg:tags":[
        "return",
        "filing"
    ],
    "wof:name":"Palmetto Express Tax",
    "wof:placetype":"venue"
},
  "geometry": {"coordinates":[-79.825818,34.178574],"type":"Point"}
}