{
  "type": "Feature",
  "properties": {
    "addr:full":"6069 Cypress Swamp Rd Conway SC 29527",
    "addr:housenumber":"6069",
    "addr:postcode":"29527",
    "addr:street":"Cypress Swamp Rd",
    "iso:country":"US",
    "sg:address":"6069 Cypress Swamp Rd",
    "sg:city":"Conway",
    "sg:classifiers":[
        {
            "category":"Shopping",
            "subcategory":"Discount & Variety Stores",
            "type":"Retail Goods"
        }
    ],
    "sg:phone":"+1 843 397 4000",
    "sg:postcode":"29527",
    "sg:province":"SC",
    "wof:name":"Carver Wood",
    "wof:placetype":"venue"
},
  "geometry": {"coordinates":[-79.149084,33.780817],"type":"Point"}
}