{
  "type": "Feature",
  "properties": {
    "addr:full":"1459 US Hwy 501 Myrtle Beach SC 29577",
    "addr:housenumber":"1459",
    "addr:postcode":"29577",
    "addr:street":"Us Hwy 501",
    "iso:country":"US",
    "sg:address":"1459 US Hwy 501",
    "sg:city":"Myrtle Beach",
    "sg:classifiers":[
        {
            "category":"Retail",
            "subcategory":"Auto Rental",
            "type":"Services"
        }
    ],
    "sg:phone":"+1 843 626 8166",
    "sg:postcode":"29577",
    "sg:province":"SC",
    "sg:tags":[
        "renting",
        "automobile"
    ],
    "wof:name":"Alamo Rent-A-Car",
    "wof:placetype":"venue"
},
  "geometry": {"coordinates":[-78.90128900000001,33.700094],"type":"Point"}
}