{
  "type": "Feature",
  "properties": {
    "iso:country":"US",
    "sg:address":"7219 Investment Dr",
    "sg:city":"North Charleston",
    "sg:classifiers":[
        {
            "category":"Professional",
            "subcategory":"Advertising",
            "type":"Services"
        }
    ],
    "sg:phone":"+1 843 767 8684",
    "sg:postcode":"29418",
    "sg:province":"SC",
    "sg:tags":[
        "distribution"
    ],
    "wof:name":"Integrity Distribution Sltns",
    "wof:placetype":"venue"
},
  "geometry": {"coordinates":[-80.06047599999999,32.921594],"type":"Point"}
}