{
  "type": "Feature",
  "properties": {
    "iso:country":"US",
    "sg:address":"1850 Charleston Hwy",
    "sg:city":"Orangeburg",
    "sg:classifiers":[
        {
            "category":"Building & Trades",
            "subcategory":"Plumbing",
            "type":"Services"
        }
    ],
    "sg:phone":"+1 803 536 0869",
    "sg:postcode":"29115",
    "sg:province":"SC",
    "sg:tags":[
        "conditioning",
        "air",
        "system",
        "contractor"
    ],
    "wof:name":"Garden City Heating & Cooling",
    "wof:placetype":"venue"
},
  "geometry": {"coordinates":[-80.843869,33.469591],"type":"Point"}
}