{
  "type": "Feature",
  "properties": {
    "iso:country":"US",
    "sg:address":"453 Charles St",
    "sg:city":"Charleston",
    "sg:classifiers":[
        {
            "category":"Travel",
            "subcategory":"Travel Agent",
            "type":"Entertainment"
        }
    ],
    "sg:phone":"+1 843 209 6236",
    "sg:postcode":"29432",
    "sg:province":"SC",
    "sg:tags":[
        "passenger",
        "transportation",
        "arrangement"
    ],
    "wof:name":"Hubert & Hoffman Travel",
    "wof:placetype":"venue"
},
  "geometry": {"coordinates":[-80.82187399999999,33.25329],"type":"Point"}
}