{
  "type": "Feature",
  "properties": {
    "iso:country":"US",
    "sg:address":"1 Bradford St",
    "sg:city":"Santee",
    "sg:classifiers":[
        {
            "category":"Health Services",
            "subcategory":"Nursing And Care Facility",
            "type":"Services"
        }
    ],
    "sg:phone":"+1 803 854 2041",
    "sg:postcode":"29150",
    "sg:province":"SC",
    "sg:tags":[
        "home",
        "retirement",
        "community"
    ],
    "wof:name":"Bradford Village Assn",
    "wof:placetype":"venue"
},
  "geometry": {"coordinates":[-80.35104,33.912495],"type":"Point"}
}