{
  "type": "Feature",
  "properties": {
    "addr:full":"182 Saluda St Chester SC 29706",
    "addr:housenumber":"182",
    "addr:postcode":"29706",
    "addr:street":"Saluda St",
    "iso:country":"US",
    "sg:address":"182 Saluda St",
    "sg:city":"Chester",
    "sg:classifiers":[
        {
            "category":"Shopping",
            "subcategory":"Florist",
            "type":"Retail Goods"
        }
    ],
    "sg:phone":"+1 803 377 7747",
    "sg:postcode":"29706",
    "sg:province":"SC",
    "wof:name":"Hunter's Creative Florist",
    "wof:placetype":"venue"
},
  "geometry": {"coordinates":[-81.201307,34.714528],"type":"Point"}
}