{
  "type": "Feature",
  "properties": {
    "iso:country":"US",
    "sg:address":"601 Bush River Rd",
    "sg:city":"Columbia",
    "sg:classifiers":[
        {
            "category":"Retail",
            "subcategory":"Car Wash",
            "type":"Services"
        }
    ],
    "sg:phone":"+1 803 359 0414",
    "sg:postcode":"29210",
    "sg:province":"SC",
    "sg:tags":[
        "polishing",
        "washing"
    ],
    "wof:name":"Frank's Car Wash",
    "wof:placetype":"venue"
},
  "geometry": {"coordinates":[-81.096603,34.030399],"type":"Point"}
}