{
  "type": "Feature",
  "properties": {
    "iso:country":"US",
    "sg:address":"121 Bridge St",
    "sg:city":"Branchville",
    "sg:classifiers":[
        {
            "category":"Professional",
            "subcategory":"Engineering",
            "type":"Services"
        }
    ],
    "sg:phone":"+1 803 274 4242",
    "sg:postcode":"29432",
    "sg:province":"SC",
    "sg:tags":[
        "engineer"
    ],
    "wof:name":"W Metts Engineering Co Inc",
    "wof:placetype":"venue"
},
  "geometry": {"coordinates":[-80.81656599999999,33.247977],"type":"Point"}
}