{
  "type": "Feature",
  "properties": {
    "iso:country":"US",
    "sg:address":"45 Briarglen Pl",
    "sg:city":"Greenville",
    "sg:classifiers":[
        {
            "category":"Recreation",
            "type":"Entertainment"
        }
    ],
    "sg:phone":"+1 864 232 2110",
    "sg:postcode":"29615",
    "sg:province":"SC",
    "sg:tags":[
        "pool",
        "swimming"
    ],
    "wof:name":"Briarcreek Pool",
    "wof:placetype":"venue"
},
  "geometry": {"coordinates":[-82.352987,34.86475],"type":"Point"}
}