{
  "type": "Feature",
  "properties": {
    "iso:country":"US",
    "sg:address":"1744 Russell Rd",
    "sg:city":"Rock Hill",
    "sg:classifiers":[
        {
            "category":"Building & Trades",
            "subcategory":"Plumbing",
            "type":"Services"
        }
    ],
    "sg:phone":"+1 803 329 4839",
    "sg:postcode":"29732",
    "sg:province":"SC",
    "sg:tags":[
        "contractor"
    ],
    "wof:name":"Brians Plumbing Repair Service",
    "wof:placetype":"venue"
},
  "geometry": {"coordinates":[-81.14843500000001,34.915709],"type":"Point"}
}