{
  "type": "Feature",
  "properties": {
    "addr:full":"161 Centre St Orangeburg SC 29115",
    "addr:housenumber":"161",
    "addr:postcode":"29115",
    "addr:street":"Centre St",
    "iso:country":"US",
    "sg:address":"161 Centre St",
    "sg:city":"Orangeburg",
    "sg:classifiers":[
        {
            "category":"Wholesale",
            "subcategory":"Construction Materials",
            "type":"Manufacturing & Wholesale Goods"
        }
    ],
    "sg:phone":"+1 803 534 1957",
    "sg:postcode":"29115",
    "sg:province":"SC",
    "sg:tags":[
        "pallet",
        "skid"
    ],
    "wof:name":"Pallet Club Foundation",
    "wof:placetype":"venue"
},
  "geometry": {"coordinates":[-80.86095299999999,33.49205],"type":"Point"}
}