{
  "type": "Feature",
  "properties": {
    "iso:country":"US",
    "sg:address":"2178 S Pine St",
    "sg:city":"Spartanburg",
    "sg:classifiers":[
        {
            "category":"Retail",
            "subcategory":"Laundry & Dry Cleaning",
            "type":"Services"
        }
    ],
    "sg:phone":"+1 864 582 9495",
    "sg:postcode":"29302",
    "sg:province":"SC",
    "wof:name":"Wash Depot",
    "wof:placetype":"venue"
},
  "geometry": {"coordinates":[-81.890225,34.931804],"type":"Point"}
}