{
  "type": "Feature",
  "properties": {
    "iso:country":"US",
    "sg:address":"4996 Willow Pond Rd",
    "sg:city":"Lake Wylie",
    "sg:classifiers":[
        {
            "category":"Wholesale",
            "subcategory":"Machinery & Supplies",
            "type":"Manufacturing & Wholesale Goods"
        }
    ],
    "sg:phone":"+1 803 831 1649",
    "sg:postcode":"29710",
    "sg:province":"SC",
    "sg:tags":[
        "compressor",
        "gas"
    ],
    "wof:name":"Lake Wylie Supply Co",
    "wof:placetype":"venue"
},
  "geometry": {"coordinates":[-81.076686,35.149295],"type":"Point"}
}