{
  "type": "Feature",
  "properties": {
    "iso:country":"US",
    "sg:address":"3188 River Rd",
    "sg:city":"Johns Island",
    "sg:classifiers":[
        {
            "category":"Retail",
            "subcategory":"Auto Repair",
            "type":"Services"
        }
    ],
    "sg:phone":"+1 843 559 0711",
    "sg:postcode":"29455",
    "sg:province":"SC",
    "sg:tags":[
        "repairing",
        "automobile"
    ],
    "wof:name":"Fipps & Sons Garage",
    "wof:placetype":"venue"
},
  "geometry": {"coordinates":[-80.02890600000001,32.681585],"type":"Point"}
}