{
  "type": "Feature",
  "properties": {
    "addr:full":"3559 US Hwy 501 S Rains SC 29574",
    "addr:housenumber":"3559",
    "addr:postcode":"29574",
    "addr:street":"Us Hwy 501 S",
    "iso:country":"US",
    "sg:address":"3559 US Hwy 501 S",
    "sg:city":"Rains",
    "sg:classifiers":[
        {
            "category":"Education",
            "subcategory":"School",
            "type":"Public Place"
        }
    ],
    "sg:phone":"+1 843 423 2891",
    "sg:postcode":"29574",
    "sg:province":"SC",
    "wof:name":"Marion School District 7",
    "wof:placetype":"venue"
},
  "geometry": {"coordinates":[-79.316343,34.086922],"type":"Point"}
}