{
  "type": "Feature",
  "properties": {
    "iso:country":"US",
    "sg:address":"15881 Wells Hwy",
    "sg:city":"Seneca",
    "sg:classifiers":[
        {
            "category":"Personal",
            "subcategory":"Beauty Salon",
            "type":"Services"
        }
    ],
    "sg:phone":"+1 864 888 4707",
    "sg:postcode":"29678",
    "sg:province":"SC",
    "wof:name":"Ciao Bella Salon",
    "wof:placetype":"venue"
},
  "geometry": {"coordinates":[-82.977214,34.664409],"type":"Point"}
}