{
  "type": "Feature",
  "properties": {
    "iso:country":"US",
    "sg:address":"5576 Gallatin Ln",
    "sg:city":"North Charleston",
    "sg:classifiers":[
        {
            "category":"Building & Trades",
            "subcategory":"Construction",
            "type":"Services"
        }
    ],
    "sg:phone":"+1 843 760 9002",
    "sg:postcode":"29420",
    "sg:province":"SC",
    "sg:tags":[
        "house"
    ],
    "wof:name":"Hilltop Construction LLC",
    "wof:placetype":"venue"
},
  "geometry": {"coordinates":[-80.128253,32.919247],"type":"Point"}
}