{
  "type": "Feature",
  "properties": {
    "iso:country":"US",
    "sg:address":"617 W Columbia Ave",
    "sg:city":"Batesburg",
    "sg:classifiers":[
        {
            "category":"Autos & Motor Vehicles",
            "subcategory":"Auto Supplies",
            "type":"Retail Goods"
        }
    ],
    "sg:phone":"+1 803 532 2718",
    "sg:postcode":"29006",
    "sg:province":"SC",
    "sg:tags":[
        "automobile",
        "parts"
    ],
    "wof:name":"Dewitt's Auto Parts",
    "wof:placetype":"venue"
},
  "geometry": {"coordinates":[-81.552832,33.901229],"type":"Point"}
}