{
  "type": "Feature",
  "properties": {
    "iso:country":"US",
    "sg:address":"1513 State Hwy 61",
    "sg:city":"Ridgeville",
    "sg:classifiers":[
        {
            "category":"Wholesale",
            "subcategory":"Machinery & Supplies",
            "type":"Manufacturing & Wholesale Goods"
        }
    ],
    "sg:phone":"+1 843 875 5674",
    "sg:postcode":"29472",
    "sg:province":"SC",
    "sg:tags":[
        "cleaning",
        "vacuum"
    ],
    "wof:name":"Eadie's Construction Inc",
    "wof:placetype":"venue"
},
  "geometry": {"coordinates":[-80.34588599999999,33.015828],"type":"Point"}
}