{
  "type": "Feature",
  "properties": {
    "addr:full":"2001 Augusta Rd Greenville SC 29605",
    "addr:housenumber":"2001",
    "addr:postcode":"29605",
    "addr:street":"Augusta Rd",
    "iso:country":"US",
    "sg:address":"2001 Augusta Rd",
    "sg:city":"Greenville",
    "sg:classifiers":[
        {
            "category":"Autos & Motor Vehicles",
            "subcategory":"Fuel & Gas Station",
            "type":"Retail Goods"
        }
    ],
    "sg:phone":"+1 864 235 8932",
    "sg:postcode":"29605",
    "sg:province":"SC",
    "sg:tags":[
        "automotive",
        "station",
        "repair"
    ],
    "wof:name":"BP",
    "wof:placetype":"venue"
},
  "geometry": {"coordinates":[-82.37712999999999,34.778728],"type":"Point"}
}