{
  "type": "Feature",
  "properties": {
    "iso:country":"US",
    "sg:address":"2180 Tharpe Rd",
    "sg:city":"Little River",
    "sg:classifiers":[
        {
            "category":"Home & Garden",
            "subcategory":"Garden Supply",
            "type":"Retail Goods"
        }
    ],
    "sg:phone":"+1 843 399 0065",
    "sg:postcode":"29566",
    "sg:province":"SC",
    "sg:tags":[
        "nurseryman"
    ],
    "wof:name":"T L C's Nursery & Garden",
    "wof:placetype":"venue"
},
  "geometry": {"coordinates":[-78.645741,33.926461],"type":"Point"}
}