{
  "type": "Feature",
  "properties": {
    "iso:country":"US",
    "sg:address":"1201 Colonial Commons Ct",
    "sg:city":"Lancaster",
    "sg:classifiers":[
        {
            "category":"Health Services",
            "subcategory":"Doctor",
            "type":"Services"
        }
    ],
    "sg:phone":"+1 803 286 8443",
    "sg:postcode":"29720",
    "sg:province":"SC",
    "sg:tags":[
        "physician",
        "surgeon"
    ],
    "wof:name":"Carolina Orthopaedic Surgery",
    "wof:placetype":"venue"
},
  "geometry": {"coordinates":[-80.795139,34.721387],"type":"Point"}
}