{
  "type": "Feature",
  "properties": {
    "addr:full":"1201 Colonial Commons Ct Lancaster SC 29720",
    "addr:housenumber":"1201",
    "addr:postcode":"29720",
    "addr:street":"Colonial Commons Ct",
    "iso:country":"US",
    "sg:address":"1201 Colonial Commons Ct",
    "sg:city":"Lancaster",
    "sg:classifiers":[
        {
            "category":"Health Services",
            "subcategory":"Doctor",
            "type":"Services"
        }
    ],
    "sg:phone":"+1 803 286 8443",
    "sg:postcode":"29720",
    "sg:province":"SC",
    "sg:tags":[
        "physician",
        "surgeon"
    ],
    "wof:name":"Carolina Orthopaedic Surgery",
    "wof:placetype":"venue"
},
  "geometry": {"coordinates":[-80.79513900000001,34.721387],"type":"Point"}
}