{
  "type": "Feature",
  "properties": {
    "iso:country":"US",
    "sg:address":"1306 N Ocean Blvd",
    "sg:city":"Myrtle Beach",
    "sg:classifiers":[
        {
            "category":"Restaurant",
            "type":"Food & Drink"
        }
    ],
    "sg:phone":"+1 843 448 4314",
    "sg:postcode":"29577",
    "sg:province":"SC",
    "sg:website":"www.pier14.com",
    "wof:name":"Pier 14 Restaurant & Lounge",
    "wof:placetype":"venue"
},
  "geometry": {"coordinates":[-78.87624599999999,33.695218],"type":"Point"}
}