{
  "type": "Feature",
  "properties": {
    "addr:full":"1211 N Main St Summerville SC 29483",
    "addr:housenumber":"1211",
    "addr:postcode":"29483",
    "addr:street":"N Main St",
    "iso:country":"US",
    "sg:address":"1211 N Main St",
    "sg:city":"Summerville",
    "sg:classifiers":[
        {
            "category":"Building & Trades",
            "subcategory":"Equipment Rental",
            "type":"Services"
        }
    ],
    "sg:phone":"+1 843 871 8722",
    "sg:postcode":"29483",
    "sg:province":"SC",
    "sg:tags":[
        "leasing",
        "furniture"
    ],
    "wof:name":"Rent Way",
    "wof:placetype":"venue"
},
  "geometry": {"coordinates":[-80.155097,33.036689],"type":"Point"}
}