{
  "type": "Feature",
  "properties": {
    "iso:country":"US",
    "sg:address":"1236 Lake Cunningham Rd",
    "sg:city":"Greer",
    "sg:classifiers":[
        {
            "category":"Building & Trades",
            "subcategory":"Construction",
            "type":"Services"
        }
    ],
    "sg:phone":"+1 864 895 4909",
    "sg:postcode":"29651",
    "sg:province":"SC",
    "sg:tags":[
        "contractor"
    ],
    "wof:name":"J & T Roofing Co",
    "wof:placetype":"venue"
},
  "geometry": {"coordinates":[-82.253174,34.978792],"type":"Point"}
}