{
  "type": "Feature",
  "properties": {
    "iso:country":"US",
    "sg:address":"203 Knight St",
    "sg:city":"Fountain Inn",
    "sg:classifiers":[
        {
            "category":"Autos & Motor Vehicles",
            "subcategory":"Automobile Sales",
            "type":"Retail Goods"
        }
    ],
    "sg:phone":"+1 864 862 0200",
    "sg:postcode":"29644",
    "sg:province":"SC",
    "sg:tags":[
        "car",
        "dealer"
    ],
    "wof:name":"Tate's Auto Sales",
    "wof:placetype":"venue"
},
  "geometry": {"coordinates":[-82.194752,34.69078],"type":"Point"}
}