{
  "type": "Feature",
  "properties": {
    "iso:country":"US",
    "sg:address":"905 S Irwin Ave",
    "sg:city":"Spartanburg",
    "sg:classifiers":[
        {
            "category":"Retail",
            "subcategory":"Auto Repair",
            "type":"Services"
        }
    ],
    "sg:phone":"+1 864 583 6362",
    "sg:postcode":"29306",
    "sg:province":"SC",
    "sg:tags":[
        "wrecker"
    ],
    "wof:name":"A-1 Wrecker Svc",
    "wof:placetype":"venue"
},
  "geometry": {"coordinates":[-81.934324,34.926231],"type":"Point"}
}