{
  "type": "Feature",
  "properties": {
    "addr:full":"605 Johnnie Dodds Blvd Mount Pleasant SC 29464",
    "addr:housenumber":"605",
    "addr:postcode":"29464",
    "addr:street":"Johnnie Dodds Blvd",
    "iso:country":"US",
    "sg:address":"605 Johnnie Dodds Blvd",
    "sg:city":"Mount Pleasant",
    "sg:classifiers":[
        {
            "category":"Shopping",
            "subcategory":"Used Merchandise",
            "type":"Retail Goods"
        }
    ],
    "sg:phone":"+1 843 849 1949",
    "sg:postcode":"29464",
    "sg:province":"SC",
    "wof:name":"Nelson Garrett Inc",
    "wof:placetype":"venue"
},
  "geometry": {"coordinates":[-79.880143,32.807557],"type":"Point"}
}