{
  "type": "Feature",
  "properties": {
    "addr:full":"2410 Air Park Rd Charleston SC 29406",
    "addr:housenumber":"2410",
    "addr:postcode":"29406",
    "addr:street":"Air Park Rd",
    "iso:country":"US",
    "sg:address":"2410 Air Park Rd",
    "sg:city":"Charleston",
    "sg:classifiers":[
        {
            "category":"Freight",
            "type":"Transportation"
        }
    ],
    "sg:phone":"+1 843 529 0220",
    "sg:postcode":"29406",
    "sg:province":"SC",
    "sg:tags":[
        "mover",
        "moving"
    ],
    "wof:name":"Two Men & A Truck",
    "wof:placetype":"venue"
},
  "geometry": {"coordinates":[-80.02051400000001,32.894753],"type":"Point"}
}