{
  "type": "Feature",
  "properties": {
    "addr:full":"200 Roper Meadow Dr Simpsonville SC 29681",
    "addr:housenumber":"200",
    "addr:postcode":"29681",
    "addr:street":"Roper Meadow Dr",
    "iso:country":"US",
    "sg:address":"200 Roper Meadow Dr",
    "sg:city":"Simpsonville",
    "sg:classifiers":[
        {
            "category":"Insurance",
            "subcategory":"Insurance Agent",
            "type":"Services"
        }
    ],
    "sg:phone":"+1 864 234 5938",
    "sg:postcode":"29681",
    "sg:province":"SC",
    "wof:name":"Palmetto Health Consultants",
    "wof:placetype":"venue"
},
  "geometry": {"coordinates":[-82.23687700000001,34.822185],"type":"Point"}
}