{
  "type": "Feature",
  "properties": {
    "addr:full":"101 Sparkleberry Ln Columbia SC 29229",
    "addr:housenumber":"101",
    "addr:postcode":"29229",
    "addr:street":"Sparkleberry Ln",
    "iso:country":"US",
    "sg:address":"101 Sparkleberry Ln",
    "sg:city":"Columbia",
    "sg:classifiers":[
        {
            "category":"Shopping",
            "subcategory":"Computers & Home Electronics",
            "type":"Retail Goods"
        }
    ],
    "sg:phone":"+1 803 699 1000",
    "sg:postcode":"29229",
    "sg:province":"SC",
    "sg:tags":[
        "television"
    ],
    "wof:name":"World Vision Satellite Inc",
    "wof:placetype":"venue"
},
  "geometry": {"coordinates":[-80.885311,34.116213],"type":"Point"}
}