{
  "type": "Feature",
  "properties": {
    "iso:country":"US",
    "sg:address":"48 Flora Louise Dr",
    "sg:city":"Piedmont",
    "sg:classifiers":[
        {
            "category":"Manufacturing",
            "subcategory":"Tools & Machinery",
            "type":"Manufacturing & Wholesale Goods"
        }
    ],
    "sg:phone":"+1 864 299 1004",
    "sg:postcode":"29673",
    "sg:province":"SC",
    "sg:tags":[
        "machine",
        "shop"
    ],
    "sg:website":"www.jjserv.com",
    "wof:name":"J & J Svc",
    "wof:placetype":"venue"
},
  "geometry": {"coordinates":[-82.384864,34.725608],"type":"Point"}
}