{
  "type": "Feature",
  "properties": {
    "iso:country":"US",
    "sg:address":"1160 S 4th St",
    "sg:city":"Hartsville",
    "sg:classifiers":[
        {
            "category":"Autos & Motor Vehicles",
            "subcategory":"Fuel & Gas Station",
            "type":"Retail Goods"
        }
    ],
    "sg:phone":"+1 843 383 0441",
    "sg:postcode":"29550",
    "sg:province":"SC",
    "sg:tags":[
        "station",
        "gasoline"
    ],
    "wof:name":"Murphy Oil Usa Inc",
    "wof:placetype":"venue"
},
  "geometry": {"coordinates":[-80.058656,34.355904],"type":"Point"}
}