{
  "type": "Feature",
  "properties": {
    "iso:country":"US",
    "sg:address":"1350 Florence Hwy",
    "sg:city":"Sumter",
    "sg:classifiers":[
        {
            "category":"Banks & Credit Unions",
            "subcategory":"Bank",
            "type":"Services"
        }
    ],
    "sg:phone":"+1 803 464 6625",
    "sg:postcode":"29153",
    "sg:province":"SC",
    "sg:tags":[
        "loan"
    ],
    "wof:name":"Prescott Christopher",
    "wof:placetype":"venue"
},
  "geometry": {"coordinates":[-80.297198,33.930414],"type":"Point"}
}