{
  "type": "Feature",
  "properties": {
    "iso:country":"US",
    "sg:address":"1529 Sam Rittenberg Blvd",
    "sg:city":"Charleston",
    "sg:classifiers":[
        {
            "category":"Social Services",
            "type":"Services"
        }
    ],
    "sg:phone":"+1 843 766 3565",
    "sg:postcode":"29407",
    "sg:province":"SC",
    "sg:tags":[
        "employee",
        "assistance",
        "program"
    ],
    "wof:name":"Intl Org Masters Mates & Pilot",
    "wof:placetype":"venue"
},
  "geometry": {"coordinates":[-80.002441,32.81123],"type":"Point"}
}