{
  "type": "Feature",
  "properties": {
    "iso:country":"US",
    "sg:address":"146 N Wilson St",
    "sg:city":"Rock Hill",
    "sg:classifiers":[
        {
            "category":"Autos & Motor Vehicles",
            "subcategory":"Automobile Sales",
            "type":"Retail Goods"
        }
    ],
    "sg:phone":"+1 803 327 7311",
    "sg:postcode":"29730",
    "sg:province":"SC",
    "sg:tags":[
        "used"
    ],
    "wof:name":"Credit Auto Mall Inc",
    "wof:placetype":"venue"
},
  "geometry": {"coordinates":[-81.028969,34.929274],"type":"Point"}
}