{
  "type": "Feature",
  "properties": {
    "iso:country":"US",
    "sg:address":"506 Augusta Rd",
    "sg:city":"North Augusta",
    "sg:classifiers":[
        {
            "category":"Real Estate",
            "subcategory":"Real Estate Operator",
            "type":"Services"
        }
    ],
    "sg:phone":"+1 803 279 9086",
    "sg:postcode":"29822",
    "sg:province":"SC",
    "sg:tags":[
        "building",
        "parks",
        "nonresidential"
    ],
    "wof:name":"506 Building",
    "wof:placetype":"venue"
},
  "geometry": {"coordinates":[-81.892122,33.49684],"type":"Point"}
}