{
  "type": "Feature",
  "properties": {
    "addr:full":"110 Nonna Ln Seneca SC 29678",
    "addr:housenumber":"110",
    "addr:postcode":"29678",
    "addr:street":"Nonna Ln",
    "iso:country":"US",
    "sg:address":"110 Nonna Ln",
    "sg:city":"Seneca",
    "sg:classifiers":[
        {
            "category":"Shopping",
            "subcategory":"Computers & Home Electronics",
            "type":"Retail Goods"
        }
    ],
    "sg:phone":"+1 864 882 6580",
    "sg:postcode":"29678",
    "sg:province":"SC",
    "sg:tags":[
        "repair",
        "electronic",
        "consumer",
        "equipment"
    ],
    "wof:name":"Seneca Micronics",
    "wof:placetype":"venue"
},
  "geometry": {"coordinates":[-82.926154,34.669004],"type":"Point"}
}