{
  "type": "Feature",
  "properties": {
    "iso:country":"US",
    "sg:address":"360 Old Socastee Hwy",
    "sg:city":"Myrtle Beach",
    "sg:classifiers":[
        {
            "category":"Building & Trades",
            "subcategory":"Construction",
            "type":"Services"
        }
    ],
    "sg:phone":"+1 843 448 3900",
    "sg:postcode":"29577",
    "sg:province":"SC",
    "sg:tags":[
        "general",
        "contractor"
    ],
    "wof:name":"Watkins Services Inc",
    "wof:placetype":"venue"
},
  "geometry": {"coordinates":[-78.908754,33.700095],"type":"Point"}
}