{
  "type": "Feature",
  "properties": {
    "iso:country":"US",
    "sg:address":"1451 Woodruff Rd",
    "sg:city":"Greenville",
    "sg:classifiers":[
        {
            "category":"Shopping",
            "type":"Retail Goods"
        }
    ],
    "sg:phone":"+1 864 286 1313",
    "sg:postcode":"29607",
    "sg:province":"SC",
    "sg:tags":[
        "pet",
        "shop",
        "merchandise"
    ],
    "wof:name":"Petland",
    "wof:placetype":"venue"
},
  "geometry": {"coordinates":[-82.281107,34.820722],"type":"Point"}
}