{
  "type": "Feature",
  "properties": {
    "iso:country":"US",
    "sg:address":"810 65th Ave N",
    "sg:city":"Myrtle Beach",
    "sg:classifiers":[
        {
            "category":"Real Estate",
            "subcategory":"Real Estate Agent",
            "type":"Services"
        },
        {
            "category":"Real Estate",
            "subcategory":"Real Estate Operator",
            "type":"Services"
        }
    ],
    "sg:phone":"+1 843 449 6242",
    "sg:postcode":"29572",
    "sg:province":"SC",
    "sg:tags":[
        "condominium"
    ],
    "wof:name":"Academy Way Condo's",
    "wof:placetype":"venue"
},
  "geometry": {"coordinates":[-78.836141,33.744358],"type":"Point"}
}