{
  "type": "Feature",
  "properties": {
    "iso:country":"US",
    "sg:address":"133 Swindon Cir",
    "sg:city":"Greenville",
    "sg:classifiers":[
        {
            "category":"Restaurant",
            "type":"Food & Drink"
        }
    ],
    "sg:phone":"+1 864 244 8448",
    "sg:postcode":"29615",
    "sg:province":"SC",
    "sg:tags":[
        "eating"
    ],
    "wof:name":"Chulkas Arthur Faye & Jim",
    "wof:placetype":"venue"
},
  "geometry": {"coordinates":[-82.321479,34.878003],"type":"Point"}
}