{
  "type": "Feature",
  "properties": {
    "iso:country":"US",
    "sg:address":"1030 Jenkins Rd",
    "sg:city":"Charleston",
    "sg:classifiers":[
        {
            "category":"Shopping",
            "subcategory":"Computers & Home Electronics",
            "type":"Retail Goods"
        }
    ],
    "sg:phone":"+1 843 532 8346",
    "sg:postcode":"29407",
    "sg:province":"SC",
    "sg:tags":[
        "high",
        "fidelity",
        "stereophonic"
    ],
    "wof:name":"Custom Home Sound",
    "wof:placetype":"venue"
},
  "geometry": {"coordinates":[-80.019752,32.798573],"type":"Point"}
}