{
  "type": "Feature",
  "properties": {
    "addr:full":"1929 Grimball Rd Charleston SC 29412",
    "addr:housenumber":"1929",
    "addr:postcode":"29412",
    "addr:street":"Grimball Rd",
    "iso:country":"US",
    "sg:address":"1929 Grimball Rd",
    "sg:city":"Charleston",
    "sg:classifiers":[
        {
            "category":"Education",
            "subcategory":"School",
            "type":"Public Place"
        }
    ],
    "sg:phone":"+1 843 762 2774",
    "sg:postcode":"29412",
    "sg:province":"SC",
    "wof:name":"Clark Corporate Academy",
    "wof:placetype":"venue"
},
  "geometry": {"coordinates":[-79.97688599999999,32.706116],"type":"Point"}
}