{
  "type": "Feature",
  "properties": {
    "iso:country":"US",
    "sg:address":"100 Ridgemoor Dr",
    "sg:city":"Aiken",
    "sg:classifiers":[
        {
            "category":"Retail",
            "subcategory":"Animal Services",
            "type":"Services"
        }
    ],
    "sg:phone":"+1 803 642 7884",
    "sg:postcode":"29803",
    "sg:province":"SC",
    "wof:name":"Shannons Grooming Servic",
    "wof:placetype":"venue"
},
  "geometry": {"coordinates":[-81.75039700000001,33.52341],"type":"Point"}
}