{
  "type": "Feature",
  "properties": {
    "iso:country":"US",
    "sg:address":"401 E Jefferson St",
    "sg:city":"Dillon",
    "sg:classifiers":[
        {
            "category":"Home & Garden",
            "subcategory":"Carpets & Floor Coverings",
            "type":"Retail Goods"
        }
    ],
    "sg:phone":"+1 843 774 5177",
    "sg:postcode":"29536",
    "sg:province":"SC",
    "wof:name":"Rants Carpet Service",
    "wof:placetype":"venue"
},
  "geometry": {"coordinates":[-79.36626099999999,34.419171],"type":"Point"}
}