{
  "type": "Feature",
  "properties": {
    "iso:country":"US",
    "sg:address":"192 Knox Abbott Dr",
    "sg:city":"Cayce",
    "sg:classifiers":[
        {
            "category":"Banks & Credit Unions",
            "subcategory":"Bank",
            "type":"Services"
        }
    ],
    "sg:phone":"+1 803 404 5640",
    "sg:postcode":"29033",
    "sg:province":"SC",
    "wof:name":"Southern First Bank",
    "wof:placetype":"venue"
},
  "geometry": {"coordinates":[-81.052503,33.986363],"type":"Point"}
}