{
  "type": "Feature",
  "properties": {
    "iso:country":"US",
    "sg:address":"1131 Crows Nest Rd",
    "sg:city":"Rock Hill",
    "sg:classifiers":[
        {
            "category":"Shopping",
            "subcategory":"Florist",
            "type":"Retail Goods"
        },
        {
            "category":"Restaurant",
            "type":"Food & Drink"
        }
    ],
    "sg:phone":"+1 803 325 1972",
    "sg:postcode":"29730",
    "sg:province":"SC",
    "sg:tags":[
        "eating"
    ],
    "wof:name":"Bobbi's Bloomies",
    "wof:placetype":"venue"
},
  "geometry": {"coordinates":[-80.932647,34.908742],"type":"Point"}
}