{
  "type": "Feature",
  "properties": {
    "iso:country":"US",
    "sg:address":"4001 E Palmetto St",
    "sg:city":"Florence",
    "sg:classifiers":[
        {
            "category":"Shopping",
            "subcategory":"Clothing, Apparel, & Fashions",
            "type":"Retail Goods"
        }
    ],
    "sg:phone":"+1 843 664 8829",
    "sg:postcode":"29506",
    "sg:province":"SC",
    "sg:tags":[
        "western"
    ],
    "wof:name":"Lel El Paisano Shoes",
    "wof:placetype":"venue"
},
  "geometry": {"coordinates":[-79.678668,34.196683],"type":"Point"}
}