{
  "type": "Feature",
  "properties": {
    "addr:full":"701 Hwy 301 S Dillon SC 29536",
    "addr:housenumber":"701",
    "addr:postcode":"29536",
    "addr:street":"Hwy 301 S",
    "iso:country":"US",
    "sg:address":"701 Hwy 301 S",
    "sg:city":"Dillon",
    "sg:classifiers":[
        {
            "category":"Organizations",
            "subcategory":"Religious Organization",
            "type":"Services"
        }
    ],
    "sg:phone":"+1 843 774 8021",
    "sg:postcode":"29536",
    "sg:province":"SC",
    "sg:tags":[
        "church"
    ],
    "wof:name":"Church Of God",
    "wof:placetype":"venue"
},
  "geometry": {"coordinates":[-79.37471499999999,34.411221],"type":"Point"}
}