{
  "type": "Feature",
  "properties": {
    "addr:full":"167 Alabama St Spartanburg SC 29302",
    "addr:housenumber":"167",
    "addr:postcode":"29302",
    "addr:street":"Alabama St",
    "iso:country":"US",
    "sg:address":"167 Alabama St",
    "sg:city":"Spartanburg",
    "sg:classifiers":[
        {
            "category":"Social Services",
            "type":"Services"
        }
    ],
    "sg:phone":"+1 864 583 1010",
    "sg:postcode":"29302",
    "sg:province":"SC",
    "sg:tags":[
        "counselor",
        "marriage",
        "family"
    ],
    "wof:name":"Westgate Family Therapy Clinic",
    "wof:placetype":"venue"
},
  "geometry": {"coordinates":[-81.925096,34.952036],"type":"Point"}
}