{
  "type": "Feature",
  "properties": {
    "addr:full":"288 Fox Catcher Dr Myrtle Beach SC 29575",
    "addr:housenumber":"288",
    "addr:postcode":"29575",
    "addr:street":"Fox Catcher Dr",
    "iso:country":"US",
    "sg:address":"288 Fox Catcher Dr",
    "sg:city":"Myrtle Beach",
    "sg:classifiers":[
        {
            "category":"Building & Trades",
            "subcategory":"Construction",
            "type":"Services"
        }
    ],
    "sg:phone":"+1 843 650 8862",
    "sg:postcode":"29575",
    "sg:province":"SC",
    "sg:tags":[
        "general",
        "contractor"
    ],
    "wof:name":"BTS Construction Inc",
    "wof:placetype":"venue"
},
  "geometry": {"coordinates":[-79.007839,33.676618],"type":"Point"}
}