{
  "type": "Feature",
  "properties": {
    "addr:full":"10 Rushmore Dr Greenville SC 29615",
    "addr:housenumber":"10",
    "addr:postcode":"29615",
    "addr:street":"Rushmore Dr",
    "iso:country":"US",
    "sg:address":"10 Rushmore Dr",
    "sg:city":"Greenville",
    "sg:classifiers":[
        {
            "category":"Restaurant",
            "type":"Food & Drink"
        }
    ],
    "sg:phone":"+1 864 268 0270",
    "sg:postcode":"29615",
    "sg:province":"SC",
    "sg:website":"www.carrols.com",
    "wof:name":"Burger King",
    "wof:placetype":"venue"
},
  "geometry": {"coordinates":[-82.35423299999999,34.884596],"type":"Point"}
}