{
  "type": "Feature",
  "properties": {
    "addr:full":"475 E Bay St Charleston SC 29403",
    "addr:housenumber":"475",
    "addr:postcode":"29403",
    "addr:street":"E Bay St",
    "iso:country":"US",
    "sg:address":"475 E Bay St",
    "sg:city":"Charleston",
    "sg:classifiers":[
        {
            "category":"Sports & Exercise",
            "subcategory":"Gym",
            "type":"Entertainment"
        }
    ],
    "sg:phone":"+1 843 723 2002",
    "sg:postcode":"29403",
    "sg:province":"SC",
    "sg:tags":[
        "personal",
        "trainer"
    ],
    "wof:name":"Top Shape",
    "wof:placetype":"venue"
},
  "geometry": {"coordinates":[-79.929678,32.789002],"type":"Point"}
}