{
  "type": "Feature",
  "properties": {
    "iso:country":"US",
    "sg:address":"1040 Charlotte Ave",
    "sg:city":"Rock Hill",
    "sg:classifiers":[
        {
            "category":"Banks & Credit Unions",
            "subcategory":"Bank",
            "type":"Services"
        }
    ],
    "sg:phone":"+1 803 324 4483",
    "sg:postcode":"29732",
    "sg:province":"SC",
    "sg:tags":[
        "mortgage",
        "loan",
        "broker",
        "real estate"
    ],
    "wof:name":"Palmetto State Mortgage Inc",
    "wof:placetype":"venue"
},
  "geometry": {"coordinates":[-81.02914,34.945181],"type":"Point"}
}