{
  "type": "Feature",
  "properties": {
    "iso:country":"US",
    "sg:address":"1175 Folly Rd",
    "sg:city":"Charleston",
    "sg:classifiers":[
        {
            "category":"Restaurant",
            "type":"Food & Drink"
        }
    ],
    "sg:phone":"+1 843 225 6996",
    "sg:postcode":"29412",
    "sg:province":"SC",
    "wof:name":"Kickin' Chicken",
    "wof:placetype":"venue"
},
  "geometry": {"coordinates":[-79.967391,32.724514],"type":"Point"}
}