{
  "type": "Feature",
  "properties": {
    "iso:country":"US",
    "sg:address":"6000 Regent Pkwy",
    "sg:city":"Fort Mill",
    "sg:classifiers":[
        {
            "category":"Sports & Exercise",
            "subcategory":"Golf",
            "type":"Entertainment"
        }
    ],
    "sg:phone":"+1 803 547 1300",
    "sg:postcode":"29715",
    "sg:province":"SC",
    "sg:tags":[
        "course"
    ],
    "wof:name":"Regent Park Golf Club",
    "wof:placetype":"venue"
},
  "geometry": {"coordinates":[-80.912808,35.068327],"type":"Point"}
}