{
  "type": "Feature",
  "properties": {
    "addr:full":"107 Columbia Ave Chapin SC 29036",
    "addr:housenumber":"107",
    "addr:postcode":"29036",
    "addr:street":"Columbia Ave",
    "iso:country":"US",
    "sg:address":"107 Columbia Ave",
    "sg:city":"Chapin",
    "sg:classifiers":[
        {
            "category":"Education",
            "subcategory":"School",
            "type":"Public Place"
        }
    ],
    "sg:phone":"+1 803 345 7136",
    "sg:postcode":"29036",
    "sg:province":"SC",
    "sg:website":"www.lex5.k12.sc.us",
    "wof:name":"Alternative Academy",
    "wof:placetype":"venue"
},
  "geometry": {"coordinates":[-81.34901600000001,34.167329],"type":"Point"}
}