{
  "type": "Feature",
  "properties": {
    "addr:full":"581 Berkeley Dr Clemson SC 29631",
    "addr:housenumber":"581",
    "addr:postcode":"29631",
    "addr:street":"Berkeley Dr",
    "iso:country":"US",
    "sg:address":"581 Berkeley Dr",
    "sg:city":"Clemson",
    "sg:classifiers":[
        {
            "category":"Organizations",
            "subcategory":"Religious Organization",
            "type":"Services"
        }
    ],
    "sg:phone":"+1 864 624 1207",
    "sg:postcode":"29631",
    "sg:province":"SC",
    "sg:tags":[
        "church"
    ],
    "wof:name":"Vineyard Community Church",
    "wof:placetype":"venue"
},
  "geometry": {"coordinates":[-82.79959100000001,34.69059],"type":"Point"}
}