{
  "type": "Feature",
  "properties": {
    "iso:country":"US",
    "sg:address":"6821 Shelley Rd",
    "sg:city":"Columbia",
    "sg:classifiers":[
        {
            "category":"Farming",
            "subcategory":"Livestock Farm",
            "type":"Manufacturing & Wholesale Goods"
        }
    ],
    "sg:phone":"+1 803 783 7210",
    "sg:postcode":"29209",
    "sg:province":"SC",
    "sg:tags":[
        "pro",
        "equine",
        "animal"
    ],
    "wof:name":"Palmetto Winn Farms Inc",
    "wof:placetype":"venue"
},
  "geometry": {"coordinates":[-80.96632099999999,33.959071],"type":"Point"}
}