{
  "type": "Feature",
  "properties": {
    "iso:country":"US",
    "sg:address":"408 Randall Rd",
    "sg:city":"Easley",
    "sg:classifiers":[
        {
            "category":"Utilities",
            "subcategory":"Refuse",
            "type":"Services"
        }
    ],
    "sg:phone":"+1 864 859 6998",
    "sg:postcode":"29642",
    "sg:province":"SC",
    "sg:tags":[
        "garbage",
        "collection"
    ],
    "wof:name":"B & J Sanitation",
    "wof:placetype":"venue"
},
  "geometry": {"coordinates":[-82.568365,34.72747],"type":"Point"}
}