{
  "type": "Feature",
  "properties": {
    "iso:country":"US",
    "sg:address":"76 State Hwy 57 S",
    "sg:city":"Little River",
    "sg:classifiers":[
        {
            "category":"Wholesale",
            "subcategory":"Non-durable Goods",
            "type":"Manufacturing & Wholesale Goods"
        }
    ],
    "sg:phone":"+1 843 399 2165",
    "sg:postcode":"29566",
    "sg:province":"SC",
    "sg:tags":[
        "beach",
        "novelty",
        "related",
        "gift",
        "item"
    ],
    "wof:name":"Kruger LTD",
    "wof:placetype":"venue"
},
  "geometry": {"coordinates":[-78.683522,33.884991],"type":"Point"}
}