{
  "type": "Feature",
  "properties": {
    "iso:country":"US",
    "sg:address":"200 75th Ave N",
    "sg:city":"Myrtle Beach",
    "sg:classifiers":[
        {
            "category":"Real Estate",
            "subcategory":"Real Estate Agent",
            "type":"Services"
        }
    ],
    "sg:phone":"+1 843 497 0862",
    "sg:postcode":"29572",
    "sg:province":"SC",
    "sg:tags":[
        "sharing",
        "condominium"
    ],
    "wof:name":"Jade Tree Cove",
    "wof:placetype":"venue"
},
  "geometry": {"coordinates":[-78.816974,33.743694],"type":"Point"}
}