{
  "type": "Feature",
  "properties": {
    "iso:country":"US",
    "sg:address":"977 Russell St",
    "sg:city":"Orangeburg",
    "sg:classifiers":[
        {
            "category":"Retail",
            "subcategory":"Laundry & Dry Cleaning",
            "type":"Services"
        }
    ],
    "sg:phone":"+1 803 534 5400",
    "sg:postcode":"29115",
    "sg:province":"SC",
    "sg:tags":[
        "cleaners"
    ],
    "wof:name":"One Rate Cleaners",
    "wof:placetype":"venue"
},
  "geometry": {"coordinates":[-80.867831,33.486878],"type":"Point"}
}