{
  "type": "Feature",
  "properties": {
    "iso:country":"US",
    "sg:address":"1320 Main St",
    "sg:city":"Columbia",
    "sg:classifiers":[
        {
            "category":"Professional",
            "subcategory":"Lawyer & Legal Services",
            "type":"Services"
        }
    ],
    "sg:phone":"+1 803 255 9522",
    "sg:postcode":"29201",
    "sg:province":"SC",
    "wof:name":"Hall Kevin A Atty",
    "wof:placetype":"venue"
},
  "geometry": {"coordinates":[-81.034384,34.003167],"type":"Point"}
}