{
  "type": "Feature",
  "properties": {
    "addr:full":"3456 Maybank Hwy Johns Island SC 29455",
    "addr:housenumber":"3456",
    "addr:postcode":"29455",
    "addr:street":"Maybank Hwy",
    "iso:country":"US",
    "sg:address":"3456 Maybank Hwy",
    "sg:city":"Johns Island",
    "sg:classifiers":[
        {
            "category":"Building & Trades",
            "subcategory":"Construction",
            "type":"Services"
        }
    ],
    "sg:phone":"+1 843 559 8854",
    "sg:postcode":"29455",
    "sg:province":"SC",
    "sg:tags":[
        "general",
        "contractor"
    ],
    "wof:name":"Stono Construction Group LLP",
    "wof:placetype":"venue"
},
  "geometry": {"coordinates":[-80.072695,32.725519],"type":"Point"}
}