{
  "type": "Feature",
  "properties": {
    "iso:country":"US",
    "sg:address":"3239 Sunset Blvd",
    "sg:city":"West Columbia",
    "sg:classifiers":[
        {
            "category":"Wholesale",
            "subcategory":"Machinery & Supplies",
            "type":"Manufacturing & Wholesale Goods"
        }
    ],
    "sg:phone":"+1 803 936 9990",
    "sg:postcode":"29169",
    "sg:province":"SC",
    "sg:tags":[
        "truck"
    ],
    "wof:name":"Pioneer Machinery",
    "wof:placetype":"venue"
},
  "geometry": {"coordinates":[-81.128721,34.00789],"type":"Point"}
}