{
  "type": "Feature",
  "properties": {
    "iso:country":"US",
    "sg:address":"2710 White Horse Rd",
    "sg:city":"Greenville",
    "sg:classifiers":[
        {
            "category":"Recreation",
            "type":"Entertainment"
        }
    ],
    "sg:phone":"+1 864 295 1183",
    "sg:postcode":"29611",
    "sg:province":"SC",
    "sg:tags":[
        "fairground"
    ],
    "wof:name":"Greenville County Fairgrounds",
    "wof:placetype":"venue"
},
  "geometry": {"coordinates":[-82.43508,34.807984],"type":"Point"}
}