{
  "type": "Feature",
  "properties": {
    "iso:country":"US",
    "sg:address":"119 Gentry Memorial Hwy",
    "sg:city":"Easley",
    "sg:classifiers":[
        {
            "category":"Health Services",
            "subcategory":"Doctor",
            "type":"Services"
        }
    ],
    "sg:phone":"+1 864 306 9920",
    "sg:postcode":"29640",
    "sg:province":"SC",
    "sg:tags":[
        "clinic"
    ],
    "wof:name":"Adaptive Medical",
    "wof:placetype":"venue"
},
  "geometry": {"coordinates":[-82.621285,34.836902],"type":"Point"}
}