{
  "type": "Feature",
  "properties": {
    "iso:country":"US",
    "sg:address":"55 Cleveland St",
    "sg:city":"Charleston",
    "sg:classifiers":[
        {
            "category":"Government",
            "subcategory":"Office",
            "type":"Public Place"
        }
    ],
    "sg:phone":"+1 843 724 7405",
    "sg:postcode":"29403",
    "sg:province":"SC",
    "sg:tags":[
        "village"
    ],
    "wof:name":"Hampton Park Playground",
    "wof:placetype":"venue"
},
  "geometry": {"coordinates":[-79.952216,32.801702],"type":"Point"}
}