{
  "type": "Feature",
  "properties": {
    "addr:full":"1728 Village Park Dr Orangeburg SC 29118",
    "addr:housenumber":"1728",
    "addr:postcode":"29118",
    "addr:street":"Village Park Dr",
    "iso:country":"US",
    "sg:address":"1728 Village Park Dr",
    "sg:city":"Orangeburg",
    "sg:classifiers":[
        {
            "category":"Health Services",
            "subcategory":"Doctor",
            "type":"Services"
        }
    ],
    "sg:phone":"+1 803 536 1106",
    "sg:postcode":"29118",
    "sg:province":"SC",
    "sg:tags":[
        "physician",
        "surgeon"
    ],
    "wof:name":"Advanced Diagnostic Imaging",
    "wof:placetype":"venue"
},
  "geometry": {"coordinates":[-80.856537,33.522937],"type":"Point"}
}