{
  "type": "Feature",
  "properties": {
    "iso:country":"US",
    "sg:address":"210 E 1st North St",
    "sg:city":"Summerville",
    "sg:classifiers":[
        {
            "category":"Personal",
            "subcategory":"Beauty Salon",
            "type":"Services"
        }
    ],
    "sg:phone":"+1 843 821 8733",
    "sg:postcode":"29483",
    "sg:province":"SC",
    "wof:name":"Marilyn's Coiffures",
    "wof:placetype":"venue"
},
  "geometry": {"coordinates":[-80.171177,33.020055],"type":"Point"}
}