{
  "type": "Feature",
  "properties": {
    "addr:full":"1324 E North St Greenville SC 29607",
    "addr:housenumber":"1324",
    "addr:postcode":"29607",
    "addr:street":"E North St",
    "iso:country":"US",
    "sg:address":"1324 E North St",
    "sg:city":"Greenville",
    "sg:classifiers":[
        {
            "category":"Travel",
            "subcategory":"Travel Agent",
            "type":"Entertainment"
        }
    ],
    "sg:phone":"+1 864 233 7703",
    "sg:postcode":"29607",
    "sg:province":"SC",
    "sg:tags":[
        "agency",
        "bureau"
    ],
    "wof:name":"Vantage Inc",
    "wof:placetype":"venue"
},
  "geometry": {"coordinates":[-82.382845,34.855431],"type":"Point"}
}