{
  "type": "Feature",
  "properties": {
    "addr:full":"593 Ridgeville Rd Ridgeville SC 29472",
    "addr:housenumber":"593",
    "addr:postcode":"29472",
    "addr:street":"Ridgeville Rd",
    "iso:country":"US",
    "sg:address":"593 Ridgeville Rd",
    "sg:city":"Ridgeville",
    "sg:classifiers":[
        {
            "category":"Manufacturing",
            "subcategory":"Watercraft",
            "type":"Manufacturing & Wholesale Goods"
        }
    ],
    "sg:phone":"+1 843 873 0112",
    "sg:postcode":"29472",
    "sg:province":"SC",
    "sg:tags":[
        "boat"
    ],
    "sg:website":"www.keywestboatsinc.com",
    "wof:name":"Key West Boats",
    "wof:placetype":"venue"
},
  "geometry": {"coordinates":[-80.308329,33.111458],"type":"Point"}
}