{
  "type": "Feature",
  "properties": {
    "iso:country":"US",
    "sg:address":"787 US Hwy 17",
    "sg:city":"Little River",
    "sg:classifiers":[
        {
            "category":"Restaurant",
            "type":"Food & Drink"
        }
    ],
    "sg:phone":"+1 843 249 4539",
    "sg:postcode":"29566",
    "sg:province":"SC",
    "wof:name":"Little River Diner",
    "wof:placetype":"venue"
},
  "geometry": {"coordinates":[-78.63764999999999,33.867062],"type":"Point"}
}