{
  "type": "Feature",
  "properties": {
    "addr:full":"415 S Irby St Florence SC 29501",
    "addr:housenumber":"415",
    "addr:postcode":"29501",
    "addr:street":"S Irby St",
    "iso:country":"US",
    "sg:address":"415 S Irby St",
    "sg:city":"Florence",
    "sg:classifiers":[
        {
            "category":"Travel",
            "subcategory":"Hotels & Motels",
            "type":"Entertainment"
        }
    ],
    "sg:phone":"+1 843 662 1486",
    "sg:postcode":"29501",
    "sg:province":"SC",
    "wof:name":"Colonial Inn",
    "wof:placetype":"venue"
},
  "geometry": {"coordinates":[-79.767786,34.19047],"type":"Point"}
}