{
  "type": "Feature",
  "properties": {
    "iso:country":"US",
    "sg:address":"521 Woodland Dr",
    "sg:city":"Manning",
    "sg:classifiers":[
        {
            "category":"Real Estate",
            "subcategory":"Real Estate Operator",
            "type":"Services"
        }
    ],
    "sg:phone":"+1 803 435 8176",
    "sg:postcode":"29102",
    "sg:province":"SC",
    "sg:tags":[
        "property",
        "lessor"
    ],
    "wof:name":"Carey Rawlinson",
    "wof:placetype":"venue"
},
  "geometry": {"coordinates":[-80.217679,33.685125],"type":"Point"}
}