{
  "type": "Feature",
  "properties": {
    "iso:country":"US",
    "sg:address":"1345 Lake Murray Blvd",
    "sg:city":"Irmo",
    "sg:classifiers":[
        {
            "category":"Shopping",
            "subcategory":"Pharmacy",
            "type":"Retail Goods"
        }
    ],
    "sg:phone":"+1 803 407 1038",
    "sg:postcode":"29212",
    "sg:province":"SC",
    "wof:name":"Eckerd Drugs",
    "wof:placetype":"venue"
},
  "geometry": {"coordinates":[-81.185652,34.084961],"type":"Point"}
}