{
  "type": "Feature",
  "properties": {
    "iso:country":"US",
    "sg:address":"3109 Casey St",
    "sg:city":"Loris",
    "sg:classifiers":[
        {
            "category":"Health Services",
            "subcategory":"Doctor",
            "type":"Services"
        }
    ],
    "sg:phone":"+1 843 716 2229",
    "sg:postcode":"29569",
    "sg:province":"SC",
    "sg:tags":[
        "physician",
        "surgeon"
    ],
    "wof:name":"Seashore Pediatrics",
    "wof:placetype":"venue"
},
  "geometry": {"coordinates":[-78.90007900000001,34.058692],"type":"Point"}
}