{
  "type": "Feature",
  "properties": {
    "addr:full":"11 N McCauley Rd Travelers Rest SC 29690",
    "addr:housenumber":"11",
    "addr:postcode":"29690",
    "addr:street":"N Mccauley Rd",
    "iso:country":"US",
    "sg:address":"11 N McCauley Rd",
    "sg:city":"Travelers Rest",
    "sg:classifiers":[
        {
            "category":"Wholesale",
            "subcategory":"Fruits & Vegetables",
            "type":"Manufacturing & Wholesale Goods"
        }
    ],
    "sg:phone":"+1 864 244 8977",
    "sg:postcode":"29690",
    "sg:province":"SC",
    "wof:name":"Apple A Day Hydroponic Farm Yo",
    "wof:placetype":"venue"
},
  "geometry": {"coordinates":[-82.42182,35.022034],"type":"Point"}
}