{
  "type": "Feature",
  "properties": {
    "iso:country":"US",
    "sg:address":"1918 Meadowbrook Dr",
    "sg:city":"Camden",
    "sg:classifiers":[
        {
            "category":"Manufacturing",
            "subcategory":"Apparel",
            "type":"Manufacturing & Wholesale Goods"
        }
    ],
    "sg:phone":"+1 803 432 6359",
    "sg:postcode":"29020",
    "sg:province":"SC",
    "sg:tags":[
        "outerwear",
        "mfg"
    ],
    "wof:name":"Southside Sportswear",
    "wof:placetype":"venue"
},
  "geometry": {"coordinates":[-80.549601,34.278638],"type":"Point"}
}