{
  "type": "Feature",
  "properties": {
    "iso:country":"US",
    "sg:address":"62 State St",
    "sg:city":"Charleston",
    "sg:classifiers":[
        {
            "category":"Restaurant",
            "type":"Food & Drink"
        }
    ],
    "sg:phone":"+1 843 722 7138",
    "sg:postcode":"29401",
    "sg:province":"SC",
    "wof:name":"Kaspers",
    "wof:placetype":"venue"
},
  "geometry": {"coordinates":[-79.928341,32.779773],"type":"Point"}
}