{
  "type": "Feature",
  "properties": {
    "iso:country":"US",
    "sg:address":"203 W Elm St",
    "sg:city":"Florence",
    "sg:classifiers":[
        {
            "category":"Health Services",
            "subcategory":"Health Practitioner",
            "type":"Services"
        }
    ],
    "sg:phone":"+1 843 678 8998",
    "sg:postcode":"29501",
    "sg:province":"SC",
    "sg:tags":[
        "psychologist"
    ],
    "wof:name":"Carolina Sleep Diagnostics Inc",
    "wof:placetype":"venue"
},
  "geometry": {"coordinates":[-79.769876,34.190214],"type":"Point"}
}