{
  "type": "Feature",
  "properties": {
    "iso:country":"US",
    "sg:address":"873 New Coward Rd",
    "sg:city":"Coward",
    "sg:classifiers":[
        {
            "category":"Personal",
            "subcategory":"Beauty Salon",
            "type":"Services"
        }
    ],
    "sg:phone":"+1 843 389 4456",
    "sg:postcode":"29530",
    "sg:province":"SC",
    "wof:name":"Bonnie's Hair Shop",
    "wof:placetype":"venue"
},
  "geometry": {"coordinates":[-79.711983,33.987473],"type":"Point"}
}