{
  "type": "Feature",
  "properties": {
    "iso:country":"US",
    "sg:address":"33 Office Park Rd",
    "sg:city":"Hilton Head Isle",
    "sg:classifiers":[
        {
            "category":"Shopping",
            "subcategory":"Bicycles & Sporting Goods",
            "type":"Retail Goods"
        }
    ],
    "sg:phone":"+1 843 842 4786",
    "sg:postcode":"29928",
    "sg:province":"SC",
    "sg:website":"www.gotrisports.com",
    "wof:name":"Go Tri Sports Inc",
    "wof:placetype":"venue"
},
  "geometry": {"coordinates":[-80.763387,32.15339],"type":"Point"}
}