{
  "type": "Feature",
  "properties": {
    "addr:full":"425 Smith Rd Lugoff SC 29078",
    "addr:housenumber":"425",
    "addr:postcode":"29078",
    "addr:street":"Smith Rd",
    "iso:country":"US",
    "sg:address":"425 Smith Rd",
    "sg:city":"Lugoff",
    "sg:classifiers":[
        {
            "category":"Building & Trades",
            "subcategory":"Construction",
            "type":"Services"
        }
    ],
    "sg:phone":"+1 803 408 8849",
    "sg:postcode":"29078",
    "sg:province":"SC",
    "sg:tags":[
        "concrete",
        "contractor"
    ],
    "wof:name":"Morning Star Concrete LLC",
    "wof:placetype":"venue"
},
  "geometry": {"coordinates":[-80.73509300000001,34.208676],"type":"Point"}
}