{
  "type": "Feature",
  "properties": {
    "iso:country":"US",
    "sg:address":"802 Augusta Rd",
    "sg:city":"North Augusta",
    "sg:classifiers":[
        {
            "category":"Freight",
            "type":"Transportation"
        }
    ],
    "sg:phone":"+1 803 202 7100",
    "sg:postcode":"29822",
    "sg:province":"SC",
    "sg:tags":[
        "dry",
        "bulk",
        "operator",
        "trucking"
    ],
    "wof:name":"Jomi Trucking",
    "wof:placetype":"venue"
},
  "geometry": {"coordinates":[-81.892081,33.496865],"type":"Point"}
}