{
  "type": "Feature",
  "properties": {
    "addr:full":"202 W Main St Dillon SC 29536",
    "addr:housenumber":"202",
    "addr:postcode":"29536",
    "addr:street":"W Main St",
    "iso:country":"US",
    "sg:address":"202 W Main St",
    "sg:city":"Dillon",
    "sg:classifiers":[
        {
            "category":"Social Services",
            "subcategory":"Child Care",
            "type":"Services"
        }
    ],
    "sg:phone":"+1 843 841 1544",
    "sg:postcode":"29536",
    "sg:province":"SC",
    "wof:name":"Fast Start Childhood Ctr",
    "wof:placetype":"venue"
},
  "geometry": {"coordinates":[-79.37458599999999,34.418463],"type":"Point"}
}