{
  "type": "Feature",
  "properties": {
    "addr:full":"467 South Ave Lancaster SC 29720",
    "addr:housenumber":"467",
    "addr:postcode":"29720",
    "addr:street":"South Ave",
    "iso:country":"US",
    "sg:address":"467 South Ave",
    "sg:city":"Lancaster",
    "sg:classifiers":[
        {
            "category":"Recreation",
            "subcategory":"Arcade",
            "type":"Entertainment"
        }
    ],
    "sg:phone":"+1 803 285 1013",
    "sg:postcode":"29720",
    "sg:province":"SC",
    "sg:tags":[
        "amusement",
        "devices"
    ],
    "wof:name":"Stroud Amusement Svc",
    "wof:placetype":"venue"
},
  "geometry": {"coordinates":[-80.774744,34.708096],"type":"Point"}
}