{
  "type": "Feature",
  "properties": {
    "addr:full":"28 Old Rockhouse Rd Greenville SC 29609",
    "addr:housenumber":"28",
    "addr:postcode":"29609",
    "addr:street":"Old Rockhouse Rd",
    "iso:country":"US",
    "sg:address":"28 Old Rockhouse Rd",
    "sg:city":"Greenville",
    "sg:classifiers":[
        {
            "category":"Shopping",
            "type":"Retail Goods"
        }
    ],
    "sg:phone":"+1 864 294 1144",
    "sg:postcode":"29609",
    "sg:province":"SC",
    "sg:tags":[
        "cosmetic",
        "perfume"
    ],
    "wof:name":"Jackie's Professional Skin",
    "wof:placetype":"venue"
},
  "geometry": {"coordinates":[-82.416805,34.930921],"type":"Point"}
}