{
  "type": "Feature",
  "properties": {
    "iso:country":"US",
    "sg:address":"130 Belcher Rd",
    "sg:city":"Spartanburg",
    "sg:classifiers":[
        {
            "category":"Professional",
            "subcategory":"Management & Consulting",
            "type":"Services"
        }
    ],
    "sg:phone":"+1 864 578 5370",
    "sg:postcode":"29316",
    "sg:province":"SC",
    "sg:tags":[
        "party",
        "planning"
    ],
    "wof:name":"Amusements By Will & Kris",
    "wof:placetype":"venue"
},
  "geometry": {"coordinates":[-82.013457,35.012674],"type":"Point"}
}