{
  "type": "Feature",
  "properties": {
    "iso:country":"US",
    "sg:address":"195 Abbott Ln",
    "sg:city":"Spartanburg",
    "sg:classifiers":[
        {
            "category":"Manufacturing",
            "subcategory":"Paper Products",
            "type":"Manufacturing & Wholesale Goods"
        }
    ],
    "sg:phone":"+1 864 579 2280",
    "sg:postcode":"29307",
    "sg:province":"SC",
    "sg:tags":[
        "packaging",
        "material"
    ],
    "sg:website":"www.dotpack.com",
    "wof:name":"Dot Packaging Group",
    "wof:placetype":"venue"
},
  "geometry": {"coordinates":[-81.875525,35.026428],"type":"Point"}
}