{
  "type": "Feature",
  "properties": {
    "iso:country":"US",
    "sg:address":"3600 Locust Hill Rd",
    "sg:city":"Taylors",
    "sg:classifiers":[
        {
            "category":"Freight",
            "type":"Transportation"
        }
    ],
    "sg:phone":"+1 864 895 7637",
    "sg:postcode":"29687",
    "sg:province":"SC",
    "sg:tags":[
        "operator",
        "local",
        "trucking"
    ],
    "wof:name":"Sal Trucking L L C",
    "wof:placetype":"venue"
},
  "geometry": {"coordinates":[-82.329982,34.974205],"type":"Point"}
}