{
  "type": "Feature",
  "properties": {
    "iso:country":"US",
    "sg:address":"2812 Standing Springs Rd",
    "sg:city":"Simpsonville",
    "sg:classifiers":[
        {
            "category":"Organizations",
            "subcategory":"Professional Association",
            "type":"Services"
        }
    ],
    "sg:phone":"+1 864 299 1100",
    "sg:postcode":"29680",
    "sg:province":"SC",
    "sg:tags":[
        "computer",
        "electronic",
        "mfg"
    ],
    "wof:name":"Packetpub",
    "wof:placetype":"venue"
},
  "geometry": {"coordinates":[-82.326047,34.723404],"type":"Point"}
}