{
  "type": "Feature",
  "properties": {
    "iso:country":"US",
    "sg:address":"314 Tribble St",
    "sg:city":"Anderson",
    "sg:classifiers":[
        {
            "category":"Government",
            "subcategory":"Office",
            "type":"Public Place"
        }
    ],
    "sg:phone":"+1 864 260 6347",
    "sg:postcode":"29625",
    "sg:province":"SC",
    "sg:tags":[
        "govt",
        "city"
    ],
    "wof:name":"Anderson Electric Utilities",
    "wof:placetype":"venue"
},
  "geometry": {"coordinates":[-82.654974,34.506788],"type":"Point"}
}