{
  "type": "Feature",
  "properties": {
    "iso:country":"US",
    "sg:address":"726 Amberly Xing",
    "sg:city":"Fort Mill",
    "sg:classifiers":[
        {
            "category":"Building & Trades",
            "subcategory":"Construction",
            "type":"Services"
        }
    ],
    "sg:phone":"+1 704 201 8538",
    "sg:postcode":"29708",
    "sg:province":"SC",
    "sg:tags":[
        "hanging",
        "contractor"
    ],
    "wof:name":"A C Paint Contracting",
    "wof:placetype":"venue"
},
  "geometry": {"coordinates":[-80.952488,35.076475],"type":"Point"}
}