{
  "type": "Feature",
  "properties": {
    "addr:full":"3300 Highway 17 S North Myrtle Beach SC 29582",
    "addr:housenumber":"3300",
    "addr:postcode":"29582",
    "addr:street":"Highway 17 S",
    "iso:country":"US",
    "sg:address":"3300 Highway 17 S",
    "sg:city":"North Myrtle Beach",
    "sg:classifiers":[
        {
            "category":"Restaurant",
            "type":"Food & Drink"
        }
    ],
    "sg:menulink":"http://www.allmenus.com/sc/little-river/129292-subway/menu/",
    "sg:phone":"+1 843 361 8664",
    "sg:postcode":"29582",
    "sg:province":"SC",
    "sg:tags":[
        "american",
        "sandwich"
    ],
    "wof:name":"Subway",
    "wof:placetype":"venue"
},
  "geometry": {"coordinates":[-78.721896,33.804643],"type":"Point"}
}