{
  "type": "Feature",
  "properties": {
    "iso:country":"US",
    "sg:address":"209 E Main St",
    "sg:city":"Clinton",
    "sg:classifiers":[
        {
            "category":"Shopping",
            "subcategory":"Used Merchandise",
            "type":"Retail Goods"
        }
    ],
    "sg:phone":"+1 864 833 7670",
    "sg:postcode":"29325",
    "sg:province":"SC",
    "sg:tags":[
        "shop",
        "thrift"
    ],
    "wof:name":"Open Door Variety Shop",
    "wof:placetype":"venue"
},
  "geometry": {"coordinates":[-81.878919,34.473087],"type":"Point"}
}