{
  "type": "Feature",
  "properties": {
    "addr:full":"128 Old Camden Monroe Hwy Lancaster SC 29720",
    "addr:housenumber":"128",
    "addr:postcode":"29720",
    "addr:street":"Old Camden Monroe Hwy",
    "iso:country":"US",
    "sg:address":"128 Old Camden Monroe Hwy",
    "sg:city":"Lancaster",
    "sg:classifiers":[
        {
            "category":"Manufacturing",
            "subcategory":"Electronics",
            "type":"Manufacturing & Wholesale Goods"
        }
    ],
    "sg:phone":"+1 803 416 8326",
    "sg:postcode":"29720",
    "sg:province":"SC",
    "sg:tags":[
        "coil",
        "transformer",
        "electronic"
    ],
    "wof:name":"Thermal Electric Co",
    "wof:placetype":"venue"
},
  "geometry": {"coordinates":[-80.541991,34.752953],"type":"Point"}
}