{
  "type": "Feature",
  "properties": {
    "iso:country":"US",
    "sg:address":"510 Mountain View Dr",
    "sg:city":"Seneca",
    "sg:classifiers":[
        {
            "category":"Real Estate",
            "subcategory":"Real Estate Agent",
            "type":"Services"
        }
    ],
    "sg:phone":"+1 864 886 0843",
    "sg:postcode":"29672",
    "sg:province":"SC",
    "wof:name":"Water Links Property Group",
    "wof:placetype":"venue"
},
  "geometry": {"coordinates":[-82.974301,34.695043],"type":"Point"}
}