{
  "type": "Feature",
  "properties": {
    "addr:full":"352 Spring Park Rd Marietta SC 29661",
    "addr:housenumber":"352",
    "addr:postcode":"29661",
    "addr:street":"Spring Park Rd",
    "iso:country":"US",
    "sg:address":"352 Spring Park Rd",
    "sg:city":"Marietta",
    "sg:classifiers":[
        {
            "category":"Organizations",
            "subcategory":"Professional Association",
            "type":"Services"
        }
    ],
    "sg:phone":"+1 864 836 5849",
    "sg:postcode":"29661",
    "sg:province":"SC",
    "wof:name":"Valley Of Youth Inc",
    "wof:placetype":"venue"
},
  "geometry": {"coordinates":[-82.508308,35.053663],"type":"Point"}
}