{
  "type": "Feature",
  "properties": {
    "iso:country":"US",
    "sg:address":"4017 Lester Dr",
    "sg:city":"Columbia",
    "sg:classifiers":[
        {
            "category":"Real Estate",
            "subcategory":"Real Estate Operator",
            "type":"Services"
        }
    ],
    "sg:phone":"+1 803 735 0842",
    "sg:postcode":"29203",
    "sg:province":"SC",
    "sg:tags":[
        "apartment"
    ],
    "wof:name":"Bayberry Mews Apartments",
    "wof:placetype":"venue"
},
  "geometry": {"coordinates":[-81.01697,34.040244],"type":"Point"}
}