{
  "type": "Feature",
  "properties": {
    "iso:country":"US",
    "sg:address":"101 Ridge St",
    "sg:city":"St George",
    "sg:classifiers":[
        {
            "category":"Government",
            "subcategory":"Court House",
            "type":"Public Place"
        }
    ],
    "sg:phone":"+1 843 563 0130",
    "sg:postcode":"29477",
    "sg:province":"SC",
    "sg:tags":[
        "county"
    ],
    "wof:name":"Magistrate Court",
    "wof:placetype":"venue"
},
  "geometry": {"coordinates":[-80.576753,33.185279],"type":"Point"}
}