{
  "type": "Feature",
  "properties": {
    "iso:country":"US",
    "sg:address":"402 Knox St",
    "sg:city":"Clover",
    "sg:classifiers":[
        {
            "category":"Education",
            "subcategory":"School",
            "type":"Public Place"
        }
    ],
    "sg:phone":"+1 803 222 8079",
    "sg:postcode":"29710",
    "sg:province":"SC",
    "wof:name":"Clover Adult Education",
    "wof:placetype":"venue"
},
  "geometry": {"coordinates":[-81.223546,35.106069],"type":"Point"}
}