{
  "type": "Feature",
  "properties": {
    "iso:country":"US",
    "sg:address":"10125 N Hwy 17",
    "sg:city":"Mc Clellanville",
    "sg:classifiers":[
        {
            "category":"Home & Garden",
            "subcategory":"Furniture",
            "type":"Retail Goods"
        }
    ],
    "sg:phone":"+1 843 887 3984",
    "sg:postcode":"29458",
    "sg:province":"SC",
    "wof:name":"Classic Furniture",
    "wof:placetype":"venue"
},
  "geometry": {"coordinates":[-79.47322699999999,33.096743],"type":"Point"}
}