{
  "type": "Feature",
  "properties": {
    "iso:country":"US",
    "sg:address":"124 E Main St",
    "sg:city":"Walhalla",
    "sg:classifiers":[
        {
            "category":"Shopping",
            "type":"Retail Goods"
        }
    ],
    "sg:phone":"+1 864 718 7171",
    "sg:postcode":"29691",
    "sg:province":"SC",
    "sg:tags":[
        "art",
        "gallery",
        "merchandise",
        "dealer"
    ],
    "wof:name":"Farm House Gallery",
    "wof:placetype":"venue"
},
  "geometry": {"coordinates":[-83.065392,34.764902],"type":"Point"}
}