{
  "type": "Feature",
  "properties": {
    "addr:full":"2900 Opry House Rd Iva SC 29684",
    "addr:housenumber":"2900",
    "addr:postcode":"29684",
    "addr:street":"Opry House Rd",
    "iso:country":"US",
    "sg:address":"2900 Opry House Rd",
    "sg:city":"Iva",
    "sg:classifiers":[
        {
            "category":"Utilities",
            "subcategory":"Electric",
            "type":"Services"
        }
    ],
    "sg:phone":"+1 864 352 6110",
    "sg:postcode":"29684",
    "sg:province":"SC",
    "sg:tags":[
        "company"
    ],
    "wof:name":"Santee Cooper",
    "wof:placetype":"venue"
},
  "geometry": {"coordinates":[-82.76854299999999,34.342627],"type":"Point"}
}