{
  "type": "Feature",
  "properties": {
    "addr:full":"549 Saint Andrews Rd Columbia SC 29210",
    "addr:housenumber":"549",
    "addr:postcode":"29210",
    "addr:street":"Saint Andrews Rd",
    "iso:country":"US",
    "sg:address":"549 Saint Andrews Rd",
    "sg:city":"Columbia",
    "sg:classifiers":[
        {
            "category":"Shopping",
            "subcategory":"Department Store",
            "type":"Retail Goods"
        }
    ],
    "sg:phone":"+1 803 551 5613",
    "sg:postcode":"29210",
    "sg:province":"SC",
    "sg:tags":[
        "mail",
        "house"
    ],
    "wof:name":"Close-Out Co",
    "wof:placetype":"venue"
},
  "geometry": {"coordinates":[-81.128907,34.045419],"type":"Point"}
}