{
  "type": "Feature",
  "properties": {
    "iso:country":"US",
    "sg:address":"950 W Main St",
    "sg:city":"Rock Hill",
    "sg:classifiers":[
        {
            "category":"Organizations",
            "subcategory":"Religious Organization",
            "type":"Services"
        }
    ],
    "sg:phone":"+1 803 328 1745",
    "sg:postcode":"29730",
    "sg:province":"SC",
    "sg:tags":[
        "church"
    ],
    "wof:name":"Adams Chapel AME Church",
    "wof:placetype":"venue"
},
  "geometry": {"coordinates":[-81.041676,34.935379],"type":"Point"}
}