{
  "type": "Feature",
  "properties": {
    "iso:country":"US",
    "sg:address":"5101 Ashley Phosphate Rd",
    "sg:city":"North Charleston",
    "sg:classifiers":[
        {
            "category":"Personal",
            "subcategory":"Beauty Salon",
            "type":"Services"
        }
    ],
    "sg:phone":"+1 843 767 7424",
    "sg:postcode":"29418",
    "sg:province":"SC",
    "sg:tags":[
        "manicuring"
    ],
    "wof:name":"Shear Reflections",
    "wof:placetype":"venue"
},
  "geometry": {"coordinates":[-80.102377,32.918129],"type":"Point"}
}