{
  "type": "Feature",
  "properties": {
    "addr:full":"4884 Sunset Blvd Lexington SC 29072",
    "addr:housenumber":"4884",
    "addr:postcode":"29072",
    "addr:street":"Sunset Blvd",
    "iso:country":"US",
    "sg:address":"4884 Sunset Blvd",
    "sg:city":"Lexington",
    "sg:classifiers":[
        {
            "category":"Professional",
            "subcategory":"Business Services",
            "type":"Services"
        }
    ],
    "sg:phone":"+1 803 996 1223",
    "sg:postcode":"29072",
    "sg:province":"SC",
    "sg:tags":[
        "water",
        "treatment"
    ],
    "wof:name":"Barker Filtration",
    "wof:placetype":"venue"
},
  "geometry": {"coordinates":[-81.18167699999999,34.012399],"type":"Point"}
}