{
  "type": "Feature",
  "properties": {
    "iso:country":"US",
    "sg:address":"450 Persimmon Fork Rd",
    "sg:city":"Blythewood",
    "sg:classifiers":[
        {
            "category":"Farming",
            "subcategory":"Farm",
            "type":"Manufacturing & Wholesale Goods"
        }
    ],
    "sg:phone":"+1 803 786 7333",
    "sg:postcode":"29016",
    "sg:province":"SC",
    "sg:tags":[
        "crop",
        "animal",
        "general"
    ],
    "sg:website":"www.middlefieldfarm.com",
    "wof:name":"Middlefield Farm",
    "wof:placetype":"venue"
},
  "geometry": {"coordinates":[-81.02557400000001,34.235909],"type":"Point"}
}