{
  "type": "Feature",
  "properties": {
    "addr:full":"5828 Brothers Hill Rd Myrtle Beach SC 29588",
    "addr:housenumber":"5828",
    "addr:postcode":"29588",
    "addr:street":"Brothers Hill Rd",
    "iso:country":"US",
    "sg:address":"5828 Brothers Hill Rd",
    "sg:city":"Myrtle Beach",
    "sg:classifiers":[
        {
            "category":"Building & Trades",
            "subcategory":"Landscaping Services",
            "type":"Services"
        }
    ],
    "sg:phone":"+1 843 293 5536",
    "sg:postcode":"29588",
    "sg:province":"SC",
    "sg:tags":[
        "landscape"
    ],
    "wof:name":"Sprouses Landscaping Inc",
    "wof:placetype":"venue"
},
  "geometry": {"coordinates":[-79.03112900000001,33.707305],"type":"Point"}
}