{
  "type": "Feature",
  "properties": {
    "addr:full":"3526 Dufford St Newberry SC 29108",
    "addr:housenumber":"3526",
    "addr:postcode":"29108",
    "addr:street":"Dufford St",
    "iso:country":"US",
    "sg:address":"3526 Dufford St",
    "sg:city":"Newberry",
    "sg:classifiers":[
        {
            "category":"Social Services",
            "subcategory":"Child Care",
            "type":"Services"
        }
    ],
    "sg:phone":"+1 803 276 9900",
    "sg:postcode":"29108",
    "sg:province":"SC",
    "wof:name":"Triangle Daycare II",
    "wof:placetype":"venue"
},
  "geometry": {"coordinates":[-81.635074,34.300371],"type":"Point"}
}