{
  "type": "Feature",
  "properties": {
    "addr:full":"151 Mitchell Rd Greenville SC 29615",
    "addr:housenumber":"151",
    "addr:postcode":"29615",
    "addr:street":"Mitchell Rd",
    "iso:country":"US",
    "sg:address":"151 Mitchell Rd",
    "sg:city":"Greenville",
    "sg:classifiers":[
        {
            "category":"Insurance",
            "subcategory":"Hazard Insurance",
            "type":"Services"
        }
    ],
    "sg:phone":"+1 864 235 2263",
    "sg:postcode":"29615",
    "sg:province":"SC",
    "sg:tags":[
        "bond"
    ],
    "wof:name":"Forrester Bonding Co",
    "wof:placetype":"venue"
},
  "geometry": {"coordinates":[-82.317644,34.870519],"type":"Point"}
}