{
  "type": "Feature",
  "properties": {
    "iso:country":"US",
    "sg:address":"553 Parris Island Gateway",
    "sg:city":"Beaufort",
    "sg:classifiers":[
        {
            "category":"Professional",
            "type":"Services"
        }
    ],
    "sg:phone":"+1 843 228 3810",
    "sg:postcode":"29906",
    "sg:province":"SC",
    "sg:tags":[
        "establishment"
    ],
    "wof:name":"Blencoe JA Cpl",
    "wof:placetype":"venue"
},
  "geometry": {"coordinates":[-80.739785,32.396823],"type":"Point"}
}