{
  "type": "Feature",
  "properties": {
    "iso:country":"US",
    "sg:address":"1109 Church St",
    "sg:city":"Georgetown",
    "sg:classifiers":[
        {
            "category":"Insurance",
            "subcategory":"Insurance Agent",
            "type":"Services"
        }
    ],
    "sg:phone":"+1 843 527 2493",
    "sg:postcode":"29440",
    "sg:province":"SC",
    "wof:name":"Atlantic Coast Life Insurance",
    "wof:placetype":"venue"
},
  "geometry": {"coordinates":[-79.28403299999999,33.374322],"type":"Point"}
}