{
  "type": "Feature",
  "properties": {
    "iso:country":"US",
    "sg:address":"102 Wappoo Creek Dr",
    "sg:city":"Charleston",
    "sg:classifiers":[
        {
            "category":"Real Estate",
            "subcategory":"Architect",
            "type":"Services"
        }
    ],
    "sg:phone":"+1 843 795 3464",
    "sg:postcode":"29412",
    "sg:province":"SC",
    "wof:name":"J Harrell Gandy & Assoc",
    "wof:placetype":"venue"
},
  "geometry": {"coordinates":[-79.97722400000001,32.762704],"type":"Point"}
}