{
  "type": "Feature",
  "properties": {
    "iso:country":"US",
    "sg:address":"2669 Landing Pointe Dr",
    "sg:city":"Clover",
    "sg:classifiers":[
        {
            "category":"Wholesale",
            "subcategory":"Machinery & Supplies",
            "type":"Manufacturing & Wholesale Goods"
        },
        {
            "category":"Wholesale",
            "subcategory":"Durable Goods & Equipment",
            "type":"Manufacturing & Wholesale Goods"
        }
    ],
    "sg:phone":"+1 803 831 1516",
    "sg:postcode":"29710",
    "sg:province":"SC",
    "sg:tags":[
        "industrial",
        "laser"
    ],
    "wof:name":"Lasercare Inc",
    "wof:placetype":"venue"
},
  "geometry": {"coordinates":[-81.077102,35.122732],"type":"Point"}
}