{
  "type": "Feature",
  "properties": {
    "iso:country":"US",
    "sg:address":"3574 Northgate Rd",
    "sg:city":"Myrtle Beach",
    "sg:classifiers":[
        {
            "category":"Personal",
            "subcategory":"Barber",
            "type":"Services"
        }
    ],
    "sg:phone":"+1 843 293 2721",
    "sg:postcode":"29588",
    "sg:province":"SC",
    "wof:name":"Ben's Barber Shop",
    "wof:placetype":"venue"
},
  "geometry": {"coordinates":[-79.090454,34.118865],"type":"Point"}
}