{
  "type": "Feature",
  "properties": {
    "iso:country":"US",
    "sg:address":"162 Old Leonard Rd",
    "sg:city":"Woodruff",
    "sg:classifiers":[
        {
            "category":"Government",
            "subcategory":"Court House",
            "type":"Public Place"
        }
    ],
    "sg:phone":"+1 864 433 9223",
    "sg:postcode":"29388",
    "sg:province":"SC",
    "sg:tags":[
        "county"
    ],
    "wof:name":"Reidville Magistrate's Office",
    "wof:placetype":"venue"
},
  "geometry": {"coordinates":[-82.109129,34.839146],"type":"Point"}
}