{
  "type": "Feature",
  "properties": {
    "iso:country":"US",
    "sg:address":"8 Brynhurst Ct",
    "sg:city":"Greenville",
    "sg:classifiers":[
        {
            "category":"Shopping",
            "subcategory":"Gifts & Souvenirs",
            "type":"Retail Goods"
        }
    ],
    "sg:phone":"+1 864 288 6749",
    "sg:postcode":"29615",
    "sg:province":"SC",
    "wof:name":"Party Land",
    "wof:placetype":"venue"
},
  "geometry": {"coordinates":[-82.29682,34.857215],"type":"Point"}
}