{
  "type": "Feature",
  "properties": {
    "iso:country":"US",
    "sg:address":"838 S Parker Dr",
    "sg:city":"Florence",
    "sg:classifiers":[
        {
            "category":"Real Estate",
            "subcategory":"Real Estate Operator",
            "type":"Services"
        }
    ],
    "sg:phone":"+1 843 669 2246",
    "sg:postcode":"29501",
    "sg:province":"SC",
    "sg:tags":[
        "building",
        "apartment"
    ],
    "wof:name":"Habitat 2000",
    "wof:placetype":"venue"
},
  "geometry": {"coordinates":[-79.821064,34.173975],"type":"Point"}
}