{
  "type": "Feature",
  "properties": {
    "addr:full":"2092 Woodruff Rd Greenville SC 29607",
    "addr:housenumber":"2092",
    "addr:postcode":"29607",
    "addr:street":"Woodruff Rd",
    "iso:country":"US",
    "sg:address":"2092 Woodruff Rd",
    "sg:city":"Greenville",
    "sg:classifiers":[
        {
            "category":"Health Services",
            "subcategory":"Health Practitioner",
            "type":"Services"
        }
    ],
    "sg:phone":"+1 864 233 9660",
    "sg:postcode":"29607",
    "sg:province":"SC",
    "sg:tags":[
        "psychologist"
    ],
    "wof:name":"Brownell Center",
    "wof:placetype":"venue"
},
  "geometry": {"coordinates":[-82.262895,34.82031],"type":"Point"}
}