{
  "type": "Feature",
  "properties": {
    "iso:country":"US",
    "sg:address":"1116 Blanding St",
    "sg:city":"Columbia",
    "sg:classifiers":[
        {
            "category":"Professional",
            "subcategory":"Lawyer & Legal Services",
            "type":"Services"
        }
    ],
    "sg:phone":"+1 803 254 9290",
    "sg:postcode":"29201",
    "sg:province":"SC",
    "wof:name":"Jan S Strifling",
    "wof:placetype":"venue"
},
  "geometry": {"coordinates":[-81.03780399999999,34.0075],"type":"Point"}
}