{
  "type": "Feature",
  "properties": {
    "addr:full":"324 W Evans St Florence SC 29501",
    "addr:housenumber":"324",
    "addr:postcode":"29501",
    "addr:street":"W Evans St",
    "iso:country":"US",
    "sg:address":"324 W Evans St",
    "sg:city":"Florence",
    "sg:classifiers":[
        {
            "category":"Banks & Credit Unions",
            "subcategory":"Investment Brokerage",
            "type":"Services"
        }
    ],
    "sg:phone":"+1 843 669 3222",
    "sg:postcode":"29501",
    "sg:province":"SC",
    "sg:tags":[
        "stock",
        "bond"
    ],
    "wof:name":"Wachovia Securities",
    "wof:placetype":"venue"
},
  "geometry": {"coordinates":[-79.772166,34.196961],"type":"Point"}
}