{
  "type": "Feature",
  "properties": {
    "iso:country":"US",
    "sg:address":"1707 Charleston Hwy",
    "sg:city":"West Columbia",
    "sg:classifiers":[
        {
            "category":"Restaurant",
            "type":"Food & Drink"
        }
    ],
    "sg:phone":"+1 803 796 2728",
    "sg:postcode":"29169",
    "sg:province":"SC",
    "wof:name":"Ryan's Family Steakhouse of Columbia",
    "wof:placetype":"venue"
},
  "geometry": {"coordinates":[-81.077904,33.968498],"type":"Point"}
}