{
  "type": "Feature",
  "properties": {
    "addr:full":"714 Pine St Pelion SC 29123",
    "addr:housenumber":"714",
    "addr:postcode":"29123",
    "addr:street":"Pine St",
    "iso:country":"US",
    "sg:address":"714 Pine St",
    "sg:city":"Pelion",
    "sg:classifiers":[
        {
            "category":"Restaurant",
            "type":"Food & Drink"
        }
    ],
    "sg:phone":"+1 803 894 4673",
    "sg:postcode":"29123",
    "sg:province":"SC",
    "wof:name":"Buddy's Pizza & Subs",
    "wof:placetype":"venue"
},
  "geometry": {"coordinates":[-81.247021,33.763323],"type":"Point"}
}