{
  "type": "Feature",
  "properties": {
    "iso:country":"US",
    "sg:address":"4824 Edmund Hwy",
    "sg:city":"West Columbia",
    "sg:classifiers":[
        {
            "category":"Autos & Motor Vehicles",
            "subcategory":"Automobile Sales",
            "type":"Retail Goods"
        }
    ],
    "sg:phone":"+1 803 755 0553",
    "sg:postcode":"29170",
    "sg:province":"SC",
    "sg:tags":[
        "used"
    ],
    "wof:name":"Terrys Auto Sales",
    "wof:placetype":"venue"
},
  "geometry": {"coordinates":[-81.15704599999999,33.893238],"type":"Point"}
}