{
  "type": "Feature",
  "properties": {
    "iso:country":"US",
    "sg:address":"901 W Floyd Baker Blvd",
    "sg:city":"Gaffney",
    "sg:classifiers":[
        {
            "category":"Food & Beverages",
            "subcategory":"Groceries & Convenience Stores",
            "type":"Retail Goods"
        }
    ],
    "sg:phone":"+1 864 489 0107",
    "sg:postcode":"29341",
    "sg:province":"SC",
    "wof:name":"Peeler's Petro Plus",
    "wof:placetype":"venue"
},
  "geometry": {"coordinates":[-81.656252,35.081069],"type":"Point"}
}