{
  "type": "Feature",
  "properties": {
    "iso:country":"US",
    "sg:address":"430 Oak Grove Rd",
    "sg:city":"Spartanburg",
    "sg:classifiers":[
        {
            "category":"Shopping",
            "subcategory":"Computers & Home Electronics",
            "type":"Retail Goods"
        }
    ],
    "sg:phone":"+1 864 587 1404",
    "sg:postcode":"29301",
    "sg:province":"SC",
    "wof:name":"Phillips Communications",
    "wof:placetype":"venue"
},
  "geometry": {"coordinates":[-82.001728,34.922816],"type":"Point"}
}