{
  "type": "Feature",
  "properties": {
    "iso:country":"US",
    "sg:address":"109 Park Ave",
    "sg:city":"Brevard",
    "sg:classifiers":[
        {
            "category":"Manufacturing",
            "subcategory":"Tools & Machinery",
            "type":"Manufacturing & Wholesale Goods"
        }
    ],
    "sg:phone":"+1 828 883 8908",
    "sg:postcode":"28712",
    "sg:province":"SC",
    "sg:tags":[
        "devices"
    ],
    "wof:name":"Thel-Mar Co",
    "wof:placetype":"venue"
},
  "geometry": {"coordinates":[-82.723439,35.232105],"type":"Point"}
}