{
  "type": "Feature",
  "properties": {
    "iso:country":"US",
    "sg:address":"221 N Longstreet St",
    "sg:city":"Kingstree",
    "sg:classifiers":[
        {
            "category":"Wholesale",
            "subcategory":"Auto Parts",
            "type":"Manufacturing & Wholesale Goods"
        }
    ],
    "sg:phone":"+1 843 354 5567",
    "sg:postcode":"29556",
    "sg:province":"SC",
    "sg:tags":[
        "supply"
    ],
    "wof:name":"NAPA Auto Parts",
    "wof:placetype":"venue"
},
  "geometry": {"coordinates":[-79.834242,33.665485],"type":"Point"}
}