{
  "type": "Feature",
  "properties": {
    "iso:country":"US",
    "sg:address":"10035 New Cut Rd",
    "sg:city":"Campobello",
    "sg:classifiers":[
        {
            "category":"Recreation",
            "type":"Entertainment"
        }
    ],
    "sg:phone":"+1 864 468 4307",
    "sg:postcode":"29322",
    "sg:province":"SC",
    "sg:tags":[
        "stable"
    ],
    "wof:name":"Motlow Creek Equestrian",
    "wof:placetype":"venue"
},
  "geometry": {"coordinates":[-82.201349,35.093416],"type":"Point"}
}