{
  "type": "Feature",
  "properties": {
    "iso:country":"US",
    "sg:address":"420 W Surfwind Dr",
    "sg:city":"Murrells Inlet",
    "sg:classifiers":[
        {
            "category":"Real Estate",
            "subcategory":"Real Estate Agent",
            "type":"Services"
        }
    ],
    "sg:phone":"+1 843 902 8383",
    "sg:postcode":"29576",
    "sg:province":"SC",
    "wof:name":"Real Estate Beaches",
    "wof:placetype":"venue"
},
  "geometry": {"coordinates":[-79.01375899999999,33.576383],"type":"Point"}
}