{
  "type": "Feature",
  "properties": {
    "addr:full":"13 Seagrass Ln Isle Of Palms SC 29451",
    "addr:housenumber":"13",
    "addr:postcode":"29451",
    "addr:street":"Seagrass Ln",
    "iso:country":"US",
    "sg:address":"13 Seagrass Ln",
    "sg:city":"Isle Of Palms",
    "sg:classifiers":[
        {
            "category":"Real Estate",
            "subcategory":"Real Estate Agent",
            "type":"Services"
        }
    ],
    "sg:phone":"+1 843 814 7308",
    "sg:postcode":"29451",
    "sg:province":"SC",
    "wof:name":"Ht Laboratories Inc",
    "wof:placetype":"venue"
},
  "geometry": {"coordinates":[-79.72986400000001,32.81473],"type":"Point"}
}