{
  "type": "Feature",
  "properties": {
    "iso:country":"US",
    "sg:address":"1605 W Palmetto St",
    "sg:city":"Florence",
    "sg:classifiers":[
        {
            "category":"Shopping",
            "subcategory":"Clothing, Apparel, & Fashions",
            "type":"Retail Goods"
        }
    ],
    "sg:phone":"+1 843 667 0101",
    "sg:postcode":"29501",
    "sg:province":"SC",
    "sg:tags":[
        "infant",
        "wear"
    ],
    "wof:name":"Kids Land Plus",
    "wof:placetype":"venue"
},
  "geometry": {"coordinates":[-79.79682699999999,34.190621],"type":"Point"}
}