{
  "type": "Feature",
  "properties": {
    "iso:country":"US",
    "sg:address":"1301 Richland St",
    "sg:city":"Columbia",
    "sg:classifiers":[
        {
            "category":"Organizations",
            "subcategory":"Religious Organization",
            "type":"Services"
        }
    ],
    "sg:phone":"+1 803 765 9430",
    "sg:postcode":"29201",
    "sg:province":"SC",
    "sg:tags":[
        "church"
    ],
    "sg:website":"www.ebenezerlutheran.org",
    "wof:name":"Ebenezer Lutheran Church",
    "wof:placetype":"venue"
},
  "geometry": {"coordinates":[-81.034483,34.011618],"type":"Point"}
}