{
  "type": "Feature",
  "properties": {
    "addr:full":"2434 Main St Elgin SC 29045",
    "addr:housenumber":"2434",
    "addr:postcode":"29045",
    "addr:street":"Main St",
    "iso:country":"US",
    "sg:address":"2434 Main St",
    "sg:city":"Elgin",
    "sg:classifiers":[
        {
            "category":"Shopping",
            "type":"Retail Goods"
        }
    ],
    "sg:phone":"+1 803 438 5645",
    "sg:postcode":"29045",
    "sg:province":"SC",
    "sg:tags":[
        "merchandise"
    ],
    "wof:name":"Palmetto Trophy",
    "wof:placetype":"venue"
},
  "geometry": {"coordinates":[-80.787049,34.172793],"type":"Point"}
}