{
  "type": "Feature",
  "properties": {
    "iso:country":"US",
    "sg:address":"9967 Ocean Hwy",
    "sg:city":"Pawleys Island",
    "sg:classifiers":[
        {
            "category":"Education",
            "subcategory":"School",
            "type":"Public Place"
        }
    ],
    "sg:phone":"+1 843 237 4147",
    "sg:postcode":"29585",
    "sg:province":"SC",
    "wof:name":"Low Country Day School",
    "wof:placetype":"venue"
},
  "geometry": {"coordinates":[-79.133274,33.43551],"type":"Point"}
}