{
  "type": "Feature",
  "properties": {
    "iso:country":"US",
    "sg:address":"3725 Barkley Rd",
    "sg:city":"Sumter",
    "sg:classifiers":[
        {
            "category":"Building & Trades",
            "subcategory":"Construction",
            "type":"Services"
        }
    ],
    "sg:phone":"+1 803 481 2051",
    "sg:postcode":"29154",
    "sg:province":"SC",
    "sg:tags":[
        "lots",
        "concrete",
        "work",
        "parking"
    ],
    "wof:name":"Evans Q L Construction",
    "wof:placetype":"venue"
},
  "geometry": {"coordinates":[-80.384274,33.816713],"type":"Point"}
}