{
  "type": "Feature",
  "properties": {
    "iso:country":"US",
    "sg:address":"411 W Butler Rd",
    "sg:city":"Mauldin",
    "sg:classifiers":[
        {
            "category":"Restaurant",
            "type":"Food & Drink"
        }
    ],
    "sg:phone":"+1 864 284 9050",
    "sg:postcode":"29607",
    "sg:province":"SC",
    "wof:name":"Olive Tree Pizza Grill",
    "wof:placetype":"venue"
},
  "geometry": {"coordinates":[-82.316934,34.775773],"type":"Point"}
}