{
  "type": "Feature",
  "properties": {
    "iso:country":"US",
    "sg:address":"122 Kay Ln",
    "sg:city":"Summerville",
    "sg:classifiers":[
        {
            "category":"Retail",
            "subcategory":"Veterinary Services",
            "type":"Services"
        }
    ],
    "sg:phone":"+1 843 875 5133",
    "sg:postcode":"29483",
    "sg:province":"SC",
    "wof:name":"Shambley Equine Clinic",
    "wof:placetype":"venue"
},
  "geometry": {"coordinates":[-80.222999,32.97492],"type":"Point"}
}