{
  "type": "Feature",
  "properties": {
    "addr:full":"1023 E Carolina Ave Hartsville SC 29550",
    "addr:housenumber":"1023",
    "addr:postcode":"29550",
    "addr:street":"E Carolina Ave",
    "iso:country":"US",
    "sg:address":"1023 E Carolina Ave",
    "sg:city":"Hartsville",
    "sg:classifiers":[
        {
            "category":"Professional",
            "subcategory":"Lawyer & Legal Services",
            "type":"Services"
        }
    ],
    "sg:phone":"+1 843 332 4709",
    "sg:postcode":"29550",
    "sg:province":"SC",
    "sg:tags":[
        "attorney"
    ],
    "wof:name":"Carl A Saleeby Law Office",
    "wof:placetype":"venue"
},
  "geometry": {"coordinates":[-80.051541,34.380268],"type":"Point"}
}