{
  "type": "Feature",
  "properties": {
    "iso:country":"US",
    "sg:address":"1055 Johnnie Dodds Blvd",
    "sg:city":"Mount Pleasant",
    "sg:classifiers":[
        {
            "category":"Shopping",
            "subcategory":"Clothing, Apparel, & Fashions",
            "type":"Retail Goods"
        }
    ],
    "sg:phone":"+1 843 971 1477",
    "sg:postcode":"29464",
    "sg:province":"SC",
    "wof:name":"Bridal House The",
    "wof:placetype":"venue"
},
  "geometry": {"coordinates":[-79.858058,32.812558],"type":"Point"}
}