{
  "type": "Feature",
  "properties": {
    "iso:country":"US",
    "sg:address":"2040 Augusta Rd",
    "sg:city":"West Columbia",
    "sg:classifiers":[
        {
            "category":"Home & Garden",
            "subcategory":"Carpets & Floor Coverings",
            "type":"Retail Goods"
        }
    ],
    "sg:phone":"+1 803 796 7114",
    "sg:postcode":"29169",
    "sg:province":"SC",
    "sg:tags":[
        "carpeting"
    ],
    "wof:name":"Eddie Shumpert's Carpets & Floor Covering",
    "wof:placetype":"venue"
},
  "geometry": {"coordinates":[-81.092102,33.9846],"type":"Point"}
}