{
  "type": "Feature",
  "properties": {
    "addr:full":"262 S Cherry Rd Rock Hill SC 29732",
    "addr:housenumber":"262",
    "addr:postcode":"29732",
    "addr:street":"S Cherry Rd",
    "iso:country":"US",
    "sg:address":"262 S Cherry Rd",
    "sg:city":"Rock Hill",
    "sg:classifiers":[
        {
            "category":"Shopping",
            "subcategory":"Used Merchandise",
            "type":"Retail Goods"
        }
    ],
    "sg:phone":"+1 803 327 2858",
    "sg:postcode":"29732",
    "sg:province":"SC",
    "wof:name":"Teagues Pawn Shop",
    "wof:placetype":"venue"
},
  "geometry": {"coordinates":[-81.040688,34.938556],"type":"Point"}
}