{
  "type": "Feature",
  "properties": {
    "iso:country":"US",
    "sg:address":"715 N Main St",
    "sg:city":"Anderson",
    "sg:classifiers":[
        {
            "category":"Banks & Credit Unions",
            "subcategory":"Bank",
            "type":"Services"
        }
    ],
    "sg:phone":"+1 864 882 6788",
    "sg:postcode":"29621",
    "sg:province":"SC",
    "sg:tags":[
        "loan",
        "real estate"
    ],
    "wof:name":"Family First Mortgage",
    "wof:placetype":"venue"
},
  "geometry": {"coordinates":[-82.651679,34.509791],"type":"Point"}
}