{
  "type": "Feature",
  "properties": {
    "iso:country":"US",
    "sg:address":"130 Varnfield Dr",
    "sg:city":"Summerville",
    "sg:classifiers":[
        {
            "category":"Home & Garden",
            "subcategory":"Furniture",
            "type":"Retail Goods"
        }
    ],
    "sg:phone":"+1 843 695 0400",
    "sg:postcode":"29483",
    "sg:province":"SC",
    "sg:tags":[
        "cabinet"
    ],
    "wof:name":"Simpson's Cabinets",
    "wof:placetype":"venue"
},
  "geometry": {"coordinates":[-80.165152,33.036625],"type":"Point"}
}