{
  "type": "Feature",
  "properties": {
    "iso:country":"US",
    "sg:address":"10177 N Kings Hwy",
    "sg:city":"Myrtle Beach",
    "sg:classifiers":[
        {
            "category":"Shopping",
            "subcategory":"Jewelry",
            "type":"Retail Goods"
        }
    ],
    "sg:phone":"+1 843 272 2603",
    "sg:postcode":"29572",
    "sg:province":"SC",
    "sg:tags":[
        "jeweler"
    ],
    "sg:website":"www.friedmans.com",
    "wof:name":"Friedman's",
    "wof:placetype":"venue"
},
  "geometry": {"coordinates":[-78.764898,33.79064],"type":"Point"}
}