{
  "type": "Feature",
  "properties": {
    "addr:full":"1220 Laurens Rd Greenville SC 29607",
    "addr:housenumber":"1220",
    "addr:postcode":"29607",
    "addr:street":"Laurens Rd",
    "iso:country":"US",
    "sg:address":"1220 Laurens Rd",
    "sg:city":"Greenville",
    "sg:classifiers":[
        {
            "category":"Restaurant",
            "type":"Food & Drink"
        }
    ],
    "sg:phone":"+1 864 255 9970",
    "sg:postcode":"29607",
    "sg:province":"SC",
    "wof:name":"Catfish City",
    "wof:placetype":"venue"
},
  "geometry": {"coordinates":[-82.365037,34.844784],"type":"Point"}
}