{
  "type": "Feature",
  "properties": {
    "iso:country":"US",
    "sg:address":"836 Woods Crossing Rd",
    "sg:city":"Greenville",
    "sg:classifiers":[
        {
            "category":"Shopping",
            "subcategory":"Clothing, Apparel, & Fashions",
            "type":"Retail Goods"
        }
    ],
    "sg:phone":"+1 864 234 9940",
    "sg:postcode":"29607",
    "sg:province":"SC",
    "wof:name":"Urban Brands",
    "wof:placetype":"venue"
},
  "geometry": {"coordinates":[-82.336378,34.848318],"type":"Point"}
}