{
  "type": "Feature",
  "properties": {
    "addr:full":"2813 Devine St Columbia SC 29205",
    "addr:housenumber":"2813",
    "addr:postcode":"29205",
    "addr:street":"Devine St",
    "iso:country":"US",
    "sg:address":"2813 Devine St",
    "sg:city":"Columbia",
    "sg:classifiers":[
        {
            "category":"Personal",
            "subcategory":"Barber",
            "type":"Services"
        }
    ],
    "sg:phone":"+1 803 252 9333",
    "sg:postcode":"29205",
    "sg:province":"SC",
    "wof:name":"Terri Murphy",
    "wof:placetype":"venue"
},
  "geometry": {"coordinates":[-81.00135299999999,33.998062],"type":"Point"}
}