{
  "type": "Feature",
  "properties": {
    "iso:country":"US",
    "sg:address":"347 Alverson Rd",
    "sg:city":"Inman",
    "sg:classifiers":[
        {
            "category":"Building & Trades",
            "subcategory":"Construction",
            "type":"Services"
        }
    ],
    "sg:phone":"+1 864 304 3023",
    "sg:postcode":"29349",
    "sg:province":"SC",
    "sg:tags":[
        "house"
    ],
    "wof:name":"Miller Lonnie Construction LLC",
    "wof:placetype":"venue"
},
  "geometry": {"coordinates":[-81.98956099999999,35.151397],"type":"Point"}
}