{
  "type": "Feature",
  "properties": {
    "addr:full":"1200 Stillwater Dr Seneca SC 29672",
    "addr:housenumber":"1200",
    "addr:postcode":"29672",
    "addr:street":"Stillwater Dr",
    "iso:country":"US",
    "sg:address":"1200 Stillwater Dr",
    "sg:city":"Seneca",
    "sg:classifiers":[
        {
            "category":"Real Estate",
            "subcategory":"Developer",
            "type":"Services"
        }
    ],
    "sg:phone":"+1 864 654 9159",
    "sg:postcode":"29672",
    "sg:province":"SC",
    "wof:name":"Stillwater Property Owners",
    "wof:placetype":"venue"
},
  "geometry": {"coordinates":[-82.880606,34.709337],"type":"Point"}
}