{
  "type": "Feature",
  "properties": {
    "iso:country":"US",
    "sg:address":"2 Westbury Park Way",
    "sg:city":"Bluffton",
    "sg:classifiers":[
        {
            "category":"Banks & Credit Unions",
            "subcategory":"Financial Services",
            "type":"Services"
        }
    ],
    "sg:phone":"+1 843 815 9600",
    "sg:postcode":"29910",
    "sg:province":"SC",
    "sg:tags":[
        "investment",
        "closed"
    ],
    "wof:name":"Lighthouse Investment",
    "wof:placetype":"venue"
},
  "geometry": {"coordinates":[-80.871926,32.274684],"type":"Point"}
}