{
  "type": "Feature",
  "properties": {
    "iso:country":"US",
    "sg:address":"1211 Highway 17 N",
    "sg:city":"North Myrtle Beach",
    "sg:classifiers":[
        {
            "category":"Restaurant",
            "type":"Food & Drink"
        }
    ],
    "sg:menulink":"http://www.allmenus.com/sc/little-river/9009-hooters/menu/",
    "sg:phone":"+1 843 280 9850",
    "sg:postcode":"29582",
    "sg:province":"SC",
    "sg:tags":[
        "american",
        "wing"
    ],
    "wof:name":"Hooters",
    "wof:placetype":"venue"
},
  "geometry": {"coordinates":[-78.666713,33.839081],"type":"Point"}
}