{
  "type": "Feature",
  "properties": {
    "addr:full":"8340 Raintree Ln Nichols SC 29581",
    "addr:housenumber":"8340",
    "addr:postcode":"29581",
    "addr:street":"Raintree Ln",
    "iso:country":"US",
    "sg:address":"8340 Raintree Ln",
    "sg:city":"Nichols",
    "sg:classifiers":[
        {
            "category":"Home & Garden",
            "subcategory":"Furniture",
            "type":"Retail Goods"
        }
    ],
    "sg:phone":"+1 843 392 0785",
    "sg:postcode":"29581",
    "sg:province":"SC",
    "sg:tags":[
        "cabinet"
    ],
    "wof:name":"Tony's Custom Cabinetry",
    "wof:placetype":"venue"
},
  "geometry": {"coordinates":[-79.11003700000001,34.183704],"type":"Point"}
}