{
  "type": "Feature",
  "properties": {
    "iso:country":"US",
    "sg:address":"521 Pettit St",
    "sg:city":"Darlington",
    "sg:classifiers":[
        {
            "category":"Building & Trades",
            "subcategory":"Construction",
            "type":"Services"
        }
    ],
    "sg:phone":"+1 843 393 7522",
    "sg:postcode":"29532",
    "sg:province":"SC",
    "sg:tags":[
        "general",
        "contractor"
    ],
    "wof:name":"B & B Construction",
    "wof:placetype":"venue"
},
  "geometry": {"coordinates":[-79.88592300000001,34.302755],"type":"Point"}
}