{
  "type": "Feature",
  "properties": {
    "addr:full":"1268 Highway 9 Byp W Lancaster SC 29720",
    "addr:housenumber":"1268",
    "addr:postcode":"29720",
    "addr:street":"Highway 9 Byp W",
    "iso:country":"US",
    "sg:address":"1268 Highway 9 Byp W",
    "sg:city":"Lancaster",
    "sg:classifiers":[
        {
            "category":"Restaurant",
            "type":"Food & Drink"
        }
    ],
    "sg:menulink":"http://www.allmenus.com/sc/lancaster/85066-applebees/menu/",
    "sg:phone":"+1 803 286 7778",
    "sg:postcode":"29720",
    "sg:province":"SC",
    "sg:tags":[
        "burger",
        "american",
        "sandwich",
        "soup"
    ],
    "wof:name":"Applebee's",
    "wof:placetype":"venue"
},
  "geometry": {"coordinates":[-80.798841,34.733505],"type":"Point"}
}