{
  "type": "Feature",
  "properties": {
    "iso:country":"US",
    "sg:address":"450 E Butler Ave",
    "sg:city":"Saluda",
    "sg:classifiers":[
        {
            "category":"Building & Trades",
            "subcategory":"Landscaping Services",
            "type":"Services"
        }
    ],
    "sg:phone":"+1 864 445 9566",
    "sg:postcode":"29138",
    "sg:province":"SC",
    "sg:tags":[
        "landscape"
    ],
    "wof:name":"Dana & James Story",
    "wof:placetype":"venue"
},
  "geometry": {"coordinates":[-81.765367,34.004085],"type":"Point"}
}