{
  "type": "Feature",
  "properties": {
    "iso:country":"US",
    "sg:address":"702 Mill St",
    "sg:city":"Marion",
    "sg:classifiers":[
        {
            "category":"Organizations",
            "subcategory":"Religious Organization",
            "type":"Services"
        }
    ],
    "sg:phone":"+1 843 423 2221",
    "sg:postcode":"29571",
    "sg:province":"SC",
    "sg:tags":[
        "church"
    ],
    "wof:name":"St Johns AME Church",
    "wof:placetype":"venue"
},
  "geometry": {"coordinates":[-79.40467599999999,34.17028],"type":"Point"}
}