{
  "type": "Feature",
  "properties": {
    "iso:country":"US",
    "sg:address":"802 36th Ave S",
    "sg:city":"North Myrtle Bch",
    "sg:classifiers":[
        {
            "category":"Professional",
            "subcategory":"Business Services",
            "type":"Services"
        }
    ],
    "sg:phone":"+1 843 361 1616",
    "sg:postcode":"29582",
    "sg:province":"SC",
    "sg:tags":[
        "interior",
        "consultant",
        "design",
        "decorator"
    ],
    "sg:website":"www.jandkhomefurnishings.com",
    "wof:name":"J & K Home Furnishings",
    "wof:placetype":"venue"
},
  "geometry": {"coordinates":[-78.724313,33.803422],"type":"Point"}
}