{
  "type": "Feature",
  "properties": {
    "iso:country":"US",
    "sg:address":"302 E Carolina Ave",
    "sg:city":"Clinton",
    "sg:classifiers":[
        {
            "category":"Banks & Credit Unions",
            "subcategory":"Investment Brokerage",
            "type":"Services"
        }
    ],
    "sg:phone":"+1 864 833 0414",
    "sg:postcode":"29325",
    "sg:province":"SC",
    "sg:tags":[
        "security"
    ],
    "wof:name":"Edward Jones Investments",
    "wof:placetype":"venue"
},
  "geometry": {"coordinates":[-81.878586,34.472645],"type":"Point"}
}