{
  "type": "Feature",
  "properties": {
    "iso:country":"US",
    "sg:address":"3021 State Hwy 86",
    "sg:city":"Piedmont",
    "sg:classifiers":[
        {
            "category":"Building & Trades",
            "subcategory":"Construction",
            "type":"Services"
        }
    ],
    "sg:phone":"+1 864 850 1292",
    "sg:postcode":"29673",
    "sg:province":"SC",
    "wof:name":"Ben Wigington",
    "wof:placetype":"venue"
},
  "geometry": {"coordinates":[-82.52519700000001,34.724174],"type":"Point"}
}