{
  "type": "Feature",
  "properties": {
    "iso:country":"US",
    "sg:address":"12907 Old Number Six Hwy",
    "sg:city":"Eutawville",
    "sg:classifiers":[
        {
            "category":"Restaurant",
            "type":"Food & Drink"
        }
    ],
    "sg:phone":"+1 803 492 7567",
    "sg:postcode":"29048",
    "sg:province":"SC",
    "wof:name":"Bells Marina",
    "wof:placetype":"venue"
},
  "geometry": {"coordinates":[-80.305334,33.407168],"type":"Point"}
}