{
  "type": "Feature",
  "properties": {
    "iso:country":"US",
    "sg:address":"2325 S Pine St",
    "sg:city":"Spartanburg",
    "sg:classifiers":[
        {
            "category":"Autos & Motor Vehicles",
            "subcategory":"Motorcycle Sales",
            "type":"Retail Goods"
        }
    ],
    "sg:phone":"+1 864 585 3329",
    "sg:postcode":"29302",
    "sg:province":"SC",
    "sg:tags":[
        "sporting",
        "goo"
    ],
    "wof:name":"Sports Cycle & Hobby",
    "wof:placetype":"venue"
},
  "geometry": {"coordinates":[-81.882288,34.929984],"type":"Point"}
}