{
  "type": "Feature",
  "properties": {
    "addr:full":"100 Davidson Dr Ladson SC 29456",
    "addr:housenumber":"100",
    "addr:postcode":"29456",
    "addr:street":"Davidson Dr",
    "iso:country":"US",
    "sg:address":"100 Davidson Dr",
    "sg:city":"Ladson",
    "sg:classifiers":[
        {
            "category":"Education",
            "subcategory":"School",
            "type":"Public Place"
        }
    ],
    "sg:phone":"+1 843 797 2711",
    "sg:postcode":"29456",
    "sg:province":"SC",
    "wof:name":"College Park Elementary School",
    "wof:placetype":"venue"
},
  "geometry": {"coordinates":[-80.090796,33.015192],"type":"Point"}
}