{
  "type": "Feature",
  "properties": {
    "iso:country":"US",
    "sg:address":"6711 State Park Rd",
    "sg:city":"Travelers Rest",
    "sg:classifiers":[
        {
            "category":"Government",
            "subcategory":"Office",
            "type":"Public Place"
        }
    ],
    "sg:phone":"+1 864 834 7958",
    "sg:postcode":"29690",
    "sg:province":"SC",
    "sg:tags":[
        "city"
    ],
    "sg:website":"www.travelersrestsc.com",
    "wof:name":"Travelers Rest City Clerk",
    "wof:placetype":"venue"
},
  "geometry": {"coordinates":[-82.437495,34.965314],"type":"Point"}
}