{
  "type": "Feature",
  "properties": {
    "iso:country":"US",
    "sg:address":"310 W Main St",
    "sg:city":"Ridgeland",
    "sg:classifiers":[
        {
            "category":"Professional",
            "subcategory":"Lawyer & Legal Services",
            "type":"Services"
        }
    ],
    "sg:phone":"+1 843 726 5593",
    "sg:postcode":"29936",
    "sg:province":"SC",
    "sg:tags":[
        "attorney"
    ],
    "wof:name":"Albert Kleckley",
    "wof:placetype":"venue"
},
  "geometry": {"coordinates":[-80.983824,32.481978],"type":"Point"}
}