{
  "type": "Feature",
  "properties": {
    "iso:country":"US",
    "sg:address":"1333 Pineview Dr",
    "sg:city":"Columbia",
    "sg:classifiers":[
        {
            "category":"Manufacturing",
            "subcategory":"Metals",
            "type":"Manufacturing & Wholesale Goods"
        }
    ],
    "sg:phone":"+1 803 776 1516",
    "sg:postcode":"29209",
    "sg:province":"SC",
    "sg:tags":[
        "steel"
    ],
    "wof:name":"Deco Industries Inc",
    "wof:placetype":"venue"
},
  "geometry": {"coordinates":[-80.95693799999999,33.934298],"type":"Point"}
}