{
  "type": "Feature",
  "properties": {
    "iso:country":"US",
    "sg:address":"238 S Congress St",
    "sg:city":"Winnsboro",
    "sg:classifiers":[
        {
            "category":"Autos & Motor Vehicles",
            "subcategory":"Automobile Sales",
            "type":"Retail Goods"
        }
    ],
    "sg:phone":"+1 803 635 4923",
    "sg:postcode":"29180",
    "sg:province":"SC",
    "sg:tags":[
        "car",
        "dealer"
    ],
    "wof:name":"Wilson Chrysler Dodge Jeep Inc",
    "wof:placetype":"venue"
},
  "geometry": {"coordinates":[-81.085538,34.377969],"type":"Point"}
}