{
  "type": "Feature",
  "properties": {
    "addr:full":"6 Office Park Rd Hilton Head Isle SC 29928",
    "addr:postcode":"29928",
    "addr:street":"Park Rd",
    "iso:country":"US",
    "sg:address":"6 Office Park Rd",
    "sg:city":"Hilton Head Isle",
    "sg:classifiers":[
        {
            "category":"Real Estate",
            "subcategory":"Real Estate Agent",
            "type":"Services"
        }
    ],
    "sg:phone":"+1 843 341 2002",
    "sg:postcode":"29928",
    "sg:province":"SC",
    "wof:name":"Gardner Realty",
    "wof:placetype":"venue"
},
  "geometry": {"coordinates":[-80.761906,32.154427],"type":"Point"}
}