{
  "type": "Feature",
  "properties": {
    "addr:full":"701 E Bay St Charleston SC 29403",
    "addr:housenumber":"701",
    "addr:postcode":"29403",
    "addr:street":"E Bay St",
    "iso:country":"US",
    "sg:address":"701 E Bay St",
    "sg:city":"Charleston",
    "sg:classifiers":[
        {
            "category":"Professional",
            "subcategory":"Lawyer & Legal Services",
            "type":"Services"
        }
    ],
    "sg:phone":"+1 843 745 9110",
    "sg:postcode":"29403",
    "sg:province":"SC",
    "sg:tags":[
        "attorney"
    ],
    "wof:name":"Edwin H Cooper III",
    "wof:placetype":"venue"
},
  "geometry": {"coordinates":[-79.934181,32.797844],"type":"Point"}
}