{
  "type": "Feature",
  "properties": {
    "iso:country":"US",
    "sg:address":"729 W Oak Forest Dr",
    "sg:city":"Charleston",
    "sg:classifiers":[
        {
            "category":"Home & Garden",
            "subcategory":"Carpets & Floor Coverings",
            "type":"Retail Goods"
        }
    ],
    "sg:phone":"+1 843 556 9372",
    "sg:postcode":"29407",
    "sg:province":"SC",
    "wof:name":"Smalls Floor Maint",
    "wof:placetype":"venue"
},
  "geometry": {"coordinates":[-79.99969,32.791001],"type":"Point"}
}