{
  "type": "Feature",
  "properties": {
    "iso:country":"US",
    "sg:address":"1407 Confederate Ave",
    "sg:city":"Columbia",
    "sg:classifiers":[
        {
            "category":"Building & Trades",
            "subcategory":"Construction",
            "type":"Services"
        }
    ],
    "sg:phone":"+1 803 252 1062",
    "sg:postcode":"29201",
    "sg:province":"SC",
    "sg:tags":[
        "contractor"
    ],
    "wof:name":"Tile Creations",
    "wof:placetype":"venue"
},
  "geometry": {"coordinates":[-81.036881,34.020788],"type":"Point"}
}