{
  "type": "Feature",
  "properties": {
    "addr:full":"649 Broad River Blvd Beaufort SC 29906",
    "addr:housenumber":"649",
    "addr:postcode":"29906",
    "addr:street":"Broad River Blvd",
    "iso:country":"US",
    "sg:address":"649 Broad River Blvd",
    "sg:city":"Beaufort",
    "sg:classifiers":[
        {
            "category":"Personal",
            "subcategory":"Beauty Salon",
            "type":"Services"
        }
    ],
    "sg:phone":"+1 843 521 9966",
    "sg:postcode":"29906",
    "sg:province":"SC",
    "sg:tags":[
        "shop",
        "retail",
        "jewelry"
    ],
    "wof:name":"Jewelry Affair",
    "wof:placetype":"venue"
},
  "geometry": {"coordinates":[-80.76854899999999,32.413581],"type":"Point"}
}