{
  "type": "Feature",
  "properties": {
    "addr:full":"216 Brookwood Dr Greer SC 29651",
    "addr:housenumber":"216",
    "addr:postcode":"29651",
    "addr:street":"Brookwood Dr",
    "iso:country":"US",
    "sg:address":"216 Brookwood Dr",
    "sg:city":"Greer",
    "sg:classifiers":[
        {
            "category":"Food & Beverages",
            "subcategory":"Bakery",
            "type":"Retail Goods"
        }
    ],
    "sg:phone":"+1 864 877 2063",
    "sg:postcode":"29651",
    "sg:province":"SC",
    "wof:name":"Thee Bakery Inc",
    "wof:placetype":"venue"
},
  "geometry": {"coordinates":[-82.24943399999999,34.950185],"type":"Point"}
}