{
  "type": "Feature",
  "properties": {
    "iso:country":"US",
    "sg:address":"4990 Dorchester Rd",
    "sg:city":"Charleston",
    "sg:classifiers":[
        {
            "category":"Organizations",
            "subcategory":"Religious Organization",
            "type":"Services"
        }
    ],
    "sg:phone":"+1 843 552 4061",
    "sg:postcode":"29418",
    "sg:province":"SC",
    "sg:tags":[
        "church"
    ],
    "wof:name":"Cokesbury United Methodist Chr",
    "wof:placetype":"venue"
},
  "geometry": {"coordinates":[-80.030728,32.857781],"type":"Point"}
}