{
  "type": "Feature",
  "properties": {
    "addr:full":"3 Summit Dr Bluffton SC 29926",
    "addr:housenumber":"3",
    "addr:postcode":"29926",
    "addr:street":"Summit Dr",
    "iso:country":"US",
    "sg:address":"3 Summit Dr",
    "sg:city":"Bluffton",
    "sg:classifiers":[
        {
            "category":"Banks & Credit Unions",
            "subcategory":"Bank",
            "type":"Services"
        }
    ],
    "sg:phone":"+1 843 815 4777",
    "sg:postcode":"29926",
    "sg:province":"SC",
    "wof:name":"First Federal",
    "wof:placetype":"venue"
},
  "geometry": {"coordinates":[-80.694636,32.224328],"type":"Point"}
}