{
  "type": "Feature",
  "properties": {
    "iso:country":"US",
    "sg:address":"529 Dave Lyle Blvd",
    "sg:city":"Rock Hill",
    "sg:classifiers":[
        {
            "category":"Utilities",
            "subcategory":"Telephone",
            "type":"Services"
        }
    ],
    "sg:phone":"+1 803 326 6150",
    "sg:postcode":"29730",
    "sg:province":"SC",
    "sg:tags":[
        "communications",
        "radiotelephone",
        "communication"
    ],
    "wof:name":"Plant Department",
    "wof:placetype":"venue"
},
  "geometry": {"coordinates":[-81.019047,34.930167],"type":"Point"}
}