{
  "type": "Feature",
  "properties": {
    "iso:country":"US",
    "sg:address":"2991 Greenville Hwy",
    "sg:city":"Brevard",
    "sg:classifiers":[
        {
            "category":"Shopping",
            "type":"Retail Goods"
        }
    ],
    "sg:phone":"+1 828 885 2149",
    "sg:postcode":"28712",
    "sg:province":"SC",
    "sg:tags":[
        "craft",
        "gallery",
        "dealer"
    ],
    "wof:name":"Mountain Forest Studio",
    "wof:placetype":"venue"
},
  "geometry": {"coordinates":[-82.719615,35.198939],"type":"Point"}
}