{
  "type": "Feature",
  "properties": {
    "iso:country":"US",
    "sg:address":"416 Tiger Tail Rd",
    "sg:city":"Seneca",
    "sg:classifiers":[
        {
            "category":"Retail",
            "subcategory":"Animal Services",
            "type":"Services"
        }
    ],
    "sg:phone":"+1 864 653 8650",
    "sg:postcode":"29678",
    "sg:province":"SC",
    "wof:name":"BRK&d K-9",
    "wof:placetype":"venue"
},
  "geometry": {"coordinates":[-82.88509500000001,34.668253],"type":"Point"}
}