{
  "type": "Feature",
  "properties": {
    "iso:country":"US",
    "sg:address":"5995 Rivers Ave",
    "sg:city":"North Charleston",
    "sg:classifiers":[
        {
            "category":"Food & Beverages",
            "subcategory":"Groceries & Convenience Stores",
            "type":"Retail Goods"
        }
    ],
    "sg:phone":"+1 843 747 5978",
    "sg:postcode":"29406",
    "sg:province":"SC",
    "wof:name":"Fast Point Food Store",
    "wof:placetype":"venue"
},
  "geometry": {"coordinates":[-80.020009,32.904116],"type":"Point"}
}