{
  "type": "Feature",
  "properties": {
    "addr:full":"210 Claremont St Gaffney SC 29341",
    "addr:housenumber":"210",
    "addr:postcode":"29341",
    "addr:street":"Claremont St",
    "iso:country":"US",
    "sg:address":"210 Claremont St",
    "sg:city":"Gaffney",
    "sg:classifiers":[
        {
            "category":"Organizations",
            "subcategory":"Religious Organization",
            "type":"Services"
        }
    ],
    "sg:phone":"+1 864 489 7004",
    "sg:postcode":"29341",
    "sg:province":"SC",
    "sg:tags":[
        "church"
    ],
    "wof:name":"Holy Trinity Righteous Church",
    "wof:placetype":"venue"
},
  "geometry": {"coordinates":[-81.660212,35.068943],"type":"Point"}
}