{
  "type": "Feature",
  "properties": {
    "addr:full":"1218 Ambling Way Dr Myrtle Beach SC 29579",
    "addr:housenumber":"1218",
    "addr:postcode":"29579",
    "addr:street":"Ambling Way Dr",
    "iso:country":"US",
    "sg:address":"1218 Ambling Way Dr",
    "sg:city":"Myrtle Beach",
    "sg:classifiers":[
        {
            "category":"Professional",
            "subcategory":"Management & Consulting",
            "type":"Services"
        }
    ],
    "sg:phone":"+1 843 236 2196",
    "sg:postcode":"29579",
    "sg:province":"SC",
    "sg:tags":[
        "consultant",
        "business"
    ],
    "wof:name":"M C Sound Consultants",
    "wof:placetype":"venue"
},
  "geometry": {"coordinates":[-78.955455,33.704508],"type":"Point"}
}