{
  "type": "Feature",
  "properties": {
    "addr:full":"323 Wofford St Spartanburg SC 29301",
    "addr:housenumber":"323",
    "addr:postcode":"29301",
    "addr:street":"Wofford St",
    "iso:country":"US",
    "sg:address":"323 Wofford St",
    "sg:city":"Spartanburg",
    "sg:classifiers":[
        {
            "category":"Building & Trades",
            "subcategory":"Construction",
            "type":"Services"
        }
    ],
    "sg:phone":"+1 864 583 4691",
    "sg:postcode":"29301",
    "sg:province":"SC",
    "sg:tags":[
        "masonry",
        "contractor"
    ],
    "wof:name":"Johnson's Stone Good Masonry",
    "wof:placetype":"venue"
},
  "geometry": {"coordinates":[-81.94014799999999,34.949843],"type":"Point"}
}