{
  "type": "Feature",
  "properties": {
    "addr:full":"693 Main St West Columbia SC 29170",
    "addr:housenumber":"693",
    "addr:postcode":"29170",
    "addr:street":"Main St",
    "iso:country":"US",
    "sg:address":"693 Main St",
    "sg:city":"West Columbia",
    "sg:classifiers":[
        {
            "category":"Cinema",
            "subcategory":"Movie Rental",
            "type":"Entertainment"
        }
    ],
    "sg:phone":"+1 803 955 0065",
    "sg:postcode":"29170",
    "sg:province":"SC",
    "sg:tags":[
        "game",
        "video"
    ],
    "sg:website":"www.moviegallery.com",
    "wof:name":"Movie Gallery",
    "wof:placetype":"venue"
},
  "geometry": {"coordinates":[-81.1353,33.910801],"type":"Point"}
}