{
  "type": "Feature",
  "properties": {
    "iso:country":"US",
    "sg:address":"7611 N Kings Hwy",
    "sg:city":"Myrtle Beach",
    "sg:classifiers":[
        {
            "category":"Shopping",
            "subcategory":"Hobbies, Toys, & Games",
            "type":"Retail Goods"
        }
    ],
    "sg:phone":"+1 843 692 2458",
    "sg:postcode":"29577",
    "sg:province":"SC",
    "sg:tags":[
        "supply"
    ],
    "wof:name":"Scientific Games Intl Inc",
    "wof:placetype":"venue"
},
  "geometry": {"coordinates":[-78.81817100000001,33.747609],"type":"Point"}
}