{
  "type": "Feature",
  "properties": {
    "addr:full":"16 Palmetto Bay Rd Hilton Head Isle SC 29928",
    "addr:housenumber":"16",
    "addr:postcode":"29928",
    "addr:street":"Palmetto Bay Rd",
    "iso:country":"US",
    "sg:address":"16 Palmetto Bay Rd",
    "sg:city":"Hilton Head Isle",
    "sg:classifiers":[
        {
            "category":"Retail",
            "subcategory":"Laundry & Dry Cleaning",
            "type":"Services"
        }
    ],
    "sg:phone":"+1 843 785 5696",
    "sg:postcode":"29928",
    "sg:province":"SC",
    "sg:tags":[
        "cleaners"
    ],
    "wof:name":"Dryclean USA",
    "wof:placetype":"venue"
},
  "geometry": {"coordinates":[-80.76404100000001,32.157104],"type":"Point"}
}