{
  "type": "Feature",
  "properties": {
    "iso:country":"US",
    "sg:address":"5575 Dick Pond Rd",
    "sg:city":"Myrtle Beach",
    "sg:classifiers":[
        {
            "category":"Organizations",
            "subcategory":"Religious Organization",
            "type":"Services"
        }
    ],
    "sg:phone":"+1 843 650 3373",
    "sg:postcode":"29588",
    "sg:province":"SC",
    "sg:tags":[
        "church"
    ],
    "wof:name":"Socastee United Methodist Chr",
    "wof:placetype":"venue"
},
  "geometry": {"coordinates":[-79.000816,33.682394],"type":"Point"}
}