{
  "type": "Feature",
  "properties": {
    "addr:full":"329 Cockfield Rd Abbeville SC 29620",
    "addr:housenumber":"329",
    "addr:postcode":"29620",
    "addr:street":"Cockfield Rd",
    "iso:country":"US",
    "sg:address":"329 Cockfield Rd",
    "sg:city":"Abbeville",
    "sg:classifiers":[
        {
            "category":"Building & Trades",
            "subcategory":"Construction",
            "type":"Services"
        }
    ],
    "sg:phone":"+1 864 446 2721",
    "sg:postcode":"29620",
    "sg:province":"SC",
    "sg:tags":[
        "grading",
        "contractor"
    ],
    "wof:name":"Tiller Backhoe & Dozer Svc",
    "wof:placetype":"venue"
},
  "geometry": {"coordinates":[-82.342859,34.263345],"type":"Point"}
}