{
  "type": "Feature",
  "properties": {
    "iso:country":"US",
    "sg:address":"1437 Jonesville Hwy",
    "sg:city":"Union",
    "sg:classifiers":[
        {
            "category":"Organizations",
            "subcategory":"Religious Organization",
            "type":"Services"
        }
    ],
    "sg:phone":"+1 864 427 8852",
    "sg:postcode":"29379",
    "sg:province":"SC",
    "sg:tags":[
        "church"
    ],
    "wof:name":"Seventh-Day Adventist Church",
    "wof:placetype":"venue"
},
  "geometry": {"coordinates":[-81.630897,34.754011],"type":"Point"}
}