{
  "type": "Feature",
  "properties": {
    "iso:country":"US",
    "sg:address":"39 General Henderson Rd",
    "sg:city":"Newberry",
    "sg:classifiers":[
        {
            "category":"Government",
            "subcategory":"Office",
            "type":"Public Place"
        }
    ],
    "sg:phone":"+1 803 405 0185",
    "sg:postcode":"29108",
    "sg:province":"SC",
    "wof:name":"Fire Dispatch Ctr",
    "wof:placetype":"venue"
},
  "geometry": {"coordinates":[-81.576674,34.325338],"type":"Point"}
}