{
  "type": "Feature",
  "properties": {
    "addr:full":"8 Parris Island Gateway Beaufort SC 29906",
    "addr:housenumber":"8",
    "addr:postcode":"29906",
    "addr:street":"Parris Island",
    "iso:country":"US",
    "sg:address":"8 Parris Island Gateway",
    "sg:city":"Beaufort",
    "sg:classifiers":[
        {
            "category":"Communications",
            "type":"Services"
        }
    ],
    "sg:phone":"+1 843 379 9267",
    "sg:postcode":"29906",
    "sg:province":"SC",
    "wof:name":"Latinos Communication",
    "wof:placetype":"venue"
},
  "geometry": {"coordinates":[-80.721592,32.441205],"type":"Point"}
}