{
  "type": "Feature",
  "properties": {
    "addr:full":"157 Williams Rd Ehrhardt SC 29020",
    "addr:housenumber":"157",
    "addr:postcode":"29020",
    "addr:street":"Williams Rd",
    "iso:country":"US",
    "sg:address":"157 Williams Rd",
    "sg:city":"Ehrhardt",
    "sg:classifiers":[
        {
            "category":"Organizations",
            "subcategory":"Religious Organization",
            "type":"Services"
        }
    ],
    "sg:phone":"+1 803 267 4302",
    "sg:postcode":"29020",
    "sg:province":"SC",
    "sg:tags":[
        "church"
    ],
    "wof:name":"Williams Chapel Baptist Church",
    "wof:placetype":"venue"
},
  "geometry": {"coordinates":[-80.458832,34.22503],"type":"Point"}
}