{
  "type": "Feature",
  "properties": {
    "iso:country":"US",
    "sg:address":"5609 Rivers Ave",
    "sg:city":"Charleston",
    "sg:classifiers":[
        {
            "category":"Personal",
            "subcategory":"Beauty Salon",
            "type":"Services"
        },
        {
            "category":"Shopping",
            "subcategory":"Beauty & Cosmetics",
            "type":"Retail Goods"
        }
    ],
    "sg:phone":"+1 843 747 7873",
    "sg:postcode":"29406",
    "sg:province":"SC",
    "sg:tags":[
        "nail",
        "manicuring",
        "supply"
    ],
    "wof:name":"City Nail Supply",
    "wof:placetype":"venue"
},
  "geometry": {"coordinates":[-80.01561599999999,32.896567],"type":"Point"}
}