{
  "type": "Feature",
  "properties": {
    "iso:country":"US",
    "sg:address":"801 Main St",
    "sg:city":"North Myrtle Beach",
    "sg:classifiers":[
        {
            "category":"Restaurant",
            "type":"Food & Drink"
        }
    ],
    "sg:menulink":"http://www.allmenus.com/sc/little-river/215345-burger-king/menu/",
    "sg:phone":"+1 843 280 6471",
    "sg:postcode":"29582",
    "sg:province":"SC",
    "sg:tags":[
        "burger",
        "american"
    ],
    "wof:name":"Burger King",
    "wof:placetype":"venue"
},
  "geometry": {"coordinates":[-78.679168,33.827524],"type":"Point"}
}