{
  "type": "Feature",
  "properties": {
    "iso:country":"US",
    "sg:address":"21 A D Asbury Dr",
    "sg:city":"Greenville",
    "sg:classifiers":[
        {
            "category":"Wholesale",
            "subcategory":"Machinery & Supplies",
            "type":"Manufacturing & Wholesale Goods"
        }
    ],
    "sg:phone":"+1 864 299 1755",
    "sg:postcode":"29605",
    "sg:province":"SC",
    "sg:tags":[
        "equipment",
        "material",
        "handling"
    ],
    "sg:website":"www.easterncrane.com",
    "wof:name":"Eastern Crane & Hoist Inc",
    "wof:placetype":"venue"
},
  "geometry": {"coordinates":[-82.385014,34.75774],"type":"Point"}
}