{
  "type": "Feature",
  "properties": {
    "iso:country":"US",
    "sg:address":"844 Magnolia Rd",
    "sg:city":"Charleston",
    "sg:classifiers":[
        {
            "category":"Retail",
            "subcategory":"Auto Repair",
            "type":"Services"
        }
    ],
    "sg:phone":"+1 843 556 1363",
    "sg:postcode":"29407",
    "sg:province":"SC",
    "sg:tags":[
        "body",
        "automobile",
        "painting"
    ],
    "wof:name":"Pete's Body Shop",
    "wof:placetype":"venue"
},
  "geometry": {"coordinates":[-79.994589,32.791968],"type":"Point"}
}