{
  "type": "Feature",
  "properties": {
    "iso:country":"US",
    "sg:address":"47 Calhoun St",
    "sg:city":"Charleston",
    "sg:classifiers":[
        {
            "category":"Real Estate",
            "subcategory":"Real Estate Agent",
            "type":"Services"
        }
    ],
    "sg:phone":"+1 843 722 6017",
    "sg:postcode":"29401",
    "sg:province":"SC",
    "wof:name":"Atlantic Realty & Investments",
    "wof:placetype":"venue"
},
  "geometry": {"coordinates":[-79.930112,32.788451],"type":"Point"}
}