{
  "type": "Feature",
  "properties": {
    "iso:country":"US",
    "sg:address":"1470 Tobias Gadson Blvd",
    "sg:city":"Charleston",
    "sg:classifiers":[
        {
            "category":"Professional",
            "type":"Services"
        }
    ],
    "sg:phone":"+1 843 571 2981",
    "sg:postcode":"29407",
    "sg:province":"SC",
    "sg:tags":[
        "actuary"
    ],
    "sg:website":"www.myplanlink.com",
    "wof:name":"Pension Systems Inc",
    "wof:placetype":"venue"
},
  "geometry": {"coordinates":[-80.028684,32.81102],"type":"Point"}
}