{
  "type": "Feature",
  "properties": {
    "iso:country":"US",
    "sg:address":"504 12th St",
    "sg:city":"West Columbia",
    "sg:classifiers":[
        {
            "category":"Building & Trades",
            "subcategory":"Locksmith",
            "type":"Services"
        }
    ],
    "sg:phone":"+1 803 791 4637",
    "sg:postcode":"29169",
    "sg:province":"SC",
    "sg:tags":[
        "key"
    ],
    "wof:name":"0 24 Hour Affordable Locksmith",
    "wof:placetype":"venue"
},
  "geometry": {"coordinates":[-81.072508,33.986399],"type":"Point"}
}