{
  "type": "Feature",
  "properties": {
    "iso:country":"US",
    "sg:address":"2597 State Hwy 66",
    "sg:city":"Whitmire",
    "sg:classifiers":[
        {
            "category":"Education",
            "subcategory":"School",
            "type":"Public Place"
        }
    ],
    "sg:phone":"+1 803 694 2320",
    "sg:postcode":"29178",
    "sg:province":"SC",
    "sg:website":"www.newberryschools.com",
    "wof:name":"Whitmire Elementary School",
    "wof:placetype":"venue"
},
  "geometry": {"coordinates":[-81.633709,34.477117],"type":"Point"}
}