{
  "type": "Feature",
  "properties": {
    "iso:country":"US",
    "sg:address":"101 Chinaberry Ln",
    "sg:city":"Cayce",
    "sg:classifiers":[
        {
            "category":"Real Estate",
            "subcategory":"Real Estate Agent",
            "type":"Services"
        }
    ],
    "sg:phone":"+1 803 791 1236",
    "sg:postcode":"29033",
    "sg:province":"SC",
    "wof:name":"Griffin Homes & Properties LLC",
    "wof:placetype":"venue"
},
  "geometry": {"coordinates":[-81.073522,33.943196],"type":"Point"}
}