{
  "type": "Feature",
  "properties": {
    "addr:full":"633 W Columbia Ave Batesburg SC 29006",
    "addr:housenumber":"633",
    "addr:postcode":"29006",
    "addr:street":"W Columbia Ave",
    "iso:country":"US",
    "sg:address":"633 W Columbia Ave",
    "sg:city":"Batesburg",
    "sg:classifiers":[
        {
            "category":"Professional",
            "subcategory":"Accounting & Tax Preparation",
            "type":"Services"
        }
    ],
    "sg:phone":"+1 803 739 2032",
    "sg:postcode":"29006",
    "sg:province":"SC",
    "sg:tags":[
        "return",
        "filing"
    ],
    "wof:name":"Pinckney's Tax & Business Svc",
    "wof:placetype":"venue"
},
  "geometry": {"coordinates":[-81.55857,33.898857],"type":"Point"}
}