{
  "type": "Feature",
  "properties": {
    "iso:country":"US",
    "sg:address":"428 E Main St",
    "sg:city":"Laurens",
    "sg:classifiers":[
        {
            "category":"Personal",
            "subcategory":"Beauty Salon",
            "type":"Services"
        }
    ],
    "sg:phone":"+1 864 984 0422",
    "sg:postcode":"29360",
    "sg:province":"SC",
    "sg:tags":[
        "cosmetologist"
    ],
    "wof:name":"Main Street Gallery",
    "wof:placetype":"venue"
},
  "geometry": {"coordinates":[-82.00503999999999,34.499312],"type":"Point"}
}