{
  "type": "Feature",
  "properties": {
    "iso:country":"US",
    "sg:address":"125 Egret Ln",
    "sg:city":"Goose Creek",
    "sg:classifiers":[
        {
            "category":"Real Estate",
            "subcategory":"Real Estate Agent",
            "type":"Services"
        }
    ],
    "sg:phone":"+1 843 818 2201",
    "sg:postcode":"29445",
    "sg:province":"SC",
    "sg:tags":[
        "inspection"
    ],
    "wof:name":"Home Inspector",
    "wof:placetype":"venue"
},
  "geometry": {"coordinates":[-80.04068599999999,33.020251],"type":"Point"}
}