{
  "type": "Feature",
  "properties": {
    "addr:full":"2225 W Brewington Rd Sumter SC 29153",
    "addr:housenumber":"2225",
    "addr:postcode":"29153",
    "addr:street":"W Brewington Rd",
    "iso:country":"US",
    "sg:address":"2225 W Brewington Rd",
    "sg:city":"Sumter",
    "sg:classifiers":[
        {
            "category":"Building & Trades",
            "subcategory":"Construction",
            "type":"Services"
        }
    ],
    "sg:phone":"+1 803 469 5351",
    "sg:postcode":"29153",
    "sg:province":"SC",
    "sg:tags":[
        "contractor"
    ],
    "wof:name":"Mcleod Building",
    "wof:placetype":"venue"
},
  "geometry": {"coordinates":[-80.40178,33.994836],"type":"Point"}
}