{
  "type": "Feature",
  "properties": {
    "iso:country":"US",
    "sg:address":"1234 Bexley St",
    "sg:city":"North Charleston",
    "sg:classifiers":[
        {
            "category":"Freight",
            "type":"Transportation"
        }
    ],
    "sg:phone":"+1 843 744 5666",
    "sg:postcode":"29405",
    "sg:province":"SC",
    "sg:tags":[
        "delivery"
    ],
    "wof:name":"C 2 Expedite",
    "wof:placetype":"venue"
},
  "geometry": {"coordinates":[-79.98572900000001,32.873455],"type":"Point"}
}