{
  "type": "Feature",
  "properties": {
    "iso:country":"US",
    "sg:address":"101 Hunt St",
    "sg:city":"Honea Path",
    "sg:classifiers":[
        {
            "category":"Organizations",
            "subcategory":"Religious Organization",
            "type":"Services"
        }
    ],
    "sg:phone":"+1 864 369 7832",
    "sg:postcode":"29654",
    "sg:province":"SC",
    "sg:tags":[
        "church"
    ],
    "wof:name":"Church Of God",
    "wof:placetype":"venue"
},
  "geometry": {"coordinates":[-82.388922,34.455024],"type":"Point"}
}