{
  "type": "Feature",
  "properties": {
    "addr:full":"4891 Earle E Morris Jr Hwy Easley SC 29642",
    "addr:housenumber":"4891",
    "addr:postcode":"29642",
    "addr:street":"Earle E;Jr Hwy",
    "iso:country":"US",
    "sg:address":"4891 Earle E Morris Jr Hwy",
    "sg:city":"Easley",
    "sg:classifiers":[
        {
            "category":"Building & Trades",
            "subcategory":"Construction",
            "type":"Services"
        }
    ],
    "sg:phone":"+1 864 269 9255",
    "sg:postcode":"29642",
    "sg:province":"SC",
    "sg:tags":[
        "contractor"
    ],
    "wof:name":"Pyramid Construction",
    "wof:placetype":"venue"
},
  "geometry": {"coordinates":[-82.515776,34.811624],"type":"Point"}
}