{
  "type": "Feature",
  "properties": {
    "iso:country":"US",
    "sg:address":"1938 Mountain Laurel Ct",
    "sg:city":"Florence",
    "sg:classifiers":[
        {
            "category":"Social Services",
            "type":"Services"
        }
    ],
    "sg:phone":"+1 843 665 7978",
    "sg:postcode":"29505",
    "sg:province":"SC",
    "sg:tags":[
        "senior",
        "citizen"
    ],
    "wof:name":"Laurel Gardens Assisted Living",
    "wof:placetype":"venue"
},
  "geometry": {"coordinates":[-79.75465800000001,34.158042],"type":"Point"}
}