{
  "type": "Feature",
  "properties": {
    "iso:country":"US",
    "sg:address":"121 Broughton Dr",
    "sg:city":"Greenville",
    "sg:classifiers":[
        {
            "category":"Wholesale",
            "subcategory":"Machinery & Supplies",
            "type":"Manufacturing & Wholesale Goods"
        }
    ],
    "sg:phone":"+1 864 235 6888",
    "sg:postcode":"29609",
    "sg:province":"SC",
    "sg:tags":[
        "equipment",
        "material",
        "handling"
    ],
    "sg:website":"www.indoff.com",
    "wof:name":"Indoff Inc",
    "wof:placetype":"venue"
},
  "geometry": {"coordinates":[-82.380657,34.887088],"type":"Point"}
}