{
  "type": "Feature",
  "properties": {
    "iso:country":"US",
    "sg:address":"410 E Brooks St",
    "sg:city":"Andrews",
    "sg:classifiers":[
        {
            "category":"Food & Beverages",
            "subcategory":"Groceries & Convenience Stores",
            "type":"Retail Goods"
        }
    ],
    "sg:phone":"+1 843 264 5650",
    "sg:postcode":"29556",
    "sg:province":"SC",
    "wof:name":"Newton's General Store",
    "wof:placetype":"venue"
},
  "geometry": {"coordinates":[-79.824994,33.668124],"type":"Point"}
}