{
  "type": "Feature",
  "properties": {
    "iso:country":"US",
    "sg:address":"104 Rubiwood Cir",
    "sg:city":"Greer",
    "sg:classifiers":[
        {
            "category":"Building & Trades",
            "subcategory":"Construction",
            "type":"Services"
        }
    ],
    "sg:phone":"+1 864 879 1170",
    "sg:postcode":"29651",
    "sg:province":"SC",
    "sg:tags":[
        "hanging",
        "contractor"
    ],
    "wof:name":"Hannon Brothers Painting",
    "wof:placetype":"venue"
},
  "geometry": {"coordinates":[-82.277877,34.95752],"type":"Point"}
}