{
  "type": "Feature",
  "properties": {
    "addr:full":"1010 Mill St Camden SC 29020",
    "addr:housenumber":"1010",
    "addr:postcode":"29020",
    "addr:street":"Mill St",
    "iso:country":"US",
    "sg:address":"1010 Mill St",
    "sg:city":"Camden",
    "sg:classifiers":[
        {
            "category":"Restaurant",
            "type":"Food & Drink"
        }
    ],
    "sg:phone":"+1 803 432 9559",
    "sg:postcode":"29020",
    "sg:province":"SC",
    "wof:name":"Galloway Enterprise",
    "wof:placetype":"venue"
},
  "geometry": {"coordinates":[-80.598772,34.246681],"type":"Point"}
}