{
  "type": "Feature",
  "properties": {
    "iso:country":"US",
    "sg:address":"2857 Lesslie Hwy",
    "sg:city":"Rock Hill",
    "sg:classifiers":[
        {
            "category":"Retail",
            "subcategory":"Repair Shop",
            "type":"Services"
        }
    ],
    "sg:phone":"+1 803 980 2453",
    "sg:postcode":"29730",
    "sg:province":"SC",
    "sg:tags":[
        "scooter",
        "motorcycle",
        "motor"
    ],
    "wof:name":"Teck Custom Cycles",
    "wof:placetype":"venue"
},
  "geometry": {"coordinates":[-80.964546,34.899399],"type":"Point"}
}