{
  "type": "Feature",
  "properties": {
    "iso:country":"US",
    "sg:address":"415 S Pine St",
    "sg:city":"Walhalla",
    "sg:classifiers":[
        {
            "category":"Government",
            "subcategory":"Office",
            "type":"Public Place"
        }
    ],
    "sg:phone":"+1 864 638 4250",
    "sg:postcode":"29691",
    "sg:province":"SC",
    "wof:name":"Oconee County E-911 Office",
    "wof:placetype":"venue"
},
  "geometry": {"coordinates":[-83.073425,34.759958],"type":"Point"}
}