{
  "type": "Feature",
  "properties": {
    "addr:full":"2230 Decker Blvd Columbia SC 29206",
    "addr:housenumber":"2230",
    "addr:postcode":"29206",
    "addr:street":"Decker Blvd",
    "iso:country":"US",
    "sg:address":"2230 Decker Blvd",
    "sg:city":"Columbia",
    "sg:classifiers":[
        {
            "category":"Food & Beverages",
            "subcategory":"Liquor & Beverages",
            "type":"Retail Goods"
        }
    ],
    "sg:phone":"+1 803 788 9009",
    "sg:postcode":"29206",
    "sg:province":"SC",
    "wof:name":"Decker Boulevard Package Shop",
    "wof:placetype":"venue"
},
  "geometry": {"coordinates":[-80.945491,34.052255],"type":"Point"}
}