{
  "type": "Feature",
  "properties": {
    "iso:country":"US",
    "sg:address":"330 Parker Dr",
    "sg:city":"Beaufort",
    "sg:classifiers":[
        {
            "category":"Home & Garden",
            "subcategory":"Building Materials",
            "type":"Retail Goods"
        }
    ],
    "sg:phone":"+1 843 726 4025",
    "sg:postcode":"29906",
    "sg:province":"SC",
    "sg:tags":[
        "concrete"
    ],
    "wof:name":"Lowcountry Con of Ridgeland",
    "wof:placetype":"venue"
},
  "geometry": {"coordinates":[-80.759423,32.465111],"type":"Point"}
}