{
  "type": "Feature",
  "properties": {
    "addr:full":"210 Phoenix St Greenwood SC 29646",
    "addr:housenumber":"210",
    "addr:postcode":"29646",
    "addr:street":"Phoenix St",
    "iso:country":"US",
    "sg:address":"210 Phoenix St",
    "sg:city":"Greenwood",
    "sg:classifiers":[
        {
            "category":"Home & Garden",
            "subcategory":"Home Furnishings",
            "type":"Retail Goods"
        }
    ],
    "sg:phone":"+1 864 223 5759",
    "sg:postcode":"29646",
    "sg:province":"SC",
    "wof:name":"Mirtas Designs",
    "wof:placetype":"venue"
},
  "geometry": {"coordinates":[-82.158584,34.190761],"type":"Point"}
}