{
  "type": "Feature",
  "properties": {
    "addr:full":"1850 Flint Ridge Rd Heath Springs SC 29058",
    "addr:housenumber":"1850",
    "addr:postcode":"29058",
    "addr:street":"Flint Ridge Rd",
    "iso:country":"US",
    "sg:address":"1850 Flint Ridge Rd",
    "sg:city":"Heath Springs",
    "sg:classifiers":[
        {
            "category":"Organizations",
            "subcategory":"Religious Organization",
            "type":"Services"
        }
    ],
    "sg:phone":"+1 803 273 9225",
    "sg:postcode":"29058",
    "sg:province":"SC",
    "sg:tags":[
        "church"
    ],
    "wof:name":"Flint Ridge Baptist Church",
    "wof:placetype":"venue"
},
  "geometry": {"coordinates":[-80.64028500000001,34.616787],"type":"Point"}
}