{
  "type": "Feature",
  "properties": {
    "iso:country":"US",
    "sg:address":"1245 Wilson Rd",
    "sg:city":"Newberry",
    "sg:classifiers":[
        {
            "category":"Shopping",
            "subcategory":"Tobacco",
            "type":"Retail Goods"
        }
    ],
    "sg:phone":"+1 803 276 0160",
    "sg:postcode":"29108",
    "sg:province":"SC",
    "sg:tags":[
        "product"
    ],
    "wof:name":"Carolina Discount Tobacco Inc",
    "wof:placetype":"venue"
},
  "geometry": {"coordinates":[-81.597037,34.283662],"type":"Point"}
}