{
  "type": "Feature",
  "properties": {
    "iso:country":"US",
    "sg:address":"901 White Pond Rd",
    "sg:city":"Elgin",
    "sg:classifiers":[
        {
            "category":"Building & Trades",
            "subcategory":"Construction",
            "type":"Services"
        }
    ],
    "sg:phone":"+1 803 438 4931",
    "sg:postcode":"29045",
    "sg:province":"SC",
    "sg:tags":[
        "house",
        "builder",
        "operative",
        "home"
    ],
    "wof:name":"Delk Construction Inc",
    "wof:placetype":"venue"
},
  "geometry": {"coordinates":[-80.758043,34.148129],"type":"Point"}
}