{
  "type": "Feature",
  "properties": {
    "addr:full":"507 Cherokee Ave Gaffney SC 29340",
    "addr:housenumber":"507",
    "addr:postcode":"29340",
    "addr:street":"Cherokee Ave",
    "iso:country":"US",
    "sg:address":"507 Cherokee Ave",
    "sg:city":"Gaffney",
    "sg:classifiers":[
        {
            "category":"Organizations",
            "subcategory":"Religious Organization",
            "type":"Services"
        }
    ],
    "sg:phone":"+1 864 489 7757",
    "sg:postcode":"29340",
    "sg:province":"SC",
    "sg:tags":[
        "church"
    ],
    "wof:name":"Fruit Of The Spirit Ministry",
    "wof:placetype":"venue"
},
  "geometry": {"coordinates":[-81.64216500000001,35.078414],"type":"Point"}
}