{
  "type": "Feature",
  "properties": {
    "iso:country":"US",
    "sg:address":"1841 Pacolet Hwy",
    "sg:city":"Gaffney",
    "sg:classifiers":[
        {
            "category":"Professional",
            "type":"Services"
        }
    ],
    "sg:phone":"+1 864 902 9883",
    "sg:postcode":"29340",
    "sg:province":"SC",
    "sg:tags":[
        "establishment"
    ],
    "wof:name":"Diner Land Co",
    "wof:placetype":"venue"
},
  "geometry": {"coordinates":[-81.688181,35.00922],"type":"Point"}
}