{
  "type": "Feature",
  "properties": {
    "iso:country":"US",
    "sg:address":"917 Bay St",
    "sg:city":"Beaufort",
    "sg:classifiers":[
        {
            "category":"Food & Beverages",
            "subcategory":"Groceries & Convenience Stores",
            "type":"Retail Goods"
        },
        {
            "category":"Manufacturing",
            "subcategory":"Printing",
            "type":"Manufacturing & Wholesale Goods"
        }
    ],
    "sg:phone":"+1 843 470 0188",
    "sg:postcode":"29902",
    "sg:province":"SC",
    "sg:tags":[
        "newspaper"
    ],
    "wof:name":"Market Place News",
    "wof:placetype":"venue"
},
  "geometry": {"coordinates":[-80.672768,32.431143],"type":"Point"}
}