{
  "type": "Feature",
  "properties": {
    "iso:country":"US",
    "sg:address":"433 N Guignard Dr",
    "sg:city":"Sumter",
    "sg:classifiers":[
        {
            "category":"Shopping",
            "subcategory":"Florist",
            "type":"Retail Goods"
        }
    ],
    "sg:phone":"+1 803 774 0204",
    "sg:postcode":"29150",
    "sg:province":"SC",
    "wof:name":"Ozzie's At The Rustic Market",
    "wof:placetype":"venue"
},
  "geometry": {"coordinates":[-80.366026,33.928458],"type":"Point"}
}