{
  "type": "Feature",
  "properties": {
    "iso:country":"US",
    "sg:address":"150 Main Rd",
    "sg:city":"Johns Island",
    "sg:classifiers":[
        {
            "category":"Real Estate",
            "subcategory":"Real Estate Agent",
            "type":"Services"
        }
    ],
    "sg:phone":"+1 843 402 0339",
    "sg:postcode":"29455",
    "sg:province":"SC",
    "wof:name":"Rugheimer Properties",
    "wof:placetype":"venue"
},
  "geometry": {"coordinates":[-80.108976,32.800682],"type":"Point"}
}