{
  "type": "Feature",
  "properties": {
    "iso:country":"US",
    "sg:address":"270 Academy Rd",
    "sg:city":"Walterboro",
    "sg:classifiers":[
        {
            "category":"Social Services",
            "subcategory":"Child Care",
            "type":"Services"
        }
    ],
    "sg:phone":"+1 843 538 5437",
    "sg:postcode":"29488",
    "sg:province":"SC",
    "wof:name":"Academy Road Country Care",
    "wof:placetype":"venue"
},
  "geometry": {"coordinates":[-80.662409,32.937664],"type":"Point"}
}