{
  "type": "Feature",
  "properties": {
    "addr:full":"809 King St Camden SC 29020",
    "addr:housenumber":"809",
    "addr:postcode":"29020",
    "addr:street":"King St",
    "iso:country":"US",
    "sg:address":"809 King St",
    "sg:city":"Camden",
    "sg:classifiers":[
        {
            "category":"Organizations",
            "subcategory":"Religious Organization",
            "type":"Services"
        }
    ],
    "sg:phone":"+1 803 425 1555",
    "sg:postcode":"29020",
    "sg:province":"SC",
    "sg:tags":[
        "church"
    ],
    "wof:name":"St Thomas Baptist Church",
    "wof:placetype":"venue"
},
  "geometry": {"coordinates":[-80.61165,34.238603],"type":"Point"}
}