{
  "type": "Feature",
  "properties": {
    "iso:country":"US",
    "sg:address":"225 Farm Lake Rd",
    "sg:city":"Spartanburg",
    "sg:classifiers":[
        {
            "category":"Banks & Credit Unions",
            "subcategory":"Financial Services",
            "type":"Services"
        }
    ],
    "sg:phone":"+1 864 578 3582",
    "sg:postcode":"29316",
    "sg:province":"SC",
    "sg:tags":[
        "investor"
    ],
    "wof:name":"K&S Upstate Investments LLC",
    "wof:placetype":"venue"
},
  "geometry": {"coordinates":[-81.990049,35.049813],"type":"Point"}
}