{
  "type": "Feature",
  "properties": {
    "iso:country":"US",
    "sg:address":"929 N Main St",
    "sg:city":"Lancaster",
    "sg:classifiers":[
        {
            "category":"Health Services",
            "subcategory":"Optometrist",
            "type":"Services"
        }
    ],
    "sg:phone":"+1 803 286 5522",
    "sg:postcode":"29720",
    "sg:province":"SC",
    "wof:name":"Dukes Eye Care",
    "wof:placetype":"venue"
},
  "geometry": {"coordinates":[-80.776354,34.730274],"type":"Point"}
}