{
  "type": "Feature",
  "properties": {
    "iso:country":"US",
    "sg:address":"1430 Congaree Dr",
    "sg:city":"West Columbia",
    "sg:classifiers":[
        {
            "category":"Building & Trades",
            "subcategory":"Construction",
            "type":"Services"
        }
    ],
    "sg:phone":"+1 803 955 0374",
    "sg:postcode":"29172",
    "sg:province":"SC",
    "sg:tags":[
        "residential",
        "contractor"
    ],
    "wof:name":"Bauer Roofing",
    "wof:placetype":"venue"
},
  "geometry": {"coordinates":[-81.118154,33.90437],"type":"Point"}
}