{
  "type": "Feature",
  "properties": {
    "iso:country":"US",
    "sg:address":"123 Lawand Dr",
    "sg:city":"Columbia",
    "sg:classifiers":[
        {
            "category":"Insurance",
            "subcategory":"Insurance Agent",
            "type":"Services"
        }
    ],
    "sg:phone":"+1 803 772 7449",
    "sg:postcode":"29210",
    "sg:province":"SC",
    "wof:name":"Primerica Financial Svc",
    "wof:placetype":"venue"
},
  "geometry": {"coordinates":[-81.09787900000001,34.027349],"type":"Point"}
}