{
  "type": "Feature",
  "properties": {
    "iso:country":"US",
    "sg:address":"161 School Rd",
    "sg:city":"Easley",
    "sg:classifiers":[
        {
            "category":"Education",
            "subcategory":"School",
            "type":"Public Place"
        }
    ],
    "sg:phone":"+1 864 855 8160",
    "sg:postcode":"29640",
    "sg:province":"SC",
    "wof:name":"Crosswell Elementary",
    "wof:placetype":"venue"
},
  "geometry": {"coordinates":[-82.524918,34.851615],"type":"Point"}
}