{
  "type": "Feature",
  "properties": {
    "addr:full":"635 NE Main St Simpsonville SC 29681",
    "addr:housenumber":"635",
    "addr:postcode":"29681",
    "addr:street":"Ne Main St",
    "iso:country":"US",
    "sg:address":"635 NE Main St",
    "sg:city":"Simpsonville",
    "sg:classifiers":[
        {
            "category":"Restaurant",
            "type":"Food & Drink"
        }
    ],
    "sg:phone":"+1 864 963 3800",
    "sg:postcode":"29681",
    "sg:province":"SC",
    "sg:tags":[
        "style",
        "family",
        "italian"
    ],
    "wof:name":"Pasta House",
    "wof:placetype":"venue"
},
  "geometry": {"coordinates":[-82.261729,34.748371],"type":"Point"}
}