{
  "type": "Feature",
  "properties": {
    "iso:country":"US",
    "sg:address":"182 Us Highway 321 Byp S",
    "sg:city":"Winnsboro",
    "sg:classifiers":[
        {
            "category":"Restaurant",
            "type":"Food & Drink"
        }
    ],
    "sg:menulink":"http://www.allmenus.com/sc/winnsboro-south/176762-kfc---kentucky-fried-chicken/menu/",
    "sg:phone":"+1 803 635 9708",
    "sg:postcode":"29180",
    "sg:province":"SC",
    "sg:tags":[
        "american",
        "chicken"
    ],
    "wof:name":"KFC - Kentucky Fried Chicken",
    "wof:placetype":"venue"
},
  "geometry": {"coordinates":[-81.100819,34.369625],"type":"Point"}
}