{
  "type": "Feature",
  "properties": {
    "iso:country":"US",
    "sg:address":"2421 2nd Loop Rd",
    "sg:city":"Florence",
    "sg:classifiers":[
        {
            "category":"Restaurant",
            "type":"Food & Drink"
        }
    ],
    "sg:phone":"+1 843 662 8334",
    "sg:postcode":"29501",
    "sg:province":"SC",
    "sg:tags":[
        "eating"
    ],
    "wof:name":"Koko Express Inc",
    "wof:placetype":"venue"
},
  "geometry": {"coordinates":[-79.80929,34.175657],"type":"Point"}
}