{
  "type": "Feature",
  "properties": {
    "addr:full":"10301 Garners Ferry Rd Eastover SC 29044",
    "addr:housenumber":"10301",
    "addr:postcode":"29044",
    "addr:street":"Garners Ferry Rd",
    "iso:country":"US",
    "sg:address":"10301 Garners Ferry Rd",
    "sg:city":"Eastover",
    "sg:classifiers":[
        {
            "category":"Government",
            "subcategory":"Office",
            "type":"Public Place"
        }
    ],
    "sg:phone":"+1 803 776 1616",
    "sg:postcode":"29044",
    "sg:province":"SC",
    "sg:tags":[
        "state",
        "security"
    ],
    "wof:name":"South Carolina National Guard",
    "wof:placetype":"venue"
},
  "geometry": {"coordinates":[-80.802977,33.941538],"type":"Point"}
}