{
  "type": "Feature",
  "properties": {
    "addr:full":"932 E Main St Duncan SC 29334",
    "addr:housenumber":"932",
    "addr:postcode":"29334",
    "addr:street":"E Main St",
    "iso:country":"US",
    "sg:address":"932 E Main St",
    "sg:city":"Duncan",
    "sg:classifiers":[
        {
            "category":"Shopping",
            "subcategory":"Used Merchandise",
            "type":"Retail Goods"
        }
    ],
    "sg:phone":"+1 864 439 3353",
    "sg:postcode":"29334",
    "sg:province":"SC",
    "sg:tags":[
        "shop",
        "consignment"
    ],
    "wof:name":"Anna Leighs Consignments",
    "wof:placetype":"venue"
},
  "geometry": {"coordinates":[-82.11901400000001,34.924365],"type":"Point"}
}