{
  "type": "Feature",
  "properties": {
    "addr:full":"109 W Savannah St Calhoun Falls SC 29628",
    "addr:housenumber":"109",
    "addr:postcode":"29628",
    "addr:street":"W Savannah St",
    "iso:country":"US",
    "sg:address":"109 W Savannah St",
    "sg:city":"Calhoun Falls",
    "sg:classifiers":[
        {
            "category":"Banks & Credit Unions",
            "subcategory":"Bank",
            "type":"Services"
        }
    ],
    "sg:phone":"+1 864 447 8539",
    "sg:postcode":"29628",
    "sg:province":"SC",
    "sg:tags":[
        "loan"
    ],
    "wof:name":"Security Finance Corp",
    "wof:placetype":"venue"
},
  "geometry": {"coordinates":[-82.596349,34.092401],"type":"Point"}
}