{
  "type": "Feature",
  "properties": {
    "iso:country":"US",
    "sg:address":"442 Parlock Rd",
    "sg:city":"Irmo",
    "sg:classifiers":[
        {
            "category":"Food & Beverages",
            "subcategory":"Groceries & Convenience Stores",
            "type":"Retail Goods"
        }
    ],
    "sg:phone":"+1 803 407 1540",
    "sg:postcode":"29063",
    "sg:province":"SC",
    "wof:name":"Clark Refining Co Inc",
    "wof:placetype":"venue"
},
  "geometry": {"coordinates":[-81.203891,34.108093],"type":"Point"}
}