{
  "type": "Feature",
  "properties": {
    "addr:full":"503 Duckett St Whitmire SC 29178",
    "addr:housenumber":"503",
    "addr:postcode":"29178",
    "addr:street":"Duckett St",
    "iso:country":"US",
    "sg:address":"503 Duckett St",
    "sg:city":"Whitmire",
    "sg:classifiers":[
        {
            "category":"Organizations",
            "subcategory":"Religious Organization",
            "type":"Services"
        }
    ],
    "sg:phone":"+1 803 694 4647",
    "sg:postcode":"29178",
    "sg:province":"SC",
    "sg:tags":[
        "church"
    ],
    "wof:name":"Friendship Baptist Church",
    "wof:placetype":"venue"
},
  "geometry": {"coordinates":[-81.61949799999999,34.499778],"type":"Point"}
}