{
  "type": "Feature",
  "properties": {
    "iso:country":"US",
    "sg:address":"238 Broughton St",
    "sg:city":"Orangeburg",
    "sg:classifiers":[
        {
            "category":"Home & Garden",
            "subcategory":"Building Materials",
            "type":"Retail Goods"
        }
    ],
    "sg:phone":"+1 803 536 1592",
    "sg:postcode":"29115",
    "sg:province":"SC",
    "sg:tags":[
        "paint"
    ],
    "wof:name":"G & G Paint & Wallpaper Ctr",
    "wof:placetype":"venue"
},
  "geometry": {"coordinates":[-80.854997,33.478787],"type":"Point"}
}