{
  "type": "Feature",
  "properties": {
    "addr:full":"3234 Hoffmeyer Rd Florence SC 29501",
    "addr:housenumber":"3234",
    "addr:postcode":"29501",
    "addr:street":"Hoffmeyer Rd",
    "iso:country":"US",
    "sg:address":"3234 Hoffmeyer Rd",
    "sg:city":"Florence",
    "sg:classifiers":[
        {
            "category":"Social Services",
            "subcategory":"Child Care",
            "type":"Services"
        }
    ],
    "sg:phone":"+1 843 676 0199",
    "sg:postcode":"29501",
    "sg:province":"SC",
    "wof:name":"Heavenly Angels Child Care",
    "wof:placetype":"venue"
},
  "geometry": {"coordinates":[-79.848472,34.208979],"type":"Point"}
}