{
  "type": "Feature",
  "properties": {
    "iso:country":"US",
    "sg:address":"400 Arch St",
    "sg:city":"Spartanburg",
    "sg:classifiers":[
        {
            "category":"Professional",
            "type":"Services"
        }
    ],
    "sg:phone":"+1 864 582 3140",
    "sg:postcode":"29301",
    "sg:province":"SC",
    "sg:tags":[
        "establishment"
    ],
    "wof:name":"Josling Inc",
    "wof:placetype":"venue"
},
  "geometry": {"coordinates":[-81.94835399999999,34.953596],"type":"Point"}
}