{
  "type": "Feature",
  "properties": {
    "addr:full":"2989 Sunset Blvd West Columbia SC 29169",
    "addr:housenumber":"2989",
    "addr:postcode":"29169",
    "addr:street":"Sunset Blvd",
    "iso:country":"US",
    "sg:address":"2989 Sunset Blvd",
    "sg:city":"West Columbia",
    "sg:classifiers":[
        {
            "category":"Health Services",
            "subcategory":"Doctor",
            "type":"Services"
        }
    ],
    "sg:phone":"+1 803 256 4107",
    "sg:postcode":"29169",
    "sg:province":"SC",
    "sg:tags":[
        "physician",
        "surgeon"
    ],
    "wof:name":"Midlands Orthopaedics",
    "wof:placetype":"venue"
},
  "geometry": {"coordinates":[-81.12185100000001,34.00623],"type":"Point"}
}