{
  "type": "Feature",
  "properties": {
    "iso:country":"US",
    "sg:address":"1 Melvin Dr",
    "sg:city":"Greenville",
    "sg:classifiers":[
        {
            "category":"Restaurant",
            "type":"Food & Drink"
        }
    ],
    "sg:menulink":"http://www.allmenus.com/sc/greenville/107679-waffle-house/menu/",
    "sg:phone":"+1 864 277 7470",
    "sg:postcode":"29605",
    "sg:province":"SC",
    "sg:tags":[
        "american"
    ],
    "wof:name":"Waffle House",
    "wof:placetype":"venue"
},
  "geometry": {"coordinates":[-82.37528,34.790802],"type":"Point"}
}