{
  "type": "Feature",
  "properties": {
    "addr:full":"14 Lockwood Dr Charleston SC 29401",
    "addr:housenumber":"14",
    "addr:postcode":"29401",
    "addr:street":"Lockwood Dr",
    "iso:country":"US",
    "sg:address":"14 Lockwood Dr",
    "sg:city":"Charleston",
    "sg:classifiers":[
        {
            "category":"Real Estate",
            "subcategory":"Real Estate Operator",
            "type":"Services"
        }
    ],
    "sg:phone":"+1 843 577 2840",
    "sg:postcode":"29401",
    "sg:province":"SC",
    "sg:tags":[
        "condominium"
    ],
    "wof:name":"Ashley House",
    "wof:placetype":"venue"
},
  "geometry": {"coordinates":[-79.953818,32.78114],"type":"Point"}
}