{
  "type": "Feature",
  "properties": {
    "iso:country":"US",
    "sg:address":"112 Southport Rd",
    "sg:city":"Spartanburg",
    "sg:classifiers":[
        {
            "category":"Building & Trades",
            "subcategory":"Construction",
            "type":"Services"
        }
    ],
    "sg:phone":"+1 864 574 3137",
    "sg:postcode":"29376",
    "sg:province":"SC",
    "sg:tags":[
        "home",
        "contractor",
        "general",
        "new"
    ],
    "wof:name":"Len Reed Construction Inc",
    "wof:placetype":"venue"
},
  "geometry": {"coordinates":[-81.970275,34.920815],"type":"Point"}
}