{
  "type": "Feature",
  "properties": {
    "iso:country":"US",
    "sg:address":"1020 Woodruff Rd",
    "sg:city":"Greenville",
    "sg:classifiers":[
        {
            "category":"Shopping",
            "subcategory":"Jewelry",
            "type":"Retail Goods"
        }
    ],
    "sg:phone":"+1 864 288 4613",
    "sg:postcode":"29607",
    "sg:province":"SC",
    "sg:tags":[
        "jeweler"
    ],
    "wof:name":"Jewelers Gallery Inc",
    "wof:placetype":"venue"
},
  "geometry": {"coordinates":[-82.308752,34.832948],"type":"Point"}
}