{
  "type": "Feature",
  "properties": {
    "addr:full":"148 Tammy St Chesterfield SC 29709",
    "addr:housenumber":"148",
    "addr:postcode":"29709",
    "addr:street":"Tammy St",
    "iso:country":"US",
    "sg:address":"148 Tammy St",
    "sg:city":"Chesterfield",
    "sg:classifiers":[
        {
            "category":"Personal",
            "subcategory":"Beauty Salon",
            "type":"Services"
        }
    ],
    "sg:phone":"+1 843 623 3120",
    "sg:postcode":"29709",
    "sg:province":"SC",
    "wof:name":"Noggins",
    "wof:placetype":"venue"
},
  "geometry": {"coordinates":[-80.108756,34.737837],"type":"Point"}
}