{
  "type": "Feature",
  "properties": {
    "addr:full":"93 Halton Rd Greenville SC 29607",
    "addr:housenumber":"93",
    "addr:postcode":"29607",
    "addr:street":"Halton Rd",
    "iso:country":"US",
    "sg:address":"93 Halton Rd",
    "sg:city":"Greenville",
    "sg:classifiers":[
        {
            "category":"Restaurant",
            "type":"Food & Drink"
        }
    ],
    "sg:phone":"+1 864 987 0630",
    "sg:postcode":"29607",
    "sg:province":"SC",
    "sg:tags":[
        "eating"
    ],
    "wof:name":"Arcobalena Enterprises Inc",
    "wof:placetype":"venue"
},
  "geometry": {"coordinates":[-82.32751399999999,34.844913],"type":"Point"}
}