{
  "type": "Feature",
  "properties": {
    "addr:full":"730 Congaree Rd Greenville SC 29607",
    "addr:housenumber":"730",
    "addr:postcode":"29607",
    "addr:street":"Congaree Rd",
    "iso:country":"US",
    "sg:address":"730 Congaree Rd",
    "sg:city":"Greenville",
    "sg:classifiers":[
        {
            "category":"Wholesale",
            "subcategory":"Machinery & Supplies",
            "type":"Manufacturing & Wholesale Goods"
        }
    ],
    "sg:phone":"+1 864 288 0110",
    "sg:postcode":"29607",
    "sg:province":"SC",
    "sg:tags":[
        "equipment",
        "industrial"
    ],
    "sg:website":"www.grainger.com",
    "wof:name":"Grainger Inc",
    "wof:placetype":"venue"
},
  "geometry": {"coordinates":[-82.321534,34.84354],"type":"Point"}
}