{
  "type": "Feature",
  "properties": {
    "iso:country":"US",
    "sg:address":"4816 Old Church Rd",
    "sg:city":"Pageland",
    "sg:classifiers":[
        {
            "category":"Recreation",
            "type":"Entertainment"
        }
    ],
    "sg:phone":"+1 843 672 7200",
    "sg:postcode":"29720",
    "sg:province":"SC",
    "sg:tags":[
        "course",
        "golf"
    ],
    "wof:name":"Whiteplains Country Club",
    "wof:placetype":"venue"
},
  "geometry": {"coordinates":[-80.797403,34.853874],"type":"Point"}
}