{
  "type": "Feature",
  "properties": {
    "iso:country":"US",
    "sg:address":"865 Detyens Rd",
    "sg:city":"Mt Pleasant",
    "sg:classifiers":[
        {
            "category":"Banks & Credit Unions",
            "subcategory":"Investment Brokerage",
            "type":"Services"
        }
    ],
    "sg:phone":"+1 843 388 0005",
    "sg:postcode":"29464",
    "sg:province":"SC",
    "sg:tags":[
        "consultant",
        "planning",
        "financial"
    ],
    "wof:name":"Cantella & Co Inc",
    "wof:placetype":"venue"
},
  "geometry": {"coordinates":[-79.85504299999999,32.828515],"type":"Point"}
}