{
  "type": "Feature",
  "properties": {
    "iso:country":"US",
    "sg:address":"555 Highland Park Dr SW",
    "sg:city":"Aiken",
    "sg:classifiers":[
        {
            "category":"Restaurant",
            "type":"Food & Drink"
        }
    ],
    "sg:phone":"+1 803 644 2815",
    "sg:postcode":"29801",
    "sg:province":"SC",
    "wof:name":"Legends-The Aiken Golf Club",
    "wof:placetype":"venue"
},
  "geometry": {"coordinates":[-81.730166,33.559386],"type":"Point"}
}