{
  "type": "Feature",
  "properties": {
    "addr:full":"105 N Main St Mauldin SC 29662",
    "addr:housenumber":"105",
    "addr:postcode":"29662",
    "addr:street":"N Main St",
    "iso:country":"US",
    "sg:address":"105 N Main St",
    "sg:city":"Mauldin",
    "sg:classifiers":[
        {
            "category":"Restaurant",
            "type":"Food & Drink"
        }
    ],
    "sg:phone":"+1 864 288 6733",
    "sg:postcode":"29662",
    "sg:province":"SC",
    "sg:tags":[
        "fast"
    ],
    "wof:name":"KFC",
    "wof:placetype":"venue"
},
  "geometry": {"coordinates":[-82.309804,34.778794],"type":"Point"}
}