{
  "type": "Feature",
  "properties": {
    "addr:full":"4943 S Main St Cowpens SC 29330",
    "addr:housenumber":"4943",
    "addr:postcode":"29330",
    "addr:street":"S Main St",
    "iso:country":"US",
    "sg:address":"4943 S Main St",
    "sg:city":"Cowpens",
    "sg:classifiers":[
        {
            "category":"Personal",
            "subcategory":"Beauty Salon",
            "type":"Services"
        }
    ],
    "sg:phone":"+1 864 463 8125",
    "sg:postcode":"29330",
    "sg:province":"SC",
    "wof:name":"Classic Designs",
    "wof:placetype":"venue"
},
  "geometry": {"coordinates":[-81.815175,35.005227],"type":"Point"}
}