{
  "type": "Feature",
  "properties": {
    "addr:full":"6862 Lower Richland Blvd Hopkins SC 29061",
    "addr:housenumber":"6862",
    "addr:postcode":"29061",
    "addr:street":"Lower Richland Blvd",
    "iso:country":"US",
    "sg:address":"6862 Lower Richland Blvd",
    "sg:city":"Hopkins",
    "sg:classifiers":[
        {
            "category":"Social Services",
            "subcategory":"Child Care",
            "type":"Services"
        }
    ],
    "sg:phone":"+1 803 783 5212",
    "sg:postcode":"29061",
    "sg:province":"SC",
    "wof:name":"Tender Years Education Cdc",
    "wof:placetype":"venue"
},
  "geometry": {"coordinates":[-80.88364900000001,33.885882],"type":"Point"}
}