{
  "type": "Feature",
  "properties": {
    "addr:full":"1716 E Palmetto St Florence SC 29506",
    "addr:housenumber":"1716",
    "addr:postcode":"29506",
    "addr:street":"E Palmetto St",
    "iso:country":"US",
    "sg:address":"1716 E Palmetto St",
    "sg:city":"Florence",
    "sg:classifiers":[
        {
            "category":"Freight",
            "type":"Transportation"
        }
    ],
    "sg:phone":"+1 843 669 3281",
    "sg:postcode":"29506",
    "sg:province":"SC",
    "sg:tags":[
        "trailer"
    ],
    "sg:website":"www.neffcorp.com",
    "wof:name":"Neff Rental",
    "wof:placetype":"venue"
},
  "geometry": {"coordinates":[-79.73920200000001,34.196844],"type":"Point"}
}