{
  "type": "Feature",
  "properties": {
    "addr:full":"212 S Lafayette Dr Sumter SC 29150",
    "addr:housenumber":"212",
    "addr:postcode":"29150",
    "addr:street":"S Lafayette Dr",
    "iso:country":"US",
    "sg:address":"212 S Lafayette Dr",
    "sg:city":"Sumter",
    "sg:classifiers":[
        {
            "category":"Home & Garden",
            "subcategory":"Building Materials",
            "type":"Retail Goods"
        }
    ],
    "sg:phone":"+1 803 775 2115",
    "sg:postcode":"29150",
    "sg:province":"SC",
    "sg:tags":[
        "glass",
        "window",
        "plate"
    ],
    "wof:name":"Shadoan's Auto Glass",
    "wof:placetype":"venue"
},
  "geometry": {"coordinates":[-80.33772999999999,33.911315],"type":"Point"}
}