{
  "type": "Feature",
  "properties": {
    "iso:country":"US",
    "sg:address":"1640 Airport Blvd",
    "sg:city":"West Columbia",
    "sg:classifiers":[
        {
            "category":"Autos & Motor Vehicles",
            "subcategory":"Automobile Sales",
            "type":"Retail Goods"
        }
    ],
    "sg:phone":"+1 803 796 6650",
    "sg:postcode":"29169",
    "sg:province":"SC",
    "sg:tags":[
        "car"
    ],
    "wof:name":"Toyota Center Inc",
    "wof:placetype":"venue"
},
  "geometry": {"coordinates":[-81.080803,33.967999],"type":"Point"}
}