{
  "type": "Feature",
  "properties": {
    "addr:full":"7116 Charleston Hwy Bowman SC 29018",
    "addr:housenumber":"7116",
    "addr:postcode":"29018",
    "addr:street":"Charleston Hwy",
    "iso:country":"US",
    "sg:address":"7116 Charleston Hwy",
    "sg:city":"Bowman",
    "sg:classifiers":[
        {
            "category":"Retail",
            "subcategory":"Repair Shop",
            "type":"Services"
        }
    ],
    "sg:phone":"+1 803 829 4242",
    "sg:postcode":"29018",
    "sg:province":"SC",
    "sg:tags":[
        "taxidermist"
    ],
    "wof:name":"Great Outdoors Taxidermy",
    "wof:placetype":"venue"
},
  "geometry": {"coordinates":[-80.682012,33.348294],"type":"Point"}
}