{
  "type": "Feature",
  "properties": {
    "iso:country":"US",
    "sg:address":"401 Western Ln",
    "sg:city":"Irmo",
    "sg:classifiers":[
        {
            "category":"Manufacturing",
            "subcategory":"Tools & Machinery",
            "type":"Manufacturing & Wholesale Goods"
        }
    ],
    "sg:phone":"+1 803 732 7573",
    "sg:postcode":"29063",
    "sg:province":"SC",
    "sg:tags":[
        "textile",
        "parts"
    ],
    "wof:name":"Lummus Corp",
    "wof:placetype":"venue"
},
  "geometry": {"coordinates":[-81.18938799999999,34.113588],"type":"Point"}
}