{
  "type": "Feature",
  "properties": {
    "iso:country":"US",
    "sg:address":"4605 Charlotte Hwy",
    "sg:city":"Lake Wylie",
    "sg:classifiers":[
        {
            "category":"Wholesale",
            "subcategory":"Machinery & Supplies",
            "type":"Manufacturing & Wholesale Goods"
        }
    ],
    "sg:phone":"+1 803 831 1001",
    "sg:postcode":"29710",
    "sg:province":"SC",
    "sg:tags":[
        "equipment",
        "material",
        "handling"
    ],
    "wof:name":"Decker Industries",
    "wof:placetype":"venue"
},
  "geometry": {"coordinates":[-81.109602,35.076265],"type":"Point"}
}