{
  "type": "Feature",
  "properties": {
    "iso:country":"US",
    "sg:address":"4250 Scott St",
    "sg:city":"North Charleston",
    "sg:classifiers":[
        {
            "category":"Shopping",
            "subcategory":"Musical Instruments",
            "type":"Retail Goods"
        }
    ],
    "sg:phone":"+1 843 724 7200",
    "sg:postcode":"29405",
    "sg:province":"SC",
    "sg:tags":[
        "music",
        "sheet",
        "combo"
    ],
    "wof:name":"Fox Music House Inc",
    "wof:placetype":"venue"
},
  "geometry": {"coordinates":[-80.006888,32.854751],"type":"Point"}
}