{
  "type": "Feature",
  "properties": {
    "iso:country":"US",
    "sg:address":"351 E Lakeshore Dr",
    "sg:city":"Landrum",
    "sg:classifiers":[
        {
            "category":"Restaurant",
            "type":"Food & Drink"
        }
    ],
    "sg:phone":"+1 864 457 4789",
    "sg:postcode":"29356",
    "sg:province":"SC",
    "wof:name":"Lake Lanier Tea House",
    "wof:placetype":"venue"
},
  "geometry": {"coordinates":[-82.232074,35.194671],"type":"Point"}
}