{
  "type": "Feature",
  "properties": {
    "addr:full":"100 Ashland Park Ln Columbia SC 29210",
    "addr:housenumber":"100",
    "addr:postcode":"29210",
    "addr:street":"Ashland Park Ln",
    "iso:country":"US",
    "sg:address":"100 Ashland Park Ln",
    "sg:city":"Columbia",
    "sg:classifiers":[
        {
            "category":"Travel",
            "subcategory":"Travel Agent",
            "type":"Entertainment"
        }
    ],
    "sg:phone":"+1 803 798 8122",
    "sg:postcode":"29210",
    "sg:province":"SC",
    "sg:tags":[
        "agency",
        "bureau"
    ],
    "sg:website":"www.travelunlimitedsc.com",
    "wof:name":"Travel Unlimited Inc",
    "wof:placetype":"venue"
},
  "geometry": {"coordinates":[-81.124184,34.043804],"type":"Point"}
}