{
  "type": "Feature",
  "properties": {
    "iso:country":"US",
    "sg:address":"447 Calhoun Ave",
    "sg:city":"Greenwood",
    "sg:classifiers":[
        {
            "category":"Social Services",
            "subcategory":"Child Care",
            "type":"Services"
        }
    ],
    "sg:phone":"+1 864 229 3207",
    "sg:postcode":"29649",
    "sg:province":"SC",
    "wof:name":"Lil Folks",
    "wof:placetype":"venue"
},
  "geometry": {"coordinates":[-82.16971,34.197564],"type":"Point"}
}