{
  "type": "Feature",
  "properties": {
    "iso:country":"US",
    "sg:address":"1616 Hwy 17",
    "sg:city":"North Myrtle Bch",
    "sg:classifiers":[
        {
            "category":"Wholesale",
            "subcategory":"Sporting Goods",
            "type":"Manufacturing & Wholesale Goods"
        }
    ],
    "sg:phone":"+1 843 361 0102",
    "sg:postcode":"29582",
    "sg:province":"SC",
    "sg:tags":[
        "equipment",
        "golf",
        "supply"
    ],
    "wof:name":"Pro-Fit Golf",
    "wof:placetype":"venue"
},
  "geometry": {"coordinates":[-78.65710300000001,33.846642],"type":"Point"}
}