{
  "type": "Feature",
  "properties": {
    "addr:full":"8731 Northpark Blvd North Charleston SC 29406",
    "addr:housenumber":"8731",
    "addr:postcode":"29406",
    "addr:street":"Northpark Blvd",
    "iso:country":"US",
    "sg:address":"8731 Northpark Blvd",
    "sg:city":"North Charleston",
    "sg:classifiers":[
        {
            "category":"Insurance",
            "subcategory":"Insurance Agent",
            "type":"Services"
        }
    ],
    "sg:phone":"+1 843 572 3535",
    "sg:postcode":"29406",
    "sg:province":"SC",
    "wof:name":"Massachusetts Mutual-Blue Chip",
    "wof:placetype":"venue"
},
  "geometry": {"coordinates":[-80.043217,32.966928],"type":"Point"}
}