{
  "type": "Feature",
  "properties": {
    "addr:full":"267 Willowbrook Ave Rock Hill SC 29730",
    "addr:housenumber":"267",
    "addr:postcode":"29730",
    "addr:street":"Willowbrook Ave",
    "iso:country":"US",
    "sg:address":"267 Willowbrook Ave",
    "sg:city":"Rock Hill",
    "sg:classifiers":[
        {
            "category":"Wholesale",
            "subcategory":"Hardware",
            "type":"Manufacturing & Wholesale Goods"
        }
    ],
    "sg:phone":"+1 803 980 8499",
    "sg:postcode":"29730",
    "sg:province":"SC",
    "sg:tags":[
        "equipment",
        "heating",
        "system"
    ],
    "wof:name":"R E Michel Co",
    "wof:placetype":"venue"
},
  "geometry": {"coordinates":[-81.01866,34.931113],"type":"Point"}
}