{
  "type": "Feature",
  "properties": {
    "iso:country":"US",
    "sg:address":"1511 S Batesville Rd",
    "sg:city":"Greer",
    "sg:classifiers":[
        {
            "category":"Manufacturing",
            "subcategory":"Chemicals & Compounds",
            "type":"Manufacturing & Wholesale Goods"
        }
    ],
    "sg:phone":"+1 864 288 4931",
    "sg:postcode":"29650",
    "sg:province":"SC",
    "sg:tags":[
        "mfg",
        "printing",
        "ink"
    ],
    "wof:name":"Coates Inks",
    "wof:placetype":"venue"
},
  "geometry": {"coordinates":[-82.23501899999999,34.859705],"type":"Point"}
}