{
  "type": "Feature",
  "properties": {
    "iso:country":"US",
    "sg:address":"12 Pine Knoll Dr",
    "sg:city":"Greenville",
    "sg:classifiers":[
        {
            "category":"Building & Trades",
            "subcategory":"Construction",
            "type":"Services"
        }
    ],
    "sg:phone":"+1 864 244 4917",
    "sg:postcode":"29609",
    "sg:province":"SC",
    "sg:tags":[
        "waterproofing",
        "contractor"
    ],
    "wof:name":"B Dry",
    "wof:placetype":"venue"
},
  "geometry": {"coordinates":[-82.35884,34.882693],"type":"Point"}
}