{
  "type": "Feature",
  "properties": {
    "iso:country":"US",
    "sg:address":"33 Office Park Rd",
    "sg:city":"Hilton Head Isle",
    "sg:classifiers":[
        {
            "category":"Restaurant",
            "type":"Food & Drink"
        }
    ],
    "sg:phone":"+1 843 686 2233",
    "sg:postcode":"29928",
    "sg:province":"SC",
    "wof:name":"Brick Oven Cafe",
    "wof:placetype":"venue"
},
  "geometry": {"coordinates":[-80.763387,32.15339],"type":"Point"}
}