{
  "type": "Feature",
  "properties": {
    "iso:country":"US",
    "sg:address":"1115 N Ogden St",
    "sg:city":"Florence",
    "sg:classifiers":[
        {
            "category":"Retail",
            "subcategory":"Repair Shop",
            "type":"Services"
        }
    ],
    "sg:phone":"+1 843 669 7391",
    "sg:postcode":"29501",
    "sg:province":"SC",
    "sg:tags":[
        "refinishing",
        "furniture"
    ],
    "wof:name":"Hodges Furniture Shop",
    "wof:placetype":"venue"
},
  "geometry": {"coordinates":[-79.776363,34.212396],"type":"Point"}
}