{
  "type": "Feature",
  "properties": {
    "addr:full":"1254 Chapin Rd Chapin SC 29036",
    "addr:housenumber":"1254",
    "addr:postcode":"29036",
    "addr:street":"Chapin Rd",
    "iso:country":"US",
    "sg:address":"1254 Chapin Rd",
    "sg:city":"Chapin",
    "sg:classifiers":[
        {
            "category":"Banks & Credit Unions",
            "subcategory":"Investment Brokerage",
            "type":"Services"
        }
    ],
    "sg:phone":"+1 803 932 2282",
    "sg:postcode":"29036",
    "sg:province":"SC",
    "sg:tags":[
        "stock",
        "bond"
    ],
    "wof:name":"National Planning Corp",
    "wof:placetype":"venue"
},
  "geometry": {"coordinates":[-81.358227,34.167745],"type":"Point"}
}