{
  "type": "Feature",
  "properties": {
    "addr:full":"2554 W Main St Rock Hill SC 29732",
    "addr:housenumber":"2554",
    "addr:postcode":"29732",
    "addr:street":"W Main St",
    "iso:country":"US",
    "sg:address":"2554 W Main St",
    "sg:city":"Rock Hill",
    "sg:classifiers":[
        {
            "category":"Personal",
            "subcategory":"Tanning Parlor",
            "type":"Services"
        }
    ],
    "sg:phone":"+1 803 327 8268",
    "sg:postcode":"29732",
    "sg:province":"SC",
    "sg:tags":[
        "salon"
    ],
    "wof:name":"Four Seasons Tanning",
    "wof:placetype":"venue"
},
  "geometry": {"coordinates":[-81.081594,34.950177],"type":"Point"}
}