{
  "type": "Feature",
  "properties": {
    "iso:country":"US",
    "sg:address":"522 Gibson Rd",
    "sg:city":"Lexington",
    "sg:classifiers":[
        {
            "category":"Insurance",
            "subcategory":"Hazard Insurance",
            "type":"Services"
        }
    ],
    "sg:phone":"+1 803 996 1121",
    "sg:postcode":"29072",
    "sg:province":"SC",
    "sg:tags":[
        "bond"
    ],
    "wof:name":"National Surety Enterprises",
    "wof:placetype":"venue"
},
  "geometry": {"coordinates":[-81.250038,33.980003],"type":"Point"}
}