{
  "type": "Feature",
  "properties": {
    "addr:full":"308 W Cambridge Ave Greenwood SC 29646",
    "addr:housenumber":"308",
    "addr:postcode":"29646",
    "addr:street":"W Cambridge Ave",
    "iso:country":"US",
    "sg:address":"308 W Cambridge Ave",
    "sg:city":"Greenwood",
    "sg:classifiers":[
        {
            "category":"Insurance",
            "subcategory":"Insurance Agent",
            "type":"Services"
        }
    ],
    "sg:phone":"+1 864 229 0507",
    "sg:postcode":"29646",
    "sg:province":"SC",
    "wof:name":"New York Life Insurance Co",
    "wof:placetype":"venue"
},
  "geometry": {"coordinates":[-82.16906899999999,34.195735],"type":"Point"}
}