{
  "type": "Feature",
  "properties": {
    "iso:country":"US",
    "sg:address":"113 E College St",
    "sg:city":"Simpsonville",
    "sg:classifiers":[
        {
            "category":"Manufacturing",
            "subcategory":"Tools & Machinery",
            "type":"Manufacturing & Wholesale Goods"
        }
    ],
    "sg:phone":"+1 864 962 2400",
    "sg:postcode":"29681",
    "sg:province":"SC",
    "sg:tags":[
        "magnifying",
        "glasses"
    ],
    "wof:name":"Southern Pines Optical",
    "wof:placetype":"venue"
},
  "geometry": {"coordinates":[-82.254845,34.739545],"type":"Point"}
}