{
  "type": "Feature",
  "properties": {
    "iso:country":"US",
    "sg:address":"4724 Charlotte Hwy",
    "sg:city":"Lake Wylie",
    "sg:classifiers":[
        {
            "category":"Shopping",
            "subcategory":"Pharmacy",
            "type":"Retail Goods"
        }
    ],
    "sg:phone":"+1 803 831 1911",
    "sg:postcode":"29710",
    "sg:province":"SC",
    "wof:name":"CVS Pharmacy",
    "wof:placetype":"venue"
},
  "geometry": {"coordinates":[-81.112402,35.0726],"type":"Point"}
}