{
  "type": "Feature",
  "properties": {
    "iso:country":"US",
    "sg:address":"19 S Main St",
    "sg:city":"Travelers Rest",
    "sg:classifiers":[
        {
            "category":"Organizations",
            "subcategory":"Religious Organization",
            "type":"Services"
        }
    ],
    "sg:phone":"+1 864 834 9862",
    "sg:postcode":"29690",
    "sg:province":"SC",
    "sg:tags":[
        "church"
    ],
    "sg:website":"www.trmethodist.org",
    "wof:name":"Travelers Rest United Meth Chr",
    "wof:placetype":"venue"
},
  "geometry": {"coordinates":[-82.441204,34.965591],"type":"Point"}
}