{
  "type": "Feature",
  "properties": {
    "addr:full":"2030 Devine St Columbia SC 29205",
    "addr:housenumber":"2030",
    "addr:postcode":"29205",
    "addr:street":"Devine St",
    "iso:country":"US",
    "sg:address":"2030 Devine St",
    "sg:city":"Columbia",
    "sg:classifiers":[
        {
            "category":"Restaurant",
            "type":"Food & Drink"
        },
        {
            "category":"Food & Beverages",
            "subcategory":"Liquor & Beverages",
            "type":"Retail Goods"
        }
    ],
    "sg:phone":"+1 803 799 0196",
    "sg:postcode":"29205",
    "sg:province":"SC",
    "sg:tags":[
        "beer",
        "spirit",
        "wine"
    ],
    "sg:website":"www.facebook.com/yesterdayssc",
    "wof:name":"Yesterdays Restaurant & Tavern",
    "wof:placetype":"venue"
},
  "geometry": {"coordinates":[-81.016998,33.998501],"type":"Point"}
}