{
  "type": "Feature",
  "properties": {
    "addr:full":"4 Pope Ave Hilton Head Isle SC 29928",
    "addr:housenumber":"4",
    "addr:postcode":"29928",
    "addr:street":"Pope Ave",
    "iso:country":"US",
    "sg:address":"4 Pope Ave",
    "sg:city":"Hilton Head Isle",
    "sg:classifiers":[
        {
            "category":"Banks & Credit Unions",
            "subcategory":"Bank",
            "type":"Services"
        }
    ],
    "sg:phone":"+1 843 341 3200",
    "sg:postcode":"29928",
    "sg:province":"SC",
    "wof:name":"RBC Centura Bank",
    "wof:placetype":"venue"
},
  "geometry": {"coordinates":[-80.757851,32.149937],"type":"Point"}
}