{
  "type": "Feature",
  "properties": {
    "iso:country":"US",
    "sg:address":"207 Dunbarton Dr",
    "sg:city":"Spartanburg",
    "sg:classifiers":[
        {
            "category":"Real Estate",
            "subcategory":"Real Estate Agent",
            "type":"Services"
        }
    ],
    "sg:phone":"+1 864 579 8955",
    "sg:postcode":"29307",
    "sg:province":"SC",
    "wof:name":"Trish Hollon Realtor",
    "wof:placetype":"venue"
},
  "geometry": {"coordinates":[-81.84865000000001,34.956091],"type":"Point"}
}