{
  "type": "Feature",
  "properties": {
    "iso:country":"US",
    "sg:address":"1640 Richland Ave E",
    "sg:city":"Aiken",
    "sg:classifiers":[
        {
            "category":"Restaurant",
            "type":"Food & Drink"
        }
    ],
    "sg:phone":"+1 803 648 7122",
    "sg:postcode":"29801",
    "sg:province":"SC",
    "wof:name":"Southern Delights",
    "wof:placetype":"venue"
},
  "geometry": {"coordinates":[-81.697659,33.553561],"type":"Point"}
}