{
  "type": "Feature",
  "properties": {
    "addr:full":"1222 Ogden Rd Rock Hill SC 29730",
    "addr:housenumber":"1222",
    "addr:postcode":"29730",
    "addr:street":"Ogden Rd",
    "iso:country":"US",
    "sg:address":"1222 Ogden Rd",
    "sg:city":"Rock Hill",
    "sg:classifiers":[
        {
            "category":"Organizations",
            "subcategory":"Religious Organization",
            "type":"Services"
        }
    ],
    "sg:phone":"+1 803 328 1788",
    "sg:postcode":"29730",
    "sg:province":"SC",
    "sg:tags":[
        "church"
    ],
    "wof:name":"Mt Olive United Methodist Chr",
    "wof:placetype":"venue"
},
  "geometry": {"coordinates":[-81.050285,34.916455],"type":"Point"}
}