{
  "type": "Feature",
  "properties": {
    "addr:full":"850 Testie Ln Summerville SC 29483",
    "addr:housenumber":"850",
    "addr:postcode":"29483",
    "addr:street":"Testie Ln",
    "iso:country":"US",
    "sg:address":"850 Testie Ln",
    "sg:city":"Summerville",
    "sg:classifiers":[
        {
            "category":"Freight",
            "type":"Transportation"
        }
    ],
    "sg:phone":"+1 843 832 6811",
    "sg:postcode":"29483",
    "sg:province":"SC",
    "sg:tags":[
        "operator",
        "hauling",
        "trucking"
    ],
    "wof:name":"Dale's Equipment Transport",
    "wof:placetype":"venue"
},
  "geometry": {"coordinates":[-80.177038,33.083388],"type":"Point"}
}