{
  "type": "Feature",
  "properties": {
    "iso:country":"US",
    "sg:address":"205 S 5th Ave",
    "sg:city":"Dillon",
    "sg:classifiers":[
        {
            "category":"Utilities",
            "subcategory":"Water",
            "type":"Services"
        }
    ],
    "sg:phone":"+1 843 774 4802",
    "sg:postcode":"29536",
    "sg:province":"SC",
    "sg:tags":[
        "system",
        "supply"
    ],
    "wof:name":"Trico Water Co",
    "wof:placetype":"venue"
},
  "geometry": {"coordinates":[-79.37629,34.417996],"type":"Point"}
}