{
  "type": "Feature",
  "properties": {
    "addr:full":"601 S Main St Marion SC 29571",
    "addr:housenumber":"601",
    "addr:postcode":"29571",
    "addr:street":"S Main St",
    "iso:country":"US",
    "sg:address":"601 S Main St",
    "sg:city":"Marion",
    "sg:classifiers":[
        {
            "category":"Shopping",
            "subcategory":"Used Merchandise",
            "type":"Retail Goods"
        }
    ],
    "sg:phone":"+1 843 275 0468",
    "sg:postcode":"29571",
    "sg:province":"SC",
    "sg:tags":[
        "pawnbroker"
    ],
    "wof:name":"Caleb's Corner",
    "wof:placetype":"venue"
},
  "geometry": {"coordinates":[-79.40043799999999,34.172073],"type":"Point"}
}