{
  "type": "Feature",
  "properties": {
    "iso:country":"US",
    "sg:address":"1440 Five Chop Rd",
    "sg:city":"Orangeburg",
    "sg:classifiers":[
        {
            "category":"Travel",
            "subcategory":"Hotels & Motels",
            "type":"Entertainment"
        }
    ],
    "sg:phone":"+1 803 534 5081",
    "sg:postcode":"29115",
    "sg:province":"SC",
    "wof:name":"Slumberland Motel",
    "wof:placetype":"venue"
},
  "geometry": {"coordinates":[-80.817228,33.477661],"type":"Point"}
}