{
  "type": "Feature",
  "properties": {
    "iso:country":"US",
    "sg:address":"1457 Leesburg Rd",
    "sg:city":"Columbia",
    "sg:classifiers":[
        {
            "category":"Real Estate",
            "subcategory":"Real Estate Agent",
            "type":"Services"
        }
    ],
    "sg:phone":"+1 803 783 0101",
    "sg:postcode":"29209",
    "sg:province":"SC",
    "wof:name":"Homevestors",
    "wof:placetype":"venue"
},
  "geometry": {"coordinates":[-80.936267,33.975595],"type":"Point"}
}