{
  "type": "Feature",
  "properties": {
    "iso:country":"US",
    "sg:address":"2910 Abbeville Hwy",
    "sg:city":"Anderson",
    "sg:classifiers":[
        {
            "category":"Retail",
            "subcategory":"Laundry & Dry Cleaning",
            "type":"Services"
        }
    ],
    "sg:phone":"+1 864 296 9717",
    "sg:postcode":"29624",
    "sg:province":"SC",
    "sg:tags":[
        "gown",
        "bridal",
        "preservation"
    ],
    "wof:name":"Superior Cleaners",
    "wof:placetype":"venue"
},
  "geometry": {"coordinates":[-82.651573,34.472849],"type":"Point"}
}