{
  "type": "Feature",
  "properties": {
    "addr:full":"310 Broad St Charleston SC 29401",
    "addr:housenumber":"310",
    "addr:postcode":"29401",
    "addr:street":"Broad St",
    "iso:country":"US",
    "sg:address":"310 Broad St",
    "sg:city":"Charleston",
    "sg:classifiers":[
        {
            "category":"Professional",
            "subcategory":"Art Services",
            "type":"Services"
        }
    ],
    "sg:phone":"+1 843 571 5222",
    "sg:postcode":"29401",
    "sg:province":"SC",
    "sg:tags":[
        "photographer"
    ],
    "wof:name":"KIRK Prouty Photography",
    "wof:placetype":"venue"
},
  "geometry": {"coordinates":[-79.94126900000001,32.775556],"type":"Point"}
}