{
  "type": "Feature",
  "properties": {
    "addr:full":"2125 Old Spartanburg Rd Greer SC 29650",
    "addr:housenumber":"2125",
    "addr:postcode":"29650",
    "addr:street":"Old Spartanburg Rd",
    "iso:country":"US",
    "sg:address":"2125 Old Spartanburg Rd",
    "sg:city":"Greer",
    "sg:classifiers":[
        {
            "category":"Travel",
            "subcategory":"Travel Agent",
            "type":"Entertainment"
        }
    ],
    "sg:phone":"+1 864 292 0345",
    "sg:postcode":"29650",
    "sg:province":"SC",
    "sg:tags":[
        "agency",
        "bureau"
    ],
    "wof:name":"Travel Planners",
    "wof:placetype":"venue"
},
  "geometry": {"coordinates":[-82.29101799999999,34.892467],"type":"Point"}
}