{
  "type": "Feature",
  "properties": {
    "iso:country":"US",
    "sg:address":"7 Lost Hollow Ln",
    "sg:city":"Bluffton",
    "sg:classifiers":[
        {
            "category":"Shopping",
            "type":"Retail Goods"
        }
    ],
    "sg:phone":"+1 843 815 6119",
    "sg:postcode":"29910",
    "sg:province":"SC",
    "sg:tags":[
        "cosmetic",
        "perfume"
    ],
    "wof:name":"United States Sports Lip Balm",
    "wof:placetype":"venue"
},
  "geometry": {"coordinates":[-80.85258,32.235204],"type":"Point"}
}