{
  "type": "Feature",
  "properties": {
    "addr:full":"1027 Elmwood Ave Columbia SC 29201",
    "addr:housenumber":"1027",
    "addr:postcode":"29201",
    "addr:street":"Elmwood Ave",
    "iso:country":"US",
    "sg:address":"1027 Elmwood Ave",
    "sg:city":"Columbia",
    "sg:classifiers":[
        {
            "category":"Food & Beverages",
            "subcategory":"Groceries & Convenience Stores",
            "type":"Retail Goods"
        }
    ],
    "sg:phone":"+1 803 254 5838",
    "sg:postcode":"29201",
    "sg:province":"SC",
    "wof:name":"Market Express Convenience Store",
    "wof:placetype":"venue"
},
  "geometry": {"coordinates":[-81.0411,34.012901],"type":"Point"}
}