{
  "type": "Feature",
  "properties": {
    "iso:country":"US",
    "sg:address":"116 Wofford Rd",
    "sg:city":"Gaffney",
    "sg:classifiers":[
        {
            "category":"Building & Trades",
            "subcategory":"Construction",
            "type":"Services"
        }
    ],
    "sg:phone":"+1 864 902 8007",
    "sg:postcode":"29340",
    "sg:province":"SC",
    "sg:tags":[
        "house"
    ],
    "wof:name":"Sks Construction",
    "wof:placetype":"venue"
},
  "geometry": {"coordinates":[-81.522659,34.973045],"type":"Point"}
}