{
  "type": "Feature",
  "properties": {
    "addr:full":"7 Gamecock Ave Charleston SC 29407",
    "addr:housenumber":"7",
    "addr:postcode":"29407",
    "addr:street":"Gamecock Ave",
    "iso:country":"US",
    "sg:address":"7 Gamecock Ave",
    "sg:city":"Charleston",
    "sg:classifiers":[
        {
            "category":"Professional",
            "subcategory":"Accounting & Tax Preparation",
            "type":"Services"
        }
    ],
    "sg:phone":"+1 843 766 3465",
    "sg:postcode":"29407",
    "sg:province":"SC",
    "sg:tags":[
        "accountant"
    ],
    "wof:name":"Brandon J Hoffman CPA",
    "wof:placetype":"venue"
},
  "geometry": {"coordinates":[-79.993619,32.819827],"type":"Point"}
}