{
  "type": "Feature",
  "properties": {
    "addr:full":"400 Market St Cheraw SC 29520",
    "addr:housenumber":"400",
    "addr:postcode":"29520",
    "addr:street":"Market St",
    "iso:country":"US",
    "sg:address":"400 Market St",
    "sg:city":"Cheraw",
    "sg:classifiers":[
        {
            "category":"Banks & Credit Unions",
            "subcategory":"Bank",
            "type":"Services"
        }
    ],
    "sg:phone":"+1 843 537 2193",
    "sg:postcode":"29520",
    "sg:province":"SC",
    "sg:tags":[
        "loan"
    ],
    "wof:name":"Citi Financial",
    "wof:placetype":"venue"
},
  "geometry": {"coordinates":[-79.887272,34.695412],"type":"Point"}
}