{
  "type": "Feature",
  "properties": {
    "iso:country":"US",
    "sg:address":"116 Ashbury Dr",
    "sg:city":"Simpsonville",
    "sg:classifiers":[
        {
            "category":"Professional",
            "subcategory":"Employment Agencies",
            "type":"Services"
        }
    ],
    "sg:phone":"+1 864 254 0866",
    "sg:postcode":"29681",
    "sg:province":"SC",
    "sg:tags":[
        "opportunity"
    ],
    "wof:name":"Management Recruiters",
    "wof:placetype":"venue"
},
  "geometry": {"coordinates":[-82.25402,34.824769],"type":"Point"}
}