{
  "type": "Feature",
  "properties": {
    "iso:country":"US",
    "sg:address":"253 E Savannah St",
    "sg:city":"Calhoun Falls",
    "sg:classifiers":[
        {
            "category":"Banks & Credit Unions",
            "subcategory":"Bank",
            "type":"Services"
        }
    ],
    "sg:phone":"+1 864 447 8541",
    "sg:postcode":"29628",
    "sg:province":"SC",
    "sg:tags":[
        "state"
    ],
    "wof:name":"Capitol Bank & Trust",
    "wof:placetype":"venue"
},
  "geometry": {"coordinates":[-82.593159,34.091159],"type":"Point"}
}