{
  "type": "Feature",
  "properties": {
    "addr:full":"1224 Whitney St Columbia SC 29201",
    "addr:housenumber":"1224",
    "addr:postcode":"29201",
    "addr:street":"Whitney St",
    "iso:country":"US",
    "sg:address":"1224 Whitney St",
    "sg:city":"Columbia",
    "sg:classifiers":[
        {
            "category":"Wholesale",
            "subcategory":"Machinery & Supplies",
            "type":"Manufacturing & Wholesale Goods"
        }
    ],
    "sg:phone":"+1 803 733 3018",
    "sg:postcode":"29201",
    "sg:province":"SC",
    "sg:tags":[
        "elementary",
        "school"
    ],
    "sg:website":"www.richlandone.org",
    "wof:name":"Richland County Schools",
    "wof:placetype":"venue"
},
  "geometry": {"coordinates":[-81.03028500000001,33.97648],"type":"Point"}
}