{
  "type": "Feature",
  "properties": {
    "iso:country":"US",
    "sg:address":"3788 Whetstone Rd",
    "sg:city":"North",
    "sg:classifiers":[
        {
            "category":"Building & Trades",
            "subcategory":"Electrical",
            "type":"Services"
        }
    ],
    "sg:phone":"+1 803 247 5173",
    "sg:postcode":"29112",
    "sg:province":"SC",
    "sg:tags":[
        "electrician"
    ],
    "wof:name":"B & B Heating & Cooling",
    "wof:placetype":"venue"
},
  "geometry": {"coordinates":[-81.212716,33.623343],"type":"Point"}
}