{
  "type": "Feature",
  "properties": {
    "addr:full":"8780 Rivers Ave North Charleston SC 29406",
    "addr:housenumber":"8780",
    "addr:postcode":"29406",
    "addr:street":"Rivers Ave",
    "iso:country":"US",
    "sg:address":"8780 Rivers Ave",
    "sg:city":"North Charleston",
    "sg:classifiers":[
        {
            "category":"Real Estate",
            "subcategory":"Real Estate Agent",
            "type":"Services"
        }
    ],
    "sg:phone":"+1 843 553 3434",
    "sg:postcode":"29406",
    "sg:province":"SC",
    "wof:name":"Home Finders Real Estate",
    "wof:placetype":"venue"
},
  "geometry": {"coordinates":[-80.044425,32.967468],"type":"Point"}
}