{
  "type": "Feature",
  "properties": {
    "addr:full":"135 McGaha Rd Easley SC 29640",
    "addr:housenumber":"135",
    "addr:postcode":"29640",
    "addr:street":"Mcgaha Rd",
    "iso:country":"US",
    "sg:address":"135 McGaha Rd",
    "sg:city":"Easley",
    "sg:classifiers":[
        {
            "category":"Manufacturing",
            "subcategory":"Lumber",
            "type":"Manufacturing & Wholesale Goods"
        }
    ],
    "sg:phone":"+1 864 859 4729",
    "sg:postcode":"29640",
    "sg:province":"SC",
    "sg:tags":[
        "logging"
    ],
    "wof:name":"Watson Logging",
    "wof:placetype":"venue"
},
  "geometry": {"coordinates":[-82.65171599999999,34.842285],"type":"Point"}
}