{
  "type": "Feature",
  "properties": {
    "iso:country":"US",
    "sg:address":"1326 Bush River Rd",
    "sg:city":"Columbia",
    "sg:classifiers":[
        {
            "category":"Health Services",
            "subcategory":"Optometrist",
            "type":"Services"
        },
        {
            "category":"Shopping",
            "subcategory":"Optician",
            "type":"Retail Goods"
        }
    ],
    "sg:phone":"+1 803 750 4949",
    "sg:postcode":"29210",
    "sg:province":"SC",
    "sg:tags":[
        "eyewear"
    ],
    "sg:website":"www.midlandsvision.com",
    "wof:name":"Midlands Vision Associates",
    "wof:placetype":"venue"
},
  "geometry": {"coordinates":[-81.108569,34.031039],"type":"Point"}
}