{
  "type": "Feature",
  "properties": {
    "iso:country":"US",
    "sg:address":"16 Mills Ave",
    "sg:city":"Greenville",
    "sg:classifiers":[
        {
            "category":"Health Services",
            "subcategory":"Doctor",
            "type":"Services"
        }
    ],
    "sg:phone":"+1 864 271 3463",
    "sg:postcode":"29605",
    "sg:province":"SC",
    "sg:tags":[
        "dentist"
    ],
    "wof:name":"Caring Family Dentistry",
    "wof:placetype":"venue"
},
  "geometry": {"coordinates":[-82.405736,34.831187],"type":"Point"}
}