{
  "type": "Feature",
  "properties": {
    "addr:full":"2 Flint St York SC 29745",
    "addr:housenumber":"2",
    "addr:postcode":"29745",
    "addr:street":"Flint St",
    "iso:country":"US",
    "sg:address":"2 Flint St",
    "sg:city":"York",
    "sg:classifiers":[
        {
            "category":"Banks & Credit Unions",
            "subcategory":"Bank",
            "type":"Services"
        }
    ],
    "sg:phone":"+1 803 628 7511",
    "sg:postcode":"29745",
    "sg:province":"SC",
    "sg:tags":[
        "institution",
        "business"
    ],
    "wof:name":"Fast Cash Advance of York",
    "wof:placetype":"venue"
},
  "geometry": {"coordinates":[-81.22678999999999,34.98918],"type":"Point"}
}