{
  "type": "Feature",
  "properties": {
    "iso:country":"US",
    "sg:address":"1952 Barnes Station Rd",
    "sg:city":"Iva",
    "sg:classifiers":[
        {
            "category":"Food & Beverages",
            "subcategory":"Liquor & Beverages",
            "type":"Retail Goods"
        },
        {
            "category":"Bars & Pubs",
            "type":"Food & Drink"
        }
    ],
    "sg:phone":"+1 864 348 2849",
    "sg:postcode":"29655",
    "sg:province":"SC",
    "sg:tags":[
        "alcoholic"
    ],
    "wof:name":"S & S Party Store",
    "wof:placetype":"venue"
},
  "geometry": {"coordinates":[-82.674504,34.236309],"type":"Point"}
}