{
  "type": "Feature",
  "properties": {
    "addr:full":"3215 N Pleasantburg Dr Greenville SC 29609",
    "addr:housenumber":"3215",
    "addr:postcode":"29609",
    "addr:street":"N Pleasantburg Dr",
    "iso:country":"US",
    "sg:address":"3215 N Pleasantburg Dr",
    "sg:city":"Greenville",
    "sg:classifiers":[
        {
            "category":"Home & Garden",
            "subcategory":"Home Furnishings",
            "type":"Retail Goods"
        }
    ],
    "sg:phone":"+1 864 232 7427",
    "sg:postcode":"29609",
    "sg:province":"SC",
    "wof:name":"Pier 1",
    "wof:placetype":"venue"
},
  "geometry": {"coordinates":[-82.40089999999999,34.889885],"type":"Point"}
}