{
  "type": "Feature",
  "properties": {
    "addr:full":"792 Sugar Creek Rd Buffalo SC 29321",
    "addr:housenumber":"792",
    "addr:postcode":"29321",
    "addr:street":"Sugar Creek Rd",
    "iso:country":"US",
    "sg:address":"792 Sugar Creek Rd",
    "sg:city":"Buffalo",
    "sg:classifiers":[
        {
            "category":"Freight",
            "type":"Transportation"
        }
    ],
    "sg:phone":"+1 864 427 4634",
    "sg:postcode":"29321",
    "sg:province":"SC",
    "sg:tags":[
        "retail",
        "trucking"
    ],
    "wof:name":"Michael B Ivey",
    "wof:placetype":"venue"
},
  "geometry": {"coordinates":[-81.757396,34.692936],"type":"Point"}
}