{
  "type": "Feature",
  "properties": {
    "iso:country":"US",
    "sg:address":"95 Montgomery Rd",
    "sg:city":"Lyman",
    "sg:classifiers":[
        {
            "category":"Retail",
            "subcategory":"Repair Shop",
            "type":"Services"
        }
    ],
    "sg:phone":"+1 864 439 6140",
    "sg:postcode":"29365",
    "sg:province":"SC",
    "sg:tags":[
        "appliance"
    ],
    "wof:name":"Benson Refrigeration/Appliance",
    "wof:placetype":"venue"
},
  "geometry": {"coordinates":[-82.15416999999999,34.992141],"type":"Point"}
}