{
  "type": "Feature",
  "properties": {
    "iso:country":"US",
    "sg:address":"125 Love Ln",
    "sg:city":"Summerville",
    "sg:classifiers":[
        {
            "category":"Building & Trades",
            "subcategory":"Construction",
            "type":"Services"
        }
    ],
    "sg:phone":"+1 843 821 6480",
    "sg:postcode":"29483",
    "sg:province":"SC",
    "sg:tags":[
        "home",
        "builder"
    ],
    "wof:name":"Prestige Home Builders",
    "wof:placetype":"venue"
},
  "geometry": {"coordinates":[-80.14693200000001,33.095443],"type":"Point"}
}