{
  "type": "Feature",
  "properties": {
    "addr:full":"1015 Butler St Columbia SC 29205",
    "addr:housenumber":"1015",
    "addr:postcode":"29205",
    "addr:street":"Butler St",
    "iso:country":"US",
    "sg:address":"1015 Butler St",
    "sg:city":"Columbia",
    "sg:classifiers":[
        {
            "category":"Retail",
            "subcategory":"Animal Services",
            "type":"Services"
        }
    ],
    "sg:phone":"+1 803 252 1080",
    "sg:postcode":"29205",
    "sg:province":"SC",
    "sg:tags":[
        "pet",
        "grooming",
        "washing"
    ],
    "wof:name":"Groomingdale's Inc",
    "wof:placetype":"venue"
},
  "geometry": {"coordinates":[-80.997494,34.0025],"type":"Point"}
}