{
  "type": "Feature",
  "properties": {
    "addr:full":"381 E Pine Logging Rd Aiken SC 29803",
    "addr:housenumber":"381",
    "addr:postcode":"29803",
    "addr:street":"E Pine Logging Rd",
    "iso:country":"US",
    "sg:address":"381 E Pine Logging Rd",
    "sg:city":"Aiken",
    "sg:classifiers":[
        {
            "category":"Personal",
            "subcategory":"Beauty Salon",
            "type":"Services"
        }
    ],
    "sg:phone":"+1 803 648 6542",
    "sg:postcode":"29803",
    "sg:province":"SC",
    "wof:name":"Rhonda's Beauty Salon",
    "wof:placetype":"venue"
},
  "geometry": {"coordinates":[-81.71099,33.527072],"type":"Point"}
}