{
  "type": "Feature",
  "properties": {
    "iso:country":"US",
    "sg:address":"4863 N Hwy 17",
    "sg:city":"Awendaw",
    "sg:classifiers":[
        {
            "category":"Building & Trades",
            "subcategory":"Landscaping Services",
            "type":"Services"
        }
    ],
    "sg:phone":"+1 843 928 4161",
    "sg:postcode":"29429",
    "sg:province":"SC",
    "sg:tags":[
        "landscape",
        "contractor"
    ],
    "wof:name":"Lawn Rangers",
    "wof:placetype":"venue"
},
  "geometry": {"coordinates":[-79.71301200000001,32.931537],"type":"Point"}
}