{
  "type": "Feature",
  "properties": {
    "iso:country":"US",
    "sg:address":"224 Crest Dr",
    "sg:city":"Easley",
    "sg:classifiers":[
        {
            "category":"Wholesale",
            "subcategory":"Construction Materials",
            "type":"Manufacturing & Wholesale Goods"
        }
    ],
    "sg:phone":"+1 864 850 6388",
    "sg:postcode":"29640",
    "sg:province":"SC",
    "sg:tags":[
        "lumber",
        "plywood"
    ],
    "wof:name":"D Cass Company",
    "wof:placetype":"venue"
},
  "geometry": {"coordinates":[-82.549665,34.841903],"type":"Point"}
}