{
  "type": "Feature",
  "properties": {
    "addr:full":"619 Coquina Ave Murrells Inlet SC 29576",
    "addr:housenumber":"619",
    "addr:postcode":"29576",
    "addr:street":"Coquina Ave",
    "iso:country":"US",
    "sg:address":"619 Coquina Ave",
    "sg:city":"Murrells Inlet",
    "sg:classifiers":[
        {
            "category":"Wholesale",
            "subcategory":"Poultry",
            "type":"Manufacturing & Wholesale Goods"
        }
    ],
    "sg:phone":"+1 843 651 2711",
    "sg:postcode":"29576",
    "sg:province":"SC",
    "wof:name":"Prestige Farms",
    "wof:placetype":"venue"
},
  "geometry": {"coordinates":[-79.04603899999999,33.546075],"type":"Point"}
}