{
  "type": "Feature",
  "properties": {
    "iso:country":"US",
    "sg:address":"1407 Marion Ave",
    "sg:city":"Florence",
    "sg:classifiers":[
        {
            "category":"Utilities",
            "subcategory":"Mobile Phone",
            "type":"Services"
        }
    ],
    "sg:phone":"+1 843 667 0735",
    "sg:postcode":"29505",
    "sg:province":"SC",
    "sg:tags":[
        "repair",
        "beeper"
    ],
    "wof:name":"Royal Communications",
    "wof:placetype":"venue"
},
  "geometry": {"coordinates":[-79.78071,34.167699],"type":"Point"}
}