{
  "type": "Feature",
  "properties": {
    "iso:country":"US",
    "sg:address":"101 Arabian Dr",
    "sg:city":"Summerville",
    "sg:classifiers":[
        {
            "category":"Building & Trades",
            "subcategory":"Construction",
            "type":"Services"
        }
    ],
    "sg:phone":"+1 843 871 3952",
    "sg:postcode":"29483",
    "sg:province":"SC",
    "sg:tags":[
        "house"
    ],
    "wof:name":"Fox Construction Company Inc",
    "wof:placetype":"venue"
},
  "geometry": {"coordinates":[-80.21314099999999,33.077742],"type":"Point"}
}