{
  "type": "Feature",
  "properties": {
    "addr:full":"2100 Five Chop Rd Orangeburg SC 29115",
    "addr:housenumber":"2100",
    "addr:postcode":"29115",
    "addr:street":"Five Chop Rd",
    "iso:country":"US",
    "sg:address":"2100 Five Chop Rd",
    "sg:city":"Orangeburg",
    "sg:classifiers":[
        {
            "category":"Shopping",
            "type":"Retail Goods"
        }
    ],
    "sg:phone":"+1 803 531 4323",
    "sg:postcode":"29115",
    "sg:province":"SC",
    "sg:tags":[
        "awning",
        "canopy"
    ],
    "wof:name":"Aronson Awning Co",
    "wof:placetype":"venue"
},
  "geometry": {"coordinates":[-80.798591,33.469813],"type":"Point"}
}