{
  "type": "Feature",
  "properties": {
    "iso:country":"US",
    "sg:address":"12 Fawn Ln",
    "sg:city":"Hilton Head Island",
    "sg:classifiers":[
        {
            "category":"Real Estate",
            "subcategory":"Real Estate Agent",
            "type":"Services"
        }
    ],
    "sg:phone":"+1 843 671 4212",
    "sg:postcode":"29928",
    "sg:province":"SC",
    "wof:name":"Harbour Beacon Inc",
    "wof:placetype":"venue"
},
  "geometry": {"coordinates":[-80.76953899999999,32.160724],"type":"Point"}
}