{
  "type": "Feature",
  "properties": {
    "addr:full":"3 Cateechee Ave Greenville SC 29605",
    "addr:housenumber":"3",
    "addr:postcode":"29605",
    "addr:street":"Cateechee Ave",
    "iso:country":"US",
    "sg:address":"3 Cateechee Ave",
    "sg:city":"Greenville",
    "sg:classifiers":[
        {
            "category":"Shopping",
            "subcategory":"Clothing, Apparel, & Fashions",
            "type":"Retail Goods"
        }
    ],
    "sg:phone":"+1 864 235 2700",
    "sg:postcode":"29605",
    "sg:province":"SC",
    "sg:tags":[
        "infant",
        "wear"
    ],
    "wof:name":"Some Day's Child Heirlooms",
    "wof:placetype":"venue"
},
  "geometry": {"coordinates":[-82.401856,34.828855],"type":"Point"}
}