{
  "type": "Feature",
  "properties": {
    "addr:full":"1670 Springdale Dr Camden SC 29020",
    "addr:housenumber":"1670",
    "addr:postcode":"29020",
    "addr:street":"Springdale Dr",
    "iso:country":"US",
    "sg:address":"1670 Springdale Dr",
    "sg:city":"Camden",
    "sg:classifiers":[
        {
            "category":"Professional",
            "subcategory":"Advertising",
            "type":"Services"
        }
    ],
    "sg:phone":"+1 803 425 9623",
    "sg:postcode":"29020",
    "sg:province":"SC",
    "sg:tags":[
        "mailing",
        "shipping"
    ],
    "wof:name":"UPS Store",
    "wof:placetype":"venue"
},
  "geometry": {"coordinates":[-80.64119599999999,34.255035],"type":"Point"}
}