{
  "type": "Feature",
  "properties": {
    "addr:full":"2375 Baker Hospital Blvd Charleston SC 29405",
    "addr:housenumber":"2375",
    "addr:postcode":"29405",
    "addr:street":"Baker Hospital Blvd",
    "iso:country":"US",
    "sg:address":"2375 Baker Hospital Blvd",
    "sg:city":"Charleston",
    "sg:classifiers":[
        {
            "category":"Health Services",
            "subcategory":"Nursing And Care Facility",
            "type":"Services"
        }
    ],
    "sg:phone":"+1 843 744 2750",
    "sg:postcode":"29405",
    "sg:province":"SC",
    "sg:tags":[
        "home",
        "convalescent"
    ],
    "wof:name":"Driftwood Rehabilitation & Nur",
    "wof:placetype":"venue"
},
  "geometry": {"coordinates":[-79.97018199999999,32.839366],"type":"Point"}
}