{
  "type": "Feature",
  "properties": {
    "iso:country":"US",
    "sg:address":"207 N Main St",
    "sg:city":"Saluda",
    "sg:classifiers":[
        {
            "category":"Banks & Credit Unions",
            "subcategory":"Investment Brokerage",
            "type":"Services"
        },
        {
            "category":"Insurance",
            "subcategory":"Hazard Insurance",
            "type":"Services"
        }
    ],
    "sg:phone":"+1 864 445 2342",
    "sg:postcode":"29138",
    "sg:province":"SC",
    "sg:tags":[
        "commercial",
        "agent",
        "business",
        "resume"
    ],
    "wof:name":"Smith, Don Insurance Agency",
    "wof:placetype":"venue"
},
  "geometry": {"coordinates":[-81.772504,34.004582],"type":"Point"}
}