{
  "type": "Feature",
  "properties": {
    "iso:country":"US",
    "sg:address":"722 Elm St W",
    "sg:city":"Hampton",
    "sg:classifiers":[
        {
            "category":"Restaurant",
            "type":"Food & Drink"
        }
    ],
    "sg:phone":"+1 803 943 3002",
    "sg:postcode":"29924",
    "sg:province":"SC",
    "wof:name":"Ernie's Restaurant",
    "wof:placetype":"venue"
},
  "geometry": {"coordinates":[-81.115906,32.872323],"type":"Point"}
}