{
  "type": "Feature",
  "properties": {
    "addr:full":"403 Clarendon St SE Orangeburg SC 29115",
    "addr:housenumber":"403",
    "addr:postcode":"29115",
    "addr:street":"Clarendon St Se",
    "iso:country":"US",
    "sg:address":"403 Clarendon St SE",
    "sg:city":"Orangeburg",
    "sg:classifiers":[
        {
            "category":"Real Estate",
            "subcategory":"Real Estate Agent",
            "type":"Services"
        }
    ],
    "sg:phone":"+1 919 880 0459",
    "sg:postcode":"29115",
    "sg:province":"SC",
    "sg:tags":[
        "insurance",
        "investment"
    ],
    "wof:name":"Goshen Real Estate",
    "wof:placetype":"venue"
},
  "geometry": {"coordinates":[-80.845654,33.492175],"type":"Point"}
}