{
  "type": "Feature",
  "properties": {
    "addr:full":"138 Loran Pointe Cir Seneca SC 29672",
    "addr:housenumber":"138",
    "addr:postcode":"29672",
    "addr:street":"Loran Pointe Cir",
    "iso:country":"US",
    "sg:address":"138 Loran Pointe Cir",
    "sg:city":"Seneca",
    "sg:classifiers":[
        {
            "category":"Professional",
            "subcategory":"Business Services",
            "type":"Services"
        }
    ],
    "sg:phone":"+1 864 885 9706",
    "sg:postcode":"29672",
    "sg:province":"SC",
    "wof:name":"Faires & Assoc",
    "wof:placetype":"venue"
},
  "geometry": {"coordinates":[-82.94623,34.705058],"type":"Point"}
}