{
  "type": "Feature",
  "properties": {
    "addr:full":"115 Midge Creek Ct Chapin SC 29036",
    "addr:housenumber":"115",
    "addr:postcode":"29036",
    "addr:street":"Midge Creek Ct",
    "iso:country":"US",
    "sg:address":"115 Midge Creek Ct",
    "sg:city":"Chapin",
    "sg:classifiers":[
        {
            "category":"Building & Trades",
            "subcategory":"Landscaping Services",
            "type":"Services"
        }
    ],
    "sg:phone":"+1 803 345 6565",
    "sg:postcode":"29036",
    "sg:province":"SC",
    "sg:tags":[
        "landscape",
        "contractor"
    ],
    "wof:name":"David E Booth Landscape Archit",
    "wof:placetype":"venue"
},
  "geometry": {"coordinates":[-81.347673,34.139808],"type":"Point"}
}