{
  "type": "Feature",
  "properties": {
    "iso:country":"US",
    "sg:address":"4447 Dorchester Rd",
    "sg:city":"Charleston",
    "sg:classifiers":[
        {
            "category":"Wholesale",
            "subcategory":"Electrical",
            "type":"Manufacturing & Wholesale Goods"
        }
    ],
    "sg:phone":"+1 843 554 9701",
    "sg:postcode":"29405",
    "sg:province":"SC",
    "sg:tags":[
        "equipment",
        "electric",
        "supply"
    ],
    "wof:name":"Eck Supply Co",
    "wof:placetype":"venue"
},
  "geometry": {"coordinates":[-80.01440100000001,32.854292],"type":"Point"}
}