{
  "type": "Feature",
  "properties": {
    "addr:full":"59 Willis St Yemassee SC 29945",
    "addr:housenumber":"59",
    "addr:postcode":"29945",
    "addr:street":"Willis St",
    "iso:country":"US",
    "sg:address":"59 Willis St",
    "sg:city":"Yemassee",
    "sg:classifiers":[
        {
            "category":"Building & Trades",
            "subcategory":"Construction",
            "type":"Services"
        }
    ],
    "sg:phone":"+1 843 589 8005",
    "sg:postcode":"29945",
    "sg:province":"SC",
    "sg:tags":[
        "residential"
    ],
    "wof:name":"Center Point LLC",
    "wof:placetype":"venue"
},
  "geometry": {"coordinates":[-80.86362200000001,32.690447],"type":"Point"}
}