{
  "type": "Feature",
  "properties": {
    "addr:full":"352 Dornoch Dr Pawleys Island SC 29585",
    "addr:housenumber":"352",
    "addr:postcode":"29585",
    "addr:street":"Dornoch Dr",
    "iso:country":"US",
    "sg:address":"352 Dornoch Dr",
    "sg:city":"Pawleys Island",
    "sg:classifiers":[
        {
            "category":"Home & Garden",
            "subcategory":"Home Furnishings",
            "type":"Retail Goods"
        }
    ],
    "sg:phone":"+1 843 237 8828",
    "sg:postcode":"29585",
    "sg:province":"SC",
    "sg:tags":[
        "curtain",
        "made",
        "drapery"
    ],
    "wof:name":"Creative Window Treatment",
    "wof:placetype":"venue"
},
  "geometry": {"coordinates":[-79.167202,33.443068],"type":"Point"}
}