{
  "type": "Feature",
  "properties": {
    "iso:country":"US",
    "sg:address":"1931 Battleground Rd",
    "sg:city":"Cowpens",
    "sg:classifiers":[
        {
            "category":"Building & Trades",
            "subcategory":"Construction",
            "type":"Services"
        }
    ],
    "sg:phone":"+1 864 463 4578",
    "sg:postcode":"29330",
    "sg:province":"SC",
    "sg:tags":[
        "special",
        "contractor"
    ],
    "wof:name":"Cash Backhoe",
    "wof:placetype":"venue"
},
  "geometry": {"coordinates":[-81.815515,35.075252],"type":"Point"}
}