{
  "type": "Feature",
  "properties": {
    "iso:country":"US",
    "sg:address":"4 Brownlee St",
    "sg:city":"Hemingway",
    "sg:classifiers":[
        {
            "category":"Building & Trades",
            "subcategory":"Plumbing",
            "type":"Services"
        }
    ],
    "sg:phone":"+1 843 558 5214",
    "sg:postcode":"29554",
    "sg:province":"SC",
    "sg:tags":[
        "mechanical",
        "contractor"
    ],
    "wof:name":"Collins Mechanical Contractors",
    "wof:placetype":"venue"
},
  "geometry": {"coordinates":[-79.430176,33.756243],"type":"Point"}
}