{
  "type": "Feature",
  "properties": {
    "iso:country":"US",
    "sg:address":"1596 Ingram Rd",
    "sg:city":"Charleston",
    "sg:classifiers":[
        {
            "category":"Building & Trades",
            "subcategory":"Construction",
            "type":"Services"
        }
    ],
    "sg:phone":"+1 843 573 8727",
    "sg:postcode":"29407",
    "sg:province":"SC",
    "sg:tags":[
        "house"
    ],
    "wof:name":"Atlantic Renovations Inc",
    "wof:placetype":"venue"
},
  "geometry": {"coordinates":[-79.994484,32.811825],"type":"Point"}
}