{
  "type": "Feature",
  "properties": {
    "iso:country":"US",
    "sg:address":"211 E Rutherford St",
    "sg:city":"Landrum",
    "sg:classifiers":[
        {
            "category":"Shopping",
            "subcategory":"Shoes",
            "type":"Retail Goods"
        }
    ],
    "sg:phone":"+1 864 457 3517",
    "sg:postcode":"29356",
    "sg:province":"SC",
    "sg:tags":[
        "repair",
        "shoe"
    ],
    "wof:name":"C C Tucker & Son",
    "wof:placetype":"venue"
},
  "geometry": {"coordinates":[-82.187036,35.17551],"type":"Point"}
}