{
  "type": "Feature",
  "properties": {
    "iso:country":"US",
    "sg:address":"1635 Hawkins St",
    "sg:city":"Georgetown",
    "sg:classifiers":[
        {
            "category":"Personal",
            "subcategory":"Beauty Salon",
            "type":"Services"
        }
    ],
    "sg:phone":"+1 843 527 1597",
    "sg:postcode":"29440",
    "sg:province":"SC",
    "wof:name":"Creative Touch",
    "wof:placetype":"venue"
},
  "geometry": {"coordinates":[-79.299171,33.367624],"type":"Point"}
}