{
  "type": "Feature",
  "properties": {
    "iso:country":"US",
    "sg:address":"1310 Curtis St",
    "sg:city":"Rock Hill",
    "sg:classifiers":[
        {
            "category":"Organizations",
            "subcategory":"Religious Organization",
            "type":"Services"
        }
    ],
    "sg:phone":"+1 803 324 3450",
    "sg:postcode":"29730",
    "sg:province":"SC",
    "sg:tags":[
        "church"
    ],
    "wof:name":"Eastern Landmark Baptist Chr",
    "wof:placetype":"venue"
},
  "geometry": {"coordinates":[-81.007912,34.936709],"type":"Point"}
}