{
  "type": "Feature",
  "properties": {
    "iso:country":"US",
    "sg:address":"158 Laurens St SW",
    "sg:city":"Aiken",
    "sg:classifiers":[
        {
            "category":"Shopping",
            "subcategory":"Gifts & Souvenirs",
            "type":"Retail Goods"
        }
    ],
    "sg:phone":"+1 803 644 0004",
    "sg:postcode":"29801",
    "sg:province":"SC",
    "sg:website":"www.curiosityshop.net",
    "wof:name":"Curiosity Shop",
    "wof:placetype":"venue"
},
  "geometry": {"coordinates":[-81.72324,33.560314],"type":"Point"}
}