{
  "type": "Feature",
  "properties": {
    "addr:full":"1405 Winding Way Taylors SC 29687",
    "addr:housenumber":"1405",
    "addr:postcode":"29687",
    "addr:street":"Winding Way",
    "iso:country":"US",
    "sg:address":"1405 Winding Way",
    "sg:city":"Taylors",
    "sg:classifiers":[
        {
            "category":"Professional",
            "subcategory":"Management & Consulting",
            "type":"Services"
        }
    ],
    "sg:phone":"+1 864 244 1156",
    "sg:postcode":"29687",
    "sg:province":"SC",
    "sg:tags":[
        "consultant",
        "business"
    ],
    "wof:name":"Estes Group",
    "wof:placetype":"venue"
},
  "geometry": {"coordinates":[-82.321674,34.936184],"type":"Point"}
}