{
  "type": "Feature",
  "properties": {
    "iso:country":"US",
    "sg:address":"1251 US Hwy 501",
    "sg:city":"Myrtle Beach",
    "sg:classifiers":[
        {
            "category":"Retail",
            "subcategory":"Auto Rental",
            "type":"Services"
        }
    ],
    "sg:phone":"+1 843 626 6527",
    "sg:postcode":"29577",
    "sg:province":"SC",
    "sg:tags":[
        "renting",
        "automobile"
    ],
    "sg:website":"www.thrifty.com",
    "wof:name":"Thrifty Car Rental",
    "wof:placetype":"venue"
},
  "geometry": {"coordinates":[-78.895471,33.697303],"type":"Point"}
}