{
  "type": "Feature",
  "properties": {
    "addr:full":"116 Merrimack Blvd Moncks Corner SC 29461",
    "addr:housenumber":"116",
    "addr:postcode":"29461",
    "addr:street":"Merrimack Blvd",
    "iso:country":"US",
    "sg:address":"116 Merrimack Blvd",
    "sg:city":"Moncks Corner",
    "sg:classifiers":[
        {
            "category":"Building & Trades",
            "subcategory":"Construction",
            "type":"Services"
        }
    ],
    "sg:phone":"+1 843 899 7198",
    "sg:postcode":"29461",
    "sg:province":"SC",
    "sg:tags":[
        "contractor"
    ],
    "wof:name":"Radichs Ceramic Tile",
    "wof:placetype":"venue"
},
  "geometry": {"coordinates":[-80.012524,33.190903],"type":"Point"}
}