{
  "type": "Feature",
  "properties": {
    "iso:country":"US",
    "sg:address":"10177 N Kings Hwy",
    "sg:city":"Myrtle Beach",
    "sg:classifiers":[
        {
            "category":"Shopping",
            "subcategory":"Music",
            "type":"Retail Goods"
        }
    ],
    "sg:phone":"+1 843 272 3383",
    "sg:postcode":"29572",
    "sg:province":"SC",
    "sg:tags":[
        "compact",
        "record",
        "disc",
        "tape"
    ],
    "wof:name":"Fye",
    "wof:placetype":"venue"
},
  "geometry": {"coordinates":[-78.764898,33.79064],"type":"Point"}
}