{
  "type": "Feature",
  "properties": {
    "iso:country":"US",
    "sg:address":"366 Sweetgrass Creek Rd",
    "sg:city":"Charleston",
    "sg:classifiers":[
        {
            "category":"Professional",
            "subcategory":"Business Services",
            "type":"Services"
        }
    ],
    "sg:phone":"+1 843 762 1661",
    "sg:postcode":"29412",
    "sg:province":"SC",
    "sg:tags":[
        "interior",
        "consultant",
        "design",
        "decorator"
    ],
    "wof:name":"Virginia Ross Interiors",
    "wof:placetype":"venue"
},
  "geometry": {"coordinates":[-79.903592,32.744588],"type":"Point"}
}