{
  "type": "Feature",
  "properties": {
    "addr:full":"778 Union St Spartanburg SC 29306",
    "addr:housenumber":"778",
    "addr:postcode":"29306",
    "addr:street":"Union St",
    "iso:country":"US",
    "sg:address":"778 Union St",
    "sg:city":"Spartanburg",
    "sg:classifiers":[
        {
            "category":"Real Estate",
            "subcategory":"Real Estate Agent",
            "type":"Services"
        }
    ],
    "sg:phone":"+1 864 585 0953",
    "sg:postcode":"29306",
    "sg:province":"SC",
    "sg:tags":[
        "appraiser"
    ],
    "wof:name":"Gowan Appraisal Svc",
    "wof:placetype":"venue"
},
  "geometry": {"coordinates":[-81.90992,34.940684],"type":"Point"}
}