{
  "type": "Feature",
  "properties": {
    "addr:full":"6 Ramey Ct Mauldin SC 29662",
    "addr:housenumber":"6",
    "addr:postcode":"29662",
    "addr:street":"Ramey Ct",
    "iso:country":"US",
    "sg:address":"6 Ramey Ct",
    "sg:city":"Mauldin",
    "sg:classifiers":[
        {
            "category":"Building & Trades",
            "subcategory":"Landscaping Services",
            "type":"Services"
        }
    ],
    "sg:phone":"+1 864 967 4820",
    "sg:postcode":"29662",
    "sg:province":"SC",
    "wof:name":"Minklers Lawn Care Inc",
    "wof:placetype":"venue"
},
  "geometry": {"coordinates":[-82.285172,34.776781],"type":"Point"}
}