{
  "type": "Feature",
  "properties": {
    "iso:country":"US",
    "sg:address":"1 N Congress St",
    "sg:city":"York",
    "sg:classifiers":[
        {
            "category":"Government",
            "subcategory":"Office",
            "type":"Public Place"
        }
    ],
    "sg:phone":"+1 803 628 3930",
    "sg:postcode":"29745",
    "sg:province":"SC",
    "wof:name":"York County Master/Equity",
    "wof:placetype":"venue"
},
  "geometry": {"coordinates":[-81.240983,34.995528],"type":"Point"}
}