{
  "type": "Feature",
  "properties": {
    "iso:country":"US",
    "sg:address":"215 Giles Dr",
    "sg:city":"Spartanburg",
    "sg:classifiers":[
        {
            "category":"Retail",
            "subcategory":"Repair Shop",
            "type":"Services"
        }
    ],
    "sg:phone":"+1 864 578 3758",
    "sg:postcode":"29316",
    "sg:province":"SC",
    "sg:tags":[
        "appliance"
    ],
    "wof:name":"Bryan Appliance & Microwave",
    "wof:placetype":"venue"
},
  "geometry": {"coordinates":[-81.97719499999999,35.037643],"type":"Point"}
}