{
  "type": "Feature",
  "properties": {
    "iso:country":"US",
    "sg:address":"4233 Sea Mountain Hwy",
    "sg:city":"Little River",
    "sg:classifiers":[
        {
            "category":"Autos & Motor Vehicles",
            "subcategory":"Auto Supplies",
            "type":"Retail Goods"
        }
    ],
    "sg:phone":"+1 843 399 4800",
    "sg:postcode":"29566",
    "sg:province":"SC",
    "sg:tags":[
        "tire"
    ],
    "wof:name":"International Tire Marketers",
    "wof:placetype":"venue"
},
  "geometry": {"coordinates":[-78.66853999999999,33.866448],"type":"Point"}
}