{
  "type": "Feature",
  "properties": {
    "iso:country":"US",
    "sg:address":"231 Hampton Ave",
    "sg:city":"Greenwood",
    "sg:classifiers":[
        {
            "category":"Organizations",
            "subcategory":"Professional Association",
            "type":"Services"
        }
    ],
    "sg:phone":"+1 864 229 6022",
    "sg:postcode":"29646",
    "sg:province":"SC",
    "wof:name":"Greenwood Association-Realtors",
    "wof:placetype":"venue"
},
  "geometry": {"coordinates":[-82.163482,34.19452],"type":"Point"}
}