{
  "type": "Feature",
  "properties": {
    "iso:country":"US",
    "sg:address":"126 Pinewood Dr",
    "sg:city":"Greer",
    "sg:classifiers":[
        {
            "category":"Building & Trades",
            "subcategory":"Construction",
            "type":"Services"
        }
    ],
    "sg:phone":"+1 864 848 0149",
    "sg:postcode":"29651",
    "sg:province":"SC",
    "sg:tags":[
        "hardwood",
        "distributor",
        "floor"
    ],
    "wof:name":"Hardwood Flooring Inc",
    "wof:placetype":"venue"
},
  "geometry": {"coordinates":[-82.218906,34.955365],"type":"Point"}
}