{
  "type": "Feature",
  "properties": {
    "iso:country":"US",
    "sg:address":"712 N Greenwood Ave",
    "sg:city":"Ware Shoals",
    "sg:classifiers":[
        {
            "category":"Social Services",
            "type":"Services"
        }
    ],
    "sg:phone":"+1 864 456 9500",
    "sg:postcode":"29692",
    "sg:province":"SC",
    "sg:tags":[
        "community"
    ],
    "wof:name":"Freedom Outreach Inc",
    "wof:placetype":"venue"
},
  "geometry": {"coordinates":[-82.251099,34.402187],"type":"Point"}
}