{
  "type": "Feature",
  "properties": {
    "iso:country":"US",
    "sg:address":"5901 S Kings Hwy",
    "sg:city":"Myrtle Beach",
    "sg:classifiers":[
        {
            "category":"Professional",
            "type":"Services"
        }
    ],
    "sg:phone":"+1 843 447 4205",
    "sg:postcode":"29575",
    "sg:province":"SC",
    "sg:tags":[
        "establishment"
    ],
    "wof:name":"Bruning & Bruning",
    "wof:placetype":"venue"
},
  "geometry": {"coordinates":[-78.96105900000001,33.630513],"type":"Point"}
}