{
  "type": "Feature",
  "properties": {
    "iso:country":"US",
    "sg:address":"302 Aster Cir",
    "sg:city":"Columbia",
    "sg:classifiers":[
        {
            "category":"Building & Trades",
            "subcategory":"Construction",
            "type":"Services"
        }
    ],
    "sg:phone":"+1 803 699 2683",
    "sg:postcode":"29201",
    "sg:province":"SC",
    "sg:tags":[
        "home",
        "builder"
    ],
    "wof:name":"D R Horton Inc",
    "wof:placetype":"venue"
},
  "geometry": {"coordinates":[-80.998143,33.962234],"type":"Point"}
}