{
  "type": "Feature",
  "properties": {
    "iso:country":"US",
    "sg:address":"4603 Jenkins Ave",
    "sg:city":"North Charleston",
    "sg:classifiers":[
        {
            "category":"Personal",
            "subcategory":"Beauty Salon",
            "type":"Services"
        }
    ],
    "sg:phone":"+1 843 554 4871",
    "sg:postcode":"29405",
    "sg:province":"SC",
    "wof:name":"Barbara Gordon Beauty Salon",
    "wof:placetype":"venue"
},
  "geometry": {"coordinates":[-79.979221,32.878449],"type":"Point"}
}