{
  "type": "Feature",
  "properties": {
    "iso:country":"US",
    "sg:address":"136 Pelham Dr",
    "sg:city":"Columbia",
    "sg:classifiers":[
        {
            "category":"Personal",
            "subcategory":"Beauty Salon",
            "type":"Services"
        }
    ],
    "sg:phone":"+1 803 783 3887",
    "sg:postcode":"29209",
    "sg:province":"SC",
    "wof:name":"Shear Xpectations",
    "wof:placetype":"venue"
},
  "geometry": {"coordinates":[-80.97345799999999,33.979172],"type":"Point"}
}