{
  "type": "Feature",
  "properties": {
    "addr:full":"2586 Holbrook Rd Fort Mill SC 29715",
    "addr:housenumber":"2586",
    "addr:postcode":"29715",
    "addr:street":"Holbrook Rd",
    "iso:country":"US",
    "sg:address":"2586 Holbrook Rd",
    "sg:city":"Fort Mill",
    "sg:classifiers":[
        {
            "category":"Professional",
            "subcategory":"Accounting & Tax Preparation",
            "type":"Services"
        }
    ],
    "sg:phone":"+1 803 547 5691",
    "sg:postcode":"29715",
    "sg:province":"SC",
    "sg:tags":[
        "bookkeeping",
        "general"
    ],
    "wof:name":"Easy Solutions Accounting",
    "wof:placetype":"venue"
},
  "geometry": {"coordinates":[-80.898706,34.975551],"type":"Point"}
}