{
  "type": "Feature",
  "properties": {
    "addr:full":"103 Michael Dr Greenville SC 29611",
    "addr:housenumber":"103",
    "addr:postcode":"29611",
    "addr:street":"Michael Dr",
    "iso:country":"US",
    "sg:address":"103 Michael Dr",
    "sg:city":"Greenville",
    "sg:classifiers":[
        {
            "category":"Freight",
            "type":"Transportation"
        }
    ],
    "sg:phone":"+1 864 295 6407",
    "sg:postcode":"29611",
    "sg:province":"SC",
    "sg:tags":[
        "operator",
        "trucking"
    ],
    "wof:name":"Stephen A Firpo",
    "wof:placetype":"venue"
},
  "geometry": {"coordinates":[-82.437297,34.806509],"type":"Point"}
}