{
  "type": "Feature",
  "properties": {
    "iso:country":"US",
    "sg:address":"1199 S Guignard Dr",
    "sg:city":"Sumter",
    "sg:classifiers":[
        {
            "category":"Wholesale",
            "subcategory":"Machinery & Supplies",
            "type":"Manufacturing & Wholesale Goods"
        }
    ],
    "sg:phone":"+1 803 773 0532",
    "sg:postcode":"29150",
    "sg:province":"SC",
    "sg:tags":[
        "tubing",
        "hose",
        "assembly",
        "plastic"
    ],
    "wof:name":"Hose & Equipment Corp",
    "wof:placetype":"venue"
},
  "geometry": {"coordinates":[-80.350545,33.887678],"type":"Point"}
}