{
  "type": "Feature",
  "properties": {
    "addr:full":"1746 Celanese Rd Rock Hill SC 29732",
    "addr:housenumber":"1746",
    "addr:postcode":"29732",
    "addr:street":"Celanese Rd",
    "iso:country":"US",
    "sg:address":"1746 Celanese Rd",
    "sg:city":"Rock Hill",
    "sg:classifiers":[
        {
            "category":"Personal",
            "subcategory":"Beauty Salon",
            "type":"Services"
        }
    ],
    "sg:phone":"+1 803 366 5877",
    "sg:postcode":"29732",
    "sg:province":"SC",
    "wof:name":"Beauty Boutique Hair Design",
    "wof:placetype":"venue"
},
  "geometry": {"coordinates":[-81.00237300000001,34.976579],"type":"Point"}
}