{
  "type": "Feature",
  "properties": {
    "iso:country":"US",
    "sg:address":"2361 Walker Swinton Rd",
    "sg:city":"Timmonsville",
    "sg:classifiers":[
        {
            "category":"Utilities",
            "subcategory":"Mobile Phone",
            "type":"Services"
        }
    ],
    "sg:phone":"+1 843 662 2337",
    "sg:postcode":"29161",
    "sg:province":"SC",
    "sg:tags":[
        "telephone",
        "cellular"
    ],
    "wof:name":"Morris Wireless",
    "wof:placetype":"venue"
},
  "geometry": {"coordinates":[-79.833872,34.14787],"type":"Point"}
}