{
  "type": "Feature",
  "properties": {
    "iso:country":"US",
    "sg:address":"404 Country Club Dr",
    "sg:city":"Bennettsville",
    "sg:classifiers":[
        {
            "category":"Organizations",
            "subcategory":"Community Association",
            "type":"Services"
        }
    ],
    "sg:phone":"+1 843 479 7741",
    "sg:postcode":"29512",
    "sg:province":"SC",
    "sg:tags":[
        "club"
    ],
    "wof:name":"Marlboro Country Club",
    "wof:placetype":"venue"
},
  "geometry": {"coordinates":[-79.687179,34.632117],"type":"Point"}
}