{
  "type": "Feature",
  "properties": {
    "iso:country":"US",
    "sg:address":"1407 Cherokee Dr",
    "sg:city":"West Columbia",
    "sg:classifiers":[
        {
            "category":"Organizations",
            "subcategory":"Membership Organization",
            "type":"Services"
        }
    ],
    "sg:phone":"+1 803 739 8701",
    "sg:postcode":"29169",
    "sg:province":"SC",
    "sg:tags":[
        "meditation",
        "instruction"
    ],
    "wof:name":"Yoga Shala & Mindbody Health",
    "wof:placetype":"venue"
},
  "geometry": {"coordinates":[-81.09243499999999,34.010175],"type":"Point"}
}