{
  "type": "Feature",
  "properties": {
    "iso:country":"US",
    "sg:address":"1218 Elmwood Ave",
    "sg:city":"Columbia",
    "sg:classifiers":[
        {
            "category":"Retail",
            "subcategory":"Car Wash",
            "type":"Services"
        }
    ],
    "sg:phone":"+1 803 779 7787",
    "sg:postcode":"29201",
    "sg:province":"SC",
    "wof:name":"Personal Care Auto Detailing Etc",
    "wof:placetype":"venue"
},
  "geometry": {"coordinates":[-81.038803,34.013302],"type":"Point"}
}