{
  "type": "Feature",
  "properties": {
    "iso:country":"US",
    "sg:address":"5514 Memorial Blvd",
    "sg:city":"St George",
    "sg:classifiers":[
        {
            "category":"Food & Beverages",
            "subcategory":"Groceries & Convenience Stores",
            "type":"Retail Goods"
        }
    ],
    "sg:phone":"+1 843 563 7622",
    "sg:postcode":"29477",
    "sg:province":"SC",
    "wof:name":"M & M Quick Stop",
    "wof:placetype":"venue"
},
  "geometry": {"coordinates":[-80.57258299999999,33.185834],"type":"Point"}
}