{
  "type": "Feature",
  "properties": {
    "addr:full":"1004 Charleston Hwy West Columbia SC 29169",
    "addr:housenumber":"1004",
    "addr:postcode":"29169",
    "addr:street":"Charleston Hwy",
    "iso:country":"US",
    "sg:address":"1004 Charleston Hwy",
    "sg:city":"West Columbia",
    "sg:classifiers":[
        {
            "category":"Building & Trades",
            "subcategory":"Construction",
            "type":"Services"
        }
    ],
    "sg:phone":"+1 803 794 6263",
    "sg:postcode":"29169",
    "sg:province":"SC",
    "sg:tags":[
        "home",
        "builder"
    ],
    "wof:name":"Griffin Homes & Properties",
    "wof:placetype":"venue"
},
  "geometry": {"coordinates":[-81.075422,33.977643],"type":"Point"}
}