{
  "type": "Feature",
  "properties": {
    "addr:full":"504 Martin Rd Anderson SC 29626",
    "addr:housenumber":"504",
    "addr:postcode":"29626",
    "addr:street":"Martin Rd",
    "iso:country":"US",
    "sg:address":"504 Martin Rd",
    "sg:city":"Anderson",
    "sg:classifiers":[
        {
            "category":"Building & Trades",
            "subcategory":"Construction",
            "type":"Services"
        }
    ],
    "sg:phone":"+1 864 964 8212",
    "sg:postcode":"29626",
    "sg:province":"SC",
    "sg:tags":[
        "remodeling",
        "contractor"
    ],
    "wof:name":"Jason Morrison",
    "wof:placetype":"venue"
},
  "geometry": {"coordinates":[-82.752526,34.50342],"type":"Point"}
}