{
  "type": "Feature",
  "properties": {
    "iso:country":"US",
    "sg:address":"405 N Main St",
    "sg:city":"Mauldin",
    "sg:classifiers":[
        {
            "category":"Home & Garden",
            "subcategory":"Furniture",
            "type":"Retail Goods"
        }
    ],
    "sg:phone":"+1 864 288 1751",
    "sg:postcode":"29662",
    "sg:province":"SC",
    "sg:tags":[
        "household",
        "appliance"
    ],
    "wof:name":"Mutual Home Stores of Mauldin",
    "wof:placetype":"venue"
},
  "geometry": {"coordinates":[-82.31226599999999,34.784097],"type":"Point"}
}