{
  "type": "Feature",
  "properties": {
    "iso:country":"US",
    "sg:address":"1640 Trinity Rd",
    "sg:city":"Lynchburg",
    "sg:classifiers":[
        {
            "category":"Shopping",
            "subcategory":"Clothing, Apparel, & Fashions",
            "type":"Retail Goods"
        }
    ],
    "sg:phone":"+1 843 659 2038",
    "sg:postcode":"29080",
    "sg:province":"SC",
    "wof:name":"Gems By Jewell",
    "wof:placetype":"venue"
},
  "geometry": {"coordinates":[-80.072244,33.964962],"type":"Point"}
}