{
  "type": "Feature",
  "properties": {
    "iso:country":"US",
    "sg:address":"100 Columbiana Dr",
    "sg:city":"Columbia",
    "sg:classifiers":[
        {
            "category":"Shopping",
            "subcategory":"Clothing, Apparel, & Fashions",
            "type":"Retail Goods"
        }
    ],
    "sg:phone":"+1 803 749 8862",
    "sg:postcode":"29212",
    "sg:province":"SC",
    "sg:tags":[
        "sportswear"
    ],
    "wof:name":"Pacific Sunwear",
    "wof:placetype":"venue"
},
  "geometry": {"coordinates":[-81.156813,34.07392],"type":"Point"}
}