{
  "type": "Feature",
  "properties": {
    "iso:country":"US",
    "sg:address":"677 Long Point Rd",
    "sg:city":"Mt Pleasant",
    "sg:classifiers":[
        {
            "category":"Organizations",
            "subcategory":"Religious Organization",
            "type":"Services"
        }
    ],
    "sg:phone":"+1 843 971 6440",
    "sg:postcode":"29464",
    "sg:province":"SC",
    "sg:tags":[
        "church"
    ],
    "wof:name":"Living Fountain Ministry",
    "wof:placetype":"venue"
},
  "geometry": {"coordinates":[-79.853337,32.84201],"type":"Point"}
}