{
  "type": "Feature",
  "properties": {
    "iso:country":"US",
    "sg:address":"518 E Fairplay Blvd",
    "sg:city":"Fair Play",
    "sg:classifiers":[
        {
            "category":"Manufacturing",
            "subcategory":"Lumber",
            "type":"Manufacturing & Wholesale Goods"
        }
    ],
    "sg:phone":"+1 864 972 9100",
    "sg:postcode":"29643",
    "sg:province":"SC",
    "sg:tags":[
        "logging"
    ],
    "wof:name":"A Stump Grinder",
    "wof:placetype":"venue"
},
  "geometry": {"coordinates":[-82.982579,34.512545],"type":"Point"}
}