{
  "type": "Feature",
  "properties": {
    "addr:full":"4860 Cade Rd Cades SC 29518",
    "addr:housenumber":"4860",
    "addr:postcode":"29518",
    "addr:street":"Cade Rd",
    "iso:country":"US",
    "sg:address":"4860 Cade Rd",
    "sg:city":"Cades",
    "sg:classifiers":[
        {
            "category":"Organizations",
            "subcategory":"Religious Organization",
            "type":"Services"
        }
    ],
    "sg:phone":"+1 843 389 9215",
    "sg:postcode":"29518",
    "sg:province":"SC",
    "sg:tags":[
        "church"
    ],
    "wof:name":"St Paul AME Church",
    "wof:placetype":"venue"
},
  "geometry": {"coordinates":[-79.793778,33.791695],"type":"Point"}
}