{
  "type": "Feature",
  "properties": {
    "iso:country":"US",
    "sg:address":"1701 Old Georgia Hwy",
    "sg:city":"Gaffney",
    "sg:classifiers":[
        {
            "category":"Retail",
            "subcategory":"Veterinary Services",
            "type":"Services"
        }
    ],
    "sg:phone":"+1 864 489 3145",
    "sg:postcode":"29341",
    "sg:province":"SC",
    "sg:tags":[
        "hospital",
        "animal"
    ],
    "wof:name":"Gaffney Animal Hospital Inc",
    "wof:placetype":"venue"
},
  "geometry": {"coordinates":[-81.67184,35.060877],"type":"Point"}
}