{
  "type": "Feature",
  "properties": {
    "addr:full":"9532 State Hwy 707 Myrtle Beach SC 29588",
    "addr:housenumber":"9532",
    "addr:postcode":"29588",
    "addr:street":"State Hwy 707",
    "iso:country":"US",
    "sg:address":"9532 State Hwy 707",
    "sg:city":"Myrtle Beach",
    "sg:classifiers":[
        {
            "category":"Building & Trades",
            "subcategory":"Plumbing",
            "type":"Services"
        }
    ],
    "sg:phone":"+1 843 650 3950",
    "sg:postcode":"29588",
    "sg:province":"SC",
    "sg:tags":[
        "plumbing",
        "contractor"
    ],
    "wof:name":"H & H Plumbing Inc",
    "wof:placetype":"venue"
},
  "geometry": {"coordinates":[-79.03452799999999,33.630337],"type":"Point"}
}