{
  "type": "Feature",
  "properties": {
    "iso:country":"US",
    "sg:address":"241 S Richardson St",
    "sg:city":"Latta",
    "sg:classifiers":[
        {
            "category":"Restaurant",
            "type":"Food & Drink"
        }
    ],
    "sg:phone":"+1 843 752 4370",
    "sg:postcode":"29565",
    "sg:province":"SC",
    "wof:name":"King's Famous Pizza Inc",
    "wof:placetype":"venue"
},
  "geometry": {"coordinates":[-79.432711,34.335422],"type":"Point"}
}