{
  "type": "Feature",
  "properties": {
    "iso:country":"US",
    "sg:address":"2 Eli St",
    "sg:city":"Greenville",
    "sg:classifiers":[
        {
            "category":"Manufacturing",
            "subcategory":"Apparel",
            "type":"Manufacturing & Wholesale Goods"
        }
    ],
    "sg:phone":"+1 864 271 2790",
    "sg:postcode":"29617",
    "sg:province":"SC",
    "sg:tags":[
        "sewing",
        "contractor"
    ],
    "wof:name":"Bowen Cleaners & Laundry",
    "wof:placetype":"venue"
},
  "geometry": {"coordinates":[-82.430731,34.872282],"type":"Point"}
}