{
  "type": "Feature",
  "properties": {
    "iso:country":"US",
    "sg:address":"926 Harden St",
    "sg:city":"Columbia",
    "sg:classifiers":[
        {
            "category":"Personal",
            "type":"Services"
        },
        {
            "category":"Professional",
            "subcategory":"Printing & Photocopies",
            "type":"Services"
        }
    ],
    "sg:phone":"+1 803 256 5281",
    "sg:postcode":"29205",
    "sg:province":"SC",
    "sg:tags":[
        "party",
        "planning",
        "event"
    ],
    "sg:website":"www.frenzyts.com/",
    "wof:name":"Frenzy Screen Printers",
    "wof:placetype":"venue"
},
  "geometry": {"coordinates":[-81.017213,34.002601],"type":"Point"}
}