{
  "type": "Feature",
  "properties": {
    "addr:full":"353 Crooked Rd Abbeville SC 29620",
    "addr:housenumber":"353",
    "addr:postcode":"29620",
    "addr:street":"Crooked Rd",
    "iso:country":"US",
    "sg:address":"353 Crooked Rd",
    "sg:city":"Abbeville",
    "sg:classifiers":[
        {
            "category":"Freight",
            "type":"Transportation"
        }
    ],
    "sg:phone":"+1 864 348 7285",
    "sg:postcode":"29620",
    "sg:province":"SC",
    "wof:name":"Anderson Express Freight Inc",
    "wof:placetype":"venue"
},
  "geometry": {"coordinates":[-82.570148,34.300619],"type":"Point"}
}