{
  "type": "Feature",
  "properties": {
    "addr:full":"728 Augusta Rd North Augusta SC 29822",
    "addr:housenumber":"728",
    "addr:postcode":"29822",
    "addr:street":"Augusta Rd",
    "iso:country":"US",
    "sg:address":"728 Augusta Rd",
    "sg:city":"North Augusta",
    "sg:classifiers":[
        {
            "category":"Shopping",
            "type":"Retail Goods"
        }
    ],
    "sg:phone":"+1 803 278 3660",
    "sg:postcode":"29822",
    "sg:province":"SC",
    "sg:tags":[
        "merchandise"
    ],
    "wof:name":"Retail Systems Inc",
    "wof:placetype":"venue"
},
  "geometry": {"coordinates":[-81.89209099999999,33.496858],"type":"Point"}
}