{
  "type": "Feature",
  "properties": {
    "iso:country":"US",
    "sg:address":"157 Ladys Island Dr",
    "sg:city":"Beaufort",
    "sg:classifiers":[
        {
            "category":"Organizations",
            "subcategory":"Religious Organization",
            "type":"Services"
        }
    ],
    "sg:phone":"+1 843 524 3461",
    "sg:postcode":"29907",
    "sg:province":"SC",
    "sg:tags":[
        "church"
    ],
    "sg:website":"www.stjohnsbeaufort.org",
    "wof:name":"St John's Lutheran Church",
    "wof:placetype":"venue"
},
  "geometry": {"coordinates":[-80.658856,32.404995],"type":"Point"}
}