{
  "type": "Feature",
  "properties": {
    "iso:country":"US",
    "sg:address":"609 E Main St",
    "sg:city":"Westminster",
    "sg:classifiers":[
        {
            "category":"Autos & Motor Vehicles",
            "subcategory":"Automobile Sales",
            "type":"Retail Goods"
        }
    ],
    "sg:phone":"+1 864 647 0555",
    "sg:postcode":"29693",
    "sg:province":"SC",
    "sg:tags":[
        "car",
        "dealer"
    ],
    "wof:name":"Car City SBD Inc",
    "wof:placetype":"venue"
},
  "geometry": {"coordinates":[-83.090273,34.660686],"type":"Point"}
}