{
  "type": "Feature",
  "properties": {
    "iso:country":"US",
    "sg:address":"3386 Wilderness Ln",
    "sg:city":"Murrells Inlet",
    "sg:classifiers":[
        {
            "category":"Manufacturing",
            "subcategory":"Chemicals & Compounds",
            "type":"Manufacturing & Wholesale Goods"
        }
    ],
    "sg:phone":"+1 843 222 7272",
    "sg:postcode":"29575",
    "sg:province":"SC",
    "sg:tags":[
        "active",
        "surface",
        "agent",
        "mfg"
    ],
    "wof:name":"Creative Illusion By Lynn LLC",
    "wof:placetype":"venue"
},
  "geometry": {"coordinates":[-79.06911599999999,33.605184],"type":"Point"}
}