{
  "type": "Feature",
  "properties": {
    "addr:full":"1812 Woodruff Rd Greenville SC 29607",
    "addr:housenumber":"1812",
    "addr:postcode":"29607",
    "addr:street":"Woodruff Rd",
    "iso:country":"US",
    "sg:address":"1812 Woodruff Rd",
    "sg:city":"Greenville",
    "sg:classifiers":[
        {
            "category":"Retail",
            "subcategory":"Photofinishing",
            "type":"Services"
        }
    ],
    "sg:phone":"+1 864 234 7570",
    "sg:postcode":"29607",
    "sg:province":"SC",
    "sg:tags":[
        "photo",
        "finishing"
    ],
    "wof:name":"Revco Drug Stores",
    "wof:placetype":"venue"
},
  "geometry": {"coordinates":[-82.273751,34.819417],"type":"Point"}
}