{
  "type": "Feature",
  "properties": {
    "iso:country":"US",
    "sg:address":"2542 Fish Hatchery Rd",
    "sg:city":"West Columbia",
    "sg:classifiers":[
        {
            "category":"Retail",
            "subcategory":"Auto Repair",
            "type":"Services"
        }
    ],
    "sg:phone":"+1 803 794 1267",
    "sg:postcode":"29172",
    "sg:province":"SC",
    "wof:name":"Pro Fleet Inc",
    "wof:placetype":"venue"
},
  "geometry": {"coordinates":[-81.088188,33.92615],"type":"Point"}
}