{
  "type": "Feature",
  "properties": {
    "iso:country":"US",
    "sg:address":"834 Malibu Dr",
    "sg:city":"Columbia",
    "sg:classifiers":[
        {
            "category":"Shopping",
            "type":"Retail Goods"
        }
    ],
    "sg:phone":"+1 803 776 0603",
    "sg:postcode":"29209",
    "sg:province":"SC",
    "sg:tags":[
        "material",
        "artist",
        "supply"
    ],
    "wof:name":"Dimig Studios",
    "wof:placetype":"venue"
},
  "geometry": {"coordinates":[-80.959652,33.961373],"type":"Point"}
}