{
  "type": "Feature",
  "properties": {
    "iso:country":"US",
    "sg:address":"163 King George Way",
    "sg:city":"Columbia",
    "sg:classifiers":[
        {
            "category":"Government",
            "subcategory":"Office",
            "type":"Public Place"
        }
    ],
    "sg:phone":"+1 803 772 1842",
    "sg:postcode":"29210",
    "sg:province":"SC",
    "sg:tags":[
        "sector",
        "commercial",
        "regulation",
        "real estate"
    ],
    "wof:name":"Finley & Associates",
    "wof:placetype":"venue"
},
  "geometry": {"coordinates":[-81.128134,34.052405],"type":"Point"}
}