{
  "type": "Feature",
  "properties": {
    "iso:country":"US",
    "sg:address":"1285 Bowater Rd",
    "sg:city":"Rock Hill",
    "sg:classifiers":[
        {
            "category":"Banks & Credit Unions",
            "subcategory":"Investment Brokerage",
            "type":"Services"
        }
    ],
    "sg:phone":"+1 803 366 6849",
    "sg:postcode":"29732",
    "sg:province":"SC",
    "sg:tags":[
        "advisory",
        "financial"
    ],
    "wof:name":"Coleman Financial LLC",
    "wof:placetype":"venue"
},
  "geometry": {"coordinates":[-81.09438400000001,35.011469],"type":"Point"}
}