{
  "type": "Feature",
  "properties": {
    "addr:full":"3997 North Rd Orangeburg SC 29118",
    "addr:housenumber":"3997",
    "addr:postcode":"29118",
    "addr:street":"North Rd",
    "iso:country":"US",
    "sg:address":"3997 North Rd",
    "sg:city":"Orangeburg",
    "sg:classifiers":[
        {
            "category":"Food & Beverages",
            "subcategory":"Groceries & Convenience Stores",
            "type":"Retail Goods"
        }
    ],
    "sg:phone":"+1 803 534 0577",
    "sg:postcode":"29118",
    "sg:province":"SC",
    "sg:tags":[
        "grocer"
    ],
    "wof:name":"Summers Country Store",
    "wof:placetype":"venue"
},
  "geometry": {"coordinates":[-80.91195500000001,33.543325],"type":"Point"}
}