{
  "type": "Feature",
  "properties": {
    "iso:country":"US",
    "sg:address":"511 S Kings Hwy",
    "sg:city":"Myrtle Beach",
    "sg:classifiers":[
        {
            "category":"Shopping",
            "subcategory":"Clothing, Apparel, & Fashions",
            "type":"Retail Goods"
        }
    ],
    "sg:phone":"+1 843 946 9808",
    "sg:postcode":"29577",
    "sg:province":"SC",
    "sg:tags":[
        "swimwear",
        "accessory"
    ],
    "wof:name":"Pacific Beachwear",
    "wof:placetype":"venue"
},
  "geometry": {"coordinates":[-78.89459100000001,33.682405],"type":"Point"}
}