{
  "type": "Feature",
  "properties": {
    "iso:country":"US",
    "sg:address":"1481 Simmons St",
    "sg:city":"Mount Pleasant",
    "sg:classifiers":[
        {
            "category":"Shopping",
            "subcategory":"Bicycles & Sporting Goods",
            "type":"Retail Goods"
        }
    ],
    "sg:phone":"+1 843 884 8229",
    "sg:postcode":"29464",
    "sg:province":"SC",
    "wof:name":"Shem Creek Bike Center Inc",
    "wof:placetype":"venue"
},
  "geometry": {"coordinates":[-79.865022,32.783062],"type":"Point"}
}