{
  "type": "Feature",
  "properties": {
    "iso:country":"US",
    "sg:address":"1000 2nd Ave S",
    "sg:city":"North Myrtle Bch",
    "sg:classifiers":[
        {
            "category":"Professional",
            "subcategory":"Management & Consulting",
            "type":"Services"
        }
    ],
    "sg:phone":"+1 843 281 3400",
    "sg:postcode":"29582",
    "sg:province":"SC",
    "sg:tags":[
        "promotion",
        "sales"
    ],
    "wof:name":"Fairfield Resorts",
    "wof:placetype":"venue"
},
  "geometry": {"coordinates":[-78.68392,33.826556],"type":"Point"}
}