{
  "type": "Feature",
  "properties": {
    "iso:country":"US",
    "sg:address":"1681 US Hwy 15 S",
    "sg:city":"Sumter",
    "sg:classifiers":[
        {
            "category":"Restaurant",
            "type":"Food & Drink"
        }
    ],
    "sg:phone":"+1 803 506 4828",
    "sg:postcode":"29150",
    "sg:province":"SC",
    "sg:website":"www.amsub.com",
    "wof:name":"Subway Sandwiches & Salads",
    "wof:placetype":"venue"
},
  "geometry": {"coordinates":[-80.355852,33.869726],"type":"Point"}
}