{
  "type": "Feature",
  "properties": {
    "addr:full":"111 Beaver Dam School Rd Gaffney SC 29340",
    "addr:housenumber":"111",
    "addr:postcode":"29340",
    "addr:street":"Beaver;School Rd",
    "iso:country":"US",
    "sg:address":"111 Beaver Dam School Rd",
    "sg:city":"Gaffney",
    "sg:classifiers":[
        {
            "category":"Manufacturing",
            "subcategory":"Metals",
            "type":"Manufacturing & Wholesale Goods"
        }
    ],
    "sg:phone":"+1 864 489 4407",
    "sg:postcode":"29340",
    "sg:province":"SC",
    "sg:tags":[
        "steel",
        "stainless",
        "m",
        "electroplating"
    ],
    "wof:name":"Accurate Plating Inc",
    "wof:placetype":"venue"
},
  "geometry": {"coordinates":[-81.702124,35.034763],"type":"Point"}
}