{
  "type": "Feature",
  "properties": {
    "iso:country":"US",
    "sg:address":"1114 College Park Rd",
    "sg:city":"Summerville",
    "sg:classifiers":[
        {
            "category":"Restaurant",
            "type":"Food & Drink"
        }
    ],
    "sg:phone":"+1 843 875 6313",
    "sg:postcode":"29483",
    "sg:province":"SC",
    "wof:name":"Joe Bessinger's Barbeque",
    "wof:placetype":"venue"
},
  "geometry": {"coordinates":[-80.097371,33.041242],"type":"Point"}
}