{
  "type": "Feature",
  "properties": {
    "addr:full":"517 12th St West Columbia SC 29033",
    "addr:housenumber":"517",
    "addr:postcode":"29033",
    "addr:street":"12Th St",
    "iso:country":"US",
    "sg:address":"517 12th St",
    "sg:city":"West Columbia",
    "sg:classifiers":[
        {
            "category":"Food & Beverages",
            "subcategory":"Groceries & Convenience Stores",
            "type":"Retail Goods"
        }
    ],
    "sg:phone":"+1 803 939 9011",
    "sg:postcode":"29033",
    "sg:province":"SC",
    "wof:name":"Rincon Vaquero",
    "wof:placetype":"venue"
},
  "geometry": {"coordinates":[-81.07189099999999,33.985716],"type":"Point"}
}