{
  "type": "Feature",
  "properties": {
    "iso:country":"US",
    "sg:address":"132 Bluffton Rd",
    "sg:city":"Bluffton",
    "sg:classifiers":[
        {
            "category":"Health Services",
            "subcategory":"Doctor",
            "type":"Services"
        }
    ],
    "sg:phone":"+1 843 706 2255",
    "sg:postcode":"29910",
    "sg:province":"SC",
    "sg:tags":[
        "physician",
        "surgeon"
    ],
    "wof:name":"Gabriel Fornari Jr DO",
    "wof:placetype":"venue"
},
  "geometry": {"coordinates":[-80.857686,32.246398],"type":"Point"}
}