{
  "type": "Feature",
  "properties": {
    "iso:country":"US",
    "sg:address":"3280 Reidville Rd",
    "sg:city":"Spartanburg",
    "sg:classifiers":[
        {
            "category":"Building & Trades",
            "subcategory":"Plumbing",
            "type":"Services"
        }
    ],
    "sg:phone":"+1 864 574 2027",
    "sg:postcode":"29301",
    "sg:province":"SC",
    "sg:tags":[
        "septic"
    ],
    "wof:name":"Caldwell & Son Inc",
    "wof:placetype":"venue"
},
  "geometry": {"coordinates":[-82.020623,34.90847],"type":"Point"}
}