{
  "type": "Feature",
  "properties": {
    "iso:country":"US",
    "sg:address":"7047 Stall Rd",
    "sg:city":"Charleston",
    "sg:classifiers":[
        {
            "category":"Building & Trades",
            "subcategory":"Construction",
            "type":"Services"
        }
    ],
    "sg:phone":"+1 843 572 2499",
    "sg:postcode":"29406",
    "sg:province":"SC",
    "sg:tags":[
        "painter"
    ],
    "wof:name":"Property Management Painters",
    "wof:placetype":"venue"
},
  "geometry": {"coordinates":[-80.049866,32.924664],"type":"Point"}
}