{
  "type": "Feature",
  "properties": {
    "addr:full":"2 Spanish Moss Ln Greer SC 29650",
    "addr:housenumber":"2",
    "addr:postcode":"29650",
    "addr:street":"Spanish Moss Ln",
    "iso:country":"US",
    "sg:address":"2 Spanish Moss Ln",
    "sg:city":"Greer",
    "sg:classifiers":[
        {
            "category":"Shopping",
            "subcategory":"Gifts & Souvenirs",
            "type":"Retail Goods"
        }
    ],
    "sg:phone":"+1 864 271 7006",
    "sg:postcode":"29650",
    "sg:province":"SC",
    "sg:tags":[
        "shop"
    ],
    "wof:name":"Miracle Gospel & Gift Shop",
    "wof:placetype":"venue"
},
  "geometry": {"coordinates":[-82.26200900000001,34.878354],"type":"Point"}
}