{
  "type": "Feature",
  "properties": {
    "addr:full":"150 Country Ln Ward SC 29127",
    "addr:housenumber":"150",
    "addr:postcode":"29127",
    "addr:street":"Country Ln",
    "iso:country":"US",
    "sg:address":"150 Country Ln",
    "sg:city":"Ward",
    "sg:classifiers":[
        {
            "category":"Freight",
            "type":"Transportation"
        }
    ],
    "sg:phone":"+1 864 445 7804",
    "sg:postcode":"29127",
    "sg:province":"SC",
    "sg:tags":[
        "operator",
        "local",
        "trucking"
    ],
    "wof:name":"Wesley A Davis",
    "wof:placetype":"venue"
},
  "geometry": {"coordinates":[-81.58555800000001,34.179475],"type":"Point"}
}