{
  "type": "Feature",
  "properties": {
    "iso:country":"US",
    "sg:address":"792 Folly Rd",
    "sg:city":"Charleston",
    "sg:classifiers":[
        {
            "category":"Food & Beverages",
            "subcategory":"Specialty",
            "type":"Retail Goods"
        }
    ],
    "sg:phone":"+1 843 762 6580",
    "sg:postcode":"29412",
    "sg:province":"SC",
    "wof:name":"East West Health Center",
    "wof:placetype":"venue"
},
  "geometry": {"coordinates":[-79.967192,32.740199],"type":"Point"}
}