{
  "type": "Feature",
  "properties": {
    "iso:country":"US",
    "sg:address":"405 Park Ave SW",
    "sg:city":"Aiken",
    "sg:classifiers":[
        {
            "category":"Professional",
            "subcategory":"Lawyer & Legal Services",
            "type":"Services"
        }
    ],
    "sg:phone":"+1 803 643 4110",
    "sg:postcode":"29801",
    "sg:province":"SC",
    "sg:tags":[
        "attorney"
    ],
    "wof:name":"Smith Massey & Brodie",
    "wof:placetype":"venue"
},
  "geometry": {"coordinates":[-81.722139,33.55901],"type":"Point"}
}