{
  "type": "Feature",
  "properties": {
    "addr:full":"1221 College Park Rd Summerville SC 29483",
    "addr:housenumber":"1221",
    "addr:postcode":"29483",
    "addr:street":"College Park Rd",
    "iso:country":"US",
    "sg:address":"1221 College Park Rd",
    "sg:city":"Summerville",
    "sg:classifiers":[
        {
            "category":"Building & Trades",
            "subcategory":"Construction",
            "type":"Services"
        }
    ],
    "sg:phone":"+1 843 871 4185",
    "sg:postcode":"29483",
    "sg:province":"SC",
    "sg:tags":[
        "house"
    ],
    "wof:name":"Still & Still Construction",
    "wof:placetype":"venue"
},
  "geometry": {"coordinates":[-80.09937499999999,33.043077],"type":"Point"}
}