{
  "type": "Feature",
  "properties": {
    "addr:full":"1511 Poinsett Hwy Greenville SC 29609",
    "addr:housenumber":"1511",
    "addr:postcode":"29609",
    "addr:street":"Poinsett Hwy",
    "iso:country":"US",
    "sg:address":"1511 Poinsett Hwy",
    "sg:city":"Greenville",
    "sg:classifiers":[
        {
            "category":"Restaurant",
            "type":"Food & Drink"
        }
    ],
    "sg:menulink":"http://www.allmenus.com/sc/greenville/153777-zaxbys/menu/",
    "sg:phone":"+1 864 421 0101",
    "sg:postcode":"29609",
    "sg:province":"SC",
    "sg:tags":[
        "american",
        "wing"
    ],
    "wof:name":"Zaxby's",
    "wof:placetype":"venue"
},
  "geometry": {"coordinates":[-82.405379,34.887967],"type":"Point"}
}