{
  "type": "Feature",
  "properties": {
    "addr:full":"1836 Kempton Ave Charleston SC 29412",
    "addr:housenumber":"1836",
    "addr:postcode":"29412",
    "addr:street":"Kempton Ave",
    "iso:country":"US",
    "sg:address":"1836 Kempton Ave",
    "sg:city":"Charleston",
    "sg:classifiers":[
        {
            "category":"Shopping",
            "subcategory":"Clothing, Apparel, & Fashions",
            "type":"Retail Goods"
        }
    ],
    "sg:phone":"+1 843 795 7886",
    "sg:postcode":"29412",
    "sg:province":"SC",
    "wof:name":"First Design",
    "wof:placetype":"venue"
},
  "geometry": {"coordinates":[-79.979975,32.753162],"type":"Point"}
}