{
  "type": "Feature",
  "properties": {
    "addr:full":"1140 Briargate Cir Columbia SC 29210",
    "addr:housenumber":"1140",
    "addr:postcode":"29210",
    "addr:street":"Briargate Cir",
    "iso:country":"US",
    "sg:address":"1140 Briargate Cir",
    "sg:city":"Columbia",
    "sg:classifiers":[
        {
            "category":"Banks & Credit Unions",
            "subcategory":"Investment Brokerage",
            "type":"Services"
        }
    ],
    "sg:phone":"+1 803 731 5959",
    "sg:postcode":"29210",
    "sg:province":"SC",
    "sg:tags":[
        "consultant",
        "planning",
        "financial"
    ],
    "wof:name":"American Express Financial Adv",
    "wof:placetype":"venue"
},
  "geometry": {"coordinates":[-81.098493,34.040621],"type":"Point"}
}