{
  "type": "Feature",
  "properties": {
    "addr:full":"852 Gold Hill Rd Fort Mill SC 29708",
    "addr:housenumber":"852",
    "addr:postcode":"29708",
    "addr:street":"Gold Hill Rd",
    "iso:country":"US",
    "sg:address":"852 Gold Hill Rd",
    "sg:city":"Fort Mill",
    "sg:classifiers":[
        {
            "category":"Education",
            "subcategory":"School",
            "type":"Public Place"
        }
    ],
    "sg:phone":"+1 803 802 5737",
    "sg:postcode":"29708",
    "sg:province":"SC",
    "wof:name":"Learning Link Of The Carolinas",
    "wof:placetype":"venue"
},
  "geometry": {"coordinates":[-80.959748,35.061195],"type":"Point"}
}