{
  "type": "Feature",
  "properties": {
    "iso:country":"US",
    "sg:address":"20 Mandarin Cir",
    "sg:city":"Sumter",
    "sg:classifiers":[
        {
            "category":"Manufacturing",
            "subcategory":"Apparel",
            "type":"Manufacturing & Wholesale Goods"
        }
    ],
    "sg:phone":"+1 803 469 6240",
    "sg:postcode":"29150",
    "sg:province":"SC",
    "wof:name":"Laurias Quilts",
    "wof:placetype":"venue"
},
  "geometry": {"coordinates":[-80.404811,33.927271],"type":"Point"}
}