{
  "type": "Feature",
  "properties": {
    "iso:country":"US",
    "sg:address":"111 Memorial Dr",
    "sg:city":"Greenwood",
    "sg:classifiers":[
        {
            "category":"Real Estate",
            "subcategory":"Developer",
            "type":"Services"
        }
    ],
    "sg:phone":"+1 864 223 5628",
    "sg:postcode":"29650",
    "sg:province":"SC",
    "sg:tags":[
        "cemetery"
    ],
    "wof:name":"Evening Star Memorial Gardens",
    "wof:placetype":"venue"
},
  "geometry": {"coordinates":[-82.235848,34.944183],"type":"Point"}
}