{
  "type": "Feature",
  "properties": {
    "iso:country":"US",
    "sg:address":"3414 State Hwy 11 Scn",
    "sg:city":"Pickens",
    "sg:classifiers":[
        {
            "category":"Real Estate",
            "subcategory":"Real Estate Agent",
            "type":"Services"
        }
    ],
    "sg:phone":"+1 864 878 4200",
    "sg:postcode":"29671",
    "sg:province":"SC",
    "wof:name":"Bolding Realty",
    "wof:placetype":"venue"
},
  "geometry": {"coordinates":[-82.623862,35.047815],"type":"Point"}
}