{
  "type": "Feature",
  "properties": {
    "iso:country":"US",
    "sg:address":"6521 State Hwy 162",
    "sg:city":"Hollywood",
    "sg:classifiers":[
        {
            "category":"Banks & Credit Unions",
            "subcategory":"Bank",
            "type":"Services"
        }
    ],
    "sg:phone":"+1 843 889 6600",
    "sg:postcode":"29449",
    "sg:province":"SC",
    "sg:tags":[
        "cashing",
        "check"
    ],
    "wof:name":"Paometto Check Advance",
    "wof:placetype":"venue"
},
  "geometry": {"coordinates":[-80.257897,32.732147],"type":"Point"}
}