{
  "type": "Feature",
  "properties": {
    "iso:country":"US",
    "sg:address":"1303 Sunset Dr",
    "sg:city":"Columbia",
    "sg:classifiers":[
        {
            "category":"Manufacturing",
            "subcategory":"Printing",
            "type":"Manufacturing & Wholesale Goods"
        }
    ],
    "sg:phone":"+1 803 256 2245",
    "sg:postcode":"29203",
    "sg:province":"SC",
    "sg:tags":[
        "reporting",
        "typesetting"
    ],
    "wof:name":"Jenkins Typography",
    "wof:placetype":"venue"
},
  "geometry": {"coordinates":[-81.037041,34.029937],"type":"Point"}
}