{
  "type": "Feature",
  "properties": {
    "iso:country":"US",
    "sg:address":"4329 E North St",
    "sg:city":"Greenville",
    "sg:classifiers":[
        {
            "category":"Freight",
            "type":"Transportation"
        }
    ],
    "sg:phone":"+1 864 322 7575",
    "sg:postcode":"29615",
    "sg:province":"SC",
    "sg:tags":[
        "general"
    ],
    "wof:name":"East North Storage",
    "wof:placetype":"venue"
},
  "geometry": {"coordinates":[-82.31297000000001,34.882283],"type":"Point"}
}