{
  "type": "Feature",
  "properties": {
    "iso:country":"US",
    "sg:address":"204 Rosemary St",
    "sg:city":"Williston",
    "sg:phone":"+1 803 266 4645",
    "sg:postcode":"29853",
    "sg:province":"SC",
    "sg:tags":[
        "gas"
    ],
    "wof:name":"Edisto Gas Co",
    "wof:placetype":"venue"
},
  "geometry": {"coordinates":[-81.42716,33.399467],"type":"Point"}
}