{
  "type": "Feature",
  "properties": {
    "iso:country":"US",
    "sg:address":"1513 Gregg St",
    "sg:city":"Columbia",
    "sg:classifiers":[
        {
            "category":"Health Services",
            "subcategory":"Optometrist",
            "type":"Services"
        }
    ],
    "sg:phone":"+1 803 254 4951",
    "sg:postcode":"29201",
    "sg:province":"SC",
    "wof:name":"Clarkson Zack C Dr Jr OD",
    "wof:placetype":"venue"
},
  "geometry": {"coordinates":[-81.02449799999999,34.009399],"type":"Point"}
}