{
  "type": "Feature",
  "properties": {
    "iso:country":"US",
    "sg:address":"2006 N Ocean Blvd",
    "sg:city":"Myrtle Beach",
    "sg:classifiers":[
        {
            "category":"Travel",
            "subcategory":"Hotels & Motels",
            "type":"Entertainment"
        }
    ],
    "sg:phone":"+1 843 444 4444",
    "sg:postcode":"29577",
    "sg:province":"SC",
    "sg:tags":[
        "resort"
    ],
    "sg:website":"www.breakers.com",
    "wof:name":"Breakers Resort Hotel",
    "wof:placetype":"venue"
},
  "geometry": {"coordinates":[-78.873537,33.697801],"type":"Point"}
}