{
  "type": "Feature",
  "properties": {
    "addr:full":"156 Cabin Rd Neeses SC 29107",
    "addr:housenumber":"156",
    "addr:postcode":"29107",
    "addr:street":"Cabin Rd",
    "iso:country":"US",
    "sg:address":"156 Cabin Rd",
    "sg:city":"Neeses",
    "sg:classifiers":[
        {
            "category":"Education",
            "subcategory":"School",
            "type":"Public Place"
        }
    ],
    "sg:phone":"+1 803 263 2127",
    "sg:postcode":"29107",
    "sg:province":"SC",
    "wof:name":"Stone Wall Academy",
    "wof:placetype":"venue"
},
  "geometry": {"coordinates":[-81.106319,33.496048],"type":"Point"}
}