{
  "type": "Feature",
  "properties": {
    "iso:country":"US",
    "sg:address":"3247 Maybank Hwy",
    "sg:city":"Johns Island",
    "sg:classifiers":[
        {
            "category":"Professional",
            "type":"Services"
        }
    ],
    "sg:phone":"+1 843 559 2111",
    "sg:postcode":"29455",
    "sg:province":"SC",
    "sg:tags":[
        "establishment"
    ],
    "wof:name":"Puentes",
    "wof:placetype":"venue"
},
  "geometry": {"coordinates":[-80.060695,32.731677],"type":"Point"}
}