{
  "type": "Feature",
  "properties": {
    "iso:country":"US",
    "sg:address":"105 Sparks Ln",
    "sg:city":"Pickens",
    "sg:classifiers":[
        {
            "category":"Autos & Motor Vehicles",
            "subcategory":"Automobile Sales",
            "type":"Retail Goods"
        }
    ],
    "sg:phone":"+1 864 878 9681",
    "sg:postcode":"29671",
    "sg:province":"SC",
    "sg:tags":[
        "car",
        "dealer"
    ],
    "wof:name":"Patterson's Auto Sales",
    "wof:placetype":"venue"
},
  "geometry": {"coordinates":[-82.707871,34.895626],"type":"Point"}
}