{
  "type": "Feature",
  "properties": {
    "iso:country":"US",
    "sg:address":"305 Lamar Hwy",
    "sg:city":"Darlington",
    "sg:classifiers":[
        {
            "category":"Shopping",
            "subcategory":"Music",
            "type":"Retail Goods"
        }
    ],
    "sg:phone":"+1 843 395 1562",
    "sg:postcode":"29532",
    "sg:province":"SC",
    "sg:tags":[
        "video",
        "disc",
        "tape",
        "cassette"
    ],
    "wof:name":"Darlington Video Hollywood Tan",
    "wof:placetype":"venue"
},
  "geometry": {"coordinates":[-79.888386,34.292934],"type":"Point"}
}