{
  "type": "Feature",
  "properties": {
    "iso:country":"US",
    "sg:address":"1600 Weaver St",
    "sg:city":"Timmonsville",
    "sg:classifiers":[
        {
            "category":"Building & Trades",
            "subcategory":"Construction",
            "type":"Services"
        }
    ],
    "sg:phone":"+1 843 346 2781",
    "sg:postcode":"29161",
    "sg:province":"SC",
    "sg:tags":[
        "clearing",
        "land",
        "leveling"
    ],
    "wof:name":"Randle Inc",
    "wof:placetype":"venue"
},
  "geometry": {"coordinates":[-79.981785,34.16237],"type":"Point"}
}