{
  "type": "Feature",
  "properties": {
    "iso:country":"US",
    "sg:address":"410 Mount Vernon Rd",
    "sg:city":"Greer",
    "sg:classifiers":[
        {
            "category":"Building & Trades",
            "subcategory":"Construction",
            "type":"Services"
        }
    ],
    "sg:phone":"+1 864 877 2537",
    "sg:postcode":"29651",
    "sg:province":"SC",
    "sg:tags":[
        "contractor"
    ],
    "wof:name":"J and L Striping",
    "wof:placetype":"venue"
},
  "geometry": {"coordinates":[-82.25263699999999,34.947696],"type":"Point"}
}