{
  "type": "Feature",
  "properties": {
    "iso:country":"US",
    "sg:address":"1004 Gervais St",
    "sg:city":"Columbia",
    "sg:classifiers":[
        {
            "category":"Restaurant",
            "type":"Food & Drink"
        },
        {
            "category":"Bars & Pubs",
            "subcategory":"Nightclub",
            "type":"Food & Drink"
        }
    ],
    "sg:phone":"+1 803 765 0404",
    "sg:postcode":"29201",
    "sg:province":"SC",
    "sg:tags":[
        "new",
        "american",
        "nightlife"
    ],
    "sg:website":"www.hushcolumbia.com",
    "wof:name":"Hush",
    "wof:placetype":"venue"
},
  "geometry": {"coordinates":[-81.036361,34.000128],"type":"Point"}
}