{
  "type": "Feature",
  "properties": {
    "iso:country":"US",
    "sg:address":"15 Major Dr",
    "sg:city":"Manning",
    "sg:classifiers":[
        {
            "category":"Education",
            "subcategory":"School",
            "type":"Public Place"
        }
    ],
    "sg:phone":"+1 803 435 4435",
    "sg:postcode":"29102",
    "sg:province":"SC",
    "wof:name":"Clarendon School District 2",
    "wof:placetype":"venue"
},
  "geometry": {"coordinates":[-80.21310800000001,33.700513],"type":"Point"}
}