{
  "type": "Feature",
  "properties": {
    "iso:country":"US",
    "sg:address":"4325 Dick Pond Rd",
    "sg:city":"Myrtle Beach",
    "sg:classifiers":[
        {
            "category":"Insurance",
            "subcategory":"Insurance Agent",
            "type":"Services"
        }
    ],
    "sg:phone":"+1 843 650 9225",
    "sg:postcode":"29588",
    "sg:province":"SC",
    "wof:name":"Jackson Sumner & Assoc",
    "wof:placetype":"venue"
},
  "geometry": {"coordinates":[-78.996044,33.664115],"type":"Point"}
}