{
  "type": "Feature",
  "properties": {
    "addr:full":"45 Hollis St Greenville SC 29611",
    "addr:housenumber":"45",
    "addr:postcode":"29611",
    "addr:street":"Hollis St",
    "iso:country":"US",
    "sg:address":"45 Hollis St",
    "sg:city":"Greenville",
    "sg:classifiers":[
        {
            "category":"Shopping",
            "subcategory":"Clothing, Apparel, & Fashions",
            "type":"Retail Goods"
        }
    ],
    "sg:phone":"+1 864 298 0392",
    "sg:postcode":"29611",
    "sg:province":"SC",
    "sg:tags":[
        "family",
        "sportswear"
    ],
    "wof:name":"Hincapie Sportswear Inc",
    "wof:placetype":"venue"
},
  "geometry": {"coordinates":[-82.437112,34.844932],"type":"Point"}
}