{
  "type": "Feature",
  "properties": {
    "iso:country":"US",
    "sg:address":"2000 W Bobo Newsome Hwy",
    "sg:city":"Hartsville",
    "sg:classifiers":[
        {
            "category":"Organizations",
            "subcategory":"Religious Organization",
            "type":"Services"
        }
    ],
    "sg:phone":"+1 843 339 2005",
    "sg:postcode":"29550",
    "sg:province":"SC",
    "sg:tags":[
        "church"
    ],
    "wof:name":"Soul's Harbor Pentecostal",
    "wof:placetype":"venue"
},
  "geometry": {"coordinates":[-80.116219,34.354504],"type":"Point"}
}