{
  "type": "Feature",
  "properties": {
    "iso:country":"US",
    "sg:address":"510 N Limestone St",
    "sg:city":"Gaffney",
    "sg:classifiers":[
        {
            "category":"Building & Trades",
            "subcategory":"Equipment Rental",
            "type":"Services"
        }
    ],
    "sg:phone":"+1 864 489 1168",
    "sg:postcode":"29340",
    "sg:province":"SC",
    "sg:tags":[
        "leasing",
        "furniture"
    ],
    "wof:name":"Quality Rentals Inc",
    "wof:placetype":"venue"
},
  "geometry": {"coordinates":[-81.646226,35.076269],"type":"Point"}
}