{
  "type": "Feature",
  "properties": {
    "iso:country":"US",
    "sg:address":"2560 Church St",
    "sg:city":"Conway",
    "sg:classifiers":[
        {
            "category":"Insurance",
            "subcategory":"Insurance Agent",
            "type":"Services"
        }
    ],
    "sg:phone":"+1 843 365 9161",
    "sg:postcode":"29527",
    "sg:province":"SC",
    "wof:name":"Fogner Insurance",
    "wof:placetype":"venue"
},
  "geometry": {"coordinates":[-79.080331,33.855175],"type":"Point"}
}