{
  "type": "Feature",
  "properties": {
    "iso:country":"US",
    "sg:address":"2508 River Rd",
    "sg:city":"Piedmont",
    "sg:classifiers":[
        {
            "category":"Autos & Motor Vehicles",
            "subcategory":"Auto Supplies",
            "type":"Retail Goods"
        }
    ],
    "sg:phone":"+1 864 269 2716",
    "sg:postcode":"29673",
    "sg:province":"SC",
    "sg:tags":[
        "trailer",
        "hitch"
    ],
    "sg:website":"www.travelierta.com",
    "wof:name":"Travelier Truck Covers & Cstmz",
    "wof:placetype":"venue"
},
  "geometry": {"coordinates":[-82.475021,34.762037],"type":"Point"}
}