{
  "type": "Feature",
  "properties": {
    "addr:full":"1525 Sam Rittenberg Blvd Charleston SC 29407",
    "addr:housenumber":"1525",
    "addr:postcode":"29407",
    "addr:street":"Sam Rittenberg Blvd",
    "iso:country":"US",
    "sg:address":"1525 Sam Rittenberg Blvd",
    "sg:city":"Charleston",
    "sg:classifiers":[
        {
            "category":"Wholesale",
            "subcategory":"Durable Goods & Equipment",
            "type":"Manufacturing & Wholesale Goods"
        }
    ],
    "sg:phone":"+1 843 763 3223",
    "sg:postcode":"29407",
    "sg:province":"SC",
    "sg:tags":[
        "representative",
        "manufacturer"
    ],
    "wof:name":"James G Murphy Co",
    "wof:placetype":"venue"
},
  "geometry": {"coordinates":[-80.003766,32.810461],"type":"Point"}
}