{
  "type": "Feature",
  "properties": {
    "addr:full":"14 Shrevewood Dr Taylors SC 29687",
    "addr:housenumber":"14",
    "addr:postcode":"29687",
    "addr:street":"Shrevewood Dr",
    "iso:country":"US",
    "sg:address":"14 Shrevewood Dr",
    "sg:city":"Taylors",
    "sg:classifiers":[
        {
            "category":"Retail",
            "subcategory":"Repair Shop",
            "type":"Services"
        }
    ],
    "sg:phone":"+1 864 234 3531",
    "sg:postcode":"29687",
    "sg:province":"SC",
    "sg:tags":[
        "equipment",
        "telecommunication"
    ],
    "wof:name":"Moore and Moore Technical",
    "wof:placetype":"venue"
},
  "geometry": {"coordinates":[-82.307514,34.913187],"type":"Point"}
}