{
  "type": "Feature",
  "properties": {
    "iso:country":"US",
    "sg:address":"301 East Blvd",
    "sg:city":"Chesterfield",
    "sg:classifiers":[
        {
            "category":"Restaurant",
            "type":"Food & Drink"
        }
    ],
    "sg:menulink":"http://www.allmenus.com/sc/chesterfield/129278-subway/menu/",
    "sg:phone":"+1 843 623 2522",
    "sg:postcode":"29709",
    "sg:province":"SC",
    "sg:tags":[
        "american",
        "sandwich"
    ],
    "wof:name":"Subway",
    "wof:placetype":"venue"
},
  "geometry": {"coordinates":[-80.082235,34.733641],"type":"Point"}
}