{
  "type": "Feature",
  "properties": {
    "iso:country":"US",
    "sg:address":"1805 Woodside Dr",
    "sg:city":"Camden",
    "sg:classifiers":[
        {
            "category":"Building & Trades",
            "subcategory":"Plumbing",
            "type":"Services"
        }
    ],
    "sg:phone":"+1 803 432 7811",
    "sg:postcode":"29020",
    "sg:province":"SC",
    "sg:tags":[
        "plumbing",
        "contractor"
    ],
    "wof:name":"Sprinkle Jerry Plumbing",
    "wof:placetype":"venue"
},
  "geometry": {"coordinates":[-80.571502,34.2682],"type":"Point"}
}