{
  "type": "Feature",
  "properties": {
    "iso:country":"US",
    "sg:address":"915 Cherokee Rd",
    "sg:city":"Florence",
    "sg:classifiers":[
        {
            "category":"Professional",
            "type":"Services"
        }
    ],
    "sg:phone":"+1 843 669 3273",
    "sg:postcode":"29501",
    "sg:province":"SC",
    "sg:tags":[
        "establishment"
    ],
    "wof:name":"Dial Daily Devotion",
    "wof:placetype":"venue"
},
  "geometry": {"coordinates":[-79.782021,34.183826],"type":"Point"}
}