{
  "type": "Feature",
  "properties": {
    "iso:country":"US",
    "sg:address":"301 Pecan Hill Dr",
    "sg:city":"Simpsonville",
    "sg:classifiers":[
        {
            "category":"Wholesale",
            "subcategory":"Stationery",
            "type":"Manufacturing & Wholesale Goods"
        }
    ],
    "sg:phone":"+1 864 963 5060",
    "sg:postcode":"29681",
    "sg:province":"SC",
    "sg:tags":[
        "business",
        "form",
        "system"
    ],
    "wof:name":"Upstate Business Forms",
    "wof:placetype":"venue"
},
  "geometry": {"coordinates":[-82.252599,34.779345],"type":"Point"}
}