{
  "type": "Feature",
  "properties": {
    "iso:country":"US",
    "sg:address":"1305 Mc Lees Rd",
    "sg:city":"Anderson",
    "sg:classifiers":[
        {
            "category":"Health Services",
            "subcategory":"Health Practitioner",
            "type":"Services"
        }
    ],
    "sg:phone":"+1 864 231 1083",
    "sg:postcode":"29621",
    "sg:province":"SC",
    "sg:tags":[
        "psychologist"
    ],
    "wof:name":"Anmed Sleep Diagnostics",
    "wof:placetype":"venue"
},
  "geometry": {"coordinates":[-82.629023,34.526528],"type":"Point"}
}