{
  "type": "Feature",
  "properties": {
    "iso:country":"US",
    "sg:address":"112 W Doty Ave",
    "sg:city":"Summerville",
    "sg:classifiers":[
        {
            "category":"Health Services",
            "subcategory":"Clinic",
            "type":"Services"
        }
    ],
    "sg:phone":"+1 843 851 0999",
    "sg:postcode":"29483",
    "sg:province":"SC",
    "sg:tags":[
        "home"
    ],
    "wof:name":"Home Health Of South Carolina",
    "wof:placetype":"venue"
},
  "geometry": {"coordinates":[-80.174966,33.02012],"type":"Point"}
}