{
  "type": "Feature",
  "properties": {
    "iso:country":"US",
    "sg:address":"321 Beechwood Dr",
    "sg:city":"Greer",
    "sg:classifiers":[
        {
            "category":"Shopping",
            "type":"Retail Goods"
        }
    ],
    "sg:phone":"+1 864 879 1487",
    "sg:postcode":"29651",
    "sg:province":"SC",
    "sg:tags":[
        "chemical"
    ],
    "wof:name":"Bulk Products Inc",
    "wof:placetype":"venue"
},
  "geometry": {"coordinates":[-82.296948,34.970479],"type":"Point"}
}