{
  "type": "Feature",
  "properties": {
    "iso:country":"US",
    "sg:address":"4462 Holmestown Rd",
    "sg:city":"Myrtle Beach",
    "sg:classifiers":[
        {
            "category":"Shopping",
            "type":"Retail Goods"
        }
    ],
    "sg:phone":"+1 843 449 4576",
    "sg:postcode":"29588",
    "sg:province":"SC",
    "sg:tags":[
        "art",
        "gallery",
        "dealer"
    ],
    "wof:name":"Sadlemire Gallery",
    "wof:placetype":"venue"
},
  "geometry": {"coordinates":[-79.028401,33.629942],"type":"Point"}
}