{
  "type": "Feature",
  "properties": {
    "addr:full":"114 S Ron McNair Blvd Lake City SC 29560",
    "addr:housenumber":"114",
    "addr:postcode":"29560",
    "addr:street":"S;Mcnair Blvd",
    "iso:country":"US",
    "sg:address":"114 S Ron McNair Blvd",
    "sg:city":"Lake City",
    "sg:classifiers":[
        {
            "category":"Communications",
            "type":"Services"
        }
    ],
    "sg:phone":"+1 843 374 5601",
    "sg:postcode":"29560",
    "sg:province":"SC",
    "wof:name":"SVI Communications",
    "wof:placetype":"venue"
},
  "geometry": {"coordinates":[-79.760621,33.875433],"type":"Point"}
}