{
  "type": "Feature",
  "properties": {
    "iso:country":"US",
    "sg:address":"1943 Remount Rd",
    "sg:city":"North Charleston",
    "sg:classifiers":[
        {
            "category":"Food & Beverages",
            "subcategory":"Groceries & Convenience Stores",
            "type":"Retail Goods"
        }
    ],
    "sg:phone":"+1 843 308 0700",
    "sg:postcode":"29406",
    "sg:province":"SC",
    "sg:tags":[
        "grocer"
    ],
    "wof:name":"Tienda Mexicana LA Lupita",
    "wof:placetype":"venue"
},
  "geometry": {"coordinates":[-80.014036,32.899347],"type":"Point"}
}