{
  "type": "Feature",
  "properties": {
    "addr:full":"271 Old Mount Holly Rd Goose Creek SC 29445",
    "addr:housenumber":"271",
    "addr:postcode":"29445",
    "addr:street":"Old Mount Holly Rd",
    "iso:country":"US",
    "sg:address":"271 Old Mount Holly Rd",
    "sg:city":"Goose Creek",
    "sg:classifiers":[
        {
            "category":"Insurance",
            "subcategory":"Insurance Agent",
            "type":"Services"
        }
    ],
    "sg:phone":"+1 843 572 4826",
    "sg:postcode":"29445",
    "sg:province":"SC",
    "wof:name":"Benefits VIP",
    "wof:placetype":"venue"
},
  "geometry": {"coordinates":[-80.042874,33.032016],"type":"Point"}
}