{
  "type": "Feature",
  "properties": {
    "iso:country":"US",
    "sg:address":"1317 3rd Ave",
    "sg:city":"Conway",
    "sg:classifiers":[
        {
            "category":"Professional",
            "subcategory":"Lawyer & Legal Services",
            "type":"Services"
        }
    ],
    "sg:phone":"+1 843 248 5707",
    "sg:postcode":"29526",
    "sg:province":"SC",
    "sg:tags":[
        "attorney"
    ],
    "wof:name":"Sasser Law Firm",
    "wof:placetype":"venue"
},
  "geometry": {"coordinates":[-79.049678,33.833398],"type":"Point"}
}