{
  "type": "Feature",
  "properties": {
    "iso:country":"US",
    "sg:address":"1209 Craig Ave",
    "sg:city":"Lancaster",
    "sg:classifiers":[
        {
            "category":"Organizations",
            "subcategory":"Community Association",
            "type":"Services"
        }
    ],
    "sg:phone":"+1 803 285 8368",
    "sg:postcode":"29720",
    "sg:province":"SC",
    "sg:tags":[
        "club"
    ],
    "wof:name":"Arrowood Swim Club",
    "wof:placetype":"venue"
},
  "geometry": {"coordinates":[-80.79178,34.761275],"type":"Point"}
}