{
  "type": "Feature",
  "properties": {
    "iso:country":"US",
    "sg:address":"5409 Dick Pond Rd",
    "sg:city":"Myrtle Beach",
    "sg:classifiers":[
        {
            "category":"Shopping",
            "subcategory":"Florist",
            "type":"Retail Goods"
        }
    ],
    "sg:phone":"+1 843 215 1606",
    "sg:postcode":"29588",
    "sg:province":"SC",
    "wof:name":"King's Florist & Gifts",
    "wof:placetype":"venue"
},
  "geometry": {"coordinates":[-78.99919199999999,33.680145],"type":"Point"}
}