{
  "type": "Feature",
  "properties": {
    "iso:country":"US",
    "sg:address":"1701 S Irby St",
    "sg:city":"Florence",
    "sg:classifiers":[
        {
            "category":"Home & Garden",
            "subcategory":"Garden Supply",
            "type":"Retail Goods"
        }
    ],
    "sg:phone":"+1 843 669 5010",
    "sg:postcode":"29505",
    "sg:province":"SC",
    "sg:tags":[
        "center"
    ],
    "wof:name":"Savanna's Garden Treasures",
    "wof:placetype":"venue"
},
  "geometry": {"coordinates":[-79.765683,34.162431],"type":"Point"}
}