{
  "type": "Feature",
  "properties": {
    "addr:full":"102 Wappoo Creek Dr Charleston SC 29412",
    "addr:housenumber":"102",
    "addr:postcode":"29412",
    "addr:street":"Wappoo Creek Dr",
    "iso:country":"US",
    "sg:address":"102 Wappoo Creek Dr",
    "sg:city":"Charleston",
    "sg:classifiers":[
        {
            "category":"Professional",
            "subcategory":"Business Services",
            "type":"Services"
        }
    ],
    "sg:phone":"+1 843 723 7072",
    "sg:postcode":"29412",
    "sg:province":"SC",
    "sg:tags":[
        "broker"
    ],
    "wof:name":"Calhoun Co",
    "wof:placetype":"venue"
},
  "geometry": {"coordinates":[-79.97722400000001,32.762704],"type":"Point"}
}