{
  "type": "Feature",
  "properties": {
    "iso:country":"US",
    "sg:address":"25 Courtenay Dr",
    "sg:city":"Charleston",
    "sg:classifiers":[
        {
            "category":"Government",
            "subcategory":"Office",
            "type":"Public Place"
        }
    ],
    "sg:phone":"+1 843 958 3300",
    "sg:postcode":"29401",
    "sg:province":"SC",
    "wof:name":"Alcohol & Other Drug Abuse Svc",
    "wof:placetype":"venue"
},
  "geometry": {"coordinates":[-79.950609,32.782508],"type":"Point"}
}