{
  "type": "Feature",
  "properties": {
    "iso:country":"US",
    "sg:address":"432 Myers St",
    "sg:city":"Allendale",
    "sg:classifiers":[
        {
            "category":"Personal",
            "subcategory":"Barber",
            "type":"Services"
        }
    ],
    "sg:phone":"+1 803 584 4726",
    "sg:postcode":"29810",
    "sg:province":"SC",
    "wof:name":"Ritter's Barber & Style Shop",
    "wof:placetype":"venue"
},
  "geometry": {"coordinates":[-81.300309,33.007976],"type":"Point"}
}