{
  "type": "Feature",
  "properties": {
    "addr:full":"812 S Cashua Dr Florence SC 29501",
    "addr:housenumber":"812",
    "addr:postcode":"29501",
    "addr:street":"S Cashua Dr",
    "iso:country":"US",
    "sg:address":"812 S Cashua Dr",
    "sg:city":"Florence",
    "sg:classifiers":[
        {
            "category":"Professional",
            "subcategory":"Accounting & Tax Preparation",
            "type":"Services"
        }
    ],
    "sg:phone":"+1 843 676 0020",
    "sg:postcode":"29501",
    "sg:province":"SC",
    "sg:tags":[
        "return",
        "filing"
    ],
    "wof:name":"Fastax",
    "wof:placetype":"venue"
},
  "geometry": {"coordinates":[-79.812152,34.174902],"type":"Point"}
}