{
  "type": "Feature",
  "properties": {
    "iso:country":"US",
    "sg:address":"612 Saint Andrews Rd # 10",
    "sg:city":"Columbia",
    "sg:classifiers":[
        {
            "category":"Restaurant",
            "type":"Food & Drink"
        }
    ],
    "sg:phone":"+1 803 731 5546",
    "sg:postcode":"29210",
    "sg:province":"SC",
    "sg:tags":[
        "mexican"
    ],
    "wof:name":"Taqueria Jalisco",
    "wof:placetype":"venue"
},
  "geometry": {"coordinates":[-81.12483400000001,34.045151],"type":"Point"}
}