{
  "type": "Feature",
  "properties": {
    "iso:country":"US",
    "sg:address":"171 Gadsden St",
    "sg:city":"Chester",
    "sg:classifiers":[
        {
            "category":"Shopping",
            "subcategory":"Clothing, Apparel, & Fashions",
            "type":"Retail Goods"
        }
    ],
    "sg:phone":"+1 803 581 3262",
    "sg:postcode":"29706",
    "sg:province":"SC",
    "sg:tags":[
        "shoes"
    ],
    "wof:name":"Hare Clothiers",
    "wof:placetype":"venue"
},
  "geometry": {"coordinates":[-81.210821,34.70513],"type":"Point"}
}