{
  "type": "Feature",
  "properties": {
    "iso:country":"US",
    "sg:address":"106 Raysor St",
    "sg:city":"St George",
    "sg:classifiers":[
        {
            "category":"Retail",
            "subcategory":"Laundry & Dry Cleaning",
            "type":"Services"
        }
    ],
    "sg:phone":"+1 843 563 3081",
    "sg:postcode":"29477",
    "sg:province":"SC",
    "sg:tags":[
        "cleaners"
    ],
    "wof:name":"Wimberly Dry Cleaners",
    "wof:placetype":"venue"
},
  "geometry": {"coordinates":[-80.573663,33.187834],"type":"Point"}
}