{
  "type": "Feature",
  "properties": {
    "iso:country":"US",
    "sg:address":"217 Cricket Rd",
    "sg:city":"Swansea",
    "sg:classifiers":[
        {
            "category":"Manufacturing",
            "subcategory":"Metals",
            "type":"Manufacturing & Wholesale Goods"
        }
    ],
    "sg:phone":"+1 803 568 3613",
    "sg:postcode":"29160",
    "sg:province":"SC",
    "sg:tags":[
        "coating",
        "powder"
    ],
    "wof:name":"G & A Powder Coaters",
    "wof:placetype":"venue"
},
  "geometry": {"coordinates":[-81.001192,33.760689],"type":"Point"}
}