{
  "type": "Feature",
  "properties": {
    "iso:country":"US",
    "sg:address":"61 W Wesmark Blvd",
    "sg:city":"Sumter",
    "sg:classifiers":[
        {
            "category":"Shopping",
            "subcategory":"Used Merchandise",
            "type":"Retail Goods"
        }
    ],
    "sg:phone":"+1 803 905 1125",
    "sg:postcode":"29150",
    "sg:province":"SC",
    "sg:tags":[
        "shop",
        "consignment"
    ],
    "wof:name":"Global Consignments",
    "wof:placetype":"venue"
},
  "geometry": {"coordinates":[-80.379894,33.951045],"type":"Point"}
}