{
  "type": "Feature",
  "properties": {
    "addr:full":"2505 Main St Newberry SC 29108",
    "addr:housenumber":"2505",
    "addr:postcode":"29108",
    "addr:street":"Main St",
    "iso:country":"US",
    "sg:address":"2505 Main St",
    "sg:city":"Newberry",
    "sg:classifiers":[
        {
            "category":"Shopping",
            "subcategory":"Clothing, Apparel, & Fashions",
            "type":"Retail Goods"
        }
    ],
    "sg:phone":"+1 803 405 0303",
    "sg:postcode":"29108",
    "sg:province":"SC",
    "wof:name":"LA Princessa",
    "wof:placetype":"venue"
},
  "geometry": {"coordinates":[-81.60185799999999,34.28091],"type":"Point"}
}