{
  "type": "Feature",
  "properties": {
    "addr:full":"1015 E Cheves St Florence SC 29506",
    "addr:housenumber":"1015",
    "addr:postcode":"29506",
    "addr:street":"E Cheves St",
    "iso:country":"US",
    "sg:address":"1015 E Cheves St",
    "sg:city":"Florence",
    "sg:classifiers":[
        {
            "category":"Professional",
            "subcategory":"Accounting & Tax Preparation",
            "type":"Services"
        }
    ],
    "sg:phone":"+1 843 669 0431",
    "sg:postcode":"29506",
    "sg:province":"SC",
    "sg:tags":[
        "return",
        "filing"
    ],
    "wof:name":"Hawkins Tax Svc",
    "wof:placetype":"venue"
},
  "geometry": {"coordinates":[-79.752965,34.196301],"type":"Point"}
}