{
  "type": "Feature",
  "properties": {
    "addr:full":"1650 Highway 160 W Fort Mill SC 29708",
    "addr:housenumber":"1650",
    "addr:postcode":"29708",
    "addr:street":"Highway 160 W",
    "iso:country":"US",
    "sg:address":"1650 Highway 160 W",
    "sg:city":"Fort Mill",
    "sg:classifiers":[
        {
            "category":"Restaurant",
            "type":"Food & Drink"
        }
    ],
    "sg:menulink":"http://www.allmenus.com/sc/fort-mill/211026-burger-king/menu/",
    "sg:phone":"+1 803 802 7906",
    "sg:postcode":"29708",
    "sg:province":"SC",
    "sg:tags":[
        "burger",
        "american"
    ],
    "wof:name":"Burger King",
    "wof:placetype":"venue"
},
  "geometry": {"coordinates":[-80.968,35.031892],"type":"Point"}
}