{
  "type": "Feature",
  "properties": {
    "addr:full":"1101 Roe Ford Rd Greenville SC 29617",
    "addr:housenumber":"1101",
    "addr:postcode":"29617",
    "addr:street":"Roe Ford Rd",
    "iso:country":"US",
    "sg:address":"1101 Roe Ford Rd",
    "sg:city":"Greenville",
    "sg:classifiers":[
        {
            "category":"Organizations",
            "subcategory":"Religious Organization",
            "type":"Services"
        }
    ],
    "sg:phone":"+1 864 246 8804",
    "sg:postcode":"29617",
    "sg:province":"SC",
    "sg:tags":[
        "church"
    ],
    "wof:name":"Mt Sinai Baptist Church",
    "wof:placetype":"venue"
},
  "geometry": {"coordinates":[-82.449236,34.937351],"type":"Point"}
}