{
  "type": "Feature",
  "properties": {
    "iso:country":"US",
    "sg:address":"114 Tomaka Dr",
    "sg:city":"Summerville",
    "sg:classifiers":[
        {
            "category":"Organizations",
            "subcategory":"Religious Organization",
            "type":"Services"
        }
    ],
    "sg:phone":"+1 843 871 2999",
    "sg:postcode":"29483",
    "sg:province":"SC",
    "sg:tags":[
        "church"
    ],
    "sg:website":"www.palmettoland.org",
    "wof:name":"Palmetto Land Baptist Church",
    "wof:placetype":"venue"
},
  "geometry": {"coordinates":[-80.139476,33.034559],"type":"Point"}
}