{
  "type": "Feature",
  "properties": {
    "addr:full":"2821 Devine St Columbia SC 29205",
    "addr:housenumber":"2821",
    "addr:postcode":"29205",
    "addr:street":"Devine St",
    "iso:country":"US",
    "sg:address":"2821 Devine St",
    "sg:city":"Columbia",
    "sg:classifiers":[
        {
            "category":"Shopping",
            "subcategory":"Clothing, Apparel, & Fashions",
            "type":"Retail Goods"
        }
    ],
    "sg:phone":"+1 803 765 9982",
    "sg:postcode":"29205",
    "sg:province":"SC",
    "sg:tags":[
        "lingerie"
    ],
    "wof:name":"I See France",
    "wof:placetype":"venue"
},
  "geometry": {"coordinates":[-81.001575,33.998074],"type":"Point"}
}