{
  "type": "Feature",
  "properties": {
    "addr:full":"825 Knox Abbott Dr Cayce SC 29033",
    "addr:housenumber":"825",
    "addr:postcode":"29033",
    "addr:street":"Knox Abbott Dr",
    "iso:country":"US",
    "sg:address":"825 Knox Abbott Dr",
    "sg:city":"Cayce",
    "sg:classifiers":[
        {
            "category":"Shopping",
            "subcategory":"Mobile Phones",
            "type":"Retail Goods"
        }
    ],
    "sg:phone":"+1 803 939 0110",
    "sg:postcode":"29033",
    "sg:province":"SC",
    "wof:name":"Sprint Pcs Cayce",
    "wof:placetype":"venue"
},
  "geometry": {"coordinates":[-81.063202,33.981602],"type":"Point"}
}