{
  "type": "Feature",
  "properties": {
    "iso:country":"US",
    "sg:address":"189 Rd 30",
    "sg:city":"Lake View",
    "sg:phone":"+1 843 759 2620",
    "sg:postcode":"29563",
    "sg:province":"SC",
    "sg:tags":[
        "farm",
        "wheat",
        "tobacco"
    ],
    "wof:name":"Betty Cox",
    "wof:placetype":"venue"
},
  "geometry": {"coordinates":[-79.16644100000001,34.355358],"type":"Point"}
}