{
  "type": "Feature",
  "properties": {
    "addr:full":"4898 S Kings Hwy Myrtle Beach SC 29575",
    "addr:housenumber":"4898",
    "addr:postcode":"29575",
    "addr:street":"S Kings Hwy",
    "iso:country":"US",
    "sg:address":"4898 S Kings Hwy",
    "sg:city":"Myrtle Beach",
    "sg:classifiers":[
        {
            "category":"Shopping",
            "type":"Retail Goods"
        }
    ],
    "sg:phone":"+1 843 272 7080",
    "sg:postcode":"29575",
    "sg:province":"SC",
    "sg:tags":[
        "candle"
    ],
    "wof:name":"Barefoot Candles",
    "wof:placetype":"venue"
},
  "geometry": {"coordinates":[-78.944512,33.644429],"type":"Point"}
}