{
  "type": "Feature",
  "properties": {
    "iso:country":"US",
    "sg:address":"114 S Jacob Smart Blvd",
    "sg:city":"Ridgeland",
    "sg:classifiers":[
        {
            "category":"Health Services",
            "subcategory":"Doctor",
            "type":"Services"
        }
    ],
    "sg:phone":"+1 843 717 2590",
    "sg:postcode":"29936",
    "sg:province":"SC",
    "sg:tags":[
        "physician",
        "surgeon"
    ],
    "wof:name":"Coastal Medical Assoc",
    "wof:placetype":"venue"
},
  "geometry": {"coordinates":[-80.982388,32.476447],"type":"Point"}
}