{
  "type": "Feature",
  "properties": {
    "iso:country":"US",
    "sg:address":"51 Old Trolley Rd",
    "sg:city":"Summerville",
    "sg:classifiers":[
        {
            "category":"Wholesale",
            "subcategory":"Meat",
            "type":"Manufacturing & Wholesale Goods"
        }
    ],
    "sg:phone":"+1 843 851 2267",
    "sg:postcode":"29485",
    "sg:province":"SC",
    "wof:name":"JC Meats Inc",
    "wof:placetype":"venue"
},
  "geometry": {"coordinates":[-80.1837,33.000198],"type":"Point"}
}