{
  "type": "Feature",
  "properties": {
    "iso:country":"US",
    "sg:address":"711 Richland Ave W",
    "sg:city":"Aiken",
    "sg:classifiers":[
        {
            "category":"Real Estate",
            "subcategory":"Real Estate Agent",
            "type":"Services"
        }
    ],
    "sg:phone":"+1 803 649 4197",
    "sg:postcode":"29801",
    "sg:province":"SC",
    "wof:name":"Virginia Dunkelbarger R Estate",
    "wof:placetype":"venue"
},
  "geometry": {"coordinates":[-81.726387,33.56278],"type":"Point"}
}