{
  "type": "Feature",
  "properties": {
    "iso:country":"US",
    "sg:address":"7700 Camp Mac Boykin Rd",
    "sg:city":"Pinewood",
    "sg:classifiers":[
        {
            "category":"Food & Beverages",
            "subcategory":"Groceries & Convenience Stores",
            "type":"Retail Goods"
        }
    ],
    "sg:phone":"+1 803 452 6713",
    "sg:postcode":"29125",
    "sg:province":"SC",
    "sg:tags":[
        "grocer"
    ],
    "wof:name":"Dot's Grocery & Grill",
    "wof:placetype":"venue"
},
  "geometry": {"coordinates":[-80.51561,33.708471],"type":"Point"}
}