{
  "type": "Feature",
  "properties": {
    "iso:country":"US",
    "sg:address":"142 S Dean St",
    "sg:city":"Spartanburg",
    "sg:classifiers":[
        {
            "category":"Government",
            "subcategory":"Office",
            "type":"Public Place"
        }
    ],
    "sg:phone":"+1 864 596 2553",
    "sg:postcode":"29302",
    "sg:province":"SC",
    "wof:name":"Spartanburg County Veterans",
    "wof:placetype":"venue"
},
  "geometry": {"coordinates":[-81.92642499999999,34.950074],"type":"Point"}
}