{
  "type": "Feature",
  "properties": {
    "iso:country":"US",
    "sg:address":"838 Rocky River Rd",
    "sg:city":"Lancaster",
    "sg:classifiers":[
        {
            "category":"Social Services",
            "subcategory":"Child Care",
            "type":"Services"
        }
    ],
    "sg:phone":"+1 803 289 1927",
    "sg:postcode":"29720",
    "sg:province":"SC",
    "wof:name":"Angels R Us",
    "wof:placetype":"venue"
},
  "geometry": {"coordinates":[-80.619325,34.721897],"type":"Point"}
}