{
  "type": "Feature",
  "properties": {
    "iso:country":"US",
    "sg:address":"101 E Dekalb St",
    "sg:city":"Camden",
    "sg:classifiers":[
        {
            "category":"Restaurant",
            "type":"Food & Drink"
        }
    ],
    "sg:menulink":"http://www.allmenus.com/sc/camden/176656-kfc---kentucky-fried-chicken/menu/",
    "sg:phone":"+1 803 432 3651",
    "sg:postcode":"29020",
    "sg:province":"SC",
    "sg:tags":[
        "american",
        "chicken"
    ],
    "wof:name":"KFC - Kentucky Fried Chicken",
    "wof:placetype":"venue"
},
  "geometry": {"coordinates":[-80.59521700000001,34.247173],"type":"Point"}
}