{
  "type": "Feature",
  "properties": {
    "iso:country":"US",
    "sg:address":"2367 Roper Mountain Rd",
    "sg:city":"Simpsonville",
    "sg:classifiers":[
        {
            "category":"Building & Trades",
            "subcategory":"Construction",
            "type":"Services"
        }
    ],
    "sg:phone":"+1 864 675 9111",
    "sg:postcode":"29681",
    "sg:province":"SC",
    "sg:tags":[
        "house"
    ],
    "sg:website":"www.dwgleaves.com",
    "wof:name":"D W Gleaves Co Inc",
    "wof:placetype":"venue"
},
  "geometry": {"coordinates":[-82.226878,34.822159],"type":"Point"}
}