{
  "type": "Feature",
  "properties": {
    "iso:country":"US",
    "sg:address":"501 W Roughfork St",
    "sg:city":"Florence",
    "sg:classifiers":[
        {
            "category":"Personal",
            "subcategory":"Beauty Salon",
            "type":"Services"
        }
    ],
    "sg:phone":"+1 843 669 5191",
    "sg:postcode":"29501",
    "sg:province":"SC",
    "sg:tags":[
        "manicuring"
    ],
    "wof:name":"Nails Of Essence",
    "wof:placetype":"venue"
},
  "geometry": {"coordinates":[-79.768321,34.210121],"type":"Point"}
}