{
  "type": "Feature",
  "properties": {
    "iso:country":"US",
    "sg:address":"410 S Main St",
    "sg:city":"Greer",
    "sg:classifiers":[
        {
            "category":"Organizations",
            "subcategory":"Religious Organization",
            "type":"Services"
        }
    ],
    "sg:phone":"+1 864 877 2672",
    "sg:postcode":"29650",
    "sg:province":"SC",
    "sg:tags":[
        "church"
    ],
    "wof:name":"Southside Baptist Church",
    "wof:placetype":"venue"
},
  "geometry": {"coordinates":[-82.230954,34.931545],"type":"Point"}
}