{
  "type": "Feature",
  "properties": {
    "addr:full":"1527 Senate St Columbia SC 29201",
    "addr:housenumber":"1527",
    "addr:postcode":"29201",
    "addr:street":"Senate St",
    "iso:country":"US",
    "sg:address":"1527 Senate St",
    "sg:city":"Columbia",
    "sg:classifiers":[
        {
            "category":"Organizations",
            "subcategory":"Professional Association",
            "type":"Services"
        }
    ],
    "sg:phone":"+1 803 777 4111",
    "sg:postcode":"29201",
    "sg:province":"SC",
    "sg:website":"www.carolinaalumni.org",
    "wof:name":"CAROLINA Alumni Assn",
    "wof:placetype":"venue"
},
  "geometry": {"coordinates":[-81.026892,34.001708],"type":"Point"}
}