{
  "type": "Feature",
  "properties": {
    "addr:full":"144 E Church St Leesville SC 29070",
    "addr:housenumber":"144",
    "addr:postcode":"29070",
    "addr:street":"E Church St",
    "iso:country":"US",
    "sg:address":"144 E Church St",
    "sg:city":"Leesville",
    "sg:classifiers":[
        {
            "category":"Wholesale",
            "subcategory":"Plants",
            "type":"Manufacturing & Wholesale Goods"
        }
    ],
    "sg:phone":"+1 803 532 3599",
    "sg:postcode":"29070",
    "sg:province":"SC",
    "sg:tags":[
        "supply"
    ],
    "wof:name":"Carols Creations",
    "wof:placetype":"venue"
},
  "geometry": {"coordinates":[-81.52558999999999,33.915091],"type":"Point"}
}