{
  "type": "Feature",
  "properties": {
    "iso:country":"US",
    "sg:address":"133 Runion Dr",
    "sg:city":"Greer",
    "sg:classifiers":[
        {
            "category":"Building & Trades",
            "subcategory":"Construction",
            "type":"Services"
        }
    ],
    "sg:phone":"+1 864 877 1798",
    "sg:postcode":"29651",
    "sg:province":"SC",
    "sg:tags":[
        "contractor"
    ],
    "wof:name":"Drywall Carolina",
    "wof:placetype":"venue"
},
  "geometry": {"coordinates":[-82.221411,34.876373],"type":"Point"}
}