{
  "type": "Feature",
  "properties": {
    "addr:full":"115 W Main St Dillon SC 29536",
    "addr:housenumber":"115",
    "addr:postcode":"29536",
    "addr:street":"W Main St",
    "iso:country":"US",
    "sg:address":"115 W Main St",
    "sg:city":"Dillon",
    "sg:classifiers":[
        {
            "category":"Shopping",
            "subcategory":"Discount & Variety Stores",
            "type":"Retail Goods"
        }
    ],
    "sg:phone":"+1 843 774 5380",
    "sg:postcode":"29536",
    "sg:province":"SC",
    "wof:name":"Dollar Deal",
    "wof:placetype":"venue"
},
  "geometry": {"coordinates":[-79.373465,34.417712],"type":"Point"}
}