{
  "type": "Feature",
  "properties": {
    "addr:full":"7843 State Hwy 395 Newberry SC 29108",
    "addr:housenumber":"7843",
    "addr:postcode":"29108",
    "addr:street":"State Hwy 395",
    "iso:country":"US",
    "sg:address":"7843 State Hwy 395",
    "sg:city":"Newberry",
    "sg:classifiers":[
        {
            "category":"Building & Trades",
            "subcategory":"Construction",
            "type":"Services"
        }
    ],
    "sg:phone":"+1 803 276 0905",
    "sg:postcode":"29108",
    "sg:province":"SC",
    "sg:tags":[
        "industrial"
    ],
    "wof:name":"Dixie Pole Buildings Inc",
    "wof:placetype":"venue"
},
  "geometry": {"coordinates":[-81.60942,34.250965],"type":"Point"}
}