{
  "type": "Feature",
  "properties": {
    "addr:full":"143 Firestone Ct Sellers SC 29592",
    "addr:housenumber":"143",
    "addr:postcode":"29592",
    "addr:street":"Firestone Ct",
    "iso:country":"US",
    "sg:address":"143 Firestone Ct",
    "sg:city":"Sellers",
    "sg:classifiers":[
        {
            "category":"Building & Trades",
            "subcategory":"Construction",
            "type":"Services"
        }
    ],
    "sg:phone":"+1 843 752 7844",
    "sg:postcode":"29592",
    "sg:province":"SC",
    "sg:tags":[
        "house"
    ],
    "wof:name":"Carters Construction Co",
    "wof:placetype":"venue"
},
  "geometry": {"coordinates":[-79.451476,34.309503],"type":"Point"}
}