{
  "type": "Feature",
  "properties": {
    "iso:country":"US",
    "sg:address":"1363 Lake Murray Blvd",
    "sg:city":"Irmo",
    "sg:classifiers":[
        {
            "category":"Banks & Credit Unions",
            "subcategory":"Bank",
            "type":"Services"
        }
    ],
    "sg:phone":"+1 803 749 5000",
    "sg:postcode":"29212",
    "sg:province":"SC",
    "wof:name":"National Bank-South Carolina",
    "wof:placetype":"venue"
},
  "geometry": {"coordinates":[-81.186219,34.084817],"type":"Point"}
}