{
  "type": "Feature",
  "properties": {
    "addr:full":"5764 Rosewood Dr Myrtle Beach SC 29588",
    "addr:housenumber":"5764",
    "addr:postcode":"29588",
    "addr:street":"Rosewood Dr",
    "iso:country":"US",
    "sg:address":"5764 Rosewood Dr",
    "sg:city":"Myrtle Beach",
    "sg:classifiers":[
        {
            "category":"Building & Trades",
            "subcategory":"Construction",
            "type":"Services"
        }
    ],
    "sg:phone":"+1 843 293 1830",
    "sg:postcode":"29588",
    "sg:province":"SC",
    "sg:tags":[
        "hanging",
        "contractor"
    ],
    "wof:name":"C R Austin Painting Inc",
    "wof:placetype":"venue"
},
  "geometry": {"coordinates":[-78.9926,33.690843],"type":"Point"}
}