{
  "type": "Feature",
  "properties": {
    "iso:country":"US",
    "sg:address":"857 Holly St",
    "sg:city":"Orangeburg",
    "sg:classifiers":[
        {
            "category":"Arts & Performance",
            "subcategory":"Theater",
            "type":"Entertainment"
        }
    ],
    "sg:phone":"+1 803 534 9989",
    "sg:postcode":"29115",
    "sg:province":"SC",
    "sg:tags":[
        "bureau"
    ],
    "wof:name":"MEA Entertainment Records",
    "wof:placetype":"venue"
},
  "geometry": {"coordinates":[-80.866551,33.501099],"type":"Point"}
}