{
  "type": "Feature",
  "properties": {
    "addr:full":"535 Broadway St Myrtle Beach SC 29577",
    "addr:housenumber":"535",
    "addr:postcode":"29577",
    "addr:street":"Broadway St",
    "iso:country":"US",
    "sg:address":"535 Broadway St",
    "sg:city":"Myrtle Beach",
    "sg:classifiers":[
        {
            "category":"Wholesale",
            "subcategory":"Auto Parts",
            "type":"Manufacturing & Wholesale Goods"
        }
    ],
    "sg:phone":"+1 843 448 3468",
    "sg:postcode":"29577",
    "sg:province":"SC",
    "sg:tags":[
        "repair",
        "general",
        "automotive"
    ],
    "wof:name":"Carolina Generator & Starter",
    "wof:placetype":"venue"
},
  "geometry": {"coordinates":[-78.888564,33.692668],"type":"Point"}
}