{
  "type": "Feature",
  "properties": {
    "addr:full":"2620 Poinsett Hwy Greenville SC 29609",
    "addr:housenumber":"2620",
    "addr:postcode":"29609",
    "addr:street":"Poinsett Hwy",
    "iso:country":"US",
    "sg:address":"2620 Poinsett Hwy",
    "sg:city":"Greenville",
    "sg:classifiers":[
        {
            "category":"Restaurant",
            "type":"Food & Drink"
        }
    ],
    "sg:phone":"+1 864 232 5333",
    "sg:postcode":"29609",
    "sg:province":"SC",
    "wof:name":"Dog House",
    "wof:placetype":"venue"
},
  "geometry": {"coordinates":[-82.429694,34.915312],"type":"Point"}
}