{
  "type": "Feature",
  "properties": {
    "iso:country":"US",
    "sg:address":"1703 A Laurel St",
    "sg:city":"Columbia",
    "sg:classifiers":[
        {
            "category":"Personal",
            "subcategory":"Skin Care",
            "type":"Services"
        }
    ],
    "sg:phone":"+1 803 454 2790",
    "sg:postcode":"29201",
    "sg:province":"SC",
    "wof:name":"Jan Counts Skin Specialist",
    "wof:placetype":"venue"
},
  "geometry": {"coordinates":[-81.028966,34.01216],"type":"Point"}
}