{
  "type": "Feature",
  "properties": {
    "iso:country":"US",
    "sg:address":"5 Whiteoaks Cir",
    "sg:city":"Bluffton",
    "sg:classifiers":[
        {
            "category":"Building & Trades",
            "subcategory":"Construction",
            "type":"Services"
        }
    ],
    "sg:phone":"+1 843 757 5452",
    "sg:postcode":"29910",
    "sg:province":"SC",
    "sg:tags":[
        "home",
        "builder"
    ],
    "wof:name":"Sawgrass Home Inc",
    "wof:placetype":"venue"
},
  "geometry": {"coordinates":[-80.886163,32.279394],"type":"Point"}
}