{
  "type": "Feature",
  "properties": {
    "iso:country":"US",
    "sg:address":"1368 Harbor St",
    "sg:city":"Georgetown",
    "sg:classifiers":[
        {
            "category":"Bus Charters",
            "type":"Transportation"
        },
        {
            "category":"Travel",
            "subcategory":"Travel Agent",
            "type":"Entertainment"
        }
    ],
    "sg:phone":"+1 843 527 3680",
    "sg:postcode":"29440",
    "sg:province":"SC",
    "sg:tags":[
        "company",
        "agency",
        "bureau",
        "tour"
    ],
    "wof:name":"Road Scholar Tours Inc",
    "wof:placetype":"venue"
},
  "geometry": {"coordinates":[-79.288266,33.354953],"type":"Point"}
}