{
  "type": "Feature",
  "properties": {
    "iso:country":"US",
    "sg:address":"2356 Pepper Rd",
    "sg:city":"Lexington",
    "sg:classifiers":[
        {
            "category":"Building & Trades",
            "subcategory":"Construction",
            "type":"Services"
        }
    ],
    "sg:phone":"+1 803 892 3401",
    "sg:postcode":"29073",
    "sg:province":"SC",
    "sg:tags":[
        "contractor"
    ],
    "wof:name":"Ornamental Iron Works",
    "wof:placetype":"venue"
},
  "geometry": {"coordinates":[-81.29919599999999,33.889953],"type":"Point"}
}