{
  "type": "Feature",
  "properties": {
    "addr:full":"1004 Old Hwy 52 Moncks Corner SC 29461",
    "addr:housenumber":"1004",
    "addr:postcode":"29461",
    "addr:street":"Old Hwy 52",
    "iso:country":"US",
    "sg:address":"1004 Old Hwy 52",
    "sg:city":"Moncks Corner",
    "sg:classifiers":[
        {
            "category":"Government",
            "subcategory":"Office",
            "type":"Public Place"
        }
    ],
    "sg:phone":"+1 843 761 8236",
    "sg:postcode":"29461",
    "sg:province":"SC",
    "wof:name":"Berkeley Cnty Chamber-Commerce",
    "wof:placetype":"venue"
},
  "geometry": {"coordinates":[-79.999813,33.186886],"type":"Point"}
}