{
  "type": "Feature",
  "properties": {
    "iso:country":"US",
    "sg:address":"766 W Main St",
    "sg:city":"Lexington",
    "sg:classifiers":[
        {
            "category":"Restaurant",
            "type":"Food & Drink"
        }
    ],
    "sg:phone":"+1 803 359 8789",
    "sg:postcode":"29072",
    "sg:province":"SC",
    "sg:tags":[
        "barbecue"
    ],
    "sg:website":"www.mauricebbq.com",
    "wof:name":"Maurice's Gourmet Barbeque",
    "wof:placetype":"venue"
},
  "geometry": {"coordinates":[-81.249898,33.984739],"type":"Point"}
}