{
  "type": "Feature",
  "properties": {
    "iso:country":"US",
    "sg:address":"222 S Main St",
    "sg:city":"Belton",
    "sg:classifiers":[
        {
            "category":"Restaurant",
            "type":"Food & Drink"
        }
    ],
    "sg:phone":"+1 864 338 9122",
    "sg:postcode":"29627",
    "sg:province":"SC",
    "sg:tags":[
        "eating"
    ],
    "wof:name":"Jake's On Main",
    "wof:placetype":"venue"
},
  "geometry": {"coordinates":[-82.492872,34.521434],"type":"Point"}
}