{
  "type": "Feature",
  "properties": {
    "iso:country":"US",
    "sg:address":"230 Buck Island Rd",
    "sg:city":"Bluffton",
    "sg:classifiers":[
        {
            "category":"Professional",
            "subcategory":"Business Services",
            "type":"Services"
        }
    ],
    "sg:phone":"+1 843 757 4658",
    "sg:postcode":"29910",
    "sg:province":"SC",
    "sg:tags":[
        "interior",
        "consultant",
        "design",
        "decorator"
    ],
    "wof:name":"Erni Stoney's Fashions",
    "wof:placetype":"venue"
},
  "geometry": {"coordinates":[-80.881384,32.255446],"type":"Point"}
}