{
  "type": "Feature",
  "properties": {
    "iso:country":"US",
    "sg:address":"398 Hitchcock Pkwy",
    "sg:city":"Aiken",
    "sg:classifiers":[
        {
            "category":"Home & Garden",
            "subcategory":"Garden Supply",
            "type":"Retail Goods"
        }
    ],
    "sg:phone":"+1 803 648 3592",
    "sg:postcode":"29801",
    "sg:province":"SC",
    "sg:tags":[
        "center"
    ],
    "wof:name":"Cold Creek Nurseries",
    "wof:placetype":"venue"
},
  "geometry": {"coordinates":[-81.771811,33.533054],"type":"Point"}
}