{
  "type": "Feature",
  "properties": {
    "addr:full":"941 Berry St Orangeburg SC 29115",
    "addr:housenumber":"941",
    "addr:postcode":"29115",
    "addr:street":"Berry St",
    "iso:country":"US",
    "sg:address":"941 Berry St",
    "sg:city":"Orangeburg",
    "sg:classifiers":[
        {
            "category":"Personal",
            "subcategory":"Beauty Salon",
            "type":"Services"
        }
    ],
    "sg:phone":"+1 803 536 3120",
    "sg:postcode":"29115",
    "sg:province":"SC",
    "wof:name":"At Stephanie's",
    "wof:placetype":"venue"
},
  "geometry": {"coordinates":[-80.86282799999999,33.505907],"type":"Point"}
}