{
  "type": "Feature",
  "properties": {
    "iso:country":"US",
    "sg:address":"3609 Trask Pkwy",
    "sg:city":"Beaufort",
    "sg:classifiers":[
        {
            "category":"Retail",
            "subcategory":"Auto Repair",
            "type":"Services"
        }
    ],
    "sg:phone":"+1 843 524 3797",
    "sg:postcode":"29906",
    "sg:province":"SC",
    "sg:tags":[
        "muffler",
        "exhaust",
        "system"
    ],
    "wof:name":"Omar's Muffler & Auto Repair",
    "wof:placetype":"venue"
},
  "geometry": {"coordinates":[-80.724593,32.442805],"type":"Point"}
}