{
  "type": "Feature",
  "properties": {
    "addr:full":"221 Wycliffe Dr Greer SC 29650",
    "addr:housenumber":"221",
    "addr:postcode":"29650",
    "addr:street":"Wycliffe Dr",
    "iso:country":"US",
    "sg:address":"221 Wycliffe Dr",
    "sg:city":"Greer",
    "sg:classifiers":[
        {
            "category":"Airline",
            "type":"Transportation"
        }
    ],
    "sg:phone":"+1 864 292 3110",
    "sg:postcode":"29650",
    "sg:province":"SC",
    "sg:tags":[
        "nonscheduled",
        "air"
    ],
    "wof:name":"Christopher Air LLC",
    "wof:placetype":"venue"
},
  "geometry": {"coordinates":[-82.27795999999999,34.875694],"type":"Point"}
}