{
  "type": "Feature",
  "properties": {
    "addr:full":"4840 Forest Dr Columbia SC 29204",
    "addr:housenumber":"4840",
    "addr:postcode":"29204",
    "addr:street":"Forest Dr",
    "iso:country":"US",
    "sg:address":"4840 Forest Dr",
    "sg:city":"Columbia",
    "sg:classifiers":[
        {
            "category":"Shopping",
            "subcategory":"Clothing, Apparel, & Fashions",
            "type":"Retail Goods"
        }
    ],
    "sg:phone":"+1 803 782 6944",
    "sg:postcode":"29204",
    "sg:province":"SC",
    "wof:name":"Chico's",
    "wof:placetype":"venue"
},
  "geometry": {"coordinates":[-80.963801,34.018613],"type":"Point"}
}