{
  "type": "Feature",
  "properties": {
    "addr:full":"439 Union St Spartanburg SC 29302",
    "addr:housenumber":"439",
    "addr:postcode":"29302",
    "addr:street":"Union St",
    "iso:country":"US",
    "sg:address":"439 Union St",
    "sg:city":"Spartanburg",
    "sg:classifiers":[
        {
            "category":"Organizations",
            "subcategory":"Religious Organization",
            "type":"Services"
        }
    ],
    "sg:phone":"+1 864 582 5700",
    "sg:postcode":"29302",
    "sg:province":"SC",
    "sg:tags":[
        "church"
    ],
    "wof:name":"For His Glory Ministry",
    "wof:placetype":"venue"
},
  "geometry": {"coordinates":[-81.918758,34.945213],"type":"Point"}
}