{
  "type": "Feature",
  "properties": {
    "iso:country":"US",
    "sg:address":"321 Anthony St",
    "sg:city":"Batesburg",
    "sg:classifiers":[
        {
            "category":"Freight",
            "type":"Transportation"
        }
    ],
    "sg:phone":"+1 803 532 4555",
    "sg:postcode":"29006",
    "sg:province":"SC",
    "sg:tags":[
        "trucking"
    ],
    "wof:name":"Palmetto Trucking Svc",
    "wof:placetype":"venue"
},
  "geometry": {"coordinates":[-81.538872,33.895545],"type":"Point"}
}