{
  "type": "Feature",
  "properties": {
    "addr:full":"124 Dusty Trail Ln Myrtle Beach SC 29575",
    "addr:housenumber":"124",
    "addr:postcode":"29575",
    "addr:street":"Dusty Trail Ln",
    "iso:country":"US",
    "sg:address":"124 Dusty Trail Ln",
    "sg:city":"Myrtle Beach",
    "sg:classifiers":[
        {
            "category":"Professional",
            "subcategory":"Accounting & Tax Preparation",
            "type":"Services"
        }
    ],
    "sg:phone":"+1 843 215 5195",
    "sg:postcode":"29575",
    "sg:province":"SC",
    "sg:tags":[
        "return",
        "filing"
    ],
    "wof:name":"Debra's Accounting & Tax Svc",
    "wof:placetype":"venue"
},
  "geometry": {"coordinates":[-78.993135,33.617877],"type":"Point"}
}