{
  "type": "Feature",
  "properties": {
    "iso:country":"US",
    "sg:address":"721 Westminster Hwy",
    "sg:city":"Westminster",
    "sg:classifiers":[
        {
            "category":"Retail",
            "subcategory":"Repair Shop",
            "type":"Services"
        }
    ],
    "sg:phone":"+1 864 647 0892",
    "sg:postcode":"29693",
    "sg:province":"SC",
    "sg:tags":[
        "repairing",
        "piano",
        "refinishing"
    ],
    "wof:name":"Boggs Piano Svc",
    "wof:placetype":"venue"
},
  "geometry": {"coordinates":[-83.08677299999999,34.680855],"type":"Point"}
}