{
  "type": "Feature",
  "properties": {
    "iso:country":"US",
    "sg:address":"7 Rapids Ct",
    "sg:city":"North Augusta",
    "sg:classifiers":[
        {
            "category":"Shopping",
            "type":"Retail Goods"
        }
    ],
    "sg:phone":"+1 803 613 9292",
    "sg:postcode":"29841",
    "sg:province":"SC",
    "sg:tags":[
        "merchandise"
    ],
    "wof:name":"Pet Pals Ptstting Prfessionals",
    "wof:placetype":"venue"
},
  "geometry": {"coordinates":[-81.991596,33.518993],"type":"Point"}
}