{
  "type": "Feature",
  "properties": {
    "addr:full":"21 Washington Dr Piedmont SC 29673",
    "addr:housenumber":"21",
    "addr:postcode":"29673",
    "addr:street":"Washington Dr",
    "iso:country":"US",
    "sg:address":"21 Washington Dr",
    "sg:city":"Piedmont",
    "sg:classifiers":[
        {
            "category":"Building & Trades",
            "subcategory":"Electrical",
            "type":"Services"
        }
    ],
    "sg:phone":"+1 864 269 6161",
    "sg:postcode":"29673",
    "sg:province":"SC",
    "sg:tags":[
        "electric",
        "contractor"
    ],
    "wof:name":"Superior Electrical Contrs",
    "wof:placetype":"venue"
},
  "geometry": {"coordinates":[-82.50984699999999,34.757062],"type":"Point"}
}