{
  "type": "Feature",
  "properties": {
    "iso:country":"US",
    "sg:address":"310 Catawba Ave",
    "sg:city":"Rock Hill",
    "sg:classifiers":[
        {
            "category":"Utilities",
            "subcategory":"Cable",
            "type":"Services"
        }
    ],
    "sg:phone":"+1 803 327 5129",
    "sg:postcode":"29730",
    "sg:province":"SC",
    "sg:tags":[
        "television"
    ],
    "wof:name":"Paul Koterba",
    "wof:placetype":"venue"
},
  "geometry": {"coordinates":[-81.021187,34.935331],"type":"Point"}
}