{
  "type": "Feature",
  "properties": {
    "addr:full":"1530 Wingate St NE Orangeburg SC 29118",
    "addr:housenumber":"1530",
    "addr:postcode":"29118",
    "addr:street":"Wingate St Ne",
    "iso:country":"US",
    "sg:address":"1530 Wingate St NE",
    "sg:city":"Orangeburg",
    "sg:classifiers":[
        {
            "category":"Banks & Credit Unions",
            "subcategory":"Financial Services",
            "type":"Services"
        },
        {
            "category":"Professional",
            "subcategory":"Accounting & Tax Preparation",
            "type":"Services"
        }
    ],
    "sg:phone":"+1 803 531 6076",
    "sg:postcode":"29118",
    "sg:province":"SC",
    "sg:tags":[
        "patent",
        "return",
        "filing"
    ],
    "wof:name":"Jackson Hewitt Tax Service",
    "wof:placetype":"venue"
},
  "geometry": {"coordinates":[-80.865134,33.518116],"type":"Point"}
}