{
  "type": "Feature",
  "properties": {
    "addr:full":"9 Harbourside Ln Hilton Head Isle SC 29928",
    "addr:housenumber":"9",
    "addr:postcode":"29928",
    "addr:street":"Harbourside Ln",
    "iso:country":"US",
    "sg:address":"9 Harbourside Ln",
    "sg:city":"Hilton Head Isle",
    "sg:classifiers":[
        {
            "category":"Professional",
            "type":"Services"
        }
    ],
    "sg:phone":"+1 843 785 3112",
    "sg:postcode":"29928",
    "sg:province":"SC",
    "sg:tags":[
        "establishment"
    ],
    "wof:name":"Galerie LA Belle Image",
    "wof:placetype":"venue"
},
  "geometry": {"coordinates":[-80.727126,32.181123],"type":"Point"}
}