{
  "type": "Feature",
  "properties": {
    "addr:full":"429 Main St Eastover SC 29044",
    "addr:housenumber":"429",
    "addr:postcode":"29044",
    "addr:street":"Main St",
    "iso:country":"US",
    "sg:address":"429 Main St",
    "sg:city":"Eastover",
    "sg:classifiers":[
        {
            "category":"Food & Beverages",
            "subcategory":"Liquor & Beverages",
            "type":"Retail Goods"
        }
    ],
    "sg:phone":"+1 803 353 8450",
    "sg:postcode":"29044",
    "sg:province":"SC",
    "sg:tags":[
        "alcoholic"
    ],
    "wof:name":"Scott's ABC Shop",
    "wof:placetype":"venue"
},
  "geometry": {"coordinates":[-80.697557,33.878444],"type":"Point"}
}