{
  "type": "Feature",
  "properties": {
    "iso:country":"US",
    "sg:address":"3600 Hoke Rd",
    "sg:city":"Heath Springs",
    "sg:classifiers":[
        {
            "category":"Building & Trades",
            "subcategory":"Pest Control",
            "type":"Services"
        }
    ],
    "sg:phone":"+1 803 286 4877",
    "sg:postcode":"29058",
    "sg:province":"SC",
    "wof:name":"Morrison's Exterminating",
    "wof:placetype":"venue"
},
  "geometry": {"coordinates":[-80.82102,34.585911],"type":"Point"}
}