{
  "type": "Feature",
  "properties": {
    "addr:full":"3014 Notch Rd Columbia SC 29204",
    "addr:postcode":"3014;29204",
    "addr:street":"Notch Rd",
    "iso:country":"US",
    "sg:address":"3014 Notch Rd",
    "sg:city":"Columbia",
    "sg:classifiers":[
        {
            "category":"Autos & Motor Vehicles",
            "subcategory":"Automobile Sales",
            "type":"Retail Goods"
        }
    ],
    "sg:phone":"+1 803 786 7300",
    "sg:postcode":"29204",
    "sg:province":"SC",
    "sg:tags":[
        "used"
    ],
    "wof:name":"Enterprise Lsg Co of St Louis",
    "wof:placetype":"venue"
},
  "geometry": {"coordinates":[-81.003407,34.036752],"type":"Point"}
}