{
  "type": "Feature",
  "properties": {
    "iso:country":"US",
    "sg:address":"122 Amaker Dr",
    "sg:city":"West Columbia",
    "sg:classifiers":[
        {
            "category":"Building & Trades",
            "subcategory":"Electrical",
            "type":"Services"
        }
    ],
    "sg:phone":"+1 803 776 6664",
    "sg:postcode":"29172",
    "sg:province":"SC",
    "sg:tags":[
        "electrician"
    ],
    "wof:name":"A & S Electric & Heating & Air Conditioning Servce",
    "wof:placetype":"venue"
},
  "geometry": {"coordinates":[-81.07240299999999,33.899101],"type":"Point"}
}