{
  "type": "Feature",
  "properties": {
    "iso:country":"US",
    "sg:address":"251 Champion Ferry Rd",
    "sg:city":"Gaffney",
    "sg:classifiers":[
        {
            "category":"Autos & Motor Vehicles",
            "subcategory":"Automobile Sales",
            "type":"Retail Goods"
        }
    ],
    "sg:phone":"+1 864 487 3389",
    "sg:postcode":"29341",
    "sg:province":"SC",
    "sg:tags":[
        "used"
    ],
    "wof:name":"Auto Connection",
    "wof:placetype":"venue"
},
  "geometry": {"coordinates":[-81.742277,35.150053],"type":"Point"}
}