{
  "type": "Feature",
  "properties": {
    "addr:full":"835 Corn Mill Rd Cowpens SC 29330",
    "addr:housenumber":"835",
    "addr:postcode":"29330",
    "addr:street":"Corn Mill Rd",
    "iso:country":"US",
    "sg:address":"835 Corn Mill Rd",
    "sg:city":"Cowpens",
    "sg:classifiers":[
        {
            "category":"Building & Trades",
            "subcategory":"Construction",
            "type":"Services"
        }
    ],
    "sg:phone":"+1 864 809 0574",
    "sg:postcode":"29330",
    "sg:province":"SC",
    "sg:tags":[
        "grading",
        "contractor"
    ],
    "wof:name":"Williams Grading",
    "wof:placetype":"venue"
},
  "geometry": {"coordinates":[-81.838866,35.082683],"type":"Point"}
}