{
  "type": "Feature",
  "properties": {
    "iso:country":"US",
    "sg:address":"1504 Kate St",
    "sg:city":"Newberry",
    "sg:classifiers":[
        {
            "category":"Building & Trades",
            "subcategory":"Electrical",
            "type":"Services"
        }
    ],
    "sg:phone":"+1 803 276 2101",
    "sg:postcode":"29108",
    "sg:province":"SC",
    "sg:tags":[
        "electrical",
        "contractor"
    ],
    "wof:name":"Tri Tek Fire & Security LLC",
    "wof:placetype":"venue"
},
  "geometry": {"coordinates":[-81.618623,34.295312],"type":"Point"}
}