{
  "type": "Feature",
  "properties": {
    "iso:country":"US",
    "sg:address":"4015 Fish Hatchery Rd",
    "sg:city":"Gaston",
    "sg:classifiers":[
        {
            "category":"Personal",
            "subcategory":"Beauty Salon",
            "type":"Services"
        }
    ],
    "sg:phone":"+1 803 755 3030",
    "sg:postcode":"29053",
    "sg:province":"SC",
    "wof:name":"Styles By Tommi",
    "wof:placetype":"venue"
},
  "geometry": {"coordinates":[-81.153391,33.840465],"type":"Point"}
}