{
  "type": "Feature",
  "properties": {
    "iso:country":"US",
    "sg:address":"224 Trade St",
    "sg:city":"Greer",
    "sg:classifiers":[
        {
            "category":"Shopping",
            "subcategory":"Clothing, Apparel, & Fashions",
            "type":"Retail Goods"
        }
    ],
    "sg:phone":"+1 864 879 7104",
    "sg:postcode":"29651",
    "sg:province":"SC",
    "sg:tags":[
        "ready",
        "woman",
        "accessory"
    ],
    "wof:name":"Chelseas Ladies Apparel & Acc",
    "wof:placetype":"venue"
},
  "geometry": {"coordinates":[-82.22629,34.936837],"type":"Point"}
}