{
  "type": "Feature",
  "properties": {
    "addr:full":"1925 Edgefield Hwy Aiken SC 29801",
    "addr:housenumber":"1925",
    "addr:postcode":"29801",
    "addr:street":"Edgefield Hwy",
    "iso:country":"US",
    "sg:address":"1925 Edgefield Hwy",
    "sg:city":"Aiken",
    "sg:classifiers":[
        {
            "category":"Food & Beverages",
            "subcategory":"Groceries & Convenience Stores",
            "type":"Retail Goods"
        }
    ],
    "sg:phone":"+1 803 643 7558",
    "sg:postcode":"29801",
    "sg:province":"SC",
    "wof:name":"Kent's Corner",
    "wof:placetype":"venue"
},
  "geometry": {"coordinates":[-81.75415,33.653491],"type":"Point"}
}