{
  "type": "Feature",
  "properties": {
    "iso:country":"US",
    "sg:address":"1435 Ebenezer Rd",
    "sg:city":"Rock Hill",
    "sg:classifiers":[
        {
            "category":"Health Services",
            "subcategory":"Doctor",
            "type":"Services"
        }
    ],
    "sg:phone":"+1 803 328 3828",
    "sg:postcode":"29732",
    "sg:province":"SC",
    "sg:tags":[
        "physician",
        "surgeon"
    ],
    "wof:name":"Rock Hill Family Practice",
    "wof:placetype":"venue"
},
  "geometry": {"coordinates":[-81.042055,34.950421],"type":"Point"}
}