{
  "type": "Feature",
  "properties": {
    "iso:country":"US",
    "sg:address":"2410 Clark St",
    "sg:city":"Columbia",
    "sg:classifiers":[
        {
            "category":"Shopping",
            "type":"Retail Goods"
        }
    ],
    "sg:phone":"+1 803 765 0432",
    "sg:postcode":"29201",
    "sg:province":"SC",
    "sg:tags":[
        "merchandise"
    ],
    "wof:name":"Hinton Centerpieces",
    "wof:placetype":"venue"
},
  "geometry": {"coordinates":[-81.044135,34.016789],"type":"Point"}
}