{
  "type": "Feature",
  "properties": {
    "iso:country":"US",
    "sg:address":"2504 River Rd",
    "sg:city":"Piedmont",
    "sg:classifiers":[
        {
            "category":"Wholesale",
            "subcategory":"Machinery & Supplies",
            "type":"Manufacturing & Wholesale Goods"
        }
    ],
    "sg:phone":"+1 864 609 9600",
    "sg:postcode":"29673",
    "sg:province":"SC",
    "sg:tags":[
        "equipment",
        "material",
        "handling"
    ],
    "sg:website":"www.equipmentresources.com",
    "wof:name":"Equipment Resources",
    "wof:placetype":"venue"
},
  "geometry": {"coordinates":[-82.474931,34.761548],"type":"Point"}
}