{
  "type": "Feature",
  "properties": {
    "iso:country":"US",
    "sg:address":"1200 Brookfield Blvd",
    "sg:city":"Greenville",
    "sg:classifiers":[
        {
            "category":"Wholesale",
            "subcategory":"Groceries",
            "type":"Manufacturing & Wholesale Goods"
        }
    ],
    "sg:phone":"+1 864 288 5138",
    "sg:postcode":"29607",
    "sg:province":"SC",
    "sg:tags":[
        "grocer"
    ],
    "wof:name":"C & S Wholesale Grocers Inc",
    "wof:placetype":"venue"
},
  "geometry": {"coordinates":[-82.281752,34.812944],"type":"Point"}
}