{
  "type": "Feature",
  "properties": {
    "iso:country":"US",
    "sg:address":"348 Dike Rd",
    "sg:city":"Bonneau",
    "sg:classifiers":[
        {
            "category":"Professional",
            "subcategory":"Detective & Security Services",
            "type":"Services"
        }
    ],
    "sg:phone":"+1 843 554 5911",
    "sg:postcode":"29431",
    "sg:province":"SC",
    "sg:tags":[
        "agency"
    ],
    "wof:name":"Scarborough Investigations",
    "wof:placetype":"venue"
},
  "geometry": {"coordinates":[-79.966217,33.350764],"type":"Point"}
}