{
  "type": "Feature",
  "properties": {
    "iso:country":"US",
    "sg:address":"187 Ligons Rd",
    "sg:city":"Ridge Spring",
    "sg:classifiers":[
        {
            "category":"Organizations",
            "subcategory":"Religious Organization",
            "type":"Services"
        }
    ],
    "sg:phone":"+1 803 685 7588",
    "sg:postcode":"29129",
    "sg:province":"SC",
    "sg:tags":[
        "church"
    ],
    "wof:name":"Faith Outreach Ctr",
    "wof:placetype":"venue"
},
  "geometry": {"coordinates":[-81.674893,33.774649],"type":"Point"}
}