{
  "type": "Feature",
  "properties": {
    "iso:country":"US",
    "sg:address":"139 N Howard Ave",
    "sg:city":"Landrum",
    "sg:classifiers":[
        {
            "category":"Autos & Motor Vehicles",
            "subcategory":"Auto Supplies",
            "type":"Retail Goods"
        }
    ],
    "sg:phone":"+1 864 457 2604",
    "sg:postcode":"29356",
    "sg:province":"SC",
    "sg:tags":[
        "automobile",
        "parts"
    ],
    "wof:name":"S & D Auto Parts Inc",
    "wof:placetype":"venue"
},
  "geometry": {"coordinates":[-82.190556,35.176092],"type":"Point"}
}