{
  "type": "Feature",
  "properties": {
    "addr:full":"466 Oak Grove Rd Spartanburg SC 29301",
    "addr:housenumber":"466",
    "addr:postcode":"29301",
    "addr:street":"Oak Grove Rd",
    "iso:country":"US",
    "sg:address":"466 Oak Grove Rd",
    "sg:city":"Spartanburg",
    "sg:classifiers":[
        {
            "category":"Education",
            "subcategory":"Dance Studio",
            "type":"Public Place"
        }
    ],
    "sg:phone":"+1 864 595 3610",
    "sg:postcode":"29301",
    "sg:province":"SC",
    "sg:tags":[
        "instruction",
        "dancing"
    ],
    "wof:name":"On Pointe Choreography",
    "wof:placetype":"venue"
},
  "geometry": {"coordinates":[-82.00188199999999,34.922488],"type":"Point"}
}