{
  "type": "Feature",
  "properties": {
    "iso:country":"US",
    "sg:address":"3305 Bainbridge Rd",
    "sg:city":"Sumter",
    "sg:classifiers":[
        {
            "category":"Building & Trades",
            "subcategory":"Construction",
            "type":"Services"
        }
    ],
    "sg:phone":"+1 803 469 6685",
    "sg:postcode":"29153",
    "sg:province":"SC",
    "sg:tags":[
        "maker",
        "cabinet"
    ],
    "wof:name":"Burt's Wood Shop",
    "wof:placetype":"venue"
},
  "geometry": {"coordinates":[-80.41542200000001,33.99199],"type":"Point"}
}