{
  "type": "Feature",
  "properties": {
    "iso:country":"US",
    "sg:address":"933 Camden Rd",
    "sg:city":"Vance",
    "sg:classifiers":[
        {
            "category":"Manufacturing",
            "subcategory":"Lumber",
            "type":"Manufacturing & Wholesale Goods"
        }
    ],
    "sg:phone":"+1 803 496 9384",
    "sg:postcode":"29163",
    "sg:province":"SC",
    "sg:tags":[
        "ornamental",
        "grape",
        "nurser",
        "vineyard",
        "tract",
        "operation",
        "timber"
    ],
    "wof:name":"Evans Witt",
    "wof:placetype":"venue"
},
  "geometry": {"coordinates":[-80.419939,33.420681],"type":"Point"}
}