{
  "type": "Feature",
  "properties": {
    "addr:full":"1021 Okatie Hwy Okatie SC 29909",
    "addr:housenumber":"1021",
    "addr:postcode":"29909",
    "addr:street":"Okatie Hwy",
    "iso:country":"US",
    "sg:address":"1021 Okatie Hwy",
    "sg:city":"Okatie",
    "sg:classifiers":[
        {
            "category":"Building & Trades",
            "subcategory":"Construction",
            "type":"Services"
        }
    ],
    "sg:phone":"+1 843 681 7490",
    "sg:postcode":"29909",
    "sg:province":"SC",
    "sg:tags":[
        "concrete",
        "contractor"
    ],
    "wof:name":"Drew Brothers Construction",
    "wof:placetype":"venue"
},
  "geometry": {"coordinates":[-80.89937999999999,32.353815],"type":"Point"}
}