{
  "type": "Feature",
  "properties": {
    "iso:country":"US",
    "sg:address":"2840 W Palmetto St",
    "sg:city":"Florence",
    "sg:classifiers":[
        {
            "category":"Professional",
            "subcategory":"Accounting & Tax Preparation",
            "type":"Services"
        }
    ],
    "sg:phone":"+1 843 629 0787",
    "sg:postcode":"29501",
    "sg:province":"SC",
    "sg:tags":[
        "return",
        "filing"
    ],
    "wof:name":"Fastax",
    "wof:placetype":"venue"
},
  "geometry": {"coordinates":[-79.832139,34.175312],"type":"Point"}
}