{
  "type": "Feature",
  "properties": {
    "iso:country":"US",
    "sg:address":"215 Cain Rd",
    "sg:city":"Laurens",
    "sg:classifiers":[
        {
            "category":"Building & Trades",
            "subcategory":"Construction",
            "type":"Services"
        }
    ],
    "sg:phone":"+1 864 682 2193",
    "sg:postcode":"29360",
    "sg:province":"SC",
    "sg:tags":[
        "house"
    ],
    "wof:name":"Young Mac Builders",
    "wof:placetype":"venue"
},
  "geometry": {"coordinates":[-82.09779,34.504308],"type":"Point"}
}