{
  "type": "Feature",
  "properties": {
    "addr:full":"904 Pinckney St Greenville SC 29609",
    "addr:housenumber":"904",
    "addr:postcode":"29609",
    "addr:street":"Pinckney St",
    "iso:country":"US",
    "sg:address":"904 Pinckney St",
    "sg:city":"Greenville",
    "sg:classifiers":[
        {
            "category":"Retail",
            "subcategory":"Auto Repair",
            "type":"Services"
        }
    ],
    "sg:phone":"+1 864 232 4416",
    "sg:postcode":"29609",
    "sg:province":"SC",
    "sg:tags":[
        "body",
        "automobile",
        "painting"
    ],
    "wof:name":"Thompson's Body & Fender",
    "wof:placetype":"venue"
},
  "geometry": {"coordinates":[-82.41280999999999,34.86504],"type":"Point"}
}