{
  "type": "Feature",
  "properties": {
    "iso:country":"US",
    "sg:address":"63 Society St",
    "sg:city":"Charleston",
    "sg:classifiers":[
        {
            "category":"Building & Trades",
            "subcategory":"Landscaping Services",
            "type":"Services"
        }
    ],
    "sg:phone":"+1 843 722 1333",
    "sg:postcode":"29401",
    "sg:province":"SC",
    "sg:tags":[
        "designer",
        "landscape"
    ],
    "wof:name":"Heidi S Brown & Associates",
    "wof:placetype":"venue"
},
  "geometry": {"coordinates":[-79.931183,32.784359],"type":"Point"}
}