{
  "type": "Feature",
  "properties": {
    "iso:country":"US",
    "sg:address":"329 W Meeting St",
    "sg:city":"Lancaster",
    "sg:classifiers":[
        {
            "category":"Real Estate",
            "subcategory":"Real Estate Agent",
            "type":"Services"
        }
    ],
    "sg:phone":"+1 803 285 8856",
    "sg:postcode":"29720",
    "sg:province":"SC",
    "sg:tags":[
        "appraiser"
    ],
    "wof:name":"Ira J Bell Appraisals",
    "wof:placetype":"venue"
},
  "geometry": {"coordinates":[-80.77411499999999,34.720011],"type":"Point"}
}