{
  "type": "Feature",
  "properties": {
    "iso:country":"US",
    "sg:address":"3226 Wade Hampton Blvd",
    "sg:city":"Taylors",
    "sg:classifiers":[
        {
            "category":"Autos & Motor Vehicles",
            "subcategory":"Fuel & Gas Station",
            "type":"Retail Goods"
        }
    ],
    "sg:phone":"+1 864 268 4781",
    "sg:postcode":"29687",
    "sg:province":"SC",
    "sg:tags":[
        "station",
        "gasoline"
    ],
    "wof:name":"Spinx 124c",
    "wof:placetype":"venue"
},
  "geometry": {"coordinates":[-82.317451,34.916117],"type":"Point"}
}