{
  "type": "Feature",
  "properties": {
    "addr:full":"3907 US Hwy 221 Greenwood SC 29649",
    "addr:housenumber":"3907",
    "addr:postcode":"29649",
    "addr:street":"Us Hwy 221",
    "iso:country":"US",
    "sg:address":"3907 US Hwy 221",
    "sg:city":"Greenwood",
    "sg:classifiers":[
        {
            "category":"Building & Trades",
            "subcategory":"Construction",
            "type":"Services"
        }
    ],
    "sg:phone":"+1 864 229 2441",
    "sg:postcode":"29649",
    "sg:province":"SC",
    "sg:tags":[
        "dock"
    ],
    "wof:name":"Southern Boat Lifts",
    "wof:placetype":"venue"
},
  "geometry": {"coordinates":[-82.078339,34.27074],"type":"Point"}
}