{
  "type": "Feature",
  "properties": {
    "iso:country":"US",
    "sg:address":"904 S Church St",
    "sg:city":"Spartanburg",
    "sg:classifiers":[
        {
            "category":"Retail",
            "subcategory":"Auto Repair",
            "type":"Services"
        }
    ],
    "sg:phone":"+1 864 579 2290",
    "sg:postcode":"29306",
    "sg:province":"SC",
    "sg:tags":[
        "wrecker"
    ],
    "wof:name":"Ace Towing Of Spartanburg",
    "wof:placetype":"venue"
},
  "geometry": {"coordinates":[-81.93263,34.928491],"type":"Point"}
}