{
  "type": "Feature",
  "properties": {
    "iso:country":"US",
    "sg:address":"305 E Boyce St",
    "sg:city":"Manning",
    "sg:classifiers":[
        {
            "category":"Wholesale",
            "subcategory":"Machinery & Supplies",
            "type":"Manufacturing & Wholesale Goods"
        }
    ],
    "sg:phone":"+1 803 435 8807",
    "sg:postcode":"29102",
    "sg:province":"SC",
    "sg:tags":[
        "farm",
        "equipment"
    ],
    "wof:name":"Manning Tractor Co Inc",
    "wof:placetype":"venue"
},
  "geometry": {"coordinates":[-80.204879,33.693423],"type":"Point"}
}