{
  "type": "Feature",
  "properties": {
    "iso:country":"US",
    "sg:address":"5 Prospect St",
    "sg:city":"Inman",
    "sg:classifiers":[
        {
            "category":"Utilities",
            "subcategory":"Water",
            "type":"Services"
        }
    ],
    "sg:phone":"+1 864 472 2858",
    "sg:postcode":"29349",
    "sg:province":"SC",
    "sg:tags":[
        "company",
        "sewage"
    ],
    "wof:name":"Inman-Campo Water Dist",
    "wof:placetype":"venue"
},
  "geometry": {"coordinates":[-82.089395,35.049837],"type":"Point"}
}