{
  "type": "Feature",
  "properties": {
    "iso:country":"US",
    "sg:address":"560 Orangeburg Rd",
    "sg:city":"Summerville",
    "sg:classifiers":[
        {
            "category":"Building & Trades",
            "subcategory":"Construction",
            "type":"Services"
        }
    ],
    "sg:phone":"+1 843 514 1353",
    "sg:postcode":"29483",
    "sg:province":"SC",
    "sg:tags":[
        "residential"
    ],
    "wof:name":"K R Driggers Construction Inc",
    "wof:placetype":"venue"
},
  "geometry": {"coordinates":[-80.226599,32.9944],"type":"Point"}
}