{
  "type": "Feature",
  "properties": {
    "addr:full":"75 William Hilton Pkwy Hilton Head Isle SC 29926",
    "addr:housenumber":"75",
    "addr:postcode":"29926",
    "addr:street":"William Hilton Pkwy",
    "iso:country":"US",
    "sg:address":"75 William Hilton Pkwy",
    "sg:city":"Hilton Head Isle",
    "sg:classifiers":[
        {
            "category":"Freight",
            "type":"Transportation"
        }
    ],
    "sg:phone":"+1 843 681 9595",
    "sg:postcode":"29926",
    "sg:province":"SC",
    "sg:tags":[
        "operator",
        "local",
        "trucking"
    ],
    "wof:name":"Simmons Trucking Co",
    "wof:placetype":"venue"
},
  "geometry": {"coordinates":[-80.766949,32.218323],"type":"Point"}
}