{
  "type": "Feature",
  "properties": {
    "iso:country":"US",
    "sg:address":"710 E Godbold St",
    "sg:city":"Marion",
    "sg:classifiers":[
        {
            "category":"Food & Beverages",
            "subcategory":"Groceries & Convenience Stores",
            "type":"Retail Goods"
        }
    ],
    "sg:phone":"+1 843 423 7972",
    "sg:postcode":"29571",
    "sg:province":"SC",
    "sg:tags":[
        "grocer"
    ],
    "wof:name":"Earls Grocery & Produce Inc",
    "wof:placetype":"venue"
},
  "geometry": {"coordinates":[-79.392467,34.177867],"type":"Point"}
}