{
  "type": "Feature",
  "properties": {
    "addr:full":"380 N Hwy 52 Moncks Corner SC 29461",
    "addr:housenumber":"380",
    "addr:postcode":"29461",
    "addr:street":"N Hwy 52",
    "iso:country":"US",
    "sg:address":"380 N Hwy 52",
    "sg:city":"Moncks Corner",
    "sg:classifiers":[
        {
            "category":"Shopping",
            "subcategory":"Discount & Variety Stores",
            "type":"Retail Goods"
        }
    ],
    "sg:phone":"+1 843 761 5554",
    "sg:postcode":"29461",
    "sg:province":"SC",
    "wof:name":"Dollar General",
    "wof:placetype":"venue"
},
  "geometry": {"coordinates":[-79.991046,33.200077],"type":"Point"}
}