{
  "type": "Feature",
  "properties": {
    "addr:full":"2650 Tv Rd Florence SC 29501",
    "addr:postcode":"2650;29501",
    "addr:street":"Tv Rd",
    "iso:country":"US",
    "sg:address":"2650 Tv Rd",
    "sg:city":"Florence",
    "sg:classifiers":[
        {
            "category":"Freight",
            "type":"Transportation"
        }
    ],
    "sg:phone":"+1 843 661 0445",
    "sg:postcode":"29501",
    "sg:province":"SC",
    "sg:tags":[
        "operator",
        "courier",
        "trucking"
    ],
    "wof:name":"Fedex",
    "wof:placetype":"venue"
},
  "geometry": {"coordinates":[-79.74399099999999,34.246366],"type":"Point"}
}