{
  "type": "Feature",
  "properties": {
    "addr:full":"304 N Green St Ridgeland SC 29936",
    "addr:housenumber":"304",
    "addr:postcode":"29936",
    "addr:street":"N Green St",
    "iso:country":"US",
    "sg:address":"304 N Green St",
    "sg:city":"Ridgeland",
    "sg:classifiers":[
        {
            "category":"Government",
            "subcategory":"Office",
            "type":"Public Place"
        }
    ],
    "sg:phone":"+1 843 726 3461",
    "sg:postcode":"29936",
    "sg:province":"SC",
    "wof:name":"Clemson University Extension",
    "wof:placetype":"venue"
},
  "geometry": {"coordinates":[-80.980279,32.484065],"type":"Point"}
}