{
  "type": "Feature",
  "properties": {
    "iso:country":"US",
    "sg:address":"1115 Orangeburg Mall Cir",
    "sg:city":"Orangeburg",
    "sg:classifiers":[
        {
            "category":"Banks & Credit Unions",
            "subcategory":"Bank",
            "type":"Services"
        }
    ],
    "sg:phone":"+1 803 531 5047",
    "sg:postcode":"29115",
    "sg:province":"SC",
    "sg:tags":[
        "personal",
        "loan",
        "institution"
    ],
    "wof:name":"First Franklin Financial Corp",
    "wof:placetype":"venue"
},
  "geometry": {"coordinates":[-80.864386,33.509809],"type":"Point"}
}