{
  "type": "Feature",
  "properties": {
    "iso:country":"US",
    "sg:address":"235 Lydia St",
    "sg:city":"Rock Hill",
    "sg:classifiers":[
        {
            "category":"Insurance",
            "subcategory":"Insurance Agent",
            "type":"Services"
        }
    ],
    "sg:phone":"+1 803 325 2403",
    "sg:postcode":"29732",
    "sg:province":"SC",
    "wof:name":"Allen Insurance Svc",
    "wof:placetype":"venue"
},
  "geometry": {"coordinates":[-81.04181699999999,34.95637],"type":"Point"}
}