{
  "type": "Feature",
  "properties": {
    "iso:country":"US",
    "sg:address":"24 Country Club Rd",
    "sg:city":"Blackville",
    "sg:classifiers":[
        {
            "category":"Building & Trades",
            "subcategory":"Construction",
            "type":"Services"
        }
    ],
    "sg:phone":"+1 803 259 6866",
    "sg:postcode":"29817",
    "sg:province":"SC",
    "sg:tags":[
        "contractor"
    ],
    "wof:name":"D & A Contractors",
    "wof:placetype":"venue"
},
  "geometry": {"coordinates":[-81.26744100000001,33.362286],"type":"Point"}
}