{
  "type": "Feature",
  "properties": {
    "iso:country":"US",
    "sg:address":"224 Drury Ln",
    "sg:city":"Mauldin",
    "sg:classifiers":[
        {
            "category":"Retail",
            "subcategory":"Repair Shop",
            "type":"Services"
        }
    ],
    "sg:phone":"+1 864 963 9778",
    "sg:postcode":"29662",
    "sg:province":"SC",
    "sg:tags":[
        "key"
    ],
    "wof:name":"B & L Locksmith Svc",
    "wof:placetype":"venue"
},
  "geometry": {"coordinates":[-82.295027,34.775033],"type":"Point"}
}