{
  "type": "Feature",
  "properties": {
    "iso:country":"US",
    "sg:address":"1700 Ridge Rd",
    "sg:city":"Greenville",
    "sg:classifiers":[
        {
            "category":"Social Services",
            "subcategory":"Child Care",
            "type":"Services"
        }
    ],
    "sg:phone":"+1 864 288 5596",
    "sg:postcode":"29607",
    "sg:province":"SC",
    "wof:name":"Hollis Center",
    "wof:placetype":"venue"
},
  "geometry": {"coordinates":[-82.339732,34.784718],"type":"Point"}
}