{
  "type": "Feature",
  "properties": {
    "iso:country":"US",
    "sg:address":"2216 Old Greenville Hwy",
    "sg:city":"Pendleton",
    "sg:classifiers":[
        {
            "category":"Restaurant",
            "type":"Food & Drink"
        }
    ],
    "sg:phone":"+1 864 646 7880",
    "sg:postcode":"29670",
    "sg:province":"SC",
    "wof:name":"Dyar's Diner",
    "wof:placetype":"venue"
},
  "geometry": {"coordinates":[-82.768502,34.663083],"type":"Point"}
}