{
  "type": "Feature",
  "properties": {
    "addr:full":"1613 Church St Conway SC 29526",
    "addr:housenumber":"1613",
    "addr:postcode":"29526",
    "addr:street":"Church St",
    "iso:country":"US",
    "sg:address":"1613 Church St",
    "sg:city":"Conway",
    "sg:classifiers":[
        {
            "category":"Restaurant",
            "type":"Food & Drink"
        }
    ],
    "sg:menulink":"http://www.allmenus.com/sc/conway/179135-chick-fil-a/menu/",
    "sg:phone":"+1 843 488 0042",
    "sg:postcode":"29526",
    "sg:province":"SC",
    "sg:tags":[
        "wrap",
        "soup",
        "american",
        "sandwich",
        "salad"
    ],
    "wof:name":"Chick-fil-A",
    "wof:placetype":"venue"
},
  "geometry": {"coordinates":[-79.063019,33.845541],"type":"Point"}
}