{
  "type": "Feature",
  "properties": {
    "iso:country":"US",
    "sg:address":"4337 Pageland Hwy",
    "sg:city":"Lancaster",
    "sg:classifiers":[
        {
            "category":"Personal",
            "subcategory":"Beauty Salon",
            "type":"Services"
        }
    ],
    "sg:phone":"+1 803 286 6318",
    "sg:postcode":"29720",
    "sg:province":"SC",
    "wof:name":"Corner Hair Stylist",
    "wof:placetype":"venue"
},
  "geometry": {"coordinates":[-80.63035600000001,34.743308],"type":"Point"}
}