{
  "type": "Feature",
  "properties": {
    "addr:full":"1414 Fording Island Rd Bluffton SC 29910",
    "addr:housenumber":"1414",
    "addr:postcode":"29910",
    "addr:street":"Fording Island Rd",
    "iso:country":"US",
    "sg:address":"1414 Fording Island Rd",
    "sg:city":"Bluffton",
    "sg:classifiers":[
        {
            "category":"Restaurant",
            "type":"Food & Drink"
        }
    ],
    "sg:phone":"+1 843 837 5765",
    "sg:postcode":"29910",
    "sg:province":"SC",
    "sg:tags":[
        "eating"
    ],
    "wof:name":"Cornerstone Grill",
    "wof:placetype":"venue"
},
  "geometry": {"coordinates":[-80.82131699999999,32.241281],"type":"Point"}
}