{
  "type": "Feature",
  "properties": {
    "iso:country":"US",
    "sg:address":"150 Campton Rd",
    "sg:city":"Inman",
    "sg:classifiers":[
        {
            "category":"Wholesale",
            "subcategory":"Non-durable Goods",
            "type":"Manufacturing & Wholesale Goods"
        }
    ],
    "sg:phone":"+1 864 472 7900",
    "sg:postcode":"29349",
    "sg:province":"SC",
    "wof:name":"Duke Industries",
    "wof:placetype":"venue"
},
  "geometry": {"coordinates":[-82.071958,35.037803],"type":"Point"}
}