{
  "type": "Feature",
  "properties": {
    "iso:country":"US",
    "sg:address":"98 N Market St",
    "sg:city":"Charleston",
    "sg:classifiers":[
        {
            "category":"Shopping",
            "subcategory":"Gifts & Souvenirs",
            "type":"Retail Goods"
        }
    ],
    "sg:phone":"+1 843 958 9888",
    "sg:postcode":"29401",
    "sg:province":"SC",
    "sg:tags":[
        "shop"
    ],
    "sg:website":"www.seldomscene.net",
    "wof:name":"Seldom Scene",
    "wof:placetype":"venue"
},
  "geometry": {"coordinates":[-79.93123900000001,32.780944],"type":"Point"}
}