{
  "type": "Feature",
  "properties": {
    "iso:country":"US",
    "sg:address":"430 Cannon St",
    "sg:city":"Georgetown",
    "sg:classifiers":[
        {
            "category":"Shopping",
            "subcategory":"Shoes",
            "type":"Retail Goods"
        }
    ],
    "sg:phone":"+1 843 527 3277",
    "sg:postcode":"29440",
    "sg:province":"SC",
    "sg:tags":[
        "boot"
    ],
    "wof:name":"Boots & Booties Day Care & Pre",
    "wof:placetype":"venue"
},
  "geometry": {"coordinates":[-79.275804,33.368033],"type":"Point"}
}