{
  "type": "Feature",
  "properties": {
    "iso:country":"US",
    "sg:address":"501 Main St",
    "sg:city":"Conway",
    "sg:classifiers":[
        {
            "category":"Banks & Credit Unions",
            "subcategory":"Bank",
            "type":"Services"
        }
    ],
    "sg:phone":"+1 843 248 4226",
    "sg:postcode":"29526",
    "sg:province":"SC",
    "sg:tags":[
        "savings",
        "loan",
        "association"
    ],
    "wof:name":"Peoples Federal",
    "wof:placetype":"venue"
},
  "geometry": {"coordinates":[-79.048518,33.838941],"type":"Point"}
}