{
  "type": "Feature",
  "properties": {
    "iso:country":"US",
    "sg:address":"1951 San Sus Dr",
    "sg:city":"West Columbia",
    "sg:classifiers":[
        {
            "category":"Shopping",
            "subcategory":"Stationery & Office Supplies",
            "type":"Retail Goods"
        }
    ],
    "sg:phone":"+1 803 755 7971",
    "sg:postcode":"29170",
    "sg:province":"SC",
    "sg:tags":[
        "equipment"
    ],
    "wof:name":"Carolina Installers Inc",
    "wof:placetype":"venue"
},
  "geometry": {"coordinates":[-81.144144,33.926661],"type":"Point"}
}