{
  "type": "Feature",
  "properties": {
    "iso:country":"US",
    "sg:address":"3511 Delree St",
    "sg:city":"West Columbia",
    "sg:classifiers":[
        {
            "category":"Building & Trades",
            "subcategory":"Electrical",
            "type":"Services"
        }
    ],
    "sg:phone":"+1 803 796 7069",
    "sg:postcode":"29170",
    "sg:province":"SC",
    "sg:tags":[
        "electrician"
    ],
    "wof:name":"Allen H R Inc",
    "wof:placetype":"venue"
},
  "geometry": {"coordinates":[-81.131798,33.972198],"type":"Point"}
}