{
  "type": "Feature",
  "properties": {
    "iso:country":"US",
    "sg:address":"2036 Gibbs Shoals Rd",
    "sg:city":"Greer",
    "sg:classifiers":[
        {
            "category":"Professional",
            "type":"Services"
        }
    ],
    "sg:phone":"+1 864 879 4814",
    "sg:postcode":"29650",
    "sg:province":"SC",
    "sg:tags":[
        "caterer"
    ],
    "wof:name":"Laurenda's Cakes & Catering",
    "wof:placetype":"venue"
},
  "geometry": {"coordinates":[-82.24063,34.87542],"type":"Point"}
}