{
  "type": "Feature",
  "properties": {
    "addr:full":"114 Jones St Chesterfield SC 29702",
    "addr:housenumber":"114",
    "addr:postcode":"29702",
    "addr:street":"Jones St",
    "iso:country":"US",
    "sg:address":"114 Jones St",
    "sg:city":"Chesterfield",
    "sg:classifiers":[
        {
            "category":"Building & Trades",
            "subcategory":"Construction",
            "type":"Services"
        }
    ],
    "sg:phone":"+1 843 623 2104",
    "sg:postcode":"29702",
    "sg:province":"SC",
    "wof:name":"IBM Construction",
    "wof:placetype":"venue"
},
  "geometry": {"coordinates":[-81.512552,35.127073],"type":"Point"}
}