{
  "type": "Feature",
  "properties": {
    "iso:country":"US",
    "sg:address":"3254 Augusta Rd",
    "sg:city":"West Columbia",
    "sg:classifiers":[
        {
            "category":"Food & Beverages",
            "subcategory":"Liquor & Beverages",
            "type":"Retail Goods"
        }
    ],
    "sg:phone":"+1 803 926 9200",
    "sg:postcode":"29170",
    "sg:province":"SC",
    "sg:tags":[
        "beer",
        "spirit",
        "wine"
    ],
    "wof:name":"Clyde's Spirits & Fine Wines",
    "wof:placetype":"venue"
},
  "geometry": {"coordinates":[-81.12786800000001,33.977369],"type":"Point"}
}