{
  "type": "Feature",
  "properties": {
    "addr:full":"3551 Rutherford Rd Ste A Taylors SC 29687",
    "addr:housenumber":"3551",
    "addr:postcode":"29687",
    "addr:street":"Rutherford Rd Ste A",
    "iso:country":"US",
    "sg:address":"3551 Rutherford Rd Ste A",
    "sg:city":"Taylors",
    "sg:phone":"+1 864 268 2333",
    "sg:postcode":"29687",
    "sg:province":"SC",
    "wof:name":"Shidhaye Namrata M Md",
    "wof:placetype":"venue"
},
  "geometry": {"coordinates":[-82.322614,34.9165],"type":"Point"}
}