{
  "type": "Feature",
  "properties": {
    "addr:full":"2406 Edmund Rd West Columbia SC 29169",
    "addr:housenumber":"2406",
    "addr:postcode":"29169",
    "addr:street":"Edmund Rd",
    "iso:country":"US",
    "sg:address":"2406 Edmund Rd",
    "sg:city":"West Columbia",
    "sg:classifiers":[
        {
            "category":"Airport",
            "type":"Transportation"
        }
    ],
    "sg:phone":"+1 803 822 8830",
    "sg:postcode":"29169",
    "sg:province":"SC",
    "sg:tags":[
        "support",
        "airline"
    ],
    "wof:name":"PCM Aviation",
    "wof:placetype":"venue"
},
  "geometry": {"coordinates":[-81.103348,33.944772],"type":"Point"}
}