{
  "type": "Feature",
  "properties": {
    "addr:full":"103 King St W Bethune SC 29009",
    "addr:housenumber":"103",
    "addr:postcode":"29009",
    "addr:street":"King St W",
    "iso:country":"US",
    "sg:address":"103 King St W",
    "sg:city":"Bethune",
    "sg:classifiers":[
        {
            "category":"Organizations",
            "subcategory":"Religious Organization",
            "type":"Services"
        }
    ],
    "sg:phone":"+1 843 334 6426",
    "sg:postcode":"29009",
    "sg:province":"SC",
    "sg:tags":[
        "church"
    ],
    "wof:name":"Bethel United Methodist Church",
    "wof:placetype":"venue"
},
  "geometry": {"coordinates":[-80.347379,34.413694],"type":"Point"}
}