{
  "type": "Feature",
  "properties": {
    "iso:country":"US",
    "sg:address":"204 Mountain View Dr",
    "sg:city":"Pickens",
    "sg:classifiers":[
        {
            "category":"Banks & Credit Unions",
            "subcategory":"Financial Services",
            "type":"Services"
        }
    ],
    "sg:phone":"+1 864 878 1703",
    "sg:postcode":"29671",
    "sg:province":"SC",
    "sg:tags":[
        "investor"
    ],
    "wof:name":"Dental Investment Properties L",
    "wof:placetype":"venue"
},
  "geometry": {"coordinates":[-82.66870299999999,34.898123],"type":"Point"}
}