{
  "type": "Feature",
  "properties": {
    "iso:country":"US",
    "sg:address":"1512 Roper Mountain Rd",
    "sg:city":"Greenville",
    "sg:classifiers":[
        {
            "category":"Freight",
            "type":"Transportation"
        }
    ],
    "sg:phone":"+1 864 297 9450",
    "sg:postcode":"29615",
    "sg:province":"SC",
    "sg:tags":[
        "warehouse",
        "merchandise"
    ],
    "wof:name":"Diversified Distribution Sys",
    "wof:placetype":"venue"
},
  "geometry": {"coordinates":[-82.2782,34.836461],"type":"Point"}
}