{
  "type": "Feature",
  "properties": {
    "iso:country":"US",
    "sg:address":"3405 Trenton St",
    "sg:city":"Florence",
    "sg:classifiers":[
        {
            "category":"Shopping",
            "subcategory":"Clothing, Apparel, & Fashions",
            "type":"Retail Goods"
        }
    ],
    "sg:phone":"+1 843 669 8415",
    "sg:postcode":"29501",
    "sg:province":"SC",
    "wof:name":"Olga/Warners",
    "wof:placetype":"venue"
},
  "geometry": {"coordinates":[-79.850241,34.215068],"type":"Point"}
}