{
  "type": "Feature",
  "properties": {
    "addr:full":"131 Bolin Rd Blacksburg SC 29702",
    "addr:housenumber":"131",
    "addr:postcode":"29702",
    "addr:street":"Bolin Rd",
    "iso:country":"US",
    "sg:address":"131 Bolin Rd",
    "sg:city":"Blacksburg",
    "sg:classifiers":[
        {
            "category":"Building & Trades",
            "subcategory":"Cleaning & Sanitation",
            "type":"Services"
        }
    ],
    "sg:phone":"+1 864 839 9875",
    "sg:postcode":"29702",
    "sg:province":"SC",
    "sg:tags":[
        "janitor"
    ],
    "wof:name":"Crystals Cleaning Svc",
    "wof:placetype":"venue"
},
  "geometry": {"coordinates":[-81.56260899999999,35.140478],"type":"Point"}
}