{
  "type": "Feature",
  "properties": {
    "addr:full":"311 Hendrix St Jackson SC 29831",
    "addr:housenumber":"311",
    "addr:postcode":"29831",
    "addr:street":"Hendrix St",
    "iso:country":"US",
    "sg:address":"311 Hendrix St",
    "sg:city":"Jackson",
    "sg:classifiers":[
        {
            "category":"Government",
            "subcategory":"Fire Station",
            "type":"Public Place"
        }
    ],
    "sg:phone":"+1 803 471 2230",
    "sg:postcode":"29831",
    "sg:province":"SC",
    "sg:tags":[
        "department"
    ],
    "wof:name":"Jackson Fire Dept",
    "wof:placetype":"venue"
},
  "geometry": {"coordinates":[-81.78363,33.335209],"type":"Point"}
}