{
  "type": "Feature",
  "properties": {
    "iso:country":"US",
    "sg:address":"6 Plantation Park Dr",
    "sg:city":"Bluffton",
    "sg:classifiers":[
        {
            "category":"Shopping",
            "subcategory":"Used Merchandise",
            "type":"Retail Goods"
        }
    ],
    "sg:phone":"+1 843 815 7283",
    "sg:postcode":"29910",
    "sg:province":"SC",
    "sg:tags":[
        "shop",
        "thrift"
    ],
    "wof:name":"Off Island Thrift",
    "wof:placetype":"venue"
},
  "geometry": {"coordinates":[-80.866245,32.27042],"type":"Point"}
}