{
  "type": "Feature",
  "properties": {
    "iso:country":"US",
    "sg:address":"130 E Main St",
    "sg:city":"Rock Hill",
    "sg:classifiers":[
        {
            "category":"Real Estate",
            "subcategory":"Developer",
            "type":"Services"
        }
    ],
    "sg:phone":"+1 803 366 1845",
    "sg:postcode":"29730",
    "sg:province":"SC",
    "sg:tags":[
        "land"
    ],
    "wof:name":"Lanford & Associates",
    "wof:placetype":"venue"
},
  "geometry": {"coordinates":[-81.027915,34.926036],"type":"Point"}
}