{
  "type": "Feature",
  "properties": {
    "iso:country":"US",
    "sg:address":"2617 Chesnee Hwy",
    "sg:city":"Spartanburg",
    "sg:classifiers":[
        {
            "category":"Home & Garden",
            "subcategory":"Mobile Homes",
            "type":"Retail Goods"
        }
    ],
    "sg:phone":"+1 864 814 3000",
    "sg:postcode":"29307",
    "sg:province":"SC",
    "wof:name":"Repo Junction Inc",
    "wof:placetype":"venue"
},
  "geometry": {"coordinates":[-81.89526,35.034783],"type":"Point"}
}