{
  "type": "Feature",
  "properties": {
    "addr:full":"3 Caledon Ct Greenville SC 29615",
    "addr:housenumber":"3",
    "addr:postcode":"29615",
    "addr:street":"Caledon Ct",
    "iso:country":"US",
    "sg:address":"3 Caledon Ct",
    "sg:city":"Greenville",
    "sg:classifiers":[
        {
            "category":"Professional",
            "subcategory":"Advertising",
            "type":"Services"
        }
    ],
    "sg:phone":"+1 864 233 1230",
    "sg:postcode":"29615",
    "sg:province":"SC",
    "sg:tags":[
        "counselor"
    ],
    "wof:name":"Mackie Rogers Agency",
    "wof:placetype":"venue"
},
  "geometry": {"coordinates":[-82.338312,34.861916],"type":"Point"}
}