{
  "type": "Feature",
  "properties": {
    "addr:full":"307 Pine Forest Rd Travelers Rest SC 29690",
    "addr:housenumber":"307",
    "addr:postcode":"29690",
    "addr:street":"Pine Forest Rd",
    "iso:country":"US",
    "sg:address":"307 Pine Forest Rd",
    "sg:city":"Travelers Rest",
    "sg:classifiers":[
        {
            "category":"Shopping",
            "subcategory":"Discount & Variety Stores",
            "type":"Retail Goods"
        }
    ],
    "sg:phone":"+1 864 834 8165",
    "sg:postcode":"29690",
    "sg:province":"SC",
    "sg:tags":[
        "merchandise",
        "general"
    ],
    "wof:name":"Coker Sales",
    "wof:placetype":"venue"
},
  "geometry": {"coordinates":[-82.431477,34.953766],"type":"Point"}
}