{
  "type": "Feature",
  "properties": {
    "iso:country":"US",
    "sg:address":"144 Dogwood Trail Ln",
    "sg:city":"Fort Mill",
    "sg:classifiers":[
        {
            "category":"Building & Trades",
            "subcategory":"Construction",
            "type":"Services"
        }
    ],
    "sg:phone":"+1 803 547 6444",
    "sg:postcode":"29707",
    "sg:province":"SC",
    "sg:tags":[
        "contractor"
    ],
    "wof:name":"Chamness Pipe Installation",
    "wof:placetype":"venue"
},
  "geometry": {"coordinates":[-80.846969,34.947845],"type":"Point"}
}