{
  "type": "Feature",
  "properties": {
    "iso:country":"US",
    "sg:address":"925 Atomic Rd",
    "sg:city":"North Augusta",
    "sg:classifiers":[
        {
            "category":"Bars & Pubs",
            "type":"Food & Drink"
        }
    ],
    "sg:phone":"+1 803 278 5873",
    "sg:postcode":"29841",
    "sg:province":"SC",
    "wof:name":"Atomic Bait & Tackle Shop",
    "wof:placetype":"venue"
},
  "geometry": {"coordinates":[-81.942409,33.494684],"type":"Point"}
}