{
  "type": "Feature",
  "properties": {
    "iso:country":"US",
    "sg:address":"146 Boy Scout Rd",
    "sg:city":"Gaston",
    "sg:classifiers":[
        {
            "category":"Shopping",
            "type":"Retail Goods"
        }
    ],
    "sg:phone":"+1 803 791 7433",
    "sg:postcode":"29053",
    "sg:province":"SC",
    "sg:tags":[
        "merchandise"
    ],
    "wof:name":"Pretty Pets",
    "wof:placetype":"venue"
},
  "geometry": {"coordinates":[-81.106084,33.821751],"type":"Point"}
}