{
  "type": "Feature",
  "properties": {
    "iso:country":"US",
    "sg:address":"919 N Logan St",
    "sg:city":"Gaffney",
    "sg:classifiers":[
        {
            "category":"Retail",
            "subcategory":"Auto Repair",
            "type":"Services"
        }
    ],
    "sg:phone":"+1 864 489 3181",
    "sg:postcode":"29341",
    "sg:province":"SC",
    "sg:tags":[
        "muffler",
        "exhaust",
        "system"
    ],
    "wof:name":"Nick's Muffler Shop",
    "wof:placetype":"venue"
},
  "geometry": {"coordinates":[-81.64545699999999,35.081562],"type":"Point"}
}