{
  "type": "Feature",
  "properties": {
    "addr:full":"2001 US Hwy 378 Conway SC 29527",
    "addr:housenumber":"2001",
    "addr:postcode":"29527",
    "addr:street":"Us Hwy 378",
    "iso:country":"US",
    "sg:address":"2001 US Hwy 378",
    "sg:city":"Conway",
    "sg:classifiers":[
        {
            "category":"Food & Beverages",
            "subcategory":"Dairy",
            "type":"Retail Goods"
        }
    ],
    "sg:phone":"+1 843 248 5548",
    "sg:postcode":"29527",
    "sg:province":"SC",
    "sg:tags":[
        "product"
    ],
    "wof:name":"Coburg Dairy LLC",
    "wof:placetype":"venue"
},
  "geometry": {"coordinates":[-79.07928200000001,33.84077],"type":"Point"}
}