{
  "type": "Feature",
  "properties": {
    "iso:country":"US",
    "sg:address":"104 Revere Rd",
    "sg:city":"Hopkins",
    "sg:classifiers":[
        {
            "category":"Building & Trades",
            "subcategory":"Plumbing",
            "type":"Services"
        }
    ],
    "sg:phone":"+1 803 776 5849",
    "sg:postcode":"29061",
    "sg:province":"SC",
    "sg:tags":[
        "plumbing",
        "contractor"
    ],
    "wof:name":"Paul Bradley Plumbing Co",
    "wof:placetype":"venue"
},
  "geometry": {"coordinates":[-80.86408,33.946384],"type":"Point"}
}