{
  "type": "Feature",
  "properties": {
    "addr:full":"17 Kensington Rd Greenville SC 29617",
    "addr:housenumber":"17",
    "addr:postcode":"29617",
    "addr:street":"Kensington Rd",
    "iso:country":"US",
    "sg:address":"17 Kensington Rd",
    "sg:city":"Greenville",
    "sg:classifiers":[
        {
            "category":"Real Estate",
            "subcategory":"Real Estate Operator",
            "type":"Services"
        }
    ],
    "sg:phone":"+1 864 246 8966",
    "sg:postcode":"29617",
    "sg:province":"SC",
    "sg:tags":[
        "building",
        "nonresidential"
    ],
    "wof:name":"Alpine Properties LLC",
    "wof:placetype":"venue"
},
  "geometry": {"coordinates":[-82.451396,34.933056],"type":"Point"}
}