{
  "type": "Feature",
  "properties": {
    "iso:country":"US",
    "sg:address":"5605 Reidville Rd",
    "sg:city":"Moore",
    "sg:classifiers":[
        {
            "category":"Personal",
            "subcategory":"Beauty Salon",
            "type":"Services"
        }
    ],
    "sg:phone":"+1 864 574 6855",
    "sg:postcode":"29369",
    "sg:province":"SC",
    "wof:name":"Signatures Salon",
    "wof:placetype":"venue"
},
  "geometry": {"coordinates":[-82.046603,34.890034],"type":"Point"}
}