{
  "type": "Feature",
  "properties": {
    "iso:country":"US",
    "sg:address":"399 Stamper Rd",
    "sg:city":"Andrews",
    "sg:classifiers":[
        {
            "category":"Personal",
            "subcategory":"Beauty Salon",
            "type":"Services"
        }
    ],
    "sg:phone":"+1 843 264 3434",
    "sg:postcode":"29510",
    "sg:province":"SC",
    "wof:name":"Krystal's Hair Korner",
    "wof:placetype":"venue"
},
  "geometry": {"coordinates":[-79.56121,33.465918],"type":"Point"}
}