{
  "type": "Feature",
  "properties": {
    "iso:country":"US",
    "sg:address":"104 Parker Dr",
    "sg:city":"Beaufort",
    "sg:classifiers":[
        {
            "category":"Government",
            "subcategory":"Office",
            "type":"Public Place"
        }
    ],
    "sg:phone":"+1 843 846 9400",
    "sg:postcode":"29906",
    "sg:province":"SC",
    "sg:tags":[
        "state",
        "program"
    ],
    "wof:name":"Ocean & Coastal Resources Mgmt",
    "wof:placetype":"venue"
},
  "geometry": {"coordinates":[-80.748898,32.476533],"type":"Point"}
}