{
  "type": "Feature",
  "properties": {
    "iso:country":"US",
    "sg:address":"3240 Walking Horse Ln",
    "sg:city":"Sumter",
    "sg:classifiers":[
        {
            "category":"Building & Trades",
            "subcategory":"Construction",
            "type":"Services"
        }
    ],
    "sg:phone":"+1 803 494 6133",
    "sg:postcode":"29154",
    "sg:province":"SC",
    "sg:tags":[
        "painter"
    ],
    "wof:name":"Palmetto Paint Co Inc",
    "wof:placetype":"venue"
},
  "geometry": {"coordinates":[-80.422104,33.904363],"type":"Point"}
}