{
  "type": "Feature",
  "properties": {
    "iso:country":"US",
    "sg:address":"7460 Notch Rd",
    "sg:city":"Columbia",
    "sg:classifiers":[
        {
            "category":"Food & Beverages",
            "subcategory":"Groceries & Convenience Stores",
            "type":"Retail Goods"
        }
    ],
    "sg:phone":"+1 803 736 2474",
    "sg:postcode":"29223",
    "sg:province":"SC",
    "wof:name":"Pitt Stop",
    "wof:placetype":"venue"
},
  "geometry": {"coordinates":[-80.949238,34.07222],"type":"Point"}
}