{
  "type": "Feature",
  "properties": {
    "addr:full":"5540 Forest Dr Columbia SC 29206",
    "addr:housenumber":"5540",
    "addr:postcode":"29206",
    "addr:street":"Forest Dr",
    "iso:country":"US",
    "sg:address":"5540 Forest Dr",
    "sg:city":"Columbia",
    "sg:classifiers":[
        {
            "category":"Wholesale",
            "subcategory":"Machinery & Supplies",
            "type":"Manufacturing & Wholesale Goods"
        },
        {
            "category":"Shopping",
            "type":"Retail Goods"
        }
    ],
    "sg:phone":"+1 803 787 3608",
    "sg:postcode":"29206",
    "sg:province":"SC",
    "sg:tags":[
        "equipment",
        "establishment",
        "cosmetic",
        "perfume"
    ],
    "wof:name":"J D's Fashions",
    "wof:placetype":"venue"
},
  "geometry": {"coordinates":[-80.949601,34.024017],"type":"Point"}
}