{
  "type": "Feature",
  "properties": {
    "addr:full":"705 Long Point Rd Mt Pleasant SC 29464",
    "addr:housenumber":"705",
    "addr:postcode":"29464",
    "addr:street":"Long Point Rd",
    "iso:country":"US",
    "sg:address":"705 Long Point Rd",
    "sg:city":"Mt Pleasant",
    "sg:classifiers":[
        {
            "category":"Retail",
            "subcategory":"Laundry & Dry Cleaning",
            "type":"Services"
        }
    ],
    "sg:phone":"+1 843 388 1814",
    "sg:postcode":"29464",
    "sg:province":"SC",
    "sg:tags":[
        "cleaners"
    ],
    "wof:name":"K B Cleaners",
    "wof:placetype":"venue"
},
  "geometry": {"coordinates":[-79.849136,32.841589],"type":"Point"}
}