{
  "type": "Feature",
  "properties": {
    "iso:country":"US",
    "sg:address":"24 Mills Ave",
    "sg:city":"Greenville",
    "sg:classifiers":[
        {
            "category":"Shopping",
            "subcategory":"Clothing, Apparel, & Fashions",
            "type":"Retail Goods"
        }
    ],
    "sg:phone":"+1 864 233 6077",
    "sg:postcode":"29605",
    "sg:province":"SC",
    "sg:tags":[
        "alteration"
    ],
    "wof:name":"Fast Service Clothing Altrtns",
    "wof:placetype":"venue"
},
  "geometry": {"coordinates":[-82.405548,34.8313],"type":"Point"}
}