{
  "type": "Feature",
  "properties": {
    "iso:country":"US",
    "sg:address":"1411 Augusta Rd",
    "sg:city":"West Columbia",
    "sg:classifiers":[
        {
            "category":"Personal",
            "subcategory":"Beauty Salon",
            "type":"Services"
        }
    ],
    "sg:phone":"+1 803 926 0074",
    "sg:postcode":"29169",
    "sg:province":"SC",
    "wof:name":"Salon 1411",
    "wof:placetype":"venue"
},
  "geometry": {"coordinates":[-81.077626,33.986267],"type":"Point"}
}