{
  "type": "Feature",
  "properties": {
    "addr:full":"2 Gardner St S Cayce SC 29020",
    "addr:housenumber":"2",
    "addr:postcode":"29020",
    "addr:street":"Gardner St S",
    "iso:country":"US",
    "sg:address":"2 Gardner St S",
    "sg:city":"Cayce",
    "sg:classifiers":[
        {
            "category":"Retail",
            "subcategory":"Auto Repair",
            "type":"Services"
        }
    ],
    "sg:phone":"+1 803 794 1938",
    "sg:postcode":"29020",
    "sg:province":"SC",
    "sg:tags":[
        "repairing",
        "automobile"
    ],
    "wof:name":"D & S Auto Repair",
    "wof:placetype":"venue"
},
  "geometry": {"coordinates":[-80.58750999999999,34.247575],"type":"Point"}
}