{
  "type": "Feature",
  "properties": {
    "iso:country":"US",
    "sg:address":"419 Columbiana Dr",
    "sg:city":"Columbia",
    "sg:classifiers":[
        {
            "category":"Restaurant",
            "type":"Food & Drink"
        }
    ],
    "sg:menulink":"http://www.allmenus.com/sc/irmo/107649-five-guys/menu/",
    "sg:phone":"+1 803 407 6443",
    "sg:postcode":"29212",
    "sg:province":"SC",
    "sg:tags":[
        "burger",
        "american",
        "hot",
        "dog"
    ],
    "wof:name":"Five Guys Burgers & Fries",
    "wof:placetype":"venue"
},
  "geometry": {"coordinates":[-81.159779,34.080622],"type":"Point"}
}