{
  "type": "Feature",
  "properties": {
    "iso:country":"US",
    "sg:address":"2080 Sam Rittenberg Blvd",
    "sg:city":"Charleston",
    "sg:classifiers":[
        {
            "category":"Restaurant",
            "type":"Food & Drink"
        }
    ],
    "sg:menulink":"http://www.allmenus.com/sc/charleston-north-charleston/128213-red-lobster/menu/",
    "sg:phone":"+1 843 763 7345",
    "sg:postcode":"29407",
    "sg:province":"SC",
    "sg:tags":[
        "seafood",
        "american"
    ],
    "wof:name":"Red Lobster",
    "wof:placetype":"venue"
},
  "geometry": {"coordinates":[-80.03128,32.792603],"type":"Point"}
}