{
  "type": "Feature",
  "properties": {
    "addr:full":"5 W Rigby St Manning SC 29102",
    "addr:housenumber":"5",
    "addr:postcode":"29102",
    "addr:street":"W Rigby St",
    "iso:country":"US",
    "sg:address":"5 W Rigby St",
    "sg:city":"Manning",
    "sg:classifiers":[
        {
            "category":"Shopping",
            "subcategory":"Optical Goods",
            "type":"Retail Goods"
        }
    ],
    "sg:phone":"+1 803 435 9191",
    "sg:postcode":"29102",
    "sg:province":"SC",
    "wof:name":"H Rubin Vision Centers",
    "wof:placetype":"venue"
},
  "geometry": {"coordinates":[-80.211741,33.696678],"type":"Point"}
}