{
  "type": "Feature",
  "properties": {
    "iso:country":"US",
    "sg:address":"1660 Sam Rittenberg Blvd",
    "sg:city":"Charleston",
    "sg:classifiers":[
        {
            "category":"Building & Trades",
            "subcategory":"Equipment Rental",
            "type":"Services"
        }
    ],
    "sg:phone":"+1 843 763 9097",
    "sg:postcode":"29407",
    "sg:province":"SC",
    "sg:tags":[
        "appliance"
    ],
    "wof:name":"Rent Way",
    "wof:placetype":"venue"
},
  "geometry": {"coordinates":[-80.01195,32.805165],"type":"Point"}
}