{
  "type": "Feature",
  "properties": {
    "addr:full":"3105 E Palmetto St Florence SC 29506",
    "addr:housenumber":"3105",
    "addr:postcode":"29506",
    "addr:street":"E Palmetto St",
    "iso:country":"US",
    "sg:address":"3105 E Palmetto St",
    "sg:city":"Florence",
    "sg:classifiers":[
        {
            "category":"Food & Beverages",
            "subcategory":"Groceries & Convenience Stores",
            "type":"Retail Goods"
        }
    ],
    "sg:phone":"+1 843 679 7146",
    "sg:postcode":"29506",
    "sg:province":"SC",
    "wof:name":"Amoco Food Mart",
    "wof:placetype":"venue"
},
  "geometry": {"coordinates":[-79.70454100000001,34.197011],"type":"Point"}
}