{
  "type": "Feature",
  "properties": {
    "iso:country":"US",
    "sg:address":"7561 State Hwy 164",
    "sg:city":"Hollywood",
    "sg:classifiers":[
        {
            "category":"Home & Garden",
            "subcategory":"Building Materials",
            "type":"Retail Goods"
        },
        {
            "category":"Building & Trades",
            "subcategory":"Construction",
            "type":"Services"
        }
    ],
    "sg:phone":"+1 843 889 6413",
    "sg:postcode":"29449",
    "sg:province":"SC",
    "sg:tags":[
        "fence",
        "contractor"
    ],
    "wof:name":"Dixie Fence Company",
    "wof:placetype":"venue"
},
  "geometry": {"coordinates":[-80.313185,32.720842],"type":"Point"}
}