{
  "type": "Feature",
  "properties": {
    "iso:country":"US",
    "sg:address":"5201 Broad St",
    "sg:city":"Loris",
    "sg:classifiers":[
        {
            "category":"Banks & Credit Unions",
            "subcategory":"Financial Services",
            "type":"Services"
        }
    ],
    "sg:phone":"+1 843 756 6333",
    "sg:postcode":"29569",
    "sg:province":"SC",
    "sg:tags":[
        "company",
        "holding"
    ],
    "wof:name":"HCSB Financial Corp",
    "wof:placetype":"venue"
},
  "geometry": {"coordinates":[-78.88342299999999,34.06275],"type":"Point"}
}