{
  "type": "Feature",
  "properties": {
    "iso:country":"US",
    "sg:address":"7 Target Rd",
    "sg:city":"Hilton Head Isle",
    "sg:classifiers":[
        {
            "category":"Home & Garden",
            "subcategory":"Home Furnishings",
            "type":"Retail Goods"
        }
    ],
    "sg:phone":"+1 843 842 4133",
    "sg:postcode":"29928",
    "sg:province":"SC",
    "sg:tags":[
        "linen"
    ],
    "wof:name":"ASAP Linen & Matts",
    "wof:placetype":"venue"
},
  "geometry": {"coordinates":[-80.760808,32.158282],"type":"Point"}
}