{
  "type": "Feature",
  "properties": {
    "iso:country":"US",
    "sg:address":"324 Sullivan Rd",
    "sg:city":"Simpsonville",
    "sg:classifiers":[
        {
            "category":"Building & Trades",
            "subcategory":"Construction",
            "type":"Services"
        }
    ],
    "sg:phone":"+1 864 299 1335",
    "sg:postcode":"29680",
    "sg:province":"SC",
    "sg:tags":[
        "contractor"
    ],
    "wof:name":"Kings Sandblasting",
    "wof:placetype":"venue"
},
  "geometry": {"coordinates":[-82.311887,34.694497],"type":"Point"}
}