{
  "type": "Feature",
  "properties": {
    "iso:country":"US",
    "sg:address":"1548 Ashley River Rd",
    "sg:city":"Charleston",
    "sg:classifiers":[
        {
            "category":"Home & Garden",
            "subcategory":"Building Materials",
            "type":"Retail Goods"
        }
    ],
    "sg:phone":"+1 843 556 0314",
    "sg:postcode":"29407",
    "sg:province":"SC",
    "sg:tags":[
        "glass",
        "window",
        "plate"
    ],
    "wof:name":"Palmetto Glass & Mirror Inc",
    "wof:placetype":"venue"
},
  "geometry": {"coordinates":[-80.00940199999999,32.799346],"type":"Point"}
}