{
  "type": "Feature",
  "properties": {
    "iso:country":"US",
    "sg:address":"3 Avenel Ct",
    "sg:city":"Simpsonville",
    "sg:classifiers":[
        {
            "category":"Building & Trades",
            "subcategory":"Plumbing",
            "type":"Services"
        }
    ],
    "sg:phone":"+1 864 286 8671",
    "sg:postcode":"29681",
    "sg:province":"SC",
    "sg:tags":[
        "contractor"
    ],
    "wof:name":"Quality Aire",
    "wof:placetype":"venue"
},
  "geometry": {"coordinates":[-82.221902,34.802105],"type":"Point"}
}