{
  "type": "Feature",
  "properties": {
    "addr:full":"122 E Baker St Pickens SC 29671",
    "addr:housenumber":"122",
    "addr:postcode":"29671",
    "addr:street":"E Baker St",
    "iso:country":"US",
    "sg:address":"122 E Baker St",
    "sg:city":"Pickens",
    "sg:classifiers":[
        {
            "category":"Insurance",
            "subcategory":"Insurance Agent",
            "type":"Services"
        }
    ],
    "sg:phone":"+1 864 878 6361",
    "sg:postcode":"29671",
    "sg:province":"SC",
    "wof:name":"PMI Mortgage Insurance Co",
    "wof:placetype":"venue"
},
  "geometry": {"coordinates":[-82.70767499999999,34.888797],"type":"Point"}
}