{
  "type": "Feature",
  "properties": {
    "iso:country":"US",
    "sg:address":"218 Jana Dr",
    "sg:city":"Walhalla",
    "sg:classifiers":[
        {
            "category":"Retail",
            "subcategory":"Portrait Studio",
            "type":"Services"
        }
    ],
    "sg:phone":"+1 864 638 7667",
    "sg:postcode":"29691",
    "sg:province":"SC",
    "sg:tags":[
        "photographer"
    ],
    "wof:name":"David Sparks Photography",
    "wof:placetype":"venue"
},
  "geometry": {"coordinates":[-83.055616,34.794974],"type":"Point"}
}