{
  "type": "Feature",
  "properties": {
    "iso:country":"US",
    "sg:address":"605 Tillman Rd",
    "sg:city":"Elgin",
    "sg:classifiers":[
        {
            "category":"Building & Trades",
            "subcategory":"Construction",
            "type":"Services"
        }
    ],
    "sg:phone":"+1 803 438 4956",
    "sg:postcode":"29045",
    "sg:province":"SC",
    "sg:tags":[
        "house"
    ],
    "wof:name":"Helping Hands General Svc",
    "wof:placetype":"venue"
},
  "geometry": {"coordinates":[-80.814407,34.241213],"type":"Point"}
}