{
  "type": "Feature",
  "properties": {
    "iso:country":"US",
    "sg:address":"171 King St",
    "sg:city":"Charleston",
    "sg:classifiers":[
        {
            "category":"Shopping",
            "type":"Retail Goods"
        }
    ],
    "sg:phone":"+1 843 722 2172",
    "sg:postcode":"29401",
    "sg:province":"SC",
    "sg:tags":[
        "art",
        "gallery",
        "dealer"
    ],
    "wof:name":"Sylvan Gallery",
    "wof:placetype":"venue"
},
  "geometry": {"coordinates":[-79.93311799999999,32.779139],"type":"Point"}
}