{
  "type": "Feature",
  "properties": {
    "iso:country":"US",
    "sg:address":"235 Haupt St",
    "sg:city":"Summerville",
    "sg:classifiers":[
        {
            "category":"Real Estate",
            "subcategory":"Real Estate Agent",
            "type":"Services"
        }
    ],
    "sg:phone":"+1 843 871 5356",
    "sg:postcode":"29483",
    "sg:province":"SC",
    "sg:tags":[
        "inspection"
    ],
    "wof:name":"Lighthouse Home Inspection",
    "wof:placetype":"venue"
},
  "geometry": {"coordinates":[-80.268142,33.011195],"type":"Point"}
}