{
  "type": "Feature",
  "properties": {
    "iso:country":"US",
    "sg:address":"120 Kelly Creek Rd",
    "sg:city":"Six Mile",
    "sg:classifiers":[
        {
            "category":"Farming",
            "subcategory":"Berry Farm",
            "type":"Manufacturing & Wholesale Goods"
        }
    ],
    "sg:phone":"+1 864 868 2946",
    "sg:postcode":"29682",
    "sg:province":"SC",
    "sg:tags":[
        "crop"
    ],
    "wof:name":"Happy Berry Consulting",
    "wof:placetype":"venue"
},
  "geometry": {"coordinates":[-82.87372,34.819986],"type":"Point"}
}