{
  "type": "Feature",
  "properties": {
    "iso:country":"US",
    "sg:address":"2245 State Hwy 101",
    "sg:city":"Duncan",
    "sg:classifiers":[
        {
            "category":"Restaurant",
            "type":"Food & Drink"
        }
    ],
    "sg:phone":"+1 864 801 8779",
    "sg:postcode":"29334",
    "sg:province":"SC",
    "wof:name":"Twin Palmetto",
    "wof:placetype":"venue"
},
  "geometry": {"coordinates":[-82.145606,34.875911],"type":"Point"}
}