{
  "type": "Feature",
  "properties": {
    "addr:full":"120 Musgrove St Clinton SC 29325",
    "addr:housenumber":"120",
    "addr:postcode":"29325",
    "addr:street":"Musgrove St",
    "iso:country":"US",
    "sg:address":"120 Musgrove St",
    "sg:city":"Clinton",
    "sg:classifiers":[
        {
            "category":"Restaurant",
            "type":"Food & Drink"
        }
    ],
    "sg:phone":"+1 864 833 0883",
    "sg:postcode":"29325",
    "sg:province":"SC",
    "wof:name":"120 Musrove",
    "wof:placetype":"venue"
},
  "geometry": {"coordinates":[-81.880195,34.473601],"type":"Point"}
}