{
  "type": "Feature",
  "properties": {
    "addr:full":"461 W Palmetto St Florence SC 29501",
    "addr:housenumber":"461",
    "addr:postcode":"29501",
    "addr:street":"W Palmetto St",
    "iso:country":"US",
    "sg:address":"461 W Palmetto St",
    "sg:city":"Florence",
    "sg:classifiers":[
        {
            "category":"Professional",
            "subcategory":"Business Services",
            "type":"Services"
        }
    ],
    "sg:phone":"+1 843 665 5548",
    "sg:postcode":"29501",
    "sg:province":"SC",
    "sg:tags":[
        "interior",
        "consultant",
        "design",
        "decorator"
    ],
    "wof:name":"HLS Design",
    "wof:placetype":"venue"
},
  "geometry": {"coordinates":[-79.77440900000001,34.193427],"type":"Point"}
}