{
  "type": "Feature",
  "properties": {
    "addr:full":"2732 Devine St Columbia SC 29205",
    "addr:housenumber":"2732",
    "addr:postcode":"29205",
    "addr:street":"Devine St",
    "iso:country":"US",
    "sg:address":"2732 Devine St",
    "sg:city":"Columbia",
    "sg:classifiers":[
        {
            "category":"Arts & Performance",
            "subcategory":"Arts Center",
            "type":"Entertainment"
        }
    ],
    "sg:phone":"+1 803 799 2080",
    "sg:postcode":"29205",
    "sg:province":"SC",
    "sg:tags":[
        "performing"
    ],
    "wof:name":"Fred Astaire Dance Studios",
    "wof:placetype":"venue"
},
  "geometry": {"coordinates":[-81.003998,33.998001],"type":"Point"}
}