{
  "type": "Feature",
  "properties": {
    "addr:full":"300 Garlington Rd Greenville SC 29615",
    "addr:housenumber":"300",
    "addr:postcode":"29615",
    "addr:street":"Garlington Rd",
    "iso:country":"US",
    "sg:address":"300 Garlington Rd",
    "sg:city":"Greenville",
    "sg:classifiers":[
        {
            "category":"Manufacturing",
            "subcategory":"Tools & Machinery",
            "type":"Manufacturing & Wholesale Goods"
        }
    ],
    "sg:phone":"+1 864 254 2000",
    "sg:postcode":"29615",
    "sg:province":"SC",
    "sg:tags":[
        "turbine"
    ],
    "wof:name":"GE Gas Turbine LLC",
    "wof:placetype":"venue"
},
  "geometry": {"coordinates":[-82.29217800000001,34.830197],"type":"Point"}
}