{
  "type": "Feature",
  "properties": {
    "iso:country":"US",
    "sg:address":"2203 N Main St",
    "sg:city":"Summerville",
    "sg:classifiers":[
        {
            "category":"Food & Beverages",
            "subcategory":"Groceries & Convenience Stores",
            "type":"Retail Goods"
        }
    ],
    "sg:phone":"+1 843 873 7882",
    "sg:postcode":"29483",
    "sg:province":"SC",
    "wof:name":"Hot Spot",
    "wof:placetype":"venue"
},
  "geometry": {"coordinates":[-80.108197,33.046979],"type":"Point"}
}