{
  "type": "Feature",
  "properties": {
    "iso:country":"US",
    "sg:address":"3841 Socastee Blvd",
    "sg:city":"Myrtle Beach",
    "sg:classifiers":[
        {
            "category":"Autos & Motor Vehicles",
            "subcategory":"Automobile Sales",
            "type":"Retail Goods"
        }
    ],
    "sg:phone":"+1 843 293 8501",
    "sg:postcode":"29588",
    "sg:province":"SC",
    "sg:tags":[
        "car",
        "dealer"
    ],
    "wof:name":"Atlantic Auto Sales",
    "wof:placetype":"venue"
},
  "geometry": {"coordinates":[-78.967868,33.684935],"type":"Point"}
}