{
  "type": "Feature",
  "properties": {
    "addr:full":"119 Saint James Ave Goose Creek SC 29445",
    "addr:housenumber":"119",
    "addr:postcode":"29445",
    "addr:street":"Saint James Ave",
    "iso:country":"US",
    "sg:address":"119 Saint James Ave",
    "sg:city":"Goose Creek",
    "sg:classifiers":[
        {
            "category":"Shopping",
            "type":"Retail Goods"
        }
    ],
    "sg:phone":"+1 843 572 1477",
    "sg:postcode":"29445",
    "sg:province":"SC",
    "sg:tags":[
        "picture",
        "frame"
    ],
    "wof:name":"Creative Framing",
    "wof:placetype":"venue"
},
  "geometry": {"coordinates":[-80.040274,32.998942],"type":"Point"}
}