{
  "type": "Feature",
  "properties": {
    "iso:country":"US",
    "sg:address":"10 Pinckney Colony Rd",
    "sg:city":"Bluffton",
    "sg:classifiers":[
        {
            "category":"Building & Trades",
            "subcategory":"Construction",
            "type":"Services"
        }
    ],
    "sg:phone":"+1 843 842 4663",
    "sg:postcode":"29909",
    "sg:province":"SC",
    "sg:tags":[
        "contractor"
    ],
    "sg:website":"www.acuffbuilders.com",
    "wof:name":"Acuff Builders Inc",
    "wof:placetype":"venue"
},
  "geometry": {"coordinates":[-80.888355,32.298107],"type":"Point"}
}