{
  "type": "Feature",
  "properties": {
    "addr:full":"222 S Cherry Rd Rock Hill SC 29732",
    "addr:housenumber":"222",
    "addr:postcode":"29732",
    "addr:street":"S Cherry Rd",
    "iso:country":"US",
    "sg:address":"222 S Cherry Rd",
    "sg:city":"Rock Hill",
    "sg:classifiers":[
        {
            "category":"Retail",
            "subcategory":"Laundry & Dry Cleaning",
            "type":"Services"
        }
    ],
    "sg:phone":"+1 803 366 7278",
    "sg:postcode":"29732",
    "sg:province":"SC",
    "sg:tags":[
        "shop",
        "sewing"
    ],
    "wof:name":"Sew Biz",
    "wof:placetype":"venue"
},
  "geometry": {"coordinates":[-81.041318,34.937993],"type":"Point"}
}