{
  "type": "Feature",
  "properties": {
    "iso:country":"US",
    "sg:address":"5766 Memorial Blvd",
    "sg:city":"St George",
    "sg:classifiers":[
        {
            "category":"Shopping",
            "subcategory":"Music",
            "type":"Retail Goods"
        }
    ],
    "sg:phone":"+1 843 563 4130",
    "sg:postcode":"29477",
    "sg:province":"SC",
    "sg:tags":[
        "video",
        "disc",
        "tape",
        "cassette"
    ],
    "wof:name":"Video Island Of St George",
    "wof:placetype":"venue"
},
  "geometry": {"coordinates":[-80.587397,33.192173],"type":"Point"}
}