{
  "type": "Feature",
  "properties": {
    "iso:country":"US",
    "sg:address":"1801 W Evans St",
    "sg:city":"Florence",
    "sg:classifiers":[
        {
            "category":"Banks & Credit Unions",
            "subcategory":"Bank",
            "type":"Services"
        }
    ],
    "sg:phone":"+1 843 317 1740",
    "sg:postcode":"29501",
    "sg:province":"SC",
    "sg:tags":[
        "loan",
        "mortgage"
    ],
    "wof:name":"Upstate Mortgage Inc",
    "wof:placetype":"venue"
},
  "geometry": {"coordinates":[-79.800586,34.195596],"type":"Point"}
}