{
  "type": "Feature",
  "properties": {
    "iso:country":"US",
    "sg:address":"3576 Wayside Rd",
    "sg:city":"Conway",
    "sg:classifiers":[
        {
            "category":"Building & Trades",
            "subcategory":"Plumbing",
            "type":"Services"
        }
    ],
    "sg:phone":"+1 843 365 6778",
    "sg:postcode":"29527",
    "sg:province":"SC",
    "sg:tags":[
        "conditioning",
        "air",
        "system",
        "contractor"
    ],
    "wof:name":"Southern Aire",
    "wof:placetype":"venue"
},
  "geometry": {"coordinates":[-79.139457,33.872911],"type":"Point"}
}