{
  "type": "Feature",
  "properties": {
    "iso:country":"US",
    "sg:address":"936 Broad St",
    "sg:city":"Camden",
    "sg:classifiers":[
        {
            "category":"Real Estate",
            "subcategory":"Surveying",
            "type":"Services"
        }
    ],
    "sg:phone":"+1 803 425 0702",
    "sg:postcode":"29020",
    "sg:province":"SC",
    "sg:tags":[
        "surveyor"
    ],
    "wof:name":"Walker Parr & Assoc Inc",
    "wof:placetype":"venue"
},
  "geometry": {"coordinates":[-80.606831,34.244604],"type":"Point"}
}