{
  "type": "Feature",
  "properties": {
    "iso:country":"US",
    "sg:address":"110 Miracle Mile Dr",
    "sg:city":"Anderson",
    "sg:classifiers":[
        {
            "category":"Real Estate",
            "subcategory":"Real Estate Agent",
            "type":"Services"
        }
    ],
    "sg:phone":"+1 864 226 2920",
    "sg:postcode":"29621",
    "sg:province":"SC",
    "wof:name":"Whitfield Enterprises Rental",
    "wof:placetype":"venue"
},
  "geometry": {"coordinates":[-82.666117,34.548772],"type":"Point"}
}