{
  "type": "Feature",
  "properties": {
    "iso:country":"US",
    "sg:address":"6200 Frontage Rd",
    "sg:city":"Myrtle Beach",
    "sg:classifiers":[
        {
            "category":"Building & Trades",
            "subcategory":"Construction",
            "type":"Services"
        }
    ],
    "sg:phone":"+1 843 449 4243",
    "sg:postcode":"29572",
    "sg:province":"SC",
    "sg:tags":[
        "general",
        "contractor"
    ],
    "wof:name":"Corbett Construction",
    "wof:placetype":"venue"
},
  "geometry": {"coordinates":[-78.839477,33.743988],"type":"Point"}
}