{
  "type": "Feature",
  "properties": {
    "iso:country":"US",
    "sg:address":"129 Groves Wood Ct",
    "sg:city":"Columbia",
    "sg:classifiers":[
        {
            "category":"Shopping",
            "type":"Retail Goods"
        }
    ],
    "sg:phone":"+1 803 749 2285",
    "sg:postcode":"29212",
    "sg:province":"SC",
    "sg:tags":[
        "wedding",
        "supply"
    ],
    "wof:name":"Kendall's Katering",
    "wof:placetype":"venue"
},
  "geometry": {"coordinates":[-81.148822,34.120521],"type":"Point"}
}