{
  "type": "Feature",
  "properties": {
    "iso:country":"US",
    "sg:address":"602 Main St",
    "sg:city":"Edgefield",
    "sg:classifiers":[
        {
            "category":"Autos & Motor Vehicles",
            "subcategory":"Fuel & Gas Station",
            "type":"Retail Goods"
        }
    ],
    "sg:phone":"+1 803 637 3622",
    "sg:postcode":"29824",
    "sg:province":"SC",
    "sg:tags":[
        "station",
        "gasoline",
        "oil"
    ],
    "wof:name":"Main Street Auto Service Ctr",
    "wof:placetype":"venue"
},
  "geometry": {"coordinates":[-81.92376899999999,33.78816],"type":"Point"}
}