{
  "type": "Feature",
  "properties": {
    "iso:country":"US",
    "sg:address":"107 N Ames St",
    "sg:city":"Greenwood",
    "sg:classifiers":[
        {
            "category":"Personal",
            "subcategory":"Beauty Salon",
            "type":"Services"
        }
    ],
    "sg:phone":"+1 864 223 4591",
    "sg:postcode":"29646",
    "sg:province":"SC",
    "wof:name":"Excelsior Beauty Parlor",
    "wof:placetype":"venue"
},
  "geometry": {"coordinates":[-82.14447800000001,34.197367],"type":"Point"}
}