{
  "type": "Feature",
  "properties": {
    "iso:country":"US",
    "sg:address":"217 State Hwy 72 Bus",
    "sg:city":"Greenwood",
    "sg:classifiers":[
        {
            "category":"Restaurant",
            "type":"Food & Drink"
        }
    ],
    "sg:phone":"+1 864 223 9234",
    "sg:postcode":"29649",
    "sg:province":"SC",
    "wof:name":"Gillespies Of Greenwood Inc",
    "wof:placetype":"venue"
},
  "geometry": {"coordinates":[-82.16047399999999,34.198349],"type":"Point"}
}