{
  "type": "Feature",
  "properties": {
    "iso:country":"US",
    "sg:address":"1118 Shop Rd",
    "sg:city":"Columbia",
    "sg:classifiers":[
        {
            "category":"Professional",
            "subcategory":"Computer Services",
            "type":"Services"
        }
    ],
    "sg:phone":"+1 803 765 1177",
    "sg:postcode":"29201",
    "sg:province":"SC",
    "sg:tags":[
        "repair"
    ],
    "wof:name":"US Laser",
    "wof:placetype":"venue"
},
  "geometry": {"coordinates":[-81.014297,33.975601],"type":"Point"}
}