{
  "type": "Feature",
  "properties": {
    "iso:country":"US",
    "sg:address":"700 US Hwy 17 Bus",
    "sg:city":"Surfside Beach",
    "sg:classifiers":[
        {
            "category":"Manufacturing",
            "subcategory":"Printing",
            "type":"Manufacturing & Wholesale Goods"
        }
    ],
    "sg:phone":"+1 843 238 8925",
    "sg:postcode":"29575",
    "sg:province":"SC",
    "sg:tags":[
        "printer"
    ],
    "wof:name":"American Speedy Printing Ctr",
    "wof:placetype":"venue"
},
  "geometry": {"coordinates":[-78.976226,33.617663],"type":"Point"}
}