{
  "type": "Feature",
  "properties": {
    "addr:full":"2137 Hoffmeyer Rd Florence SC 29501",
    "addr:housenumber":"2137",
    "addr:postcode":"29501",
    "addr:street":"Hoffmeyer Rd",
    "iso:country":"US",
    "sg:address":"2137 Hoffmeyer Rd",
    "sg:city":"Florence",
    "sg:classifiers":[
        {
            "category":"Professional",
            "subcategory":"Employment Agencies",
            "type":"Services"
        }
    ],
    "sg:phone":"+1 843 669 8826",
    "sg:postcode":"29501",
    "sg:province":"SC",
    "sg:tags":[
        "opportunity"
    ],
    "wof:name":"Columbia Health Care Svc",
    "wof:placetype":"venue"
},
  "geometry": {"coordinates":[-79.810089,34.192724],"type":"Point"}
}