{
  "type": "Feature",
  "properties": {
    "addr:full":"3870 Leeds Ave North Charleston SC 29405",
    "addr:housenumber":"3870",
    "addr:postcode":"29405",
    "addr:street":"Leeds Ave",
    "iso:country":"US",
    "sg:address":"3870 Leeds Ave",
    "sg:city":"North Charleston",
    "sg:classifiers":[
        {
            "category":"Health Services",
            "subcategory":"Nursing And Care Facility",
            "type":"Services"
        }
    ],
    "sg:phone":"+1 843 529 3100",
    "sg:postcode":"29405",
    "sg:province":"SC",
    "sg:tags":[
        "hospice"
    ],
    "sg:website":"www.hospiceofcharleston.org",
    "wof:name":"Hospice Of Charleston",
    "wof:placetype":"venue"
},
  "geometry": {"coordinates":[-80.01525100000001,32.84547],"type":"Point"}
}