{
  "type": "Feature",
  "properties": {
    "addr:full":"5241 Round O Rd Ridgeville SC 29474",
    "addr:housenumber":"5241",
    "addr:postcode":"29474",
    "addr:street":"Round O Rd",
    "iso:country":"US",
    "sg:address":"5241 Round O Rd",
    "sg:city":"Ridgeville",
    "sg:classifiers":[
        {
            "category":"Manufacturing",
            "subcategory":"Lumber",
            "type":"Manufacturing & Wholesale Goods"
        }
    ],
    "sg:phone":"+1 843 835 2834",
    "sg:postcode":"29474",
    "sg:province":"SC",
    "sg:tags":[
        "pulpwood"
    ],
    "wof:name":"Mead Westvaco Corp",
    "wof:placetype":"venue"
},
  "geometry": {"coordinates":[-80.494866,32.877198],"type":"Point"}
}