{
  "type": "Feature",
  "properties": {
    "iso:country":"US",
    "sg:address":"6 Davis Rd",
    "sg:city":"Hemingway",
    "sg:classifiers":[
        {
            "category":"Food & Beverages",
            "subcategory":"Groceries & Convenience Stores",
            "type":"Retail Goods"
        }
    ],
    "sg:phone":"+1 843 558 6291",
    "sg:postcode":"29554",
    "sg:province":"SC",
    "sg:tags":[
        "grocer"
    ],
    "wof:name":"Muddy Creek Grocery",
    "wof:placetype":"venue"
},
  "geometry": {"coordinates":[-79.411479,33.778886],"type":"Point"}
}