{
  "type": "Feature",
  "properties": {
    "iso:country":"US",
    "sg:address":"199 Alta Vista Ct",
    "sg:city":"Lexington",
    "sg:classifiers":[
        {
            "category":"Manufacturing",
            "subcategory":"Signs",
            "type":"Manufacturing & Wholesale Goods"
        }
    ],
    "sg:phone":"+1 803 957 3745",
    "sg:postcode":"29073",
    "sg:province":"SC",
    "sg:tags":[
        "specialty",
        "mfg"
    ],
    "wof:name":"Carolina Neon Manufacturing",
    "wof:placetype":"venue"
},
  "geometry": {"coordinates":[-81.223311,33.959029],"type":"Point"}
}