{
  "type": "Feature",
  "properties": {
    "iso:country":"US",
    "sg:address":"111 Telfair St",
    "sg:city":"Greenville",
    "sg:classifiers":[
        {
            "category":"Retail",
            "subcategory":"Portrait Studio",
            "type":"Services"
        }
    ],
    "sg:phone":"+1 864 421 0993",
    "sg:postcode":"29609",
    "sg:province":"SC",
    "sg:tags":[
        "photographer"
    ],
    "sg:website":"www.baileysphotos.com",
    "wof:name":"Bailey's Photos",
    "wof:placetype":"venue"
},
  "geometry": {"coordinates":[-82.392533,34.890667],"type":"Point"}
}