{
  "type": "Feature",
  "properties": {
    "iso:country":"US",
    "sg:address":"2992 Bowen St",
    "sg:city":"Elgin",
    "sg:classifiers":[
        {
            "category":"Organizations",
            "subcategory":"Religious Organization",
            "type":"Services"
        }
    ],
    "sg:phone":"+1 803 438 0460",
    "sg:postcode":"29045",
    "sg:province":"SC",
    "sg:tags":[
        "church"
    ],
    "wof:name":"Sand Hills Heights Baptist Chr",
    "wof:placetype":"venue"
},
  "geometry": {"coordinates":[-80.839643,34.179288],"type":"Point"}
}