{
  "type": "Feature",
  "properties": {
    "iso:country":"US",
    "sg:address":"1747 Gene Hudson Dr",
    "sg:city":"Lancaster",
    "sg:classifiers":[
        {
            "category":"Utilities",
            "subcategory":"Refuse",
            "type":"Services"
        }
    ],
    "sg:phone":"+1 803 285 1422",
    "sg:postcode":"29720",
    "sg:province":"SC",
    "sg:tags":[
        "garbage",
        "collection"
    ],
    "wof:name":"Rural Garbage Svc",
    "wof:placetype":"venue"
},
  "geometry": {"coordinates":[-80.794213,34.693712],"type":"Point"}
}