{
  "type": "Feature",
  "properties": {
    "addr:full":"582 US Hwy 1 Lugoff SC 29078",
    "addr:housenumber":"582",
    "addr:postcode":"29078",
    "addr:street":"Us Hwy 1",
    "iso:country":"US",
    "sg:address":"582 US Hwy 1",
    "sg:city":"Lugoff",
    "sg:classifiers":[
        {
            "category":"Wholesale",
            "subcategory":"Groceries",
            "type":"Manufacturing & Wholesale Goods"
        }
    ],
    "sg:phone":"+1 803 408 2576",
    "sg:postcode":"29078",
    "sg:province":"SC",
    "sg:tags":[
        "food",
        "product"
    ],
    "wof:name":"Tindea Rodriguez",
    "wof:placetype":"venue"
},
  "geometry": {"coordinates":[-80.65813,34.241031],"type":"Point"}
}