{
  "type": "Feature",
  "properties": {
    "iso:country":"US",
    "sg:address":"3263 Hughes Gasque Rd",
    "sg:city":"Conway",
    "sg:classifiers":[
        {
            "category":"Shopping",
            "subcategory":"Gifts & Souvenirs",
            "type":"Retail Goods"
        }
    ],
    "sg:phone":"+1 843 365 2976",
    "sg:postcode":"29511",
    "sg:province":"SC",
    "sg:tags":[
        "basket",
        "parcel"
    ],
    "wof:name":"A Basket Of Thoughts",
    "wof:placetype":"venue"
},
  "geometry": {"coordinates":[-79.078281,33.960185],"type":"Point"}
}