{
  "type": "Feature",
  "properties": {
    "iso:country":"US",
    "sg:address":"403 Stagecoach Dr",
    "sg:city":"Anderson",
    "sg:classifiers":[
        {
            "category":"Retail",
            "subcategory":"Portrait Studio",
            "type":"Services"
        }
    ],
    "sg:phone":"+1 864 226 2727",
    "sg:postcode":"29625",
    "sg:province":"SC",
    "sg:tags":[
        "photographer"
    ],
    "wof:name":"B & L Interprises",
    "wof:placetype":"venue"
},
  "geometry": {"coordinates":[-82.731582,34.558392],"type":"Point"}
}