{
  "type": "Feature",
  "properties": {
    "addr:full":"200 Boling Ct Taylors SC 29687",
    "addr:housenumber":"200",
    "addr:postcode":"29687",
    "addr:street":"Boling Ct",
    "iso:country":"US",
    "sg:address":"200 Boling Ct",
    "sg:city":"Taylors",
    "sg:classifiers":[
        {
            "category":"Utilities",
            "subcategory":"Refuse",
            "type":"Services"
        }
    ],
    "sg:phone":"+1 864 268 2696",
    "sg:postcode":"29687",
    "sg:province":"SC",
    "sg:tags":[
        "disposal",
        "waste"
    ],
    "wof:name":"Taylor's Waste Treatment Plant",
    "wof:placetype":"venue"
},
  "geometry": {"coordinates":[-82.284065,34.913167],"type":"Point"}
}