{
  "type": "Feature",
  "properties": {
    "iso:country":"US",
    "sg:address":"161 Old Sulphur Springs Rd",
    "sg:city":"Greenville",
    "sg:classifiers":[
        {
            "category":"Wholesale",
            "subcategory":"Motor Vehicles",
            "type":"Manufacturing & Wholesale Goods"
        }
    ],
    "sg:phone":"+1 864 271 7738",
    "sg:postcode":"29607",
    "sg:province":"SC",
    "sg:tags":[
        "trailer"
    ],
    "wof:name":"A R Semi Trailers",
    "wof:placetype":"venue"
},
  "geometry": {"coordinates":[-82.318417,34.833648],"type":"Point"}
}