{
  "type": "Feature",
  "properties": {
    "addr:full":"9332 Long Creek Hwy Westminster SC 29693",
    "addr:housenumber":"9332",
    "addr:postcode":"29693",
    "addr:street":"Long Creek Hwy",
    "iso:country":"US",
    "sg:address":"9332 Long Creek Hwy",
    "sg:city":"Westminster",
    "sg:classifiers":[
        {
            "category":"Personal",
            "subcategory":"Beauty Salon",
            "type":"Services"
        }
    ],
    "sg:phone":"+1 864 647 1080",
    "sg:postcode":"29693",
    "sg:province":"SC",
    "wof:name":"Sharons Place Hair Salon",
    "wof:placetype":"venue"
},
  "geometry": {"coordinates":[-83.122094,34.681479],"type":"Point"}
}