{
  "type": "Feature",
  "properties": {
    "iso:country":"US",
    "sg:address":"108 Shadowood Rd",
    "sg:city":"Clemson",
    "sg:classifiers":[
        {
            "category":"Food & Beverages",
            "subcategory":"Liquor & Beverages",
            "type":"Retail Goods"
        }
    ],
    "sg:phone":"+1 864 653 9757",
    "sg:postcode":"29631",
    "sg:province":"SC",
    "sg:tags":[
        "alcoholic"
    ],
    "wof:name":"Blue Ridge Package Service",
    "wof:placetype":"venue"
},
  "geometry": {"coordinates":[-82.801801,34.677734],"type":"Point"}
}