{
  "type": "Feature",
  "properties": {
    "addr:full":"16 Church Rd Beaufort SC 29910",
    "addr:housenumber":"16",
    "addr:postcode":"29910",
    "addr:street":"Church Rd",
    "iso:country":"US",
    "sg:address":"16 Church Rd",
    "sg:city":"Beaufort",
    "sg:classifiers":[
        {
            "category":"Personal",
            "type":"Services"
        }
    ],
    "sg:phone":"+1 843 846 6452",
    "sg:postcode":"29910",
    "sg:province":"SC",
    "sg:tags":[
        "wedding",
        "chapel"
    ],
    "wof:name":"Allen AME Chapel",
    "wof:placetype":"venue"
},
  "geometry": {"coordinates":[-80.881193,32.110521],"type":"Point"}
}