{
  "type": "Feature",
  "properties": {
    "addr:full":"26 S Main St Travelers Rest SC 29690",
    "addr:housenumber":"26",
    "addr:postcode":"29690",
    "addr:street":"S Main St",
    "iso:country":"US",
    "sg:address":"26 S Main St",
    "sg:city":"Travelers Rest",
    "sg:classifiers":[
        {
            "category":"Food & Beverages",
            "subcategory":"Specialty",
            "type":"Retail Goods"
        }
    ],
    "sg:phone":"+1 864 834 5500",
    "sg:postcode":"29690",
    "sg:province":"SC",
    "sg:tags":[
        "tea",
        "coffee"
    ],
    "wof:name":"Leopard Forest Coffee Co",
    "wof:placetype":"venue"
},
  "geometry": {"coordinates":[-82.44137000000001,34.965582],"type":"Point"}
}