{
  "type": "Feature",
  "properties": {
    "iso:country":"US",
    "sg:address":"115 S Congress St",
    "sg:city":"Winnsboro",
    "sg:classifiers":[
        {
            "category":"Government",
            "subcategory":"Court House",
            "type":"Public Place"
        }
    ],
    "sg:phone":"+1 803 635 4525",
    "sg:postcode":"29180",
    "sg:province":"SC",
    "sg:tags":[
        "county"
    ],
    "wof:name":"Fairfield County Magistrate",
    "wof:placetype":"venue"
},
  "geometry": {"coordinates":[-81.08648,34.380244],"type":"Point"}
}