{
  "type": "Feature",
  "properties": {
    "addr:full":"8 S Main St Inman SC 29349",
    "addr:housenumber":"8",
    "addr:postcode":"29349",
    "addr:street":"S Main St",
    "iso:country":"US",
    "sg:address":"8 S Main St",
    "sg:city":"Inman",
    "sg:classifiers":[
        {
            "category":"Shopping",
            "subcategory":"Used Merchandise",
            "type":"Retail Goods"
        }
    ],
    "sg:phone":"+1 864 472 5081",
    "sg:postcode":"29349",
    "sg:province":"SC",
    "sg:tags":[
        "antique"
    ],
    "wof:name":"Homestead Antiques",
    "wof:placetype":"venue"
},
  "geometry": {"coordinates":[-82.090299,35.047768],"type":"Point"}
}