{
  "type": "Feature",
  "properties": {
    "addr:full":"1205 Wylie St Camden SC 29020",
    "addr:housenumber":"1205",
    "addr:postcode":"29020",
    "addr:street":"Wylie St",
    "iso:country":"US",
    "sg:address":"1205 Wylie St",
    "sg:city":"Camden",
    "sg:classifiers":[
        {
            "category":"Retail",
            "subcategory":"Auto Repair",
            "type":"Services"
        }
    ],
    "sg:phone":"+1 803 432 3499",
    "sg:postcode":"29020",
    "sg:province":"SC",
    "sg:tags":[
        "repairing",
        "automobile"
    ],
    "wof:name":"Wateree Auto Electric Svc",
    "wof:placetype":"venue"
},
  "geometry": {"coordinates":[-80.615228,34.245774],"type":"Point"}
}