{
  "type": "Feature",
  "properties": {
    "addr:full":"3103 Wade Hampton Blvd Taylors SC 29687",
    "addr:housenumber":"3103",
    "addr:postcode":"29687",
    "addr:street":"Wade Hampton Blvd",
    "iso:country":"US",
    "sg:address":"3103 Wade Hampton Blvd",
    "sg:city":"Taylors",
    "sg:classifiers":[
        {
            "category":"Autos & Motor Vehicles",
            "subcategory":"Automobile Sales",
            "type":"Retail Goods"
        }
    ],
    "sg:phone":"+1 864 292 0004",
    "sg:postcode":"29687",
    "sg:province":"SC",
    "sg:tags":[
        "car",
        "dealer"
    ],
    "sg:website":"www.jdbyrider.com",
    "wof:name":"J D Byrider Auto Sales",
    "wof:placetype":"venue"
},
  "geometry": {"coordinates":[-82.32610099999999,34.91011],"type":"Point"}
}