{
  "type": "Feature",
  "properties": {
    "iso:country":"US",
    "sg:address":"5640 Broad St",
    "sg:city":"Sumter",
    "sg:classifiers":[
        {
            "category":"Autos & Motor Vehicles",
            "subcategory":"Fuel & Gas Station",
            "type":"Retail Goods"
        }
    ],
    "sg:phone":"+1 803 494 8574",
    "sg:postcode":"29154",
    "sg:province":"SC",
    "sg:tags":[
        "station",
        "gasoline"
    ],
    "wof:name":"Exxon",
    "wof:placetype":"venue"
},
  "geometry": {"coordinates":[-80.49737399999999,33.951308],"type":"Point"}
}