{
  "type": "Feature",
  "properties": {
    "iso:country":"US",
    "sg:address":"616 W Oak Forest Dr",
    "sg:city":"Charleston",
    "sg:classifiers":[
        {
            "category":"Utilities",
            "type":"Services"
        }
    ],
    "sg:phone":"+1 843 559 5822",
    "sg:postcode":"29407",
    "sg:province":"SC",
    "sg:tags":[
        "control",
        "aerial",
        "mosquito"
    ],
    "wof:name":"Steed Flying Service Inc",
    "wof:placetype":"venue"
},
  "geometry": {"coordinates":[-79.996583,32.784627],"type":"Point"}
}