{
  "type": "Feature",
  "properties": {
    "iso:country":"US",
    "sg:address":"441 N Duncan Byp",
    "sg:city":"Union",
    "sg:classifiers":[
        {
            "category":"Shopping",
            "subcategory":"Jewelry",
            "type":"Retail Goods"
        }
    ],
    "sg:phone":"+1 864 427 5611",
    "sg:postcode":"29379",
    "sg:province":"SC",
    "wof:name":"Friedmans Jewelers",
    "wof:placetype":"venue"
},
  "geometry": {"coordinates":[-81.639606,34.720038],"type":"Point"}
}