{
  "type": "Feature",
  "properties": {
    "iso:country":"US",
    "sg:address":"24 Vardry St",
    "sg:city":"Greenville",
    "sg:classifiers":[
        {
            "category":"Health Services",
            "subcategory":"Clinic",
            "type":"Services"
        }
    ],
    "sg:phone":"+1 864 242 5810",
    "sg:postcode":"29601",
    "sg:province":"SC",
    "sg:tags":[
        "hypnotherapy"
    ],
    "wof:name":"A Better Way Hypnotherapy",
    "wof:placetype":"venue"
},
  "geometry": {"coordinates":[-82.40677599999999,34.840467],"type":"Point"}
}