{
  "type": "Feature",
  "properties": {
    "iso:country":"US",
    "sg:address":"151 E Wood St",
    "sg:city":"Spartanburg",
    "sg:classifiers":[
        {
            "category":"Government",
            "subcategory":"Office",
            "type":"Public Place"
        }
    ],
    "sg:phone":"+1 864 596 3305",
    "sg:postcode":"29303",
    "sg:province":"SC",
    "sg:tags":[
        "county",
        "program",
        "health"
    ],
    "wof:name":"Health DEPT-Wic Office",
    "wof:placetype":"venue"
},
  "geometry": {"coordinates":[-81.934828,34.967541],"type":"Point"}
}