{
  "type": "Feature",
  "properties": {
    "iso:country":"US",
    "sg:address":"655 Saint Andrews Rd",
    "sg:city":"Columbia",
    "sg:classifiers":[
        {
            "category":"Professional",
            "subcategory":"Accounting & Tax Preparation",
            "type":"Services"
        }
    ],
    "sg:phone":"+1 803 771 0605",
    "sg:postcode":"29210",
    "sg:province":"SC",
    "sg:tags":[
        "consultant"
    ],
    "wof:name":"Carolina Tax Credit Spec",
    "wof:placetype":"venue"
},
  "geometry": {"coordinates":[-81.123926,34.045095],"type":"Point"}
}