{
  "type": "Feature",
  "properties": {
    "addr:full":"210 W Cedar Rock St Pickens SC 29671",
    "addr:housenumber":"210",
    "addr:postcode":"29671",
    "addr:street":"W Cedar Rock St",
    "iso:country":"US",
    "sg:address":"210 W Cedar Rock St",
    "sg:city":"Pickens",
    "sg:classifiers":[
        {
            "category":"Banks & Credit Unions",
            "subcategory":"Bank",
            "type":"Services"
        }
    ],
    "sg:phone":"+1 864 878 3544",
    "sg:postcode":"29671",
    "sg:province":"SC",
    "sg:tags":[
        "federal",
        "savings"
    ],
    "wof:name":"CCB",
    "wof:placetype":"venue"
},
  "geometry": {"coordinates":[-82.708568,34.882049],"type":"Point"}
}