{
  "type": "Feature",
  "properties": {
    "iso:country":"US",
    "sg:address":"1175 Folly Rd",
    "sg:city":"Charleston",
    "sg:classifiers":[
        {
            "category":"Bars & Pubs",
            "type":"Food & Drink"
        }
    ],
    "sg:phone":"+1 843 762 2255",
    "sg:postcode":"29412",
    "sg:province":"SC",
    "wof:name":"Skipper's Sports Grill",
    "wof:placetype":"venue"
},
  "geometry": {"coordinates":[-79.96739100000001,32.724514],"type":"Point"}
}