{
  "type": "Feature",
  "properties": {
    "iso:country":"US",
    "sg:address":"117 Boulevard St",
    "sg:city":"Orangeburg",
    "sg:classifiers":[
        {
            "category":"Professional",
            "subcategory":"Accounting & Tax Preparation",
            "type":"Services"
        }
    ],
    "sg:phone":"+1 803 536 4445",
    "sg:postcode":"29115",
    "sg:province":"SC",
    "sg:tags":[
        "bookkeeping",
        "general"
    ],
    "wof:name":"Horizon Data Management",
    "wof:placetype":"venue"
},
  "geometry": {"coordinates":[-80.85617000000001,33.496461],"type":"Point"}
}