{
  "type": "Feature",
  "properties": {
    "iso:country":"US",
    "sg:address":"423 Barony St",
    "sg:city":"Moncks Corner",
    "sg:classifiers":[
        {
            "category":"Professional",
            "subcategory":"Management & Consulting",
            "type":"Services"
        }
    ],
    "sg:phone":"+1 843 761 5111",
    "sg:postcode":"29461",
    "sg:province":"SC",
    "sg:tags":[
        "marketing",
        "program"
    ],
    "wof:name":"Upper Works Marketing",
    "wof:placetype":"venue"
},
  "geometry": {"coordinates":[-79.989469,33.199528],"type":"Point"}
}