{
  "type": "Feature",
  "properties": {
    "iso:country":"US",
    "sg:address":"4870 Dubose Siding Rd",
    "sg:city":"Sumter",
    "sg:classifiers":[
        {
            "category":"Farming",
            "subcategory":"Farm",
            "type":"Manufacturing & Wholesale Goods"
        }
    ],
    "sg:phone":"+1 803 469 2804",
    "sg:postcode":"29153",
    "sg:province":"SC",
    "sg:tags":[
        "crop",
        "general"
    ],
    "wof:name":"Riverdale Farms",
    "wof:placetype":"venue"
},
  "geometry": {"coordinates":[-80.351526,34.057694],"type":"Point"}
}