{
  "type": "Feature",
  "properties": {
    "addr:full":"3462 Cinema Ave Anderson SC 29621",
    "addr:housenumber":"3462",
    "addr:postcode":"29621",
    "addr:street":"Cinema Ave",
    "iso:country":"US",
    "sg:address":"3462 Cinema Ave",
    "sg:city":"Anderson",
    "sg:classifiers":[
        {
            "category":"Shopping",
            "subcategory":"Clothing, Apparel, & Fashions",
            "type":"Retail Goods"
        }
    ],
    "sg:phone":"+1 864 226 4634",
    "sg:postcode":"29621",
    "sg:province":"SC",
    "sg:tags":[
        "lingerie"
    ],
    "wof:name":"Lucy's Love Shop",
    "wof:placetype":"venue"
},
  "geometry": {"coordinates":[-82.67211,34.550159],"type":"Point"}
}