{
  "type": "Feature",
  "properties": {
    "addr:full":"233 Giles Dr Spartanburg SC 29316",
    "addr:housenumber":"233",
    "addr:postcode":"29316",
    "addr:street":"Giles Dr",
    "iso:country":"US",
    "sg:address":"233 Giles Dr",
    "sg:city":"Spartanburg",
    "sg:classifiers":[
        {
            "category":"Retail",
            "subcategory":"Auto Repair",
            "type":"Services"
        }
    ],
    "sg:phone":"+1 864 578 0151",
    "sg:postcode":"29316",
    "sg:province":"SC",
    "sg:tags":[
        "repairing",
        "automobile",
        "general",
        "supply"
    ],
    "wof:name":"Kirkland Automotive Svc Inc",
    "wof:placetype":"venue"
},
  "geometry": {"coordinates":[-81.97673,35.037844],"type":"Point"}
}