{
  "type": "Feature",
  "properties": {
    "iso:country":"US",
    "sg:address":"325 Old Moncks Corner Rd",
    "sg:city":"Goose Creek",
    "sg:classifiers":[
        {
            "category":"Education",
            "subcategory":"Library",
            "type":"Public Place"
        }
    ],
    "sg:phone":"+1 843 572 1376",
    "sg:postcode":"29445",
    "sg:province":"SC",
    "sg:website":"www.berkeley.lib.sc.us",
    "wof:name":"Berkeley County Library",
    "wof:placetype":"venue"
},
  "geometry": {"coordinates":[-80.045836,33.011297],"type":"Point"}
}