{
  "type": "Feature",
  "properties": {
    "iso:country":"US",
    "sg:address":"8193 Palmetto Rd",
    "sg:city":"Edisto Island",
    "sg:classifiers":[
        {
            "category":"Organizations",
            "subcategory":"Religious Organization",
            "type":"Services"
        }
    ],
    "sg:phone":"+1 843 869 3456",
    "sg:postcode":"29438",
    "sg:province":"SC",
    "sg:tags":[
        "church"
    ],
    "wof:name":"Edisto Island United Meth Chr",
    "wof:placetype":"venue"
},
  "geometry": {"coordinates":[-80.307395,32.516624],"type":"Point"}
}