{
  "type": "Feature",
  "properties": {
    "iso:country":"US",
    "sg:address":"309 Brookgreen Dr",
    "sg:city":"Columbia",
    "sg:classifiers":[
        {
            "category":"Building & Trades",
            "subcategory":"Construction",
            "type":"Services"
        }
    ],
    "sg:phone":"+1 803 772 8033",
    "sg:postcode":"29210",
    "sg:province":"SC",
    "sg:tags":[
        "contractor"
    ],
    "wof:name":"Brown & Co",
    "wof:placetype":"venue"
},
  "geometry": {"coordinates":[-81.123046,34.060586],"type":"Point"}
}