{
  "type": "Feature",
  "properties": {
    "addr:full":"817 2nd Ave N Surfside Beach SC 29575",
    "addr:housenumber":"817",
    "addr:postcode":"29575",
    "addr:street":"2Nd Ave N",
    "iso:country":"US",
    "sg:address":"817 2nd Ave N",
    "sg:city":"Surfside Beach",
    "sg:classifiers":[
        {
            "category":"Real Estate",
            "subcategory":"Real Estate Agent",
            "type":"Services"
        }
    ],
    "sg:phone":"+1 843 238 8734",
    "sg:postcode":"29575",
    "sg:province":"SC",
    "wof:name":"HRA Realty Inc",
    "wof:placetype":"venue"
},
  "geometry": {"coordinates":[-78.978746,33.61323],"type":"Point"}
}