{
  "type": "Feature",
  "properties": {
    "addr:full":"94 N Shorecrest Dr Columbia SC 29209",
    "addr:housenumber":"94",
    "addr:postcode":"29209",
    "addr:street":"N Shorecrest Dr",
    "iso:country":"US",
    "sg:address":"94 N Shorecrest Dr",
    "sg:city":"Columbia",
    "sg:classifiers":[
        {
            "category":"Manufacturing",
            "subcategory":"Glass & Minerals",
            "type":"Manufacturing & Wholesale Goods"
        },
        {
            "category":"Building & Trades",
            "subcategory":"Construction",
            "type":"Services"
        }
    ],
    "sg:phone":"+1 803 776 2226",
    "sg:postcode":"29209",
    "sg:province":"SC",
    "sg:tags":[
        "fabricator",
        "product",
        "installer",
        "marble",
        "granite"
    ],
    "wof:name":"Marble & Granite Creations Inc",
    "wof:placetype":"venue"
},
  "geometry": {"coordinates":[-80.96384999999999,33.942989],"type":"Point"}
}