{
  "type": "Feature",
  "properties": {
    "addr:full":"2368 US Hwy 17 Alt Summerville SC 29483",
    "addr:housenumber":"2368",
    "addr:postcode":"29483",
    "addr:street":"Us Hwy 17",
    "iso:country":"US",
    "sg:address":"2368 US Hwy 17 Alt",
    "sg:city":"Summerville",
    "sg:classifiers":[
        {
            "category":"Wholesale",
            "subcategory":"Meat",
            "type":"Manufacturing & Wholesale Goods"
        }
    ],
    "sg:phone":"+1 843 875 5354",
    "sg:postcode":"29483",
    "sg:province":"SC",
    "sg:tags":[
        "packer"
    ],
    "wof:name":"Butcher Boys Processing",
    "wof:placetype":"venue"
},
  "geometry": {"coordinates":[-80.10349100000001,33.051329],"type":"Point"}
}