{
  "type": "Feature",
  "properties": {
    "iso:country":"US",
    "sg:address":"7384 Industry Dr",
    "sg:city":"North Charleston",
    "sg:classifiers":[
        {
            "category":"Wholesale",
            "subcategory":"Electrical",
            "type":"Manufacturing & Wholesale Goods"
        }
    ],
    "sg:phone":"+1 843 760 6421",
    "sg:postcode":"29418",
    "sg:province":"SC",
    "sg:tags":[
        "equipment"
    ],
    "wof:name":"Chad Supply Div 2012",
    "wof:placetype":"venue"
},
  "geometry": {"coordinates":[-80.06890199999999,32.924979],"type":"Point"}
}