{
  "type": "Feature",
  "properties": {
    "iso:country":"US",
    "sg:address":"101 Medical Sciences Dr",
    "sg:city":"Union",
    "sg:classifiers":[
        {
            "category":"Health Services",
            "subcategory":"Podiatrist",
            "type":"Services"
        }
    ],
    "sg:phone":"+1 864 427 4789",
    "sg:postcode":"29379",
    "sg:province":"SC",
    "wof:name":"Bruce H Wellmon DPM",
    "wof:placetype":"venue"
},
  "geometry": {"coordinates":[-81.641526,34.715759],"type":"Point"}
}