{
  "type": "Feature",
  "properties": {
    "addr:full":"112 Arrow Rd Hilton Head Isle SC 29928",
    "addr:housenumber":"112",
    "addr:postcode":"29928",
    "addr:street":"Arrow Rd",
    "iso:country":"US",
    "sg:address":"112 Arrow Rd",
    "sg:city":"Hilton Head Isle",
    "sg:classifiers":[
        {
            "category":"Shopping",
            "subcategory":"Bicycles & Sporting Goods",
            "type":"Retail Goods"
        }
    ],
    "sg:phone":"+1 843 842 3155",
    "sg:postcode":"29928",
    "sg:province":"SC",
    "wof:name":"Best Bikes Rentals Inc",
    "wof:placetype":"venue"
},
  "geometry": {"coordinates":[-80.76121999999999,32.158901],"type":"Point"}
}