{
  "type": "Feature",
  "properties": {
    "addr:full":"714 Seaboard St Myrtle Beach SC 29577",
    "addr:housenumber":"714",
    "addr:postcode":"29577",
    "addr:street":"Seaboard St",
    "iso:country":"US",
    "sg:address":"714 Seaboard St",
    "sg:city":"Myrtle Beach",
    "sg:classifiers":[
        {
            "category":"Building & Trades",
            "subcategory":"Plumbing",
            "type":"Services"
        }
    ],
    "sg:phone":"+1 843 626 7153",
    "sg:postcode":"29577",
    "sg:province":"SC",
    "sg:tags":[
        "heating",
        "contractor"
    ],
    "wof:name":"Peachtree Heating & Air Cond",
    "wof:placetype":"venue"
},
  "geometry": {"coordinates":[-78.90427699999999,33.708565],"type":"Point"}
}