{
  "type": "Feature",
  "properties": {
    "iso:country":"US",
    "sg:address":"428 Joe Black Rd",
    "sg:city":"Pelzer",
    "sg:classifiers":[
        {
            "category":"Retail",
            "subcategory":"Animal Services",
            "type":"Services"
        }
    ],
    "sg:phone":"+1 864 947 2528",
    "sg:postcode":"29669",
    "sg:province":"SC",
    "wof:name":"Shimgong Sharpei",
    "wof:placetype":"venue"
},
  "geometry": {"coordinates":[-82.507125,34.647077],"type":"Point"}
}