{
  "type": "Feature",
  "properties": {
    "iso:country":"US",
    "sg:address":"687 US Hwy 15",
    "sg:city":"Bishopville",
    "sg:classifiers":[
        {
            "category":"Restaurant",
            "type":"Food & Drink"
        }
    ],
    "sg:phone":"+1 803 484 6477",
    "sg:postcode":"29010",
    "sg:province":"SC",
    "sg:tags":[
        "eating"
    ],
    "wof:name":"China Town Express",
    "wof:placetype":"venue"
},
  "geometry": {"coordinates":[-80.240679,34.224426],"type":"Point"}
}