{
  "type": "Feature",
  "properties": {
    "iso:country":"US",
    "sg:address":"247 Columbia Ave",
    "sg:city":"Lexington",
    "sg:classifiers":[
        {
            "category":"Health Services",
            "subcategory":"Doctor",
            "type":"Services"
        }
    ],
    "sg:phone":"+1 803 359 5533",
    "sg:postcode":"29072",
    "sg:province":"SC",
    "sg:tags":[
        "physician",
        "surgeon"
    ],
    "sg:website":"www.doctorscare.com",
    "wof:name":"Doctor's Care",
    "wof:placetype":"venue"
},
  "geometry": {"coordinates":[-81.243167,33.987626],"type":"Point"}
}