{
  "type": "Feature",
  "properties": {
    "iso:country":"US",
    "sg:address":"7251 Cross County Rd",
    "sg:city":"North Charleston",
    "sg:classifiers":[
        {
            "category":"Manufacturing",
            "subcategory":"Metals",
            "type":"Manufacturing & Wholesale Goods"
        }
    ],
    "sg:phone":"+1 843 760 3000",
    "sg:postcode":"29418",
    "sg:province":"SC",
    "sg:tags":[
        "coating"
    ],
    "sg:website":"www.blastandpaint.com",
    "wof:name":"Carolina Equipment & Supply Co",
    "wof:placetype":"venue"
},
  "geometry": {"coordinates":[-80.06937,32.921405],"type":"Point"}
}