{
  "type": "Feature",
  "properties": {
    "iso:country":"US",
    "sg:address":"1 Harbison Way",
    "sg:city":"Columbia",
    "sg:classifiers":[
        {
            "category":"Professional",
            "subcategory":"Accounting & Tax Preparation",
            "type":"Services"
        }
    ],
    "sg:phone":"+1 803 781 9792",
    "sg:postcode":"29212",
    "sg:province":"SC",
    "sg:tags":[
        "payroll"
    ],
    "wof:name":"Automatic Data Processing",
    "wof:placetype":"venue"
},
  "geometry": {"coordinates":[-81.146223,34.073275],"type":"Point"}
}