{
  "type": "Feature",
  "properties": {
    "iso:country":"US",
    "sg:address":"500 Main St S",
    "sg:city":"Bethune",
    "sg:classifiers":[
        {
            "category":"Food & Beverages",
            "subcategory":"Groceries & Convenience Stores",
            "type":"Retail Goods"
        }
    ],
    "sg:phone":"+1 843 334 6246",
    "sg:postcode":"29009",
    "sg:province":"SC",
    "wof:name":"Sunshine Enterprises",
    "wof:placetype":"venue"
},
  "geometry": {"coordinates":[-80.344979,34.410737],"type":"Point"}
}