{
  "type": "Feature",
  "properties": {
    "iso:country":"US",
    "sg:address":"208 W Main St",
    "sg:city":"Williston",
    "sg:classifiers":[
        {
            "category":"Organizations",
            "subcategory":"Religious Organization",
            "type":"Services"
        }
    ],
    "sg:phone":"+1 803 266 7904",
    "sg:postcode":"29853",
    "sg:province":"SC",
    "sg:tags":[
        "church"
    ],
    "wof:name":"St Stephen True Holiness Tmpl",
    "wof:placetype":"venue"
},
  "geometry": {"coordinates":[-81.42523199999999,33.40355],"type":"Point"}
}