{
  "type": "Feature",
  "properties": {
    "iso:country":"US",
    "sg:address":"814 Brandt Court N E",
    "sg:city":"Aiken",
    "sg:classifiers":[
        {
            "category":"Personal",
            "subcategory":"Beauty Salon",
            "type":"Services"
        }
    ],
    "sg:phone":"+1 803 642 9996",
    "sg:postcode":"29801",
    "sg:province":"SC",
    "wof:name":"Braiding Salon",
    "wof:placetype":"venue"
},
  "geometry": {"coordinates":[-81.69947500000001,33.568489],"type":"Point"}
}