{
  "type": "Feature",
  "properties": {
    "iso:country":"US",
    "sg:address":"1190 Bennet Loop",
    "sg:city":"Loris",
    "sg:classifiers":[
        {
            "category":"Food & Beverages",
            "subcategory":"Groceries & Convenience Stores",
            "type":"Retail Goods"
        }
    ],
    "sg:phone":"+1 843 756 3585",
    "sg:postcode":"29569",
    "sg:province":"SC",
    "wof:name":"Loop Express Store",
    "wof:placetype":"venue"
},
  "geometry": {"coordinates":[-78.869227,34.084108],"type":"Point"}
}