{
  "type": "Feature",
  "properties": {
    "iso:country":"US",
    "sg:address":"1604 W Floyd Baker Blvd",
    "sg:city":"Gaffney",
    "sg:classifiers":[
        {
            "category":"Shopping",
            "subcategory":"News",
            "type":"Retail Goods"
        }
    ],
    "sg:phone":"+1 864 489 0060",
    "sg:postcode":"29341",
    "sg:province":"SC",
    "sg:tags":[
        "dealer"
    ],
    "wof:name":"Talking Newspaper",
    "wof:placetype":"venue"
},
  "geometry": {"coordinates":[-81.662996,35.091348],"type":"Point"}
}