{
  "type": "Feature",
  "properties": {
    "addr:full":"115 E Bobo Newsome Hwy Hartsville SC 29550",
    "addr:housenumber":"115",
    "addr:postcode":"29550",
    "addr:street":"E Bobo Newsome Hwy",
    "iso:country":"US",
    "sg:address":"115 E Bobo Newsome Hwy",
    "sg:city":"Hartsville",
    "sg:classifiers":[
        {
            "category":"Building & Trades",
            "subcategory":"Equipment Rental",
            "type":"Services"
        }
    ],
    "sg:phone":"+1 843 383 4261",
    "sg:postcode":"29550",
    "sg:province":"SC",
    "sg:tags":[
        "nonresidential"
    ],
    "wof:name":"Cindys Restaurant",
    "wof:placetype":"venue"
},
  "geometry": {"coordinates":[-80.073376,34.336283],"type":"Point"}
}