{
  "type": "Feature",
  "properties": {
    "iso:country":"US",
    "sg:address":"11 Palmetto Pkwy",
    "sg:city":"Hilton Head Isle",
    "sg:classifiers":[
        {
            "category":"Professional",
            "subcategory":"Lawyer & Legal Services",
            "type":"Services"
        }
    ],
    "sg:phone":"+1 843 681 7000",
    "sg:postcode":"29926",
    "sg:province":"SC",
    "sg:tags":[
        "attorney"
    ],
    "wof:name":"Finger & Andrews",
    "wof:placetype":"venue"
},
  "geometry": {"coordinates":[-80.704375,32.220158],"type":"Point"}
}