{
  "type": "Feature",
  "properties": {
    "addr:full":"2350 Tickle Hill Rd Camden SC 29020",
    "addr:postcode":"2350;29020",
    "addr:street":"Tickle Hill Rd",
    "iso:country":"US",
    "sg:address":"2350 Tickle Hill Rd",
    "sg:city":"Camden",
    "sg:classifiers":[
        {
            "category":"Manufacturing",
            "subcategory":"Tools & Machinery",
            "type":"Manufacturing & Wholesale Goods"
        }
    ],
    "sg:phone":"+1 803 432 9121",
    "sg:postcode":"29020",
    "sg:province":"SC",
    "sg:tags":[
        "machine",
        "shop"
    ],
    "wof:name":"F & W Machine",
    "wof:placetype":"venue"
},
  "geometry": {"coordinates":[-80.58876100000001,34.229622],"type":"Point"}
}