{
  "type": "Feature",
  "properties": {
    "addr:full":"110 Miracle Mile Dr Anderson SC 29621",
    "addr:housenumber":"110",
    "addr:postcode":"29621",
    "addr:street":"Miracle Mile Dr",
    "iso:country":"US",
    "sg:address":"110 Miracle Mile Dr",
    "sg:city":"Anderson",
    "sg:classifiers":[
        {
            "category":"Personal",
            "subcategory":"Beauty Salon",
            "type":"Services"
        }
    ],
    "sg:phone":"+1 864 261 0860",
    "sg:postcode":"29621",
    "sg:province":"SC",
    "wof:name":"Lollipop Hair",
    "wof:placetype":"venue"
},
  "geometry": {"coordinates":[-82.666117,34.548772],"type":"Point"}
}