{
  "type": "Feature",
  "properties": {
    "iso:country":"US",
    "sg:address":"347 Spring Forest Dr",
    "sg:city":"Simpsonville",
    "sg:classifiers":[
        {
            "category":"Freight",
            "type":"Transportation"
        }
    ],
    "sg:phone":"+1 864 967 9000",
    "sg:postcode":"29681",
    "sg:province":"SC",
    "sg:tags":[
        "trucking"
    ],
    "wof:name":"Gould Transportation",
    "wof:placetype":"venue"
},
  "geometry": {"coordinates":[-82.246229,34.777163],"type":"Point"}
}