{
  "type": "Feature",
  "properties": {
    "addr:full":"6808 Hwy 81 N Piedmont SC 29673",
    "addr:housenumber":"6808",
    "addr:postcode":"29673",
    "addr:street":"Hwy 81 N",
    "iso:country":"US",
    "sg:address":"6808 Hwy 81 N",
    "sg:city":"Piedmont",
    "sg:classifiers":[
        {
            "category":"Professional",
            "subcategory":"Engineering",
            "type":"Services"
        }
    ],
    "sg:phone":"+1 864 947 7227",
    "sg:postcode":"29673",
    "sg:province":"SC",
    "sg:tags":[
        "engineer"
    ],
    "wof:name":"Land Design Svc Inc",
    "wof:placetype":"venue"
},
  "geometry": {"coordinates":[-82.556476,34.69819],"type":"Point"}
}