{
  "type": "Feature",
  "properties": {
    "addr:full":"2308 Old Laurens Rd Greenwood SC 29649",
    "addr:housenumber":"2308",
    "addr:postcode":"29649",
    "addr:street":"Old Laurens Rd",
    "iso:country":"US",
    "sg:address":"2308 Old Laurens Rd",
    "sg:city":"Greenwood",
    "sg:classifiers":[
        {
            "category":"Building & Trades",
            "subcategory":"Construction",
            "type":"Services"
        }
    ],
    "sg:phone":"+1 864 223 1777",
    "sg:postcode":"29649",
    "sg:province":"SC",
    "sg:tags":[
        "siding",
        "contractor"
    ],
    "wof:name":"Huskey Inc",
    "wof:placetype":"venue"
},
  "geometry": {"coordinates":[-82.136134,34.237635],"type":"Point"}
}