{
  "type": "Feature",
  "properties": {
    "iso:country":"US",
    "sg:address":"209 W Caudle Ave",
    "sg:city":"Florence",
    "sg:classifiers":[
        {
            "category":"Food & Beverages",
            "subcategory":"Groceries & Convenience Stores",
            "type":"Retail Goods"
        }
    ],
    "sg:phone":"+1 843 665 5379",
    "sg:postcode":"29505",
    "sg:province":"SC",
    "wof:name":"Country Express Groc",
    "wof:placetype":"venue"
},
  "geometry": {"coordinates":[-79.76862800000001,34.159558],"type":"Point"}
}