{
  "type": "Feature",
  "properties": {
    "addr:full":"2440 Mountain Gap Rd Richburg SC 29729",
    "addr:housenumber":"2440",
    "addr:postcode":"29729",
    "addr:street":"Mountain Gap Rd",
    "iso:country":"US",
    "sg:address":"2440 Mountain Gap Rd",
    "sg:city":"Richburg",
    "sg:classifiers":[
        {
            "category":"Manufacturing",
            "subcategory":"Metals",
            "type":"Manufacturing & Wholesale Goods"
        }
    ],
    "sg:phone":"+1 803 789 5429",
    "sg:postcode":"29729",
    "sg:province":"SC",
    "sg:tags":[
        "steel",
        "repair",
        "welding",
        "fabrication",
        "structural"
    ],
    "wof:name":"Mosely Fabrication & Welding",
    "wof:placetype":"venue"
},
  "geometry": {"coordinates":[-80.998149,34.654942],"type":"Point"}
}