{
  "type": "Feature",
  "properties": {
    "iso:country":"US",
    "sg:address":"12 Chancellors Park Ct",
    "sg:city":"Simpsonville",
    "sg:classifiers":[
        {
            "category":"Building & Trades",
            "subcategory":"Construction",
            "type":"Services"
        }
    ],
    "sg:phone":"+1 864 963 9783",
    "sg:postcode":"29681",
    "sg:province":"SC",
    "sg:tags":[
        "house"
    ],
    "wof:name":"Tkf Development Co LLC",
    "wof:placetype":"venue"
},
  "geometry": {"coordinates":[-82.253963,34.728447],"type":"Point"}
}