{
  "type": "Feature",
  "properties": {
    "addr:full":"20 Medical Ridge Rd Greenville SC 29605",
    "addr:housenumber":"20",
    "addr:postcode":"29605",
    "addr:street":"Medical Ridge Rd",
    "iso:country":"US",
    "sg:address":"20 Medical Ridge Rd",
    "sg:city":"Greenville",
    "sg:classifiers":[
        {
            "category":"Health Services",
            "subcategory":"Doctor",
            "type":"Services"
        }
    ],
    "sg:phone":"+1 864 242 6447",
    "sg:postcode":"29605",
    "sg:province":"SC",
    "sg:tags":[
        "physician",
        "surgeon"
    ],
    "wof:name":"Pain Management Assoc",
    "wof:placetype":"venue"
},
  "geometry": {"coordinates":[-82.413178,34.815008],"type":"Point"}
}