{
  "type": "Feature",
  "properties": {
    "iso:country":"US",
    "sg:address":"2473 Savannah Hwy",
    "sg:city":"Charleston",
    "sg:classifiers":[
        {
            "category":"Manufacturing",
            "subcategory":"Apparel",
            "type":"Manufacturing & Wholesale Goods"
        }
    ],
    "sg:phone":"+1 843 763 4580",
    "sg:postcode":"29414",
    "sg:province":"SC",
    "wof:name":"Quick Stitch",
    "wof:placetype":"venue"
},
  "geometry": {"coordinates":[-80.05036800000001,32.792838],"type":"Point"}
}