{
  "type": "Feature",
  "properties": {
    "iso:country":"US",
    "sg:address":"321 Derrick Dr",
    "sg:city":"Irmo",
    "sg:classifiers":[
        {
            "category":"Health Services",
            "subcategory":"Clinic",
            "type":"Services"
        }
    ],
    "sg:phone":"+1 803 407 9923",
    "sg:postcode":"29063",
    "sg:province":"SC",
    "sg:tags":[
        "organization",
        "medical",
        "surgical"
    ],
    "wof:name":"Crown Medical Svc",
    "wof:placetype":"venue"
},
  "geometry": {"coordinates":[-81.24980600000001,34.122346],"type":"Point"}
}