{
  "type": "Feature",
  "properties": {
    "iso:country":"US",
    "sg:address":"1000 N Pinckney St",
    "sg:city":"Union",
    "sg:classifiers":[
        {
            "category":"Building & Trades",
            "subcategory":"Construction",
            "type":"Services"
        }
    ],
    "sg:phone":"+1 864 427 9278",
    "sg:postcode":"29379",
    "sg:province":"SC",
    "wof:name":"S C Highway Department",
    "wof:placetype":"venue"
},
  "geometry": {"coordinates":[-81.629234,34.727655],"type":"Point"}
}