{
  "type": "Feature",
  "properties": {
    "addr:full":"8861 Asheville Hwy Spartanburg SC 29316",
    "addr:housenumber":"8861",
    "addr:postcode":"29316",
    "addr:street":"Asheville Hwy",
    "iso:country":"US",
    "sg:address":"8861 Asheville Hwy",
    "sg:city":"Spartanburg",
    "sg:classifiers":[
        {
            "category":"Home & Garden",
            "subcategory":"Mobile Homes",
            "type":"Retail Goods"
        }
    ],
    "sg:phone":"+1 864 578 7067",
    "sg:postcode":"29316",
    "sg:province":"SC",
    "wof:name":"Sun Belt Homes Inc",
    "wof:placetype":"venue"
},
  "geometry": {"coordinates":[-82.014481,35.00914],"type":"Point"}
}