{
  "type": "Feature",
  "properties": {
    "iso:country":"US",
    "sg:address":"866 Mellichamp Dr",
    "sg:city":"Charleston",
    "sg:classifiers":[
        {
            "category":"Building & Trades",
            "subcategory":"Construction",
            "type":"Services"
        }
    ],
    "sg:phone":"+1 843 762 3450",
    "sg:postcode":"29412",
    "sg:province":"SC",
    "sg:tags":[
        "concrete",
        "contractor"
    ],
    "wof:name":"Crosby's Fencing & Concrete Co",
    "wof:placetype":"venue"
},
  "geometry": {"coordinates":[-79.975872,32.737481],"type":"Point"}
}