{
  "type": "Feature",
  "properties": {
    "iso:country":"US",
    "sg:address":"206 W Main St",
    "sg:city":"Lake City",
    "sg:classifiers":[
        {
            "category":"Restaurant",
            "type":"Food & Drink"
        }
    ],
    "sg:phone":"+1 843 394 5583",
    "sg:postcode":"29560",
    "sg:province":"SC",
    "sg:tags":[
        "eating"
    ],
    "wof:name":"Mandarine Restaurant",
    "wof:placetype":"venue"
},
  "geometry": {"coordinates":[-79.75790600000001,33.875537],"type":"Point"}
}