{
  "type": "Feature",
  "properties": {
    "iso:country":"US",
    "sg:address":"1 Kirk Ct",
    "sg:city":"Bluffton",
    "sg:classifiers":[
        {
            "category":"Home & Garden",
            "subcategory":"Carpets & Floor Coverings",
            "type":"Retail Goods"
        }
    ],
    "sg:phone":"+1 843 757 6141",
    "sg:postcode":"29910",
    "sg:province":"SC",
    "wof:name":"M & M Floor Coverings Inc",
    "wof:placetype":"venue"
},
  "geometry": {"coordinates":[-80.871389,32.292676],"type":"Point"}
}