{
  "type": "Feature",
  "properties": {
    "iso:country":"US",
    "sg:address":"550 Lancaster Rd",
    "sg:city":"Roebuck",
    "sg:phone":"+1 864 576 2239",
    "sg:postcode":"29376",
    "sg:province":"SC",
    "sg:tags":[
        "farm",
        "field",
        "crop"
    ],
    "wof:name":"Steve Gelband",
    "wof:placetype":"venue"
},
  "geometry": {"coordinates":[-81.931164,34.804705],"type":"Point"}
}