{
  "type": "Feature",
  "properties": {
    "iso:country":"US",
    "sg:address":"301 Rogers St",
    "sg:city":"Anderson",
    "sg:classifiers":[
        {
            "category":"Organizations",
            "subcategory":"Religious Organization",
            "type":"Services"
        }
    ],
    "sg:phone":"+1 864 226 0774",
    "sg:postcode":"29625",
    "sg:province":"SC",
    "sg:tags":[
        "church"
    ],
    "wof:name":"Bethel Baptist Church",
    "wof:placetype":"venue"
},
  "geometry": {"coordinates":[-82.66968300000001,34.513086],"type":"Point"}
}