{
  "type": "Feature",
  "properties": {
    "addr:full":"1500 Lady St Columbia SC 29201",
    "addr:housenumber":"1500",
    "addr:postcode":"29201",
    "addr:street":"Lady St",
    "iso:country":"US",
    "sg:address":"1500 Lady St",
    "sg:city":"Columbia",
    "sg:classifiers":[
        {
            "category":"Social Services",
            "type":"Services"
        }
    ],
    "sg:phone":"+1 803 779 1995",
    "sg:postcode":"29201",
    "sg:province":"SC",
    "sg:tags":[
        "counselor",
        "marriage",
        "family"
    ],
    "wof:name":"Christian Counseling Ctr",
    "wof:placetype":"venue"
},
  "geometry": {"coordinates":[-81.02791999999999,34.004566],"type":"Point"}
}