{
  "type": "Feature",
  "properties": {
    "iso:country":"US",
    "sg:address":"1603 Charleston Dr",
    "sg:city":"Beaufort",
    "sg:classifiers":[
        {
            "category":"Home & Garden",
            "subcategory":"Mobile Homes",
            "type":"Retail Goods"
        }
    ],
    "sg:phone":"+1 843 846 1803",
    "sg:postcode":"29906",
    "sg:province":"SC",
    "wof:name":"Crestwood Mobile Homes",
    "wof:placetype":"venue"
},
  "geometry": {"coordinates":[-80.73741800000001,32.513571],"type":"Point"}
}