{
  "type": "Feature",
  "properties": {
    "addr:full":"105 Cotton St Chester SC 29709",
    "addr:housenumber":"105",
    "addr:postcode":"29709",
    "addr:street":"Cotton St",
    "iso:country":"US",
    "sg:address":"105 Cotton St",
    "sg:city":"Chester",
    "sg:classifiers":[
        {
            "category":"Shopping",
            "subcategory":"Used Merchandise",
            "type":"Retail Goods"
        }
    ],
    "sg:phone":"+1 803 581 0219",
    "sg:postcode":"29709",
    "sg:province":"SC",
    "sg:tags":[
        "shop",
        "thrift"
    ],
    "wof:name":"Dove's Nest",
    "wof:placetype":"venue"
},
  "geometry": {"coordinates":[-80.089032,34.734559],"type":"Point"}
}