{
  "type": "Feature",
  "properties": {
    "iso:country":"US",
    "sg:address":"3129 Bluff Rd",
    "sg:city":"Columbia",
    "sg:classifiers":[
        {
            "category":"Home & Garden",
            "subcategory":"Hardware",
            "type":"Retail Goods"
        }
    ],
    "sg:phone":"+1 803 776 8450",
    "sg:postcode":"29209",
    "sg:province":"SC",
    "wof:name":"Tosco Industrial Supplies",
    "wof:placetype":"venue"
},
  "geometry": {"coordinates":[-80.978709,33.937092],"type":"Point"}
}