{
  "type": "Feature",
  "properties": {
    "iso:country":"US",
    "sg:address":"2585 Jefferson Davis Hwy",
    "sg:city":"Warrenville",
    "sg:classifiers":[
        {
            "category":"Banks & Credit Unions",
            "subcategory":"Bank",
            "type":"Services"
        }
    ],
    "sg:phone":"+1 803 593 8250",
    "sg:postcode":"29851",
    "sg:province":"SC",
    "sg:tags":[
        "depository",
        "banking"
    ],
    "wof:name":"Fast Cash Payday Advance",
    "wof:placetype":"venue"
},
  "geometry": {"coordinates":[-81.84693,33.527149],"type":"Point"}
}