{
  "type": "Feature",
  "properties": {
    "iso:country":"US",
    "sg:address":"113 US Hwy 17 Alt",
    "sg:city":"Hardeeville",
    "sg:classifiers":[
        {
            "category":"Shopping",
            "subcategory":"Discount & Variety Stores",
            "type":"Retail Goods"
        }
    ],
    "sg:phone":"+1 843 784 6184",
    "sg:postcode":"29945",
    "sg:province":"SC",
    "sg:tags":[
        "merchandise",
        "general"
    ],
    "wof:name":"Dollar Wise",
    "wof:placetype":"venue"
},
  "geometry": {"coordinates":[-80.853855,32.669033],"type":"Point"}
}