{
  "type": "Feature",
  "properties": {
    "iso:country":"US",
    "sg:address":"1329 Cox Rd",
    "sg:city":"Pamplico",
    "sg:classifiers":[
        {
            "category":"Professional",
            "subcategory":"Business Services",
            "type":"Services"
        }
    ],
    "sg:phone":"+1 843 493 0302",
    "sg:postcode":"29583",
    "sg:province":"SC",
    "sg:tags":[
        "auctioneer"
    ],
    "wof:name":"Auction Treasure 2000 Internet",
    "wof:placetype":"venue"
},
  "geometry": {"coordinates":[-79.638908,34.024242],"type":"Point"}
}