{
  "type": "Feature",
  "properties": {
    "iso:country":"US",
    "sg:address":"5 Folly Rd",
    "sg:city":"Hilton Head Isle",
    "sg:classifiers":[
        {
            "category":"Shopping",
            "subcategory":"Clothing, Apparel, & Fashions",
            "type":"Retail Goods"
        }
    ],
    "sg:phone":"+1 843 785 2661",
    "sg:postcode":"29920",
    "sg:province":"SC",
    "sg:tags":[
        "infant",
        "wear"
    ],
    "wof:name":"Children's Corner",
    "wof:placetype":"venue"
},
  "geometry": {"coordinates":[-80.539575,32.399129],"type":"Point"}
}