{
  "type": "Feature",
  "properties": {
    "addr:full":"879 Gentry Memorial Hwy Easley SC 29640",
    "addr:housenumber":"879",
    "addr:postcode":"29640",
    "addr:street":"Gentry Memorial Hwy",
    "iso:country":"US",
    "sg:address":"879 Gentry Memorial Hwy",
    "sg:city":"Easley",
    "sg:classifiers":[
        {
            "category":"Social Services",
            "type":"Services"
        }
    ],
    "sg:phone":"+1 864 855 8500",
    "sg:postcode":"29640",
    "sg:province":"SC",
    "sg:tags":[
        "pregnancy",
        "counseling",
        "information"
    ],
    "wof:name":"Hope Women's Ctr",
    "wof:placetype":"venue"
},
  "geometry": {"coordinates":[-82.63806700000001,34.841251],"type":"Point"}
}