{
  "type": "Feature",
  "properties": {
    "iso:country":"US",
    "sg:address":"222 Greenland Rd",
    "sg:city":"Anderson",
    "sg:classifiers":[
        {
            "category":"Building & Trades",
            "subcategory":"Electrical",
            "type":"Services"
        }
    ],
    "sg:phone":"+1 864 226 5835",
    "sg:postcode":"29626",
    "sg:province":"SC",
    "sg:tags":[
        "electrical",
        "contractor"
    ],
    "wof:name":"Dial Electrical Contracting",
    "wof:placetype":"venue"
},
  "geometry": {"coordinates":[-82.696716,34.492927],"type":"Point"}
}