{
  "type": "Feature",
  "properties": {
    "iso:country":"US",
    "sg:address":"320 Sleepy Prong Rd",
    "sg:city":"Andrews",
    "sg:classifiers":[
        {
            "category":"Wholesale",
            "subcategory":"Farm Supplies",
            "type":"Manufacturing & Wholesale Goods"
        }
    ],
    "sg:phone":"+1 843 221 7025",
    "sg:postcode":"29510",
    "sg:province":"SC",
    "sg:tags":[
        "livestock"
    ],
    "wof:name":"Casselman John",
    "wof:placetype":"venue"
},
  "geometry": {"coordinates":[-79.54358,33.51113],"type":"Point"}
}