{
  "type": "Feature",
  "properties": {
    "iso:country":"US",
    "sg:address":"534 Ascot Ridge Rd",
    "sg:city":"Rock Hill",
    "sg:classifiers":[
        {
            "category":"Professional",
            "subcategory":"Advertising",
            "type":"Services"
        }
    ],
    "sg:phone":"+1 803 327 0941",
    "sg:postcode":"29730",
    "sg:province":"SC",
    "sg:tags":[
        "counselor"
    ],
    "wof:name":"Pure Creative Inc",
    "wof:placetype":"venue"
},
  "geometry": {"coordinates":[-81.016431,34.940349],"type":"Point"}
}