{
  "type": "Feature",
  "properties": {
    "iso:country":"US",
    "sg:address":"2107 S Main St",
    "sg:city":"Anderson",
    "sg:classifiers":[
        {
            "category":"Autos & Motor Vehicles",
            "subcategory":"Automobile Sales",
            "type":"Retail Goods"
        }
    ],
    "sg:phone":"+1 864 226 3398",
    "sg:postcode":"29624",
    "sg:province":"SC",
    "sg:tags":[
        "used"
    ],
    "wof:name":"Ronnies Auto Sales",
    "wof:placetype":"venue"
},
  "geometry": {"coordinates":[-82.647722,34.485922],"type":"Point"}
}