{
  "type": "Feature",
  "properties": {
    "iso:country":"US",
    "sg:address":"404 Johnson St",
    "sg:city":"Pickens",
    "sg:classifiers":[
        {
            "category":"Social Services",
            "type":"Services"
        }
    ],
    "sg:phone":"+1 864 898 5575",
    "sg:postcode":"29671",
    "sg:province":"SC",
    "sg:tags":[
        "crisis",
        "intervention"
    ],
    "wof:name":"Rape Crisis Pickens County",
    "wof:placetype":"venue"
},
  "geometry": {"coordinates":[-82.70701,34.881041],"type":"Point"}
}