{
  "type": "Feature",
  "properties": {
    "iso:country":"US",
    "sg:address":"1448 State Hwy 9 Byp",
    "sg:city":"Lancaster",
    "sg:classifiers":[
        {
            "category":"Home & Garden",
            "subcategory":"Mobile Homes",
            "type":"Retail Goods"
        }
    ],
    "sg:phone":"+1 803 289 1217",
    "sg:postcode":"29720",
    "sg:province":"SC",
    "wof:name":"Family Home Ctr Lancaster LLC",
    "wof:placetype":"venue"
},
  "geometry": {"coordinates":[-80.805576,34.732257],"type":"Point"}
}