{
  "type": "Feature",
  "properties": {
    "iso:country":"US",
    "sg:address":"5219 Trenholm Rd",
    "sg:city":"Columbia",
    "sg:classifiers":[
        {
            "category":"Real Estate",
            "subcategory":"Real Estate Agent",
            "type":"Services"
        }
    ],
    "sg:phone":"+1 803 782 9171",
    "sg:postcode":"29206",
    "sg:province":"SC",
    "sg:tags":[
        "residential",
        "commercial"
    ],
    "sg:website":"www.russellandjeffcoat.com",
    "wof:name":"Russell & Jeffcoat Realtors",
    "wof:placetype":"venue"
},
  "geometry": {"coordinates":[-80.9664,34.018758],"type":"Point"}
}