{
  "type": "Feature",
  "properties": {
    "addr:full":"628 John C Calhoun Dr Orangeburg SC 29115",
    "addr:housenumber":"628",
    "addr:postcode":"29115",
    "addr:street":"John C Calhoun Dr",
    "iso:country":"US",
    "sg:address":"628 John C Calhoun Dr",
    "sg:city":"Orangeburg",
    "sg:classifiers":[
        {
            "category":"Insurance",
            "subcategory":"Insurance Agent",
            "type":"Services"
        }
    ],
    "sg:phone":"+1 803 534 0447",
    "sg:postcode":"29115",
    "sg:province":"SC",
    "wof:name":"American General Life & Accdnt",
    "wof:placetype":"venue"
},
  "geometry": {"coordinates":[-80.852158,33.491012],"type":"Point"}
}