{
  "type": "Feature",
  "properties": {
    "addr:full":"401 Brookhollow Dr York SC 29745",
    "addr:housenumber":"401",
    "addr:postcode":"29745",
    "addr:street":"Brookhollow Dr",
    "iso:country":"US",
    "sg:address":"401 Brookhollow Dr",
    "sg:city":"York",
    "sg:classifiers":[
        {
            "category":"Building & Trades",
            "subcategory":"Construction",
            "type":"Services"
        }
    ],
    "sg:phone":"+1 803 628 5498",
    "sg:postcode":"29745",
    "sg:province":"SC",
    "sg:tags":[
        "house"
    ],
    "wof:name":"KB Homes Inc",
    "wof:placetype":"venue"
},
  "geometry": {"coordinates":[-81.19149299999999,34.981289],"type":"Point"}
}