{
  "type": "Feature",
  "properties": {
    "iso:country":"US",
    "sg:address":"106 S 9th Ave",
    "sg:city":"Dillon",
    "sg:classifiers":[
        {
            "category":"Social Services",
            "subcategory":"Child Care",
            "type":"Services"
        }
    ],
    "sg:phone":"+1 843 774 6418",
    "sg:postcode":"29536",
    "sg:province":"SC",
    "wof:name":"Little Pumpkin Day Care",
    "wof:placetype":"venue"
},
  "geometry": {"coordinates":[-79.377877,34.419969],"type":"Point"}
}