{
  "type": "Feature",
  "properties": {
    "addr:full":"704 E Main St Westminster SC 29693",
    "addr:housenumber":"704",
    "addr:postcode":"29693",
    "addr:street":"E Main St",
    "iso:country":"US",
    "sg:address":"704 E Main St",
    "sg:city":"Westminster",
    "sg:classifiers":[
        {
            "category":"Autos & Motor Vehicles",
            "subcategory":"Auto Supplies",
            "type":"Retail Goods"
        },
        {
            "category":"Wholesale",
            "subcategory":"Auto Parts",
            "type":"Manufacturing & Wholesale Goods"
        }
    ],
    "sg:phone":"+1 864 647 5401",
    "sg:postcode":"29693",
    "sg:province":"SC",
    "sg:tags":[
        "automobile"
    ],
    "wof:name":"Anderson Auto Parts Co Inc",
    "wof:placetype":"venue"
},
  "geometry": {"coordinates":[-83.089011,34.659665],"type":"Point"}
}