{
  "type": "Feature",
  "properties": {
    "iso:country":"US",
    "sg:address":"929 N Lake Dr",
    "sg:city":"Lexington",
    "sg:classifiers":[
        {
            "category":"Professional",
            "subcategory":"Employment Agencies",
            "type":"Services"
        }
    ],
    "sg:phone":"+1 803 356 2138",
    "sg:postcode":"29072",
    "sg:province":"SC",
    "sg:tags":[
        "opportunity"
    ],
    "wof:name":"Holland Employment",
    "wof:placetype":"venue"
},
  "geometry": {"coordinates":[-81.230454,33.994413],"type":"Point"}
}