{
  "type": "Feature",
  "properties": {
    "iso:country":"US",
    "sg:address":"1320 King St",
    "sg:city":"Columbia",
    "sg:classifiers":[
        {
            "category":"Professional",
            "subcategory":"Secretarial Services",
            "type":"Services"
        }
    ],
    "sg:phone":"+1 803 779 7761",
    "sg:postcode":"29205",
    "sg:province":"SC",
    "sg:tags":[
        "reporting",
        "court"
    ],
    "wof:name":"Youngbloods Consulting Agency",
    "wof:placetype":"venue"
},
  "geometry": {"coordinates":[-81.00607100000001,34.006499],"type":"Point"}
}