{
  "type": "Feature",
  "properties": {
    "iso:country":"US",
    "sg:address":"30 Malphrus Rd",
    "sg:city":"Bluffton",
    "sg:classifiers":[
        {
            "category":"Communications",
            "type":"Services"
        }
    ],
    "sg:phone":"+1 843 836 1930",
    "sg:postcode":"29910",
    "sg:province":"SC",
    "wof:name":"Prime Communications",
    "wof:placetype":"venue"
},
  "geometry": {"coordinates":[-80.844598,32.226462],"type":"Point"}
}