{
  "type": "Feature",
  "properties": {
    "addr:full":"607 E Lee Rd Taylors SC 29687",
    "addr:housenumber":"607",
    "addr:postcode":"29687",
    "addr:street":"E Lee Rd",
    "iso:country":"US",
    "sg:address":"607 E Lee Rd",
    "sg:city":"Taylors",
    "sg:classifiers":[
        {
            "category":"Personal",
            "subcategory":"Beauty Salon",
            "type":"Services"
        }
    ],
    "sg:phone":"+1 864 322 5400",
    "sg:postcode":"29687",
    "sg:province":"SC",
    "wof:name":"Gatz Hair Studio",
    "wof:placetype":"venue"
},
  "geometry": {"coordinates":[-82.32983900000001,34.902171],"type":"Point"}
}