{
  "type": "Feature",
  "properties": {
    "iso:country":"US",
    "sg:address":"631 Rutledge Ave",
    "sg:city":"Charleston",
    "sg:classifiers":[
        {
            "category":"Food & Beverages",
            "subcategory":"Liquor & Beverages",
            "type":"Retail Goods"
        }
    ],
    "sg:phone":"+1 843 577 7230",
    "sg:postcode":"29403",
    "sg:province":"SC",
    "wof:name":"Rutledge Avenue",
    "wof:placetype":"venue"
},
  "geometry": {"coordinates":[-79.95096,32.798153],"type":"Point"}
}