{
  "type": "Feature",
  "properties": {
    "iso:country":"US",
    "sg:address":"409 W Main St",
    "sg:city":"Easley",
    "sg:classifiers":[
        {
            "category":"Education",
            "subcategory":"School",
            "type":"Public Place"
        }
    ],
    "sg:phone":"+1 864 850 0558",
    "sg:postcode":"29640",
    "sg:province":"SC",
    "wof:name":"Young's Kajenkenbo Acad-Self",
    "wof:placetype":"venue"
},
  "geometry": {"coordinates":[-82.608373,34.828886],"type":"Point"}
}