{
  "type": "Feature",
  "properties": {
    "iso:country":"US",
    "sg:address":"655 Fairview Rd",
    "sg:city":"Simpsonville",
    "sg:classifiers":[
        {
            "category":"Banks & Credit Unions",
            "subcategory":"Bank",
            "type":"Services"
        }
    ],
    "sg:phone":"+1 864 962 5641",
    "sg:postcode":"29680",
    "sg:province":"SC",
    "sg:tags":[
        "cashing",
        "check"
    ],
    "wof:name":"Check 'n Go",
    "wof:placetype":"venue"
},
  "geometry": {"coordinates":[-82.25785399999999,34.705831],"type":"Point"}
}