{
  "type": "Feature",
  "properties": {
    "iso:country":"US",
    "sg:address":"299 Freedom Trl",
    "sg:city":"Roebuck",
    "sg:classifiers":[
        {
            "category":"Building & Trades",
            "subcategory":"Construction",
            "type":"Services"
        }
    ],
    "sg:phone":"+1 864 542 7028",
    "sg:postcode":"29376",
    "sg:province":"SC",
    "sg:tags":[
        "house"
    ],
    "wof:name":"Paul K Lee Construction",
    "wof:placetype":"venue"
},
  "geometry": {"coordinates":[-81.938902,34.860901],"type":"Point"}
}