{
  "type": "Feature",
  "properties": {
    "iso:country":"US",
    "sg:address":"1301 Laurel St",
    "sg:city":"Columbia",
    "sg:classifiers":[
        {
            "category":"Manufacturing",
            "subcategory":"Printing",
            "type":"Manufacturing & Wholesale Goods"
        }
    ],
    "sg:phone":"+1 803 765 1122",
    "sg:postcode":"29201",
    "sg:province":"SC",
    "sg:tags":[
        "print",
        "photocopying",
        "lithographic"
    ],
    "wof:name":"Print House Plus Inc",
    "wof:placetype":"venue"
},
  "geometry": {"coordinates":[-81.033885,34.010276],"type":"Point"}
}