{
  "type": "Feature",
  "properties": {
    "iso:country":"US",
    "sg:address":"951 Old Cherokee Rd",
    "sg:city":"Lexington",
    "sg:classifiers":[
        {
            "category":"Personal",
            "type":"Services"
        }
    ],
    "sg:phone":"+1 803 356 8044",
    "sg:postcode":"29072",
    "sg:province":"SC",
    "sg:tags":[
        "therapist",
        "massage"
    ],
    "wof:name":"Body Tech",
    "wof:placetype":"venue"
},
  "geometry": {"coordinates":[-81.25522,34.008781],"type":"Point"}
}