{
  "type": "Feature",
  "properties": {
    "iso:country":"US",
    "sg:address":"901 Colleton St",
    "sg:city":"Columbia",
    "sg:classifiers":[
        {
            "category":"Freight",
            "type":"Transportation"
        }
    ],
    "sg:phone":"+1 803 735 9145",
    "sg:postcode":"29203",
    "sg:province":"SC",
    "sg:tags":[
        "delivery"
    ],
    "wof:name":"Do-Boy Delivery Svc",
    "wof:placetype":"venue"
},
  "geometry": {"coordinates":[-81.022641,34.056148],"type":"Point"}
}