{
  "type": "Feature",
  "properties": {
    "iso:country":"US",
    "sg:address":"128 Ashley Rd",
    "sg:city":"Clemson",
    "sg:classifiers":[
        {
            "category":"Manufacturing",
            "subcategory":"Tools & Machinery",
            "type":"Manufacturing & Wholesale Goods"
        }
    ],
    "sg:phone":"+1 864 654 7509",
    "sg:postcode":"29631",
    "sg:province":"SC",
    "sg:tags":[
        "fabrication",
        "mechanical"
    ],
    "wof:name":"Carson Industries",
    "wof:placetype":"venue"
},
  "geometry": {"coordinates":[-82.791984,34.6901],"type":"Point"}
}