{
  "type": "Feature",
  "properties": {
    "iso:country":"US",
    "sg:address":"661 Boyer Rd",
    "sg:city":"Holly Hill",
    "sg:classifiers":[
        {
            "category":"Retail",
            "subcategory":"Auto Repair",
            "type":"Services"
        }
    ],
    "sg:phone":"+1 803 496 7228",
    "sg:postcode":"29059",
    "sg:province":"SC",
    "sg:tags":[
        "wrecker"
    ],
    "wof:name":"Cusack's Auto Sales & Garage",
    "wof:placetype":"venue"
},
  "geometry": {"coordinates":[-80.416274,33.304985],"type":"Point"}
}