{
  "type": "Feature",
  "properties": {
    "iso:country":"US",
    "sg:address":"1 Space Dr",
    "sg:city":"Taylors",
    "sg:classifiers":[
        {
            "category":"Building & Trades",
            "subcategory":"Electrical",
            "type":"Services"
        }
    ],
    "sg:phone":"+1 864 244 5536",
    "sg:postcode":"29687",
    "sg:province":"SC",
    "sg:tags":[
        "electric",
        "contractor"
    ],
    "wof:name":"Collins Electric Co",
    "wof:placetype":"venue"
},
  "geometry": {"coordinates":[-82.33242799999999,34.910844],"type":"Point"}
}