{
  "type": "Feature",
  "properties": {
    "iso:country":"US",
    "sg:address":"102 N Maple St",
    "sg:city":"Simpsonville",
    "sg:classifiers":[
        {
            "category":"Personal",
            "subcategory":"Shoe Repair & Shine",
            "type":"Services"
        }
    ],
    "sg:phone":"+1 864 963 7288",
    "sg:postcode":"29681",
    "sg:province":"SC",
    "sg:tags":[
        "repairing",
        "boot"
    ],
    "wof:name":"Cobblers Corner",
    "wof:placetype":"venue"
},
  "geometry": {"coordinates":[-82.256515,34.737143],"type":"Point"}
}