{
  "type": "Feature",
  "properties": {
    "iso:country":"US",
    "sg:address":"111 Eagle Rd",
    "sg:city":"Hopkins",
    "sg:classifiers":[
        {
            "category":"Professional",
            "subcategory":"Computer Services",
            "type":"Services"
        }
    ],
    "sg:phone":"+1 803 776 6242",
    "sg:postcode":"29061",
    "sg:province":"SC",
    "sg:tags":[
        "consultant",
        "designer"
    ],
    "wof:name":"EKG Of South Carolina",
    "wof:placetype":"venue"
},
  "geometry": {"coordinates":[-80.841762,33.94989],"type":"Point"}
}