{
  "type": "Feature",
  "properties": {
    "iso:country":"US",
    "sg:address":"137 Cordillo Pkwy",
    "sg:city":"Hilton Head Isle",
    "sg:classifiers":[
        {
            "category":"Building & Trades",
            "subcategory":"Equipment Rental",
            "type":"Services"
        }
    ],
    "sg:phone":"+1 843 342 9338",
    "sg:postcode":"29928",
    "sg:province":"SC",
    "sg:tags":[
        "yard"
    ],
    "wof:name":"Affairs To Remember",
    "wof:placetype":"venue"
},
  "geometry": {"coordinates":[-80.760285,32.145125],"type":"Point"}
}