{
  "type": "Feature",
  "properties": {
    "addr:full":"1620 Lady St Columbia SC 29201",
    "addr:housenumber":"1620",
    "addr:postcode":"29201",
    "addr:street":"Lady St",
    "iso:country":"US",
    "sg:address":"1620 Lady St",
    "sg:city":"Columbia",
    "sg:classifiers":[
        {
            "category":"Professional",
            "subcategory":"Lawyer & Legal Services",
            "type":"Services"
        }
    ],
    "sg:phone":"+1 803 779 9197",
    "sg:postcode":"29201",
    "sg:province":"SC",
    "sg:tags":[
        "attorney"
    ],
    "wof:name":"Marshall Lawson",
    "wof:placetype":"venue"
},
  "geometry": {"coordinates":[-81.02619,34.004846],"type":"Point"}
}