{
  "type": "Feature",
  "properties": {
    "iso:country":"US",
    "sg:address":"646 Manning Ave",
    "sg:city":"Sumter",
    "sg:classifiers":[
        {
            "category":"Autos & Motor Vehicles",
            "subcategory":"Automobile Sales",
            "type":"Retail Goods"
        }
    ],
    "sg:phone":"+1 803 775 5162",
    "sg:postcode":"29150",
    "sg:province":"SC",
    "sg:tags":[
        "used"
    ],
    "wof:name":"Warren Auto Sales",
    "wof:placetype":"venue"
},
  "geometry": {"coordinates":[-80.340209,33.902163],"type":"Point"}
}