{
  "type": "Feature",
  "properties": {
    "addr:full":"2 Mayo Dr Greenville SC 29605",
    "addr:housenumber":"2",
    "addr:postcode":"29605",
    "addr:street":"Mayo Dr",
    "iso:country":"US",
    "sg:address":"2 Mayo Dr",
    "sg:city":"Greenville",
    "sg:classifiers":[
        {
            "category":"Professional",
            "subcategory":"Management & Consulting",
            "type":"Services"
        }
    ],
    "sg:phone":"+1 864 299 3429",
    "sg:postcode":"29605",
    "sg:province":"SC",
    "sg:tags":[
        "retail",
        "direct",
        "sales"
    ],
    "wof:name":"Thompson Fuel Oil",
    "wof:placetype":"venue"
},
  "geometry": {"coordinates":[-82.37084299999999,34.804916],"type":"Point"}
}