{
  "type": "Feature",
  "properties": {
    "iso:country":"US",
    "sg:address":"21 Nunan St",
    "sg:city":"Charleston",
    "sg:classifiers":[
        {
            "category":"Real Estate",
            "subcategory":"Real Estate Operator",
            "type":"Services"
        }
    ],
    "sg:phone":"+1 843 723 5527",
    "sg:postcode":"29403",
    "sg:province":"SC",
    "sg:tags":[
        "apartment"
    ],
    "wof:name":"Nunan Apartments",
    "wof:placetype":"venue"
},
  "geometry": {"coordinates":[-79.951021,32.792454],"type":"Point"}
}