{
  "type": "Feature",
  "properties": {
    "iso:country":"US",
    "sg:address":"114 E Main St",
    "sg:city":"Kingstree",
    "sg:classifiers":[
        {
            "category":"Professional",
            "subcategory":"Accounting & Tax Preparation",
            "type":"Services"
        }
    ],
    "sg:phone":"+1 843 354 9003",
    "sg:postcode":"29556",
    "sg:province":"SC",
    "sg:tags":[
        "accountant"
    ],
    "wof:name":"J & L Tax",
    "wof:placetype":"venue"
},
  "geometry": {"coordinates":[-79.82956,33.663887],"type":"Point"}
}