{
  "type": "Feature",
  "properties": {
    "iso:country":"US",
    "sg:address":"433 Saddlebrook Ln",
    "sg:city":"Hopkins",
    "sg:classifiers":[
        {
            "category":"Building & Trades",
            "subcategory":"Landscaping Services",
            "type":"Services"
        }
    ],
    "sg:phone":"+1 803 783 7207",
    "sg:postcode":"29061",
    "sg:province":"SC",
    "wof:name":"Organic Lawn Systems",
    "wof:placetype":"venue"
},
  "geometry": {"coordinates":[-80.853848,33.939224],"type":"Point"}
}