{
  "type": "Feature",
  "properties": {
    "iso:country":"US",
    "sg:address":"1620 Gervais St",
    "sg:city":"Columbia",
    "sg:classifiers":[
        {
            "category":"Professional",
            "subcategory":"Printing & Photocopies",
            "type":"Services"
        }
    ],
    "sg:phone":"+1 803 771 6829",
    "sg:postcode":"29201",
    "sg:province":"SC",
    "wof:name":"Copy Shop the",
    "wof:placetype":"venue"
},
  "geometry": {"coordinates":[-81.025902,34.003502],"type":"Point"}
}