{
  "type": "Feature",
  "properties": {
    "addr:full":"931 Senate St Columbia SC 29201",
    "addr:housenumber":"931",
    "addr:postcode":"29201",
    "addr:street":"Senate St",
    "iso:country":"US",
    "sg:address":"931 Senate St",
    "sg:city":"Columbia",
    "sg:classifiers":[
        {
            "category":"Bars & Pubs",
            "type":"Food & Drink"
        },
        {
            "category":"Restaurant",
            "type":"Food & Drink"
        },
        {
            "category":"Bars & Pubs",
            "subcategory":"Lounge",
            "type":"Food & Drink"
        }
    ],
    "sg:phone":"+1 803 933 9997",
    "sg:postcode":"29201",
    "sg:province":"SC",
    "sg:website":"www.beerknurd.com",
    "wof:name":"Flying Saucer",
    "wof:placetype":"venue"
},
  "geometry": {"coordinates":[-81.037003,34.000301],"type":"Point"}
}