{
  "type": "Feature",
  "properties": {
    "iso:country":"US",
    "sg:address":"2312 W Parker Rd",
    "sg:city":"Greenville",
    "sg:classifiers":[
        {
            "category":"Banks & Credit Unions",
            "subcategory":"Bank",
            "type":"Services"
        }
    ],
    "sg:phone":"+1 864 239 6888",
    "sg:postcode":"29617",
    "sg:province":"SC",
    "wof:name":"Wachovia Bank",
    "wof:placetype":"venue"
},
  "geometry": {"coordinates":[-82.455015,34.882132],"type":"Point"}
}