{
  "type": "Feature",
  "properties": {
    "iso:country":"US",
    "sg:address":"3131 N Main St",
    "sg:city":"Anderson",
    "sg:classifiers":[
        {
            "category":"Shopping",
            "type":"Retail Goods"
        }
    ],
    "sg:phone":"+1 864 225 0000",
    "sg:postcode":"29621",
    "sg:province":"SC",
    "sg:tags":[
        "merchandise"
    ],
    "wof:name":"Nicks Sales",
    "wof:placetype":"venue"
},
  "geometry": {"coordinates":[-82.667667,34.539113],"type":"Point"}
}