{
  "type": "Feature",
  "properties": {
    "iso:country":"US",
    "sg:address":"120 Sparkleberry Ln",
    "sg:city":"Columbia",
    "sg:classifiers":[
        {
            "category":"Restaurant",
            "type":"Food & Drink"
        }
    ],
    "sg:menulink":"http://www.allmenus.com/sc/pontiac/12088-caffe-corner-coffee/menu/",
    "sg:phone":"+1 803 462 0077",
    "sg:postcode":"29229",
    "sg:province":"SC",
    "sg:tags":[
        "american"
    ],
    "wof:name":"Caffe Corner Coffee",
    "wof:placetype":"venue"
},
  "geometry": {"coordinates":[-80.88398100000001,34.114896],"type":"Point"}
}