{
  "type": "Feature",
  "properties": {
    "addr:full":"139 Anderson Hwy Clemson SC 29631",
    "addr:housenumber":"139",
    "addr:postcode":"29631",
    "addr:street":"Anderson Hwy",
    "iso:country":"US",
    "sg:address":"139 Anderson Hwy",
    "sg:city":"Clemson",
    "sg:classifiers":[
        {
            "category":"Shopping",
            "subcategory":"Florist",
            "type":"Retail Goods"
        },
        {
            "category":"Shopping",
            "subcategory":"Gifts & Souvenirs",
            "type":"Retail Goods"
        }
    ],
    "sg:phone":"+1 864 654 1927",
    "sg:postcode":"29631",
    "sg:province":"SC",
    "wof:name":"Tiger Lily Gifts & Flowers Inc",
    "wof:placetype":"venue"
},
  "geometry": {"coordinates":[-82.826593,34.688634],"type":"Point"}
}