{
  "type": "Feature",
  "properties": {
    "iso:country":"US",
    "sg:address":"600 Monument St",
    "sg:city":"Greenwood",
    "sg:classifiers":[
        {
            "category":"Health Services",
            "subcategory":"Doctor",
            "type":"Services"
        }
    ],
    "sg:phone":"+1 864 227 3908",
    "sg:postcode":"29646",
    "sg:province":"SC",
    "sg:tags":[
        "physician",
        "surgeon"
    ],
    "wof:name":"Western Carolina Psychiatric",
    "wof:placetype":"venue"
},
  "geometry": {"coordinates":[-82.161604,34.187887],"type":"Point"}
}