{
  "type": "Feature",
  "properties": {
    "iso:country":"US",
    "sg:address":"146 Main St N",
    "sg:city":"Wagener",
    "sg:classifiers":[
        {
            "category":"Autos & Motor Vehicles",
            "subcategory":"Auto Supplies",
            "type":"Retail Goods"
        }
    ],
    "sg:phone":"+1 803 564 3125",
    "sg:postcode":"29164",
    "sg:province":"SC",
    "sg:tags":[
        "automobile",
        "parts"
    ],
    "wof:name":"NAPA Auto Parts",
    "wof:placetype":"venue"
},
  "geometry": {"coordinates":[-81.361571,33.651851],"type":"Point"}
}