{
  "type": "Feature",
  "properties": {
    "iso:country":"US",
    "sg:address":"614 Pearman Dairy Rd",
    "sg:city":"Anderson",
    "sg:classifiers":[
        {
            "category":"Autos & Motor Vehicles",
            "subcategory":"Fuel & Gas Station",
            "type":"Retail Goods"
        }
    ],
    "sg:phone":"+1 864 225 4099",
    "sg:postcode":"29625",
    "sg:province":"SC",
    "sg:tags":[
        "station",
        "gasoline"
    ],
    "wof:name":"Enmark Stations Inc",
    "wof:placetype":"venue"
},
  "geometry": {"coordinates":[-82.691746,34.51932],"type":"Point"}
}