{
  "type": "Feature",
  "properties": {
    "iso:country":"US",
    "sg:address":"1317 Bear Creek Rd",
    "sg:city":"Blythewood",
    "sg:classifiers":[
        {
            "category":"Building & Trades",
            "subcategory":"Construction",
            "type":"Services"
        }
    ],
    "sg:phone":"+1 803 735 9456",
    "sg:postcode":"29016",
    "sg:province":"SC",
    "sg:tags":[
        "new",
        "contractor",
        "home"
    ],
    "wof:name":"R & E Home Builders Inc",
    "wof:placetype":"venue"
},
  "geometry": {"coordinates":[-80.87876300000001,34.251666],"type":"Point"}
}