{
  "type": "Feature",
  "properties": {
    "iso:country":"US",
    "sg:address":"1306 Red Bank Rd",
    "sg:city":"Goose Creek",
    "sg:classifiers":[
        {
            "category":"Food & Beverages",
            "subcategory":"Groceries & Convenience Stores",
            "type":"Retail Goods"
        }
    ],
    "sg:phone":"+1 843 572 2984",
    "sg:postcode":"29445",
    "sg:province":"SC",
    "wof:name":"Circle K",
    "wof:placetype":"venue"
},
  "geometry": {"coordinates":[-80.009505,32.970069],"type":"Point"}
}