{
  "type": "Feature",
  "properties": {
    "iso:country":"US",
    "sg:address":"4110 Clemson Blvd",
    "sg:city":"Anderson",
    "sg:classifiers":[
        {
            "category":"Autos & Motor Vehicles",
            "subcategory":"Motorcycle Sales",
            "type":"Retail Goods"
        }
    ],
    "sg:phone":"+1 864 224 1531",
    "sg:postcode":"29621",
    "sg:province":"SC",
    "sg:tags":[
        "scooter"
    ],
    "wof:name":"Harley-Davidson-Anderson",
    "wof:placetype":"venue"
},
  "geometry": {"coordinates":[-82.695676,34.560953],"type":"Point"}
}