{
  "type": "Feature",
  "properties": {
    "iso:country":"US",
    "sg:address":"374 Lake City Hwy",
    "sg:city":"Johnsonville",
    "sg:classifiers":[
        {
            "category":"Building & Trades",
            "subcategory":"Electrical",
            "type":"Services"
        }
    ],
    "sg:phone":"+1 843 386 2922",
    "sg:postcode":"29555",
    "sg:province":"SC",
    "sg:tags":[
        "electric",
        "contractor"
    ],
    "wof:name":"Stone's Electrical Contractors",
    "wof:placetype":"venue"
},
  "geometry": {"coordinates":[-79.460773,33.815004],"type":"Point"}
}