{
  "type": "Feature",
  "properties": {
    "iso:country":"US",
    "sg:address":"2015 US Hwy 378",
    "sg:city":"Conway",
    "sg:classifiers":[
        {
            "category":"Professional",
            "subcategory":"Lawyer & Legal Services",
            "type":"Services"
        }
    ],
    "sg:phone":"+1 843 248 4615",
    "sg:postcode":"29527",
    "sg:province":"SC",
    "sg:tags":[
        "attorney"
    ],
    "wof:name":"Mc Iver & Graham",
    "wof:placetype":"venue"
},
  "geometry": {"coordinates":[-79.079582,33.840999],"type":"Point"}
}