{
  "type": "Feature",
  "properties": {
    "iso:country":"US",
    "sg:address":"2273 Burkett Dr",
    "sg:city":"Rock Hill",
    "sg:classifiers":[
        {
            "category":"Manufacturing",
            "subcategory":"Metals",
            "type":"Manufacturing & Wholesale Goods"
        }
    ],
    "sg:phone":"+1 803 366 6171",
    "sg:postcode":"29730",
    "sg:province":"SC",
    "sg:tags":[
        "grating"
    ],
    "sg:website":"www.carolinagrating.com",
    "wof:name":"Carolina Grating Co",
    "wof:placetype":"venue"
},
  "geometry": {"coordinates":[-80.981961,34.948896],"type":"Point"}
}