{
  "type": "Feature",
  "properties": {
    "addr:full":"900 S Broad St Clinton SC 29325",
    "addr:housenumber":"900",
    "addr:postcode":"29325",
    "addr:street":"S Broad St",
    "iso:country":"US",
    "sg:address":"900 S Broad St",
    "sg:city":"Clinton",
    "sg:classifiers":[
        {
            "category":"Restaurant",
            "type":"Food & Drink"
        }
    ],
    "sg:phone":"+1 864 833 3583",
    "sg:postcode":"29325",
    "sg:province":"SC",
    "wof:name":"Robert's Restaurant",
    "wof:placetype":"venue"
},
  "geometry": {"coordinates":[-81.878382,34.459016],"type":"Point"}
}