{
  "type": "Feature",
  "properties": {
    "iso:country":"US",
    "sg:address":"1234 State Hwy 61",
    "sg:city":"Ridgeville",
    "sg:classifiers":[
        {
            "category":"Organizations",
            "subcategory":"Religious Organization",
            "type":"Services"
        }
    ],
    "sg:phone":"+1 843 871 4702",
    "sg:postcode":"29472",
    "sg:province":"SC",
    "sg:tags":[
        "church"
    ],
    "wof:name":"Magnolia Baptist Church",
    "wof:placetype":"venue"
},
  "geometry": {"coordinates":[-80.32966500000001,33.00735],"type":"Point"}
}