{
  "type": "Feature",
  "properties": {
    "iso:country":"US",
    "sg:address":"7680 Pelham Rd",
    "sg:city":"Greenville",
    "sg:classifiers":[
        {
            "category":"Wholesale",
            "subcategory":"Home Furnishings",
            "type":"Manufacturing & Wholesale Goods"
        }
    ],
    "sg:phone":"+1 864 297 4000",
    "sg:postcode":"29615",
    "sg:province":"SC",
    "sg:tags":[
        "top",
        "floor"
    ],
    "wof:name":"Circa Floor Covering Inc",
    "wof:placetype":"venue"
},
  "geometry": {"coordinates":[-82.236581,34.853585],"type":"Point"}
}