{
  "type": "Feature",
  "properties": {
    "iso:country":"US",
    "sg:address":"401 S Edisto Ave",
    "sg:city":"Columbia",
    "sg:classifiers":[
        {
            "category":"Personal",
            "subcategory":"Piercing",
            "type":"Services"
        }
    ],
    "sg:phone":"+1 803 933 9350",
    "sg:postcode":"29205",
    "sg:province":"SC",
    "sg:tags":[
        "body"
    ],
    "wof:name":"Voodoo Garage",
    "wof:placetype":"venue"
},
  "geometry": {"coordinates":[-81.011144,33.984013],"type":"Point"}
}