{
  "type": "Feature",
  "properties": {
    "iso:country":"US",
    "sg:address":"20 Bell Rd",
    "sg:city":"Greenville",
    "sg:classifiers":[
        {
            "category":"Organizations",
            "subcategory":"Religious Organization",
            "type":"Services"
        }
    ],
    "sg:phone":"+1 864 288 1543",
    "sg:postcode":"29607",
    "sg:province":"SC",
    "sg:tags":[
        "church"
    ],
    "wof:name":"Woodruff Road Christian Church",
    "wof:placetype":"venue"
},
  "geometry": {"coordinates":[-82.264686,34.819961],"type":"Point"}
}