{
  "type": "Feature",
  "properties": {
    "iso:country":"US",
    "sg:address":"119 W Home Ave",
    "sg:city":"Hartsville",
    "sg:classifiers":[
        {
            "category":"Wholesale",
            "subcategory":"Electrical",
            "type":"Manufacturing & Wholesale Goods"
        }
    ],
    "sg:phone":"+1 843 857 0850",
    "sg:postcode":"29550",
    "sg:province":"SC",
    "sg:tags":[
        "meter"
    ],
    "wof:name":"Amron Technology Inc",
    "wof:placetype":"venue"
},
  "geometry": {"coordinates":[-80.074628,34.376118],"type":"Point"}
}