{
  "type": "Feature",
  "properties": {
    "addr:full":"1204 Caldwell St Newberry SC 29108",
    "addr:housenumber":"1204",
    "addr:postcode":"29108",
    "addr:street":"Caldwell St",
    "iso:country":"US",
    "sg:address":"1204 Caldwell St",
    "sg:city":"Newberry",
    "sg:classifiers":[
        {
            "category":"Banks & Credit Unions",
            "subcategory":"Investment Brokerage",
            "type":"Services"
        }
    ],
    "sg:phone":"+1 803 276 8866",
    "sg:postcode":"29108",
    "sg:province":"SC",
    "sg:tags":[
        "stock",
        "bond"
    ],
    "wof:name":"Edward Jones Co",
    "wof:placetype":"venue"
},
  "geometry": {"coordinates":[-81.620424,34.276023],"type":"Point"}
}