{
  "type": "Feature",
  "properties": {
    "iso:country":"US",
    "sg:address":"119 Professional Park Dr",
    "sg:city":"Seneca",
    "sg:classifiers":[
        {
            "category":"Professional",
            "subcategory":"Lawyer & Legal Services",
            "type":"Services"
        }
    ],
    "sg:phone":"+1 864 882 2466",
    "sg:postcode":"29678",
    "sg:province":"SC",
    "sg:tags":[
        "attorney"
    ],
    "wof:name":"Merrell & Jahn",
    "wof:placetype":"venue"
},
  "geometry": {"coordinates":[-82.97229400000001,34.69382],"type":"Point"}
}