{
  "type": "Feature",
  "properties": {
    "iso:country":"US",
    "sg:address":"1202 Port Dr",
    "sg:city":"Myrtle Beach",
    "sg:classifiers":[
        {
            "category":"Food & Beverages",
            "subcategory":"Groceries & Convenience Stores",
            "type":"Retail Goods"
        }
    ],
    "sg:phone":"+1 843 293 7990",
    "sg:postcode":"29577",
    "sg:province":"SC",
    "wof:name":"Scotchman Store",
    "wof:placetype":"venue"
},
  "geometry": {"coordinates":[-78.952984,33.689655],"type":"Point"}
}