{
  "type": "Feature",
  "properties": {
    "iso:country":"US",
    "sg:address":"141 N Main St",
    "sg:city":"Sumter",
    "sg:classifiers":[
        {
            "category":"Government",
            "subcategory":"Office",
            "type":"Public Place"
        }
    ],
    "sg:phone":"+1 803 436 2198",
    "sg:postcode":"29150",
    "sg:province":"SC",
    "wof:name":"Sumter County SOLICITOR-Pti",
    "wof:placetype":"venue"
},
  "geometry": {"coordinates":[-80.34136700000001,33.92283],"type":"Point"}
}