{
  "type": "Feature",
  "properties": {
    "addr:full":"100 W Scenic Dr Travelers Rest SC 29690",
    "addr:housenumber":"100",
    "addr:postcode":"29690",
    "addr:street":"W Scenic Dr",
    "iso:country":"US",
    "sg:address":"100 W Scenic Dr",
    "sg:city":"Travelers Rest",
    "sg:classifiers":[
        {
            "category":"Building & Trades",
            "subcategory":"Construction",
            "type":"Services"
        }
    ],
    "sg:phone":"+1 864 915 1590",
    "sg:postcode":"29690",
    "sg:province":"SC",
    "sg:tags":[
        "house"
    ],
    "wof:name":"Scotts Painting",
    "wof:placetype":"venue"
},
  "geometry": {"coordinates":[-82.41931099999999,34.963563],"type":"Point"}
}