{
  "type": "Feature",
  "properties": {
    "iso:country":"US",
    "sg:address":"110 E Roosevelt St",
    "sg:city":"Dillon",
    "sg:classifiers":[
        {
            "category":"Communications",
            "type":"Services"
        }
    ],
    "sg:phone":"+1 843 774 5903",
    "sg:postcode":"29536",
    "sg:province":"SC",
    "wof:name":"Digital Communications",
    "wof:placetype":"venue"
},
  "geometry": {"coordinates":[-79.36791599999999,34.420927],"type":"Point"}
}