{
  "type": "Feature",
  "properties": {
    "addr:full":"102 Elaine Ct Easley SC 29640",
    "addr:housenumber":"102",
    "addr:postcode":"29640",
    "addr:street":"Elaine Ct",
    "iso:country":"US",
    "sg:address":"102 Elaine Ct",
    "sg:city":"Easley",
    "sg:classifiers":[
        {
            "category":"Retail",
            "subcategory":"Repair Shop",
            "type":"Services"
        }
    ],
    "sg:phone":"+1 864 859 7554",
    "sg:postcode":"29640",
    "sg:province":"SC",
    "sg:tags":[
        "steel",
        "erection",
        "welding",
        "structural"
    ],
    "wof:name":"Holcomb Welding & Erectors",
    "wof:placetype":"venue"
},
  "geometry": {"coordinates":[-82.576207,34.881366],"type":"Point"}
}