{
  "type": "Feature",
  "properties": {
    "iso:country":"US",
    "sg:address":"225 Bonnie Woods Dr",
    "sg:city":"Greenville",
    "sg:classifiers":[
        {
            "category":"Building & Trades",
            "subcategory":"Construction",
            "type":"Services"
        }
    ],
    "sg:phone":"+1 864 901 6080",
    "sg:postcode":"29605",
    "sg:province":"SC",
    "sg:tags":[
        "house"
    ],
    "wof:name":"Anchor Construction",
    "wof:placetype":"venue"
},
  "geometry": {"coordinates":[-82.34537,34.754947],"type":"Point"}
}