{
  "type": "Feature",
  "properties": {
    "iso:country":"US",
    "sg:address":"1807 W Whitner St",
    "sg:city":"Anderson",
    "sg:classifiers":[
        {
            "category":"Retail",
            "subcategory":"Car Wash",
            "type":"Services"
        }
    ],
    "sg:phone":"+1 864 225 0868",
    "sg:postcode":"29624",
    "sg:province":"SC",
    "sg:tags":[
        "polishing",
        "washing"
    ],
    "wof:name":"Lee Clean Up Shop",
    "wof:placetype":"venue"
},
  "geometry": {"coordinates":[-82.672505,34.503073],"type":"Point"}
}