{
  "type": "Feature",
  "properties": {
    "addr:full":"3000 Pelzer Hwy Easley SC 29642",
    "addr:postcode":"3000;29642",
    "addr:street":"Pelzer Hwy",
    "iso:country":"US",
    "sg:address":"3000 Pelzer Hwy",
    "sg:city":"Easley",
    "sg:classifiers":[
        {
            "category":"Food & Beverages",
            "subcategory":"Groceries & Convenience Stores",
            "type":"Retail Goods"
        }
    ],
    "sg:phone":"+1 864 855 4744",
    "sg:postcode":"29642",
    "sg:province":"SC",
    "sg:tags":[
        "grocer"
    ],
    "wof:name":"3 & 20 Food Mart",
    "wof:placetype":"venue"
},
  "geometry": {"coordinates":[-82.575076,34.771294],"type":"Point"}
}