{
  "type": "Feature",
  "properties": {
    "iso:country":"US",
    "sg:address":"140 Westover St",
    "sg:city":"Lake City",
    "sg:classifiers":[
        {
            "category":"Professional",
            "type":"Services"
        }
    ],
    "sg:phone":"+1 843 394 2393",
    "sg:postcode":"29560",
    "sg:province":"SC",
    "sg:tags":[
        "establishment"
    ],
    "wof:name":"Special Services Building",
    "wof:placetype":"venue"
},
  "geometry": {"coordinates":[-79.763253,33.873576],"type":"Point"}
}