{
  "type": "Feature",
  "properties": {
    "addr:full":"140 Westover St Lake City SC 29560",
    "addr:housenumber":"140",
    "addr:postcode":"29560",
    "addr:street":"Westover St",
    "iso:country":"US",
    "sg:address":"140 Westover St",
    "sg:city":"Lake City",
    "sg:classifiers":[
        {
            "category":"Professional",
            "type":"Services"
        }
    ],
    "sg:phone":"+1 843 394 2393",
    "sg:postcode":"29560",
    "sg:province":"SC",
    "sg:tags":[
        "establishment"
    ],
    "wof:name":"Special Services Building",
    "wof:placetype":"venue"
},
  "geometry": {"coordinates":[-79.76325300000001,33.873576],"type":"Point"}
}