{
  "type": "Feature",
  "properties": {
    "iso:country":"US",
    "sg:address":"319 Harbor Dr",
    "sg:city":"Seneca",
    "sg:classifiers":[
        {
            "category":"Professional",
            "subcategory":"Business Services",
            "type":"Services"
        }
    ],
    "sg:phone":"+1 864 885 9298",
    "sg:postcode":"29672",
    "sg:province":"SC",
    "sg:tags":[
        "drafting"
    ],
    "sg:website":"www.cadworkscorp.com",
    "wof:name":"Cadworks Residential Drafting",
    "wof:placetype":"venue"
},
  "geometry": {"coordinates":[-82.962695,34.700994],"type":"Point"}
}