{
  "type": "Feature",
  "properties": {
    "iso:country":"US",
    "sg:address":"7660 Garners Ferry Rd",
    "sg:city":"Columbia",
    "sg:classifiers":[
        {
            "category":"Home & Garden",
            "subcategory":"Carpets & Floor Coverings",
            "type":"Retail Goods"
        }
    ],
    "sg:phone":"+1 803 783 0094",
    "sg:postcode":"29209",
    "sg:province":"SC",
    "sg:tags":[
        "dealer",
        "rug"
    ],
    "wof:name":"Wholesale Carpet",
    "wof:placetype":"venue"
},
  "geometry": {"coordinates":[-80.937623,33.958395],"type":"Point"}
}