{
  "type": "Feature",
  "properties": {
    "iso:country":"US",
    "sg:address":"188 Jersey St",
    "sg:city":"Cheraw",
    "sg:classifiers":[
        {
            "category":"Personal",
            "subcategory":"Beauty Salon",
            "type":"Services"
        }
    ],
    "sg:phone":"+1 843 537 2256",
    "sg:postcode":"29520",
    "sg:province":"SC",
    "wof:name":"Sondra's Hair Palace",
    "wof:placetype":"venue"
},
  "geometry": {"coordinates":[-79.897172,34.690014],"type":"Point"}
}