{
  "type": "Feature",
  "properties": {
    "iso:country":"US",
    "sg:address":"3054 Forestbrook Rd",
    "sg:city":"Myrtle Beach",
    "sg:classifiers":[
        {
            "category":"Retail",
            "subcategory":"Animal Services",
            "type":"Services"
        }
    ],
    "sg:phone":"+1 843 236 0366",
    "sg:postcode":"29588",
    "sg:province":"SC",
    "wof:name":"Jamcroft Kennels",
    "wof:placetype":"venue"
},
  "geometry": {"coordinates":[-78.993495,33.700643],"type":"Point"}
}