{
  "type": "Feature",
  "properties": {
    "iso:country":"US",
    "sg:address":"5950 Garners Ferry Rd",
    "sg:city":"Columbia",
    "sg:classifiers":[
        {
            "category":"Shopping",
            "subcategory":"Clothing, Apparel, & Fashions",
            "type":"Retail Goods"
        }
    ],
    "sg:phone":"+1 803 695 2101",
    "sg:postcode":"29209",
    "sg:province":"SC",
    "sg:tags":[
        "shop",
        "bridal"
    ],
    "wof:name":"Lemon Tree Bridal & Formal",
    "wof:placetype":"venue"
},
  "geometry": {"coordinates":[-80.970613,33.986046],"type":"Point"}
}