{
  "type": "Feature",
  "properties": {
    "addr:full":"113 W Main St Walhalla SC 29691",
    "addr:housenumber":"113",
    "addr:postcode":"29691",
    "addr:street":"W Main St",
    "iso:country":"US",
    "sg:address":"113 W Main St",
    "sg:city":"Walhalla",
    "sg:classifiers":[
        {
            "category":"Restaurant",
            "type":"Food & Drink"
        }
    ],
    "sg:phone":"+1 864 638 5995",
    "sg:postcode":"29691",
    "sg:province":"SC",
    "sg:tags":[
        "out"
    ],
    "wof:name":"Bantam Chef",
    "wof:placetype":"venue"
},
  "geometry": {"coordinates":[-83.066261,34.765069],"type":"Point"}
}