{
  "type": "Feature",
  "properties": {
    "iso:country":"US",
    "sg:address":"8024 Myrtle Trace Dr",
    "sg:city":"Conway",
    "sg:classifiers":[
        {
            "category":"Health Services",
            "subcategory":"Doctor",
            "type":"Services"
        }
    ],
    "sg:phone":"+1 843 347 7333",
    "sg:postcode":"29526",
    "sg:province":"SC",
    "sg:tags":[
        "physician",
        "surgeon"
    ],
    "wof:name":"Center Of Obstetrics & Gyn",
    "wof:placetype":"venue"
},
  "geometry": {"coordinates":[-78.993379,33.773185],"type":"Point"}
}