{
  "type": "Feature",
  "properties": {
    "addr:full":"1015 S Ocean Blvd North Myrtle Beach SC 29582",
    "addr:housenumber":"1015",
    "addr:postcode":"29582",
    "addr:street":"S Ocean Blvd",
    "iso:country":"US",
    "sg:address":"1015 S Ocean Blvd",
    "sg:city":"North Myrtle Beach",
    "sg:classifiers":[
        {
            "category":"Building & Trades",
            "subcategory":"Landscaping Services",
            "type":"Services"
        }
    ],
    "sg:phone":"+1 843 272 2581",
    "sg:postcode":"29582",
    "sg:province":"SC",
    "wof:name":"Wellington Homeowners Assn",
    "wof:placetype":"venue"
},
  "geometry": {"coordinates":[-78.68821199999999,33.812667],"type":"Point"}
}