{
  "type": "Feature",
  "properties": {
    "iso:country":"US",
    "sg:address":"1512 Laurel St",
    "sg:city":"Columbia",
    "sg:classifiers":[
        {
            "category":"Health Services",
            "subcategory":"Doctor",
            "type":"Services"
        },
        {
            "category":"Health Services",
            "subcategory":"Clinic",
            "type":"Services"
        }
    ],
    "sg:phone":"+1 803 252 5455",
    "sg:postcode":"29201",
    "sg:province":"SC",
    "sg:tags":[
        "counseling",
        "mental"
    ],
    "wof:name":"Wandersman Lois P PHD",
    "wof:placetype":"venue"
},
  "geometry": {"coordinates":[-81.031898,34.010799],"type":"Point"}
}