{
  "type": "Feature",
  "properties": {
    "iso:country":"US",
    "sg:address":"151 Tandem Dr",
    "sg:city":"Greer",
    "sg:classifiers":[
        {
            "category":"Professional",
            "subcategory":"Engineering",
            "type":"Services"
        }
    ],
    "sg:phone":"+1 864 848 1602",
    "sg:postcode":"29650",
    "sg:province":"SC",
    "sg:tags":[
        "engineer"
    ],
    "wof:name":"Accttech LLC",
    "wof:placetype":"venue"
},
  "geometry": {"coordinates":[-82.235704,34.892465],"type":"Point"}
}