{
  "type": "Feature",
  "properties": {
    "addr:full":"150 N Dogwood Ave Ridgeway SC 29130",
    "addr:housenumber":"150",
    "addr:postcode":"29130",
    "addr:street":"N Dogwood Ave",
    "iso:country":"US",
    "sg:address":"150 N Dogwood Ave",
    "sg:city":"Ridgeway",
    "sg:classifiers":[
        {
            "category":"Shopping",
            "subcategory":"Clothing, Apparel, & Fashions",
            "type":"Retail Goods"
        }
    ],
    "sg:phone":"+1 803 337 8344",
    "sg:postcode":"29130",
    "sg:province":"SC",
    "sg:tags":[
        "garment"
    ],
    "wof:name":"Ruby's Apparel",
    "wof:placetype":"venue"
},
  "geometry": {"coordinates":[-80.96240899999999,34.307366],"type":"Point"}
}