{
  "type": "Feature",
  "properties": {
    "addr:full":"4912 White Horse Rd Greenville SC 29611",
    "addr:housenumber":"4912",
    "addr:postcode":"29611",
    "addr:street":"White Horse Rd",
    "iso:country":"US",
    "sg:address":"4912 White Horse Rd",
    "sg:city":"Greenville",
    "sg:classifiers":[
        {
            "category":"Wholesale",
            "subcategory":"Machinery & Supplies",
            "type":"Manufacturing & Wholesale Goods"
        }
    ],
    "sg:phone":"+1 864 269 5715",
    "sg:postcode":"29611",
    "sg:province":"SC",
    "sg:tags":[
        "textile",
        "parts"
    ],
    "wof:name":"Pittman's Textile Machinery",
    "wof:placetype":"venue"
},
  "geometry": {"coordinates":[-82.467156,34.870891],"type":"Point"}
}