{
  "type": "Feature",
  "properties": {
    "iso:country":"US",
    "sg:address":"222 Floyd Rd",
    "sg:city":"Spartanburg",
    "sg:classifiers":[
        {
            "category":"Organizations",
            "subcategory":"Religious Organization",
            "type":"Services"
        }
    ],
    "sg:phone":"+1 864 577 9041",
    "sg:postcode":"29303",
    "sg:province":"SC",
    "sg:tags":[
        "church"
    ],
    "wof:name":"Bible Truth Chapel",
    "wof:placetype":"venue"
},
  "geometry": {"coordinates":[-81.90807700000001,34.994653],"type":"Point"}
}