{
  "type": "Feature",
  "properties": {
    "iso:country":"US",
    "sg:address":"102 College Dr",
    "sg:city":"Clinton",
    "sg:classifiers":[
        {
            "category":"Organizations",
            "subcategory":"Religious Organization",
            "type":"Services"
        }
    ],
    "sg:phone":"+1 864 833 3507",
    "sg:postcode":"29340",
    "sg:province":"SC",
    "sg:tags":[
        "church"
    ],
    "wof:name":"LDS Missionaries",
    "wof:placetype":"venue"
},
  "geometry": {"coordinates":[-81.65220600000001,35.069484],"type":"Point"}
}