{
  "type": "Feature",
  "properties": {
    "iso:country":"US",
    "sg:address":"1508 Washington St",
    "sg:city":"Columbia",
    "sg:classifiers":[
        {
            "category":"Professional",
            "subcategory":"Lawyer & Legal Services",
            "type":"Services"
        }
    ],
    "sg:phone":"+1 803 758 6000",
    "sg:postcode":"29201",
    "sg:province":"SC",
    "sg:tags":[
        "attorney"
    ],
    "sg:website":"www.hnblaw.com",
    "wof:name":"Howser Newman & Besley",
    "wof:placetype":"venue"
},
  "geometry": {"coordinates":[-81.028387,34.005801],"type":"Point"}
}