{
  "type": "Feature",
  "properties": {
    "addr:full":"176 Broad St Charleston SC 29401",
    "addr:housenumber":"176",
    "addr:postcode":"29401",
    "addr:street":"Broad St",
    "iso:country":"US",
    "sg:address":"176 Broad St",
    "sg:city":"Charleston",
    "sg:classifiers":[
        {
            "category":"Freight",
            "type":"Transportation"
        }
    ],
    "sg:phone":"+1 843 937 0105",
    "sg:postcode":"29401",
    "sg:province":"SC",
    "sg:tags":[
        "mover"
    ],
    "wof:name":"Aardvark Moving",
    "wof:placetype":"venue"
},
  "geometry": {"coordinates":[-79.939392,32.775741],"type":"Point"}
}