{
  "type": "Feature",
  "properties": {
    "iso:country":"US",
    "sg:address":"536 Lawrence Rd",
    "sg:city":"Anderson",
    "sg:classifiers":[
        {
            "category":"Building & Trades",
            "subcategory":"Construction",
            "type":"Services"
        }
    ],
    "sg:phone":"+1 864 226 5558",
    "sg:postcode":"29624",
    "sg:province":"SC",
    "sg:tags":[
        "general",
        "contractor"
    ],
    "wof:name":"DLR Construction Inc",
    "wof:placetype":"venue"
},
  "geometry": {"coordinates":[-82.622793,34.472021],"type":"Point"}
}