{
  "type": "Feature",
  "properties": {
    "iso:country":"US",
    "sg:address":"1063 S Pendleton St",
    "sg:city":"Easley",
    "sg:classifiers":[
        {
            "category":"Shopping",
            "subcategory":"Pharmacy",
            "type":"Retail Goods"
        }
    ],
    "sg:phone":"+1 864 859 2564",
    "sg:postcode":"29642",
    "sg:province":"SC",
    "wof:name":"CVS Pharmacy",
    "wof:placetype":"venue"
},
  "geometry": {"coordinates":[-82.60208799999999,34.812959],"type":"Point"}
}