{
  "type": "Feature",
  "properties": {
    "addr:full":"1402 E River St Anderson SC 29624",
    "addr:housenumber":"1402",
    "addr:postcode":"29624",
    "addr:street":"E River St",
    "iso:country":"US",
    "sg:address":"1402 E River St",
    "sg:city":"Anderson",
    "sg:classifiers":[
        {
            "category":"Autos & Motor Vehicles",
            "subcategory":"Auto Supplies",
            "type":"Retail Goods"
        }
    ],
    "sg:phone":"+1 864 261 3133",
    "sg:postcode":"29624",
    "sg:province":"SC",
    "sg:tags":[
        "automobile",
        "parts"
    ],
    "wof:name":"Autozone",
    "wof:placetype":"venue"
},
  "geometry": {"coordinates":[-82.631423,34.49558],"type":"Point"}
}