{
  "type": "Feature",
  "properties": {
    "iso:country":"US",
    "sg:address":"111 Waterton Way",
    "sg:city":"Simpsonville",
    "sg:classifiers":[
        {
            "category":"Building & Trades",
            "subcategory":"Construction",
            "type":"Services"
        }
    ],
    "sg:phone":"+1 864 449 1803",
    "sg:postcode":"29680",
    "sg:province":"SC",
    "sg:tags":[
        "tile",
        "dealer"
    ],
    "wof:name":"Florentino Tile & Marble",
    "wof:placetype":"venue"
},
  "geometry": {"coordinates":[-82.245358,34.700788],"type":"Point"}
}