{
  "type": "Feature",
  "properties": {
    "addr:full":"840 Little Creek Rd Myrtle Beach SC 29572",
    "addr:housenumber":"840",
    "addr:postcode":"29572",
    "addr:street":"Little Creek Rd",
    "iso:country":"US",
    "sg:address":"840 Little Creek Rd",
    "sg:city":"Myrtle Beach",
    "sg:classifiers":[
        {
            "category":"Shopping",
            "subcategory":"Florist",
            "type":"Retail Goods"
        }
    ],
    "sg:phone":"+1 843 272 5902",
    "sg:postcode":"29572",
    "sg:province":"SC",
    "wof:name":"Daytona Beach Florist",
    "wof:placetype":"venue"
},
  "geometry": {"coordinates":[-78.75637,33.793637],"type":"Point"}
}