{
  "type": "Feature",
  "properties": {
    "iso:country":"US",
    "sg:address":"5780 Allison Creek Rd",
    "sg:city":"York",
    "sg:classifiers":[
        {
            "category":"Organizations",
            "subcategory":"Religious Organization",
            "type":"Services"
        }
    ],
    "sg:phone":"+1 803 366 1302",
    "sg:postcode":"29745",
    "sg:province":"SC",
    "sg:tags":[
        "church"
    ],
    "sg:website":"www.allisoncreekchurch.com",
    "wof:name":"Allison Creek Presbyterian Chr",
    "wof:placetype":"venue"
},
  "geometry": {"coordinates":[-81.06677999999999,35.026036],"type":"Point"}
}