{
  "type": "Feature",
  "properties": {
    "addr:full":"563 Wild Flower Trl Myrtle Beach SC 29578",
    "addr:housenumber":"563",
    "addr:postcode":"29578",
    "addr:street":"Wild Flower Trl",
    "iso:country":"US",
    "sg:address":"563 Wild Flower Trl",
    "sg:city":"Myrtle Beach",
    "sg:classifiers":[
        {
            "category":"Building & Trades",
            "subcategory":"Construction",
            "type":"Services"
        }
    ],
    "sg:phone":"+1 843 347 9993",
    "sg:postcode":"29578",
    "sg:province":"SC",
    "sg:tags":[
        "contractor"
    ],
    "wof:name":"Suncoast Seamless Gutters Inc",
    "wof:placetype":"venue"
},
  "geometry": {"coordinates":[-78.96606199999999,33.78733],"type":"Point"}
}