{
  "type": "Feature",
  "properties": {
    "addr:full":"1202 Elmore St Columbia SC 29203",
    "addr:housenumber":"1202",
    "addr:postcode":"29203",
    "addr:street":"Elmore St",
    "iso:country":"US",
    "sg:address":"1202 Elmore St",
    "sg:city":"Columbia",
    "sg:classifiers":[
        {
            "category":"Shopping",
            "subcategory":"Beauty & Cosmetics",
            "type":"Retail Goods"
        }
    ],
    "sg:phone":"+1 803 256 9304",
    "sg:postcode":"29203",
    "sg:province":"SC",
    "sg:tags":[
        "merchandise"
    ],
    "wof:name":"Tucker & Tucker LLC",
    "wof:placetype":"venue"
},
  "geometry": {"coordinates":[-81.039744,34.035173],"type":"Point"}
}