{
  "type": "Feature",
  "properties": {
    "iso:country":"US",
    "sg:address":"191 Halton Rd",
    "sg:city":"Greenville",
    "sg:classifiers":[
        {
            "category":"Home & Garden",
            "subcategory":"Furniture",
            "type":"Retail Goods"
        }
    ],
    "sg:phone":"+1 864 987 0555",
    "sg:postcode":"29607",
    "sg:province":"SC",
    "sg:tags":[
        "mattress"
    ],
    "wof:name":"Relax The Back Store",
    "wof:placetype":"venue"
},
  "geometry": {"coordinates":[-82.32818,34.844035],"type":"Point"}
}