{
  "type": "Feature",
  "properties": {
    "iso:country":"US",
    "sg:address":"1550 Clark Sound Cir",
    "sg:city":"Charleston",
    "sg:classifiers":[
        {
            "category":"Freight",
            "type":"Transportation"
        }
    ],
    "sg:phone":"+1 843 324 7376",
    "sg:postcode":"29412",
    "sg:province":"SC",
    "sg:tags":[
        "operator",
        "local",
        "trucking"
    ],
    "wof:name":"Store To Shore Inc",
    "wof:placetype":"venue"
},
  "geometry": {"coordinates":[-79.93449200000001,32.729315],"type":"Point"}
}