{
  "type": "Feature",
  "properties": {
    "iso:country":"US",
    "sg:address":"3284 E Gap Creek Rd",
    "sg:city":"Greer",
    "sg:classifiers":[
        {
            "category":"Home & Garden",
            "subcategory":"Garden Supply",
            "type":"Retail Goods"
        }
    ],
    "sg:phone":"+1 864 848 0174",
    "sg:postcode":"29651",
    "sg:province":"SC",
    "sg:tags":[
        "farm",
        "equipment",
        "lawn"
    ],
    "wof:name":"McAbbee Tractor & Turf Eqp",
    "wof:placetype":"venue"
},
  "geometry": {"coordinates":[-82.242092,34.989465],"type":"Point"}
}