{
  "type": "Feature",
  "properties": {
    "iso:country":"US",
    "sg:address":"3912 Rivers Ave",
    "sg:city":"North Charleston",
    "sg:classifiers":[
        {
            "category":"Shopping",
            "subcategory":"Used Merchandise",
            "type":"Retail Goods"
        }
    ],
    "sg:phone":"+1 843 744 0011",
    "sg:postcode":"29405",
    "sg:province":"SC",
    "wof:name":"Big Value Furniture",
    "wof:placetype":"venue"
},
  "geometry": {"coordinates":[-79.986881,32.862825],"type":"Point"}
}