{
  "type": "Feature",
  "properties": {
    "addr:full":"712 Chesterfield Ct Cheraw SC 29520",
    "addr:housenumber":"712",
    "addr:postcode":"29520",
    "addr:street":"Chesterfield Ct",
    "iso:country":"US",
    "sg:address":"712 Chesterfield Ct",
    "sg:city":"Cheraw",
    "sg:classifiers":[
        {
            "category":"Real Estate",
            "subcategory":"Real Estate Operator",
            "type":"Services"
        }
    ],
    "sg:phone":"+1 843 537 0808",
    "sg:postcode":"29520",
    "sg:province":"SC",
    "sg:tags":[
        "building",
        "apartment"
    ],
    "wof:name":"Chesterfield Courts Apartments",
    "wof:placetype":"venue"
},
  "geometry": {"coordinates":[-79.914709,34.704202],"type":"Point"}
}