{
  "type": "Feature",
  "properties": {
    "addr:full":"4883 E US Hwy 501 Myrtle Beach SC 29579",
    "addr:housenumber":"4883",
    "addr:postcode":"29579",
    "addr:street":"E Us Hwy 501",
    "iso:country":"US",
    "sg:address":"4883 E US Hwy 501",
    "sg:city":"Myrtle Beach",
    "sg:classifiers":[
        {
            "category":"Restaurant",
            "type":"Food & Drink"
        }
    ],
    "sg:phone":"+1 843 236 8815",
    "sg:postcode":"29579",
    "sg:province":"SC",
    "sg:tags":[
        "shop",
        "coffee"
    ],
    "wof:name":"Dunkin Donuts",
    "wof:placetype":"venue"
},
  "geometry": {"coordinates":[-78.977267,33.768934],"type":"Point"}
}