{
  "type": "Feature",
  "properties": {
    "iso:country":"US",
    "sg:address":"49 Elizabeth St",
    "sg:city":"Charleston",
    "sg:classifiers":[
        {
            "category":"Real Estate",
            "subcategory":"Real Estate Agent",
            "type":"Services"
        }
    ],
    "sg:phone":"+1 843 722 1585",
    "sg:postcode":"29403",
    "sg:province":"SC",
    "sg:tags":[
        "management"
    ],
    "wof:name":"Clement/Reinier Properties",
    "wof:placetype":"venue"
},
  "geometry": {"coordinates":[-79.934074,32.789899],"type":"Point"}
}