{
  "type": "Feature",
  "properties": {
    "iso:country":"US",
    "sg:address":"2711 Middleburg Dr",
    "sg:city":"Columbia",
    "sg:classifiers":[
        {
            "category":"Real Estate",
            "subcategory":"Real Estate Agent",
            "type":"Services"
        }
    ],
    "sg:phone":"+1 803 799 2500",
    "sg:postcode":"29204",
    "sg:province":"SC",
    "sg:tags":[
        "appraiser"
    ],
    "wof:name":"Parker Associates",
    "wof:placetype":"venue"
},
  "geometry": {"coordinates":[-81.001867,34.01584],"type":"Point"}
}