{
  "type": "Feature",
  "properties": {
    "iso:country":"US",
    "sg:address":"12131 Asheville Hwy",
    "sg:city":"Inman",
    "sg:classifiers":[
        {
            "category":"Banks & Credit Unions",
            "subcategory":"Investment Brokerage",
            "type":"Services"
        }
    ],
    "sg:phone":"+1 864 472 3544",
    "sg:postcode":"29349",
    "sg:province":"SC",
    "sg:tags":[
        "security"
    ],
    "wof:name":"A G Edwards & Sons Inc",
    "wof:placetype":"venue"
},
  "geometry": {"coordinates":[-82.090971,35.042348],"type":"Point"}
}