{
  "type": "Feature",
  "properties": {
    "iso:country":"US",
    "sg:address":"1017 E Middleton St",
    "sg:city":"Florence",
    "sg:classifiers":[
        {
            "category":"Social Services",
            "subcategory":"Child Care",
            "type":"Services"
        }
    ],
    "sg:phone":"+1 843 317 9918",
    "sg:postcode":"29506",
    "sg:province":"SC",
    "wof:name":"E & W Hines Daycare",
    "wof:placetype":"venue"
},
  "geometry": {"coordinates":[-79.744491,34.20802],"type":"Point"}
}