{
  "type": "Feature",
  "properties": {
    "iso:country":"US",
    "sg:address":"360 Riverchase Way",
    "sg:city":"Lexington",
    "sg:classifiers":[
        {
            "category":"Building & Trades",
            "subcategory":"Construction",
            "type":"Services"
        }
    ],
    "sg:phone":"+1 803 796 9695",
    "sg:postcode":"29072",
    "sg:province":"SC",
    "sg:tags":[
        "waterproofing",
        "contractor"
    ],
    "sg:website":"www.watertightsystems.com",
    "wof:name":"Watertight Systems Inc",
    "wof:placetype":"venue"
},
  "geometry": {"coordinates":[-81.133714,34.022753],"type":"Point"}
}