{
  "type": "Feature",
  "properties": {
    "iso:country":"US",
    "sg:address":"103 Hush Hole Rd",
    "sg:city":"Travelers Rest",
    "sg:classifiers":[
        {
            "category":"Wholesale",
            "subcategory":"Machinery & Supplies",
            "type":"Manufacturing & Wholesale Goods"
        }
    ],
    "sg:phone":"+1 864 609 0525",
    "sg:postcode":"29690",
    "sg:province":"SC",
    "sg:tags":[
        "packaging",
        "industrial"
    ],
    "wof:name":"Integrated Package Systems",
    "wof:placetype":"venue"
},
  "geometry": {"coordinates":[-82.439133,35.11162],"type":"Point"}
}