{
  "type": "Feature",
  "properties": {
    "iso:country":"US",
    "sg:address":"27 S Mill St",
    "sg:city":"Manning",
    "sg:classifiers":[
        {
            "category":"Professional",
            "subcategory":"Accounting & Tax Preparation",
            "type":"Services"
        }
    ],
    "sg:phone":"+1 803 435 5466",
    "sg:postcode":"29102",
    "sg:province":"SC",
    "sg:tags":[
        "consultant"
    ],
    "wof:name":"Liz's Income Tax Svc",
    "wof:placetype":"venue"
},
  "geometry": {"coordinates":[-80.212012,33.694908],"type":"Point"}
}