{
  "type": "Feature",
  "properties": {
    "iso:country":"US",
    "sg:address":"105 Charles St",
    "sg:city":"Mullins",
    "sg:classifiers":[
        {
            "category":"Education",
            "subcategory":"School",
            "type":"Public Place"
        }
    ],
    "sg:phone":"+1 843 464 3750",
    "sg:postcode":"29574",
    "sg:province":"SC",
    "wof:name":"North Mullins Primary School",
    "wof:placetype":"venue"
},
  "geometry": {"coordinates":[-79.257352,34.219529],"type":"Point"}
}