{
  "type": "Feature",
  "properties": {
    "iso:country":"US",
    "sg:address":"2 S Congress St",
    "sg:city":"York",
    "sg:classifiers":[
        {
            "category":"Government",
            "subcategory":"Office",
            "type":"Public Place"
        }
    ],
    "sg:phone":"+1 803 684 8576",
    "sg:postcode":"29745",
    "sg:province":"SC",
    "wof:name":"York County Coroner",
    "wof:placetype":"venue"
},
  "geometry": {"coordinates":[-81.241951,34.994061],"type":"Point"}
}