{
  "type": "Feature",
  "properties": {
    "iso:country":"US",
    "sg:address":"106 W Main St",
    "sg:city":"Williamston",
    "sg:classifiers":[
        {
            "category":"Manufacturing",
            "subcategory":"Printing",
            "type":"Manufacturing & Wholesale Goods"
        }
    ],
    "sg:phone":"+1 864 847 7361",
    "sg:postcode":"29697",
    "sg:province":"SC",
    "sg:tags":[
        "newspaper"
    ],
    "sg:website":"www.thejournalonline.com",
    "wof:name":"Journal",
    "wof:placetype":"venue"
},
  "geometry": {"coordinates":[-82.479417,34.618219],"type":"Point"}
}