{
  "type": "Feature",
  "properties": {
    "addr:full":"511 S Main St Mullins SC 29574",
    "addr:housenumber":"511",
    "addr:postcode":"29574",
    "addr:street":"S Main St",
    "iso:country":"US",
    "sg:address":"511 S Main St",
    "sg:city":"Mullins",
    "sg:classifiers":[
        {
            "category":"Health Services",
            "subcategory":"Doctor",
            "type":"Services"
        }
    ],
    "sg:phone":"+1 843 464 8244",
    "sg:postcode":"29574",
    "sg:province":"SC",
    "sg:tags":[
        "physician",
        "surgeon"
    ],
    "wof:name":"Thourani & Dawani",
    "wof:placetype":"venue"
},
  "geometry": {"coordinates":[-79.253112,34.200113],"type":"Point"}
}