{
  "type": "Feature",
  "properties": {
    "addr:full":"2506 River Rd Piedmont SC 29673",
    "addr:housenumber":"2506",
    "addr:postcode":"29673",
    "addr:street":"River Rd",
    "iso:country":"US",
    "sg:address":"2506 River Rd",
    "sg:city":"Piedmont",
    "sg:classifiers":[
        {
            "category":"Shopping",
            "subcategory":"Bicycles & Sporting Goods",
            "type":"Retail Goods"
        }
    ],
    "sg:phone":"+1 864 220 1443",
    "sg:postcode":"29673",
    "sg:province":"SC",
    "sg:tags":[
        "equipment",
        "playground"
    ],
    "wof:name":"Yards Of Fun",
    "wof:placetype":"venue"
},
  "geometry": {"coordinates":[-82.474981,34.761793],"type":"Point"}
}