{
  "type": "Feature",
  "properties": {
    "iso:country":"US",
    "sg:address":"215 E Bay St",
    "sg:city":"Charleston",
    "sg:classifiers":[
        {
            "category":"Shopping",
            "subcategory":"Computers & Home Electronics",
            "type":"Retail Goods"
        }
    ],
    "sg:phone":"+1 843 853 6999",
    "sg:postcode":"29401",
    "sg:province":"SC",
    "sg:tags":[
        "software"
    ],
    "sg:website":"www.carepoint.com",
    "wof:name":"Carepoint",
    "wof:placetype":"venue"
},
  "geometry": {"coordinates":[-79.927235,32.780558],"type":"Point"}
}