{
  "type": "Feature",
  "properties": {
    "iso:country":"US",
    "sg:address":"101 E Washington St",
    "sg:city":"Greenville",
    "sg:classifiers":[
        {
            "category":"Banks & Credit Unions",
            "subcategory":"Investment Brokerage",
            "type":"Services"
        }
    ],
    "sg:phone":"+1 864 370 0737",
    "sg:postcode":"29601",
    "sg:province":"SC",
    "sg:tags":[
        "advisory",
        "financial"
    ],
    "wof:name":"Colonial Trust Co",
    "wof:placetype":"venue"
},
  "geometry": {"coordinates":[-82.397324,34.850235],"type":"Point"}
}