{
  "type": "Feature",
  "properties": {
    "iso:country":"US",
    "sg:address":"208 Terrace St",
    "sg:city":"Kingstree",
    "sg:classifiers":[
        {
            "category":"Real Estate",
            "subcategory":"Real Estate Operator",
            "type":"Services"
        }
    ],
    "sg:phone":"+1 843 355 9495",
    "sg:postcode":"29556",
    "sg:province":"SC",
    "sg:tags":[
        "property",
        "lessor"
    ],
    "wof:name":"W Gourdin",
    "wof:placetype":"venue"
},
  "geometry": {"coordinates":[-79.84134299999999,33.675451],"type":"Point"}
}