{
  "type": "Feature",
  "properties": {
    "iso:country":"US",
    "sg:address":"2545 Sharpes Hill Rd",
    "sg:city":"Gaston",
    "sg:classifiers":[
        {
            "category":"Real Estate",
            "subcategory":"Developer",
            "type":"Services"
        }
    ],
    "sg:phone":"+1 803 755 9293",
    "sg:postcode":"29053",
    "sg:province":"SC",
    "wof:name":"Sightler Development",
    "wof:placetype":"venue"
},
  "geometry": {"coordinates":[-81.15692300000001,33.800176],"type":"Point"}
}