{
  "type": "Feature",
  "properties": {
    "iso:country":"US",
    "sg:address":"3455 Whitmire Hwy",
    "sg:city":"Kinards",
    "sg:classifiers":[
        {
            "category":"Retail",
            "subcategory":"Auto Repair",
            "type":"Services"
        }
    ],
    "sg:phone":"+1 864 697 6231",
    "sg:postcode":"29355",
    "sg:province":"SC",
    "sg:tags":[
        "wrecker"
    ],
    "wof:name":"Shady Grove Svc Ctr",
    "wof:placetype":"venue"
},
  "geometry": {"coordinates":[-81.77264099999999,34.426933],"type":"Point"}
}