{
  "type": "Feature",
  "properties": {
    "iso:country":"US",
    "sg:address":"103 Chatsworth Rd",
    "sg:city":"Greer",
    "sg:classifiers":[
        {
            "category":"Autos & Motor Vehicles",
            "subcategory":"Fuel & Gas Station",
            "type":"Retail Goods"
        }
    ],
    "sg:phone":"+1 864 288 2440",
    "sg:postcode":"29651",
    "sg:province":"SC",
    "sg:tags":[
        "station",
        "gasoline"
    ],
    "wof:name":"Five Point Owners Assoc",
    "wof:placetype":"venue"
},
  "geometry": {"coordinates":[-82.224829,34.843816],"type":"Point"}
}