{
  "type": "Feature",
  "properties": {
    "addr:full":"3 Park Ave Brevard SC 28712",
    "addr:housenumber":"3",
    "addr:postcode":"28712",
    "addr:street":"Park Ave",
    "iso:country":"US",
    "sg:address":"3 Park Ave",
    "sg:city":"Brevard",
    "sg:classifiers":[
        {
            "category":"Health Services",
            "subcategory":"Doctor",
            "type":"Services"
        }
    ],
    "sg:phone":"+1 828 884 3440",
    "sg:postcode":"28712",
    "sg:province":"SC",
    "sg:tags":[
        "physician",
        "surgeon"
    ],
    "wof:name":"Hendersonville Pediatrics",
    "wof:placetype":"venue"
},
  "geometry": {"coordinates":[-82.727671,35.229516],"type":"Point"}
}