{
  "type": "Feature",
  "properties": {
    "addr:full":"207 Richland Ave E Aiken SC 29801",
    "addr:housenumber":"207",
    "addr:postcode":"29801",
    "addr:street":"Richland Ave E",
    "iso:country":"US",
    "sg:address":"207 Richland Ave E",
    "sg:city":"Aiken",
    "sg:classifiers":[
        {
            "category":"Retail",
            "subcategory":"Auto Repair",
            "type":"Services"
        }
    ],
    "sg:phone":"+1 803 648 8465",
    "sg:postcode":"29801",
    "sg:province":"SC",
    "sg:tags":[
        "muffler",
        "exhaust",
        "system"
    ],
    "wof:name":"Aiken Muffler & Hitch",
    "wof:placetype":"venue"
},
  "geometry": {"coordinates":[-81.716792,33.559588],"type":"Point"}
}