{
  "type": "Feature",
  "properties": {
    "iso:country":"US",
    "sg:address":"1 Dillon Rd",
    "sg:city":"Hilton Head Isle",
    "sg:classifiers":[
        {
            "category":"Travel",
            "subcategory":"Hotels & Motels",
            "type":"Entertainment"
        }
    ],
    "sg:phone":"+1 843 681 7900",
    "sg:postcode":"29926",
    "sg:province":"SC",
    "sg:website":"www.hampton-inn.net",
    "wof:name":"Hampton Inn",
    "wof:placetype":"venue"
},
  "geometry": {"coordinates":[-80.694397,32.221255],"type":"Point"}
}