{
  "type": "Feature",
  "properties": {
    "iso:country":"US",
    "sg:address":"124 NE Main St",
    "sg:city":"Simpsonville",
    "sg:classifiers":[
        {
            "category":"Banks & Credit Unions",
            "subcategory":"Bank",
            "type":"Services"
        }
    ],
    "sg:phone":"+1 864 963 5747",
    "sg:postcode":"29681",
    "sg:province":"SC",
    "wof:name":"Central Carolina Bank",
    "wof:placetype":"venue"
},
  "geometry": {"coordinates":[-82.255321,34.738004],"type":"Point"}
}