{
  "type": "Feature",
  "properties": {
    "addr:full":"21 Gamecock Ave Charleston SC 29407",
    "addr:housenumber":"21",
    "addr:postcode":"29407",
    "addr:street":"Gamecock Ave",
    "iso:country":"US",
    "sg:address":"21 Gamecock Ave",
    "sg:city":"Charleston",
    "sg:classifiers":[
        {
            "category":"Real Estate",
            "subcategory":"Real Estate Agent",
            "type":"Services"
        }
    ],
    "sg:phone":"+1 843 766 7500",
    "sg:postcode":"29407",
    "sg:province":"SC",
    "sg:tags":[
        "appraiser"
    ],
    "sg:website":"www.sassherrin.com",
    "wof:name":"Sass Herrin & Assoc",
    "wof:placetype":"venue"
},
  "geometry": {"coordinates":[-79.993548,32.820345],"type":"Point"}
}