{
  "type": "Feature",
  "properties": {
    "iso:country":"US",
    "sg:address":"2305 US Hwy 378",
    "sg:city":"Conway",
    "sg:classifiers":[
        {
            "category":"Manufacturing",
            "subcategory":"Metals",
            "type":"Manufacturing & Wholesale Goods"
        },
        {
            "category":"Professional",
            "type":"Services"
        }
    ],
    "sg:phone":"+1 843 397 7788",
    "sg:postcode":"29527",
    "sg:province":"SC",
    "sg:tags":[
        "tool",
        "establishment",
        "mfg"
    ],
    "wof:name":"Key Knife Inc",
    "wof:placetype":"venue"
},
  "geometry": {"coordinates":[-79.09082100000001,33.84309],"type":"Point"}
}