{
  "type": "Feature",
  "properties": {
    "iso:country":"US",
    "sg:address":"523 N Guignard Dr",
    "sg:city":"Sumter",
    "sg:classifiers":[
        {
            "category":"Restaurant",
            "type":"Food & Drink"
        }
    ],
    "sg:menulink":"http://www.allmenus.com/sc/sumter/292488-duncan-dogs/menu/",
    "sg:phone":"+1 803 774 3647",
    "sg:postcode":"29150",
    "sg:province":"SC",
    "sg:tags":[
        "hot",
        "dog"
    ],
    "wof:name":"Duncan Dogs",
    "wof:placetype":"venue"
},
  "geometry": {"coordinates":[-80.370321,33.934569],"type":"Point"}
}