{
  "type": "Feature",
  "properties": {
    "iso:country":"US",
    "sg:address":"1011 E White St",
    "sg:city":"Rock Hill",
    "sg:classifiers":[
        {
            "category":"Restaurant",
            "type":"Food & Drink"
        }
    ],
    "sg:menulink":"http://www.allmenus.com/sc/rock-hill/53242-dominos-pizza/menu/",
    "sg:phone":"+1 803 324 3111",
    "sg:postcode":"29730",
    "sg:province":"SC",
    "sg:tags":[
        "american",
        "wing",
        "pizza"
    ],
    "wof:name":"Domino's Pizza",
    "wof:placetype":"venue"
},
  "geometry": {"coordinates":[-81.00998199999999,34.919189],"type":"Point"}
}