{
  "type": "Feature",
  "properties": {
    "iso:country":"US",
    "sg:address":"10216 Broad River Rd",
    "sg:city":"Irmo",
    "sg:classifiers":[
        {
            "category":"Retail",
            "subcategory":"Veterinary Services",
            "type":"Services"
        }
    ],
    "sg:phone":"+1 803 781 3890",
    "sg:postcode":"29063",
    "sg:province":"SC",
    "wof:name":"Mundell Jeffrey L Dvm",
    "wof:placetype":"venue"
},
  "geometry": {"coordinates":[-81.19775,34.115118],"type":"Point"}
}