{
  "type": "Feature",
  "properties": {
    "addr:full":"44 Groce Rd Lyman SC 29365",
    "addr:housenumber":"44",
    "addr:postcode":"29365",
    "addr:street":"Groce Rd",
    "iso:country":"US",
    "sg:address":"44 Groce Rd",
    "sg:city":"Lyman",
    "sg:classifiers":[
        {
            "category":"Home & Garden",
            "subcategory":"Household Appliances",
            "type":"Retail Goods"
        }
    ],
    "sg:phone":"+1 864 949 8693",
    "sg:postcode":"29365",
    "sg:province":"SC",
    "sg:tags":[
        "cleaners",
        "vacuum"
    ],
    "wof:name":"Rainbow Of Lyman",
    "wof:placetype":"venue"
},
  "geometry": {"coordinates":[-82.12459,34.953284],"type":"Point"}
}