{
  "type": "Feature",
  "properties": {
    "addr:full":"116 King Charles Cir Summerville SC 29485",
    "addr:housenumber":"116",
    "addr:postcode":"29485",
    "addr:street":"King Charles Cir",
    "iso:country":"US",
    "sg:address":"116 King Charles Cir",
    "sg:city":"Summerville",
    "sg:classifiers":[
        {
            "category":"Freight",
            "type":"Transportation"
        }
    ],
    "sg:phone":"+1 843 871 5515",
    "sg:postcode":"29485",
    "sg:province":"SC",
    "sg:tags":[
        "government",
        "contractor"
    ],
    "wof:name":"Southern Terminal Services LLC",
    "wof:placetype":"venue"
},
  "geometry": {"coordinates":[-80.19981199999999,32.988101],"type":"Point"}
}