{
  "type": "Feature",
  "properties": {
    "iso:country":"US",
    "sg:address":"4033 State Hwy 86",
    "sg:city":"Easley",
    "sg:classifiers":[
        {
            "category":"Wholesale",
            "subcategory":"Construction Materials",
            "type":"Manufacturing & Wholesale Goods"
        }
    ],
    "sg:phone":"+1 864 855 0484",
    "sg:postcode":"29642",
    "sg:province":"SC",
    "sg:tags":[
        "insulation",
        "thermal"
    ],
    "wof:name":"T & R Sales Inc",
    "wof:placetype":"venue"
},
  "geometry": {"coordinates":[-82.549048,34.739895],"type":"Point"}
}