{
  "type": "Feature",
  "properties": {
    "iso:country":"US",
    "sg:address":"1300 Pridgen Rd",
    "sg:city":"Myrtle Beach",
    "sg:classifiers":[
        {
            "category":"Building & Trades",
            "subcategory":"Construction",
            "type":"Services"
        }
    ],
    "sg:phone":"+1 843 626 7550",
    "sg:postcode":"29577",
    "sg:province":"SC",
    "sg:tags":[
        "house"
    ],
    "wof:name":"Pd Builders",
    "wof:placetype":"venue"
},
  "geometry": {"coordinates":[-78.907501,33.682821],"type":"Point"}
}