{
  "type": "Feature",
  "properties": {
    "iso:country":"US",
    "sg:address":"1434 N Limestone St",
    "sg:city":"Gaffney",
    "sg:classifiers":[
        {
            "category":"Government",
            "subcategory":"Office",
            "type":"Public Place"
        }
    ],
    "sg:phone":"+1 864 487 2704",
    "sg:postcode":"29340",
    "sg:province":"SC",
    "sg:tags":[
        "county",
        "resource"
    ],
    "wof:name":"Cherokee Social Svc Dept",
    "wof:placetype":"venue"
},
  "geometry": {"coordinates":[-81.636859,35.088812],"type":"Point"}
}