{
  "type": "Feature",
  "properties": {
    "iso:country":"US",
    "sg:address":"4185 Columbia Hwy N",
    "sg:city":"Ridge Spring",
    "sg:classifiers":[
        {
            "category":"Organizations",
            "subcategory":"Religious Organization",
            "type":"Services"
        }
    ],
    "sg:phone":"+1 803 685 7628",
    "sg:postcode":"29129",
    "sg:province":"SC",
    "sg:tags":[
        "church"
    ],
    "wof:name":"Jersulem Baptist Church",
    "wof:placetype":"venue"
},
  "geometry": {"coordinates":[-81.64204100000001,33.762647],"type":"Point"}
}