{
  "type": "Feature",
  "properties": {
    "iso:country":"US",
    "sg:address":"930 Gervais St",
    "sg:city":"Columbia",
    "sg:classifiers":[
        {
            "category":"Arts & Performance",
            "subcategory":"Art Gallery",
            "type":"Entertainment"
        },
        {
            "category":"Restaurant",
            "type":"Food & Drink"
        }
    ],
    "sg:phone":"+1 803 779 9599",
    "sg:postcode":"29201",
    "sg:province":"SC",
    "wof:name":"Nonnah's",
    "wof:placetype":"venue"
},
  "geometry": {"coordinates":[-81.036903,34.000099],"type":"Point"}
}