{
  "type": "Feature",
  "properties": {
    "addr:full":"826 Assembly St Columbia SC 29202",
    "addr:housenumber":"826",
    "addr:postcode":"29202",
    "addr:street":"Assembly St",
    "iso:country":"US",
    "sg:address":"826 Assembly St",
    "sg:city":"Columbia",
    "sg:classifiers":[
        {
            "category":"Professional",
            "subcategory":"Management & Consulting",
            "type":"Services"
        }
    ],
    "sg:phone":"+1 843 661 5086",
    "sg:postcode":"29202",
    "sg:province":"SC",
    "sg:tags":[
        "legislative",
        "consultant",
        "analyst"
    ],
    "wof:name":"Mc Millan & Assoc",
    "wof:placetype":"venue"
},
  "geometry": {"coordinates":[-81.03306600000001,33.996321],"type":"Point"}
}