{
  "type": "Feature",
  "properties": {
    "iso:country":"US",
    "sg:address":"146 Factory Rd",
    "sg:city":"Eutawville",
    "sg:classifiers":[
        {
            "category":"Building & Trades",
            "subcategory":"Construction",
            "type":"Services"
        }
    ],
    "sg:phone":"+1 803 492 5050",
    "sg:postcode":"29048",
    "sg:province":"SC",
    "sg:tags":[
        "general",
        "contractor"
    ],
    "wof:name":"CMS Inc",
    "wof:placetype":"venue"
},
  "geometry": {"coordinates":[-80.348697,33.394782],"type":"Point"}
}