{
  "type": "Feature",
  "properties": {
    "iso:country":"US",
    "sg:address":"4628 Spruill Ave",
    "sg:city":"North Charleston",
    "sg:classifiers":[
        {
            "category":"Bars & Pubs",
            "type":"Food & Drink"
        }
    ],
    "sg:phone":"+1 843 554 5959",
    "sg:postcode":"29405",
    "sg:province":"SC",
    "sg:tags":[
        "club",
        "night"
    ],
    "sg:website":"www.dejavuii.com",
    "wof:name":"Deja Vu II",
    "wof:placetype":"venue"
},
  "geometry": {"coordinates":[-79.980092,32.878883],"type":"Point"}
}