{
  "type": "Feature",
  "properties": {
    "iso:country":"US",
    "sg:address":"2420 Whitehall Rd",
    "sg:city":"Anderson",
    "sg:classifiers":[
        {
            "category":"Autos & Motor Vehicles",
            "subcategory":"Automobile Sales",
            "type":"Retail Goods"
        }
    ],
    "sg:phone":"+1 864 226 3780",
    "sg:postcode":"29625",
    "sg:province":"SC",
    "sg:tags":[
        "car",
        "dealer"
    ],
    "wof:name":"Mc Curley Auto Sales",
    "wof:placetype":"venue"
},
  "geometry": {"coordinates":[-82.730794,34.52045],"type":"Point"}
}