{
  "type": "Feature",
  "properties": {
    "iso:country":"US",
    "sg:address":"305 E McIntyre St",
    "sg:city":"Mullins",
    "sg:classifiers":[
        {
            "category":"Restaurant",
            "type":"Food & Drink"
        }
    ],
    "sg:phone":"+1 843 464 4071",
    "sg:postcode":"29574",
    "sg:province":"SC",
    "wof:name":"Ann's Diner & Seafood",
    "wof:placetype":"venue"
},
  "geometry": {"coordinates":[-79.243165,34.201427],"type":"Point"}
}