{
  "type": "Feature",
  "properties": {
    "iso:country":"US",
    "sg:address":"1311 Parkwood Dr",
    "sg:city":"Florence",
    "sg:classifiers":[
        {
            "category":"Education",
            "subcategory":"Special Training",
            "type":"Public Place"
        }
    ],
    "sg:phone":"+1 843 662 3051",
    "sg:postcode":"29505",
    "sg:province":"SC",
    "sg:tags":[
        "instruction",
        "music"
    ],
    "wof:name":"Mapes Voice Studio",
    "wof:placetype":"venue"
},
  "geometry": {"coordinates":[-79.750108,34.143106],"type":"Point"}
}