{
  "type": "Feature",
  "properties": {
    "addr:full":"818 E Main St Spartanburg SC 29302",
    "addr:housenumber":"818",
    "addr:postcode":"29302",
    "addr:street":"E Main St",
    "iso:country":"US",
    "sg:address":"818 E Main St",
    "sg:city":"Spartanburg",
    "sg:classifiers":[
        {
            "category":"Organizations",
            "subcategory":"Membership Organization",
            "type":"Services"
        }
    ],
    "sg:phone":"+1 864 583 2766",
    "sg:postcode":"29302",
    "sg:province":"SC",
    "sg:tags":[
        "travel",
        "agency"
    ],
    "wof:name":"Triple A Travel Agcy & Mtr CLB",
    "wof:placetype":"venue"
},
  "geometry": {"coordinates":[-81.910569,34.957842],"type":"Point"}
}