{
  "type": "Feature",
  "properties": {
    "iso:country":"US",
    "sg:address":"4810 N Kings Hwy",
    "sg:city":"Myrtle Beach",
    "sg:classifiers":[
        {
            "category":"Health Services",
            "subcategory":"Clinic",
            "type":"Services"
        }
    ],
    "sg:phone":"+1 843 692 9243",
    "sg:postcode":"29577",
    "sg:province":"SC",
    "wof:name":"Myrtle Beach Health Ctr",
    "wof:placetype":"venue"
},
  "geometry": {"coordinates":[-78.84595400000001,33.724126],"type":"Point"}
}