{
  "type": "Feature",
  "properties": {
    "addr:full":"801 N Main St Summerville SC 29483",
    "addr:housenumber":"801",
    "addr:postcode":"29483",
    "addr:street":"N Main St",
    "iso:country":"US",
    "sg:address":"801 N Main St",
    "sg:city":"Summerville",
    "sg:classifiers":[
        {
            "category":"Banks & Credit Unions",
            "subcategory":"Bank",
            "type":"Services"
        }
    ],
    "sg:phone":"+1 843 832 8685",
    "sg:postcode":"29483",
    "sg:province":"SC",
    "sg:tags":[
        "cashing",
        "check"
    ],
    "wof:name":"Advance America",
    "wof:placetype":"venue"
},
  "geometry": {"coordinates":[-80.16848,33.028807],"type":"Point"}
}