{
  "type": "Feature",
  "properties": {
    "iso:country":"US",
    "sg:address":"1310 Azalea Ct",
    "sg:city":"Myrtle Beach",
    "sg:classifiers":[
        {
            "category":"Real Estate",
            "subcategory":"Real Estate Agent",
            "type":"Services"
        }
    ],
    "sg:phone":"+1 843 946 9292",
    "sg:postcode":"29577",
    "sg:province":"SC",
    "sg:website":"www.carolinaseacoast.com",
    "wof:name":"Carolina Sea Coast Realty",
    "wof:placetype":"venue"
},
  "geometry": {"coordinates":[-78.864215,33.730752],"type":"Point"}
}