{
  "type": "Feature",
  "properties": {
    "addr:full":"1208 Bush River Rd Columbia SC 29210",
    "addr:housenumber":"1208",
    "addr:postcode":"29210",
    "addr:street":"Bush River Rd",
    "iso:country":"US",
    "sg:address":"1208 Bush River Rd",
    "sg:city":"Columbia",
    "sg:classifiers":[
        {
            "category":"Building & Trades",
            "subcategory":"Construction",
            "type":"Services"
        }
    ],
    "sg:phone":"+1 803 750 4806",
    "sg:postcode":"29210",
    "sg:province":"SC",
    "sg:tags":[
        "painter"
    ],
    "wof:name":"Congaree Painting & Small Rprs",
    "wof:placetype":"venue"
},
  "geometry": {"coordinates":[-81.104366,34.030557],"type":"Point"}
}