{
  "type": "Feature",
  "properties": {
    "iso:country":"US",
    "sg:address":"109 W Perry Rd",
    "sg:city":"Myrtle Beach",
    "sg:classifiers":[
        {
            "category":"Social Services",
            "subcategory":"Child Care",
            "type":"Services"
        }
    ],
    "sg:phone":"+1 843 903 0770",
    "sg:postcode":"29579",
    "sg:province":"SC",
    "sg:website":"www.gatewayacademy.com",
    "wof:name":"Gateway Academy",
    "wof:placetype":"venue"
},
  "geometry": {"coordinates":[-78.96740699999999,33.757422],"type":"Point"}
}