{
  "type": "Feature",
  "properties": {
    "iso:country":"US",
    "sg:address":"2160 W Evans St",
    "sg:city":"Florence",
    "sg:classifiers":[
        {
            "category":"Home & Garden",
            "subcategory":"Furniture",
            "type":"Retail Goods"
        }
    ],
    "sg:phone":"+1 843 661 7667",
    "sg:postcode":"29501",
    "sg:province":"SC",
    "sg:tags":[
        "mattress"
    ],
    "wof:name":"Americas Mattress",
    "wof:placetype":"venue"
},
  "geometry": {"coordinates":[-79.80985,34.190445],"type":"Point"}
}