{
  "type": "Feature",
  "properties": {
    "iso:country":"US",
    "sg:address":"104 Mauldin Rd",
    "sg:city":"Greenville",
    "sg:classifiers":[
        {
            "category":"Personal",
            "subcategory":"Beauty Salon",
            "type":"Services"
        }
    ],
    "sg:phone":"+1 864 277 7411",
    "sg:postcode":"29605",
    "sg:province":"SC",
    "sg:tags":[
        "manicuring"
    ],
    "wof:name":"Celadon Nail Spa",
    "wof:placetype":"venue"
},
  "geometry": {"coordinates":[-82.379144,34.806919],"type":"Point"}
}