{
  "type": "Feature",
  "properties": {
    "iso:country":"US",
    "sg:address":"902 N Pleasantburg Dr",
    "sg:city":"Greenville",
    "sg:classifiers":[
        {
            "category":"Wholesale",
            "subcategory":"Stationery",
            "type":"Manufacturing & Wholesale Goods"
        }
    ],
    "sg:phone":"+1 864 235 7939",
    "sg:postcode":"29607",
    "sg:province":"SC",
    "sg:tags":[
        "business",
        "form",
        "system"
    ],
    "wof:name":"Allied-Western Inc",
    "wof:placetype":"venue"
},
  "geometry": {"coordinates":[-82.358153,34.868694],"type":"Point"}
}