{
  "type": "Feature",
  "properties": {
    "iso:country":"US",
    "sg:address":"147 State St",
    "sg:city":"West Columbia",
    "sg:classifiers":[
        {
            "category":"Professional",
            "subcategory":"Lawyer & Legal Services",
            "type":"Services"
        }
    ],
    "sg:phone":"+1 803 794 5508",
    "sg:postcode":"29169",
    "sg:province":"SC",
    "sg:tags":[
        "notary"
    ],
    "wof:name":"Huggins Tax Service",
    "wof:placetype":"venue"
},
  "geometry": {"coordinates":[-81.055702,33.993198],"type":"Point"}
}