{
  "type": "Feature",
  "properties": {
    "addr:full":"1111 Harry Byrd Hwy Darlington SC 29532",
    "addr:housenumber":"1111",
    "addr:postcode":"29532",
    "addr:street":"Harry Byrd Hwy",
    "iso:country":"US",
    "sg:address":"1111 Harry Byrd Hwy",
    "sg:city":"Darlington",
    "sg:classifiers":[
        {
            "category":"Wholesale",
            "subcategory":"Motor Vehicles",
            "type":"Manufacturing & Wholesale Goods"
        }
    ],
    "sg:phone":"+1 843 393 2861",
    "sg:postcode":"29532",
    "sg:province":"SC",
    "sg:tags":[
        "auction",
        "automobile"
    ],
    "wof:name":"Clanton's Auto Auction",
    "wof:placetype":"venue"
},
  "geometry": {"coordinates":[-79.897257,34.296778],"type":"Point"}
}