{
  "type": "Feature",
  "properties": {
    "iso:country":"US",
    "sg:address":"216 Glen Rose Cir",
    "sg:city":"Irmo",
    "sg:classifiers":[
        {
            "category":"Communications",
            "type":"Services"
        }
    ],
    "sg:phone":"+1 803 407 0099",
    "sg:postcode":"29063",
    "sg:province":"SC",
    "wof:name":"Sass Communications",
    "wof:placetype":"venue"
},
  "geometry": {"coordinates":[-81.21911799999999,34.141308],"type":"Point"}
}