{
  "type": "Feature",
  "properties": {
    "iso:country":"US",
    "sg:address":"1218 Bull St",
    "sg:city":"Columbia",
    "sg:classifiers":[
        {
            "category":"Organizations",
            "subcategory":"Professional Association",
            "type":"Services"
        }
    ],
    "sg:phone":"+1 803 765 1394",
    "sg:postcode":"29201",
    "sg:province":"SC",
    "wof:name":"Alston Wilkes Home",
    "wof:placetype":"venue"
},
  "geometry": {"coordinates":[-81.02916,34.003881],"type":"Point"}
}