{
  "type": "Feature",
  "properties": {
    "iso:country":"US",
    "sg:address":"1285 Broad St",
    "sg:city":"Sumter",
    "sg:classifiers":[
        {
            "category":"Shopping",
            "subcategory":"Department Store",
            "type":"Retail Goods"
        }
    ],
    "sg:phone":"+1 803 905 5134",
    "sg:postcode":"29150",
    "sg:province":"SC",
    "sg:tags":[
        "shop"
    ],
    "wof:name":"Dollar Tree",
    "wof:placetype":"venue"
},
  "geometry": {"coordinates":[-80.388656,33.956896],"type":"Point"}
}