{
  "type": "Feature",
  "properties": {
    "iso:country":"US",
    "sg:address":"113 Summerwalk Pl",
    "sg:city":"Simpsonville",
    "sg:classifiers":[
        {
            "category":"Wholesale",
            "subcategory":"Scrap",
            "type":"Manufacturing & Wholesale Goods"
        }
    ],
    "sg:phone":"+1 864 962 9889",
    "sg:postcode":"29681",
    "sg:province":"SC",
    "sg:tags":[
        "recycling",
        "center"
    ],
    "wof:name":"Advanced Recycling Syst Inc",
    "wof:placetype":"venue"
},
  "geometry": {"coordinates":[-82.23557099999999,34.781731],"type":"Point"}
}