{
  "type": "Feature",
  "properties": {
    "addr:full":"302 Jeffs Cir Goose Creek SC 29445",
    "addr:housenumber":"302",
    "addr:postcode":"29445",
    "addr:street":"Jeffs Cir",
    "iso:country":"US",
    "sg:address":"302 Jeffs Cir",
    "sg:city":"Goose Creek",
    "sg:classifiers":[
        {
            "category":"Organizations",
            "subcategory":"Religious Organization",
            "type":"Services"
        }
    ],
    "sg:phone":"+1 843 553 5000",
    "sg:postcode":"29445",
    "sg:province":"SC",
    "sg:tags":[
        "church"
    ],
    "wof:name":"Calvary Church-God In Christ",
    "wof:placetype":"venue"
},
  "geometry": {"coordinates":[-80.023126,33.000828],"type":"Point"}
}