{
  "type": "Feature",
  "properties": {
    "iso:country":"US",
    "sg:address":"2091 E Main St",
    "sg:city":"Spartanburg",
    "sg:classifiers":[
        {
            "category":"Wholesale",
            "subcategory":"Farm Supplies",
            "type":"Manufacturing & Wholesale Goods"
        },
        {
            "category":"Shopping",
            "type":"Retail Goods"
        }
    ],
    "sg:phone":"+1 864 577 9288",
    "sg:postcode":"29307",
    "sg:province":"SC",
    "sg:tags":[
        "merchandise"
    ],
    "sg:website":"www.tractorsupply.com",
    "wof:name":"Tractor Supply Co 503",
    "wof:placetype":"venue"
},
  "geometry": {"coordinates":[-81.881969,34.973765],"type":"Point"}
}