{
  "type": "Feature",
  "properties": {
    "iso:country":"US",
    "sg:address":"1425 Powdersville Rd",
    "sg:city":"Easley",
    "sg:classifiers":[
        {
            "category":"Real Estate",
            "subcategory":"Developer",
            "type":"Services"
        }
    ],
    "sg:phone":"+1 864 855 8008",
    "sg:postcode":"29642",
    "sg:province":"SC",
    "sg:tags":[
        "cemetery"
    ],
    "wof:name":"Robinson Memorial Gardens",
    "wof:placetype":"venue"
},
  "geometry": {"coordinates":[-82.539964,34.809392],"type":"Point"}
}