{
  "type": "Feature",
  "properties": {
    "iso:country":"US",
    "sg:address":"302 Pimlico Rd",
    "sg:city":"Greenville",
    "sg:classifiers":[
        {
            "category":"Freight",
            "type":"Transportation"
        }
    ],
    "sg:phone":"+1 864 288 5168",
    "sg:postcode":"29607",
    "sg:province":"SC",
    "sg:tags":[
        "consultant"
    ],
    "wof:name":"Purse Travel",
    "wof:placetype":"venue"
},
  "geometry": {"coordinates":[-82.360443,34.821388],"type":"Point"}
}