{
  "type": "Feature",
  "properties": {
    "addr:full":"110 S Main St Bishopville SC 29010",
    "addr:housenumber":"110",
    "addr:postcode":"29010",
    "addr:street":"S Main St",
    "iso:country":"US",
    "sg:address":"110 S Main St",
    "sg:city":"Bishopville",
    "sg:classifiers":[
        {
            "category":"Shopping",
            "subcategory":"Hobbies, Toys, & Games",
            "type":"Retail Goods"
        }
    ],
    "sg:phone":"+1 803 484 3535",
    "sg:postcode":"29010",
    "sg:province":"SC",
    "sg:tags":[
        "supply"
    ],
    "wof:name":"Scientific Games Intl Inc",
    "wof:placetype":"venue"
},
  "geometry": {"coordinates":[-80.24916399999999,34.217773],"type":"Point"}
}