{
  "type": "Feature",
  "properties": {
    "iso:country":"US",
    "sg:address":"1995 Perimeter Rd",
    "sg:city":"Greenville",
    "sg:classifiers":[
        {
            "category":"Professional",
            "subcategory":"Research",
            "type":"Services"
        }
    ],
    "sg:phone":"+1 864 277 1309",
    "sg:postcode":"29605",
    "sg:province":"SC",
    "sg:tags":[
        "environmental",
        "ecological"
    ],
    "sg:website":"www.danielsscientific.com",
    "wof:name":"Daniels Scientific",
    "wof:placetype":"venue"
},
  "geometry": {"coordinates":[-82.377077,34.735707],"type":"Point"}
}