{
  "type": "Feature",
  "properties": {
    "iso:country":"US",
    "sg:address":"102 S Main St",
    "sg:city":"Simpsonville",
    "sg:classifiers":[
        {
            "category":"Shopping",
            "subcategory":"Pharmacy",
            "type":"Retail Goods"
        }
    ],
    "sg:phone":"+1 864 963 5303",
    "sg:postcode":"29681",
    "sg:province":"SC",
    "sg:tags":[
        "drug",
        "store"
    ],
    "wof:name":"Howard's Pharmacy",
    "wof:placetype":"venue"
},
  "geometry": {"coordinates":[-82.255008,34.735721],"type":"Point"}
}