{
  "type": "Feature",
  "properties": {
    "addr:full":"1206 Red Bank Rd Goose Creek SC 29445",
    "addr:housenumber":"1206",
    "addr:postcode":"29445",
    "addr:street":"Red Bank Rd",
    "iso:country":"US",
    "sg:address":"1206 Red Bank Rd",
    "sg:city":"Goose Creek",
    "sg:classifiers":[
        {
            "category":"Banks & Credit Unions",
            "subcategory":"Bank",
            "type":"Services"
        }
    ],
    "sg:phone":"+1 843 225 2900",
    "sg:postcode":"29445",
    "sg:province":"SC",
    "sg:tags":[
        "mortgage"
    ],
    "wof:name":"Allied Home Mortage Capital",
    "wof:placetype":"venue"
},
  "geometry": {"coordinates":[-80.012834,32.970841],"type":"Point"}
}