{
  "type": "Feature",
  "properties": {
    "iso:country":"US",
    "sg:address":"3101 N Main St",
    "sg:city":"Anderson",
    "sg:classifiers":[
        {
            "category":"Shopping",
            "subcategory":"Music",
            "type":"Retail Goods"
        }
    ],
    "sg:phone":"+1 864 224 7125",
    "sg:postcode":"29621",
    "sg:province":"SC",
    "sg:tags":[
        "compact",
        "record",
        "disc",
        "tape"
    ],
    "wof:name":"Fye",
    "wof:placetype":"venue"
},
  "geometry": {"coordinates":[-82.66795500000001,34.540683],"type":"Point"}
}