{
  "type": "Feature",
  "properties": {
    "iso:country":"US",
    "sg:address":"7679 Dorchester Rd",
    "sg:city":"Charleston",
    "sg:classifiers":[
        {
            "category":"Insurance",
            "subcategory":"Insurance Agent",
            "type":"Services"
        }
    ],
    "sg:phone":"+1 843 760 1180",
    "sg:postcode":"29418",
    "sg:province":"SC",
    "wof:name":"Wally Burbage & Assoc",
    "wof:placetype":"venue"
},
  "geometry": {"coordinates":[-80.081315,32.903034],"type":"Point"}
}