{
  "type": "Feature",
  "properties": {
    "addr:full":"1518 S Irby St Florence SC 29505",
    "addr:housenumber":"1518",
    "addr:postcode":"29505",
    "addr:street":"S Irby St",
    "iso:country":"US",
    "sg:address":"1518 S Irby St",
    "sg:city":"Florence",
    "sg:classifiers":[
        {
            "category":"Shopping",
            "subcategory":"Clothing, Apparel, & Fashions",
            "type":"Retail Goods"
        }
    ],
    "sg:phone":"+1 843 665 4612",
    "sg:postcode":"29505",
    "sg:province":"SC",
    "sg:tags":[
        "uniform"
    ],
    "wof:name":"Uniforms By John Inc",
    "wof:placetype":"venue"
},
  "geometry": {"coordinates":[-79.771163,34.136118],"type":"Point"}
}