{
  "type": "Feature",
  "properties": {
    "iso:country":"US",
    "sg:address":"5146 Wade Hampton Blvd",
    "sg:city":"Taylors",
    "sg:classifiers":[
        {
            "category":"Banks & Credit Unions",
            "subcategory":"Bank",
            "type":"Services"
        }
    ],
    "sg:phone":"+1 864 268 3040",
    "sg:postcode":"29687",
    "sg:province":"SC",
    "sg:tags":[
        "financing"
    ],
    "wof:name":"Upstate Title Loans Inc",
    "wof:placetype":"venue"
},
  "geometry": {"coordinates":[-82.288679,34.931498],"type":"Point"}
}