{
  "type": "Feature",
  "properties": {
    "addr:full":"402 N Cedar St Summerville SC 29483",
    "addr:housenumber":"402",
    "addr:postcode":"29483",
    "addr:street":"N Cedar St",
    "iso:country":"US",
    "sg:address":"402 N Cedar St",
    "sg:city":"Summerville",
    "sg:classifiers":[
        {
            "category":"Professional",
            "subcategory":"Business Services",
            "type":"Services"
        }
    ],
    "sg:phone":"+1 843 871 6957",
    "sg:postcode":"29483",
    "sg:province":"SC",
    "wof:name":"Greenbax Stamp Co",
    "wof:placetype":"venue"
},
  "geometry": {"coordinates":[-80.172962,33.026119],"type":"Point"}
}