{
  "type": "Feature",
  "properties": {
    "iso:country":"US",
    "sg:address":"5591 Fewell Rd",
    "sg:city":"Clover",
    "sg:classifiers":[
        {
            "category":"Autos & Motor Vehicles",
            "subcategory":"Automobile Sales",
            "type":"Retail Goods"
        }
    ],
    "sg:phone":"+1 803 831 1652",
    "sg:postcode":"29710",
    "sg:province":"SC",
    "sg:tags":[
        "car",
        "dealer"
    ],
    "wof:name":"Bob's Auto Sales",
    "wof:placetype":"venue"
},
  "geometry": {"coordinates":[-81.088,35.152073],"type":"Point"}
}