{
  "type": "Feature",
  "properties": {
    "addr:full":"7600 Richard St Columbia SC 29209",
    "addr:housenumber":"7600",
    "addr:postcode":"29209",
    "addr:street":"Richard St",
    "iso:country":"US",
    "sg:address":"7600 Richard St",
    "sg:city":"Columbia",
    "sg:classifiers":[
        {
            "category":"Wholesale",
            "subcategory":"Wine & Distilled Alcoholic Beverages",
            "type":"Manufacturing & Wholesale Goods"
        }
    ],
    "sg:phone":"+1 803 695 1630",
    "sg:postcode":"29209",
    "sg:province":"SC",
    "sg:tags":[
        "liquor"
    ],
    "wof:name":"Southern Wine & Spirits",
    "wof:placetype":"venue"
},
  "geometry": {"coordinates":[-80.95538500000001,33.951359],"type":"Point"}
}