{
  "type": "Feature",
  "properties": {
    "iso:country":"US",
    "sg:address":"125 Wesmark Blvd",
    "sg:city":"Sumter",
    "sg:classifiers":[
        {
            "category":"Banks & Credit Unions",
            "subcategory":"Bank",
            "type":"Services"
        }
    ],
    "sg:phone":"+1 803 469 2274",
    "sg:postcode":"29150",
    "sg:province":"SC",
    "sg:tags":[
        "cashing",
        "check"
    ],
    "wof:name":"Express Money Svc",
    "wof:placetype":"venue"
},
  "geometry": {"coordinates":[-80.371932,33.954835],"type":"Point"}
}