{
  "type": "Feature",
  "properties": {
    "addr:full":"6801 Notch Rd Columbia SC 29223",
    "addr:housenumber":"6801",
    "addr:postcode":"29223",
    "addr:street":"Notch Rd",
    "iso:country":"US",
    "sg:address":"6801 Notch Rd",
    "sg:city":"Columbia",
    "sg:classifiers":[
        {
            "category":"Wholesale",
            "subcategory":"Groceries",
            "type":"Manufacturing & Wholesale Goods"
        }
    ],
    "sg:phone":"+1 803 419 5011",
    "sg:postcode":"29223",
    "sg:province":"SC",
    "wof:name":"Marita Breads",
    "wof:placetype":"venue"
},
  "geometry": {"coordinates":[-80.961651,34.060966],"type":"Point"}
}