{
  "type": "Feature",
  "properties": {
    "iso:country":"US",
    "sg:address":"301 N Main St",
    "sg:city":"Greenville",
    "sg:classifiers":[
        {
            "category":"Travel",
            "subcategory":"Travel Agent",
            "type":"Entertainment"
        }
    ],
    "sg:phone":"+1 864 331 1140",
    "sg:postcode":"29601",
    "sg:province":"SC",
    "sg:tags":[
        "agency",
        "bureau"
    ],
    "sg:website":"www.my11th.com",
    "wof:name":"11th Hour Vacations",
    "wof:placetype":"venue"
},
  "geometry": {"coordinates":[-82.397156,34.854858],"type":"Point"}
}