{
  "type": "Feature",
  "properties": {
    "iso:country":"US",
    "sg:address":"513 N Mc Duffie St",
    "sg:city":"Anderson",
    "sg:classifiers":[
        {
            "category":"Banks & Credit Unions",
            "subcategory":"Bank",
            "type":"Services"
        }
    ],
    "sg:phone":"+1 864 226 9985",
    "sg:postcode":"29621",
    "sg:province":"SC",
    "sg:tags":[
        "loan",
        "real estate"
    ],
    "wof:name":"Llindsey & Lindsey Mortgage",
    "wof:placetype":"venue"
},
  "geometry": {"coordinates":[-82.64977,34.508504],"type":"Point"}
}