{
  "type": "Feature",
  "properties": {
    "iso:country":"US",
    "sg:address":"401 N Ocean Blvd",
    "sg:city":"Myrtle Beach",
    "sg:classifiers":[
        {
            "category":"Travel",
            "subcategory":"Hotels & Motels",
            "type":"Entertainment"
        }
    ],
    "sg:phone":"+1 843 626 3223",
    "sg:postcode":"29577",
    "sg:province":"SC",
    "wof:name":"Sea Cruz Motel",
    "wof:placetype":"venue"
},
  "geometry": {"coordinates":[-78.88382,33.687864],"type":"Point"}
}