{
  "type": "Feature",
  "properties": {
    "addr:full":"4717 Devine St Columbia SC 29209",
    "addr:housenumber":"4717",
    "addr:postcode":"29209",
    "addr:street":"Devine St",
    "iso:country":"US",
    "sg:address":"4717 Devine St",
    "sg:city":"Columbia",
    "sg:classifiers":[
        {
            "category":"Restaurant",
            "type":"Food & Drink"
        }
    ],
    "sg:menulink":"http://www.allmenus.com/sc/columbia/228893-jersey-mikes/menu/",
    "sg:phone":"+1 803 787 0945",
    "sg:postcode":"29209",
    "sg:province":"SC",
    "sg:tags":[
        "american",
        "sandwich"
    ],
    "wof:name":"Jersey Mike's",
    "wof:placetype":"venue"
},
  "geometry": {"coordinates":[-80.973788,33.989936],"type":"Point"}
}