{
  "type": "Feature",
  "properties": {
    "addr:full":"1413 Silas St Newberry SC 29108",
    "addr:housenumber":"1413",
    "addr:postcode":"29108",
    "addr:street":"Silas St",
    "iso:country":"US",
    "sg:address":"1413 Silas St",
    "sg:city":"Newberry",
    "sg:classifiers":[
        {
            "category":"Home & Garden",
            "subcategory":"Garden Supply",
            "type":"Retail Goods"
        }
    ],
    "sg:phone":"+1 803 276 9909",
    "sg:postcode":"29108",
    "sg:province":"SC",
    "sg:tags":[
        "nurseryman"
    ],
    "wof:name":"Chappells Nursery & Landscpg",
    "wof:placetype":"venue"
},
  "geometry": {"coordinates":[-81.610083,34.268013],"type":"Point"}
}