{
  "type": "Feature",
  "properties": {
    "addr:full":"806 Tyler Ave North Augusta SC 29841",
    "addr:housenumber":"806",
    "addr:postcode":"29841",
    "addr:street":"Tyler Ave",
    "iso:country":"US",
    "sg:address":"806 Tyler Ave",
    "sg:city":"North Augusta",
    "sg:classifiers":[
        {
            "category":"Organizations",
            "subcategory":"Religious Organization",
            "type":"Services"
        }
    ],
    "sg:phone":"+1 803 441 8447",
    "sg:postcode":"29841",
    "sg:province":"SC",
    "sg:tags":[
        "church"
    ],
    "wof:name":"Faith Tabernacle",
    "wof:placetype":"venue"
},
  "geometry": {"coordinates":[-81.94682299999999,33.485676],"type":"Point"}
}