{
  "type": "Feature",
  "properties": {
    "iso:country":"US",
    "sg:address":"114 S Ron McNair Blvd",
    "sg:city":"Lake City",
    "sg:classifiers":[
        {
            "category":"Shopping",
            "type":"Retail Goods"
        }
    ],
    "sg:phone":"+1 843 394 1651",
    "sg:postcode":"29560",
    "sg:province":"SC",
    "sg:tags":[
        "merchandise"
    ],
    "wof:name":"S V I Telecommunications Inc",
    "wof:placetype":"venue"
},
  "geometry": {"coordinates":[-79.760621,33.875433],"type":"Point"}
}