{
  "type": "Feature",
  "properties": {
    "addr:full":"49 Immigration St Charleston SC 29403",
    "addr:housenumber":"49",
    "addr:postcode":"29403",
    "addr:street":"Immigration St",
    "iso:country":"US",
    "sg:address":"49 Immigration St",
    "sg:city":"Charleston",
    "sg:classifiers":[
        {
            "category":"Real Estate",
            "subcategory":"Real Estate Agent",
            "type":"Services"
        }
    ],
    "sg:phone":"+1 843 805 6060",
    "sg:postcode":"29403",
    "sg:province":"SC",
    "sg:website":"www.battenandmoore.com",
    "wof:name":"Batten & Moore",
    "wof:placetype":"venue"
},
  "geometry": {"coordinates":[-79.930576,32.798257],"type":"Point"}
}