{
  "type": "Feature",
  "properties": {
    "iso:country":"US",
    "sg:address":"120 N Marigold St",
    "sg:city":"Florence",
    "sg:classifiers":[
        {
            "category":"Building & Trades",
            "subcategory":"Landscaping Services",
            "type":"Services"
        }
    ],
    "sg:phone":"+1 843 669 7672",
    "sg:postcode":"29506",
    "sg:province":"SC",
    "sg:tags":[
        "supply"
    ],
    "wof:name":"Kemmerlin Tree Service",
    "wof:placetype":"venue"
},
  "geometry": {"coordinates":[-79.74025399999999,34.198768],"type":"Point"}
}