{
  "type": "Feature",
  "properties": {
    "iso:country":"US",
    "sg:address":"6600 N Kings Hwy",
    "sg:city":"Myrtle Beach",
    "sg:classifiers":[
        {
            "category":"Organizations",
            "subcategory":"Religious Organization",
            "type":"Services"
        }
    ],
    "sg:phone":"+1 843 449 5496",
    "sg:postcode":"29572",
    "sg:province":"SC",
    "sg:tags":[
        "church"
    ],
    "wof:name":"First Ch Of Christ Scientist",
    "wof:placetype":"venue"
},
  "geometry": {"coordinates":[-78.82732799999999,33.739843],"type":"Point"}
}