{
  "type": "Feature",
  "properties": {
    "iso:country":"US",
    "sg:address":"609 Tidal Pointe Ln",
    "sg:city":"Myrtle Beach",
    "sg:classifiers":[
        {
            "category":"Insurance",
            "subcategory":"Insurance Agent",
            "type":"Services"
        }
    ],
    "sg:phone":"+1 843 236 2198",
    "sg:postcode":"29579",
    "sg:province":"SC",
    "wof:name":"St Paul Travelers",
    "wof:placetype":"venue"
},
  "geometry": {"coordinates":[-78.950354,33.705617],"type":"Point"}
}