{
  "type": "Feature",
  "properties": {
    "addr:full":"107 S White St Lancaster SC 29720",
    "addr:housenumber":"107",
    "addr:postcode":"29720",
    "addr:street":"S White St",
    "iso:country":"US",
    "sg:address":"107 S White St",
    "sg:city":"Lancaster",
    "sg:classifiers":[
        {
            "category":"Professional",
            "subcategory":"Accounting & Tax Preparation",
            "type":"Services"
        }
    ],
    "sg:phone":"+1 803 285 7617",
    "sg:postcode":"29720",
    "sg:province":"SC",
    "sg:tags":[
        "return",
        "filing"
    ],
    "wof:name":"H & R Block Tax Svc",
    "wof:placetype":"venue"
},
  "geometry": {"coordinates":[-80.770141,34.721546],"type":"Point"}
}