{
  "type": "Feature",
  "properties": {
    "iso:country":"US",
    "sg:address":"7563 Flat Creek Rd",
    "sg:city":"Kershaw",
    "sg:classifiers":[
        {
            "category":"Government",
            "subcategory":"Fire Station",
            "type":"Public Place"
        }
    ],
    "sg:phone":"+1 803 475 4450",
    "sg:postcode":"29067",
    "sg:province":"SC",
    "sg:tags":[
        "department"
    ],
    "wof:name":"Flat Creek Volunteer Fire Dept",
    "wof:placetype":"venue"
},
  "geometry": {"coordinates":[-80.518636,34.632942],"type":"Point"}
}