{
  "type": "Feature",
  "properties": {
    "iso:country":"US",
    "sg:address":"1040 S Kings Hwy",
    "sg:city":"Myrtle Beach",
    "sg:classifiers":[
        {
            "category":"Shopping",
            "type":"Retail Goods"
        }
    ],
    "sg:phone":"+1 843 215 7358",
    "sg:postcode":"29577",
    "sg:province":"SC",
    "sg:tags":[
        "merchandise"
    ],
    "wof:name":"Trang Nguyen",
    "wof:placetype":"venue"
},
  "geometry": {"coordinates":[-78.899231,33.679058],"type":"Point"}
}