{
  "type": "Feature",
  "properties": {
    "iso:country":"US",
    "sg:address":"818 Garlington Rd",
    "sg:city":"Mountville",
    "sg:classifiers":[
        {
            "category":"Building & Trades",
            "subcategory":"Construction",
            "type":"Services"
        }
    ],
    "sg:phone":"+1 864 923 0052",
    "sg:postcode":"29370",
    "sg:province":"SC",
    "sg:tags":[
        "contractor"
    ],
    "wof:name":"Sherfields Roofing",
    "wof:placetype":"venue"
},
  "geometry": {"coordinates":[-81.938913,34.323054],"type":"Point"}
}