{
  "type": "Feature",
  "properties": {
    "iso:country":"US",
    "sg:address":"1622 Two Notch Rd",
    "sg:city":"Lexington",
    "sg:classifiers":[
        {
            "category":"Manufacturing",
            "subcategory":"Metals",
            "type":"Manufacturing & Wholesale Goods"
        }
    ],
    "sg:phone":"+1 803 951 3040",
    "sg:postcode":"29073",
    "sg:province":"SC",
    "sg:tags":[
        "pipe",
        "fitting",
        "fabricated"
    ],
    "wof:name":"Fast Fabricators Inc",
    "wof:placetype":"venue"
},
  "geometry": {"coordinates":[-81.23627,33.951004],"type":"Point"}
}