{
  "type": "Feature",
  "properties": {
    "iso:country":"US",
    "sg:address":"1739 Maybank Hwy",
    "sg:city":"Charleston",
    "sg:classifiers":[
        {
            "category":"Utilities",
            "subcategory":"Mobile Phone",
            "type":"Services"
        }
    ],
    "sg:phone":"+1 843 762 6252",
    "sg:postcode":"29412",
    "sg:province":"SC",
    "sg:tags":[
        "telephone",
        "cellular"
    ],
    "wof:name":"Total Communication Systems",
    "wof:placetype":"venue"
},
  "geometry": {"coordinates":[-79.976737,32.762615],"type":"Point"}
}