{
  "type": "Feature",
  "properties": {
    "addr:full":"937 Cottingham Blvd N Bennettsville SC 29512",
    "addr:housenumber":"937",
    "addr:postcode":"29512",
    "addr:street":"Cottingham Blvd N",
    "iso:country":"US",
    "sg:address":"937 Cottingham Blvd N",
    "sg:city":"Bennettsville",
    "sg:classifiers":[
        {
            "category":"Home & Garden",
            "subcategory":"Furniture",
            "type":"Retail Goods"
        }
    ],
    "sg:phone":"+1 843 479 7911",
    "sg:postcode":"29512",
    "sg:province":"SC",
    "wof:name":"Tyler's Fine Furnishings",
    "wof:placetype":"venue"
},
  "geometry": {"coordinates":[-79.699713,34.636299],"type":"Point"}
}