{
  "type": "Feature",
  "properties": {
    "addr:full":"770 W Liberty St Sumter SC 29150",
    "addr:housenumber":"770",
    "addr:postcode":"29150",
    "addr:street":"W Liberty St",
    "iso:country":"US",
    "sg:address":"770 W Liberty St",
    "sg:city":"Sumter",
    "sg:classifiers":[
        {
            "category":"Health Services",
            "subcategory":"Doctor",
            "type":"Services"
        }
    ],
    "sg:phone":"+1 803 773 5411",
    "sg:postcode":"29150",
    "sg:province":"SC",
    "sg:tags":[
        "dentist"
    ],
    "wof:name":"Wallie B Jones DDS",
    "wof:placetype":"venue"
},
  "geometry": {"coordinates":[-80.366443,33.919427],"type":"Point"}
}