{
  "type": "Feature",
  "properties": {
    "iso:country":"US",
    "sg:address":"117 Kay Dr",
    "sg:city":"Easley",
    "sg:classifiers":[
        {
            "category":"Autos & Motor Vehicles",
            "subcategory":"Auto Supplies",
            "type":"Retail Goods"
        }
    ],
    "sg:phone":"+1 864 269 3006",
    "sg:postcode":"29640",
    "sg:province":"SC",
    "wof:name":"Metro Wheels & Hubcaps",
    "wof:placetype":"venue"
},
  "geometry": {"coordinates":[-82.520859,34.830653],"type":"Point"}
}