{
  "type": "Feature",
  "properties": {
    "addr:full":"5100 Fairfield Rd Columbia SC 29203",
    "addr:housenumber":"5100",
    "addr:postcode":"29203",
    "addr:street":"Fairfield Rd",
    "iso:country":"US",
    "sg:address":"5100 Fairfield Rd",
    "sg:city":"Columbia",
    "sg:classifiers":[
        {
            "category":"Shopping",
            "subcategory":"Clothing, Apparel, & Fashions",
            "type":"Retail Goods"
        }
    ],
    "sg:phone":"+1 803 754 6152",
    "sg:postcode":"29203",
    "sg:province":"SC",
    "wof:name":"Simply Fashions",
    "wof:placetype":"venue"
},
  "geometry": {"coordinates":[-81.028001,34.054082],"type":"Point"}
}