{
  "type": "Feature",
  "properties": {
    "addr:full":"3770 Plum Aly Murrells Inlet SC 29576",
    "addr:housenumber":"3770",
    "addr:postcode":"29576",
    "addr:street":"Plum Aly",
    "iso:country":"US",
    "sg:address":"3770 Plum Aly",
    "sg:city":"Murrells Inlet",
    "sg:classifiers":[
        {
            "category":"Wholesale",
            "subcategory":"Hardware",
            "type":"Manufacturing & Wholesale Goods"
        },
        {
            "category":"Building & Trades",
            "subcategory":"Plumbing",
            "type":"Services"
        }
    ],
    "sg:phone":"+1 843 357 3865",
    "sg:postcode":"29576",
    "sg:province":"SC",
    "sg:tags":[
        "commercial",
        "refrigeration",
        "installation",
        "refrigerating",
        "repair"
    ],
    "wof:name":"South East Refrigeration",
    "wof:placetype":"venue"
},
  "geometry": {"coordinates":[-79.07377099999999,33.565202],"type":"Point"}
}