{
  "type": "Feature",
  "properties": {
    "iso:country":"US",
    "sg:address":"514 Ezra Jumper Rd",
    "sg:city":"Swansea",
    "sg:classifiers":[
        {
            "category":"Building & Trades",
            "subcategory":"Construction",
            "type":"Services"
        }
    ],
    "sg:phone":"+1 803 568 3579",
    "sg:postcode":"29160",
    "sg:province":"SC",
    "sg:tags":[
        "carpentry"
    ],
    "wof:name":"Freddie Stabler Jr",
    "wof:placetype":"venue"
},
  "geometry": {"coordinates":[-81.068864,33.735123],"type":"Point"}
}