{
  "type": "Feature",
  "properties": {
    "iso:country":"US",
    "sg:address":"10313 Garners Ferry Rd",
    "sg:city":"Eastover",
    "sg:classifiers":[
        {
            "category":"Manufacturing",
            "subcategory":"Aerospace",
            "type":"Manufacturing & Wholesale Goods"
        }
    ],
    "sg:phone":"+1 803 776 6007",
    "sg:postcode":"29044",
    "sg:province":"SC",
    "sg:tags":[
        "engine",
        "aircraft",
        "parts"
    ],
    "wof:name":"Pratt & Whitney",
    "wof:placetype":"venue"
},
  "geometry": {"coordinates":[-80.80331,33.941788],"type":"Point"}
}