{
  "type": "Feature",
  "properties": {
    "iso:country":"US",
    "sg:address":"636 E Carolina Ave",
    "sg:city":"Hartsville",
    "sg:classifiers":[
        {
            "category":"Personal",
            "subcategory":"Beauty Salon",
            "type":"Services"
        }
    ],
    "sg:phone":"+1 843 383 5258",
    "sg:postcode":"29550",
    "sg:province":"SC",
    "wof:name":"Carolina Cuts",
    "wof:placetype":"venue"
},
  "geometry": {"coordinates":[-80.060763,34.379192],"type":"Point"}
}