{
  "type": "Feature",
  "properties": {
    "addr:full":"1814 Bull St Columbia SC 29201",
    "addr:housenumber":"1814",
    "addr:postcode":"29201",
    "addr:street":"Bull St",
    "iso:country":"US",
    "sg:address":"1814 Bull St",
    "sg:city":"Columbia",
    "sg:classifiers":[
        {
            "category":"Professional",
            "subcategory":"Lawyer & Legal Services",
            "type":"Services"
        }
    ],
    "sg:phone":"+1 803 779 7193",
    "sg:postcode":"29201",
    "sg:province":"SC",
    "wof:name":"Ohanesian & Ohanesian",
    "wof:placetype":"venue"
},
  "geometry": {"coordinates":[-81.032303,34.0112],"type":"Point"}
}