{
  "type": "Feature",
  "properties": {
    "addr:full":"4530 US Hwy 29 Belton SC 29627",
    "addr:housenumber":"4530",
    "addr:postcode":"29627",
    "addr:street":"Us Hwy 29",
    "iso:country":"US",
    "sg:address":"4530 US Hwy 29",
    "sg:city":"Belton",
    "sg:classifiers":[
        {
            "category":"Shopping",
            "subcategory":"Gifts & Souvenirs",
            "type":"Retail Goods"
        }
    ],
    "sg:phone":"+1 864 222 3044",
    "sg:postcode":"29627",
    "sg:province":"SC",
    "sg:tags":[
        "collectible"
    ],
    "wof:name":"A A A Collectables",
    "wof:placetype":"venue"
},
  "geometry": {"coordinates":[-82.548855,34.588745],"type":"Point"}
}