{
  "type": "Feature",
  "properties": {
    "iso:country":"US",
    "sg:address":"2449 Santee River Rd",
    "sg:city":"St Stephen",
    "sg:classifiers":[
        {
            "category":"Organizations",
            "subcategory":"Religious Organization",
            "type":"Services"
        }
    ],
    "sg:phone":"+1 843 567 3779",
    "sg:postcode":"29479",
    "sg:province":"SC",
    "sg:tags":[
        "church"
    ],
    "wof:name":"Bethlehem Baptist Church",
    "wof:placetype":"venue"
},
  "geometry": {"coordinates":[-79.823632,33.360715],"type":"Point"}
}