{
  "type": "Feature",
  "properties": {
    "iso:country":"US",
    "sg:address":"3484 Johan Blvd",
    "sg:city":"Johns Island",
    "sg:classifiers":[
        {
            "category":"Building & Trades",
            "subcategory":"Landscaping Services",
            "type":"Services"
        }
    ],
    "sg:phone":"+1 843 559 6988",
    "sg:postcode":"29455",
    "sg:province":"SC",
    "wof:name":"Lawns & Moorer",
    "wof:placetype":"venue"
},
  "geometry": {"coordinates":[-80.100217,32.757657],"type":"Point"}
}