{
  "type": "Feature",
  "properties": {
    "addr:full":"115 W Main St Union SC 29379",
    "addr:housenumber":"115",
    "addr:postcode":"29379",
    "addr:street":"W Main St",
    "iso:country":"US",
    "sg:address":"115 W Main St",
    "sg:city":"Union",
    "sg:classifiers":[
        {
            "category":"Organizations",
            "subcategory":"Non-profit Organization",
            "type":"Services"
        }
    ],
    "sg:phone":"+1 864 427 0447",
    "sg:postcode":"29379",
    "sg:province":"SC",
    "sg:tags":[
        "alternative",
        "abortion"
    ],
    "wof:name":"Union County Pregnancy Ctr",
    "wof:placetype":"venue"
},
  "geometry": {"coordinates":[-81.624832,34.71507],"type":"Point"}
}