{
  "type": "Feature",
  "properties": {
    "iso:country":"US",
    "sg:address":"1213 River Rd",
    "sg:city":"Johns Island",
    "sg:classifiers":[
        {
            "category":"Autos & Motor Vehicles",
            "subcategory":"Fuel & Gas Station",
            "type":"Retail Goods"
        }
    ],
    "sg:phone":"+1 843 559 9345",
    "sg:postcode":"29455",
    "sg:province":"SC",
    "sg:tags":[
        "station",
        "gasoline"
    ],
    "wof:name":"Marilyn Reeves Sea & Shell",
    "wof:placetype":"venue"
},
  "geometry": {"coordinates":[-80.063676,32.764846],"type":"Point"}
}