{
  "type": "Feature",
  "properties": {
    "iso:country":"US",
    "sg:address":"1411 Columbia Hwy N",
    "sg:city":"Aiken",
    "sg:classifiers":[
        {
            "category":"Organizations",
            "subcategory":"Religious Organization",
            "type":"Services"
        }
    ],
    "sg:phone":"+1 803 648 4047",
    "sg:postcode":"29801",
    "sg:province":"SC",
    "sg:tags":[
        "church"
    ],
    "sg:website":"www.riveroflifechurch-aiken.org",
    "wof:name":"River Of Life",
    "wof:placetype":"venue"
},
  "geometry": {"coordinates":[-81.69903100000001,33.586465],"type":"Point"}
}