{
  "type": "Feature",
  "properties": {
    "iso:country":"US",
    "sg:address":"115 Overland Dr",
    "sg:city":"Greenwood",
    "sg:classifiers":[
        {
            "category":"Health Services",
            "subcategory":"Doctor",
            "type":"Services"
        }
    ],
    "sg:phone":"+1 864 227 6641",
    "sg:postcode":"29646",
    "sg:province":"SC",
    "sg:tags":[
        "physician",
        "surgeon"
    ],
    "wof:name":"Greenwood Internal Medicine",
    "wof:placetype":"venue"
},
  "geometry": {"coordinates":[-82.154634,34.170728],"type":"Point"}
}