{
  "type": "Feature",
  "properties": {
    "iso:country":"US",
    "sg:address":"1831 Sandy St",
    "sg:city":"North Charleston",
    "sg:classifiers":[
        {
            "category":"Restaurant",
            "type":"Food & Drink"
        }
    ],
    "sg:phone":"+1 843 744 7944",
    "sg:postcode":"29405",
    "sg:province":"SC",
    "sg:tags":[
        "eating"
    ],
    "wof:name":"Shortys Snack Bar",
    "wof:placetype":"venue"
},
  "geometry": {"coordinates":[-80.000658,32.859596],"type":"Point"}
}