{
  "type": "Feature",
  "properties": {
    "iso:country":"US",
    "sg:address":"10831 Two Notch Rd",
    "sg:city":"Elgin",
    "sg:classifiers":[
        {
            "category":"Retail",
            "subcategory":"Repair Shop",
            "type":"Services"
        }
    ],
    "sg:phone":"+1 803 736 5982",
    "sg:postcode":"29045",
    "sg:province":"SC",
    "sg:tags":[
        "welding"
    ],
    "wof:name":"Henley's Equipment Repair",
    "wof:placetype":"venue"
},
  "geometry": {"coordinates":[-80.835843,34.142064],"type":"Point"}
}