{
  "type": "Feature",
  "properties": {
    "addr:full":"336 Chowning Pl Lexington SC 29072",
    "addr:housenumber":"336",
    "addr:postcode":"29072",
    "addr:street":"Chowning Pl",
    "iso:country":"US",
    "sg:address":"336 Chowning Pl",
    "sg:city":"Lexington",
    "sg:classifiers":[
        {
            "category":"Wholesale",
            "subcategory":"Groceries",
            "type":"Manufacturing & Wholesale Goods"
        }
    ],
    "sg:phone":"+1 803 356 0986",
    "sg:postcode":"29072",
    "sg:province":"SC",
    "sg:tags":[
        "food",
        "broker"
    ],
    "wof:name":"CROSSMARK",
    "wof:placetype":"venue"
},
  "geometry": {"coordinates":[-81.32468,33.989507],"type":"Point"}
}