{
  "type": "Feature",
  "properties": {
    "iso:country":"US",
    "sg:address":"102 N Macarthur Ave",
    "sg:city":"Dillon",
    "sg:classifiers":[
        {
            "category":"Insurance",
            "subcategory":"Insurance Agent",
            "type":"Services"
        }
    ],
    "sg:phone":"+1 843 774 2227",
    "sg:postcode":"29536",
    "sg:province":"SC",
    "wof:name":"Blue Cross & Blue Shield",
    "wof:placetype":"venue"
},
  "geometry": {"coordinates":[-79.371409,34.418003],"type":"Point"}
}