{
  "type": "Feature",
  "properties": {
    "iso:country":"US",
    "sg:address":"5314 Wade Hampton Blvd",
    "sg:city":"Taylors",
    "sg:classifiers":[
        {
            "category":"Autos & Motor Vehicles",
            "subcategory":"Motorcycle Sales",
            "type":"Retail Goods"
        }
    ],
    "sg:phone":"+1 864 848 6300",
    "sg:postcode":"29687",
    "sg:province":"SC",
    "sg:tags":[
        "scooter"
    ],
    "sg:website":"www.motolinx.com",
    "wof:name":"Motolinx",
    "wof:placetype":"venue"
},
  "geometry": {"coordinates":[-82.27849399999999,34.93498],"type":"Point"}
}