{
  "type": "Feature",
  "properties": {
    "addr:full":"650 Huckleberry Finn Rd Batesburg SC 29006",
    "addr:housenumber":"650",
    "addr:postcode":"29006",
    "addr:street":"Huckleberry Finn Rd",
    "iso:country":"US",
    "sg:address":"650 Huckleberry Finn Rd",
    "sg:city":"Batesburg",
    "sg:classifiers":[
        {
            "category":"Government",
            "subcategory":"Fire Station",
            "type":"Public Place"
        }
    ],
    "sg:phone":"+1 803 657 5366",
    "sg:postcode":"29006",
    "sg:province":"SC",
    "sg:tags":[
        "department"
    ],
    "wof:name":"Sandy Ridge Volunteer Fire",
    "wof:placetype":"venue"
},
  "geometry": {"coordinates":[-81.48817699999999,33.788387],"type":"Point"}
}