{
  "type": "Feature",
  "properties": {
    "iso:country":"US",
    "sg:address":"516 S Coit St",
    "sg:city":"Florence",
    "sg:classifiers":[
        {
            "category":"Professional",
            "subcategory":"Management & Consulting",
            "type":"Services"
        }
    ],
    "sg:phone":"+1 843 629 1533",
    "sg:postcode":"29501",
    "sg:province":"SC",
    "sg:tags":[
        "consultant",
        "business"
    ],
    "sg:website":"www.bbsllc.com",
    "wof:name":"Billings Business Svc",
    "wof:placetype":"venue"
},
  "geometry": {"coordinates":[-79.769727,34.188717],"type":"Point"}
}