{
  "type": "Feature",
  "properties": {
    "iso:country":"US",
    "sg:address":"6306 Gill Creek Rd",
    "sg:city":"Columbia",
    "sg:classifiers":[
        {
            "category":"Wholesale",
            "subcategory":"Jewelry",
            "type":"Manufacturing & Wholesale Goods"
        }
    ],
    "sg:phone":"+1 803 787 8579",
    "sg:postcode":"29206",
    "sg:province":"SC",
    "sg:tags":[
        "stone"
    ],
    "wof:name":"Southeastern Diamond Brkr",
    "wof:placetype":"venue"
},
  "geometry": {"coordinates":[-80.943067,34.036726],"type":"Point"}
}