{
  "type": "Feature",
  "properties": {
    "iso:country":"US",
    "sg:address":"2200 College St Exd",
    "sg:city":"Columbia",
    "sg:classifiers":[
        {
            "category":"Restaurant",
            "type":"Food & Drink"
        }
    ],
    "sg:phone":"+1 803 251 6606",
    "sg:postcode":"29205",
    "sg:province":"SC",
    "wof:name":"Steppin' Out Diner",
    "wof:placetype":"venue"
},
  "geometry": {"coordinates":[-81.014065,34.002539],"type":"Point"}
}