{
  "type": "Feature",
  "properties": {
    "addr:full":"301 Main St Greenwood SC 29646",
    "addr:housenumber":"301",
    "addr:postcode":"29646",
    "addr:street":"Main St",
    "iso:country":"US",
    "sg:address":"301 Main St",
    "sg:city":"Greenwood",
    "sg:classifiers":[
        {
            "category":"Health Services",
            "subcategory":"Clinic",
            "type":"Services"
        }
    ],
    "sg:phone":"+1 864 229 3200",
    "sg:postcode":"29646",
    "sg:province":"SC",
    "sg:tags":[
        "home"
    ],
    "wof:name":"Health Related Home Care",
    "wof:placetype":"venue"
},
  "geometry": {"coordinates":[-82.16054,34.191061],"type":"Point"}
}