{
  "type": "Feature",
  "properties": {
    "addr:full":"205 N Church St Swansea SC 29160",
    "addr:housenumber":"205",
    "addr:postcode":"29160",
    "addr:street":"N Church St",
    "iso:country":"US",
    "sg:address":"205 N Church St",
    "sg:city":"Swansea",
    "sg:classifiers":[
        {
            "category":"Wholesale",
            "subcategory":"Electrical",
            "type":"Manufacturing & Wholesale Goods"
        }
    ],
    "sg:phone":"+1 803 568 4012",
    "sg:postcode":"29160",
    "sg:province":"SC",
    "sg:tags":[
        "operated",
        "telephone",
        "card"
    ],
    "wof:name":"Telaleasing Enterprises Inc",
    "wof:placetype":"venue"
},
  "geometry": {"coordinates":[-81.09962299999999,33.740013],"type":"Point"}
}