{
  "type": "Feature",
  "properties": {
    "iso:country":"US",
    "sg:address":"1715 Whiskey Rd",
    "sg:city":"Aiken",
    "sg:classifiers":[
        {
            "category":"Banks & Credit Unions",
            "subcategory":"Investment Brokerage",
            "type":"Services"
        }
    ],
    "sg:phone":"+1 803 641 0213",
    "sg:postcode":"29803",
    "sg:province":"SC",
    "sg:tags":[
        "stock",
        "bond"
    ],
    "wof:name":"People's Financial Svc",
    "wof:placetype":"venue"
},
  "geometry": {"coordinates":[-81.71890500000001,33.522612],"type":"Point"}
}