{
  "type": "Feature",
  "properties": {
    "addr:full":"121 Dozier Blvd Florence SC 29501",
    "addr:housenumber":"121",
    "addr:postcode":"29501",
    "addr:street":"Dozier Blvd",
    "iso:country":"US",
    "sg:address":"121 Dozier Blvd",
    "sg:city":"Florence",
    "sg:classifiers":[
        {
            "category":"Banks & Credit Unions",
            "subcategory":"Bank",
            "type":"Services"
        }
    ],
    "sg:phone":"+1 843 665 8701",
    "sg:postcode":"29501",
    "sg:province":"SC",
    "wof:name":"Carolina First Bank",
    "wof:placetype":"venue"
},
  "geometry": {"coordinates":[-79.810957,34.19223],"type":"Point"}
}