{
  "type": "Feature",
  "properties": {
    "iso:country":"US",
    "sg:address":"600 S College St",
    "sg:city":"Walhalla",
    "sg:classifiers":[
        {
            "category":"Autos & Motor Vehicles",
            "subcategory":"Automobile Sales",
            "type":"Retail Goods"
        }
    ],
    "sg:phone":"+1 864 638 6162",
    "sg:postcode":"29691",
    "sg:province":"SC",
    "sg:tags":[
        "car",
        "used",
        "dealer"
    ],
    "wof:name":"Wilson's Used Cars",
    "wof:placetype":"venue"
},
  "geometry": {"coordinates":[-83.067417,34.758882],"type":"Point"}
}