{
  "type": "Feature",
  "properties": {
    "iso:country":"US",
    "sg:address":"11 Segres Rd",
    "sg:city":"Kingstree",
    "sg:classifiers":[
        {
            "category":"Social Services",
            "subcategory":"Child Care",
            "type":"Services"
        }
    ],
    "sg:phone":"+1 843 354 2021",
    "sg:postcode":"29556",
    "sg:province":"SC",
    "wof:name":"Teeni Tots Day Care",
    "wof:placetype":"venue"
},
  "geometry": {"coordinates":[-79.81025099999999,33.646752],"type":"Point"}
}