{
  "type": "Feature",
  "properties": {
    "iso:country":"US",
    "sg:address":"103 Barrington Park Dr",
    "sg:city":"Greer",
    "sg:classifiers":[
        {
            "category":"Organizations",
            "subcategory":"Community Association",
            "type":"Services"
        }
    ],
    "sg:phone":"+1 864 848 4580",
    "sg:postcode":"29650",
    "sg:province":"SC",
    "sg:tags":[
        "club"
    ],
    "wof:name":"Barrington Park Club House",
    "wof:placetype":"venue"
},
  "geometry": {"coordinates":[-82.255942,34.876001],"type":"Point"}
}