{
  "type": "Feature",
  "properties": {
    "iso:country":"US",
    "sg:address":"1921 Sam Rittenberg Blvd",
    "sg:city":"Charleston",
    "sg:classifiers":[
        {
            "category":"Wholesale",
            "subcategory":"Auto Parts",
            "type":"Manufacturing & Wholesale Goods"
        }
    ],
    "sg:phone":"+1 843 571 0310",
    "sg:postcode":"29407",
    "sg:province":"SC",
    "sg:tags":[
        "automotive",
        "retail",
        "supply"
    ],
    "wof:name":"Auto Supply & Equipment Co",
    "wof:placetype":"venue"
},
  "geometry": {"coordinates":[-80.023226,32.798139],"type":"Point"}
}