{
  "type": "Feature",
  "properties": {
    "addr:full":"334 Anita Dr Goose Creek SC 29445",
    "addr:housenumber":"334",
    "addr:postcode":"29445",
    "addr:street":"Anita Dr",
    "iso:country":"US",
    "sg:address":"334 Anita Dr",
    "sg:city":"Goose Creek",
    "sg:classifiers":[
        {
            "category":"Building & Trades",
            "subcategory":"Construction",
            "type":"Services"
        }
    ],
    "sg:phone":"+1 843 553 2663",
    "sg:postcode":"29445",
    "sg:province":"SC",
    "sg:tags":[
        "siding",
        "contractor"
    ],
    "wof:name":"J & A Siding",
    "wof:placetype":"venue"
},
  "geometry": {"coordinates":[-80.033575,33.021167],"type":"Point"}
}