{
  "type": "Feature",
  "properties": {
    "iso:country":"US",
    "sg:address":"86 Wentworth St",
    "sg:city":"Charleston",
    "sg:classifiers":[
        {
            "category":"Restaurant",
            "type":"Food & Drink"
        }
    ],
    "sg:phone":"+1 843 853 3287",
    "sg:postcode":"29401",
    "sg:province":"SC",
    "wof:name":"Yo Burrito",
    "wof:placetype":"venue"
},
  "geometry": {"coordinates":[-79.934034,32.782429],"type":"Point"}
}