{
  "type": "Feature",
  "properties": {
    "addr:full":"400 N Kings Hwy Myrtle Beach SC 29577",
    "addr:housenumber":"400",
    "addr:postcode":"29577",
    "addr:street":"N Kings Hwy",
    "iso:country":"US",
    "sg:address":"400 N Kings Hwy",
    "sg:city":"Myrtle Beach",
    "sg:classifiers":[
        {
            "category":"Shopping",
            "subcategory":"Used Merchandise",
            "type":"Retail Goods"
        }
    ],
    "sg:phone":"+1 843 946 7279",
    "sg:postcode":"29577",
    "sg:province":"SC",
    "sg:tags":[
        "shop",
        "thrift"
    ],
    "wof:name":"Salvation Army Thrift Store",
    "wof:placetype":"venue"
},
  "geometry": {"coordinates":[-78.886774,33.68982],"type":"Point"}
}