{
  "type": "Feature",
  "properties": {
    "addr:full":"3308 N Main St Anderson SC 29621",
    "addr:housenumber":"3308",
    "addr:postcode":"29621",
    "addr:street":"N Main St",
    "iso:country":"US",
    "sg:address":"3308 N Main St",
    "sg:city":"Anderson",
    "sg:classifiers":[
        {
            "category":"Manufacturing",
            "subcategory":"Printing",
            "type":"Manufacturing & Wholesale Goods"
        }
    ],
    "sg:phone":"+1 864 224 9115",
    "sg:postcode":"29621",
    "sg:province":"SC",
    "sg:tags":[
        "offset"
    ],
    "wof:name":"Minuteman Press",
    "wof:placetype":"venue"
},
  "geometry": {"coordinates":[-82.66821299999999,34.54196],"type":"Point"}
}