{
  "type": "Feature",
  "properties": {
    "iso:country":"US",
    "sg:address":"204 Mineral Springs Cir",
    "sg:city":"Lexington",
    "sg:classifiers":[
        {
            "category":"Manufacturing",
            "subcategory":"Building Materials",
            "type":"Manufacturing & Wholesale Goods"
        }
    ],
    "sg:phone":"+1 803 926 9237",
    "sg:postcode":"29170",
    "sg:province":"SC",
    "sg:tags":[
        "mfg",
        "wood",
        "kitchen",
        "cabinet"
    ],
    "wof:name":"Casteen Custom Cabinets & Trim",
    "wof:placetype":"venue"
},
  "geometry": {"coordinates":[-81.127146,33.994356],"type":"Point"}
}