{
  "type": "Feature",
  "properties": {
    "addr:full":"3585 Camden Hwy Dalzell SC 29040",
    "addr:housenumber":"3585",
    "addr:postcode":"29040",
    "addr:street":"Camden Hwy",
    "iso:country":"US",
    "sg:address":"3585 Camden Hwy",
    "sg:city":"Dalzell",
    "sg:classifiers":[
        {
            "category":"Food & Beverages",
            "subcategory":"Groceries & Convenience Stores",
            "type":"Retail Goods"
        }
    ],
    "sg:phone":"+1 803 469 0141",
    "sg:postcode":"29040",
    "sg:province":"SC",
    "sg:tags":[
        "grocer"
    ],
    "wof:name":"Rabon Sav-On",
    "wof:placetype":"venue"
},
  "geometry": {"coordinates":[-80.421384,34.014502],"type":"Point"}
}