{
  "type": "Feature",
  "properties": {
    "iso:country":"US",
    "sg:address":"137 Mont Clare Rd",
    "sg:city":"Darlington",
    "sg:classifiers":[
        {
            "category":"Organizations",
            "subcategory":"Religious Organization",
            "type":"Services"
        }
    ],
    "sg:phone":"+1 843 393 1140",
    "sg:postcode":"29540",
    "sg:province":"SC",
    "sg:tags":[
        "church"
    ],
    "wof:name":"Black Creek Baptist Church",
    "wof:placetype":"venue"
},
  "geometry": {"coordinates":[-79.893767,34.401682],"type":"Point"}
}