{
  "type": "Feature",
  "properties": {
    "iso:country":"US",
    "sg:address":"2916 Emanuel Church Rd",
    "sg:city":"West Columbia",
    "sg:classifiers":[
        {
            "category":"Cinema",
            "subcategory":"Movie Rental",
            "type":"Entertainment"
        }
    ],
    "sg:phone":"+1 803 808 3322",
    "sg:postcode":"29170",
    "sg:province":"SC",
    "sg:tags":[
        "game",
        "video"
    ],
    "sg:website":"www.blockbuster.com",
    "wof:name":"Blockbuster Video # 45061",
    "wof:placetype":"venue"
},
  "geometry": {"coordinates":[-81.170303,33.945702],"type":"Point"}
}