{
  "type": "Feature",
  "properties": {
    "iso:country":"US",
    "sg:address":"124 Gadsden St",
    "sg:city":"Chester",
    "sg:classifiers":[
        {
            "category":"Professional",
            "subcategory":"Lawyer & Legal Services",
            "type":"Services"
        }
    ],
    "sg:phone":"+1 803 385 2114",
    "sg:postcode":"29706",
    "sg:province":"SC",
    "sg:tags":[
        "attorney"
    ],
    "wof:name":"Gaston Gaston & Marion",
    "wof:placetype":"venue"
},
  "geometry": {"coordinates":[-81.212419,34.705334],"type":"Point"}
}