{
  "type": "Feature",
  "properties": {
    "iso:country":"US",
    "sg:address":"2611 Willow Creek Rd",
    "sg:city":"Effingham",
    "sg:classifiers":[
        {
            "category":"Manufacturing",
            "subcategory":"Tools & Machinery",
            "type":"Manufacturing & Wholesale Goods"
        }
    ],
    "sg:phone":"+1 843 667 6374",
    "sg:postcode":"29541",
    "sg:province":"SC",
    "sg:tags":[
        "machine",
        "shop"
    ],
    "wof:name":"Machine Shop",
    "wof:placetype":"venue"
},
  "geometry": {"coordinates":[-79.713829,34.085626],"type":"Point"}
}