{
  "type": "Feature",
  "properties": {
    "iso:country":"US",
    "sg:address":"9520 Hwy 81",
    "sg:city":"Iva",
    "sg:classifiers":[
        {
            "category":"Building & Trades",
            "subcategory":"Construction",
            "type":"Services"
        }
    ],
    "sg:phone":"+1 864 348 2384",
    "sg:postcode":"29655",
    "sg:province":"SC",
    "sg:tags":[
        "excavation",
        "contractor"
    ],
    "wof:name":"Seawright Construction",
    "wof:placetype":"venue"
},
  "geometry": {"coordinates":[-82.669504,34.324858],"type":"Point"}
}