{
  "type": "Feature",
  "properties": {
    "iso:country":"US",
    "sg:address":"107 Virginia St",
    "sg:city":"Chapin",
    "sg:classifiers":[
        {
            "category":"Organizations",
            "subcategory":"Religious Organization",
            "type":"Services"
        }
    ],
    "sg:phone":"+1 803 932 4821",
    "sg:postcode":"29036",
    "sg:province":"SC",
    "sg:tags":[
        "church"
    ],
    "sg:website":"www.chapinpres.com",
    "wof:name":"Chapin Presbyterian Church",
    "wof:placetype":"venue"
},
  "geometry": {"coordinates":[-81.355383,34.166201],"type":"Point"}
}