{
  "type": "Feature",
  "properties": {
    "addr:full":"84 Villa Rd Greenville SC 29615",
    "addr:housenumber":"84",
    "addr:postcode":"29615",
    "addr:street":"Villa Rd",
    "iso:country":"US",
    "sg:address":"84 Villa Rd",
    "sg:city":"Greenville",
    "sg:classifiers":[
        {
            "category":"Professional",
            "subcategory":"Advertising",
            "type":"Services"
        }
    ],
    "sg:phone":"+1 864 271 6000",
    "sg:postcode":"29615",
    "sg:province":"SC",
    "sg:tags":[
        "counselor"
    ],
    "sg:website":"www.hendersonadv.com",
    "wof:name":"Henderson Advertising",
    "wof:placetype":"venue"
},
  "geometry": {"coordinates":[-82.34302,34.857451],"type":"Point"}
}