{
  "type": "Feature",
  "properties": {
    "addr:full":"2080 Northbrook Blvd Charleston SC 29406",
    "addr:housenumber":"2080",
    "addr:postcode":"29406",
    "addr:street":"Northbrook Blvd",
    "iso:country":"US",
    "sg:address":"2080 Northbrook Blvd",
    "sg:city":"Charleston",
    "sg:classifiers":[
        {
            "category":"Insurance",
            "subcategory":"Insurance Agent",
            "type":"Services"
        }
    ],
    "sg:phone":"+1 843 553 9963",
    "sg:postcode":"29406",
    "sg:province":"SC",
    "wof:name":"Direct General Ins Agency",
    "wof:placetype":"venue"
},
  "geometry": {"coordinates":[-80.041124,32.949022],"type":"Point"}
}