{
  "type": "Feature",
  "properties": {
    "addr:full":"1233 Boiling Springs Rd Spartanburg SC 29303",
    "addr:housenumber":"1233",
    "addr:postcode":"29303",
    "addr:street":"Boiling Springs Rd",
    "iso:country":"US",
    "sg:address":"1233 Boiling Springs Rd",
    "sg:city":"Spartanburg",
    "sg:classifiers":[
        {
            "category":"Shopping",
            "subcategory":"Pharmacy",
            "type":"Retail Goods"
        }
    ],
    "sg:phone":"+1 864 582 8280",
    "sg:postcode":"29303",
    "sg:province":"SC",
    "wof:name":"White Oak Pharmacy",
    "wof:placetype":"venue"
},
  "geometry": {"coordinates":[-81.94651500000001,34.989535],"type":"Point"}
}