{
  "type": "Feature",
  "properties": {
    "iso:country":"US",
    "sg:address":"302 Rock Creek Dr",
    "sg:city":"Greenville",
    "sg:classifiers":[
        {
            "category":"Wholesale",
            "subcategory":"Apparel",
            "type":"Manufacturing & Wholesale Goods"
        }
    ],
    "sg:phone":"+1 864 233 0325",
    "sg:postcode":"29605",
    "sg:province":"SC",
    "sg:tags":[
        "piece"
    ],
    "wof:name":"Pronto Labels",
    "wof:placetype":"venue"
},
  "geometry": {"coordinates":[-82.379668,34.823021],"type":"Point"}
}