{
  "type": "Feature",
  "properties": {
    "iso:country":"US",
    "sg:address":"4829 Seewee Rd",
    "sg:city":"Awendaw",
    "sg:classifiers":[
        {
            "category":"Health Services",
            "subcategory":"Hospital",
            "type":"Services"
        }
    ],
    "sg:phone":"+1 843 881 6929",
    "sg:postcode":"29429",
    "sg:province":"SC",
    "sg:tags":[
        "mental"
    ],
    "wof:name":"Atwater Counseling Ctr Inc",
    "wof:placetype":"venue"
},
  "geometry": {"coordinates":[-79.713316,32.925697],"type":"Point"}
}