{
  "type": "Feature",
  "properties": {
    "iso:country":"US",
    "sg:address":"1491 Astley Rd",
    "sg:city":"Mt Pleasant",
    "sg:classifiers":[
        {
            "category":"Building & Trades",
            "subcategory":"Construction",
            "type":"Services"
        }
    ],
    "sg:phone":"+1 843 856 9813",
    "sg:postcode":"29464",
    "sg:province":"SC",
    "sg:tags":[
        "painter"
    ],
    "wof:name":"Bell Painting",
    "wof:placetype":"venue"
},
  "geometry": {"coordinates":[-79.83596900000001,32.804865],"type":"Point"}
}