{
  "type": "Feature",
  "properties": {
    "iso:country":"US",
    "sg:address":"4593 Oleander Dr",
    "sg:city":"Myrtle Beach",
    "sg:classifiers":[
        {
            "category":"Professional",
            "subcategory":"Lawyer & Legal Services",
            "type":"Services"
        }
    ],
    "sg:phone":"+1 843 449 9417",
    "sg:postcode":"29577",
    "sg:province":"SC",
    "sg:tags":[
        "attorney"
    ],
    "wof:name":"Newby Pridgen Sartip & Masel",
    "wof:placetype":"venue"
},
  "geometry": {"coordinates":[-78.863672,33.730537],"type":"Point"}
}