{
  "type": "Feature",
  "properties": {
    "addr:full":"418 Anderson Ridge Rd Greer SC 29651",
    "addr:housenumber":"418",
    "addr:postcode":"29651",
    "addr:street":"Anderson Ridge Rd",
    "iso:country":"US",
    "sg:address":"418 Anderson Ridge Rd",
    "sg:city":"Greer",
    "sg:classifiers":[
        {
            "category":"Building & Trades",
            "subcategory":"Construction",
            "type":"Services"
        }
    ],
    "sg:phone":"+1 864 281 9525",
    "sg:postcode":"29651",
    "sg:province":"SC",
    "sg:tags":[
        "hanging",
        "contractor"
    ],
    "wof:name":"Lisa Painter",
    "wof:placetype":"venue"
},
  "geometry": {"coordinates":[-82.21566199999999,34.824837],"type":"Point"}
}