{
  "type": "Feature",
  "properties": {
    "iso:country":"US",
    "sg:address":"2093 Henry Teckenburg Dr",
    "sg:city":"Charleston",
    "sg:classifiers":[
        {
            "category":"Health Services",
            "subcategory":"Health Practitioner",
            "type":"Services"
        }
    ],
    "sg:phone":"+1 843 958 2505",
    "sg:postcode":"29414",
    "sg:province":"SC",
    "sg:tags":[
        "therapist",
        "physical"
    ],
    "wof:name":"Rehabilitation Centers",
    "wof:placetype":"venue"
},
  "geometry": {"coordinates":[-80.043543,32.810969],"type":"Point"}
}