{
  "type": "Feature",
  "properties": {
    "iso:country":"US",
    "sg:address":"131 Alpha Dr",
    "sg:city":"Greenville",
    "sg:classifiers":[
        {
            "category":"Personal",
            "subcategory":"Beauty Salon",
            "type":"Services"
        }
    ],
    "sg:phone":"+1 864 422 1900",
    "sg:postcode":"29605",
    "sg:province":"SC",
    "wof:name":"Mrs Young",
    "wof:placetype":"venue"
},
  "geometry": {"coordinates":[-82.402732,34.775799],"type":"Point"}
}