{
  "type": "Feature",
  "properties": {
    "iso:country":"US",
    "sg:address":"112 Colonial Ave",
    "sg:city":"Greenville",
    "sg:classifiers":[
        {
            "category":"Building & Trades",
            "subcategory":"Construction",
            "type":"Services"
        }
    ],
    "sg:phone":"+1 864 288 2493",
    "sg:postcode":"29611",
    "sg:province":"SC",
    "sg:tags":[
        "painter"
    ],
    "wof:name":"Howard Pirkle Painting",
    "wof:placetype":"venue"
},
  "geometry": {"coordinates":[-82.426115,34.871316],"type":"Point"}
}