{
  "type": "Feature",
  "properties": {
    "addr:full":"314 N Congress St Winnsboro SC 29180",
    "addr:housenumber":"314",
    "addr:postcode":"29180",
    "addr:street":"N Congress St",
    "iso:country":"US",
    "sg:address":"314 N Congress St",
    "sg:city":"Winnsboro",
    "sg:classifiers":[
        {
            "category":"Personal",
            "subcategory":"Barber",
            "type":"Services"
        }
    ],
    "sg:phone":"+1 803 635 6620",
    "sg:postcode":"29180",
    "sg:province":"SC",
    "wof:name":"Heath's Barber Shop",
    "wof:placetype":"venue"
},
  "geometry": {"coordinates":[-81.088301,34.386066],"type":"Point"}
}