{
  "type": "Feature",
  "properties": {
    "iso:country":"US",
    "sg:address":"3528 Earle E Morris Jr Hwy",
    "sg:city":"Greenville",
    "sg:classifiers":[
        {
            "category":"Shopping",
            "subcategory":"Gifts & Souvenirs",
            "type":"Retail Goods"
        }
    ],
    "sg:phone":"+1 864 605 1083",
    "sg:postcode":"29611",
    "sg:province":"SC",
    "sg:tags":[
        "shop"
    ],
    "wof:name":"Thoughts Of You LTD",
    "wof:placetype":"venue"
},
  "geometry": {"coordinates":[-82.48576300000001,34.789888],"type":"Point"}
}