{
  "type": "Feature",
  "properties": {
    "iso:country":"US",
    "sg:address":"5801 Liberty Chapel Rd",
    "sg:city":"Florence",
    "sg:classifiers":[
        {
            "category":"Building & Trades",
            "subcategory":"Landscaping Services",
            "type":"Services"
        }
    ],
    "sg:phone":"+1 843 665 7273",
    "sg:postcode":"29506",
    "sg:province":"SC",
    "wof:name":"B & C Pumping & Drain Line Svc",
    "wof:placetype":"venue"
},
  "geometry": {"coordinates":[-79.620436,34.176738],"type":"Point"}
}