{
  "type": "Feature",
  "properties": {
    "addr:full":"320 Haywood Rd Greenville SC 29607",
    "addr:housenumber":"320",
    "addr:postcode":"29607",
    "addr:street":"Haywood Rd",
    "iso:country":"US",
    "sg:address":"320 Haywood Rd",
    "sg:city":"Greenville",
    "sg:classifiers":[
        {
            "category":"Shopping",
            "subcategory":"Gifts & Souvenirs",
            "type":"Retail Goods"
        }
    ],
    "sg:phone":"+1 864 288 1270",
    "sg:postcode":"29607",
    "sg:province":"SC",
    "sg:tags":[
        "party",
        "supply"
    ],
    "wof:name":"Christmas Tree Corner",
    "wof:placetype":"venue"
},
  "geometry": {"coordinates":[-82.343067,34.841453],"type":"Point"}
}