{
  "type": "Feature",
  "properties": {
    "addr:full":"3809 Socastee Blvd Myrtle Beach SC 29588",
    "addr:housenumber":"3809",
    "addr:postcode":"29588",
    "addr:street":"Socastee Blvd",
    "iso:country":"US",
    "sg:address":"3809 Socastee Blvd",
    "sg:city":"Myrtle Beach",
    "sg:classifiers":[
        {
            "category":"Retail",
            "subcategory":"Auto Repair",
            "type":"Services"
        }
    ],
    "sg:phone":"+1 843 293 7077",
    "sg:postcode":"29588",
    "sg:province":"SC",
    "sg:tags":[
        "repairing",
        "automobile"
    ],
    "wof:name":"Socastee Automotive Mntnc Svc",
    "wof:placetype":"venue"
},
  "geometry": {"coordinates":[-78.967088,33.685039],"type":"Point"}
}