{
  "type": "Feature",
  "properties": {
    "addr:full":"1176 John C Calhoun Dr Orangeburg SC 29115",
    "addr:housenumber":"1176",
    "addr:postcode":"29115",
    "addr:street":"John C Calhoun Dr",
    "iso:country":"US",
    "sg:address":"1176 John C Calhoun Dr",
    "sg:city":"Orangeburg",
    "sg:classifiers":[
        {
            "category":"Restaurant",
            "type":"Food & Drink"
        }
    ],
    "sg:phone":"+1 803 531 3444",
    "sg:postcode":"29115",
    "sg:province":"SC",
    "wof:name":"Central Park USA",
    "wof:placetype":"venue"
},
  "geometry": {"coordinates":[-80.86414600000001,33.485647],"type":"Point"}
}