{
  "type": "Feature",
  "properties": {
    "iso:country":"US",
    "sg:address":"506 River St",
    "sg:city":"Belton",
    "sg:classifiers":[
        {
            "category":"Retail",
            "subcategory":"Repair Shop",
            "type":"Services"
        }
    ],
    "sg:phone":"+1 864 338 7020",
    "sg:postcode":"29627",
    "sg:province":"SC",
    "sg:tags":[
        "welding"
    ],
    "wof:name":"Industrial Maintenance Svc",
    "wof:placetype":"venue"
},
  "geometry": {"coordinates":[-82.484544,34.527284],"type":"Point"}
}