{
  "type": "Feature",
  "properties": {
    "addr:full":"129 S Main St Mc Cormick SC 29835",
    "addr:housenumber":"129",
    "addr:postcode":"29835",
    "addr:street":"S Main St Mc Cormick",
    "iso:country":"US",
    "sg:address":"129 S Main St",
    "sg:city":"Mc Cormick",
    "sg:classifiers":[
        {
            "category":"Insurance",
            "subcategory":"Insurance Agent",
            "type":"Services"
        }
    ],
    "sg:phone":"+1 864 465 9301",
    "sg:postcode":"29835",
    "sg:province":"SC",
    "wof:name":"Clyde King",
    "wof:placetype":"venue"
},
  "geometry": {"coordinates":[-82.29346099999999,33.911728],"type":"Point"}
}