{
  "type": "Feature",
  "properties": {
    "iso:country":"US",
    "sg:address":"1417 Laurens Rd",
    "sg:city":"Greenville",
    "sg:classifiers":[
        {
            "category":"Manufacturing",
            "subcategory":"Signs",
            "type":"Manufacturing & Wholesale Goods"
        }
    ],
    "sg:phone":"+1 864 233 4659",
    "sg:postcode":"29607",
    "sg:province":"SC",
    "sg:website":"www.signsnow.com",
    "wof:name":"Signs Now",
    "wof:placetype":"venue"
},
  "geometry": {"coordinates":[-82.362635,34.843294],"type":"Point"}
}