{
  "type": "Feature",
  "properties": {
    "iso:country":"US",
    "sg:address":"2811 Reidville Rd",
    "sg:city":"Spartanburg",
    "sg:classifiers":[
        {
            "category":"Food & Beverages",
            "subcategory":"Groceries & Convenience Stores",
            "type":"Retail Goods"
        }
    ],
    "sg:phone":"+1 864 587 1009",
    "sg:postcode":"29301",
    "sg:province":"SC",
    "sg:tags":[
        "gasoline"
    ],
    "wof:name":"Fast Point Food Store Office",
    "wof:placetype":"venue"
},
  "geometry": {"coordinates":[-82.003669,34.916908],"type":"Point"}
}