{
  "type": "Feature",
  "properties": {
    "iso:country":"US",
    "sg:address":"8505 White Horse Rd",
    "sg:city":"Greenville",
    "sg:classifiers":[
        {
            "category":"Real Estate",
            "subcategory":"Real Estate Operator",
            "type":"Services"
        }
    ],
    "sg:phone":"+1 864 246 0183",
    "sg:postcode":"29617",
    "sg:province":"SC",
    "sg:tags":[
        "mobile",
        "home",
        "site"
    ],
    "wof:name":"Park West Mobile Homes",
    "wof:placetype":"venue"
},
  "geometry": {"coordinates":[-82.460714,34.908832],"type":"Point"}
}