{
  "type": "Feature",
  "properties": {
    "addr:full":"208 Scott St Mt Pleasant SC 29464",
    "addr:housenumber":"208",
    "addr:postcode":"29464",
    "addr:street":"Scott St",
    "iso:country":"US",
    "sg:address":"208 Scott St",
    "sg:city":"Mt Pleasant",
    "sg:classifiers":[
        {
            "category":"Health Services",
            "subcategory":"Health Practitioner",
            "type":"Services"
        }
    ],
    "sg:phone":"+1 843 884 7710",
    "sg:postcode":"29464",
    "sg:province":"SC",
    "sg:tags":[
        "psychotherapist"
    ],
    "wof:name":"Carole Bennett",
    "wof:placetype":"venue"
},
  "geometry": {"coordinates":[-79.876327,32.791626],"type":"Point"}
}