{
  "type": "Feature",
  "properties": {
    "iso:country":"US",
    "sg:address":"1302 N Cashua Dr",
    "sg:city":"Florence",
    "sg:classifiers":[
        {
            "category":"Autos & Motor Vehicles",
            "subcategory":"Automobile Sales",
            "type":"Retail Goods"
        }
    ],
    "sg:phone":"+1 843 665 7397",
    "sg:postcode":"29501",
    "sg:province":"SC",
    "sg:tags":[
        "car",
        "dealer"
    ],
    "wof:name":"Palmetto Consignments Used Car",
    "wof:placetype":"venue"
},
  "geometry": {"coordinates":[-79.796892,34.217428],"type":"Point"}
}