{
  "type": "Feature",
  "properties": {
    "iso:country":"US",
    "sg:address":"480 Beech Island Ave",
    "sg:city":"Beech Island",
    "sg:classifiers":[
        {
            "category":"Utilities",
            "subcategory":"Water",
            "type":"Services"
        }
    ],
    "sg:phone":"+1 803 827 1004",
    "sg:postcode":"29842",
    "sg:province":"SC",
    "sg:tags":[
        "system",
        "supply"
    ],
    "wof:name":"Beech Island Rur Cmnty Wtr Dst",
    "wof:placetype":"venue"
},
  "geometry": {"coordinates":[-81.871045,33.436315],"type":"Point"}
}