{
  "type": "Feature",
  "properties": {
    "iso:country":"US",
    "sg:address":"Taylor At Marion",
    "sg:city":"Columbia",
    "sg:classifiers":[
        {
            "category":"Health Services",
            "subcategory":"Hospital",
            "type":"Services"
        }
    ],
    "sg:phone":"+1 803 296 5010",
    "sg:postcode":"29201",
    "sg:province":"SC",
    "wof:name":"Baptist Medical Ctr Palmetto Baptist Medical Ctr",
    "wof:placetype":"venue"
},
  "geometry": {"coordinates":[-81.037003,34.000301],"type":"Point"}
}