{
  "type": "Feature",
  "properties": {
    "iso:country":"US",
    "sg:address":"4009 Pelham Ct",
    "sg:city":"Greer",
    "sg:classifiers":[
        {
            "category":"Home & Garden",
            "subcategory":"Building Materials",
            "type":"Retail Goods"
        },
        {
            "category":"Building & Trades",
            "subcategory":"Construction",
            "type":"Services"
        }
    ],
    "sg:phone":"+1 864 233 9277",
    "sg:postcode":"29650",
    "sg:province":"SC",
    "sg:tags":[
        "door",
        "nonresidential"
    ],
    "wof:name":"Precision Ovrhd Gar Door Svc",
    "wof:placetype":"venue"
},
  "geometry": {"coordinates":[-82.230481,34.852813],"type":"Point"}
}