{
  "type": "Feature",
  "properties": {
    "iso:country":"US",
    "sg:address":"320 Clarendon St SE",
    "sg:city":"Orangeburg",
    "sg:classifiers":[
        {
            "category":"Social Services",
            "subcategory":"Child Care",
            "type":"Services"
        }
    ],
    "sg:phone":"+1 803 533 0364",
    "sg:postcode":"29115",
    "sg:province":"SC",
    "wof:name":"ABC'S & 123's Children Day",
    "wof:placetype":"venue"
},
  "geometry": {"coordinates":[-80.846388,33.493],"type":"Point"}
}