{
  "type": "Feature",
  "properties": {
    "iso:country":"US",
    "sg:address":"150 Litton Dr",
    "sg:city":"Lexington",
    "sg:classifiers":[
        {
            "category":"Building & Trades",
            "subcategory":"Construction",
            "type":"Services"
        }
    ],
    "sg:phone":"+1 803 359 0096",
    "sg:postcode":"29073",
    "sg:province":"SC",
    "sg:tags":[
        "residential"
    ],
    "wof:name":"Bracebridge Construction",
    "wof:placetype":"venue"
},
  "geometry": {"coordinates":[-81.23875700000001,33.954224],"type":"Point"}
}