{
  "type": "Feature",
  "properties": {
    "iso:country":"US",
    "sg:address":"1301 Greenville Hwy",
    "sg:city":"Greenville",
    "sg:classifiers":[
        {
            "category":"Utilities",
            "subcategory":"Fuel Oil & Lpg",
            "type":"Services"
        }
    ],
    "sg:phone":"+1 864 235 7789",
    "sg:postcode":"29657",
    "sg:province":"SC",
    "sg:tags":[
        "propane",
        "gas"
    ],
    "wof:name":"Synergy Gas",
    "wof:placetype":"venue"
},
  "geometry": {"coordinates":[-82.73211999999999,34.775845],"type":"Point"}
}