{
  "type": "Feature",
  "properties": {
    "iso:country":"US",
    "sg:address":"382 Rolling Mill Rd",
    "sg:city":"Gaffney",
    "sg:classifiers":[
        {
            "category":"Building & Trades",
            "subcategory":"Construction",
            "type":"Services"
        }
    ],
    "sg:phone":"+1 864 489 5039",
    "sg:postcode":"29340",
    "sg:province":"SC",
    "sg:tags":[
        "maker",
        "cabinet"
    ],
    "wof:name":"Mc Kown's Custom Cabinets",
    "wof:placetype":"venue"
},
  "geometry": {"coordinates":[-81.543302,35.035054],"type":"Point"}
}