{
  "type": "Feature",
  "properties": {
    "addr:full":"3514 Old Buncombe Rd Greenville SC 29617",
    "addr:housenumber":"3514",
    "addr:postcode":"29617",
    "addr:street":"Old Buncombe Rd",
    "iso:country":"US",
    "sg:address":"3514 Old Buncombe Rd",
    "sg:city":"Greenville",
    "sg:classifiers":[
        {
            "category":"Building & Trades",
            "subcategory":"Construction",
            "type":"Services"
        },
        {
            "category":"Building & Trades",
            "subcategory":"Electrical",
            "type":"Services"
        },
        {
            "category":"Home & Garden",
            "subcategory":"Household Appliances",
            "type":"Retail Goods"
        },
        {
            "category":"Home & Garden",
            "subcategory":"Building Materials",
            "type":"Retail Goods"
        },
        {
            "category":"Real Estate",
            "subcategory":"Real Estate Services",
            "type":"Services"
        },
        {
            "category":"Professional",
            "subcategory":"Engineering",
            "type":"Services"
        },
        {
            "category":"Building & Trades",
            "subcategory":"Cleaning & Sanitation",
            "type":"Services"
        }
    ],
    "sg:phone":"+1 864 421 0289",
    "sg:postcode":"29617",
    "sg:province":"SC",
    "sg:tags":[
        "repair",
        "industrial",
        "electrician",
        "electric",
        "pump",
        "duct",
        "system",
        "specialty",
        "equipment",
        "furnaces-heating",
        "heating",
        "contractors-commercial",
        "maintenance",
        "contractor",
        "heat",
        "air conditioning"
    ],
    "sg:website":"http://clemson.aireserv.com/",
    "wof:name":"Aire Serv Of Clemson",
    "wof:placetype":"venue"
},
  "geometry": {"coordinates":[-82.428029,34.885804],"type":"Point"}
}