{
  "type": "Feature",
  "properties": {
    "addr:full":"1521 Sunset Blvd West Columbia SC 29169",
    "addr:housenumber":"1521",
    "addr:postcode":"29169",
    "addr:street":"Sunset Blvd",
    "iso:country":"US",
    "sg:address":"1521 Sunset Blvd",
    "sg:city":"West Columbia",
    "sg:classifiers":[
        {
            "category":"Professional",
            "subcategory":"Accounting & Tax Preparation",
            "type":"Services"
        }
    ],
    "sg:phone":"+1 803 791 1040",
    "sg:postcode":"29169",
    "sg:province":"SC",
    "sg:tags":[
        "accountant"
    ],
    "wof:name":"Hutto John R AP Mba",
    "wof:placetype":"venue"
},
  "geometry": {"coordinates":[-81.084396,33.998501],"type":"Point"}
}