{
  "type": "Feature",
  "properties": {
    "iso:country":"US",
    "sg:address":"401 Old Canaan Rd",
    "sg:city":"Spartanburg",
    "sg:classifiers":[
        {
            "category":"Food & Beverages",
            "subcategory":"Groceries & Convenience Stores",
            "type":"Retail Goods"
        }
    ],
    "sg:phone":"+1 864 583 6752",
    "sg:postcode":"29306",
    "sg:province":"SC",
    "sg:tags":[
        "grocer"
    ],
    "wof:name":"Abernathy's Grocery",
    "wof:placetype":"venue"
},
  "geometry": {"coordinates":[-81.932915,34.891676],"type":"Point"}
}