{
  "type": "Feature",
  "properties": {
    "iso:country":"US",
    "sg:address":"1150 E Main St",
    "sg:city":"Rock Hill",
    "sg:classifiers":[
        {
            "category":"Manufacturing",
            "subcategory":"Retail Goods",
            "type":"Manufacturing & Wholesale Goods"
        }
    ],
    "sg:phone":"+1 803 329 2434",
    "sg:postcode":"29730",
    "sg:province":"SC",
    "sg:tags":[
        "manufacturer"
    ],
    "wof:name":"Assembli Tek Industries",
    "wof:placetype":"venue"
},
  "geometry": {"coordinates":[-81.007559,34.916821],"type":"Point"}
}