{
  "type": "Feature",
  "properties": {
    "addr:full":"1131 48th Ave N Myrtle Beach SC 29577",
    "addr:housenumber":"1131",
    "addr:postcode":"29577",
    "addr:street":"48Th Ave N",
    "iso:country":"US",
    "sg:address":"1131 48th Ave N",
    "sg:city":"Myrtle Beach",
    "sg:classifiers":[
        {
            "category":"Real Estate",
            "subcategory":"Architect",
            "type":"Services"
        }
    ],
    "sg:phone":"+1 843 449 5202",
    "sg:postcode":"29577",
    "sg:province":"SC",
    "wof:name":"Pegram Associates Inc",
    "wof:placetype":"venue"
},
  "geometry": {"coordinates":[-78.859134,33.732642],"type":"Point"}
}