{
  "type": "Feature",
  "properties": {
    "iso:country":"US",
    "sg:address":"102 Dowling St",
    "sg:city":"Easley",
    "sg:classifiers":[
        {
            "category":"Social Services",
            "subcategory":"Adult Care",
            "type":"Services"
        }
    ],
    "sg:phone":"+1 864 859 3722",
    "sg:postcode":"29640",
    "sg:province":"SC",
    "sg:tags":[
        "home",
        "residential"
    ],
    "wof:name":"Easley Retirement Ctr",
    "wof:placetype":"venue"
},
  "geometry": {"coordinates":[-82.577242,34.834774],"type":"Point"}
}