{
  "type": "Feature",
  "properties": {
    "iso:country":"US",
    "sg:address":"1309 Enterprise Ave",
    "sg:city":"Myrtle Beach",
    "sg:classifiers":[
        {
            "category":"Building & Trades",
            "subcategory":"Landscaping Services",
            "type":"Services"
        }
    ],
    "sg:phone":"+1 843 444 0023",
    "sg:postcode":"29577",
    "sg:province":"SC",
    "sg:tags":[
        "landscape",
        "contractor"
    ],
    "wof:name":"Evergreen Landscaping",
    "wof:placetype":"venue"
},
  "geometry": {"coordinates":[-78.903555,33.708423],"type":"Point"}
}