{
  "type": "Feature",
  "properties": {
    "iso:country":"US",
    "sg:address":"118 Church Rd",
    "sg:city":"St Stephen",
    "sg:classifiers":[
        {
            "category":"Personal",
            "subcategory":"Barber",
            "type":"Services"
        }
    ],
    "sg:phone":"+1 843 567 7105",
    "sg:postcode":"29479",
    "sg:province":"SC",
    "wof:name":"Jenkins Barber Shop",
    "wof:placetype":"venue"
},
  "geometry": {"coordinates":[-79.923874,33.405288],"type":"Point"}
}