{
  "type": "Feature",
  "properties": {
    "iso:country":"US",
    "sg:address":"200 Miracle Mile Dr",
    "sg:city":"Anderson",
    "sg:classifiers":[
        {
            "category":"Real Estate",
            "subcategory":"Real Estate Operator",
            "type":"Services"
        }
    ],
    "sg:phone":"+1 864 225 7803",
    "sg:postcode":"29621",
    "sg:province":"SC",
    "sg:tags":[
        "apartment"
    ],
    "wof:name":"Anderson Village Apartments",
    "wof:placetype":"venue"
},
  "geometry": {"coordinates":[-82.668201,34.547605],"type":"Point"}
}