{
  "type": "Feature",
  "properties": {
    "addr:full":"7068 Nursery Rd Columbia SC 29212",
    "addr:housenumber":"7068",
    "addr:postcode":"29212",
    "addr:street":"Nursery Rd",
    "iso:country":"US",
    "sg:address":"7068 Nursery Rd",
    "sg:city":"Columbia",
    "sg:classifiers":[
        {
            "category":"Organizations",
            "subcategory":"Religious Organization",
            "type":"Services"
        }
    ],
    "sg:phone":"+1 803 781 1345",
    "sg:postcode":"29212",
    "sg:province":"SC",
    "sg:tags":[
        "church"
    ],
    "sg:website":"www.firstbaptistirmo.org",
    "wof:name":"First Baptist Church Of Irmo",
    "wof:placetype":"venue"
},
  "geometry": {"coordinates":[-81.194136,34.077287],"type":"Point"}
}