{
  "type": "Feature",
  "properties": {
    "iso:country":"US",
    "sg:address":"3385 Brushy Creek Rd",
    "sg:city":"Greer",
    "sg:classifiers":[
        {
            "category":"Building & Trades",
            "subcategory":"Plumbing",
            "type":"Services"
        }
    ],
    "sg:phone":"+1 864 208 8000",
    "sg:postcode":"29650",
    "sg:province":"SC",
    "sg:tags":[
        "conditioning",
        "air",
        "system",
        "contractor"
    ],
    "wof:name":"TSC/The Svc Co",
    "wof:placetype":"venue"
},
  "geometry": {"coordinates":[-82.249561,34.924295],"type":"Point"}
}