{
  "type": "Feature",
  "properties": {
    "addr:full":"1545 Falls Rd Rock Hill SC 29730",
    "addr:housenumber":"1545",
    "addr:postcode":"29730",
    "addr:street":"Falls Rd",
    "iso:country":"US",
    "sg:address":"1545 Falls Rd",
    "sg:city":"Rock Hill",
    "sg:classifiers":[
        {
            "category":"Shopping",
            "type":"Retail Goods"
        }
    ],
    "sg:phone":"+1 803 980 0500",
    "sg:postcode":"29730",
    "sg:province":"SC",
    "sg:tags":[
        "equipment",
        "telephone",
        "supply"
    ],
    "wof:name":"Communication Networks Corp",
    "wof:placetype":"venue"
},
  "geometry": {"coordinates":[-81.09348199999999,34.925169],"type":"Point"}
}