{
  "type": "Feature",
  "properties": {
    "iso:country":"US",
    "sg:address":"1728 Main St",
    "sg:city":"Columbia",
    "sg:classifiers":[
        {
            "category":"Professional",
            "subcategory":"Lawyer & Legal Services",
            "type":"Services"
        }
    ],
    "sg:phone":"+1 803 252 7046",
    "sg:postcode":"29201",
    "sg:province":"SC",
    "sg:tags":[
        "attorney"
    ],
    "wof:name":"Jimie Rogers Law Office",
    "wof:placetype":"venue"
},
  "geometry": {"coordinates":[-81.036853,34.008934],"type":"Point"}
}