{
  "type": "Feature",
  "properties": {
    "addr:full":"760 Foot Hills Rd Greenville SC 29617",
    "addr:housenumber":"760",
    "addr:postcode":"29617",
    "addr:street":"Foot Hills Rd",
    "iso:country":"US",
    "sg:address":"760 Foot Hills Rd",
    "sg:city":"Greenville",
    "sg:classifiers":[
        {
            "category":"Recreation",
            "type":"Entertainment"
        }
    ],
    "sg:phone":"+1 864 246 4441",
    "sg:postcode":"29617",
    "sg:province":"SC",
    "sg:tags":[
        "stable"
    ],
    "wof:name":"Valley Stables",
    "wof:placetype":"venue"
},
  "geometry": {"coordinates":[-82.45256999999999,34.943973],"type":"Point"}
}