{
  "type": "Feature",
  "properties": {
    "addr:full":"1103 Bur Dr Dillon SC 29536",
    "addr:housenumber":"1103",
    "addr:postcode":"29536",
    "addr:street":"Bur Dr",
    "iso:country":"US",
    "sg:address":"1103 Bur Dr",
    "sg:city":"Dillon",
    "sg:classifiers":[
        {
            "category":"Freight",
            "type":"Transportation"
        }
    ],
    "sg:phone":"+1 843 841 0318",
    "sg:postcode":"29536",
    "sg:province":"SC",
    "sg:tags":[
        "operator",
        "trucking"
    ],
    "wof:name":"Timmy L Lenhart",
    "wof:placetype":"venue"
},
  "geometry": {"coordinates":[-79.326065,34.355051],"type":"Point"}
}