{
  "type": "Feature",
  "properties": {
    "addr:full":"2701 Church St Conway SC 29526",
    "addr:housenumber":"2701",
    "addr:postcode":"29526",
    "addr:street":"Church St",
    "iso:country":"US",
    "sg:address":"2701 Church St",
    "sg:city":"Conway",
    "sg:classifiers":[
        {
            "category":"Shopping",
            "subcategory":"Department Store",
            "type":"Retail Goods"
        }
    ],
    "sg:phone":"+1 843 365 9556",
    "sg:postcode":"29526",
    "sg:province":"SC",
    "sg:tags":[
        "shop"
    ],
    "sg:website":"www.dollartree.com",
    "wof:name":"Dollar Tree",
    "wof:placetype":"venue"
},
  "geometry": {"coordinates":[-79.088694,33.859511],"type":"Point"}
}