{
  "type": "Feature",
  "properties": {
    "addr:full":"33 W Liberty St Sumter SC 29150",
    "addr:housenumber":"33",
    "addr:postcode":"29150",
    "addr:street":"W Liberty St",
    "iso:country":"US",
    "sg:address":"33 W Liberty St",
    "sg:city":"Sumter",
    "sg:classifiers":[
        {
            "category":"Real Estate",
            "subcategory":"Real Estate Agent",
            "type":"Services"
        }
    ],
    "sg:phone":"+1 803 778 2144",
    "sg:postcode":"29150",
    "sg:province":"SC",
    "sg:tags":[
        "investment"
    ],
    "wof:name":"ORC LLC",
    "wof:placetype":"venue"
},
  "geometry": {"coordinates":[-80.34322299999999,33.920574],"type":"Point"}
}