{
  "type": "Feature",
  "properties": {
    "iso:country":"US",
    "sg:address":"1486 Juniper Rd",
    "sg:city":"Olar",
    "sg:classifiers":[
        {
            "category":"Organizations",
            "subcategory":"Religious Organization",
            "type":"Services"
        }
    ],
    "sg:phone":"+1 803 793 3409",
    "sg:postcode":"29843",
    "sg:province":"SC",
    "sg:tags":[
        "church"
    ],
    "wof:name":"Georges Creek Baptist Church",
    "wof:placetype":"venue"
},
  "geometry": {"coordinates":[-81.23051,33.202251],"type":"Point"}
}