{
  "type": "Feature",
  "properties": {
    "addr:full":"6810 Garners Ferry Rd Columbia SC 29209",
    "addr:housenumber":"6810",
    "addr:postcode":"29209",
    "addr:street":"Garners Ferry Rd",
    "iso:country":"US",
    "sg:address":"6810 Garners Ferry Rd",
    "sg:city":"Columbia",
    "sg:classifiers":[
        {
            "category":"Shopping",
            "subcategory":"Clothing, Apparel, & Fashions",
            "type":"Retail Goods"
        }
    ],
    "sg:phone":"+1 803 776 4999",
    "sg:postcode":"29209",
    "sg:province":"SC",
    "sg:tags":[
        "florist"
    ],
    "wof:name":"Cedar Florist & Gift Shop",
    "wof:placetype":"venue"
},
  "geometry": {"coordinates":[-80.95759,33.976201],"type":"Point"}
}