{
  "type": "Feature",
  "properties": {
    "iso:country":"US",
    "sg:address":"908 S Parker Dr",
    "sg:city":"Florence",
    "sg:classifiers":[
        {
            "category":"Insurance",
            "subcategory":"Life Insurance",
            "type":"Services"
        }
    ],
    "sg:phone":"+1 843 669 3241",
    "sg:postcode":"29501",
    "sg:province":"SC",
    "sg:tags":[
        "carrier"
    ],
    "wof:name":"GE",
    "wof:placetype":"venue"
},
  "geometry": {"coordinates":[-79.821467,34.174219],"type":"Point"}
}