{
  "type": "Feature",
  "properties": {
    "iso:country":"US",
    "sg:address":"611 Main St",
    "sg:city":"Columbia",
    "sg:classifiers":[
        {
            "category":"Wholesale",
            "subcategory":"Meat",
            "type":"Manufacturing & Wholesale Goods"
        }
    ],
    "sg:phone":"+1 803 799 0602",
    "sg:postcode":"29201",
    "sg:province":"SC",
    "wof:name":"Brantley Meats Inc",
    "wof:placetype":"venue"
},
  "geometry": {"coordinates":[-81.030536,33.99432],"type":"Point"}
}