{
  "type": "Feature",
  "properties": {
    "iso:country":"US",
    "sg:address":"4244 Scott St",
    "sg:city":"Charleston",
    "sg:classifiers":[
        {
            "category":"Home & Garden",
            "subcategory":"Furniture",
            "type":"Retail Goods"
        }
    ],
    "sg:phone":"+1 843 763 5225",
    "sg:postcode":"29405",
    "sg:province":"SC",
    "wof:name":"Red Label Inc",
    "wof:placetype":"venue"
},
  "geometry": {"coordinates":[-80.00653800000001,32.854813],"type":"Point"}
}