{
  "type": "Feature",
  "properties": {
    "iso:country":"US",
    "sg:address":"6094 Fairview Rd",
    "sg:city":"Batesburg",
    "sg:classifiers":[
        {
            "category":"Building & Trades",
            "subcategory":"Construction",
            "type":"Services"
        }
    ],
    "sg:phone":"+1 803 657 6306",
    "sg:postcode":"29006",
    "sg:province":"SC",
    "sg:tags":[
        "general",
        "contractor"
    ],
    "wof:name":"Ready Construction",
    "wof:placetype":"venue"
},
  "geometry": {"coordinates":[-81.484962,33.845105],"type":"Point"}
}