{
  "type": "Feature",
  "properties": {
    "iso:country":"US",
    "sg:address":"112 Duval St",
    "sg:city":"Cheraw",
    "sg:classifiers":[
        {
            "category":"Manufacturing",
            "subcategory":"Printing",
            "type":"Manufacturing & Wholesale Goods"
        }
    ],
    "sg:phone":"+1 843 921 0607",
    "sg:postcode":"29520",
    "sg:province":"SC",
    "sg:tags":[
        "screen"
    ],
    "wof:name":"T-Riffic Screenprinting",
    "wof:placetype":"venue"
},
  "geometry": {"coordinates":[-79.882651,34.699754],"type":"Point"}
}