{
  "type": "Feature",
  "properties": {
    "iso:country":"US",
    "sg:address":"329 Salem Dr",
    "sg:city":"Ladson",
    "sg:classifiers":[
        {
            "category":"Building & Trades",
            "subcategory":"Cleaning & Sanitation",
            "type":"Services"
        }
    ],
    "sg:phone":"+1 843 574 9805",
    "sg:postcode":"29456",
    "sg:province":"SC",
    "wof:name":"Real Clean Hood Cleaners",
    "wof:placetype":"venue"
},
  "geometry": {"coordinates":[-80.094182,33.020524],"type":"Point"}
}