{
  "type": "Feature",
  "properties": {
    "iso:country":"US",
    "sg:address":"542 Main St",
    "sg:city":"Barnwell",
    "sg:classifiers":[
        {
            "category":"Banks & Credit Unions",
            "subcategory":"Bank",
            "type":"Services"
        }
    ],
    "sg:phone":"+1 803 541 0081",
    "sg:postcode":"29812",
    "sg:province":"SC",
    "sg:tags":[
        "loan"
    ],
    "wof:name":"Instant Cash Title Loans",
    "wof:placetype":"venue"
},
  "geometry": {"coordinates":[-81.35780699999999,33.24469],"type":"Point"}
}