{
  "type": "Feature",
  "properties": {
    "iso:country":"US",
    "sg:address":"112 N Church St",
    "sg:city":"Manning",
    "sg:classifiers":[
        {
            "category":"Organizations",
            "subcategory":"Religious Organization",
            "type":"Services"
        }
    ],
    "sg:phone":"+1 803 435 2168",
    "sg:postcode":"29102",
    "sg:province":"SC",
    "sg:tags":[
        "church"
    ],
    "wof:name":"Redeemed United Holy Church",
    "wof:placetype":"venue"
},
  "geometry": {"coordinates":[-80.208925,33.698243],"type":"Point"}
}