{
  "type": "Feature",
  "properties": {
    "addr:full":"1016 Jones Rd Irmo SC 29063",
    "addr:housenumber":"1016",
    "addr:postcode":"29063",
    "addr:street":"Jones Rd",
    "iso:country":"US",
    "sg:address":"1016 Jones Rd",
    "sg:city":"Irmo",
    "sg:classifiers":[
        {
            "category":"Building & Trades",
            "subcategory":"Construction",
            "type":"Services"
        }
    ],
    "sg:phone":"+1 803 732 3101",
    "sg:postcode":"29063",
    "sg:province":"SC",
    "sg:tags":[
        "house"
    ],
    "wof:name":"BSC Construction Services LLC",
    "wof:placetype":"venue"
},
  "geometry": {"coordinates":[-81.241573,34.11711],"type":"Point"}
}