{
  "type": "Feature",
  "properties": {
    "iso:country":"US",
    "sg:address":"109 Cypress St",
    "sg:city":"St Matthews",
    "sg:classifiers":[
        {
            "category":"Building & Trades",
            "subcategory":"Plumbing",
            "type":"Services"
        }
    ],
    "sg:phone":"+1 803 874 1245",
    "sg:postcode":"29113",
    "sg:province":"SC",
    "sg:tags":[
        "conditioning",
        "air",
        "system",
        "contractor"
    ],
    "wof:name":"Tri-County Heating & Cooling",
    "wof:placetype":"venue"
},
  "geometry": {"coordinates":[-81.120926,33.43831],"type":"Point"}
}