{
  "type": "Feature",
  "properties": {
    "iso:country":"US",
    "sg:address":"209 W Blackstock Rd",
    "sg:city":"Spartanburg",
    "sg:classifiers":[
        {
            "category":"Shopping",
            "subcategory":"Clothing, Apparel, & Fashions",
            "type":"Retail Goods"
        }
    ],
    "sg:phone":"+1 864 574 6428",
    "sg:postcode":"29301",
    "sg:province":"SC",
    "sg:tags":[
        "accessory"
    ],
    "wof:name":"Claires",
    "wof:placetype":"venue"
},
  "geometry": {"coordinates":[-81.990692,34.936905],"type":"Point"}
}