{
  "type": "Feature",
  "properties": {
    "iso:country":"US",
    "sg:address":"741 Bultman Dr",
    "sg:city":"Sumter",
    "sg:classifiers":[
        {
            "category":"Personal",
            "type":"Services"
        }
    ],
    "sg:phone":"+1 803 775 4105",
    "sg:postcode":"29150",
    "sg:province":"SC",
    "sg:tags":[
        "therapist",
        "massage"
    ],
    "wof:name":"Jenny Disher Massage Therapy",
    "wof:placetype":"venue"
},
  "geometry": {"coordinates":[-80.372287,33.942902],"type":"Point"}
}