{
  "type": "Feature",
  "properties": {
    "iso:country":"US",
    "sg:address":"8001 Utica St",
    "sg:city":"Seneca",
    "sg:classifiers":[
        {
            "category":"Arts & Performance",
            "subcategory":"Theater",
            "type":"Entertainment"
        }
    ],
    "sg:phone":"+1 864 882 7700",
    "sg:postcode":"29678",
    "sg:province":"SC",
    "sg:website":"www.oconeetheater.com",
    "wof:name":"Oconee Community Theatre Inc",
    "wof:placetype":"venue"
},
  "geometry": {"coordinates":[-82.926619,34.675512],"type":"Point"}
}