{
  "type": "Feature",
  "properties": {
    "iso:country":"US",
    "sg:address":"6094 Parris Bridge Rd",
    "sg:city":"Chesnee",
    "sg:classifiers":[
        {
            "category":"Retail",
            "subcategory":"Car Wash",
            "type":"Services"
        }
    ],
    "sg:phone":"+1 864 578 3341",
    "sg:postcode":"29323",
    "sg:province":"SC",
    "sg:tags":[
        "automobile",
        "detail",
        "clean"
    ],
    "wof:name":"Tip-Top Auto Detailing",
    "wof:placetype":"venue"
},
  "geometry": {"coordinates":[-81.924816,35.097899],"type":"Point"}
}