{
  "type": "Feature",
  "properties": {
    "addr:full":"5560 Cedarcrest Drive Rd Clover SC 29710",
    "addr:housenumber":"5560",
    "addr:postcode":"29710",
    "addr:street":"Cedarcrest Drive Rd",
    "iso:country":"US",
    "sg:address":"5560 Cedarcrest Drive Rd",
    "sg:city":"Clover",
    "sg:classifiers":[
        {
            "category":"Travel",
            "subcategory":"Travel Agent",
            "type":"Entertainment"
        }
    ],
    "sg:phone":"+1 803 831 7298",
    "sg:postcode":"29710",
    "sg:province":"SC",
    "sg:tags":[
        "agency"
    ],
    "wof:name":"Four Winds Vacations Ltd",
    "wof:placetype":"venue"
},
  "geometry": {"coordinates":[-81.07583,35.109519],"type":"Point"}
}