{
  "type": "Feature",
  "properties": {
    "iso:country":"US",
    "sg:address":"29 Hunter Rd",
    "sg:city":"Hilton Head Isle",
    "sg:classifiers":[
        {
            "category":"Professional",
            "subcategory":"Business Services",
            "type":"Services"
        }
    ],
    "sg:phone":"+1 843 342 9400",
    "sg:postcode":"29926",
    "sg:province":"SC",
    "sg:tags":[
        "recording",
        "studio"
    ],
    "wof:name":"Global Star Studios",
    "wof:placetype":"venue"
},
  "geometry": {"coordinates":[-80.701177,32.222204],"type":"Point"}
}