{
  "type": "Feature",
  "properties": {
    "iso:country":"US",
    "sg:address":"1706 Montague Ave Exd",
    "sg:city":"Greenwood",
    "sg:classifiers":[
        {
            "category":"Autos & Motor Vehicles",
            "subcategory":"Automobile Sales",
            "type":"Retail Goods"
        }
    ],
    "sg:phone":"+1 864 223 0586",
    "sg:postcode":"29649",
    "sg:province":"SC",
    "sg:tags":[
        "car",
        "dealer"
    ],
    "sg:website":"www.cthompsonautomotive.com",
    "wof:name":"C Thompson Automotive",
    "wof:placetype":"venue"
},
  "geometry": {"coordinates":[-82.188467,34.222439],"type":"Point"}
}