{
  "type": "Feature",
  "properties": {
    "iso:country":"US",
    "sg:address":"311 Anita Dr",
    "sg:city":"Goose Creek",
    "sg:classifiers":[
        {
            "category":"Shopping",
            "subcategory":"Gifts & Souvenirs",
            "type":"Retail Goods"
        }
    ],
    "sg:phone":"+1 843 797 6863",
    "sg:postcode":"29445",
    "sg:province":"SC",
    "wof:name":"R&R Gift World",
    "wof:placetype":"venue"
},
  "geometry": {"coordinates":[-80.033901,33.019731],"type":"Point"}
}