{
  "type": "Feature",
  "properties": {
    "iso:country":"US",
    "sg:address":"1145 Venning Rd",
    "sg:city":"Mt Pleasant",
    "sg:phone":"+1 843 971 5145",
    "sg:postcode":"29464",
    "sg:province":"SC",
    "sg:tags":[
        "gas"
    ],
    "wof:name":"Gold's LP Gas Inc",
    "wof:placetype":"venue"
},
  "geometry": {"coordinates":[-79.83722299999999,32.821066],"type":"Point"}
}