{
  "type": "Feature",
  "properties": {
    "iso:country":"US",
    "sg:address":"270 Store Rd",
    "sg:city":"Easley",
    "sg:classifiers":[
        {
            "category":"Building & Trades",
            "subcategory":"Construction",
            "type":"Services"
        }
    ],
    "sg:phone":"+1 864 859 3481",
    "sg:postcode":"29640",
    "sg:province":"SC",
    "sg:tags":[
        "industrial"
    ],
    "wof:name":"Howard Industrial",
    "wof:placetype":"venue"
},
  "geometry": {"coordinates":[-82.642051,34.863448],"type":"Point"}
}