{
  "type": "Feature",
  "properties": {
    "addr:full":"1806 Wasp St Charleston SC 29405",
    "addr:housenumber":"1806",
    "addr:postcode":"29405",
    "addr:street":"Wasp St",
    "iso:country":"US",
    "sg:address":"1806 Wasp St",
    "sg:city":"Charleston",
    "sg:classifiers":[
        {
            "category":"Retail",
            "subcategory":"Animal Services",
            "type":"Services"
        }
    ],
    "sg:phone":"+1 843 813 0684",
    "sg:postcode":"29405",
    "sg:province":"SC",
    "sg:tags":[
        "pet",
        "grooming",
        "washing"
    ],
    "wof:name":"Beauty Paws Mobile Grooming",
    "wof:placetype":"venue"
},
  "geometry": {"coordinates":[-80.003822,32.890211],"type":"Point"}
}