{
  "type": "Feature",
  "properties": {
    "iso:country":"US",
    "sg:address":"67 77",
    "sg:city":"Williamston",
    "sg:classifiers":[
        {
            "category":"Retail",
            "subcategory":"Auto Repair",
            "type":"Services"
        }
    ],
    "sg:phone":"+1 864 847 5166",
    "sg:postcode":"29697",
    "sg:province":"SC",
    "sg:tags":[
        "repairing",
        "automobile"
    ],
    "wof:name":"C & C Automotive Specialist",
    "wof:placetype":"venue"
},
  "geometry": {"coordinates":[-82.633792,34.510982],"type":"Point"}
}