{
  "type": "Feature",
  "properties": {
    "iso:country":"US",
    "sg:address":"3550 Rutherford Rd",
    "sg:city":"Taylors",
    "sg:classifiers":[
        {
            "category":"Professional",
            "type":"Services"
        }
    ],
    "sg:phone":"+1 864 292 9185",
    "sg:postcode":"29609",
    "sg:province":"SC",
    "sg:tags":[
        "establishment"
    ],
    "wof:name":"Kyrus Corp",
    "wof:placetype":"venue"
},
  "geometry": {"coordinates":[-82.32549899999999,34.915537],"type":"Point"}
}