{
  "type": "Feature",
  "properties": {
    "addr:full":"803 US Hwy 17 Bus Surfside Beach SC 29575",
    "addr:housenumber":"803",
    "addr:postcode":"29575",
    "addr:street":"Us Hwy 17 Bus",
    "iso:country":"US",
    "sg:address":"803 US Hwy 17 Bus",
    "sg:city":"Surfside Beach",
    "sg:classifiers":[
        {
            "category":"Cinema",
            "subcategory":"Movie Rental",
            "type":"Entertainment"
        }
    ],
    "sg:phone":"+1 843 238 9817",
    "sg:postcode":"29575",
    "sg:province":"SC",
    "sg:tags":[
        "leasing",
        "video",
        "disc",
        "tape"
    ],
    "sg:website":"www.blockbuster.com",
    "wof:name":"Blockbuster Video",
    "wof:placetype":"venue"
},
  "geometry": {"coordinates":[-78.97574299999999,33.617719],"type":"Point"}
}