{
  "type": "Feature",
  "properties": {
    "iso:country":"US",
    "sg:address":"4528 Outwood Dr",
    "sg:city":"Ladson",
    "sg:classifiers":[
        {
            "category":"Building & Trades",
            "subcategory":"Construction",
            "type":"Services"
        }
    ],
    "sg:phone":"+1 843 851 1142",
    "sg:postcode":"29456",
    "sg:province":"SC",
    "sg:tags":[
        "contractor"
    ],
    "wof:name":"Unique Vinyl Siding",
    "wof:placetype":"venue"
},
  "geometry": {"coordinates":[-80.134415,32.99948],"type":"Point"}
}