{
  "type": "Feature",
  "properties": {
    "iso:country":"US",
    "sg:address":"20 S Main St",
    "sg:city":"Greenville",
    "sg:classifiers":[
        {
            "category":"Real Estate",
            "subcategory":"Real Estate Agent",
            "type":"Services"
        }
    ],
    "sg:phone":"+1 864 467 2000",
    "sg:postcode":"29601",
    "sg:province":"SC",
    "wof:name":"Commercial Specialist Realty",
    "wof:placetype":"venue"
},
  "geometry": {"coordinates":[-82.399473,34.849856],"type":"Point"}
}