{
  "type": "Feature",
  "properties": {
    "iso:country":"US",
    "sg:address":"1322 Young Rd",
    "sg:city":"Timmonsville",
    "sg:classifiers":[
        {
            "category":"Manufacturing",
            "subcategory":"Paper Products",
            "type":"Manufacturing & Wholesale Goods"
        }
    ],
    "sg:phone":"+1 843 346 2380",
    "sg:postcode":"29161",
    "sg:province":"SC",
    "sg:tags":[
        "box",
        "wood",
        "container",
        "fiber",
        "mfg"
    ],
    "wof:name":"North American Container Corp",
    "wof:placetype":"venue"
},
  "geometry": {"coordinates":[-79.910062,34.079582],"type":"Point"}
}