{
  "type": "Feature",
  "properties": {
    "addr:full":"1725 N Main St Summerville SC 29483",
    "addr:housenumber":"1725",
    "addr:postcode":"29483",
    "addr:street":"N Main St",
    "iso:country":"US",
    "sg:address":"1725 N Main St",
    "sg:city":"Summerville",
    "sg:classifiers":[
        {
            "category":"Professional",
            "subcategory":"Business Services",
            "type":"Services"
        }
    ],
    "sg:phone":"+1 843 871 0400",
    "sg:postcode":"29483",
    "sg:province":"SC",
    "sg:tags":[
        "real estate"
    ],
    "wof:name":"Custom Goldwork",
    "wof:placetype":"venue"
},
  "geometry": {"coordinates":[-80.12988,33.041957],"type":"Point"}
}