{
  "type": "Feature",
  "properties": {
    "iso:country":"US",
    "sg:address":"617 Richardson St",
    "sg:city":"Simpsonville",
    "sg:classifiers":[
        {
            "category":"Real Estate",
            "subcategory":"Real Estate Operator",
            "type":"Services"
        }
    ],
    "sg:phone":"+1 864 967 3301",
    "sg:postcode":"29680",
    "sg:province":"SC",
    "sg:tags":[
        "building",
        "apartment"
    ],
    "wof:name":"Bridgeway Apartment Office",
    "wof:placetype":"venue"
},
  "geometry": {"coordinates":[-82.26593200000001,34.729981],"type":"Point"}
}