{
  "type": "Feature",
  "properties": {
    "iso:country":"US",
    "sg:address":"729 Brockman McClimon Rd",
    "sg:city":"Greer",
    "sg:classifiers":[
        {
            "category":"Personal",
            "type":"Services"
        }
    ],
    "sg:phone":"+1 864 848 0881",
    "sg:postcode":"29651",
    "sg:province":"SC",
    "sg:tags":[
        "concierge"
    ],
    "wof:name":"Andrews & Associates",
    "wof:placetype":"venue"
},
  "geometry": {"coordinates":[-82.194996,34.882328],"type":"Point"}
}