{
  "type": "Feature",
  "properties": {
    "addr:full":"1531 Chinquapin Church Rd Batesburg SC 29006",
    "addr:housenumber":"1531",
    "addr:postcode":"29006",
    "addr:street":"Chinquapin Church Rd",
    "iso:country":"US",
    "sg:address":"1531 Chinquapin Church Rd",
    "sg:city":"Batesburg",
    "sg:classifiers":[
        {
            "category":"Building & Trades",
            "subcategory":"Construction",
            "type":"Services"
        }
    ],
    "sg:phone":"+1 803 532 5121",
    "sg:postcode":"29006",
    "sg:province":"SC",
    "sg:tags":[
        "heavy",
        "house",
        "moving",
        "lifting"
    ],
    "wof:name":"J E Oswalt Housemoving Inc",
    "wof:placetype":"venue"
},
  "geometry": {"coordinates":[-81.550907,33.853391],"type":"Point"}
}