{
  "type": "Feature",
  "properties": {
    "iso:country":"US",
    "sg:address":"224 Fraley Dr",
    "sg:city":"Inman",
    "sg:classifiers":[
        {
            "category":"Building & Trades",
            "subcategory":"Construction",
            "type":"Services"
        }
    ],
    "sg:phone":"+1 864 592 3134",
    "sg:postcode":"29349",
    "sg:province":"SC",
    "sg:tags":[
        "hanging",
        "contractor"
    ],
    "wof:name":"Flint Painting",
    "wof:placetype":"venue"
},
  "geometry": {"coordinates":[-82.030784,35.130717],"type":"Point"}
}