{
  "type": "Feature",
  "properties": {
    "iso:country":"US",
    "sg:address":"176 Lumberton Dr",
    "sg:city":"Georgetown",
    "sg:classifiers":[
        {
            "category":"Banks & Credit Unions",
            "subcategory":"Investment Brokerage",
            "type":"Services"
        }
    ],
    "sg:phone":"+1 843 527 4812",
    "sg:postcode":"29440",
    "sg:province":"SC",
    "sg:tags":[
        "advisory",
        "financial"
    ],
    "wof:name":"Us Mortgage Inc",
    "wof:placetype":"venue"
},
  "geometry": {"coordinates":[-79.40867900000001,33.612413],"type":"Point"}
}