{
  "type": "Feature",
  "properties": {
    "iso:country":"US",
    "sg:address":"232 S Sea Pines Dr",
    "sg:city":"Hilton Head Isle",
    "sg:classifiers":[
        {
            "category":"Ferry",
            "type":"Transportation"
        }
    ],
    "sg:phone":"+1 843 671 3344",
    "sg:postcode":"29928",
    "sg:province":"SC",
    "sg:tags":[
        "boat"
    ],
    "wof:name":"Commander Zodiac",
    "wof:placetype":"venue"
},
  "geometry": {"coordinates":[-80.82610099999999,32.115584],"type":"Point"}
}