{
  "type": "Feature",
  "properties": {
    "iso:country":"US",
    "sg:address":"1603 10th Ave",
    "sg:city":"Conway",
    "sg:classifiers":[
        {
            "category":"Health Services",
            "subcategory":"Doctor",
            "type":"Services"
        }
    ],
    "sg:phone":"+1 843 248 2705",
    "sg:postcode":"29526",
    "sg:province":"SC",
    "sg:tags":[
        "dentist"
    ],
    "wof:name":"Russell A Boatwright DDS",
    "wof:placetype":"venue"
},
  "geometry": {"coordinates":[-79.060045,33.839005],"type":"Point"}
}