{
  "type": "Feature",
  "properties": {
    "iso:country":"US",
    "sg:address":"1295 E Main St",
    "sg:city":"Rock Hill",
    "sg:classifiers":[
        {
            "category":"Shopping",
            "subcategory":"Pharmacy",
            "type":"Retail Goods"
        }
    ],
    "sg:phone":"+1 803 324 7563",
    "sg:postcode":"29730",
    "sg:province":"SC",
    "wof:name":"Eckerd",
    "wof:placetype":"venue"
},
  "geometry": {"coordinates":[-81.004391,34.915863],"type":"Point"}
}