{
  "type": "Feature",
  "properties": {
    "iso:country":"US",
    "sg:address":"110 W Liberty St",
    "sg:city":"Marion",
    "sg:classifiers":[
        {
            "category":"Shopping",
            "type":"Retail Goods"
        }
    ],
    "sg:phone":"+1 843 423 4423",
    "sg:postcode":"29571",
    "sg:province":"SC",
    "sg:tags":[
        "cosmetic",
        "perfume"
    ],
    "wof:name":"Perfume City",
    "wof:placetype":"venue"
},
  "geometry": {"coordinates":[-79.400667,34.172095],"type":"Point"}
}