{
  "type": "Feature",
  "properties": {
    "addr:full":"3200 Service Dr West Columbia SC 29170",
    "addr:housenumber":"3200",
    "addr:postcode":"29170",
    "addr:street":"Service Dr",
    "iso:country":"US",
    "sg:address":"3200 Service Dr",
    "sg:city":"West Columbia",
    "sg:classifiers":[
        {
            "category":"Retail",
            "subcategory":"Auto Rental",
            "type":"Services"
        }
    ],
    "sg:phone":"+1 803 822 8341",
    "sg:postcode":"29170",
    "sg:province":"SC",
    "sg:tags":[
        "renting",
        "automobile"
    ],
    "sg:website":"www.hertz.com",
    "wof:name":"Hertz Rent A Car",
    "wof:placetype":"venue"
},
  "geometry": {"coordinates":[-81.127932,33.949709],"type":"Point"}
}