{
  "type": "Feature",
  "properties": {
    "addr:full":"102 Myers Rd Summerville SC 29483",
    "addr:housenumber":"102",
    "addr:postcode":"29483",
    "addr:street":"Myers Rd",
    "iso:country":"US",
    "sg:address":"102 Myers Rd",
    "sg:city":"Summerville",
    "sg:classifiers":[
        {
            "category":"Organizations",
            "subcategory":"Religious Organization",
            "type":"Services"
        }
    ],
    "sg:phone":"+1 843 821 1961",
    "sg:postcode":"29483",
    "sg:province":"SC",
    "sg:tags":[
        "church"
    ],
    "wof:name":"Sonrise Christian Church",
    "wof:placetype":"venue"
},
  "geometry": {"coordinates":[-80.076598,33.044095],"type":"Point"}
}