{
  "type": "Feature",
  "properties": {
    "addr:full":"534 Pendleton St Rock Hill SC 29730",
    "addr:housenumber":"534",
    "addr:postcode":"29730",
    "addr:street":"Pendleton St",
    "iso:country":"US",
    "sg:address":"534 Pendleton St",
    "sg:city":"Rock Hill",
    "sg:classifiers":[
        {
            "category":"Food & Beverages",
            "subcategory":"Groceries & Convenience Stores",
            "type":"Retail Goods"
        }
    ],
    "sg:phone":"+1 803 324 4058",
    "sg:postcode":"29730",
    "sg:province":"SC",
    "wof:name":"Quick C Food Mart",
    "wof:placetype":"venue"
},
  "geometry": {"coordinates":[-81.017983,34.925024],"type":"Point"}
}