{
  "type": "Feature",
  "properties": {
    "addr:full":"406 N Nelson Dr Fountain Inn SC 29644",
    "addr:housenumber":"406",
    "addr:postcode":"29644",
    "addr:street":"N Nelson Dr",
    "iso:country":"US",
    "sg:address":"406 N Nelson Dr",
    "sg:city":"Fountain Inn",
    "sg:classifiers":[
        {
            "category":"Autos & Motor Vehicles",
            "subcategory":"Automobile Sales",
            "type":"Retail Goods"
        }
    ],
    "sg:phone":"+1 864 862 5130",
    "sg:postcode":"29644",
    "sg:province":"SC",
    "sg:tags":[
        "car",
        "dealer"
    ],
    "wof:name":"Fountain Inn Truck Sales Inc",
    "wof:placetype":"venue"
},
  "geometry": {"coordinates":[-82.218744,34.687897],"type":"Point"}
}