{
  "type": "Feature",
  "properties": {
    "iso:country":"US",
    "sg:address":"101 Travelers Rest Blvd",
    "sg:city":"Summerville",
    "sg:classifiers":[
        {
            "category":"Building & Trades",
            "subcategory":"Construction",
            "type":"Services"
        }
    ],
    "sg:phone":"+1 843 871 6175",
    "sg:postcode":"29485",
    "sg:province":"SC",
    "sg:tags":[
        "house"
    ],
    "wof:name":"Homestead Builders Inc",
    "wof:placetype":"venue"
},
  "geometry": {"coordinates":[-80.166619,32.981614],"type":"Point"}
}