{
  "type": "Feature",
  "properties": {
    "iso:country":"US",
    "sg:address":"723 Columbia Rd",
    "sg:city":"Edgefield",
    "sg:classifiers":[
        {
            "category":"Building & Trades",
            "subcategory":"Plumbing",
            "type":"Services"
        }
    ],
    "sg:phone":"+1 803 637 5410",
    "sg:postcode":"29824",
    "sg:province":"SC",
    "sg:tags":[
        "contractor"
    ],
    "wof:name":"Hornes Pest Control Co Inc",
    "wof:placetype":"venue"
},
  "geometry": {"coordinates":[-81.908052,33.793792],"type":"Point"}
}