{
  "type": "Feature",
  "properties": {
    "iso:country":"US",
    "sg:address":"1595 Savannah Hwy",
    "sg:city":"Charleston",
    "sg:classifiers":[
        {
            "category":"Retail",
            "subcategory":"Laundry & Dry Cleaning",
            "type":"Services"
        }
    ],
    "sg:phone":"+1 843 769 7575",
    "sg:postcode":"29407",
    "sg:province":"SC",
    "sg:tags":[
        "cleaners"
    ],
    "wof:name":"Dryclean USA",
    "wof:placetype":"venue"
},
  "geometry": {"coordinates":[-80.008319,32.785876],"type":"Point"}
}