{
  "type": "Feature",
  "properties": {
    "iso:country":"US",
    "sg:address":"158 Executive Center Dr",
    "sg:city":"Greenville",
    "sg:classifiers":[
        {
            "category":"Organizations",
            "subcategory":"Professional Association",
            "type":"Services"
        }
    ],
    "sg:phone":"+1 864 234 3131",
    "sg:postcode":"29615",
    "sg:province":"SC",
    "wof:name":"Parents Without Partners",
    "wof:placetype":"venue"
},
  "geometry": {"coordinates":[-82.308172,34.837627],"type":"Point"}
}