{
  "type": "Feature",
  "properties": {
    "iso:country":"US",
    "sg:address":"1824 Five Chop Rd",
    "sg:city":"Orangeburg",
    "sg:classifiers":[
        {
            "category":"Recreation",
            "subcategory":"Arcade",
            "type":"Entertainment"
        }
    ],
    "sg:phone":"+1 803 531 0814",
    "sg:postcode":"29115",
    "sg:province":"SC",
    "sg:tags":[
        "amusement",
        "devices"
    ],
    "wof:name":"Stardust Amusement",
    "wof:placetype":"venue"
},
  "geometry": {"coordinates":[-80.806962,33.4719],"type":"Point"}
}