{
  "type": "Feature",
  "properties": {
    "iso:country":"US",
    "sg:address":"353 Manning Ave",
    "sg:city":"Sumter",
    "sg:classifiers":[
        {
            "category":"Retail",
            "subcategory":"Funeral Services",
            "type":"Services"
        }
    ],
    "sg:phone":"+1 803 773 3962",
    "sg:postcode":"29150",
    "sg:province":"SC",
    "sg:tags":[
        "director"
    ],
    "wof:name":"Community Funeral Home Inc",
    "wof:placetype":"venue"
},
  "geometry": {"coordinates":[-80.340889,33.908674],"type":"Point"}
}