{
  "type": "Feature",
  "properties": {
    "addr:full":"2619 State Hwy 6 Gaston SC 29053",
    "addr:housenumber":"2619",
    "addr:postcode":"29053",
    "addr:street":"State Hwy 6",
    "iso:country":"US",
    "sg:address":"2619 State Hwy 6",
    "sg:city":"Gaston",
    "sg:classifiers":[
        {
            "category":"Manufacturing",
            "subcategory":"Building Materials",
            "type":"Manufacturing & Wholesale Goods"
        }
    ],
    "sg:phone":"+1 803 315 1134",
    "sg:postcode":"29053",
    "sg:province":"SC",
    "sg:tags":[
        "mfg",
        "wood",
        "kitchen",
        "cabinet"
    ],
    "wof:name":"Trendsetter Cabinets",
    "wof:placetype":"venue"
},
  "geometry": {"coordinates":[-81.18488600000001,33.800939],"type":"Point"}
}