{
  "type": "Feature",
  "properties": {
    "iso:country":"US",
    "sg:address":"1 Law Range",
    "sg:city":"Sumter",
    "sg:classifiers":[
        {
            "category":"Real Estate",
            "subcategory":"Surveying",
            "type":"Services"
        }
    ],
    "sg:phone":"+1 803 775 3017",
    "sg:postcode":"29150",
    "sg:province":"SC",
    "sg:tags":[
        "surveyor"
    ],
    "wof:name":"Allen-Makela Land Surveyors",
    "wof:placetype":"venue"
},
  "geometry": {"coordinates":[-80.341493,33.922354],"type":"Point"}
}