{
  "type": "Feature",
  "properties": {
    "iso:country":"US",
    "sg:address":"1449 Bethel Church Rd",
    "sg:city":"Prosperity",
    "sg:classifiers":[
        {
            "category":"Building & Trades",
            "subcategory":"Construction",
            "type":"Services"
        }
    ],
    "sg:phone":"+1 803 364 3292",
    "sg:postcode":"29127",
    "sg:province":"SC",
    "sg:tags":[
        "contractor"
    ],
    "wof:name":"Praylow Pressure Washing",
    "wof:placetype":"venue"
},
  "geometry": {"coordinates":[-81.492148,34.109985],"type":"Point"}
}