{
  "type": "Feature",
  "properties": {
    "iso:country":"US",
    "sg:address":"750 N Calhoun St",
    "sg:city":"Calhoun Falls",
    "sg:classifiers":[
        {
            "category":"Education",
            "subcategory":"School",
            "type":"Public Place"
        }
    ],
    "sg:phone":"+1 864 447 8016",
    "sg:postcode":"29628",
    "sg:province":"SC",
    "wof:name":"John C Calhoun Elementary",
    "wof:placetype":"venue"
},
  "geometry": {"coordinates":[-82.598476,34.100133],"type":"Point"}
}