{
  "type": "Feature",
  "properties": {
    "iso:country":"US",
    "sg:address":"205 Scott St",
    "sg:city":"Beaufort",
    "sg:classifiers":[
        {
            "category":"Restaurant",
            "type":"Food & Drink"
        }
    ],
    "sg:phone":"+1 843 524 4330",
    "sg:postcode":"29902",
    "sg:province":"SC",
    "sg:tags":[
        "eating"
    ],
    "wof:name":"Blackstones Cafe",
    "wof:placetype":"venue"
},
  "geometry": {"coordinates":[-80.670789,32.431192],"type":"Point"}
}