{
  "type": "Feature",
  "properties": {
    "iso:country":"US",
    "sg:address":"100 Watts Ave",
    "sg:city":"Clio",
    "sg:classifiers":[
        {
            "category":"Real Estate",
            "subcategory":"Real Estate Operator",
            "type":"Services"
        }
    ],
    "sg:phone":"+1 843 586 2674",
    "sg:postcode":"29577",
    "sg:province":"SC",
    "sg:tags":[
        "apartment"
    ],
    "wof:name":"Clio East Apartments",
    "wof:placetype":"venue"
},
  "geometry": {"coordinates":[-78.892479,33.699994],"type":"Point"}
}