{
  "type": "Feature",
  "properties": {
    "iso:country":"US",
    "sg:address":"1950 W Palmetto St",
    "sg:city":"Florence",
    "sg:classifiers":[
        {
            "category":"Shopping",
            "subcategory":"Jewelry",
            "type":"Retail Goods"
        }
    ],
    "sg:phone":"+1 843 661 0905",
    "sg:postcode":"29501",
    "sg:province":"SC",
    "sg:tags":[
        "jeweler"
    ],
    "wof:name":"Hughes Jewselry & Repair Ctr",
    "wof:placetype":"venue"
},
  "geometry": {"coordinates":[-79.805502,34.188957],"type":"Point"}
}