{
  "type": "Feature",
  "properties": {
    "iso:country":"US",
    "sg:address":"10 Carriage Ln",
    "sg:city":"Charleston",
    "sg:classifiers":[
        {
            "category":"Travel",
            "subcategory":"Travel Agent",
            "type":"Entertainment"
        }
    ],
    "sg:phone":"+1 843 556 9051",
    "sg:postcode":"29407",
    "sg:province":"SC",
    "sg:tags":[
        "agency",
        "bureau"
    ],
    "sg:website":"www.abbottandhilltravel.com",
    "wof:name":"Abbott & Hill Travel",
    "wof:placetype":"venue"
},
  "geometry": {"coordinates":[-79.99668,32.79902],"type":"Point"}
}