{
  "type": "Feature",
  "properties": {
    "iso:country":"US",
    "sg:address":"2075 Colony Church Rd",
    "sg:city":"Newberry",
    "sg:classifiers":[
        {
            "category":"Building & Trades",
            "subcategory":"Landscaping Services",
            "type":"Services"
        }
    ],
    "sg:phone":"+1 803 276 8248",
    "sg:postcode":"29108",
    "sg:province":"SC",
    "sg:tags":[
        "landscape",
        "contractor"
    ],
    "wof:name":"Cutting Edge Lawn Care Svc Inc",
    "wof:placetype":"venue"
},
  "geometry": {"coordinates":[-81.587839,34.219306],"type":"Point"}
}