{
  "type": "Feature",
  "properties": {
    "addr:full":"116 Beatrice Ln Summerville SC 29485",
    "addr:housenumber":"116",
    "addr:postcode":"29485",
    "addr:street":"Beatrice Ln",
    "iso:country":"US",
    "sg:address":"116 Beatrice Ln",
    "sg:city":"Summerville",
    "sg:classifiers":[
        {
            "category":"Social Services",
            "subcategory":"Child Care",
            "type":"Services"
        }
    ],
    "sg:phone":"+1 843 873 4647",
    "sg:postcode":"29485",
    "sg:province":"SC",
    "wof:name":"Lots Of Love Daycare",
    "wof:placetype":"venue"
},
  "geometry": {"coordinates":[-80.16162199999999,32.992766],"type":"Point"}
}