{
  "type": "Feature",
  "properties": {
    "iso:country":"US",
    "sg:address":"2025 Ebenezer Rd",
    "sg:city":"Rock Hill",
    "sg:classifiers":[
        {
            "category":"Health Services",
            "subcategory":"Clinic",
            "type":"Services"
        }
    ],
    "sg:phone":"+1 803 581 8088",
    "sg:postcode":"29732",
    "sg:province":"SC",
    "sg:tags":[
        "home"
    ],
    "wof:name":"Total Care",
    "wof:placetype":"venue"
},
  "geometry": {"coordinates":[-81.052229,34.966135],"type":"Point"}
}