{
  "type": "Feature",
  "properties": {
    "iso:country":"US",
    "sg:address":"1243 Knox Ave",
    "sg:city":"North Augusta",
    "sg:classifiers":[
        {
            "category":"Personal",
            "subcategory":"Beauty Salon",
            "type":"Services"
        }
    ],
    "sg:phone":"+1 803 279 0126",
    "sg:postcode":"29841",
    "sg:province":"SC",
    "sg:tags":[
        "manicuring"
    ],
    "wof:name":"Luxury Nail & Tan Salon",
    "wof:placetype":"venue"
},
  "geometry": {"coordinates":[-81.958451,33.506558],"type":"Point"}
}