{
  "type": "Feature",
  "properties": {
    "addr:full":"205 Sumter Hwy Camden SC 29020",
    "addr:housenumber":"205",
    "addr:postcode":"29020",
    "addr:street":"Sumter Hwy",
    "iso:country":"US",
    "sg:address":"205 Sumter Hwy",
    "sg:city":"Camden",
    "sg:classifiers":[
        {
            "category":"Utilities",
            "subcategory":"Natural Gas",
            "type":"Services"
        }
    ],
    "sg:phone":"+1 803 432 7615",
    "sg:postcode":"29020",
    "sg:province":"SC",
    "sg:tags":[
        "company"
    ],
    "sg:website":"www.scana.com",
    "wof:name":"South Carolina Electric & Gas",
    "wof:placetype":"venue"
},
  "geometry": {"coordinates":[-80.60555100000001,34.230681],"type":"Point"}
}