{
  "type": "Feature",
  "properties": {
    "iso:country":"US",
    "sg:address":"107 Cely Ln",
    "sg:city":"Piedmont",
    "sg:classifiers":[
        {
            "category":"Building & Trades",
            "subcategory":"Pest Control",
            "type":"Services"
        }
    ],
    "sg:phone":"+1 864 295 2540",
    "sg:postcode":"29673",
    "sg:province":"SC",
    "wof:name":"ACC Pest Control",
    "wof:placetype":"venue"
},
  "geometry": {"coordinates":[-82.48194,34.782446],"type":"Point"}
}