{
  "type": "Feature",
  "properties": {
    "iso:country":"US",
    "sg:address":"1210 S Granard St",
    "sg:city":"Gaffney",
    "sg:classifiers":[
        {
            "category":"Food & Beverages",
            "subcategory":"Groceries & Convenience Stores",
            "type":"Retail Goods"
        }
    ],
    "sg:phone":"+1 864 489 6728",
    "sg:postcode":"29341",
    "sg:province":"SC",
    "wof:name":"Fast & Fresh Food Stores",
    "wof:placetype":"venue"
},
  "geometry": {"coordinates":[-81.663521,35.064991],"type":"Point"}
}