{
  "type": "Feature",
  "properties": {
    "iso:country":"US",
    "sg:address":"248 Easler Dr",
    "sg:city":"Spartanburg",
    "sg:classifiers":[
        {
            "category":"Building & Trades",
            "subcategory":"Electrical",
            "type":"Services"
        }
    ],
    "sg:phone":"+1 864 599 8985",
    "sg:postcode":"29307",
    "sg:province":"SC",
    "sg:tags":[
        "security",
        "system"
    ],
    "wof:name":"MSI Security Systems",
    "wof:placetype":"venue"
},
  "geometry": {"coordinates":[-81.879999,35.046057],"type":"Point"}
}