{
  "type": "Feature",
  "properties": {
    "addr:full":"206 Beresford Creek St Charleston SC 29492",
    "addr:housenumber":"206",
    "addr:postcode":"29492",
    "addr:street":"Beresford Creek St",
    "iso:country":"US",
    "sg:address":"206 Beresford Creek St",
    "sg:city":"Charleston",
    "sg:classifiers":[
        {
            "category":"Restaurant",
            "type":"Food & Drink"
        }
    ],
    "sg:phone":"+1 843 881 3731",
    "sg:postcode":"29492",
    "sg:province":"SC",
    "sg:tags":[
        "eating"
    ],
    "wof:name":"Potts of Coffee LLC",
    "wof:placetype":"venue"
},
  "geometry": {"coordinates":[-79.919809,32.865727],"type":"Point"}
}