{
  "type": "Feature",
  "properties": {
    "iso:country":"US",
    "sg:address":"223 Columbia Ave",
    "sg:city":"Chapin",
    "sg:classifiers":[
        {
            "category":"Building & Trades",
            "subcategory":"Construction",
            "type":"Services"
        }
    ],
    "sg:phone":"+1 803 345 8815",
    "sg:postcode":"29036",
    "sg:province":"SC",
    "sg:tags":[
        "stucco",
        "contractor"
    ],
    "wof:name":"Casas De Flores Inc",
    "wof:placetype":"venue"
},
  "geometry": {"coordinates":[-81.343636,34.167757],"type":"Point"}
}