{
  "type": "Feature",
  "properties": {
    "addr:full":"5315 State Park Rd Travelers Rest SC 29690",
    "addr:housenumber":"5315",
    "addr:postcode":"29690",
    "addr:street":"State Park Rd",
    "iso:country":"US",
    "sg:address":"5315 State Park Rd",
    "sg:city":"Travelers Rest",
    "sg:classifiers":[
        {
            "category":"Organizations",
            "subcategory":"Religious Organization",
            "type":"Services"
        }
    ],
    "sg:phone":"+1 864 610 9544",
    "sg:postcode":"29690",
    "sg:province":"SC",
    "sg:tags":[
        "church"
    ],
    "wof:name":"Good Shepherd Church",
    "wof:placetype":"venue"
},
  "geometry": {"coordinates":[-82.40282999999999,34.967298],"type":"Point"}
}