{
  "type": "Feature",
  "properties": {
    "addr:full":"200 N Main St Greenville SC 29601",
    "addr:housenumber":"200",
    "addr:postcode":"29601",
    "addr:street":"N Main St",
    "iso:country":"US",
    "sg:address":"200 N Main St",
    "sg:city":"Greenville",
    "sg:classifiers":[
        {
            "category":"Professional",
            "subcategory":"Management & Consulting",
            "type":"Services"
        }
    ],
    "sg:phone":"+1 864 672 1600",
    "sg:postcode":"29601",
    "sg:province":"SC",
    "sg:tags":[
        "consultant",
        "business"
    ],
    "wof:name":"Mccallum Sweeney Consltng Inc",
    "wof:placetype":"venue"
},
  "geometry": {"coordinates":[-82.397487,34.853991],"type":"Point"}
}