{
  "type": "Feature",
  "properties": {
    "iso:country":"US",
    "sg:address":"100 Fuldner Rd",
    "sg:city":"Barnwell",
    "sg:classifiers":[
        {
            "category":"Government",
            "subcategory":"Office",
            "type":"Public Place"
        }
    ],
    "sg:phone":"+1 803 259 7143",
    "sg:postcode":"29812",
    "sg:province":"SC",
    "sg:tags":[
        "federal"
    ],
    "wof:name":"US Consolidated Farm Svc Agcy",
    "wof:placetype":"venue"
},
  "geometry": {"coordinates":[-81.379051,33.258042],"type":"Point"}
}