{
  "type": "Feature",
  "properties": {
    "addr:full":"2114 Wilson Rd Newberry SC 29108",
    "addr:housenumber":"2114",
    "addr:postcode":"29108",
    "addr:street":"Wilson Rd",
    "iso:country":"US",
    "sg:address":"2114 Wilson Rd",
    "sg:city":"Newberry",
    "sg:classifiers":[
        {
            "category":"Food & Beverages",
            "subcategory":"Fruits & Vegetables",
            "type":"Retail Goods"
        }
    ],
    "sg:phone":"+1 803 321 0922",
    "sg:postcode":"29108",
    "sg:province":"SC",
    "sg:tags":[
        "produce"
    ],
    "wof:name":"Mike's Produce",
    "wof:placetype":"venue"
},
  "geometry": {"coordinates":[-81.609334,34.297446],"type":"Point"}
}