{
  "type": "Feature",
  "properties": {
    "iso:country":"US",
    "sg:address":"1736 Old Columbia Rd",
    "sg:city":"Chester",
    "sg:classifiers":[
        {
            "category":"Organizations",
            "subcategory":"Religious Organization",
            "type":"Services"
        }
    ],
    "sg:phone":"+1 803 385 2124",
    "sg:postcode":"29014",
    "sg:province":"SC",
    "sg:tags":[
        "church"
    ],
    "wof:name":"Pleasant View AME Zion",
    "wof:placetype":"venue"
},
  "geometry": {"coordinates":[-81.187992,34.645716],"type":"Point"}
}