{
  "type": "Feature",
  "properties": {
    "iso:country":"US",
    "sg:address":"234 Miami Rd",
    "sg:city":"Ladson",
    "sg:classifiers":[
        {
            "category":"Real Estate",
            "subcategory":"Real Estate Operator",
            "type":"Services"
        }
    ],
    "sg:phone":"+1 843 572 5712",
    "sg:postcode":"29456",
    "sg:province":"SC",
    "sg:tags":[
        "mobile",
        "home",
        "site",
        "community"
    ],
    "wof:name":"Rye Field Mobile Home Park",
    "wof:placetype":"venue"
},
  "geometry": {"coordinates":[-80.092856,33.027458],"type":"Point"}
}