{
  "type": "Feature",
  "properties": {
    "iso:country":"US",
    "sg:address":"13 Running Springs Ct",
    "sg:city":"Greer",
    "sg:classifiers":[
        {
            "category":"Real Estate",
            "subcategory":"Real Estate Operator",
            "type":"Services"
        }
    ],
    "sg:phone":"+1 864 322 8959",
    "sg:postcode":"29650",
    "sg:province":"SC",
    "sg:tags":[
        "building",
        "nonresidential"
    ],
    "wof:name":"Gasworks Properties LLC",
    "wof:placetype":"venue"
},
  "geometry": {"coordinates":[-82.280153,34.880514],"type":"Point"}
}