{
  "type": "Feature",
  "properties": {
    "iso:country":"US",
    "sg:address":"1305 Sam Rittenberg Blvd",
    "sg:city":"Charleston",
    "sg:classifiers":[
        {
            "category":"Banks & Credit Unions",
            "subcategory":"Bank",
            "type":"Services"
        }
    ],
    "sg:phone":"+1 843 577 8352",
    "sg:postcode":"29407",
    "sg:province":"SC",
    "wof:name":"Wachovia Bank",
    "wof:placetype":"venue"
},
  "geometry": {"coordinates":[-79.995796,32.815576],"type":"Point"}
}