{
  "type": "Feature",
  "properties": {
    "addr:full":"719 Thompson Blvd Union SC 29379",
    "addr:housenumber":"719",
    "addr:postcode":"29379",
    "addr:street":"Thompson Blvd",
    "iso:country":"US",
    "sg:address":"719 Thompson Blvd",
    "sg:city":"Union",
    "sg:classifiers":[
        {
            "category":"Shopping",
            "subcategory":"Used Merchandise",
            "type":"Retail Goods"
        }
    ],
    "sg:phone":"+1 864 429 5124",
    "sg:postcode":"29379",
    "sg:province":"SC",
    "wof:name":"Cgd and Grd Management Co LLC",
    "wof:placetype":"venue"
},
  "geometry": {"coordinates":[-81.634107,34.735225],"type":"Point"}
}