{
  "type": "Feature",
  "properties": {
    "iso:country":"US",
    "sg:address":"108 Bluff Ave",
    "sg:city":"North Augusta",
    "sg:classifiers":[
        {
            "category":"Autos & Motor Vehicles",
            "subcategory":"Motorcycle Sales",
            "type":"Retail Goods"
        }
    ],
    "sg:phone":"+1 803 279 4673",
    "sg:postcode":"29841",
    "sg:province":"SC",
    "wof:name":"Southeastern Choppers",
    "wof:placetype":"venue"
},
  "geometry": {"coordinates":[-81.972777,33.48959],"type":"Point"}
}