{
  "type": "Feature",
  "properties": {
    "addr:full":"604 Pettigru St Greenville SC 29601",
    "addr:housenumber":"604",
    "addr:postcode":"29601",
    "addr:street":"Pettigru St",
    "iso:country":"US",
    "sg:address":"604 Pettigru St",
    "sg:city":"Greenville",
    "sg:classifiers":[
        {
            "category":"Professional",
            "subcategory":"Lawyer & Legal Services",
            "type":"Services"
        }
    ],
    "sg:phone":"+1 864 240 4449",
    "sg:postcode":"29601",
    "sg:province":"SC",
    "sg:tags":[
        "attorney"
    ],
    "wof:name":"E Kimberly Berry",
    "wof:placetype":"venue"
},
  "geometry": {"coordinates":[-82.38436900000001,34.852117],"type":"Point"}
}