{
  "type": "Feature",
  "properties": {
    "iso:country":"US",
    "sg:address":"9 Hope Harbor Dr",
    "sg:city":"Greeleyville",
    "sg:classifiers":[
        {
            "category":"Real Estate",
            "subcategory":"Real Estate Operator",
            "type":"Services"
        }
    ],
    "sg:phone":"+1 843 426 4053",
    "sg:postcode":"29056",
    "sg:province":"SC",
    "sg:tags":[
        "apartment"
    ],
    "wof:name":"Hope Harbor Apartments",
    "wof:placetype":"venue"
},
  "geometry": {"coordinates":[-79.993723,33.575505],"type":"Point"}
}