{
  "type": "Feature",
  "properties": {
    "iso:country":"US",
    "sg:address":"3381 Ashley Phosphate Rd",
    "sg:city":"North Charleston",
    "sg:classifiers":[
        {
            "category":"Bars & Pubs",
            "type":"Food & Drink"
        }
    ],
    "sg:phone":"+1 843 552 1095",
    "sg:postcode":"29418",
    "sg:province":"SC",
    "wof:name":"Sonia's Manili Grill & Lounge",
    "wof:placetype":"venue"
},
  "geometry": {"coordinates":[-80.074831,32.928503],"type":"Point"}
}