{
  "type": "Feature",
  "properties": {
    "iso:country":"US",
    "sg:address":"1223 Victory St",
    "sg:city":"Newberry",
    "sg:classifiers":[
        {
            "category":"Wholesale",
            "subcategory":"Sporting Goods",
            "type":"Manufacturing & Wholesale Goods"
        }
    ],
    "sg:phone":"+1 803 276 4993",
    "sg:postcode":"29108",
    "sg:province":"SC",
    "sg:tags":[
        "equipment",
        "pool",
        "swimming"
    ],
    "wof:name":"Moseley Pools & Spas",
    "wof:placetype":"venue"
},
  "geometry": {"coordinates":[-81.621585,34.273929],"type":"Point"}
}