{
  "type": "Feature",
  "properties": {
    "iso:country":"US",
    "sg:address":"4389 Wade Hampton Blvd",
    "sg:city":"Taylors",
    "sg:phone":"+1 864 292 1842",
    "sg:postcode":"29687",
    "sg:province":"SC",
    "wof:name":"Carolina Lawn & Tractor Inc",
    "wof:placetype":"venue"
},
  "geometry": {"coordinates":[-82.299882,34.927522],"type":"Point"}
}