{
  "type": "Feature",
  "properties": {
    "iso:country":"US",
    "sg:address":"900 Beech St",
    "sg:city":"Gaffney",
    "sg:classifiers":[
        {
            "category":"Shopping",
            "subcategory":"Used Merchandise",
            "type":"Retail Goods"
        }
    ],
    "sg:phone":"+1 864 489 8113",
    "sg:postcode":"29340",
    "sg:province":"SC",
    "sg:tags":[
        "shop",
        "consignment"
    ],
    "wof:name":"A To Z Consignment Shop",
    "wof:placetype":"venue"
},
  "geometry": {"coordinates":[-81.635111,35.074706],"type":"Point"}
}