{
  "type": "Feature",
  "properties": {
    "iso:country":"US",
    "sg:address":"4150 Choice Ct",
    "sg:city":"Sumter",
    "sg:classifiers":[
        {
            "category":"Retail",
            "subcategory":"Auto Repair",
            "type":"Services"
        }
    ],
    "sg:phone":"+1 803 494 5348",
    "sg:postcode":"29154",
    "sg:province":"SC",
    "sg:tags":[
        "repairing",
        "automobile"
    ],
    "wof:name":"Davis Body Shop",
    "wof:placetype":"venue"
},
  "geometry": {"coordinates":[-80.44399799999999,33.882865],"type":"Point"}
}