{
  "type": "Feature",
  "properties": {
    "iso:country":"US",
    "sg:address":"227 Glassmaster Rd",
    "sg:city":"Lexington",
    "sg:classifiers":[
        {
            "category":"Utilities",
            "subcategory":"Refuse",
            "type":"Services"
        }
    ],
    "sg:phone":"+1 803 808 5099",
    "sg:postcode":"29072",
    "sg:province":"SC",
    "sg:tags":[
        "garbage",
        "collection"
    ],
    "sg:website":"www.asi-sc.com",
    "wof:name":"Allwaste Services Inc",
    "wof:placetype":"venue"
},
  "geometry": {"coordinates":[-81.225437,33.961563],"type":"Point"}
}