{
  "type": "Feature",
  "properties": {
    "addr:full":"2516 Augusta Rd West Columbia SC 29169",
    "addr:housenumber":"2516",
    "addr:postcode":"29169",
    "addr:street":"Augusta Rd",
    "iso:country":"US",
    "sg:address":"2516 Augusta Rd",
    "sg:city":"West Columbia",
    "sg:classifiers":[
        {
            "category":"Travel",
            "subcategory":"Hotels & Motels",
            "type":"Entertainment"
        }
    ],
    "sg:phone":"+1 803 791 5160",
    "sg:postcode":"29169",
    "sg:province":"SC",
    "sg:website":"www.qualityinn.com",
    "wof:name":"Quality Inn",
    "wof:placetype":"venue"
},
  "geometry": {"coordinates":[-81.102845,33.981903],"type":"Point"}
}