{
  "type": "Feature",
  "properties": {
    "addr:full":"103 Shamrock Ct Easley SC 29640",
    "addr:housenumber":"103",
    "addr:postcode":"29640",
    "addr:street":"Shamrock Ct",
    "iso:country":"US",
    "sg:address":"103 Shamrock Ct",
    "sg:city":"Easley",
    "sg:classifiers":[
        {
            "category":"Retail",
            "subcategory":"Repair Shop",
            "type":"Services"
        }
    ],
    "sg:phone":"+1 864 859 3638",
    "sg:postcode":"29640",
    "sg:province":"SC",
    "sg:tags":[
        "cleaners",
        "parts",
        "vacuum"
    ],
    "wof:name":"Kenny Grant",
    "wof:placetype":"venue"
},
  "geometry": {"coordinates":[-82.609622,34.840147],"type":"Point"}
}