{
  "type": "Feature",
  "properties": {
    "iso:country":"US",
    "sg:address":"111 McGee St",
    "sg:city":"Greenville",
    "sg:classifiers":[
        {
            "category":"Insurance",
            "subcategory":"Hazard Insurance",
            "type":"Services"
        }
    ],
    "sg:phone":"+1 864 233 3076",
    "sg:postcode":"29601",
    "sg:province":"SC",
    "sg:tags":[
        "bond"
    ],
    "wof:name":"Trotter Bonding Co",
    "wof:placetype":"venue"
},
  "geometry": {"coordinates":[-82.38910199999999,34.854693],"type":"Point"}
}