{
  "type": "Feature",
  "properties": {
    "addr:full":"817 Buncombe St Edgefield SC 29824",
    "addr:housenumber":"817",
    "addr:postcode":"29824",
    "addr:street":"Buncombe St",
    "iso:country":"US",
    "sg:address":"817 Buncombe St",
    "sg:city":"Edgefield",
    "sg:classifiers":[
        {
            "category":"Building & Trades",
            "subcategory":"Construction",
            "type":"Services"
        }
    ],
    "sg:phone":"+1 803 637 4622",
    "sg:postcode":"29824",
    "sg:province":"SC",
    "sg:tags":[
        "contractor"
    ],
    "wof:name":"Edgefield Construction Inc",
    "wof:placetype":"venue"
},
  "geometry": {"coordinates":[-81.931399,33.805197],"type":"Point"}
}