{
  "type": "Feature",
  "properties": {
    "iso:country":"US",
    "sg:address":"230 Baron Rd",
    "sg:city":"Lexington",
    "sg:classifiers":[
        {
            "category":"Real Estate",
            "subcategory":"Real Estate Agent",
            "type":"Services"
        }
    ],
    "sg:phone":"+1 803 808 0722",
    "sg:postcode":"29072",
    "sg:province":"SC",
    "wof:name":"Corely & Associates LLC",
    "wof:placetype":"venue"
},
  "geometry": {"coordinates":[-81.196973,34.021677],"type":"Point"}
}