{
  "type": "Feature",
  "properties": {
    "iso:country":"US",
    "sg:address":"517 Kings Mountain St",
    "sg:city":"Clover",
    "sg:classifiers":[
        {
            "category":"Organizations",
            "subcategory":"Religious Organization",
            "type":"Services"
        }
    ],
    "sg:phone":"+1 803 222 2090",
    "sg:postcode":"29710",
    "sg:province":"SC",
    "sg:tags":[
        "church"
    ],
    "wof:name":"Mt Carmel Holiness Church-God",
    "wof:placetype":"venue"
},
  "geometry": {"coordinates":[-81.23326299999999,35.116489],"type":"Point"}
}