{
  "type": "Feature",
  "properties": {
    "iso:country":"US",
    "sg:address":"330 Stamford Bridge Rd",
    "sg:city":"Columbia",
    "sg:classifiers":[
        {
            "category":"Building & Trades",
            "subcategory":"Construction",
            "type":"Services"
        }
    ],
    "sg:phone":"+1 803 407 9153",
    "sg:postcode":"29212",
    "sg:province":"SC",
    "sg:tags":[
        "contractor"
    ],
    "wof:name":"Schluter Systems",
    "wof:placetype":"venue"
},
  "geometry": {"coordinates":[-81.193964,34.06202],"type":"Point"}
}