{
  "type": "Feature",
  "properties": {
    "addr:full":"620 Main St Newberry SC 29108",
    "addr:housenumber":"620",
    "addr:postcode":"29108",
    "addr:street":"Main St",
    "iso:country":"US",
    "sg:address":"620 Main St",
    "sg:city":"Newberry",
    "sg:classifiers":[
        {
            "category":"Organizations",
            "subcategory":"Religious Organization",
            "type":"Services"
        }
    ],
    "sg:phone":"+1 803 276 1676",
    "sg:postcode":"29108",
    "sg:province":"SC",
    "sg:tags":[
        "church"
    ],
    "wof:name":"West End Baptist Church",
    "wof:placetype":"venue"
},
  "geometry": {"coordinates":[-81.625332,34.270539],"type":"Point"}
}