{
  "type": "Feature",
  "properties": {
    "iso:country":"US",
    "sg:address":"1398 Cassidy Ct",
    "sg:city":"Mt Pleasant",
    "sg:classifiers":[
        {
            "category":"Real Estate",
            "subcategory":"Real Estate Operator",
            "type":"Services"
        }
    ],
    "sg:phone":"+1 843 216 0142",
    "sg:postcode":"29464",
    "sg:province":"SC",
    "sg:tags":[
        "apartment"
    ],
    "wof:name":"Remington Forest Apartments",
    "wof:placetype":"venue"
},
  "geometry": {"coordinates":[-79.854812,32.794883],"type":"Point"}
}