{
  "type": "Feature",
  "properties": {
    "iso:country":"US",
    "sg:address":"1975 All Seymour Ln",
    "sg:city":"Charleston",
    "sg:classifiers":[
        {
            "category":"Restaurant",
            "type":"Food & Drink"
        }
    ],
    "sg:phone":"+1 843 571 6999",
    "sg:postcode":"29412",
    "sg:province":"SC",
    "sg:tags":[
        "chinese"
    ],
    "wof:name":"Panda Express Chinese Rest",
    "wof:placetype":"venue"
},
  "geometry": {"coordinates":[-79.98210400000001,32.72704],"type":"Point"}
}