{
  "type": "Feature",
  "properties": {
    "iso:country":"US",
    "sg:address":"902 Bacons Bridge Rd",
    "sg:city":"Summerville",
    "sg:classifiers":[
        {
            "category":"Restaurant",
            "type":"Food & Drink"
        }
    ],
    "sg:phone":"+1 843 851 7487",
    "sg:postcode":"29485",
    "sg:province":"SC",
    "sg:tags":[
        "caterer"
    ],
    "wof:name":"Perfect Touch Catering",
    "wof:placetype":"venue"
},
  "geometry": {"coordinates":[-80.201572,32.963245],"type":"Point"}
}