{
  "type": "Feature",
  "properties": {
    "iso:country":"US",
    "sg:address":"807 Gervais St",
    "sg:city":"Columbia",
    "sg:classifiers":[
        {
            "category":"Professional",
            "subcategory":"Art Services",
            "type":"Services"
        }
    ],
    "sg:phone":"+1 803 376 5120",
    "sg:postcode":"29201",
    "sg:province":"SC",
    "sg:tags":[
        "graphic",
        "designer"
    ],
    "wof:name":"My Image Appeals",
    "wof:placetype":"venue"
},
  "geometry": {"coordinates":[-81.038661,33.999787],"type":"Point"}
}