{
  "type": "Feature",
  "properties": {
    "addr:full":"200 Brozinni Ct Greenville SC 29615",
    "addr:housenumber":"200",
    "addr:postcode":"29615",
    "addr:street":"Brozinni Ct",
    "iso:country":"US",
    "sg:address":"200 Brozinni Ct",
    "sg:city":"Greenville",
    "sg:classifiers":[
        {
            "category":"Wholesale",
            "subcategory":"Machinery & Supplies",
            "type":"Manufacturing & Wholesale Goods"
        }
    ],
    "sg:phone":"+1 864 254 0071",
    "sg:postcode":"29615",
    "sg:province":"SC",
    "sg:tags":[
        "textile",
        "parts"
    ],
    "wof:name":"Fiber Tech Products",
    "wof:placetype":"venue"
},
  "geometry": {"coordinates":[-82.253319,34.852187],"type":"Point"}
}