{
  "type": "Feature",
  "properties": {
    "iso:country":"US",
    "sg:address":"319 Bellhaven Ln",
    "sg:city":"Spartanburg",
    "sg:classifiers":[
        {
            "category":"Shopping",
            "subcategory":"Beauty & Cosmetics",
            "type":"Retail Goods"
        }
    ],
    "sg:phone":"+1 864 574 6389",
    "sg:postcode":"29301",
    "sg:province":"SC",
    "sg:tags":[
        "merchandise"
    ],
    "wof:name":"Lc Cosmetics Kerin Hannah",
    "wof:placetype":"venue"
},
  "geometry": {"coordinates":[-82.012556,34.94113],"type":"Point"}
}