{
  "type": "Feature",
  "properties": {
    "iso:country":"US",
    "sg:address":"12 H E McCracken Cir",
    "sg:city":"Bluffton",
    "sg:classifiers":[
        {
            "category":"Building & Trades",
            "subcategory":"Construction",
            "type":"Services"
        }
    ],
    "sg:phone":"+1 843 706 2493",
    "sg:postcode":"29910",
    "sg:province":"SC",
    "sg:tags":[
        "general",
        "contractor"
    ],
    "wof:name":"Beers Skanska",
    "wof:placetype":"venue"
},
  "geometry": {"coordinates":[-80.901093,32.245169],"type":"Point"}
}