{
  "type": "Feature",
  "properties": {
    "iso:country":"US",
    "sg:address":"205 Gadsden St",
    "sg:city":"Summerville",
    "sg:classifiers":[
        {
            "category":"Professional",
            "subcategory":"Business Services",
            "type":"Services"
        }
    ],
    "sg:phone":"+1 843 873 6155",
    "sg:postcode":"29483",
    "sg:province":"SC",
    "wof:name":"Ice Age Ice Scultures",
    "wof:placetype":"venue"
},
  "geometry": {"coordinates":[-80.193026,33.01083],"type":"Point"}
}