{
  "type": "Feature",
  "properties": {
    "addr:full":"57 Morgan Rd Hilton Head Isle SC 29940",
    "addr:housenumber":"57",
    "addr:postcode":"29940",
    "addr:street":"Morgan Rd",
    "iso:country":"US",
    "sg:address":"57 Morgan Rd",
    "sg:city":"Hilton Head Isle",
    "sg:classifiers":[
        {
            "category":"Professional",
            "type":"Services"
        }
    ],
    "sg:phone":"+1 843 686 3579",
    "sg:postcode":"29940",
    "sg:province":"SC",
    "sg:tags":[
        "establishment"
    ],
    "wof:name":"Southland Environmental Inc",
    "wof:placetype":"venue"
},
  "geometry": {"coordinates":[-80.743819,32.547357],"type":"Point"}
}