{
  "type": "Feature",
  "properties": {
    "iso:country":"US",
    "sg:address":"108 E Steele Dr",
    "sg:city":"Summerville",
    "sg:classifiers":[
        {
            "category":"Retail",
            "subcategory":"Repair Shop",
            "type":"Services"
        }
    ],
    "sg:phone":"+1 843 871 8284",
    "sg:postcode":"29483",
    "sg:province":"SC",
    "sg:tags":[
        "refinishing",
        "furniture"
    ],
    "wof:name":"Susan Cramers Quality Rfnshng",
    "wof:placetype":"venue"
},
  "geometry": {"coordinates":[-80.19493199999999,33.050866],"type":"Point"}
}