{
  "type": "Feature",
  "properties": {
    "addr:full":"8011 Marlboro Ave Barnwell SC 29812",
    "addr:housenumber":"8011",
    "addr:postcode":"29812",
    "addr:street":"Marlboro Ave",
    "iso:country":"US",
    "sg:address":"8011 Marlboro Ave",
    "sg:city":"Barnwell",
    "sg:classifiers":[
        {
            "category":"Home & Garden",
            "subcategory":"Mobile Homes",
            "type":"Retail Goods"
        }
    ],
    "sg:phone":"+1 803 541 4008",
    "sg:postcode":"29812",
    "sg:province":"SC",
    "wof:name":"Horton Homes",
    "wof:placetype":"venue"
},
  "geometry": {"coordinates":[-81.35597,33.222148],"type":"Point"}
}