{
  "type": "Feature",
  "properties": {
    "iso:country":"US",
    "sg:address":"190 Cherokee Farms Rd",
    "sg:city":"Beaufort",
    "sg:classifiers":[
        {
            "category":"Building & Trades",
            "subcategory":"Construction",
            "type":"Services"
        }
    ],
    "sg:phone":"+1 843 846 9883",
    "sg:postcode":"29906",
    "sg:province":"SC",
    "sg:tags":[
        "excavating",
        "contractor"
    ],
    "wof:name":"LCR Construction",
    "wof:placetype":"venue"
},
  "geometry": {"coordinates":[-80.768902,32.431381],"type":"Point"}
}