{
  "type": "Feature",
  "properties": {
    "iso:country":"US",
    "sg:address":"1554 Old Dairy Dr",
    "sg:city":"Columbia",
    "sg:classifiers":[
        {
            "category":"Wholesale",
            "subcategory":"Machinery & Supplies",
            "type":"Manufacturing & Wholesale Goods"
        }
    ],
    "sg:phone":"+1 803 252 6754",
    "sg:postcode":"29201",
    "sg:province":"SC",
    "sg:tags":[
        "rubber",
        "product",
        "industrial"
    ],
    "wof:name":"Interstate Indus Rbr Co LLC",
    "wof:placetype":"venue"
},
  "geometry": {"coordinates":[-81.008343,33.964259],"type":"Point"}
}