{
  "type": "Feature",
  "properties": {
    "iso:country":"US",
    "sg:address":"1 Wendy Ln",
    "sg:city":"Charleston",
    "sg:classifiers":[
        {
            "category":"Shopping",
            "subcategory":"Gifts & Souvenirs",
            "type":"Retail Goods"
        }
    ],
    "sg:phone":"+1 843 763 9039",
    "sg:postcode":"29407",
    "sg:province":"SC",
    "wof:name":"Lou S Mary Ltd",
    "wof:placetype":"venue"
},
  "geometry": {"coordinates":[-80.006242,32.804801],"type":"Point"}
}