{
  "type": "Feature",
  "properties": {
    "addr:full":"703 W Pine St Kershaw SC 29067",
    "addr:housenumber":"703",
    "addr:postcode":"29067",
    "addr:street":"W Pine St",
    "iso:country":"US",
    "sg:address":"703 W Pine St",
    "sg:city":"Kershaw",
    "sg:classifiers":[
        {
            "category":"Banks & Credit Unions",
            "subcategory":"Financial Services",
            "type":"Services"
        }
    ],
    "sg:phone":"+1 803 475 5675",
    "sg:postcode":"29067",
    "sg:province":"SC",
    "sg:tags":[
        "investor"
    ],
    "wof:name":"Thomas Investment Properties",
    "wof:placetype":"venue"
},
  "geometry": {"coordinates":[-80.590737,34.54293],"type":"Point"}
}