{
  "type": "Feature",
  "properties": {
    "addr:full":"116 S Lake Emory Dr Inman SC 29349",
    "addr:housenumber":"116",
    "addr:postcode":"29349",
    "addr:street":"S Lake Emory Dr",
    "iso:country":"US",
    "sg:address":"116 S Lake Emory Dr",
    "sg:city":"Inman",
    "sg:classifiers":[
        {
            "category":"Building & Trades",
            "subcategory":"Construction",
            "type":"Services"
        }
    ],
    "sg:phone":"+1 864 472 6985",
    "sg:postcode":"29349",
    "sg:province":"SC",
    "sg:tags":[
        "house"
    ],
    "wof:name":"Daystar Builders Inc",
    "wof:placetype":"venue"
},
  "geometry": {"coordinates":[-82.064324,35.035418],"type":"Point"}
}