{
  "type": "Feature",
  "properties": {
    "iso:country":"US",
    "sg:address":"411 2nd Loop Rd",
    "sg:city":"Florence",
    "sg:classifiers":[
        {
            "category":"Banks & Credit Unions",
            "subcategory":"Bank",
            "type":"Services"
        }
    ],
    "sg:phone":"+1 843 656 2100",
    "sg:postcode":"29505",
    "sg:province":"SC",
    "sg:tags":[
        "commercial"
    ],
    "wof:name":"First Reliance Bank",
    "wof:placetype":"venue"
},
  "geometry": {"coordinates":[-79.770048,34.166883],"type":"Point"}
}