{
  "type": "Feature",
  "properties": {
    "iso:country":"US",
    "sg:address":"119 Spring St",
    "sg:city":"Charleston",
    "sg:classifiers":[
        {
            "category":"Restaurant",
            "type":"Food & Drink"
        }
    ],
    "sg:phone":"+1 843 853 2517",
    "sg:postcode":"29403",
    "sg:province":"SC",
    "wof:name":"Wali's Fish Supreme",
    "wof:placetype":"venue"
},
  "geometry": {"coordinates":[-79.948497,32.789665],"type":"Point"}
}