{
  "type": "Feature",
  "properties": {
    "iso:country":"US",
    "sg:address":"208 Brookstone Way",
    "sg:city":"Irmo",
    "sg:classifiers":[
        {
            "category":"Building & Trades",
            "subcategory":"Construction",
            "type":"Services"
        }
    ],
    "sg:phone":"+1 803 781 5485",
    "sg:postcode":"29063",
    "sg:province":"SC",
    "sg:tags":[
        "project"
    ],
    "wof:name":"J P Enterprises",
    "wof:placetype":"venue"
},
  "geometry": {"coordinates":[-81.217493,34.142643],"type":"Point"}
}