{
  "type": "Feature",
  "properties": {
    "iso:country":"US",
    "sg:address":"385 N Church St",
    "sg:city":"Spartanburg",
    "sg:classifiers":[
        {
            "category":"Professional",
            "subcategory":"Business Services",
            "type":"Services"
        }
    ],
    "sg:phone":"+1 864 582 8107",
    "sg:postcode":"29303",
    "sg:province":"SC",
    "sg:tags":[
        "conference",
        "center"
    ],
    "sg:website":"www.crowdpleaser.com",
    "wof:name":"Spartanburg Memorial Adtrm",
    "wof:placetype":"venue"
},
  "geometry": {"coordinates":[-81.937505,34.957367],"type":"Point"}
}