{
  "type": "Feature",
  "properties": {
    "addr:full":"1280 Eighteen Mile Rd Central SC 29630",
    "addr:housenumber":"1280",
    "addr:postcode":"29630",
    "addr:street":"Eighteen Mile Rd",
    "iso:country":"US",
    "sg:address":"1280 Eighteen Mile Rd",
    "sg:city":"Central",
    "sg:classifiers":[
        {
            "category":"Restaurant",
            "type":"Food & Drink"
        }
    ],
    "sg:menulink":"http://www.allmenus.com/sc/central/129174-subway/menu/",
    "sg:phone":"+1 864 639 2227",
    "sg:postcode":"29630",
    "sg:province":"SC",
    "sg:tags":[
        "american",
        "sandwich"
    ],
    "wof:name":"Subway",
    "wof:placetype":"venue"
},
  "geometry": {"coordinates":[-82.752329,34.699405],"type":"Point"}
}