{
  "type": "Feature",
  "properties": {
    "iso:country":"US",
    "sg:address":"248 Meeting Street Rd",
    "sg:city":"Edgefield",
    "sg:classifiers":[
        {
            "category":"Farming",
            "subcategory":"Livestock Farm",
            "type":"Manufacturing & Wholesale Goods"
        }
    ],
    "sg:phone":"+1 803 637 6940",
    "sg:postcode":"29824",
    "sg:province":"SC",
    "sg:tags":[
        "beef",
        "feedlot",
        "cattle"
    ],
    "wof:name":"Pottersville Ranch Inc",
    "wof:placetype":"venue"
},
  "geometry": {"coordinates":[-81.92845199999999,33.831331],"type":"Point"}
}