{
  "type": "Feature",
  "properties": {
    "iso:country":"US",
    "sg:address":"81 Charleston Hwy",
    "sg:city":"Yemassee",
    "sg:classifiers":[
        {
            "category":"Food & Beverages",
            "subcategory":"Specialty",
            "type":"Retail Goods"
        }
    ],
    "sg:phone":"+1 843 846 1899",
    "sg:postcode":"29945",
    "sg:province":"SC",
    "sg:tags":[
        "gourmet",
        "shop"
    ],
    "sg:website":"www.carolinacidercompany.com",
    "wof:name":"Carolina Cherry Co",
    "wof:placetype":"venue"
},
  "geometry": {"coordinates":[-80.751392,32.608129],"type":"Point"}
}