{
  "type": "Feature",
  "properties": {
    "addr:full":"230 Swartz Rd Lexington SC 29072",
    "addr:housenumber":"230",
    "addr:postcode":"29072",
    "addr:street":"Swartz Rd",
    "iso:country":"US",
    "sg:address":"230 Swartz Rd",
    "sg:city":"Lexington",
    "sg:classifiers":[
        {
            "category":"Building & Trades",
            "subcategory":"Plumbing",
            "type":"Services"
        }
    ],
    "sg:phone":"+1 803 359 7801",
    "sg:postcode":"29072",
    "sg:province":"SC",
    "sg:tags":[
        "heating",
        "contractor"
    ],
    "wof:name":"Cool Flow Heating & Air Inc",
    "wof:placetype":"venue"
},
  "geometry": {"coordinates":[-81.226353,33.972022],"type":"Point"}
}