{
  "type": "Feature",
  "properties": {
    "iso:country":"US",
    "sg:address":"115 Zion Church Rd",
    "sg:city":"Clover",
    "sg:classifiers":[
        {
            "category":"Organizations",
            "subcategory":"Religious Organization",
            "type":"Services"
        }
    ],
    "sg:phone":"+1 803 222 9141",
    "sg:postcode":"29710",
    "sg:province":"SC",
    "sg:tags":[
        "church"
    ],
    "wof:name":"Zoar AME Zion Church",
    "wof:placetype":"venue"
},
  "geometry": {"coordinates":[-81.235747,35.119606],"type":"Point"}
}