{
  "type": "Feature",
  "properties": {
    "addr:full":"114 Northman Dr Columbia SC 29210",
    "addr:housenumber":"114",
    "addr:postcode":"29210",
    "addr:street":"Northman Dr",
    "iso:country":"US",
    "sg:address":"114 Northman Dr",
    "sg:city":"Columbia",
    "sg:classifiers":[
        {
            "category":"Building & Trades",
            "subcategory":"Landscaping Services",
            "type":"Services"
        }
    ],
    "sg:phone":"+1 803 772 4370",
    "sg:postcode":"29210",
    "sg:province":"SC",
    "sg:tags":[
        "lawn",
        "maintenance",
        "grounds"
    ],
    "wof:name":"Wahab's Lawn Svc & Landscaping",
    "wof:placetype":"venue"
},
  "geometry": {"coordinates":[-81.147558,34.04944],"type":"Point"}
}