{
  "type": "Feature",
  "properties": {
    "addr:full":"6746 Johnston Ave Reevesville SC 29471",
    "addr:housenumber":"6746",
    "addr:postcode":"29471",
    "addr:street":"Johnston Ave",
    "iso:country":"US",
    "sg:address":"6746 Johnston Ave",
    "sg:city":"Reevesville",
    "sg:classifiers":[
        {
            "category":"Shopping",
            "subcategory":"Gifts & Souvenirs",
            "type":"Retail Goods"
        }
    ],
    "sg:phone":"+1 843 563 9855",
    "sg:postcode":"29471",
    "sg:province":"SC",
    "sg:tags":[
        "shop"
    ],
    "wof:name":"Other Place",
    "wof:placetype":"venue"
},
  "geometry": {"coordinates":[-80.64327299999999,33.206028],"type":"Point"}
}