{
  "type": "Feature",
  "properties": {
    "iso:country":"US",
    "sg:address":"101 Pickens Dr",
    "sg:city":"Liberty",
    "sg:classifiers":[
        {
            "category":"Health Services",
            "subcategory":"Doctor",
            "type":"Services"
        }
    ],
    "sg:phone":"+1 864 843 9213",
    "sg:postcode":"29657",
    "sg:province":"SC",
    "sg:tags":[
        "physician",
        "surgeon"
    ],
    "wof:name":"Holcombe Family Practice",
    "wof:placetype":"venue"
},
  "geometry": {"coordinates":[-82.69301299999999,34.788637],"type":"Point"}
}