{
  "type": "Feature",
  "properties": {
    "addr:full":"332 W Main St Kingstree SC 29556",
    "addr:housenumber":"332",
    "addr:postcode":"29556",
    "addr:street":"W Main St",
    "iso:country":"US",
    "sg:address":"332 W Main St",
    "sg:city":"Kingstree",
    "sg:classifiers":[
        {
            "category":"Autos & Motor Vehicles",
            "subcategory":"Fuel & Gas Station",
            "type":"Retail Goods"
        }
    ],
    "sg:phone":"+1 843 354 6294",
    "sg:postcode":"29556",
    "sg:province":"SC",
    "sg:tags":[
        "oil"
    ],
    "wof:name":"Mc Knight's Texaco",
    "wof:placetype":"venue"
},
  "geometry": {"coordinates":[-79.835027,33.662707],"type":"Point"}
}