{
  "type": "Feature",
  "properties": {
    "iso:country":"US",
    "sg:address":"306 N Main St",
    "sg:city":"Hemingway",
    "sg:classifiers":[
        {
            "category":"Education",
            "subcategory":"Library",
            "type":"Public Place"
        }
    ],
    "sg:phone":"+1 843 558 0743",
    "sg:postcode":"29554",
    "sg:province":"SC",
    "wof:name":"Hemingway Public Library",
    "wof:placetype":"venue"
},
  "geometry": {"coordinates":[-79.44700899999999,33.757276],"type":"Point"}
}