{
  "type": "Feature",
  "properties": {
    "iso:country":"US",
    "sg:address":"15 Broad St",
    "sg:city":"Charleston",
    "sg:classifiers":[
        {
            "category":"Banks & Credit Unions",
            "subcategory":"Investment Brokerage",
            "type":"Services"
        }
    ],
    "sg:phone":"+1 843 722 3331",
    "sg:postcode":"29401",
    "sg:province":"SC",
    "sg:tags":[
        "consultant",
        "planning",
        "financial"
    ],
    "wof:name":"William C Prewitt MSCFP",
    "wof:placetype":"venue"
},
  "geometry": {"coordinates":[-79.927098,32.776761],"type":"Point"}
}