{
  "type": "Feature",
  "properties": {
    "addr:full":"207 Quarry Rd Spartanburg SC 29302",
    "addr:housenumber":"207",
    "addr:postcode":"29302",
    "addr:street":"Quarry Rd",
    "iso:country":"US",
    "sg:address":"207 Quarry Rd",
    "sg:city":"Spartanburg",
    "sg:classifiers":[
        {
            "category":"Shopping",
            "subcategory":"Catalog Store",
            "type":"Retail Goods"
        }
    ],
    "sg:phone":"+1 864 598 9354",
    "sg:postcode":"29302",
    "sg:province":"SC",
    "sg:tags":[
        "mail",
        "house"
    ],
    "wof:name":"Berbank & Co",
    "wof:placetype":"venue"
},
  "geometry": {"coordinates":[-81.89543500000001,34.92662],"type":"Point"}
}