{
  "type": "Feature",
  "properties": {
    "iso:country":"US",
    "sg:address":"813 Bay St",
    "sg:city":"Beaufort",
    "sg:classifiers":[
        {
            "category":"Shopping",
            "type":"Retail Goods"
        }
    ],
    "sg:phone":"+1 843 524 1036",
    "sg:postcode":"29902",
    "sg:province":"SC",
    "sg:tags":[
        "art",
        "dealer"
    ],
    "wof:name":"Collins Margaret",
    "wof:placetype":"venue"
},
  "geometry": {"coordinates":[-80.671679,32.430937],"type":"Point"}
}