{
  "type": "Feature",
  "properties": {
    "iso:country":"US",
    "sg:address":"442 Elder Rd",
    "sg:city":"Camden",
    "sg:classifiers":[
        {
            "category":"Recreation",
            "type":"Entertainment"
        }
    ],
    "sg:phone":"+1 803 432 9200",
    "sg:postcode":"29020",
    "sg:province":"SC",
    "sg:tags":[
        "stable"
    ],
    "wof:name":"Summer Tree Stables",
    "wof:placetype":"venue"
},
  "geometry": {"coordinates":[-80.508189,34.211213],"type":"Point"}
}