{
  "type": "Feature",
  "properties": {
    "iso:country":"US",
    "sg:address":"108 Timber Dr",
    "sg:city":"Greenville",
    "sg:classifiers":[
        {
            "category":"Shopping",
            "subcategory":"Clothing, Apparel, & Fashions",
            "type":"Retail Goods"
        }
    ],
    "sg:phone":"+1 864 269 2140",
    "sg:postcode":"29611",
    "sg:province":"SC",
    "wof:name":"G Maries Algnmnt Svc",
    "wof:placetype":"venue"
},
  "geometry": {"coordinates":[-82.49460000000001,34.828244],"type":"Point"}
}