{
  "type": "Feature",
  "properties": {
    "iso:country":"US",
    "sg:address":"1198 Busy Corner Rd",
    "sg:city":"Conway",
    "sg:classifiers":[
        {
            "category":"Building & Trades",
            "subcategory":"Landscaping Services",
            "type":"Services"
        }
    ],
    "sg:phone":"+1 843 365 9272",
    "sg:postcode":"29527",
    "sg:province":"SC",
    "wof:name":"Mews Lawn Care",
    "wof:placetype":"venue"
},
  "geometry": {"coordinates":[-79.166156,33.891107],"type":"Point"}
}