{
  "type": "Feature",
  "properties": {
    "iso:country":"US",
    "sg:address":"1661 Glenns Bay Rd",
    "sg:city":"Surfside Beach",
    "sg:classifiers":[
        {
            "category":"Professional",
            "subcategory":"Lawyer & Legal Services",
            "type":"Services"
        }
    ],
    "sg:phone":"+1 843 650 6777",
    "sg:postcode":"29575",
    "sg:province":"SC",
    "sg:tags":[
        "attorney"
    ],
    "wof:name":"Willcox Buyck & Williams",
    "wof:placetype":"venue"
},
  "geometry": {"coordinates":[-78.988867,33.618688],"type":"Point"}
}