{
  "type": "Feature",
  "properties": {
    "addr:full":"1579 Savannah Hwy Charleston SC 29407",
    "addr:housenumber":"1579",
    "addr:postcode":"29407",
    "addr:street":"Savannah Hwy",
    "iso:country":"US",
    "sg:address":"1579 Savannah Hwy",
    "sg:city":"Charleston",
    "sg:classifiers":[
        {
            "category":"Personal",
            "type":"Services"
        }
    ],
    "sg:phone":"+1 843 571 3322",
    "sg:postcode":"29407",
    "sg:province":"SC",
    "sg:tags":[
        "therapist",
        "massage"
    ],
    "wof:name":"Body Mind & Spirit",
    "wof:placetype":"venue"
},
  "geometry": {"coordinates":[-80.009349,32.786028],"type":"Point"}
}