{
  "type": "Feature",
  "properties": {
    "iso:country":"US",
    "sg:address":"1012 Pocalla Rd",
    "sg:city":"Sumter",
    "sg:classifiers":[
        {
            "category":"Autos & Motor Vehicles",
            "subcategory":"Auto Supplies",
            "type":"Retail Goods"
        }
    ],
    "sg:phone":"+1 803 778 2809",
    "sg:postcode":"29150",
    "sg:province":"SC",
    "sg:tags":[
        "automobile",
        "parts"
    ],
    "wof:name":"Parts Connection Inc",
    "wof:placetype":"venue"
},
  "geometry": {"coordinates":[-80.33905799999999,33.896353],"type":"Point"}
}