{
  "type": "Feature",
  "properties": {
    "iso:country":"US",
    "sg:address":"65 N Congress St",
    "sg:city":"York",
    "sg:classifiers":[
        {
            "category":"Shopping",
            "subcategory":"Bicycles & Sporting Goods",
            "type":"Retail Goods"
        }
    ],
    "sg:phone":"+1 803 684 7405",
    "sg:postcode":"29745",
    "sg:province":"SC",
    "sg:tags":[
        "equipment",
        "outdoor",
        "accessory"
    ],
    "wof:name":"Outdoor Shop",
    "wof:placetype":"venue"
},
  "geometry": {"coordinates":[-81.240346,34.996524],"type":"Point"}
}