{
  "type": "Feature",
  "properties": {
    "iso:country":"US",
    "sg:address":"4476 Socastee Blvd",
    "sg:city":"Myrtle Beach",
    "sg:classifiers":[
        {
            "category":"Personal",
            "subcategory":"Beauty Salon",
            "type":"Services"
        }
    ],
    "sg:phone":"+1 843 294 1149",
    "sg:postcode":"29588",
    "sg:province":"SC",
    "sg:tags":[
        "manicuring"
    ],
    "wof:name":"Magic Nails",
    "wof:placetype":"venue"
},
  "geometry": {"coordinates":[-78.97633999999999,33.686034],"type":"Point"}
}