{
  "type": "Feature",
  "properties": {
    "addr:full":"315 Thompson Blvd Union SC 29379",
    "addr:housenumber":"315",
    "addr:postcode":"29379",
    "addr:street":"Thompson Blvd",
    "iso:country":"US",
    "sg:address":"315 Thompson Blvd",
    "sg:city":"Union",
    "sg:classifiers":[
        {
            "category":"Health Services",
            "subcategory":"Doctor",
            "type":"Services"
        }
    ],
    "sg:phone":"+1 864 429 2940",
    "sg:postcode":"29379",
    "sg:province":"SC",
    "sg:tags":[
        "clinic"
    ],
    "wof:name":"Dialysis Clinic Inc",
    "wof:placetype":"venue"
},
  "geometry": {"coordinates":[-81.629706,34.72612],"type":"Point"}
}