{
  "type": "Feature",
  "properties": {
    "iso:country":"US",
    "sg:address":"1201 State St",
    "sg:city":"Cayce",
    "sg:classifiers":[
        {
            "category":"Personal",
            "subcategory":"Beauty Salon",
            "type":"Services"
        }
    ],
    "sg:phone":"+1 803 794 6777",
    "sg:postcode":"29033",
    "sg:province":"SC",
    "wof:name":"Mill Village Salon",
    "wof:placetype":"venue"
},
  "geometry": {"coordinates":[-81.05534,33.982434],"type":"Point"}
}