{
  "type": "Feature",
  "properties": {
    "iso:country":"US",
    "sg:address":"213 Valley Dr",
    "sg:city":"Aiken",
    "sg:classifiers":[
        {
            "category":"Building & Trades",
            "subcategory":"Construction",
            "type":"Services"
        }
    ],
    "sg:phone":"+1 803 652 7474",
    "sg:postcode":"29803",
    "sg:province":"SC",
    "sg:tags":[
        "contractor"
    ],
    "wof:name":"Simpson Ellis & Charles",
    "wof:placetype":"venue"
},
  "geometry": {"coordinates":[-81.698191,33.446393],"type":"Point"}
}