{
  "type": "Feature",
  "properties": {
    "iso:country":"US",
    "sg:address":"120 Goodwin Rd",
    "sg:city":"Gaston",
    "sg:classifiers":[
        {
            "category":"Building & Trades",
            "subcategory":"Electrical",
            "type":"Services"
        }
    ],
    "sg:phone":"+1 803 794 1788",
    "sg:postcode":"29053",
    "sg:province":"SC",
    "sg:tags":[
        "electrical",
        "contractor"
    ],
    "wof:name":"Jacs Electric",
    "wof:placetype":"venue"
},
  "geometry": {"coordinates":[-81.08957100000001,33.829245],"type":"Point"}
}