{
  "type": "Feature",
  "properties": {
    "iso:country":"US",
    "sg:address":"5301 Notch Rd",
    "sg:city":"Columbia",
    "sg:classifiers":[
        {
            "category":"Shopping",
            "type":"Retail Goods"
        }
    ],
    "sg:phone":"+1 803 786 2174",
    "sg:postcode":"29204",
    "sg:province":"SC",
    "sg:tags":[
        "hearing",
        "equipment",
        "supply",
        "impaired"
    ],
    "wof:name":"American Hearing Svc",
    "wof:placetype":"venue"
},
  "geometry": {"coordinates":[-80.986193,34.048346],"type":"Point"}
}