{
  "type": "Feature",
  "properties": {
    "iso:country":"US",
    "sg:address":"375 S Ebenezer Rd",
    "sg:city":"Florence",
    "sg:classifiers":[
        {
            "category":"Home & Garden",
            "subcategory":"Garden Supply",
            "type":"Retail Goods"
        }
    ],
    "sg:phone":"+1 843 665 7288",
    "sg:postcode":"29501",
    "sg:province":"SC",
    "sg:tags":[
        "lawn"
    ],
    "wof:name":"Moseley Outdoor Power Equip",
    "wof:placetype":"venue"
},
  "geometry": {"coordinates":[-79.85260700000001,34.178233],"type":"Point"}
}