{
  "type": "Feature",
  "properties": {
    "iso:country":"US",
    "sg:address":"2111 N Pleasantburg Dr",
    "sg:city":"Greenville",
    "sg:classifiers":[
        {
            "category":"Food & Beverages",
            "subcategory":"Groceries & Convenience Stores",
            "type":"Retail Goods"
        }
    ],
    "sg:phone":"+1 864 242 3851",
    "sg:postcode":"29609",
    "sg:province":"SC",
    "sg:tags":[
        "grocer"
    ],
    "sg:website":"www.bilo.com",
    "wof:name":"Bi-Lo",
    "wof:placetype":"venue"
},
  "geometry": {"coordinates":[-82.375172,34.889608],"type":"Point"}
}