{
  "type": "Feature",
  "properties": {
    "iso:country":"US",
    "sg:address":"300 Main St",
    "sg:city":"Conway",
    "sg:classifiers":[
        {
            "category":"Personal",
            "subcategory":"Beauty Salon",
            "type":"Services"
        }
    ],
    "sg:phone":"+1 843 248 9083",
    "sg:postcode":"29526",
    "sg:province":"SC",
    "wof:name":"Vanite' Beauty Salon",
    "wof:placetype":"venue"
},
  "geometry": {"coordinates":[-79.04631999999999,33.835688],"type":"Point"}
}