{
  "type": "Feature",
  "properties": {
    "iso:country":"US",
    "sg:address":"903 Saint Andrews Blvd",
    "sg:city":"Charleston",
    "sg:classifiers":[
        {
            "category":"Health Services",
            "subcategory":"Doctor",
            "type":"Services"
        }
    ],
    "sg:phone":"+1 843 225 4080",
    "sg:postcode":"29407",
    "sg:province":"SC",
    "sg:tags":[
        "clinic"
    ],
    "wof:name":"Keystone Chiropractic",
    "wof:placetype":"venue"
},
  "geometry": {"coordinates":[-79.989485,32.792515],"type":"Point"}
}