{
  "type": "Feature",
  "properties": {
    "addr:full":"1000 Church St Conway SC 29526",
    "addr:housenumber":"1000",
    "addr:postcode":"29526",
    "addr:street":"Church St",
    "iso:country":"US",
    "sg:address":"1000 Church St",
    "sg:city":"Conway",
    "sg:classifiers":[
        {
            "category":"Manufacturing",
            "subcategory":"Food",
            "type":"Manufacturing & Wholesale Goods"
        }
    ],
    "sg:phone":"+1 843 248 7212",
    "sg:postcode":"29526",
    "sg:province":"SC",
    "sg:tags":[
        "product",
        "mfg"
    ],
    "wof:name":"Donut Stop",
    "wof:placetype":"venue"
},
  "geometry": {"coordinates":[-79.060171,33.839832],"type":"Point"}
}