{
  "type": "Feature",
  "properties": {
    "iso:country":"US",
    "sg:address":"101 Fabling Ct",
    "sg:city":"Taylors",
    "sg:classifiers":[
        {
            "category":"Building & Trades",
            "subcategory":"Electrical",
            "type":"Services"
        }
    ],
    "sg:phone":"+1 864 292 9299",
    "sg:postcode":"29687",
    "sg:province":"SC",
    "sg:tags":[
        "fiber",
        "installation",
        "optic",
        "cable",
        "datum",
        "voice"
    ],
    "wof:name":"Sterling Communications Inc",
    "wof:placetype":"venue"
},
  "geometry": {"coordinates":[-82.332008,34.944659],"type":"Point"}
}