{
  "type": "Feature",
  "properties": {
    "iso:country":"US",
    "sg:address":"429 Crowley St",
    "sg:city":"Darlington",
    "sg:classifiers":[
        {
            "category":"Professional",
            "subcategory":"Business Services",
            "type":"Services"
        }
    ],
    "sg:phone":"+1 843 393 3331",
    "sg:postcode":"29532",
    "sg:province":"SC",
    "sg:tags":[
        "plant",
        "design",
        "maintenance"
    ],
    "wof:name":"Decorative Plants Of SC",
    "wof:placetype":"venue"
},
  "geometry": {"coordinates":[-79.896858,34.288863],"type":"Point"}
}