{
  "type": "Feature",
  "properties": {
    "iso:country":"US",
    "sg:address":"140 N Main St",
    "sg:city":"Six Mile",
    "sg:classifiers":[
        {
            "category":"Shopping",
            "subcategory":"Florist",
            "type":"Retail Goods"
        }
    ],
    "sg:phone":"+1 864 868 2820",
    "sg:postcode":"29682",
    "sg:province":"SC",
    "wof:name":"Sixmile/Frazier's Floral Dsgns",
    "wof:placetype":"venue"
},
  "geometry": {"coordinates":[-82.82011,34.807934],"type":"Point"}
}