{
  "type": "Feature",
  "properties": {
    "addr:full":"2014 Jacksonville Rd Charleston SC 29405",
    "addr:housenumber":"2014",
    "addr:postcode":"29405",
    "addr:street":"Jacksonville Rd",
    "iso:country":"US",
    "sg:address":"2014 Jacksonville Rd",
    "sg:city":"Charleston",
    "sg:classifiers":[
        {
            "category":"Wholesale",
            "subcategory":"Machinery & Supplies",
            "type":"Manufacturing & Wholesale Goods"
        }
    ],
    "sg:phone":"+1 843 566 9982",
    "sg:postcode":"29405",
    "sg:province":"SC",
    "sg:tags":[
        "equipment",
        "material",
        "handling"
    ],
    "sg:website":"www.bigredinc.com",
    "wof:name":"Big Red Inc",
    "wof:placetype":"venue"
},
  "geometry": {"coordinates":[-79.964372,32.84561],"type":"Point"}
}