{
  "type": "Feature",
  "properties": {
    "iso:country":"US",
    "sg:address":"103 Maria Ln",
    "sg:city":"Seneca",
    "sg:classifiers":[
        {
            "category":"Building & Trades",
            "subcategory":"Construction",
            "type":"Services"
        }
    ],
    "sg:phone":"+1 864 886 8498",
    "sg:postcode":"29678",
    "sg:province":"SC",
    "wof:name":"Duvall Enterprises",
    "wof:placetype":"venue"
},
  "geometry": {"coordinates":[-82.92774300000001,34.671757],"type":"Point"}
}