{
  "type": "Feature",
  "properties": {
    "iso:country":"US",
    "sg:address":"1202 Hampton St",
    "sg:city":"Walterboro",
    "sg:classifiers":[
        {
            "category":"Professional",
            "subcategory":"Accounting & Tax Preparation",
            "type":"Services"
        }
    ],
    "sg:phone":"+1 843 549 0144",
    "sg:postcode":"29488",
    "sg:province":"SC",
    "sg:tags":[
        "accountant"
    ],
    "wof:name":"Michael M Berry Accounting Tax",
    "wof:placetype":"venue"
},
  "geometry": {"coordinates":[-80.648186,32.897753],"type":"Point"}
}