{
  "type": "Feature",
  "properties": {
    "iso:country":"US",
    "sg:address":"213 Hampton Ave",
    "sg:city":"Greenwood",
    "sg:classifiers":[
        {
            "category":"Professional",
            "subcategory":"Management & Consulting",
            "type":"Services"
        }
    ],
    "sg:phone":"+1 864 943 4160",
    "sg:postcode":"29646",
    "sg:province":"SC",
    "sg:tags":[
        "consultant",
        "resource",
        "human"
    ],
    "sg:website":"www.htijobs.com",
    "wof:name":"Human Technologies Inc",
    "wof:placetype":"venue"
},
  "geometry": {"coordinates":[-82.163686,34.194662],"type":"Point"}
}