{
  "type": "Feature",
  "properties": {
    "iso:country":"US",
    "sg:address":"1073 W Meeting St",
    "sg:city":"Lancaster",
    "sg:classifiers":[
        {
            "category":"Shopping",
            "subcategory":"Pharmacy",
            "type":"Retail Goods"
        }
    ],
    "sg:phone":"+1 803 285 2021",
    "sg:postcode":"29720",
    "sg:province":"SC",
    "sg:tags":[
        "drug",
        "store"
    ],
    "wof:name":"Mobley Drugs & Medical",
    "wof:placetype":"venue"
},
  "geometry": {"coordinates":[-80.79669800000001,34.713967],"type":"Point"}
}