{
  "type": "Feature",
  "properties": {
    "iso:country":"US",
    "sg:address":"535 N Cedar St",
    "sg:city":"Summerville",
    "sg:classifiers":[
        {
            "category":"Government",
            "subcategory":"Office",
            "type":"Public Place"
        }
    ],
    "sg:phone":"+1 843 832 0043",
    "sg:postcode":"29483",
    "sg:province":"SC",
    "sg:tags":[
        "county"
    ],
    "wof:name":"Dorchester County",
    "wof:placetype":"venue"
},
  "geometry": {"coordinates":[-80.172265,33.026898],"type":"Point"}
}