{
  "type": "Feature",
  "properties": {
    "addr:full":"920 Herndon Dairy Rd Beech Island SC 29842",
    "addr:housenumber":"920",
    "addr:postcode":"29842",
    "addr:street":"Herndon Dairy Rd",
    "iso:country":"US",
    "sg:address":"920 Herndon Dairy Rd",
    "sg:city":"Beech Island",
    "sg:classifiers":[
        {
            "category":"Building & Trades",
            "subcategory":"Construction",
            "type":"Services"
        }
    ],
    "sg:phone":"+1 803 593 5173",
    "sg:postcode":"29842",
    "sg:province":"SC",
    "sg:tags":[
        "contractor"
    ],
    "wof:name":"Dicks General Contractors",
    "wof:placetype":"venue"
},
  "geometry": {"coordinates":[-81.815995,33.470485],"type":"Point"}
}