{
  "type": "Feature",
  "properties": {
    "iso:country":"US",
    "sg:address":"374 Sunnyside Ave",
    "sg:city":"Murrells Inlet",
    "sg:classifiers":[
        {
            "category":"Wholesale",
            "subcategory":"Construction Materials",
            "type":"Manufacturing & Wholesale Goods"
        }
    ],
    "sg:phone":"+1 843 651 3857",
    "sg:postcode":"29576",
    "sg:province":"SC",
    "sg:tags":[
        "fence"
    ],
    "wof:name":"A-1 Fence Co",
    "wof:placetype":"venue"
},
  "geometry": {"coordinates":[-79.02450899999999,33.566429],"type":"Point"}
}