{
  "type": "Feature",
  "properties": {
    "iso:country":"US",
    "sg:address":"1614 Executive Ave",
    "sg:city":"Myrtle Beach",
    "sg:classifiers":[
        {
            "category":"Professional",
            "subcategory":"Detective & Security Services",
            "type":"Services"
        }
    ],
    "sg:phone":"+1 843 448 7858",
    "sg:postcode":"29577",
    "sg:province":"SC",
    "sg:tags":[
        "car",
        "armored"
    ],
    "wof:name":"Loomis Fargo & Co",
    "wof:placetype":"venue"
},
  "geometry": {"coordinates":[-78.901159,33.702402],"type":"Point"}
}