{
  "type": "Feature",
  "properties": {
    "iso:country":"US",
    "sg:address":"3373 S Morgans Point Rd",
    "sg:city":"Mount Pleasant",
    "sg:classifiers":[
        {
            "category":"Banks & Credit Unions",
            "subcategory":"Investment Brokerage",
            "type":"Services"
        }
    ],
    "sg:phone":"+1 843 388 0468",
    "sg:postcode":"29466",
    "sg:province":"SC",
    "sg:tags":[
        "security"
    ],
    "wof:name":"Edward Jones 29234",
    "wof:placetype":"venue"
},
  "geometry": {"coordinates":[-79.774523,32.871456],"type":"Point"}
}