{
  "type": "Feature",
  "properties": {
    "iso:country":"US",
    "sg:address":"112 Lake Dr",
    "sg:city":"Cheraw",
    "sg:classifiers":[
        {
            "category":"Home & Garden",
            "subcategory":"Building Materials",
            "type":"Retail Goods"
        }
    ],
    "sg:phone":"+1 843 537 5390",
    "sg:postcode":"29520",
    "sg:province":"SC",
    "sg:tags":[
        "glass",
        "window",
        "plate"
    ],
    "wof:name":"Binswanger Glass Co",
    "wof:placetype":"venue"
},
  "geometry": {"coordinates":[-79.8952,34.702726],"type":"Point"}
}