{
  "type": "Feature",
  "properties": {
    "addr:full":"120 Dutchman Blvd Irmo SC 29063",
    "addr:housenumber":"120",
    "addr:postcode":"29063",
    "addr:street":"Dutchman Blvd",
    "iso:country":"US",
    "sg:address":"120 Dutchman Blvd",
    "sg:city":"Irmo",
    "sg:classifiers":[
        {
            "category":"Home & Garden",
            "subcategory":"Building Materials",
            "type":"Retail Goods"
        }
    ],
    "sg:phone":"+1 803 407 1112",
    "sg:postcode":"29063",
    "sg:province":"SC",
    "sg:tags":[
        "windows"
    ],
    "wof:name":"Pella Window & Door Co",
    "wof:placetype":"venue"
},
  "geometry": {"coordinates":[-81.15745,34.093809],"type":"Point"}
}