{
  "type": "Feature",
  "properties": {
    "addr:full":"919 Bennett St Orangeburg SC 29115",
    "addr:housenumber":"919",
    "addr:postcode":"29115",
    "addr:street":"Bennett St",
    "iso:country":"US",
    "sg:address":"919 Bennett St",
    "sg:city":"Orangeburg",
    "sg:classifiers":[
        {
            "category":"Education",
            "subcategory":"School",
            "type":"Public Place"
        }
    ],
    "sg:phone":"+1 803 531 2200",
    "sg:postcode":"29115",
    "sg:province":"SC",
    "wof:name":"William Clark Middle School",
    "wof:placetype":"venue"
},
  "geometry": {"coordinates":[-80.86567599999999,33.506178],"type":"Point"}
}