{
  "type": "Feature",
  "properties": {
    "addr:full":"655 Bultman Dr Sumter SC 29150",
    "addr:housenumber":"655",
    "addr:postcode":"29150",
    "addr:street":"Bultman Dr",
    "iso:country":"US",
    "sg:address":"655 Bultman Dr",
    "sg:city":"Sumter",
    "sg:classifiers":[
        {
            "category":"Retail",
            "subcategory":"Photofinishing",
            "type":"Services"
        }
    ],
    "sg:phone":"+1 803 773 4451",
    "sg:postcode":"29150",
    "sg:province":"SC",
    "sg:tags":[
        "photo",
        "finishing"
    ],
    "wof:name":"Photos Unlimited",
    "wof:placetype":"venue"
},
  "geometry": {"coordinates":[-80.371483,33.938911],"type":"Point"}
}