{
  "type": "Feature",
  "properties": {
    "iso:country":"US",
    "sg:address":"418 Wood St",
    "sg:city":"Georgetown",
    "sg:classifiers":[
        {
            "category":"Health Services",
            "subcategory":"Optometrist",
            "type":"Services"
        }
    ],
    "sg:phone":"+1 843 545 0182",
    "sg:postcode":"29440",
    "sg:province":"SC",
    "wof:name":"Henry Franklin OD",
    "wof:placetype":"venue"
},
  "geometry": {"coordinates":[-79.282904,33.373217],"type":"Point"}
}