{
  "type": "Feature",
  "properties": {
    "iso:country":"US",
    "sg:address":"1235 Northfield Pl",
    "sg:city":"Charleston",
    "sg:classifiers":[
        {
            "category":"Building & Trades",
            "subcategory":"Construction",
            "type":"Services"
        }
    ],
    "sg:phone":"+1 843 744 4787",
    "sg:postcode":"29410",
    "sg:province":"SC",
    "sg:tags":[
        "contractor"
    ],
    "wof:name":"Splash Pools Chemicals & Servi",
    "wof:placetype":"venue"
},
  "geometry": {"coordinates":[-80.011426,32.911653],"type":"Point"}
}