{
  "type": "Feature",
  "properties": {
    "addr:full":"2430 Cherry Rd Rock Hill SC 29732",
    "addr:housenumber":"2430",
    "addr:postcode":"29732",
    "addr:street":"Cherry Rd",
    "iso:country":"US",
    "sg:address":"2430 Cherry Rd",
    "sg:city":"Rock Hill",
    "sg:classifiers":[
        {
            "category":"Restaurant",
            "type":"Food & Drink"
        }
    ],
    "sg:menulink":"http://www.allmenus.com/sc/rock-hill/211024-burger-king/menu/",
    "sg:phone":"+1 803 366 9342",
    "sg:postcode":"29732",
    "sg:province":"SC",
    "sg:tags":[
        "burger",
        "american"
    ],
    "wof:name":"Burger King",
    "wof:placetype":"venue"
},
  "geometry": {"coordinates":[-80.993539,34.968448],"type":"Point"}
}