{
  "type": "Feature",
  "properties": {
    "iso:country":"US",
    "sg:address":"624 Long Point Rd",
    "sg:city":"Mount Pleasant",
    "sg:classifiers":[
        {
            "category":"Restaurant",
            "type":"Food & Drink"
        }
    ],
    "sg:phone":"+1 843 881 1311",
    "sg:postcode":"29464",
    "sg:province":"SC",
    "sg:tags":[
        "eating"
    ],
    "wof:name":"Just Fresh Bakery Cafe",
    "wof:placetype":"venue"
},
  "geometry": {"coordinates":[-79.85697999999999,32.841141],"type":"Point"}
}