{
  "type": "Feature",
  "properties": {
    "iso:country":"US",
    "sg:address":"65 Alexander St",
    "sg:city":"Charleston",
    "sg:classifiers":[
        {
            "category":"Local Transit",
            "type":"Transportation"
        }
    ],
    "sg:phone":"+1 843 958 0606",
    "sg:postcode":"29403",
    "sg:province":"SC",
    "sg:tags":[
        "limousine"
    ],
    "wof:name":"Coastal Limousine Inc",
    "wof:placetype":"venue"
},
  "geometry": {"coordinates":[-79.930965,32.789547],"type":"Point"}
}