{
  "type": "Feature",
  "properties": {
    "iso:country":"US",
    "sg:address":"3307 New Easley Hwy",
    "sg:city":"Greenville",
    "sg:classifiers":[
        {
            "category":"Building & Trades",
            "subcategory":"Plumbing",
            "type":"Services"
        }
    ],
    "sg:phone":"+1 864 269 5550",
    "sg:postcode":"29611",
    "sg:province":"SC",
    "sg:tags":[
        "contractor"
    ],
    "wof:name":"Ahc Mechanical LLC",
    "wof:placetype":"venue"
},
  "geometry": {"coordinates":[-82.479251,34.832644],"type":"Point"}
}