{
  "type": "Feature",
  "properties": {
    "iso:country":"US",
    "sg:address":"1905 Sunset Blvd",
    "sg:city":"West Columbia",
    "sg:classifiers":[
        {
            "category":"Education",
            "subcategory":"Vocational School",
            "type":"Public Place"
        }
    ],
    "sg:phone":"+1 803 939 9600",
    "sg:postcode":"29169",
    "sg:province":"SC",
    "sg:tags":[
        "cosmetology"
    ],
    "wof:name":"South Carolina Massage & Esthetics Institute",
    "wof:placetype":"venue"
},
  "geometry": {"coordinates":[-81.09320099999999,33.998901],"type":"Point"}
}