{
  "type": "Feature",
  "properties": {
    "iso:country":"US",
    "sg:address":"303 Montague Ave",
    "sg:city":"Greenwood",
    "sg:classifiers":[
        {
            "category":"Shopping",
            "subcategory":"Gifts & Souvenirs",
            "type":"Retail Goods"
        }
    ],
    "sg:phone":"+1 864 388 7772",
    "sg:postcode":"29649",
    "sg:province":"SC",
    "wof:name":"Heaven Sent Gift Shop",
    "wof:placetype":"venue"
},
  "geometry": {"coordinates":[-82.172093,34.201062],"type":"Point"}
}