{
  "type": "Feature",
  "properties": {
    "iso:country":"US",
    "sg:address":"1005 E Smith St",
    "sg:city":"Timmonsville",
    "sg:classifiers":[
        {
            "category":"Autos & Motor Vehicles",
            "subcategory":"Automobile Sales",
            "type":"Retail Goods"
        }
    ],
    "sg:phone":"+1 843 346 3263",
    "sg:postcode":"29161",
    "sg:province":"SC",
    "sg:tags":[
        "car",
        "dealer"
    ],
    "wof:name":"White's Auto Sales",
    "wof:placetype":"venue"
},
  "geometry": {"coordinates":[-79.917242,34.143238],"type":"Point"}
}