{
  "type": "Feature",
  "properties": {
    "iso:country":"US",
    "sg:address":"5067 Victoria Ave",
    "sg:city":"North Charleston",
    "sg:classifiers":[
        {
            "category":"Building & Trades",
            "subcategory":"Construction",
            "type":"Services"
        }
    ],
    "sg:phone":"+1 843 566 0855",
    "sg:postcode":"29405",
    "sg:province":"SC",
    "sg:tags":[
        "restoration",
        "cleaning",
        "patio",
        "deck"
    ],
    "wof:name":"Cherokee Steam & Pressure Svc",
    "wof:placetype":"venue"
},
  "geometry": {"coordinates":[-79.98654000000001,32.887728],"type":"Point"}
}