{
  "type": "Feature",
  "properties": {
    "addr:full":"617 State Hwy 385 Bennettsville SC 29512",
    "addr:housenumber":"617",
    "addr:postcode":"29512",
    "addr:street":"State Hwy 385",
    "iso:country":"US",
    "sg:address":"617 State Hwy 385",
    "sg:city":"Bennettsville",
    "sg:classifiers":[
        {
            "category":"Organizations",
            "subcategory":"Religious Organization",
            "type":"Services"
        }
    ],
    "sg:phone":"+1 843 479 6688",
    "sg:postcode":"29512",
    "sg:province":"SC",
    "sg:tags":[
        "church"
    ],
    "wof:name":"Bennettsville Congregation",
    "wof:placetype":"venue"
},
  "geometry": {"coordinates":[-79.66597299999999,34.643177],"type":"Point"}
}