{
  "type": "Feature",
  "properties": {
    "iso:country":"US",
    "sg:address":"1323 N Lake Dr",
    "sg:city":"Lexington",
    "sg:classifiers":[
        {
            "category":"Organizations",
            "subcategory":"Religious Organization",
            "type":"Services"
        }
    ],
    "sg:phone":"+1 803 957 2562",
    "sg:postcode":"29072",
    "sg:province":"SC",
    "sg:tags":[
        "church"
    ],
    "wof:name":"Johns Chapel AME Church",
    "wof:placetype":"venue"
},
  "geometry": {"coordinates":[-81.224051,34.014058],"type":"Point"}
}