{
  "type": "Feature",
  "properties": {
    "iso:country":"US",
    "sg:address":"72 Wilson Way",
    "sg:city":"Abbeville",
    "sg:classifiers":[
        {
            "category":"Building & Trades",
            "subcategory":"Construction",
            "type":"Services"
        }
    ],
    "sg:phone":"+1 864 446 8077",
    "sg:postcode":"29620",
    "sg:province":"SC",
    "sg:tags":[
        "concrete",
        "contractor"
    ],
    "wof:name":"Wilson Enterprises",
    "wof:placetype":"venue"
},
  "geometry": {"coordinates":[-82.489932,34.14135],"type":"Point"}
}