{
  "type": "Feature",
  "properties": {
    "iso:country":"US",
    "sg:address":"4652 Howe Rd",
    "sg:city":"Landrum",
    "sg:classifiers":[
        {
            "category":"Retail",
            "subcategory":"Repair Shop",
            "type":"Services"
        }
    ],
    "sg:phone":"+1 864 895 3778",
    "sg:postcode":"29356",
    "sg:province":"SC",
    "sg:tags":[
        "lock",
        "locksmith"
    ],
    "wof:name":"Edward's Lock & Key",
    "wof:placetype":"venue"
},
  "geometry": {"coordinates":[-82.278899,35.093189],"type":"Point"}
}