{
  "type": "Feature",
  "properties": {
    "iso:country":"US",
    "sg:address":"215 Marks Rd",
    "sg:city":"Jackson",
    "sg:classifiers":[
        {
            "category":"Real Estate",
            "subcategory":"Real Estate Operator",
            "type":"Services"
        }
    ],
    "sg:phone":"+1 803 827 1647",
    "sg:postcode":"29831",
    "sg:province":"SC",
    "sg:tags":[
        "mobile",
        "home",
        "site"
    ],
    "wof:name":"Holly Hill Mobile Home Park",
    "wof:placetype":"venue"
},
  "geometry": {"coordinates":[-81.867541,33.390228],"type":"Point"}
}