{
  "type": "Feature",
  "properties": {
    "addr:full":"1006 Hammett Bridge Rd Greer SC 29650",
    "addr:housenumber":"1006",
    "addr:postcode":"29650",
    "addr:street":"Hammett Bridge Rd",
    "iso:country":"US",
    "sg:address":"1006 Hammett Bridge Rd",
    "sg:city":"Greer",
    "sg:classifiers":[
        {
            "category":"Food & Beverages",
            "subcategory":"Groceries & Convenience Stores",
            "type":"Retail Goods"
        }
    ],
    "sg:phone":"+1 864 801 9752",
    "sg:postcode":"29650",
    "sg:province":"SC",
    "wof:name":"Hot Spot",
    "wof:placetype":"venue"
},
  "geometry": {"coordinates":[-82.252224,34.904513],"type":"Point"}
}