{
  "type": "Feature",
  "properties": {
    "iso:country":"US",
    "sg:address":"4506 E National Cemetery Rd",
    "sg:city":"Florence",
    "sg:phone":"+1 843 665 7198",
    "sg:postcode":"29506",
    "sg:province":"SC",
    "sg:tags":[
        "farm",
        "corn"
    ],
    "wof:name":"Gladys Pitts",
    "wof:placetype":"venue"
},
  "geometry": {"coordinates":[-79.66303499999999,34.157638],"type":"Point"}
}