{
  "type": "Feature",
  "properties": {
    "iso:country":"US",
    "sg:address":"2112 Airport Rd",
    "sg:city":"Greer",
    "sg:classifiers":[
        {
            "category":"Real Estate",
            "subcategory":"Developer",
            "type":"Services"
        }
    ],
    "sg:phone":"+1 864 879 7231",
    "sg:postcode":"29651",
    "sg:province":"SC",
    "wof:name":"Eddie Runion Developers",
    "wof:placetype":"venue"
},
  "geometry": {"coordinates":[-82.212632,34.892814],"type":"Point"}
}