{
  "type": "Feature",
  "properties": {
    "iso:country":"US",
    "sg:address":"3807 Kilbourne Rd",
    "sg:city":"Columbia",
    "sg:classifiers":[
        {
            "category":"Professional",
            "subcategory":"Lawyer & Legal Services",
            "type":"Services"
        }
    ],
    "sg:phone":"+1 803 787 9034",
    "sg:postcode":"29205",
    "sg:province":"SC",
    "wof:name":"Smith Joel H Atty",
    "wof:placetype":"venue"
},
  "geometry": {"coordinates":[-80.986099,34.001499],"type":"Point"}
}