{
  "type": "Feature",
  "properties": {
    "iso:country":"US",
    "sg:address":"6289 Augusta Hwy",
    "sg:city":"Smoaks",
    "sg:classifiers":[
        {
            "category":"Organizations",
            "subcategory":"Religious Organization",
            "type":"Services"
        }
    ],
    "sg:phone":"+1 843 562 2896",
    "sg:postcode":"29481",
    "sg:province":"SC",
    "sg:tags":[
        "clergy"
    ],
    "wof:name":"Springtown United Methodist",
    "wof:placetype":"venue"
},
  "geometry": {"coordinates":[-80.737837,33.134217],"type":"Point"}
}