{
  "type": "Feature",
  "properties": {
    "iso:country":"US",
    "sg:address":"1385 W Alice Dr",
    "sg:city":"Florence",
    "sg:classifiers":[
        {
            "category":"Professional",
            "subcategory":"Advertising",
            "type":"Services"
        }
    ],
    "sg:phone":"+1 843 662 4514",
    "sg:postcode":"29505",
    "sg:province":"SC",
    "wof:name":"Adams Outdoor Advertising",
    "wof:placetype":"venue"
},
  "geometry": {"coordinates":[-79.792597,34.167739],"type":"Point"}
}