{
  "type": "Feature",
  "properties": {
    "iso:country":"US",
    "sg:address":"5 Warbler Ln",
    "sg:city":"Hilton Head Island",
    "sg:classifiers":[
        {
            "category":"Manufacturing",
            "subcategory":"Textiles",
            "type":"Manufacturing & Wholesale Goods"
        }
    ],
    "sg:phone":"+1 843 681 8960",
    "sg:postcode":"29926",
    "sg:province":"SC",
    "sg:tags":[
        "mill",
        "fabric",
        "cotton"
    ],
    "wof:name":"Mary Matt Inc",
    "wof:placetype":"venue"
},
  "geometry": {"coordinates":[-80.72454999999999,32.242795],"type":"Point"}
}