{
  "type": "Feature",
  "properties": {
    "addr:full":"1164 Elm St Aynor SC 29511",
    "addr:housenumber":"1164",
    "addr:postcode":"29511",
    "addr:street":"Elm St",
    "iso:country":"US",
    "sg:address":"1164 Elm St",
    "sg:city":"Aynor",
    "sg:classifiers":[
        {
            "category":"Building & Trades",
            "subcategory":"Construction",
            "type":"Services"
        }
    ],
    "sg:phone":"+1 843 358 0936",
    "sg:postcode":"29511",
    "sg:province":"SC",
    "sg:tags":[
        "company"
    ],
    "wof:name":"Larson Construction",
    "wof:placetype":"venue"
},
  "geometry": {"coordinates":[-79.194254,33.999071],"type":"Point"}
}