{
  "type": "Feature",
  "properties": {
    "iso:country":"US",
    "sg:address":"1220 Charleston Hwy",
    "sg:city":"West Columbia",
    "sg:classifiers":[
        {
            "category":"Restaurant",
            "type":"Food & Drink"
        }
    ],
    "sg:phone":"+1 803 796 7004",
    "sg:postcode":"29169",
    "sg:province":"SC",
    "sg:tags":[
        "mexican"
    ],
    "wof:name":"La Fiesta Mexican Restaurant",
    "wof:placetype":"venue"
},
  "geometry": {"coordinates":[-81.07530199999999,33.978401],"type":"Point"}
}