{
  "type": "Feature",
  "properties": {
    "iso:country":"US",
    "sg:address":"19 S Irvine St",
    "sg:city":"Greenville",
    "sg:classifiers":[
        {
            "category":"Wholesale",
            "subcategory":"Durable Goods & Equipment",
            "type":"Manufacturing & Wholesale Goods"
        }
    ],
    "sg:phone":"+1 864 242 6284",
    "sg:postcode":"29601",
    "sg:province":"SC",
    "sg:tags":[
        "importer"
    ],
    "wof:name":"J J Ryan & Sons Inc",
    "wof:placetype":"venue"
},
  "geometry": {"coordinates":[-82.39688,34.849073],"type":"Point"}
}