{
  "type": "Feature",
  "properties": {
    "addr:full":"256 S Church St Spartanburg SC 29306",
    "addr:housenumber":"256",
    "addr:postcode":"29306",
    "addr:street":"S Church St",
    "iso:country":"US",
    "sg:address":"256 S Church St",
    "sg:city":"Spartanburg",
    "sg:classifiers":[
        {
            "category":"Restaurant",
            "type":"Food & Drink"
        }
    ],
    "sg:phone":"+1 864 573 2575",
    "sg:postcode":"29306",
    "sg:province":"SC",
    "wof:name":"Sake Grill",
    "wof:placetype":"venue"
},
  "geometry": {"coordinates":[-81.92894099999999,34.944288],"type":"Point"}
}