{
  "type": "Feature",
  "properties": {
    "iso:country":"US",
    "sg:address":"118 Lake Elizabeth Dr",
    "sg:city":"Columbia",
    "sg:classifiers":[
        {
            "category":"Freight",
            "type":"Transportation"
        }
    ],
    "sg:phone":"+1 803 754 6142",
    "sg:postcode":"29203",
    "sg:province":"SC",
    "sg:tags":[
        "terminal",
        "truck",
        "facility"
    ],
    "wof:name":"Ligon & Assoc LLC",
    "wof:placetype":"venue"
},
  "geometry": {"coordinates":[-80.983065,34.114478],"type":"Point"}
}