{
  "type": "Feature",
  "properties": {
    "addr:full":"6 Calender Ct Columbia SC 29206",
    "addr:housenumber":"6",
    "addr:postcode":"29206",
    "addr:street":"Calender Ct",
    "iso:country":"US",
    "sg:address":"6 Calender Ct",
    "sg:city":"Columbia",
    "sg:classifiers":[
        {
            "category":"Banks & Credit Unions",
            "subcategory":"Bank",
            "type":"Services"
        }
    ],
    "sg:phone":"+1 803 782 1954",
    "sg:postcode":"29206",
    "sg:province":"SC",
    "wof:name":"East Broad Trust Co",
    "wof:placetype":"venue"
},
  "geometry": {"coordinates":[-80.96452499999999,34.014478],"type":"Point"}
}