{
  "type": "Feature",
  "properties": {
    "addr:full":"1800 Main St Columbia SC 29201",
    "addr:housenumber":"1800",
    "addr:postcode":"29201",
    "addr:street":"Main St",
    "iso:country":"US",
    "sg:address":"1800 Main St",
    "sg:city":"Columbia",
    "sg:classifiers":[
        {
            "category":"Social Services",
            "type":"Services"
        }
    ],
    "sg:phone":"+1 803 733 5455",
    "sg:postcode":"29201",
    "sg:province":"SC",
    "sg:tags":[
        "employee",
        "assistance",
        "program"
    ],
    "sg:website":"www.fsconline.com",
    "wof:name":"Employee Assistance Program",
    "wof:placetype":"venue"
},
  "geometry": {"coordinates":[-81.03768599999999,34.010625],"type":"Point"}
}