{
  "type": "Feature",
  "properties": {
    "iso:country":"US",
    "sg:address":"2015 Laurens Rd",
    "sg:city":"Greenville",
    "sg:classifiers":[
        {
            "category":"Professional",
            "subcategory":"Computer Services",
            "type":"Services"
        }
    ],
    "sg:phone":"+1 864 241 9995",
    "sg:postcode":"29607",
    "sg:province":"SC",
    "sg:tags":[
        "repair"
    ],
    "sg:website":"www.computerclinicent.com",
    "wof:name":"Computer Clinic",
    "wof:placetype":"venue"
},
  "geometry": {"coordinates":[-82.355383,34.837093],"type":"Point"}
}