{
  "type": "Feature",
  "properties": {
    "iso:country":"US",
    "sg:address":"2700 Broad River Rd",
    "sg:city":"Columbia",
    "sg:classifiers":[
        {
            "category":"Food & Beverages",
            "subcategory":"Liquor & Beverages",
            "type":"Retail Goods"
        }
    ],
    "sg:phone":"+1 803 772 5420",
    "sg:postcode":"29210",
    "sg:province":"SC",
    "sg:tags":[
        "beer",
        "spirit",
        "wine"
    ],
    "wof:name":"Sun Bar # 3",
    "wof:placetype":"venue"
},
  "geometry": {"coordinates":[-81.100098,34.044899],"type":"Point"}
}