{
  "type": "Feature",
  "properties": {
    "iso:country":"US",
    "sg:address":"729 N Main St",
    "sg:city":"Mauldin",
    "sg:classifiers":[
        {
            "category":"Home & Garden",
            "subcategory":"Furniture",
            "type":"Retail Goods"
        }
    ],
    "sg:phone":"+1 864 297 5595",
    "sg:postcode":"29662",
    "sg:province":"SC",
    "wof:name":"Factory Furniture Discount",
    "wof:placetype":"venue"
},
  "geometry": {"coordinates":[-82.313456,34.788063],"type":"Point"}
}