{
  "type": "Feature",
  "properties": {
    "iso:country":"US",
    "sg:address":"65 Windermere Blvd",
    "sg:city":"Charleston",
    "sg:classifiers":[
        {
            "category":"Restaurant",
            "type":"Food & Drink"
        }
    ],
    "sg:phone":"+1 843 571 1410",
    "sg:postcode":"29407",
    "sg:province":"SC",
    "sg:tags":[
        "eating"
    ],
    "wof:name":"Mise En Place Inc",
    "wof:placetype":"venue"
},
  "geometry": {"coordinates":[-79.974625,32.776807],"type":"Point"}
}