{
  "type": "Feature",
  "properties": {
    "addr:full":"118 W Butler Rd Mauldin SC 29662",
    "addr:housenumber":"118",
    "addr:postcode":"29662",
    "addr:street":"W Butler Rd",
    "iso:country":"US",
    "sg:address":"118 W Butler Rd",
    "sg:city":"Mauldin",
    "sg:classifiers":[
        {
            "category":"Insurance",
            "subcategory":"Insurance Agent",
            "type":"Services"
        }
    ],
    "sg:phone":"+1 864 288 1597",
    "sg:postcode":"29662",
    "sg:province":"SC",
    "wof:name":"State Farm Insurance",
    "wof:placetype":"venue"
},
  "geometry": {"coordinates":[-82.310417,34.778454],"type":"Point"}
}