{
  "type": "Feature",
  "properties": {
    "iso:country":"US",
    "sg:address":"17 Fieldfare Way",
    "sg:city":"Charleston",
    "sg:classifiers":[
        {
            "category":"Building & Trades",
            "subcategory":"Construction",
            "type":"Services"
        }
    ],
    "sg:phone":"+1 843 571 4600",
    "sg:postcode":"29414",
    "sg:province":"SC",
    "sg:tags":[
        "resurfacing",
        "laying",
        "refinishing",
        "floor"
    ],
    "wof:name":"Tri County Hardwood Floors",
    "wof:placetype":"venue"
},
  "geometry": {"coordinates":[-80.075125,32.850076],"type":"Point"}
}