{
  "type": "Feature",
  "properties": {
    "iso:country":"US",
    "sg:address":"403 Bagnel",
    "sg:city":"Manning",
    "sg:classifiers":[
        {
            "category":"Organizations",
            "subcategory":"Religious Organization",
            "type":"Services"
        }
    ],
    "sg:phone":"+1 803 435 2588",
    "sg:postcode":"29102",
    "sg:province":"SC",
    "sg:tags":[
        "church"
    ],
    "wof:name":"Manning United Methodist Chr",
    "wof:placetype":"venue"
},
  "geometry": {"coordinates":[-80.220163,33.685392],"type":"Point"}
}