{
  "type": "Feature",
  "properties": {
    "iso:country":"US",
    "sg:address":"68 Wentworth St",
    "sg:city":"Charleston",
    "sg:classifiers":[
        {
            "category":"Travel",
            "subcategory":"Hotels & Motels",
            "type":"Entertainment"
        }
    ],
    "sg:phone":"+1 843 534 0300",
    "sg:postcode":"29401",
    "sg:province":"SC",
    "wof:name":"Renaissance Charleston Hotel",
    "wof:placetype":"venue"
},
  "geometry": {"coordinates":[-79.93245,32.783185],"type":"Point"}
}