{
  "type": "Feature",
  "properties": {
    "iso:country":"US",
    "sg:address":"10 Woodcross Dr",
    "sg:city":"Columbia",
    "sg:classifiers":[
        {
            "category":"Professional",
            "subcategory":"Lawyer & Legal Services",
            "type":"Services"
        }
    ],
    "sg:phone":"+1 803 781 0954",
    "sg:postcode":"29212",
    "sg:province":"SC",
    "sg:tags":[
        "attorney"
    ],
    "wof:name":"Dunn Dunn & Peeples",
    "wof:placetype":"venue"
},
  "geometry": {"coordinates":[-81.14084200000001,34.075078],"type":"Point"}
}