{
  "type": "Feature",
  "properties": {
    "iso:country":"US",
    "sg:address":"53 Full Sweep",
    "sg:city":"Hilton Head Island",
    "sg:classifiers":[
        {
            "category":"Real Estate",
            "subcategory":"Real Estate Agent",
            "type":"Services"
        }
    ],
    "sg:phone":"+1 843 785 9670",
    "sg:postcode":"29928",
    "sg:province":"SC",
    "wof:name":"Linda Palmer",
    "wof:placetype":"venue"
},
  "geometry": {"coordinates":[-80.710926,32.18829],"type":"Point"}
}