{
  "type": "Feature",
  "properties": {
    "addr:full":"8156 N Ridgebrook Dr North Charleston SC 29420",
    "addr:housenumber":"8156",
    "addr:postcode":"29420",
    "addr:street":"N Ridgebrook Dr",
    "iso:country":"US",
    "sg:address":"8156 N Ridgebrook Dr",
    "sg:city":"North Charleston",
    "sg:classifiers":[
        {
            "category":"Travel",
            "subcategory":"Travel Agent",
            "type":"Entertainment"
        }
    ],
    "sg:phone":"+1 843 552 2811",
    "sg:postcode":"29420",
    "sg:province":"SC",
    "sg:tags":[
        "tours",
        "promoter"
    ],
    "wof:name":"Bryant Tours",
    "wof:placetype":"venue"
},
  "geometry": {"coordinates":[-80.091341,32.930342],"type":"Point"}
}