{
  "type": "Feature",
  "properties": {
    "iso:country":"US",
    "sg:address":"165 Murray Vista Cir",
    "sg:city":"Lexington",
    "sg:classifiers":[
        {
            "category":"Banks & Credit Unions",
            "subcategory":"Bank",
            "type":"Services"
        }
    ],
    "sg:phone":"+1 803 356 0650",
    "sg:postcode":"29072",
    "sg:province":"SC",
    "sg:tags":[
        "loan",
        "real estate"
    ],
    "wof:name":"American Mortgage Svc",
    "wof:placetype":"venue"
},
  "geometry": {"coordinates":[-81.266362,34.03354],"type":"Point"}
}