{
  "type": "Feature",
  "properties": {
    "iso:country":"US",
    "sg:address":"531 W Evans St",
    "sg:city":"Florence",
    "sg:classifiers":[
        {
            "category":"Insurance",
            "subcategory":"Insurance Agent",
            "type":"Services"
        }
    ],
    "sg:phone":"+1 843 667 4839",
    "sg:postcode":"29501",
    "sg:province":"SC",
    "wof:name":"First Choice Insurance",
    "wof:placetype":"venue"
},
  "geometry": {"coordinates":[-79.774193,34.197008],"type":"Point"}
}