{
  "type": "Feature",
  "properties": {
    "iso:country":"US",
    "sg:address":"2913 White Horse Rd",
    "sg:city":"Greenville",
    "sg:classifiers":[
        {
            "category":"Wholesale",
            "subcategory":"Groceries",
            "type":"Manufacturing & Wholesale Goods"
        }
    ],
    "sg:phone":"+1 864 269 7804",
    "sg:postcode":"29611",
    "sg:province":"SC",
    "sg:tags":[
        "grocer"
    ],
    "wof:name":"Thomas & Howard Co",
    "wof:placetype":"venue"
},
  "geometry": {"coordinates":[-82.440444,34.813072],"type":"Point"}
}