{
  "type": "Feature",
  "properties": {
    "iso:country":"US",
    "sg:address":"705 Ila St",
    "sg:city":"Anderson",
    "sg:classifiers":[
        {
            "category":"Building & Trades",
            "subcategory":"Construction",
            "type":"Services"
        }
    ],
    "sg:phone":"+1 864 260 5905",
    "sg:postcode":"29624",
    "sg:province":"SC",
    "sg:tags":[
        "house"
    ],
    "wof:name":"Gilliard Construction",
    "wof:placetype":"venue"
},
  "geometry": {"coordinates":[-82.660541,34.494556],"type":"Point"}
}