{
  "type": "Feature",
  "properties": {
    "iso:country":"US",
    "sg:address":"418 S Main St",
    "sg:city":"Anderson",
    "sg:classifiers":[
        {
            "category":"Shopping",
            "subcategory":"News",
            "type":"Retail Goods"
        },
        {
            "category":"Shopping",
            "subcategory":"Books",
            "type":"Retail Goods"
        }
    ],
    "sg:phone":"+1 864 225 0676",
    "sg:postcode":"29624",
    "sg:province":"SC",
    "sg:tags":[
        "product",
        "dealer",
        "tobacco"
    ],
    "wof:name":"Reid-A-Book & Tobacco Shoppe",
    "wof:placetype":"venue"
},
  "geometry": {"coordinates":[-82.64972899999999,34.500885],"type":"Point"}
}