{
  "type": "Feature",
  "properties": {
    "iso:country":"US",
    "sg:address":"224 Sumter Ave",
    "sg:city":"Summerville",
    "sg:classifiers":[
        {
            "category":"Travel",
            "subcategory":"Hotels & Motels",
            "type":"Entertainment"
        }
    ],
    "sg:phone":"+1 843 871 1877",
    "sg:postcode":"29483",
    "sg:province":"SC",
    "sg:tags":[
        "breakfast",
        "accommodation",
        "bed"
    ],
    "wof:name":"Price House Cottage Bed Brkfst",
    "wof:placetype":"venue"
},
  "geometry": {"coordinates":[-80.183123,33.014192],"type":"Point"}
}