{
  "type": "Feature",
  "properties": {
    "addr:full":"1787 Ebenezer Rd Rock Hill SC 29732",
    "addr:housenumber":"1787",
    "addr:postcode":"29732",
    "addr:street":"Ebenezer Rd",
    "iso:country":"US",
    "sg:address":"1787 Ebenezer Rd",
    "sg:city":"Rock Hill",
    "sg:classifiers":[
        {
            "category":"Health Services",
            "subcategory":"Doctor",
            "type":"Services"
        }
    ],
    "sg:phone":"+1 803 324 7777",
    "sg:postcode":"29732",
    "sg:province":"SC",
    "sg:tags":[
        "physician",
        "surgeon"
    ],
    "wof:name":"Primary Medical Assoc",
    "wof:placetype":"venue"
},
  "geometry": {"coordinates":[-81.048666,34.960372],"type":"Point"}
}