{
  "type": "Feature",
  "properties": {
    "iso:country":"US",
    "sg:address":"21801 Low Country Hwy",
    "sg:city":"Ruffin",
    "sg:classifiers":[
        {
            "category":"Farming",
            "subcategory":"Farm",
            "type":"Manufacturing & Wholesale Goods"
        }
    ],
    "sg:phone":"+1 843 562 8471",
    "sg:postcode":"29475",
    "sg:province":"SC",
    "sg:tags":[
        "crop",
        "general"
    ],
    "wof:name":"Padgett Farm Properties LLC",
    "wof:placetype":"venue"
},
  "geometry": {"coordinates":[-80.814617,33.005232],"type":"Point"}
}