{
  "type": "Feature",
  "properties": {
    "iso:country":"US",
    "sg:address":"1400 State Hwy 161 N",
    "sg:city":"Clover",
    "sg:classifiers":[
        {
            "category":"Organizations",
            "subcategory":"Religious Organization",
            "type":"Services"
        }
    ],
    "sg:phone":"+1 803 222 9897",
    "sg:postcode":"29710",
    "sg:province":"SC",
    "sg:tags":[
        "church"
    ],
    "wof:name":"Bethany ARP Church",
    "wof:placetype":"venue"
},
  "geometry": {"coordinates":[-81.30728999999999,35.124322],"type":"Point"}
}