{
  "type": "Feature",
  "properties": {
    "iso:country":"US",
    "sg:address":"1954 Dulsey Rd",
    "sg:city":"Charleston",
    "sg:classifiers":[
        {
            "category":"Building & Trades",
            "subcategory":"Construction",
            "type":"Services"
        }
    ],
    "sg:phone":"+1 843 571 0275",
    "sg:postcode":"29407",
    "sg:province":"SC",
    "sg:tags":[
        "house"
    ],
    "wof:name":"Charlston Edgwater Restoration",
    "wof:placetype":"venue"
},
  "geometry": {"coordinates":[-80.02386,32.792919],"type":"Point"}
}