{
  "type": "Feature",
  "properties": {
    "iso:country":"US",
    "sg:address":"1406 Mill Pond Rd",
    "sg:city":"Conway",
    "sg:classifiers":[
        {
            "category":"Shopping",
            "subcategory":"Clothing, Apparel, & Fashions",
            "type":"Retail Goods"
        }
    ],
    "sg:phone":"+1 843 381 8189",
    "sg:postcode":"29527",
    "sg:province":"SC",
    "wof:name":"S & S Fashions",
    "wof:placetype":"venue"
},
  "geometry": {"coordinates":[-79.069284,33.847865],"type":"Point"}
}