{
  "type": "Feature",
  "properties": {
    "iso:country":"US",
    "sg:address":"2601 Kennerly Rd",
    "sg:city":"Irmo",
    "sg:classifiers":[
        {
            "category":"Retail",
            "subcategory":"Repair Shop",
            "type":"Services"
        }
    ],
    "sg:phone":"+1 803 407 8400",
    "sg:postcode":"29063",
    "sg:province":"SC",
    "sg:tags":[
        "welding"
    ],
    "wof:name":"Chariot Ironworks",
    "wof:placetype":"venue"
},
  "geometry": {"coordinates":[-81.18159,34.158741],"type":"Point"}
}