{
  "type": "Feature",
  "properties": {
    "iso:country":"US",
    "sg:address":"8329 State Hwy 908",
    "sg:city":"Gresham",
    "sg:classifiers":[
        {
            "category":"Building & Trades",
            "subcategory":"Construction",
            "type":"Services"
        }
    ],
    "sg:phone":"+1 843 362 0729",
    "sg:postcode":"29546",
    "sg:province":"SC",
    "sg:tags":[
        "farm",
        "house",
        "crop",
        "general"
    ],
    "wof:name":"Richardson Billy Bldg Contrs",
    "wof:placetype":"venue"
},
  "geometry": {"coordinates":[-79.337036,33.877646],"type":"Point"}
}