{
  "type": "Feature",
  "properties": {
    "iso:country":"US",
    "sg:address":"6507 N Kings Hwy",
    "sg:city":"Myrtle Beach",
    "sg:classifiers":[
        {
            "category":"Restaurant",
            "type":"Food & Drink"
        }
    ],
    "sg:phone":"+1 843 449 9596",
    "sg:postcode":"29572",
    "sg:province":"SC",
    "wof:name":"Atlantic Grille & Seafood Bar",
    "wof:placetype":"venue"
},
  "geometry": {"coordinates":[-78.828315,33.739116],"type":"Point"}
}