{
  "type": "Feature",
  "properties": {
    "iso:country":"US",
    "sg:address":"116 Goose Creek Blvd S",
    "sg:city":"Goose Creek",
    "sg:classifiers":[
        {
            "category":"Shopping",
            "subcategory":"Used Merchandise",
            "type":"Retail Goods"
        }
    ],
    "sg:phone":"+1 843 797 1702",
    "sg:postcode":"29445",
    "sg:province":"SC",
    "sg:tags":[
        "pawnbroker"
    ],
    "wof:name":"Money Man Pawn",
    "wof:placetype":"venue"
},
  "geometry": {"coordinates":[-80.038946,32.993656],"type":"Point"}
}