{
  "type": "Feature",
  "properties": {
    "iso:country":"US",
    "sg:address":"1408 S Main St",
    "sg:city":"Anderson",
    "sg:classifiers":[
        {
            "category":"Banks & Credit Unions",
            "subcategory":"Bank",
            "type":"Services"
        }
    ],
    "sg:phone":"+1 864 231 6660",
    "sg:postcode":"29624",
    "sg:province":"SC",
    "sg:tags":[
        "loan"
    ],
    "wof:name":"Sunbelt Credit",
    "wof:placetype":"venue"
},
  "geometry": {"coordinates":[-82.64770900000001,34.490233],"type":"Point"}
}