{
  "type": "Feature",
  "properties": {
    "iso:country":"US",
    "sg:address":"207 N Richardson St",
    "sg:city":"Latta",
    "sg:classifiers":[
        {
            "category":"Travel",
            "subcategory":"Hotels & Motels",
            "type":"Entertainment"
        }
    ],
    "sg:phone":"+1 843 752 1100",
    "sg:postcode":"29565",
    "sg:province":"SC",
    "wof:name":"Patrick Henry Motor Lodge",
    "wof:placetype":"venue"
},
  "geometry": {"coordinates":[-79.430125,34.338888],"type":"Point"}
}