{
  "type": "Feature",
  "properties": {
    "iso:country":"US",
    "sg:address":"3241 College St",
    "sg:city":"Newberry",
    "sg:classifiers":[
        {
            "category":"Farming",
            "subcategory":"Poultry Farm",
            "type":"Manufacturing & Wholesale Goods"
        }
    ],
    "sg:phone":"+1 803 276 3869",
    "sg:postcode":"29108",
    "sg:province":"SC",
    "sg:tags":[
        "egg"
    ],
    "wof:name":"Setzlers Farm",
    "wof:placetype":"venue"
},
  "geometry": {"coordinates":[-81.620481,34.299155],"type":"Point"}
}