{
  "type": "Feature",
  "properties": {
    "addr:full":"12 Distribution Ct Greer SC 29650",
    "addr:postcode":"29650",
    "addr:street":"Distribution Ct",
    "iso:country":"US",
    "sg:address":"12 Distribution Ct",
    "sg:city":"Greer",
    "sg:classifiers":[
        {
            "category":"Building & Trades",
            "subcategory":"Plumbing",
            "type":"Services"
        }
    ],
    "sg:phone":"+1 864 662 1070",
    "sg:postcode":"29650",
    "sg:province":"SC",
    "sg:tags":[
        "product",
        "management",
        "energy",
        "system"
    ],
    "wof:name":"Powersource Energy Components",
    "wof:placetype":"venue"
},
  "geometry": {"coordinates":[-82.232091,34.857545],"type":"Point"}
}