{
  "type": "Feature",
  "properties": {
    "iso:country":"US",
    "sg:address":"221 N Clemson Ave",
    "sg:city":"Clemson",
    "sg:classifiers":[
        {
            "category":"Professional",
            "subcategory":"Accounting & Tax Preparation",
            "type":"Services"
        }
    ],
    "sg:phone":"+1 864 653 7368",
    "sg:postcode":"29631",
    "sg:province":"SC",
    "sg:tags":[
        "bookkeeping",
        "general"
    ],
    "wof:name":"D & J Support Svc Inc",
    "wof:placetype":"venue"
},
  "geometry": {"coordinates":[-82.83855800000001,34.683811],"type":"Point"}
}