{
  "type": "Feature",
  "properties": {
    "iso:country":"US",
    "sg:address":"7418 Augusta Rd",
    "sg:city":"Piedmont",
    "sg:classifiers":[
        {
            "category":"Restaurant",
            "type":"Food & Drink"
        }
    ],
    "sg:menulink":"http://www.allmenus.com/sc/piedmont/176735-kfc---kentucky-fried-chicken/menu/",
    "sg:phone":"+1 864 277 2471",
    "sg:postcode":"29673",
    "sg:province":"SC",
    "sg:tags":[
        "american",
        "chicken"
    ],
    "wof:name":"KFC - Kentucky Fried Chicken",
    "wof:placetype":"venue"
},
  "geometry": {"coordinates":[-82.387685,34.721346],"type":"Point"}
}