{
  "type": "Feature",
  "properties": {
    "addr:full":"637 SE Main St Simpsonville SC 29681",
    "addr:housenumber":"637",
    "addr:postcode":"29681",
    "addr:street":"Se Main St",
    "iso:country":"US",
    "sg:address":"637 SE Main St",
    "sg:city":"Simpsonville",
    "sg:classifiers":[
        {
            "category":"Restaurant",
            "type":"Food & Drink"
        }
    ],
    "sg:phone":"+1 864 967 8840",
    "sg:postcode":"29681",
    "sg:province":"SC",
    "sg:tags":[
        "eating"
    ],
    "sg:website":"www.coachhouse.com",
    "wof:name":"Coach House Restaurant",
    "wof:placetype":"venue"
},
  "geometry": {"coordinates":[-82.251294,34.71997],"type":"Point"}
}