{
  "type": "Feature",
  "properties": {
    "addr:full":"213 S Coit St Florence SC 29501",
    "addr:housenumber":"213",
    "addr:postcode":"29501",
    "addr:street":"S Coit St",
    "iso:country":"US",
    "sg:address":"213 S Coit St",
    "sg:city":"Florence",
    "sg:classifiers":[
        {
            "category":"Health Services",
            "subcategory":"Doctor",
            "type":"Services"
        }
    ],
    "sg:phone":"+1 843 669 5058",
    "sg:postcode":"29501",
    "sg:province":"SC",
    "sg:tags":[
        "physician",
        "surgeon"
    ],
    "wof:name":"Anesthesioly Consultants",
    "wof:placetype":"venue"
},
  "geometry": {"coordinates":[-79.770233,34.193781],"type":"Point"}
}