{
  "type": "Feature",
  "properties": {
    "iso:country":"US",
    "sg:address":"201 Perry Hill Rd",
    "sg:city":"Easley",
    "sg:classifiers":[
        {
            "category":"Freight",
            "type":"Transportation"
        }
    ],
    "sg:phone":"+1 864 859 2234",
    "sg:postcode":"29640",
    "sg:province":"SC",
    "sg:tags":[
        "operator",
        "local",
        "trucking"
    ],
    "wof:name":"Daystar & Co Trucking",
    "wof:placetype":"venue"
},
  "geometry": {"coordinates":[-82.5403,34.843203],"type":"Point"}
}