{
  "type": "Feature",
  "properties": {
    "iso:country":"US",
    "sg:address":"205 Jacobs Hwy",
    "sg:city":"Clinton",
    "sg:classifiers":[
        {
            "category":"Banks & Credit Unions",
            "subcategory":"Bank",
            "type":"Services"
        }
    ],
    "sg:phone":"+1 864 833 1588",
    "sg:postcode":"29325",
    "sg:province":"SC",
    "sg:website":"www.arthurstatebank.com",
    "wof:name":"Arthur State Bank",
    "wof:placetype":"venue"
},
  "geometry": {"coordinates":[-81.876373,34.454435],"type":"Point"}
}