{
  "type": "Feature",
  "properties": {
    "iso:country":"US",
    "sg:address":"1205 Pendleton St",
    "sg:city":"Columbia",
    "sg:classifiers":[
        {
            "category":"Government",
            "subcategory":"Office",
            "type":"Public Place"
        }
    ],
    "sg:phone":"+1 803 734 0662",
    "sg:postcode":"29201",
    "sg:province":"SC",
    "sg:tags":[
        "program",
        "state",
        "adm"
    ],
    "sg:website":"www.govoepp.state.sc.us/oeo.htm",
    "wof:name":"Economic Opportunity Div",
    "wof:placetype":"venue"
},
  "geometry": {"coordinates":[-81.030751,33.99903],"type":"Point"}
}