{
  "type": "Feature",
  "properties": {
    "iso:country":"US",
    "sg:address":"1907 Thurmond Mall",
    "sg:city":"Columbia",
    "sg:classifiers":[
        {
            "category":"Real Estate",
            "subcategory":"Real Estate Services",
            "type":"Services"
        }
    ],
    "sg:phone":"+1 803 799 0033",
    "sg:postcode":"29201",
    "sg:province":"SC",
    "wof:name":"Christopher Jim Rl Est",
    "wof:placetype":"venue"
},
  "geometry": {"coordinates":[-81.0476,34.009399],"type":"Point"}
}