{
  "type": "Feature",
  "properties": {
    "addr:full":"2701 David H McLeod Blvd Florence SC 29501",
    "addr:housenumber":"2701",
    "addr:postcode":"29501",
    "addr:street":"David H Mcleod Blvd",
    "iso:country":"US",
    "sg:address":"2701 David H McLeod Blvd",
    "sg:city":"Florence",
    "sg:classifiers":[
        {
            "category":"Retail",
            "subcategory":"Repair Shop",
            "type":"Services"
        }
    ],
    "sg:phone":"+1 843 667 0861",
    "sg:postcode":"29501",
    "sg:province":"SC",
    "sg:tags":[
        "jewelry"
    ],
    "wof:name":"Reeds Jewelers Inc",
    "wof:placetype":"venue"
},
  "geometry": {"coordinates":[-79.83568099999999,34.18968],"type":"Point"}
}