{
  "type": "Feature",
  "properties": {
    "addr:full":"5916 Calhoun Memorial Hwy Easley SC 29642",
    "addr:housenumber":"5916",
    "addr:postcode":"29642",
    "addr:street":"Calhoun Memorial Hwy",
    "iso:country":"US",
    "sg:address":"5916 Calhoun Memorial Hwy",
    "sg:city":"Easley",
    "sg:classifiers":[
        {
            "category":"Autos & Motor Vehicles",
            "subcategory":"Automobile Sales",
            "type":"Retail Goods"
        }
    ],
    "sg:phone":"+1 864 859 3833",
    "sg:postcode":"29642",
    "sg:province":"SC",
    "sg:tags":[
        "car",
        "dealer"
    ],
    "wof:name":"Toyota Of Easley Truck Ctr",
    "wof:placetype":"venue"
},
  "geometry": {"coordinates":[-82.593293,34.820251],"type":"Point"}
}