{
  "type": "Feature",
  "properties": {
    "iso:country":"US",
    "sg:address":"5223 Notch Rd",
    "sg:city":"Columbia",
    "sg:classifiers":[
        {
            "category":"Banks & Credit Unions",
            "subcategory":"Bank",
            "type":"Services"
        }
    ],
    "sg:phone":"+1 803 754 7887",
    "sg:postcode":"29204",
    "sg:province":"SC",
    "sg:tags":[
        "loan"
    ],
    "wof:name":"Clear Credit",
    "wof:placetype":"venue"
},
  "geometry": {"coordinates":[-80.987034,34.047573],"type":"Point"}
}