{
  "type": "Feature",
  "properties": {
    "iso:country":"US",
    "sg:address":"773 Mount Bethel Garmany Rd",
    "sg:city":"Newberry",
    "sg:classifiers":[
        {
            "category":"Building & Trades",
            "subcategory":"Electrical",
            "type":"Services"
        }
    ],
    "sg:phone":"+1 803 276 8898",
    "sg:postcode":"29108",
    "sg:province":"SC",
    "sg:tags":[
        "electrical",
        "contractor"
    ],
    "wof:name":"Mikes Electric",
    "wof:placetype":"venue"
},
  "geometry": {"coordinates":[-81.59646100000001,34.300554],"type":"Point"}
}