{
  "type": "Feature",
  "properties": {
    "iso:country":"US",
    "sg:address":"5 Windsor Dr",
    "sg:city":"Charleston",
    "sg:classifiers":[
        {
            "category":"Organizations",
            "subcategory":"Religious Organization",
            "type":"Services"
        }
    ],
    "sg:phone":"+1 843 571 3264",
    "sg:postcode":"29407",
    "sg:province":"SC",
    "sg:tags":[
        "synagogue"
    ],
    "sg:website":"www.emanu-el.com",
    "wof:name":"Synagogue Emanuel-Conservative",
    "wof:placetype":"venue"
},
  "geometry": {"coordinates":[-79.987382,32.827588],"type":"Point"}
}