{
  "type": "Feature",
  "properties": {
    "iso:country":"US",
    "sg:address":"1907 State Hwy 402",
    "sg:city":"Moncks Corner",
    "sg:classifiers":[
        {
            "category":"Building & Trades",
            "subcategory":"Construction",
            "type":"Services"
        }
    ],
    "sg:phone":"+1 843 871 6400",
    "sg:postcode":"29461",
    "sg:province":"SC",
    "sg:tags":[
        "house"
    ],
    "wof:name":"Reeves Home Repair",
    "wof:placetype":"venue"
},
  "geometry": {"coordinates":[-79.918353,33.179799],"type":"Point"}
}