{
  "type": "Feature",
  "properties": {
    "iso:country":"US",
    "sg:address":"2768 Decker Blvd",
    "sg:city":"Columbia",
    "sg:classifiers":[
        {
            "category":"Retail",
            "subcategory":"Repair Shop",
            "type":"Services"
        }
    ],
    "sg:phone":"+1 803 788 1892",
    "sg:postcode":"29206",
    "sg:province":"SC",
    "sg:tags":[
        "picture",
        "framing"
    ],
    "wof:name":"Madison-Alexander",
    "wof:placetype":"venue"
},
  "geometry": {"coordinates":[-80.955767,34.064087],"type":"Point"}
}