{
  "type": "Feature",
  "properties": {
    "addr:full":"1123 Pleasant Oaks Dr Mt Pleasant SC 29464",
    "addr:housenumber":"1123",
    "addr:postcode":"29464",
    "addr:street":"Pleasant Oaks Dr",
    "iso:country":"US",
    "sg:address":"1123 Pleasant Oaks Dr",
    "sg:city":"Mt Pleasant",
    "sg:classifiers":[
        {
            "category":"Building & Trades",
            "subcategory":"Construction",
            "type":"Services"
        }
    ],
    "sg:phone":"+1 843 216 0410",
    "sg:postcode":"29464",
    "sg:province":"SC",
    "sg:tags":[
        "masonry",
        "contractor"
    ],
    "sg:website":"www.stonescape.com",
    "wof:name":"Paver Scape Design Group",
    "wof:placetype":"venue"
},
  "geometry": {"coordinates":[-79.85478999999999,32.8016],"type":"Point"}
}