{
  "type": "Feature",
  "properties": {
    "iso:country":"US",
    "sg:address":"1515 Boundary St",
    "sg:city":"Newberry",
    "sg:classifiers":[
        {
            "category":"Organizations",
            "subcategory":"Religious Organization",
            "type":"Services"
        }
    ],
    "sg:phone":"+1 803 276 2003",
    "sg:postcode":"29108",
    "sg:province":"SC",
    "sg:tags":[
        "church"
    ],
    "sg:website":"www.lutheranredeemer.org",
    "wof:name":"Lutheran Church-The Redeemer",
    "wof:placetype":"venue"
},
  "geometry": {"coordinates":[-81.616225,34.27361],"type":"Point"}
}