{
  "type": "Feature",
  "properties": {
    "iso:country":"US",
    "sg:address":"507 Chesnut St",
    "sg:city":"Camden",
    "sg:classifiers":[
        {
            "category":"Building & Trades",
            "subcategory":"Construction",
            "type":"Services"
        }
    ],
    "sg:phone":"+1 803 713 0297",
    "sg:postcode":"29020",
    "sg:province":"SC",
    "sg:tags":[
        "house"
    ],
    "wof:name":"Sunshine Construction Camden",
    "wof:placetype":"venue"
},
  "geometry": {"coordinates":[-80.60617499999999,34.256866],"type":"Point"}
}