{
  "type": "Feature",
  "properties": {
    "addr:full":"3216 McTavish Ave West Columbia SC 29172",
    "addr:housenumber":"3216",
    "addr:postcode":"29172",
    "addr:street":"Mctavish Ave",
    "iso:country":"US",
    "sg:address":"3216 McTavish Ave",
    "sg:city":"West Columbia",
    "sg:classifiers":[
        {
            "category":"Building & Trades",
            "subcategory":"Locksmith",
            "type":"Services"
        }
    ],
    "sg:phone":"+1 803 407 0002",
    "sg:postcode":"29172",
    "sg:province":"SC",
    "sg:tags":[
        "key"
    ],
    "wof:name":"A 1 Lockouts",
    "wof:placetype":"venue"
},
  "geometry": {"coordinates":[-81.14647600000001,33.895704],"type":"Point"}
}