{
  "type": "Feature",
  "properties": {
    "iso:country":"US",
    "sg:address":"300 E Henry St",
    "sg:city":"Spartanburg",
    "sg:classifiers":[
        {
            "category":"Professional",
            "subcategory":"Research",
            "type":"Services"
        }
    ],
    "sg:phone":"+1 864 573 9853",
    "sg:postcode":"29302",
    "sg:province":"SC",
    "sg:tags":[
        "market",
        "analysis"
    ],
    "sg:website":"www.pmgco.com",
    "wof:name":"Priority Metrics Group",
    "wof:placetype":"venue"
},
  "geometry": {"coordinates":[-81.922491,34.947538],"type":"Point"}
}