{
  "type": "Feature",
  "properties": {
    "addr:full":"27 Edwards Lake Rd Greer SC 29651",
    "addr:housenumber":"27",
    "addr:postcode":"29651",
    "addr:street":"Edwards Lake Rd",
    "iso:country":"US",
    "sg:address":"27 Edwards Lake Rd",
    "sg:city":"Greer",
    "sg:classifiers":[
        {
            "category":"Building & Trades",
            "subcategory":"Cleaning & Sanitation",
            "type":"Services"
        }
    ],
    "sg:phone":"+1 864 895 4204",
    "sg:postcode":"29651",
    "sg:province":"SC",
    "sg:tags":[
        "maintenance",
        "contractor"
    ],
    "wof:name":"Leavesout Of Greer",
    "wof:placetype":"venue"
},
  "geometry": {"coordinates":[-82.28101700000001,35.018472],"type":"Point"}
}