{
  "type": "Feature",
  "properties": {
    "iso:country":"US",
    "sg:address":"2932 W Black Creek Rd",
    "sg:city":"Florence",
    "sg:classifiers":[
        {
            "category":"Autos & Motor Vehicles",
            "subcategory":"Automobile Sales",
            "type":"Retail Goods"
        }
    ],
    "sg:phone":"+1 843 667 9932",
    "sg:postcode":"29501",
    "sg:province":"SC",
    "wof:name":"TMI",
    "wof:placetype":"venue"
},
  "geometry": {"coordinates":[-79.752535,34.250547],"type":"Point"}
}