{
  "type": "Feature",
  "properties": {
    "iso:country":"US",
    "sg:address":"5319 N Kings Hwy",
    "sg:city":"Myrtle Beach",
    "sg:classifiers":[
        {
            "category":"Personal",
            "subcategory":"Beauty Salon",
            "type":"Services"
        }
    ],
    "sg:phone":"+1 843 692 2322",
    "sg:postcode":"29577",
    "sg:province":"SC",
    "wof:name":"Fa Fa Do",
    "wof:placetype":"venue"
},
  "geometry": {"coordinates":[-78.842822,33.726949],"type":"Point"}
}