{
  "type": "Feature",
  "properties": {
    "iso:country":"US",
    "sg:address":"500 Mount Airy Church Rd",
    "sg:city":"Easley",
    "sg:classifiers":[
        {
            "category":"Organizations",
            "subcategory":"Religious Organization",
            "type":"Services"
        }
    ],
    "sg:phone":"+1 864 859 0974",
    "sg:postcode":"29642",
    "sg:province":"SC",
    "sg:tags":[
        "church"
    ],
    "wof:name":"Mt Tabor Baptist Church",
    "wof:placetype":"venue"
},
  "geometry": {"coordinates":[-82.532767,34.755804],"type":"Point"}
}