{
  "type": "Feature",
  "properties": {
    "iso:country":"US",
    "sg:address":"2201 Woodruff Rd",
    "sg:city":"Simpsonville",
    "sg:classifiers":[
        {
            "category":"Food & Beverages",
            "subcategory":"Groceries & Convenience Stores",
            "type":"Retail Goods"
        }
    ],
    "sg:phone":"+1 864 297 7959",
    "sg:postcode":"29681",
    "sg:province":"SC",
    "wof:name":"Pantry Inc",
    "wof:placetype":"venue"
},
  "geometry": {"coordinates":[-82.24723400000001,34.815739],"type":"Point"}
}