{
  "type": "Feature",
  "properties": {
    "iso:country":"US",
    "sg:address":"4695 Franchise St",
    "sg:city":"North Charleston",
    "sg:classifiers":[
        {
            "category":"Building & Trades",
            "subcategory":"Construction",
            "type":"Services"
        }
    ],
    "sg:phone":"+1 843 760 9993",
    "sg:postcode":"29418",
    "sg:province":"SC",
    "sg:tags":[
        "contractor"
    ],
    "wof:name":"B & K Global Group Inc",
    "wof:placetype":"venue"
},
  "geometry": {"coordinates":[-80.092634,32.911698],"type":"Point"}
}