{
  "type": "Feature",
  "properties": {
    "iso:country":"US",
    "sg:address":"4714 US Hwy 221",
    "sg:city":"Greenwood",
    "sg:classifiers":[
        {
            "category":"Restaurant",
            "type":"Food & Drink"
        }
    ],
    "sg:phone":"+1 864 943 2278",
    "sg:postcode":"29649",
    "sg:province":"SC",
    "wof:name":"Fish House",
    "wof:placetype":"venue"
},
  "geometry": {"coordinates":[-82.061223,34.276122],"type":"Point"}
}