{
  "type": "Feature",
  "properties": {
    "iso:country":"US",
    "sg:address":"211 55th Ave N",
    "sg:city":"North Myrtle Beach",
    "sg:classifiers":[
        {
            "category":"Real Estate",
            "subcategory":"Real Estate Operator",
            "type":"Services"
        }
    ],
    "sg:phone":"+1 843 280 0184",
    "sg:postcode":"29582",
    "sg:province":"SC",
    "sg:tags":[
        "building",
        "nonresidential"
    ],
    "wof:name":"Jts Grove Properties LLC",
    "wof:placetype":"venue"
},
  "geometry": {"coordinates":[-78.613361,33.838519],"type":"Point"}
}