{
  "type": "Feature",
  "properties": {
    "addr:full":"480 Hodge Rd Summerville SC 29483",
    "addr:housenumber":"480",
    "addr:postcode":"29483",
    "addr:street":"Hodge Rd",
    "iso:country":"US",
    "sg:address":"480 Hodge Rd",
    "sg:city":"Summerville",
    "sg:classifiers":[
        {
            "category":"Home & Garden",
            "subcategory":"Building Materials",
            "type":"Retail Goods"
        }
    ],
    "sg:phone":"+1 843 873 0226",
    "sg:postcode":"29483",
    "sg:province":"SC",
    "sg:tags":[
        "mixed",
        "concrete"
    ],
    "wof:name":"Knights Concrete Product Inc",
    "wof:placetype":"venue"
},
  "geometry": {"coordinates":[-80.217637,33.058085],"type":"Point"}
}