{
  "type": "Feature",
  "properties": {
    "iso:country":"US",
    "sg:address":"618 S Manning St",
    "sg:city":"Anderson",
    "sg:classifiers":[
        {
            "category":"Organizations",
            "subcategory":"Professional Association",
            "type":"Services"
        }
    ],
    "sg:phone":"+1 864 225 8586",
    "sg:postcode":"29624",
    "sg:province":"SC",
    "wof:name":"Anderson Sunshine House",
    "wof:placetype":"venue"
},
  "geometry": {"coordinates":[-82.646196,34.499382],"type":"Point"}
}