{
  "type": "Feature",
  "properties": {
    "addr:full":"508 Davis St Lake City SC 29560",
    "addr:housenumber":"508",
    "addr:postcode":"29560",
    "addr:street":"Davis St",
    "iso:country":"US",
    "sg:address":"508 Davis St",
    "sg:city":"Lake City",
    "sg:classifiers":[
        {
            "category":"Freight",
            "type":"Transportation"
        }
    ],
    "sg:phone":"+1 843 374 3840",
    "sg:postcode":"29560",
    "sg:province":"SC",
    "sg:tags":[
        "trucking"
    ],
    "wof:name":"Thomas Trucking Co LLC",
    "wof:placetype":"venue"
},
  "geometry": {"coordinates":[-79.776218,33.859653],"type":"Point"}
}