{
  "type": "Feature",
  "properties": {
    "iso:country":"US",
    "sg:address":"2470 Old Mill Rd",
    "sg:city":"Inman",
    "sg:classifiers":[
        {
            "category":"Health Services",
            "subcategory":"Nursing And Care Facility",
            "type":"Services"
        }
    ],
    "sg:phone":"+1 864 472 6979",
    "sg:postcode":"29349",
    "sg:province":"SC",
    "sg:tags":[
        "home",
        "retirement",
        "community"
    ],
    "wof:name":"Oakridge Community Care Home",
    "wof:placetype":"venue"
},
  "geometry": {"coordinates":[-82.099054,35.086591],"type":"Point"}
}