{
  "type": "Feature",
  "properties": {
    "iso:country":"US",
    "sg:address":"2230 Airport Blvd",
    "sg:city":"West Columbia",
    "sg:classifiers":[
        {
            "category":"Health Services",
            "subcategory":"Chiropractor",
            "type":"Services"
        }
    ],
    "sg:phone":"+1 803 796 3750",
    "sg:postcode":"29170",
    "sg:province":"SC",
    "wof:name":"Jones Steven A Dr Chiropctr",
    "wof:placetype":"venue"
},
  "geometry": {"coordinates":[-81.099197,33.950901],"type":"Point"}
}