{
  "type": "Feature",
  "properties": {
    "iso:country":"US",
    "sg:address":"314 Rembert C Dennis Blvd",
    "sg:city":"Moncks Corner",
    "sg:classifiers":[
        {
            "category":"Personal",
            "type":"Services"
        }
    ],
    "sg:phone":"+1 843 761 0071",
    "sg:postcode":"29461",
    "sg:province":"SC",
    "sg:tags":[
        "therapist",
        "massage"
    ],
    "wof:name":"Hands On Therapy",
    "wof:placetype":"venue"
},
  "geometry": {"coordinates":[-79.986076,33.194642],"type":"Point"}
}