{
  "type": "Feature",
  "properties": {
    "addr:full":"627 Bultman Dr Sumter SC 29150",
    "addr:housenumber":"627",
    "addr:postcode":"29150",
    "addr:street":"Bultman Dr",
    "iso:country":"US",
    "sg:address":"627 Bultman Dr",
    "sg:city":"Sumter",
    "sg:classifiers":[
        {
            "category":"Food & Beverages",
            "subcategory":"Bakery",
            "type":"Retail Goods"
        }
    ],
    "sg:phone":"+1 803 938 8099",
    "sg:postcode":"29150",
    "sg:province":"SC",
    "sg:tags":[
        "baker"
    ],
    "wof:name":"Murray's Donuts",
    "wof:placetype":"venue"
},
  "geometry": {"coordinates":[-80.371646,33.93983],"type":"Point"}
}