{
  "type": "Feature",
  "properties": {
    "iso:country":"US",
    "sg:address":"403 Cherry Rd",
    "sg:city":"Rock Hill",
    "sg:classifiers":[
        {
            "category":"Restaurant",
            "type":"Food & Drink"
        }
    ],
    "sg:menulink":"http://www.allmenus.com/sc/rock-hill/235299-sub-station-ii/menu/",
    "sg:phone":"+1 803 329 0073",
    "sg:postcode":"29732",
    "sg:province":"SC",
    "sg:tags":[
        "wrap",
        "american",
        "sandwich"
    ],
    "wof:name":"Sub Station II",
    "wof:placetype":"venue"
},
  "geometry": {"coordinates":[-81.032607,34.943243],"type":"Point"}
}