{
  "type": "Feature",
  "properties": {
    "iso:country":"US",
    "sg:address":"1823 Augusta St",
    "sg:city":"Greenville",
    "sg:classifiers":[
        {
            "category":"Social Services",
            "type":"Services"
        }
    ],
    "sg:phone":"+1 864 241 1399",
    "sg:postcode":"29605",
    "sg:province":"SC",
    "sg:tags":[
        "organization",
        "welfare"
    ],
    "wof:name":"Diligent Hands Gracious Hearts",
    "wof:placetype":"venue"
},
  "geometry": {"coordinates":[-82.39825500000001,34.827635],"type":"Point"}
}