{
  "type": "Feature",
  "properties": {
    "iso:country":"US",
    "sg:address":"251 E Bay St",
    "sg:city":"Charleston",
    "sg:classifiers":[
        {
            "category":"Bars & Pubs",
            "type":"Food & Drink"
        }
    ],
    "sg:phone":"+1 843 723 3483",
    "sg:postcode":"29401",
    "sg:province":"SC",
    "sg:tags":[
        "drinking"
    ],
    "wof:name":"Big John's Tavern",
    "wof:placetype":"venue"
},
  "geometry": {"coordinates":[-79.927695,32.782004],"type":"Point"}
}