{
  "type": "Feature",
  "properties": {
    "iso:country":"US",
    "sg:address":"909 Central Ave",
    "sg:city":"Summerville",
    "sg:classifiers":[
        {
            "category":"Retail",
            "subcategory":"Animal Services",
            "type":"Services"
        }
    ],
    "sg:phone":"+1 843 873 4740",
    "sg:postcode":"29483",
    "sg:province":"SC",
    "sg:tags":[
        "pet",
        "grooming",
        "washing"
    ],
    "wof:name":"Pampered Pooch",
    "wof:placetype":"venue"
},
  "geometry": {"coordinates":[-80.243682,33.009321],"type":"Point"}
}