{
  "type": "Feature",
  "properties": {
    "iso:country":"US",
    "sg:address":"308 Middleton Blvd",
    "sg:city":"Summerville",
    "sg:classifiers":[
        {
            "category":"Real Estate",
            "subcategory":"Real Estate Agent",
            "type":"Services"
        }
    ],
    "sg:phone":"+1 843 875 1115",
    "sg:postcode":"29485",
    "sg:province":"SC",
    "wof:name":"Klm Enterprises",
    "wof:placetype":"venue"
},
  "geometry": {"coordinates":[-80.182963,32.95917],"type":"Point"}
}