{
  "type": "Feature",
  "properties": {
    "addr:full":"1621 Dusty Rd Newberry SC 29108",
    "addr:housenumber":"1621",
    "addr:postcode":"29108",
    "addr:street":"Dusty Rd",
    "iso:country":"US",
    "sg:address":"1621 Dusty Rd",
    "sg:city":"Newberry",
    "sg:classifiers":[
        {
            "category":"Farming",
            "subcategory":"Poultry Farm",
            "type":"Manufacturing & Wholesale Goods"
        }
    ],
    "sg:phone":"+1 803 321 5806",
    "sg:postcode":"29108",
    "sg:province":"SC",
    "sg:tags":[
        "chicken",
        "egg"
    ],
    "wof:name":"Bonnie Cromer",
    "wof:placetype":"venue"
},
  "geometry": {"coordinates":[-81.561069,34.313076],"type":"Point"}
}