{
  "type": "Feature",
  "properties": {
    "addr:full":"1956 Remount Rd Charleston SC 29406",
    "addr:housenumber":"1956",
    "addr:postcode":"29406",
    "addr:street":"Remount Rd",
    "iso:country":"US",
    "sg:address":"1956 Remount Rd",
    "sg:city":"Charleston",
    "sg:classifiers":[
        {
            "category":"Insurance",
            "subcategory":"Insurance Agent",
            "type":"Services"
        }
    ],
    "sg:phone":"+1 843 747 9073",
    "sg:postcode":"29406",
    "sg:province":"SC",
    "sg:tags":[
        "agency"
    ],
    "wof:name":"Pinckney-Carter Company",
    "wof:placetype":"venue"
},
  "geometry": {"coordinates":[-80.013936,32.899528],"type":"Point"}
}