{
  "type": "Feature",
  "properties": {
    "addr:full":"930 Richland Ave W Aiken SC 29801",
    "addr:housenumber":"930",
    "addr:postcode":"29801",
    "addr:street":"Richland Ave W",
    "iso:country":"US",
    "sg:address":"930 Richland Ave W",
    "sg:city":"Aiken",
    "sg:phone":"+1 803 649 1194",
    "sg:postcode":"29801",
    "sg:province":"SC",
    "sg:tags":[
        "oil"
    ],
    "wof:name":"Milner Super Gas Inc",
    "wof:placetype":"venue"
},
  "geometry": {"coordinates":[-81.73184500000001,33.564968],"type":"Point"}
}