{
  "type": "Feature",
  "properties": {
    "iso:country":"US",
    "sg:address":"6601 Dorchester Rd",
    "sg:city":"North Charleston",
    "sg:classifiers":[
        {
            "category":"Professional",
            "type":"Services"
        }
    ],
    "sg:phone":"+1 843 207 9937",
    "sg:postcode":"29418",
    "sg:province":"SC",
    "sg:tags":[
        "establishment"
    ],
    "wof:name":"C AC",
    "wof:placetype":"venue"
},
  "geometry": {"coordinates":[-80.063812,32.879801],"type":"Point"}
}