{
  "type": "Feature",
  "properties": {
    "addr:full":"2752 Pleasant Rd Fort Mill SC 29708",
    "addr:housenumber":"2752",
    "addr:postcode":"29708",
    "addr:street":"Pleasant Rd",
    "iso:country":"US",
    "sg:address":"2752 Pleasant Rd",
    "sg:city":"Fort Mill",
    "sg:classifiers":[
        {
            "category":"Health Services",
            "subcategory":"Chiropractor",
            "type":"Services"
        }
    ],
    "sg:phone":"+1 803 802 3737",
    "sg:postcode":"29708",
    "sg:province":"SC",
    "wof:name":"Mc Cartney Chiropractic Ctr",
    "wof:placetype":"venue"
},
  "geometry": {"coordinates":[-80.96710299999999,35.058607],"type":"Point"}
}