{
  "type": "Feature",
  "properties": {
    "iso:country":"US",
    "sg:address":"1414 Fording Island Rd",
    "sg:city":"Bluffton",
    "sg:classifiers":[
        {
            "category":"Shopping",
            "type":"Retail Goods"
        }
    ],
    "sg:phone":"+1 843 836 2720",
    "sg:postcode":"29910",
    "sg:province":"SC",
    "sg:tags":[
        "factory",
        "outlet"
    ],
    "wof:name":"Rockport Factory Outlet Store",
    "wof:placetype":"venue"
},
  "geometry": {"coordinates":[-80.821317,32.241281],"type":"Point"}
}