{
  "type": "Feature",
  "properties": {
    "iso:country":"US",
    "sg:address":"304 Ledbetter Rd",
    "sg:city":"Travelers Rest",
    "sg:classifiers":[
        {
            "category":"Building & Trades",
            "subcategory":"Pest Control",
            "type":"Services"
        }
    ],
    "sg:phone":"+1 864 834 3875",
    "sg:postcode":"29690",
    "sg:province":"SC",
    "wof:name":"Hawkins Pest Control",
    "wof:placetype":"venue"
},
  "geometry": {"coordinates":[-82.497435,34.970593],"type":"Point"}
}