{
  "type": "Feature",
  "properties": {
    "addr:full":"7201 Notch Rd Columbia SC 29223",
    "addr:housenumber":"7201",
    "addr:postcode":"29223",
    "addr:street":"Notch Rd",
    "iso:country":"US",
    "sg:address":"7201 Notch Rd",
    "sg:city":"Columbia",
    "sg:classifiers":[
        {
            "category":"Food & Beverages",
            "subcategory":"Specialty",
            "type":"Retail Goods"
        }
    ],
    "sg:phone":"+1 803 788 7811",
    "sg:postcode":"29223",
    "sg:province":"SC",
    "sg:tags":[
        "tea",
        "coffee"
    ],
    "wof:name":"Cones'n Cappuccino",
    "wof:placetype":"venue"
},
  "geometry": {"coordinates":[-80.956811,34.065152],"type":"Point"}
}