{
  "type": "Feature",
  "properties": {
    "addr:full":"445 S Suber Rd Greer SC 29650",
    "addr:housenumber":"445",
    "addr:postcode":"29650",
    "addr:street":"S Suber Rd",
    "iso:country":"US",
    "sg:address":"445 S Suber Rd",
    "sg:city":"Greer",
    "sg:classifiers":[
        {
            "category":"Organizations",
            "subcategory":"Religious Organization",
            "type":"Services"
        }
    ],
    "sg:phone":"+1 864 801 0181",
    "sg:postcode":"29650",
    "sg:province":"SC",
    "sg:tags":[
        "church"
    ],
    "sg:website":"www.suberroad.org",
    "wof:name":"Suber Road Baptist Church",
    "wof:placetype":"venue"
},
  "geometry": {"coordinates":[-82.26897700000001,34.929424],"type":"Point"}
}