{
  "type": "Feature",
  "properties": {
    "iso:country":"US",
    "sg:address":"301 W Cherokee St",
    "sg:city":"Blacksburg",
    "sg:classifiers":[
        {
            "category":"Personal",
            "subcategory":"Beauty Salon",
            "type":"Services"
        }
    ],
    "sg:phone":"+1 864 839 9682",
    "sg:postcode":"29702",
    "sg:province":"SC",
    "wof:name":"Headlines Unlimited",
    "wof:placetype":"venue"
},
  "geometry": {"coordinates":[-81.52032699999999,35.119102],"type":"Point"}
}