{
  "type": "Feature",
  "properties": {
    "addr:full":"1058 E Montague Ave Charleston SC 29405",
    "addr:housenumber":"1058",
    "addr:postcode":"29405",
    "addr:street":"E Montague Ave",
    "iso:country":"US",
    "sg:address":"1058 E Montague Ave",
    "sg:city":"Charleston",
    "sg:classifiers":[
        {
            "category":"Restaurant",
            "type":"Food & Drink"
        }
    ],
    "sg:phone":"+1 843 225 6151",
    "sg:postcode":"29405",
    "sg:province":"SC",
    "sg:tags":[
        "caterer"
    ],
    "wof:name":"Especially For You By Denise",
    "wof:placetype":"venue"
},
  "geometry": {"coordinates":[-79.976403,32.881609],"type":"Point"}
}