{
  "type": "Feature",
  "properties": {
    "addr:full":"880 Rawlinson Rd Rock Hill SC 29732",
    "addr:housenumber":"880",
    "addr:postcode":"29732",
    "addr:street":"Rawlinson Rd",
    "iso:country":"US",
    "sg:address":"880 Rawlinson Rd",
    "sg:city":"Rock Hill",
    "sg:classifiers":[
        {
            "category":"Building & Trades",
            "subcategory":"Construction",
            "type":"Services"
        }
    ],
    "sg:phone":"+1 803 329 0613",
    "sg:postcode":"29732",
    "sg:province":"SC",
    "sg:tags":[
        "contractor"
    ],
    "wof:name":"Parrots Landing Swimming Pools",
    "wof:placetype":"venue"
},
  "geometry": {"coordinates":[-81.084827,34.957558],"type":"Point"}
}