{
  "type": "Feature",
  "properties": {
    "addr:full":"507 9th Ave S North Myrtle Beach SC 29582",
    "addr:housenumber":"507",
    "addr:postcode":"29582",
    "addr:street":"9Th Ave S North",
    "iso:country":"US",
    "sg:address":"507 9th Ave S",
    "sg:city":"North Myrtle Beach",
    "sg:classifiers":[
        {
            "category":"Food & Beverages",
            "subcategory":"Bakery",
            "type":"Retail Goods"
        }
    ],
    "sg:phone":"+1 843 448 3327",
    "sg:postcode":"29582",
    "sg:province":"SC",
    "wof:name":"Antonios Bakery",
    "wof:placetype":"venue"
},
  "geometry": {"coordinates":[-78.686013,33.817384],"type":"Point"}
}