{
  "type": "Feature",
  "properties": {
    "addr:full":"2004 Tickle Hill Rd Camden SC 29020",
    "addr:housenumber":"2004",
    "addr:postcode":"29020",
    "addr:street":"Tickle Hill Rd",
    "iso:country":"US",
    "sg:address":"2004 Tickle Hill Rd",
    "sg:city":"Camden",
    "sg:classifiers":[
        {
            "category":"Wholesale",
            "subcategory":"Machinery & Supplies",
            "type":"Manufacturing & Wholesale Goods"
        }
    ],
    "sg:phone":"+1 803 432 1680",
    "sg:postcode":"29020",
    "sg:province":"SC",
    "sg:tags":[
        "janitor",
        "establishment",
        "equipment"
    ],
    "wof:name":"G & J Supply & Service Co",
    "wof:placetype":"venue"
},
  "geometry": {"coordinates":[-80.56589,34.237235],"type":"Point"}
}