{
  "type": "Feature",
  "properties": {
    "iso:country":"US",
    "sg:address":"611 N Main St",
    "sg:city":"Simpsonville",
    "sg:classifiers":[
        {
            "category":"Professional",
            "subcategory":"Research",
            "type":"Services"
        }
    ],
    "sg:phone":"+1 864 962 0431",
    "sg:postcode":"29681",
    "sg:province":"SC",
    "sg:tags":[
        "medical"
    ],
    "wof:name":"Palmetto Clinical Trial Svc",
    "wof:placetype":"venue"
},
  "geometry": {"coordinates":[-82.261075,34.747555],"type":"Point"}
}