{
  "type": "Feature",
  "properties": {
    "iso:country":"US",
    "sg:address":"342 Amicks Ferry Rd",
    "sg:city":"Chapin",
    "sg:classifiers":[
        {
            "category":"Wholesale",
            "subcategory":"Machinery & Supplies",
            "type":"Manufacturing & Wholesale Goods"
        }
    ],
    "sg:phone":"+1 800 258 7614",
    "sg:postcode":"29036",
    "sg:province":"SC",
    "sg:tags":[
        "industrial"
    ],
    "wof:name":"Southern Tooling Systems Inc",
    "wof:placetype":"venue"
},
  "geometry": {"coordinates":[-81.358442,34.155946],"type":"Point"}
}