{
  "type": "Feature",
  "properties": {
    "iso:country":"US",
    "sg:address":"511 E Church Rd",
    "sg:city":"Easley",
    "sg:classifiers":[
        {
            "category":"Organizations",
            "subcategory":"Religious Organization",
            "type":"Services"
        }
    ],
    "sg:phone":"+1 864 855 4446",
    "sg:postcode":"29642",
    "sg:province":"SC",
    "sg:tags":[
        "church"
    ],
    "wof:name":"Corinth No 1 Baptist Church",
    "wof:placetype":"venue"
},
  "geometry": {"coordinates":[-82.58647499999999,34.767305],"type":"Point"}
}