{
  "type": "Feature",
  "properties": {
    "addr:full":"1215 Celebrity Cir Myrtle Beach SC 29577",
    "addr:housenumber":"1215",
    "addr:postcode":"29577",
    "addr:street":"Celebrity Cir",
    "iso:country":"US",
    "sg:address":"1215 Celebrity Cir",
    "sg:city":"Myrtle Beach",
    "sg:classifiers":[
        {
            "category":"Shopping",
            "subcategory":"Hobbies, Toys, & Games",
            "type":"Retail Goods"
        }
    ],
    "sg:phone":"+1 843 626 8191",
    "sg:postcode":"29577",
    "sg:province":"SC",
    "sg:tags":[
        "magician",
        "supply"
    ],
    "wof:name":"Broadway Magic",
    "wof:placetype":"venue"
},
  "geometry": {"coordinates":[-78.88577600000001,33.715613],"type":"Point"}
}