{
  "type": "Feature",
  "properties": {
    "addr:full":"462 N Guignard Dr Sumter SC 29150",
    "addr:housenumber":"462",
    "addr:postcode":"29150",
    "addr:street":"N Guignard Dr",
    "iso:country":"US",
    "sg:address":"462 N Guignard Dr",
    "sg:city":"Sumter",
    "sg:classifiers":[
        {
            "category":"Real Estate",
            "subcategory":"Real Estate Agent",
            "type":"Services"
        }
    ],
    "sg:phone":"+1 803 775 2139",
    "sg:postcode":"29150",
    "sg:province":"SC",
    "wof:name":"Colonial Real Estate",
    "wof:placetype":"venue"
},
  "geometry": {"coordinates":[-80.36927900000001,33.932679],"type":"Point"}
}