{
  "type": "Feature",
  "properties": {
    "iso:country":"US",
    "sg:address":"501 Montague Ave",
    "sg:city":"Greenwood",
    "sg:classifiers":[
        {
            "category":"Sports & Exercise",
            "subcategory":"Gym",
            "type":"Entertainment"
        }
    ],
    "sg:phone":"+1 864 227 4664",
    "sg:postcode":"29649",
    "sg:province":"SC",
    "sg:tags":[
        "club",
        "health",
        "studio",
        "gymnasium"
    ],
    "wof:name":"Wellness Works-Self Memorial",
    "wof:placetype":"venue"
},
  "geometry": {"coordinates":[-82.17299800000001,34.203982],"type":"Point"}
}