{
  "type": "Feature",
  "properties": {
    "addr:full":"1141 Clements Ferry Rd Charleston SC 29492",
    "addr:housenumber":"1141",
    "addr:postcode":"29492",
    "addr:street":"Clements Ferry Rd",
    "iso:country":"US",
    "sg:address":"1141 Clements Ferry Rd",
    "sg:city":"Charleston",
    "sg:classifiers":[
        {
            "category":"Retail",
            "subcategory":"Repair Shop",
            "type":"Services"
        }
    ],
    "sg:phone":"+1 843 884 8706",
    "sg:postcode":"29492",
    "sg:province":"SC",
    "sg:tags":[
        "parts",
        "boat"
    ],
    "wof:name":"Whitton Marine Inc",
    "wof:placetype":"venue"
},
  "geometry": {"coordinates":[-79.827457,32.933526],"type":"Point"}
}