{
  "type": "Feature",
  "properties": {
    "addr:full":"1121 Broad St Sumter SC 29150",
    "addr:housenumber":"1121",
    "addr:postcode":"29150",
    "addr:street":"Broad St",
    "iso:country":"US",
    "sg:address":"1121 Broad St",
    "sg:city":"Sumter",
    "sg:classifiers":[
        {
            "category":"Shopping",
            "subcategory":"Department Store",
            "type":"Retail Goods"
        }
    ],
    "sg:phone":"+1 803 778 2688",
    "sg:postcode":"29150",
    "sg:province":"SC",
    "sg:tags":[
        "shop"
    ],
    "wof:name":"Big Lots",
    "wof:placetype":"venue"
},
  "geometry": {"coordinates":[-80.378128,33.952971],"type":"Point"}
}