{
  "type": "Feature",
  "properties": {
    "iso:country":"US",
    "sg:address":"13002 Choppee Rd",
    "sg:city":"Hemingway",
    "sg:classifiers":[
        {
            "category":"Education",
            "subcategory":"School",
            "type":"Public Place"
        }
    ],
    "sg:phone":"+1 843 545 5837",
    "sg:postcode":"29440",
    "sg:province":"SC",
    "wof:name":"Carvers Bay High School",
    "wof:placetype":"venue"
},
  "geometry": {"coordinates":[-79.328183,33.61747],"type":"Point"}
}