{
  "type": "Feature",
  "properties": {
    "iso:country":"US",
    "sg:address":"1596 Carterett Ave",
    "sg:city":"Charleston",
    "sg:classifiers":[
        {
            "category":"Shopping",
            "type":"Retail Goods"
        }
    ],
    "sg:phone":"+1 843 769 6889",
    "sg:postcode":"29407",
    "sg:province":"SC",
    "sg:tags":[
        "wedding",
        "supply"
    ],
    "wof:name":"Charleston Oyster Machine Co",
    "wof:placetype":"venue"
},
  "geometry": {"coordinates":[-79.99234800000001,32.809274],"type":"Point"}
}