{
  "type": "Feature",
  "properties": {
    "addr:full":"502 Travis Ave Saluda SC 29138",
    "addr:housenumber":"502",
    "addr:postcode":"29138",
    "addr:street":"Travis Ave",
    "iso:country":"US",
    "sg:address":"502 Travis Ave",
    "sg:city":"Saluda",
    "sg:classifiers":[
        {
            "category":"Banks & Credit Unions",
            "subcategory":"Bank",
            "type":"Services"
        }
    ],
    "sg:phone":"+1 864 445 1152",
    "sg:postcode":"29138",
    "sg:province":"SC",
    "sg:tags":[
        "loan",
        "real estate"
    ],
    "wof:name":"Partners Mortgages",
    "wof:placetype":"venue"
},
  "geometry": {"coordinates":[-81.76120899999999,34.010321],"type":"Point"}
}