{
  "type": "Feature",
  "properties": {
    "iso:country":"US",
    "sg:address":"1511 Richland St",
    "sg:city":"Columbia",
    "sg:classifiers":[
        {
            "category":"Professional",
            "subcategory":"Lawyer & Legal Services",
            "type":"Services"
        }
    ],
    "sg:phone":"+1 803 779 4238",
    "sg:postcode":"29201",
    "sg:province":"SC",
    "sg:tags":[
        "attorney"
    ],
    "wof:name":"Lester L Bates Law Offices",
    "wof:placetype":"venue"
},
  "geometry": {"coordinates":[-81.03144,34.012621],"type":"Point"}
}