{
  "type": "Feature",
  "properties": {
    "iso:country":"US",
    "sg:address":"3379 Pine Needles Rd",
    "sg:city":"Florence",
    "sg:classifiers":[
        {
            "category":"Government",
            "subcategory":"Fire Station",
            "type":"Public Place"
        }
    ],
    "sg:phone":"+1 843 665 8857",
    "sg:postcode":"29501",
    "sg:province":"SC",
    "sg:tags":[
        "department"
    ],
    "wof:name":"West Florence Fire Dept",
    "wof:placetype":"venue"
},
  "geometry": {"coordinates":[-79.852923,34.176331],"type":"Point"}
}