{
  "type": "Feature",
  "properties": {
    "iso:country":"US",
    "sg:address":"498 Chapman Loop",
    "sg:city":"Pawleys Island",
    "sg:classifiers":[
        {
            "category":"Professional",
            "subcategory":"Lawyer & Legal Services",
            "type":"Services"
        }
    ],
    "sg:phone":"+1 843 237 7278",
    "sg:postcode":"29585",
    "sg:province":"SC",
    "sg:tags":[
        "attorney"
    ],
    "wof:name":"Joseph Muffolett",
    "wof:placetype":"venue"
},
  "geometry": {"coordinates":[-79.128591,33.489911],"type":"Point"}
}