{
  "type": "Feature",
  "properties": {
    "iso:country":"US",
    "sg:address":"146 W Phillips Rd",
    "sg:city":"Greer",
    "sg:classifiers":[
        {
            "category":"Retail",
            "subcategory":"Repair Shop",
            "type":"Services"
        }
    ],
    "sg:phone":"+1 864 968 1191",
    "sg:postcode":"29650",
    "sg:province":"SC",
    "sg:tags":[
        "related"
    ],
    "wof:name":"Repair Services",
    "wof:placetype":"venue"
},
  "geometry": {"coordinates":[-82.22589499999999,34.872252],"type":"Point"}
}