{
  "type": "Feature",
  "properties": {
    "iso:country":"US",
    "sg:address":"190 S Pine St",
    "sg:city":"Spartanburg",
    "sg:classifiers":[
        {
            "category":"Restaurant",
            "type":"Food & Drink"
        }
    ],
    "sg:phone":"+1 864 585 9461",
    "sg:postcode":"29302",
    "sg:province":"SC",
    "wof:name":"Simon Simple Inc",
    "wof:placetype":"venue"
},
  "geometry": {"coordinates":[-81.920548,34.951848],"type":"Point"}
}