{
  "type": "Feature",
  "properties": {
    "iso:country":"US",
    "sg:address":"2422 Hemingway Hwy",
    "sg:city":"Hemingway",
    "sg:classifiers":[
        {
            "category":"Restaurant",
            "type":"Food & Drink"
        }
    ],
    "sg:phone":"+1 843 558 3629",
    "sg:postcode":"29554",
    "sg:province":"SC",
    "wof:name":"Kenny's Bar B Que",
    "wof:placetype":"venue"
},
  "geometry": {"coordinates":[-79.462583,33.749592],"type":"Point"}
}