{
  "type": "Feature",
  "properties": {
    "iso:country":"US",
    "sg:address":"418 West Blvd",
    "sg:city":"Chesterfield",
    "sg:classifiers":[
        {
            "category":"Wholesale",
            "subcategory":"Home Furnishings",
            "type":"Manufacturing & Wholesale Goods"
        }
    ],
    "sg:phone":"+1 843 623 5161",
    "sg:postcode":"29709",
    "sg:province":"SC",
    "wof:name":"Home Decorations",
    "wof:placetype":"venue"
},
  "geometry": {"coordinates":[-80.092117,34.734449],"type":"Point"}
}