{
  "type": "Feature",
  "properties": {
    "iso:country":"US",
    "sg:address":"317 Memorial Ave S",
    "sg:city":"Allendale",
    "sg:classifiers":[
        {
            "category":"Social Services",
            "subcategory":"Child Care",
            "type":"Services"
        }
    ],
    "sg:phone":"+1 803 584 4277",
    "sg:postcode":"29810",
    "sg:province":"SC",
    "wof:name":"Happyland Infant Care Ctr",
    "wof:placetype":"venue"
},
  "geometry": {"coordinates":[-81.310578,33.007858],"type":"Point"}
}