{
  "type": "Feature",
  "properties": {
    "iso:country":"US",
    "sg:address":"1937 Brushy Creek Rd",
    "sg:city":"Easley",
    "sg:classifiers":[
        {
            "category":"Building & Trades",
            "subcategory":"Construction",
            "type":"Services"
        }
    ],
    "sg:phone":"+1 864 859 6002",
    "sg:postcode":"29642",
    "sg:province":"SC",
    "sg:tags":[
        "concrete",
        "contractor"
    ],
    "wof:name":"Daniel K Day Concrete Inc",
    "wof:placetype":"venue"
},
  "geometry": {"coordinates":[-82.553985,34.785656],"type":"Point"}
}