{
  "type": "Feature",
  "properties": {
    "addr:full":"1376 Cleveland St Greenville SC 29607",
    "addr:housenumber":"1376",
    "addr:postcode":"29607",
    "addr:street":"Cleveland St",
    "iso:country":"US",
    "sg:address":"1376 Cleveland St",
    "sg:city":"Greenville",
    "sg:classifiers":[
        {
            "category":"Health Services",
            "subcategory":"Doctor",
            "type":"Services"
        }
    ],
    "sg:phone":"+1 864 250 1500",
    "sg:postcode":"29607",
    "sg:province":"SC",
    "sg:tags":[
        "dentist"
    ],
    "wof:name":"Donald L Herndon DDS",
    "wof:placetype":"venue"
},
  "geometry": {"coordinates":[-82.373108,34.821157],"type":"Point"}
}