{
  "type": "Feature",
  "properties": {
    "iso:country":"US",
    "sg:address":"10 McNeal St",
    "sg:city":"Jackson",
    "sg:classifiers":[
        {
            "category":"Retail",
            "subcategory":"Repair Shop",
            "type":"Services"
        }
    ],
    "sg:phone":"+1 803 827 3782",
    "sg:postcode":"29831",
    "sg:province":"SC",
    "sg:tags":[
        "lock",
        "locksmith"
    ],
    "wof:name":"Marc's Lock & Key",
    "wof:placetype":"venue"
},
  "geometry": {"coordinates":[-81.868746,33.38726],"type":"Point"}
}