{
  "type": "Feature",
  "properties": {
    "iso:country":"US",
    "sg:address":"1242 Whispering Pine Rd",
    "sg:city":"Ridge Spring",
    "sg:classifiers":[
        {
            "category":"Farming",
            "subcategory":"Farm",
            "type":"Manufacturing & Wholesale Goods"
        }
    ],
    "sg:phone":"+1 803 685 7163",
    "sg:postcode":"29129",
    "sg:province":"SC",
    "sg:tags":[
        "crop",
        "general"
    ],
    "wof:name":"W Satcher",
    "wof:placetype":"venue"
},
  "geometry": {"coordinates":[-81.66066499999999,33.78256],"type":"Point"}
}