{
  "type": "Feature",
  "properties": {
    "iso:country":"US",
    "sg:address":"409 Simpkins St",
    "sg:city":"Edgefield",
    "sg:classifiers":[
        {
            "category":"Health Services",
            "subcategory":"Hospital",
            "type":"Services"
        }
    ],
    "sg:phone":"+1 803 637 5788",
    "sg:postcode":"29824",
    "sg:province":"SC",
    "sg:tags":[
        "mental"
    ],
    "wof:name":"Mental Health Svc-Edgefield",
    "wof:placetype":"venue"
},
  "geometry": {"coordinates":[-81.922814,33.7902],"type":"Point"}
}