{
  "type": "Feature",
  "properties": {
    "iso:country":"US",
    "sg:address":"945 Turner Rd",
    "sg:city":"Jackson",
    "sg:classifiers":[
        {
            "category":"Farming",
            "subcategory":"Farm",
            "type":"Manufacturing & Wholesale Goods"
        }
    ],
    "sg:phone":"+1 803 471 3902",
    "sg:postcode":"29831",
    "sg:province":"SC",
    "sg:tags":[
        "crop",
        "general"
    ],
    "wof:name":"Fred Chavous",
    "wof:placetype":"venue"
},
  "geometry": {"coordinates":[-81.776879,33.354712],"type":"Point"}
}