{
  "type": "Feature",
  "properties": {
    "iso:country":"US",
    "sg:address":"2818 Oak St",
    "sg:city":"Conway",
    "sg:classifiers":[
        {
            "category":"Organizations",
            "subcategory":"Religious Organization",
            "type":"Services"
        }
    ],
    "sg:phone":"+1 843 365 2727",
    "sg:postcode":"29526",
    "sg:province":"SC",
    "sg:tags":[
        "church"
    ],
    "wof:name":"Greater St James AME Chr",
    "wof:placetype":"venue"
},
  "geometry": {"coordinates":[-79.07140099999999,33.878],"type":"Point"}
}