{
  "type": "Feature",
  "properties": {
    "iso:country":"US",
    "sg:address":"7400 Wilson Blvd",
    "sg:city":"Columbia",
    "sg:classifiers":[
        {
            "category":"Restaurant",
            "type":"Food & Drink"
        }
    ],
    "sg:menulink":"http://www.allmenus.com/sc/columbia/201301-mcdonalds/menu/",
    "sg:postcode":"29203",
    "sg:province":"SC",
    "sg:tags":[
        "burger",
        "american"
    ],
    "wof:name":"McDonald's",
    "wof:placetype":"venue"
},
  "geometry": {"coordinates":[-80.998824,34.074933],"type":"Point"}
}