{
  "type": "Feature",
  "properties": {
    "iso:country":"US",
    "sg:address":"1 Godfrey Pl",
    "sg:city":"Bluffton",
    "sg:classifiers":[
        {
            "category":"Banks & Credit Unions",
            "subcategory":"Bank",
            "type":"Services"
        }
    ],
    "sg:phone":"+1 843 815 3880",
    "sg:postcode":"29910",
    "sg:province":"SC",
    "sg:tags":[
        "cashing",
        "check"
    ],
    "wof:name":"Local Cash Advance South",
    "wof:placetype":"venue"
},
  "geometry": {"coordinates":[-80.856123,32.251339],"type":"Point"}
}