{
  "type": "Feature",
  "properties": {
    "addr:full":"47 Tide Watch Dr Beaufort SC 29902",
    "addr:housenumber":"47",
    "addr:postcode":"29902",
    "addr:street":"Tide Watch Dr",
    "iso:country":"US",
    "sg:address":"47 Tide Watch Dr",
    "sg:city":"Beaufort",
    "sg:classifiers":[
        {
            "category":"Food & Beverages",
            "subcategory":"Specialty",
            "type":"Retail Goods"
        }
    ],
    "sg:phone":"+1 843 470 9001",
    "sg:postcode":"29902",
    "sg:province":"SC",
    "sg:tags":[
        "health",
        "diet"
    ],
    "wof:name":"Island Wellness Shoppe",
    "wof:placetype":"venue"
},
  "geometry": {"coordinates":[-80.932328,32.297829],"type":"Point"}
}