{
  "type": "Feature",
  "properties": {
    "addr:full":"4509 Savannah Hwy Ravenel SC 29470",
    "addr:housenumber":"4509",
    "addr:postcode":"29470",
    "addr:street":"Savannah Hwy",
    "iso:country":"US",
    "sg:address":"4509 Savannah Hwy",
    "sg:city":"Ravenel",
    "sg:classifiers":[
        {
            "category":"Retail",
            "subcategory":"Auto Repair",
            "type":"Services"
        }
    ],
    "sg:phone":"+1 843 556 1550",
    "sg:postcode":"29470",
    "sg:province":"SC",
    "sg:tags":[
        "body",
        "automobile",
        "painting"
    ],
    "wof:name":"West Ashley Collision",
    "wof:placetype":"venue"
},
  "geometry": {"coordinates":[-80.161767,32.780729],"type":"Point"}
}