{
  "type": "Feature",
  "properties": {
    "iso:country":"US",
    "sg:address":"2305 Timmonsville Hwy",
    "sg:city":"Darlington",
    "sg:classifiers":[
        {
            "category":"Food & Beverages",
            "subcategory":"Groceries & Convenience Stores",
            "type":"Retail Goods"
        }
    ],
    "sg:phone":"+1 843 398 0027",
    "sg:postcode":"29501",
    "sg:province":"SC",
    "sg:tags":[
        "grocer"
    ],
    "wof:name":"Isgett's Grocery",
    "wof:placetype":"venue"
},
  "geometry": {"coordinates":[-79.89359899999999,34.231065],"type":"Point"}
}