{
  "type": "Feature",
  "properties": {
    "iso:country":"US",
    "sg:address":"120 Hospital Dr W",
    "sg:city":"West Columbia",
    "sg:classifiers":[
        {
            "category":"Health Services",
            "subcategory":"Doctor",
            "type":"Services"
        }
    ],
    "sg:phone":"+1 803 739 6500",
    "sg:postcode":"29169",
    "sg:province":"SC",
    "sg:tags":[
        "cardiologist"
    ],
    "wof:name":"Baugh J Kevin MD Facc",
    "wof:placetype":"venue"
},
  "geometry": {"coordinates":[-81.116106,34.007376],"type":"Point"}
}