{
  "type": "Feature",
  "properties": {
    "iso:country":"US",
    "sg:address":"805 Ingram St",
    "sg:city":"Florence",
    "sg:classifiers":[
        {
            "category":"Building & Trades",
            "subcategory":"Construction",
            "type":"Services"
        }
    ],
    "sg:phone":"+1 843 673 9473",
    "sg:postcode":"29501",
    "sg:province":"SC",
    "sg:tags":[
        "house"
    ],
    "wof:name":"Monique Builders",
    "wof:placetype":"venue"
},
  "geometry": {"coordinates":[-79.781482,34.206657],"type":"Point"}
}