{
  "type": "Feature",
  "properties": {
    "iso:country":"US",
    "sg:address":"65 Persimmon Ct",
    "sg:city":"Johns Island",
    "sg:classifiers":[
        {
            "category":"Professional",
            "subcategory":"Management & Consulting",
            "type":"Services"
        }
    ],
    "sg:phone":"+1 843 768 0420",
    "sg:postcode":"29455",
    "sg:province":"SC",
    "sg:tags":[
        "consultant",
        "energy",
        "conservation"
    ],
    "wof:name":"Garrison Resources",
    "wof:placetype":"venue"
},
  "geometry": {"coordinates":[-80.064645,32.618801],"type":"Point"}
}