{
  "type": "Feature",
  "properties": {
    "addr:full":"1112 Hummingbird Dr West Columbia SC 29169",
    "addr:housenumber":"1112",
    "addr:postcode":"29169",
    "addr:street":"Hummingbird Dr",
    "iso:country":"US",
    "sg:address":"1112 Hummingbird Dr",
    "sg:city":"West Columbia",
    "sg:classifiers":[
        {
            "category":"Social Services",
            "subcategory":"Child Care",
            "type":"Services"
        }
    ],
    "sg:phone":"+1 803 794 6766",
    "sg:postcode":"29169",
    "sg:province":"SC",
    "sg:tags":[
        "day"
    ],
    "wof:name":"Providence Presbyterian Church",
    "wof:placetype":"venue"
},
  "geometry": {"coordinates":[-81.094398,34.000999],"type":"Point"}
}