{
  "type": "Feature",
  "properties": {
    "iso:country":"US",
    "sg:address":"536 E Pine Logging Rd",
    "sg:city":"Aiken",
    "sg:classifiers":[
        {
            "category":"Retail",
            "subcategory":"Auto Repair",
            "type":"Services"
        }
    ],
    "sg:phone":"+1 803 649 1341",
    "sg:postcode":"29803",
    "sg:province":"SC",
    "sg:tags":[
        "general",
        "supply"
    ],
    "wof:name":"Polk Tire",
    "wof:placetype":"venue"
},
  "geometry": {"coordinates":[-81.705934,33.529099],"type":"Point"}
}