{
  "type": "Feature",
  "properties": {
    "iso:country":"US",
    "sg:address":"2714 Dawson Dr",
    "sg:city":"Chester",
    "sg:classifiers":[
        {
            "category":"Government",
            "subcategory":"Office",
            "type":"Public Place"
        }
    ],
    "sg:phone":"+1 803 385 6341",
    "sg:postcode":"29706",
    "sg:province":"SC",
    "wof:name":"Chester County Animal Shelter",
    "wof:placetype":"venue"
},
  "geometry": {"coordinates":[-81.23293,34.707707],"type":"Point"}
}