{
  "type": "Feature",
  "properties": {
    "iso:country":"US",
    "sg:address":"37 Castle Rock Rd",
    "sg:city":"Beaufort",
    "sg:classifiers":[
        {
            "category":"Organizations",
            "subcategory":"Non-profit Organization",
            "type":"Services"
        }
    ],
    "sg:phone":"+1 843 524 8760",
    "sg:postcode":"29906",
    "sg:province":"SC",
    "wof:name":"Veterans Of Foreign Wars",
    "wof:placetype":"venue"
},
  "geometry": {"coordinates":[-80.75268,32.419301],"type":"Point"}
}