{
  "type": "Feature",
  "properties": {
    "iso:country":"US",
    "sg:address":"500 U C C I Way",
    "sg:city":"Spartanburg",
    "sg:classifiers":[
        {
            "category":"Wholesale",
            "subcategory":"Scrap",
            "type":"Manufacturing & Wholesale Goods"
        }
    ],
    "sg:phone":"+1 864 578 0100",
    "sg:postcode":"29303",
    "sg:province":"SC",
    "sg:tags":[
        "textile",
        "waste"
    ],
    "wof:name":"Allied Textiles",
    "wof:placetype":"venue"
},
  "geometry": {"coordinates":[-82.028861,35.002769],"type":"Point"}
}