{
  "type": "Feature",
  "properties": {
    "addr:full":"250 Blythewood Rd Blythewood SC 29016",
    "addr:housenumber":"250",
    "addr:postcode":"29016",
    "addr:street":"Blythewood Rd",
    "iso:country":"US",
    "sg:address":"250 Blythewood Rd",
    "sg:city":"Blythewood",
    "sg:classifiers":[
        {
            "category":"Restaurant",
            "type":"Food & Drink"
        }
    ],
    "sg:menulink":"http://www.allmenus.com/sc/blythewood/201278-mcdonalds/menu/",
    "sg:postcode":"29016",
    "sg:province":"SC",
    "sg:tags":[
        "burger",
        "american"
    ],
    "wof:name":"McDonald's",
    "wof:placetype":"venue"
},
  "geometry": {"coordinates":[-80.981279,34.21445],"type":"Point"}
}