{
  "type": "Feature",
  "properties": {
    "addr:full":"605 Augusta Rd Edgefield SC 29824",
    "addr:housenumber":"605",
    "addr:postcode":"29824",
    "addr:street":"Augusta Rd",
    "iso:country":"US",
    "sg:address":"605 Augusta Rd",
    "sg:city":"Edgefield",
    "sg:classifiers":[
        {
            "category":"Wholesale",
            "subcategory":"Auto Parts",
            "type":"Manufacturing & Wholesale Goods"
        }
    ],
    "sg:phone":"+1 803 637 5331",
    "sg:postcode":"29824",
    "sg:province":"SC",
    "sg:tags":[
        "supply"
    ],
    "wof:name":"NAPA Auto Parts",
    "wof:placetype":"venue"
},
  "geometry": {"coordinates":[-81.897764,33.763879],"type":"Point"}
}