{
  "type": "Feature",
  "properties": {
    "iso:country":"US",
    "sg:address":"133 Sunset Dr",
    "sg:city":"Greenville",
    "sg:classifiers":[
        {
            "category":"Retail",
            "subcategory":"Animal Services",
            "type":"Services"
        }
    ],
    "sg:phone":"+1 864 242 6942",
    "sg:postcode":"29605",
    "sg:province":"SC",
    "wof:name":"Whiskers & Paws",
    "wof:placetype":"venue"
},
  "geometry": {"coordinates":[-82.395645,34.813876],"type":"Point"}
}