{
  "type": "Feature",
  "properties": {
    "iso:country":"US",
    "sg:address":"4254 Villas Dr",
    "sg:city":"Longs",
    "sg:classifiers":[
        {
            "category":"Building & Trades",
            "subcategory":"Construction",
            "type":"Services"
        }
    ],
    "sg:phone":"+1 843 390 0665",
    "sg:postcode":"29566",
    "sg:province":"SC",
    "sg:tags":[
        "company"
    ],
    "wof:name":"Encompass Electrical Tech",
    "wof:placetype":"venue"
},
  "geometry": {"coordinates":[-78.649445,33.865871],"type":"Point"}
}