{
  "type": "Feature",
  "properties": {
    "iso:country":"US",
    "sg:address":"2388 Air Park Rd",
    "sg:city":"North Charleston",
    "sg:classifiers":[
        {
            "category":"Building & Trades",
            "subcategory":"Construction",
            "type":"Services"
        }
    ],
    "sg:phone":"+1 843 554 8408",
    "sg:postcode":"29406",
    "sg:province":"SC",
    "sg:tags":[
        "demolition",
        "contractor"
    ],
    "wof:name":"B & B Demolition Specialists",
    "wof:placetype":"venue"
},
  "geometry": {"coordinates":[-80.019924,32.894675],"type":"Point"}
}