{
  "type": "Feature",
  "properties": {
    "iso:country":"US",
    "sg:address":"1145 W Greene St",
    "sg:city":"Cheraw",
    "sg:classifiers":[
        {
            "category":"Personal",
            "subcategory":"Beauty Salon",
            "type":"Services"
        }
    ],
    "sg:phone":"+1 843 921 0610",
    "sg:postcode":"29520",
    "sg:province":"SC",
    "sg:tags":[
        "manicuring"
    ],
    "wof:name":"Nail Chic",
    "wof:placetype":"venue"
},
  "geometry": {"coordinates":[-79.90956799999999,34.693635],"type":"Point"}
}