{
  "type": "Feature",
  "properties": {
    "iso:country":"US",
    "sg:address":"92 Maiden Bush St",
    "sg:city":"Georgetown",
    "sg:classifiers":[
        {
            "category":"Building & Trades",
            "subcategory":"Plumbing",
            "type":"Services"
        }
    ],
    "sg:phone":"+1 843 546 6645",
    "sg:postcode":"29440",
    "sg:province":"SC",
    "sg:tags":[
        "conditioning",
        "air",
        "heating",
        "contractor"
    ],
    "wof:name":"Lesane Heating & Air",
    "wof:placetype":"venue"
},
  "geometry": {"coordinates":[-79.333777,33.525959],"type":"Point"}
}