{
  "type": "Feature",
  "properties": {
    "addr:full":"3108 Palomino Dr Beaufort SC 29906",
    "addr:housenumber":"3108",
    "addr:postcode":"29906",
    "addr:street":"Palomino Dr",
    "iso:country":"US",
    "sg:address":"3108 Palomino Dr",
    "sg:city":"Beaufort",
    "sg:classifiers":[
        {
            "category":"Autos & Motor Vehicles",
            "subcategory":"Auto Supplies",
            "type":"Retail Goods"
        }
    ],
    "sg:phone":"+1 843 522 8899",
    "sg:postcode":"29906",
    "sg:province":"SC",
    "wof:name":"Auto Care Center",
    "wof:placetype":"venue"
},
  "geometry": {"coordinates":[-80.734437,32.406858],"type":"Point"}
}