{
  "type": "Feature",
  "properties": {
    "iso:country":"US",
    "sg:address":"223 W Main St",
    "sg:city":"Brevard",
    "sg:classifiers":[
        {
            "category":"Government",
            "subcategory":"Office",
            "type":"Public Place"
        }
    ],
    "sg:phone":"+1 828 877 3009",
    "sg:postcode":"28712",
    "sg:province":"SC",
    "sg:tags":[
        "county"
    ],
    "wof:name":"Transylvania County Republican",
    "wof:placetype":"venue"
},
  "geometry": {"coordinates":[-82.736749,35.234929],"type":"Point"}
}