{
  "type": "Feature",
  "properties": {
    "addr:full":"1354 Cannon Rd Myrtle Beach SC 29577",
    "addr:housenumber":"1354",
    "addr:postcode":"29577",
    "addr:street":"Cannon Rd",
    "iso:country":"US",
    "sg:address":"1354 Cannon Rd",
    "sg:city":"Myrtle Beach",
    "sg:classifiers":[
        {
            "category":"Taxi",
            "type":"Transportation"
        }
    ],
    "sg:phone":"+1 843 445 2999",
    "sg:postcode":"29577",
    "sg:province":"SC",
    "sg:tags":[
        "taxicab"
    ],
    "wof:name":"Anytime Cab",
    "wof:placetype":"venue"
},
  "geometry": {"coordinates":[-78.901518,33.697246],"type":"Point"}
}