{
  "type": "Feature",
  "properties": {
    "addr:full":"7695 State Hwy 64 Barnwell SC 29812",
    "addr:housenumber":"7695",
    "addr:postcode":"29812",
    "addr:street":"State Hwy 64",
    "iso:country":"US",
    "sg:address":"7695 State Hwy 64",
    "sg:city":"Barnwell",
    "sg:classifiers":[
        {
            "category":"Manufacturing",
            "subcategory":"Lumber",
            "type":"Manufacturing & Wholesale Goods"
        }
    ],
    "sg:phone":"+1 803 259 3373",
    "sg:postcode":"29812",
    "sg:province":"SC",
    "sg:tags":[
        "government"
    ],
    "wof:name":"Forestry Dept",
    "wof:placetype":"venue"
},
  "geometry": {"coordinates":[-81.333838,33.218973],"type":"Point"}
}