{
  "type": "Feature",
  "properties": {
    "addr:full":"1008 Country Ln N Elgin SC 29045",
    "addr:housenumber":"1008",
    "addr:postcode":"29045",
    "addr:street":"Country Ln N",
    "iso:country":"US",
    "sg:address":"1008 Country Ln N",
    "sg:city":"Elgin",
    "sg:classifiers":[
        {
            "category":"Building & Trades",
            "subcategory":"Landscaping Services",
            "type":"Services"
        }
    ],
    "sg:phone":"+1 803 438 9818",
    "sg:postcode":"29045",
    "sg:province":"SC",
    "wof:name":"Deans Yard Service",
    "wof:placetype":"venue"
},
  "geometry": {"coordinates":[-80.807903,34.196245],"type":"Point"}
}