{
  "type": "Feature",
  "properties": {
    "iso:country":"US",
    "sg:address":"2600 S Irby St",
    "sg:city":"Florence",
    "sg:classifiers":[
        {
            "category":"Food & Beverages",
            "subcategory":"Groceries & Convenience Stores",
            "type":"Retail Goods"
        }
    ],
    "sg:phone":"+1 843 678 9555",
    "sg:postcode":"29505",
    "sg:province":"SC",
    "sg:tags":[
        "supermarket",
        "chain"
    ],
    "wof:name":"Food Lion Store 618",
    "wof:placetype":"venue"
},
  "geometry": {"coordinates":[-79.777044,34.12697],"type":"Point"}
}