{
  "type": "Feature",
  "properties": {
    "addr:full":"114 Ridge St Georgetown SC 29440",
    "addr:housenumber":"114",
    "addr:postcode":"29440",
    "addr:street":"Ridge St",
    "iso:country":"US",
    "sg:address":"114 Ridge St",
    "sg:city":"Georgetown",
    "sg:classifiers":[
        {
            "category":"Home & Garden",
            "subcategory":"Building Materials",
            "type":"Retail Goods"
        }
    ],
    "sg:phone":"+1 843 546 5121",
    "sg:postcode":"29440",
    "sg:province":"SC",
    "sg:tags":[
        "mixed",
        "concrete"
    ],
    "wof:name":"S & W Ready Mixed Concrete",
    "wof:placetype":"venue"
},
  "geometry": {"coordinates":[-79.310176,33.367206],"type":"Point"}
}