{
  "type": "Feature",
  "properties": {
    "addr:full":"4116 Little River Rd Myrtle Beach SC 29577",
    "addr:housenumber":"4116",
    "addr:postcode":"29577",
    "addr:street":"Little River Rd",
    "iso:country":"US",
    "sg:address":"4116 Little River Rd",
    "sg:city":"Myrtle Beach",
    "sg:classifiers":[
        {
            "category":"Local Transit",
            "type":"Transportation"
        }
    ],
    "sg:phone":"+1 843 626 9265",
    "sg:postcode":"29577",
    "sg:province":"SC",
    "sg:tags":[
        "limousine"
    ],
    "wof:name":"Art's Limousine Inc",
    "wof:placetype":"venue"
},
  "geometry": {"coordinates":[-78.85672099999999,33.720906],"type":"Point"}
}