{
  "type": "Feature",
  "properties": {
    "iso:country":"US",
    "sg:address":"5461 Woodbine Ave",
    "sg:city":"Charleston",
    "sg:classifiers":[
        {
            "category":"Real Estate",
            "subcategory":"Real Estate Operator",
            "type":"Services"
        }
    ],
    "sg:phone":"+1 843 553 8377",
    "sg:postcode":"29406",
    "sg:province":"SC",
    "sg:tags":[
        "mobile",
        "home",
        "site"
    ],
    "wof:name":"Louise Gordon",
    "wof:placetype":"venue"
},
  "geometry": {"coordinates":[-80.015848,32.893292],"type":"Point"}
}