{
  "type": "Feature",
  "properties": {
    "addr:full":"866 York St NE Aiken SC 29801",
    "addr:housenumber":"866",
    "addr:postcode":"29801",
    "addr:street":"York St Ne",
    "iso:country":"US",
    "sg:address":"866 York St NE",
    "sg:city":"Aiken",
    "sg:classifiers":[
        {
            "category":"Retail",
            "subcategory":"Auto Repair",
            "type":"Services"
        }
    ],
    "sg:phone":"+1 803 642 6801",
    "sg:postcode":"29801",
    "sg:province":"SC",
    "sg:tags":[
        "body",
        "automobile",
        "painting"
    ],
    "wof:name":"Aiken Towing & Transport",
    "wof:placetype":"venue"
},
  "geometry": {"coordinates":[-81.706019,33.572428],"type":"Point"}
}