{
  "type": "Feature",
  "properties": {
    "iso:country":"US",
    "sg:address":"132 Vinge Rd",
    "sg:city":"Newberry",
    "sg:classifiers":[
        {
            "category":"Professional",
            "type":"Services"
        }
    ],
    "sg:phone":"+1 803 276 5837",
    "sg:postcode":"29127",
    "sg:province":"SC",
    "sg:tags":[
        "establishment"
    ],
    "wof:name":"Proseeker",
    "wof:placetype":"venue"
},
  "geometry": {"coordinates":[-81.495248,34.080389],"type":"Point"}
}