{
  "type": "Feature",
  "properties": {
    "iso:country":"US",
    "sg:address":"9 Hunter Rd",
    "sg:city":"Hilton Head Isle",
    "sg:classifiers":[
        {
            "category":"Building & Trades",
            "subcategory":"Construction",
            "type":"Services"
        },
        {
            "category":"Retail",
            "subcategory":"Auto Repair",
            "type":"Services"
        }
    ],
    "sg:phone":"+1 843 681 5446",
    "sg:postcode":"29926",
    "sg:province":"SC",
    "sg:tags":[
        "filming",
        "coating",
        "tinting",
        "glass",
        "window",
        "security"
    ],
    "wof:name":"Coastal Applied Systems LLC",
    "wof:placetype":"venue"
},
  "geometry": {"coordinates":[-80.702353,32.226971],"type":"Point"}
}