{
  "type": "Feature",
  "properties": {
    "iso:country":"US",
    "sg:address":"1539 Meeting Street Rd",
    "sg:city":"North Charleston",
    "sg:classifiers":[
        {
            "category":"Real Estate",
            "subcategory":"Developer",
            "type":"Services"
        }
    ],
    "sg:phone":"+1 843 723 4447",
    "sg:postcode":"29405",
    "sg:province":"SC",
    "sg:tags":[
        "specializing",
        "mu",
        "remodeling",
        "contractor"
    ],
    "wof:name":"Wilson & Associates Developers",
    "wof:placetype":"venue"
},
  "geometry": {"coordinates":[-79.950824,32.81897],"type":"Point"}
}