{
  "type": "Feature",
  "properties": {
    "iso:country":"US",
    "sg:address":"170 Elgin Rd",
    "sg:city":"Elgin",
    "sg:classifiers":[
        {
            "category":"Real Estate",
            "subcategory":"Real Estate Agent",
            "type":"Services"
        }
    ],
    "sg:phone":"+1 803 786 1121",
    "sg:postcode":"29045",
    "sg:province":"SC",
    "wof:name":"Just Appraisal Services LLC",
    "wof:placetype":"venue"
},
  "geometry": {"coordinates":[-80.85109300000001,34.228897],"type":"Point"}
}