{
  "type": "Feature",
  "properties": {
    "iso:country":"US",
    "sg:address":"463 Calhoun Ave",
    "sg:city":"Greenwood",
    "sg:classifiers":[
        {
            "category":"Health Services",
            "subcategory":"Chiropractor",
            "type":"Services"
        }
    ],
    "sg:phone":"+1 864 229 3017",
    "sg:postcode":"29649",
    "sg:province":"SC",
    "wof:name":"Ouzts Tinney Chiropractic",
    "wof:placetype":"venue"
},
  "geometry": {"coordinates":[-82.169876,34.197543],"type":"Point"}
}