{
  "type": "Feature",
  "properties": {
    "iso:country":"US",
    "sg:address":"608 N Hwy 52",
    "sg:city":"Moncks Corner",
    "sg:classifiers":[
        {
            "category":"Personal",
            "subcategory":"Beauty Salon",
            "type":"Services"
        }
    ],
    "sg:phone":"+1 843 899 5449",
    "sg:postcode":"29461",
    "sg:province":"SC",
    "sg:tags":[
        "manicuring"
    ],
    "wof:name":"Tony's Nails",
    "wof:placetype":"venue"
},
  "geometry": {"coordinates":[-79.98190099999999,33.209527],"type":"Point"}
}