{
  "type": "Feature",
  "properties": {
    "iso:country":"US",
    "sg:address":"115 Shamrock Ct",
    "sg:city":"Fort Mill",
    "sg:classifiers":[
        {
            "category":"Shopping",
            "subcategory":"Crafts & Fabrics",
            "type":"Retail Goods"
        }
    ],
    "sg:phone":"+1 803 547 6936",
    "sg:postcode":"29715",
    "sg:province":"SC",
    "sg:tags":[
        "sewing"
    ],
    "wof:name":"So Zebras Do Sew LLC",
    "wof:placetype":"venue"
},
  "geometry": {"coordinates":[-80.947603,35.004201],"type":"Point"}
}