{
  "type": "Feature",
  "properties": {
    "addr:full":"1109 Wappoo Rd Charleston SC 29407",
    "addr:housenumber":"1109",
    "addr:postcode":"29407",
    "addr:street":"Wappoo Rd",
    "iso:country":"US",
    "sg:address":"1109 Wappoo Rd",
    "sg:city":"Charleston",
    "sg:classifiers":[
        {
            "category":"Building & Trades",
            "subcategory":"Construction",
            "type":"Services"
        }
    ],
    "sg:phone":"+1 843 556 1220",
    "sg:postcode":"29407",
    "sg:province":"SC",
    "sg:tags":[
        "grading",
        "contractor"
    ],
    "wof:name":"Davis & Doscher Construction",
    "wof:placetype":"venue"
},
  "geometry": {"coordinates":[-80.01552599999999,32.798428],"type":"Point"}
}