{
  "type": "Feature",
  "properties": {
    "iso:country":"US",
    "sg:address":"319 Effingham Hwy",
    "sg:city":"Effingham",
    "sg:classifiers":[
        {
            "category":"Shopping",
            "subcategory":"Used Merchandise",
            "type":"Retail Goods"
        }
    ],
    "sg:phone":"+1 843 413 9881",
    "sg:postcode":"29541",
    "sg:province":"SC",
    "wof:name":"Effingham Supply & Antiques",
    "wof:placetype":"venue"
},
  "geometry": {"coordinates":[-79.75497,34.057732],"type":"Point"}
}