{
  "type": "Feature",
  "properties": {
    "addr:full":"1013 Old Hwy 52 Moncks Corner SC 29461",
    "addr:housenumber":"1013",
    "addr:postcode":"29461",
    "addr:street":"Old Hwy 52",
    "iso:country":"US",
    "sg:address":"1013 Old Hwy 52",
    "sg:city":"Moncks Corner",
    "sg:classifiers":[
        {
            "category":"Shopping",
            "subcategory":"Clothing, Apparel, & Fashions",
            "type":"Retail Goods"
        }
    ],
    "sg:phone":"+1 843 899 7681",
    "sg:postcode":"29461",
    "sg:province":"SC",
    "sg:tags":[
        "infant",
        "wear"
    ],
    "wof:name":"R & D Kids Fashion Intl",
    "wof:placetype":"venue"
},
  "geometry": {"coordinates":[-80.00010899999999,33.186712],"type":"Point"}
}