{
  "type": "Feature",
  "properties": {
    "iso:country":"US",
    "sg:address":"402 E Martintown Rd",
    "sg:city":"North Augusta",
    "sg:classifiers":[
        {
            "category":"Restaurant",
            "type":"Food & Drink"
        }
    ],
    "sg:menulink":"http://www.allmenus.com/sc/north-augusta/215285-burger-king/menu/",
    "sg:phone":"+1 803 278 2177",
    "sg:postcode":"29841",
    "sg:province":"SC",
    "sg:tags":[
        "burger",
        "american"
    ],
    "wof:name":"Burger King",
    "wof:placetype":"venue"
},
  "geometry": {"coordinates":[-81.95868,33.495893],"type":"Point"}
}