{
  "type": "Feature",
  "properties": {
    "addr:full":"319 Turtle Pond Rd Summerville SC 29483",
    "addr:housenumber":"319",
    "addr:postcode":"29483",
    "addr:street":"Turtle Pond Rd",
    "iso:country":"US",
    "sg:address":"319 Turtle Pond Rd",
    "sg:city":"Summerville",
    "sg:classifiers":[
        {
            "category":"Home & Garden",
            "subcategory":"Garden Supply",
            "type":"Retail Goods"
        }
    ],
    "sg:phone":"+1 843 871 8071",
    "sg:postcode":"29483",
    "sg:province":"SC",
    "wof:name":"Dirt Dobber Nursery",
    "wof:placetype":"venue"
},
  "geometry": {"coordinates":[-80.134702,33.042387],"type":"Point"}
}