{
  "type": "Feature",
  "properties": {
    "addr:full":"700 Haywood Rd Greenville SC 29607",
    "addr:housenumber":"700",
    "addr:postcode":"29607",
    "addr:street":"Haywood Rd",
    "iso:country":"US",
    "sg:address":"700 Haywood Rd",
    "sg:city":"Greenville",
    "sg:classifiers":[
        {
            "category":"Utilities",
            "subcategory":"Mobile Phone",
            "type":"Services"
        }
    ],
    "sg:phone":"+1 864 676 0000",
    "sg:postcode":"29607",
    "sg:province":"SC",
    "sg:tags":[
        "telephone",
        "cellular"
    ],
    "wof:name":"Nextel Communications Inc",
    "wof:placetype":"venue"
},
  "geometry": {"coordinates":[-82.336084,34.851595],"type":"Point"}
}