{
  "type": "Feature",
  "properties": {
    "addr:full":"531 Oxford St Sumter SC 29150",
    "addr:housenumber":"531",
    "addr:postcode":"29150",
    "addr:street":"Oxford St",
    "iso:country":"US",
    "sg:address":"531 Oxford St",
    "sg:city":"Sumter",
    "sg:classifiers":[
        {
            "category":"Real Estate",
            "subcategory":"Real Estate Agent",
            "type":"Services"
        }
    ],
    "sg:phone":"+1 803 774 0344",
    "sg:postcode":"29150",
    "sg:province":"SC",
    "wof:name":"Gulledge Realty LLC",
    "wof:placetype":"venue"
},
  "geometry": {"coordinates":[-80.368059,33.934544],"type":"Point"}
}