{
  "type": "Feature",
  "properties": {
    "iso:country":"US",
    "sg:address":"2705 Hanover Ln",
    "sg:city":"Beaufort",
    "sg:classifiers":[
        {
            "category":"Real Estate",
            "subcategory":"Real Estate Operator",
            "type":"Services"
        }
    ],
    "sg:phone":"+1 843 525 9154",
    "sg:postcode":"29902",
    "sg:province":"SC",
    "wof:name":"Seagull Villa",
    "wof:placetype":"venue"
},
  "geometry": {"coordinates":[-80.698314,32.39923],"type":"Point"}
}