{
  "type": "Feature",
  "properties": {
    "iso:country":"US",
    "sg:address":"2000 Clemson Rd",
    "sg:city":"Columbia",
    "sg:classifiers":[
        {
            "category":"Building & Trades",
            "subcategory":"Construction",
            "type":"Services"
        }
    ],
    "sg:phone":"+1 803 513 3005",
    "sg:postcode":"29229",
    "sg:province":"SC",
    "sg:tags":[
        "home",
        "improvement"
    ],
    "wof:name":"Christian Brothers Constr",
    "wof:placetype":"venue"
},
  "geometry": {"coordinates":[-80.91172899999999,34.14004],"type":"Point"}
}