{
  "type": "Feature",
  "properties": {
    "iso:country":"US",
    "sg:address":"11 Barkingham Ln",
    "sg:city":"Greenville",
    "sg:classifiers":[
        {
            "category":"Manufacturing",
            "subcategory":"Printing",
            "type":"Manufacturing & Wholesale Goods"
        }
    ],
    "sg:phone":"+1 864 297 5639",
    "sg:postcode":"29607",
    "sg:province":"SC",
    "sg:tags":[
        "commercial"
    ],
    "wof:name":"Bradham Printing",
    "wof:placetype":"venue"
},
  "geometry": {"coordinates":[-82.270175,34.815986],"type":"Point"}
}