{
  "type": "Feature",
  "properties": {
    "iso:country":"US",
    "sg:address":"1635 Cosgrove Ave",
    "sg:city":"Charleston",
    "sg:classifiers":[
        {
            "category":"Social Services",
            "type":"Services"
        }
    ],
    "sg:phone":"+1 843 747 8146",
    "sg:postcode":"29405",
    "sg:province":"SC",
    "sg:tags":[
        "food",
        "banks"
    ],
    "sg:website":"www.lowcountryfoodbank.org",
    "wof:name":"Low Country Food Bank Inc",
    "wof:placetype":"venue"
},
  "geometry": {"coordinates":[-79.973196,32.859878],"type":"Point"}
}