{
  "type": "Feature",
  "properties": {
    "iso:country":"US",
    "sg:address":"123 Greenfield Dr",
    "sg:city":"Georgetown",
    "sg:classifiers":[
        {
            "category":"Utilities",
            "subcategory":"Mobile Phone",
            "type":"Services"
        }
    ],
    "sg:phone":"+1 843 545 9434",
    "sg:postcode":"29471",
    "sg:province":"SC",
    "sg:tags":[
        "telephone",
        "cellular"
    ],
    "wof:name":"MBC Wireless Technologies",
    "wof:placetype":"venue"
},
  "geometry": {"coordinates":[-80.625589,33.206511],"type":"Point"}
}