{
  "type": "Feature",
  "properties": {
    "iso:country":"US",
    "sg:address":"2513 W Lucas St",
    "sg:city":"Florence",
    "sg:classifiers":[
        {
            "category":"Wholesale",
            "subcategory":"Plants",
            "type":"Manufacturing & Wholesale Goods"
        },
        {
            "category":"Home & Garden",
            "subcategory":"Garden Supply",
            "type":"Retail Goods"
        }
    ],
    "sg:phone":"+1 843 679 0999",
    "sg:postcode":"29501",
    "sg:province":"SC",
    "sg:tags":[
        "center"
    ],
    "wof:name":"Indigo Marsh Garden & Gift",
    "wof:placetype":"venue"
},
  "geometry": {"coordinates":[-79.815702,34.242508],"type":"Point"}
}