{
  "type": "Feature",
  "properties": {
    "iso:country":"US",
    "sg:address":"704 10th Ave N",
    "sg:city":"Myrtle Beach",
    "sg:classifiers":[
        {
            "category":"Insurance",
            "subcategory":"Hazard Insurance",
            "type":"Services"
        }
    ],
    "sg:phone":"+1 843 626 6575",
    "sg:postcode":"29577",
    "sg:province":"SC",
    "sg:tags":[
        "bond"
    ],
    "wof:name":"Beach Bail Bonds",
    "wof:placetype":"venue"
},
  "geometry": {"coordinates":[-78.884012,33.697945],"type":"Point"}
}