{
  "type": "Feature",
  "properties": {
    "addr:full":"425 Feaster Rd Greenville SC 29615",
    "addr:housenumber":"425",
    "addr:postcode":"29615",
    "addr:street":"Feaster Rd",
    "iso:country":"US",
    "sg:address":"425 Feaster Rd",
    "sg:city":"Greenville",
    "sg:classifiers":[
        {
            "category":"Organizations",
            "subcategory":"Religious Organization",
            "type":"Services"
        }
    ],
    "sg:phone":"+1 864 987 0515",
    "sg:postcode":"29615",
    "sg:province":"SC",
    "sg:tags":[
        "church"
    ],
    "wof:name":"Refreshing Spring Church Intl",
    "wof:placetype":"venue"
},
  "geometry": {"coordinates":[-82.2714,34.833014],"type":"Point"}
}