{
  "type": "Feature",
  "properties": {
    "iso:country":"US",
    "sg:address":"1914 Nation Rd",
    "sg:city":"Hodges",
    "sg:classifiers":[
        {
            "category":"Building & Trades",
            "subcategory":"Construction",
            "type":"Services"
        }
    ],
    "sg:phone":"+1 864 861 9565",
    "sg:postcode":"29653",
    "sg:province":"SC",
    "sg:tags":[
        "bathroom",
        "remodeling"
    ],
    "wof:name":"Pope's Home Improvements",
    "wof:placetype":"venue"
},
  "geometry": {"coordinates":[-82.194581,34.361002],"type":"Point"}
}