{
  "type": "Feature",
  "properties": {
    "iso:country":"US",
    "sg:address":"903 Meadow Ln",
    "sg:city":"Anderson",
    "sg:classifiers":[
        {
            "category":"Real Estate",
            "subcategory":"Real Estate Operator",
            "type":"Services"
        }
    ],
    "sg:phone":"+1 864 226 3008",
    "sg:postcode":"29621",
    "sg:province":"SC",
    "sg:tags":[
        "property",
        "lessor"
    ],
    "wof:name":"Nancy Christopher",
    "wof:placetype":"venue"
},
  "geometry": {"coordinates":[-82.65042099999999,34.541972],"type":"Point"}
}