{
  "type": "Feature",
  "properties": {
    "addr:full":"900 Lake Murray Blvd Irmo SC 29063",
    "addr:housenumber":"900",
    "addr:postcode":"29063",
    "addr:street":"Lake Murray Blvd",
    "iso:country":"US",
    "sg:address":"900 Lake Murray Blvd",
    "sg:city":"Irmo",
    "sg:classifiers":[
        {
            "category":"Health Services",
            "subcategory":"Doctor",
            "type":"Services"
        }
    ],
    "sg:phone":"+1 803 781 9090",
    "sg:postcode":"29063",
    "sg:province":"SC",
    "sg:tags":[
        "dentist"
    ],
    "sg:website":"www.smilecolumbia.com",
    "wof:name":"Smile Columbia",
    "wof:placetype":"venue"
},
  "geometry": {"coordinates":[-81.148487,34.087421],"type":"Point"}
}