{
  "type": "Feature",
  "properties": {
    "iso:country":"US",
    "sg:address":"1035 Dandridge Rd",
    "sg:city":"Walterboro",
    "sg:classifiers":[
        {
            "category":"Organizations",
            "subcategory":"Religious Organization",
            "type":"Services"
        }
    ],
    "sg:phone":"+1 843 538 2576",
    "sg:postcode":"29488",
    "sg:province":"SC",
    "sg:tags":[
        "church"
    ],
    "wof:name":"Church Of Jesus Christ",
    "wof:placetype":"venue"
},
  "geometry": {"coordinates":[-80.681276,32.928446],"type":"Point"}
}