{
  "type": "Feature",
  "properties": {
    "iso:country":"US",
    "sg:address":"12 Greenleaf Ln",
    "sg:city":"Beaufort",
    "sg:classifiers":[
        {
            "category":"Building & Trades",
            "subcategory":"Construction",
            "type":"Services"
        }
    ],
    "sg:phone":"+1 843 846 6083",
    "sg:postcode":"29906",
    "sg:province":"SC",
    "sg:tags":[
        "concrete",
        "contractor"
    ],
    "wof:name":"Free Agent Concrete",
    "wof:placetype":"venue"
},
  "geometry": {"coordinates":[-80.738794,32.49745],"type":"Point"}
}