{
  "type": "Feature",
  "properties": {
    "iso:country":"US",
    "sg:address":"430 Haywood Rd",
    "sg:city":"Greenville",
    "sg:classifiers":[
        {
            "category":"Home & Garden",
            "subcategory":"Furniture",
            "type":"Retail Goods"
        }
    ],
    "sg:phone":"+1 864 627 8255",
    "sg:postcode":"29607",
    "sg:province":"SC",
    "sg:tags":[
        "mattress"
    ],
    "wof:name":"Mattress City",
    "wof:placetype":"venue"
},
  "geometry": {"coordinates":[-82.343437,34.840082],"type":"Point"}
}