{
  "type": "Feature",
  "properties": {
    "iso:country":"US",
    "sg:address":"10125 US Hwy 17 Byp",
    "sg:city":"Murrells Inlet",
    "sg:classifiers":[
        {
            "category":"Food & Beverages",
            "subcategory":"Specialty",
            "type":"Retail Goods"
        }
    ],
    "sg:phone":"+1 843 651 9097",
    "sg:postcode":"29576",
    "sg:province":"SC",
    "sg:tags":[
        "health",
        "diet"
    ],
    "wof:name":"General Nutrition Ctr",
    "wof:placetype":"venue"
},
  "geometry": {"coordinates":[-79.02333299999999,33.595936],"type":"Point"}
}