{
  "type": "Feature",
  "properties": {
    "iso:country":"US",
    "sg:address":"1430 W Market St",
    "sg:city":"Anderson",
    "sg:classifiers":[
        {
            "category":"Retail",
            "subcategory":"Auto Repair",
            "type":"Services"
        }
    ],
    "sg:phone":"+1 864 964 0345",
    "sg:postcode":"29624",
    "sg:province":"SC",
    "sg:tags":[
        "repairing",
        "automobile"
    ],
    "wof:name":"Market Street Garage",
    "wof:placetype":"venue"
},
  "geometry": {"coordinates":[-82.670231,34.500485],"type":"Point"}
}