{
  "type": "Feature",
  "properties": {
    "iso:country":"US",
    "sg:address":"2434 Boundary St",
    "sg:city":"Beaufort",
    "sg:classifiers":[
        {
            "category":"Restaurant",
            "type":"Food & Drink"
        }
    ],
    "sg:menulink":"http://www.allmenus.com/sc/beaufort-port-royal/215351-burger-king/menu/",
    "sg:phone":"+1 843 525 0952",
    "sg:postcode":"29906",
    "sg:province":"SC",
    "sg:tags":[
        "burger",
        "american"
    ],
    "wof:name":"Burger King",
    "wof:placetype":"venue"
},
  "geometry": {"coordinates":[-80.705303,32.440592],"type":"Point"}
}