{
  "type": "Feature",
  "properties": {
    "iso:country":"US",
    "sg:address":"115 E South Broad St",
    "sg:city":"Walhalla",
    "sg:classifiers":[
        {
            "category":"Food & Beverages",
            "subcategory":"Liquor & Beverages",
            "type":"Retail Goods"
        }
    ],
    "sg:phone":"+1 864 638 2062",
    "sg:postcode":"29691",
    "sg:province":"SC",
    "wof:name":"Miss Sandra's Liquors",
    "wof:placetype":"venue"
},
  "geometry": {"coordinates":[-83.06585,34.76376],"type":"Point"}
}