{
  "type": "Feature",
  "properties": {
    "iso:country":"US",
    "sg:address":"2111 N Pleasantburg Dr",
    "sg:city":"Greenville",
    "sg:classifiers":[
        {
            "category":"Banks & Credit Unions",
            "subcategory":"Bank",
            "type":"Services"
        }
    ],
    "sg:phone":"+1 864 233 6158",
    "sg:postcode":"29609",
    "sg:province":"SC",
    "wof:name":"Central Carolina Bank",
    "wof:placetype":"venue"
},
  "geometry": {"coordinates":[-82.375172,34.889608],"type":"Point"}
}