{
  "type": "Feature",
  "properties": {
    "iso:country":"US",
    "sg:address":"107 Pitt St",
    "sg:city":"Mt Pleasant",
    "sg:classifiers":[
        {
            "category":"Banks & Credit Unions",
            "subcategory":"Investment Brokerage",
            "type":"Services"
        },
        {
            "category":"Banks & Credit Unions",
            "subcategory":"Financial Services",
            "type":"Services"
        }
    ],
    "sg:phone":"+1 843 884 6192",
    "sg:postcode":"29464",
    "sg:province":"SC",
    "sg:tags":[
        "consultant",
        "security",
        "planning",
        "closed"
    ],
    "wof:name":"Morris Financial Concepts Inc",
    "wof:placetype":"venue"
},
  "geometry": {"coordinates":[-79.876762,32.787191],"type":"Point"}
}