{
  "type": "Feature",
  "properties": {
    "addr:full":"2351 Longtown Rd E Blythewood SC 29016",
    "addr:housenumber":"2351",
    "addr:postcode":"29016",
    "addr:street":"Longtown Rd E",
    "iso:country":"US",
    "sg:address":"2351 Longtown Rd E",
    "sg:city":"Blythewood",
    "sg:classifiers":[
        {
            "category":"Education",
            "subcategory":"School",
            "type":"Public Place"
        }
    ],
    "sg:phone":"+1 803 691 6850",
    "sg:postcode":"29016",
    "sg:province":"SC",
    "sg:website":"www.richland2.org",
    "wof:name":"Blythewood Middle School",
    "wof:placetype":"venue"
},
  "geometry": {"coordinates":[-80.93001099999999,34.191766],"type":"Point"}
}