{
  "type": "Feature",
  "properties": {
    "iso:country":"US",
    "sg:address":"165 Factory Shops Blvd",
    "sg:city":"Gaffney",
    "sg:classifiers":[
        {
            "category":"Wholesale",
            "subcategory":"Electrical",
            "type":"Manufacturing & Wholesale Goods"
        },
        {
            "category":"Shopping",
            "subcategory":"Computers & Home Electronics",
            "type":"Retail Goods"
        },
        {
            "category":"Communications",
            "type":"Services"
        }
    ],
    "sg:phone":"+1 864 761 0181",
    "sg:postcode":"29341",
    "sg:province":"SC",
    "sg:tags":[
        "sound",
        "television",
        "theater",
        "equipment-wholesale",
        "stereo",
        "system",
        "high",
        "equipment",
        "stereophonic",
        "video",
        "equipment-dealers",
        "radio",
        "fidelity",
        "audio",
        "consumer",
        "store",
        "manufacturer"
    ],
    "sg:website":"http://national.citysearch.com/profile/external/46292497/gaffney_sc/bose.html?publisher=yellowpages&reference_id=1&placement=ypwebsitemip",
    "wof:name":"Bose",
    "wof:placetype":"venue"
},
  "geometry": {"coordinates":[-81.710246,35.082149],"type":"Point"}
}