{
  "type": "Feature",
  "properties": {
    "iso:country":"US",
    "sg:address":"4546 Dorchester Rd",
    "sg:city":"North Charleston",
    "sg:classifiers":[
        {
            "category":"Freight",
            "type":"Transportation"
        }
    ],
    "sg:phone":"+1 843 747 8880",
    "sg:postcode":"29405",
    "sg:province":"SC",
    "sg:tags":[
        "trucking"
    ],
    "wof:name":"LMR Trucking Inc",
    "wof:placetype":"venue"
},
  "geometry": {"coordinates":[-80.01621299999999,32.854339],"type":"Point"}
}