{
  "type": "Feature",
  "properties": {
    "iso:country":"US",
    "sg:address":"35 Meadows Springs Ln",
    "sg:city":"Greer",
    "sg:classifiers":[
        {
            "category":"Building & Trades",
            "subcategory":"Construction",
            "type":"Services"
        }
    ],
    "sg:phone":"+1 864 879 2807",
    "sg:postcode":"29650",
    "sg:province":"SC",
    "sg:tags":[
        "hanging",
        "contractor"
    ],
    "wof:name":"Glen Myers Co",
    "wof:placetype":"venue"
},
  "geometry": {"coordinates":[-82.25514,34.919371],"type":"Point"}
}