{
  "type": "Feature",
  "properties": {
    "addr:full":"3213 Boiling Springs Rd Spartanburg SC 29316",
    "addr:housenumber":"3213",
    "addr:postcode":"29316",
    "addr:street":"Boiling Springs Rd",
    "iso:country":"US",
    "sg:address":"3213 Boiling Springs Rd",
    "sg:city":"Spartanburg",
    "sg:classifiers":[
        {
            "category":"Wholesale",
            "subcategory":"Auto Parts",
            "type":"Manufacturing & Wholesale Goods"
        }
    ],
    "sg:phone":"+1 864 578 8365",
    "sg:postcode":"29316",
    "sg:province":"SC",
    "sg:tags":[
        "re",
        "supply",
        "general"
    ],
    "wof:name":"Boiling Springs Tire Sales",
    "wof:placetype":"venue"
},
  "geometry": {"coordinates":[-81.979083,35.043626],"type":"Point"}
}