{
  "type": "Feature",
  "properties": {
    "addr:full":"118 Carolina Ave Moncks Corner SC 29461",
    "addr:housenumber":"118",
    "addr:postcode":"29461",
    "addr:street":"Carolina Ave",
    "iso:country":"US",
    "sg:address":"118 Carolina Ave",
    "sg:city":"Moncks Corner",
    "sg:classifiers":[
        {
            "category":"Government",
            "subcategory":"Court House",
            "type":"Public Place"
        }
    ],
    "sg:phone":"+1 843 719 7918",
    "sg:postcode":"29461",
    "sg:province":"SC",
    "sg:tags":[
        "city"
    ],
    "wof:name":"Moncks Corner Clerk Of Court",
    "wof:placetype":"venue"
},
  "geometry": {"coordinates":[-80.006173,33.195458],"type":"Point"}
}