{
  "type": "Feature",
  "properties": {
    "iso:country":"US",
    "sg:address":"2088 Industrial Park Rd",
    "sg:city":"Lancaster",
    "sg:classifiers":[
        {
            "category":"Manufacturing",
            "subcategory":"Metals",
            "type":"Manufacturing & Wholesale Goods"
        }
    ],
    "sg:phone":"+1 803 313 9292",
    "sg:postcode":"29720",
    "sg:province":"SC",
    "sg:tags":[
        "plating",
        "industrial",
        "plasma",
        "spray",
        "brush"
    ],
    "wof:name":"MBI Coatings",
    "wof:placetype":"venue"
},
  "geometry": {"coordinates":[-80.842658,34.786744],"type":"Point"}
}