{
  "type": "Feature",
  "properties": {
    "iso:country":"US",
    "sg:address":"206 W Barr St",
    "sg:city":"Lancaster",
    "sg:classifiers":[
        {
            "category":"Organizations",
            "subcategory":"Non-profit Organization",
            "type":"Services"
        }
    ],
    "sg:phone":"+1 803 285 2442",
    "sg:postcode":"29720",
    "sg:province":"SC",
    "wof:name":"Listening Center",
    "wof:placetype":"venue"
},
  "geometry": {"coordinates":[-80.773123,34.721943],"type":"Point"}
}