{
  "type": "Feature",
  "properties": {
    "iso:country":"US",
    "sg:address":"339 W Main St",
    "sg:city":"Lake City",
    "sg:classifiers":[
        {
            "category":"Health Services",
            "subcategory":"Optometrist",
            "type":"Services"
        }
    ],
    "sg:phone":"+1 843 374 2040",
    "sg:postcode":"29560",
    "sg:province":"SC",
    "wof:name":"Hobbs Eye Clinic",
    "wof:placetype":"venue"
},
  "geometry": {"coordinates":[-79.765425,33.877486],"type":"Point"}
}