{
  "type": "Feature",
  "properties": {
    "addr:full":"1901 Whiskey Rd Aiken SC 29803",
    "addr:housenumber":"1901",
    "addr:postcode":"29803",
    "addr:street":"Whiskey Rd",
    "iso:country":"US",
    "sg:address":"1901 Whiskey Rd",
    "sg:city":"Aiken",
    "sg:classifiers":[
        {
            "category":"Restaurant",
            "type":"Food & Drink"
        }
    ],
    "sg:menulink":"http://www.allmenus.com/sc/aiken/173071-wendys/menu/",
    "sg:phone":"+1 803 649 1879",
    "sg:postcode":"29803",
    "sg:province":"SC",
    "sg:tags":[
        "burger",
        "american",
        "soup"
    ],
    "wof:name":"Wendy's",
    "wof:placetype":"venue"
},
  "geometry": {"coordinates":[-81.719725,33.523625],"type":"Point"}
}