{
  "type": "Feature",
  "properties": {
    "addr:full":"4035 Hands Mill Hwy York SC 29745",
    "addr:housenumber":"4035",
    "addr:postcode":"29745",
    "addr:street":"Hands Mill Hwy",
    "iso:country":"US",
    "sg:address":"4035 Hands Mill Hwy",
    "sg:city":"York",
    "sg:classifiers":[
        {
            "category":"Real Estate",
            "subcategory":"Real Estate Agent",
            "type":"Services"
        }
    ],
    "sg:phone":"+1 803 396 8228",
    "sg:postcode":"29745",
    "sg:province":"SC",
    "wof:name":"May Green Properties",
    "wof:placetype":"venue"
},
  "geometry": {"coordinates":[-81.096655,35.084469],"type":"Point"}
}