{
  "type": "Feature",
  "properties": {
    "addr:full":"1412 Barnwell St Columbia SC 29201",
    "addr:housenumber":"1412",
    "addr:postcode":"29201",
    "addr:street":"Barnwell St",
    "iso:country":"US",
    "sg:address":"1412 Barnwell St",
    "sg:city":"Columbia",
    "sg:classifiers":[
        {
            "category":"Health Services",
            "subcategory":"Doctor",
            "type":"Services"
        }
    ],
    "sg:phone":"+1 803 256 2333",
    "sg:postcode":"29201",
    "sg:province":"SC",
    "sg:tags":[
        "dentist"
    ],
    "wof:name":"Crystal Smiles",
    "wof:placetype":"venue"
},
  "geometry": {"coordinates":[-81.025398,34.007999],"type":"Point"}
}