{
  "type": "Feature",
  "properties": {
    "addr:full":"1200 Oswego Hwy Sumter SC 29153",
    "addr:housenumber":"1200",
    "addr:postcode":"29153",
    "addr:street":"Oswego Hwy",
    "iso:country":"US",
    "sg:address":"1200 Oswego Hwy",
    "sg:city":"Sumter",
    "sg:classifiers":[
        {
            "category":"Education",
            "subcategory":"School",
            "type":"Public Place"
        }
    ],
    "sg:phone":"+1 803 775 7272",
    "sg:postcode":"29153",
    "sg:province":"SC",
    "wof:name":"Chestnut Oaks Middle School",
    "wof:placetype":"venue"
},
  "geometry": {"coordinates":[-80.309389,33.951441],"type":"Point"}
}