{
  "type": "Feature",
  "properties": {
    "iso:country":"US",
    "sg:address":"23 Plantation Dr",
    "sg:city":"Hilton Head Isle",
    "sg:classifiers":[
        {
            "category":"Building & Trades",
            "subcategory":"Construction",
            "type":"Services"
        }
    ],
    "sg:phone":"+1 843 757 9036",
    "sg:postcode":"29928",
    "sg:province":"SC",
    "sg:tags":[
        "general",
        "contractor"
    ],
    "sg:website":"www.breezebuilders.com",
    "wof:name":"Breeze Builders Inc",
    "wof:placetype":"venue"
},
  "geometry": {"coordinates":[-80.795661,32.140139],"type":"Point"}
}