{
  "type": "Feature",
  "properties": {
    "iso:country":"US",
    "sg:address":"7 Spur St",
    "sg:city":"Lyman",
    "sg:classifiers":[
        {
            "category":"Real Estate",
            "subcategory":"Real Estate Agent",
            "type":"Services"
        }
    ],
    "sg:phone":"+1 864 439 1800",
    "sg:postcode":"29365",
    "sg:province":"SC",
    "wof:name":"Bolding Realty",
    "wof:placetype":"venue"
},
  "geometry": {"coordinates":[-82.124513,34.953123],"type":"Point"}
}