{
  "type": "Feature",
  "properties": {
    "iso:country":"US",
    "sg:address":"2600 Locust Hill Rd",
    "sg:city":"Taylors",
    "sg:classifiers":[
        {
            "category":"Food & Beverages",
            "subcategory":"Groceries & Convenience Stores",
            "type":"Retail Goods"
        }
    ],
    "sg:phone":"+1 864 877 4570",
    "sg:postcode":"29687",
    "sg:province":"SC",
    "wof:name":"Corner Mart",
    "wof:placetype":"venue"
},
  "geometry": {"coordinates":[-82.305908,34.959809],"type":"Point"}
}