{
  "type": "Feature",
  "properties": {
    "iso:country":"US",
    "sg:address":"371 E Columbia Ave",
    "sg:city":"Leesville",
    "sg:classifiers":[
        {
            "category":"Food & Beverages",
            "subcategory":"Groceries & Convenience Stores",
            "type":"Retail Goods"
        }
    ],
    "sg:phone":"+1 803 532 2767",
    "sg:postcode":"29070",
    "sg:province":"SC",
    "wof:name":"Kwikarry II",
    "wof:placetype":"venue"
},
  "geometry": {"coordinates":[-81.514878,33.915321],"type":"Point"}
}