{
  "type": "Feature",
  "properties": {
    "iso:country":"US",
    "sg:address":"21 Maple Creek Cir",
    "sg:city":"Greenville",
    "sg:classifiers":[
        {
            "category":"Wholesale",
            "subcategory":"Machinery & Supplies",
            "type":"Manufacturing & Wholesale Goods"
        }
    ],
    "sg:phone":"+1 864 299 0990",
    "sg:postcode":"29607",
    "sg:province":"SC",
    "sg:tags":[
        "equipment",
        "safety",
        "clothing"
    ],
    "wof:name":"Gloves Plus",
    "wof:placetype":"venue"
},
  "geometry": {"coordinates":[-82.337855,34.77695],"type":"Point"}
}