{
  "type": "Feature",
  "properties": {
    "iso:country":"US",
    "sg:address":"525 Thurgood Marshall Hwy",
    "sg:city":"Kingstree",
    "sg:classifiers":[
        {
            "category":"Social Services",
            "subcategory":"Child Care",
            "type":"Services"
        }
    ],
    "sg:phone":"+1 843 355 9050",
    "sg:postcode":"29556",
    "sg:province":"SC",
    "wof:name":"Kid's Kingdom Academy",
    "wof:placetype":"venue"
},
  "geometry": {"coordinates":[-79.815823,33.659985],"type":"Point"}
}