{
  "type": "Feature",
  "properties": {
    "iso:country":"US",
    "sg:address":"7640 Pelham Rd",
    "sg:city":"Greenville",
    "sg:classifiers":[
        {
            "category":"Wholesale",
            "subcategory":"Computers",
            "type":"Manufacturing & Wholesale Goods"
        }
    ],
    "sg:phone":"+1 864 627 8800",
    "sg:postcode":"29615",
    "sg:province":"SC",
    "sg:tags":[
        "peripheral"
    ],
    "wof:name":"Computer Dymanics Sales",
    "wof:placetype":"venue"
},
  "geometry": {"coordinates":[-82.23642100000001,34.853591],"type":"Point"}
}