{
  "type": "Feature",
  "properties": {
    "addr:full":"17 N Williamsburg County Hwy Kingstree SC 29556",
    "addr:housenumber":"17",
    "addr:postcode":"29556",
    "addr:street":"N Williamsburg County Hwy",
    "iso:country":"US",
    "sg:address":"17 N Williamsburg County Hwy",
    "sg:city":"Kingstree",
    "sg:classifiers":[
        {
            "category":"Shopping",
            "subcategory":"Discount & Variety Stores",
            "type":"Retail Goods"
        },
        {
            "category":"Shopping",
            "subcategory":"Department Store",
            "type":"Retail Goods"
        }
    ],
    "sg:phone":"+1 843 354 9126",
    "sg:postcode":"29556",
    "sg:province":"SC",
    "sg:tags":[
        "shop"
    ],
    "wof:name":"Family Dollar Stores",
    "wof:placetype":"venue"
},
  "geometry": {"coordinates":[-79.823127,33.684223],"type":"Point"}
}