{
  "type": "Feature",
  "properties": {
    "iso:country":"US",
    "sg:address":"841 McJunkin Rd",
    "sg:city":"Nesmith",
    "sg:phone":"+1 843 382 9022",
    "sg:postcode":"29580",
    "sg:province":"SC",
    "sg:tags":[
        "farm",
        "cotton"
    ],
    "wof:name":"Thomas Stuckey",
    "wof:placetype":"venue"
},
  "geometry": {"coordinates":[-79.568265,33.667604],"type":"Point"}
}