{
  "type": "Feature",
  "properties": {
    "addr:full":"30 Plantation Park Dr Suite 202 Bluffton SC 29910",
    "addr:housenumber":"30",
    "addr:postcode":"29910",
    "addr:street":"Plantation Park Dr Suite 202",
    "iso:country":"US",
    "sg:address":"30 Plantation Park Dr Suite 202",
    "sg:city":"Bluffton",
    "sg:classifiers":[
        {
            "category":"Utilities",
            "subcategory":"Mobile Phone",
            "type":"Services"
        },
        {
            "category":"Shopping",
            "subcategory":"Mobile Phones",
            "type":"Retail Goods"
        }
    ],
    "sg:phone":"+1 843 815 6970",
    "sg:postcode":"29910",
    "sg:province":"SC",
    "sg:tags":[
        "supply",
        "communication",
        "telephone",
        "wireless",
        "equipment",
        "cellular"
    ],
    "sg:website":"http://www.sprint.com",
    "wof:name":"Sprint Store",
    "wof:placetype":"venue"
},
  "geometry": {"coordinates":[-80.867897,32.27161],"type":"Point"}
}