{
  "type": "Feature",
  "properties": {
    "iso:country":"US",
    "sg:address":"345 Folly Rd",
    "sg:city":"Charleston",
    "sg:classifiers":[
        {
            "category":"Restaurant",
            "type":"Food & Drink"
        }
    ],
    "sg:menulink":"http://www.allmenus.com/sc/james-island/176659-kfc---kentucky-fried-chicken/menu/",
    "sg:phone":"+1 843 795 5211",
    "sg:postcode":"29412",
    "sg:province":"SC",
    "sg:tags":[
        "american",
        "chicken"
    ],
    "wof:name":"KFC - Kentucky Fried Chicken",
    "wof:placetype":"venue"
},
  "geometry": {"coordinates":[-79.97405500000001,32.757522],"type":"Point"}
}