{
  "type": "Feature",
  "properties": {
    "iso:country":"US",
    "sg:address":"145 Southchase Blvd",
    "sg:city":"Fountain Inn",
    "sg:classifiers":[
        {
            "category":"Manufacturing",
            "subcategory":"Chemicals & Compounds",
            "type":"Manufacturing & Wholesale Goods"
        }
    ],
    "sg:phone":"+1 864 967 0444",
    "sg:postcode":"29644",
    "sg:province":"SC",
    "sg:tags":[
        "preparation",
        "research",
        "commercial",
        "physical",
        "mfg"
    ],
    "wof:name":"Bic Corporation",
    "wof:placetype":"venue"
},
  "geometry": {"coordinates":[-82.239094,34.697838],"type":"Point"}
}