{
  "type": "Feature",
  "properties": {
    "iso:country":"US",
    "sg:address":"3101 S Kings Hwy",
    "sg:city":"Myrtle Beach",
    "sg:classifiers":[
        {
            "category":"Sports & Exercise",
            "subcategory":"Golf",
            "type":"Entertainment"
        }
    ],
    "sg:phone":"+1 843 913 5335",
    "sg:postcode":"29577",
    "sg:province":"SC",
    "sg:tags":[
        "course"
    ],
    "wof:name":"Midway PAR 3",
    "wof:placetype":"venue"
},
  "geometry": {"coordinates":[-78.925006,33.660613],"type":"Point"}
}