{
  "type": "Feature",
  "properties": {
    "addr:full":"3801 Old Buncombe Rd Greenville SC 29617",
    "addr:housenumber":"3801",
    "addr:postcode":"29617",
    "addr:street":"Old Buncombe Rd",
    "iso:country":"US",
    "sg:address":"3801 Old Buncombe Rd",
    "sg:city":"Greenville",
    "sg:classifiers":[
        {
            "category":"Education",
            "subcategory":"School",
            "type":"Public Place"
        }
    ],
    "sg:phone":"+1 864 294 4353",
    "sg:postcode":"29617",
    "sg:province":"SC",
    "wof:name":"Lakeview Middle School",
    "wof:placetype":"venue"
},
  "geometry": {"coordinates":[-82.43181,34.891504],"type":"Point"}
}