{
  "type": "Feature",
  "properties": {
    "iso:country":"US",
    "sg:address":"119 Blake Dr",
    "sg:city":"Summerville",
    "sg:classifiers":[
        {
            "category":"Shopping",
            "type":"Retail Goods"
        }
    ],
    "sg:phone":"+1 843 297 0105",
    "sg:postcode":"29485",
    "sg:province":"SC",
    "sg:tags":[
        "sales"
    ],
    "wof:name":"Cone Sales",
    "wof:placetype":"venue"
},
  "geometry": {"coordinates":[-80.201712,32.987502],"type":"Point"}
}