{
  "type": "Feature",
  "properties": {
    "addr:full":"330 E Coffee St Greenville SC 29601",
    "addr:housenumber":"330",
    "addr:postcode":"29601",
    "addr:street":"E Coffee St",
    "iso:country":"US",
    "sg:address":"330 E Coffee St",
    "sg:city":"Greenville",
    "sg:classifiers":[
        {
            "category":"Insurance",
            "subcategory":"Title Insurance",
            "type":"Services"
        }
    ],
    "sg:phone":"+1 864 421 0802",
    "sg:postcode":"29601",
    "sg:province":"SC",
    "wof:name":"Ticor Title Insurance",
    "wof:placetype":"venue"
},
  "geometry": {"coordinates":[-82.395408,34.850542],"type":"Point"}
}