{
  "type": "Feature",
  "properties": {
    "addr:full":"1952 Belgrade Ave Charleston SC 29407",
    "addr:housenumber":"1952",
    "addr:postcode":"29407",
    "addr:street":"Belgrade Ave",
    "iso:country":"US",
    "sg:address":"1952 Belgrade Ave",
    "sg:city":"Charleston",
    "sg:classifiers":[
        {
            "category":"Building & Trades",
            "subcategory":"Plumbing",
            "type":"Services"
        }
    ],
    "sg:phone":"+1 843 766 9001",
    "sg:postcode":"29407",
    "sg:province":"SC",
    "sg:tags":[
        "heating",
        "contractor"
    ],
    "sg:website":"www.serxsc.com",
    "wof:name":"Pardee Service Experts",
    "wof:placetype":"venue"
},
  "geometry": {"coordinates":[-80.02453,32.79622],"type":"Point"}
}