{
  "type": "Feature",
  "properties": {
    "iso:country":"US",
    "sg:address":"107 Lancaster Dr",
    "sg:city":"Blacksburg",
    "sg:classifiers":[
        {
            "category":"Building & Trades",
            "subcategory":"Construction",
            "type":"Services"
        },
        {
            "category":"Building & Trades",
            "subcategory":"Landscaping Services",
            "type":"Services"
        }
    ],
    "sg:phone":"+1 864 839 6012",
    "sg:postcode":"29702",
    "sg:province":"SC",
    "sg:tags":[
        "grading",
        "landscape",
        "contractor"
    ],
    "wof:name":"Cookseys Landscaping",
    "wof:placetype":"venue"
},
  "geometry": {"coordinates":[-81.51955700000001,35.103391],"type":"Point"}
}