{
  "type": "Feature",
  "properties": {
    "iso:country":"US",
    "sg:address":"171 Lake Park Dr",
    "sg:city":"Spartanburg",
    "sg:classifiers":[
        {
            "category":"Insurance",
            "subcategory":"Life Insurance",
            "type":"Services"
        }
    ],
    "sg:phone":"+1 864 574 7176",
    "sg:postcode":"29301",
    "sg:province":"SC",
    "sg:tags":[
        "carrier"
    ],
    "wof:name":"National Assoc of Insuran",
    "wof:placetype":"venue"
},
  "geometry": {"coordinates":[-82.026122,34.92866],"type":"Point"}
}