{
  "type": "Feature",
  "properties": {
    "addr:full":"120 Briarwood Rd Spartanburg SC 29301",
    "addr:housenumber":"120",
    "addr:postcode":"29301",
    "addr:street":"Briarwood Rd",
    "iso:country":"US",
    "sg:address":"120 Briarwood Rd",
    "sg:city":"Spartanburg",
    "sg:classifiers":[
        {
            "category":"Professional",
            "subcategory":"Art Services",
            "type":"Services"
        }
    ],
    "sg:phone":"+1 864 574 5330",
    "sg:postcode":"29301",
    "sg:province":"SC",
    "sg:tags":[
        "photographer"
    ],
    "wof:name":"John Byrum Photography",
    "wof:placetype":"venue"
},
  "geometry": {"coordinates":[-81.956839,34.933143],"type":"Point"}
}