{
  "type": "Feature",
  "properties": {
    "iso:country":"US",
    "sg:address":"601 Beach Rd",
    "sg:city":"Walterboro",
    "sg:classifiers":[
        {
            "category":"Building & Trades",
            "subcategory":"Landscaping Services",
            "type":"Services"
        }
    ],
    "sg:phone":"+1 843 538 5471",
    "sg:postcode":"29488",
    "sg:province":"SC",
    "sg:tags":[
        "designer",
        "landscape"
    ],
    "wof:name":"Robert E Marvin/Howell Beach",
    "wof:placetype":"venue"
},
  "geometry": {"coordinates":[-80.70280700000001,32.893664],"type":"Point"}
}