{
  "type": "Feature",
  "properties": {
    "addr:full":"456 Meeting St Charleston SC 29403",
    "addr:housenumber":"456",
    "addr:postcode":"29403",
    "addr:street":"Meeting St",
    "iso:country":"US",
    "sg:address":"456 Meeting St",
    "sg:city":"Charleston",
    "sg:classifiers":[
        {
            "category":"Shopping",
            "subcategory":"Clothing, Apparel, & Fashions",
            "type":"Retail Goods"
        }
    ],
    "sg:phone":"+1 843 722 2526",
    "sg:postcode":"29403",
    "sg:province":"SC",
    "wof:name":"Simply Fashions Store 39",
    "wof:placetype":"venue"
},
  "geometry": {"coordinates":[-79.939139,32.794081],"type":"Point"}
}