{
  "type": "Feature",
  "properties": {
    "iso:country":"US",
    "sg:address":"5960 State Hwy 55 E",
    "sg:city":"Clover",
    "sg:classifiers":[
        {
            "category":"Social Services",
            "subcategory":"Child Care",
            "type":"Services"
        }
    ],
    "sg:phone":"+1 803 831 1303",
    "sg:postcode":"29710",
    "sg:province":"SC",
    "wof:name":"Bethel Day Care Ctr",
    "wof:placetype":"venue"
},
  "geometry": {"coordinates":[-81.122979,35.08794],"type":"Point"}
}