{
  "type": "Feature",
  "properties": {
    "iso:country":"US",
    "sg:address":"901 N Kings Hwy",
    "sg:city":"Myrtle Beach",
    "sg:classifiers":[
        {
            "category":"Social Services",
            "type":"Services"
        }
    ],
    "sg:phone":"+1 843 448 4820",
    "sg:postcode":"29577",
    "sg:province":"SC",
    "sg:tags":[
        "counselor",
        "marriage",
        "family"
    ],
    "wof:name":"Coastal Samaritan Ctr",
    "wof:placetype":"venue"
},
  "geometry": {"coordinates":[-78.88102499999999,33.69489],"type":"Point"}
}