{
  "type": "Feature",
  "properties": {
    "iso:country":"US",
    "sg:address":"5855 Pageland Hwy",
    "sg:city":"Lancaster",
    "sg:classifiers":[
        {
            "category":"Home & Garden",
            "subcategory":"Building Materials",
            "type":"Retail Goods"
        }
    ],
    "sg:phone":"+1 803 286 8338",
    "sg:postcode":"29720",
    "sg:province":"SC",
    "wof:name":"Number 9 Lumber Co",
    "wof:placetype":"venue"
},
  "geometry": {"coordinates":[-80.580399,34.752936],"type":"Point"}
}