{
  "type": "Feature",
  "properties": {
    "addr:full":"359 Hampton St Chesnee SC 29323",
    "addr:housenumber":"359",
    "addr:postcode":"29323",
    "addr:street":"Hampton St",
    "iso:country":"US",
    "sg:address":"359 Hampton St",
    "sg:city":"Chesnee",
    "sg:classifiers":[
        {
            "category":"Recreation",
            "type":"Entertainment"
        }
    ],
    "sg:phone":"+1 864 461 4488",
    "sg:postcode":"29323",
    "sg:province":"SC",
    "sg:tags":[
        "range",
        "baseball",
        "batting"
    ],
    "wof:name":"Hit It Big",
    "wof:placetype":"venue"
},
  "geometry": {"coordinates":[-81.85591599999999,35.152699],"type":"Point"}
}