{
  "type": "Feature",
  "properties": {
    "addr:full":"1110 Meeting St West Columbia SC 29169",
    "addr:housenumber":"1110",
    "addr:postcode":"29169",
    "addr:street":"Meeting St",
    "iso:country":"US",
    "sg:address":"1110 Meeting St",
    "sg:city":"West Columbia",
    "sg:classifiers":[
        {
            "category":"Education",
            "subcategory":"School",
            "type":"Public Place"
        }
    ],
    "sg:phone":"+1 803 796 7025",
    "sg:postcode":"29169",
    "sg:province":"SC",
    "sg:tags":[
        "elementary"
    ],
    "wof:name":"Colonial Christian Academy Day Care",
    "wof:placetype":"venue"
},
  "geometry": {"coordinates":[-81.071602,33.9897],"type":"Point"}
}