{
  "type": "Feature",
  "properties": {
    "iso:country":"US",
    "sg:address":"102 Redds Branch Rd",
    "sg:city":"Aiken",
    "sg:classifiers":[
        {
            "category":"Building & Trades",
            "subcategory":"Construction",
            "type":"Services"
        }
    ],
    "sg:phone":"+1 803 649 0260",
    "sg:postcode":"29801",
    "sg:province":"SC",
    "sg:tags":[
        "fabricator",
        "metal"
    ],
    "wof:name":"Overcash Enterprises Inc",
    "wof:placetype":"venue"
},
  "geometry": {"coordinates":[-81.668074,33.548076],"type":"Point"}
}