{
  "type": "Feature",
  "properties": {
    "addr:full":"404 Pendleton St Columbia SC 29201",
    "addr:housenumber":"404",
    "addr:postcode":"29201",
    "addr:street":"Pendleton St",
    "iso:country":"US",
    "sg:address":"404 Pendleton St",
    "sg:city":"Columbia",
    "sg:classifiers":[
        {
            "category":"Building & Trades",
            "subcategory":"Construction",
            "type":"Services"
        },
        {
            "category":"Home & Garden",
            "subcategory":"Furniture",
            "type":"Retail Goods"
        }
    ],
    "sg:phone":"+1 803 376 1020",
    "sg:postcode":"29201",
    "sg:province":"SC",
    "sg:tags":[
        "interior",
        "design",
        "store"
    ],
    "sg:website":"www.avantiinteriors.com",
    "wof:name":"Avanti Interior Design Inc",
    "wof:placetype":"venue"
},
  "geometry": {"coordinates":[-81.044855,33.994525],"type":"Point"}
}