{
  "type": "Feature",
  "properties": {
    "iso:country":"US",
    "sg:address":"120 Old Seneca Rd",
    "sg:city":"Westminster",
    "sg:classifiers":[
        {
            "category":"Manufacturing",
            "subcategory":"Retail Goods",
            "type":"Manufacturing & Wholesale Goods"
        }
    ],
    "sg:phone":"+1 864 647 8416",
    "sg:postcode":"29693",
    "sg:province":"SC",
    "sg:tags":[
        "textile",
        "used",
        "mfg",
        "novelty",
        "hair",
        "item",
        "including"
    ],
    "wof:name":"Holiday Textiles Inc",
    "wof:placetype":"venue"
},
  "geometry": {"coordinates":[-83.04173400000001,34.672282],"type":"Point"}
}