{
  "type": "Feature",
  "properties": {
    "addr:full":"220 Chardonnay Ln Aiken SC 29803",
    "addr:housenumber":"220",
    "addr:postcode":"29803",
    "addr:street":"Chardonnay Ln",
    "iso:country":"US",
    "sg:address":"220 Chardonnay Ln",
    "sg:city":"Aiken",
    "sg:classifiers":[
        {
            "category":"Building & Trades",
            "subcategory":"Construction",
            "type":"Services"
        }
    ],
    "sg:phone":"+1 803 644 3200",
    "sg:postcode":"29803",
    "sg:province":"SC",
    "sg:tags":[
        "residential"
    ],
    "wof:name":"R C B Inc",
    "wof:placetype":"venue"
},
  "geometry": {"coordinates":[-81.66509600000001,33.498416],"type":"Point"}
}