{
  "type": "Feature",
  "properties": {
    "iso:country":"US",
    "sg:address":"760 Waterloo St",
    "sg:city":"Charleston",
    "sg:classifiers":[
        {
            "category":"Freight",
            "type":"Transportation"
        }
    ],
    "sg:phone":"+1 843 762 0375",
    "sg:postcode":"29412",
    "sg:province":"SC",
    "sg:tags":[
        "warehouse"
    ],
    "wof:name":"Dann Distribution Inc",
    "wof:placetype":"venue"
},
  "geometry": {"coordinates":[-79.927779,32.74366],"type":"Point"}
}