{
  "type": "Feature",
  "properties": {
    "addr:full":"236 Persimmon Fork Rd Blythewood SC 29016",
    "addr:housenumber":"236",
    "addr:postcode":"29016",
    "addr:street":"Persimmon Fork Rd",
    "iso:country":"US",
    "sg:address":"236 Persimmon Fork Rd",
    "sg:city":"Blythewood",
    "sg:classifiers":[
        {
            "category":"Farming",
            "subcategory":"Livestock Farm",
            "type":"Manufacturing & Wholesale Goods"
        },
        {
            "category":"Recreation",
            "type":"Entertainment"
        }
    ],
    "sg:phone":"+1 803 691 9484",
    "sg:postcode":"29016",
    "sg:province":"SC",
    "sg:tags":[
        "equine",
        "stable"
    ],
    "wof:name":"Second Wind Farm LLC",
    "wof:placetype":"venue"
},
  "geometry": {"coordinates":[-81.022288,34.223839],"type":"Point"}
}