{
  "type": "Feature",
  "properties": {
    "iso:country":"US",
    "sg:address":"299 Garlington Rd",
    "sg:city":"Greenville",
    "sg:classifiers":[
        {
            "category":"Manufacturing",
            "subcategory":"Tools & Machinery",
            "type":"Manufacturing & Wholesale Goods"
        }
    ],
    "sg:phone":"+1 864 672 1500",
    "sg:postcode":"29615",
    "sg:province":"SC",
    "sg:tags":[
        "machine",
        "shop"
    ],
    "wof:name":"Gloenco Greenville",
    "wof:placetype":"venue"
},
  "geometry": {"coordinates":[-82.292323,34.830238],"type":"Point"}
}