{
  "type": "Feature",
  "properties": {
    "iso:country":"US",
    "sg:address":"140 Falcon Dr",
    "sg:city":"Easley",
    "sg:classifiers":[
        {
            "category":"Manufacturing",
            "subcategory":"Textiles",
            "type":"Manufacturing & Wholesale Goods"
        }
    ],
    "sg:phone":"+1 864 855 2147",
    "sg:postcode":"29640",
    "sg:province":"SC",
    "sg:tags":[
        "dyer"
    ],
    "sg:website":"www.hanesfinishing.com",
    "wof:name":"Hanes Dye & Finishing",
    "wof:placetype":"venue"
},
  "geometry": {"coordinates":[-82.647705,34.853738],"type":"Point"}
}