{
  "type": "Feature",
  "properties": {
    "iso:country":"US",
    "sg:address":"153 Chapin Rd",
    "sg:city":"Chapin",
    "sg:classifiers":[
        {
            "category":"Shopping",
            "type":"Retail Goods"
        }
    ],
    "sg:phone":"+1 803 932 7777",
    "sg:postcode":"29036",
    "sg:province":"SC",
    "sg:tags":[
        "material",
        "merchandise"
    ],
    "wof:name":"Cutrock Kitchens & Baths",
    "wof:placetype":"venue"
},
  "geometry": {"coordinates":[-81.318581,34.139444],"type":"Point"}
}