{
  "type": "Feature",
  "properties": {
    "addr:full":"951 Ferree Rd Campobello SC 29322",
    "addr:housenumber":"951",
    "addr:postcode":"29322",
    "addr:street":"Ferree Rd",
    "iso:country":"US",
    "sg:address":"951 Ferree Rd",
    "sg:city":"Campobello",
    "sg:classifiers":[
        {
            "category":"Retail",
            "subcategory":"Animal Services",
            "type":"Services"
        }
    ],
    "sg:phone":"+1 864 468 4982",
    "sg:postcode":"29322",
    "sg:province":"SC",
    "sg:tags":[
        "pet",
        "grooming"
    ],
    "wof:name":"Doggie Designs & Kitty Cuts",
    "wof:placetype":"venue"
},
  "geometry": {"coordinates":[-82.18020199999999,35.111516],"type":"Point"}
}