{
  "type": "Feature",
  "properties": {
    "iso:country":"US",
    "sg:address":"319 Mill Creek Rd",
    "sg:city":"Sunset",
    "sg:classifiers":[
        {
            "category":"Banks & Credit Unions",
            "subcategory":"Financial Services",
            "type":"Services"
        }
    ],
    "sg:phone":"+1 864 878 9844",
    "sg:postcode":"29685",
    "sg:province":"SC",
    "sg:tags":[
        "trust",
        "investment",
        "real estate"
    ],
    "wof:name":"Darla Ljarvis Enterpris",
    "wof:placetype":"venue"
},
  "geometry": {"coordinates":[-82.862377,34.986701],"type":"Point"}
}