{
  "type": "Feature",
  "properties": {
    "addr:full":"5867 Friendship Ln Myrtle Beach SC 29588",
    "addr:housenumber":"5867",
    "addr:postcode":"29588",
    "addr:street":"Friendship Ln",
    "iso:country":"US",
    "sg:address":"5867 Friendship Ln",
    "sg:city":"Myrtle Beach",
    "sg:classifiers":[
        {
            "category":"Building & Trades",
            "subcategory":"Plumbing",
            "type":"Services"
        }
    ],
    "sg:phone":"+1 843 650 1672",
    "sg:postcode":"29588",
    "sg:province":"SC",
    "sg:tags":[
        "conditioning",
        "air",
        "system",
        "contractor"
    ],
    "wof:name":"Gross Mechanical",
    "wof:placetype":"venue"
},
  "geometry": {"coordinates":[-79.011847,33.652486],"type":"Point"}
}