{
  "type": "Feature",
  "properties": {
    "iso:country":"US",
    "sg:address":"11 Farringdon Dr",
    "sg:city":"Greenville",
    "sg:classifiers":[
        {
            "category":"Building & Trades",
            "subcategory":"Landscaping Services",
            "type":"Services"
        }
    ],
    "sg:phone":"+1 864 505 8782",
    "sg:postcode":"29615",
    "sg:province":"SC",
    "sg:tags":[
        "lawn",
        "maintenance",
        "grounds"
    ],
    "wof:name":"Chestnut Oaks Lawn Maintenance",
    "wof:placetype":"venue"
},
  "geometry": {"coordinates":[-82.307236,34.849628],"type":"Point"}
}