{
  "type": "Feature",
  "properties": {
    "addr:full":"8800 Deerwood Dr North Charleston SC 29406",
    "addr:housenumber":"8800",
    "addr:postcode":"29406",
    "addr:street":"Deerwood Dr",
    "iso:country":"US",
    "sg:address":"8800 Deerwood Dr",
    "sg:city":"North Charleston",
    "sg:classifiers":[
        {
            "category":"Building & Trades",
            "subcategory":"Construction",
            "type":"Services"
        }
    ],
    "sg:phone":"+1 843 572 7766",
    "sg:postcode":"29406",
    "sg:province":"SC",
    "sg:tags":[
        "general",
        "contractor"
    ],
    "wof:name":"Salerno Custom Masonry",
    "wof:placetype":"venue"
},
  "geometry": {"coordinates":[-80.064375,32.965672],"type":"Point"}
}