{
  "type": "Feature",
  "properties": {
    "addr:full":"306 Lockemy Hwy Dillon SC 29536",
    "addr:housenumber":"306",
    "addr:postcode":"29536",
    "addr:street":"Lockemy Hwy",
    "iso:country":"US",
    "sg:address":"306 Lockemy Hwy",
    "sg:city":"Dillon",
    "sg:classifiers":[
        {
            "category":"Building & Trades",
            "subcategory":"Construction",
            "type":"Services"
        }
    ],
    "sg:phone":"+1 843 774 5222",
    "sg:postcode":"29536",
    "sg:province":"SC",
    "sg:tags":[
        "home",
        "renovation",
        "family",
        "contractor"
    ],
    "wof:name":"McLaughlins Construction LLC",
    "wof:placetype":"venue"
},
  "geometry": {"coordinates":[-79.359807,34.407431],"type":"Point"}
}