{
  "type": "Feature",
  "properties": {
    "addr:full":"1520 W Palmetto St Florence SC 29501",
    "addr:housenumber":"1520",
    "addr:postcode":"29501",
    "addr:street":"W Palmetto St",
    "iso:country":"US",
    "sg:address":"1520 W Palmetto St",
    "sg:city":"Florence",
    "sg:classifiers":[
        {
            "category":"Bars & Pubs",
            "type":"Food & Drink"
        }
    ],
    "sg:phone":"+1 843 413 9313",
    "sg:postcode":"29501",
    "sg:province":"SC",
    "sg:tags":[
        "club",
        "drinking",
        "night"
    ],
    "wof:name":"Miss Kitty's Saloon LLC",
    "wof:placetype":"venue"
},
  "geometry": {"coordinates":[-79.79719799999999,34.190402],"type":"Point"}
}