{
  "type": "Feature",
  "properties": {
    "addr:full":"1311 Chuck Dawley Blvd Mount Pleasant SC 29464",
    "addr:housenumber":"1311",
    "addr:postcode":"29464",
    "addr:street":"Chuck Dawley Blvd",
    "iso:country":"US",
    "sg:address":"1311 Chuck Dawley Blvd",
    "sg:city":"Mount Pleasant",
    "sg:classifiers":[
        {
            "category":"Communications",
            "subcategory":"Radio Station",
            "type":"Services"
        }
    ],
    "sg:phone":"+1 843 972 2200",
    "sg:postcode":"29464",
    "sg:province":"SC",
    "sg:tags":[
        "brokerage",
        "develop"
    ],
    "wof:name":"American Media Services LLC",
    "wof:placetype":"venue"
},
  "geometry": {"coordinates":[-79.851674,32.806447],"type":"Point"}
}