{
  "type": "Feature",
  "properties": {
    "iso:country":"US",
    "sg:address":"309 S Church St",
    "sg:city":"Lake City",
    "sg:classifiers":[
        {
            "category":"Retail",
            "subcategory":"Funeral Services",
            "type":"Services"
        }
    ],
    "sg:phone":"+1 843 394 8433",
    "sg:postcode":"29560",
    "sg:province":"SC",
    "sg:tags":[
        "director"
    ],
    "wof:name":"Green's Funeral Home",
    "wof:placetype":"venue"
},
  "geometry": {"coordinates":[-79.757147,33.865279],"type":"Point"}
}