{
  "type": "Feature",
  "properties": {
    "iso:country":"US",
    "sg:address":"4731 US Hwy 17 Bus",
    "sg:city":"Myrtle Beach",
    "sg:classifiers":[
        {
            "category":"Personal",
            "subcategory":"Beauty Salon",
            "type":"Services"
        }
    ],
    "sg:phone":"+1 843 293 7445",
    "sg:postcode":"29577",
    "sg:province":"SC",
    "sg:tags":[
        "manicuring"
    ],
    "wof:name":"Formal Nails",
    "wof:placetype":"venue"
},
  "geometry": {"coordinates":[-78.848083,33.72255],"type":"Point"}
}