{
  "type": "Feature",
  "properties": {
    "iso:country":"US",
    "sg:address":"2838 Devine St",
    "sg:city":"Columbia",
    "sg:classifiers":[
        {
            "category":"Health Services",
            "subcategory":"Health Practitioner",
            "type":"Services"
        }
    ],
    "sg:phone":"+1 803 256 1121",
    "sg:postcode":"29205",
    "sg:province":"SC",
    "sg:tags":[
        "psychologist"
    ],
    "wof:name":"Psychological Service Assoc",
    "wof:placetype":"venue"
},
  "geometry": {"coordinates":[-81.001918,33.997951],"type":"Point"}
}