{
  "type": "Feature",
  "properties": {
    "iso:country":"US",
    "sg:address":"7369 Driggers Rd",
    "sg:city":"Hollywood",
    "sg:classifiers":[
        {
            "category":"Manufacturing",
            "subcategory":"Signs",
            "type":"Manufacturing & Wholesale Goods"
        }
    ],
    "sg:phone":"+1 843 889 5449",
    "sg:postcode":"29449",
    "sg:province":"SC",
    "wof:name":"Giley's",
    "wof:placetype":"venue"
},
  "geometry": {"coordinates":[-80.29351200000001,32.695084],"type":"Point"}
}