{
  "type": "Feature",
  "properties": {
    "addr:full":"152 S Main St Mauldin SC 29662",
    "addr:housenumber":"152",
    "addr:postcode":"29662",
    "addr:street":"S Main St",
    "iso:country":"US",
    "sg:address":"152 S Main St",
    "sg:city":"Mauldin",
    "sg:classifiers":[
        {
            "category":"Shopping",
            "subcategory":"Used Merchandise",
            "type":"Retail Goods"
        }
    ],
    "sg:phone":"+1 864 329 9500",
    "sg:postcode":"29662",
    "sg:province":"SC",
    "sg:tags":[
        "shop",
        "thrift"
    ],
    "wof:name":"Salvation Army Thrift Store",
    "wof:placetype":"venue"
},
  "geometry": {"coordinates":[-82.309635,34.778643],"type":"Point"}
}