{
  "type": "Feature",
  "properties": {
    "addr:full":"7085 Martin Luther King Jr Ave Lane SC 29564",
    "addr:housenumber":"7085",
    "addr:postcode":"29564",
    "addr:street":"Martin Luther King Jr Ave Lane",
    "iso:country":"US",
    "sg:address":"7085 Martin Luther King Jr Ave",
    "sg:city":"Lane",
    "sg:classifiers":[
        {
            "category":"Communications",
            "type":"Services"
        }
    ],
    "sg:phone":"+1 843 387 6256",
    "sg:postcode":"29564",
    "sg:province":"SC",
    "wof:name":"Communications Glory",
    "wof:placetype":"venue"
},
  "geometry": {"coordinates":[-79.890576,33.492354],"type":"Point"}
}