{
  "type": "Feature",
  "properties": {
    "iso:country":"US",
    "sg:address":"101 Goodrich St",
    "sg:city":"Greenville",
    "sg:classifiers":[
        {
            "category":"Building & Trades",
            "subcategory":"Construction",
            "type":"Services"
        }
    ],
    "sg:phone":"+1 864 269 2542",
    "sg:postcode":"29611",
    "sg:province":"SC",
    "sg:tags":[
        "painting",
        "contractor"
    ],
    "wof:name":"Etris Painting & Sandblasting",
    "wof:placetype":"venue"
},
  "geometry": {"coordinates":[-82.42831700000001,34.83107],"type":"Point"}
}