{
  "type": "Feature",
  "properties": {
    "iso:country":"US",
    "sg:address":"140 Joel St",
    "sg:city":"Lake City",
    "sg:classifiers":[
        {
            "category":"Retail",
            "subcategory":"Auto Repair",
            "type":"Services"
        }
    ],
    "sg:phone":"+1 843 394 5762",
    "sg:postcode":"29560",
    "sg:province":"SC",
    "sg:tags":[
        "body",
        "automobile",
        "painting"
    ],
    "wof:name":"Custom Auto Painting",
    "wof:placetype":"venue"
},
  "geometry": {"coordinates":[-79.761707,33.874379],"type":"Point"}
}