{
  "type": "Feature",
  "properties": {
    "addr:full":"1305 Whippoorwill Farm Rd Johns Island SC 29455",
    "addr:housenumber":"1305",
    "addr:postcode":"29455",
    "addr:street":"Whippoorwill Farm Rd",
    "iso:country":"US",
    "sg:address":"1305 Whippoorwill Farm Rd",
    "sg:city":"Johns Island",
    "sg:classifiers":[
        {
            "category":"Manufacturing",
            "subcategory":"Wood Products",
            "type":"Manufacturing & Wholesale Goods"
        }
    ],
    "sg:phone":"+1 843 559 6007",
    "sg:postcode":"29455",
    "sg:province":"SC",
    "sg:tags":[
        "mfg"
    ],
    "wof:name":"Lowcountry Baskets & Balloons",
    "wof:placetype":"venue"
},
  "geometry": {"coordinates":[-80.15074199999999,32.728347],"type":"Point"}
}