{
  "type": "Feature",
  "properties": {
    "iso:country":"US",
    "sg:address":"4581 US Hwy 501 W",
    "sg:city":"Conway",
    "sg:phone":"+1 843 365 8332",
    "sg:postcode":"29527",
    "sg:province":"SC",
    "sg:tags":[
        "farm",
        "tobacco"
    ],
    "wof:name":"Steven Edge",
    "wof:placetype":"venue"
},
  "geometry": {"coordinates":[-79.13197099999999,33.900446],"type":"Point"}
}