{
  "type": "Feature",
  "properties": {
    "addr:full":"2701 Broad River Rd Columbia SC 29210",
    "addr:housenumber":"2701",
    "addr:postcode":"29210",
    "addr:street":"Broad River Rd",
    "iso:country":"US",
    "sg:address":"2701 Broad River Rd",
    "sg:city":"Columbia",
    "sg:classifiers":[
        {
            "category":"Autos & Motor Vehicles",
            "subcategory":"Automobile Sales",
            "type":"Retail Goods"
        }
    ],
    "sg:phone":"+1 803 798 1932",
    "sg:postcode":"29210",
    "sg:province":"SC",
    "sg:tags":[
        "used"
    ],
    "wof:name":"Craft Auto Mart",
    "wof:placetype":"venue"
},
  "geometry": {"coordinates":[-81.10117099999999,34.045784],"type":"Point"}
}