{
  "type": "Feature",
  "properties": {
    "addr:full":"3509 Clemson Blvd Anderson SC 29621",
    "addr:housenumber":"3509",
    "addr:postcode":"29621",
    "addr:street":"Clemson Blvd",
    "iso:country":"US",
    "sg:address":"3509 Clemson Blvd",
    "sg:city":"Anderson",
    "sg:classifiers":[
        {
            "category":"Utilities",
            "subcategory":"Cable",
            "type":"Services"
        }
    ],
    "sg:phone":"+1 864 226 0195",
    "sg:postcode":"29621",
    "sg:province":"SC",
    "sg:tags":[
        "television"
    ],
    "wof:name":"Lodge Net Entertainment",
    "wof:placetype":"venue"
},
  "geometry": {"coordinates":[-82.675708,34.55025],"type":"Point"}
}