{
  "type": "Feature",
  "properties": {
    "iso:country":"US",
    "sg:address":"1018 York St NE",
    "sg:city":"Aiken",
    "sg:classifiers":[
        {
            "category":"Restaurant",
            "type":"Food & Drink"
        }
    ],
    "sg:phone":"+1 803 649 2878",
    "sg:postcode":"29801",
    "sg:province":"SC",
    "wof:name":"Little China",
    "wof:placetype":"venue"
},
  "geometry": {"coordinates":[-81.704178,33.575139],"type":"Point"}
}