{
  "type": "Feature",
  "properties": {
    "iso:country":"US",
    "sg:address":"3209 Millwood Ave",
    "sg:city":"Columbia",
    "sg:classifiers":[
        {
            "category":"Personal",
            "type":"Services"
        }
    ],
    "sg:phone":"+1 803 254 8346",
    "sg:postcode":"29205",
    "sg:province":"SC",
    "sg:tags":[
        "therapist",
        "massage"
    ],
    "wof:name":"Massage Therapy Ctr",
    "wof:placetype":"venue"
},
  "geometry": {"coordinates":[-80.995311,33.999076],"type":"Point"}
}