{
  "type": "Feature",
  "properties": {
    "iso:country":"US",
    "sg:address":"108 Elery Ter",
    "sg:city":"Summerville",
    "sg:classifiers":[
        {
            "category":"Real Estate",
            "subcategory":"Real Estate Agent",
            "type":"Services"
        }
    ],
    "sg:phone":"+1 843 821 6218",
    "sg:postcode":"29485",
    "sg:province":"SC",
    "wof:name":"Low Country Realty",
    "wof:placetype":"venue"
},
  "geometry": {"coordinates":[-80.184285,32.961291],"type":"Point"}
}