{
  "type": "Feature",
  "properties": {
    "iso:country":"US",
    "sg:address":"6342 Old State Rd",
    "sg:city":"Holly Hill",
    "sg:classifiers":[
        {
            "category":"Organizations",
            "subcategory":"Religious Organization",
            "type":"Services"
        }
    ],
    "sg:phone":"+1 803 496 5552",
    "sg:postcode":"29059",
    "sg:province":"SC",
    "sg:tags":[
        "church"
    ],
    "wof:name":"Eleventh Hour Baptist Church",
    "wof:placetype":"venue"
},
  "geometry": {"coordinates":[-80.47777600000001,33.36941],"type":"Point"}
}