{
  "type": "Feature",
  "properties": {
    "iso:country":"US",
    "sg:address":"3241 Homestead Rd",
    "sg:city":"Bowman",
    "sg:classifiers":[
        {
            "category":"Farming",
            "subcategory":"Dairy Farm",
            "type":"Manufacturing & Wholesale Goods"
        }
    ],
    "sg:phone":"+1 803 829 2172",
    "sg:postcode":"29018",
    "sg:province":"SC",
    "wof:name":"Triple A Farm",
    "wof:placetype":"venue"
},
  "geometry": {"coordinates":[-80.679727,33.375301],"type":"Point"}
}