{
  "type": "Feature",
  "properties": {
    "iso:country":"US",
    "sg:address":"6712 Augusta Hwy",
    "sg:city":"Leesville",
    "sg:classifiers":[
        {
            "category":"Personal",
            "subcategory":"Beauty Salon",
            "type":"Services"
        }
    ],
    "sg:phone":"+1 803 604 9978",
    "sg:postcode":"29070",
    "sg:province":"SC",
    "sg:tags":[
        "spa",
        "day"
    ],
    "wof:name":"Majestic Touch",
    "wof:placetype":"venue"
},
  "geometry": {"coordinates":[-81.49277,33.92651],"type":"Point"}
}