{
  "type": "Feature",
  "properties": {
    "iso:country":"US",
    "sg:address":"165 W Butler Ave",
    "sg:city":"Saluda",
    "sg:classifiers":[
        {
            "category":"Organizations",
            "subcategory":"Religious Organization",
            "type":"Services"
        }
    ],
    "sg:phone":"+1 864 445 3620",
    "sg:postcode":"29138",
    "sg:province":"SC",
    "sg:tags":[
        "church"
    ],
    "wof:name":"Butler United Methodist Church",
    "wof:placetype":"venue"
},
  "geometry": {"coordinates":[-81.77327200000001,34.003482],"type":"Point"}
}