{
  "type": "Feature",
  "properties": {
    "addr:full":"1696 Asheville Hwy Spartanburg SC 29303",
    "addr:housenumber":"1696",
    "addr:postcode":"29303",
    "addr:street":"Asheville Hwy",
    "iso:country":"US",
    "sg:address":"1696 Asheville Hwy",
    "sg:city":"Spartanburg",
    "sg:classifiers":[
        {
            "category":"Restaurant",
            "type":"Food & Drink"
        }
    ],
    "sg:menulink":"http://www.allmenus.com/sc/spartanburg/73244-pizza-hut/menu/",
    "sg:phone":"+1 864 577 0000",
    "sg:postcode":"29303",
    "sg:province":"SC",
    "sg:tags":[
        "american",
        "pizza"
    ],
    "wof:name":"Pizza Hut",
    "wof:placetype":"venue"
},
  "geometry": {"coordinates":[-81.968435,34.980658],"type":"Point"}
}