{
  "type": "Feature",
  "properties": {
    "iso:country":"US",
    "sg:address":"215 Thompson Blvd",
    "sg:city":"Union",
    "sg:classifiers":[
        {
            "category":"Government",
            "subcategory":"Fire Station",
            "type":"Public Place"
        }
    ],
    "sg:phone":"+1 864 429 1710",
    "sg:postcode":"29379",
    "sg:province":"SC",
    "sg:tags":[
        "department"
    ],
    "wof:name":"Union Fire Dept",
    "wof:placetype":"venue"
},
  "geometry": {"coordinates":[-81.628685,34.724751],"type":"Point"}
}