{
  "type": "Feature",
  "properties": {
    "iso:country":"US",
    "sg:address":"206 Elliot Rd",
    "sg:city":"Lyman",
    "sg:classifiers":[
        {
            "category":"Health Services",
            "subcategory":"Doctor",
            "type":"Services"
        }
    ],
    "sg:phone":"+1 864 439 6559",
    "sg:postcode":"29365",
    "sg:province":"SC",
    "sg:tags":[
        "dentist"
    ],
    "wof:name":"Neil F Wyss DDS",
    "wof:placetype":"venue"
},
  "geometry": {"coordinates":[-82.12208,34.951969],"type":"Point"}
}