{
  "type": "Feature",
  "properties": {
    "iso:country":"US",
    "sg:address":"4507 King Kennedy St",
    "sg:city":"Carlisle",
    "sg:classifiers":[
        {
            "category":"Organizations",
            "subcategory":"Religious Organization",
            "type":"Services"
        }
    ],
    "sg:phone":"+1 864 429 8811",
    "sg:postcode":"29031",
    "sg:province":"SC",
    "sg:tags":[
        "church"
    ],
    "wof:name":"Outreach Deliverance Ctr",
    "wof:placetype":"venue"
},
  "geometry": {"coordinates":[-81.46864600000001,34.593402],"type":"Point"}
}