{
  "type": "Feature",
  "properties": {
    "iso:country":"US",
    "sg:address":"132 N Memorial Ave",
    "sg:city":"Walterboro",
    "sg:classifiers":[
        {
            "category":"Real Estate",
            "subcategory":"Real Estate Agent",
            "type":"Services"
        }
    ],
    "sg:phone":"+1 843 549 6928",
    "sg:postcode":"29488",
    "sg:province":"SC",
    "wof:name":"Ulmer-Carolina",
    "wof:placetype":"venue"
},
  "geometry": {"coordinates":[-80.66257899999999,32.902335],"type":"Point"}
}