{
  "type": "Feature",
  "properties": {
    "addr:full":"743 Saluda Ave Columbia SC 29205",
    "addr:housenumber":"743",
    "addr:postcode":"29205",
    "addr:street":"Saluda Ave",
    "iso:country":"US",
    "sg:address":"743 Saluda Ave",
    "sg:city":"Columbia",
    "sg:classifiers":[
        {
            "category":"Shopping",
            "subcategory":"Gifts & Souvenirs",
            "type":"Retail Goods"
        }
    ],
    "sg:phone":"+1 803 771 4520",
    "sg:postcode":"29205",
    "sg:province":"SC",
    "sg:tags":[
        "shop",
        "glassware",
        "china",
        "cutlery"
    ],
    "wof:name":"Gibsons On Saluda Inc",
    "wof:placetype":"venue"
},
  "geometry": {"coordinates":[-81.01716999999999,33.99923],"type":"Point"}
}