{
  "type": "Feature",
  "properties": {
    "iso:country":"US",
    "sg:address":"219 Trade St",
    "sg:city":"Greer",
    "sg:classifiers":[
        {
            "category":"Restaurant",
            "type":"Food & Drink"
        }
    ],
    "sg:phone":"+1 864 801 9511",
    "sg:postcode":"29651",
    "sg:province":"SC",
    "wof:name":"Southern Thyme Cafe",
    "wof:placetype":"venue"
},
  "geometry": {"coordinates":[-82.226128,34.936797],"type":"Point"}
}