{
  "type": "Feature",
  "properties": {
    "iso:country":"US",
    "sg:address":"1103 E Rutherford St",
    "sg:city":"Landrum",
    "sg:classifiers":[
        {
            "category":"Real Estate",
            "subcategory":"Real Estate Agent",
            "type":"Services"
        }
    ],
    "sg:phone":"+1 864 457 5243",
    "sg:postcode":"29356",
    "sg:province":"SC",
    "wof:name":"Pruitt Real Estate Inc",
    "wof:placetype":"venue"
},
  "geometry": {"coordinates":[-82.176191,35.178009],"type":"Point"}
}