{
  "type": "Feature",
  "properties": {
    "iso:country":"US",
    "sg:address":"535 Parliament Cir",
    "sg:city":"Florence",
    "sg:classifiers":[
        {
            "category":"Building & Trades",
            "subcategory":"Construction",
            "type":"Services"
        }
    ],
    "sg:phone":"+1 843 317 9260",
    "sg:postcode":"29501",
    "sg:province":"SC",
    "sg:tags":[
        "residential"
    ],
    "wof:name":"Munnerlyn Signature Properties",
    "wof:placetype":"venue"
},
  "geometry": {"coordinates":[-79.862881,34.184508],"type":"Point"}
}