{
  "type": "Feature",
  "properties": {
    "iso:country":"US",
    "sg:address":"635 Southport Rd",
    "sg:city":"Roebuck",
    "sg:classifiers":[
        {
            "category":"Manufacturing",
            "subcategory":"Wood Products",
            "type":"Manufacturing & Wholesale Goods"
        }
    ],
    "sg:phone":"+1 864 573 6835",
    "sg:postcode":"29376",
    "sg:province":"SC",
    "sg:tags":[
        "prefabricated",
        "mfg",
        "portable",
        "install",
        "doc"
    ],
    "wof:name":"Trammell Mfg Inc",
    "wof:placetype":"venue"
},
  "geometry": {"coordinates":[-81.950024,34.90846],"type":"Point"}
}