{
  "type": "Feature",
  "properties": {
    "addr:full":"459 Park Ave Johnston SC 29832",
    "addr:housenumber":"459",
    "addr:postcode":"29832",
    "addr:street":"Park Ave",
    "iso:country":"US",
    "sg:address":"459 Park Ave",
    "sg:city":"Johnston",
    "sg:classifiers":[
        {
            "category":"Travel",
            "subcategory":"Travel Agent",
            "type":"Entertainment"
        }
    ],
    "sg:phone":"+1 803 275 1958",
    "sg:postcode":"29832",
    "sg:province":"SC",
    "sg:tags":[
        "operator",
        "tour"
    ],
    "wof:name":"Lj Bus Tours",
    "wof:placetype":"venue"
},
  "geometry": {"coordinates":[-81.807205,33.824211],"type":"Point"}
}