{
  "type": "Feature",
  "properties": {
    "iso:country":"US",
    "sg:address":"4625 Datura Rd",
    "sg:city":"Columbia",
    "sg:phone":"+1 803 782 4489",
    "sg:postcode":"29205",
    "sg:province":"SC",
    "sg:tags":[
        "fixture",
        "store"
    ],
    "wof:name":"Brantley & Assoc LLC",
    "wof:placetype":"venue"
},
  "geometry": {"coordinates":[-80.974171,33.997312],"type":"Point"}
}