{
  "type": "Feature",
  "properties": {
    "iso:country":"US",
    "sg:address":"1507 Nance St",
    "sg:city":"Newberry",
    "sg:classifiers":[
        {
            "category":"Government",
            "subcategory":"Police Station",
            "type":"Public Place"
        }
    ],
    "sg:phone":"+1 803 321 1010",
    "sg:postcode":"29108",
    "sg:province":"SC",
    "sg:tags":[
        "department"
    ],
    "wof:name":"Newberry Police Dept",
    "wof:placetype":"venue"
},
  "geometry": {"coordinates":[-81.623442,34.277904],"type":"Point"}
}