{
  "type": "Feature",
  "properties": {
    "addr:full":"5100 Notch Rd Columbia SC 29204",
    "addr:housenumber":"5100",
    "addr:postcode":"29204",
    "addr:street":"Notch Rd",
    "iso:country":"US",
    "sg:address":"5100 Notch Rd",
    "sg:city":"Columbia",
    "sg:classifiers":[
        {
            "category":"Retail",
            "subcategory":"Repair Shop",
            "type":"Services"
        }
    ],
    "sg:phone":"+1 803 736 2872",
    "sg:postcode":"29204",
    "sg:province":"SC",
    "sg:tags":[
        "jewelry"
    ],
    "wof:name":"Clocks Unique",
    "wof:placetype":"venue"
},
  "geometry": {"coordinates":[-80.98948,34.045272],"type":"Point"}
}