{
  "type": "Feature",
  "properties": {
    "iso:country":"US",
    "sg:address":"273 Collum Pond Rd",
    "sg:city":"Wagener",
    "sg:classifiers":[
        {
            "category":"Freight",
            "type":"Transportation"
        }
    ],
    "sg:phone":"+1 803 564 5839",
    "sg:postcode":"29164",
    "sg:province":"SC",
    "sg:tags":[
        "trucking"
    ],
    "wof:name":"Flatwoods Trucking",
    "wof:placetype":"venue"
},
  "geometry": {"coordinates":[-81.346405,33.668312],"type":"Point"}
}