{
  "type": "Feature",
  "properties": {
    "iso:country":"US",
    "sg:address":"2421 Bush River Rd",
    "sg:city":"Columbia",
    "sg:classifiers":[
        {
            "category":"Restaurant",
            "type":"Food & Drink"
        }
    ],
    "sg:phone":"+1 803 750 9292",
    "sg:postcode":"29210",
    "sg:province":"SC",
    "sg:website":"www.steak-out.com",
    "wof:name":"Steak-Out Charbroiled Delivery",
    "wof:placetype":"venue"
},
  "geometry": {"coordinates":[-81.126121,34.033893],"type":"Point"}
}