{
  "type": "Feature",
  "properties": {
    "iso:country":"US",
    "sg:address":"3674 Old Charleston Rd",
    "sg:city":"Johns Island",
    "sg:classifiers":[
        {
            "category":"Building & Trades",
            "subcategory":"Plumbing",
            "type":"Services"
        }
    ],
    "sg:phone":"+1 843 556 5636",
    "sg:postcode":"29455",
    "sg:province":"SC",
    "sg:tags":[
        "mechanical",
        "contractor"
    ],
    "wof:name":"Triad Mechanical Contractors",
    "wof:placetype":"venue"
},
  "geometry": {"coordinates":[-80.111644,32.801949],"type":"Point"}
}