{
  "type": "Feature",
  "properties": {
    "addr:full":"496 Garlington Rd Greenville SC 29615",
    "addr:housenumber":"496",
    "addr:postcode":"29615",
    "addr:street":"Garlington Rd",
    "iso:country":"US",
    "sg:address":"496 Garlington Rd",
    "sg:city":"Greenville",
    "sg:classifiers":[
        {
            "category":"Building & Trades",
            "subcategory":"Cleaning & Sanitation",
            "type":"Services"
        }
    ],
    "sg:phone":"+1 864 286 3323",
    "sg:postcode":"29615",
    "sg:province":"SC",
    "sg:tags":[
        "janitor"
    ],
    "wof:name":"Ace Building Maintenance",
    "wof:placetype":"venue"
},
  "geometry": {"coordinates":[-82.28779900000001,34.835285],"type":"Point"}
}