{
  "type": "Feature",
  "properties": {
    "addr:full":"408 Tirzah Church Rd Lancaster SC 29720",
    "addr:housenumber":"408",
    "addr:postcode":"29720",
    "addr:street":"Church Rd",
    "iso:country":"US",
    "sg:address":"408 Tirzah Church Rd",
    "sg:city":"Lancaster",
    "sg:classifiers":[
        {
            "category":"Building & Trades",
            "subcategory":"Construction",
            "type":"Services"
        }
    ],
    "sg:phone":"+1 803 285 3504",
    "sg:postcode":"29720",
    "sg:province":"SC",
    "sg:tags":[
        "floor",
        "laying",
        "contractor"
    ],
    "wof:name":"Quality Flooring",
    "wof:placetype":"venue"
},
  "geometry": {"coordinates":[-80.78897600000001,34.817113],"type":"Point"}
}