{
  "type": "Feature",
  "properties": {
    "iso:country":"US",
    "sg:address":"208 W Turner St",
    "sg:city":"Pageland",
    "sg:classifiers":[
        {
            "category":"Government",
            "subcategory":"Office",
            "type":"Public Place"
        }
    ],
    "sg:phone":"+1 843 672 5321",
    "sg:postcode":"29728",
    "sg:province":"SC",
    "sg:tags":[
        "state",
        "program"
    ],
    "wof:name":"Motor Vehicles Div",
    "wof:placetype":"venue"
},
  "geometry": {"coordinates":[-80.392872,34.767723],"type":"Point"}
}