{
  "type": "Feature",
  "properties": {
    "iso:country":"US",
    "sg:address":"1670 Hwy 17",
    "sg:city":"North Myrtle Bch",
    "sg:classifiers":[
        {
            "category":"Real Estate",
            "subcategory":"Real Estate Agent",
            "type":"Services"
        }
    ],
    "sg:phone":"+1 843 249 3491",
    "sg:postcode":"29582",
    "sg:province":"SC",
    "wof:name":"Mc Lamb Realty & Auction Co",
    "wof:placetype":"venue"
},
  "geometry": {"coordinates":[-78.658412,33.845544],"type":"Point"}
}