{
  "type": "Feature",
  "properties": {
    "iso:country":"US",
    "sg:address":"2050 Columbia Rd NE",
    "sg:city":"Orangeburg",
    "sg:classifiers":[
        {
            "category":"Banks & Credit Unions",
            "subcategory":"Bank",
            "type":"Services"
        }
    ],
    "sg:phone":"+1 803 536 4222",
    "sg:postcode":"29118",
    "sg:province":"SC",
    "sg:tags":[
        "depository",
        "banking",
        "check",
        "cashing"
    ],
    "wof:name":"Check n Go",
    "wof:placetype":"venue"
},
  "geometry": {"coordinates":[-80.86600799999999,33.516942],"type":"Point"}
}