{
  "type": "Feature",
  "properties": {
    "addr:full":"209 Northgate Cir Spartanburg SC 29316",
    "addr:housenumber":"209",
    "addr:postcode":"29316",
    "addr:street":"Northgate Cir",
    "iso:country":"US",
    "sg:address":"209 Northgate Cir",
    "sg:city":"Spartanburg",
    "sg:classifiers":[
        {
            "category":"Building & Trades",
            "subcategory":"Construction",
            "type":"Services"
        }
    ],
    "sg:phone":"+1 864 483 0599",
    "sg:postcode":"29316",
    "sg:province":"SC",
    "sg:tags":[
        "covering",
        "floor",
        "contractor"
    ],
    "wof:name":"Floor Coverings International",
    "wof:placetype":"venue"
},
  "geometry": {"coordinates":[-81.97475,35.07013],"type":"Point"}
}