{
  "type": "Feature",
  "properties": {
    "iso:country":"US",
    "sg:address":"605 N Pine St",
    "sg:city":"Seneca",
    "sg:classifiers":[
        {
            "category":"Sports & Exercise",
            "subcategory":"Gym",
            "type":"Entertainment"
        }
    ],
    "sg:phone":"+1 864 985 1333",
    "sg:postcode":"29678",
    "sg:province":"SC",
    "sg:tags":[
        "spa",
        "health"
    ],
    "wof:name":"A Natural Day Spa",
    "wof:placetype":"venue"
},
  "geometry": {"coordinates":[-82.958397,34.693778],"type":"Point"}
}