{
  "type": "Feature",
  "properties": {
    "addr:full":"824 Thackston Dr Spartanburg SC 29307",
    "addr:housenumber":"824",
    "addr:postcode":"29307",
    "addr:street":"Thackston Dr",
    "iso:country":"US",
    "sg:address":"824 Thackston Dr",
    "sg:city":"Spartanburg",
    "sg:classifiers":[
        {
            "category":"Building & Trades",
            "subcategory":"Cleaning & Sanitation",
            "type":"Services"
        }
    ],
    "sg:phone":"+1 864 205 6773",
    "sg:postcode":"29307",
    "sg:province":"SC",
    "sg:tags":[
        "ventilating",
        "system"
    ],
    "wof:name":"Spartanburg Air Duct Cleaning",
    "wof:placetype":"venue"
},
  "geometry": {"coordinates":[-81.851477,34.975118],"type":"Point"}
}