{
  "type": "Feature",
  "properties": {
    "addr:full":"420 Barton St Branchville SC 29432",
    "addr:housenumber":"420",
    "addr:postcode":"29432",
    "addr:street":"Barton St",
    "iso:country":"US",
    "sg:address":"420 Barton St",
    "sg:city":"Branchville",
    "sg:classifiers":[
        {
            "category":"Organizations",
            "subcategory":"Religious Organization",
            "type":"Services"
        }
    ],
    "sg:phone":"+1 803 274 8467",
    "sg:postcode":"29432",
    "sg:province":"SC",
    "sg:tags":[
        "church"
    ],
    "wof:name":"Branchville United Methodist",
    "wof:placetype":"venue"
},
  "geometry": {"coordinates":[-80.818191,33.248554],"type":"Point"}
}