{
  "type": "Feature",
  "properties": {
    "addr:full":"618 Drayton St Newberry SC 29108",
    "addr:housenumber":"618",
    "addr:postcode":"29108",
    "addr:street":"Drayton St",
    "iso:country":"US",
    "sg:address":"618 Drayton St",
    "sg:city":"Newberry",
    "sg:phone":"+1 803 276 0320",
    "sg:postcode":"29108",
    "sg:province":"SC",
    "sg:tags":[
        "gas"
    ],
    "wof:name":"Ellco Industries",
    "wof:placetype":"venue"
},
  "geometry": {"coordinates":[-81.61882,34.267778],"type":"Point"}
}