{
  "type": "Feature",
  "properties": {
    "addr:full":"15 Louise Ave Greenville SC 29617",
    "addr:housenumber":"15",
    "addr:postcode":"29617",
    "addr:street":"Louise Ave",
    "iso:country":"US",
    "sg:address":"15 Louise Ave",
    "sg:city":"Greenville",
    "sg:classifiers":[
        {
            "category":"Retail",
            "subcategory":"Repair Shop",
            "type":"Services"
        }
    ],
    "sg:phone":"+1 864 246 1642",
    "sg:postcode":"29617",
    "sg:province":"SC",
    "sg:tags":[
        "upholsterer"
    ],
    "wof:name":"Loopers Upholstery Shop",
    "wof:placetype":"venue"
},
  "geometry": {"coordinates":[-82.43772300000001,34.864922],"type":"Point"}
}