{
  "type": "Feature",
  "properties": {
    "addr:full":"4650 Boxwood Dr Myrtle Beach SC 29588",
    "addr:housenumber":"4650",
    "addr:postcode":"29588",
    "addr:street":"Boxwood Dr",
    "iso:country":"US",
    "sg:address":"4650 Boxwood Dr",
    "sg:city":"Myrtle Beach",
    "sg:classifiers":[
        {
            "category":"Restaurant",
            "type":"Food & Drink"
        }
    ],
    "sg:phone":"+1 843 626 5384",
    "sg:postcode":"29588",
    "sg:province":"SC",
    "sg:tags":[
        "eating"
    ],
    "wof:name":"Bangkok Restaurant",
    "wof:placetype":"venue"
},
  "geometry": {"coordinates":[-78.9923,33.687824],"type":"Point"}
}