{
  "type": "Feature",
  "properties": {
    "iso:country":"US",
    "sg:address":"37 New Orleans Rd",
    "sg:city":"Hilton Head Isle",
    "sg:classifiers":[
        {
            "category":"Manufacturing",
            "subcategory":"Lumber",
            "type":"Manufacturing & Wholesale Goods"
        }
    ],
    "sg:phone":"+1 843 842 6626",
    "sg:postcode":"29928",
    "sg:province":"SC",
    "sg:tags":[
        "hardwood",
        "flooring"
    ],
    "wof:name":"Louis Sterling's Magna-Dry",
    "wof:placetype":"venue"
},
  "geometry": {"coordinates":[-80.755377,32.157026],"type":"Point"}
}