{
  "type": "Feature",
  "properties": {
    "addr:full":"3007 Broad River Rd Columbia SC 29210",
    "addr:housenumber":"3007",
    "addr:postcode":"29210",
    "addr:street":"Broad River Rd",
    "iso:country":"US",
    "sg:address":"3007 Broad River Rd",
    "sg:city":"Columbia",
    "sg:classifiers":[
        {
            "category":"Building & Trades",
            "subcategory":"Cleaning & Sanitation",
            "type":"Services"
        }
    ],
    "sg:phone":"+1 803 798 8866",
    "sg:postcode":"29210",
    "sg:province":"SC",
    "sg:tags":[
        "dry",
        "venetian",
        "laundry",
        "blind"
    ],
    "wof:name":"Deluxe Cleaners",
    "wof:placetype":"venue"
},
  "geometry": {"coordinates":[-81.104401,34.048698],"type":"Point"}
}