{
  "type": "Feature",
  "properties": {
    "iso:country":"US",
    "sg:address":"1047 Berea Rd",
    "sg:city":"Columbia",
    "sg:classifiers":[
        {
            "category":"Manufacturing",
            "subcategory":"Metals",
            "type":"Manufacturing & Wholesale Goods"
        },
        {
            "category":"Wholesale",
            "subcategory":"Home Furnishings",
            "type":"Manufacturing & Wholesale Goods"
        }
    ],
    "sg:phone":"+1 803 799 9268",
    "sg:postcode":"29201",
    "sg:province":"SC",
    "sg:tags":[
        "equipment",
        "layer",
        "carpet",
        "establishment",
        "supply"
    ],
    "wof:name":"Ellis Flooring Sales Inc",
    "wof:placetype":"venue"
},
  "geometry": {"coordinates":[-81.01824499999999,33.971172],"type":"Point"}
}