{
  "type": "Feature",
  "properties": {
    "iso:country":"US",
    "sg:address":"1504 Turntable Rd",
    "sg:city":"Murrells Inlet",
    "sg:classifiers":[
        {
            "category":"Organizations",
            "subcategory":"Religious Organization",
            "type":"Services"
        }
    ],
    "sg:phone":"+1 843 651 8577",
    "sg:postcode":"29576",
    "sg:province":"SC",
    "sg:tags":[
        "church"
    ],
    "wof:name":"Holy Temple Church Of God",
    "wof:placetype":"venue"
},
  "geometry": {"coordinates":[-79.062614,33.546397],"type":"Point"}
}