{
  "type": "Feature",
  "properties": {
    "addr:full":"414 Lakewood Ln Anderson SC 29625",
    "addr:housenumber":"414",
    "addr:postcode":"29625",
    "addr:street":"Lakewood Ln",
    "iso:country":"US",
    "sg:address":"414 Lakewood Ln",
    "sg:city":"Anderson",
    "sg:classifiers":[
        {
            "category":"Farming",
            "subcategory":"Nursery",
            "type":"Manufacturing & Wholesale Goods"
        }
    ],
    "sg:phone":"+1 864 224 6788",
    "sg:postcode":"29625",
    "sg:province":"SC",
    "sg:tags":[
        "ornamental",
        "greenhouse"
    ],
    "wof:name":"Davis Greenhouses",
    "wof:placetype":"venue"
},
  "geometry": {"coordinates":[-82.740297,34.513105],"type":"Point"}
}