{
  "type": "Feature",
  "properties": {
    "iso:country":"US",
    "sg:address":"4064 W Belt Line Blvd",
    "sg:city":"Columbia",
    "sg:classifiers":[
        {
            "category":"Professional",
            "subcategory":"Lawyer & Legal Services",
            "type":"Services"
        }
    ],
    "sg:phone":"+1 803 254 4228",
    "sg:postcode":"29204",
    "sg:province":"SC",
    "sg:tags":[
        "attorney"
    ],
    "wof:name":"Julian M Sellers",
    "wof:placetype":"venue"
},
  "geometry": {"coordinates":[-81.00794999999999,34.036667],"type":"Point"}
}