{
  "type": "Feature",
  "properties": {
    "iso:country":"US",
    "sg:address":"417 W Lakeside Ave",
    "sg:city":"Columbia",
    "sg:classifiers":[
        {
            "category":"Real Estate",
            "subcategory":"Real Estate Agent",
            "type":"Services"
        }
    ],
    "sg:phone":"+1 803 779 7498",
    "sg:postcode":"29203",
    "sg:province":"SC",
    "wof:name":"Hopkins Rental",
    "wof:placetype":"venue"
},
  "geometry": {"coordinates":[-81.058922,34.047812],"type":"Point"}
}