{
  "type": "Feature",
  "properties": {
    "iso:country":"US",
    "sg:address":"1198 Whitman St SE",
    "sg:city":"Orangeburg",
    "sg:classifiers":[
        {
            "category":"Professional",
            "subcategory":"Business Services",
            "type":"Services"
        }
    ],
    "sg:phone":"+1 803 531 7087",
    "sg:postcode":"29115",
    "sg:province":"SC",
    "sg:tags":[
        "embroidery"
    ],
    "wof:name":"Wactor & Assoc",
    "wof:placetype":"venue"
},
  "geometry": {"coordinates":[-80.84490599999999,33.490978],"type":"Point"}
}