{
  "type": "Feature",
  "properties": {
    "iso:country":"US",
    "sg:address":"710 S Guignard Dr",
    "sg:city":"Sumter",
    "sg:classifiers":[
        {
            "category":"Wholesale",
            "subcategory":"Hardware",
            "type":"Manufacturing & Wholesale Goods"
        }
    ],
    "sg:phone":"+1 803 775 7355",
    "sg:postcode":"29150",
    "sg:province":"SC",
    "sg:tags":[
        "plumbing",
        "supply"
    ],
    "wof:name":"City Supply Co",
    "wof:placetype":"venue"
},
  "geometry": {"coordinates":[-80.353512,33.900297],"type":"Point"}
}