{
  "type": "Feature",
  "properties": {
    "addr:full":"306 N Elm St Pageland SC 29728",
    "addr:housenumber":"306",
    "addr:postcode":"29728",
    "addr:street":"N Elm St",
    "iso:country":"US",
    "sg:address":"306 N Elm St",
    "sg:city":"Pageland",
    "sg:classifiers":[
        {
            "category":"Food & Beverages",
            "subcategory":"Groceries & Convenience Stores",
            "type":"Retail Goods"
        }
    ],
    "sg:phone":"+1 843 672 3274",
    "sg:postcode":"29728",
    "sg:province":"SC",
    "sg:tags":[
        "grocer"
    ],
    "wof:name":"TJT Discount Grocery & Fish",
    "wof:placetype":"venue"
},
  "geometry": {"coordinates":[-80.400358,34.773839],"type":"Point"}
}