{
  "type": "Feature",
  "properties": {
    "iso:country":"US",
    "sg:address":"870 Anderson Ridge Rd",
    "sg:city":"Greer",
    "sg:classifiers":[
        {
            "category":"Building & Trades",
            "subcategory":"Electrical",
            "type":"Services"
        }
    ],
    "sg:phone":"+1 864 675 6146",
    "sg:postcode":"29681",
    "sg:province":"SC",
    "sg:tags":[
        "rigging",
        "theatrical",
        "sound",
        "lighting"
    ],
    "wof:name":"Productions Unlimited Inc",
    "wof:placetype":"venue"
},
  "geometry": {"coordinates":[-82.202946,34.815923],"type":"Point"}
}