{
  "type": "Feature",
  "properties": {
    "iso:country":"US",
    "sg:address":"2804 Bluff Rd",
    "sg:city":"Marion",
    "sg:classifiers":[
        {
            "category":"Bars & Pubs",
            "type":"Food & Drink"
        }
    ],
    "sg:phone":"+1 843 423 6699",
    "sg:postcode":"29571",
    "sg:province":"SC",
    "wof:name":"RNJ Sports Bar",
    "wof:placetype":"venue"
},
  "geometry": {"coordinates":[-79.354046,34.168279],"type":"Point"}
}