{
  "type": "Feature",
  "properties": {
    "iso:country":"US",
    "sg:address":"4249 Old Georgia Hwy",
    "sg:city":"Cowpens",
    "sg:classifiers":[
        {
            "category":"Restaurant",
            "type":"Food & Drink"
        }
    ],
    "sg:phone":"+1 864 463 2498",
    "sg:postcode":"29330",
    "sg:province":"SC",
    "wof:name":"Lil Thicketty Cafe",
    "wof:placetype":"venue"
},
  "geometry": {"coordinates":[-81.75179,35.015349],"type":"Point"}
}