{
  "type": "Feature",
  "properties": {
    "iso:country":"US",
    "sg:address":"530 Martin Luther King Jr Ave",
    "sg:city":"Kingstree",
    "sg:classifiers":[
        {
            "category":"Social Services",
            "subcategory":"Job Training",
            "type":"Services"
        }
    ],
    "sg:phone":"+1 843 354 7436",
    "sg:postcode":"29556",
    "sg:province":"SC",
    "sg:tags":[
        "rehab",
        "government"
    ],
    "wof:name":"South Carolina Job Svc",
    "wof:placetype":"venue"
},
  "geometry": {"coordinates":[-79.81969599999999,33.658712],"type":"Point"}
}