{
  "type": "Feature",
  "properties": {
    "iso:country":"US",
    "sg:address":"916 Lake Club Dr",
    "sg:city":"Rock Hill",
    "sg:classifiers":[
        {
            "category":"Professional",
            "subcategory":"Management & Consulting",
            "type":"Services"
        }
    ],
    "sg:phone":"+1 803 366 4238",
    "sg:postcode":"29732",
    "sg:province":"SC",
    "sg:tags":[
        "consultant"
    ],
    "wof:name":"RFW Corp",
    "wof:placetype":"venue"
},
  "geometry": {"coordinates":[-81.04734000000001,35.023226],"type":"Point"}
}