{
  "type": "Feature",
  "properties": {
    "iso:country":"US",
    "sg:address":"841 E Liberty St",
    "sg:city":"Sumter",
    "sg:classifiers":[
        {
            "category":"Wholesale",
            "subcategory":"Electrical",
            "type":"Manufacturing & Wholesale Goods"
        }
    ],
    "sg:phone":"+1 803 778 0022",
    "sg:postcode":"29153",
    "sg:province":"SC",
    "sg:tags":[
        "equipment",
        "electric",
        "supply"
    ],
    "wof:name":"Santee Electric Supply Co Inc",
    "wof:placetype":"venue"
},
  "geometry": {"coordinates":[-80.311734,33.926672],"type":"Point"}
}