{
  "type": "Feature",
  "properties": {
    "addr:full":"2095 N Beltline Blvd Columbia SC 29204",
    "addr:housenumber":"2095",
    "addr:postcode":"29204",
    "addr:street":"N Beltline Blvd",
    "iso:country":"US",
    "sg:address":"2095 N Beltline Blvd",
    "sg:city":"Columbia",
    "sg:classifiers":[
        {
            "category":"Banks & Credit Unions",
            "subcategory":"Bank",
            "type":"Services"
        },
        {
            "category":"Banks & Credit Unions",
            "subcategory":"Financial Services",
            "type":"Services"
        }
    ],
    "sg:phone":"+1 803 765 4940",
    "sg:postcode":"29204",
    "sg:province":"SC",
    "sg:tags":[
        "broker",
        "mortgage"
    ],
    "sg:website":"www.bankofamerica.com",
    "wof:name":"Bank of America",
    "wof:placetype":"venue"
},
  "geometry": {"coordinates":[-80.98736,34.015352],"type":"Point"}
}