{
  "type": "Feature",
  "properties": {
    "iso:country":"US",
    "sg:address":"3520 US Hwy 501 N",
    "sg:city":"Marion",
    "sg:classifiers":[
        {
            "category":"Organizations",
            "subcategory":"Religious Organization",
            "type":"Services"
        }
    ],
    "sg:phone":"+1 843 423 4212",
    "sg:postcode":"29571",
    "sg:province":"SC",
    "sg:tags":[
        "church"
    ],
    "wof:name":"Bethlehem AME Church",
    "wof:placetype":"venue"
},
  "geometry": {"coordinates":[-79.38848900000001,34.230329],"type":"Point"}
}