{
  "type": "Feature",
  "properties": {
    "addr:full":"1025 Woodruff Rd Greenville SC 29607",
    "addr:housenumber":"1025",
    "addr:postcode":"29607",
    "addr:street":"Woodruff Rd",
    "iso:country":"US",
    "sg:address":"1025 Woodruff Rd",
    "sg:city":"Greenville",
    "sg:classifiers":[
        {
            "category":"Real Estate",
            "subcategory":"Real Estate Operator",
            "type":"Services"
        }
    ],
    "sg:phone":"+1 864 288 0573",
    "sg:postcode":"29607",
    "sg:province":"SC",
    "sg:tags":[
        "mall",
        "shopping",
        "center"
    ],
    "sg:website":"www.shopgreenvillemall.com",
    "wof:name":"Greenville Mall",
    "wof:placetype":"venue"
},
  "geometry": {"coordinates":[-82.30865,34.832844],"type":"Point"}
}