{
  "type": "Feature",
  "properties": {
    "iso:country":"US",
    "sg:address":"1775 Ashley River Rd",
    "sg:city":"Charleston",
    "sg:classifiers":[
        {
            "category":"Government",
            "subcategory":"Office",
            "type":"Public Place"
        }
    ],
    "sg:phone":"+1 843 556 6310",
    "sg:postcode":"29407",
    "sg:province":"SC",
    "wof:name":"St Andrews Public Svc District",
    "wof:placetype":"venue"
},
  "geometry": {"coordinates":[-80.016228,32.801041],"type":"Point"}
}