{
  "type": "Feature",
  "properties": {
    "addr:full":"8631 Bentwood Dr Charleston SC 29406",
    "addr:housenumber":"8631",
    "addr:postcode":"29406",
    "addr:street":"Bentwood Dr",
    "iso:country":"US",
    "sg:address":"8631 Bentwood Dr",
    "sg:city":"Charleston",
    "sg:classifiers":[
        {
            "category":"Building & Trades",
            "subcategory":"Electrical",
            "type":"Services"
        }
    ],
    "sg:phone":"+1 843 553 9605",
    "sg:postcode":"29406",
    "sg:province":"SC",
    "sg:tags":[
        "electrical",
        "contractor"
    ],
    "wof:name":"Rusty Cohen Electric",
    "wof:placetype":"venue"
},
  "geometry": {"coordinates":[-80.068573,32.960699],"type":"Point"}
}