{
  "type": "Feature",
  "properties": {
    "addr:full":"1027 S Pendleton St Easley SC 29642",
    "addr:housenumber":"1027",
    "addr:postcode":"29642",
    "addr:street":"S Pendleton St",
    "iso:country":"US",
    "sg:address":"1027 S Pendleton St",
    "sg:city":"Easley",
    "sg:classifiers":[
        {
            "category":"Personal",
            "type":"Services"
        }
    ],
    "sg:phone":"+1 864 859 8658",
    "sg:postcode":"29642",
    "sg:province":"SC",
    "sg:tags":[
        "wear",
        "formal"
    ],
    "wof:name":"Gregory's Formal Wear",
    "wof:placetype":"venue"
},
  "geometry": {"coordinates":[-82.60213299999999,34.812681],"type":"Point"}
}