{
  "type": "Feature",
  "properties": {
    "iso:country":"US",
    "sg:address":"1540 Airport Rd",
    "sg:city":"Sumter",
    "sg:classifiers":[
        {
            "category":"Food & Beverages",
            "subcategory":"Groceries & Convenience Stores",
            "type":"Retail Goods"
        }
    ],
    "sg:phone":"+1 803 469 9262",
    "sg:postcode":"29153",
    "sg:province":"SC",
    "sg:tags":[
        "product",
        "snack"
    ],
    "wof:name":"Tom's Foods Inc",
    "wof:placetype":"venue"
},
  "geometry": {"coordinates":[-80.34912,33.963735],"type":"Point"}
}