{
  "type": "Feature",
  "properties": {
    "addr:full":"895 Farm Quarter Rd Mount Pleasant SC 29464",
    "addr:housenumber":"895",
    "addr:postcode":"29464",
    "addr:street":"Farm Quarter Rd",
    "iso:country":"US",
    "sg:address":"895 Farm Quarter Rd",
    "sg:city":"Mount Pleasant",
    "sg:classifiers":[
        {
            "category":"Building & Trades",
            "subcategory":"Construction",
            "type":"Services"
        }
    ],
    "sg:phone":"+1 843 881 7956",
    "sg:postcode":"29464",
    "sg:province":"SC",
    "sg:tags":[
        "house"
    ],
    "wof:name":"System Builders LLC",
    "wof:placetype":"venue"
},
  "geometry": {"coordinates":[-79.83338500000001,32.836336],"type":"Point"}
}