{
  "type": "Feature",
  "properties": {
    "iso:country":"US",
    "sg:address":"10476 Dunbarton Blvd",
    "sg:city":"Barnwell",
    "sg:classifiers":[
        {
            "category":"Autos & Motor Vehicles",
            "subcategory":"Automobile Sales",
            "type":"Retail Goods"
        }
    ],
    "sg:phone":"+1 803 259 5524",
    "sg:postcode":"29812",
    "sg:province":"SC",
    "sg:tags":[
        "car",
        "dealer"
    ],
    "sg:website":"www.b-bford.com",
    "wof:name":"B & B Ford Inc",
    "wof:placetype":"venue"
},
  "geometry": {"coordinates":[-81.37654,33.243631],"type":"Point"}
}