{
  "type": "Feature",
  "properties": {
    "iso:country":"US",
    "sg:address":"923 Old York Rd",
    "sg:city":"Chester",
    "sg:classifiers":[
        {
            "category":"Building & Trades",
            "subcategory":"Construction",
            "type":"Services"
        }
    ],
    "sg:phone":"+1 803 581 6000",
    "sg:postcode":"29706",
    "sg:province":"SC",
    "sg:tags":[
        "bridge",
        "builder"
    ],
    "wof:name":"United Contractors Inc",
    "wof:placetype":"venue"
},
  "geometry": {"coordinates":[-81.200408,34.736837],"type":"Point"}
}