{
  "type": "Feature",
  "properties": {
    "addr:full":"110 Perpetual Square Dr Anderson SC 29621",
    "addr:housenumber":"110",
    "addr:postcode":"29621",
    "addr:street":"Perpetual Square Dr",
    "iso:country":"US",
    "sg:address":"110 Perpetual Square Dr",
    "sg:city":"Anderson",
    "sg:classifiers":[
        {
            "category":"Health Services",
            "subcategory":"Doctor",
            "type":"Services"
        }
    ],
    "sg:phone":"+1 864 261 9888",
    "sg:postcode":"29621",
    "sg:province":"SC",
    "sg:tags":[
        "physician",
        "surgeon"
    ],
    "wof:name":"Paradigm Medical Svc",
    "wof:placetype":"venue"
},
  "geometry": {"coordinates":[-82.630218,34.552461],"type":"Point"}
}