{
  "type": "Feature",
  "properties": {
    "iso:country":"US",
    "sg:address":"110 N Rutherford Rd",
    "sg:city":"Greer",
    "sg:classifiers":[
        {
            "category":"Education",
            "subcategory":"School",
            "type":"Public Place"
        }
    ],
    "sg:phone":"+1 864 877 6232",
    "sg:postcode":"29651",
    "sg:province":"SC",
    "wof:name":"Pleasantview Baptist School",
    "wof:placetype":"venue"
},
  "geometry": {"coordinates":[-82.28312200000001,34.970189],"type":"Point"}
}