{
  "type": "Feature",
  "properties": {
    "addr:full":"340 S Vanderhorst St Winnsboro SC 29180",
    "addr:housenumber":"340",
    "addr:postcode":"29180",
    "addr:street":"S Vanderhorst St",
    "iso:country":"US",
    "sg:address":"340 S Vanderhorst St",
    "sg:city":"Winnsboro",
    "sg:classifiers":[
        {
            "category":"Home & Garden",
            "subcategory":"Building Materials",
            "type":"Retail Goods"
        }
    ],
    "sg:phone":"+1 803 635 4711",
    "sg:postcode":"29180",
    "sg:province":"SC",
    "wof:name":"Winnsboro Builders Supply",
    "wof:placetype":"venue"
},
  "geometry": {"coordinates":[-81.086507,34.375698],"type":"Point"}
}