{
  "type": "Feature",
  "properties": {
    "iso:country":"US",
    "sg:address":"1550 Meeting Street Rd",
    "sg:city":"North Charleston",
    "sg:classifiers":[
        {
            "category":"Organizations",
            "subcategory":"Religious Organization",
            "type":"Services"
        }
    ],
    "sg:phone":"+1 843 723 7851",
    "sg:postcode":"29405",
    "sg:province":"SC",
    "sg:tags":[
        "church"
    ],
    "wof:name":"Jehovah's Witness",
    "wof:placetype":"venue"
},
  "geometry": {"coordinates":[-79.950795,32.819303],"type":"Point"}
}