{
  "type": "Feature",
  "properties": {
    "iso:country":"US",
    "sg:address":"1109 Main St",
    "sg:city":"Newberry",
    "sg:classifiers":[
        {
            "category":"Organizations",
            "subcategory":"Professional Association",
            "type":"Services"
        }
    ],
    "sg:phone":"+1 803 276 4274",
    "sg:postcode":"29108",
    "sg:province":"SC",
    "sg:tags":[
        "chambers",
        "commerce"
    ],
    "wof:name":"Newberry County Chamber-Cmmrce",
    "wof:placetype":"venue"
},
  "geometry": {"coordinates":[-81.61998199999999,34.274342],"type":"Point"}
}