{
  "type": "Feature",
  "properties": {
    "addr:full":"1905 McKelvey Rd Fountain Inn SC 29644",
    "addr:housenumber":"1905",
    "addr:postcode":"29644",
    "addr:street":"Mckelvey Rd",
    "iso:country":"US",
    "sg:address":"1905 McKelvey Rd",
    "sg:city":"Fountain Inn",
    "sg:classifiers":[
        {
            "category":"Professional",
            "subcategory":"Management & Consulting",
            "type":"Services"
        }
    ],
    "sg:phone":"+1 864 467 0055",
    "sg:postcode":"29644",
    "sg:province":"SC",
    "sg:tags":[
        "consultant"
    ],
    "wof:name":"Morningstar Consultants Inc",
    "wof:placetype":"venue"
},
  "geometry": {"coordinates":[-82.31225999999999,34.620903],"type":"Point"}
}