{
  "type": "Feature",
  "properties": {
    "iso:country":"US",
    "sg:address":"101 Devenger Pl",
    "sg:city":"Greer",
    "sg:classifiers":[
        {
            "category":"Wholesale",
            "subcategory":"Electrical",
            "type":"Manufacturing & Wholesale Goods"
        }
    ],
    "sg:phone":"+1 864 322 5200",
    "sg:postcode":"29650",
    "sg:province":"SC",
    "sg:tags":[
        "control",
        "security",
        "system"
    ],
    "wof:name":"Dynamark Security Ctr",
    "wof:placetype":"venue"
},
  "geometry": {"coordinates":[-82.292519,34.86783],"type":"Point"}
}