{
  "type": "Feature",
  "properties": {
    "addr:full":"1925 N Ocean Blvd North Myrtle Bch SC 29582",
    "addr:housenumber":"1925",
    "addr:postcode":"29582",
    "addr:street":"N Ocean Blvd North Myrtle",
    "iso:country":"US",
    "sg:address":"1925 N Ocean Blvd",
    "sg:city":"North Myrtle Bch",
    "sg:classifiers":[
        {
            "category":"Travel",
            "subcategory":"Hotels & Motels",
            "type":"Entertainment"
        }
    ],
    "sg:phone":"+1 843 249 1332",
    "sg:postcode":"29582",
    "sg:province":"SC",
    "wof:name":"Sea Horse Motel",
    "wof:placetype":"venue"
},
  "geometry": {"coordinates":[-78.646241,33.82717],"type":"Point"}
}