{
  "type": "Feature",
  "properties": {
    "iso:country":"US",
    "sg:address":"1000 N Eden Dr",
    "sg:city":"Cayce",
    "sg:classifiers":[
        {
            "category":"Building & Trades",
            "subcategory":"Construction",
            "type":"Services"
        }
    ],
    "sg:phone":"+1 803 939 1330",
    "sg:postcode":"29033",
    "sg:province":"SC",
    "sg:tags":[
        "contractor"
    ],
    "wof:name":"Bailey & Yobs Inc",
    "wof:placetype":"venue"
},
  "geometry": {"coordinates":[-81.07379899999999,33.946499],"type":"Point"}
}