{
  "type": "Feature",
  "properties": {
    "addr:full":"558 Spruce St Florence SC 29501",
    "addr:housenumber":"558",
    "addr:postcode":"29501",
    "addr:street":"Spruce St",
    "iso:country":"US",
    "sg:address":"558 Spruce St",
    "sg:city":"Florence",
    "sg:classifiers":[
        {
            "category":"Museum",
            "type":"Entertainment"
        }
    ],
    "sg:phone":"+1 843 662 3351",
    "sg:postcode":"29501",
    "sg:province":"SC",
    "wof:name":"Florence Museum",
    "wof:placetype":"venue"
},
  "geometry": {"coordinates":[-79.77587699999999,34.18716],"type":"Point"}
}