{
  "type": "Feature",
  "properties": {
    "iso:country":"US",
    "sg:address":"1043 Lincoln Ave",
    "sg:city":"North Charleston",
    "sg:classifiers":[
        {
            "category":"Retail",
            "subcategory":"Auto Repair",
            "type":"Services"
        }
    ],
    "sg:phone":"+1 843 740 0984",
    "sg:postcode":"29405",
    "sg:province":"SC",
    "sg:tags":[
        "truck"
    ],
    "wof:name":"P & M Heavy Truck Repair Inc",
    "wof:placetype":"venue"
},
  "geometry": {"coordinates":[-79.975537,32.891534],"type":"Point"}
}