{
  "type": "Feature",
  "properties": {
    "iso:country":"US",
    "sg:address":"3118 Dudley Rd",
    "sg:city":"West Columbia",
    "sg:classifiers":[
        {
            "category":"Taxi",
            "type":"Transportation"
        }
    ],
    "sg:phone":"+1 803 622 2083",
    "sg:postcode":"29170",
    "sg:province":"SC",
    "sg:tags":[
        "taxicab"
    ],
    "wof:name":"Alec's Airport Taxi",
    "wof:placetype":"venue"
},
  "geometry": {"coordinates":[-81.124982,33.982716],"type":"Point"}
}