{
  "type": "Feature",
  "properties": {
    "iso:country":"US",
    "sg:address":"11 Fox Den Ct",
    "sg:city":"Hilton Head Isle",
    "sg:classifiers":[
        {
            "category":"Building & Trades",
            "subcategory":"Construction",
            "type":"Services"
        }
    ],
    "sg:phone":"+1 843 683 1113",
    "sg:postcode":"29926",
    "sg:province":"SC",
    "sg:tags":[
        "paving",
        "contractor"
    ],
    "wof:name":"Infrastructure Pavement Tech",
    "wof:placetype":"venue"
},
  "geometry": {"coordinates":[-80.728055,32.237136],"type":"Point"}
}