{
  "type": "Feature",
  "properties": {
    "iso:country":"US",
    "sg:address":"236 Silverbell Dr",
    "sg:city":"Spartanburg",
    "sg:classifiers":[
        {
            "category":"Professional",
            "type":"Services"
        }
    ],
    "sg:phone":"+1 864 814 3505",
    "sg:postcode":"29316",
    "sg:province":"SC",
    "sg:tags":[
        "establishment"
    ],
    "wof:name":"Hillwood Co",
    "wof:placetype":"venue"
},
  "geometry": {"coordinates":[-81.947361,35.03112],"type":"Point"}
}