{
  "type": "Feature",
  "properties": {
    "addr:full":"850 Jason Blvd Myrtle Beach SC 29577",
    "addr:housenumber":"850",
    "addr:postcode":"29577",
    "addr:street":"Jason Blvd",
    "iso:country":"US",
    "sg:address":"850 Jason Blvd",
    "sg:city":"Myrtle Beach",
    "sg:classifiers":[
        {
            "category":"Autos & Motor Vehicles",
            "subcategory":"Auto Supplies",
            "type":"Retail Goods"
        }
    ],
    "sg:phone":"+1 843 839 0048",
    "sg:postcode":"29577",
    "sg:province":"SC",
    "sg:tags":[
        "battery"
    ],
    "wof:name":"Batteries Plus",
    "wof:placetype":"venue"
},
  "geometry": {"coordinates":[-78.91158799999999,33.710342],"type":"Point"}
}