{
  "type": "Feature",
  "properties": {
    "iso:country":"US",
    "sg:address":"5400 Farrow Rd",
    "sg:city":"Columbia",
    "sg:classifiers":[
        {
            "category":"Food & Beverages",
            "subcategory":"Groceries & Convenience Stores",
            "type":"Retail Goods"
        }
    ],
    "sg:phone":"+1 803 754 4475",
    "sg:postcode":"29203",
    "sg:province":"SC",
    "wof:name":"Stop & Save",
    "wof:placetype":"venue"
},
  "geometry": {"coordinates":[-81.01370199999999,34.047199],"type":"Point"}
}