{
  "type": "Feature",
  "properties": {
    "iso:country":"US",
    "sg:address":"65 Century Cir",
    "sg:city":"Greenville",
    "sg:classifiers":[
        {
            "category":"Real Estate",
            "subcategory":"Real Estate Operator",
            "type":"Services"
        }
    ],
    "sg:phone":"+1 864 232 9544",
    "sg:postcode":"29607",
    "sg:province":"SC",
    "sg:tags":[
        "apartment",
        "complex"
    ],
    "wof:name":"Stonesthrow 1765",
    "wof:placetype":"venue"
},
  "geometry": {"coordinates":[-82.36182599999999,34.859406],"type":"Point"}
}