{
  "type": "Feature",
  "properties": {
    "iso:country":"US",
    "sg:address":"610 Augusta Rd",
    "sg:city":"North Augusta",
    "sg:classifiers":[
        {
            "category":"Banks & Credit Unions",
            "subcategory":"Bank",
            "type":"Services"
        }
    ],
    "sg:phone":"+1 803 442 9004",
    "sg:postcode":"29822",
    "sg:province":"SC",
    "sg:tags":[
        "depository",
        "banking"
    ],
    "wof:name":"Cash Now",
    "wof:placetype":"venue"
},
  "geometry": {"coordinates":[-81.892108,33.496848],"type":"Point"}
}