{
  "type": "Feature",
  "properties": {
    "addr:full":"100 Lyman Lodge Rd Lyman SC 29365",
    "addr:housenumber":"100",
    "addr:postcode":"29365",
    "addr:street":"Lyman Lodge Rd",
    "iso:country":"US",
    "sg:address":"100 Lyman Lodge Rd",
    "sg:city":"Lyman",
    "sg:classifiers":[
        {
            "category":"Travel",
            "subcategory":"Hotels & Motels",
            "type":"Entertainment"
        }
    ],
    "sg:phone":"+1 864 879 0804",
    "sg:postcode":"29365",
    "sg:province":"SC",
    "sg:tags":[
        "resort"
    ],
    "wof:name":"Lyman Lake Lodge",
    "wof:placetype":"venue"
},
  "geometry": {"coordinates":[-82.19868700000001,34.992619],"type":"Point"}
}