{
  "type": "Feature",
  "properties": {
    "iso:country":"US",
    "sg:address":"900 Johnnie Dodds Blvd",
    "sg:city":"Mount Pleasant",
    "sg:classifiers":[
        {
            "category":"Building & Trades",
            "subcategory":"Construction",
            "type":"Services"
        }
    ],
    "sg:phone":"+1 843 216 0022",
    "sg:postcode":"29464",
    "sg:province":"SC",
    "sg:tags":[
        "housing",
        "program"
    ],
    "wof:name":"Charleston Affordable Housing",
    "wof:placetype":"venue"
},
  "geometry": {"coordinates":[-79.86908699999999,32.810807],"type":"Point"}
}