{
  "type": "Feature",
  "properties": {
    "iso:country":"US",
    "sg:address":"759 Century Cir",
    "sg:city":"Conway",
    "sg:classifiers":[
        {
            "category":"Government",
            "subcategory":"Office",
            "type":"Public Place"
        }
    ],
    "sg:phone":"+1 843 347 4604",
    "sg:postcode":"29526",
    "sg:province":"SC",
    "sg:website":"www.myrtlebeachdevelopment.com",
    "wof:name":"Partner Economics Dev Corp",
    "wof:placetype":"venue"
},
  "geometry": {"coordinates":[-78.99448,33.799967],"type":"Point"}
}