{
  "type": "Feature",
  "properties": {
    "iso:country":"US",
    "sg:address":"1921 Woods Dr",
    "sg:city":"Florence",
    "sg:classifiers":[
        {
            "category":"Building & Trades",
            "subcategory":"Construction",
            "type":"Services"
        }
    ],
    "sg:phone":"+1 843 245 3252",
    "sg:postcode":"29505",
    "sg:province":"SC",
    "sg:tags":[
        "house"
    ],
    "wof:name":"RR Builders",
    "wof:placetype":"venue"
},
  "geometry": {"coordinates":[-79.799465,34.159685],"type":"Point"}
}