{
  "type": "Feature",
  "properties": {
    "addr:full":"3634 Humbert Rd Johns Island SC 29455",
    "addr:housenumber":"3634",
    "addr:postcode":"29455",
    "addr:street":"Humbert Rd",
    "iso:country":"US",
    "sg:address":"3634 Humbert Rd",
    "sg:city":"Johns Island",
    "sg:classifiers":[
        {
            "category":"Building & Trades",
            "subcategory":"Plumbing",
            "type":"Services"
        }
    ],
    "sg:phone":"+1 843 559 7515",
    "sg:postcode":"29455",
    "sg:province":"SC",
    "sg:tags":[
        "plumbing",
        "contractor"
    ],
    "wof:name":"Al Naumann Plumbing Inc",
    "wof:placetype":"venue"
},
  "geometry": {"coordinates":[-80.108565,32.754941],"type":"Point"}
}