{
  "type": "Feature",
  "properties": {
    "iso:country":"US",
    "sg:address":"3935 Sunset Blvd",
    "sg:city":"West Columbia",
    "sg:classifiers":[
        {
            "category":"Wholesale",
            "subcategory":"Metals & Minerals",
            "type":"Manufacturing & Wholesale Goods"
        }
    ],
    "sg:phone":"+1 803 781 7679",
    "sg:postcode":"29169",
    "sg:province":"SC",
    "sg:tags":[
        "center"
    ],
    "wof:name":"Franklin E Taylor",
    "wof:placetype":"venue"
},
  "geometry": {"coordinates":[-81.144256,34.008028],"type":"Point"}
}