{
  "type": "Feature",
  "properties": {
    "addr:full":"3426 Clemson Blvd Anderson SC 29621",
    "addr:housenumber":"3426",
    "addr:postcode":"29621",
    "addr:street":"Clemson Blvd",
    "iso:country":"US",
    "sg:address":"3426 Clemson Blvd",
    "sg:city":"Anderson",
    "sg:classifiers":[
        {
            "category":"Restaurant",
            "type":"Food & Drink"
        }
    ],
    "sg:menulink":"http://www.allmenus.com/sc/anderson/128211-red-lobster/menu/",
    "sg:phone":"+1 864 224 8709",
    "sg:postcode":"29621",
    "sg:province":"SC",
    "sg:tags":[
        "seafood",
        "american"
    ],
    "wof:name":"Red Lobster",
    "wof:placetype":"venue"
},
  "geometry": {"coordinates":[-82.67382600000001,34.54908],"type":"Point"}
}