{
  "type": "Feature",
  "properties": {
    "iso:country":"US",
    "sg:address":"102 Bonneau Ct",
    "sg:city":"Summerville",
    "sg:classifiers":[
        {
            "category":"Freight",
            "type":"Transportation"
        }
    ],
    "sg:phone":"+1 843 873 8000",
    "sg:postcode":"29485",
    "sg:province":"SC",
    "sg:tags":[
        "trucking"
    ],
    "wof:name":"L & D Logistics",
    "wof:placetype":"venue"
},
  "geometry": {"coordinates":[-80.190515,32.978798],"type":"Point"}
}