{
  "type": "Feature",
  "properties": {
    "addr:full":"2815 Gervais St Columbia SC 29204",
    "addr:housenumber":"2815",
    "addr:postcode":"29204",
    "addr:street":"Gervais St",
    "iso:country":"US",
    "sg:address":"2815 Gervais St",
    "sg:city":"Columbia",
    "sg:classifiers":[
        {
            "category":"Real Estate",
            "subcategory":"Architect",
            "type":"Services"
        }
    ],
    "sg:phone":"+1 803 254 5050",
    "sg:postcode":"29204",
    "sg:province":"SC",
    "wof:name":"Nichols David M",
    "wof:placetype":"venue"
},
  "geometry": {"coordinates":[-81.000198,34.011101],"type":"Point"}
}