{
  "type": "Feature",
  "properties": {
    "addr:full":"411 N Coit St Florence SC 29501",
    "addr:housenumber":"411",
    "addr:postcode":"29501",
    "addr:street":"N Coit St",
    "iso:country":"US",
    "sg:address":"411 N Coit St",
    "sg:city":"Florence",
    "sg:classifiers":[
        {
            "category":"Personal",
            "subcategory":"Beauty Salon",
            "type":"Services"
        }
    ],
    "sg:phone":"+1 843 673 0894",
    "sg:postcode":"29501",
    "sg:province":"SC",
    "wof:name":"Family Image",
    "wof:placetype":"venue"
},
  "geometry": {"coordinates":[-79.770911,34.202975],"type":"Point"}
}