{
  "type": "Feature",
  "properties": {
    "addr:full":"168 Willimon Rd Pickens SC 29671",
    "addr:housenumber":"168",
    "addr:postcode":"29671",
    "addr:street":"Willimon Rd",
    "iso:country":"US",
    "sg:address":"168 Willimon Rd",
    "sg:city":"Pickens",
    "sg:classifiers":[
        {
            "category":"Utilities",
            "subcategory":"Telephone",
            "type":"Services"
        }
    ],
    "sg:phone":"+1 704 607 3975",
    "sg:postcode":"29671",
    "sg:province":"SC",
    "sg:tags":[
        "communications"
    ],
    "wof:name":"Hnb Inc",
    "wof:placetype":"venue"
},
  "geometry": {"coordinates":[-82.73524999999999,34.879377],"type":"Point"}
}