{
  "type": "Feature",
  "properties": {
    "addr:full":"1102 Hillside Dr Charleston SC 29407",
    "addr:housenumber":"1102",
    "addr:postcode":"29407",
    "addr:street":"Hillside Dr",
    "iso:country":"US",
    "sg:address":"1102 Hillside Dr",
    "sg:city":"Charleston",
    "sg:classifiers":[
        {
            "category":"Real Estate",
            "subcategory":"Real Estate Operator",
            "type":"Services"
        }
    ],
    "sg:phone":"+1 843 763 5378",
    "sg:postcode":"29407",
    "sg:province":"SC",
    "sg:tags":[
        "building",
        "apartment"
    ],
    "wof:name":"River Oaks Apartments",
    "wof:placetype":"venue"
},
  "geometry": {"coordinates":[-79.992907,32.797016],"type":"Point"}
}