{
  "type": "Feature",
  "properties": {
    "iso:country":"US",
    "sg:address":"3080 Whitestone Glendale Rd",
    "sg:city":"Spartanburg",
    "sg:classifiers":[
        {
            "category":"Autos & Motor Vehicles",
            "subcategory":"Automobile Sales",
            "type":"Retail Goods"
        }
    ],
    "sg:phone":"+1 864 583 1748",
    "sg:postcode":"29302",
    "sg:province":"SC",
    "sg:tags":[
        "sport",
        "trailer",
        "utility"
    ],
    "wof:name":"Mack's Metal Fab",
    "wof:placetype":"venue"
},
  "geometry": {"coordinates":[-81.840642,34.941106],"type":"Point"}
}