{
  "type": "Feature",
  "properties": {
    "addr:full":"1219 Sherwood Rd Columbia SC 29204",
    "addr:housenumber":"1219",
    "addr:postcode":"29204",
    "addr:street":"Sherwood Rd",
    "iso:country":"US",
    "sg:address":"1219 Sherwood Rd",
    "sg:city":"Columbia",
    "sg:classifiers":[
        {
            "category":"Wholesale",
            "subcategory":"Durable Goods & Equipment",
            "type":"Manufacturing & Wholesale Goods"
        }
    ],
    "sg:phone":"+1 803 779 8236",
    "sg:postcode":"29204",
    "sg:province":"SC",
    "sg:tags":[
        "magnet",
        "magnetic",
        "devices"
    ],
    "wof:name":"Jeffrey F Siedel",
    "wof:placetype":"venue"
},
  "geometry": {"coordinates":[-80.99936700000001,34.012166],"type":"Point"}
}