{
  "type": "Feature",
  "properties": {
    "iso:country":"US",
    "sg:address":"525 Columbia Ave",
    "sg:city":"Lexington",
    "sg:classifiers":[
        {
            "category":"Wholesale",
            "subcategory":"Farm Supplies",
            "type":"Manufacturing & Wholesale Goods"
        },
        {
            "category":"Home & Garden",
            "subcategory":"Garden Supply",
            "type":"Retail Goods"
        }
    ],
    "sg:phone":"+1 803 359 4275",
    "sg:postcode":"29072",
    "sg:province":"SC",
    "sg:tags":[
        "feed"
    ],
    "wof:name":"Consumers Feed & Seed Store",
    "wof:placetype":"venue"
},
  "geometry": {"coordinates":[-81.23635299999999,33.989148],"type":"Point"}
}