{
  "type": "Feature",
  "properties": {
    "iso:country":"US",
    "sg:address":"1701 Pamplico Hwy",
    "sg:city":"Florence",
    "sg:classifiers":[
        {
            "category":"Professional",
            "type":"Services"
        }
    ],
    "sg:phone":"+1 843 669 5943",
    "sg:postcode":"29505",
    "sg:province":"SC",
    "sg:tags":[
        "establishment"
    ],
    "wof:name":"Florence County Customs",
    "wof:placetype":"venue"
},
  "geometry": {"coordinates":[-79.740128,34.154351],"type":"Point"}
}