{
  "type": "Feature",
  "properties": {
    "addr:full":"207 W Church St Anderson SC 29624",
    "addr:housenumber":"207",
    "addr:postcode":"29624",
    "addr:street":"W Church St",
    "iso:country":"US",
    "sg:address":"207 W Church St",
    "sg:city":"Anderson",
    "sg:classifiers":[
        {
            "category":"Personal",
            "subcategory":"Barber",
            "type":"Services"
        }
    ],
    "sg:phone":"+1 864 225 0238",
    "sg:postcode":"29624",
    "sg:province":"SC",
    "wof:name":"Friendly Barber Shop",
    "wof:placetype":"venue"
},
  "geometry": {"coordinates":[-82.65292700000001,34.501639],"type":"Point"}
}