{
  "type": "Feature",
  "properties": {
    "addr:full":"414 N Fant St Anderson SC 29621",
    "addr:housenumber":"414",
    "addr:postcode":"29621",
    "addr:street":"N Fant St",
    "iso:country":"US",
    "sg:address":"414 N Fant St",
    "sg:city":"Anderson",
    "sg:classifiers":[
        {
            "category":"Health Services",
            "subcategory":"Doctor",
            "type":"Services"
        }
    ],
    "sg:phone":"+1 864 226 1294",
    "sg:postcode":"29621",
    "sg:province":"SC",
    "sg:tags":[
        "clinic"
    ],
    "wof:name":"Anderson Free Clinic",
    "wof:placetype":"venue"
},
  "geometry": {"coordinates":[-82.646208,34.507091],"type":"Point"}
}