{
  "type": "Feature",
  "properties": {
    "iso:country":"US",
    "sg:address":"101 N Lafayette Dr",
    "sg:city":"Sumter",
    "sg:classifiers":[
        {
            "category":"Restaurant",
            "type":"Food & Drink"
        }
    ],
    "sg:phone":"+1 803 773 8515",
    "sg:postcode":"29150",
    "sg:province":"SC",
    "wof:name":"Mc Donald's",
    "wof:placetype":"venue"
},
  "geometry": {"coordinates":[-80.336326,33.924147],"type":"Point"}
}