{
  "type": "Feature",
  "properties": {
    "iso:country":"US",
    "sg:address":"256 Savannah Hwy",
    "sg:city":"Beaufort",
    "sg:classifiers":[
        {
            "category":"Organizations",
            "subcategory":"Religious Organization",
            "type":"Services"
        }
    ],
    "sg:phone":"+1 843 525 1133",
    "sg:postcode":"29906",
    "sg:province":"SC",
    "sg:tags":[
        "church"
    ],
    "wof:name":"Calvary Baptist Church",
    "wof:placetype":"venue"
},
  "geometry": {"coordinates":[-80.75883899999999,32.395021],"type":"Point"}
}