{
  "type": "Feature",
  "properties": {
    "addr:full":"115 Little St Belton SC 29627",
    "addr:housenumber":"115",
    "addr:postcode":"29627",
    "addr:street":"Little St",
    "iso:country":"US",
    "sg:address":"115 Little St",
    "sg:city":"Belton",
    "sg:classifiers":[
        {
            "category":"Health Services",
            "subcategory":"Medical Lab",
            "type":"Services"
        }
    ],
    "sg:phone":"+1 864 338 0062",
    "sg:postcode":"29627",
    "sg:province":"SC",
    "sg:tags":[
        "laboratory"
    ],
    "wof:name":"Quest Diagnostics Inc",
    "wof:placetype":"venue"
},
  "geometry": {"coordinates":[-82.514094,34.528199],"type":"Point"}
}