{
  "type": "Feature",
  "properties": {
    "addr:full":"9425 S Chelsea Rd Columbia SC 29223",
    "addr:housenumber":"9425",
    "addr:postcode":"29223",
    "addr:street":"S Chelsea Rd",
    "iso:country":"US",
    "sg:address":"9425 S Chelsea Rd",
    "sg:city":"Columbia",
    "sg:classifiers":[
        {
            "category":"Home & Garden",
            "subcategory":"Building Materials",
            "type":"Retail Goods"
        }
    ],
    "sg:phone":"+1 803 730 8255",
    "sg:postcode":"29223",
    "sg:province":"SC",
    "sg:tags":[
        "door"
    ],
    "wof:name":"Door Solutions",
    "wof:placetype":"venue"
},
  "geometry": {"coordinates":[-80.931618,34.08518],"type":"Point"}
}