{
  "type": "Feature",
  "properties": {
    "iso:country":"US",
    "sg:address":"1111 US Hwy 501 Bus",
    "sg:city":"Conway",
    "sg:classifiers":[
        {
            "category":"Manufacturing",
            "subcategory":"Signs",
            "type":"Manufacturing & Wholesale Goods"
        }
    ],
    "sg:phone":"+1 843 347 7000",
    "sg:postcode":"29526",
    "sg:province":"SC",
    "wof:name":"Lance Kelly Designs",
    "wof:placetype":"venue"
},
  "geometry": {"coordinates":[-79.057176,33.849227],"type":"Point"}
}