{
  "type": "Feature",
  "properties": {
    "iso:country":"US",
    "sg:address":"709 W Calhoun St",
    "sg:city":"Marion",
    "sg:classifiers":[
        {
            "category":"Insurance",
            "subcategory":"Hazard Insurance",
            "type":"Services"
        }
    ],
    "sg:phone":"+1 843 423 2104",
    "sg:postcode":"29536",
    "sg:province":"SC",
    "sg:tags":[
        "bond"
    ],
    "wof:name":"De-Boy Fast",
    "wof:placetype":"venue"
},
  "geometry": {"coordinates":[-79.381131,34.419333],"type":"Point"}
}