{
  "type": "Feature",
  "properties": {
    "iso:country":"US",
    "sg:address":"1739 Maybank Hwy",
    "sg:city":"Charleston",
    "sg:classifiers":[
        {
            "category":"Bars & Pubs",
            "type":"Food & Drink"
        }
    ],
    "sg:menulink":"http://www.allmenus.com/sc/james-island/241708-barberitos/menu/",
    "sg:phone":"+1 843 406 4955",
    "sg:postcode":"29412",
    "sg:province":"SC",
    "sg:tags":[
        "mexican"
    ],
    "wof:name":"Barberitos",
    "wof:placetype":"venue"
},
  "geometry": {"coordinates":[-79.97641400000001,32.761845],"type":"Point"}
}