{
  "type": "Feature",
  "properties": {
    "iso:country":"US",
    "sg:address":"284 Trexler Ln",
    "sg:city":"Rock Hill",
    "sg:classifiers":[
        {
            "category":"Building & Trades",
            "subcategory":"Landscaping Services",
            "type":"Services"
        }
    ],
    "sg:phone":"+1 803 366 4489",
    "sg:postcode":"29732",
    "sg:province":"SC",
    "sg:tags":[
        "lawn",
        "maintenance",
        "grounds"
    ],
    "wof:name":"Yard-Man Lawn-Care Svc",
    "wof:placetype":"venue"
},
  "geometry": {"coordinates":[-81.053391,34.974792],"type":"Point"}
}