{
  "type": "Feature",
  "properties": {
    "iso:country":"US",
    "sg:address":"4409 N Ocean Blvd",
    "sg:city":"North Myrtle Bch",
    "sg:classifiers":[
        {
            "category":"Travel",
            "subcategory":"Hotels & Motels",
            "type":"Entertainment"
        }
    ],
    "sg:phone":"+1 843 249 2122",
    "sg:postcode":"29582",
    "sg:province":"SC",
    "wof:name":"Carolina Blue Motel",
    "wof:placetype":"venue"
},
  "geometry": {"coordinates":[-78.623752,33.834298],"type":"Point"}
}