{
  "type": "Feature",
  "properties": {
    "addr:full":"108 W Harrison St Dillon SC 29536",
    "addr:housenumber":"108",
    "addr:postcode":"29536",
    "addr:street":"W Harrison St",
    "iso:country":"US",
    "sg:address":"108 W Harrison St",
    "sg:city":"Dillon",
    "sg:classifiers":[
        {
            "category":"Government",
            "subcategory":"Office",
            "type":"Public Place"
        }
    ],
    "sg:phone":"+1 843 774 2241",
    "sg:postcode":"29536",
    "sg:province":"SC",
    "sg:tags":[
        "federal",
        "program"
    ],
    "wof:name":"US Animal Plant Health Inspctn",
    "wof:placetype":"venue"
},
  "geometry": {"coordinates":[-79.372726,34.418813],"type":"Point"}
}