{
  "type": "Feature",
  "properties": {
    "addr:full":"7307 Ninety Six Hwy Ninety Six SC 29666",
    "addr:housenumber":"7307",
    "addr:postcode":"29666",
    "addr:street":"Ninety Six Hwy",
    "iso:country":"US",
    "sg:address":"7307 Ninety Six Hwy",
    "sg:city":"Ninety Six",
    "sg:classifiers":[
        {
            "category":"Farming",
            "subcategory":"Livestock Farm",
            "type":"Manufacturing & Wholesale Goods"
        }
    ],
    "sg:phone":"+1 864 543 3560",
    "sg:postcode":"29666",
    "sg:province":"SC",
    "sg:tags":[
        "beef",
        "feedlot",
        "cattle"
    ],
    "wof:name":"Harold S Butler",
    "wof:placetype":"venue"
},
  "geometry": {"coordinates":[-81.917058,34.170177],"type":"Point"}
}