{
  "type": "Feature",
  "properties": {
    "addr:full":"214 S Jefferies Blvd Walterboro SC 29488",
    "addr:housenumber":"214",
    "addr:postcode":"29488",
    "addr:street":"S Jefferies Blvd",
    "iso:country":"US",
    "sg:address":"214 S Jefferies Blvd",
    "sg:city":"Walterboro",
    "sg:classifiers":[
        {
            "category":"Building & Trades",
            "subcategory":"Construction",
            "type":"Services"
        }
    ],
    "sg:phone":"+1 843 549 2839",
    "sg:postcode":"29488",
    "sg:province":"SC",
    "sg:tags":[
        "repairing",
        "house",
        "remodeling",
        "contractor"
    ],
    "wof:name":"Low Country Pride Remodel",
    "wof:placetype":"venue"
},
  "geometry": {"coordinates":[-80.66732399999999,32.901209],"type":"Point"}
}