{
  "type": "Feature",
  "properties": {
    "iso:country":"US",
    "sg:address":"3330 Charleston Hwy",
    "sg:city":"West Columbia",
    "sg:classifiers":[
        {
            "category":"Freight",
            "type":"Transportation"
        }
    ],
    "sg:phone":"+1 803 794 7004",
    "sg:postcode":"29172",
    "sg:province":"SC",
    "sg:tags":[
        "hauling",
        "trucking"
    ],
    "wof:name":"M & W Trucks & Transport",
    "wof:placetype":"venue"
},
  "geometry": {"coordinates":[-81.072073,33.914322],"type":"Point"}
}