{
  "type": "Feature",
  "properties": {
    "iso:country":"US",
    "sg:address":"646 Elm Ave",
    "sg:city":"Columbia",
    "sg:classifiers":[
        {
            "category":"Building & Trades",
            "subcategory":"Plumbing",
            "type":"Services"
        }
    ],
    "sg:phone":"+1 803 929 0400",
    "sg:postcode":"29205",
    "sg:province":"SC",
    "sg:tags":[
        "repair"
    ],
    "wof:name":"Driggers Plumbing Co",
    "wof:placetype":"venue"
},
  "geometry": {"coordinates":[-80.998977,33.984181],"type":"Point"}
}