{
  "type": "Feature",
  "properties": {
    "addr:full":"2041 Wedgefield Rd Sumter SC 29154",
    "addr:housenumber":"2041",
    "addr:postcode":"29154",
    "addr:street":"Wedgefield Rd",
    "iso:country":"US",
    "sg:address":"2041 Wedgefield Rd",
    "sg:city":"Sumter",
    "sg:classifiers":[
        {
            "category":"Autos & Motor Vehicles",
            "subcategory":"Auto Supplies",
            "type":"Retail Goods"
        }
    ],
    "sg:phone":"+1 803 773 2709",
    "sg:postcode":"29154",
    "sg:province":"SC",
    "sg:tags":[
        "automobile",
        "parts"
    ],
    "wof:name":"Parts Connection Inc",
    "wof:placetype":"venue"
},
  "geometry": {"coordinates":[-80.38401,33.91453],"type":"Point"}
}