{
  "type": "Feature",
  "properties": {
    "iso:country":"US",
    "sg:address":"2244 Hodge Rd",
    "sg:city":"Newberry",
    "sg:classifiers":[
        {
            "category":"Farming",
            "subcategory":"Farm",
            "type":"Manufacturing & Wholesale Goods"
        }
    ],
    "sg:phone":"+1 803 364 2740",
    "sg:postcode":"29108",
    "sg:province":"SC",
    "sg:tags":[
        "crop",
        "general"
    ],
    "wof:name":"Harmon Farm",
    "wof:placetype":"venue"
},
  "geometry": {"coordinates":[-81.603914,34.12393],"type":"Point"}
}