{
  "type": "Feature",
  "properties": {
    "iso:country":"US",
    "sg:address":"2208 N Ocean Blvd",
    "sg:city":"North Myrtle Bch",
    "sg:classifiers":[
        {
            "category":"Recreation",
            "type":"Entertainment"
        }
    ],
    "sg:phone":"+1 843 249 9908",
    "sg:postcode":"29582",
    "sg:province":"SC",
    "wof:name":"Bob's Water Sports",
    "wof:placetype":"venue"
},
  "geometry": {"coordinates":[-78.643861,33.827618],"type":"Point"}
}