{
  "type": "Feature",
  "properties": {
    "iso:country":"US",
    "sg:address":"204 Washington St",
    "sg:city":"Belton",
    "sg:phone":"+1 864 338 7737",
    "sg:postcode":"29627",
    "sg:province":"SC",
    "sg:tags":[
        "oil"
    ],
    "wof:name":"O'Dell Oil Co Inc",
    "wof:placetype":"venue"
},
  "geometry": {"coordinates":[-82.492417,34.528451],"type":"Point"}
}