{
  "type": "Feature",
  "properties": {
    "addr:full":"117 N Main St Greenville SC 29601",
    "addr:housenumber":"117",
    "addr:postcode":"29601",
    "addr:street":"N Main St",
    "iso:country":"US",
    "sg:address":"117 N Main St",
    "sg:city":"Greenville",
    "sg:classifiers":[
        {
            "category":"Shopping",
            "subcategory":"Hobbies, Toys, & Games",
            "type":"Retail Goods"
        }
    ],
    "sg:phone":"+1 864 467 1984",
    "sg:postcode":"29601",
    "sg:province":"SC",
    "wof:name":"O P Taylor's",
    "wof:placetype":"venue"
},
  "geometry": {"coordinates":[-82.398291,34.85236],"type":"Point"}
}