{
  "type": "Feature",
  "properties": {
    "addr:full":"1585 Jonesville Hwy Union SC 29379",
    "addr:housenumber":"1585",
    "addr:postcode":"29379",
    "addr:street":"Jonesville Hwy",
    "iso:country":"US",
    "sg:address":"1585 Jonesville Hwy",
    "sg:city":"Union",
    "sg:classifiers":[
        {
            "category":"Government",
            "subcategory":"Office",
            "type":"Public Place"
        }
    ],
    "sg:phone":"+1 864 427 2075",
    "sg:postcode":"29379",
    "sg:province":"SC",
    "sg:tags":[
        "state"
    ],
    "wof:name":"S C State Govt Dept - Juvenile",
    "wof:placetype":"venue"
},
  "geometry": {"coordinates":[-81.63047,34.756074],"type":"Point"}
}