{
  "type": "Feature",
  "properties": {
    "iso:country":"US",
    "sg:address":"1030 Chapel Rd",
    "sg:city":"West Columbia",
    "sg:classifiers":[
        {
            "category":"Building & Trades",
            "subcategory":"Construction",
            "type":"Services"
        }
    ],
    "sg:phone":"+1 803 755 7039",
    "sg:postcode":"29172",
    "sg:province":"SC",
    "sg:tags":[
        "concrete",
        "contractor"
    ],
    "wof:name":"Newman Concrete Inc",
    "wof:placetype":"venue"
},
  "geometry": {"coordinates":[-81.133957,33.893039],"type":"Point"}
}