{
  "type": "Feature",
  "properties": {
    "iso:country":"US",
    "sg:address":"549 College Park Rd",
    "sg:city":"Ladson",
    "sg:classifiers":[
        {
            "category":"Wholesale",
            "subcategory":"Durable Goods & Equipment",
            "type":"Manufacturing & Wholesale Goods"
        }
    ],
    "sg:phone":"+1 843 553 2677",
    "sg:postcode":"29456",
    "sg:province":"SC",
    "sg:tags":[
        "exporter"
    ],
    "wof:name":"Kims 2 Shoe Repair & Altrtns",
    "wof:placetype":"venue"
},
  "geometry": {"coordinates":[-80.088313,33.007933],"type":"Point"}
}