{
  "type": "Feature",
  "properties": {
    "iso:country":"US",
    "sg:address":"407 79th Ave N",
    "sg:city":"Myrtle Beach",
    "sg:classifiers":[
        {
            "category":"Education",
            "subcategory":"School",
            "type":"Public Place"
        }
    ],
    "sg:phone":"+1 843 497 3691",
    "sg:postcode":"29572",
    "sg:province":"SC",
    "wof:name":"Tang Soo Do School",
    "wof:placetype":"venue"
},
  "geometry": {"coordinates":[-78.815478,33.748406],"type":"Point"}
}