{
  "type": "Feature",
  "properties": {
    "iso:country":"US",
    "sg:address":"104 Court Sq",
    "sg:city":"Abbeville",
    "sg:classifiers":[
        {
            "category":"Insurance",
            "subcategory":"Insurance Agent",
            "type":"Services"
        }
    ],
    "sg:phone":"+1 864 366 2195",
    "sg:postcode":"29620",
    "sg:province":"SC",
    "wof:name":"Horton Insurance",
    "wof:placetype":"venue"
},
  "geometry": {"coordinates":[-82.378186,34.177921],"type":"Point"}
}