{
  "type": "Feature",
  "properties": {
    "iso:country":"US",
    "sg:address":"9744 Kings Grant Dr",
    "sg:city":"Murrells Inlet",
    "sg:classifiers":[
        {
            "category":"Real Estate",
            "subcategory":"Real Estate Agent",
            "type":"Services"
        }
    ],
    "sg:phone":"+1 843 651 5923",
    "sg:postcode":"29576",
    "sg:province":"SC",
    "wof:name":"Collins Real Estate",
    "wof:placetype":"venue"
},
  "geometry": {"coordinates":[-79.02665399999999,33.593534],"type":"Point"}
}