{
  "type": "Feature",
  "properties": {
    "iso:country":"US",
    "sg:address":"401 N Main St",
    "sg:city":"Greenville",
    "sg:classifiers":[
        {
            "category":"Banks & Credit Unions",
            "subcategory":"Investment Brokerage",
            "type":"Services"
        }
    ],
    "sg:phone":"+1 864 467 9800",
    "sg:postcode":"29601",
    "sg:province":"SC",
    "sg:tags":[
        "stock",
        "bond"
    ],
    "sg:website":"www.wachoviasec.com",
    "wof:name":"Wachovia Securities",
    "wof:placetype":"venue"
},
  "geometry": {"coordinates":[-82.39616100000001,34.85715],"type":"Point"}
}