{
  "type": "Feature",
  "properties": {
    "iso:country":"US",
    "sg:address":"240 Maple St",
    "sg:city":"Johnsonville",
    "sg:classifiers":[
        {
            "category":"Building & Trades",
            "subcategory":"Plumbing",
            "type":"Services"
        }
    ],
    "sg:phone":"+1 843 386 3566",
    "sg:postcode":"29555",
    "sg:province":"SC",
    "sg:tags":[
        "conditioning",
        "air",
        "system",
        "contractor"
    ],
    "wof:name":"Capps Heating & Cooling Svc",
    "wof:placetype":"venue"
},
  "geometry": {"coordinates":[-79.45448,33.813828],"type":"Point"}
}