{
  "type": "Feature",
  "properties": {
    "addr:full":"305 Hall Rd Easley SC 29642",
    "addr:housenumber":"305",
    "addr:postcode":"29642",
    "addr:street":"Hall Rd",
    "iso:country":"US",
    "sg:address":"305 Hall Rd",
    "sg:city":"Easley",
    "sg:classifiers":[
        {
            "category":"Building & Trades",
            "subcategory":"Plumbing",
            "type":"Services"
        }
    ],
    "sg:phone":"+1 864 901 2988",
    "sg:postcode":"29642",
    "sg:province":"SC",
    "sg:tags":[
        "contractor"
    ],
    "wof:name":"Edwards Heating/Air",
    "wof:placetype":"venue"
},
  "geometry": {"coordinates":[-82.567893,34.720486],"type":"Point"}
}