{
  "type": "Feature",
  "properties": {
    "iso:country":"US",
    "sg:address":"3123 W Montague Ave",
    "sg:city":"Charleston",
    "sg:classifiers":[
        {
            "category":"Restaurant",
            "type":"Food & Drink"
        }
    ],
    "sg:phone":"+1 843 554 3943",
    "sg:postcode":"29418",
    "sg:province":"SC",
    "wof:name":"Gabby's",
    "wof:placetype":"venue"
},
  "geometry": {"coordinates":[-80.014439,32.864756],"type":"Point"}
}