{
  "type": "Feature",
  "properties": {
    "addr:full":"1002 N Main St Lancaster SC 29720",
    "addr:housenumber":"1002",
    "addr:postcode":"29720",
    "addr:street":"N Main St",
    "iso:country":"US",
    "sg:address":"1002 N Main St",
    "sg:city":"Lancaster",
    "sg:classifiers":[
        {
            "category":"Shopping",
            "subcategory":"Department Store",
            "type":"Retail Goods"
        }
    ],
    "sg:phone":"+1 803 286 8503",
    "sg:postcode":"29720",
    "sg:province":"SC",
    "sg:tags":[
        "shop"
    ],
    "wof:name":"Dollar General",
    "wof:placetype":"venue"
},
  "geometry": {"coordinates":[-80.776023,34.72992],"type":"Point"}
}