{
  "type": "Feature",
  "properties": {
    "iso:country":"US",
    "sg:address":"1487 S McElhaney Rd",
    "sg:city":"Greer",
    "sg:classifiers":[
        {
            "category":"Professional",
            "subcategory":"Accounting & Tax Preparation",
            "type":"Services"
        }
    ],
    "sg:phone":"+1 864 879 7922",
    "sg:postcode":"29651",
    "sg:province":"SC",
    "sg:tags":[
        "bookkeeping",
        "general"
    ],
    "wof:name":"JVI",
    "wof:placetype":"venue"
},
  "geometry": {"coordinates":[-82.273473,34.977411],"type":"Point"}
}