{
  "type": "Feature",
  "properties": {
    "iso:country":"US",
    "sg:address":"2465 The Haul Over",
    "sg:city":"Johns Island",
    "sg:classifiers":[
        {
            "category":"Wholesale",
            "subcategory":"Hardware",
            "type":"Manufacturing & Wholesale Goods"
        }
    ],
    "sg:phone":"+1 843 768 1688",
    "sg:postcode":"29455",
    "sg:province":"SC",
    "wof:name":"C I P",
    "wof:placetype":"venue"
},
  "geometry": {"coordinates":[-80.16458900000001,32.57726],"type":"Point"}
}