{
  "type": "Feature",
  "properties": {
    "iso:country":"US",
    "sg:address":"2809 US Hwy 301 N",
    "sg:city":"Hamer",
    "sg:classifiers":[
        {
            "category":"Government",
            "subcategory":"Post Office",
            "type":"Public Place"
        }
    ],
    "sg:phone":"+1 843 774 8233",
    "sg:postcode":"29547",
    "sg:province":"SC",
    "sg:tags":[
        "postal",
        "us"
    ],
    "wof:name":"US Post Office",
    "wof:placetype":"venue"
},
  "geometry": {"coordinates":[-79.32700199999999,34.475944],"type":"Point"}
}