{
  "type": "Feature",
  "properties": {
    "addr:full":"517 N Main St Whitmire SC 29178",
    "addr:housenumber":"517",
    "addr:postcode":"29178",
    "addr:street":"N Main St",
    "iso:country":"US",
    "sg:address":"517 N Main St",
    "sg:city":"Whitmire",
    "sg:classifiers":[
        {
            "category":"Organizations",
            "subcategory":"Religious Organization",
            "type":"Services"
        }
    ],
    "sg:phone":"+1 803 694 3434",
    "sg:postcode":"29178",
    "sg:province":"SC",
    "sg:tags":[
        "church"
    ],
    "wof:name":"Sims Chapel Baptist Church",
    "wof:placetype":"venue"
},
  "geometry": {"coordinates":[-81.623127,34.507075],"type":"Point"}
}