{
  "type": "Feature",
  "properties": {
    "addr:full":"1274 21st Ave N Myrtle Beach SC 29577",
    "addr:housenumber":"1274",
    "addr:postcode":"29577",
    "addr:street":"21St Ave N",
    "iso:country":"US",
    "sg:address":"1274 21st Ave N",
    "sg:city":"Myrtle Beach",
    "sg:classifiers":[
        {
            "category":"Food & Beverages",
            "subcategory":"Groceries & Convenience Stores",
            "type":"Retail Goods"
        }
    ],
    "sg:phone":"+1 843 916 9516",
    "sg:postcode":"29577",
    "sg:province":"SC",
    "wof:name":"Scotchman Store 221",
    "wof:placetype":"venue"
},
  "geometry": {"coordinates":[-78.885443,33.713268],"type":"Point"}
}