{
  "type": "Feature",
  "properties": {
    "addr:full":"1428 N Sally Hill Rd Timmonsville SC 29161",
    "addr:housenumber":"1428",
    "addr:postcode":"29161",
    "addr:street":"N Sally Hill Rd",
    "iso:country":"US",
    "sg:address":"1428 N Sally Hill Rd",
    "sg:city":"Timmonsville",
    "sg:classifiers":[
        {
            "category":"Autos & Motor Vehicles",
            "subcategory":"Auto Supplies",
            "type":"Retail Goods"
        },
        {
            "category":"Retail",
            "subcategory":"Auto Repair",
            "type":"Services"
        }
    ],
    "sg:phone":"+1 843 346 3847",
    "sg:postcode":"29161",
    "sg:province":"SC",
    "sg:tags":[
        "automobile",
        "customizing"
    ],
    "wof:name":"Walkie's Rod Shop",
    "wof:placetype":"venue"
},
  "geometry": {"coordinates":[-79.91614199999999,34.179391],"type":"Point"}
}