{
  "type": "Feature",
  "properties": {
    "addr:full":"935 S 4th St Hartsville SC 29550",
    "addr:housenumber":"935",
    "addr:postcode":"29550",
    "addr:street":"S 4Th St",
    "iso:country":"US",
    "sg:address":"935 S 4th St",
    "sg:city":"Hartsville",
    "sg:classifiers":[
        {
            "category":"Home & Garden",
            "subcategory":"Hardware",
            "type":"Retail Goods"
        }
    ],
    "sg:phone":"+1 843 383 5131",
    "sg:postcode":"29550",
    "sg:province":"SC",
    "wof:name":"Henderson Supply Ace Hardware",
    "wof:placetype":"venue"
},
  "geometry": {"coordinates":[-80.05873099999999,34.356279],"type":"Point"}
}