{
  "type": "Feature",
  "properties": {
    "iso:country":"US",
    "sg:address":"506 Broad St",
    "sg:city":"Camden",
    "sg:classifiers":[
        {
            "category":"Retail",
            "subcategory":"Auto Repair",
            "type":"Services"
        }
    ],
    "sg:phone":"+1 803 432 3611",
    "sg:postcode":"29020",
    "sg:province":"SC",
    "sg:tags":[
        "repairing",
        "automobile",
        "radiator"
    ],
    "wof:name":"Camden Radiator Shop",
    "wof:placetype":"venue"
},
  "geometry": {"coordinates":[-80.606082,34.237056],"type":"Point"}
}