{
  "type": "Feature",
  "properties": {
    "addr:full":"1204 Fording Island Rd Bluffton SC 29910",
    "addr:housenumber":"1204",
    "addr:postcode":"29910",
    "addr:street":"Fording Island Rd",
    "iso:country":"US",
    "sg:address":"1204 Fording Island Rd",
    "sg:city":"Bluffton",
    "sg:classifiers":[
        {
            "category":"Building & Trades",
            "subcategory":"Plumbing",
            "type":"Services"
        }
    ],
    "sg:phone":"+1 843 681 2350",
    "sg:postcode":"29910",
    "sg:province":"SC",
    "sg:tags":[
        "conditioning",
        "air",
        "system",
        "contractor"
    ],
    "sg:website":"www.marksinc.com",
    "wof:name":"Marke's Air Cond & Heating Inc",
    "wof:placetype":"venue"
},
  "geometry": {"coordinates":[-80.83766799999999,32.249569],"type":"Point"}
}