{
  "type": "Feature",
  "properties": {
    "iso:country":"US",
    "sg:address":"3105 Augusta St",
    "sg:city":"Greenville",
    "sg:classifiers":[
        {
            "category":"Autos & Motor Vehicles",
            "subcategory":"Motorcycle Sales",
            "type":"Retail Goods"
        }
    ],
    "sg:phone":"+1 864 297 4243",
    "sg:postcode":"29605",
    "sg:province":"SC",
    "sg:tags":[
        "scooter"
    ],
    "wof:name":"Lil' Boys Toys",
    "wof:placetype":"venue"
},
  "geometry": {"coordinates":[-82.382063,34.810628],"type":"Point"}
}