{
  "type": "Feature",
  "properties": {
    "iso:country":"US",
    "sg:address":"1241 Boiling Springs Rd",
    "sg:city":"Spartanburg",
    "sg:classifiers":[
        {
            "category":"Health Services",
            "subcategory":"Doctor",
            "type":"Services"
        }
    ],
    "sg:phone":"+1 864 585 5633",
    "sg:postcode":"29303",
    "sg:province":"SC",
    "sg:tags":[
        "physician",
        "surgeon"
    ],
    "wof:name":"Palmetto Orthopaedics",
    "wof:placetype":"venue"
},
  "geometry": {"coordinates":[-81.94649,34.988891],"type":"Point"}
}