{
  "type": "Feature",
  "properties": {
    "iso:country":"US",
    "sg:address":"4900 Lacross Rd",
    "sg:city":"Charleston",
    "sg:classifiers":[
        {
            "category":"Government",
            "subcategory":"Police Station",
            "type":"Public Place"
        }
    ],
    "sg:phone":"+1 843 740 2876",
    "sg:postcode":"29406",
    "sg:province":"SC",
    "sg:tags":[
        "department"
    ],
    "wof:name":"North Charleston Police Record",
    "wof:placetype":"venue"
},
  "geometry": {"coordinates":[-80.015973,32.881417],"type":"Point"}
}