{
  "type": "Feature",
  "properties": {
    "addr:full":"700 Anders Dr Columbia SC 29203",
    "addr:housenumber":"700",
    "addr:postcode":"29203",
    "addr:street":"Anders Dr",
    "iso:country":"US",
    "sg:address":"700 Anders Dr",
    "sg:city":"Columbia",
    "sg:classifiers":[
        {
            "category":"Building & Trades",
            "subcategory":"Landscaping Services",
            "type":"Services"
        }
    ],
    "sg:phone":"+1 803 935 0904",
    "sg:postcode":"29203",
    "sg:province":"SC",
    "sg:tags":[
        "landscape"
    ],
    "wof:name":"Narada Williams",
    "wof:placetype":"venue"
},
  "geometry": {"coordinates":[-80.967753,34.083667],"type":"Point"}
}