{
  "type": "Feature",
  "properties": {
    "iso:country":"US",
    "sg:address":"810 Travelers Blvd",
    "sg:city":"Summerville",
    "sg:classifiers":[
        {
            "category":"Banks & Credit Unions",
            "subcategory":"Investment Brokerage",
            "type":"Services"
        }
    ],
    "sg:phone":"+1 843 875 1774",
    "sg:postcode":"29485",
    "sg:province":"SC",
    "sg:tags":[
        "advisory",
        "financial"
    ],
    "wof:name":"Lowcountry Advisors",
    "wof:placetype":"venue"
},
  "geometry": {"coordinates":[-80.16757200000001,32.95592],"type":"Point"}
}