{
  "type": "Feature",
  "properties": {
    "iso:country":"US",
    "sg:address":"813 Hunter St",
    "sg:city":"York",
    "sg:classifiers":[
        {
            "category":"Wholesale",
            "subcategory":"Apparel",
            "type":"Manufacturing & Wholesale Goods"
        }
    ],
    "sg:phone":"+1 803 684 0558",
    "sg:postcode":"29745",
    "sg:province":"SC",
    "sg:tags":[
        "fabric"
    ],
    "wof:name":"Brooksel Textiles",
    "wof:placetype":"venue"
},
  "geometry": {"coordinates":[-81.21890399999999,34.995767],"type":"Point"}
}