{
  "type": "Feature",
  "properties": {
    "iso:country":"US",
    "sg:address":"153 Greenville St SW",
    "sg:city":"Aiken",
    "sg:classifiers":[
        {
            "category":"Real Estate",
            "subcategory":"Developer",
            "type":"Services"
        }
    ],
    "sg:phone":"+1 803 649 5782",
    "sg:postcode":"29801",
    "sg:province":"SC",
    "wof:name":"Farmer & Assoc",
    "wof:placetype":"venue"
},
  "geometry": {"coordinates":[-81.725525,33.562457],"type":"Point"}
}