{
  "type": "Feature",
  "properties": {
    "addr:full":"107 Piedmont Rd Piedmont SC 29673",
    "addr:housenumber":"107",
    "addr:postcode":"29673",
    "addr:street":"Piedmont Rd",
    "iso:country":"US",
    "sg:address":"107 Piedmont Rd",
    "sg:city":"Piedmont",
    "sg:classifiers":[
        {
            "category":"Building & Trades",
            "subcategory":"Construction",
            "type":"Services"
        }
    ],
    "sg:phone":"+1 864 233 1990",
    "sg:postcode":"29673",
    "sg:province":"SC",
    "sg:tags":[
        "pavement",
        "contractor"
    ],
    "wof:name":"Pavement Products & Services",
    "wof:placetype":"venue"
},
  "geometry": {"coordinates":[-82.47680699999999,34.759999],"type":"Point"}
}