{
  "type": "Feature",
  "properties": {
    "iso:country":"US",
    "sg:address":"2816 Wade Hampton Blvd",
    "sg:city":"Taylors",
    "sg:classifiers":[
        {
            "category":"Food & Beverages",
            "subcategory":"Liquor & Beverages",
            "type":"Retail Goods"
        }
    ],
    "sg:phone":"+1 864 322 9046",
    "sg:postcode":"29687",
    "sg:province":"SC",
    "sg:tags":[
        "alcoholic"
    ],
    "wof:name":"Wade Hampton Liquors",
    "wof:placetype":"venue"
},
  "geometry": {"coordinates":[-82.333944,34.902865],"type":"Point"}
}