{
  "type": "Feature",
  "properties": {
    "iso:country":"US",
    "sg:address":"25 Spruce Ct",
    "sg:city":"Hilton Head Island",
    "sg:classifiers":[
        {
            "category":"Manufacturing",
            "subcategory":"Electronics",
            "type":"Manufacturing & Wholesale Goods"
        }
    ],
    "sg:phone":"+1 843 341 7966",
    "sg:postcode":"29928",
    "sg:province":"SC",
    "sg:tags":[
        "equipment",
        "mfg"
    ],
    "wof:name":"George R Snell Associates",
    "wof:placetype":"venue"
},
  "geometry": {"coordinates":[-80.776887,32.170168],"type":"Point"}
}