{
  "type": "Feature",
  "properties": {
    "iso:country":"US",
    "sg:address":"1030 N Pleasantburg Dr",
    "sg:city":"Greenville",
    "sg:classifiers":[
        {
            "category":"Restaurant",
            "type":"Food & Drink"
        }
    ],
    "sg:phone":"+1 864 241 0805",
    "sg:postcode":"29607",
    "sg:province":"SC",
    "wof:name":"Aussie Bush Burgers",
    "wof:placetype":"venue"
},
  "geometry": {"coordinates":[-82.357934,34.867443],"type":"Point"}
}