{
  "type": "Feature",
  "properties": {
    "iso:country":"US",
    "sg:address":"27 Boland Ct",
    "sg:city":"Greenville",
    "sg:classifiers":[
        {
            "category":"Shopping",
            "subcategory":"Pharmacy",
            "type":"Retail Goods"
        }
    ],
    "sg:phone":"+1 864 297 8163",
    "sg:postcode":"29615",
    "sg:province":"SC",
    "wof:name":"Longs Home Medical",
    "wof:placetype":"venue"
},
  "geometry": {"coordinates":[-82.255835,34.858696],"type":"Point"}
}