{
  "type": "Feature",
  "properties": {
    "addr:full":"710 Milwee Ave Greenwood SC 29646",
    "addr:housenumber":"710",
    "addr:postcode":"29646",
    "addr:street":"Milwee Ave",
    "iso:country":"US",
    "sg:address":"710 Milwee Ave",
    "sg:city":"Greenwood",
    "sg:classifiers":[
        {
            "category":"Organizations",
            "subcategory":"Religious Organization",
            "type":"Services"
        }
    ],
    "sg:phone":"+1 864 388 7493",
    "sg:postcode":"29646",
    "sg:province":"SC",
    "sg:tags":[
        "church"
    ],
    "wof:name":"Faith Christian Ctr Church",
    "wof:placetype":"venue"
},
  "geometry": {"coordinates":[-82.156008,34.185441],"type":"Point"}
}