{
  "type": "Feature",
  "properties": {
    "iso:country":"US",
    "sg:address":"2000 Bay St",
    "sg:city":"Cayce",
    "sg:classifiers":[
        {
            "category":"Banks & Credit Unions",
            "subcategory":"Bank",
            "type":"Services"
        }
    ],
    "sg:phone":"+1 803 791 3951",
    "sg:postcode":"29033",
    "sg:province":"SC",
    "sg:tags":[
        "depository",
        "banking"
    ],
    "wof:name":"West Bank Services LLC",
    "wof:placetype":"venue"
},
  "geometry": {"coordinates":[-81.087863,33.956848],"type":"Point"}
}