{
  "type": "Feature",
  "properties": {
    "iso:country":"US",
    "sg:address":"793 Hillsboro Rd",
    "sg:city":"Orangeburg",
    "sg:classifiers":[
        {
            "category":"Personal",
            "subcategory":"Beauty Salon",
            "type":"Services"
        }
    ],
    "sg:phone":"+1 803 516 8453",
    "sg:postcode":"29118",
    "sg:province":"SC",
    "wof:name":"Wild Styles Hair Salon",
    "wof:placetype":"venue"
},
  "geometry": {"coordinates":[-80.887777,33.50472],"type":"Point"}
}