{
  "type": "Feature",
  "properties": {
    "iso:country":"US",
    "sg:address":"125 Mathews Dr",
    "sg:city":"Hilton Head Isle",
    "sg:classifiers":[
        {
            "category":"Retail",
            "subcategory":"Auto Repair",
            "type":"Services"
        }
    ],
    "sg:phone":"+1 843 681 9278",
    "sg:postcode":"29926",
    "sg:province":"SC",
    "sg:tags":[
        "repairing",
        "automobile"
    ],
    "wof:name":"Advance Automotive & Towing",
    "wof:placetype":"venue"
},
  "geometry": {"coordinates":[-80.70265999999999,32.208754],"type":"Point"}
}