{
  "type": "Feature",
  "properties": {
    "iso:country":"US",
    "sg:address":"760 Ray Rd",
    "sg:city":"Hemingway",
    "sg:classifiers":[
        {
            "category":"Manufacturing",
            "subcategory":"Printing",
            "type":"Manufacturing & Wholesale Goods"
        }
    ],
    "sg:phone":"+1 843 558 7432",
    "sg:postcode":"29554",
    "sg:province":"SC",
    "sg:tags":[
        "publisher"
    ],
    "wof:name":"Doll-Mc Ginnis Publications",
    "wof:placetype":"venue"
},
  "geometry": {"coordinates":[-79.344909,33.694434],"type":"Point"}
}