{
  "type": "Feature",
  "properties": {
    "iso:country":"US",
    "sg:address":"1300 E Blackstock Rd",
    "sg:city":"Moore",
    "sg:classifiers":[
        {
            "category":"Education",
            "subcategory":"School",
            "type":"Public Place"
        }
    ],
    "sg:phone":"+1 864 576 8088",
    "sg:postcode":"29369",
    "sg:province":"SC",
    "sg:website":"www.spartanburg6.k12.sc.us/rpdms/dawkins",
    "wof:name":"Dawkins Middle School",
    "wof:placetype":"venue"
},
  "geometry": {"coordinates":[-81.973814,34.902223],"type":"Point"}
}