{
  "type": "Feature",
  "properties": {
    "addr:full":"1003 Union St Spartanburg SC 29302",
    "addr:housenumber":"1003",
    "addr:postcode":"29302",
    "addr:street":"Union St",
    "iso:country":"US",
    "sg:address":"1003 Union St",
    "sg:city":"Spartanburg",
    "sg:classifiers":[
        {
            "category":"Banks & Credit Unions",
            "subcategory":"Investment Brokerage",
            "type":"Services"
        }
    ],
    "sg:phone":"+1 864 463 8000",
    "sg:postcode":"29302",
    "sg:province":"SC",
    "sg:tags":[
        "cotton"
    ],
    "wof:name":"Southeastern Cotton Sales Inc",
    "wof:placetype":"venue"
},
  "geometry": {"coordinates":[-81.902119,34.935705],"type":"Point"}
}