{
  "type": "Feature",
  "properties": {
    "addr:full":"213 N Pleasantburg Dr Greenville SC 29607",
    "addr:housenumber":"213",
    "addr:postcode":"29607",
    "addr:street":"N Pleasantburg Dr",
    "iso:country":"US",
    "sg:address":"213 N Pleasantburg Dr",
    "sg:city":"Greenville",
    "sg:classifiers":[
        {
            "category":"Home & Garden",
            "subcategory":"Building Materials",
            "type":"Retail Goods"
        }
    ],
    "sg:phone":"+1 864 233 0580",
    "sg:postcode":"29607",
    "sg:province":"SC",
    "sg:tags":[
        "equipment",
        "electric",
        "supply"
    ],
    "sg:website":"www.hughessupply.com",
    "wof:name":"Hughes Supply Inc",
    "wof:placetype":"venue"
},
  "geometry": {"coordinates":[-82.35953499999999,34.849814],"type":"Point"}
}