{
  "type": "Feature",
  "properties": {
    "iso:country":"US",
    "sg:address":"321 Webber Rd",
    "sg:city":"Spartanburg",
    "sg:classifiers":[
        {
            "category":"Retail",
            "subcategory":"Animal Services",
            "type":"Services"
        }
    ],
    "sg:phone":"+1 864 579 0828",
    "sg:postcode":"29307",
    "sg:province":"SC",
    "sg:tags":[
        "pet",
        "boarding",
        "sitting"
    ],
    "wof:name":"Woodpoint Bed & Biscuit Salon",
    "wof:placetype":"venue"
},
  "geometry": {"coordinates":[-81.871679,34.978193],"type":"Point"}
}