{
  "type": "Feature",
  "properties": {
    "iso:country":"US",
    "sg:address":"1650 E Main St",
    "sg:city":"Dorchester",
    "sg:classifiers":[
        {
            "category":"Education",
            "subcategory":"School",
            "type":"Public Place"
        }
    ],
    "sg:phone":"+1 843 462 7671",
    "sg:postcode":"29437",
    "sg:province":"SC",
    "wof:name":"Harleyville-Ridgeville Elem",
    "wof:placetype":"venue"
},
  "geometry": {"coordinates":[-80.377741,33.155577],"type":"Point"}
}