{
  "type": "Feature",
  "properties": {
    "addr:full":"2106 S Main St Anderson SC 29624",
    "addr:housenumber":"2106",
    "addr:postcode":"29624",
    "addr:street":"S Main St",
    "iso:country":"US",
    "sg:address":"2106 S Main St",
    "sg:city":"Anderson",
    "sg:classifiers":[
        {
            "category":"Shopping",
            "subcategory":"Clothing, Apparel, & Fashions",
            "type":"Retail Goods"
        }
    ],
    "sg:phone":"+1 864 225 6999",
    "sg:postcode":"29624",
    "sg:province":"SC",
    "sg:tags":[
        "shop",
        "bridal"
    ],
    "wof:name":"Amberly's Satin & Lace",
    "wof:placetype":"venue"
},
  "geometry": {"coordinates":[-82.64787699999999,34.48599],"type":"Point"}
}