{
  "type": "Feature",
  "properties": {
    "iso:country":"US",
    "sg:address":"122 Lansfair Way",
    "sg:city":"Greenville",
    "sg:classifiers":[
        {
            "category":"Professional",
            "subcategory":"Management & Consulting",
            "type":"Services"
        }
    ],
    "sg:phone":"+1 864 675 0111",
    "sg:postcode":"29607",
    "sg:province":"SC",
    "sg:tags":[
        "marketing",
        "program"
    ],
    "wof:name":"De Mint Group",
    "wof:placetype":"venue"
},
  "geometry": {"coordinates":[-82.27364799999999,34.811716],"type":"Point"}
}