{
  "type": "Feature",
  "properties": {
    "iso:country":"US",
    "sg:address":"1203 Greenville Cir",
    "sg:city":"Columbia",
    "sg:classifiers":[
        {
            "category":"Organizations",
            "subcategory":"Religious Organization",
            "type":"Services"
        }
    ],
    "sg:phone":"+1 803 731 9378",
    "sg:postcode":"29210",
    "sg:province":"SC",
    "sg:tags":[
        "church"
    ],
    "wof:name":"Universal Light Church",
    "wof:placetype":"venue"
},
  "geometry": {"coordinates":[-81.083394,34.028693],"type":"Point"}
}