{
  "type": "Feature",
  "properties": {
    "addr:full":"1028 Laurens St Columbia SC 29201",
    "addr:housenumber":"1028",
    "addr:postcode":"29201",
    "addr:street":"Laurens St",
    "iso:country":"US",
    "sg:address":"1028 Laurens St",
    "sg:city":"Columbia",
    "sg:classifiers":[
        {
            "category":"Health Services",
            "subcategory":"Doctor",
            "type":"Services"
        }
    ],
    "sg:phone":"+1 803 779 8357",
    "sg:postcode":"29201",
    "sg:province":"SC",
    "wof:name":"Rich Smythe MD",
    "wof:placetype":"venue"
},
  "geometry": {"coordinates":[-81.020302,34.003799],"type":"Point"}
}