{
  "type": "Feature",
  "properties": {
    "iso:country":"US",
    "sg:address":"100 Fort Lyttleton Rd",
    "sg:city":"Beaufort",
    "sg:classifiers":[
        {
            "category":"Building & Trades",
            "subcategory":"Cleaning & Sanitation",
            "type":"Services"
        },
        {
            "category":"Manufacturing",
            "subcategory":"Metals",
            "type":"Manufacturing & Wholesale Goods"
        }
    ],
    "sg:phone":"+1 843 521 2174",
    "sg:postcode":"29902",
    "sg:province":"SC",
    "sg:tags":[
        "prefab",
        "repair",
        "business",
        "mfg"
    ],
    "wof:name":"Island Power Washing & Screen",
    "wof:placetype":"venue"
},
  "geometry": {"coordinates":[-80.684547,32.40874],"type":"Point"}
}