{
  "type": "Feature",
  "properties": {
    "iso:country":"US",
    "sg:address":"109 N Main St",
    "sg:city":"Bishopville",
    "sg:classifiers":[
        {
            "category":"Museum",
            "type":"Entertainment"
        }
    ],
    "sg:phone":"+1 803 484 5090",
    "sg:postcode":"29010",
    "sg:province":"SC",
    "sg:tags":[
        "art",
        "center"
    ],
    "wof:name":"Opera The House",
    "wof:placetype":"venue"
},
  "geometry": {"coordinates":[-80.24762800000001,34.2189],"type":"Point"}
}