{
  "type": "Feature",
  "properties": {
    "addr:full":"10794 State Hwy 11 Campobello SC 29322",
    "addr:housenumber":"10794",
    "addr:postcode":"29322",
    "addr:street":"State Hwy 11",
    "iso:country":"US",
    "sg:address":"10794 State Hwy 11",
    "sg:city":"Campobello",
    "sg:classifiers":[
        {
            "category":"Social Services",
            "subcategory":"Child Care",
            "type":"Services"
        }
    ],
    "sg:phone":"+1 864 468 4771",
    "sg:postcode":"29322",
    "sg:province":"SC",
    "wof:name":"Jack Bee's Little Flock Day",
    "wof:placetype":"venue"
},
  "geometry": {"coordinates":[-82.140011,35.123349],"type":"Point"}
}