{
  "type": "Feature",
  "properties": {
    "iso:country":"US",
    "sg:address":"1831 Chesnee Hwy",
    "sg:city":"Gaffney",
    "sg:classifiers":[
        {
            "category":"Social Services",
            "subcategory":"Child Care",
            "type":"Services"
        }
    ],
    "sg:phone":"+1 864 206 0041",
    "sg:postcode":"29341",
    "sg:province":"SC",
    "wof:name":"Little Friends Childcare Ctr",
    "wof:placetype":"venue"
},
  "geometry": {"coordinates":[-81.821613,35.143106],"type":"Point"}
}