{
  "type": "Feature",
  "properties": {
    "addr:full":"2908 Trotter Rd Hopkins SC 29061",
    "addr:housenumber":"2908",
    "addr:postcode":"29061",
    "addr:street":"Trotter Rd",
    "iso:country":"US",
    "sg:address":"2908 Trotter Rd",
    "sg:city":"Hopkins",
    "sg:classifiers":[
        {
            "category":"Building & Trades",
            "subcategory":"Pest Control",
            "type":"Services"
        }
    ],
    "sg:phone":"+1 803 776 5120",
    "sg:postcode":"29061",
    "sg:province":"SC",
    "wof:name":"Summers All Seasons Pest Cntrl",
    "wof:placetype":"venue"
},
  "geometry": {"coordinates":[-80.88535,33.960684],"type":"Point"}
}