{
  "type": "Feature",
  "properties": {
    "iso:country":"US",
    "sg:address":"1305 Augusta Rd",
    "sg:city":"West Columbia",
    "sg:classifiers":[
        {
            "category":"Wholesale",
            "subcategory":"Non-durable Goods",
            "type":"Manufacturing & Wholesale Goods"
        }
    ],
    "sg:phone":"+1 803 926 9692",
    "sg:postcode":"29169",
    "sg:province":"SC",
    "wof:name":"Specialties & Etc Inc",
    "wof:placetype":"venue"
},
  "geometry": {"coordinates":[-81.076504,33.986463],"type":"Point"}
}