{
  "type": "Feature",
  "properties": {
    "iso:country":"US",
    "sg:address":"3364 W Palmetto St",
    "sg:city":"Florence",
    "sg:classifiers":[
        {
            "category":"Shopping",
            "subcategory":"Stationery & Office Supplies",
            "type":"Retail Goods"
        }
    ],
    "sg:phone":"+1 843 665 8090",
    "sg:postcode":"29501",
    "sg:province":"SC",
    "wof:name":"OCS Supply Co",
    "wof:placetype":"venue"
},
  "geometry": {"coordinates":[-79.84637600000001,34.167991],"type":"Point"}
}