{
  "type": "Feature",
  "properties": {
    "addr:full":"2081 Sandy St North Charleston SC 29405",
    "addr:housenumber":"2081",
    "addr:postcode":"29405",
    "addr:street":"Sandy St",
    "iso:country":"US",
    "sg:address":"2081 Sandy St",
    "sg:city":"North Charleston",
    "sg:classifiers":[
        {
            "category":"Manufacturing",
            "subcategory":"Metals",
            "type":"Manufacturing & Wholesale Goods"
        }
    ],
    "sg:phone":"+1 843 442 5901",
    "sg:postcode":"29405",
    "sg:province":"SC",
    "sg:tags":[
        "personnel",
        "support"
    ],
    "wof:name":"Technica LLC",
    "wof:placetype":"venue"
},
  "geometry": {"coordinates":[-80.000601,32.859648],"type":"Point"}
}