{
  "type": "Feature",
  "properties": {
    "iso:country":"US",
    "sg:address":"717 Saluda Ave",
    "sg:city":"Columbia",
    "sg:classifiers":[
        {
            "category":"Shopping",
            "subcategory":"Used Merchandise",
            "type":"Retail Goods"
        },
        {
            "category":"Shopping",
            "subcategory":"Clothing, Apparel, & Fashions",
            "type":"Retail Goods"
        }
    ],
    "sg:phone":"+1 803 256 3868",
    "sg:postcode":"29205",
    "sg:province":"SC",
    "sg:tags":[
        "shop",
        "consignment"
    ],
    "wof:name":"Gentleman's Closet",
    "wof:placetype":"venue"
},
  "geometry": {"coordinates":[-81.01701199999999,33.999561],"type":"Point"}
}