{
  "type": "Feature",
  "properties": {
    "addr:full":"128 Gaston St Gaston SC 29053",
    "addr:housenumber":"128",
    "addr:postcode":"29053",
    "addr:street":"Gaston St",
    "iso:country":"US",
    "sg:address":"128 Gaston St",
    "sg:city":"Gaston",
    "sg:classifiers":[
        {
            "category":"Home & Garden",
            "subcategory":"Furniture",
            "type":"Retail Goods"
        }
    ],
    "sg:phone":"+1 803 318 6915",
    "sg:postcode":"29053",
    "sg:province":"SC",
    "sg:tags":[
        "equipment",
        "kitchen",
        "cabinet"
    ],
    "wof:name":"Rocky's Cabinets & Trim",
    "wof:placetype":"venue"
},
  "geometry": {"coordinates":[-81.094499,33.81851],"type":"Point"}
}