{
  "type": "Feature",
  "properties": {
    "iso:country":"US",
    "sg:address":"2712 Laurens Rd",
    "sg:city":"Greenville",
    "sg:classifiers":[
        {
            "category":"Home & Garden",
            "subcategory":"Home Furnishings",
            "type":"Retail Goods"
        }
    ],
    "sg:phone":"+1 864 288 7752",
    "sg:postcode":"29607",
    "sg:province":"SC",
    "sg:tags":[
        "linen",
        "bedding"
    ],
    "wof:name":"Westpint Stvens Bed Bath Lnens",
    "wof:placetype":"venue"
},
  "geometry": {"coordinates":[-82.338746,34.816029],"type":"Point"}
}