{
  "type": "Feature",
  "properties": {
    "addr:full":"107 N Lafayette Dr Sumter SC 29150",
    "addr:housenumber":"107",
    "addr:postcode":"29150",
    "addr:street":"N Lafayette Dr",
    "iso:country":"US",
    "sg:address":"107 N Lafayette Dr",
    "sg:city":"Sumter",
    "sg:classifiers":[
        {
            "category":"Home & Garden",
            "subcategory":"Building Materials",
            "type":"Retail Goods"
        }
    ],
    "sg:phone":"+1 803 775 3787",
    "sg:postcode":"29150",
    "sg:province":"SC",
    "sg:tags":[
        "mixed",
        "concrete"
    ],
    "wof:name":"Glasscox Ready Mixed Concrete",
    "wof:placetype":"venue"
},
  "geometry": {"coordinates":[-80.336252,33.923983],"type":"Point"}
}