{
  "type": "Feature",
  "properties": {
    "iso:country":"US",
    "sg:address":"403 Hillcrest Dr",
    "sg:city":"Easley",
    "sg:classifiers":[
        {
            "category":"Health Services",
            "subcategory":"Doctor",
            "type":"Services"
        }
    ],
    "sg:phone":"+1 864 306 7858",
    "sg:postcode":"29640",
    "sg:province":"SC",
    "sg:tags":[
        "physician",
        "surgeon"
    ],
    "wof:name":"Physical Medicine Devices",
    "wof:placetype":"venue"
},
  "geometry": {"coordinates":[-82.610505,34.838356],"type":"Point"}
}