{
  "type": "Feature",
  "properties": {
    "iso:country":"US",
    "sg:address":"706 Old N Main St",
    "sg:city":"Clover",
    "sg:classifiers":[
        {
            "category":"Organizations",
            "subcategory":"Non-profit Organization",
            "type":"Services"
        }
    ],
    "sg:phone":"+1 803 222 0711",
    "sg:postcode":"29710",
    "sg:province":"SC",
    "sg:tags":[
        "human"
    ],
    "wof:name":"God's Kitchen",
    "wof:placetype":"venue"
},
  "geometry": {"coordinates":[-81.224158,35.118178],"type":"Point"}
}