{
  "type": "Feature",
  "properties": {
    "iso:country":"US",
    "sg:address":"1511 Windwalk Dr",
    "sg:city":"Myrtle Beach",
    "sg:classifiers":[
        {
            "category":"Wholesale",
            "subcategory":"Groceries",
            "type":"Manufacturing & Wholesale Goods"
        }
    ],
    "sg:phone":"+1 843 215 7202",
    "sg:postcode":"29575",
    "sg:province":"SC",
    "wof:name":"Lynn Com LLC",
    "wof:placetype":"venue"
},
  "geometry": {"coordinates":[-78.97861,33.643884],"type":"Point"}
}