{
  "type": "Feature",
  "properties": {
    "addr:full":"2675 US Hwy 17 Bus Myrtle Beach SC 29577",
    "addr:housenumber":"2675",
    "addr:postcode":"29577",
    "addr:street":"Us Hwy 17 Bus",
    "iso:country":"US",
    "sg:address":"2675 US Hwy 17 Bus",
    "sg:city":"Myrtle Beach",
    "sg:classifiers":[
        {
            "category":"Wholesale",
            "subcategory":"Machinery & Supplies",
            "type":"Manufacturing & Wholesale Goods"
        }
    ],
    "sg:phone":"+1 843 293 2021",
    "sg:postcode":"29577",
    "sg:province":"SC",
    "sg:tags":[
        "equipment",
        "irrigation",
        "system"
    ],
    "wof:name":"Hughes Supply Inc",
    "wof:placetype":"venue"
},
  "geometry": {"coordinates":[-78.866631,33.706933],"type":"Point"}
}