{
  "type": "Feature",
  "properties": {
    "iso:country":"US",
    "sg:address":"2009 S Ocean Blvd",
    "sg:city":"North Myrtle Bch",
    "sg:classifiers":[
        {
            "category":"Professional",
            "type":"Services"
        }
    ],
    "sg:phone":"+1 843 272 5671",
    "sg:postcode":"29582",
    "sg:province":"SC",
    "sg:tags":[
        "establishment"
    ],
    "wof:name":"Cresent Villas",
    "wof:placetype":"venue"
},
  "geometry": {"coordinates":[-78.704632,33.805648],"type":"Point"}
}