{
  "type": "Feature",
  "properties": {
    "addr:full":"400 Main St Hilton Head Isle SC 29926",
    "addr:housenumber":"400",
    "addr:postcode":"29926",
    "addr:street":"Main St",
    "iso:country":"US",
    "sg:address":"400 Main St",
    "sg:city":"Hilton Head Isle",
    "sg:classifiers":[
        {
            "category":"Professional",
            "type":"Services"
        }
    ],
    "sg:phone":"+1 843 689 3689",
    "sg:postcode":"29926",
    "sg:province":"SC",
    "sg:tags":[
        "establishment"
    ],
    "wof:name":"Second Helpings",
    "wof:placetype":"venue"
},
  "geometry": {"coordinates":[-80.722435,32.216131],"type":"Point"}
}