{
  "type": "Feature",
  "properties": {
    "iso:country":"US",
    "sg:address":"92 Cumberland Dr",
    "sg:city":"Bluffton",
    "sg:classifiers":[
        {
            "category":"Real Estate",
            "subcategory":"Developer",
            "type":"Services"
        }
    ],
    "sg:phone":"+1 843 757 0055",
    "sg:postcode":"29910",
    "sg:province":"SC",
    "wof:name":"Oakmont Of Carolina",
    "wof:placetype":"venue"
},
  "geometry": {"coordinates":[-80.854282,32.279673],"type":"Point"}
}