{
  "type": "Feature",
  "properties": {
    "iso:country":"US",
    "sg:address":"2022 Cokesbury Rd",
    "sg:city":"Greenwood",
    "sg:classifiers":[
        {
            "category":"Organizations",
            "subcategory":"Religious Organization",
            "type":"Services"
        }
    ],
    "sg:phone":"+1 864 223 2770",
    "sg:postcode":"29649",
    "sg:province":"SC",
    "sg:tags":[
        "church"
    ],
    "sg:website":"www.gc2n.org",
    "wof:name":"Greenwood Community Church",
    "wof:placetype":"venue"
},
  "geometry": {"coordinates":[-82.17980799999999,34.237066],"type":"Point"}
}