{
  "type": "Feature",
  "properties": {
    "iso:country":"US",
    "sg:address":"2015 W Evans St",
    "sg:city":"Florence",
    "sg:classifiers":[
        {
            "category":"Shopping",
            "subcategory":"Clothing, Apparel, & Fashions",
            "type":"Retail Goods"
        }
    ],
    "sg:phone":"+1 843 662 0584",
    "sg:postcode":"29501",
    "sg:province":"SC",
    "wof:name":"Hi Lites",
    "wof:placetype":"venue"
},
  "geometry": {"coordinates":[-79.804605,34.19524],"type":"Point"}
}