{
  "type": "Feature",
  "properties": {
    "iso:country":"US",
    "sg:address":"122 Salak Rd",
    "sg:city":"Greenwood",
    "sg:classifiers":[
        {
            "category":"Sports & Exercise",
            "subcategory":"Golf",
            "type":"Entertainment"
        }
    ],
    "sg:phone":"+1 864 223 4482",
    "sg:postcode":"29646",
    "sg:province":"SC",
    "sg:tags":[
        "course"
    ],
    "wof:name":"PAR Three West",
    "wof:placetype":"venue"
},
  "geometry": {"coordinates":[-82.21862400000001,34.14754],"type":"Point"}
}