{
  "type": "Feature",
  "properties": {
    "iso:country":"US",
    "sg:address":"2245 Lamb St",
    "sg:city":"Charleston",
    "sg:classifiers":[
        {
            "category":"Building & Trades",
            "subcategory":"Construction",
            "type":"Services"
        }
    ],
    "sg:phone":"+1 843 763 7666",
    "sg:postcode":"29414",
    "sg:province":"SC",
    "sg:tags":[
        "concrete",
        "contractor"
    ],
    "wof:name":"Jet Flooring Inc",
    "wof:placetype":"venue"
},
  "geometry": {"coordinates":[-80.041162,32.785765],"type":"Point"}
}