{
  "type": "Feature",
  "properties": {
    "addr:full":"700 Haywood Rd Greenville SC 29607",
    "addr:housenumber":"700",
    "addr:postcode":"29607",
    "addr:street":"Haywood Rd",
    "iso:country":"US",
    "sg:address":"700 Haywood Rd",
    "sg:city":"Greenville",
    "sg:classifiers":[
        {
            "category":"Bakery",
            "type":"Food & Drink"
        }
    ],
    "sg:menulink":"http://www.allmenus.com/sc/greenville/230562-great-american-cookies/menu/",
    "sg:phone":"+1 864 234 5559",
    "sg:postcode":"29607",
    "sg:province":"SC",
    "sg:tags":[
        "american",
        "pastry"
    ],
    "wof:name":"Great American Cookies",
    "wof:placetype":"venue"
},
  "geometry": {"coordinates":[-82.33769599999999,34.849708],"type":"Point"}
}