{
  "type": "Feature",
  "properties": {
    "iso:country":"US",
    "sg:address":"126 White Cir",
    "sg:city":"Greenville",
    "sg:classifiers":[
        {
            "category":"Building & Trades",
            "subcategory":"Construction",
            "type":"Services"
        }
    ],
    "sg:phone":"+1 864 295 2370",
    "sg:postcode":"29611",
    "sg:province":"SC",
    "sg:tags":[
        "house"
    ],
    "wof:name":"Barker & Sons Builders",
    "wof:placetype":"venue"
},
  "geometry": {"coordinates":[-82.446907,34.841761],"type":"Point"}
}