{
  "type": "Feature",
  "properties": {
    "addr:full":"3045 N Main St Anderson SC 29621",
    "addr:housenumber":"3045",
    "addr:postcode":"29621",
    "addr:street":"N Main St",
    "iso:country":"US",
    "sg:address":"3045 N Main St",
    "sg:city":"Anderson",
    "sg:classifiers":[
        {
            "category":"Shopping",
            "subcategory":"Books",
            "type":"Retail Goods"
        }
    ],
    "sg:phone":"+1 864 225 4030",
    "sg:postcode":"29621",
    "sg:province":"SC",
    "sg:tags":[
        "dealer"
    ],
    "wof:name":"Life Way Christian Bookstore",
    "wof:placetype":"venue"
},
  "geometry": {"coordinates":[-82.66722900000001,34.537093],"type":"Point"}
}