{
  "type": "Feature",
  "properties": {
    "addr:full":"10 Lockwood Ln Bluffton SC 29945",
    "addr:housenumber":"10",
    "addr:postcode":"29945",
    "addr:street":"Lockwood Ln",
    "iso:country":"US",
    "sg:address":"10 Lockwood Ln",
    "sg:city":"Bluffton",
    "sg:classifiers":[
        {
            "category":"Professional",
            "type":"Services"
        }
    ],
    "sg:phone":"+1 843 757 4383",
    "sg:postcode":"29945",
    "sg:province":"SC",
    "sg:tags":[
        "establishment"
    ],
    "wof:name":"Medical Claims Management",
    "wof:placetype":"venue"
},
  "geometry": {"coordinates":[-80.716578,32.614363],"type":"Point"}
}