{
  "type": "Feature",
  "properties": {
    "iso:country":"US",
    "sg:address":"127 W Laurens St",
    "sg:city":"Hartsville",
    "sg:classifiers":[
        {
            "category":"Food & Beverages",
            "subcategory":"Meat & Fish",
            "type":"Retail Goods"
        }
    ],
    "sg:phone":"+1 843 332 7000",
    "sg:postcode":"29550",
    "sg:province":"SC",
    "sg:tags":[
        "seafood"
    ],
    "wof:name":"Hannibal's Seafood Market",
    "wof:placetype":"venue"
},
  "geometry": {"coordinates":[-80.073205,34.371625],"type":"Point"}
}