{
  "type": "Feature",
  "properties": {
    "iso:country":"US",
    "sg:address":"1521 Main St",
    "sg:city":"Hilton Head Isle",
    "sg:classifiers":[
        {
            "category":"Personal",
            "subcategory":"Beauty Salon",
            "type":"Services"
        }
    ],
    "sg:phone":"+1 843 681 5201",
    "sg:postcode":"29926",
    "sg:province":"SC",
    "sg:tags":[
        "manicuring"
    ],
    "wof:name":"Nails By Connie & Jill",
    "wof:placetype":"venue"
},
  "geometry": {"coordinates":[-80.724485,32.214751],"type":"Point"}
}