{
  "type": "Feature",
  "properties": {
    "iso:country":"US",
    "sg:address":"4948 Sunset Blvd",
    "sg:city":"Lexington",
    "sg:classifiers":[
        {
            "category":"Wholesale",
            "subcategory":"Sporting Goods",
            "type":"Manufacturing & Wholesale Goods"
        }
    ],
    "sg:phone":"+1 803 957 5822",
    "sg:postcode":"29072",
    "sg:province":"SC",
    "sg:tags":[
        "paint",
        "game",
        "ball"
    ],
    "wof:name":"Ballbusters Paintball",
    "wof:placetype":"venue"
},
  "geometry": {"coordinates":[-81.180181,34.012653],"type":"Point"}
}