{
  "type": "Feature",
  "properties": {
    "addr:full":"301 N Bouknight Ferry Rd Saluda SC 29138",
    "addr:housenumber":"301",
    "addr:postcode":"29138",
    "addr:street":"N Bouknight Ferry Rd",
    "iso:country":"US",
    "sg:address":"301 N Bouknight Ferry Rd",
    "sg:city":"Saluda",
    "sg:classifiers":[
        {
            "category":"Retail",
            "subcategory":"Laundry & Dry Cleaning",
            "type":"Services"
        }
    ],
    "sg:phone":"+1 864 445 2015",
    "sg:postcode":"29138",
    "sg:province":"SC",
    "sg:tags":[
        "cleaners"
    ],
    "wof:name":"Abney Cleaners",
    "wof:placetype":"venue"
},
  "geometry": {"coordinates":[-81.76139999999999,34.005244],"type":"Point"}
}