{
  "type": "Feature",
  "properties": {
    "iso:country":"US",
    "sg:address":"2100 Bush River Rd",
    "sg:city":"Columbia",
    "sg:classifiers":[
        {
            "category":"Building & Trades",
            "subcategory":"Equipment Rental",
            "type":"Services"
        }
    ],
    "sg:phone":"+1 803 731 2838",
    "sg:postcode":"29210",
    "sg:province":"SC",
    "sg:tags":[
        "audio",
        "leasing"
    ],
    "wof:name":"Presentations Services",
    "wof:placetype":"venue"
},
  "geometry": {"coordinates":[-81.119379,34.030896],"type":"Point"}
}