{
  "type": "Feature",
  "properties": {
    "iso:country":"US",
    "sg:address":"1803 Augusta St",
    "sg:city":"Greenville",
    "sg:classifiers":[
        {
            "category":"Personal",
            "subcategory":"Beauty Salon",
            "type":"Services"
        }
    ],
    "sg:phone":"+1 864 242 3081",
    "sg:postcode":"29605",
    "sg:province":"SC",
    "wof:name":"Peggy's & Cheney's Salon-Bty",
    "wof:placetype":"venue"
},
  "geometry": {"coordinates":[-82.398184,34.827486],"type":"Point"}
}