{
  "type": "Feature",
  "properties": {
    "iso:country":"US",
    "sg:address":"597 Old Mount Holly Rd",
    "sg:city":"Goose Creek",
    "sg:classifiers":[
        {
            "category":"Professional",
            "subcategory":"Lawyer & Legal Services",
            "type":"Services"
        }
    ],
    "sg:phone":"+1 843 553 6799",
    "sg:postcode":"29445",
    "sg:province":"SC",
    "sg:tags":[
        "attorney"
    ],
    "wof:name":"Wooddy Law Firm",
    "wof:placetype":"venue"
},
  "geometry": {"coordinates":[-80.057936,33.034081],"type":"Point"}
}