{
  "type": "Feature",
  "properties": {
    "addr:full":"3898 Liberty Hwy Anderson SC 29621",
    "addr:housenumber":"3898",
    "addr:postcode":"29621",
    "addr:street":"Liberty Hwy",
    "iso:country":"US",
    "sg:address":"3898 Liberty Hwy",
    "sg:city":"Anderson",
    "sg:classifiers":[
        {
            "category":"Banks & Credit Unions",
            "subcategory":"Bank",
            "type":"Services"
        }
    ],
    "sg:phone":"+1 864 260 3671",
    "sg:postcode":"29621",
    "sg:province":"SC",
    "wof:name":"Central Carolina Bank",
    "wof:placetype":"venue"
},
  "geometry": {"coordinates":[-82.682688,34.556589],"type":"Point"}
}