{
  "type": "Feature",
  "properties": {
    "iso:country":"US",
    "sg:address":"3035 Rivers Ave",
    "sg:city":"Charleston",
    "sg:classifiers":[
        {
            "category":"Retail",
            "subcategory":"Auto Repair",
            "type":"Services"
        }
    ],
    "sg:phone":"+1 843 744 0377",
    "sg:postcode":"29405",
    "sg:province":"SC",
    "sg:tags":[
        "repairing",
        "automobile"
    ],
    "wof:name":"German Auto Repair",
    "wof:placetype":"venue"
},
  "geometry": {"coordinates":[-79.969474,32.849621],"type":"Point"}
}