{
  "type": "Feature",
  "properties": {
    "iso:country":"US",
    "sg:address":"136 Greenacre Rd",
    "sg:city":"Greenville",
    "sg:classifiers":[
        {
            "category":"Professional",
            "subcategory":"Computer Services",
            "type":"Services"
        }
    ],
    "sg:phone":"+1 864 271 1200",
    "sg:postcode":"29607",
    "sg:province":"SC",
    "sg:tags":[
        "wiring"
    ],
    "sg:website":"www.integralservices.com",
    "wof:name":"Integral Services",
    "wof:placetype":"venue"
},
  "geometry": {"coordinates":[-82.368021,34.840693],"type":"Point"}
}