{
  "type": "Feature",
  "properties": {
    "iso:country":"US",
    "sg:address":"401 E Gold St",
    "sg:city":"Mc Cormick",
    "sg:classifiers":[
        {
            "category":"Health Services",
            "subcategory":"Chiropractor",
            "type":"Services"
        }
    ],
    "sg:phone":"+1 864 852 3634",
    "sg:postcode":"29835",
    "sg:province":"SC",
    "wof:name":"Lewis Chiropractic",
    "wof:placetype":"venue"
},
  "geometry": {"coordinates":[-82.290317,33.916157],"type":"Point"}
}