{
  "type": "Feature",
  "properties": {
    "iso:country":"US",
    "sg:address":"1205 2nd St",
    "sg:city":"Camden",
    "sg:classifiers":[
        {
            "category":"Retail",
            "subcategory":"Auto Repair",
            "type":"Services"
        }
    ],
    "sg:phone":"+1 803 432 7227",
    "sg:postcode":"29020",
    "sg:province":"SC",
    "sg:tags":[
        "repairing",
        "automobile"
    ],
    "wof:name":"Hough's Garage",
    "wof:placetype":"venue"
},
  "geometry": {"coordinates":[-80.571265,34.265427],"type":"Point"}
}