{
  "type": "Feature",
  "properties": {
    "addr:full":"380 Serpentine Dr Spartanburg SC 29303",
    "addr:housenumber":"380",
    "addr:postcode":"29303",
    "addr:street":"Serpentine Dr",
    "iso:country":"US",
    "sg:address":"380 Serpentine Dr",
    "sg:city":"Spartanburg",
    "sg:classifiers":[
        {
            "category":"Shopping",
            "type":"Retail Goods"
        }
    ],
    "sg:phone":"+1 864 560 7080",
    "sg:postcode":"29303",
    "sg:province":"SC",
    "sg:tags":[
        "miscellaneous",
        "store"
    ],
    "wof:name":"That Special Look-Gibbs Reginl",
    "wof:placetype":"venue"
},
  "geometry": {"coordinates":[-81.937749,34.965812],"type":"Point"}
}