{
  "type": "Feature",
  "properties": {
    "iso:country":"US",
    "sg:address":"1511 Savannah Hwy",
    "sg:city":"Charleston",
    "sg:classifiers":[
        {
            "category":"Autos & Motor Vehicles",
            "subcategory":"Automobile Sales",
            "type":"Retail Goods"
        }
    ],
    "sg:phone":"+1 843 852 4001",
    "sg:postcode":"29407",
    "sg:province":"SC",
    "sg:tags":[
        "car",
        "dealer"
    ],
    "wof:name":"Baker Motor Co",
    "wof:placetype":"venue"
},
  "geometry": {"coordinates":[-80.00485500000001,32.785266],"type":"Point"}
}