{
  "type": "Feature",
  "properties": {
    "iso:country":"US",
    "sg:address":"320 Main St",
    "sg:city":"Conway",
    "sg:classifiers":[
        {
            "category":"Shopping",
            "subcategory":"Clothing, Apparel, & Fashions",
            "type":"Retail Goods"
        }
    ],
    "sg:phone":"+1 843 488 0595",
    "sg:postcode":"29526",
    "sg:province":"SC",
    "sg:tags":[
        "swimwear",
        "accessory"
    ],
    "wof:name":"Tara Grinna Swimwear",
    "wof:placetype":"venue"
},
  "geometry": {"coordinates":[-79.04608,33.835436],"type":"Point"}
}