{
  "type": "Feature",
  "properties": {
    "iso:country":"US",
    "sg:address":"6079 Crabtree Rd",
    "sg:city":"Columbia",
    "sg:classifiers":[
        {
            "category":"Building & Trades",
            "subcategory":"Plumbing",
            "type":"Services"
        }
    ],
    "sg:phone":"+1 803 782 6422",
    "sg:postcode":"29206",
    "sg:province":"SC",
    "sg:tags":[
        "plumbing",
        "contractor"
    ],
    "wof:name":"Cook Plumbing Co",
    "wof:placetype":"venue"
},
  "geometry": {"coordinates":[-80.945705,34.03735],"type":"Point"}
}