{
  "type": "Feature",
  "properties": {
    "iso:country":"US",
    "sg:address":"5830 State Hwy 174",
    "sg:city":"Adams Run",
    "sg:classifiers":[
        {
            "category":"Organizations",
            "subcategory":"Religious Organization",
            "type":"Services"
        }
    ],
    "sg:phone":"+1 843 889 8813",
    "sg:postcode":"29426",
    "sg:province":"SC",
    "sg:tags":[
        "church"
    ],
    "wof:name":"Grace Chapel Baptist Church",
    "wof:placetype":"venue"
},
  "geometry": {"coordinates":[-80.346534,32.75307],"type":"Point"}
}