{
  "type": "Feature",
  "properties": {
    "iso:country":"US",
    "sg:address":"124 Old Mill Rd",
    "sg:city":"Greenville",
    "sg:classifiers":[
        {
            "category":"Wholesale",
            "subcategory":"Machinery & Supplies",
            "type":"Manufacturing & Wholesale Goods"
        },
        {
            "category":"Manufacturing",
            "subcategory":"Tools & Machinery",
            "type":"Manufacturing & Wholesale Goods"
        }
    ],
    "sg:phone":"+1 864 234 0706",
    "sg:postcode":"29607",
    "sg:province":"SC",
    "sg:tags":[
        "equipment",
        "dock",
        "loading",
        "mfg"
    ],
    "wof:name":"Arbon Equipment Corporation",
    "wof:placetype":"venue"
},
  "geometry": {"coordinates":[-82.306494,34.794644],"type":"Point"}
}