{
  "type": "Feature",
  "properties": {
    "addr:full":"270 Heatherlock Rd Clover SC 29710",
    "addr:housenumber":"270",
    "addr:postcode":"29710",
    "addr:street":"Heatherlock Rd",
    "iso:country":"US",
    "sg:address":"270 Heatherlock Rd",
    "sg:city":"Clover",
    "sg:classifiers":[
        {
            "category":"Manufacturing",
            "subcategory":"Printing",
            "type":"Manufacturing & Wholesale Goods"
        }
    ],
    "sg:phone":"+1 803 222 6514",
    "sg:postcode":"29710",
    "sg:province":"SC",
    "sg:tags":[
        "lithographic",
        "commercial"
    ],
    "wof:name":"Pressroom Printing Company",
    "wof:placetype":"venue"
},
  "geometry": {"coordinates":[-81.25067799999999,35.115084],"type":"Point"}
}