{
  "type": "Feature",
  "properties": {
    "iso:country":"US",
    "sg:address":"312 Porcher Ave",
    "sg:city":"Eutawville",
    "sg:classifiers":[
        {
            "category":"Organizations",
            "subcategory":"Non-profit Organization",
            "type":"Services"
        }
    ],
    "sg:phone":"+1 803 492 4963",
    "sg:postcode":"29048",
    "sg:province":"SC",
    "sg:tags":[
        "alternative",
        "abortion"
    ],
    "wof:name":"A Place For Zoe",
    "wof:placetype":"venue"
},
  "geometry": {"coordinates":[-80.347334,33.394708],"type":"Point"}
}