{
  "type": "Feature",
  "properties": {
    "iso:country":"US",
    "sg:address":"6 Calender Ct",
    "sg:city":"Columbia",
    "sg:classifiers":[
        {
            "category":"Banks & Credit Unions",
            "subcategory":"Investment Brokerage",
            "type":"Services"
        }
    ],
    "sg:phone":"+1 803 782 7646",
    "sg:postcode":"29206",
    "sg:province":"SC",
    "wof:name":"Graham & Assoc",
    "wof:placetype":"venue"
},
  "geometry": {"coordinates":[-80.96452499999999,34.014478],"type":"Point"}
}