{
  "type": "Feature",
  "properties": {
    "iso:country":"US",
    "sg:address":"167 Bluffton Rd",
    "sg:city":"Bluffton",
    "sg:classifiers":[
        {
            "category":"Health Services",
            "subcategory":"Doctor",
            "type":"Services"
        }
    ],
    "sg:phone":"+1 843 706 3592",
    "sg:postcode":"29910",
    "sg:province":"SC",
    "sg:tags":[
        "physician",
        "surgeon"
    ],
    "wof:name":"Coastal Cardiovascular Clinic",
    "wof:placetype":"venue"
},
  "geometry": {"coordinates":[-80.858645,32.243492],"type":"Point"}
}