{
  "type": "Feature",
  "properties": {
    "addr:full":"3910 Bluff Rd Columbia SC 29209",
    "addr:housenumber":"3910",
    "addr:postcode":"29209",
    "addr:street":"Bluff Rd",
    "iso:country":"US",
    "sg:address":"3910 Bluff Rd",
    "sg:city":"Columbia",
    "sg:classifiers":[
        {
            "category":"Organizations",
            "subcategory":"Religious Organization",
            "type":"Services"
        }
    ],
    "sg:phone":"+1 803 695 0226",
    "sg:postcode":"29209",
    "sg:province":"SC",
    "sg:tags":[
        "church"
    ],
    "wof:name":"Bethlehem Baptist Church",
    "wof:placetype":"venue"
},
  "geometry": {"coordinates":[-80.97624,33.935624],"type":"Point"}
}