{
  "type": "Feature",
  "properties": {
    "iso:country":"US",
    "sg:address":"350 Wilson Ferry Rd",
    "sg:city":"Moore",
    "sg:classifiers":[
        {
            "category":"Building & Trades",
            "subcategory":"Landscaping Services",
            "type":"Services"
        }
    ],
    "sg:phone":"+1 864 576 0910",
    "sg:postcode":"29369",
    "sg:province":"SC",
    "wof:name":"C & N Enterprises",
    "wof:placetype":"venue"
},
  "geometry": {"coordinates":[-82.034676,34.880463],"type":"Point"}
}