{
  "type": "Feature",
  "properties": {
    "iso:country":"US",
    "sg:address":"1012 Glenns Bay Rd",
    "sg:city":"Myrtle Beach",
    "sg:classifiers":[
        {
            "category":"Autos & Motor Vehicles",
            "subcategory":"Automobile Sales",
            "type":"Retail Goods"
        }
    ],
    "sg:phone":"+1 843 238 5519",
    "sg:postcode":"29575",
    "sg:province":"SC",
    "sg:tags":[
        "car",
        "dealer"
    ],
    "wof:name":"Beach Boys Auto Sales",
    "wof:placetype":"venue"
},
  "geometry": {"coordinates":[-78.982881,33.613029],"type":"Point"}
}