{
  "type": "Feature",
  "properties": {
    "addr:full":"640 Folly Rd Charleston SC 29412",
    "addr:housenumber":"640",
    "addr:postcode":"29412",
    "addr:street":"Folly Rd",
    "iso:country":"US",
    "sg:address":"640 Folly Rd",
    "sg:city":"Charleston",
    "sg:classifiers":[
        {
            "category":"Banks & Credit Unions",
            "subcategory":"Bank",
            "type":"Services"
        }
    ],
    "sg:phone":"+1 843 727 1120",
    "sg:postcode":"29412",
    "sg:province":"SC",
    "wof:name":"Wachovia Bank",
    "wof:placetype":"venue"
},
  "geometry": {"coordinates":[-79.97215300000001,32.750405],"type":"Point"}
}