{
  "type": "Feature",
  "properties": {
    "iso:country":"US",
    "sg:address":"4819 State Hwy 86",
    "sg:city":"Easley",
    "sg:classifiers":[
        {
            "category":"Building & Trades",
            "subcategory":"Construction",
            "type":"Services"
        }
    ],
    "sg:phone":"+1 864 306 6544",
    "sg:postcode":"29642",
    "sg:province":"SC",
    "sg:tags":[
        "contractor"
    ],
    "wof:name":"Greenville Builders",
    "wof:placetype":"venue"
},
  "geometry": {"coordinates":[-82.55453,34.750134],"type":"Point"}
}