{
  "type": "Feature",
  "properties": {
    "addr:full":"196 Michelin Rd Greenville SC 29605",
    "addr:housenumber":"196",
    "addr:postcode":"29605",
    "addr:street":"Michelin Rd",
    "iso:country":"US",
    "sg:address":"196 Michelin Rd",
    "sg:city":"Greenville",
    "sg:classifiers":[
        {
            "category":"Manufacturing",
            "subcategory":"Paper Products",
            "type":"Manufacturing & Wholesale Goods"
        }
    ],
    "sg:phone":"+1 864 422 0121",
    "sg:postcode":"29605",
    "sg:province":"SC",
    "sg:tags":[
        "mill",
        "pulp"
    ],
    "wof:name":"SE Paperboard",
    "wof:placetype":"venue"
},
  "geometry": {"coordinates":[-82.356874,34.721914],"type":"Point"}
}