{
  "type": "Feature",
  "properties": {
    "iso:country":"US",
    "sg:address":"1424 Madison Dr",
    "sg:city":"North Myrtle Bch",
    "sg:classifiers":[
        {
            "category":"Real Estate",
            "subcategory":"Real Estate Agent",
            "type":"Services"
        }
    ],
    "sg:phone":"+1 843 361 7502",
    "sg:postcode":"29582",
    "sg:province":"SC",
    "wof:name":"Samuel Blaine Realty",
    "wof:placetype":"venue"
},
  "geometry": {"coordinates":[-78.697749,33.814156],"type":"Point"}
}