{
  "type": "Feature",
  "properties": {
    "addr:full":"108 Park Dr Chapin SC 29036",
    "addr:housenumber":"108",
    "addr:postcode":"29036",
    "addr:street":"Park Dr",
    "iso:country":"US",
    "sg:address":"108 Park Dr",
    "sg:city":"Chapin",
    "sg:classifiers":[
        {
            "category":"Building & Trades",
            "subcategory":"Construction",
            "type":"Services"
        }
    ],
    "sg:phone":"+1 803 945 4652",
    "sg:postcode":"29036",
    "sg:province":"SC",
    "sg:tags":[
        "contractor"
    ],
    "wof:name":"A Lott Tile",
    "wof:placetype":"venue"
},
  "geometry": {"coordinates":[-81.426171,34.131004],"type":"Point"}
}