{
  "type": "Feature",
  "properties": {
    "iso:country":"US",
    "sg:address":"807 Holland Rd",
    "sg:city":"Simpsonville",
    "sg:classifiers":[
        {
            "category":"Freight",
            "type":"Transportation"
        }
    ],
    "sg:phone":"+1 864 288 3900",
    "sg:postcode":"29681",
    "sg:province":"SC",
    "sg:tags":[
        "repair",
        "management",
        "container",
        "cleaning"
    ],
    "wof:name":"RPR",
    "wof:placetype":"venue"
},
  "geometry": {"coordinates":[-82.276872,34.785061],"type":"Point"}
}