{
  "type": "Feature",
  "properties": {
    "addr:full":"910 Knox Abbott Dr Cayce SC 29033",
    "addr:housenumber":"910",
    "addr:postcode":"29033",
    "addr:street":"Knox Abbott Dr",
    "iso:country":"US",
    "sg:address":"910 Knox Abbott Dr",
    "sg:city":"Cayce",
    "sg:classifiers":[
        {
            "category":"Personal",
            "subcategory":"Beauty Salon",
            "type":"Services"
        }
    ],
    "sg:phone":"+1 803 936 1717",
    "sg:postcode":"29033",
    "sg:province":"SC",
    "wof:name":"Unique Images II",
    "wof:placetype":"venue"
},
  "geometry": {"coordinates":[-81.066564,33.980744],"type":"Point"}
}