{
  "type": "Feature",
  "properties": {
    "iso:country":"US",
    "sg:address":"832 Bush River Rd",
    "sg:city":"Columbia",
    "sg:classifiers":[
        {
            "category":"Banks & Credit Unions",
            "subcategory":"Bank",
            "type":"Services"
        }
    ],
    "sg:phone":"+1 803 251 7900",
    "sg:postcode":"29210",
    "sg:province":"SC",
    "sg:tags":[
        "national",
        "commercial"
    ],
    "wof:name":"Wachovia Bank National Assn",
    "wof:placetype":"venue"
},
  "geometry": {"coordinates":[-81.10061,34.030103],"type":"Point"}
}