{
  "type": "Feature",
  "properties": {
    "addr:full":"255 Arlington Rd Sumter SC 29153",
    "addr:housenumber":"255",
    "addr:postcode":"29153",
    "addr:street":"Arlington Rd",
    "iso:country":"US",
    "sg:address":"255 Arlington Rd",
    "sg:city":"Sumter",
    "sg:classifiers":[
        {
            "category":"Real Estate",
            "subcategory":"Real Estate Operator",
            "type":"Services"
        }
    ],
    "sg:phone":"+1 803 469 4409",
    "sg:postcode":"29153",
    "sg:province":"SC",
    "sg:tags":[
        "farm",
        "property",
        "lessor",
        "cotton"
    ],
    "wof:name":"Porter John",
    "wof:placetype":"venue"
},
  "geometry": {"coordinates":[-80.33956000000001,34.038504],"type":"Point"}
}