{
  "type": "Feature",
  "properties": {
    "iso:country":"US",
    "sg:address":"6518 Dorchester Rd",
    "sg:city":"North Charleston",
    "sg:classifiers":[
        {
            "category":"Health Services",
            "subcategory":"Doctor",
            "type":"Services"
        }
    ],
    "sg:phone":"+1 843 767 3323",
    "sg:postcode":"29418",
    "sg:province":"SC",
    "sg:tags":[
        "physician",
        "surgeon"
    ],
    "wof:name":"Heather R Dawson MD",
    "wof:placetype":"venue"
},
  "geometry": {"coordinates":[-80.062183,32.878214],"type":"Point"}
}