{
  "type": "Feature",
  "properties": {
    "addr:full":"2701 David H McLeod Blvd Florence SC 29501",
    "addr:housenumber":"2701",
    "addr:postcode":"29501",
    "addr:street":"David H Mcleod Blvd",
    "iso:country":"US",
    "sg:address":"2701 David H McLeod Blvd",
    "sg:city":"Florence",
    "sg:classifiers":[
        {
            "category":"Restaurant",
            "type":"Food & Drink"
        }
    ],
    "sg:phone":"+1 843 667 4569",
    "sg:postcode":"29501",
    "sg:province":"SC",
    "sg:tags":[
        "family"
    ],
    "wof:name":"Ruby Tuesday",
    "wof:placetype":"venue"
},
  "geometry": {"coordinates":[-79.83568099999999,34.18968],"type":"Point"}
}