{
  "type": "Feature",
  "properties": {
    "iso:country":"US",
    "sg:address":"113 S Forest St",
    "sg:city":"Spartanburg",
    "sg:classifiers":[
        {
            "category":"Retail",
            "subcategory":"Auto Repair",
            "type":"Services"
        }
    ],
    "sg:phone":"+1 864 582 8848",
    "sg:postcode":"29306",
    "sg:province":"SC",
    "sg:tags":[
        "wrecker"
    ],
    "wof:name":"Scruggs Wrecker Svc",
    "wof:placetype":"venue"
},
  "geometry": {"coordinates":[-81.939714,34.945782],"type":"Point"}
}