{
  "type": "Feature",
  "properties": {
    "iso:country":"US",
    "sg:address":"5822 Columbia Hwy N",
    "sg:city":"Monetta",
    "sg:classifiers":[
        {
            "category":"Cinema",
            "subcategory":"Movie Theater",
            "type":"Entertainment"
        }
    ],
    "sg:phone":"+1 803 685 7949",
    "sg:postcode":"29105",
    "sg:province":"SC",
    "wof:name":"Monetta Drive In Theatre",
    "wof:placetype":"venue"
},
  "geometry": {"coordinates":[-81.594565,33.856135],"type":"Point"}
}