{
  "type": "Feature",
  "properties": {
    "iso:country":"US",
    "sg:address":"8510 Rivers Ave",
    "sg:city":"Charleston",
    "sg:classifiers":[
        {
            "category":"Retail",
            "subcategory":"Laundry & Dry Cleaning",
            "type":"Services"
        }
    ],
    "sg:phone":"+1 843 797 5218",
    "sg:postcode":"29406",
    "sg:province":"SC",
    "sg:tags":[
        "cleaners",
        "plant",
        "power",
        "drycleaning"
    ],
    "wof:name":"One Hour Valet",
    "wof:placetype":"venue"
},
  "geometry": {"coordinates":[-80.04285299999999,32.958276],"type":"Point"}
}