{
  "type": "Feature",
  "properties": {
    "iso:country":"US",
    "sg:address":"300 Henry Pl",
    "sg:city":"Spartanburg",
    "sg:classifiers":[
        {
            "category":"Professional",
            "subcategory":"Research",
            "type":"Services"
        }
    ],
    "sg:phone":"+1 864 582 1222",
    "sg:postcode":"29306",
    "sg:province":"SC",
    "sg:tags":[
        "environmental",
        "ecological"
    ],
    "sg:website":"www.aaaenvironmental.com",
    "wof:name":"AAA Environmental",
    "wof:placetype":"venue"
},
  "geometry": {"coordinates":[-81.925524,34.946518],"type":"Point"}
}