{
  "type": "Feature",
  "properties": {
    "iso:country":"US",
    "sg:address":"4141 Dorchester Rd",
    "sg:city":"North Charleston",
    "sg:classifiers":[
        {
            "category":"Retail",
            "subcategory":"Auto Repair",
            "type":"Services"
        }
    ],
    "sg:phone":"+1 843 554 1426",
    "sg:postcode":"29405",
    "sg:province":"SC",
    "sg:tags":[
        "body",
        "automobile",
        "painting"
    ],
    "wof:name":"Palmetto Collision",
    "wof:placetype":"venue"
},
  "geometry": {"coordinates":[-80.00191599999999,32.853757],"type":"Point"}
}