{
  "type": "Feature",
  "properties": {
    "addr:full":"950 W Faris Rd Greenville SC 29605",
    "addr:housenumber":"950",
    "addr:postcode":"29605",
    "addr:street":"W Faris Rd",
    "iso:country":"US",
    "sg:address":"950 W Faris Rd",
    "sg:city":"Greenville",
    "sg:classifiers":[
        {
            "category":"Health Services",
            "subcategory":"Hospital",
            "type":"Services"
        }
    ],
    "sg:phone":"+1 864 271 3444",
    "sg:postcode":"29605",
    "sg:province":"SC",
    "wof:name":"Shriners Hospital For Children",
    "wof:placetype":"venue"
},
  "geometry": {"coordinates":[-82.41762199999999,34.817824],"type":"Point"}
}