{
  "type": "Feature",
  "properties": {
    "addr:full":"2 Merchant Ln Beaufort SC 29907",
    "addr:housenumber":"2",
    "addr:postcode":"29907",
    "addr:street":"Merchant Ln",
    "iso:country":"US",
    "sg:address":"2 Merchant Ln",
    "sg:city":"Beaufort",
    "sg:classifiers":[
        {
            "category":"Food & Beverages",
            "subcategory":"Specialty",
            "type":"Retail Goods"
        }
    ],
    "sg:phone":"+1 843 470 9001",
    "sg:postcode":"29907",
    "sg:province":"SC",
    "wof:name":"Island Wellness Shoppe",
    "wof:placetype":"venue"
},
  "geometry": {"coordinates":[-80.640654,32.434354],"type":"Point"}
}