{
  "type": "Feature",
  "properties": {
    "iso:country":"US",
    "sg:address":"60 Pope Ave",
    "sg:city":"Hilton Head Isle",
    "sg:classifiers":[
        {
            "category":"Building & Trades",
            "subcategory":"Equipment Rental",
            "type":"Services"
        }
    ],
    "sg:phone":"+1 843 686 2003",
    "sg:postcode":"29928",
    "sg:province":"SC",
    "sg:tags":[
        "audio",
        "leasing"
    ],
    "wof:name":"Presentation Services",
    "wof:placetype":"venue"
},
  "geometry": {"coordinates":[-80.755196,32.146648],"type":"Point"}
}