{
  "type": "Feature",
  "properties": {
    "iso:country":"US",
    "sg:address":"35 de Allyon Ave",
    "sg:city":"Hilton Head Isle",
    "sg:classifiers":[
        {
            "category":"Real Estate",
            "subcategory":"Real Estate Agent",
            "type":"Services"
        }
    ],
    "sg:phone":"+1 843 785 3355",
    "sg:postcode":"29928",
    "sg:province":"SC",
    "sg:tags":[
        "management"
    ],
    "wof:name":"Southwind Management Corp",
    "wof:placetype":"venue"
},
  "geometry": {"coordinates":[-80.758329,32.142364],"type":"Point"}
}