{
  "type": "Feature",
  "properties": {
    "addr:full":"5897 Farrow Rd Columbia SC 29203",
    "addr:housenumber":"5897",
    "addr:postcode":"29203",
    "addr:street":"Farrow Rd",
    "iso:country":"US",
    "sg:address":"5897 Farrow Rd",
    "sg:city":"Columbia",
    "sg:classifiers":[
        {
            "category":"Organizations",
            "subcategory":"Religious Organization",
            "type":"Services"
        }
    ],
    "sg:phone":"+1 803 333 9444",
    "sg:postcode":"29203",
    "sg:province":"SC",
    "sg:tags":[
        "church"
    ],
    "wof:name":"Saving Grace In The Lord Jesus",
    "wof:placetype":"venue"
},
  "geometry": {"coordinates":[-81.001521,34.056642],"type":"Point"}
}