{
  "type": "Feature",
  "properties": {
    "iso:country":"US",
    "sg:address":"110 Wildewood Park Dr",
    "sg:city":"Columbia",
    "sg:classifiers":[
        {
            "category":"Professional",
            "subcategory":"Research",
            "type":"Services"
        }
    ],
    "sg:phone":"+1 803 788 0397",
    "sg:postcode":"29223",
    "sg:province":"SC",
    "sg:tags":[
        "market",
        "analysis"
    ],
    "sg:website":"www.woodsresearch.net",
    "wof:name":"Woods Research Inc",
    "wof:placetype":"venue"
},
  "geometry": {"coordinates":[-80.890117,34.11207],"type":"Point"}
}