{
  "type": "Feature",
  "properties": {
    "addr:full":"1731 Old Newberry Hwy Saluda SC 29178",
    "addr:housenumber":"1731",
    "addr:postcode":"29178",
    "addr:street":"Old Newberry Hwy",
    "iso:country":"US",
    "sg:address":"1731 Old Newberry Hwy",
    "sg:city":"Saluda",
    "sg:classifiers":[
        {
            "category":"Manufacturing",
            "subcategory":"Lumber",
            "type":"Manufacturing & Wholesale Goods"
        }
    ],
    "sg:phone":"+1 864 445 2165",
    "sg:postcode":"29178",
    "sg:province":"SC",
    "sg:tags":[
        "logging"
    ],
    "wof:name":"Chajan Logging",
    "wof:placetype":"venue"
},
  "geometry": {"coordinates":[-81.600768,34.444695],"type":"Point"}
}