{
  "type": "Feature",
  "properties": {
    "iso:country":"US",
    "sg:address":"412 Main St",
    "sg:city":"Conway",
    "sg:classifiers":[
        {
            "category":"Shopping",
            "subcategory":"Gifts & Souvenirs",
            "type":"Retail Goods"
        }
    ],
    "sg:phone":"+1 843 248 9676",
    "sg:postcode":"29526",
    "sg:province":"SC",
    "wof:name":"Paynes Pickins",
    "wof:placetype":"venue"
},
  "geometry": {"coordinates":[-79.047413,33.837397],"type":"Point"}
}