{
  "type": "Feature",
  "properties": {
    "addr:full":"412 Main St Conway SC 29526",
    "addr:housenumber":"412",
    "addr:postcode":"29526",
    "addr:street":"Main St",
    "iso:country":"US",
    "sg:address":"412 Main St",
    "sg:city":"Conway",
    "sg:classifiers":[
        {
            "category":"Shopping",
            "subcategory":"Gifts & Souvenirs",
            "type":"Retail Goods"
        }
    ],
    "sg:phone":"+1 843 248 9676",
    "sg:postcode":"29526",
    "sg:province":"SC",
    "wof:name":"Paynes Pickins",
    "wof:placetype":"venue"
},
  "geometry": {"coordinates":[-79.04741300000001,33.837397],"type":"Point"}
}