{
  "type": "Feature",
  "properties": {
    "addr:full":"1837 N Main St Summerville SC 29483",
    "addr:housenumber":"1837",
    "addr:postcode":"29483",
    "addr:street":"N Main St",
    "iso:country":"US",
    "sg:address":"1837 N Main St",
    "sg:city":"Summerville",
    "sg:phone":"+1 843 821 0161",
    "sg:postcode":"29483",
    "sg:province":"SC",
    "sg:tags":[
        "fuel",
        "diesel"
    ],
    "wof:name":"Carolina Diesel Svc",
    "wof:placetype":"venue"
},
  "geometry": {"coordinates":[-80.127506,33.042491],"type":"Point"}
}