{
  "type": "Feature",
  "properties": {
    "iso:country":"US",
    "sg:address":"2750 Camden Hwy",
    "sg:city":"Sumter",
    "sg:classifiers":[
        {
            "category":"Wholesale",
            "subcategory":"Hardware",
            "type":"Manufacturing & Wholesale Goods"
        }
    ],
    "sg:phone":"+1 803 469 6658",
    "sg:postcode":"29153",
    "sg:province":"SC",
    "sg:tags":[
        "equipment",
        "heating",
        "system"
    ],
    "wof:name":"Earnie's Heating & Air",
    "wof:placetype":"venue"
},
  "geometry": {"coordinates":[-80.405591,33.997881],"type":"Point"}
}