{
  "type": "Feature",
  "properties": {
    "addr:full":"3875 River Dr Columbia SC 29201",
    "addr:housenumber":"3875",
    "addr:postcode":"29201",
    "addr:street":"River Dr",
    "iso:country":"US",
    "sg:address":"3875 River Dr",
    "sg:city":"Columbia",
    "sg:classifiers":[
        {
            "category":"Personal",
            "subcategory":"Beauty Salon",
            "type":"Services"
        }
    ],
    "sg:phone":"+1 803 806 8093",
    "sg:postcode":"29201",
    "sg:province":"SC",
    "wof:name":"Solution Beauty Salon",
    "wof:placetype":"venue"
},
  "geometry": {"coordinates":[-81.06186,34.027465],"type":"Point"}
}