{
  "type": "Feature",
  "properties": {
    "iso:country":"US",
    "sg:address":"146 W Phillips Rd",
    "sg:city":"Greer",
    "sg:classifiers":[
        {
            "category":"Wholesale",
            "subcategory":"Office Equipment",
            "type":"Manufacturing & Wholesale Goods"
        }
    ],
    "sg:phone":"+1 864 877 9899",
    "sg:postcode":"29650",
    "sg:province":"SC",
    "sg:tags":[
        "machine",
        "facsimile",
        "copier",
        "duplicating",
        "copying"
    ],
    "wof:name":"Upstate Business Solutions",
    "wof:placetype":"venue"
},
  "geometry": {"coordinates":[-82.22589499999999,34.872252],"type":"Point"}
}