{
  "type": "Feature",
  "properties": {
    "iso:country":"US",
    "sg:address":"787 Wilson Rd",
    "sg:city":"Newberry",
    "sg:classifiers":[
        {
            "category":"Manufacturing",
            "subcategory":"Lumber",
            "type":"Manufacturing & Wholesale Goods"
        }
    ],
    "sg:phone":"+1 803 276 9425",
    "sg:postcode":"29108",
    "sg:province":"SC",
    "sg:tags":[
        "forester"
    ],
    "wof:name":"Henderson & Major Inc",
    "wof:placetype":"venue"
},
  "geometry": {"coordinates":[-81.592219,34.275883],"type":"Point"}
}