{
  "type": "Feature",
  "properties": {
    "addr:full":"1799 US Hwy 701 N Loris SC 29569",
    "addr:housenumber":"1799",
    "addr:postcode":"29569",
    "addr:street":"Us Hwy 701 N",
    "iso:country":"US",
    "sg:address":"1799 US Hwy 701 N",
    "sg:city":"Loris",
    "sg:classifiers":[
        {
            "category":"Shopping",
            "type":"Retail Goods"
        }
    ],
    "sg:phone":"+1 843 756 4056",
    "sg:postcode":"29569",
    "sg:province":"SC",
    "sg:tags":[
        "farm",
        "feed",
        "supply"
    ],
    "wof:name":"S S C",
    "wof:placetype":"venue"
},
  "geometry": {"coordinates":[-78.87519399999999,34.098991],"type":"Point"}
}