{
  "type": "Feature",
  "properties": {
    "addr:full":"1544 Pine Ridge Dr West Columbia SC 29172",
    "addr:housenumber":"1544",
    "addr:postcode":"29172",
    "addr:street":"Pine Ridge Dr",
    "iso:country":"US",
    "sg:address":"1544 Pine Ridge Dr",
    "sg:city":"West Columbia",
    "sg:classifiers":[
        {
            "category":"Manufacturing",
            "subcategory":"Metals",
            "type":"Manufacturing & Wholesale Goods"
        }
    ],
    "sg:phone":"+1 803 794 5452",
    "sg:postcode":"29172",
    "sg:province":"SC",
    "sg:tags":[
        "steel"
    ],
    "wof:name":"Dixiana Steel Co",
    "wof:placetype":"venue"
},
  "geometry": {"coordinates":[-81.06770899999999,33.90907],"type":"Point"}
}