{
  "type": "Feature",
  "properties": {
    "iso:country":"US",
    "sg:address":"1704 Old Trolley Rd",
    "sg:city":"Summerville",
    "sg:classifiers":[
        {
            "category":"Restaurant",
            "type":"Food & Drink"
        }
    ],
    "sg:phone":"+1 843 695 0606",
    "sg:postcode":"29485",
    "sg:province":"SC",
    "wof:name":"Coffee Detour",
    "wof:placetype":"venue"
},
  "geometry": {"coordinates":[-80.164963,32.959148],"type":"Point"}
}