{
  "type": "Feature",
  "properties": {
    "iso:country":"US",
    "sg:address":"1500 Sj Workman Hwy",
    "sg:city":"Woodruff",
    "sg:classifiers":[
        {
            "category":"Building & Trades",
            "subcategory":"Construction",
            "type":"Services"
        }
    ],
    "sg:phone":"+1 864 476 8147",
    "sg:postcode":"29388",
    "sg:province":"SC",
    "sg:tags":[
        "excavating",
        "contractor"
    ],
    "wof:name":"Theo Brothers Construction Co",
    "wof:placetype":"venue"
},
  "geometry": {"coordinates":[-81.98189499999999,34.744615],"type":"Point"}
}