{
  "type": "Feature",
  "properties": {
    "addr:full":"3163 Hall Rd Conway SC 29526",
    "addr:housenumber":"3163",
    "addr:postcode":"29526",
    "addr:street":"Hall Rd",
    "iso:country":"US",
    "sg:address":"3163 Hall Rd",
    "sg:city":"Conway",
    "sg:classifiers":[
        {
            "category":"Building & Trades",
            "subcategory":"Construction",
            "type":"Services"
        }
    ],
    "sg:phone":"+1 843 365 4044",
    "sg:postcode":"29526",
    "sg:province":"SC",
    "sg:tags":[
        "siding",
        "contractor"
    ],
    "wof:name":"Hall's Vinyl Skirting",
    "wof:placetype":"venue"
},
  "geometry": {"coordinates":[-79.031662,33.913572],"type":"Point"}
}