{
  "type": "Feature",
  "properties": {
    "iso:country":"US",
    "sg:address":"225 Kingston St",
    "sg:city":"Conway",
    "sg:classifiers":[
        {
            "category":"Shopping",
            "subcategory":"Used Merchandise",
            "type":"Retail Goods"
        }
    ],
    "sg:phone":"+1 843 488 9472",
    "sg:postcode":"29526",
    "sg:province":"SC",
    "wof:name":"Encore",
    "wof:placetype":"venue"
},
  "geometry": {"coordinates":[-79.044498,33.835131],"type":"Point"}
}