{
  "type": "Feature",
  "properties": {
    "iso:country":"US",
    "sg:address":"763 Givhans Rd",
    "sg:city":"Ridgeville",
    "sg:classifiers":[
        {
            "category":"Building & Trades",
            "subcategory":"Construction",
            "type":"Services"
        }
    ],
    "sg:phone":"+1 843 873 4502",
    "sg:postcode":"29472",
    "sg:province":"SC",
    "sg:tags":[
        "contractor"
    ],
    "wof:name":"Custom Construction & Rmdlg",
    "wof:placetype":"venue"
},
  "geometry": {"coordinates":[-80.31527199999999,33.053316],"type":"Point"}
}