{
  "type": "Feature",
  "properties": {
    "iso:country":"US",
    "sg:address":"124 N Georgetown Hwy",
    "sg:city":"Johnsonville",
    "sg:classifiers":[
        {
            "category":"Insurance",
            "subcategory":"Insurance Agent",
            "type":"Services"
        }
    ],
    "sg:phone":"+1 843 386 2836",
    "sg:postcode":"29555",
    "sg:province":"SC",
    "wof:name":"Farm Bureau Insurance",
    "wof:placetype":"venue"
},
  "geometry": {"coordinates":[-79.442672,33.820411],"type":"Point"}
}