{
  "type": "Feature",
  "properties": {
    "iso:country":"US",
    "sg:address":"201 Oak Dr",
    "sg:city":"Lexington",
    "sg:classifiers":[
        {
            "category":"Manufacturing",
            "subcategory":"Printing",
            "type":"Manufacturing & Wholesale Goods"
        }
    ],
    "sg:phone":"+1 803 358 6527",
    "sg:postcode":"29073",
    "sg:province":"SC",
    "sg:tags":[
        "periodical"
    ],
    "wof:name":"Simply Southern Magazine Inc",
    "wof:placetype":"venue"
},
  "geometry": {"coordinates":[-81.155312,33.976627],"type":"Point"}
}