{
  "type": "Feature",
  "properties": {
    "iso:country":"US",
    "sg:address":"175 Benthomp Rd",
    "sg:city":"Orangeburg",
    "sg:classifiers":[
        {
            "category":"Building & Trades",
            "subcategory":"Construction",
            "type":"Services"
        }
    ],
    "sg:phone":"+1 803 534 8031",
    "sg:postcode":"29115",
    "sg:province":"SC",
    "sg:tags":[
        "house"
    ],
    "wof:name":"M & K Remodeling LLC",
    "wof:placetype":"venue"
},
  "geometry": {"coordinates":[-80.797698,33.512383],"type":"Point"}
}