{
  "type": "Feature",
  "properties": {
    "iso:country":"US",
    "sg:address":"130 Willard St",
    "sg:city":"Greenville",
    "sg:classifiers":[
        {
            "category":"Railroad",
            "type":"Transportation"
        }
    ],
    "sg:phone":"+1 864 282 1977",
    "sg:postcode":"29611",
    "sg:province":"SC",
    "sg:tags":[
        "line"
    ],
    "wof:name":"CSX",
    "wof:placetype":"venue"
},
  "geometry": {"coordinates":[-82.417544,34.854143],"type":"Point"}
}