{
  "type": "Feature",
  "properties": {
    "addr:full":"130 Willard St Greenville SC 29611",
    "addr:housenumber":"130",
    "addr:postcode":"29611",
    "addr:street":"Willard St",
    "iso:country":"US",
    "sg:address":"130 Willard St",
    "sg:city":"Greenville",
    "sg:classifiers":[
        {
            "category":"Railroad",
            "type":"Transportation"
        }
    ],
    "sg:phone":"+1 864 282 1977",
    "sg:postcode":"29611",
    "sg:province":"SC",
    "sg:tags":[
        "line"
    ],
    "wof:name":"CSX",
    "wof:placetype":"venue"
},
  "geometry": {"coordinates":[-82.41754400000001,34.854143],"type":"Point"}
}