{
  "type": "Feature",
  "properties": {
    "iso:country":"US",
    "sg:address":"4556 Broad River Rd",
    "sg:city":"Columbia",
    "sg:classifiers":[
        {
            "category":"Government",
            "subcategory":"Jail",
            "type":"Public Place"
        }
    ],
    "sg:phone":"+1 803 896 8565",
    "sg:postcode":"29210",
    "sg:province":"SC",
    "sg:tags":[
        "govt",
        "state",
        "institution"
    ],
    "wof:name":"Goodman Correctional Inst",
    "wof:placetype":"venue"
},
  "geometry": {"coordinates":[-81.11760099999999,34.067322],"type":"Point"}
}