{
  "type": "Feature",
  "properties": {
    "addr:full":"136 Lisa Dr Lexington SC 29073",
    "addr:housenumber":"136",
    "addr:postcode":"29073",
    "addr:street":"Lisa Dr",
    "iso:country":"US",
    "sg:address":"136 Lisa Dr",
    "sg:city":"Lexington",
    "sg:classifiers":[
        {
            "category":"Building & Trades",
            "subcategory":"Electrical",
            "type":"Services"
        }
    ],
    "sg:phone":"+1 803 356 1209",
    "sg:postcode":"29073",
    "sg:province":"SC",
    "sg:tags":[
        "electrical",
        "contractor"
    ],
    "wof:name":"Zeigler Electric Inc",
    "wof:placetype":"venue"
},
  "geometry": {"coordinates":[-81.156308,33.981658],"type":"Point"}
}