{
  "type": "Feature",
  "properties": {
    "addr:full":"208 W Main St Clinton SC 29325",
    "addr:housenumber":"208",
    "addr:postcode":"29325",
    "addr:street":"W Main St",
    "iso:country":"US",
    "sg:address":"208 W Main St",
    "sg:city":"Clinton",
    "sg:classifiers":[
        {
            "category":"Professional",
            "subcategory":"Business Services",
            "type":"Services"
        }
    ],
    "sg:phone":"+1 864 833 2002",
    "sg:postcode":"29325",
    "sg:province":"SC",
    "sg:tags":[
        "interior",
        "consultant",
        "design",
        "decorator"
    ],
    "wof:name":"Design System Interiors",
    "wof:placetype":"venue"
},
  "geometry": {"coordinates":[-81.881472,34.473469],"type":"Point"}
}