{
  "type": "Feature",
  "properties": {
    "iso:country":"US",
    "sg:address":"1775 N Pike E",
    "sg:city":"Sumter",
    "sg:classifiers":[
        {
            "category":"Freight",
            "type":"Transportation"
        },
        {
            "category":"Building & Trades",
            "subcategory":"Construction",
            "type":"Services"
        }
    ],
    "sg:phone":"+1 803 778 5428",
    "sg:postcode":"29153",
    "sg:province":"SC",
    "sg:tags":[
        "mobile",
        "home",
        "contractor"
    ],
    "wof:name":"Baxley's Best Way Trnsprtn",
    "wof:placetype":"venue"
},
  "geometry": {"coordinates":[-80.289098,33.916342],"type":"Point"}
}