{
  "type": "Feature",
  "properties": {
    "iso:country":"US",
    "sg:address":"725 E Bay St",
    "sg:city":"Charleston",
    "sg:classifiers":[
        {
            "category":"Professional",
            "type":"Services"
        }
    ],
    "sg:phone":"+1 843 577 0108",
    "sg:postcode":"29403",
    "sg:province":"SC",
    "sg:tags":[
        "establishment"
    ],
    "wof:name":"Elpis Josiah Smith Tenant Bldg",
    "wof:placetype":"venue"
},
  "geometry": {"coordinates":[-79.93469,32.799008],"type":"Point"}
}