{
  "type": "Feature",
  "properties": {
    "iso:country":"US",
    "sg:address":"3400 Forest Dr Ste 2048",
    "sg:city":"Columbia",
    "sg:classifiers":[
        {
            "category":"Shopping",
            "subcategory":"Clothing, Apparel, & Fashions",
            "type":"Retail Goods"
        }
    ],
    "sg:phone":"+1 803 787 5399",
    "sg:postcode":"29204",
    "sg:province":"SC",
    "sg:tags":[
        "children's",
        "clothing"
    ],
    "sg:website":"www.gymboree.com",
    "wof:name":"Gymboree Store At Richland Mall",
    "wof:placetype":"venue"
},
  "geometry": {"coordinates":[-81.000198,34.025501],"type":"Point"}
}