{
  "type": "Feature",
  "properties": {
    "addr:full":"1309 Secessionville Rd Charleston SC 29412",
    "addr:housenumber":"1309",
    "addr:postcode":"29412",
    "addr:street":"Secessionville Rd",
    "iso:country":"US",
    "sg:address":"1309 Secessionville Rd",
    "sg:city":"Charleston",
    "sg:classifiers":[
        {
            "category":"Organizations",
            "subcategory":"Religious Organization",
            "type":"Services"
        }
    ],
    "sg:phone":"+1 843 795 7444",
    "sg:postcode":"29412",
    "sg:province":"SC",
    "sg:tags":[
        "church"
    ],
    "sg:website":"www.watchtower.org",
    "wof:name":"Kingdom Hall-Jehovah's Witness",
    "wof:placetype":"venue"
},
  "geometry": {"coordinates":[-79.956851,32.720268],"type":"Point"}
}