{
  "type": "Feature",
  "properties": {
    "iso:country":"US",
    "sg:address":"303 Main St",
    "sg:city":"Conway",
    "sg:classifiers":[
        {
            "category":"Museum",
            "type":"Entertainment"
        }
    ],
    "sg:phone":"+1 843 248 7200",
    "sg:postcode":"29526",
    "sg:province":"SC",
    "sg:tags":[
        "organization",
        "arts",
        "information"
    ],
    "wof:name":"Horry Cultural Arts Council",
    "wof:placetype":"venue"
},
  "geometry": {"coordinates":[-79.046369,33.835622],"type":"Point"}
}