{
  "type": "Feature",
  "properties": {
    "iso:country":"US",
    "sg:address":"6626 US Hwy 76",
    "sg:city":"Pendleton",
    "sg:classifiers":[
        {
            "category":"Retail",
            "subcategory":"Auto Rental",
            "type":"Services"
        }
    ],
    "sg:phone":"+1 864 646 6251",
    "sg:postcode":"29670",
    "sg:province":"SC",
    "sg:tags":[
        "renting",
        "truck",
        "leasing"
    ],
    "wof:name":"U-Haul Co",
    "wof:placetype":"venue"
},
  "geometry": {"coordinates":[-82.765794,34.606834],"type":"Point"}
}