{
  "type": "Feature",
  "properties": {
    "addr:full":"1329 Dizzy Gillespie Dr Cheraw SC 29520",
    "addr:housenumber":"1329",
    "addr:postcode":"29520",
    "addr:street":"Dizzy Gillespie Dr",
    "iso:country":"US",
    "sg:address":"1329 Dizzy Gillespie Dr",
    "sg:city":"Cheraw",
    "sg:classifiers":[
        {
            "category":"Social Services",
            "type":"Services"
        }
    ],
    "sg:phone":"+1 843 537 9999",
    "sg:postcode":"29520",
    "sg:province":"SC",
    "sg:tags":[
        "organization",
        "welfare"
    ],
    "wof:name":"Boys & Girls Club-Pee Dee Area",
    "wof:placetype":"venue"
},
  "geometry": {"coordinates":[-79.90515499999999,34.680057],"type":"Point"}
}