{
  "type": "Feature",
  "properties": {
    "iso:country":"US",
    "sg:address":"5822 Robinson St",
    "sg:city":"Hanahan",
    "sg:classifiers":[
        {
            "category":"Building & Trades",
            "subcategory":"Electrical",
            "type":"Services"
        }
    ],
    "sg:phone":"+1 843 554 6048",
    "sg:postcode":"29410",
    "sg:province":"SC",
    "sg:tags":[
        "electric",
        "contractor"
    ],
    "wof:name":"RLT Electricl Contractors",
    "wof:placetype":"venue"
},
  "geometry": {"coordinates":[-80.007443,32.904066],"type":"Point"}
}