{
  "type": "Feature",
  "properties": {
    "iso:country":"US",
    "sg:address":"134 W Columbia Ave",
    "sg:city":"Batesburg",
    "sg:classifiers":[
        {
            "category":"Shopping",
            "subcategory":"Pharmacy",
            "type":"Retail Goods"
        }
    ],
    "sg:phone":"+1 803 781 1085",
    "sg:postcode":"29006",
    "sg:province":"SC",
    "wof:name":"Apothecare Pharmacy",
    "wof:placetype":"venue"
},
  "geometry": {"coordinates":[-81.53251299999999,33.909528],"type":"Point"}
}