{
  "type": "Feature",
  "properties": {
    "addr:full":"317 N Hwy 52 Moncks Corner SC 29461",
    "addr:housenumber":"317",
    "addr:postcode":"29461",
    "addr:street":"N Hwy 52",
    "iso:country":"US",
    "sg:address":"317 N Hwy 52",
    "sg:city":"Moncks Corner",
    "sg:classifiers":[
        {
            "category":"Banks & Credit Unions",
            "subcategory":"Bank",
            "type":"Services"
        }
    ],
    "sg:phone":"+1 843 761 8024",
    "sg:postcode":"29461",
    "sg:province":"SC",
    "sg:website":"www.scbandt.com",
    "wof:name":"South Carolina Bank & Trust",
    "wof:placetype":"venue"
},
  "geometry": {"coordinates":[-79.99146,33.199711],"type":"Point"}
}