{
  "type": "Feature",
  "properties": {
    "iso:country":"US",
    "sg:address":"104 Duck Pond Rd",
    "sg:city":"Columbia",
    "sg:classifiers":[
        {
            "category":"Banks & Credit Unions",
            "subcategory":"Bank",
            "type":"Services"
        }
    ],
    "sg:phone":"+1 803 736 3557",
    "sg:postcode":"29223",
    "sg:province":"SC",
    "sg:tags":[
        "short",
        "institution",
        "business"
    ],
    "wof:name":"GE",
    "wof:placetype":"venue"
},
  "geometry": {"coordinates":[-80.878068,34.098772],"type":"Point"}
}