{
  "type": "Feature",
  "properties": {
    "iso:country":"US",
    "sg:address":"2330 Calks Ferry Rd",
    "sg:city":"Lexington",
    "sg:classifiers":[
        {
            "category":"Building & Trades",
            "subcategory":"Construction",
            "type":"Services"
        }
    ],
    "sg:phone":"+1 803 894 3209",
    "sg:postcode":"29073",
    "sg:province":"SC",
    "sg:tags":[
        "house"
    ],
    "wof:name":"Simons Construction LLC",
    "wof:placetype":"venue"
},
  "geometry": {"coordinates":[-81.31653,33.864523],"type":"Point"}
}