{
  "type": "Feature",
  "properties": {
    "iso:country":"US",
    "sg:address":"108 Causeway Dr",
    "sg:city":"Bowman",
    "sg:classifiers":[
        {
            "category":"Health Services",
            "subcategory":"Doctor",
            "type":"Services"
        }
    ],
    "sg:phone":"+1 803 829 2566",
    "sg:postcode":"29018",
    "sg:province":"SC",
    "sg:tags":[
        "dentist"
    ],
    "wof:name":"S Theodore Mc Gill DDS",
    "wof:placetype":"venue"
},
  "geometry": {"coordinates":[-80.691489,33.355926],"type":"Point"}
}