{
  "type": "Feature",
  "properties": {
    "iso:country":"US",
    "sg:address":"160 Assembly St",
    "sg:city":"Columbia",
    "sg:classifiers":[
        {
            "category":"Restaurant",
            "type":"Food & Drink"
        }
    ],
    "sg:menulink":"http://www.allmenus.com/sc/columbia/129201-subway/menu/",
    "sg:phone":"+1 803 254 2958",
    "sg:postcode":"29201",
    "sg:province":"SC",
    "sg:tags":[
        "american",
        "sandwich"
    ],
    "wof:name":"Subway",
    "wof:placetype":"venue"
},
  "geometry": {"coordinates":[-81.028565,33.986937],"type":"Point"}
}