{
  "type": "Feature",
  "properties": {
    "addr:full":"501 Donaldson Rd Greenville SC 29605",
    "addr:housenumber":"501",
    "addr:postcode":"29605",
    "addr:street":"Donaldson Rd",
    "iso:country":"US",
    "sg:address":"501 Donaldson Rd",
    "sg:city":"Greenville",
    "sg:classifiers":[
        {
            "category":"Retail",
            "subcategory":"Auto Rental",
            "type":"Services"
        }
    ],
    "sg:phone":"+1 864 299 0684",
    "sg:postcode":"29605",
    "sg:province":"SC",
    "sg:tags":[
        "renting",
        "truck",
        "leasing"
    ],
    "wof:name":"U-Haul Co",
    "wof:placetype":"venue"
},
  "geometry": {"coordinates":[-82.38458300000001,34.763416],"type":"Point"}
}