{
  "type": "Feature",
  "properties": {
    "addr:full":"810 Travelers Blvd Summerville SC 29485",
    "addr:housenumber":"810",
    "addr:postcode":"29485",
    "addr:street":"Travelers Blvd",
    "iso:country":"US",
    "sg:address":"810 Travelers Blvd",
    "sg:city":"Summerville",
    "sg:classifiers":[
        {
            "category":"Manufacturing",
            "subcategory":"Printing",
            "type":"Manufacturing & Wholesale Goods"
        }
    ],
    "sg:phone":"+1 843 875 5115",
    "sg:postcode":"29485",
    "sg:province":"SC",
    "sg:tags":[
        "publisher"
    ],
    "sg:website":"www.poolmag.com",
    "wof:name":"Pool & Billiard Magazine",
    "wof:placetype":"venue"
},
  "geometry": {"coordinates":[-80.16757200000001,32.95592],"type":"Point"}
}