{
  "type": "Feature",
  "properties": {
    "iso:country":"US",
    "sg:address":"400 Main St",
    "sg:city":"North Myrtle Bch",
    "sg:classifiers":[
        {
            "category":"Shopping",
            "subcategory":"Used Merchandise",
            "type":"Retail Goods"
        }
    ],
    "sg:phone":"+1 843 280 3387",
    "sg:postcode":"29582",
    "sg:province":"SC",
    "sg:tags":[
        "second",
        "store",
        "hand"
    ],
    "wof:name":"Salvation Army",
    "wof:placetype":"venue"
},
  "geometry": {"coordinates":[-78.67461,33.823049],"type":"Point"}
}