{
  "type": "Feature",
  "properties": {
    "iso:country":"US",
    "sg:address":"2200 N Main St",
    "sg:city":"Anderson",
    "sg:classifiers":[
        {
            "category":"Health Services",
            "subcategory":"Podiatrist",
            "type":"Services"
        }
    ],
    "sg:phone":"+1 864 225 8131",
    "sg:postcode":"29621",
    "sg:province":"SC",
    "wof:name":"Anderson Podiatry Assoc",
    "wof:placetype":"venue"
},
  "geometry": {"coordinates":[-82.65837999999999,34.525856],"type":"Point"}
}