{
  "type": "Feature",
  "properties": {
    "iso:country":"US",
    "sg:address":"206 Saddlebred Dr",
    "sg:city":"Greenville",
    "sg:classifiers":[
        {
            "category":"Real Estate",
            "subcategory":"Real Estate Agent",
            "type":"Services"
        }
    ],
    "sg:phone":"+1 864 243 9998",
    "sg:postcode":"29669",
    "sg:province":"SC",
    "wof:name":"Saddlehorn",
    "wof:placetype":"venue"
},
  "geometry": {"coordinates":[-82.357397,34.659801],"type":"Point"}
}