{
  "type": "Feature",
  "properties": {
    "addr:full":"1001 County Home Rd Anderson SC 29625",
    "addr:housenumber":"1001",
    "addr:postcode":"29625",
    "addr:street":"County Home Rd",
    "iso:country":"US",
    "sg:address":"1001 County Home Rd",
    "sg:city":"Anderson",
    "sg:classifiers":[
        {
            "category":"Government",
            "subcategory":"Office",
            "type":"Public Place"
        }
    ],
    "sg:phone":"+1 864 226 0882",
    "sg:postcode":"29625",
    "sg:province":"SC",
    "sg:tags":[
        "federal",
        "security"
    ],
    "wof:name":"US Defense Investigation Svc",
    "wof:placetype":"venue"
},
  "geometry": {"coordinates":[-82.68249,34.534275],"type":"Point"}
}