{
  "type": "Feature",
  "properties": {
    "iso:country":"US",
    "sg:address":"588 Fairview Church Rd",
    "sg:city":"Fountain Inn",
    "sg:classifiers":[
        {
            "category":"Building & Trades",
            "subcategory":"Construction",
            "type":"Services"
        }
    ],
    "sg:phone":"+1 864 862 1046",
    "sg:postcode":"29644",
    "sg:province":"SC",
    "sg:tags":[
        "steel",
        "erection",
        "structural"
    ],
    "wof:name":"Walden Erectors Partnership",
    "wof:placetype":"venue"
},
  "geometry": {"coordinates":[-82.229108,34.63879],"type":"Point"}
}