{
  "type": "Feature",
  "properties": {
    "iso:country":"US",
    "sg:address":"110 Wilkinsville Hwy",
    "sg:city":"Gaffney",
    "sg:classifiers":[
        {
            "category":"Food & Beverages",
            "subcategory":"Groceries & Convenience Stores",
            "type":"Retail Goods"
        }
    ],
    "sg:phone":"+1 864 487 7714",
    "sg:postcode":"29340",
    "sg:province":"SC",
    "wof:name":"Winn-Dixie",
    "wof:placetype":"venue"
},
  "geometry": {"coordinates":[-81.640119,35.057038],"type":"Point"}
}