{
  "type": "Feature",
  "properties": {
    "addr:full":"850 US Hwy 1 Lugoff SC 29078",
    "addr:housenumber":"850",
    "addr:postcode":"29078",
    "addr:street":"Us Hwy 1",
    "iso:country":"US",
    "sg:address":"850 US Hwy 1",
    "sg:city":"Lugoff",
    "sg:classifiers":[
        {
            "category":"Restaurant",
            "type":"Food & Drink"
        }
    ],
    "sg:phone":"+1 803 438 9441",
    "sg:postcode":"29078",
    "sg:province":"SC",
    "sg:tags":[
        "eating"
    ],
    "wof:name":"Plum's Restaurant & Lounge",
    "wof:placetype":"venue"
},
  "geometry": {"coordinates":[-80.674603,34.228437],"type":"Point"}
}