{
  "type": "Feature",
  "properties": {
    "addr:full":"701 Brockman Rd Greer SC 29651",
    "addr:housenumber":"701",
    "addr:postcode":"29651",
    "addr:street":"Brockman Rd",
    "iso:country":"US",
    "sg:address":"701 Brockman Rd",
    "sg:city":"Greer",
    "sg:phone":"+1 864 877 6932",
    "sg:postcode":"29651",
    "sg:province":"SC",
    "sg:tags":[
        "farm",
        "soybean"
    ],
    "wof:name":"Darwin Deyoung",
    "wof:placetype":"venue"
},
  "geometry": {"coordinates":[-82.154205,34.828384],"type":"Point"}
}