{
  "type": "Feature",
  "properties": {
    "addr:full":"1359 21st Ave N Myrtle Beach SC 29577",
    "addr:housenumber":"1359",
    "addr:postcode":"29577",
    "addr:street":"21St Ave N",
    "iso:country":"US",
    "sg:address":"1359 21st Ave N",
    "sg:city":"Myrtle Beach",
    "sg:classifiers":[
        {
            "category":"Professional",
            "subcategory":"Art Services",
            "type":"Services"
        }
    ],
    "sg:phone":"+1 843 946 9020",
    "sg:postcode":"29577",
    "sg:province":"SC",
    "sg:tags":[
        "photographer"
    ],
    "wof:name":"Forensic Record Inc",
    "wof:placetype":"venue"
},
  "geometry": {"coordinates":[-78.884677,33.712691],"type":"Point"}
}