{
  "type": "Feature",
  "properties": {
    "iso:country":"US",
    "sg:address":"998 Russell St",
    "sg:city":"Orangeburg",
    "sg:classifiers":[
        {
            "category":"Food & Beverages",
            "subcategory":"Specialty",
            "type":"Retail Goods"
        }
    ],
    "sg:phone":"+1 803 516 9076",
    "sg:postcode":"29115",
    "sg:province":"SC",
    "sg:tags":[
        "health",
        "diet"
    ],
    "wof:name":"Mr G's Health & Variety Store",
    "wof:placetype":"venue"
},
  "geometry": {"coordinates":[-80.868211,33.486589],"type":"Point"}
}