{
  "type": "Feature",
  "properties": {
    "iso:country":"US",
    "sg:address":"951 S Pine St",
    "sg:city":"Spartanburg",
    "sg:classifiers":[
        {
            "category":"Wholesale",
            "subcategory":"Drugs",
            "type":"Manufacturing & Wholesale Goods"
        }
    ],
    "sg:phone":"+1 864 583 8058",
    "sg:postcode":"29302",
    "sg:province":"SC",
    "sg:tags":[
        "home",
        "fragrance"
    ],
    "wof:name":"Willowbrook Company LLC",
    "wof:placetype":"venue"
},
  "geometry": {"coordinates":[-81.89555,34.934647],"type":"Point"}
}