{
  "type": "Feature",
  "properties": {
    "addr:full":"1208 Windmill Rd Leesville SC 29070",
    "addr:housenumber":"1208",
    "addr:postcode":"29070",
    "addr:street":"Windmill Rd",
    "iso:country":"US",
    "sg:address":"1208 Windmill Rd",
    "sg:city":"Leesville",
    "sg:classifiers":[
        {
            "category":"Insurance",
            "subcategory":"Life Insurance",
            "type":"Services"
        }
    ],
    "sg:phone":"+1 803 532 9676",
    "sg:postcode":"29070",
    "sg:province":"SC",
    "sg:tags":[
        "carrier"
    ],
    "wof:name":"Aid Assoc For Lutherans",
    "wof:placetype":"venue"
},
  "geometry": {"coordinates":[-81.44850599999999,33.98583],"type":"Point"}
}