{
  "type": "Feature",
  "properties": {
    "iso:country":"US",
    "sg:address":"3900 Clemson Blvd",
    "sg:city":"Anderson",
    "sg:classifiers":[
        {
            "category":"Retail",
            "subcategory":"Auto Rental",
            "type":"Services"
        }
    ],
    "sg:phone":"+1 864 231 6226",
    "sg:postcode":"29621",
    "sg:province":"SC",
    "sg:tags":[
        "renting",
        "automobile"
    ],
    "wof:name":"Budget Rent A Car",
    "wof:placetype":"venue"
},
  "geometry": {"coordinates":[-82.686842,34.557221],"type":"Point"}
}