{
  "type": "Feature",
  "properties": {
    "iso:country":"US",
    "sg:address":"220 Stoneridge Dr",
    "sg:city":"Columbia",
    "sg:classifiers":[
        {
            "category":"Professional",
            "type":"Services"
        }
    ],
    "sg:phone":"+1 803 771 9698",
    "sg:postcode":"29210",
    "sg:province":"SC",
    "sg:tags":[
        "establishment"
    ],
    "sg:website":"www.scrha.org",
    "wof:name":"S C State Office Of Rural Hlth",
    "wof:placetype":"venue"
},
  "geometry": {"coordinates":[-81.077852,34.015397],"type":"Point"}
}