{
  "type": "Feature",
  "properties": {
    "iso:country":"US",
    "sg:address":"603 Broad St",
    "sg:city":"Bennettsville",
    "sg:classifiers":[
        {
            "category":"Banks & Credit Unions",
            "subcategory":"Bank",
            "type":"Services"
        }
    ],
    "sg:phone":"+1 843 454 0205",
    "sg:postcode":"29512",
    "sg:province":"SC",
    "sg:tags":[
        "financing"
    ],
    "wof:name":"Loan City",
    "wof:placetype":"venue"
},
  "geometry": {"coordinates":[-79.67967899999999,34.608765],"type":"Point"}
}