{
  "type": "Feature",
  "properties": {
    "iso:country":"US",
    "sg:address":"1200 Pocalla Rd",
    "sg:city":"Sumter",
    "sg:classifiers":[
        {
            "category":"Shopping",
            "subcategory":"Department Store",
            "type":"Retail Goods"
        }
    ],
    "sg:phone":"+1 803 934 8351",
    "sg:postcode":"29150",
    "sg:province":"SC",
    "sg:tags":[
        "shop"
    ],
    "wof:name":"Family Dollar Store",
    "wof:placetype":"venue"
},
  "geometry": {"coordinates":[-80.34718100000001,33.886143],"type":"Point"}
}