{
  "type": "Feature",
  "properties": {
    "iso:country":"US",
    "sg:address":"101 New St",
    "sg:city":"Spartanburg",
    "sg:classifiers":[
        {
            "category":"Freight",
            "type":"Transportation"
        }
    ],
    "sg:phone":"+1 864 574 8522",
    "sg:postcode":"29303",
    "sg:province":"SC",
    "sg:tags":[
        "warehouse",
        "merchandise"
    ],
    "wof:name":"Southeast Transportation",
    "wof:placetype":"venue"
},
  "geometry": {"coordinates":[-81.955915,34.962838],"type":"Point"}
}