{
  "type": "Feature",
  "properties": {
    "iso:country":"US",
    "sg:address":"2300 Airport Blvd",
    "sg:city":"West Columbia",
    "sg:classifiers":[
        {
            "category":"Food & Beverages",
            "subcategory":"Groceries & Convenience Stores",
            "type":"Retail Goods"
        }
    ],
    "sg:phone":"+1 803 794 6383",
    "sg:postcode":"29170",
    "sg:province":"SC",
    "wof:name":"Kwik Mart",
    "wof:placetype":"venue"
},
  "geometry": {"coordinates":[-81.099752,33.950043],"type":"Point"}
}