{
  "type": "Feature",
  "properties": {
    "iso:country":"US",
    "sg:address":"3690 Bohicket Rd",
    "sg:city":"Johns Island",
    "sg:classifiers":[
        {
            "category":"Real Estate",
            "subcategory":"Architect",
            "type":"Services"
        }
    ],
    "sg:phone":"+1 843 768 1333",
    "sg:postcode":"29455",
    "sg:province":"SC",
    "sg:website":"www.campbell-schneider.com",
    "wof:name":"Campbell Schneider & Assoc",
    "wof:placetype":"venue"
},
  "geometry": {"coordinates":[-80.136454,32.648039],"type":"Point"}
}