{
  "type": "Feature",
  "properties": {
    "iso:country":"US",
    "sg:address":"1625 Hiers Corner Rd",
    "sg:city":"Walterboro",
    "sg:classifiers":[
        {
            "category":"Personal",
            "subcategory":"Beauty Salon",
            "type":"Services"
        }
    ],
    "sg:phone":"+1 843 538 7895",
    "sg:postcode":"29488",
    "sg:province":"SC",
    "wof:name":"Cutting Edge",
    "wof:placetype":"venue"
},
  "geometry": {"coordinates":[-80.692348,32.909513],"type":"Point"}
}