{
  "type": "Feature",
  "properties": {
    "iso:country":"US",
    "sg:address":"1033 Howle St",
    "sg:city":"Hartsville",
    "sg:classifiers":[
        {
            "category":"Manufacturing",
            "subcategory":"Tools & Machinery",
            "type":"Manufacturing & Wholesale Goods"
        }
    ],
    "sg:phone":"+1 843 339 9464",
    "sg:postcode":"29550",
    "sg:province":"SC",
    "sg:tags":[
        "machine",
        "shop"
    ],
    "wof:name":"P D Machine & Tool",
    "wof:placetype":"venue"
},
  "geometry": {"coordinates":[-80.080654,34.391996],"type":"Point"}
}