{
  "type": "Feature",
  "properties": {
    "iso:country":"US",
    "sg:address":"43 S Burty Rd",
    "sg:city":"Piedmont",
    "sg:classifiers":[
        {
            "category":"Building & Trades",
            "subcategory":"Construction",
            "type":"Services"
        }
    ],
    "sg:phone":"+1 864 299 0398",
    "sg:postcode":"29673",
    "sg:province":"SC",
    "sg:tags":[
        "siding",
        "contractor"
    ],
    "wof:name":"B & C Siding Co",
    "wof:placetype":"venue"
},
  "geometry": {"coordinates":[-82.420668,34.785439],"type":"Point"}
}