{
  "type": "Feature",
  "properties": {
    "iso:country":"US",
    "sg:address":"359 Barr Rd",
    "sg:city":"Lexington",
    "sg:classifiers":[
        {
            "category":"Wholesale",
            "subcategory":"Seafood",
            "type":"Manufacturing & Wholesale Goods"
        }
    ],
    "sg:phone":"+1 803 359 4700",
    "sg:postcode":"29072",
    "sg:province":"SC",
    "wof:name":"Salty Mikes Seafood Sales LLC",
    "wof:placetype":"venue"
},
  "geometry": {"coordinates":[-81.261365,33.97055],"type":"Point"}
}