{
  "type": "Feature",
  "properties": {
    "iso:country":"US",
    "sg:address":"4976 Seewee Rd",
    "sg:city":"Awendaw",
    "sg:classifiers":[
        {
            "category":"Wholesale",
            "subcategory":"Hardware",
            "type":"Manufacturing & Wholesale Goods"
        }
    ],
    "sg:phone":"+1 843 928 3624",
    "sg:postcode":"29429",
    "sg:province":"SC",
    "wof:name":"RB Enterprises",
    "wof:placetype":"venue"
},
  "geometry": {"coordinates":[-79.70669700000001,32.925424],"type":"Point"}
}