{
  "type": "Feature",
  "properties": {
    "iso:country":"US",
    "sg:address":"773 N Jefferies Blvd",
    "sg:city":"Walterboro",
    "sg:classifiers":[
        {
            "category":"Home & Garden",
            "subcategory":"Furniture",
            "type":"Retail Goods"
        }
    ],
    "sg:phone":"+1 843 549 6161",
    "sg:postcode":"29488",
    "sg:province":"SC",
    "wof:name":"Lowcountry Furniture Barn",
    "wof:placetype":"venue"
},
  "geometry": {"coordinates":[-80.668065,32.911099],"type":"Point"}
}