{
  "type": "Feature",
  "properties": {
    "addr:full":"301 S Ron McNair Blvd Lake City SC 29560",
    "addr:housenumber":"301",
    "addr:postcode":"29560",
    "addr:street":"S Ron Mcnair Blvd",
    "iso:country":"US",
    "sg:address":"301 S Ron McNair Blvd",
    "sg:city":"Lake City",
    "sg:classifiers":[
        {
            "category":"Food & Beverages",
            "subcategory":"Groceries & Convenience Stores",
            "type":"Retail Goods"
        }
    ],
    "sg:phone":"+1 843 394 8331",
    "sg:postcode":"29560",
    "sg:province":"SC",
    "sg:tags":[
        "grocer"
    ],
    "wof:name":"Jim's IGA Food Store",
    "wof:placetype":"venue"
},
  "geometry": {"coordinates":[-79.76236900000001,33.866688],"type":"Point"}
}