{
  "type": "Feature",
  "properties": {
    "addr:full":"1077 King St Charleston SC 29403",
    "addr:housenumber":"1077",
    "addr:postcode":"29403",
    "addr:street":"King St",
    "iso:country":"US",
    "sg:address":"1077 King St",
    "sg:city":"Charleston",
    "sg:classifiers":[
        {
            "category":"Social Services",
            "subcategory":"Job Training",
            "type":"Services"
        }
    ],
    "sg:phone":"+1 843 727 2024",
    "sg:postcode":"29403",
    "sg:province":"SC",
    "sg:tags":[
        "rehab",
        "government"
    ],
    "wof:name":"Employment Security Commission",
    "wof:placetype":"venue"
},
  "geometry": {"coordinates":[-79.95087599999999,32.8056],"type":"Point"}
}