{
  "type": "Feature",
  "properties": {
    "iso:country":"US",
    "sg:address":"100 Pine Ridge Dr",
    "sg:city":"Easley",
    "sg:classifiers":[
        {
            "category":"Recreation",
            "type":"Entertainment"
        }
    ],
    "sg:phone":"+1 864 859 9545",
    "sg:postcode":"29642",
    "sg:province":"SC",
    "sg:tags":[
        "course",
        "golf"
    ],
    "wof:name":"Smithfields Country Club",
    "wof:placetype":"venue"
},
  "geometry": {"coordinates":[-82.55658699999999,34.80524],"type":"Point"}
}