{
  "type": "Feature",
  "properties": {
    "iso:country":"US",
    "sg:address":"30 Orchard Park Dr",
    "sg:city":"Greenville",
    "sg:classifiers":[
        {
            "category":"Professional",
            "subcategory":"Business Services",
            "type":"Services"
        }
    ],
    "sg:phone":"+1 864 675 0046",
    "sg:postcode":"29615",
    "sg:province":"SC",
    "sg:tags":[
        "interior",
        "consultant",
        "design",
        "decorator"
    ],
    "wof:name":"Alden Co",
    "wof:placetype":"venue"
},
  "geometry": {"coordinates":[-82.333597,34.856844],"type":"Point"}
}