{
  "type": "Feature",
  "properties": {
    "iso:country":"US",
    "sg:address":"25 W Washington St",
    "sg:city":"Greenville",
    "sg:classifiers":[
        {
            "category":"Restaurant",
            "type":"Food & Drink"
        }
    ],
    "sg:phone":"+1 864 232 3706",
    "sg:postcode":"29601",
    "sg:province":"SC",
    "sg:tags":[
        "pub"
    ],
    "wof:name":"Barley's Taproom & Pizzeria",
    "wof:placetype":"venue"
},
  "geometry": {"coordinates":[-82.399747,34.850914],"type":"Point"}
}