{
  "type": "Feature",
  "properties": {
    "iso:country":"US",
    "sg:address":"1320 Old Manning Rd",
    "sg:city":"Sumter",
    "sg:classifiers":[
        {
            "category":"Farming",
            "subcategory":"Farm",
            "type":"Manufacturing & Wholesale Goods"
        }
    ],
    "sg:phone":"+1 803 481 2011",
    "sg:postcode":"29150",
    "sg:province":"SC",
    "wof:name":"Black Crest Farms",
    "wof:placetype":"venue"
},
  "geometry": {"coordinates":[-80.33244999999999,33.835713],"type":"Point"}
}