{
  "type": "Feature",
  "properties": {
    "iso:country":"US",
    "sg:address":"12 Combahee Rd",
    "sg:city":"Hilton Head Isle",
    "sg:classifiers":[
        {
            "category":"Real Estate",
            "subcategory":"Real Estate Agent",
            "type":"Services"
        }
    ],
    "sg:phone":"+1 843 686 2316",
    "sg:postcode":"29928",
    "sg:province":"SC",
    "wof:name":"K & A Properties",
    "wof:placetype":"venue"
},
  "geometry": {"coordinates":[-80.74704,32.176943],"type":"Point"}
}