{
  "type": "Feature",
  "properties": {
    "iso:country":"US",
    "sg:address":"112 Kneece Rd",
    "sg:city":"Bradley",
    "sg:classifiers":[
        {
            "category":"Building & Trades",
            "subcategory":"Construction",
            "type":"Services"
        },
        {
            "category":"Building & Trades",
            "subcategory":"Plumbing",
            "type":"Services"
        }
    ],
    "sg:phone":"+1 864 227 6204",
    "sg:postcode":"29819",
    "sg:province":"SC",
    "sg:tags":[
        "contracting",
        "mechanical",
        "piping",
        "contractor"
    ],
    "wof:name":"Pro-Fab Unlimited Inc",
    "wof:placetype":"venue"
},
  "geometry": {"coordinates":[-82.155393,34.029537],"type":"Point"}
}