{
  "type": "Feature",
  "properties": {
    "iso:country":"US",
    "sg:address":"110 E Dekalb St",
    "sg:city":"Camden",
    "sg:classifiers":[
        {
            "category":"Professional",
            "type":"Services"
        }
    ],
    "sg:phone":"+1 803 425 5973",
    "sg:postcode":"29020",
    "sg:province":"SC",
    "wof:name":"Family Service Ctr",
    "wof:placetype":"venue"
},
  "geometry": {"coordinates":[-80.59618399999999,34.247169],"type":"Point"}
}