{
  "type": "Feature",
  "properties": {
    "iso:country":"US",
    "sg:address":"281 Cedarcrest Dr",
    "sg:city":"Lexington",
    "sg:classifiers":[
        {
            "category":"Building & Trades",
            "subcategory":"Construction",
            "type":"Services"
        }
    ],
    "sg:phone":"+1 803 957 3705",
    "sg:postcode":"29072",
    "sg:province":"SC",
    "sg:tags":[
        "waterproofing",
        "contractor"
    ],
    "wof:name":"R W Ford Co",
    "wof:placetype":"venue"
},
  "geometry": {"coordinates":[-81.210072,33.969952],"type":"Point"}
}