{
  "type": "Feature",
  "properties": {
    "iso:country":"US",
    "sg:address":"537 Harden St",
    "sg:city":"Columbia",
    "sg:classifiers":[
        {
            "category":"Professional",
            "subcategory":"Engineering",
            "type":"Services"
        }
    ],
    "sg:phone":"+1 803 799 6914",
    "sg:postcode":"29205",
    "sg:province":"SC",
    "sg:tags":[
        "engineer"
    ],
    "wof:name":"Anderson-Foreman Engineers Inc",
    "wof:placetype":"venue"
},
  "geometry": {"coordinates":[-81.015138,33.997041],"type":"Point"}
}