{
  "type": "Feature",
  "properties": {
    "iso:country":"US",
    "sg:address":"601 Main St Ste B",
    "sg:city":"Columbia",
    "sg:classifiers":[
        {
            "category":"Ice Cream",
            "type":"Food & Drink"
        }
    ],
    "sg:phone":"+1 803 386 9786",
    "sg:postcode":"29201",
    "sg:province":"SC",
    "sg:tags":[
        "frozen",
        "yogurt"
    ],
    "sg:website":"www.yoghut.com",
    "wof:name":"Yoghut",
    "wof:placetype":"venue"
},
  "geometry": {"coordinates":[-81.030567,33.993222],"type":"Point"}
}