{
  "type": "Feature",
  "properties": {
    "addr:full":"2301 Hoffmeyer Rd Florence SC 29501",
    "addr:housenumber":"2301",
    "addr:postcode":"29501",
    "addr:street":"Hoffmeyer Rd",
    "iso:country":"US",
    "sg:address":"2301 Hoffmeyer Rd",
    "sg:city":"Florence",
    "sg:classifiers":[
        {
            "category":"Food & Beverages",
            "subcategory":"Groceries & Convenience Stores",
            "type":"Retail Goods"
        }
    ],
    "sg:phone":"+1 843 665 5639",
    "sg:postcode":"29501",
    "sg:province":"SC",
    "wof:name":"Young's Food Stores",
    "wof:placetype":"venue"
},
  "geometry": {"coordinates":[-79.814013,34.194838],"type":"Point"}
}