{
  "type": "Feature",
  "properties": {
    "iso:country":"US",
    "sg:address":"236 Mountainview Rd",
    "sg:city":"Landrum",
    "sg:classifiers":[
        {
            "category":"Real Estate",
            "subcategory":"Developer",
            "type":"Services"
        }
    ],
    "sg:phone":"+1 864 457 2026",
    "sg:postcode":"29356",
    "sg:province":"SC",
    "wof:name":"Hill Properties",
    "wof:placetype":"venue"
},
  "geometry": {"coordinates":[-82.211935,35.17037],"type":"Point"}
}