{
  "type": "Feature",
  "properties": {
    "iso:country":"US",
    "sg:address":"1720 N Lake Dr",
    "sg:city":"Lexington",
    "sg:classifiers":[
        {
            "category":"Building & Trades",
            "subcategory":"Plumbing",
            "type":"Services"
        }
    ],
    "sg:phone":"+1 803 808 1717",
    "sg:postcode":"29072",
    "sg:province":"SC",
    "sg:tags":[
        "plumbing",
        "contractor"
    ],
    "wof:name":"Brasington Plumbing & Heating",
    "wof:placetype":"venue"
},
  "geometry": {"coordinates":[-81.219649,34.033807],"type":"Point"}
}