{
  "type": "Feature",
  "properties": {
    "addr:full":"1967 Westside St Summerville SC 29483",
    "addr:housenumber":"1967",
    "addr:postcode":"29483",
    "addr:street":"Westside St",
    "iso:country":"US",
    "sg:address":"1967 Westside St",
    "sg:city":"Summerville",
    "sg:classifiers":[
        {
            "category":"Retail",
            "subcategory":"Repair Shop",
            "type":"Services"
        }
    ],
    "sg:phone":"+1 843 875 3661",
    "sg:postcode":"29483",
    "sg:province":"SC",
    "sg:tags":[
        "welding"
    ],
    "wof:name":"M & M Welding Svc Inc",
    "wof:placetype":"venue"
},
  "geometry": {"coordinates":[-80.11798400000001,33.036773],"type":"Point"}
}