{
  "type": "Feature",
  "properties": {
    "iso:country":"US",
    "sg:address":"11033 Anderson Rd",
    "sg:city":"Piedmont",
    "sg:classifiers":[
        {
            "category":"Professional",
            "subcategory":"Lawyer & Legal Services",
            "type":"Services"
        }
    ],
    "sg:phone":"+1 864 220 5500",
    "sg:postcode":"29673",
    "sg:province":"SC",
    "sg:tags":[
        "attorney"
    ],
    "wof:name":"Merck Law Firm",
    "wof:placetype":"venue"
},
  "geometry": {"coordinates":[-82.481561,34.789543],"type":"Point"}
}