{
  "type": "Feature",
  "properties": {
    "iso:country":"US",
    "sg:address":"180 Montgomery Ave",
    "sg:city":"Pacolet",
    "sg:classifiers":[
        {
            "category":"Government",
            "subcategory":"Office",
            "type":"Public Place"
        }
    ],
    "sg:phone":"+1 864 474 9504",
    "sg:postcode":"29372",
    "sg:province":"SC",
    "sg:tags":[
        "city"
    ],
    "wof:name":"Pacolet Town Hall",
    "wof:placetype":"venue"
},
  "geometry": {"coordinates":[-81.741477,34.920471],"type":"Point"}
}