{
  "type": "Feature",
  "properties": {
    "addr:full":"1665 Cygnus Dr Myrtle Beach SC 29575",
    "addr:housenumber":"1665",
    "addr:postcode":"29575",
    "addr:street":"Cygnus Dr",
    "iso:country":"US",
    "sg:address":"1665 Cygnus Dr",
    "sg:city":"Myrtle Beach",
    "sg:classifiers":[
        {
            "category":"Building & Trades",
            "subcategory":"Electrical",
            "type":"Services"
        }
    ],
    "sg:phone":"+1 843 458 0007",
    "sg:postcode":"29575",
    "sg:province":"SC",
    "sg:tags":[
        "electrical",
        "contractor"
    ],
    "wof:name":"Ricks Electric Company Inc",
    "wof:placetype":"venue"
},
  "geometry": {"coordinates":[-78.953459,33.653524],"type":"Point"}
}