{
  "type": "Feature",
  "properties": {
    "iso:country":"US",
    "sg:address":"1818 Augusta Rd",
    "sg:city":"West Columbia",
    "sg:classifiers":[
        {
            "category":"Autos & Motor Vehicles",
            "subcategory":"Automobile Sales",
            "type":"Retail Goods"
        }
    ],
    "sg:phone":"+1 803 600 3740",
    "sg:postcode":"29169",
    "sg:province":"SC",
    "sg:tags":[
        "car",
        "dealer"
    ],
    "wof:name":"Mc Neill Auto Group",
    "wof:placetype":"venue"
},
  "geometry": {"coordinates":[-81.085494,33.985549],"type":"Point"}
}