{
  "type": "Feature",
  "properties": {
    "addr:full":"8590 Pelham Rd Greenville SC 29615",
    "addr:housenumber":"8590",
    "addr:postcode":"29615",
    "addr:street":"Pelham Rd",
    "iso:country":"US",
    "sg:address":"8590 Pelham Rd",
    "sg:city":"Greenville",
    "sg:classifiers":[
        {
            "category":"Professional",
            "subcategory":"Computer Services",
            "type":"Services"
        }
    ],
    "sg:phone":"+1 864 627 1474",
    "sg:postcode":"29615",
    "sg:province":"SC",
    "sg:tags":[
        "repair"
    ],
    "sg:website":"www.computerhandymaninc.com",
    "wof:name":"Computer Handyman",
    "wof:placetype":"venue"
},
  "geometry": {"coordinates":[-82.23342100000001,34.853525],"type":"Point"}
}