{
  "type": "Feature",
  "properties": {
    "iso:country":"US",
    "sg:address":"1716 State Hwy 55 W",
    "sg:city":"Clover",
    "sg:classifiers":[
        {
            "category":"Building & Trades",
            "subcategory":"Construction",
            "type":"Services"
        }
    ],
    "sg:phone":"+1 803 222 6260",
    "sg:postcode":"29710",
    "sg:province":"SC",
    "sg:tags":[
        "contractor"
    ],
    "wof:name":"Casper Tile & Marble Co Inc",
    "wof:placetype":"venue"
},
  "geometry": {"coordinates":[-81.254566,35.133604],"type":"Point"}
}