{
  "type": "Feature",
  "properties": {
    "iso:country":"US",
    "sg:address":"4143 Rivers Ave",
    "sg:city":"Charleston",
    "sg:classifiers":[
        {
            "category":"Retail",
            "subcategory":"Auto Repair",
            "type":"Services"
        }
    ],
    "sg:phone":"+1 843 744 0992",
    "sg:postcode":"29405",
    "sg:province":"SC",
    "sg:tags":[
        "glass",
        "coating",
        "tinting"
    ],
    "wof:name":"Carrigg's",
    "wof:placetype":"venue"
},
  "geometry": {"coordinates":[-79.99222,32.869213],"type":"Point"}
}