{
  "type": "Feature",
  "properties": {
    "iso:country":"US",
    "sg:address":"112 Pamplico Hwy",
    "sg:city":"Florence",
    "sg:classifiers":[
        {
            "category":"Real Estate",
            "subcategory":"Real Estate Services",
            "type":"Services"
        }
    ],
    "sg:phone":"+1 843 669 9941",
    "sg:postcode":"29505",
    "sg:province":"SC",
    "sg:tags":[
        "company",
        "title"
    ],
    "wof:name":"Best Rate Car Title Loans",
    "wof:placetype":"venue"
},
  "geometry": {"coordinates":[-79.763352,34.166157],"type":"Point"}
}