{
  "type": "Feature",
  "properties": {
    "addr:full":"4605 Belton Hwy Anderson SC 29621",
    "addr:housenumber":"4605",
    "addr:postcode":"29621",
    "addr:street":"Belton Hwy",
    "iso:country":"US",
    "sg:address":"4605 Belton Hwy",
    "sg:city":"Anderson",
    "sg:classifiers":[
        {
            "category":"Organizations",
            "subcategory":"Non-profit Organization",
            "type":"Services"
        }
    ],
    "sg:phone":"+1 864 261 6734",
    "sg:postcode":"29621",
    "sg:province":"SC",
    "wof:name":"Richard M Campbell Veterans Hm",
    "wof:placetype":"venue"
},
  "geometry": {"coordinates":[-82.581718,34.476517],"type":"Point"}
}