{
  "type": "Feature",
  "properties": {
    "iso:country":"US",
    "sg:address":"108 Aimwell Rd",
    "sg:city":"Andrews",
    "sg:classifiers":[
        {
            "category":"Restaurant",
            "type":"Food & Drink"
        }
    ],
    "sg:phone":"+1 843 221 4352",
    "sg:postcode":"29510",
    "sg:province":"SC",
    "sg:tags":[
        "eating"
    ],
    "wof:name":"Larry's Restaurant & Bar Inc",
    "wof:placetype":"venue"
},
  "geometry": {"coordinates":[-79.640443,33.462787],"type":"Point"}
}