{
  "type": "Feature",
  "properties": {
    "addr:full":"451 Columbia Ave Lexington SC 29072",
    "addr:housenumber":"451",
    "addr:postcode":"29072",
    "addr:street":"Columbia Ave",
    "iso:country":"US",
    "sg:address":"451 Columbia Ave",
    "sg:city":"Lexington",
    "sg:classifiers":[
        {
            "category":"Shopping",
            "subcategory":"Gifts & Souvenirs",
            "type":"Retail Goods"
        }
    ],
    "sg:phone":"+1 803 359 2843",
    "sg:postcode":"29072",
    "sg:province":"SC",
    "sg:tags":[
        "shop"
    ],
    "wof:name":"Parker's Of Lexington",
    "wof:placetype":"venue"
},
  "geometry": {"coordinates":[-81.239446,33.988461],"type":"Point"}
}