{
  "type": "Feature",
  "properties": {
    "addr:full":"117 Murray Dr Mauldin SC 29662",
    "addr:housenumber":"117",
    "addr:postcode":"29662",
    "addr:street":"Murray Dr",
    "iso:country":"US",
    "sg:address":"117 Murray Dr",
    "sg:city":"Mauldin",
    "sg:classifiers":[
        {
            "category":"Freight",
            "type":"Transportation"
        }
    ],
    "sg:phone":"+1 864 234 7483",
    "sg:postcode":"29662",
    "sg:province":"SC",
    "sg:tags":[
        "commercial",
        "storage"
    ],
    "wof:name":"Pac Rat Self Storage",
    "wof:placetype":"venue"
},
  "geometry": {"coordinates":[-82.31064499999999,34.78591],"type":"Point"}
}