{
  "type": "Feature",
  "properties": {
    "addr:full":"115 Atrium Way Columbia SC 29223",
    "addr:housenumber":"115",
    "addr:postcode":"29223",
    "addr:street":"Atrium Way",
    "iso:country":"US",
    "sg:address":"115 Atrium Way",
    "sg:city":"Columbia",
    "sg:classifiers":[
        {
            "category":"Banks & Credit Unions",
            "subcategory":"Bank",
            "type":"Services"
        }
    ],
    "sg:phone":"+1 803 865 5198",
    "sg:postcode":"29223",
    "sg:province":"SC",
    "sg:tags":[
        "financing"
    ],
    "wof:name":"American General Finance Inc",
    "wof:placetype":"venue"
},
  "geometry": {"coordinates":[-80.936571,34.085707],"type":"Point"}
}