{
  "type": "Feature",
  "properties": {
    "iso:country":"US",
    "sg:address":"402 Hyatt St",
    "sg:city":"Gaffney",
    "sg:classifiers":[
        {
            "category":"Wholesale",
            "subcategory":"Hardware",
            "type":"Manufacturing & Wholesale Goods"
        }
    ],
    "sg:phone":"+1 864 489 5139",
    "sg:postcode":"29341",
    "sg:province":"SC",
    "sg:tags":[
        "plumbing",
        "fixture",
        "supply"
    ],
    "wof:name":"Ferguson Bath & Kitchen Gllry",
    "wof:placetype":"venue"
},
  "geometry": {"coordinates":[-81.679157,35.071181],"type":"Point"}
}