{
  "type": "Feature",
  "properties": {
    "iso:country":"US",
    "sg:address":"720 S Duncan Byp",
    "sg:city":"Union",
    "sg:classifiers":[
        {
            "category":"Health Services",
            "subcategory":"Doctor",
            "type":"Services"
        }
    ],
    "sg:phone":"+1 864 429 3292",
    "sg:postcode":"29379",
    "sg:province":"SC",
    "sg:tags":[
        "physician",
        "surgeon"
    ],
    "wof:name":"Union Obstetrics & Gynecology",
    "wof:placetype":"venue"
},
  "geometry": {"coordinates":[-81.631162,34.703111],"type":"Point"}
}