{
  "type": "Feature",
  "properties": {
    "addr:full":"221 E Floyd Baker Blvd Gaffney SC 29340",
    "addr:housenumber":"221",
    "addr:postcode":"29340",
    "addr:street":"E Floyd Baker Blvd",
    "iso:country":"US",
    "sg:address":"221 E Floyd Baker Blvd",
    "sg:city":"Gaffney",
    "sg:classifiers":[
        {
            "category":"Professional",
            "subcategory":"Lawyer & Legal Services",
            "type":"Services"
        }
    ],
    "sg:phone":"+1 864 489 8128",
    "sg:postcode":"29340",
    "sg:province":"SC",
    "sg:tags":[
        "attorney"
    ],
    "wof:name":"Winter & Rhoden",
    "wof:placetype":"venue"
},
  "geometry": {"coordinates":[-81.647446,35.072366],"type":"Point"}
}