{
  "type": "Feature",
  "properties": {
    "iso:country":"US",
    "sg:address":"115 Longview Dr",
    "sg:city":"Piedmont",
    "sg:classifiers":[
        {
            "category":"Wholesale",
            "subcategory":"Furniture",
            "type":"Manufacturing & Wholesale Goods"
        }
    ],
    "sg:phone":"+1 864 845 6437",
    "sg:postcode":"29673",
    "sg:province":"SC",
    "wof:name":"Shred Away",
    "wof:placetype":"venue"
},
  "geometry": {"coordinates":[-82.51696200000001,34.724572],"type":"Point"}
}