{
  "type": "Feature",
  "properties": {
    "iso:country":"US",
    "sg:address":"2133 Remount Rd",
    "sg:city":"Charleston",
    "sg:classifiers":[
        {
            "category":"Retail",
            "subcategory":"Laundry & Dry Cleaning",
            "type":"Services"
        },
        {
            "category":"Shopping",
            "subcategory":"Clothing, Apparel, & Fashions",
            "type":"Retail Goods"
        }
    ],
    "sg:phone":"+1 843 744 6435",
    "sg:postcode":"29406",
    "sg:province":"SC",
    "sg:tags":[
        "dress",
        "alteration",
        "mfg"
    ],
    "wof:name":"Alterations By Dolores",
    "wof:placetype":"venue"
},
  "geometry": {"coordinates":[-80.01836299999999,32.898174],"type":"Point"}
}