{
  "type": "Feature",
  "properties": {
    "iso:country":"US",
    "sg:address":"1516 Augusta Rd",
    "sg:city":"West Columbia",
    "sg:classifiers":[
        {
            "category":"Shopping",
            "subcategory":"Antiques",
            "type":"Retail Goods"
        }
    ],
    "sg:phone":"+1 803 939 9225",
    "sg:postcode":"29169",
    "sg:province":"SC",
    "wof:name":"Attic Treasuresantiquesandgifts",
    "wof:placetype":"venue"
},
  "geometry": {"coordinates":[-81.07811599999999,33.986428],"type":"Point"}
}