{
  "type": "Feature",
  "properties": {
    "iso:country":"US",
    "sg:address":"7 W Rigby St",
    "sg:city":"Manning",
    "sg:classifiers":[
        {
            "category":"Government",
            "subcategory":"Office",
            "type":"Public Place"
        }
    ],
    "sg:phone":"+1 803 435 2201",
    "sg:postcode":"29102",
    "sg:province":"SC",
    "sg:tags":[
        "federal"
    ],
    "wof:name":"US Consolidated Farm Svc Agcy",
    "wof:placetype":"venue"
},
  "geometry": {"coordinates":[-80.211623,33.696677],"type":"Point"}
}