{
  "type": "Feature",
  "properties": {
    "addr:full":"635 Augusta St Greenville SC 29605",
    "addr:housenumber":"635",
    "addr:postcode":"29605",
    "addr:street":"Augusta St",
    "iso:country":"US",
    "sg:address":"635 Augusta St",
    "sg:city":"Greenville",
    "sg:classifiers":[
        {
            "category":"Wholesale",
            "subcategory":"Computers",
            "type":"Manufacturing & Wholesale Goods"
        }
    ],
    "sg:phone":"+1 864 467 0003",
    "sg:postcode":"29605",
    "sg:province":"SC",
    "sg:tags":[
        "software"
    ],
    "wof:name":"Omnivore Inc",
    "wof:placetype":"venue"
},
  "geometry": {"coordinates":[-82.40591499999999,34.836975],"type":"Point"}
}