{
  "type": "Feature",
  "properties": {
    "addr:full":"73 Chestnut St Cheraw SC 29520",
    "addr:housenumber":"73",
    "addr:postcode":"29520",
    "addr:street":"Chestnut St",
    "iso:country":"US",
    "sg:address":"73 Chestnut St",
    "sg:city":"Cheraw",
    "sg:classifiers":[
        {
            "category":"Manufacturing",
            "subcategory":"Wood Products",
            "type":"Manufacturing & Wholesale Goods"
        }
    ],
    "sg:phone":"+1 843 537 2426",
    "sg:postcode":"29520",
    "sg:province":"SC",
    "sg:tags":[
        "pallet",
        "skid"
    ],
    "wof:name":"Pee Dee Pallet",
    "wof:placetype":"venue"
},
  "geometry": {"coordinates":[-79.878159,34.696521],"type":"Point"}
}