{
  "type": "Feature",
  "properties": {
    "iso:country":"US",
    "sg:address":"1902 Ebenezer Rd",
    "sg:city":"Rock Hill",
    "sg:classifiers":[
        {
            "category":"Health Services",
            "subcategory":"Health Practitioner",
            "type":"Services"
        }
    ],
    "sg:phone":"+1 803 324 5191",
    "sg:postcode":"29732",
    "sg:province":"SC",
    "sg:tags":[
        "psychologist"
    ],
    "wof:name":"Psychological Associates",
    "wof:placetype":"venue"
},
  "geometry": {"coordinates":[-81.051322,34.964555],"type":"Point"}
}