{
  "type": "Feature",
  "properties": {
    "addr:full":"2708 Shop Rd Columbia SC 29201",
    "addr:housenumber":"2708",
    "addr:postcode":"29201",
    "addr:street":"Shop Rd",
    "iso:country":"US",
    "sg:address":"2708 Shop Rd",
    "sg:city":"Columbia",
    "sg:classifiers":[
        {
            "category":"Freight",
            "type":"Transportation"
        }
    ],
    "sg:phone":"+1 803 776 7171",
    "sg:postcode":"29201",
    "sg:province":"SC",
    "sg:tags":[
        "commercial",
        "storage"
    ],
    "wof:name":"Cardinal North American",
    "wof:placetype":"venue"
},
  "geometry": {"coordinates":[-80.961249,33.944061],"type":"Point"}
}