{
  "type": "Feature",
  "properties": {
    "addr:full":"330 Robert Smalls Pkwy Beaufort SC 29906",
    "addr:housenumber":"330",
    "addr:postcode":"29906",
    "addr:street":"Robert Smalls Pkwy",
    "iso:country":"US",
    "sg:address":"330 Robert Smalls Pkwy",
    "sg:city":"Beaufort",
    "sg:classifiers":[
        {
            "category":"Restaurant",
            "type":"Food & Drink"
        }
    ],
    "sg:menulink":"http://www.allmenus.com/sc/beaufort-port-royal/84257-papa-johns-pizza/menu/",
    "sg:phone":"+1 843 524 3400",
    "sg:postcode":"29906",
    "sg:province":"SC",
    "sg:tags":[
        "american",
        "pizza"
    ],
    "wof:name":"Papa John's Pizza",
    "wof:placetype":"venue"
},
  "geometry": {"coordinates":[-80.73560500000001,32.422253],"type":"Point"}
}