{
  "type": "Feature",
  "properties": {
    "iso:country":"US",
    "sg:address":"525 Galway Ln",
    "sg:city":"Columbia",
    "sg:classifiers":[
        {
            "category":"Education",
            "subcategory":"School",
            "type":"Public Place"
        }
    ],
    "sg:phone":"+1 803 783 5549",
    "sg:postcode":"29209",
    "sg:province":"SC",
    "sg:website":"www.richlandone.org",
    "wof:name":"Meadowfield Elementary School",
    "wof:placetype":"venue"
},
  "geometry": {"coordinates":[-80.961702,33.969605],"type":"Point"}
}