{
  "type": "Feature",
  "properties": {
    "addr:full":"845 William Hilton Pkwy Hilton Head Isle SC 29928",
    "addr:housenumber":"845",
    "addr:postcode":"29928",
    "addr:street":"William Hilton Pkwy",
    "iso:country":"US",
    "sg:address":"845 William Hilton Pkwy",
    "sg:city":"Hilton Head Isle",
    "sg:classifiers":[
        {
            "category":"Health Services",
            "subcategory":"Doctor",
            "type":"Services"
        }
    ],
    "sg:phone":"+1 843 785 7515",
    "sg:postcode":"29928",
    "sg:province":"SC",
    "sg:tags":[
        "physician",
        "surgeon"
    ],
    "wof:name":"Parkway Medical Ctr",
    "wof:placetype":"venue"
},
  "geometry": {"coordinates":[-80.73312199999999,32.173619],"type":"Point"}
}