{
  "type": "Feature",
  "properties": {
    "iso:country":"US",
    "sg:address":"2245 Hayne St",
    "sg:city":"Spartanburg",
    "sg:classifiers":[
        {
            "category":"Restaurant",
            "type":"Food & Drink"
        }
    ],
    "sg:phone":"+1 864 576 6005",
    "sg:postcode":"29301",
    "sg:province":"SC",
    "sg:tags":[
        "eating"
    ],
    "wof:name":"Reds Grille",
    "wof:placetype":"venue"
},
  "geometry": {"coordinates":[-82.003949,34.956267],"type":"Point"}
}