{
  "type": "Feature",
  "properties": {
    "iso:country":"US",
    "sg:address":"3525 Air Commerce Dr",
    "sg:city":"West Columbia",
    "sg:classifiers":[
        {
            "category":"Professional",
            "subcategory":"Lawyer & Legal Services",
            "type":"Services"
        }
    ],
    "sg:phone":"+1 800 463 3339",
    "sg:postcode":"29170",
    "sg:province":"SC",
    "sg:tags":[
        "notary"
    ],
    "sg:website":"www.kinkos.com",
    "wof:name":"Fedex Express Airport Facility",
    "wof:placetype":"venue"
},
  "geometry": {"coordinates":[-81.133788,33.949363],"type":"Point"}
}