{
  "type": "Feature",
  "properties": {
    "addr:full":"3516 Earle E Morris Jr Hwy Greenville SC 29611",
    "addr:housenumber":"3516",
    "addr:postcode":"29611",
    "addr:street":"Earle E;Jr Hwy",
    "iso:country":"US",
    "sg:address":"3516 Earle E Morris Jr Hwy",
    "sg:city":"Greenville",
    "sg:classifiers":[
        {
            "category":"Shopping",
            "subcategory":"Department Store",
            "type":"Retail Goods"
        }
    ],
    "sg:phone":"+1 864 605 1076",
    "sg:postcode":"29611",
    "sg:province":"SC",
    "sg:tags":[
        "shop"
    ],
    "wof:name":"Dollar General",
    "wof:placetype":"venue"
},
  "geometry": {"coordinates":[-82.484309,34.789364],"type":"Point"}
}