{
  "type": "Feature",
  "properties": {
    "iso:country":"US",
    "sg:address":"125 Riverland Dr",
    "sg:city":"Charleston",
    "sg:classifiers":[
        {
            "category":"Building & Trades",
            "subcategory":"Construction",
            "type":"Services"
        }
    ],
    "sg:phone":"+1 843 971 4750",
    "sg:postcode":"29412",
    "sg:province":"SC",
    "sg:tags":[
        "contractor"
    ],
    "sg:website":"www.newtradition.biz",
    "wof:name":"New Tradition Custom Homes",
    "wof:placetype":"venue"
},
  "geometry": {"coordinates":[-80.000248,32.764663],"type":"Point"}
}