{
  "type": "Feature",
  "properties": {
    "addr:full":"518 North Ave Rock Hill SC 29732",
    "addr:housenumber":"518",
    "addr:postcode":"29732",
    "addr:street":"North Ave",
    "iso:country":"US",
    "sg:address":"518 North Ave",
    "sg:city":"Rock Hill",
    "sg:classifiers":[
        {
            "category":"Organizations",
            "subcategory":"Religious Organization",
            "type":"Services"
        }
    ],
    "sg:phone":"+1 803 366 9518",
    "sg:postcode":"29732",
    "sg:province":"SC",
    "wof:name":"Young Life",
    "wof:placetype":"venue"
},
  "geometry": {"coordinates":[-81.03083700000001,34.945327],"type":"Point"}
}