{
  "type": "Feature",
  "properties": {
    "iso:country":"US",
    "sg:address":"813 Miller Rd",
    "sg:city":"Sumter",
    "sg:classifiers":[
        {
            "category":"Social Services",
            "subcategory":"Child Care",
            "type":"Services"
        }
    ],
    "sg:phone":"+1 803 775 0214",
    "sg:postcode":"29150",
    "sg:province":"SC",
    "wof:name":"Small Talk Day Care Ctr",
    "wof:placetype":"venue"
},
  "geometry": {"coordinates":[-80.356276,33.944022],"type":"Point"}
}