{
  "type": "Feature",
  "properties": {
    "addr:full":"7273 Peppermill Pkwy North Charleston SC 29418",
    "addr:housenumber":"7273",
    "addr:postcode":"29418",
    "addr:street":"Peppermill Pkwy",
    "iso:country":"US",
    "sg:address":"7273 Peppermill Pkwy",
    "sg:city":"North Charleston",
    "sg:classifiers":[
        {
            "category":"Retail",
            "subcategory":"Auto Rental",
            "type":"Services"
        }
    ],
    "sg:phone":"+1 843 767 9288",
    "sg:postcode":"29418",
    "sg:province":"SC",
    "sg:tags":[
        "renting",
        "automobile"
    ],
    "wof:name":"Budget Rent A Car",
    "wof:placetype":"venue"
},
  "geometry": {"coordinates":[-80.07570699999999,32.919784],"type":"Point"}
}