{
  "type": "Feature",
  "properties": {
    "iso:country":"US",
    "sg:address":"269 Calhoun St",
    "sg:city":"Charleston",
    "sg:classifiers":[
        {
            "category":"Organizations",
            "subcategory":"Professional Association",
            "type":"Services"
        }
    ],
    "sg:phone":"+1 843 723 8850",
    "sg:postcode":"29401",
    "sg:province":"SC",
    "wof:name":"American Cancer Society",
    "wof:placetype":"venue"
},
  "geometry": {"coordinates":[-79.945555,32.78326],"type":"Point"}
}