{
  "type": "Feature",
  "properties": {
    "iso:country":"US",
    "sg:address":"1015 Whaley St",
    "sg:city":"Columbia",
    "sg:classifiers":[
        {
            "category":"Shopping",
            "subcategory":"Used Merchandise",
            "type":"Retail Goods"
        }
    ],
    "sg:phone":"+1 803 254 8448",
    "sg:postcode":"29201",
    "sg:province":"SC",
    "sg:tags":[
        "antique"
    ],
    "wof:name":"Safran's Antiques",
    "wof:placetype":"venue"
},
  "geometry": {"coordinates":[-81.0299,33.987099],"type":"Point"}
}