{
  "type": "Feature",
  "properties": {
    "iso:country":"US",
    "sg:address":"7520 Garners Ferry Rd",
    "sg:city":"Columbia",
    "sg:classifiers":[
        {
            "category":"Restaurant",
            "type":"Food & Drink"
        }
    ],
    "sg:menulink":"http://www.allmenus.com/sc/columbia/129391-subway/menu/",
    "sg:phone":"+1 803 695 5151",
    "sg:postcode":"29209",
    "sg:province":"SC",
    "sg:tags":[
        "american",
        "sandwich"
    ],
    "wof:name":"Subway",
    "wof:placetype":"venue"
},
  "geometry": {"coordinates":[-80.94123399999999,33.962604],"type":"Point"}
}