{
  "type": "Feature",
  "properties": {
    "iso:country":"US",
    "sg:address":"500 Charlie Rast Rd",
    "sg:city":"Swansea",
    "sg:classifiers":[
        {
            "category":"Government",
            "subcategory":"Office",
            "type":"Public Place"
        }
    ],
    "sg:phone":"+1 803 568 3616",
    "sg:postcode":"29160",
    "sg:province":"SC",
    "wof:name":"Honorable WG Shockley",
    "wof:placetype":"venue"
},
  "geometry": {"coordinates":[-81.092905,33.76512],"type":"Point"}
}