{
  "type": "Feature",
  "properties": {
    "addr:full":"27 N Main St Travelers Rest SC 29690",
    "addr:housenumber":"27",
    "addr:postcode":"29690",
    "addr:street":"N Main St",
    "iso:country":"US",
    "sg:address":"27 N Main St",
    "sg:city":"Travelers Rest",
    "sg:classifiers":[
        {
            "category":"Retail",
            "subcategory":"Auto Repair",
            "type":"Services"
        }
    ],
    "sg:phone":"+1 864 834 7157",
    "sg:postcode":"29690",
    "sg:province":"SC",
    "sg:tags":[
        "muffler",
        "exhaust",
        "system"
    ],
    "wof:name":"Barrett's Garage Muffler",
    "wof:placetype":"venue"
},
  "geometry": {"coordinates":[-82.444023,34.967727],"type":"Point"}
}