{
  "type": "Feature",
  "properties": {
    "iso:country":"US",
    "sg:address":"3662 Kershaw Hwy",
    "sg:city":"Kershaw",
    "sg:classifiers":[
        {
            "category":"Sports & Exercise",
            "subcategory":"Race Track",
            "type":"Entertainment"
        }
    ],
    "sg:phone":"+1 803 475 2448",
    "sg:postcode":"29067",
    "sg:province":"SC",
    "wof:name":"Carolina Motorsport Park",
    "wof:placetype":"venue"
},
  "geometry": {"coordinates":[-80.599188,34.494491],"type":"Point"}
}