{
  "type": "Feature",
  "properties": {
    "addr:full":"10177 N Kings Hwy Myrtle Beach SC 29572",
    "addr:housenumber":"10177",
    "addr:postcode":"29572",
    "addr:street":"N Kings Hwy",
    "iso:country":"US",
    "sg:address":"10177 N Kings Hwy",
    "sg:city":"Myrtle Beach",
    "sg:classifiers":[
        {
            "category":"Shopping",
            "subcategory":"Discount & Variety Stores",
            "type":"Retail Goods"
        }
    ],
    "sg:phone":"+1 843 447 5018",
    "sg:postcode":"29572",
    "sg:province":"SC",
    "sg:tags":[
        "merchandise",
        "general"
    ],
    "wof:name":"Haywood House Inc",
    "wof:placetype":"venue"
},
  "geometry": {"coordinates":[-78.764898,33.79064],"type":"Point"}
}