{
  "type": "Feature",
  "properties": {
    "iso:country":"US",
    "sg:address":"247 Calhoun St",
    "sg:city":"Charleston",
    "sg:classifiers":[
        {
            "category":"Health Services",
            "subcategory":"Doctor",
            "type":"Services"
        }
    ],
    "sg:phone":"+1 843 722 5904",
    "sg:postcode":"29401",
    "sg:province":"SC",
    "sg:tags":[
        "physician",
        "surgeon"
    ],
    "wof:name":"Southeastern Facial Plastic",
    "wof:placetype":"venue"
},
  "geometry": {"coordinates":[-79.943472,32.783811],"type":"Point"}
}