{
  "type": "Feature",
  "properties": {
    "addr:full":"705 N White St Lancaster SC 29720",
    "addr:housenumber":"705",
    "addr:postcode":"29720",
    "addr:street":"N White St",
    "iso:country":"US",
    "sg:address":"705 N White St",
    "sg:city":"Lancaster",
    "sg:classifiers":[
        {
            "category":"Professional",
            "subcategory":"Employment Agencies",
            "type":"Services"
        }
    ],
    "sg:phone":"+1 803 285 6966",
    "sg:postcode":"29720",
    "sg:province":"SC",
    "sg:tags":[
        "consultant",
        "outplacement"
    ],
    "wof:name":"Employment Service",
    "wof:placetype":"venue"
},
  "geometry": {"coordinates":[-80.773167,34.728805],"type":"Point"}
}