{
  "type": "Feature",
  "properties": {
    "addr:full":"115 Belle Meade Rd Summerville SC 29483",
    "addr:housenumber":"115",
    "addr:postcode":"29483",
    "addr:street":"Belle Meade Rd",
    "iso:country":"US",
    "sg:address":"115 Belle Meade Rd",
    "sg:city":"Summerville",
    "sg:classifiers":[
        {
            "category":"Building & Trades",
            "subcategory":"Construction",
            "type":"Services"
        }
    ],
    "sg:phone":"+1 843 871 4091",
    "sg:postcode":"29483",
    "sg:province":"SC",
    "sg:tags":[
        "house"
    ],
    "wof:name":"Fairway Construction",
    "wof:placetype":"venue"
},
  "geometry": {"coordinates":[-80.277698,33.014781],"type":"Point"}
}