{
  "type": "Feature",
  "properties": {
    "addr:full":"819 S 5th St Hartsville SC 29550",
    "addr:housenumber":"819",
    "addr:postcode":"29550",
    "addr:street":"S 5Th St",
    "iso:country":"US",
    "sg:address":"819 S 5th St",
    "sg:city":"Hartsville",
    "sg:classifiers":[
        {
            "category":"Shopping",
            "subcategory":"Department Store",
            "type":"Retail Goods"
        }
    ],
    "sg:phone":"+1 843 332 1173",
    "sg:postcode":"29550",
    "sg:province":"SC",
    "wof:name":"Rose's Stores",
    "wof:placetype":"venue"
},
  "geometry": {"coordinates":[-80.06896,34.35491],"type":"Point"}
}