{
  "type": "Feature",
  "properties": {
    "addr:full":"2512 Laurens Rd Greenville SC 29607",
    "addr:housenumber":"2512",
    "addr:postcode":"29607",
    "addr:street":"Laurens Rd",
    "iso:country":"US",
    "sg:address":"2512 Laurens Rd",
    "sg:city":"Greenville",
    "sg:classifiers":[
        {
            "category":"Autos & Motor Vehicles",
            "subcategory":"Automobile Sales",
            "type":"Retail Goods"
        }
    ],
    "sg:phone":"+1 864 458 3500",
    "sg:postcode":"29607",
    "sg:province":"SC",
    "sg:tags":[
        "car",
        "dealer"
    ],
    "wof:name":"John Finger Mazda",
    "wof:placetype":"venue"
},
  "geometry": {"coordinates":[-82.345558,34.826283],"type":"Point"}
}