{
  "type": "Feature",
  "properties": {
    "addr:full":"1221 Osheal Rd Irmo SC 29063",
    "addr:housenumber":"1221",
    "addr:postcode":"29063",
    "addr:street":"Osheal Rd",
    "iso:country":"US",
    "sg:address":"1221 Osheal Rd",
    "sg:city":"Irmo",
    "sg:classifiers":[
        {
            "category":"Shopping",
            "subcategory":"Gifts & Souvenirs",
            "type":"Retail Goods"
        }
    ],
    "sg:phone":"+1 803 732 4849",
    "sg:postcode":"29063",
    "sg:province":"SC",
    "sg:tags":[
        "used",
        "merchandise"
    ],
    "wof:name":"Broad River Antiques",
    "wof:placetype":"venue"
},
  "geometry": {"coordinates":[-81.17705100000001,34.171281],"type":"Point"}
}