{
  "type": "Feature",
  "properties": {
    "iso:country":"US",
    "sg:address":"111 E North St",
    "sg:city":"Greenville",
    "sg:classifiers":[
        {
            "category":"Professional",
            "subcategory":"Lawyer & Legal Services",
            "type":"Services"
        }
    ],
    "sg:phone":"+1 864 255 9255",
    "sg:postcode":"29601",
    "sg:province":"SC",
    "sg:tags":[
        "attorney"
    ],
    "wof:name":"Anderson & Herlong LLC",
    "wof:placetype":"venue"
},
  "geometry": {"coordinates":[-82.396356,34.852012],"type":"Point"}
}