{
  "type": "Feature",
  "properties": {
    "iso:country":"US",
    "sg:address":"500 Cherry Rd",
    "sg:city":"Clemson",
    "sg:classifiers":[
        {
            "category":"Manufacturing",
            "subcategory":"Textiles",
            "type":"Manufacturing & Wholesale Goods"
        }
    ],
    "sg:phone":"+1 864 653 2600",
    "sg:postcode":"29631",
    "sg:province":"SC",
    "sg:tags":[
        "mills"
    ],
    "wof:name":"West Point Stevens",
    "wof:placetype":"venue"
},
  "geometry": {"coordinates":[-82.836288,34.666782],"type":"Point"}
}