{
  "type": "Feature",
  "properties": {
    "iso:country":"US",
    "sg:address":"502 Goddard Ave",
    "sg:city":"Seneca",
    "sg:classifiers":[
        {
            "category":"Organizations",
            "subcategory":"Religious Organization",
            "type":"Services"
        }
    ],
    "sg:phone":"+1 864 882 8577",
    "sg:postcode":"29678",
    "sg:province":"SC",
    "wof:name":"House Of Judah Ministries",
    "wof:placetype":"venue"
},
  "geometry": {"coordinates":[-82.929362,34.681889],"type":"Point"}
}