{
  "type": "Feature",
  "properties": {
    "iso:country":"US",
    "sg:address":"137 Parker Rd",
    "sg:city":"Edgefield",
    "sg:classifiers":[
        {
            "category":"Place Of Worship",
            "subcategory":"Church",
            "type":"Public Place"
        },
        {
            "category":"Place Of Worship",
            "type":"Public Place"
        }
    ],
    "sg:phone":"+1 803 637 0873",
    "sg:postcode":"29824",
    "sg:province":"SC",
    "sg:tags":[
        "churches-interdenominational",
        "churches-various",
        "denomination"
    ],
    "wof:name":"Kingdom Hall Of Jehovahs Witnesses",
    "wof:placetype":"venue"
},
  "geometry": {"coordinates":[-81.887997,33.77506],"type":"Point"}
}