{
  "type": "Feature",
  "properties": {
    "iso:country":"US",
    "sg:address":"905 Gervais St",
    "sg:city":"Columbia",
    "sg:classifiers":[
        {
            "category":"Autos & Motor Vehicles",
            "subcategory":"Boat Sales",
            "type":"Retail Goods"
        }
    ],
    "sg:phone":"+1 803 771 0353",
    "sg:postcode":"29201",
    "sg:province":"SC",
    "sg:tags":[
        "rafting/kayaking",
        "sporting",
        "canoe"
    ],
    "sg:website":"www.riverrunner.us",
    "wof:name":"River Runner Outdoor Center",
    "wof:placetype":"venue"
},
  "geometry": {"coordinates":[-81.038498,33.999901],"type":"Point"}
}