{
  "type": "Feature",
  "properties": {
    "iso:country":"US",
    "sg:address":"106 Wall St",
    "sg:city":"Clinton",
    "sg:classifiers":[
        {
            "category":"Personal",
            "subcategory":"Beauty Salon",
            "type":"Services"
        }
    ],
    "sg:phone":"+1 864 833 5686",
    "sg:postcode":"29325",
    "sg:province":"SC",
    "wof:name":"Design Systems",
    "wof:placetype":"venue"
},
  "geometry": {"coordinates":[-81.8814,34.474108],"type":"Point"}
}