{
  "type": "Feature",
  "properties": {
    "iso:country":"US",
    "sg:address":"119 W Cherokee St",
    "sg:city":"Blacksburg",
    "sg:classifiers":[
        {
            "category":"Shopping",
            "subcategory":"Discount & Variety Stores",
            "type":"Retail Goods"
        }
    ],
    "sg:phone":"+1 864 839 6001",
    "sg:postcode":"29702",
    "sg:province":"SC",
    "wof:name":"Variety Wholesalers Inc",
    "wof:placetype":"venue"
},
  "geometry": {"coordinates":[-81.51622500000001,35.120936],"type":"Point"}
}