{
  "type": "Feature",
  "properties": {
    "addr:full":"140 N Cedar Ln Hartsville SC 29550",
    "addr:housenumber":"140",
    "addr:postcode":"29550",
    "addr:street":"N Cedar Ln",
    "iso:country":"US",
    "sg:address":"140 N Cedar Ln",
    "sg:city":"Hartsville",
    "sg:classifiers":[
        {
            "category":"Government",
            "subcategory":"Office",
            "type":"Public Place"
        }
    ],
    "sg:phone":"+1 843 383 3004",
    "sg:postcode":"29550",
    "sg:province":"SC",
    "sg:tags":[
        "village"
    ],
    "wof:name":"City Cemeteries",
    "wof:placetype":"venue"
},
  "geometry": {"coordinates":[-80.091144,34.36773],"type":"Point"}
}