{
  "type": "Feature",
  "properties": {
    "addr:full":"205 S Main St Greer SC 29650",
    "addr:housenumber":"205",
    "addr:postcode":"29650",
    "addr:street":"S Main St",
    "iso:country":"US",
    "sg:address":"205 S Main St",
    "sg:city":"Greer",
    "sg:classifiers":[
        {
            "category":"Home & Garden",
            "subcategory":"Building Materials",
            "type":"Retail Goods"
        }
    ],
    "sg:phone":"+1 864 877 7576",
    "sg:postcode":"29650",
    "sg:province":"SC",
    "sg:tags":[
        "glass",
        "leaded"
    ],
    "wof:name":"Mt Airy Glass Co",
    "wof:placetype":"venue"
},
  "geometry": {"coordinates":[-82.23005999999999,34.935734],"type":"Point"}
}