{
  "type": "Feature",
  "properties": {
    "iso:country":"US",
    "sg:address":"2206 Airport Blvd",
    "sg:city":"West Columbia",
    "sg:classifiers":[
        {
            "category":"Food & Beverages",
            "subcategory":"Liquor & Beverages",
            "type":"Retail Goods"
        }
    ],
    "sg:phone":"+1 803 796 3242",
    "sg:postcode":"29170",
    "sg:province":"SC",
    "sg:tags":[
        "beer",
        "spirit",
        "wine"
    ],
    "wof:name":"Midland Liquor Store",
    "wof:placetype":"venue"
},
  "geometry": {"coordinates":[-81.09559,33.954171],"type":"Point"}
}