{
  "type": "Feature",
  "properties": {
    "addr:full":"1250 N Matthews Rd Lake City SC 29560",
    "addr:housenumber":"1250",
    "addr:postcode":"29560",
    "addr:street":"N Matthews Rd",
    "iso:country":"US",
    "sg:address":"1250 N Matthews Rd",
    "sg:city":"Lake City",
    "sg:classifiers":[
        {
            "category":"Retail",
            "subcategory":"Funeral Services",
            "type":"Services"
        }
    ],
    "sg:phone":"+1 843 389 3848",
    "sg:postcode":"29560",
    "sg:province":"SC",
    "sg:tags":[
        "director"
    ],
    "wof:name":"Fryar Funeral Home",
    "wof:placetype":"venue"
},
  "geometry": {"coordinates":[-79.774841,33.900009],"type":"Point"}
}