{
  "type": "Feature",
  "properties": {
    "addr:full":"3950 US Hwy 221 S Laurens SC 29360",
    "addr:housenumber":"3950",
    "addr:postcode":"29360",
    "addr:street":"Us Hwy 221 S",
    "iso:country":"US",
    "sg:address":"3950 US Hwy 221 S",
    "sg:city":"Laurens",
    "sg:classifiers":[
        {
            "category":"Shopping",
            "subcategory":"Bicycles & Sporting Goods",
            "type":"Retail Goods"
        }
    ],
    "sg:phone":"+1 864 682 2060",
    "sg:postcode":"29360",
    "sg:province":"SC",
    "sg:tags":[
        "bait",
        "fishing"
    ],
    "wof:name":"Hickory Point I",
    "wof:placetype":"venue"
},
  "geometry": {"coordinates":[-82.05374,34.460401],"type":"Point"}
}