{
  "type": "Feature",
  "properties": {
    "addr:full":"7860 Dorchester Rd North Charleston SC 29418",
    "addr:housenumber":"7860",
    "addr:postcode":"29418",
    "addr:street":"Dorchester Rd",
    "iso:country":"US",
    "sg:address":"7860 Dorchester Rd",
    "sg:city":"North Charleston",
    "sg:classifiers":[
        {
            "category":"Food & Beverages",
            "subcategory":"Meat & Fish",
            "type":"Retail Goods"
        }
    ],
    "sg:phone":"+1 843 767 0490",
    "sg:postcode":"29418",
    "sg:province":"SC",
    "sg:tags":[
        "seafood"
    ],
    "wof:name":"Chunga's Grocery",
    "wof:placetype":"venue"
},
  "geometry": {"coordinates":[-80.086438,32.904863],"type":"Point"}
}