{
  "type": "Feature",
  "properties": {
    "iso:country":"US",
    "sg:address":"337 State Hwy 9 Bus",
    "sg:city":"Bennettsville",
    "sg:classifiers":[
        {
            "category":"Government",
            "subcategory":"Office",
            "type":"Public Place"
        }
    ],
    "sg:phone":"+1 843 479 0785",
    "sg:postcode":"29512",
    "sg:province":"SC",
    "sg:tags":[
        "state",
        "program"
    ],
    "wof:name":"Public Safety Dept",
    "wof:placetype":"venue"
},
  "geometry": {"coordinates":[-79.681714,34.612396],"type":"Point"}
}