{
  "type": "Feature",
  "properties": {
    "iso:country":"US",
    "sg:address":"470 S Guignard Dr",
    "sg:city":"Sumter",
    "sg:classifiers":[
        {
            "category":"Wholesale",
            "subcategory":"Machinery & Supplies",
            "type":"Manufacturing & Wholesale Goods"
        }
    ],
    "sg:phone":"+1 803 418 0300",
    "sg:postcode":"29150",
    "sg:province":"SC",
    "sg:tags":[
        "equipment",
        "steam",
        "cleaning"
    ],
    "wof:name":"Hydro Clean Solutions",
    "wof:placetype":"venue"
},
  "geometry": {"coordinates":[-80.354089,33.908762],"type":"Point"}
}