{
  "type": "Feature",
  "properties": {
    "iso:country":"US",
    "sg:address":"614 Mary Ln",
    "sg:city":"Camden",
    "sg:classifiers":[
        {
            "category":"Sports & Exercise",
            "subcategory":"Golf",
            "type":"Entertainment"
        }
    ],
    "sg:phone":"+1 803 432 7442",
    "sg:postcode":"29020",
    "sg:province":"SC",
    "sg:tags":[
        "course"
    ],
    "wof:name":"White Pines Golf Club",
    "wof:placetype":"venue"
},
  "geometry": {"coordinates":[-80.53380799999999,34.273569],"type":"Point"}
}