{
  "type": "Feature",
  "properties": {
    "iso:country":"US",
    "sg:address":"411 Carpenter Parker Ln",
    "sg:city":"Rock Hill",
    "sg:classifiers":[
        {
            "category":"Building & Trades",
            "subcategory":"Construction",
            "type":"Services"
        }
    ],
    "sg:phone":"+1 803 324 2617",
    "sg:postcode":"29730",
    "sg:province":"SC",
    "sg:tags":[
        "floor",
        "laying",
        "contractor"
    ],
    "wof:name":"Eric Parkers Hardwood Floors",
    "wof:placetype":"venue"
},
  "geometry": {"coordinates":[-80.89632400000001,34.918488],"type":"Point"}
}