{
  "type": "Feature",
  "properties": {
    "iso:country":"US",
    "sg:address":"2665 Peach Orchard Rd",
    "sg:city":"Dalzell",
    "sg:classifiers":[
        {
            "category":"Retail",
            "subcategory":"Laundry & Dry Cleaning",
            "type":"Services"
        }
    ],
    "sg:phone":"+1 803 494 8287",
    "sg:postcode":"29040",
    "sg:province":"SC",
    "sg:tags":[
        "cleaners",
        "rug",
        "carpet"
    ],
    "wof:name":"Muller Cleaning Svc Inc",
    "wof:placetype":"venue"
},
  "geometry": {"coordinates":[-80.495458,33.998156],"type":"Point"}
}