{
  "type": "Feature",
  "properties": {
    "iso:country":"US",
    "sg:address":"1844 W Blue Ridge Dr",
    "sg:city":"Greenville",
    "sg:classifiers":[
        {
            "category":"Building & Trades",
            "subcategory":"Landscaping Services",
            "type":"Services"
        }
    ],
    "sg:phone":"+1 864 294 1002",
    "sg:postcode":"29611",
    "sg:province":"SC",
    "sg:tags":[
        "grating"
    ],
    "wof:name":"Anders Inc",
    "wof:placetype":"venue"
},
  "geometry": {"coordinates":[-82.43227899999999,34.868152],"type":"Point"}
}