{
  "type": "Feature",
  "properties": {
    "iso:country":"US",
    "sg:address":"7050 White Ave",
    "sg:city":"Spartanburg",
    "sg:classifiers":[
        {
            "category":"Freight",
            "type":"Transportation"
        }
    ],
    "sg:phone":"+1 864 583 5538",
    "sg:postcode":"29303",
    "sg:province":"SC",
    "sg:tags":[
        "operator",
        "trucking"
    ],
    "wof:name":"Sunflower Carriers",
    "wof:placetype":"venue"
},
  "geometry": {"coordinates":[-81.96971499999999,34.976039],"type":"Point"}
}