{
  "type": "Feature",
  "properties": {
    "iso:country":"US",
    "sg:address":"1810 Richland Ave",
    "sg:city":"Aiken",
    "sg:classifiers":[
        {
            "category":"Restaurant",
            "type":"Food & Drink"
        }
    ],
    "sg:menulink":"http://www.allmenus.com/sc/aiken/201258-mcdonalds/menu/",
    "sg:postcode":"29801",
    "sg:province":"SC",
    "sg:tags":[
        "burger",
        "american"
    ],
    "wof:name":"McDonald's",
    "wof:placetype":"venue"
},
  "geometry": {"coordinates":[-81.69287300000001,33.551854],"type":"Point"}
}