{
  "type": "Feature",
  "properties": {
    "iso:country":"US",
    "sg:address":"1523 Savannah Hwy",
    "sg:city":"Charleston",
    "sg:classifiers":[
        {
            "category":"Food & Beverages",
            "subcategory":"Groceries & Convenience Stores",
            "type":"Retail Goods"
        }
    ],
    "sg:phone":"+1 843 556 4494",
    "sg:postcode":"29407",
    "sg:province":"SC",
    "wof:name":"Li' L Cricket Store",
    "wof:placetype":"venue"
},
  "geometry": {"coordinates":[-80.00802,32.785911],"type":"Point"}
}