{
  "type": "Feature",
  "properties": {
    "iso:country":"US",
    "sg:address":"132 E Bay St",
    "sg:city":"Charleston",
    "sg:classifiers":[
        {
            "category":"Real Estate",
            "subcategory":"Real Estate Agent",
            "type":"Services"
        }
    ],
    "sg:phone":"+1 843 722 2773",
    "sg:postcode":"29401",
    "sg:province":"SC",
    "sg:website":"www.wmiselinco.com",
    "wof:name":"William Iselin Co",
    "wof:placetype":"venue"
},
  "geometry": {"coordinates":[-79.927009,32.776843],"type":"Point"}
}