{
  "type": "Feature",
  "properties": {
    "iso:country":"US",
    "sg:address":"645 Eagle Rd",
    "sg:city":"Wedgefield",
    "sg:classifiers":[
        {
            "category":"Restaurant",
            "type":"Food & Drink"
        }
    ],
    "sg:phone":"+1 803 494 3320",
    "sg:postcode":"29168",
    "sg:province":"SC",
    "sg:tags":[
        "caterer"
    ],
    "wof:name":"H & H Catering Svc",
    "wof:placetype":"venue"
},
  "geometry": {"coordinates":[-80.475325,33.936893],"type":"Point"}
}