{
  "type": "Feature",
  "properties": {
    "addr:full":"212 Candi Ln Columbia SC 29210",
    "addr:housenumber":"212",
    "addr:postcode":"29210",
    "addr:street":"Candi Ln",
    "iso:country":"US",
    "sg:address":"212 Candi Ln",
    "sg:city":"Columbia",
    "sg:classifiers":[
        {
            "category":"Wholesale",
            "subcategory":"Apparel",
            "type":"Manufacturing & Wholesale Goods"
        }
    ],
    "sg:phone":"+1 803 929 1404",
    "sg:postcode":"29210",
    "sg:province":"SC",
    "sg:tags":[
        "fabric"
    ],
    "wof:name":"Zimmerman Co",
    "wof:placetype":"venue"
},
  "geometry": {"coordinates":[-81.078615,34.012608],"type":"Point"}
}