{
  "type": "Feature",
  "properties": {
    "iso:country":"US",
    "sg:address":"135 W Wesmark Blvd",
    "sg:city":"Sumter",
    "sg:classifiers":[
        {
            "category":"Home & Garden",
            "subcategory":"Building Materials",
            "type":"Retail Goods"
        }
    ],
    "sg:phone":"+1 803 469 6065",
    "sg:postcode":"29150",
    "sg:province":"SC",
    "sg:tags":[
        "wholesale",
        "wallpaper",
        "floor",
        "paint",
        "covering"
    ],
    "wof:name":"Mc Kenzie Paint & Decorating",
    "wof:placetype":"venue"
},
  "geometry": {"coordinates":[-80.387067,33.951071],"type":"Point"}
}