{
  "type": "Feature",
  "properties": {
    "addr:full":"130 Linwood Ln Summerville SC 29483",
    "addr:housenumber":"130",
    "addr:postcode":"29483",
    "addr:street":"Linwood Ln",
    "iso:country":"US",
    "sg:address":"130 Linwood Ln",
    "sg:city":"Summerville",
    "sg:classifiers":[
        {
            "category":"Social Services",
            "type":"Services"
        }
    ],
    "sg:phone":"+1 843 871 9697",
    "sg:postcode":"29483",
    "sg:province":"SC",
    "sg:tags":[
        "counselor",
        "marriage",
        "family"
    ],
    "wof:name":"Virginia C Wilder",
    "wof:placetype":"venue"
},
  "geometry": {"coordinates":[-80.190095,33.010853],"type":"Point"}
}