{
  "type": "Feature",
  "properties": {
    "iso:country":"US",
    "sg:address":"960 Lansing Dr",
    "sg:city":"Mt Pleasant",
    "sg:classifiers":[
        {
            "category":"Manufacturing",
            "subcategory":"Printing",
            "type":"Manufacturing & Wholesale Goods"
        }
    ],
    "sg:phone":"+1 843 856 3593",
    "sg:postcode":"29464",
    "sg:province":"SC",
    "sg:tags":[
        "publisher"
    ],
    "wof:name":"F W Dodge Mc Graw-Hill",
    "wof:placetype":"venue"
},
  "geometry": {"coordinates":[-79.88576999999999,32.800195],"type":"Point"}
}