{
  "type": "Feature",
  "properties": {
    "addr:full":"799 Lang Jennings Dr Sumter SC 29150",
    "addr:housenumber":"799",
    "addr:postcode":"29150",
    "addr:street":"Lang Jennings Dr",
    "iso:country":"US",
    "sg:address":"799 Lang Jennings Dr",
    "sg:city":"Sumter",
    "sg:classifiers":[
        {
            "category":"Building & Trades",
            "subcategory":"Cleaning & Sanitation",
            "type":"Services"
        }
    ],
    "sg:phone":"+1 803 469 0778",
    "sg:postcode":"29150",
    "sg:province":"SC",
    "sg:tags":[
        "janitor"
    ],
    "wof:name":"Ultimate Cleaning Svc",
    "wof:placetype":"venue"
},
  "geometry": {"coordinates":[-80.387467,33.953016],"type":"Point"}
}