{
  "type": "Feature",
  "properties": {
    "iso:country":"US",
    "sg:address":"1988 Garvin Rd",
    "sg:city":"York",
    "sg:classifiers":[
        {
            "category":"Building & Trades",
            "subcategory":"Construction",
            "type":"Services"
        }
    ],
    "sg:phone":"+1 803 684 2133",
    "sg:postcode":"29745",
    "sg:province":"SC",
    "sg:tags":[
        "house"
    ],
    "wof:name":"Country Builders",
    "wof:placetype":"venue"
},
  "geometry": {"coordinates":[-81.23155300000001,34.924409],"type":"Point"}
}