{
  "type": "Feature",
  "properties": {
    "iso:country":"US",
    "sg:address":"1411 Pearman Dairy Rd",
    "sg:city":"Anderson",
    "sg:classifiers":[
        {
            "category":"Restaurant",
            "type":"Food & Drink"
        }
    ],
    "sg:menulink":"http://www.allmenus.com/sc/anderson/191618-sonic/menu/",
    "sg:phone":"+1 864 226 9022",
    "sg:postcode":"29625",
    "sg:province":"SC",
    "sg:tags":[
        "burger",
        "american"
    ],
    "wof:name":"Sonic",
    "wof:placetype":"venue"
},
  "geometry": {"coordinates":[-82.693607,34.524196],"type":"Point"}
}