{
  "type": "Feature",
  "properties": {
    "addr:full":"295 N Hwy 52 Moncks Corner SC 29461",
    "addr:housenumber":"295",
    "addr:postcode":"29461",
    "addr:street":"N Hwy 52",
    "iso:country":"US",
    "sg:address":"295 N Hwy 52",
    "sg:city":"Moncks Corner",
    "sg:classifiers":[
        {
            "category":"Banks & Credit Unions",
            "subcategory":"Bank",
            "type":"Services"
        }
    ],
    "sg:phone":"+1 843 761 8373",
    "sg:postcode":"29461",
    "sg:province":"SC",
    "sg:tags":[
        "loan",
        "real estate"
    ],
    "wof:name":"PGNF Home Lending",
    "wof:placetype":"venue"
},
  "geometry": {"coordinates":[-79.991969,33.198822],"type":"Point"}
}