{
  "type": "Feature",
  "properties": {
    "iso:country":"US",
    "sg:address":"2621 Poinsett Hwy",
    "sg:city":"Greenville",
    "sg:classifiers":[
        {
            "category":"Wholesale",
            "subcategory":"Machinery & Supplies",
            "type":"Manufacturing & Wholesale Goods"
        }
    ],
    "sg:phone":"+1 864 232 5154",
    "sg:postcode":"29609",
    "sg:province":"SC",
    "sg:tags":[
        "janitor"
    ],
    "wof:name":"Janitor's Wholesale Supply Co",
    "wof:placetype":"venue"
},
  "geometry": {"coordinates":[-82.42973600000001,34.91534],"type":"Point"}
}