{
  "type": "Feature",
  "properties": {
    "addr:full":"300 E McBee Ave Greenville SC 29601",
    "addr:housenumber":"300",
    "addr:postcode":"29601",
    "addr:street":"E Mcbee Ave",
    "iso:country":"US",
    "sg:address":"300 E McBee Ave",
    "sg:city":"Greenville",
    "sg:classifiers":[
        {
            "category":"Professional",
            "subcategory":"Management & Consulting",
            "type":"Services"
        }
    ],
    "sg:phone":"+1 864 233 6070",
    "sg:postcode":"29601",
    "sg:province":"SC",
    "sg:tags":[
        "marketing",
        "consultant"
    ],
    "sg:website":"www.imiliving.com",
    "wof:name":"IMI Resort Holdings",
    "wof:placetype":"venue"
},
  "geometry": {"coordinates":[-82.39597500000001,34.848591],"type":"Point"}
}