{
  "type": "Feature",
  "properties": {
    "iso:country":"US",
    "sg:address":"1101 Main St",
    "sg:city":"Hilton Head Isle",
    "sg:classifiers":[
        {
            "category":"Shopping",
            "type":"Retail Goods"
        }
    ],
    "sg:phone":"+1 843 681 2622",
    "sg:postcode":"29926",
    "sg:province":"SC",
    "sg:tags":[
        "wheel",
        "chair",
        "scooter"
    ],
    "sg:website":"www.burkespharmacy.com",
    "wof:name":"Burke's Main Street Pharmacy",
    "wof:placetype":"venue"
},
  "geometry": {"coordinates":[-80.723752,32.215561],"type":"Point"}
}