{
  "type": "Feature",
  "properties": {
    "iso:country":"US",
    "sg:address":"742 Congaree Rd",
    "sg:city":"Greenville",
    "sg:classifiers":[
        {
            "category":"Building & Trades",
            "subcategory":"Cleaning & Sanitation",
            "type":"Services"
        }
    ],
    "sg:phone":"+1 864 255 4660",
    "sg:postcode":"29607",
    "sg:province":"SC",
    "sg:tags":[
        "janitor"
    ],
    "wof:name":"ABM Janitorial Svc",
    "wof:placetype":"venue"
},
  "geometry": {"coordinates":[-82.32181799999999,34.843803],"type":"Point"}
}