{
  "type": "Feature",
  "properties": {
    "iso:country":"US",
    "sg:address":"478 Meeting St",
    "sg:city":"Charleston",
    "sg:classifiers":[
        {
            "category":"Shopping",
            "subcategory":"Department Store",
            "type":"Retail Goods"
        }
    ],
    "sg:phone":"+1 843 722 3828",
    "sg:postcode":"29403",
    "sg:province":"SC",
    "sg:tags":[
        "shop"
    ],
    "sg:website":"www.familydollar.com",
    "wof:name":"Family Dollar Store",
    "wof:placetype":"venue"
},
  "geometry": {"coordinates":[-79.94040800000001,32.796138],"type":"Point"}
}