{
  "type": "Feature",
  "properties": {
    "iso:country":"US",
    "sg:address":"853 Bethel St",
    "sg:city":"Clover",
    "sg:classifiers":[
        {
            "category":"Restaurant",
            "type":"Food & Drink"
        }
    ],
    "sg:phone":"+1 803 222 8885",
    "sg:postcode":"29710",
    "sg:province":"SC",
    "wof:name":"Jin Jin Chinese Restaurant",
    "wof:placetype":"venue"
},
  "geometry": {"coordinates":[-81.214797,35.108647],"type":"Point"}
}