{
  "type": "Feature",
  "properties": {
    "iso:country":"US",
    "sg:address":"190 Goethe Rd",
    "sg:city":"Bluffton",
    "sg:classifiers":[
        {
            "category":"Shopping",
            "subcategory":"Clothing, Apparel, & Fashions",
            "type":"Retail Goods"
        }
    ],
    "sg:phone":"+1 843 757 7700",
    "sg:postcode":"29910",
    "sg:province":"SC",
    "sg:tags":[
        "alteration"
    ],
    "wof:name":"Jc's Tailoring & Alterations",
    "wof:placetype":"venue"
},
  "geometry": {"coordinates":[-80.862595,32.240681],"type":"Point"}
}