{
  "type": "Feature",
  "properties": {
    "iso:country":"US",
    "sg:address":"7332 Peppermill Pkwy",
    "sg:city":"North Charleston",
    "sg:classifiers":[
        {
            "category":"Building & Trades",
            "subcategory":"Construction",
            "type":"Services"
        }
    ],
    "sg:phone":"+1 843 552 6000",
    "sg:postcode":"29418",
    "sg:province":"SC",
    "sg:tags":[
        "designer",
        "dealer",
        "pool",
        "swimming"
    ],
    "wof:name":"Blue Haven Pools",
    "wof:placetype":"venue"
},
  "geometry": {"coordinates":[-80.076538,32.922672],"type":"Point"}
}