{
  "type": "Feature",
  "properties": {
    "addr:full":"325 Market St Seneca SC 29678",
    "addr:housenumber":"325",
    "addr:postcode":"29678",
    "addr:street":"Market St",
    "iso:country":"US",
    "sg:address":"325 Market St",
    "sg:city":"Seneca",
    "sg:classifiers":[
        {
            "category":"Shopping",
            "subcategory":"Gifts & Souvenirs",
            "type":"Retail Goods"
        }
    ],
    "sg:phone":"+1 864 882 9481",
    "sg:postcode":"29678",
    "sg:province":"SC",
    "sg:tags":[
        "shop"
    ],
    "wof:name":"Heartwarmers",
    "wof:placetype":"venue"
},
  "geometry": {"coordinates":[-82.992778,34.689607],"type":"Point"}
}