{
  "type": "Feature",
  "properties": {
    "iso:country":"US",
    "sg:address":"1365 Kingfisher Dr",
    "sg:city":"Ridgeway",
    "sg:classifiers":[
        {
            "category":"Real Estate",
            "subcategory":"Real Estate Agent",
            "type":"Services"
        }
    ],
    "sg:phone":"+1 803 337 8304",
    "sg:postcode":"29130",
    "sg:province":"SC",
    "wof:name":"All Shores Realty",
    "wof:placetype":"venue"
},
  "geometry": {"coordinates":[-80.830799,34.393884],"type":"Point"}
}