{
  "type": "Feature",
  "properties": {
    "addr:full":"2 Medical Park Rd Columbia SC 29203",
    "addr:housenumber":"2",
    "addr:postcode":"29203",
    "addr:street":"Medical Park Rd",
    "iso:country":"US",
    "sg:address":"2 Medical Park Rd",
    "sg:city":"Columbia",
    "sg:classifiers":[
        {
            "category":"Health Services",
            "subcategory":"Doctor",
            "type":"Services"
        }
    ],
    "sg:phone":"+1 803 256 2657",
    "sg:postcode":"29203",
    "sg:province":"SC",
    "sg:tags":[
        "surgeon",
        "cosmetic"
    ],
    "sg:website":"specialtyclinics.med.sc.edu",
    "wof:name":"Haynes James L MD Facs",
    "wof:placetype":"venue"
},
  "geometry": {"coordinates":[-81.034401,34.0257],"type":"Point"}
}