{
  "type": "Feature",
  "properties": {
    "addr:full":"415 N Fraser St Georgetown SC 29440",
    "addr:housenumber":"415",
    "addr:postcode":"29440",
    "addr:street":"N Fraser St",
    "iso:country":"US",
    "sg:address":"415 N Fraser St",
    "sg:city":"Georgetown",
    "sg:classifiers":[
        {
            "category":"Restaurant",
            "type":"Food & Drink"
        }
    ],
    "sg:phone":"+1 843 546 1612",
    "sg:postcode":"29440",
    "sg:province":"SC",
    "sg:tags":[
        "eating",
        "pizza"
    ],
    "wof:name":"Tony's Famous Pizza",
    "wof:placetype":"venue"
},
  "geometry": {"coordinates":[-79.28761799999999,33.377045],"type":"Point"}
}