{
  "type": "Feature",
  "properties": {
    "iso:country":"US",
    "sg:address":"2253 Rogers Rd",
    "sg:city":"Darlington",
    "sg:classifiers":[
        {
            "category":"Government",
            "subcategory":"Office",
            "type":"Public Place"
        }
    ],
    "sg:phone":"+1 843 393 0287",
    "sg:postcode":"29532",
    "sg:province":"SC",
    "wof:name":"Darlington County Roads & Brdg",
    "wof:placetype":"venue"
},
  "geometry": {"coordinates":[-79.92227,34.293625],"type":"Point"}
}