{
  "type": "Feature",
  "properties": {
    "iso:country":"US",
    "sg:address":"205 E Godfrey St",
    "sg:city":"Pageland",
    "sg:classifiers":[
        {
            "category":"Building & Trades",
            "subcategory":"Construction",
            "type":"Services"
        }
    ],
    "sg:phone":"+1 843 672 7920",
    "sg:postcode":"29728",
    "sg:province":"SC",
    "sg:tags":[
        "contractor"
    ],
    "wof:name":"Tab Co Dry Wall",
    "wof:placetype":"venue"
},
  "geometry": {"coordinates":[-80.389471,34.774055],"type":"Point"}
}