{
  "type": "Feature",
  "properties": {
    "iso:country":"US",
    "sg:address":"680 Nazareth Church Rd",
    "sg:city":"Moore",
    "sg:classifiers":[
        {
            "category":"Organizations",
            "subcategory":"Religious Organization",
            "type":"Services"
        }
    ],
    "sg:phone":"+1 864 576 8034",
    "sg:postcode":"29369",
    "sg:province":"SC",
    "sg:tags":[
        "church"
    ],
    "sg:website":"www.nazarethchurch.org",
    "wof:name":"Nazareth Presbyterian Church",
    "wof:placetype":"venue"
},
  "geometry": {"coordinates":[-82.032547,34.8979],"type":"Point"}
}