{
  "type": "Feature",
  "properties": {
    "iso:country":"US",
    "sg:address":"102 Race Club Rd",
    "sg:city":"Summerville",
    "sg:classifiers":[
        {
            "category":"Shopping",
            "subcategory":"Discount & Variety Stores",
            "type":"Retail Goods"
        }
    ],
    "sg:phone":"+1 843 873 1642",
    "sg:postcode":"29483",
    "sg:province":"SC",
    "sg:tags":[
        "merchandise",
        "general"
    ],
    "wof:name":"By Jody",
    "wof:placetype":"venue"
},
  "geometry": {"coordinates":[-80.203868,33.000037],"type":"Point"}
}