{
  "type": "Feature",
  "properties": {
    "iso:country":"US",
    "sg:address":"924 Front St",
    "sg:city":"Georgetown",
    "sg:classifiers":[
        {
            "category":"Personal",
            "subcategory":"Beauty Salon",
            "type":"Services"
        }
    ],
    "sg:phone":"+1 843 546 4698",
    "sg:postcode":"29440",
    "sg:province":"SC",
    "wof:name":"LA Sheek Beauty Salon",
    "wof:placetype":"venue"
},
  "geometry": {"coordinates":[-79.28699,33.369045],"type":"Point"}
}