{
  "type": "Feature",
  "properties": {
    "iso:country":"US",
    "sg:address":"1 Mathews Dr",
    "sg:city":"Hilton Head Isle",
    "sg:classifiers":[
        {
            "category":"Building & Trades",
            "subcategory":"Construction",
            "type":"Services"
        }
    ],
    "sg:phone":"+1 843 681 5133",
    "sg:postcode":"29926",
    "sg:province":"SC",
    "sg:tags":[
        "home",
        "builder"
    ],
    "wof:name":"Randy Jeffcoat Builders",
    "wof:placetype":"venue"
},
  "geometry": {"coordinates":[-80.708929,32.222443],"type":"Point"}
}