{
  "type": "Feature",
  "properties": {
    "iso:country":"US",
    "sg:address":"865 Old Clemson Hwy",
    "sg:city":"Seneca",
    "sg:classifiers":[
        {
            "category":"Banks & Credit Unions",
            "subcategory":"Bank",
            "type":"Services"
        }
    ],
    "sg:phone":"+1 864 886 0025",
    "sg:postcode":"29672",
    "sg:province":"SC",
    "sg:tags":[
        "broker",
        "mortgage"
    ],
    "wof:name":"Lamplightera Mortgage Co",
    "wof:placetype":"venue"
},
  "geometry": {"coordinates":[-82.883918,34.708015],"type":"Point"}
}