{
  "type": "Feature",
  "properties": {
    "addr:full":"7369 Two Notch Rd Columbia SC 29223",
    "addr:housenumber":"7369",
    "addr:postcode":"29223",
    "addr:street":"Two Notch Rd",
    "iso:country":"US",
    "sg:address":"7369 Two Notch Rd",
    "sg:city":"Columbia",
    "sg:classifiers":[
        {
            "category":"Restaurant",
            "type":"Food & Drink"
        }
    ],
    "sg:menulink":"http://www.allmenus.com/sc/columbia/100905-captain-ds-seafood/menu/",
    "sg:phone":"+1 803 788 4775",
    "sg:postcode":"29223",
    "sg:province":"SC",
    "sg:tags":[
        "seafood",
        "american"
    ],
    "wof:name":"Captain D's Seafood",
    "wof:placetype":"venue"
},
  "geometry": {"coordinates":[-80.952929,34.068595],"type":"Point"}
}