{
  "type": "Feature",
  "properties": {
    "iso:country":"US",
    "sg:address":"3710 Landmark Dr",
    "sg:city":"Columbia",
    "sg:classifiers":[
        {
            "category":"Social Services",
            "subcategory":"Job Training",
            "type":"Services"
        }
    ],
    "sg:phone":"+1 803 750 1501",
    "sg:postcode":"29204",
    "sg:province":"SC",
    "sg:tags":[
        "rehabilitation"
    ],
    "wof:name":"Joel Leonard",
    "wof:placetype":"venue"
},
  "geometry": {"coordinates":[-80.986501,34.018647],"type":"Point"}
}