{
  "type": "Feature",
  "properties": {
    "iso:country":"US",
    "sg:address":"1947 Belgrade Ave",
    "sg:city":"Charleston",
    "sg:classifiers":[
        {
            "category":"Autos & Motor Vehicles",
            "subcategory":"Auto Supplies",
            "type":"Retail Goods"
        }
    ],
    "sg:phone":"+1 843 769 2116",
    "sg:postcode":"29407",
    "sg:province":"SC",
    "sg:tags":[
        "tire"
    ],
    "wof:name":"Southware Tire Repair",
    "wof:placetype":"venue"
},
  "geometry": {"coordinates":[-80.024608,32.795638],"type":"Point"}
}