{
  "type": "Feature",
  "properties": {
    "addr:full":"222 Highlands Hwy Walhalla SC 29691",
    "addr:housenumber":"222",
    "addr:postcode":"29691",
    "addr:street":"Highlands Hwy",
    "iso:country":"US",
    "sg:address":"222 Highlands Hwy",
    "sg:city":"Walhalla",
    "sg:classifiers":[
        {
            "category":"Shopping",
            "subcategory":"Florist",
            "type":"Retail Goods"
        }
    ],
    "sg:phone":"+1 864 638 2320",
    "sg:postcode":"29691",
    "sg:province":"SC",
    "wof:name":"Village Creek Flower Shop",
    "wof:placetype":"venue"
},
  "geometry": {"coordinates":[-83.08513499999999,34.767427],"type":"Point"}
}