{
  "type": "Feature",
  "properties": {
    "iso:country":"US",
    "sg:address":"4406 State Hwy 162",
    "sg:city":"Hollywood",
    "sg:classifiers":[
        {
            "category":"Retail",
            "subcategory":"Repair Shop",
            "type":"Services"
        }
    ],
    "sg:phone":"+1 843 571 1230",
    "sg:postcode":"29449",
    "sg:province":"SC",
    "sg:tags":[
        "refinishing",
        "furniture"
    ],
    "wof:name":"B Alexander Furniture Rfnshng",
    "wof:placetype":"venue"
},
  "geometry": {"coordinates":[-80.15216599999999,32.778041],"type":"Point"}
}