{
  "type": "Feature",
  "properties": {
    "iso:country":"US",
    "sg:address":"645 Russell St",
    "sg:city":"Batesburg",
    "sg:classifiers":[
        {
            "category":"Manufacturing",
            "subcategory":"Tools & Machinery",
            "type":"Manufacturing & Wholesale Goods"
        },
        {
            "category":"Manufacturing",
            "subcategory":"Electronics",
            "type":"Manufacturing & Wholesale Goods"
        }
    ],
    "sg:phone":"+1 803 532 4432",
    "sg:postcode":"29006",
    "sg:province":"SC",
    "sg:tags":[
        "equipment",
        "railroad",
        "mfg",
        "apparatus",
        "communications"
    ],
    "sg:website":"www.unionswitch.com",
    "wof:name":"Union Switch & Signal Inc",
    "wof:placetype":"venue"
},
  "geometry": {"coordinates":[-81.555846,33.901153],"type":"Point"}
}