{
  "type": "Feature",
  "properties": {
    "addr:full":"2432 Jefferson Davis Hwy Graniteville SC 29829",
    "addr:housenumber":"2432",
    "addr:postcode":"29829",
    "addr:street":"Jefferson Davis Hwy",
    "iso:country":"US",
    "sg:address":"2432 Jefferson Davis Hwy",
    "sg:city":"Graniteville",
    "sg:classifiers":[
        {
            "category":"Education",
            "subcategory":"School",
            "type":"Public Place"
        }
    ],
    "sg:phone":"+1 803 594 1000",
    "sg:postcode":"29829",
    "sg:province":"SC",
    "wof:name":"Midland Valley Preparatory Sch",
    "wof:placetype":"venue"
},
  "geometry": {"coordinates":[-81.842956,33.530598],"type":"Point"}
}