{
  "type": "Feature",
  "properties": {
    "addr:full":"307 Waters Edge Rd Hilton Head Island SC 29924",
    "addr:housenumber":"307",
    "addr:postcode":"29924",
    "addr:street":"Waters Edge Rd",
    "iso:country":"US",
    "sg:address":"307 Waters Edge Rd",
    "sg:city":"Hilton Head Island",
    "sg:classifiers":[
        {
            "category":"Real Estate",
            "subcategory":"Real Estate Agent",
            "type":"Services"
        }
    ],
    "sg:phone":"+1 843 842 1133",
    "sg:postcode":"29924",
    "sg:province":"SC",
    "sg:tags":[
        "management"
    ],
    "wof:name":"Property Administrators Inc",
    "wof:placetype":"venue"
},
  "geometry": {"coordinates":[-81.132035,32.875607],"type":"Point"}
}