{
  "type": "Feature",
  "properties": {
    "iso:country":"US",
    "sg:address":"1019 Pine Logging Rd",
    "sg:city":"Aiken",
    "sg:classifiers":[
        {
            "category":"Health Services",
            "subcategory":"Clinic",
            "type":"Services"
        }
    ],
    "sg:phone":"+1 803 643 7996",
    "sg:postcode":"29803",
    "sg:province":"SC",
    "sg:tags":[
        "banks",
        "blood",
        "center"
    ],
    "wof:name":"Shepeard's Aiken Community",
    "wof:placetype":"venue"
},
  "geometry": {"coordinates":[-81.737526,33.516201],"type":"Point"}
}