{
  "type": "Feature",
  "properties": {
    "iso:country":"US",
    "sg:address":"1204 Mount Gallant Rd",
    "sg:city":"Rock Hill",
    "sg:classifiers":[
        {
            "category":"Cafe",
            "type":"Food & Drink"
        }
    ],
    "sg:menulink":"http://www.allmenus.com/sc/rock-hill/56021-the-little-cafe/menu/",
    "sg:phone":"+1 803 329 1440",
    "sg:postcode":"29732",
    "sg:province":"SC",
    "sg:tags":[
        "american"
    ],
    "wof:name":"The Little Cafe",
    "wof:placetype":"venue"
},
  "geometry": {"coordinates":[-81.002734,34.96715],"type":"Point"}
}