{
  "type": "Feature",
  "properties": {
    "addr:full":"106 Goodwin St Moncks Corner SC 29461",
    "addr:housenumber":"106",
    "addr:postcode":"29461",
    "addr:street":"Goodwin St",
    "iso:country":"US",
    "sg:address":"106 Goodwin St",
    "sg:city":"Moncks Corner",
    "sg:classifiers":[
        {
            "category":"Retail",
            "subcategory":"Repair Shop",
            "type":"Services"
        }
    ],
    "sg:phone":"+1 843 899 3453",
    "sg:postcode":"29461",
    "sg:province":"SC",
    "sg:tags":[
        "ironwork"
    ],
    "wof:name":"Iron Creations",
    "wof:placetype":"venue"
},
  "geometry": {"coordinates":[-80.014005,33.196306],"type":"Point"}
}