{
  "type": "Feature",
  "properties": {
    "iso:country":"US",
    "sg:address":"101 Hartzell Ave",
    "sg:city":"Cheraw",
    "sg:classifiers":[
        {
            "category":"Organizations",
            "subcategory":"Religious Organization",
            "type":"Services"
        }
    ],
    "sg:phone":"+1 843 537 3011",
    "sg:postcode":"29520",
    "sg:province":"SC",
    "sg:tags":[
        "church"
    ],
    "wof:name":"North Cheraw Baptist Church",
    "wof:placetype":"venue"
},
  "geometry": {"coordinates":[-79.88933900000001,34.70556],"type":"Point"}
}