{
  "type": "Feature",
  "properties": {
    "iso:country":"US",
    "sg:address":"311 Royal Palm Blvd",
    "sg:city":"Charleston",
    "sg:classifiers":[
        {
            "category":"Real Estate",
            "subcategory":"Real Estate Operator",
            "type":"Services"
        }
    ],
    "sg:phone":"+1 843 766 0472",
    "sg:postcode":"29407",
    "sg:province":"SC",
    "sg:tags":[
        "building",
        "apartment"
    ],
    "wof:name":"Palms Apts",
    "wof:placetype":"venue"
},
  "geometry": {"coordinates":[-80.00018,32.818383],"type":"Point"}
}