{
  "type": "Feature",
  "properties": {
    "addr:full":"876 E Main St Spartanburg SC 29302",
    "addr:housenumber":"876",
    "addr:postcode":"29302",
    "addr:street":"E Main St",
    "iso:country":"US",
    "sg:address":"876 E Main St",
    "sg:city":"Spartanburg",
    "sg:classifiers":[
        {
            "category":"Real Estate",
            "subcategory":"Real Estate Agent",
            "type":"Services"
        }
    ],
    "sg:phone":"+1 864 542 8060",
    "sg:postcode":"29302",
    "sg:province":"SC",
    "wof:name":"Premier Real Estate Inc",
    "wof:placetype":"venue"
},
  "geometry": {"coordinates":[-81.911214,34.9574],"type":"Point"}
}