{
  "type": "Feature",
  "properties": {
    "iso:country":"US",
    "sg:address":"525 Spanish Wells Rd",
    "sg:city":"Hilton Head Island",
    "sg:classifiers":[
        {
            "category":"Building & Trades",
            "subcategory":"Construction",
            "type":"Services"
        }
    ],
    "sg:phone":"+1 843 681 2920",
    "sg:postcode":"29926",
    "sg:province":"SC",
    "wof:name":"Odebrecht Construction Inc",
    "wof:placetype":"venue"
},
  "geometry": {"coordinates":[-80.766677,32.193594],"type":"Point"}
}