{
  "type": "Feature",
  "properties": {
    "addr:full":"73 S Market St Charleston SC 29401",
    "addr:housenumber":"73",
    "addr:postcode":"29401",
    "addr:street":"S Market St",
    "iso:country":"US",
    "sg:address":"73 S Market St",
    "sg:city":"Charleston",
    "sg:classifiers":[
        {
            "category":"Shopping",
            "subcategory":"Optical Goods",
            "type":"Retail Goods"
        }
    ],
    "sg:phone":"+1 843 723 9004",
    "sg:postcode":"29401",
    "sg:province":"SC",
    "sg:tags":[
        "sun",
        "goggles",
        "sunglasses"
    ],
    "wof:name":"Sunglass Hut",
    "wof:placetype":"venue"
},
  "geometry": {"coordinates":[-79.931438,32.780551],"type":"Point"}
}