{
  "type": "Feature",
  "properties": {
    "iso:country":"US",
    "sg:address":"71 E Dekalb St",
    "sg:city":"Camden",
    "sg:classifiers":[
        {
            "category":"Autos & Motor Vehicles",
            "subcategory":"Auto Supplies",
            "type":"Retail Goods"
        }
    ],
    "sg:phone":"+1 803 425 1885",
    "sg:postcode":"29020",
    "sg:province":"SC",
    "sg:tags":[
        "equipment",
        "electrical"
    ],
    "wof:name":"Autozone",
    "wof:placetype":"venue"
},
  "geometry": {"coordinates":[-80.593889,34.247166],"type":"Point"}
}