{
  "type": "Feature",
  "properties": {
    "addr:full":"1801 W Evans St Florence SC 29501",
    "addr:housenumber":"1801",
    "addr:postcode":"29501",
    "addr:street":"W Evans St",
    "iso:country":"US",
    "sg:address":"1801 W Evans St",
    "sg:city":"Florence",
    "sg:classifiers":[
        {
            "category":"Manufacturing",
            "subcategory":"Lumber",
            "type":"Manufacturing & Wholesale Goods"
        }
    ],
    "sg:phone":"+1 843 667 6910",
    "sg:postcode":"29501",
    "sg:province":"SC",
    "sg:tags":[
        "forester"
    ],
    "wof:name":"Dougherty & Dougherty Forest",
    "wof:placetype":"venue"
},
  "geometry": {"coordinates":[-79.800586,34.195596],"type":"Point"}
}