{
  "type": "Feature",
  "properties": {
    "addr:full":"407 Artillery Rd Taylors SC 29687",
    "addr:housenumber":"407",
    "addr:postcode":"29687",
    "addr:street":"Artillery Rd",
    "iso:country":"US",
    "sg:address":"407 Artillery Rd",
    "sg:city":"Taylors",
    "sg:classifiers":[
        {
            "category":"Wholesale",
            "subcategory":"Farm Supplies",
            "type":"Manufacturing & Wholesale Goods"
        }
    ],
    "sg:phone":"+1 864 244 3556",
    "sg:postcode":"29687",
    "sg:province":"SC",
    "sg:tags":[
        "feed"
    ],
    "wof:name":"Bartlett Milling Co",
    "wof:placetype":"venue"
},
  "geometry": {"coordinates":[-82.34141200000001,34.904892],"type":"Point"}
}