{
  "type": "Feature",
  "properties": {
    "iso:country":"US",
    "sg:address":"4440 Argent Ct",
    "sg:city":"Columbia",
    "sg:classifiers":[
        {
            "category":"Sports & Exercise",
            "subcategory":"Sports Center",
            "type":"Entertainment"
        }
    ],
    "sg:phone":"+1 803 735 1438",
    "sg:postcode":"29203",
    "sg:province":"SC",
    "sg:tags":[
        "amateur",
        "team"
    ],
    "wof:name":"Refuge Temple Family Life Center",
    "wof:placetype":"venue"
},
  "geometry": {"coordinates":[-81.031502,34.041599],"type":"Point"}
}