{
  "type": "Feature",
  "properties": {
    "iso:country":"US",
    "sg:address":"568 N Anderson Rd",
    "sg:city":"Rock Hill",
    "sg:classifiers":[
        {
            "category":"Professional",
            "subcategory":"Advertising",
            "type":"Services"
        }
    ],
    "sg:phone":"+1 803 329 7340",
    "sg:postcode":"29730",
    "sg:province":"SC",
    "wof:name":"SCINSURANCE.COM",
    "wof:placetype":"venue"
},
  "geometry": {"coordinates":[-80.997344,34.951493],"type":"Point"}
}