{
  "type": "Feature",
  "properties": {
    "addr:full":"956 E Main St Spartanburg SC 29302",
    "addr:housenumber":"956",
    "addr:postcode":"29302",
    "addr:street":"E Main St",
    "iso:country":"US",
    "sg:address":"956 E Main St",
    "sg:city":"Spartanburg",
    "sg:classifiers":[
        {
            "category":"Shopping",
            "subcategory":"Used Merchandise",
            "type":"Retail Goods"
        }
    ],
    "sg:phone":"+1 864 582 0403",
    "sg:postcode":"29302",
    "sg:province":"SC",
    "sg:tags":[
        "antique"
    ],
    "wof:name":"Rusty Gate",
    "wof:placetype":"venue"
},
  "geometry": {"coordinates":[-81.90714800000001,34.959606],"type":"Point"}
}