{
  "type": "Feature",
  "properties": {
    "iso:country":"US",
    "sg:address":"501 Oak Forest Ln",
    "sg:city":"Myrtle Beach",
    "sg:classifiers":[
        {
            "category":"Building & Trades",
            "subcategory":"Landscaping Services",
            "type":"Services"
        }
    ],
    "sg:phone":"+1 843 626 1459",
    "sg:postcode":"29577",
    "sg:province":"SC",
    "wof:name":"Tcb Tree Service",
    "wof:placetype":"venue"
},
  "geometry": {"coordinates":[-78.908434,33.701104],"type":"Point"}
}