{
  "type": "Feature",
  "properties": {
    "iso:country":"US",
    "sg:address":"104 Banner Dr",
    "sg:city":"Greenville",
    "sg:classifiers":[
        {
            "category":"Retail",
            "subcategory":"Repair Shop",
            "type":"Services"
        }
    ],
    "sg:phone":"+1 864 269 7248",
    "sg:postcode":"29611",
    "sg:province":"SC",
    "sg:tags":[
        "lock",
        "locksmith"
    ],
    "wof:name":"Motes Certified Locksmith Sale",
    "wof:placetype":"venue"
},
  "geometry": {"coordinates":[-82.453022,34.849914],"type":"Point"}
}