{
  "type": "Feature",
  "properties": {
    "addr:full":"1237 Calhoun St Newberry SC 29108",
    "addr:housenumber":"1237",
    "addr:postcode":"29108",
    "addr:street":"Calhoun St",
    "iso:country":"US",
    "sg:address":"1237 Calhoun St",
    "sg:city":"Newberry",
    "sg:classifiers":[
        {
            "category":"Communications",
            "type":"Services"
        }
    ],
    "sg:phone":"+1 803 276 5586",
    "sg:postcode":"29108",
    "sg:province":"SC",
    "wof:name":"WMC Communications LLC",
    "wof:placetype":"venue"
},
  "geometry": {"coordinates":[-81.616044,34.278279],"type":"Point"}
}