{
  "type": "Feature",
  "properties": {
    "iso:country":"US",
    "sg:address":"1352 Hayne Ave SW",
    "sg:city":"Aiken",
    "sg:classifiers":[
        {
            "category":"Shopping",
            "subcategory":"Used Merchandise",
            "type":"Retail Goods"
        }
    ],
    "sg:phone":"+1 803 642 6328",
    "sg:postcode":"29801",
    "sg:province":"SC",
    "wof:name":"Kalmia Gold & Pawn",
    "wof:placetype":"venue"
},
  "geometry": {"coordinates":[-81.737343,33.564561],"type":"Point"}
}