{
  "type": "Feature",
  "properties": {
    "iso:country":"US",
    "sg:address":"410 Hall St",
    "sg:city":"Anderson",
    "sg:classifiers":[
        {
            "category":"Organizations",
            "subcategory":"Religious Organization",
            "type":"Services"
        }
    ],
    "sg:phone":"+1 864 224 5566",
    "sg:postcode":"29624",
    "sg:province":"SC",
    "sg:tags":[
        "church"
    ],
    "wof:name":"Rock Hill Baptist Church",
    "wof:placetype":"venue"
},
  "geometry": {"coordinates":[-82.641912,34.485577],"type":"Point"}
}