{
  "type": "Feature",
  "properties": {
    "iso:country":"US",
    "sg:address":"1025 Camden Ave",
    "sg:city":"Rock Hill",
    "sg:classifiers":[
        {
            "category":"Restaurant",
            "type":"Food & Drink"
        }
    ],
    "sg:phone":"+1 803 327 9943",
    "sg:postcode":"29732",
    "sg:province":"SC",
    "sg:tags":[
        "eating"
    ],
    "wof:name":"Anna JS",
    "wof:placetype":"venue"
},
  "geometry": {"coordinates":[-81.035963,34.943424],"type":"Point"}
}