{
  "type": "Feature",
  "properties": {
    "iso:country":"US",
    "sg:address":"5775 Lartigue St",
    "sg:city":"Blackville",
    "sg:classifiers":[
        {
            "category":"Shopping",
            "subcategory":"Used Merchandise",
            "type":"Retail Goods"
        }
    ],
    "sg:phone":"+1 803 284 3670",
    "sg:postcode":"29817",
    "sg:province":"SC",
    "sg:tags":[
        "antique"
    ],
    "wof:name":"Parrott's Antiques & Gifts",
    "wof:placetype":"venue"
},
  "geometry": {"coordinates":[-81.269389,33.359126],"type":"Point"}
}