{
  "type": "Feature",
  "properties": {
    "addr:city":"Cheyenne",
    "addr:full":"616 Crook Avenue Cheyenne, Wy 82001-5420",
    "addr:house_number":"616",
    "addr:phone":"+1 307-635-8959",
    "addr:postcode":"82001-5420",
    "addr:road":"Crook Avenue",
    "addr:state":"WY",
    "iso:country":"US",
    "name:eng_x_preferred":[
        "Messengers Old West Museum",
        "Messengers Old West Museum"
    ],
    "sfomuseum:placetype":"museum",
    "wof:airports":[
        102531225
    ],
    "wof:name":"Messengers Old West Museum",
    "wof:placetype":"venue"
},
  "geometry": {"coordinates":[-104.78873,41.13201],"type":"Point"}
}