{
  "type": "Feature",
  "properties": {
    "addr:full":"4056 Byrnes Dr St Stephen SC 29479",
    "addr:housenumber":"4056",
    "addr:postcode":"29479",
    "addr:street":"Byrnes Dr",
    "iso:country":"US",
    "sg:address":"4056 Byrnes Dr",
    "sg:city":"St Stephen",
    "sg:classifiers":[
        {
            "category":"Personal",
            "subcategory":"Beauty Salon",
            "type":"Services"
        }
    ],
    "sg:phone":"+1 843 567 2937",
    "sg:postcode":"29479",
    "sg:province":"SC",
    "wof:name":"Shelby's Beauty Salon",
    "wof:placetype":"venue"
},
  "geometry": {"coordinates":[-79.93405300000001,33.411411],"type":"Point"}
}