{
  "type": "Feature",
  "properties": {
    "addr:full":"25 William Pope Dr Bluffton SC 29909",
    "addr:housenumber":"25",
    "addr:postcode":"29909",
    "addr:street":"William Pope Dr",
    "iso:country":"US",
    "sg:address":"25 William Pope Dr",
    "sg:city":"Bluffton",
    "sg:classifiers":[
        {
            "category":"Government",
            "subcategory":"Fire Station",
            "type":"Public Place"
        }
    ],
    "sg:phone":"+1 843 705 5355",
    "sg:postcode":"29909",
    "sg:province":"SC",
    "sg:tags":[
        "department"
    ],
    "wof:name":"Bluffton Township Fire Dept",
    "wof:placetype":"venue"
},
  "geometry": {"coordinates":[-80.94905,32.296858],"type":"Point"}
}