{
  "type": "Feature",
  "properties": {
    "addr:full":"80 Carolina Way Fountain Inn SC 29644",
    "addr:housenumber":"80",
    "addr:postcode":"29644",
    "addr:street":"Carolina Way",
    "iso:country":"US",
    "sg:address":"80 Carolina Way",
    "sg:city":"Fountain Inn",
    "sg:classifiers":[
        {
            "category":"Building & Trades",
            "subcategory":"Construction",
            "type":"Services"
        }
    ],
    "sg:phone":"+1 864 862 3126",
    "sg:postcode":"29644",
    "sg:province":"SC",
    "sg:tags":[
        "tile",
        "ceramic",
        "contractor"
    ],
    "wof:name":"Mahaffey Williard Wayne",
    "wof:placetype":"venue"
},
  "geometry": {"coordinates":[-82.18828600000001,34.726455],"type":"Point"}
}