{
  "type": "Feature",
  "properties": {
    "iso:country":"US",
    "sg:address":"108 Taylor St",
    "sg:city":"Aiken",
    "sg:classifiers":[
        {
            "category":"Building & Trades",
            "subcategory":"Construction",
            "type":"Services"
        }
    ],
    "sg:phone":"+1 803 648 7955",
    "sg:postcode":"29803",
    "sg:province":"SC",
    "sg:tags":[
        "house",
        "general",
        "contractor"
    ],
    "wof:name":"Findley Construction Co Inc",
    "wof:placetype":"venue"
},
  "geometry": {"coordinates":[-81.72171299999999,33.526927],"type":"Point"}
}