{
  "type": "Feature",
  "properties": {
    "addr:full":"130 Stokes Rd Simpsonville SC 29681",
    "addr:housenumber":"130",
    "addr:postcode":"29681",
    "addr:street":"Stokes Rd",
    "iso:country":"US",
    "sg:address":"130 Stokes Rd",
    "sg:city":"Simpsonville",
    "sg:classifiers":[
        {
            "category":"Organizations",
            "subcategory":"Religious Organization",
            "type":"Services"
        }
    ],
    "sg:phone":"+1 864 963 9708",
    "sg:postcode":"29681",
    "sg:province":"SC",
    "sg:tags":[
        "church"
    ],
    "wof:name":"Church Of God Simpsonville",
    "wof:placetype":"venue"
},
  "geometry": {"coordinates":[-82.263751,34.756603],"type":"Point"}
}