{
  "type": "Feature",
  "properties": {
    "addr:full":"111 Spring Hall Dr Goose Creek SC 29445",
    "addr:housenumber":"111",
    "addr:postcode":"29445",
    "addr:street":"Spring Hall Dr",
    "iso:country":"US",
    "sg:address":"111 Spring Hall Dr",
    "sg:city":"Goose Creek",
    "sg:classifiers":[
        {
            "category":"Building & Trades",
            "subcategory":"Construction",
            "type":"Services"
        }
    ],
    "sg:phone":"+1 843 552 7055",
    "sg:postcode":"29445",
    "sg:province":"SC",
    "wof:name":"CDS",
    "wof:placetype":"venue"
},
  "geometry": {"coordinates":[-80.05344700000001,33.00972],"type":"Point"}
}