{
  "type": "Feature",
  "properties": {
    "iso:country":"US",
    "sg:address":"1724 Jonesville Rd",
    "sg:city":"Simpsonville",
    "sg:classifiers":[
        {
            "category":"Building & Trades",
            "subcategory":"Construction",
            "type":"Services"
        }
    ],
    "sg:phone":"+1 864 967 9865",
    "sg:postcode":"29681",
    "sg:province":"SC",
    "sg:tags":[
        "house"
    ],
    "wof:name":"Knights Home Improvements",
    "wof:placetype":"venue"
},
  "geometry": {"coordinates":[-82.204317,34.786975],"type":"Point"}
}