{
  "type": "Feature",
  "properties": {
    "addr:full":"210 Haywood Acres Dr Easley SC 29640",
    "addr:housenumber":"210",
    "addr:postcode":"29640",
    "addr:street":"Haywood Acres Dr",
    "iso:country":"US",
    "sg:address":"210 Haywood Acres Dr",
    "sg:city":"Easley",
    "sg:classifiers":[
        {
            "category":"Wholesale",
            "subcategory":"Non-durable Goods",
            "type":"Manufacturing & Wholesale Goods"
        }
    ],
    "sg:phone":"+1 864 306 0205",
    "sg:postcode":"29640",
    "sg:province":"SC",
    "wof:name":"Bostic Distribution Inc",
    "wof:placetype":"venue"
},
  "geometry": {"coordinates":[-82.65196400000001,34.823409],"type":"Point"}
}