{
  "type": "Feature",
  "properties": {
    "iso:country":"US",
    "sg:address":"216 Old Towne Rd",
    "sg:city":"Spartanburg",
    "sg:classifiers":[
        {
            "category":"Building & Trades",
            "subcategory":"Construction",
            "type":"Services"
        }
    ],
    "sg:phone":"+1 864 574 1871",
    "sg:postcode":"29301",
    "sg:province":"SC",
    "sg:tags":[
        "house"
    ],
    "wof:name":"Builder/Automotive",
    "wof:placetype":"venue"
},
  "geometry": {"coordinates":[-82.006009,34.915067],"type":"Point"}
}