{
  "type": "Feature",
  "properties": {
    "iso:country":"US",
    "sg:address":"1605 Easley Bridge Rd",
    "sg:city":"Greenville",
    "sg:classifiers":[
        {
            "category":"Shopping",
            "subcategory":"Used Merchandise",
            "type":"Retail Goods"
        }
    ],
    "sg:phone":"+1 864 269 8342",
    "sg:postcode":"29611",
    "sg:province":"SC",
    "wof:name":"Youth Alliances of America",
    "wof:placetype":"venue"
},
  "geometry": {"coordinates":[-82.439351,34.835399],"type":"Point"}
}