{
  "type": "Feature",
  "properties": {
    "iso:country":"US",
    "sg:address":"375 W Main St",
    "sg:city":"Spartanburg",
    "sg:classifiers":[
        {
            "category":"Restaurant",
            "type":"Food & Drink"
        }
    ],
    "sg:menulink":"http://www.allmenus.com/sc/spartanburg/154844-hardees/menu/",
    "sg:phone":"+1 864 582 5810",
    "sg:postcode":"29301",
    "sg:province":"SC",
    "sg:tags":[
        "burger",
        "american"
    ],
    "wof:name":"Hardee's",
    "wof:placetype":"venue"
},
  "geometry": {"coordinates":[-81.940303,34.946684],"type":"Point"}
}