{
  "type": "Feature",
  "properties": {
    "iso:country":"US",
    "sg:address":"1460 Fording Island Rd",
    "sg:city":"Bluffton",
    "sg:classifiers":[
        {
            "category":"Shopping",
            "subcategory":"Shoes",
            "type":"Retail Goods"
        }
    ],
    "sg:phone":"+1 843 836 3304",
    "sg:postcode":"29910",
    "sg:province":"SC",
    "wof:name":"Famous Footwear",
    "wof:placetype":"venue"
},
  "geometry": {"coordinates":[-80.816593,32.240918],"type":"Point"}
}