{
  "type": "Feature",
  "properties": {
    "iso:country":"US",
    "sg:address":"5128 Pearl Dr",
    "sg:city":"Lancaster",
    "sg:classifiers":[
        {
            "category":"Building & Trades",
            "subcategory":"Construction",
            "type":"Services"
        }
    ],
    "sg:phone":"+1 803 286 5592",
    "sg:postcode":"29720",
    "sg:province":"SC",
    "sg:tags":[
        "contractor"
    ],
    "wof:name":"Wright Masonry",
    "wof:placetype":"venue"
},
  "geometry": {"coordinates":[-80.627139,34.785205],"type":"Point"}
}