{
  "type": "Feature",
  "properties": {
    "iso:country":"US",
    "sg:address":"200 Concord Rd",
    "sg:city":"Anderson",
    "sg:classifiers":[
        {
            "category":"Food & Beverages",
            "subcategory":"Groceries & Convenience Stores",
            "type":"Retail Goods"
        }
    ],
    "sg:phone":"+1 864 231 9721",
    "sg:postcode":"29621",
    "sg:province":"SC",
    "wof:name":"U Plez Stores Inc",
    "wof:placetype":"venue"
},
  "geometry": {"coordinates":[-82.661949,34.534338],"type":"Point"}
}