{
  "type": "Feature",
  "properties": {
    "addr:full":"6966 Whitcomb Dr Charleston SC 29406",
    "addr:housenumber":"6966",
    "addr:postcode":"29406",
    "addr:street":"Whitcomb Dr",
    "iso:country":"US",
    "sg:address":"6966 Whitcomb Dr",
    "sg:city":"Charleston",
    "sg:classifiers":[
        {
            "category":"Retail",
            "subcategory":"Animal Services",
            "type":"Services"
        }
    ],
    "sg:phone":"+1 843 553 7861",
    "sg:postcode":"29406",
    "sg:province":"SC",
    "wof:name":"Casa Del Cane",
    "wof:placetype":"venue"
},
  "geometry": {"coordinates":[-80.042458,32.921593],"type":"Point"}
}