{
  "type": "Feature",
  "properties": {
    "addr:full":"122 Strode Cir Clemson SC 29631",
    "addr:housenumber":"122",
    "addr:postcode":"29631",
    "addr:street":"Strode Cir",
    "iso:country":"US",
    "sg:address":"122 Strode Cir",
    "sg:city":"Clemson",
    "sg:classifiers":[
        {
            "category":"Professional",
            "subcategory":"Lawyer & Legal Services",
            "type":"Services"
        }
    ],
    "sg:phone":"+1 864 654 1669",
    "sg:postcode":"29631",
    "sg:province":"SC",
    "sg:tags":[
        "attorney"
    ],
    "wof:name":"Deal & Deal",
    "wof:placetype":"venue"
},
  "geometry": {"coordinates":[-82.83485400000001,34.688777],"type":"Point"}
}