{
  "type": "Feature",
  "properties": {
    "iso:country":"US",
    "sg:address":"3614 Ashley Phosphate Rd",
    "sg:city":"Charleston",
    "sg:classifiers":[
        {
            "category":"Autos & Motor Vehicles",
            "subcategory":"Fuel & Gas Station",
            "type":"Retail Goods"
        }
    ],
    "sg:phone":"+1 843 760 0041",
    "sg:postcode":"29418",
    "sg:province":"SC",
    "sg:tags":[
        "oil"
    ],
    "wof:name":"Speedway",
    "wof:placetype":"venue"
},
  "geometry": {"coordinates":[-80.079252,32.926973],"type":"Point"}
}