{
  "type": "Feature",
  "properties": {
    "addr:full":"112 Martin Luther King Jr Ave Kingstree SC 29556",
    "addr:housenumber":"112",
    "addr:postcode":"29556",
    "addr:street":"Martin Luther King Jr Ave",
    "iso:country":"US",
    "sg:address":"112 Martin Luther King Jr Ave",
    "sg:city":"Kingstree",
    "sg:classifiers":[
        {
            "category":"Retail",
            "subcategory":"Car Wash",
            "type":"Services"
        }
    ],
    "sg:phone":"+1 843 354 5290",
    "sg:postcode":"29556",
    "sg:province":"SC",
    "sg:tags":[
        "polishing",
        "washing"
    ],
    "wof:name":"Scott's Car Wash",
    "wof:placetype":"venue"
},
  "geometry": {"coordinates":[-79.82259999999999,33.665516],"type":"Point"}
}