{
  "type": "Feature",
  "properties": {
    "iso:country":"US",
    "sg:address":"289 State Hwy 90 E",
    "sg:city":"Little River",
    "sg:classifiers":[
        {
            "category":"Travel",
            "subcategory":"Travel Agent",
            "type":"Entertainment"
        }
    ],
    "sg:phone":"+1 843 249 3195",
    "sg:postcode":"29566",
    "sg:province":"SC",
    "sg:tags":[
        "golf",
        "vacation",
        "package"
    ],
    "wof:name":"Grand Strand Golf Assn",
    "wof:placetype":"venue"
},
  "geometry": {"coordinates":[-78.65287600000001,33.860848],"type":"Point"}
}