{
  "type": "Feature",
  "properties": {
    "iso:country":"US",
    "sg:address":"316 Morrisville Rd",
    "sg:city":"Andrews",
    "sg:classifiers":[
        {
            "category":"Retail",
            "subcategory":"Repair Shop",
            "type":"Services"
        }
    ],
    "sg:phone":"+1 843 221 5776",
    "sg:postcode":"29510",
    "sg:province":"SC",
    "sg:tags":[
        "welding"
    ],
    "wof:name":"Low Country Ind Svc",
    "wof:placetype":"venue"
},
  "geometry": {"coordinates":[-79.551682,33.521342],"type":"Point"}
}