{
  "type": "Feature",
  "properties": {
    "addr:full":"241 Stone Rd Barnwell SC 29812",
    "addr:housenumber":"241",
    "addr:postcode":"29812",
    "addr:street":"Stone Rd",
    "iso:country":"US",
    "sg:address":"241 Stone Rd",
    "sg:city":"Barnwell",
    "sg:classifiers":[
        {
            "category":"Food & Beverages",
            "subcategory":"Specialty",
            "type":"Retail Goods"
        }
    ],
    "sg:phone":"+1 803 259 2712",
    "sg:postcode":"29812",
    "sg:province":"SC",
    "wof:name":"Dak Enterprises",
    "wof:placetype":"venue"
},
  "geometry": {"coordinates":[-81.46917000000001,33.22903],"type":"Point"}
}