{
  "type": "Feature",
  "properties": {
    "addr:full":"320 N Main St Bishopville SC 29010",
    "addr:housenumber":"320",
    "addr:postcode":"29010",
    "addr:street":"N Main St",
    "iso:country":"US",
    "sg:address":"320 N Main St",
    "sg:city":"Bishopville",
    "sg:classifiers":[
        {
            "category":"Cinema",
            "subcategory":"Movie Rental",
            "type":"Entertainment"
        }
    ],
    "sg:phone":"+1 803 484 4479",
    "sg:postcode":"29010",
    "sg:province":"SC",
    "sg:tags":[
        "leasing",
        "video",
        "disc",
        "tape"
    ],
    "wof:name":"Movie Gallery",
    "wof:placetype":"venue"
},
  "geometry": {"coordinates":[-80.24484,34.220892],"type":"Point"}
}