{
  "type": "Feature",
  "properties": {
    "iso:country":"US",
    "sg:address":"719 S Howard Ave",
    "sg:city":"Landrum",
    "sg:classifiers":[
        {
            "category":"Professional",
            "subcategory":"Lawyer & Legal Services",
            "type":"Services"
        }
    ],
    "sg:phone":"+1 864 457 2222",
    "sg:postcode":"29356",
    "sg:province":"SC",
    "sg:tags":[
        "attorney"
    ],
    "wof:name":"Howard Law Firm",
    "wof:placetype":"venue"
},
  "geometry": {"coordinates":[-82.18271,35.165085],"type":"Point"}
}