{
  "type": "Feature",
  "properties": {
    "addr:full":"616 N Limestone St Gaffney SC 29340",
    "addr:housenumber":"616",
    "addr:postcode":"29340",
    "addr:street":"N Limestone St",
    "iso:country":"US",
    "sg:address":"616 N Limestone St",
    "sg:city":"Gaffney",
    "sg:classifiers":[
        {
            "category":"Shopping",
            "subcategory":"Used Merchandise",
            "type":"Retail Goods"
        }
    ],
    "sg:phone":"+1 864 489 4668",
    "sg:postcode":"29340",
    "sg:province":"SC",
    "sg:tags":[
        "antique"
    ],
    "wof:name":"Pieces From The Past",
    "wof:placetype":"venue"
},
  "geometry": {"coordinates":[-81.644946,35.077739],"type":"Point"}
}