{
  "type": "Feature",
  "properties": {
    "iso:country":"US",
    "sg:address":"8542 Raccoon Island Rd",
    "sg:city":"Edisto Island",
    "sg:classifiers":[
        {
            "category":"Professional",
            "subcategory":"Accounting & Tax Preparation",
            "type":"Services"
        }
    ],
    "sg:phone":"+1 843 869 4128",
    "sg:postcode":"29438",
    "sg:province":"SC",
    "sg:tags":[
        "bookkeeping",
        "general"
    ],
    "wof:name":"Island Images",
    "wof:placetype":"venue"
},
  "geometry": {"coordinates":[-80.365574,32.569788],"type":"Point"}
}