{
  "type": "Feature",
  "properties": {
    "iso:country":"US",
    "sg:address":"125 S Main St",
    "sg:city":"Lancaster",
    "sg:classifiers":[
        {
            "category":"Insurance",
            "subcategory":"Insurance Agent",
            "type":"Services"
        }
    ],
    "sg:phone":"+1 803 289 6523",
    "sg:postcode":"29720",
    "sg:province":"SC",
    "wof:name":"Alpine Agency",
    "wof:placetype":"venue"
},
  "geometry": {"coordinates":[-80.770481,34.719946],"type":"Point"}
}