{
  "type": "Feature",
  "properties": {
    "iso:country":"US",
    "sg:address":"76 Allen St",
    "sg:city":"Greenville",
    "sg:classifiers":[
        {
            "category":"Organizations",
            "subcategory":"Religious Organization",
            "type":"Services"
        }
    ],
    "sg:phone":"+1 864 269 6500",
    "sg:postcode":"29605",
    "sg:province":"SC",
    "sg:tags":[
        "church"
    ],
    "wof:name":"Holy Ground Chr Of Deliverance",
    "wof:placetype":"venue"
},
  "geometry": {"coordinates":[-82.422917,34.822012],"type":"Point"}
}