{
  "type": "Feature",
  "properties": {
    "addr:full":"8800 Northpark Blvd North Charleston SC 29406",
    "addr:housenumber":"8800",
    "addr:postcode":"29406",
    "addr:street":"Northpark Blvd",
    "iso:country":"US",
    "sg:address":"8800 Northpark Blvd",
    "sg:city":"North Charleston",
    "sg:classifiers":[
        {
            "category":"Organizations",
            "subcategory":"Professional Association",
            "type":"Services"
        }
    ],
    "sg:phone":"+1 843 572 1414",
    "sg:postcode":"29406",
    "sg:province":"SC",
    "sg:website":"www.cthba.org",
    "wof:name":"Charleston Trident Home Bldrs",
    "wof:placetype":"venue"
},
  "geometry": {"coordinates":[-80.042953,32.967771],"type":"Point"}
}