{
  "type": "Feature",
  "properties": {
    "addr:full":"927 Elmwood Ave Columbia SC 29201",
    "addr:housenumber":"927",
    "addr:postcode":"29201",
    "addr:street":"Elmwood Ave",
    "iso:country":"US",
    "sg:address":"927 Elmwood Ave",
    "sg:city":"Columbia",
    "sg:classifiers":[
        {
            "category":"Retail",
            "subcategory":"Auto Repair",
            "type":"Services"
        }
    ],
    "sg:phone":"+1 803 779 3445",
    "sg:postcode":"29201",
    "sg:province":"SC",
    "sg:tags":[
        "automobile",
        "lubrication"
    ],
    "wof:name":"Texaco Xpress Lube",
    "wof:placetype":"venue"
},
  "geometry": {"coordinates":[-81.042768,34.012249],"type":"Point"}
}