{
  "type": "Feature",
  "properties": {
    "iso:country":"US",
    "sg:address":"3025 Ashley Phosphate Rd",
    "sg:city":"North Charleston",
    "sg:classifiers":[
        {
            "category":"Shopping",
            "subcategory":"Gifts & Souvenirs",
            "type":"Retail Goods"
        }
    ],
    "sg:phone":"+1 843 767 9400",
    "sg:postcode":"29418",
    "sg:province":"SC",
    "sg:tags":[
        "shop"
    ],
    "wof:name":"Charleston Gifts & Collectible",
    "wof:placetype":"venue"
},
  "geometry": {"coordinates":[-80.06167499999999,32.931243],"type":"Point"}
}