{
  "type": "Feature",
  "properties": {
    "iso:country":"US",
    "sg:address":"15195 Wells Hwy",
    "sg:city":"Seneca",
    "sg:classifiers":[
        {
            "category":"Organizations",
            "subcategory":"Religious Organization",
            "type":"Services"
        }
    ],
    "sg:phone":"+1 864 888 0703",
    "sg:postcode":"29678",
    "sg:province":"SC",
    "sg:tags":[
        "church"
    ],
    "wof:name":"Grace Baptist Church",
    "wof:placetype":"venue"
},
  "geometry": {"coordinates":[-82.990951,34.685707],"type":"Point"}
}