{
  "type": "Feature",
  "properties": {
    "addr:full":"110 Centre St Orangeburg SC 29115",
    "addr:housenumber":"110",
    "addr:postcode":"29115",
    "addr:street":"Centre St",
    "iso:country":"US",
    "sg:address":"110 Centre St",
    "sg:city":"Orangeburg",
    "sg:classifiers":[
        {
            "category":"Organizations",
            "subcategory":"Community Association",
            "type":"Services"
        }
    ],
    "sg:phone":"+1 803 515 9758",
    "sg:postcode":"29115",
    "sg:province":"SC",
    "sg:tags":[
        "club"
    ],
    "wof:name":"Paragon",
    "wof:placetype":"venue"
},
  "geometry": {"coordinates":[-80.86151700000001,33.493039],"type":"Point"}
}