{
  "type": "Feature",
  "properties": {
    "iso:country":"US",
    "sg:address":"601 Riverhill Circle",
    "sg:city":"Columbia",
    "sg:classifiers":[
        {
            "category":"Professional",
            "type":"Services"
        },
        {
            "category":"Restaurant",
            "type":"Food & Drink"
        }
    ],
    "sg:phone":"+1 803 665 9245",
    "sg:postcode":"29210",
    "sg:province":"SC",
    "sg:tags":[
        "caterer"
    ],
    "sg:website":"www.occasionsbycandice.vpweb.com",
    "wof:name":"Occasions by Candice",
    "wof:placetype":"venue"
},
  "geometry": {"coordinates":[-81.07326999999999,34.022855],"type":"Point"}
}