{
  "type": "Feature",
  "properties": {
    "addr:full":"6 Dutchman Ct Great Falls SC 29037",
    "addr:housenumber":"6",
    "addr:postcode":"29037",
    "addr:street":"Dutchman Ct",
    "iso:country":"US",
    "sg:address":"6 Dutchman Ct",
    "sg:city":"Great Falls",
    "sg:classifiers":[
        {
            "category":"Government",
            "subcategory":"Police Station",
            "type":"Public Place"
        }
    ],
    "sg:phone":"+1 803 482 6837",
    "sg:postcode":"29037",
    "sg:province":"SC",
    "sg:tags":[
        "sheriff"
    ],
    "wof:name":"Fairfield County Sheriff Dept",
    "wof:placetype":"venue"
},
  "geometry": {"coordinates":[-81.922656,34.199033],"type":"Point"}
}