{
  "type": "Feature",
  "properties": {
    "addr:full":"18 Dudley Rd Roebuck SC 29376",
    "addr:housenumber":"18",
    "addr:postcode":"29376",
    "addr:street":"Dudley Rd",
    "iso:country":"US",
    "sg:address":"18 Dudley Rd",
    "sg:city":"Roebuck",
    "sg:classifiers":[
        {
            "category":"Manufacturing",
            "subcategory":"Apparel",
            "type":"Manufacturing & Wholesale Goods"
        }
    ],
    "sg:phone":"+1 864 587 8400",
    "sg:postcode":"29376",
    "sg:province":"SC",
    "sg:tags":[
        "sewing",
        "contractor"
    ],
    "wof:name":"S & D Sewing",
    "wof:placetype":"venue"
},
  "geometry": {"coordinates":[-81.965608,34.912428],"type":"Point"}
}