{
  "type": "Feature",
  "properties": {
    "addr:full":"2887 Murraywood Rd Johns Island SC 29455",
    "addr:housenumber":"2887",
    "addr:postcode":"29455",
    "addr:street":"Murraywood Rd",
    "iso:country":"US",
    "sg:address":"2887 Murraywood Rd",
    "sg:city":"Johns Island",
    "sg:classifiers":[
        {
            "category":"Professional",
            "subcategory":"Engineering",
            "type":"Services"
        },
        {
            "category":"Wholesale",
            "subcategory":"Machinery & Supplies",
            "type":"Manufacturing & Wholesale Goods"
        }
    ],
    "sg:phone":"+1 843 559 2205",
    "sg:postcode":"29455",
    "sg:province":"SC",
    "sg:tags":[
        "specializing",
        "equipment",
        "irrigation",
        "system"
    ],
    "wof:name":"Coastal Irrigation & Supply Co",
    "wof:placetype":"venue"
},
  "geometry": {"coordinates":[-80.05260800000001,32.750585],"type":"Point"}
}