{
  "type": "Feature",
  "properties": {
    "iso:country":"US",
    "sg:address":"2267 Pristine View Rd",
    "sg:city":"Charleston",
    "sg:classifiers":[
        {
            "category":"Shopping",
            "subcategory":"Computers & Home Electronics",
            "type":"Retail Goods"
        }
    ],
    "sg:phone":"+1 843 766 8970",
    "sg:postcode":"29414",
    "sg:province":"SC",
    "sg:tags":[
        "software"
    ],
    "wof:name":"Quantum Technologies",
    "wof:placetype":"venue"
},
  "geometry": {"coordinates":[-80.043755,32.787731],"type":"Point"}
}