{
  "type": "Feature",
  "properties": {
    "iso:country":"US",
    "sg:address":"1132 Pineview Dr",
    "sg:city":"Columbia",
    "sg:classifiers":[
        {
            "category":"Retail",
            "subcategory":"Repair Shop",
            "type":"Services"
        }
    ],
    "sg:phone":"+1 803 783 6677",
    "sg:postcode":"29209",
    "sg:province":"SC",
    "sg:tags":[
        "refinishing",
        "furniture"
    ],
    "wof:name":"Furniture Restorations",
    "wof:placetype":"venue"
},
  "geometry": {"coordinates":[-80.961251,33.930428],"type":"Point"}
}