{
  "type": "Feature",
  "properties": {
    "addr:full":"1685 Busbee Rd Gaston SC 29053",
    "addr:housenumber":"1685",
    "addr:postcode":"29053",
    "addr:street":"Busbee Rd",
    "iso:country":"US",
    "sg:address":"1685 Busbee Rd",
    "sg:city":"Gaston",
    "sg:classifiers":[
        {
            "category":"Freight",
            "type":"Transportation"
        }
    ],
    "sg:phone":"+1 803 794 9356",
    "sg:postcode":"29053",
    "sg:province":"SC",
    "sg:tags":[
        "operator",
        "trucking"
    ],
    "wof:name":"Maranatha Transport LLC",
    "wof:placetype":"venue"
},
  "geometry": {"coordinates":[-81.09415300000001,33.854765],"type":"Point"}
}