{
  "type": "Feature",
  "properties": {
    "iso:country":"US",
    "sg:address":"420 W Cheves St",
    "sg:city":"Florence",
    "sg:classifiers":[
        {
            "category":"Real Estate",
            "subcategory":"Real Estate Agent",
            "type":"Services"
        }
    ],
    "sg:phone":"+1 843 669 2848",
    "sg:postcode":"29501",
    "sg:province":"SC",
    "wof:name":"Inland Realty",
    "wof:placetype":"venue"
},
  "geometry": {"coordinates":[-79.774322,34.195075],"type":"Point"}
}