{
  "type": "Feature",
  "properties": {
    "iso:country":"US",
    "sg:address":"1089 Howard Pkwy",
    "sg:city":"Myrtle Beach",
    "sg:classifiers":[
        {
            "category":"Professional",
            "type":"Services"
        }
    ],
    "sg:phone":"+1 843 238 4878",
    "sg:postcode":"29577",
    "sg:province":"SC",
    "sg:tags":[
        "establishment"
    ],
    "wof:name":"T N & Assoc",
    "wof:placetype":"venue"
},
  "geometry": {"coordinates":[-78.939115,33.666894],"type":"Point"}
}