{
  "type": "Feature",
  "properties": {
    "iso:country":"US",
    "sg:address":"106 Broad St",
    "sg:city":"Bennettsville",
    "sg:classifiers":[
        {
            "category":"Shopping",
            "subcategory":"Clothing, Apparel, & Fashions",
            "type":"Retail Goods"
        }
    ],
    "sg:phone":"+1 843 479 8180",
    "sg:postcode":"29512",
    "sg:province":"SC",
    "sg:tags":[
        "design"
    ],
    "wof:name":"Fits Clothing",
    "wof:placetype":"venue"
},
  "geometry": {"coordinates":[-79.684331,34.616331],"type":"Point"}
}