{
  "type": "Feature",
  "properties": {
    "iso:country":"US",
    "sg:address":"1212 Windsor Rd",
    "sg:city":"Florence",
    "sg:classifiers":[
        {
            "category":"Professional",
            "subcategory":"Credit Reporting & Collection",
            "type":"Services"
        }
    ],
    "sg:phone":"+1 843 673 0105",
    "sg:postcode":"29505",
    "sg:province":"SC",
    "sg:tags":[
        "real estate"
    ],
    "wof:name":"Rental Property Owners Network",
    "wof:placetype":"venue"
},
  "geometry": {"coordinates":[-79.790882,34.159282],"type":"Point"}
}