{
  "type": "Feature",
  "properties": {
    "iso:country":"US",
    "sg:address":"4637 Augusta Rd",
    "sg:city":"Lexington",
    "sg:classifiers":[
        {
            "category":"Retail",
            "subcategory":"Auto Rental",
            "type":"Services"
        }
    ],
    "sg:phone":"+1 803 951 0612",
    "sg:postcode":"29073",
    "sg:province":"SC",
    "sg:tags":[
        "car"
    ],
    "wof:name":"Heritage Motors Llc",
    "wof:placetype":"venue"
},
  "geometry": {"coordinates":[-81.173912,33.974923],"type":"Point"}
}