{
  "type": "Feature",
  "properties": {
    "addr:full":"1194 Tirzah Rd Rock Hill SC 29732",
    "addr:housenumber":"1194",
    "addr:postcode":"29732",
    "addr:street":"Tirzah Rd",
    "iso:country":"US",
    "sg:address":"1194 Tirzah Rd",
    "sg:city":"Rock Hill",
    "sg:classifiers":[
        {
            "category":"Building & Trades",
            "subcategory":"Plumbing",
            "type":"Services"
        }
    ],
    "sg:phone":"+1 803 366 7082",
    "sg:postcode":"29732",
    "sg:province":"SC",
    "sg:tags":[
        "contractor"
    ],
    "wof:name":"Butchs Plumbing Service",
    "wof:placetype":"venue"
},
  "geometry": {"coordinates":[-81.134176,34.960141],"type":"Point"}
}