{
  "type": "Feature",
  "properties": {
    "addr:full":"105 Dreher Rd West Columbia SC 29169",
    "addr:housenumber":"105",
    "addr:postcode":"29169",
    "addr:street":"Dreher Rd",
    "iso:country":"US",
    "sg:address":"105 Dreher Rd",
    "sg:city":"West Columbia",
    "sg:classifiers":[
        {
            "category":"Wholesale",
            "subcategory":"Machinery & Supplies",
            "type":"Manufacturing & Wholesale Goods"
        }
    ],
    "sg:phone":"+1 803 926 2201",
    "sg:postcode":"29169",
    "sg:province":"SC",
    "sg:tags":[
        "industrial",
        "contractor",
        "special",
        "trade"
    ],
    "wof:name":"Precision Window Tinting Inc",
    "wof:placetype":"venue"
},
  "geometry": {"coordinates":[-81.094284,33.98059],"type":"Point"}
}