{
  "type": "Feature",
  "properties": {
    "iso:country":"US",
    "sg:address":"1668 Old Towne Rd",
    "sg:city":"Charleston",
    "sg:classifiers":[
        {
            "category":"Restaurant",
            "type":"Food & Drink"
        }
    ],
    "sg:phone":"+1 843 556 2478",
    "sg:postcode":"29407",
    "sg:province":"SC",
    "wof:name":"T-Bonz Gill & Grill",
    "wof:placetype":"venue"
},
  "geometry": {"coordinates":[-79.992899,32.818285],"type":"Point"}
}