{
  "type": "Feature",
  "properties": {
    "addr:full":"2728 Sunset Blvd West Columbia SC 29169",
    "addr:housenumber":"2728",
    "addr:postcode":"29169",
    "addr:street":"Sunset Blvd",
    "iso:country":"US",
    "sg:address":"2728 Sunset Blvd",
    "sg:city":"West Columbia",
    "sg:classifiers":[
        {
            "category":"Health Services",
            "subcategory":"Doctor",
            "type":"Services"
        }
    ],
    "sg:phone":"+1 803 794 7511",
    "sg:postcode":"29169",
    "sg:province":"SC",
    "sg:website":"www.lexonc.com",
    "wof:name":"Madden Steven A MD",
    "wof:placetype":"venue"
},
  "geometry": {"coordinates":[-81.085503,33.997799],"type":"Point"}
}