{
  "type": "Feature",
  "properties": {
    "iso:country":"US",
    "sg:address":"4717 US Hwy 17 Bus",
    "sg:city":"Myrtle Beach",
    "sg:classifiers":[
        {
            "category":"Health Services",
            "subcategory":"Clinic",
            "type":"Services"
        }
    ],
    "sg:phone":"+1 843 293 2963",
    "sg:postcode":"29577",
    "sg:province":"SC",
    "sg:tags":[
        "home"
    ],
    "wof:name":"In Care Homemakers Inc",
    "wof:placetype":"venue"
},
  "geometry": {"coordinates":[-78.847904,33.722691],"type":"Point"}
}