{
  "type": "Feature",
  "properties": {
    "addr:full":"8801 Monticello Rd Columbia SC 29203",
    "addr:housenumber":"8801",
    "addr:postcode":"29203",
    "addr:street":"Monticello Rd",
    "iso:country":"US",
    "sg:address":"8801 Monticello Rd",
    "sg:city":"Columbia",
    "sg:classifiers":[
        {
            "category":"Restaurant",
            "type":"Food & Drink"
        }
    ],
    "sg:phone":"+1 803 754 4578",
    "sg:postcode":"29203",
    "sg:province":"SC",
    "sg:tags":[
        "eating"
    ],
    "wof:name":"The Deaver Diner",
    "wof:placetype":"venue"
},
  "geometry": {"coordinates":[-81.086538,34.121041],"type":"Point"}
}