{
  "type": "Feature",
  "properties": {
    "iso:country":"US",
    "sg:address":"1106 Green Fern Dr",
    "sg:city":"Greenville",
    "sg:classifiers":[
        {
            "category":"Shopping",
            "subcategory":"Bicycles & Sporting Goods",
            "type":"Retail Goods"
        }
    ],
    "sg:phone":"+1 864 246 1651",
    "sg:postcode":"29611",
    "sg:province":"SC",
    "wof:name":"Flying Tgers Sport Prchute Ctr",
    "wof:placetype":"venue"
},
  "geometry": {"coordinates":[-82.47611499999999,34.870785],"type":"Point"}
}