{
  "type": "Feature",
  "properties": {
    "iso:country":"US",
    "sg:address":"1307 E Calhoun Rd",
    "sg:city":"Belton",
    "sg:classifiers":[
        {
            "category":"Wholesale",
            "subcategory":"Plants",
            "type":"Manufacturing & Wholesale Goods"
        }
    ],
    "sg:phone":"+1 864 338 6723",
    "sg:postcode":"29627",
    "sg:province":"SC",
    "sg:tags":[
        "supply"
    ],
    "wof:name":"Diannes Flower Shop",
    "wof:placetype":"venue"
},
  "geometry": {"coordinates":[-82.460405,34.526609],"type":"Point"}
}