{
  "type": "Feature",
  "properties": {
    "iso:country":"US",
    "sg:address":"1060 Pineland St SE",
    "sg:city":"Orangeburg",
    "sg:classifiers":[
        {
            "category":"Government",
            "subcategory":"Office",
            "type":"Public Place"
        }
    ],
    "sg:phone":"+1 803 533 5871",
    "sg:postcode":"29115",
    "sg:province":"SC",
    "wof:name":"Orangeburg Development Ctr",
    "wof:placetype":"venue"
},
  "geometry": {"coordinates":[-80.838942,33.482464],"type":"Point"}
}