{
  "type": "Feature",
  "properties": {
    "iso:country":"US",
    "sg:address":"452 Hemingford Grey",
    "sg:city":"Fort Mill",
    "sg:classifiers":[
        {
            "category":"Banks & Credit Unions",
            "subcategory":"Bank",
            "type":"Services"
        }
    ],
    "sg:phone":"+1 803 547 0216",
    "sg:postcode":"29708",
    "sg:province":"SC",
    "sg:tags":[
        "loan",
        "real estate"
    ],
    "wof:name":"Berry & Assoc",
    "wof:placetype":"venue"
},
  "geometry": {"coordinates":[-80.956429,35.076931],"type":"Point"}
}