{
  "type": "Feature",
  "properties": {
    "addr:full":"3 Shelter Cove Ln Hilton Head Isle SC 29928",
    "addr:housenumber":"3",
    "addr:postcode":"29928",
    "addr:street":"Shelter Cove Ln",
    "iso:country":"US",
    "sg:address":"3 Shelter Cove Ln",
    "sg:city":"Hilton Head Isle",
    "sg:classifiers":[
        {
            "category":"Shopping",
            "subcategory":"Gifts & Souvenirs",
            "type":"Retail Goods"
        }
    ],
    "sg:phone":"+1 843 842 3666",
    "sg:postcode":"29928",
    "sg:province":"SC",
    "wof:name":"Camp Hilton Head",
    "wof:placetype":"venue"
},
  "geometry": {"coordinates":[-80.733762,32.179962],"type":"Point"}
}