{
  "type": "Feature",
  "properties": {
    "addr:full":"915 Lady Street Columbia SC 29210",
    "addr:housenumber":"915",
    "addr:postcode":"29210",
    "addr:street":"Lady Street",
    "iso:country":"US",
    "sg:address":"915 Lady Street",
    "sg:city":"Columbia",
    "sg:classifiers":[
        {
            "category":"Professional",
            "subcategory":"Advertising",
            "type":"Services"
        }
    ],
    "sg:phone":"+1 803 588 9310",
    "sg:postcode":"29210",
    "sg:province":"SC",
    "sg:tags":[
        "website-design",
        "email-marketing-software",
        "content-management-software",
        "web-based-software"
    ],
    "sg:website":"http://www.period-three.com",
    "wof:name":"Period Three",
    "wof:placetype":"venue"
},
  "geometry": {"coordinates":[-81.038078,34.001428],"type":"Point"}
}