{
  "type": "Feature",
  "properties": {
    "addr:full":"1239 Boiling Springs Rd Spartanburg SC 29303",
    "addr:housenumber":"1239",
    "addr:postcode":"29303",
    "addr:street":"Boiling Springs Rd",
    "iso:country":"US",
    "sg:address":"1239 Boiling Springs Rd",
    "sg:city":"Spartanburg",
    "sg:classifiers":[
        {
            "category":"Personal",
            "subcategory":"Beauty Salon",
            "type":"Services"
        }
    ],
    "sg:phone":"+1 864 585 4247",
    "sg:postcode":"29303",
    "sg:province":"SC",
    "wof:name":"Hair Stop",
    "wof:placetype":"venue"
},
  "geometry": {"coordinates":[-81.946496,34.989052],"type":"Point"}
}