{
  "type": "Feature",
  "properties": {
    "iso:country":"US",
    "sg:address":"102 E Butler Rd",
    "sg:city":"Mauldin",
    "sg:classifiers":[
        {
            "category":"Building & Trades",
            "subcategory":"Plumbing",
            "type":"Services"
        }
    ],
    "sg:phone":"+1 864 288 4231",
    "sg:postcode":"29662",
    "sg:province":"SC",
    "sg:tags":[
        "plumbing",
        "contractor"
    ],
    "wof:name":"L S Green Plumbing Co Inc",
    "wof:placetype":"venue"
},
  "geometry": {"coordinates":[-82.30155000000001,34.780739],"type":"Point"}
}