{
  "type": "Feature",
  "properties": {
    "addr:full":"1630 Camp Rd Charleston SC 29412",
    "addr:housenumber":"1630",
    "addr:postcode":"29412",
    "addr:street":"Camp Rd",
    "iso:country":"US",
    "sg:address":"1630 Camp Rd",
    "sg:city":"Charleston",
    "sg:classifiers":[
        {
            "category":"Recreation",
            "type":"Entertainment"
        }
    ],
    "sg:phone":"+1 843 762 6580",
    "sg:postcode":"29412",
    "sg:province":"SC",
    "sg:tags":[
        "martial",
        "arts",
        "instruction"
    ],
    "wof:name":"East West Health Arts",
    "wof:placetype":"venue"
},
  "geometry": {"coordinates":[-79.968746,32.734342],"type":"Point"}
}