{
  "type": "Feature",
  "properties": {
    "iso:country":"US",
    "sg:address":"102 Harpers Row",
    "sg:city":"Summerville",
    "sg:classifiers":[
        {
            "category":"Real Estate",
            "subcategory":"Real Estate Agent",
            "type":"Services"
        }
    ],
    "sg:phone":"+1 843 821 4000",
    "sg:postcode":"29483",
    "sg:province":"SC",
    "wof:name":"Coastal Commercial Realty",
    "wof:placetype":"venue"
},
  "geometry": {"coordinates":[-80.190186,33.026518],"type":"Point"}
}