{
  "type": "Feature",
  "properties": {
    "iso:country":"US",
    "sg:address":"1034 Jefferson Davis Hwy",
    "sg:city":"Graniteville",
    "sg:classifiers":[
        {
            "category":"Manufacturing",
            "subcategory":"Signs",
            "type":"Manufacturing & Wholesale Goods"
        }
    ],
    "sg:phone":"+1 803 593 9551",
    "sg:postcode":"29829",
    "sg:province":"SC",
    "wof:name":"Mixon Sign Co",
    "wof:placetype":"venue"
},
  "geometry": {"coordinates":[-81.808138,33.55504],"type":"Point"}
}