{
  "type": "Feature",
  "properties": {
    "iso:country":"US",
    "sg:address":"8 Lake Selisa Dr",
    "sg:city":"North Augusta",
    "sg:classifiers":[
        {
            "category":"Building & Trades",
            "subcategory":"Electrical",
            "type":"Services"
        }
    ],
    "sg:phone":"+1 803 279 1029",
    "sg:postcode":"29860",
    "sg:province":"SC",
    "sg:tags":[
        "fiber",
        "optic",
        "installs",
        "communication",
        "system",
        "design"
    ],
    "wof:name":"Pro Fiber Inc",
    "wof:placetype":"venue"
},
  "geometry": {"coordinates":[-81.977422,33.555699],"type":"Point"}
}