{
  "type": "Feature",
  "properties": {
    "iso:country":"US",
    "sg:address":"1130 Pleasant Oaks Dr",
    "sg:city":"Mt Pleasant",
    "sg:classifiers":[
        {
            "category":"Travel",
            "subcategory":"Hotels & Motels",
            "type":"Entertainment"
        }
    ],
    "sg:phone":"+1 843 216 0004",
    "sg:postcode":"29464",
    "sg:province":"SC",
    "sg:website":"www.comfortsuites.com",
    "wof:name":"Comfort Inn",
    "wof:placetype":"venue"
},
  "geometry": {"coordinates":[-79.854759,32.801847],"type":"Point"}
}