{
  "type": "Feature",
  "properties": {
    "iso:country":"US",
    "sg:address":"6740 Liberty Hwy",
    "sg:city":"Pendleton",
    "sg:classifiers":[
        {
            "category":"Real Estate",
            "subcategory":"Real Estate Agent",
            "type":"Services"
        }
    ],
    "sg:phone":"+1 864 261 6775",
    "sg:postcode":"29670",
    "sg:province":"SC",
    "wof:name":"Ricky L Cushman",
    "wof:placetype":"venue"
},
  "geometry": {"coordinates":[-82.702758,34.654362],"type":"Point"}
}