{
  "type": "Feature",
  "properties": {
    "iso:country":"US",
    "sg:address":"8700 Black River Rd",
    "sg:city":"Rembert",
    "sg:classifiers":[
        {
            "category":"Building & Trades",
            "subcategory":"Plumbing",
            "type":"Services"
        }
    ],
    "sg:phone":"+1 803 425 4453",
    "sg:postcode":"29128",
    "sg:province":"SC",
    "sg:tags":[
        "conditioning",
        "air",
        "system",
        "contractor"
    ],
    "wof:name":"Olin's Heating & Air Cond",
    "wof:placetype":"venue"
},
  "geometry": {"coordinates":[-80.492729,34.152406],"type":"Point"}
}