{
  "type": "Feature",
  "properties": {
    "iso:country":"US",
    "sg:address":"2988 W Montague Ave",
    "sg:city":"North Charleston",
    "sg:classifiers":[
        {
            "category":"Restaurant",
            "type":"Food & Drink"
        }
    ],
    "sg:phone":"+1 843 744 0626",
    "sg:postcode":"29418",
    "sg:province":"SC",
    "wof:name":"Mc Donald's",
    "wof:placetype":"venue"
},
  "geometry": {"coordinates":[-80.01302099999999,32.867879],"type":"Point"}
}