{
  "type": "Feature",
  "properties": {
    "iso:country":"US",
    "sg:address":"1304 Mc Lees Rd",
    "sg:city":"Anderson",
    "sg:classifiers":[
        {
            "category":"Social Services",
            "subcategory":"Adult Care",
            "type":"Services"
        }
    ],
    "sg:phone":"+1 864 964 9088",
    "sg:postcode":"29621",
    "sg:province":"SC",
    "sg:tags":[
        "home",
        "residential"
    ],
    "wof:name":"Morningside Of Anderson",
    "wof:placetype":"venue"
},
  "geometry": {"coordinates":[-82.628998,34.526529],"type":"Point"}
}