{
  "type": "Feature",
  "properties": {
    "addr:full":"432 Calhoun Ave Greenwood SC 29649",
    "addr:housenumber":"432",
    "addr:postcode":"29649",
    "addr:street":"Calhoun Ave",
    "iso:country":"US",
    "sg:address":"432 Calhoun Ave",
    "sg:city":"Greenwood",
    "sg:classifiers":[
        {
            "category":"Retail",
            "subcategory":"Car Wash",
            "type":"Services"
        }
    ],
    "sg:phone":"+1 864 223 6535",
    "sg:postcode":"29649",
    "sg:province":"SC",
    "sg:tags":[
        "polishing",
        "washing"
    ],
    "wof:name":"Frank's Car Wash & Fast Lube",
    "wof:placetype":"venue"
},
  "geometry": {"coordinates":[-82.169057,34.197386],"type":"Point"}
}