{
  "type": "Feature",
  "properties": {
    "iso:country":"US",
    "sg:address":"414 Center St",
    "sg:city":"West Columbia",
    "sg:classifiers":[
        {
            "category":"Social Services",
            "type":"Services"
        }
    ],
    "sg:phone":"+1 803 796 9332",
    "sg:postcode":"29169",
    "sg:province":"SC",
    "sg:tags":[
        "agency",
        "adoption"
    ],
    "wof:name":"Bethany Christian Svc",
    "wof:placetype":"venue"
},
  "geometry": {"coordinates":[-81.057698,33.99314],"type":"Point"}
}