{
  "type": "Feature",
  "properties": {
    "addr:full":"1241 Green Sea Rd Green Sea SC 29545",
    "addr:housenumber":"1241",
    "addr:postcode":"29545",
    "addr:street":"Green Sea Rd",
    "iso:country":"US",
    "sg:address":"1241 Green Sea Rd",
    "sg:city":"Green Sea",
    "sg:classifiers":[
        {
            "category":"Organizations",
            "subcategory":"Religious Organization",
            "type":"Services"
        }
    ],
    "sg:phone":"+1 843 756 2363",
    "sg:postcode":"29545",
    "sg:province":"SC",
    "sg:tags":[
        "church"
    ],
    "wof:name":"Green Sea Baptist Church",
    "wof:placetype":"venue"
},
  "geometry": {"coordinates":[-78.975644,34.127738],"type":"Point"}
}