{
  "type": "Feature",
  "properties": {
    "iso:country":"US",
    "sg:address":"98 Riverwalk Way",
    "sg:city":"Irmo",
    "sg:classifiers":[
        {
            "category":"Building & Trades",
            "subcategory":"Construction",
            "type":"Services"
        }
    ],
    "sg:phone":"+1 803 781 2008",
    "sg:postcode":"29063",
    "sg:province":"SC",
    "sg:tags":[
        "hanging",
        "contractor"
    ],
    "wof:name":"Palmetto Decorators Inc",
    "wof:placetype":"venue"
},
  "geometry": {"coordinates":[-81.1537,34.092804],"type":"Point"}
}