{
  "type": "Feature",
  "properties": {
    "iso:country":"US",
    "sg:address":"2066 Black Tom Rd",
    "sg:city":"Moncks Corner",
    "sg:classifiers":[
        {
            "category":"Retail",
            "subcategory":"Auto Repair",
            "type":"Services"
        }
    ],
    "sg:phone":"+1 843 688 6006",
    "sg:postcode":"29461",
    "sg:province":"SC",
    "sg:tags":[
        "truck"
    ],
    "wof:name":"Alonzo's Truck Repair",
    "wof:placetype":"venue"
},
  "geometry": {"coordinates":[-80.143027,33.143396],"type":"Point"}
}