{
  "type": "Feature",
  "properties": {
    "iso:country":"US",
    "sg:address":"1011 Saint Andrews Blvd",
    "sg:city":"Charleston",
    "sg:classifiers":[
        {
            "category":"Shopping",
            "subcategory":"Used Merchandise",
            "type":"Retail Goods"
        }
    ],
    "sg:phone":"+1 843 571 3389",
    "sg:postcode":"29407",
    "sg:province":"SC",
    "wof:name":"Architectural Elements",
    "wof:placetype":"venue"
},
  "geometry": {"coordinates":[-79.991056,32.793568],"type":"Point"}
}