{
  "type": "Feature",
  "properties": {
    "addr:full":"330 Augusta Rd North Augusta SC 29822",
    "addr:housenumber":"330",
    "addr:postcode":"29822",
    "addr:street":"Augusta Rd",
    "iso:country":"US",
    "sg:address":"330 Augusta Rd",
    "sg:city":"North Augusta",
    "sg:classifiers":[
        {
            "category":"Manufacturing",
            "subcategory":"Printing",
            "type":"Manufacturing & Wholesale Goods"
        }
    ],
    "sg:phone":"+1 803 278 1893",
    "sg:postcode":"29822",
    "sg:province":"SC",
    "sg:tags":[
        "printer"
    ],
    "wof:name":"TNT Graphics",
    "wof:placetype":"venue"
},
  "geometry": {"coordinates":[-81.89214699999999,33.496825],"type":"Point"}
}