{
  "type": "Feature",
  "properties": {
    "addr:full":"158 Sandy Acres St Stephen SC 29479",
    "addr:housenumber":"158",
    "addr:postcode":"29479",
    "addr:street":"Sandy Acres",
    "iso:country":"US",
    "sg:address":"158 Sandy Acres",
    "sg:city":"St Stephen",
    "sg:classifiers":[
        {
            "category":"Organizations",
            "subcategory":"Religious Organization",
            "type":"Services"
        }
    ],
    "sg:phone":"+1 843 567 4775",
    "sg:postcode":"29479",
    "sg:province":"SC",
    "sg:tags":[
        "church"
    ],
    "wof:name":"Life Baptist Church Mission",
    "wof:placetype":"venue"
},
  "geometry": {"coordinates":[-79.90983900000001,33.371735],"type":"Point"}
}