{
  "type": "Feature",
  "properties": {
    "iso:country":"US",
    "sg:address":"12 Clusters Ct",
    "sg:city":"Columbia",
    "sg:classifiers":[
        {
            "category":"Personal",
            "type":"Services"
        },
        {
            "category":"Sports & Exercise",
            "subcategory":"Gym",
            "type":"Entertainment"
        }
    ],
    "sg:phone":"+1 803 731 0027",
    "sg:postcode":"29210",
    "sg:province":"SC",
    "sg:tags":[
        "control",
        "weight",
        "facility",
        "mi",
        "fitness",
        "physical"
    ],
    "wof:name":"Physicians Weight Loss Centers",
    "wof:placetype":"venue"
},
  "geometry": {"coordinates":[-81.142346,34.042925],"type":"Point"}
}