{
  "type": "Feature",
  "properties": {
    "addr:full":"4712 S Kings Hwy Myrtle Beach SC 29575",
    "addr:housenumber":"4712",
    "addr:postcode":"29575",
    "addr:street":"S Kings Hwy",
    "iso:country":"US",
    "sg:address":"4712 S Kings Hwy",
    "sg:city":"Myrtle Beach",
    "sg:classifiers":[
        {
            "category":"Shopping",
            "subcategory":"Shoes",
            "type":"Retail Goods"
        }
    ],
    "sg:phone":"+1 843 232 0583",
    "sg:postcode":"29575",
    "sg:province":"SC",
    "sg:tags":[
        "boot"
    ],
    "wof:name":"Boot Connection",
    "wof:placetype":"venue"
},
  "geometry": {"coordinates":[-78.941593,33.64687],"type":"Point"}
}