{
  "type": "Feature",
  "properties": {
    "iso:country":"US",
    "sg:address":"400 Filter Plant Rd",
    "sg:city":"Honea Path",
    "sg:classifiers":[
        {
            "category":"Travel",
            "subcategory":"Travel Agent",
            "type":"Entertainment"
        }
    ],
    "sg:phone":"+1 864 369 1534",
    "sg:postcode":"29654",
    "sg:province":"SC",
    "sg:tags":[
        "agency",
        "bureau"
    ],
    "wof:name":"M & R Travel",
    "wof:placetype":"venue"
},
  "geometry": {"coordinates":[-82.39319999999999,34.512201],"type":"Point"}
}