{
  "type": "Feature",
  "properties": {
    "addr:full":"34 Broad St Charleston SC 29401",
    "addr:housenumber":"34",
    "addr:postcode":"29401",
    "addr:street":"Broad St",
    "iso:country":"US",
    "sg:address":"34 Broad St",
    "sg:city":"Charleston",
    "sg:classifiers":[
        {
            "category":"Banks & Credit Unions",
            "subcategory":"Financial Services",
            "type":"Services"
        }
    ],
    "sg:phone":"+1 843 724 0800",
    "sg:postcode":"29401",
    "sg:province":"SC",
    "sg:tags":[
        "company",
        "holding"
    ],
    "sg:website":"www.firstfederal.com",
    "wof:name":"First Financial Holdings Inc",
    "wof:placetype":"venue"
},
  "geometry": {"coordinates":[-79.92845199999999,32.776782],"type":"Point"}
}