{
  "type": "Feature",
  "properties": {
    "iso:country":"US",
    "sg:address":"105 Musgrove St",
    "sg:city":"Clinton",
    "sg:classifiers":[
        {
            "category":"Sports & Exercise",
            "subcategory":"Gym",
            "type":"Entertainment"
        }
    ],
    "sg:phone":"+1 864 833 0544",
    "sg:postcode":"29325",
    "sg:province":"SC",
    "sg:tags":[
        "spa",
        "health"
    ],
    "wof:name":"Uptown Day Spa",
    "wof:placetype":"venue"
},
  "geometry": {"coordinates":[-81.88029400000001,34.473833],"type":"Point"}
}