{
  "type": "Feature",
  "properties": {
    "addr:full":"1639 Woodruff Rd Greenville SC 29681",
    "addr:housenumber":"1639",
    "addr:postcode":"29681",
    "addr:street":"Woodruff Rd",
    "iso:country":"US",
    "sg:address":"1639 Woodruff Rd",
    "sg:city":"Greenville",
    "sg:classifiers":[
        {
            "category":"Health Services",
            "subcategory":"Doctor",
            "type":"Services"
        }
    ],
    "sg:phone":"+1 864 297 7232",
    "sg:postcode":"29681",
    "sg:province":"SC",
    "sg:tags":[
        "dentist"
    ],
    "wof:name":"Crowns Now",
    "wof:placetype":"venue"
},
  "geometry": {"coordinates":[-82.26759699999999,34.819812],"type":"Point"}
}