{
  "type": "Feature",
  "properties": {
    "iso:country":"US",
    "sg:address":"2971 Midiron Ct",
    "sg:city":"Myrtle Beach",
    "sg:classifiers":[
        {
            "category":"Shopping",
            "subcategory":"Computers & Home Electronics",
            "type":"Retail Goods"
        }
    ],
    "sg:phone":"+1 843 916 0109",
    "sg:postcode":"29577",
    "sg:province":"SC",
    "sg:tags":[
        "radio",
        "television",
        "electronic",
        "store"
    ],
    "wof:name":"Storm Front Productions Co",
    "wof:placetype":"venue"
},
  "geometry": {"coordinates":[-78.884575,33.72369],"type":"Point"}
}