{
  "type": "Feature",
  "properties": {
    "iso:country":"US",
    "sg:address":"1626 Shop Rd",
    "sg:city":"Columbia",
    "sg:classifiers":[
        {
            "category":"Government",
            "subcategory":"Police Station",
            "type":"Public Place"
        }
    ],
    "sg:phone":"+1 803 737 8340",
    "sg:postcode":"29201",
    "sg:province":"SC",
    "sg:tags":[
        "state"
    ],
    "sg:website":"www.schp.org",
    "wof:name":"Highway Patrol",
    "wof:placetype":"venue"
},
  "geometry": {"coordinates":[-81.00369999999999,33.969073],"type":"Point"}
}