{
  "type": "Feature",
  "properties": {
    "iso:country":"US",
    "sg:address":"7 Commercial Pl",
    "sg:city":"Bluffton",
    "sg:classifiers":[
        {
            "category":"Wholesale",
            "subcategory":"Auto Parts",
            "type":"Manufacturing & Wholesale Goods"
        }
    ],
    "sg:phone":"+1 843 757 6272",
    "sg:postcode":"29910",
    "sg:province":"SC",
    "wof:name":"NAPA Auto Parts",
    "wof:placetype":"venue"
},
  "geometry": {"coordinates":[-80.841359,32.248639],"type":"Point"}
}