{
  "type": "Feature",
  "properties": {
    "addr:full":"511 Rhett St Greenville SC 29601",
    "addr:housenumber":"511",
    "addr:postcode":"29601",
    "addr:street":"Rhett St",
    "iso:country":"US",
    "sg:address":"511 Rhett St",
    "sg:city":"Greenville",
    "sg:classifiers":[
        {
            "category":"Building & Trades",
            "subcategory":"Construction",
            "type":"Services"
        }
    ],
    "sg:phone":"+1 864 235 6702",
    "sg:postcode":"29601",
    "sg:province":"SC",
    "sg:tags":[
        "general",
        "contractor"
    ],
    "wof:name":"Weekes Construction Inc",
    "wof:placetype":"venue"
},
  "geometry": {"coordinates":[-82.409644,34.843931],"type":"Point"}
}