{
  "type": "Feature",
  "properties": {
    "iso:country":"US",
    "sg:address":"403 Hunters Hill Rd",
    "sg:city":"Simpsonville",
    "sg:classifiers":[
        {
            "category":"Shopping",
            "subcategory":"Catalog Store",
            "type":"Retail Goods"
        }
    ],
    "sg:phone":"+1 864 915 5053",
    "sg:postcode":"29680",
    "sg:province":"SC",
    "sg:tags":[
        "mail",
        "house"
    ],
    "wof:name":"Wwwyakcessoriescom",
    "wof:placetype":"venue"
},
  "geometry": {"coordinates":[-82.26393,34.713335],"type":"Point"}
}