{
  "type": "Feature",
  "properties": {
    "addr:full":"43 Alston Rd Beaufort SC 29907",
    "addr:housenumber":"43",
    "addr:postcode":"29907",
    "addr:street":"Alston Rd",
    "iso:country":"US",
    "sg:address":"43 Alston Rd",
    "sg:city":"Beaufort",
    "sg:classifiers":[
        {
            "category":"Education",
            "subcategory":"School",
            "type":"Public Place"
        }
    ],
    "sg:phone":"+1 843 322 2500",
    "sg:postcode":"29907",
    "sg:province":"SC",
    "sg:website":"www.beaufort.com",
    "wof:name":"Robert Smalls Middle School",
    "wof:placetype":"venue"
},
  "geometry": {"coordinates":[-80.60914200000001,32.488336],"type":"Point"}
}