{
  "type": "Feature",
  "properties": {
    "iso:country":"US",
    "sg:address":"380 Bessie Ave",
    "sg:city":"Greer",
    "sg:classifiers":[
        {
            "category":"Wholesale",
            "subcategory":"Machinery & Supplies",
            "type":"Manufacturing & Wholesale Goods"
        }
    ],
    "sg:phone":"+1 864 877 5222",
    "sg:postcode":"29651",
    "sg:province":"SC",
    "sg:tags":[
        "truck"
    ],
    "wof:name":"Barloworld Handling",
    "wof:placetype":"venue"
},
  "geometry": {"coordinates":[-82.235438,34.911543],"type":"Point"}
}