{
  "type": "Feature",
  "properties": {
    "iso:country":"US",
    "sg:address":"220 Kelley St",
    "sg:city":"Lake City",
    "sg:classifiers":[
        {
            "category":"Real Estate",
            "subcategory":"Real Estate Operator",
            "type":"Services"
        }
    ],
    "sg:phone":"+1 843 394 2688",
    "sg:postcode":"29560",
    "sg:province":"SC",
    "sg:tags":[
        "building",
        "apartment"
    ],
    "wof:name":"Lake City Apartments",
    "wof:placetype":"venue"
},
  "geometry": {"coordinates":[-79.755322,33.877207],"type":"Point"}
}