{
  "type": "Feature",
  "properties": {
    "addr:full":"6352 Saint Andrews Rd Columbia SC 29212",
    "addr:housenumber":"6352",
    "addr:postcode":"29212",
    "addr:street":"Saint Andrews Rd",
    "iso:country":"US",
    "sg:address":"6352 Saint Andrews Rd",
    "sg:city":"Columbia",
    "sg:classifiers":[
        {
            "category":"Wholesale",
            "subcategory":"Meat",
            "type":"Manufacturing & Wholesale Goods"
        }
    ],
    "sg:phone":"+1 803 798 2521",
    "sg:postcode":"29212",
    "sg:province":"SC",
    "sg:tags":[
        "fresh",
        "retail",
        "market"
    ],
    "wof:name":"Ole Timey Meat Market",
    "wof:placetype":"venue"
},
  "geometry": {"coordinates":[-81.164643,34.061538],"type":"Point"}
}