{
  "type": "Feature",
  "properties": {
    "iso:country":"US",
    "sg:address":"1045 W Dekalb St",
    "sg:city":"Camden",
    "sg:classifiers":[
        {
            "category":"Restaurant",
            "type":"Food & Drink"
        }
    ],
    "sg:phone":"+1 803 432 4640",
    "sg:postcode":"29020",
    "sg:province":"SC",
    "wof:name":"Laura's Restaurant",
    "wof:placetype":"venue"
},
  "geometry": {"coordinates":[-80.623256,34.246595],"type":"Point"}
}