{
  "type": "Feature",
  "properties": {
    "iso:country":"US",
    "sg:address":"607 Haywood Rd",
    "sg:city":"Greenville",
    "sg:classifiers":[
        {
            "category":"Shopping",
            "subcategory":"Books",
            "type":"Retail Goods"
        }
    ],
    "sg:phone":"+1 864 281 1517",
    "sg:postcode":"29607",
    "sg:province":"SC",
    "wof:name":"Greenville Lifeway Christn Str",
    "wof:placetype":"venue"
},
  "geometry": {"coordinates":[-82.34132,34.84494],"type":"Point"}
}