{
  "type": "Feature",
  "properties": {
    "iso:country":"US",
    "sg:address":"7125 Valley Falls Rd",
    "sg:city":"Spartanburg",
    "sg:classifiers":[
        {
            "category":"Retail",
            "subcategory":"Auto Repair",
            "type":"Services"
        }
    ],
    "sg:phone":"+1 864 503 9344",
    "sg:postcode":"29303",
    "sg:province":"SC",
    "sg:tags":[
        "machine",
        "automobile",
        "shop"
    ],
    "wof:name":"Spartan Crankshaft Inc",
    "wof:placetype":"venue"
},
  "geometry": {"coordinates":[-81.981241,34.988694],"type":"Point"}
}