{
  "type": "Feature",
  "properties": {
    "addr:full":"120 Commerce Dr Spartanburg SC 29340",
    "addr:housenumber":"120",
    "addr:postcode":"29340",
    "addr:street":"Commerce Dr",
    "iso:country":"US",
    "sg:address":"120 Commerce Dr",
    "sg:city":"Spartanburg",
    "sg:classifiers":[
        {
            "category":"Restaurant",
            "type":"Food & Drink"
        }
    ],
    "sg:phone":"+1 864 576 7723",
    "sg:postcode":"29340",
    "sg:province":"SC",
    "wof:name":"Subway Sandwiches & Salads",
    "wof:placetype":"venue"
},
  "geometry": {"coordinates":[-81.60581999999999,35.104387],"type":"Point"}
}