{
  "type": "Feature",
  "properties": {
    "addr:full":"140 Stoneridge Dr Columbia SC 29210",
    "addr:housenumber":"140",
    "addr:postcode":"29210",
    "addr:street":"Stoneridge Dr",
    "iso:country":"US",
    "sg:address":"140 Stoneridge Dr",
    "sg:city":"Columbia",
    "sg:classifiers":[
        {
            "category":"Professional",
            "subcategory":"Computer Services",
            "type":"Services"
        }
    ],
    "sg:phone":"+1 803 799 4200",
    "sg:postcode":"29210",
    "sg:province":"SC",
    "sg:tags":[
        "internet"
    ],
    "wof:name":"ITC Deltacom",
    "wof:placetype":"venue"
},
  "geometry": {"coordinates":[-81.071324,34.014309],"type":"Point"}
}