{
  "type": "Feature",
  "properties": {
    "iso:country":"US",
    "sg:address":"903 Chestnut St",
    "sg:city":"Darlington",
    "sg:classifiers":[
        {
            "category":"Taxi",
            "type":"Transportation"
        }
    ],
    "sg:phone":"+1 843 395 1950",
    "sg:postcode":"29532",
    "sg:province":"SC",
    "sg:tags":[
        "taxicab"
    ],
    "wof:name":"Pee Dee Taxi",
    "wof:placetype":"venue"
},
  "geometry": {"coordinates":[-79.877469,34.28874],"type":"Point"}
}