{
  "type": "Feature",
  "properties": {
    "iso:country":"US",
    "sg:address":"358 College Ave",
    "sg:city":"Clemson",
    "sg:classifiers":[
        {
            "category":"Personal",
            "subcategory":"Beauty Salon",
            "type":"Services"
        }
    ],
    "sg:phone":"+1 864 654 6555",
    "sg:postcode":"29631",
    "sg:province":"SC",
    "wof:name":"Hair South",
    "wof:placetype":"venue"
},
  "geometry": {"coordinates":[-82.837443,34.683452],"type":"Point"}
}