{
  "type": "Feature",
  "properties": {
    "iso:country":"US",
    "sg:address":"1275 Remount Rd",
    "sg:city":"North Charleston",
    "sg:classifiers":[
        {
            "category":"Professional",
            "subcategory":"Advertising",
            "type":"Services"
        }
    ],
    "sg:phone":"+1 843 554 5842",
    "sg:postcode":"29406",
    "sg:province":"SC",
    "wof:name":"Charleston Funtime",
    "wof:placetype":"venue"
},
  "geometry": {"coordinates":[-79.991855,32.901653],"type":"Point"}
}