{
  "type": "Feature",
  "properties": {
    "iso:country":"US",
    "sg:address":"426 W Boyce St",
    "sg:city":"Manning",
    "sg:classifiers":[
        {
            "category":"Organizations",
            "subcategory":"Religious Organization",
            "type":"Services"
        }
    ],
    "sg:phone":"+1 803 435 8220",
    "sg:postcode":"29102",
    "sg:province":"SC",
    "sg:tags":[
        "church"
    ],
    "wof:name":"Church Mt Calvary FBH",
    "wof:placetype":"venue"
},
  "geometry": {"coordinates":[-80.222842,33.696684],"type":"Point"}
}