{
  "type": "Feature",
  "properties": {
    "iso:country":"US",
    "sg:address":"1127 N Pleasantburg Dr",
    "sg:city":"Greenville",
    "sg:classifiers":[
        {
            "category":"Autos & Motor Vehicles",
            "subcategory":"Automobile Sales",
            "type":"Retail Goods"
        }
    ],
    "sg:phone":"+1 864 322 1394",
    "sg:postcode":"29607",
    "sg:province":"SC",
    "wof:name":"Train Auto Sales & Leasing",
    "wof:placetype":"venue"
},
  "geometry": {"coordinates":[-82.358852,34.871208],"type":"Point"}
}