{
  "type": "Feature",
  "properties": {
    "iso:country":"US",
    "sg:address":"553 John C Calhoun Dr",
    "sg:city":"Orangeburg",
    "sg:classifiers":[
        {
            "category":"Food & Beverages",
            "subcategory":"Groceries & Convenience Stores",
            "type":"Retail Goods"
        }
    ],
    "sg:phone":"+1 803 531 3228",
    "sg:postcode":"29115",
    "sg:province":"SC",
    "wof:name":"Hot Spot 3004",
    "wof:placetype":"venue"
},
  "geometry": {"coordinates":[-80.849538,33.490563],"type":"Point"}
}