{
  "type": "Feature",
  "properties": {
    "iso:country":"US",
    "sg:address":"7650 Pennyroyal Rd",
    "sg:city":"Georgetown",
    "sg:classifiers":[
        {
            "category":"Organizations",
            "subcategory":"Religious Organization",
            "type":"Services"
        }
    ],
    "sg:phone":"+1 843 546 1926",
    "sg:postcode":"29440",
    "sg:province":"SC",
    "sg:tags":[
        "church"
    ],
    "wof:name":"Cumberland AME Church",
    "wof:placetype":"venue"
},
  "geometry": {"coordinates":[-79.448396,33.364677],"type":"Point"}
}