{
  "type": "Feature",
  "properties": {
    "addr:full":"413 Vardry St Greenville SC 29601",
    "addr:housenumber":"413",
    "addr:postcode":"29601",
    "addr:street":"Vardry St",
    "iso:country":"US",
    "sg:address":"413 Vardry St",
    "sg:city":"Greenville",
    "sg:classifiers":[
        {
            "category":"Building & Trades",
            "subcategory":"Construction",
            "type":"Services"
        }
    ],
    "sg:phone":"+1 864 239 2126",
    "sg:postcode":"29601",
    "sg:province":"SC",
    "sg:tags":[
        "home",
        "improvement"
    ],
    "wof:name":"Dynamic Renovations",
    "wof:placetype":"venue"
},
  "geometry": {"coordinates":[-82.41073900000001,34.841658],"type":"Point"}
}