{
  "type": "Feature",
  "properties": {
    "addr:full":"258 Industrial Park Rd Newberry SC 29108",
    "addr:housenumber":"258",
    "addr:postcode":"29108",
    "addr:street":"Industrial Park Rd",
    "iso:country":"US",
    "sg:address":"258 Industrial Park Rd",
    "sg:city":"Newberry",
    "sg:classifiers":[
        {
            "category":"Manufacturing",
            "subcategory":"Tools & Machinery",
            "type":"Manufacturing & Wholesale Goods"
        }
    ],
    "sg:phone":"+1 803 321 0020",
    "sg:postcode":"29108",
    "sg:province":"SC",
    "sg:tags":[
        "physician",
        "surgeon"
    ],
    "wof:name":"Comfort Care Products Corp",
    "wof:placetype":"venue"
},
  "geometry": {"coordinates":[-81.64451200000001,34.247318],"type":"Point"}
}