{
  "type": "Feature",
  "properties": {
    "addr:full":"1402 N Ocean Blvd Myrtle Beach SC 29577",
    "addr:housenumber":"1402",
    "addr:postcode":"29577",
    "addr:street":"N Ocean Blvd",
    "iso:country":"US",
    "sg:address":"1402 N Ocean Blvd",
    "sg:city":"Myrtle Beach",
    "sg:classifiers":[
        {
            "category":"Travel",
            "subcategory":"Hotels & Motels",
            "type":"Entertainment"
        }
    ],
    "sg:phone":"+1 843 448 8595",
    "sg:postcode":"29577",
    "sg:province":"SC",
    "wof:name":"Tropical Court",
    "wof:placetype":"venue"
},
  "geometry": {"coordinates":[-78.874298,33.697109],"type":"Point"}
}