{
  "type": "Feature",
  "properties": {
    "iso:country":"US",
    "sg:address":"40 Whitash Ct",
    "sg:city":"Sumter",
    "sg:classifiers":[
        {
            "category":"Real Estate",
            "subcategory":"Real Estate Operator",
            "type":"Services"
        }
    ],
    "sg:phone":"+1 803 494 8330",
    "sg:postcode":"29154",
    "sg:province":"SC",
    "sg:tags":[
        "mobile",
        "home",
        "community"
    ],
    "wof:name":"Whitash Subdivision",
    "wof:placetype":"venue"
},
  "geometry": {"coordinates":[-80.472396,33.942112],"type":"Point"}
}