{
  "type": "Feature",
  "properties": {
    "iso:country":"US",
    "sg:address":"1134 Kincaid Bridge Rd",
    "sg:city":"Winnsboro",
    "sg:classifiers":[
        {
            "category":"Health Services",
            "subcategory":"Doctor",
            "type":"Services"
        }
    ],
    "sg:phone":"+1 803 635 6096",
    "sg:postcode":"29180",
    "sg:province":"SC",
    "sg:tags":[
        "clinic"
    ],
    "wof:name":"Gambro Healthcare",
    "wof:placetype":"venue"
},
  "geometry": {"coordinates":[-81.132335,34.379574],"type":"Point"}
}