{
  "type": "Feature",
  "properties": {
    "iso:country":"US",
    "sg:address":"713 W Main St",
    "sg:city":"Lexington",
    "sg:classifiers":[
        {
            "category":"Shopping",
            "subcategory":"Shoes",
            "type":"Retail Goods"
        }
    ],
    "sg:phone":"+1 803 356 0147",
    "sg:postcode":"29072",
    "sg:province":"SC",
    "wof:name":"Payless Shoe Source",
    "wof:placetype":"venue"
},
  "geometry": {"coordinates":[-81.249116,33.984817],"type":"Point"}
}