{
  "type": "Feature",
  "properties": {
    "iso:country":"US",
    "sg:address":"2412 E River St",
    "sg:city":"Anderson",
    "sg:classifiers":[
        {
            "category":"Shopping",
            "subcategory":"Gifts & Souvenirs",
            "type":"Retail Goods"
        }
    ],
    "sg:phone":"+1 864 260 9015",
    "sg:postcode":"29621",
    "sg:province":"SC",
    "sg:tags":[
        "florist"
    ],
    "wof:name":"Apple Blossom Florist",
    "wof:placetype":"venue"
},
  "geometry": {"coordinates":[-82.612578,34.49037],"type":"Point"}
}