{
  "type": "Feature",
  "properties": {
    "addr:full":"7117 Cross County Rd North Charleston SC 29418",
    "addr:housenumber":"7117",
    "addr:postcode":"29418",
    "addr:street":"Cross County Rd",
    "iso:country":"US",
    "sg:address":"7117 Cross County Rd",
    "sg:city":"North Charleston",
    "sg:classifiers":[
        {
            "category":"Professional",
            "type":"Services"
        }
    ],
    "sg:phone":"+1 843 207 0445",
    "sg:postcode":"29418",
    "sg:province":"SC",
    "sg:tags":[
        "establishment"
    ],
    "wof:name":"Superior Carriers Inc",
    "wof:placetype":"venue"
},
  "geometry": {"coordinates":[-80.077162,32.900993],"type":"Point"}
}