{
  "type": "Feature",
  "properties": {
    "addr:full":"521 N Mc Duffie St Anderson SC 29621",
    "addr:housenumber":"521",
    "addr:postcode":"29621",
    "addr:street":"N Mc Duffie St",
    "iso:country":"US",
    "sg:address":"521 N Mc Duffie St",
    "sg:city":"Anderson",
    "sg:classifiers":[
        {
            "category":"Real Estate",
            "subcategory":"Real Estate Agent",
            "type":"Services"
        }
    ],
    "sg:phone":"+1 864 224 4848",
    "sg:postcode":"29621",
    "sg:province":"SC",
    "wof:name":"Shalimar Homes Properties",
    "wof:placetype":"venue"
},
  "geometry": {"coordinates":[-82.649737,34.508384],"type":"Point"}
}