{
  "type": "Feature",
  "properties": {
    "iso:country":"US",
    "sg:address":"307 Myrtle Beach Hwy",
    "sg:city":"Sumter",
    "sg:classifiers":[
        {
            "category":"Professional",
            "subcategory":"Management & Consulting",
            "type":"Services"
        }
    ],
    "sg:phone":"+1 803 773 2588",
    "sg:postcode":"29153",
    "sg:province":"SC",
    "sg:tags":[
        "trade",
        "business",
        "contractor"
    ],
    "wof:name":"C & C Mobile Homes",
    "wof:placetype":"venue"
},
  "geometry": {"coordinates":[-80.30858499999999,33.915087],"type":"Point"}
}