{
  "type": "Feature",
  "properties": {
    "iso:country":"US",
    "sg:address":"1609 Blossom St",
    "sg:city":"Columbia",
    "sg:classifiers":[
        {
            "category":"Shopping",
            "subcategory":"Jewelry",
            "type":"Retail Goods"
        }
    ],
    "sg:phone":"+1 803 254 5330",
    "sg:postcode":"29201",
    "sg:province":"SC",
    "wof:name":"Balfour S C Company Inc",
    "wof:placetype":"venue"
},
  "geometry": {"coordinates":[-81.02330000000001,33.995602],"type":"Point"}
}