{
  "type": "Feature",
  "properties": {
    "iso:country":"US",
    "sg:address":"4 Marshland Ln",
    "sg:city":"Hilton Head Isle",
    "sg:classifiers":[
        {
            "category":"Professional",
            "type":"Services"
        }
    ],
    "sg:phone":"+1 843 342 6718",
    "sg:postcode":"29926",
    "sg:province":"SC",
    "wof:name":"Palmetto Pass Customer Svc Ctr",
    "wof:placetype":"venue"
},
  "geometry": {"coordinates":[-80.76366299999999,32.186614],"type":"Point"}
}