{
  "type": "Feature",
  "properties": {
    "iso:country":"US",
    "sg:address":"1221 W Floyd Baker Blvd",
    "sg:city":"Gaffney",
    "sg:classifiers":[
        {
            "category":"Banks & Credit Unions",
            "subcategory":"Bank",
            "type":"Services"
        }
    ],
    "sg:phone":"+1 864 487 2222",
    "sg:postcode":"29341",
    "sg:province":"SC",
    "sg:tags":[
        "depository",
        "banking"
    ],
    "wof:name":"Fast Cash Check Advance",
    "wof:placetype":"venue"
},
  "geometry": {"coordinates":[-81.657562,35.083216],"type":"Point"}
}