{
  "type": "Feature",
  "properties": {
    "addr:full":"1529 Assembly St Columbia SC 29201",
    "addr:housenumber":"1529",
    "addr:postcode":"29201",
    "addr:street":"Assembly St",
    "iso:country":"US",
    "sg:address":"1529 Assembly St",
    "sg:city":"Columbia",
    "sg:classifiers":[
        {
            "category":"Restaurant",
            "type":"Food & Drink"
        }
    ],
    "sg:phone":"+1 803 754 5773",
    "sg:postcode":"29201",
    "sg:province":"SC",
    "sg:tags":[
        "cafe"
    ],
    "wof:name":"Angel Food",
    "wof:placetype":"venue"
},
  "geometry": {"coordinates":[-81.03740999999999,34.005736],"type":"Point"}
}