{
  "type": "Feature",
  "properties": {
    "iso:country":"US",
    "sg:address":"107 Hendrix St",
    "sg:city":"West Columbia",
    "sg:classifiers":[
        {
            "category":"Building & Trades",
            "subcategory":"Construction",
            "type":"Services"
        }
    ],
    "sg:phone":"+1 803 796 4425",
    "sg:postcode":"29169",
    "sg:province":"SC",
    "sg:tags":[
        "contractor"
    ],
    "wof:name":"Midland Construction",
    "wof:placetype":"venue"
},
  "geometry": {"coordinates":[-81.090757,33.985633],"type":"Point"}
}