{
  "type": "Feature",
  "properties": {
    "iso:country":"US",
    "sg:address":"3447 Pelham Rd",
    "sg:city":"Greenville",
    "sg:classifiers":[
        {
            "category":"Insurance",
            "subcategory":"Insurance Agent",
            "type":"Services"
        }
    ],
    "sg:phone":"+1 864 675 1007",
    "sg:postcode":"29615",
    "sg:province":"SC",
    "wof:name":"First Choice Ins Of Greenville",
    "wof:placetype":"venue"
},
  "geometry": {"coordinates":[-82.30255699999999,34.856581],"type":"Point"}
}