{
  "type": "Feature",
  "properties": {
    "iso:country":"US",
    "sg:address":"204 Hunting Hollow Rd",
    "sg:city":"Greenville",
    "sg:classifiers":[
        {
            "category":"Freight",
            "type":"Transportation"
        }
    ],
    "sg:phone":"+1 864 281 7874",
    "sg:postcode":"29615",
    "sg:province":"SC",
    "sg:tags":[
        "courier"
    ],
    "wof:name":"Courier Dujour Inc",
    "wof:placetype":"venue"
},
  "geometry": {"coordinates":[-82.296164,34.860848],"type":"Point"}
}