{
  "type": "Feature",
  "properties": {
    "addr:full":"702 N Governor Williams Hwy Darlington SC 29532",
    "addr:housenumber":"702",
    "addr:postcode":"29532",
    "addr:street":"N Governor Williams Hwy",
    "iso:country":"US",
    "sg:address":"702 N Governor Williams Hwy",
    "sg:city":"Darlington",
    "sg:classifiers":[
        {
            "category":"Organizations",
            "subcategory":"Religious Organization",
            "type":"Services"
        }
    ],
    "sg:phone":"+1 843 393 7010",
    "sg:postcode":"29532",
    "sg:province":"SC",
    "sg:tags":[
        "church"
    ],
    "wof:name":"Darlington Church Of God",
    "wof:placetype":"venue"
},
  "geometry": {"coordinates":[-79.89670599999999,34.308502],"type":"Point"}
}