{
  "type": "Feature",
  "properties": {
    "iso:country":"US",
    "sg:address":"282 Christian Rd",
    "sg:city":"Conway",
    "sg:classifiers":[
        {
            "category":"Recreation",
            "type":"Entertainment"
        }
    ],
    "sg:phone":"+1 843 365 5588",
    "sg:postcode":"29526",
    "sg:province":"SC",
    "sg:tags":[
        "fish"
    ],
    "wof:name":"Hickory Hills Catfish Farm",
    "wof:placetype":"venue"
},
  "geometry": {"coordinates":[-78.971405,33.886078],"type":"Point"}
}