{
  "type": "Feature",
  "properties": {
    "iso:country":"US",
    "sg:address":"221 Pickens St",
    "sg:city":"Columbia",
    "sg:classifiers":[
        {
            "category":"Building & Trades",
            "subcategory":"Landscaping Services",
            "type":"Services"
        }
    ],
    "sg:phone":"+1 803 256 0562",
    "sg:postcode":"29205",
    "sg:province":"SC",
    "sg:tags":[
        "landscape"
    ],
    "wof:name":"Landplan Group South Inc",
    "wof:placetype":"venue"
},
  "geometry": {"coordinates":[-81.021662,33.990823],"type":"Point"}
}