{
  "type": "Feature",
  "properties": {
    "iso:country":"US",
    "sg:address":"400 S Main St",
    "sg:city":"Fountain Inn",
    "sg:classifiers":[
        {
            "category":"Professional",
            "type":"Services"
        }
    ],
    "sg:phone":"+1 864 862 6715",
    "sg:postcode":"29644",
    "sg:province":"SC",
    "sg:tags":[
        "establishment"
    ],
    "wof:name":"Cashion Co",
    "wof:placetype":"venue"
},
  "geometry": {"coordinates":[-82.194095,34.687183],"type":"Point"}
}