{
  "type": "Feature",
  "properties": {
    "addr:full":"7130 Rivers Ave Charleston SC 29406",
    "addr:housenumber":"7130",
    "addr:postcode":"29406",
    "addr:street":"Rivers Ave",
    "iso:country":"US",
    "sg:address":"7130 Rivers Ave",
    "sg:city":"Charleston",
    "sg:classifiers":[
        {
            "category":"Shopping",
            "subcategory":"Computers & Home Electronics",
            "type":"Retail Goods"
        }
    ],
    "sg:phone":"+1 843 824 6025",
    "sg:postcode":"29406",
    "sg:province":"SC",
    "sg:tags":[
        "consumer",
        "appliance"
    ],
    "wof:name":"Rex",
    "wof:placetype":"venue"
},
  "geometry": {"coordinates":[-80.035753,32.930839],"type":"Point"}
}