{
  "type": "Feature",
  "properties": {
    "addr:full":"1217 Sapaugh Ave Rock Hill SC 29732",
    "addr:housenumber":"1217",
    "addr:postcode":"29732",
    "addr:street":"Sapaugh Ave",
    "iso:country":"US",
    "sg:address":"1217 Sapaugh Ave",
    "sg:city":"Rock Hill",
    "sg:classifiers":[
        {
            "category":"Government",
            "subcategory":"Office",
            "type":"Public Place"
        }
    ],
    "sg:phone":"+1 803 366 7416",
    "sg:postcode":"29732",
    "sg:province":"SC",
    "sg:tags":[
        "county",
        "resource"
    ],
    "wof:name":"York County Disabilities Board",
    "wof:placetype":"venue"
},
  "geometry": {"coordinates":[-81.00701100000001,34.966945],"type":"Point"}
}