{
  "type": "Feature",
  "properties": {
    "addr:full":"408 S Parsonage St Bennettsville SC 29512",
    "addr:housenumber":"408",
    "addr:postcode":"29512",
    "addr:street":"S Parsonage St",
    "iso:country":"US",
    "sg:address":"408 S Parsonage St",
    "sg:city":"Bennettsville",
    "sg:classifiers":[
        {
            "category":"Shopping",
            "subcategory":"Music",
            "type":"Retail Goods"
        }
    ],
    "sg:phone":"+1 843 479 9781",
    "sg:postcode":"29512",
    "sg:province":"SC",
    "sg:tags":[
        "video",
        "disc",
        "tape",
        "cassette"
    ],
    "wof:name":"Quick's Video & Games",
    "wof:placetype":"venue"
},
  "geometry": {"coordinates":[-79.67773800000001,34.611242],"type":"Point"}
}