{
  "type": "Feature",
  "properties": {
    "iso:country":"US",
    "sg:address":"7421 College St",
    "sg:city":"Irmo",
    "sg:classifiers":[
        {
            "category":"Personal",
            "subcategory":"Beauty Salon",
            "type":"Services"
        }
    ],
    "sg:phone":"+1 803 732 3232",
    "sg:postcode":"29063",
    "sg:province":"SC",
    "wof:name":"Bedazzled Salon & Day Spa",
    "wof:placetype":"venue"
},
  "geometry": {"coordinates":[-81.174106,34.090517],"type":"Point"}
}