{
  "type": "Feature",
  "properties": {
    "iso:country":"US",
    "sg:address":"6701 Two Notch Rd",
    "sg:city":"Columbia",
    "sg:classifiers":[
        {
            "category":"Health Services",
            "subcategory":"Medical Lab",
            "type":"Services"
        }
    ],
    "sg:phone":"+1 803 736 2359",
    "sg:postcode":"29223",
    "sg:province":"SC",
    "sg:tags":[
        "laboratory"
    ],
    "wof:name":"Land Dental Lab",
    "wof:placetype":"venue"
},
  "geometry": {"coordinates":[-80.963787,34.059247],"type":"Point"}
}