{
  "type": "Feature",
  "properties": {
    "addr:full":"169 Suttles Rd Inman SC 29349",
    "addr:housenumber":"169",
    "addr:postcode":"29349",
    "addr:street":"Suttles Rd",
    "iso:country":"US",
    "sg:address":"169 Suttles Rd",
    "sg:city":"Inman",
    "sg:classifiers":[
        {
            "category":"Building & Trades",
            "subcategory":"Electrical",
            "type":"Services"
        }
    ],
    "sg:phone":"+1 864 592 1200",
    "sg:postcode":"29349",
    "sg:province":"SC",
    "sg:tags":[
        "electrical",
        "contractor"
    ],
    "wof:name":"Mg Electrical",
    "wof:placetype":"venue"
},
  "geometry": {"coordinates":[-82.03671300000001,35.110213],"type":"Point"}
}