{
  "type": "Feature",
  "properties": {
    "iso:country":"US",
    "sg:address":"2989 E Main St Exd",
    "sg:city":"Spartanburg",
    "sg:classifiers":[
        {
            "category":"Autos & Motor Vehicles",
            "subcategory":"Automobile Sales",
            "type":"Retail Goods"
        }
    ],
    "sg:phone":"+1 864 579 3131",
    "sg:postcode":"29307",
    "sg:province":"SC",
    "sg:tags":[
        "car",
        "dealer"
    ],
    "wof:name":"Ace Motor Co Of Spartanburg",
    "wof:placetype":"venue"
},
  "geometry": {"coordinates":[-81.858915,34.985363],"type":"Point"}
}