{
  "type": "Feature",
  "properties": {
    "iso:country":"US",
    "sg:address":"3890 Pelham Rd",
    "sg:city":"Greenville",
    "sg:classifiers":[
        {
            "category":"Restaurant",
            "type":"Food & Drink"
        }
    ],
    "sg:phone":"+1 864 297 9912",
    "sg:postcode":"29615",
    "sg:province":"SC",
    "wof:name":"Chick-Fil-A",
    "wof:placetype":"venue"
},
  "geometry": {"coordinates":[-82.29609000000001,34.859003],"type":"Point"}
}