{
  "type": "Feature",
  "properties": {
    "addr:full":"305 W Evans St Florence SC 29501",
    "addr:housenumber":"305",
    "addr:postcode":"29501",
    "addr:street":"W Evans St",
    "iso:country":"US",
    "sg:address":"305 W Evans St",
    "sg:city":"Florence",
    "sg:classifiers":[
        {
            "category":"Shopping",
            "subcategory":"Gifts & Souvenirs",
            "type":"Retail Goods"
        }
    ],
    "sg:phone":"+1 843 664 0480",
    "sg:postcode":"29501",
    "sg:province":"SC",
    "sg:tags":[
        "basket",
        "parcel"
    ],
    "wof:name":"Sisters",
    "wof:placetype":"venue"
},
  "geometry": {"coordinates":[-79.77255,34.197087],"type":"Point"}
}