{
  "type": "Feature",
  "properties": {
    "iso:country":"US",
    "sg:address":"2620 Shop Rd",
    "sg:city":"Columbia",
    "sg:classifiers":[
        {
            "category":"Manufacturing",
            "subcategory":"Motor Vehicles & Parts",
            "type":"Manufacturing & Wholesale Goods"
        }
    ],
    "sg:phone":"+1 803 695 1770",
    "sg:postcode":"29201",
    "sg:province":"SC",
    "sg:tags":[
        "manufacture",
        "body",
        "truck"
    ],
    "wof:name":"W & W Body Bldrs of Columbia",
    "wof:placetype":"venue"
},
  "geometry": {"coordinates":[-80.96320799999999,33.946041],"type":"Point"}
}