{
  "type": "Feature",
  "properties": {
    "iso:country":"US",
    "sg:address":"1000 Dave Gibson Blvd",
    "sg:city":"Fort Mill",
    "sg:classifiers":[
        {
            "category":"Social Services",
            "subcategory":"Child Care",
            "type":"Services"
        }
    ],
    "sg:phone":"+1 803 547 1395",
    "sg:postcode":"29708",
    "sg:province":"SC",
    "wof:name":"Leroy Springs Flyers Gold Hill",
    "wof:placetype":"venue"
},
  "geometry": {"coordinates":[-80.989696,35.040139],"type":"Point"}
}