{
  "type": "Feature",
  "properties": {
    "addr:full":"1321 Old Pacolet Rd Spartanburg SC 29307",
    "addr:housenumber":"1321",
    "addr:postcode":"29307",
    "addr:street":"Old Pacolet Rd",
    "iso:country":"US",
    "sg:address":"1321 Old Pacolet Rd",
    "sg:city":"Spartanburg",
    "sg:classifiers":[
        {
            "category":"Recreation",
            "type":"Entertainment"
        }
    ],
    "sg:phone":"+1 864 463 6323",
    "sg:postcode":"29307",
    "sg:province":"SC",
    "sg:tags":[
        "stable"
    ],
    "wof:name":"Oakridge Equestrian Ctr LLC",
    "wof:placetype":"venue"
},
  "geometry": {"coordinates":[-81.790277,35.002344],"type":"Point"}
}