{
  "type": "Feature",
  "properties": {
    "iso:country":"US",
    "sg:address":"913 Robinhood Trl",
    "sg:city":"Aiken",
    "sg:classifiers":[
        {
            "category":"Building & Trades",
            "subcategory":"Construction",
            "type":"Services"
        }
    ],
    "sg:phone":"+1 803 648 5266",
    "sg:postcode":"29803",
    "sg:province":"SC",
    "sg:tags":[
        "painter"
    ],
    "wof:name":"Campbell Painting",
    "wof:placetype":"venue"
},
  "geometry": {"coordinates":[-81.712484,33.51633],"type":"Point"}
}