{
  "type": "Feature",
  "properties": {
    "iso:country":"US",
    "sg:address":"204 E 4th St S",
    "sg:city":"Summerville",
    "sg:classifiers":[
        {
            "category":"Restaurant",
            "type":"Food & Drink"
        }
    ],
    "sg:phone":"+1 843 871 5252",
    "sg:postcode":"29483",
    "sg:province":"SC",
    "sg:tags":[
        "eating"
    ],
    "wof:name":"Paul Trentinos Itln Cafe & Bky",
    "wof:placetype":"venue"
},
  "geometry": {"coordinates":[-80.17573400000001,33.013669],"type":"Point"}
}