{
  "type": "Feature",
  "properties": {
    "iso:country":"US",
    "sg:address":"1805 Matthews Dr",
    "sg:city":"Rock Hill",
    "sg:classifiers":[
        {
            "category":"Building & Trades",
            "subcategory":"Landscaping Services",
            "type":"Services"
        }
    ],
    "sg:phone":"+1 803 366 4443",
    "sg:postcode":"29732",
    "sg:province":"SC",
    "wof:name":"Piedmont Landscape & Nurs Svcs",
    "wof:placetype":"venue"
},
  "geometry": {"coordinates":[-81.028313,34.97238],"type":"Point"}
}