{
  "type": "Feature",
  "properties": {
    "iso:country":"US",
    "sg:address":"116 Bickleigh Rd",
    "sg:city":"Irmo",
    "sg:classifiers":[
        {
            "category":"Shopping",
            "subcategory":"Catalog Store",
            "type":"Retail Goods"
        }
    ],
    "sg:phone":"+1 803 732 1823",
    "sg:postcode":"29063",
    "sg:province":"SC",
    "sg:tags":[
        "mail",
        "house"
    ],
    "wof:name":"Saints Shamrocks of Midland",
    "wof:placetype":"venue"
},
  "geometry": {"coordinates":[-81.190144,34.093204],"type":"Point"}
}