{
  "type": "Feature",
  "properties": {
    "addr:full":"3030 Charleston Hwy Orangeburg SC 29115",
    "addr:housenumber":"3030",
    "addr:postcode":"29115",
    "addr:street":"Charleston Hwy",
    "iso:country":"US",
    "sg:address":"3030 Charleston Hwy",
    "sg:city":"Orangeburg",
    "sg:classifiers":[
        {
            "category":"Real Estate",
            "subcategory":"Real Estate Agent",
            "type":"Services"
        }
    ],
    "sg:phone":"+1 803 534 5683",
    "sg:postcode":"29115",
    "sg:province":"SC",
    "wof:name":"Cow Castle Land & Timber Co",
    "wof:placetype":"venue"
},
  "geometry": {"coordinates":[-80.812744,33.450586],"type":"Point"}
}