{
  "type": "Feature",
  "properties": {
    "addr:full":"513 Gilbertson Dr Spartanburg SC 29303",
    "addr:housenumber":"513",
    "addr:postcode":"29303",
    "addr:street":"Gilbertson Dr",
    "iso:country":"US",
    "sg:address":"513 Gilbertson Dr",
    "sg:city":"Spartanburg",
    "sg:classifiers":[
        {
            "category":"Freight",
            "type":"Transportation"
        }
    ],
    "sg:phone":"+1 864 591 1451",
    "sg:postcode":"29303",
    "sg:province":"SC",
    "sg:tags":[
        "operator",
        "trucking"
    ],
    "wof:name":"Ricky Lee Cromer",
    "wof:placetype":"venue"
},
  "geometry": {"coordinates":[-81.915384,34.980806],"type":"Point"}
}