{
  "type": "Feature",
  "properties": {
    "addr:full":"107 Carolina Blvd Isle Of Palms SC 29451",
    "addr:housenumber":"107",
    "addr:postcode":"isle;29451",
    "addr:street":"Carolina Blvd",
    "iso:country":"US",
    "sg:address":"107 Carolina Blvd",
    "sg:city":"Isle Of Palms",
    "sg:classifiers":[
        {
            "category":"Building & Trades",
            "subcategory":"Construction",
            "type":"Services"
        }
    ],
    "sg:phone":"+1 843 886 8984",
    "sg:postcode":"29451",
    "sg:province":"SC",
    "sg:tags":[
        "excavation",
        "home",
        "builder",
        "demolition"
    ],
    "wof:name":"Van Cott Custom Homes Inc",
    "wof:placetype":"venue"
},
  "geometry": {"coordinates":[-79.80785400000001,32.77788],"type":"Point"}
}