{
  "type": "Feature",
  "properties": {
    "iso:country":"US",
    "sg:address":"131 Ninety Six Hwy",
    "sg:city":"Ninety Six",
    "sg:classifiers":[
        {
            "category":"Autos & Motor Vehicles",
            "subcategory":"Automobile Sales",
            "type":"Retail Goods"
        }
    ],
    "sg:phone":"+1 864 543 3604",
    "sg:postcode":"29666",
    "sg:province":"SC",
    "sg:tags":[
        "car",
        "dealer"
    ],
    "wof:name":"Riley's",
    "wof:placetype":"venue"
},
  "geometry": {"coordinates":[-82.023746,34.175109],"type":"Point"}
}