{
  "type": "Feature",
  "properties": {
    "addr:full":"1082 Renwood Dr Charleston SC 29412",
    "addr:housenumber":"1082",
    "addr:postcode":"29412",
    "addr:street":"Renwood Dr",
    "iso:country":"US",
    "sg:address":"1082 Renwood Dr",
    "sg:city":"Charleston",
    "sg:classifiers":[
        {
            "category":"Restaurant",
            "type":"Food & Drink"
        }
    ],
    "sg:phone":"+1 843 577 5202",
    "sg:postcode":"29412",
    "sg:province":"SC",
    "sg:tags":[
        "caterer"
    ],
    "wof:name":"Caterers Extraordinaire",
    "wof:placetype":"venue"
},
  "geometry": {"coordinates":[-79.9592,32.728312],"type":"Point"}
}