{
  "type": "Feature",
  "properties": {
    "iso:country":"US",
    "sg:address":"325 Savannah Hwy",
    "sg:city":"Charleston",
    "sg:classifiers":[
        {
            "category":"Restaurant",
            "type":"Food & Drink"
        }
    ],
    "sg:menulink":"http://www.allmenus.com/sc/charleston-north-charleston/107741-waffle-house/menu/",
    "sg:phone":"+1 843 766 0717",
    "sg:postcode":"29407",
    "sg:province":"SC",
    "sg:tags":[
        "american"
    ],
    "wof:name":"Waffle House",
    "wof:placetype":"venue"
},
  "geometry": {"coordinates":[-79.966097,32.780819],"type":"Point"}
}