{
  "type": "Feature",
  "properties": {
    "iso:country":"US",
    "sg:address":"407 W Main St",
    "sg:city":"Lexington",
    "sg:classifiers":[
        {
            "category":"Professional",
            "subcategory":"Research",
            "type":"Services"
        }
    ],
    "sg:phone":"+1 803 951 8470",
    "sg:postcode":"29072",
    "sg:province":"SC",
    "sg:tags":[
        "environmental",
        "ecological"
    ],
    "wof:name":"Advanced Environmental Sltns",
    "wof:placetype":"venue"
},
  "geometry": {"coordinates":[-81.243688,33.985772],"type":"Point"}
}