{
  "type": "Feature",
  "properties": {
    "iso:country":"US",
    "sg:address":"3090 Trask Pkwy",
    "sg:city":"Beaufort",
    "sg:classifiers":[
        {
            "category":"Shopping",
            "type":"Retail Goods"
        }
    ],
    "sg:phone":"+1 843 846 1050",
    "sg:postcode":"29906",
    "sg:province":"SC",
    "sg:tags":[
        "chemical"
    ],
    "wof:name":"Kalama Specialty Chemical",
    "wof:placetype":"venue"
},
  "geometry": {"coordinates":[-80.737582,32.474044],"type":"Point"}
}