{
  "type": "Feature",
  "properties": {
    "iso:country":"US",
    "sg:address":"321 Old Broad St",
    "sg:city":"Leesville",
    "sg:classifiers":[
        {
            "category":"Government",
            "subcategory":"Office",
            "type":"Public Place"
        }
    ],
    "sg:phone":"+1 803 892 6161",
    "sg:postcode":"29070",
    "sg:province":"SC",
    "sg:tags":[
        "village"
    ],
    "wof:name":"Summit Town Office",
    "wof:placetype":"venue"
},
  "geometry": {"coordinates":[-81.423209,33.925242],"type":"Point"}
}