{
  "type": "Feature",
  "properties": {
    "addr:full":"3037 Sandy Bay Rd Kingstree SC 29556",
    "addr:housenumber":"3037",
    "addr:postcode":"29556",
    "addr:street":"Sandy Bay Rd",
    "iso:country":"US",
    "sg:address":"3037 Sandy Bay Rd",
    "sg:city":"Kingstree",
    "sg:classifiers":[
        {
            "category":"Farming",
            "subcategory":"Farm & Veterinary Services",
            "type":"Manufacturing & Wholesale Goods"
        }
    ],
    "sg:phone":"+1 843 382 8289",
    "sg:postcode":"29556",
    "sg:province":"SC",
    "sg:tags":[
        "aerial",
        "applicator"
    ],
    "wof:name":"Williamsburg Aircraft Svc Inc",
    "wof:placetype":"venue"
},
  "geometry": {"coordinates":[-79.849006,33.713764],"type":"Point"}
}