{
  "type": "Feature",
  "properties": {
    "addr:full":"1886 Little John Dr Lancaster SC 29720",
    "addr:housenumber":"1886",
    "addr:postcode":"29720",
    "addr:street":"Little John Dr",
    "iso:country":"US",
    "sg:address":"1886 Little John Dr",
    "sg:city":"Lancaster",
    "sg:classifiers":[
        {
            "category":"Shopping",
            "subcategory":"Used Merchandise",
            "type":"Retail Goods"
        }
    ],
    "sg:phone":"+1 803 286 9833",
    "sg:postcode":"29720",
    "sg:province":"SC",
    "wof:name":"Angelo Sciulli",
    "wof:placetype":"venue"
},
  "geometry": {"coordinates":[-80.754656,34.758086],"type":"Point"}
}