{
  "type": "Feature",
  "properties": {
    "addr:full":"202 Third Loop Rd Florence SC 29505",
    "addr:housenumber":"202",
    "addr:postcode":"29505",
    "addr:street":"Third Loop Rd",
    "iso:country":"US",
    "sg:address":"202 Third Loop Rd",
    "sg:city":"Florence",
    "sg:classifiers":[
        {
            "category":"Retail",
            "subcategory":"Repair Shop",
            "type":"Services"
        }
    ],
    "sg:phone":"+1 843 669 8389",
    "sg:postcode":"29505",
    "sg:province":"SC",
    "sg:tags":[
        "lock",
        "locksmith"
    ],
    "wof:name":"Tong Lock",
    "wof:placetype":"venue"
},
  "geometry": {"coordinates":[-79.77273,34.144419],"type":"Point"}
}