{
  "type": "Feature",
  "properties": {
    "addr:full":"1310 Tiger Blvd Clemson SC 29631",
    "addr:housenumber":"1310",
    "addr:postcode":"29631",
    "addr:street":"Tiger Blvd",
    "iso:country":"US",
    "sg:address":"1310 Tiger Blvd",
    "sg:city":"Clemson",
    "sg:classifiers":[
        {
            "category":"Restaurant",
            "type":"Food & Drink"
        }
    ],
    "sg:phone":"+1 864 654 9944",
    "sg:postcode":"29631",
    "sg:province":"SC",
    "wof:name":"Rock Hoppers Restaurant & Bar",
    "wof:placetype":"venue"
},
  "geometry": {"coordinates":[-82.826657,34.68949],"type":"Point"}
}