{
  "type": "Feature",
  "properties": {
    "iso:country":"US",
    "sg:address":"505 E 2nd Ave",
    "sg:city":"Easley",
    "sg:classifiers":[
        {
            "category":"Education",
            "subcategory":"School",
            "type":"Public Place"
        }
    ],
    "sg:phone":"+1 864 855 7860",
    "sg:postcode":"29640",
    "sg:province":"SC",
    "wof:name":"East End Elementary School",
    "wof:placetype":"venue"
},
  "geometry": {"coordinates":[-82.59390399999999,34.828195],"type":"Point"}
}