{
  "type": "Feature",
  "properties": {
    "iso:country":"US",
    "sg:address":"62 New Orleans Rd",
    "sg:city":"Hilton Head Isle",
    "sg:classifiers":[
        {
            "category":"Organizations",
            "subcategory":"Non-profit Organization",
            "type":"Services"
        }
    ],
    "sg:phone":"+1 843 341 9005",
    "sg:postcode":"29928",
    "sg:province":"SC",
    "wof:name":"March Of Dimes",
    "wof:placetype":"venue"
},
  "geometry": {"coordinates":[-80.76026899999999,32.1539],"type":"Point"}
}