{
  "type": "Feature",
  "properties": {
    "iso:country":"US",
    "sg:address":"625 Mount Olivet Rd",
    "sg:city":"Camden",
    "sg:classifiers":[
        {
            "category":"Utilities",
            "subcategory":"Telephone",
            "type":"Services"
        }
    ],
    "sg:phone":"+1 803 432 3169",
    "sg:postcode":"29020",
    "sg:province":"SC",
    "sg:tags":[
        "telecommunication"
    ],
    "wof:name":"American Tower Corp",
    "wof:placetype":"venue"
},
  "geometry": {"coordinates":[-80.537525,34.218719],"type":"Point"}
}