{
  "type": "Feature",
  "properties": {
    "addr:full":"1331 Hagood St Columbia SC 29205",
    "addr:housenumber":"1331",
    "addr:postcode":"29205",
    "addr:street":"Hagood St",
    "iso:country":"US",
    "sg:address":"1331 Hagood St",
    "sg:city":"Columbia",
    "sg:classifiers":[
        {
            "category":"Professional",
            "subcategory":"Art Services",
            "type":"Services"
        }
    ],
    "sg:phone":"+1 803 771 7432",
    "sg:postcode":"29205",
    "sg:province":"SC",
    "sg:tags":[
        "photographer"
    ],
    "wof:name":"Photos By Crewe LLC",
    "wof:placetype":"venue"
},
  "geometry": {"coordinates":[-81.000207,34.006339],"type":"Point"}
}