{
  "type": "Feature",
  "properties": {
    "iso:country":"US",
    "sg:address":"180 Alabama St",
    "sg:city":"Spartanburg",
    "sg:classifiers":[
        {
            "category":"Professional",
            "subcategory":"Accounting & Tax Preparation",
            "type":"Services"
        }
    ],
    "sg:phone":"+1 864 573 9211",
    "sg:postcode":"29302",
    "sg:province":"SC",
    "sg:tags":[
        "accountant"
    ],
    "wof:name":"Gosnell Menard & Brooks",
    "wof:placetype":"venue"
},
  "geometry": {"coordinates":[-81.92504,34.951621],"type":"Point"}
}