{
  "type": "Feature",
  "properties": {
    "iso:country":"US",
    "sg:address":"101 Academy Ave",
    "sg:city":"Greenwood",
    "sg:classifiers":[
        {
            "category":"Health Services",
            "subcategory":"Hospital",
            "type":"Services"
        }
    ],
    "sg:phone":"+1 864 330 7500",
    "sg:postcode":"29646",
    "sg:province":"SC",
    "wof:name":"Outpatient Surgery Ctr",
    "wof:placetype":"venue"
},
  "geometry": {"coordinates":[-82.15369,34.178183],"type":"Point"}
}