{
  "type": "Feature",
  "properties": {
    "iso:country":"US",
    "sg:address":"4143 Azalea Dr",
    "sg:city":"Charleston",
    "sg:classifiers":[
        {
            "category":"Retail",
            "subcategory":"Repair Shop",
            "type":"Services"
        },
        {
            "category":"Wholesale",
            "subcategory":"Electrical",
            "type":"Manufacturing & Wholesale Goods"
        }
    ],
    "sg:phone":"+1 843 747 5670",
    "sg:postcode":"29405",
    "sg:province":"SC",
    "sg:tags":[
        "whole",
        "rebuilds",
        "electric",
        "motor",
        "rewinds"
    ],
    "wof:name":"Rewind Specialties Inc",
    "wof:placetype":"venue"
},
  "geometry": {"coordinates":[-80.002773,32.847086],"type":"Point"}
}