{
  "type": "Feature",
  "properties": {
    "iso:country":"US",
    "sg:address":"829 Friendship Rd",
    "sg:city":"Seneca",
    "sg:classifiers":[
        {
            "category":"Retail",
            "subcategory":"Auto Repair",
            "type":"Services"
        }
    ],
    "sg:phone":"+1 864 882 1177",
    "sg:postcode":"29678",
    "sg:province":"SC",
    "sg:tags":[
        "body",
        "automobile",
        "painting"
    ],
    "wof:name":"Gene Shipman Body Shop",
    "wof:placetype":"venue"
},
  "geometry": {"coordinates":[-82.928894,34.631462],"type":"Point"}
}