{
  "type": "Feature",
  "properties": {
    "addr:full":"1221 State Hwy 9 Byp Lancaster SC 29720",
    "addr:housenumber":"1221",
    "addr:postcode":"29720",
    "addr:street":"State Hwy 9 Byp",
    "iso:country":"US",
    "sg:address":"1221 State Hwy 9 Byp",
    "sg:city":"Lancaster",
    "sg:classifiers":[
        {
            "category":"Retail",
            "subcategory":"Auto Repair",
            "type":"Services"
        }
    ],
    "sg:phone":"+1 803 285 5598",
    "sg:postcode":"29720",
    "sg:province":"SC",
    "sg:tags":[
        "automobile",
        "lubrication"
    ],
    "wof:name":"By-Pass Fast Lube",
    "wof:placetype":"venue"
},
  "geometry": {"coordinates":[-80.797005,34.733328],"type":"Point"}
}