{
  "type": "Feature",
  "properties": {
    "iso:country":"US",
    "sg:address":"1720 Remount Rd",
    "sg:city":"North Charleston",
    "sg:classifiers":[
        {
            "category":"Building & Trades",
            "subcategory":"Equipment Rental",
            "type":"Services"
        }
    ],
    "sg:phone":"+1 843 744 8288",
    "sg:postcode":"29406",
    "sg:province":"SC",
    "sg:tags":[
        "party",
        "supply"
    ],
    "wof:name":"All Purpose Tents",
    "wof:placetype":"venue"
},
  "geometry": {"coordinates":[-80.006964,32.900341],"type":"Point"}
}