{
  "type": "Feature",
  "properties": {
    "iso:country":"US",
    "sg:address":"1475 E Liberty St",
    "sg:city":"York",
    "sg:classifiers":[
        {
            "category":"Education",
            "subcategory":"School",
            "type":"Public Place"
        }
    ],
    "sg:phone":"+1 803 684 9916",
    "sg:postcode":"29745",
    "sg:province":"SC",
    "sg:website":"www.york.k12.sc.us",
    "wof:name":"York School District 1",
    "wof:placetype":"venue"
},
  "geometry": {"coordinates":[-81.207145,34.984258],"type":"Point"}
}