{
  "type": "Feature",
  "properties": {
    "iso:country":"US",
    "sg:address":"1428 Smallwood Rd",
    "sg:city":"Ridgeway",
    "sg:classifiers":[
        {
            "category":"Building & Trades",
            "subcategory":"Construction",
            "type":"Services"
        }
    ],
    "sg:phone":"+1 803 337 8728",
    "sg:postcode":"29130",
    "sg:province":"SC",
    "sg:tags":[
        "home"
    ],
    "wof:name":"JMB Company",
    "wof:placetype":"venue"
},
  "geometry": {"coordinates":[-80.92439400000001,34.273089],"type":"Point"}
}