{
  "type": "Feature",
  "properties": {
    "iso:country":"US",
    "sg:address":"828 Saint Mark Rd",
    "sg:city":"Taylors",
    "sg:classifiers":[
        {
            "category":"Professional",
            "subcategory":"Art Services",
            "type":"Services"
        }
    ],
    "sg:phone":"+1 864 609 0525",
    "sg:postcode":"29687",
    "sg:province":"SC",
    "sg:tags":[
        "development",
        "package",
        "designing"
    ],
    "wof:name":"Numatech Industries Southeast",
    "wof:placetype":"venue"
},
  "geometry": {"coordinates":[-82.30057,34.951626],"type":"Point"}
}