{
  "type": "Feature",
  "properties": {
    "iso:country":"US",
    "sg:address":"11891 C R Koon Hwy",
    "sg:city":"Prosperity",
    "sg:classifiers":[
        {
            "category":"Food & Beverages",
            "subcategory":"Groceries & Convenience Stores",
            "type":"Retail Goods"
        }
    ],
    "sg:phone":"+1 803 364 2077",
    "sg:postcode":"29127",
    "sg:province":"SC",
    "sg:tags":[
        "product"
    ],
    "wof:name":"Pioneer Foods - South Carolina",
    "wof:placetype":"venue"
},
  "geometry": {"coordinates":[-81.549449,34.228296],"type":"Point"}
}