{
  "type": "Feature",
  "properties": {
    "iso:country":"US",
    "sg:address":"1306 N Sally Hill Rd",
    "sg:city":"Timmonsville",
    "sg:classifiers":[
        {
            "category":"Food & Beverages",
            "subcategory":"Groceries & Convenience Stores",
            "type":"Retail Goods"
        }
    ],
    "sg:phone":"+1 843 346 3541",
    "sg:postcode":"29161",
    "sg:province":"SC",
    "sg:tags":[
        "grocer"
    ],
    "wof:name":"S J Wilson Svc Ctr & Grocery",
    "wof:placetype":"venue"
},
  "geometry": {"coordinates":[-79.91405399999999,34.167404],"type":"Point"}
}