{
  "type": "Feature",
  "properties": {
    "iso:country":"US",
    "sg:address":"230 Ulmer Rd",
    "sg:city":"Bluffton",
    "sg:classifiers":[
        {
            "category":"Building & Trades",
            "subcategory":"Construction",
            "type":"Services"
        }
    ],
    "sg:phone":"+1 843 757 4226",
    "sg:postcode":"29910",
    "sg:province":"SC",
    "sg:tags":[
        "house",
        "builder",
        "home"
    ],
    "wof:name":"C B Home Builders Inc",
    "wof:placetype":"venue"
},
  "geometry": {"coordinates":[-80.84142300000001,32.21705],"type":"Point"}
}