{
  "type": "Feature",
  "properties": {
    "addr:full":"7109 Charleston Hwy Bowman SC 29018",
    "addr:housenumber":"7109",
    "addr:postcode":"29018",
    "addr:street":"Charleston Hwy",
    "iso:country":"US",
    "sg:address":"7109 Charleston Hwy",
    "sg:city":"Bowman",
    "sg:classifiers":[
        {
            "category":"Shopping",
            "subcategory":"Discount & Variety Stores",
            "type":"Retail Goods"
        }
    ],
    "sg:phone":"+1 803 829 2714",
    "sg:postcode":"29018",
    "sg:province":"SC",
    "wof:name":"Variety Dollar",
    "wof:placetype":"venue"
},
  "geometry": {"coordinates":[-80.681974,33.348467],"type":"Point"}
}