{
  "type": "Feature",
  "properties": {
    "addr:full":"302 Whit Chamblee Rd Starr SC 29684",
    "addr:housenumber":"302",
    "addr:postcode":"29684",
    "addr:street":"Whit Chamblee Rd",
    "iso:country":"US",
    "sg:address":"302 Whit Chamblee Rd",
    "sg:city":"Starr",
    "sg:classifiers":[
        {
            "category":"Manufacturing",
            "subcategory":"Lumber",
            "type":"Manufacturing & Wholesale Goods"
        }
    ],
    "sg:phone":"+1 864 352 6555",
    "sg:postcode":"29684",
    "sg:province":"SC",
    "sg:tags":[
        "operation",
        "timber",
        "tract"
    ],
    "wof:name":"Dwain Chamblee",
    "wof:placetype":"venue"
},
  "geometry": {"coordinates":[-82.68315800000001,34.351529],"type":"Point"}
}