{
  "type": "Feature",
  "properties": {
    "addr:full":"790 Monroe Hwy Lancaster SC 29720",
    "addr:housenumber":"790",
    "addr:postcode":"29720",
    "addr:street":"Monroe Hwy",
    "iso:country":"US",
    "sg:address":"790 Monroe Hwy",
    "sg:city":"Lancaster",
    "sg:classifiers":[
        {
            "category":"Building & Trades",
            "subcategory":"Pest Control",
            "type":"Services"
        }
    ],
    "sg:phone":"+1 803 285 7157",
    "sg:postcode":"29720",
    "sg:province":"SC",
    "wof:name":"Care Exterminating",
    "wof:placetype":"venue"
},
  "geometry": {"coordinates":[-80.75644200000001,34.760705],"type":"Point"}
}