{
  "type": "Feature",
  "properties": {
    "addr:full":"1566 Brennen Rd Columbia SC 29206",
    "addr:housenumber":"1566",
    "addr:postcode":"29206",
    "addr:street":"Brennen Rd",
    "iso:country":"US",
    "sg:address":"1566 Brennen Rd",
    "sg:city":"Columbia",
    "sg:classifiers":[
        {
            "category":"Personal",
            "type":"Services"
        }
    ],
    "sg:phone":"+1 803 790 0278",
    "sg:postcode":"29206",
    "sg:province":"SC",
    "sg:tags":[
        "consultant",
        "program",
        "health",
        "fitness"
    ],
    "wof:name":"Elizabeth H Bonniwell Conslnt",
    "wof:placetype":"venue"
},
  "geometry": {"coordinates":[-80.970214,34.008047],"type":"Point"}
}