{
  "type": "Feature",
  "properties": {
    "iso:country":"US",
    "sg:address":"1519 Executive Ave",
    "sg:city":"Myrtle Beach",
    "sg:classifiers":[
        {
            "category":"Professional",
            "type":"Services"
        }
    ],
    "sg:phone":"+1 843 626 7285",
    "sg:postcode":"29577",
    "sg:province":"SC",
    "sg:tags":[
        "establishment"
    ],
    "wof:name":"Gsrmc Archives",
    "wof:placetype":"venue"
},
  "geometry": {"coordinates":[-78.901159,33.702402],"type":"Point"}
}