{
  "type": "Feature",
  "properties": {
    "iso:country":"US",
    "sg:address":"311 Independence Ave",
    "sg:city":"Lake City",
    "sg:classifiers":[
        {
            "category":"Wholesale",
            "subcategory":"Machinery & Supplies",
            "type":"Manufacturing & Wholesale Goods"
        }
    ],
    "sg:phone":"+1 843 394 3766",
    "sg:postcode":"29560",
    "sg:province":"SC",
    "sg:tags":[
        "equipment",
        "establishment"
    ],
    "wof:name":"JW Fashions Unlimited",
    "wof:placetype":"venue"
},
  "geometry": {"coordinates":[-79.77258399999999,33.864367],"type":"Point"}
}