{
  "type": "Feature",
  "properties": {
    "addr:full":"704 43rd Ave S North Myrtle Bch SC 29582",
    "addr:housenumber":"704",
    "addr:postcode":"29582",
    "addr:street":"43Rd Ave S North Myrtle",
    "iso:country":"US",
    "sg:address":"704 43rd Ave S",
    "sg:city":"North Myrtle Bch",
    "sg:classifiers":[
        {
            "category":"Wholesale",
            "subcategory":"Construction Materials",
            "type":"Manufacturing & Wholesale Goods"
        },
        {
            "category":"Real Estate",
            "subcategory":"Real Estate Agent",
            "type":"Services"
        }
    ],
    "sg:phone":"+1 843 361 1244",
    "sg:postcode":"29582",
    "sg:province":"SC",
    "sg:tags":[
        "manufactured",
        "housing",
        "broker"
    ],
    "wof:name":"Sebrite Financial Corporation",
    "wof:placetype":"venue"
},
  "geometry": {"coordinates":[-78.729356,33.79901],"type":"Point"}
}