{
  "type": "Feature",
  "properties": {
    "addr:full":"545 US Hwy 25 Travelers Rest SC 29690",
    "addr:housenumber":"545",
    "addr:postcode":"29690",
    "addr:street":"Us Hwy 25",
    "iso:country":"US",
    "sg:address":"545 US Hwy 25",
    "sg:city":"Travelers Rest",
    "sg:classifiers":[
        {
            "category":"Restaurant",
            "type":"Food & Drink"
        }
    ],
    "sg:phone":"+1 864 834 1007",
    "sg:postcode":"29690",
    "sg:province":"SC",
    "sg:tags":[
        "eating"
    ],
    "wof:name":"Classic Cafe",
    "wof:placetype":"venue"
},
  "geometry": {"coordinates":[-82.42400600000001,34.984227],"type":"Point"}
}