{
  "type": "Feature",
  "properties": {
    "addr:full":"1121 State Hwy 292 Inman SC 29349",
    "addr:housenumber":"1121",
    "addr:postcode":"29349",
    "addr:street":"State Hwy 292",
    "iso:country":"US",
    "sg:address":"1121 State Hwy 292",
    "sg:city":"Inman",
    "sg:classifiers":[
        {
            "category":"Mining & Drilling",
            "type":"Manufacturing & Wholesale Goods"
        }
    ],
    "sg:phone":"+1 864 473 1646",
    "sg:postcode":"29349",
    "sg:province":"SC",
    "sg:tags":[
        "stone"
    ],
    "wof:name":"Inman Stone Co",
    "wof:placetype":"venue"
},
  "geometry": {"coordinates":[-82.075514,35.071424],"type":"Point"}
}