{
  "type": "Feature",
  "properties": {
    "addr:full":"9093 Old State Rd Holly Hill SC 29059",
    "addr:housenumber":"9093",
    "addr:postcode":"29059",
    "addr:street":"Old State Rd",
    "iso:country":"US",
    "sg:address":"9093 Old State Rd",
    "sg:city":"Holly Hill",
    "sg:classifiers":[
        {
            "category":"Retail",
            "subcategory":"Auto Repair",
            "type":"Services"
        }
    ],
    "sg:phone":"+1 803 496 7697",
    "sg:postcode":"29059",
    "sg:province":"SC",
    "sg:tags":[
        "repairing",
        "automobile"
    ],
    "wof:name":"Austin's Auto Svc",
    "wof:placetype":"venue"
},
  "geometry": {"coordinates":[-80.393809,33.309359],"type":"Point"}
}