{
  "type": "Feature",
  "properties": {
    "addr:full":"155 Varnfield Dr Summerville SC 29483",
    "addr:housenumber":"155",
    "addr:postcode":"29483",
    "addr:street":"Varnfield Dr",
    "iso:country":"US",
    "sg:address":"155 Varnfield Dr",
    "sg:city":"Summerville",
    "sg:classifiers":[
        {
            "category":"Building & Trades",
            "subcategory":"Plumbing",
            "type":"Services"
        }
    ],
    "sg:phone":"+1 843 821 0937",
    "sg:postcode":"29483",
    "sg:province":"SC",
    "sg:tags":[
        "conditioning",
        "air",
        "system",
        "contractor"
    ],
    "sg:website":"www.arcticairinc.com",
    "wof:name":"Arctic Air Inc",
    "wof:placetype":"venue"
},
  "geometry": {"coordinates":[-80.163262,33.03624],"type":"Point"}
}