{
  "type": "Feature",
  "properties": {
    "addr:full":"103 E Madison St Dillon SC 29536",
    "addr:housenumber":"103",
    "addr:postcode":"29536",
    "addr:street":"E Madison St",
    "iso:country":"US",
    "sg:address":"103 E Madison St",
    "sg:city":"Dillon",
    "sg:classifiers":[
        {
            "category":"Government",
            "subcategory":"Office",
            "type":"Public Place"
        }
    ],
    "sg:phone":"+1 843 774 5138",
    "sg:postcode":"29536",
    "sg:province":"SC",
    "sg:tags":[
        "federal",
        "human"
    ],
    "wof:name":"US Social Security Adm",
    "wof:placetype":"venue"
},
  "geometry": {"coordinates":[-79.36712199999999,34.423025],"type":"Point"}
}