{
  "type": "Feature",
  "properties": {
    "addr:full":"3600 Kennerly Rd Orangeburg SC 29118",
    "addr:postcode":"3600;29118",
    "addr:street":"Kennerly Rd",
    "iso:country":"US",
    "sg:address":"3600 Kennerly Rd",
    "sg:city":"Orangeburg",
    "sg:classifiers":[
        {
            "category":"Shopping",
            "type":"Retail Goods"
        }
    ],
    "sg:phone":"+1 803 536 1150",
    "sg:postcode":"29118",
    "sg:province":"SC",
    "sg:tags":[
        "merchandise"
    ],
    "wof:name":"Nettles Tele Cmmncations Servi",
    "wof:placetype":"venue"
},
  "geometry": {"coordinates":[-80.903549,33.556712],"type":"Point"}
}