{
  "type": "Feature",
  "properties": {
    "iso:country":"US",
    "sg:address":"219 Pendleton St",
    "sg:city":"Pickens",
    "sg:classifiers":[
        {
            "category":"Government",
            "subcategory":"Office",
            "type":"Public Place"
        }
    ],
    "sg:phone":"+1 864 878 4018",
    "sg:postcode":"29671",
    "sg:province":"SC",
    "sg:tags":[
        "city"
    ],
    "wof:name":"Pickens Mayor's Office",
    "wof:placetype":"venue"
},
  "geometry": {"coordinates":[-82.706552,34.882311],"type":"Point"}
}