{
  "type": "Feature",
  "properties": {
    "iso:country":"US",
    "sg:address":"404 E Poinsett St",
    "sg:city":"Greer",
    "sg:classifiers":[
        {
            "category":"Shopping",
            "subcategory":"Clothing, Apparel, & Fashions",
            "type":"Retail Goods"
        }
    ],
    "sg:phone":"+1 864 848 0670",
    "sg:postcode":"29651",
    "sg:province":"SC",
    "wof:name":"Karina & Jobana Fashion",
    "wof:placetype":"venue"
},
  "geometry": {"coordinates":[-82.222443,34.936363],"type":"Point"}
}