{
  "type": "Feature",
  "properties": {
    "iso:country":"US",
    "sg:address":"1175 Folly Rd",
    "sg:city":"Charleston",
    "sg:classifiers":[
        {
            "category":"Banks & Credit Unions",
            "subcategory":"Bank",
            "type":"Services"
        }
    ],
    "sg:phone":"+1 843 406 4986",
    "sg:postcode":"29412",
    "sg:province":"SC",
    "sg:tags":[
        "cashing",
        "check"
    ],
    "wof:name":"Check Into Cash",
    "wof:placetype":"venue"
},
  "geometry": {"coordinates":[-79.96739100000001,32.724514],"type":"Point"}
}