{
  "type": "Feature",
  "properties": {
    "iso:country":"US",
    "sg:address":"1319 Ladys Island Dr",
    "sg:city":"Port Royal",
    "sg:classifiers":[
        {
            "category":"Health Services",
            "subcategory":"Doctor",
            "type":"Services"
        }
    ],
    "sg:phone":"+1 843 524 6736",
    "sg:postcode":"29935",
    "sg:province":"SC",
    "sg:tags":[
        "physician",
        "surgeon"
    ],
    "wof:name":"Beaufort Open MRI",
    "wof:placetype":"venue"
},
  "geometry": {"coordinates":[-80.68437299999999,32.394441],"type":"Point"}
}