{
  "type": "Feature",
  "properties": {
    "iso:country":"US",
    "sg:address":"11 Penny Ln",
    "sg:city":"Pawleys Island",
    "sg:classifiers":[
        {
            "category":"Sports & Exercise",
            "subcategory":"Golf",
            "type":"Entertainment"
        }
    ],
    "sg:phone":"+1 843 237 8880",
    "sg:postcode":"29585",
    "sg:province":"SC",
    "sg:tags":[
        "course"
    ],
    "sg:website":"www.mbn.com",
    "wof:name":"River Club",
    "wof:placetype":"venue"
},
  "geometry": {"coordinates":[-79.141396,33.459768],"type":"Point"}
}