{
  "type": "Feature",
  "properties": {
    "iso:country":"US",
    "sg:address":"503 2nd Loop Rd",
    "sg:city":"Florence",
    "sg:classifiers":[
        {
            "category":"Retail",
            "subcategory":"Laundry & Dry Cleaning",
            "type":"Services"
        }
    ],
    "sg:phone":"+1 843 292 0411",
    "sg:postcode":"29505",
    "sg:province":"SC",
    "sg:tags":[
        "cleaners"
    ],
    "wof:name":"Cappi's Cleaners",
    "wof:placetype":"venue"
},
  "geometry": {"coordinates":[-79.77239899999999,34.167188],"type":"Point"}
}