{
  "type": "Feature",
  "properties": {
    "addr:full":"112 S Parler Ave St George SC 29477",
    "addr:housenumber":"112",
    "addr:postcode":"29477",
    "addr:street":"S Parler Ave",
    "iso:country":"US",
    "sg:address":"112 S Parler Ave",
    "sg:city":"St George",
    "sg:classifiers":[
        {
            "category":"Retail",
            "subcategory":"Auto Repair",
            "type":"Services"
        }
    ],
    "sg:phone":"+1 843 563 5025",
    "sg:postcode":"29477",
    "sg:province":"SC",
    "sg:tags":[
        "wrecker"
    ],
    "wof:name":"David Colson's Towing & Repair",
    "wof:placetype":"venue"
},
  "geometry": {"coordinates":[-80.57441,33.18313],"type":"Point"}
}