{
  "type": "Feature",
  "properties": {
    "iso:country":"US",
    "sg:address":"210 Colchester Dr",
    "sg:city":"Columbia",
    "sg:classifiers":[
        {
            "category":"Retail",
            "subcategory":"Car Wash",
            "type":"Services"
        }
    ],
    "sg:phone":"+1 803 788 5962",
    "sg:postcode":"29223",
    "sg:province":"SC",
    "sg:tags":[
        "automobile",
        "detail",
        "clean"
    ],
    "wof:name":"Your Place Vehicle Detail",
    "wof:placetype":"venue"
},
  "geometry": {"coordinates":[-80.902305,34.132799],"type":"Point"}
}