{
  "type": "Feature",
  "properties": {
    "iso:country":"US",
    "sg:address":"3140 Quandry Rd",
    "sg:city":"Sumter",
    "sg:classifiers":[
        {
            "category":"Manufacturing",
            "subcategory":"Metals",
            "type":"Manufacturing & Wholesale Goods"
        }
    ],
    "sg:phone":"+1 803 494 8698",
    "sg:postcode":"29150",
    "sg:province":"SC",
    "sg:tags":[
        "fabricator",
        "sheet"
    ],
    "wof:name":"Harrington's Metal Shop",
    "wof:placetype":"venue"
},
  "geometry": {"coordinates":[-80.418132,33.960682],"type":"Point"}
}