{
  "type": "Feature",
  "properties": {
    "iso:country":"US",
    "sg:address":"10210 Two Notch Rd",
    "sg:city":"Columbia",
    "sg:classifiers":[
        {
            "category":"Personal",
            "subcategory":"Beauty Salon",
            "type":"Services"
        }
    ],
    "sg:phone":"+1 803 865 8885",
    "sg:postcode":"29229",
    "sg:province":"SC",
    "sg:website":"www.sportclips.com",
    "wof:name":"Sport Clips",
    "wof:placetype":"venue"
},
  "geometry": {"coordinates":[-80.87926299999999,34.118808],"type":"Point"}
}