{
  "type": "Feature",
  "properties": {
    "iso:country":"US",
    "sg:address":"3231 Ladson Rd",
    "sg:city":"Ladson",
    "sg:classifiers":[
        {
            "category":"Organizations",
            "subcategory":"Religious Organization",
            "type":"Services"
        }
    ],
    "sg:phone":"+1 843 797 1014",
    "sg:postcode":"29456",
    "sg:province":"SC",
    "sg:tags":[
        "church"
    ],
    "wof:name":"Ladson Baptist Church",
    "wof:placetype":"venue"
},
  "geometry": {"coordinates":[-80.098862,32.98789],"type":"Point"}
}