{
  "type": "Feature",
  "properties": {
    "iso:country":"US",
    "sg:address":"72 S Boundary St",
    "sg:city":"Bamberg",
    "sg:classifiers":[
        {
            "category":"Organizations",
            "subcategory":"Religious Organization",
            "type":"Services"
        }
    ],
    "sg:phone":"+1 803 245 7040",
    "sg:postcode":"29075",
    "sg:province":"SC",
    "sg:tags":[
        "church"
    ],
    "wof:name":"Lemon Swamp Missionary Bapt",
    "wof:placetype":"venue"
},
  "geometry": {"coordinates":[-81.411523,34.195114],"type":"Point"}
}