{
  "type": "Feature",
  "properties": {
    "addr:full":"1975 Magwood Dr Charleston SC 29414",
    "addr:housenumber":"1975",
    "addr:postcode":"29414",
    "addr:street":"Magwood Dr",
    "iso:country":"US",
    "sg:address":"1975 Magwood Dr",
    "sg:city":"Charleston",
    "sg:classifiers":[
        {
            "category":"Banks & Credit Unions",
            "subcategory":"Investment Brokerage",
            "type":"Services"
        }
    ],
    "sg:phone":"+1 843 766 4978",
    "sg:postcode":"29414",
    "sg:province":"SC",
    "sg:tags":[
        "security"
    ],
    "wof:name":"Edward Jones Co",
    "wof:placetype":"venue"
},
  "geometry": {"coordinates":[-80.04133400000001,32.814821],"type":"Point"}
}