{
  "type": "Feature",
  "properties": {
    "iso:country":"US",
    "sg:address":"10060 Long Creek Hwy",
    "sg:city":"Westminster",
    "sg:classifiers":[
        {
            "category":"Home & Garden",
            "subcategory":"Furniture",
            "type":"Retail Goods"
        }
    ],
    "sg:phone":"+1 864 647 4707",
    "sg:postcode":"29693",
    "sg:province":"SC",
    "wof:name":"Swing-O-Things Inc",
    "wof:placetype":"venue"
},
  "geometry": {"coordinates":[-83.153998,34.685057],"type":"Point"}
}