{
  "type": "Feature",
  "properties": {
    "addr:full":"1263 Edgefield Hwy Aiken SC 29801",
    "addr:housenumber":"1263",
    "addr:postcode":"29801",
    "addr:street":"Edgefield Hwy",
    "iso:country":"US",
    "sg:address":"1263 Edgefield Hwy",
    "sg:city":"Aiken",
    "sg:classifiers":[
        {
            "category":"Personal",
            "subcategory":"Beauty Salon",
            "type":"Services"
        }
    ],
    "sg:phone":"+1 803 642 1269",
    "sg:postcode":"29801",
    "sg:province":"SC",
    "wof:name":"En-Vogue Styling Salon",
    "wof:placetype":"venue"
},
  "geometry": {"coordinates":[-81.724484,33.592532],"type":"Point"}
}