{
  "type": "Feature",
  "properties": {
    "iso:country":"US",
    "sg:address":"117 Hugh Ln",
    "sg:city":"Pauline",
    "sg:classifiers":[
        {
            "category":"Shopping",
            "type":"Retail Goods"
        }
    ],
    "sg:phone":"+1 864 582 5854",
    "sg:postcode":"29374",
    "sg:province":"SC",
    "sg:tags":[
        "merchandise"
    ],
    "wof:name":"Pauline General Store Inc",
    "wof:placetype":"venue"
},
  "geometry": {"coordinates":[-81.816363,34.787934],"type":"Point"}
}