{
  "type": "Feature",
  "properties": {
    "addr:full":"704 N A St Easley SC 29640",
    "addr:housenumber":"704",
    "addr:postcode":"29640",
    "addr:street":"N A St",
    "iso:country":"US",
    "sg:address":"704 N A St",
    "sg:city":"Easley",
    "sg:classifiers":[
        {
            "category":"Health Services",
            "subcategory":"Doctor",
            "type":"Services"
        }
    ],
    "sg:phone":"+1 864 855 4431",
    "sg:postcode":"29640",
    "sg:province":"SC",
    "sg:tags":[
        "physician",
        "surgeon"
    ],
    "wof:name":"Easley Orthopaedic",
    "wof:placetype":"venue"
},
  "geometry": {"coordinates":[-82.603483,34.835473],"type":"Point"}
}