{
  "type": "Feature",
  "properties": {
    "addr:full":"444 Sease Hill Rd Lexington SC 29073",
    "addr:housenumber":"444",
    "addr:postcode":"29073",
    "addr:street":"Sease Hill Rd",
    "iso:country":"US",
    "sg:address":"444 Sease Hill Rd",
    "sg:city":"Lexington",
    "sg:classifiers":[
        {
            "category":"Retail",
            "subcategory":"Auto Repair",
            "type":"Services"
        }
    ],
    "sg:phone":"+1 803 957 3837",
    "sg:postcode":"29073",
    "sg:province":"SC",
    "sg:tags":[
        "repairing",
        "automobile"
    ],
    "wof:name":"Sease's Automotive Svc",
    "wof:placetype":"venue"
},
  "geometry": {"coordinates":[-81.24464999999999,33.934477],"type":"Point"}
}