{
  "type": "Feature",
  "properties": {
    "iso:country":"US",
    "sg:address":"110 Maiden Ln",
    "sg:city":"Lexington",
    "sg:classifiers":[
        {
            "category":"Recreation",
            "type":"Entertainment"
        }
    ],
    "sg:phone":"+1 803 359 1027",
    "sg:postcode":"29072",
    "sg:province":"SC",
    "sg:tags":[
        "parks"
    ],
    "sg:website":"www.lexsc.com",
    "wof:name":"Lexington Parks Ofc",
    "wof:placetype":"venue"
},
  "geometry": {"coordinates":[-81.237483,33.980555],"type":"Point"}
}