{
  "type": "Feature",
  "properties": {
    "iso:country":"US",
    "sg:address":"4331 Highway 24",
    "sg:city":"Anderson",
    "sg:classifiers":[
        {
            "category":"Retail",
            "subcategory":"Auto Repair",
            "type":"Services"
        }
    ],
    "sg:phone":"+1 864 225 4091",
    "sg:postcode":"29626",
    "sg:province":"SC",
    "sg:tags":[
        "body",
        "automobile",
        "painting",
        "repairing"
    ],
    "wof:name":"Troy Masters Autobody and Marine",
    "wof:placetype":"venue"
},
  "geometry": {"coordinates":[-82.746521,34.50856],"type":"Point"}
}