{
  "type": "Feature",
  "properties": {
    "addr:full":"5192 Calhoun Memorial Hwy Easley SC 29640",
    "addr:housenumber":"5192",
    "addr:postcode":"29640",
    "addr:street":"Calhoun Memorial Hwy",
    "iso:country":"US",
    "sg:address":"5192 Calhoun Memorial Hwy",
    "sg:city":"Easley",
    "sg:classifiers":[
        {
            "category":"Restaurant",
            "type":"Food & Drink"
        }
    ],
    "sg:phone":"+1 864 855 0533",
    "sg:postcode":"29640",
    "sg:province":"SC",
    "wof:name":"Carolina Creme Inc",
    "wof:placetype":"venue"
},
  "geometry": {"coordinates":[-82.558035,34.82465],"type":"Point"}
}