{
  "type": "Feature",
  "properties": {
    "addr:full":"355 S Georgetown Hwy Johnsonville SC 29555",
    "addr:housenumber":"355",
    "addr:postcode":"29555",
    "addr:street":"S Georgetown Hwy",
    "iso:country":"US",
    "sg:address":"355 S Georgetown Hwy",
    "sg:city":"Johnsonville",
    "sg:classifiers":[
        {
            "category":"Health Services",
            "subcategory":"Doctor",
            "type":"Services"
        }
    ],
    "sg:phone":"+1 843 380 2000",
    "sg:postcode":"29555",
    "sg:province":"SC",
    "sg:tags":[
        "physician",
        "surgeon"
    ],
    "wof:name":"Mc Leod Family Medicine",
    "wof:placetype":"venue"
},
  "geometry": {"coordinates":[-79.442234,33.81179],"type":"Point"}
}