{
  "type": "Feature",
  "properties": {
    "addr:full":"2352 Pamplico Hwy Florence SC 29505",
    "addr:housenumber":"2352",
    "addr:postcode":"29505",
    "addr:street":"Pamplico Hwy",
    "iso:country":"US",
    "sg:address":"2352 Pamplico Hwy",
    "sg:city":"Florence",
    "sg:classifiers":[
        {
            "category":"Food & Beverages",
            "subcategory":"Groceries & Convenience Stores",
            "type":"Retail Goods"
        }
    ],
    "sg:phone":"+1 843 667 0515",
    "sg:postcode":"29505",
    "sg:province":"SC",
    "wof:name":"Pantry 317 The",
    "wof:placetype":"venue"
},
  "geometry": {"coordinates":[-79.728222,34.145421],"type":"Point"}
}