{
  "type": "Feature",
  "properties": {
    "iso:country":"US",
    "sg:address":"214 Whitney St",
    "sg:city":"Slater",
    "sg:classifiers":[
        {
            "category":"Building & Trades",
            "subcategory":"Plumbing",
            "type":"Services"
        }
    ],
    "sg:phone":"+1 864 836 0814",
    "sg:postcode":"29683",
    "sg:province":"SC",
    "sg:tags":[
        "contractor"
    ],
    "wof:name":"Temple Heating & AC",
    "wof:placetype":"venue"
},
  "geometry": {"coordinates":[-82.492847,35.031262],"type":"Point"}
}