{
  "type": "Feature",
  "properties": {
    "iso:country":"US",
    "sg:address":"200 Patewood Dr",
    "sg:city":"Greenville",
    "sg:classifiers":[
        {
            "category":"Health Services",
            "subcategory":"Doctor",
            "type":"Services"
        }
    ],
    "sg:phone":"+1 864 454 5130",
    "sg:postcode":"29615",
    "sg:province":"SC",
    "sg:tags":[
        "physician",
        "surgeon"
    ],
    "wof:name":"Pediatric Cardiology",
    "wof:placetype":"venue"
},
  "geometry": {"coordinates":[-82.326245,34.853403],"type":"Point"}
}