{
  "type": "Feature",
  "properties": {
    "addr:full":"707 Edwards Rd Greenville SC 29615",
    "addr:housenumber":"707",
    "addr:postcode":"29615",
    "addr:street":"Edwards Rd",
    "iso:country":"US",
    "sg:address":"707 Edwards Rd",
    "sg:city":"Greenville",
    "sg:classifiers":[
        {
            "category":"Shopping",
            "type":"Retail Goods"
        }
    ],
    "sg:phone":"+1 864 292 8958",
    "sg:postcode":"29615",
    "sg:province":"SC",
    "sg:tags":[
        "picture",
        "frame"
    ],
    "wof:name":"Garden Frame Shop",
    "wof:placetype":"venue"
},
  "geometry": {"coordinates":[-82.347621,34.882888],"type":"Point"}
}