{
  "type": "Feature",
  "properties": {
    "iso:country":"US",
    "sg:address":"315 W Franklin St",
    "sg:city":"Anderson",
    "sg:classifiers":[
        {
            "category":"Personal",
            "subcategory":"Barber",
            "type":"Services"
        }
    ],
    "sg:phone":"+1 864 225 1865",
    "sg:postcode":"29624",
    "sg:province":"SC",
    "wof:name":"West Side Barber Shop",
    "wof:placetype":"venue"
},
  "geometry": {"coordinates":[-82.651261,34.496537],"type":"Point"}
}