{
  "type": "Feature",
  "properties": {
    "addr:full":"106 W Gay St Lancaster SC 29720",
    "addr:housenumber":"106",
    "addr:postcode":"29720",
    "addr:street":"W Gay St",
    "iso:country":"US",
    "sg:address":"106 W Gay St",
    "sg:city":"Lancaster",
    "sg:classifiers":[
        {
            "category":"Personal",
            "type":"Services"
        }
    ],
    "sg:phone":"+1 803 283 4689",
    "sg:postcode":"29720",
    "sg:province":"SC",
    "sg:tags":[
        "wear",
        "formal"
    ],
    "wof:name":"Dianne Shop",
    "wof:placetype":"venue"
},
  "geometry": {"coordinates":[-80.770054,34.718938],"type":"Point"}
}