{
  "type": "Feature",
  "properties": {
    "addr:full":"702 Railroad Ave Summerville SC 29485",
    "addr:housenumber":"702",
    "addr:postcode":"29485",
    "addr:street":"Railroad Ave",
    "iso:country":"US",
    "sg:address":"702 Railroad Ave",
    "sg:city":"Summerville",
    "sg:classifiers":[
        {
            "category":"Social Services",
            "subcategory":"Adult Care",
            "type":"Services"
        }
    ],
    "sg:phone":"+1 843 821 9608",
    "sg:postcode":"29485",
    "sg:province":"SC",
    "sg:tags":[
        "home",
        "residential"
    ],
    "wof:name":"Nichols Residential Care",
    "wof:placetype":"venue"
},
  "geometry": {"coordinates":[-80.15813,33.011606],"type":"Point"}
}