{
  "type": "Feature",
  "properties": {
    "addr:full":"104 Gainesborough Dr Goose Creek SC 29445",
    "addr:housenumber":"104",
    "addr:postcode":"29445",
    "addr:street":"Gainesborough Dr",
    "iso:country":"US",
    "sg:address":"104 Gainesborough Dr",
    "sg:city":"Goose Creek",
    "sg:classifiers":[
        {
            "category":"Real Estate",
            "subcategory":"Real Estate Operator",
            "type":"Services"
        }
    ],
    "sg:phone":"+1 843 797 3005",
    "sg:postcode":"29445",
    "sg:province":"SC",
    "sg:tags":[
        "building",
        "apartment"
    ],
    "wof:name":"Coventry Green Apartments",
    "wof:placetype":"venue"
},
  "geometry": {"coordinates":[-80.054648,33.023387],"type":"Point"}
}