{
  "type": "Feature",
  "properties": {
    "iso:country":"US",
    "sg:address":"308 Stinson Dr",
    "sg:city":"Charleston",
    "sg:classifiers":[
        {
            "category":"Building & Trades",
            "subcategory":"Cleaning & Sanitation",
            "type":"Services"
        }
    ],
    "sg:phone":"+1 843 769 7697",
    "sg:postcode":"29407",
    "sg:province":"SC",
    "sg:tags":[
        "butler",
        "maid"
    ],
    "wof:name":"Debbie Does Charleston Clng",
    "wof:placetype":"venue"
},
  "geometry": {"coordinates":[-80.026415,32.781977],"type":"Point"}
}