{
  "type": "Feature",
  "properties": {
    "addr:full":"6890 S Pine St Pacolet SC 29372",
    "addr:housenumber":"6890",
    "addr:postcode":"29372",
    "addr:street":"S Pine St",
    "iso:country":"US",
    "sg:address":"6890 S Pine St",
    "sg:city":"Pacolet",
    "sg:classifiers":[
        {
            "category":"Shopping",
            "subcategory":"Department Store",
            "type":"Retail Goods"
        }
    ],
    "sg:phone":"+1 864 474 9789",
    "sg:postcode":"29372",
    "sg:province":"SC",
    "sg:tags":[
        "shop"
    ],
    "wof:name":"Dollar General",
    "wof:placetype":"venue"
},
  "geometry": {"coordinates":[-81.768767,34.899252],"type":"Point"}
}