{
  "type": "Feature",
  "properties": {
    "iso:country":"US",
    "sg:address":"9 Polatty St",
    "sg:city":"Warrenville",
    "sg:classifiers":[
        {
            "category":"Organizations",
            "subcategory":"Religious Organization",
            "type":"Services"
        }
    ],
    "sg:phone":"+1 803 663 7753",
    "sg:postcode":"29851",
    "sg:province":"SC",
    "sg:tags":[
        "church"
    ],
    "sg:website":"www.warrenvillerevivalcenter.org",
    "wof:name":"Warrenville Revival Ctr Chr",
    "wof:placetype":"venue"
},
  "geometry": {"coordinates":[-81.80583,33.545737],"type":"Point"}
}