{
  "type": "Feature",
  "properties": {
    "iso:country":"US",
    "sg:address":"37 Brinton Hite Rd",
    "sg:city":"Prosperity",
    "sg:classifiers":[
        {
            "category":"Farming",
            "subcategory":"Livestock Farm",
            "type":"Manufacturing & Wholesale Goods"
        }
    ],
    "sg:phone":"+1 803 364 2185",
    "sg:postcode":"29127",
    "sg:province":"SC",
    "sg:tags":[
        "beef",
        "feedlot",
        "cattle"
    ],
    "wof:name":"Johnny Buzhardt",
    "wof:placetype":"venue"
},
  "geometry": {"coordinates":[-81.566547,34.137083],"type":"Point"}
}