{
  "type": "Feature",
  "properties": {
    "iso:country":"US",
    "sg:address":"702 Seaboard St",
    "sg:city":"Myrtle Beach",
    "sg:classifiers":[
        {
            "category":"Building & Trades",
            "subcategory":"Construction",
            "type":"Services"
        }
    ],
    "sg:phone":"+1 843 445 7575",
    "sg:postcode":"29577",
    "sg:province":"SC",
    "sg:tags":[
        "steel",
        "fabrication",
        "welding"
    ],
    "wof:name":"Hot Steel Jewelry",
    "wof:placetype":"venue"
},
  "geometry": {"coordinates":[-78.903853,33.708718],"type":"Point"}
}