{
  "type": "Feature",
  "properties": {
    "addr:full":"112 Ayers Cir Summerville SC 29485",
    "addr:housenumber":"112",
    "addr:postcode":"29485",
    "addr:street":"Ayers Cir",
    "iso:country":"US",
    "sg:address":"112 Ayers Cir",
    "sg:city":"Summerville",
    "sg:classifiers":[
        {
            "category":"Home & Garden",
            "subcategory":"Home Furnishings",
            "type":"Retail Goods"
        }
    ],
    "sg:phone":"+1 843 817 6731",
    "sg:postcode":"29485",
    "sg:province":"SC",
    "sg:tags":[
        "pottery"
    ],
    "wof:name":"Mc Cauley Pottery",
    "wof:placetype":"venue"
},
  "geometry": {"coordinates":[-80.198194,32.985397],"type":"Point"}
}