{
  "type": "Feature",
  "properties": {
    "iso:country":"US",
    "sg:address":"4404 Jefferson Davis Hwy",
    "sg:city":"Beech Island",
    "sg:classifiers":[
        {
            "category":"Restaurant",
            "type":"Food & Drink"
        }
    ],
    "sg:phone":"+1 803 593 2952",
    "sg:postcode":"29842",
    "sg:province":"SC",
    "sg:tags":[
        "eating"
    ],
    "wof:name":"Newman's Barbecue",
    "wof:placetype":"venue"
},
  "geometry": {"coordinates":[-81.90075400000001,33.503975],"type":"Point"}
}