{
  "type": "Feature",
  "properties": {
    "iso:country":"US",
    "sg:address":"4495 Jones Rd",
    "sg:city":"Myrtle Beach",
    "sg:classifiers":[
        {
            "category":"Retail",
            "subcategory":"Animal Services",
            "type":"Services"
        }
    ],
    "sg:phone":"+1 843 236 4171",
    "sg:postcode":"29588",
    "sg:province":"SC",
    "sg:tags":[
        "breeder",
        "horse"
    ],
    "wof:name":"Rabbits Galore",
    "wof:placetype":"venue"
},
  "geometry": {"coordinates":[-79.02106499999999,33.698355],"type":"Point"}
}