{
  "type": "Feature",
  "properties": {
    "iso:country":"US",
    "sg:address":"106 Barkwood Dr",
    "sg:city":"Greenwood",
    "sg:classifiers":[
        {
            "category":"Real Estate",
            "subcategory":"Real Estate Operator",
            "type":"Services"
        }
    ],
    "sg:phone":"+1 864 223 6285",
    "sg:postcode":"29649",
    "sg:province":"SC",
    "sg:tags":[
        "apartment"
    ],
    "wof:name":"Pinetree Apartments",
    "wof:placetype":"venue"
},
  "geometry": {"coordinates":[-82.191941,34.210643],"type":"Point"}
}