{
  "type": "Feature",
  "properties": {
    "addr:full":"6396 Valley Farm Rd Seneca SC 29678",
    "addr:housenumber":"6396",
    "addr:postcode":"29678",
    "addr:street":"Valley Farm Rd",
    "iso:country":"US",
    "sg:address":"6396 Valley Farm Rd",
    "sg:city":"Seneca",
    "sg:classifiers":[
        {
            "category":"Professional",
            "type":"Services"
        }
    ],
    "sg:phone":"+1 864 972 9012",
    "sg:postcode":"29678",
    "sg:province":"SC",
    "sg:tags":[
        "establishment"
    ],
    "wof:name":"Consolidated Hydro",
    "wof:placetype":"venue"
},
  "geometry": {"coordinates":[-82.972067,34.624644],"type":"Point"}
}