{
  "type": "Feature",
  "properties": {
    "iso:country":"US",
    "sg:address":"955 Park St",
    "sg:city":"Columbia",
    "sg:classifiers":[
        {
            "category":"Government",
            "subcategory":"Office",
            "type":"Public Place"
        }
    ],
    "sg:phone":"+1 803 737 1767",
    "sg:postcode":"29201",
    "sg:province":"SC",
    "sg:tags":[
        "state",
        "program"
    ],
    "wof:name":"Motor Vehicle Svc",
    "wof:placetype":"venue"
},
  "geometry": {"coordinates":[-81.035416,33.996657],"type":"Point"}
}