{
  "type": "Feature",
  "properties": {
    "addr:full":"101 Forest View Cir Liberty SC 29657",
    "addr:housenumber":"101",
    "addr:postcode":"29657",
    "addr:street":"Forest View Cir",
    "iso:country":"US",
    "sg:address":"101 Forest View Cir",
    "sg:city":"Liberty",
    "sg:classifiers":[
        {
            "category":"Real Estate",
            "subcategory":"Real Estate Operator",
            "type":"Services"
        }
    ],
    "sg:phone":"+1 864 843 9755",
    "sg:postcode":"29657",
    "sg:province":"SC",
    "sg:tags":[
        "apartment"
    ],
    "wof:name":"Forest View Apartments",
    "wof:placetype":"venue"
},
  "geometry": {"coordinates":[-82.707335,34.786798],"type":"Point"}
}