{
  "type": "Feature",
  "properties": {
    "iso:country":"US",
    "sg:address":"3102 Whiskey Rd",
    "sg:city":"Aiken",
    "sg:classifiers":[
        {
            "category":"Personal",
            "subcategory":"Beauty Salon",
            "type":"Services"
        }
    ],
    "sg:phone":"+1 803 644 2482",
    "sg:postcode":"29803",
    "sg:province":"SC",
    "wof:name":"Chuck Carver",
    "wof:placetype":"venue"
},
  "geometry": {"coordinates":[-81.699951,33.490879],"type":"Point"}
}