{
  "type": "Feature",
  "properties": {
    "addr:full":"1255 Woodruff Rd Greenville SC 29607",
    "addr:housenumber":"1255",
    "addr:postcode":"29607",
    "addr:street":"Woodruff Rd",
    "iso:country":"US",
    "sg:address":"1255 Woodruff Rd",
    "sg:city":"Greenville",
    "sg:classifiers":[
        {
            "category":"Restaurant",
            "type":"Food & Drink"
        }
    ],
    "sg:menulink":"http://www.allmenus.com/sc/greenville/105316-ryans/menu/",
    "sg:phone":"+1 864 329 9280",
    "sg:postcode":"29607",
    "sg:province":"SC",
    "sg:tags":[
        "american"
    ],
    "wof:name":"Ryan's",
    "wof:placetype":"venue"
},
  "geometry": {"coordinates":[-82.28817100000001,34.822568],"type":"Point"}
}