{
  "type": "Feature",
  "properties": {
    "iso:country":"US",
    "sg:address":"1768 Pinewood Rd",
    "sg:city":"Sumter",
    "sg:classifiers":[
        {
            "category":"Food & Beverages",
            "subcategory":"Groceries & Convenience Stores",
            "type":"Retail Goods"
        }
    ],
    "sg:phone":"+1 803 481 7548",
    "sg:postcode":"29154",
    "sg:province":"SC",
    "sg:tags":[
        "grocer"
    ],
    "wof:name":"K F Grocery Inc",
    "wof:placetype":"venue"
},
  "geometry": {"coordinates":[-80.40320699999999,33.869684],"type":"Point"}
}