{
  "type": "Feature",
  "properties": {
    "addr:full":"1923 US Hwy 15 Grover SC 29477",
    "addr:housenumber":"1923",
    "addr:postcode":"29477",
    "addr:street":"Us Hwy 15",
    "iso:country":"US",
    "sg:address":"1923 US Hwy 15",
    "sg:city":"Grover",
    "sg:classifiers":[
        {
            "category":"Government",
            "subcategory":"Post Office",
            "type":"Public Place"
        }
    ],
    "sg:phone":"+1 843 563 3771",
    "sg:postcode":"29477",
    "sg:province":"SC",
    "wof:name":"US Post Office",
    "wof:placetype":"venue"
},
  "geometry": {"coordinates":[-80.53278899999999,33.246699],"type":"Point"}
}