{
  "type": "Feature",
  "properties": {
    "iso:country":"US",
    "sg:address":"312 Old Cemetery Rd",
    "sg:city":"Andrews",
    "sg:classifiers":[
        {
            "category":"Personal",
            "subcategory":"Beauty Salon",
            "type":"Services"
        }
    ],
    "sg:phone":"+1 843 264 5991",
    "sg:postcode":"29510",
    "sg:province":"SC",
    "wof:name":"Unlimited Hair & Nails",
    "wof:placetype":"venue"
},
  "geometry": {"coordinates":[-79.54905100000001,33.440679],"type":"Point"}
}