{
  "type": "Feature",
  "properties": {
    "iso:country":"US",
    "sg:address":"1645 Old Latta Hwy",
    "sg:city":"Dillon",
    "sg:classifiers":[
        {
            "category":"Wholesale",
            "subcategory":"Auto Parts",
            "type":"Manufacturing & Wholesale Goods"
        }
    ],
    "sg:phone":"+1 843 774 6633",
    "sg:postcode":"29536",
    "sg:province":"SC",
    "sg:tags":[
        "automobile",
        "wrecking"
    ],
    "wof:name":"Discount Auto Wrecker Svc",
    "wof:placetype":"venue"
},
  "geometry": {"coordinates":[-79.39057699999999,34.386781],"type":"Point"}
}