{
  "type": "Feature",
  "properties": {
    "iso:country":"US",
    "sg:address":"10180 Two Notch Rd",
    "sg:city":"Columbia",
    "sg:classifiers":[
        {
            "category":"Retail",
            "subcategory":"Auto Repair",
            "type":"Services"
        }
    ],
    "sg:phone":"+1 803 736 4788",
    "sg:postcode":"29229",
    "sg:province":"SC",
    "sg:tags":[
        "tire",
        "supply"
    ],
    "sg:website":"www.tirekingdom.com",
    "wof:name":"Tire Kingdom",
    "wof:placetype":"venue"
},
  "geometry": {"coordinates":[-80.877064,34.120526],"type":"Point"}
}