{
  "type": "Feature",
  "properties": {
    "iso:country":"US",
    "sg:address":"1513 Hampton St",
    "sg:city":"Columbia",
    "sg:classifiers":[
        {
            "category":"Professional",
            "subcategory":"Lawyer & Legal Services",
            "type":"Services"
        }
    ],
    "sg:phone":"+1 803 771 8000",
    "sg:postcode":"29201",
    "sg:province":"SC",
    "wof:name":"Walters Fred A Attys",
    "wof:placetype":"venue"
},
  "geometry": {"coordinates":[-81.030098,34.007],"type":"Point"}
}