{
  "type": "Feature",
  "properties": {
    "iso:country":"US",
    "sg:address":"1 Meadowland Ct",
    "sg:city":"Columbia",
    "sg:classifiers":[
        {
            "category":"Real Estate",
            "subcategory":"Real Estate Operator",
            "type":"Services"
        }
    ],
    "sg:phone":"+1 803 731 1346",
    "sg:postcode":"29210",
    "sg:province":"SC",
    "sg:tags":[
        "apartment"
    ],
    "wof:name":"Harmon Hill Apartments",
    "wof:placetype":"venue"
},
  "geometry": {"coordinates":[-81.1035,34.050598],"type":"Point"}
}