{
  "type": "Feature",
  "properties": {
    "addr:full":"1210 Laurens Rd Greenville SC 29607",
    "addr:housenumber":"1210",
    "addr:postcode":"29607",
    "addr:street":"Laurens Rd",
    "iso:country":"US",
    "sg:address":"1210 Laurens Rd",
    "sg:city":"Greenville",
    "sg:classifiers":[
        {
            "category":"Insurance",
            "subcategory":"Hazard Insurance",
            "type":"Services"
        }
    ],
    "sg:phone":"+1 864 582 2663",
    "sg:postcode":"29607",
    "sg:province":"SC",
    "sg:tags":[
        "bond"
    ],
    "wof:name":"Convenant Bonding",
    "wof:placetype":"venue"
},
  "geometry": {"coordinates":[-82.36504499999999,34.844699],"type":"Point"}
}