{
  "type": "Feature",
  "properties": {
    "addr:full":"904 S 4th St Hartsville SC 29550",
    "addr:housenumber":"904",
    "addr:postcode":"29550",
    "addr:street":"S 4Th St",
    "iso:country":"US",
    "sg:address":"904 S 4th St",
    "sg:city":"Hartsville",
    "sg:classifiers":[
        {
            "category":"Government",
            "subcategory":"Office",
            "type":"Public Place"
        }
    ],
    "sg:phone":"+1 843 857 0700",
    "sg:postcode":"29550",
    "sg:province":"SC",
    "sg:tags":[
        "county",
        "resource"
    ],
    "wof:name":"Darlington County Comm Action",
    "wof:placetype":"venue"
},
  "geometry": {"coordinates":[-80.058882,34.356236],"type":"Point"}
}