{
  "type": "Feature",
  "properties": {
    "iso:country":"US",
    "sg:address":"2399 W Main St",
    "sg:city":"Rock Hill",
    "sg:classifiers":[
        {
            "category":"Education",
            "subcategory":"Junior College",
            "type":"Public Place"
        }
    ],
    "sg:phone":"+1 803 981 1100",
    "sg:postcode":"29732",
    "sg:province":"SC",
    "sg:tags":[
        "technical",
        "institute"
    ],
    "sg:website":"www.rock-hill.k12.sc.us",
    "wof:name":"Applied Technology Ctr",
    "wof:placetype":"venue"
},
  "geometry": {"coordinates":[-81.075684,34.947246],"type":"Point"}
}