{
  "type": "Feature",
  "properties": {
    "addr:full":"11319 State Hwy 707 Murrells Inlet SC 29576",
    "addr:housenumber":"11319",
    "addr:postcode":"29576",
    "addr:street":"State Hwy 707",
    "iso:country":"US",
    "sg:address":"11319 State Hwy 707",
    "sg:city":"Murrells Inlet",
    "sg:classifiers":[
        {
            "category":"Building & Trades",
            "subcategory":"Plumbing",
            "type":"Services"
        }
    ],
    "sg:phone":"+1 843 650 3448",
    "sg:postcode":"29576",
    "sg:province":"SC",
    "sg:tags":[
        "contractor"
    ],
    "wof:name":"Vereens Plumbing Co",
    "wof:placetype":"venue"
},
  "geometry": {"coordinates":[-79.059506,33.593703],"type":"Point"}
}