{
  "type": "Feature",
  "properties": {
    "iso:country":"US",
    "sg:address":"1451 E Main St",
    "sg:city":"Spartanburg",
    "sg:classifiers":[
        {
            "category":"Professional",
            "subcategory":"Management & Consulting",
            "type":"Services"
        }
    ],
    "sg:phone":"+1 864 585 4685",
    "sg:postcode":"29307",
    "sg:province":"SC",
    "sg:tags":[
        "consultant",
        "business"
    ],
    "wof:name":"Network",
    "wof:placetype":"venue"
},
  "geometry": {"coordinates":[-81.900982,34.963159],"type":"Point"}
}