{
  "type": "Feature",
  "properties": {
    "addr:full":"103 W Jones Dr Pineville SC 29468",
    "addr:housenumber":"103",
    "addr:postcode":"29468",
    "addr:street":"W Jones Dr",
    "iso:country":"US",
    "sg:address":"103 W Jones Dr",
    "sg:city":"Pineville",
    "sg:classifiers":[
        {
            "category":"Travel",
            "subcategory":"Campground",
            "type":"Entertainment"
        }
    ],
    "sg:phone":"+1 843 351 4274",
    "sg:postcode":"29468",
    "sg:province":"SC",
    "wof:name":"Angel's Landing",
    "wof:placetype":"venue"
},
  "geometry": {"coordinates":[-80.092184,33.381617],"type":"Point"}
}