{
  "type": "Feature",
  "properties": {
    "iso:country":"US",
    "sg:address":"1125 Barrett Rd",
    "sg:city":"Charleston",
    "sg:classifiers":[
        {
            "category":"Wholesale",
            "subcategory":"Vending Machines",
            "type":"Manufacturing & Wholesale Goods"
        }
    ],
    "sg:phone":"+1 843 813 5043",
    "sg:postcode":"29407",
    "sg:province":"SC",
    "sg:tags":[
        "operator"
    ],
    "wof:name":"Vending Plus",
    "wof:placetype":"venue"
},
  "geometry": {"coordinates":[-79.99700300000001,32.789763],"type":"Point"}
}