{
  "type": "Feature",
  "properties": {
    "iso:country":"US",
    "sg:address":"315 Daventon Rd",
    "sg:city":"Pelzer",
    "sg:classifiers":[
        {
            "category":"Organizations",
            "subcategory":"Religious Organization",
            "type":"Services"
        }
    ],
    "sg:phone":"+1 864 243 2784",
    "sg:postcode":"29669",
    "sg:province":"SC",
    "sg:tags":[
        "church"
    ],
    "wof:name":"Daventon Baptist Church",
    "wof:placetype":"venue"
},
  "geometry": {"coordinates":[-82.31703,34.573638],"type":"Point"}
}