{
  "type": "Feature",
  "properties": {
    "iso:country":"US",
    "sg:address":"1325 Spring St",
    "sg:city":"Greenwood",
    "sg:classifiers":[
        {
            "category":"Health Services",
            "subcategory":"Doctor",
            "type":"Services"
        }
    ],
    "sg:phone":"+1 864 330 1700",
    "sg:postcode":"29646",
    "sg:province":"SC",
    "sg:tags":[
        "physician",
        "surgeon"
    ],
    "wof:name":"Cancer Centers Of Carolinas",
    "wof:placetype":"venue"
},
  "geometry": {"coordinates":[-82.158023,34.175522],"type":"Point"}
}