{
  "type": "Feature",
  "properties": {
    "addr:full":"2013 W Meeting St Lancaster SC 29720",
    "addr:housenumber":"2013",
    "addr:postcode":"29720",
    "addr:street":"W Meeting St",
    "iso:country":"US",
    "sg:address":"2013 W Meeting St",
    "sg:city":"Lancaster",
    "sg:classifiers":[
        {
            "category":"Wholesale",
            "subcategory":"Electrical",
            "type":"Manufacturing & Wholesale Goods"
        },
        {
            "category":"Manufacturing",
            "subcategory":"Tools & Machinery",
            "type":"Manufacturing & Wholesale Goods"
        }
    ],
    "sg:phone":"+1 803 286 8491",
    "sg:postcode":"29720",
    "sg:province":"SC",
    "sg:tags":[
        "control",
        "electric",
        "motor",
        "mfg"
    ],
    "wof:name":"Joslyn Clark Controls Inc",
    "wof:placetype":"venue"
},
  "geometry": {"coordinates":[-80.823939,34.722481],"type":"Point"}
}