{
  "type": "Feature",
  "properties": {
    "iso:country":"US",
    "sg:address":"308 N Main St",
    "sg:city":"Mauldin",
    "sg:classifiers":[
        {
            "category":"Home & Garden",
            "subcategory":"Building Materials",
            "type":"Retail Goods"
        }
    ],
    "sg:phone":"+1 864 234 8883",
    "sg:postcode":"29662",
    "sg:province":"SC",
    "sg:tags":[
        "windows"
    ],
    "wof:name":"A Unique World Of Remodeling",
    "wof:placetype":"venue"
},
  "geometry": {"coordinates":[-82.311801,34.782909],"type":"Point"}
}