{
  "type": "Feature",
  "properties": {
    "addr:full":"22 W Antrim Dr Greenville SC 29607",
    "addr:housenumber":"22",
    "addr:postcode":"29607",
    "addr:street":"W Antrim Dr",
    "iso:country":"US",
    "sg:address":"22 W Antrim Dr",
    "sg:city":"Greenville",
    "sg:classifiers":[
        {
            "category":"Bars & Pubs",
            "type":"Food & Drink"
        }
    ],
    "sg:phone":"+1 864 232 3130",
    "sg:postcode":"29607",
    "sg:province":"SC",
    "sg:tags":[
        "club",
        "drinking",
        "night"
    ],
    "wof:name":"Shaum's Cafe",
    "wof:placetype":"venue"
},
  "geometry": {"coordinates":[-82.36416199999999,34.841253],"type":"Point"}
}