{
  "type": "Feature",
  "properties": {
    "iso:country":"US",
    "sg:address":"208 N Morgan Ave",
    "sg:city":"Andrews",
    "sg:classifiers":[
        {
            "category":"Personal",
            "subcategory":"Beauty Salon",
            "type":"Services"
        }
    ],
    "sg:phone":"+1 843 264 2208",
    "sg:postcode":"29510",
    "sg:province":"SC",
    "wof:name":"Salon 208",
    "wof:placetype":"venue"
},
  "geometry": {"coordinates":[-79.559681,33.454958],"type":"Point"}
}