{
  "type": "Feature",
  "properties": {
    "iso:country":"US",
    "sg:address":"2050 Mabeline Rd",
    "sg:city":"Charleston",
    "sg:classifiers":[
        {
            "category":"Building & Trades",
            "subcategory":"Plumbing",
            "type":"Services"
        }
    ],
    "sg:phone":"+1 843 722 8483",
    "sg:postcode":"29406",
    "sg:province":"SC",
    "sg:tags":[
        "plumbing",
        "contractor"
    ],
    "wof:name":"A American Plumbing",
    "wof:placetype":"venue"
},
  "geometry": {"coordinates":[-80.03313900000001,32.929651],"type":"Point"}
}