{
  "type": "Feature",
  "properties": {
    "iso:country":"US",
    "sg:address":"5150 Ashley Phosphate Rd",
    "sg:city":"North Charleston",
    "sg:classifiers":[
        {
            "category":"Insurance",
            "subcategory":"Insurance Agent",
            "type":"Services"
        }
    ],
    "sg:phone":"+1 843 552 9777",
    "sg:postcode":"29418",
    "sg:province":"SC",
    "wof:name":"State Farm Insurance",
    "wof:placetype":"venue"
},
  "geometry": {"coordinates":[-80.103323,32.917425],"type":"Point"}
}