{
  "type": "Feature",
  "properties": {
    "iso:country":"US",
    "sg:address":"4761 Northgate Blvd",
    "sg:city":"Myrtle Beach",
    "sg:classifiers":[
        {
            "category":"Home & Garden",
            "subcategory":"Carpets & Floor Coverings",
            "type":"Retail Goods"
        }
    ],
    "sg:phone":"+1 843 294 5444",
    "sg:postcode":"29577",
    "sg:province":"SC",
    "wof:name":"Stone Temple",
    "wof:placetype":"venue"
},
  "geometry": {"coordinates":[-78.964319,33.676251],"type":"Point"}
}