{
  "type": "Feature",
  "properties": {
    "iso:country":"US",
    "sg:address":"213 E Market St",
    "sg:city":"Bennettsville",
    "sg:classifiers":[
        {
            "category":"Education",
            "subcategory":"College",
            "type":"Public Place"
        }
    ],
    "sg:phone":"+1 843 479 6991",
    "sg:postcode":"29512",
    "sg:province":"SC",
    "sg:tags":[
        "academic",
        "school"
    ],
    "wof:name":"South Carolina State Univ",
    "wof:placetype":"venue"
},
  "geometry": {"coordinates":[-79.683769,34.617964],"type":"Point"}
}