{
  "type": "Feature",
  "properties": {
    "iso:country":"US",
    "sg:address":"8440 Dorchester Rd",
    "sg:city":"North Charleston",
    "sg:classifiers":[
        {
            "category":"Banks & Credit Unions",
            "subcategory":"Bank",
            "type":"Services"
        }
    ],
    "sg:phone":"+1 843 760 6464",
    "sg:postcode":"29420",
    "sg:province":"SC",
    "sg:tags":[
        "cashing",
        "check"
    ],
    "wof:name":"Check Loans",
    "wof:placetype":"venue"
},
  "geometry": {"coordinates":[-80.113342,32.91757],"type":"Point"}
}