{
  "type": "Feature",
  "properties": {
    "iso:country":"US",
    "sg:address":"831 Cleveland St",
    "sg:city":"Greenville",
    "sg:classifiers":[
        {
            "category":"Real Estate",
            "subcategory":"Real Estate Agent",
            "type":"Services"
        }
    ],
    "sg:phone":"+1 864 232 9086",
    "sg:postcode":"29601",
    "sg:province":"SC",
    "wof:name":"Andover Park",
    "wof:placetype":"venue"
},
  "geometry": {"coordinates":[-82.381105,34.830634],"type":"Point"}
}