{
  "type": "Feature",
  "properties": {
    "addr:full":"1211 Boundary St Beaufort SC 29902",
    "addr:housenumber":"1211",
    "addr:postcode":"29902",
    "addr:street":"Boundary St",
    "iso:country":"US",
    "sg:address":"1211 Boundary St",
    "sg:city":"Beaufort",
    "sg:classifiers":[
        {
            "category":"Real Estate",
            "subcategory":"Real Estate Agent",
            "type":"Services"
        }
    ],
    "sg:phone":"+1 843 522 2121",
    "sg:postcode":"29902",
    "sg:province":"SC",
    "sg:website":"www.coldwellbanker.com",
    "wof:name":"Coldwell Banker",
    "wof:placetype":"venue"
},
  "geometry": {"coordinates":[-80.676117,32.439696],"type":"Point"}
}