{
  "type": "Feature",
  "properties": {
    "addr:full":"701 Gervais St Ste 150 Columbia SC 29201",
    "addr:housenumber":"701",
    "addr:postcode":"29201",
    "addr:street":"Gervais St Ste 150",
    "iso:country":"US",
    "sg:address":"701 Gervais St Ste 150",
    "sg:city":"Columbia",
    "sg:classifiers":[
        {
            "category":"Freight",
            "type":"Transportation"
        },
        {
            "category":"Professional",
            "subcategory":"Printing & Photocopies",
            "type":"Services"
        }
    ],
    "sg:phone":"+1 803 254 1601",
    "sg:postcode":"29201",
    "sg:province":"SC",
    "sg:tags":[
        "shipping"
    ],
    "sg:website":"www.theupsstorelocal.com/3770",
    "wof:name":"The Ups Store",
    "wof:placetype":"venue"
},
  "geometry": {"coordinates":[-81.041591,33.999127],"type":"Point"}
}