{
  "type": "Feature",
  "properties": {
    "iso:country":"US",
    "sg:address":"109 Claussen St",
    "sg:city":"Summerville",
    "sg:classifiers":[
        {
            "category":"Building & Trades",
            "subcategory":"Construction",
            "type":"Services"
        }
    ],
    "sg:phone":"+1 843 875 9265",
    "sg:postcode":"29483",
    "sg:province":"SC",
    "sg:tags":[
        "house"
    ],
    "wof:name":"Custom Home Finishers",
    "wof:placetype":"venue"
},
  "geometry": {"coordinates":[-80.230946,33.00595],"type":"Point"}
}