{
  "type": "Feature",
  "properties": {
    "iso:country":"US",
    "sg:address":"1650 Stoney Fork Rd",
    "sg:city":"York",
    "sg:classifiers":[
        {
            "category":"Building & Trades",
            "subcategory":"Plumbing",
            "type":"Services"
        }
    ],
    "sg:phone":"+1 803 417 5921",
    "sg:postcode":"29745",
    "sg:province":"SC",
    "sg:tags":[
        "contractor"
    ],
    "wof:name":"Permanent Plumbing",
    "wof:placetype":"venue"
},
  "geometry": {"coordinates":[-81.194642,34.911231],"type":"Point"}
}