{
  "type": "Feature",
  "properties": {
    "iso:country":"US",
    "sg:address":"101 Green Lake Dr",
    "sg:city":"Myrtle Beach",
    "sg:classifiers":[
        {
            "category":"Organizations",
            "subcategory":"Religious Organization",
            "type":"Services"
        }
    ],
    "sg:phone":"+1 843 497 2862",
    "sg:postcode":"29572",
    "sg:province":"SC",
    "sg:tags":[
        "reach",
        "ministry"
    ],
    "wof:name":"Bosko Ministries",
    "wof:placetype":"venue"
},
  "geometry": {"coordinates":[-78.781157,33.779314],"type":"Point"}
}