{
  "type": "Feature",
  "properties": {
    "addr:full":"83 Blacksmith Cir Beaufort SC 29906",
    "addr:housenumber":"83",
    "addr:postcode":"29906",
    "addr:street":"Blacksmith Cir",
    "iso:country":"US",
    "sg:address":"83 Blacksmith Cir",
    "sg:city":"Beaufort",
    "sg:classifiers":[
        {
            "category":"Retail",
            "subcategory":"Repair Shop",
            "type":"Services"
        }
    ],
    "sg:phone":"+1 843 522 9980",
    "sg:postcode":"29906",
    "sg:province":"SC",
    "sg:tags":[
        "lock",
        "locksmith"
    ],
    "wof:name":"Secure Lock & Key Svc",
    "wof:placetype":"venue"
},
  "geometry": {"coordinates":[-80.782324,32.460363],"type":"Point"}
}