{
  "type": "Feature",
  "properties": {
    "addr:full":"2528 Boiling Springs Rd Spartanburg SC 29316",
    "addr:housenumber":"2528",
    "addr:postcode":"29316",
    "addr:street":"Boiling Springs Rd",
    "iso:country":"US",
    "sg:address":"2528 Boiling Springs Rd",
    "sg:city":"Spartanburg",
    "sg:classifiers":[
        {
            "category":"Banks & Credit Unions",
            "subcategory":"Bank",
            "type":"Services"
        }
    ],
    "sg:phone":"+1 864 599 7840",
    "sg:postcode":"29316",
    "sg:province":"SC",
    "sg:tags":[
        "cashing",
        "check"
    ],
    "wof:name":"Check Into Cash",
    "wof:placetype":"venue"
},
  "geometry": {"coordinates":[-81.974301,35.039051],"type":"Point"}
}