{
  "type": "Feature",
  "properties": {
    "iso:country":"US",
    "sg:address":"1249 Counts Ferry Rd",
    "sg:city":"Lexington",
    "sg:classifiers":[
        {
            "category":"Manufacturing",
            "subcategory":"Printing",
            "type":"Manufacturing & Wholesale Goods"
        }
    ],
    "sg:phone":"+1 803 951 3080",
    "sg:postcode":"29072",
    "sg:province":"SC",
    "sg:tags":[
        "publisher"
    ],
    "wof:name":"Palmetto Bookworks",
    "wof:placetype":"venue"
},
  "geometry": {"coordinates":[-81.344775,34.013023],"type":"Point"}
}