{
  "type": "Feature",
  "properties": {
    "iso:country":"US",
    "sg:address":"20 Riverside Dr",
    "sg:city":"Greenville",
    "sg:classifiers":[
        {
            "category":"Building & Trades",
            "subcategory":"Construction",
            "type":"Services"
        }
    ],
    "sg:phone":"+1 864 295 0622",
    "sg:postcode":"29605",
    "sg:province":"SC",
    "sg:tags":[
        "painter"
    ],
    "wof:name":"Salter's Decorating Svc",
    "wof:placetype":"venue"
},
  "geometry": {"coordinates":[-82.379047,34.812754],"type":"Point"}
}