{
  "type": "Feature",
  "properties": {
    "iso:country":"US",
    "sg:address":"15 S Palmetto St",
    "sg:city":"Liberty",
    "sg:classifiers":[
        {
            "category":"Education",
            "subcategory":"Library",
            "type":"Public Place"
        }
    ],
    "sg:phone":"+1 864 843 5805",
    "sg:postcode":"29657",
    "sg:province":"SC",
    "wof:name":"Liberty Library",
    "wof:placetype":"venue"
},
  "geometry": {"coordinates":[-82.695153,34.787344],"type":"Point"}
}