{
  "type": "Feature",
  "properties": {
    "iso:country":"US",
    "sg:address":"817 Catawba Hill Ct",
    "sg:city":"Walterboro",
    "sg:classifiers":[
        {
            "category":"Retail",
            "subcategory":"Repair Shop",
            "type":"Services"
        }
    ],
    "sg:phone":"+1 843 893 3253",
    "sg:postcode":"29488",
    "sg:province":"SC",
    "sg:tags":[
        "equipment",
        "conditioning",
        "air"
    ],
    "wof:name":"Bob Newman Htg & Air Repair",
    "wof:placetype":"venue"
},
  "geometry": {"coordinates":[-80.645161,32.83646],"type":"Point"}
}