{
  "type": "Feature",
  "properties": {
    "addr:full":"4604 Haile Gold Mine Rd Kershaw SC 29067",
    "addr:housenumber":"4604",
    "addr:postcode":"29067",
    "addr:street":"Haile Gold Mine Rd",
    "iso:country":"US",
    "sg:address":"4604 Haile Gold Mine Rd",
    "sg:city":"Kershaw",
    "sg:classifiers":[
        {
            "category":"Professional",
            "type":"Services"
        }
    ],
    "sg:phone":"+1 803 475 4258",
    "sg:postcode":"29067",
    "sg:province":"SC",
    "sg:tags":[
        "establishment"
    ],
    "wof:name":"Tall Pines Pinestraw Co",
    "wof:placetype":"venue"
},
  "geometry": {"coordinates":[-80.501334,34.57252],"type":"Point"}
}