{
  "type": "Feature",
  "properties": {
    "iso:country":"US",
    "sg:address":"96 Channing Dr",
    "sg:city":"Little River",
    "sg:classifiers":[
        {
            "category":"Utilities",
            "subcategory":"Telephone",
            "type":"Services"
        }
    ],
    "sg:phone":"+1 843 663 1004",
    "sg:postcode":"29566",
    "sg:province":"SC",
    "sg:tags":[
        "communications"
    ],
    "sg:website":"www.linkbrokersgroup.com",
    "wof:name":"Linkbrokers Group",
    "wof:placetype":"venue"
},
  "geometry": {"coordinates":[-78.663692,33.853745],"type":"Point"}
}