{
  "type": "Feature",
  "properties": {
    "iso:country":"US",
    "sg:address":"143 Summit Ave",
    "sg:city":"Goose Creek",
    "sg:classifiers":[
        {
            "category":"Building & Trades",
            "subcategory":"Construction",
            "type":"Services"
        }
    ],
    "sg:phone":"+1 843 553 7244",
    "sg:postcode":"29445",
    "sg:province":"SC",
    "sg:tags":[
        "general",
        "industrial",
        "commercial",
        "contractor"
    ],
    "wof:name":"Coastal Construction Services",
    "wof:placetype":"venue"
},
  "geometry": {"coordinates":[-80.010228,32.980387],"type":"Point"}
}