{
  "type": "Feature",
  "properties": {
    "iso:country":"US",
    "sg:address":"1118 Main St",
    "sg:city":"Union",
    "sg:classifiers":[
        {
            "category":"Restaurant",
            "type":"Food & Drink"
        }
    ],
    "sg:phone":"+1 864 427 4971",
    "sg:postcode":"29379",
    "sg:province":"SC",
    "wof:name":"Los Tucanes",
    "wof:placetype":"venue"
},
  "geometry": {"coordinates":[-81.63755,34.708609],"type":"Point"}
}