{
  "type": "Feature",
  "properties": {
    "iso:country":"US",
    "sg:address":"1224 Alice Dr",
    "sg:city":"Sumter",
    "sg:classifiers":[
        {
            "category":"Retail",
            "subcategory":"Portrait Studio",
            "type":"Services"
        }
    ],
    "sg:phone":"+1 803 469 2440",
    "sg:postcode":"29150",
    "sg:province":"SC",
    "sg:tags":[
        "photographer"
    ],
    "sg:website":"www.jeffcoatphotography.com",
    "wof:name":"Jeffcoat Photography",
    "wof:placetype":"venue"
},
  "geometry": {"coordinates":[-80.387165,33.950998],"type":"Point"}
}