{
  "type": "Feature",
  "properties": {
    "addr:full":"135 Wimberly Dr Ladson SC 29456",
    "addr:housenumber":"135",
    "addr:postcode":"29456",
    "addr:street":"Wimberly Dr",
    "iso:country":"US",
    "sg:address":"135 Wimberly Dr",
    "sg:city":"Ladson",
    "sg:classifiers":[
        {
            "category":"Government",
            "subcategory":"Office",
            "type":"Public Place"
        }
    ],
    "sg:phone":"+1 843 572 7956",
    "sg:postcode":"29456",
    "sg:province":"SC",
    "sg:tags":[
        "state",
        "program"
    ],
    "wof:name":"Public Safety Dept",
    "wof:placetype":"venue"
},
  "geometry": {"coordinates":[-80.09582899999999,32.99346],"type":"Point"}
}