{
  "type": "Feature",
  "properties": {
    "addr:full":"721 S Main St Abbeville SC 29620",
    "addr:housenumber":"721",
    "addr:postcode":"29620",
    "addr:street":"S Main St",
    "iso:country":"US",
    "sg:address":"721 S Main St",
    "sg:city":"Abbeville",
    "sg:classifiers":[
        {
            "category":"Retail",
            "subcategory":"Repair Shop",
            "type":"Services"
        }
    ],
    "sg:phone":"+1 864 459 2624",
    "sg:postcode":"29620",
    "sg:province":"SC",
    "sg:tags":[
        "scooter",
        "motorcycle",
        "motor"
    ],
    "wof:name":"Abbeville Cycle Thearpy",
    "wof:placetype":"venue"
},
  "geometry": {"coordinates":[-82.373324,34.172719],"type":"Point"}
}