{
  "type": "Feature",
  "properties": {
    "iso:country":"US",
    "sg:address":"322 N Hampton St",
    "sg:city":"Kershaw",
    "sg:classifiers":[
        {
            "category":"Restaurant",
            "type":"Food & Drink"
        }
    ],
    "sg:phone":"+1 803 475 6912",
    "sg:postcode":"29067",
    "sg:province":"SC",
    "sg:tags":[
        "caterer"
    ],
    "wof:name":"Chris Cromer Cafeteria",
    "wof:placetype":"venue"
},
  "geometry": {"coordinates":[-80.582413,34.548624],"type":"Point"}
}