{
  "type": "Feature",
  "properties": {
    "iso:country":"US",
    "sg:address":"1346 James Jones Ave",
    "sg:city":"Florence",
    "sg:classifiers":[
        {
            "category":"Home & Garden",
            "subcategory":"Furniture",
            "type":"Retail Goods"
        }
    ],
    "sg:phone":"+1 843 292 0570",
    "sg:postcode":"29505",
    "sg:province":"SC",
    "wof:name":"Habitat For Humanity Hm Store",
    "wof:placetype":"venue"
},
  "geometry": {"coordinates":[-79.762191,34.174386],"type":"Point"}
}