{
  "type": "Feature",
  "properties": {
    "addr:full":"406 Hwy 301 N Dillon SC 29536",
    "addr:housenumber":"406",
    "addr:postcode":"29536",
    "addr:street":"Hwy 301 N",
    "iso:country":"US",
    "sg:address":"406 Hwy 301 N",
    "sg:city":"Dillon",
    "sg:classifiers":[
        {
            "category":"Banks & Credit Unions",
            "subcategory":"Bank",
            "type":"Services"
        }
    ],
    "sg:phone":"+1 843 774 3360",
    "sg:postcode":"29536",
    "sg:province":"SC",
    "sg:website":"www.fcbsc.com",
    "wof:name":"First Citizens Bank & Trust Co",
    "wof:placetype":"venue"
},
  "geometry": {"coordinates":[-79.368292,34.420145],"type":"Point"}
}