{
  "type": "Feature",
  "properties": {
    "addr:full":"1611 Atascadero Dr Columbia SC 29206",
    "addr:housenumber":"1611",
    "addr:postcode":"29206",
    "addr:street":"Atascadero Dr",
    "iso:country":"US",
    "sg:address":"1611 Atascadero Dr",
    "sg:city":"Columbia",
    "sg:classifiers":[
        {
            "category":"Building & Trades",
            "subcategory":"Construction",
            "type":"Services"
        }
    ],
    "sg:phone":"+1 803 790 5851",
    "sg:postcode":"29206",
    "sg:province":"SC",
    "sg:tags":[
        "contractor"
    ],
    "wof:name":"Graterol Roofing",
    "wof:placetype":"venue"
},
  "geometry": {"coordinates":[-80.97771299999999,34.02482],"type":"Point"}
}