{
  "type": "Feature",
  "properties": {
    "addr:full":"235 Snider St Elloree SC 29047",
    "addr:housenumber":"235",
    "addr:postcode":"29047",
    "addr:street":"Snider St",
    "iso:country":"US",
    "sg:address":"235 Snider St",
    "sg:city":"Elloree",
    "sg:classifiers":[
        {
            "category":"Wholesale",
            "subcategory":"Farm Supplies",
            "type":"Manufacturing & Wholesale Goods"
        }
    ],
    "sg:phone":"+1 803 897 2842",
    "sg:postcode":"29047",
    "sg:province":"SC",
    "sg:tags":[
        "purchase",
        "seed",
        "wheat"
    ],
    "wof:name":"Gasque Farms Inc",
    "wof:placetype":"venue"
},
  "geometry": {"coordinates":[-80.555902,33.535955],"type":"Point"}
}