{
  "type": "Feature",
  "properties": {
    "addr:full":"810 Broughton St Orangeburg SC 29115",
    "addr:housenumber":"810",
    "addr:postcode":"29115",
    "addr:street":"Broughton St",
    "iso:country":"US",
    "sg:address":"810 Broughton St",
    "sg:city":"Orangeburg",
    "sg:classifiers":[
        {
            "category":"Insurance",
            "subcategory":"Insurance Agent",
            "type":"Services"
        }
    ],
    "sg:phone":"+1 803 531 3959",
    "sg:postcode":"29115",
    "sg:province":"SC",
    "wof:name":"Jones Insurance",
    "wof:placetype":"venue"
},
  "geometry": {"coordinates":[-80.86235600000001,33.485981],"type":"Point"}
}