{
  "type": "Feature",
  "properties": {
    "iso:country":"US",
    "sg:address":"112 Southwold Cir",
    "sg:city":"Goose Creek",
    "sg:classifiers":[
        {
            "category":"Building & Trades",
            "subcategory":"Plumbing",
            "type":"Services"
        }
    ],
    "sg:phone":"+1 843 574 9183",
    "sg:postcode":"29445",
    "sg:province":"SC",
    "sg:tags":[
        "contractor"
    ],
    "wof:name":"B & K Mechanical",
    "wof:placetype":"venue"
},
  "geometry": {"coordinates":[-80.051722,33.016052],"type":"Point"}
}