{
  "type": "Feature",
  "properties": {
    "addr:full":"1302 Montague Avenue Ext Greenwood SC 29649",
    "addr:housenumber":"1302",
    "addr:postcode":"29649",
    "addr:street":"Montague Avenue Ext",
    "iso:country":"US",
    "sg:address":"1302 Montague Avenue Ext",
    "sg:city":"Greenwood",
    "sg:classifiers":[
        {
            "category":"Cafe",
            "type":"Food & Drink"
        }
    ],
    "sg:menulink":"http://www.allmenus.com/sc/greenwood/146543-fatz-cafe/menu/",
    "sg:phone":"+1 864 229 3711",
    "sg:postcode":"29649",
    "sg:province":"SC",
    "sg:tags":[
        "american"
    ],
    "wof:name":"Fatz Cafe",
    "wof:placetype":"venue"
},
  "geometry": {"coordinates":[-82.189595,34.222963],"type":"Point"}
}