{
  "type": "Feature",
  "properties": {
    "iso:country":"US",
    "sg:address":"22 Gardner Rd",
    "sg:city":"Blackville",
    "sg:classifiers":[
        {
            "category":"Health Services",
            "subcategory":"Nursing And Care Facility",
            "type":"Services"
        }
    ],
    "sg:phone":"+1 803 284 0156",
    "sg:postcode":"29817",
    "sg:province":"SC",
    "sg:tags":[
        "home",
        "convalescent"
    ],
    "wof:name":"Blackville Medical Ctr",
    "wof:placetype":"venue"
},
  "geometry": {"coordinates":[-81.270127,33.399417],"type":"Point"}
}