{
  "type": "Feature",
  "properties": {
    "iso:country":"US",
    "sg:address":"1707 Ashley River Rd",
    "sg:city":"Charleston",
    "sg:classifiers":[
        {
            "category":"Real Estate",
            "subcategory":"Real Estate Agent",
            "type":"Services"
        }
    ],
    "sg:phone":"+1 843 556 6142",
    "sg:postcode":"29407",
    "sg:province":"SC",
    "wof:name":"Anlen Construction & Realty",
    "wof:placetype":"venue"
},
  "geometry": {"coordinates":[-80.014236,32.800064],"type":"Point"}
}