{
  "type": "Feature",
  "properties": {
    "iso:country":"US",
    "sg:address":"1084 Boiling Springs Rd",
    "sg:city":"Spartanburg",
    "sg:classifiers":[
        {
            "category":"Real Estate",
            "subcategory":"Developer",
            "type":"Services"
        }
    ],
    "sg:phone":"+1 864 583 5833",
    "sg:postcode":"29303",
    "sg:province":"SC",
    "wof:name":"Alliance Real Estate Services",
    "wof:placetype":"venue"
},
  "geometry": {"coordinates":[-81.942848,34.978131],"type":"Point"}
}