{
  "type": "Feature",
  "properties": {
    "iso:country":"US",
    "sg:address":"500 S Ocean Blvd",
    "sg:city":"North Myrtle Bch",
    "sg:classifiers":[
        {
            "category":"Travel",
            "subcategory":"Hotels & Motels",
            "type":"Entertainment"
        }
    ],
    "sg:phone":"+1 843 249 1720",
    "sg:postcode":"29582",
    "sg:province":"SC",
    "wof:name":"Del Mar Inn",
    "wof:placetype":"venue"
},
  "geometry": {"coordinates":[-78.677707,33.816826],"type":"Point"}
}