{
  "type": "Feature",
  "properties": {
    "addr:full":"1301 Boiling Springs Rd Spartanburg SC 29303",
    "addr:housenumber":"1301",
    "addr:postcode":"29303",
    "addr:street":"Boiling Springs Rd",
    "iso:country":"US",
    "sg:address":"1301 Boiling Springs Rd",
    "sg:city":"Spartanburg",
    "sg:classifiers":[
        {
            "category":"Organizations",
            "subcategory":"Religious Organization",
            "type":"Services"
        }
    ],
    "sg:phone":"+1 864 585 3113",
    "sg:postcode":"29303",
    "sg:province":"SC",
    "sg:tags":[
        "church"
    ],
    "sg:website":"www.cudd.org",
    "wof:name":"Cudd Memorial Baptist Church",
    "wof:placetype":"venue"
},
  "geometry": {"coordinates":[-81.946564,34.996219],"type":"Point"}
}