{
  "type": "Feature",
  "properties": {
    "iso:country":"US",
    "sg:address":"3271 Timrod Rd",
    "sg:city":"Bethune",
    "sg:classifiers":[
        {
            "category":"Manufacturing",
            "subcategory":"Printing",
            "type":"Manufacturing & Wholesale Goods"
        }
    ],
    "sg:phone":"+1 843 334 6222",
    "sg:postcode":"29009",
    "sg:province":"SC",
    "sg:tags":[
        "periodical"
    ],
    "wof:name":"Requiem Press",
    "wof:placetype":"venue"
},
  "geometry": {"coordinates":[-80.350248,34.450669],"type":"Point"}
}