{
  "type": "Feature",
  "properties": {
    "addr:full":"2900 Reidville Rd Spartanburg SC 29301",
    "addr:postcode":"2900;29301",
    "addr:street":"Reidville Rd",
    "iso:country":"US",
    "sg:address":"2900 Reidville Rd",
    "sg:city":"Spartanburg",
    "sg:classifiers":[
        {
            "category":"Real Estate",
            "subcategory":"Real Estate Operator",
            "type":"Services"
        }
    ],
    "sg:phone":"+1 864 574 5714",
    "sg:postcode":"29301",
    "sg:province":"SC",
    "sg:tags":[
        "building",
        "apartment"
    ],
    "wof:name":"Willow Lakes Apartments",
    "wof:placetype":"venue"
},
  "geometry": {"coordinates":[-82.00778800000001,34.915447],"type":"Point"}
}