{
  "type": "Feature",
  "properties": {
    "iso:country":"US",
    "sg:address":"124 S Railroad Ave",
    "sg:city":"Ridgeland",
    "sg:classifiers":[
        {
            "category":"Health Services",
            "subcategory":"Nursing And Care Facility",
            "type":"Services"
        },
        {
            "category":"Health Services",
            "subcategory":"Health Practitioner",
            "type":"Services"
        },
        {
            "category":"Health Services",
            "subcategory":"Chiropractor",
            "type":"Services"
        }
    ],
    "sg:phone":"+1 843 726 5990",
    "sg:postcode":"29936",
    "sg:province":"SC",
    "sg:tags":[
        "therapist",
        "management",
        "pain",
        "physical",
        "chiropractic"
    ],
    "wof:name":"Ridgeland Chiropractic Center",
    "wof:placetype":"venue"
},
  "geometry": {"coordinates":[-80.982274,32.481355],"type":"Point"}
}