{
  "type": "Feature",
  "properties": {
    "iso:country":"US",
    "sg:address":"270 Farmingdale Rd",
    "sg:city":"Nichols",
    "sg:classifiers":[
        {
            "category":"Real Estate",
            "subcategory":"Real Estate Operator",
            "type":"Services"
        }
    ],
    "sg:phone":"+1 843 392 3572",
    "sg:postcode":"29581",
    "sg:province":"SC",
    "sg:tags":[
        "property",
        "lessor"
    ],
    "wof:name":"Gerrald Farms",
    "wof:placetype":"venue"
},
  "geometry": {"coordinates":[-79.135381,34.117086],"type":"Point"}
}