{
  "type": "Feature",
  "properties": {
    "iso:country":"US",
    "sg:address":"128 Lakeside Rd",
    "sg:city":"Chapin",
    "sg:classifiers":[
        {
            "category":"Manufacturing",
            "subcategory":"Apparel",
            "type":"Manufacturing & Wholesale Goods"
        }
    ],
    "sg:phone":"+1 803 345 3998",
    "sg:postcode":"29036",
    "sg:province":"SC",
    "wof:name":"Carolina Raines",
    "wof:placetype":"venue"
},
  "geometry": {"coordinates":[-81.353201,34.141925],"type":"Point"}
}