{
  "type": "Feature",
  "properties": {
    "addr:full":"235 Main St Seneca SC 29678",
    "addr:housenumber":"235",
    "addr:postcode":"29678",
    "addr:street":"Main St",
    "iso:country":"US",
    "sg:address":"235 Main St",
    "sg:city":"Seneca",
    "sg:classifiers":[
        {
            "category":"Shopping",
            "subcategory":"Gifts & Souvenirs",
            "type":"Retail Goods"
        }
    ],
    "sg:phone":"+1 864 888 8961",
    "sg:postcode":"29678",
    "sg:province":"SC",
    "wof:name":"Stars & Moon Engravables",
    "wof:placetype":"venue"
},
  "geometry": {"coordinates":[-82.95146,34.685068],"type":"Point"}
}