{
  "type": "Feature",
  "properties": {
    "iso:country":"US",
    "sg:address":"305 Bryton Trce",
    "sg:city":"Columbia",
    "sg:classifiers":[
        {
            "category":"Wholesale",
            "subcategory":"Machinery & Supplies",
            "type":"Manufacturing & Wholesale Goods"
        }
    ],
    "sg:phone":"+1 803 699 2222",
    "sg:postcode":"29210",
    "sg:province":"SC",
    "sg:tags":[
        "equipment",
        "industrial"
    ],
    "wof:name":"Advent Age Automation Ltd",
    "wof:placetype":"venue"
},
  "geometry": {"coordinates":[-81.074433,34.026183],"type":"Point"}
}