{
  "type": "Feature",
  "properties": {
    "iso:country":"US",
    "sg:address":"100 Springfield Cir",
    "sg:city":"Darlington",
    "sg:classifiers":[
        {
            "category":"Real Estate",
            "subcategory":"Real Estate Operator",
            "type":"Services"
        }
    ],
    "sg:phone":"+1 843 393 7521",
    "sg:postcode":"29532",
    "sg:province":"SC",
    "sg:tags":[
        "apartment"
    ],
    "wof:name":"Palmetto-Springfield Apts",
    "wof:placetype":"venue"
},
  "geometry": {"coordinates":[-79.873909,34.313939],"type":"Point"}
}