{
  "type": "Feature",
  "properties": {
    "iso:country":"US",
    "sg:address":"18 Boland Ct",
    "sg:city":"Greenville",
    "sg:classifiers":[
        {
            "category":"Arena",
            "subcategory":"Sports Club",
            "type":"Entertainment"
        }
    ],
    "sg:phone":"+1 864 329 1113",
    "sg:postcode":"29615",
    "sg:province":"SC",
    "sg:tags":[
        "soccer"
    ],
    "wof:name":"Carolina Elite Soccer Acad",
    "wof:placetype":"venue"
},
  "geometry": {"coordinates":[-82.255673,34.85889],"type":"Point"}
}