{
  "type": "Feature",
  "properties": {
    "iso:country":"US",
    "sg:address":"1709 Old Easley Hwy",
    "sg:city":"Easley",
    "sg:classifiers":[
        {
            "category":"Building & Trades",
            "subcategory":"Landscaping Services",
            "type":"Services"
        }
    ],
    "sg:phone":"+1 864 269 4114",
    "sg:postcode":"29640",
    "sg:province":"SC",
    "sg:tags":[
        "lawn",
        "maintenance",
        "grounds"
    ],
    "wof:name":"Showcase Lawn Mntnc & Landscpg",
    "wof:placetype":"venue"
},
  "geometry": {"coordinates":[-82.49748,34.832806],"type":"Point"}
}