{
  "type": "Feature",
  "properties": {
    "iso:country":"US",
    "sg:address":"1518 Two Notch Rd SE",
    "sg:city":"Aiken",
    "sg:classifiers":[
        {
            "category":"Health Services",
            "subcategory":"Doctor",
            "type":"Services"
        }
    ],
    "sg:phone":"+1 803 649 7746",
    "sg:postcode":"29803",
    "sg:province":"SC",
    "sg:tags":[
        "physician",
        "surgeon"
    ],
    "wof:name":"Parkside Womens Ctr LLC",
    "wof:placetype":"venue"
},
  "geometry": {"coordinates":[-81.719213,33.530486],"type":"Point"}
}