{
  "type": "Feature",
  "properties": {
    "iso:country":"US",
    "sg:address":"889 Camden Rd",
    "sg:city":"Vance",
    "sg:classifiers":[
        {
            "category":"Organizations",
            "subcategory":"Religious Organization",
            "type":"Services"
        }
    ],
    "sg:phone":"+1 803 496 3221",
    "sg:postcode":"29163",
    "sg:province":"SC",
    "sg:tags":[
        "church"
    ],
    "wof:name":"Liberty Hill Baptist Church",
    "wof:placetype":"venue"
},
  "geometry": {"coordinates":[-80.419813,33.42255],"type":"Point"}
}