{
  "type": "Feature",
  "properties": {
    "iso:country":"US",
    "sg:address":"10 Sunning Hill Rd",
    "sg:city":"Simpsonville",
    "sg:classifiers":[
        {
            "category":"Recreation",
            "type":"Entertainment"
        }
    ],
    "sg:phone":"+1 864 281 0780",
    "sg:postcode":"29681",
    "sg:province":"SC",
    "sg:tags":[
        "center"
    ],
    "wof:name":"Stone Haven Recreation Ctr II",
    "wof:placetype":"venue"
},
  "geometry": {"coordinates":[-82.249813,34.801634],"type":"Point"}
}