{
  "type": "Feature",
  "properties": {
    "addr:full":"201 S Maple St Pageland SC 29728",
    "addr:housenumber":"201",
    "addr:postcode":"29728",
    "addr:street":"S Maple St",
    "iso:country":"US",
    "sg:address":"201 S Maple St",
    "sg:city":"Pageland",
    "sg:classifiers":[
        {
            "category":"Organizations",
            "subcategory":"Religious Organization",
            "type":"Services"
        }
    ],
    "sg:phone":"+1 843 672 7313",
    "sg:postcode":"29728",
    "sg:province":"SC",
    "sg:tags":[
        "church"
    ],
    "wof:name":"Salem Pageland Presbyterian",
    "wof:placetype":"venue"
},
  "geometry": {"coordinates":[-80.392214,34.770513],"type":"Point"}
}