{
  "type": "Feature",
  "properties": {
    "iso:country":"US",
    "sg:address":"723 S Doctors Dr",
    "sg:city":"Cheraw",
    "sg:classifiers":[
        {
            "category":"Health Services",
            "subcategory":"Doctor",
            "type":"Services"
        }
    ],
    "sg:phone":"+1 843 921 4851",
    "sg:postcode":"29520",
    "sg:province":"SC",
    "sg:tags":[
        "physician",
        "surgeon"
    ],
    "wof:name":"Palmetto Family Medicine",
    "wof:placetype":"venue"
},
  "geometry": {"coordinates":[-79.920498,34.69519],"type":"Point"}
}