{
  "type": "Feature",
  "properties": {
    "iso:country":"US",
    "sg:address":"2028 Pittsburgh Ave",
    "sg:city":"Charleston",
    "sg:classifiers":[
        {
            "category":"Shopping",
            "subcategory":"Music",
            "type":"Retail Goods"
        }
    ],
    "sg:phone":"+1 843 958 0578",
    "sg:postcode":"29405",
    "sg:province":"SC",
    "sg:tags":[
        "video",
        "disc",
        "tape",
        "cassette"
    ],
    "wof:name":"Wet & Wild Adult Videos & Toys",
    "wof:placetype":"venue"
},
  "geometry": {"coordinates":[-79.952631,32.832788],"type":"Point"}
}