{
  "type": "Feature",
  "properties": {
    "iso:country":"US",
    "sg:address":"104 Westchester Way",
    "sg:city":"Easley",
    "sg:classifiers":[
        {
            "category":"Building & Trades",
            "subcategory":"Construction",
            "type":"Services"
        }
    ],
    "sg:phone":"+1 864 220 0124",
    "sg:postcode":"29642",
    "sg:province":"SC",
    "sg:tags":[
        "house"
    ],
    "wof:name":"Saluda Valley Custom Homes",
    "wof:placetype":"venue"
},
  "geometry": {"coordinates":[-82.505328,34.783242],"type":"Point"}
}