{
  "type": "Feature",
  "properties": {
    "iso:country":"US",
    "sg:address":"1735 Saint Julian Pl",
    "sg:city":"Columbia",
    "sg:classifiers":[
        {
            "category":"Professional",
            "subcategory":"Lawyer & Legal Services",
            "type":"Services"
        }
    ],
    "sg:phone":"+1 803 254 2791",
    "sg:postcode":"29204",
    "sg:province":"SC",
    "wof:name":"Earle Thomas G Atty",
    "wof:placetype":"venue"
},
  "geometry": {"coordinates":[-81.001701,34.0172],"type":"Point"}
}