{
  "type": "Feature",
  "properties": {
    "iso:country":"US",
    "sg:address":"1302 State Hwy 319",
    "sg:city":"Aynor",
    "sg:classifiers":[
        {
            "category":"Personal",
            "subcategory":"Beauty Salon",
            "type":"Services"
        }
    ],
    "sg:phone":"+1 843 358 0889",
    "sg:postcode":"29511",
    "sg:province":"SC",
    "wof:name":"Holly's House Of Beauty",
    "wof:placetype":"venue"
},
  "geometry": {"coordinates":[-79.190073,33.998409],"type":"Point"}
}