{
  "type": "Feature",
  "properties": {
    "iso:country":"US",
    "sg:address":"26 Maverick St",
    "sg:city":"Charleston",
    "sg:classifiers":[
        {
            "category":"Organizations",
            "subcategory":"Religious Organization",
            "type":"Services"
        }
    ],
    "sg:phone":"+1 843 723 0187",
    "sg:postcode":"29403",
    "sg:province":"SC",
    "sg:tags":[
        "clergy",
        "church"
    ],
    "wof:name":"Jerusalem Baptist Church",
    "wof:placetype":"venue"
},
  "geometry": {"coordinates":[-79.952296,32.800952],"type":"Point"}
}