{
  "type": "Feature",
  "properties": {
    "iso:country":"US",
    "sg:address":"223 Waller Rd",
    "sg:city":"Greenwood",
    "sg:classifiers":[
        {
            "category":"Personal",
            "subcategory":"Beauty Salon",
            "type":"Services"
        }
    ],
    "sg:phone":"+1 864 229 4040",
    "sg:postcode":"29646",
    "sg:province":"SC",
    "wof:name":"Sittin Pretty Salon",
    "wof:placetype":"venue"
},
  "geometry": {"coordinates":[-82.066346,34.102452],"type":"Point"}
}