{
  "type": "Feature",
  "properties": {
    "addr:full":"1645 Sandra Dr Columbia SC 29209",
    "addr:housenumber":"1645",
    "addr:postcode":"29209",
    "addr:street":"Sandra Dr",
    "iso:country":"US",
    "sg:address":"1645 Sandra Dr",
    "sg:city":"Columbia",
    "sg:classifiers":[
        {
            "category":"Building & Trades",
            "subcategory":"Construction",
            "type":"Services"
        }
    ],
    "sg:phone":"+1 803 695 9896",
    "sg:postcode":"29209",
    "sg:province":"SC",
    "sg:tags":[
        "general",
        "contractor"
    ],
    "wof:name":"Hazelwood Construction",
    "wof:placetype":"venue"
},
  "geometry": {"coordinates":[-80.92624600000001,33.97177],"type":"Point"}
}