{
  "type": "Feature",
  "properties": {
    "iso:country":"US",
    "sg:address":"4415 Lord Proprietors Rd",
    "sg:city":"Hollywood",
    "sg:classifiers":[
        {
            "category":"Real Estate",
            "subcategory":"Surveying",
            "type":"Services"
        }
    ],
    "sg:phone":"+1 843 559 2335",
    "sg:postcode":"29449",
    "sg:province":"SC",
    "sg:tags":[
        "surveyor"
    ],
    "wof:name":"Geometric Surveying Co",
    "wof:placetype":"venue"
},
  "geometry": {"coordinates":[-80.241185,32.696965],"type":"Point"}
}