{
  "type": "Feature",
  "properties": {
    "iso:country":"US",
    "sg:address":"1001 Washington St",
    "sg:city":"Columbia",
    "sg:classifiers":[
        {
            "category":"Professional",
            "subcategory":"Lawyer & Legal Services",
            "type":"Services"
        }
    ],
    "sg:phone":"+1 803 929 0001",
    "sg:postcode":"29201",
    "sg:province":"SC",
    "sg:tags":[
        "attorney"
    ],
    "wof:name":"Paul Reeves Law Office",
    "wof:placetype":"venue"
},
  "geometry": {"coordinates":[-81.036406,34.00342],"type":"Point"}
}