{
  "type": "Feature",
  "properties": {
    "iso:country":"US",
    "sg:address":"1646 Hayne St",
    "sg:city":"Spartanburg",
    "sg:classifiers":[
        {
            "category":"Restaurant",
            "type":"Food & Drink"
        }
    ],
    "sg:phone":"+1 864 576 7394",
    "sg:postcode":"29301",
    "sg:province":"SC",
    "wof:name":"William's Bar & Grill",
    "wof:placetype":"venue"
},
  "geometry": {"coordinates":[-81.984211,34.960401],"type":"Point"}
}