{
  "type": "Feature",
  "properties": {
    "addr:full":"705 3rd St E Hampton SC 29924",
    "addr:housenumber":"705",
    "addr:postcode":"29924",
    "addr:street":"3Rd St E",
    "iso:country":"US",
    "sg:address":"705 3rd St E",
    "sg:city":"Hampton",
    "sg:classifiers":[
        {
            "category":"Food & Beverages",
            "subcategory":"Groceries & Convenience Stores",
            "type":"Retail Goods"
        }
    ],
    "sg:phone":"+1 803 943 2925",
    "sg:postcode":"29924",
    "sg:province":"SC",
    "wof:name":"Pic & Pay Convenience Store",
    "wof:placetype":"venue"
},
  "geometry": {"coordinates":[-81.10955,32.862459],"type":"Point"}
}