{
  "type": "Feature",
  "properties": {
    "addr:full":"1940 Gray Oaks Dr Conway SC 29526",
    "addr:housenumber":"1940",
    "addr:postcode":"29526",
    "addr:street":"Gray Oaks Dr",
    "iso:country":"US",
    "sg:address":"1940 Gray Oaks Dr",
    "sg:city":"Conway",
    "sg:classifiers":[
        {
            "category":"Restaurant",
            "type":"Food & Drink"
        }
    ],
    "sg:phone":"+1 843 399 9969",
    "sg:postcode":"29526",
    "sg:province":"SC",
    "sg:tags":[
        "eating"
    ],
    "wof:name":"Sumter Shrimper Inc",
    "wof:placetype":"venue"
},
  "geometry": {"coordinates":[-78.90297099999999,33.843227],"type":"Point"}
}