{
  "type": "Feature",
  "properties": {
    "iso:country":"US",
    "sg:address":"5720 Diamond Head Loop",
    "sg:city":"Florence",
    "sg:classifiers":[
        {
            "category":"Organizations",
            "subcategory":"Religious Organization",
            "type":"Services"
        }
    ],
    "sg:phone":"+1 843 661 5198",
    "sg:postcode":"29505",
    "sg:province":"SC",
    "sg:tags":[
        "church"
    ],
    "wof:name":"Cave Of Adullam Ministries",
    "wof:placetype":"venue"
},
  "geometry": {"coordinates":[-79.605726,34.118295],"type":"Point"}
}