{
  "type": "Feature",
  "properties": {
    "addr:full":"795 University Forest Cir Conway SC 29526",
    "addr:housenumber":"795",
    "addr:postcode":"29526",
    "addr:street":"University Forest Cir",
    "iso:country":"US",
    "sg:address":"795 University Forest Cir",
    "sg:city":"Conway",
    "sg:classifiers":[
        {
            "category":"Retail",
            "subcategory":"Auto Repair",
            "type":"Services"
        }
    ],
    "sg:phone":"+1 843 421 6954",
    "sg:postcode":"29526",
    "sg:province":"SC",
    "sg:tags":[
        "repairing",
        "automobile"
    ],
    "wof:name":"A 1 Mobile Mechanic",
    "wof:placetype":"venue"
},
  "geometry": {"coordinates":[-79.006675,33.810501],"type":"Point"}
}