{
  "type": "Feature",
  "properties": {
    "iso:country":"US",
    "sg:address":"1613 E North St",
    "sg:city":"Greenville",
    "sg:classifiers":[
        {
            "category":"Freight",
            "type":"Transportation"
        }
    ],
    "sg:phone":"+1 864 233 5006",
    "sg:postcode":"29607",
    "sg:province":"SC",
    "sg:tags":[
        "courier"
    ],
    "wof:name":"Executive Courier Svc",
    "wof:placetype":"venue"
},
  "geometry": {"coordinates":[-82.3753,34.860234],"type":"Point"}
}