{
  "type": "Feature",
  "properties": {
    "iso:country":"US",
    "sg:address":"1609 Elm St W",
    "sg:city":"Hampton",
    "sg:classifiers":[
        {
            "category":"Autos & Motor Vehicles",
            "subcategory":"Fuel & Gas Station",
            "type":"Retail Goods"
        }
    ],
    "sg:phone":"+1 803 943 0095",
    "sg:postcode":"29924",
    "sg:province":"SC",
    "sg:tags":[
        "station",
        "gasoline"
    ],
    "wof:name":"Tiger Express Vii",
    "wof:placetype":"venue"
},
  "geometry": {"coordinates":[-81.124751,32.880815],"type":"Point"}
}