{
  "type": "Feature",
  "properties": {
    "iso:country":"US",
    "sg:address":"508 Hicks Grove Rd",
    "sg:city":"Mooresboro",
    "sg:classifiers":[
        {
            "category":"Organizations",
            "subcategory":"Religious Organization",
            "type":"Services"
        }
    ],
    "sg:phone":"+1 828 245 0301",
    "sg:postcode":"28114",
    "sg:province":"SC",
    "sg:tags":[
        "church"
    ],
    "wof:name":"Hicks Grove Baptist Church",
    "wof:placetype":"venue"
},
  "geometry": {"coordinates":[-81.84586400000001,35.194912],"type":"Point"}
}