{
  "type": "Feature",
  "properties": {
    "addr:full":"501 Society St Greeleyville SC 29056",
    "addr:housenumber":"501",
    "addr:postcode":"29056",
    "addr:street":"Society St",
    "iso:country":"US",
    "sg:address":"501 Society St",
    "sg:city":"Greeleyville",
    "sg:classifiers":[
        {
            "category":"Food & Beverages",
            "subcategory":"Groceries & Convenience Stores",
            "type":"Retail Goods"
        }
    ],
    "sg:phone":"+1 843 426 2799",
    "sg:postcode":"29056",
    "sg:province":"SC",
    "wof:name":"Young's Food Stores",
    "wof:placetype":"venue"
},
  "geometry": {"coordinates":[-79.99863499999999,33.58224],"type":"Point"}
}