{
  "type": "Feature",
  "properties": {
    "addr:full":"704 Halls Rd Pineville SC 29468",
    "addr:housenumber":"704",
    "addr:postcode":"29468",
    "addr:street":"Halls Rd",
    "iso:country":"US",
    "sg:address":"704 Halls Rd",
    "sg:city":"Pineville",
    "sg:classifiers":[
        {
            "category":"Shopping",
            "subcategory":"Computers & Home Electronics",
            "type":"Retail Goods"
        }
    ],
    "sg:phone":"+1 843 351 2697",
    "sg:postcode":"29468",
    "sg:province":"SC",
    "sg:tags":[
        "equipment",
        "electronic",
        "supply"
    ],
    "wof:name":"Rigby Electric Supplies",
    "wof:placetype":"venue"
},
  "geometry": {"coordinates":[-80.099796,33.370991],"type":"Point"}
}