{
  "type": "Feature",
  "properties": {
    "addr:full":"306 N Main St Bishopville SC 29010",
    "addr:housenumber":"306",
    "addr:postcode":"29010",
    "addr:street":"N Main St",
    "iso:country":"US",
    "sg:address":"306 N Main St",
    "sg:city":"Bishopville",
    "sg:classifiers":[
        {
            "category":"Freight",
            "type":"Transportation"
        }
    ],
    "sg:phone":"+1 803 484 5633",
    "sg:postcode":"29010",
    "sg:province":"SC",
    "sg:tags":[
        "bulk",
        "storage"
    ],
    "wof:name":"Holland Enterprises",
    "wof:placetype":"venue"
},
  "geometry": {"coordinates":[-80.246167,34.219924],"type":"Point"}
}