{
  "type": "Feature",
  "properties": {
    "iso:country":"US",
    "sg:address":"2615 W Emery Ln",
    "sg:city":"Florence",
    "sg:classifiers":[
        {
            "category":"Personal",
            "subcategory":"Barber",
            "type":"Services"
        }
    ],
    "sg:phone":"+1 843 673 9920",
    "sg:postcode":"29501",
    "sg:province":"SC",
    "wof:name":"Classic Cuts",
    "wof:placetype":"venue"
},
  "geometry": {"coordinates":[-79.82326399999999,34.177339],"type":"Point"}
}