{
  "type": "Feature",
  "properties": {
    "iso:country":"US",
    "sg:address":"270 Mercer Ave",
    "sg:city":"Georgetown",
    "sg:classifiers":[
        {
            "category":"Building & Trades",
            "subcategory":"Construction",
            "type":"Services"
        }
    ],
    "sg:phone":"+1 843 546 5065",
    "sg:postcode":"29440",
    "sg:province":"SC",
    "sg:tags":[
        "repairing",
        "remodeling",
        "contractor"
    ],
    "wof:name":"Reid Home Building & Remodel",
    "wof:placetype":"venue"
},
  "geometry": {"coordinates":[-79.326907,33.395608],"type":"Point"}
}