{
  "type": "Feature",
  "properties": {
    "iso:country":"US",
    "sg:address":"112 Buoy Ln",
    "sg:city":"Chapin",
    "sg:classifiers":[
        {
            "category":"Shopping",
            "subcategory":"Catalog Store",
            "type":"Retail Goods"
        },
        {
            "category":"Shopping",
            "subcategory":"Clothing, Apparel, & Fashions",
            "type":"Retail Goods"
        }
    ],
    "sg:phone":"+1 803 356 0776",
    "sg:postcode":"29036",
    "sg:province":"SC",
    "sg:tags":[
        "mail",
        "hat",
        "order",
        "monogrammed"
    ],
    "wof:name":"Tam Beret Selections Inc",
    "wof:placetype":"venue"
},
  "geometry": {"coordinates":[-81.27176799999999,34.125469],"type":"Point"}
}