{
  "type": "Feature",
  "properties": {
    "iso:country":"US",
    "sg:address":"430 N Main St",
    "sg:city":"Woodruff",
    "sg:classifiers":[
        {
            "category":"Personal",
            "subcategory":"Beauty Salon",
            "type":"Services"
        }
    ],
    "sg:phone":"+1 864 476 2011",
    "sg:postcode":"29388",
    "sg:province":"SC",
    "wof:name":"Magic Touch Styling Salon",
    "wof:placetype":"venue"
},
  "geometry": {"coordinates":[-82.04158700000001,34.744002],"type":"Point"}
}