{
  "type": "Feature",
  "properties": {
    "iso:country":"US",
    "sg:address":"2190 Douglas Heights Ln",
    "sg:city":"Lancaster",
    "sg:classifiers":[
        {
            "category":"Building & Trades",
            "subcategory":"Plumbing",
            "type":"Services"
        }
    ],
    "sg:phone":"+1 803 285 1920",
    "sg:postcode":"29720",
    "sg:province":"SC",
    "sg:tags":[
        "contractor"
    ],
    "wof:name":"Ricks Heating & Air Condition",
    "wof:placetype":"venue"
},
  "geometry": {"coordinates":[-80.82959,34.665337],"type":"Point"}
}