{
  "type": "Feature",
  "properties": {
    "addr:full":"1465 Stuart Engals Blvd Mount Pleasant SC 29464",
    "addr:housenumber":"1465",
    "addr:postcode":"29464",
    "addr:street":"Stuart Engals Blvd",
    "iso:country":"US",
    "sg:address":"1465 Stuart Engals Blvd",
    "sg:city":"Mount Pleasant",
    "sg:classifiers":[
        {
            "category":"Shopping",
            "subcategory":"Discount & Variety Stores",
            "type":"Retail Goods"
        }
    ],
    "sg:phone":"+1 843 216 1235",
    "sg:postcode":"29464",
    "sg:province":"SC",
    "sg:tags":[
        "merchandise",
        "general"
    ],
    "wof:name":"Omni Products",
    "wof:placetype":"venue"
},
  "geometry": {"coordinates":[-79.84756299999999,32.814146],"type":"Point"}
}