{
  "type": "Feature",
  "properties": {
    "iso:country":"US",
    "sg:address":"907 S Market St",
    "sg:city":"Lancaster",
    "sg:classifiers":[
        {
            "category":"Retail",
            "subcategory":"Auto Repair",
            "type":"Services"
        }
    ],
    "sg:phone":"+1 803 285 1540",
    "sg:postcode":"29720",
    "sg:province":"SC",
    "sg:tags":[
        "repairing",
        "automobile"
    ],
    "wof:name":"M P's Detail & Small Repair",
    "wof:placetype":"venue"
},
  "geometry": {"coordinates":[-80.760774,34.707303],"type":"Point"}
}