{
  "type": "Feature",
  "properties": {
    "addr:full":"242 S Jefferies Blvd Walterboro SC 29488",
    "addr:housenumber":"242",
    "addr:postcode":"29488",
    "addr:street":"S Jefferies Blvd",
    "iso:country":"US",
    "sg:address":"242 S Jefferies Blvd",
    "sg:city":"Walterboro",
    "sg:classifiers":[
        {
            "category":"Retail",
            "subcategory":"Auto Repair",
            "type":"Services"
        }
    ],
    "sg:phone":"+1 843 549 9100",
    "sg:postcode":"29488",
    "sg:province":"SC",
    "sg:tags":[
        "body",
        "automobile",
        "painting"
    ],
    "wof:name":"Extreme Custom Paint & Body",
    "wof:placetype":"venue"
},
  "geometry": {"coordinates":[-80.667329,32.901167],"type":"Point"}
}