{
  "type": "Feature",
  "properties": {
    "iso:country":"US",
    "sg:address":"1124 Glenwood Rd",
    "sg:city":"Columbia",
    "sg:classifiers":[
        {
            "category":"Real Estate",
            "subcategory":"Real Estate Operator",
            "type":"Services"
        }
    ],
    "sg:phone":"+1 803 782 3057",
    "sg:postcode":"29204",
    "sg:province":"SC",
    "sg:tags":[
        "building",
        "nonresidential"
    ],
    "wof:name":"Dts Properties LLC",
    "wof:placetype":"venue"
},
  "geometry": {"coordinates":[-80.997404,34.011245],"type":"Point"}
}