{
  "type": "Feature",
  "properties": {
    "iso:country":"US",
    "sg:address":"158 Broad St",
    "sg:city":"Charleston",
    "sg:classifiers":[
        {
            "category":"Real Estate",
            "subcategory":"Architect",
            "type":"Services"
        }
    ],
    "sg:phone":"+1 843 853 3417",
    "sg:postcode":"29401",
    "sg:province":"SC",
    "wof:name":"David Richards Architects",
    "wof:placetype":"venue"
},
  "geometry": {"coordinates":[-79.937282,32.77575],"type":"Point"}
}