{
  "type": "Feature",
  "properties": {
    "iso:country":"US",
    "sg:address":"829 Knox Abbott Dr Ste B",
    "sg:city":"Cayce",
    "sg:classifiers":[
        {
            "category":"Personal",
            "subcategory":"Barber",
            "type":"Services"
        }
    ],
    "sg:phone":"+1 803 791 8466",
    "sg:postcode":"29033",
    "sg:province":"SC",
    "wof:name":"Hair West",
    "wof:placetype":"venue"
},
  "geometry": {"coordinates":[-81.062302,33.982201],"type":"Point"}
}