{
  "type": "Feature",
  "properties": {
    "iso:country":"US",
    "sg:address":"1526 Poinsett Hwy",
    "sg:city":"Greenville",
    "sg:classifiers":[
        {
            "category":"Shopping",
            "subcategory":"Shoes",
            "type":"Retail Goods"
        }
    ],
    "sg:phone":"+1 864 233 5401",
    "sg:postcode":"29609",
    "sg:province":"SC",
    "wof:name":"Hibbett Sporting Goods Inc",
    "wof:placetype":"venue"
},
  "geometry": {"coordinates":[-82.408912,34.893876],"type":"Point"}
}