{
  "type": "Feature",
  "properties": {
    "addr:full":"215 Riverview Dr Greenville SC 29611",
    "addr:housenumber":"215",
    "addr:postcode":"29611",
    "addr:street":"Riverview Dr",
    "iso:country":"US",
    "sg:address":"215 Riverview Dr",
    "sg:city":"Greenville",
    "sg:classifiers":[
        {
            "category":"Wholesale",
            "subcategory":"Machinery & Supplies",
            "type":"Manufacturing & Wholesale Goods"
        }
    ],
    "sg:phone":"+1 864 295 3457",
    "sg:postcode":"29611",
    "sg:province":"SC",
    "sg:tags":[
        "equipment",
        "industrial"
    ],
    "wof:name":"OKelleys Textile Machines",
    "wof:placetype":"venue"
},
  "geometry": {"coordinates":[-82.486082,34.835386],"type":"Point"}
}