{
  "type": "Feature",
  "properties": {
    "iso:country":"US",
    "sg:address":"2719 US Hwy 378 W",
    "sg:city":"Gilbert",
    "sg:classifiers":[
        {
            "category":"Retail",
            "subcategory":"Repair Shop",
            "type":"Services"
        }
    ],
    "sg:phone":"+1 803 892 6145",
    "sg:postcode":"29054",
    "sg:province":"SC",
    "sg:tags":[
        "outboard",
        "motor"
    ],
    "wof:name":"Boat Doctor",
    "wof:placetype":"venue"
},
  "geometry": {"coordinates":[-81.423942,34.017536],"type":"Point"}
}