{
  "type": "Feature",
  "properties": {
    "iso:country":"US",
    "sg:address":"1808 Asheville Hwy",
    "sg:city":"Spartanburg",
    "sg:classifiers":[
        {
            "category":"Food & Beverages",
            "subcategory":"Groceries & Convenience Stores",
            "type":"Retail Goods"
        }
    ],
    "sg:phone":"+1 864 583 7470",
    "sg:postcode":"29303",
    "sg:province":"SC",
    "wof:name":"Spinx Oil Co",
    "wof:placetype":"venue"
},
  "geometry": {"coordinates":[-81.971566,34.983341],"type":"Point"}
}