{
  "type": "Feature",
  "properties": {
    "addr:full":"400 S Main St Mauldin SC 29662",
    "addr:housenumber":"400",
    "addr:postcode":"29662",
    "addr:street":"S Main St",
    "iso:country":"US",
    "sg:address":"400 S Main St",
    "sg:city":"Mauldin",
    "sg:classifiers":[
        {
            "category":"Personal",
            "subcategory":"Beauty Salon",
            "type":"Services"
        }
    ],
    "sg:phone":"+1 864 962 1635",
    "sg:postcode":"29662",
    "sg:province":"SC",
    "wof:name":"Lady Eloise Styling Salon",
    "wof:placetype":"venue"
},
  "geometry": {"coordinates":[-82.298411,34.772904],"type":"Point"}
}