{
  "type": "Feature",
  "properties": {
    "addr:full":"165 E Kennedy St Spartanburg SC 29302",
    "addr:housenumber":"165",
    "addr:postcode":"29302",
    "addr:street":"E Kennedy St",
    "iso:country":"US",
    "sg:address":"165 E Kennedy St",
    "sg:city":"Spartanburg",
    "sg:classifiers":[
        {
            "category":"Real Estate",
            "subcategory":"Real Estate Agent",
            "type":"Services"
        }
    ],
    "sg:phone":"+1 864 585 0582",
    "sg:postcode":"29302",
    "sg:province":"SC",
    "wof:name":"Spann Realty Co",
    "wof:placetype":"venue"
},
  "geometry": {"coordinates":[-81.927409,34.94821],"type":"Point"}
}