{
  "type": "Feature",
  "properties": {
    "iso:country":"US",
    "sg:address":"3 Centella Ct",
    "sg:city":"Hilton Head Isle",
    "sg:classifiers":[
        {
            "category":"Insurance",
            "subcategory":"Insurance Agent",
            "type":"Services"
        }
    ],
    "sg:phone":"+1 843 683 9774",
    "sg:postcode":"29926",
    "sg:province":"SC",
    "wof:name":"Island Benefit Plans Inc",
    "wof:placetype":"venue"
},
  "geometry": {"coordinates":[-80.71821199999999,32.243803],"type":"Point"}
}