{
  "type": "Feature",
  "properties": {
    "iso:country":"US",
    "sg:address":"1024 Elmwood Ave",
    "sg:city":"Columbia",
    "sg:classifiers":[
        {
            "category":"Restaurant",
            "type":"Food & Drink"
        }
    ],
    "sg:menulink":"http://www.allmenus.com/sc/columbia/201300-mcdonalds/menu/",
    "sg:postcode":"29201",
    "sg:province":"SC",
    "sg:tags":[
        "burger",
        "american"
    ],
    "wof:name":"McDonald's",
    "wof:placetype":"venue"
},
  "geometry": {"coordinates":[-81.041507,34.012499],"type":"Point"}
}