{
  "type": "Feature",
  "properties": {
    "iso:country":"US",
    "sg:address":"631 Augusta St",
    "sg:city":"Greenville",
    "sg:classifiers":[
        {
            "category":"Shopping",
            "subcategory":"Pharmacy",
            "type":"Retail Goods"
        }
    ],
    "sg:phone":"+1 864 232 1932",
    "sg:postcode":"29605",
    "sg:province":"SC",
    "wof:name":"Medical Arts Pharmacy",
    "wof:placetype":"venue"
},
  "geometry": {"coordinates":[-82.40590899999999,34.836945],"type":"Point"}
}