{
  "type": "Feature",
  "properties": {
    "addr:full":"232 Tathom Rd Eastover SC 29044",
    "addr:housenumber":"232",
    "addr:postcode":"29044",
    "addr:street":"Tathom Rd",
    "iso:country":"US",
    "sg:address":"232 Tathom Rd",
    "sg:city":"Eastover",
    "sg:classifiers":[
        {
            "category":"Building & Trades",
            "subcategory":"Electrical",
            "type":"Services"
        }
    ],
    "sg:phone":"+1 803 353 8393",
    "sg:postcode":"29044",
    "sg:province":"SC",
    "sg:tags":[
        "electric",
        "contractor"
    ],
    "wof:name":"Taylor Electric",
    "wof:placetype":"venue"
},
  "geometry": {"coordinates":[-80.733369,33.918684],"type":"Point"}
}