{
  "type": "Feature",
  "properties": {
    "iso:country":"US",
    "sg:address":"4600 Lamar Hwy",
    "sg:city":"Lamar",
    "sg:classifiers":[
        {
            "category":"Restaurant",
            "type":"Food & Drink"
        }
    ],
    "sg:phone":"+1 843 326 1607",
    "sg:postcode":"29069",
    "sg:province":"SC",
    "wof:name":"Ronnie's Cafe",
    "wof:placetype":"venue"
},
  "geometry": {"coordinates":[-80.028147,34.204866],"type":"Point"}
}