{
  "type": "Feature",
  "properties": {
    "iso:country":"US",
    "sg:address":"355 Night Harbor Dr",
    "sg:city":"Chapin",
    "sg:classifiers":[
        {
            "category":"Real Estate",
            "subcategory":"Real Estate Operator",
            "type":"Services"
        }
    ],
    "sg:phone":"+1 803 345 0641",
    "sg:postcode":"29036",
    "sg:province":"SC",
    "sg:tags":[
        "building",
        "nonresidential"
    ],
    "wof:name":"Gore Properties LLC",
    "wof:placetype":"venue"
},
  "geometry": {"coordinates":[-81.373414,34.11012],"type":"Point"}
}