{
  "type": "Feature",
  "properties": {
    "addr:full":"445 Folly Rd Charleston SC 29412",
    "addr:housenumber":"445",
    "addr:postcode":"29412",
    "addr:street":"Folly Rd",
    "iso:country":"US",
    "sg:address":"445 Folly Rd",
    "sg:city":"Charleston",
    "sg:classifiers":[
        {
            "category":"Professional",
            "subcategory":"Lawyer & Legal Services",
            "type":"Services"
        }
    ],
    "sg:phone":"+1 843 795 3727",
    "sg:postcode":"29412",
    "sg:province":"SC",
    "sg:tags":[
        "attorney"
    ],
    "wof:name":"Mario S Inglese PC Attorney",
    "wof:placetype":"venue"
},
  "geometry": {"coordinates":[-79.972815,32.755881],"type":"Point"}
}