{
  "type": "Feature",
  "properties": {
    "iso:country":"US",
    "sg:address":"101 Lafayette St",
    "sg:city":"Spartanburg",
    "sg:classifiers":[
        {
            "category":"Banks & Credit Unions",
            "subcategory":"Investment Brokerage",
            "type":"Services"
        }
    ],
    "sg:phone":"+1 864 585 0020",
    "sg:postcode":"29302",
    "sg:province":"SC",
    "sg:tags":[
        "security"
    ],
    "wof:name":"Mahon & Ryan Investments",
    "wof:placetype":"venue"
},
  "geometry": {"coordinates":[-81.91923199999999,34.949467],"type":"Point"}
}