{
  "type": "Feature",
  "properties": {
    "iso:country":"US",
    "sg:address":"3505 Pelham Rd",
    "sg:city":"Greenville",
    "sg:classifiers":[
        {
            "category":"Health Services",
            "subcategory":"Doctor",
            "type":"Services"
        }
    ],
    "sg:phone":"+1 864 288 8878",
    "sg:postcode":"29615",
    "sg:province":"SC",
    "sg:tags":[
        "physician",
        "surgeon"
    ],
    "wof:name":"Oaktree Medical Ctr",
    "wof:placetype":"venue"
},
  "geometry": {"coordinates":[-82.301439,34.856685],"type":"Point"}
}