{
  "type": "Feature",
  "properties": {
    "addr:full":"1115 Central Ave Summerville SC 29483",
    "addr:housenumber":"1115",
    "addr:postcode":"29483",
    "addr:street":"Central Ave",
    "iso:country":"US",
    "sg:address":"1115 Central Ave",
    "sg:city":"Summerville",
    "sg:classifiers":[
        {
            "category":"Personal",
            "subcategory":"Tanning Parlor",
            "type":"Services"
        }
    ],
    "sg:phone":"+1 843 832 8269",
    "sg:postcode":"29483",
    "sg:province":"SC",
    "sg:tags":[
        "salon"
    ],
    "wof:name":"Tantastic",
    "wof:placetype":"venue"
},
  "geometry": {"coordinates":[-80.257542,33.003667],"type":"Point"}
}