{
  "type": "Feature",
  "properties": {
    "addr:full":"1616 Cedar Creek Rd Pelion SC 29123",
    "addr:housenumber":"1616",
    "addr:postcode":"29123",
    "addr:street":"Cedar Creek Rd",
    "iso:country":"US",
    "sg:address":"1616 Cedar Creek Rd",
    "sg:city":"Pelion",
    "sg:classifiers":[
        {
            "category":"Building & Trades",
            "subcategory":"Construction",
            "type":"Services"
        }
    ],
    "sg:phone":"+1 803 894 7741",
    "sg:postcode":"29123",
    "sg:province":"SC",
    "sg:tags":[
        "residential",
        "general",
        "contractor"
    ],
    "wof:name":"Green O'Neal Construction",
    "wof:placetype":"venue"
},
  "geometry": {"coordinates":[-81.254379,33.690273],"type":"Point"}
}