{
  "type": "Feature",
  "properties": {
    "iso:country":"US",
    "sg:address":"203 Race St",
    "sg:city":"St Stephen",
    "sg:classifiers":[
        {
            "category":"Building & Trades",
            "subcategory":"Construction",
            "type":"Services"
        }
    ],
    "sg:phone":"+1 843 567 7223",
    "sg:postcode":"29403",
    "sg:province":"SC",
    "sg:tags":[
        "clearing",
        "land",
        "leveling"
    ],
    "wof:name":"Crawford Land Clearing",
    "wof:placetype":"venue"
},
  "geometry": {"coordinates":[-79.949907,32.796879],"type":"Point"}
}