{
  "type": "Feature",
  "properties": {
    "addr:full":"205 E Broad St Darlington SC 29532",
    "addr:housenumber":"205",
    "addr:postcode":"29532",
    "addr:street":"E Broad St",
    "iso:country":"US",
    "sg:address":"205 E Broad St",
    "sg:city":"Darlington",
    "sg:classifiers":[
        {
            "category":"Shopping",
            "subcategory":"Florist",
            "type":"Retail Goods"
        }
    ],
    "sg:phone":"+1 843 393 3865",
    "sg:postcode":"29532",
    "sg:province":"SC",
    "wof:name":"Park Florist",
    "wof:placetype":"venue"
},
  "geometry": {"coordinates":[-79.865362,34.30155],"type":"Point"}
}