{
  "type": "Feature",
  "properties": {
    "iso:country":"US",
    "sg:address":"608 Furman Rd",
    "sg:city":"Greenville",
    "sg:classifiers":[
        {
            "category":"Manufacturing",
            "subcategory":"Rubber & Plastics",
            "type":"Manufacturing & Wholesale Goods"
        }
    ],
    "sg:phone":"+1 864 232 4423",
    "sg:postcode":"29609",
    "sg:province":"SC",
    "wof:name":"G F League Co",
    "wof:placetype":"venue"
},
  "geometry": {"coordinates":[-82.40550399999999,34.887762],"type":"Point"}
}