{
  "type": "Feature",
  "properties": {
    "iso:country":"US",
    "sg:address":"5020 Rivers Ave",
    "sg:city":"North Charleston",
    "sg:classifiers":[
        {
            "category":"Travel",
            "subcategory":"Hotels & Motels",
            "type":"Entertainment"
        }
    ],
    "sg:phone":"+1 843 554 4982",
    "sg:postcode":"29406",
    "sg:province":"SC",
    "wof:name":"Economy Inn & Suites",
    "wof:placetype":"venue"
},
  "geometry": {"coordinates":[-80.008645,32.885003],"type":"Point"}
}