{
  "type": "Feature",
  "properties": {
    "iso:country":"US",
    "sg:address":"6601 Rivers Ave",
    "sg:city":"North Charleston",
    "sg:classifiers":[
        {
            "category":"Restaurant",
            "type":"Food & Drink"
        }
    ],
    "sg:phone":"+1 843 797 5561",
    "sg:postcode":"29406",
    "sg:province":"SC",
    "wof:name":"Carey Hilliard's Restaurant",
    "wof:placetype":"venue"
},
  "geometry": {"coordinates":[-80.027779,32.917341],"type":"Point"}
}