{
  "type": "Feature",
  "properties": {
    "iso:country":"US",
    "sg:address":"1731 Bush River Rd",
    "sg:city":"Columbia",
    "sg:classifiers":[
        {
            "category":"Professional",
            "type":"Services"
        }
    ],
    "sg:phone":"+1 803 731 3879",
    "sg:postcode":"29210",
    "sg:province":"SC",
    "wof:name":"S C State Govt Sled Tech Svc",
    "wof:placetype":"venue"
},
  "geometry": {"coordinates":[-81.116331,34.029922],"type":"Point"}
}