{
  "type": "Feature",
  "properties": {
    "iso:country":"US",
    "sg:address":"1221 Peach Orchard Rd",
    "sg:city":"Sumter",
    "sg:classifiers":[
        {
            "category":"Shopping",
            "type":"Retail Goods"
        }
    ],
    "sg:phone":"+1 803 494 9691",
    "sg:postcode":"29154",
    "sg:province":"SC",
    "sg:tags":[
        "pet",
        "shop"
    ],
    "wof:name":"Sugar N Spice",
    "wof:placetype":"venue"
},
  "geometry": {"coordinates":[-80.498,33.95299],"type":"Point"}
}