{
  "type": "Feature",
  "properties": {
    "iso:country":"US",
    "sg:address":"1318 State Hwy 9 Byp",
    "sg:city":"Lancaster",
    "sg:classifiers":[
        {
            "category":"Personal",
            "subcategory":"Beauty Salon",
            "type":"Services"
        }
    ],
    "sg:phone":"+1 803 285 6654",
    "sg:postcode":"29720",
    "sg:province":"SC",
    "wof:name":"Double Take",
    "wof:placetype":"venue"
},
  "geometry": {"coordinates":[-80.800574,34.733079],"type":"Point"}
}