{
  "type": "Feature",
  "properties": {
    "iso:country":"US",
    "sg:address":"2617 Boyer St",
    "sg:city":"Beaufort",
    "sg:classifiers":[
        {
            "category":"Building & Trades",
            "subcategory":"Plumbing",
            "type":"Services"
        }
    ],
    "sg:phone":"+1 843 524 9134",
    "sg:postcode":"29902",
    "sg:province":"SC",
    "sg:tags":[
        "sheet",
        "work",
        "metal",
        "contractor"
    ],
    "wof:name":"Beaufort Home Improvements",
    "wof:placetype":"venue"
},
  "geometry": {"coordinates":[-80.694022,32.401908],"type":"Point"}
}