{
  "type": "Feature",
  "properties": {
    "iso:country":"US",
    "sg:address":"146 Sea Island Pkwy",
    "sg:city":"Beaufort",
    "sg:classifiers":[
        {
            "category":"Banks & Credit Unions",
            "subcategory":"Bank",
            "type":"Services"
        }
    ],
    "sg:phone":"+1 843 525 8451",
    "sg:postcode":"29907",
    "sg:province":"SC",
    "sg:website":"www.regions.com",
    "wof:name":"Regions",
    "wof:placetype":"venue"
},
  "geometry": {"coordinates":[-80.649587,32.41338],"type":"Point"}
}