{
  "type": "Feature",
  "properties": {
    "iso:country":"US",
    "sg:address":"743 Congaree Rd",
    "sg:city":"Greenville",
    "sg:classifiers":[
        {
            "category":"Personal",
            "type":"Services"
        }
    ],
    "sg:phone":"+1 864 213 9223",
    "sg:postcode":"29607",
    "sg:province":"SC",
    "sg:tags":[
        "wear",
        "formal"
    ],
    "wof:name":"Gregorys Formal Wear",
    "wof:placetype":"venue"
},
  "geometry": {"coordinates":[-82.321717,34.843914],"type":"Point"}
}