{
  "type": "Feature",
  "properties": {
    "addr:full":"9561 Hamburg Rd Ladson SC 29456",
    "addr:housenumber":"9561",
    "addr:postcode":"29456",
    "addr:street":"Hamburg Rd",
    "iso:country":"US",
    "sg:address":"9561 Hamburg Rd",
    "sg:city":"Ladson",
    "sg:classifiers":[
        {
            "category":"Building & Trades",
            "subcategory":"Construction",
            "type":"Services"
        }
    ],
    "sg:phone":"+1 843 851 1449",
    "sg:postcode":"29456",
    "sg:province":"SC",
    "wof:name":"Design Build Corp",
    "wof:placetype":"venue"
},
  "geometry": {"coordinates":[-80.11520400000001,32.980917],"type":"Point"}
}