{
  "type": "Feature",
  "properties": {
    "iso:country":"US",
    "sg:address":"112 Sam Brown Rd",
    "sg:city":"Seneca",
    "sg:classifiers":[
        {
            "category":"Wholesale",
            "subcategory":"Auto Parts",
            "type":"Manufacturing & Wholesale Goods"
        }
    ],
    "sg:phone":"+1 864 972 2090",
    "sg:postcode":"29678",
    "sg:province":"SC",
    "sg:tags":[
        "supply"
    ],
    "wof:name":"Morgan Auto Parts",
    "wof:placetype":"venue"
},
  "geometry": {"coordinates":[-82.98128,34.628384],"type":"Point"}
}