{
  "type": "Feature",
  "properties": {
    "addr:full":"303 Thompson Blvd Union SC 29379",
    "addr:housenumber":"303",
    "addr:postcode":"29379",
    "addr:street":"Thompson Blvd",
    "iso:country":"US",
    "sg:address":"303 Thompson Blvd",
    "sg:city":"Union",
    "sg:classifiers":[
        {
            "category":"Autos & Motor Vehicles",
            "subcategory":"Fuel & Gas Station",
            "type":"Retail Goods"
        }
    ],
    "sg:phone":"+1 864 427 9751",
    "sg:postcode":"29379",
    "sg:province":"SC",
    "sg:tags":[
        "oil"
    ],
    "wof:name":"Enmark Stations",
    "wof:placetype":"venue"
},
  "geometry": {"coordinates":[-81.629773,34.726232],"type":"Point"}
}