{
  "type": "Feature",
  "properties": {
    "iso:country":"US",
    "sg:address":"1401 Phoenix St",
    "sg:city":"Greenwood",
    "sg:classifiers":[
        {
            "category":"Real Estate",
            "subcategory":"Real Estate Operator",
            "type":"Services"
        }
    ],
    "sg:phone":"+1 864 227 6091",
    "sg:postcode":"29646",
    "sg:province":"SC",
    "sg:tags":[
        "apartment"
    ],
    "wof:name":"Greenwood Gardens Apartments",
    "wof:placetype":"venue"
},
  "geometry": {"coordinates":[-82.149123,34.177304],"type":"Point"}
}