{
  "type": "Feature",
  "properties": {
    "iso:country":"US",
    "sg:address":"9570 Shore Dr",
    "sg:city":"Myrtle Beach",
    "sg:classifiers":[
        {
            "category":"Real Estate",
            "subcategory":"Real Estate Operator",
            "type":"Services"
        }
    ],
    "sg:phone":"+1 843 692 0907",
    "sg:postcode":"29572",
    "sg:province":"SC",
    "sg:tags":[
        "condominium"
    ],
    "wof:name":"Pelicans Watch Condo Assn",
    "wof:placetype":"venue"
},
  "geometry": {"coordinates":[-78.792225,33.757997],"type":"Point"}
}