{
  "type": "Feature",
  "properties": {
    "iso:country":"US",
    "sg:address":"1214 Pine St",
    "sg:city":"Conway",
    "sg:classifiers":[
        {
            "category":"Retail",
            "subcategory":"Veterinary Services",
            "type":"Services"
        }
    ],
    "sg:phone":"+1 843 248 2752",
    "sg:postcode":"29526",
    "sg:province":"SC",
    "wof:name":"Rjazs LLP",
    "wof:placetype":"venue"
},
  "geometry": {"coordinates":[-79.062298,33.845229],"type":"Point"}
}