{
  "type": "Feature",
  "properties": {
    "addr:full":"702 W 3rd Ave Lake View SC 29563",
    "addr:housenumber":"702",
    "addr:postcode":"29563",
    "addr:street":"W 3Rd Ave",
    "iso:country":"US",
    "sg:address":"702 W 3rd Ave",
    "sg:city":"Lake View",
    "sg:classifiers":[
        {
            "category":"Health Services",
            "subcategory":"Nursing And Care Facility",
            "type":"Services"
        }
    ],
    "sg:phone":"+1 843 759 9099",
    "sg:postcode":"29563",
    "sg:province":"SC",
    "sg:tags":[
        "home",
        "retirement",
        "community"
    ],
    "wof:name":"Thorne Retirement Home",
    "wof:placetype":"venue"
},
  "geometry": {"coordinates":[-79.175794,34.343454],"type":"Point"}
}