{
  "type": "Feature",
  "properties": {
    "iso:country":"US",
    "sg:address":"3106 Broad River Rd Ste 1",
    "sg:city":"Columbia",
    "sg:classifiers":[
        {
            "category":"Personal",
            "subcategory":"Barber",
            "type":"Services"
        }
    ],
    "sg:phone":"+1 803 731 5020",
    "sg:postcode":"29210",
    "sg:province":"SC",
    "wof:name":"J's Top Notch Barber Shop",
    "wof:placetype":"venue"
},
  "geometry": {"coordinates":[-81.105797,34.050201],"type":"Point"}
}