{
  "type": "Feature",
  "properties": {
    "addr:full":"104 Tolar Rd Travelers Rest SC 29690",
    "addr:housenumber":"104",
    "addr:postcode":"29690",
    "addr:street":"Tolar Rd",
    "iso:country":"US",
    "sg:address":"104 Tolar Rd",
    "sg:city":"Travelers Rest",
    "sg:classifiers":[
        {
            "category":"Building & Trades",
            "subcategory":"Construction",
            "type":"Services"
        }
    ],
    "sg:phone":"+1 864 834 2681",
    "sg:postcode":"29690",
    "sg:province":"SC",
    "sg:tags":[
        "contractor"
    ],
    "wof:name":"Joey Metcalf Masonry Cnstr",
    "wof:placetype":"venue"
},
  "geometry": {"coordinates":[-82.444992,34.974885],"type":"Point"}
}