{
  "type": "Feature",
  "properties": {
    "iso:country":"US",
    "sg:address":"30 Carroll Ct",
    "sg:city":"West Columbia",
    "sg:classifiers":[
        {
            "category":"Retail",
            "subcategory":"Repair Shop",
            "type":"Services"
        }
    ],
    "sg:phone":"+1 803 926 7083",
    "sg:postcode":"29170",
    "sg:province":"SC",
    "sg:tags":[
        "reupholstery",
        "furniture"
    ],
    "wof:name":"Discount Upholstering",
    "wof:placetype":"venue"
},
  "geometry": {"coordinates":[-81.141237,33.974818],"type":"Point"}
}