{
  "type": "Feature",
  "properties": {
    "addr:full":"532 Brooks Rd Belton SC 29627",
    "addr:housenumber":"532",
    "addr:postcode":"29627",
    "addr:street":"Brooks Rd",
    "iso:country":"US",
    "sg:address":"532 Brooks Rd",
    "sg:city":"Belton",
    "sg:classifiers":[
        {
            "category":"Building & Trades",
            "subcategory":"Plumbing",
            "type":"Services"
        }
    ],
    "sg:phone":"+1 864 940 2971",
    "sg:postcode":"29627",
    "sg:province":"SC",
    "sg:tags":[
        "conditioning",
        "air",
        "system",
        "contractor"
    ],
    "wof:name":"Norman's Comfort Control",
    "wof:placetype":"venue"
},
  "geometry": {"coordinates":[-82.568972,34.565218],"type":"Point"}
}