{
  "type": "Feature",
  "properties": {
    "addr:full":"607 Broad St Camden SC 29020",
    "addr:housenumber":"607",
    "addr:postcode":"29020",
    "addr:street":"Broad St",
    "iso:country":"US",
    "sg:address":"607 Broad St",
    "sg:city":"Camden",
    "sg:classifiers":[
        {
            "category":"Organizations",
            "subcategory":"Professional Association",
            "type":"Services"
        }
    ],
    "sg:phone":"+1 803 432 2525",
    "sg:postcode":"29020",
    "sg:province":"SC",
    "sg:tags":[
        "chambers",
        "commerce"
    ],
    "wof:name":"Chamber Of Commerce",
    "wof:placetype":"venue"
},
  "geometry": {"coordinates":[-80.606421,34.238988],"type":"Point"}
}