{
  "type": "Feature",
  "properties": {
    "iso:country":"US",
    "sg:address":"3009 Church St",
    "sg:city":"Myrtle Beach",
    "sg:classifiers":[
        {
            "category":"Real Estate",
            "subcategory":"Real Estate Agent",
            "type":"Services"
        }
    ],
    "sg:phone":"+1 843 946 5300",
    "sg:postcode":"29577",
    "sg:province":"SC",
    "sg:tags":[
        "management"
    ],
    "sg:website":"www.ccmcnet.com",
    "wof:name":"Capital Consultants Mgmt Corp",
    "wof:placetype":"venue"
},
  "geometry": {"coordinates":[-78.880709,33.722677],"type":"Point"}
}