{
  "type": "Feature",
  "properties": {
    "iso:country":"US",
    "sg:address":"1720 Sam Rittenberg Blvd",
    "sg:city":"Charleston",
    "sg:classifiers":[
        {
            "category":"Personal",
            "subcategory":"Beauty Salon",
            "type":"Services"
        }
    ],
    "sg:phone":"+1 843 571 0990",
    "sg:postcode":"29407",
    "sg:province":"SC",
    "wof:name":"Years A Head Hair Nail & Skin",
    "wof:placetype":"venue"
},
  "geometry": {"coordinates":[-80.01269499999999,32.804574],"type":"Point"}
}