{
  "type": "Feature",
  "properties": {
    "iso:country":"US",
    "sg:address":"63 Port Tack",
    "sg:city":"Hilton Head Island",
    "sg:classifiers":[
        {
            "category":"Real Estate",
            "subcategory":"Real Estate Agent",
            "type":"Services"
        }
    ],
    "sg:phone":"+1 843 842 5050",
    "sg:postcode":"29928",
    "sg:province":"SC",
    "wof:name":"Phil Porter Realtor LLC",
    "wof:placetype":"venue"
},
  "geometry": {"coordinates":[-80.715901,32.182358],"type":"Point"}
}