{
  "type": "Feature",
  "properties": {
    "iso:country":"US",
    "sg:address":"973 N Main St",
    "sg:city":"Lancaster",
    "sg:classifiers":[
        {
            "category":"Insurance",
            "subcategory":"Insurance Agent",
            "type":"Services"
        }
    ],
    "sg:phone":"+1 803 286 2115",
    "sg:postcode":"29720",
    "sg:province":"SC",
    "wof:name":"Allstate Insurance",
    "wof:placetype":"venue"
},
  "geometry": {"coordinates":[-80.776262,34.730028],"type":"Point"}
}