{
  "type": "Feature",
  "properties": {
    "addr:full":"384 Shelter Bay Dr Prosperity SC 29127",
    "addr:housenumber":"384",
    "addr:postcode":"29127",
    "addr:street":"Shelter Bay Dr",
    "iso:country":"US",
    "sg:address":"384 Shelter Bay Dr",
    "sg:city":"Prosperity",
    "sg:classifiers":[
        {
            "category":"Building & Trades",
            "subcategory":"Construction",
            "type":"Services"
        }
    ],
    "sg:phone":"+1 803 924 6152",
    "sg:postcode":"29127",
    "sg:province":"SC",
    "sg:tags":[
        "house"
    ],
    "wof:name":"RC Reynolds Construction Inc",
    "wof:placetype":"venue"
},
  "geometry": {"coordinates":[-81.541892,34.094817],"type":"Point"}
}