{
  "type": "Feature",
  "properties": {
    "iso:country":"US",
    "sg:address":"1626 Hwy 17",
    "sg:city":"North Myrtle Bch",
    "sg:classifiers":[
        {
            "category":"Professional",
            "subcategory":"Accounting & Tax Preparation",
            "type":"Services"
        }
    ],
    "sg:phone":"+1 843 361 3263",
    "sg:postcode":"29582",
    "sg:province":"SC",
    "sg:tags":[
        "billing"
    ],
    "wof:name":"Rapid Receivables",
    "wof:placetype":"venue"
},
  "geometry": {"coordinates":[-78.657311,33.846438],"type":"Point"}
}