{
  "type": "Feature",
  "properties": {
    "iso:country":"US",
    "sg:address":"209 Augusta Rd",
    "sg:city":"North Augusta",
    "sg:classifiers":[
        {
            "category":"Building & Trades",
            "subcategory":"Landscaping Services",
            "type":"Services"
        }
    ],
    "sg:phone":"+1 803 270 6433",
    "sg:postcode":"29822",
    "sg:province":"SC",
    "sg:tags":[
        "tree"
    ],
    "wof:name":"Affordable Tree Removal Co",
    "wof:placetype":"venue"
},
  "geometry": {"coordinates":[-81.892088,33.496685],"type":"Point"}
}