{
  "type": "Feature",
  "properties": {
    "iso:country":"US",
    "sg:address":"2070 Harley St",
    "sg:city":"North Charleston",
    "sg:classifiers":[
        {
            "category":"Organizations",
            "subcategory":"Religious Organization",
            "type":"Services"
        }
    ],
    "sg:phone":"+1 843 554 7355",
    "sg:postcode":"29406",
    "sg:province":"SC",
    "sg:tags":[
        "church"
    ],
    "wof:name":"New Life Missionary Bapt Chr",
    "wof:placetype":"venue"
},
  "geometry": {"coordinates":[-80.009959,32.892194],"type":"Point"}
}