{
  "type": "Feature",
  "properties": {
    "addr:full":"2070 Harley St North Charleston SC 29406",
    "addr:housenumber":"2070",
    "addr:postcode":"29406",
    "addr:street":"Harley St",
    "iso:country":"US",
    "sg:address":"2070 Harley St",
    "sg:city":"North Charleston",
    "sg:classifiers":[
        {
            "category":"Organizations",
            "subcategory":"Religious Organization",
            "type":"Services"
        }
    ],
    "sg:phone":"+1 843 554 7355",
    "sg:postcode":"29406",
    "sg:province":"SC",
    "sg:tags":[
        "church"
    ],
    "wof:name":"New Life Missionary Bapt Chr",
    "wof:placetype":"venue"
},
  "geometry": {"coordinates":[-80.00995899999999,32.892194],"type":"Point"}
}