{
  "type": "Feature",
  "properties": {
    "addr:full":"155 S Cherry Rd Rock Hill SC 29732",
    "addr:housenumber":"155",
    "addr:postcode":"29732",
    "addr:street":"S Cherry Rd",
    "iso:country":"US",
    "sg:address":"155 S Cherry Rd",
    "sg:city":"Rock Hill",
    "sg:classifiers":[
        {
            "category":"Building & Trades",
            "subcategory":"Construction",
            "type":"Services"
        }
    ],
    "sg:phone":"+1 803 328 6556",
    "sg:postcode":"29732",
    "sg:province":"SC",
    "sg:tags":[
        "painter"
    ],
    "wof:name":"J & W Paint Co",
    "wof:placetype":"venue"
},
  "geometry": {"coordinates":[-81.038583,34.939963],"type":"Point"}
}