{
  "type": "Feature",
  "properties": {
    "iso:country":"US",
    "sg:address":"116 Craigwood Dr",
    "sg:city":"Blythewood",
    "sg:classifiers":[
        {
            "category":"Professional",
            "subcategory":"Computer Services",
            "type":"Services"
        }
    ],
    "sg:phone":"+1 803 754 5085",
    "sg:postcode":"29016",
    "sg:province":"SC",
    "sg:tags":[
        "consultant",
        "designer"
    ],
    "wof:name":"CAD Designs Inc",
    "wof:placetype":"venue"
},
  "geometry": {"coordinates":[-80.926244,34.179139],"type":"Point"}
}