{
  "type": "Feature",
  "properties": {
    "iso:country":"US",
    "sg:address":"702 Hunters Creek Blvd",
    "sg:city":"Greenwood",
    "sg:classifiers":[
        {
            "category":"Real Estate",
            "subcategory":"Developer",
            "type":"Services"
        }
    ],
    "sg:phone":"+1 864 223 0606",
    "sg:postcode":"29649",
    "sg:province":"SC",
    "wof:name":"Southern Land Development",
    "wof:placetype":"venue"
},
  "geometry": {"coordinates":[-82.233232,34.202444],"type":"Point"}
}