{
  "type": "Feature",
  "properties": {
    "iso:country":"US",
    "sg:address":"1403 Pearman Dairy Rd",
    "sg:city":"Anderson",
    "sg:classifiers":[
        {
            "category":"Retail",
            "subcategory":"Veterinary Services",
            "type":"Services"
        }
    ],
    "sg:phone":"+1 864 225 0015",
    "sg:postcode":"29625",
    "sg:province":"SC",
    "wof:name":"Electric City Animal Clinic",
    "wof:placetype":"venue"
},
  "geometry": {"coordinates":[-82.69366100000001,34.523847],"type":"Point"}
}