{
  "type": "Feature",
  "properties": {
    "iso:country":"US",
    "sg:address":"287 E Bay St",
    "sg:city":"Charleston",
    "sg:classifiers":[
        {
            "category":"Shopping",
            "subcategory":"Used Merchandise",
            "type":"Retail Goods"
        }
    ],
    "sg:phone":"+1 843 853 3307",
    "sg:postcode":"29401",
    "sg:province":"SC",
    "wof:name":"Green Shutters",
    "wof:placetype":"venue"
},
  "geometry": {"coordinates":[-79.928871,32.784591],"type":"Point"}
}