{
  "type": "Feature",
  "properties": {
    "iso:country":"US",
    "sg:address":"301 Haywood Rd",
    "sg:city":"Greenville",
    "sg:classifiers":[
        {
            "category":"Travel",
            "subcategory":"Travel Agent",
            "type":"Entertainment"
        }
    ],
    "sg:phone":"+1 864 329 9997",
    "sg:postcode":"29607",
    "sg:province":"SC",
    "sg:tags":[
        "agency",
        "bureau"
    ],
    "wof:name":"Andy On Call",
    "wof:placetype":"venue"
},
  "geometry": {"coordinates":[-82.343076,34.841709],"type":"Point"}
}