{
  "type": "Feature",
  "properties": {
    "addr:full":"707 Sulphur Springs Rd Greenville SC 29617",
    "addr:housenumber":"707",
    "addr:postcode":"29617",
    "addr:street":"Sulphur Springs Rd",
    "iso:country":"US",
    "sg:address":"707 Sulphur Springs Rd",
    "sg:city":"Greenville",
    "sg:classifiers":[
        {
            "category":"Shopping",
            "subcategory":"Used Merchandise",
            "type":"Retail Goods"
        }
    ],
    "sg:phone":"+1 864 294 6136",
    "sg:postcode":"29617",
    "sg:province":"SC",
    "wof:name":"United Veterans Thrift Store",
    "wof:placetype":"venue"
},
  "geometry": {"coordinates":[-82.45371400000001,34.888208],"type":"Point"}
}