{
  "type": "Feature",
  "properties": {
    "addr:full":"1135 Bowman Rd Mt Pleasant SC 29464",
    "addr:housenumber":"1135",
    "addr:postcode":"29464",
    "addr:street":"Bowman Rd",
    "iso:country":"US",
    "sg:address":"1135 Bowman Rd",
    "sg:city":"Mt Pleasant",
    "sg:classifiers":[
        {
            "category":"Manufacturing",
            "subcategory":"Printing",
            "type":"Manufacturing & Wholesale Goods"
        }
    ],
    "sg:phone":"+1 843 884 1953",
    "sg:postcode":"29464",
    "sg:province":"SC",
    "sg:tags":[
        "screen"
    ],
    "wof:name":"S K Designs",
    "wof:placetype":"venue"
},
  "geometry": {"coordinates":[-79.851882,32.810189],"type":"Point"}
}