{
  "type": "Feature",
  "properties": {
    "iso:country":"US",
    "sg:address":"1642 Rivers St",
    "sg:city":"Greenwood",
    "sg:classifiers":[
        {
            "category":"Building & Trades",
            "subcategory":"Electrical",
            "type":"Services"
        }
    ],
    "sg:phone":"+1 864 229 1155",
    "sg:postcode":"29649",
    "sg:province":"SC",
    "sg:tags":[
        "electric",
        "contractor"
    ],
    "wof:name":"Ward's Electric Inc",
    "wof:placetype":"venue"
},
  "geometry": {"coordinates":[-82.19924899999999,34.205118],"type":"Point"}
}