{
  "type": "Feature",
  "properties": {
    "iso:country":"US",
    "sg:address":"714 8th Ave N",
    "sg:city":"Myrtle Beach",
    "sg:classifiers":[
        {
            "category":"Shopping",
            "type":"Retail Goods"
        }
    ],
    "sg:phone":"+1 843 429 0018",
    "sg:postcode":"29577",
    "sg:province":"SC",
    "sg:tags":[
        "art",
        "gallery",
        "dealer"
    ],
    "wof:name":"Gallery On 8th",
    "wof:placetype":"venue"
},
  "geometry": {"coordinates":[-78.886214,33.694656],"type":"Point"}
}