{
  "type": "Feature",
  "properties": {
    "iso:country":"US",
    "sg:address":"1001 Bluff Rd",
    "sg:city":"Columbia",
    "sg:classifiers":[
        {
            "category":"Government",
            "subcategory":"Office",
            "type":"Public Place"
        }
    ],
    "sg:phone":"+1 803 737 4588",
    "sg:postcode":"29201",
    "sg:province":"SC",
    "wof:name":"Grading & Inspection",
    "wof:placetype":"venue"
},
  "geometry": {"coordinates":[-81.02067599999999,33.972508],"type":"Point"}
}