{
  "type": "Feature",
  "properties": {
    "addr:full":"1927 Augusta St Greenville SC 29605",
    "addr:housenumber":"1927",
    "addr:postcode":"29605",
    "addr:street":"Augusta St",
    "iso:country":"US",
    "sg:address":"1927 Augusta St",
    "sg:city":"Greenville",
    "sg:classifiers":[
        {
            "category":"Banks & Credit Unions",
            "subcategory":"Bank",
            "type":"Services"
        }
    ],
    "sg:phone":"+1 864 271 5912",
    "sg:postcode":"29605",
    "sg:province":"SC",
    "wof:name":"Bank Of America",
    "wof:placetype":"venue"
},
  "geometry": {"coordinates":[-82.396055,34.825888],"type":"Point"}
}