{
  "type": "Feature",
  "properties": {
    "iso:country":"US",
    "sg:address":"185 Ponderosa Dr",
    "sg:city":"Ladson",
    "sg:classifiers":[
        {
            "category":"Professional",
            "subcategory":"Management & Consulting",
            "type":"Services"
        }
    ],
    "sg:phone":"+1 843 553 0336",
    "sg:postcode":"29456",
    "sg:province":"SC",
    "sg:tags":[
        "consultant"
    ],
    "wof:name":"Gill Inc",
    "wof:placetype":"venue"
},
  "geometry": {"coordinates":[-80.116084,33.016169],"type":"Point"}
}