{
  "type": "Feature",
  "properties": {
    "addr:full":"305 Clarendon Ct Chesnee SC 29323",
    "addr:housenumber":"305",
    "addr:postcode":"29323",
    "addr:street":"Clarendon Ct",
    "iso:country":"US",
    "sg:address":"305 Clarendon Ct",
    "sg:city":"Chesnee",
    "sg:classifiers":[
        {
            "category":"Organizations",
            "subcategory":"Religious Organization",
            "type":"Services"
        }
    ],
    "sg:phone":"+1 864 461 8501",
    "sg:postcode":"29323",
    "sg:province":"SC",
    "sg:tags":[
        "church"
    ],
    "wof:name":"Mayo First Baptist Parsonage",
    "wof:placetype":"venue"
},
  "geometry": {"coordinates":[-81.860192,35.092944],"type":"Point"}
}