{
  "type": "Feature",
  "properties": {
    "addr:full":"5710 Rivers Ave Charleston SC 29406",
    "addr:housenumber":"5710",
    "addr:postcode":"29406",
    "addr:street":"Rivers Ave",
    "iso:country":"US",
    "sg:address":"5710 Rivers Ave",
    "sg:city":"Charleston",
    "sg:classifiers":[
        {
            "category":"Utilities",
            "subcategory":"Telephone",
            "type":"Services"
        }
    ],
    "sg:phone":"+1 843 308 0000",
    "sg:postcode":"29406",
    "sg:province":"SC",
    "sg:tags":[
        "communications"
    ],
    "wof:name":"Ndci",
    "wof:placetype":"venue"
},
  "geometry": {"coordinates":[-80.017235,32.899536],"type":"Point"}
}