{
  "type": "Feature",
  "properties": {
    "addr:full":"265 W Halfway Branch Rd Walhalla SC 29691",
    "addr:housenumber":"265",
    "addr:postcode":"29691",
    "addr:street":"W Halfway Branch Rd",
    "iso:country":"US",
    "sg:address":"265 W Halfway Branch Rd",
    "sg:city":"Walhalla",
    "sg:classifiers":[
        {
            "category":"Manufacturing",
            "subcategory":"Tools & Machinery",
            "type":"Manufacturing & Wholesale Goods"
        }
    ],
    "sg:phone":"+1 864 888 8578",
    "sg:postcode":"29691",
    "sg:province":"SC",
    "sg:tags":[
        "mfg",
        "vehicle"
    ],
    "wof:name":"Southern Eagle Mfg Inc",
    "wof:placetype":"venue"
},
  "geometry": {"coordinates":[-83.016898,34.720521],"type":"Point"}
}