{
  "type": "Feature",
  "properties": {
    "iso:country":"US",
    "sg:address":"620 Senn Rd",
    "sg:city":"Inman",
    "sg:classifiers":[
        {
            "category":"Building & Trades",
            "subcategory":"Pest Control",
            "type":"Services"
        }
    ],
    "sg:phone":"+1 864 578 7777",
    "sg:postcode":"29349",
    "sg:province":"SC",
    "wof:name":"Senn Pest Control",
    "wof:placetype":"venue"
},
  "geometry": {"coordinates":[-82.053665,35.079908],"type":"Point"}
}