{
  "type": "Feature",
  "properties": {
    "addr:full":"10823 Hemingway Hwy Kingstree SC 29556",
    "addr:housenumber":"10823",
    "addr:postcode":"29556",
    "addr:street":"Hemingway Hwy",
    "iso:country":"US",
    "sg:address":"10823 Hemingway Hwy",
    "sg:city":"Kingstree",
    "sg:classifiers":[
        {
            "category":"Food & Beverages",
            "subcategory":"Meat & Fish",
            "type":"Retail Goods"
        }
    ],
    "sg:phone":"+1 843 382 2971",
    "sg:postcode":"29556",
    "sg:province":"SC",
    "wof:name":"Carolina Meat Processors",
    "wof:placetype":"venue"
},
  "geometry": {"coordinates":[-79.796824,33.672982],"type":"Point"}
}