{
  "type": "Feature",
  "properties": {
    "iso:country":"US",
    "sg:address":"4430 Parris Bridge Rd",
    "sg:city":"Spartanburg",
    "sg:classifiers":[
        {
            "category":"Organizations",
            "subcategory":"Religious Organization",
            "type":"Services"
        }
    ],
    "sg:phone":"+1 864 578 0485",
    "sg:postcode":"29316",
    "sg:province":"SC",
    "sg:tags":[
        "church"
    ],
    "wof:name":"Jehovah's Witnesses",
    "wof:placetype":"venue"
},
  "geometry": {"coordinates":[-81.940292,35.050895],"type":"Point"}
}