{
  "type": "Feature",
  "properties": {
    "iso:country":"US",
    "sg:address":"325 Old Dunham Bridge Rd",
    "sg:city":"Greenville",
    "sg:classifiers":[
        {
            "category":"Freight",
            "type":"Transportation"
        }
    ],
    "sg:phone":"+1 864 269 6214",
    "sg:postcode":"29611",
    "sg:province":"SC",
    "sg:tags":[
        "operator",
        "local",
        "trucking"
    ],
    "wof:name":"Sdt Trucking Inc",
    "wof:placetype":"venue"
},
  "geometry": {"coordinates":[-82.460228,34.819763],"type":"Point"}
}