{
  "type": "Feature",
  "properties": {
    "iso:country":"US",
    "sg:address":"3267 Emanuel Church Rd",
    "sg:city":"Lexington",
    "sg:classifiers":[
        {
            "category":"Freight",
            "type":"Transportation"
        }
    ],
    "sg:phone":"+1 803 356 6854",
    "sg:postcode":"29073",
    "sg:province":"SC",
    "sg:tags":[
        "operator",
        "trucking"
    ],
    "wof:name":"Cross Country Auto Carriers In",
    "wof:placetype":"venue"
},
  "geometry": {"coordinates":[-81.185376,33.954826],"type":"Point"}
}