{
  "type": "Feature",
  "properties": {
    "iso:country":"US",
    "sg:address":"214 W Benson St",
    "sg:city":"Anderson",
    "sg:classifiers":[
        {
            "category":"Retail",
            "subcategory":"Repair Shop",
            "type":"Services"
        }
    ],
    "sg:phone":"+1 864 225 1930",
    "sg:postcode":"29624",
    "sg:province":"SC",
    "sg:tags":[
        "antique",
        "restoring"
    ],
    "wof:name":"Clarke Repair & Refinishing",
    "wof:placetype":"venue"
},
  "geometry": {"coordinates":[-82.653004,34.502462],"type":"Point"}
}