{
  "type": "Feature",
  "properties": {
    "iso:country":"US",
    "sg:address":"28 Professional Village Cir",
    "sg:city":"Beaufort",
    "sg:classifiers":[
        {
            "category":"Real Estate",
            "subcategory":"Surveying",
            "type":"Services"
        }
    ],
    "sg:phone":"+1 843 522 1798",
    "sg:postcode":"29907",
    "sg:province":"SC",
    "sg:tags":[
        "surveyor"
    ],
    "wof:name":"Gasque & Assoc Inc",
    "wof:placetype":"venue"
},
  "geometry": {"coordinates":[-80.652033,32.416076],"type":"Point"}
}