{
  "type": "Feature",
  "properties": {
    "iso:country":"US",
    "sg:address":"10201 Garners Ferry Rd",
    "sg:city":"Eastover",
    "sg:classifiers":[
        {
            "category":"Food & Beverages",
            "subcategory":"Groceries & Convenience Stores",
            "type":"Retail Goods"
        }
    ],
    "sg:phone":"+1 803 776 1582",
    "sg:postcode":"29044",
    "sg:province":"SC",
    "sg:tags":[
        "station",
        "gasoline"
    ],
    "wof:name":"OKellys Inc",
    "wof:placetype":"venue"
},
  "geometry": {"coordinates":[-80.81019499999999,33.947224],"type":"Point"}
}