{
  "type": "Feature",
  "properties": {
    "iso:country":"US",
    "sg:address":"50 Canal St",
    "sg:city":"Graniteville",
    "sg:classifiers":[
        {
            "category":"Shopping",
            "type":"Retail Goods"
        }
    ],
    "sg:phone":"+1 803 663 7588",
    "sg:postcode":"29829",
    "sg:province":"SC",
    "sg:tags":[
        "wedding",
        "supply"
    ],
    "wof:name":"Memorable Occasions",
    "wof:placetype":"venue"
},
  "geometry": {"coordinates":[-81.8079,33.563517],"type":"Point"}
}