{
  "type": "Feature",
  "properties": {
    "iso:country":"US",
    "sg:address":"208 N Main St",
    "sg:city":"Campobello",
    "sg:classifiers":[
        {
            "category":"Government",
            "subcategory":"Police Station",
            "type":"Public Place"
        }
    ],
    "sg:phone":"+1 864 468 4545",
    "sg:postcode":"29322",
    "sg:province":"SC",
    "sg:tags":[
        "department"
    ],
    "wof:name":"Campobello Police Dept",
    "wof:placetype":"venue"
},
  "geometry": {"coordinates":[-82.154432,35.116254],"type":"Point"}
}