{
  "type": "Feature",
  "properties": {
    "iso:country":"US",
    "sg:address":"230 Buist Ave",
    "sg:city":"Greenville",
    "sg:classifiers":[
        {
            "category":"Building & Trades",
            "subcategory":"Electrical",
            "type":"Services"
        }
    ],
    "sg:phone":"+1 864 235 6333",
    "sg:postcode":"29609",
    "sg:province":"SC",
    "sg:tags":[
        "electric",
        "contractor"
    ],
    "wof:name":"Huntington & Guerry Electric",
    "wof:placetype":"venue"
},
  "geometry": {"coordinates":[-82.40259,34.869851],"type":"Point"}
}