{
  "type": "Feature",
  "properties": {
    "iso:country":"US",
    "sg:address":"726 Old Spartanburg Hwy",
    "sg:city":"Wellford",
    "sg:classifiers":[
        {
            "category":"Social Services",
            "subcategory":"Adult Care",
            "type":"Services"
        }
    ],
    "sg:phone":"+1 864 439 9238",
    "sg:postcode":"29385",
    "sg:province":"SC",
    "sg:tags":[
        "home",
        "residential"
    ],
    "wof:name":"Reid's Residential Care Fclty",
    "wof:placetype":"venue"
},
  "geometry": {"coordinates":[-82.092364,34.940842],"type":"Point"}
}