{
  "type": "Feature",
  "properties": {
    "iso:country":"US",
    "sg:address":"2121 Boiling Springs Rd",
    "sg:city":"Spartanburg",
    "sg:classifiers":[
        {
            "category":"Health Services",
            "subcategory":"Chiropractor",
            "type":"Services"
        }
    ],
    "sg:phone":"+1 864 814 4325",
    "sg:postcode":"29316",
    "sg:province":"SC",
    "wof:name":"Golden Rule Chiropractic",
    "wof:placetype":"venue"
},
  "geometry": {"coordinates":[-81.967411,35.029659],"type":"Point"}
}