{
  "type": "Feature",
  "properties": {
    "iso:country":"US",
    "sg:address":"426 Aiken Hunt Cir",
    "sg:city":"Columbia",
    "sg:classifiers":[
        {
            "category":"Real Estate",
            "subcategory":"Real Estate Agent",
            "type":"Services"
        }
    ],
    "sg:phone":"+1 803 419 7418",
    "sg:postcode":"29223",
    "sg:province":"SC",
    "wof:name":"Pan K Assoc LLC",
    "wof:placetype":"venue"
},
  "geometry": {"coordinates":[-80.861688,34.094716],"type":"Point"}
}