{
  "type": "Feature",
  "properties": {
    "iso:country":"US",
    "sg:address":"1976 Treebark Dr",
    "sg:city":"Charleston",
    "sg:classifiers":[
        {
            "category":"Building & Trades",
            "subcategory":"Construction",
            "type":"Services"
        }
    ],
    "sg:phone":"+1 843 769 6333",
    "sg:postcode":"29414",
    "sg:province":"SC",
    "sg:tags":[
        "house"
    ],
    "wof:name":"Remington Remodeling LLC",
    "wof:placetype":"venue"
},
  "geometry": {"coordinates":[-80.04593300000001,32.821304],"type":"Point"}
}