{
  "type": "Feature",
  "properties": {
    "addr:full":"141 McDonald Ct Myrtle Beach SC 29588",
    "addr:housenumber":"141",
    "addr:postcode":"29588",
    "addr:street":"Mcdonald Ct",
    "iso:country":"US",
    "sg:address":"141 McDonald Ct",
    "sg:city":"Myrtle Beach",
    "sg:classifiers":[
        {
            "category":"Health Services",
            "subcategory":"Doctor",
            "type":"Services"
        }
    ],
    "sg:phone":"+1 843 293 5601",
    "sg:postcode":"29588",
    "sg:province":"SC",
    "sg:tags":[
        "physician",
        "surgeon"
    ],
    "wof:name":"Grand Strand Internal Medicine",
    "wof:placetype":"venue"
},
  "geometry": {"coordinates":[-78.963773,33.682815],"type":"Point"}
}