{
  "type": "Feature",
  "properties": {
    "iso:country":"US",
    "sg:address":"14 Riley St",
    "sg:city":"Sumter",
    "sg:classifiers":[
        {
            "category":"Autos & Motor Vehicles",
            "subcategory":"Automobile Sales",
            "type":"Retail Goods"
        }
    ],
    "sg:phone":"+1 803 494 3826",
    "sg:postcode":"29150",
    "sg:province":"SC",
    "sg:tags":[
        "used"
    ],
    "wof:name":"Evan Queen Auto Sales Inc",
    "wof:placetype":"venue"
},
  "geometry": {"coordinates":[-80.363271,33.921783],"type":"Point"}
}