{
  "type": "Feature",
  "properties": {
    "iso:country":"US",
    "sg:address":"615 Mount Carmel Rd",
    "sg:city":"Timmonsville",
    "sg:classifiers":[
        {
            "category":"Building & Trades",
            "subcategory":"Construction",
            "type":"Services"
        }
    ],
    "sg:phone":"+1 843 346 2353",
    "sg:postcode":"29161",
    "sg:province":"SC",
    "sg:tags":[
        "general",
        "contractor"
    ],
    "wof:name":"Grace Construction Co Inc",
    "wof:placetype":"venue"
},
  "geometry": {"coordinates":[-79.921431,34.154185],"type":"Point"}
}