{
  "type": "Feature",
  "properties": {
    "iso:country":"US",
    "sg:address":"55 Mathews Dr",
    "sg:city":"Hilton Head Isle",
    "sg:classifiers":[
        {
            "category":"Cinema",
            "subcategory":"Movie Rental",
            "type":"Entertainment"
        }
    ],
    "sg:phone":"+1 843 681 8804",
    "sg:postcode":"29926",
    "sg:province":"SC",
    "sg:tags":[
        "leasing",
        "video",
        "disc",
        "tape"
    ],
    "wof:name":"Video Azteca Silvia Verduzco",
    "wof:placetype":"venue"
},
  "geometry": {"coordinates":[-80.703167,32.21803],"type":"Point"}
}