{
  "type": "Feature",
  "properties": {
    "addr:full":"302 Hampton Ave Greenwood SC 29646",
    "addr:housenumber":"302",
    "addr:postcode":"29646",
    "addr:street":"Hampton Ave",
    "iso:country":"US",
    "sg:address":"302 Hampton Ave",
    "sg:city":"Greenwood",
    "sg:classifiers":[
        {
            "category":"Banks & Credit Unions",
            "subcategory":"Bank",
            "type":"Services"
        }
    ],
    "sg:phone":"+1 864 229 4955",
    "sg:postcode":"29646",
    "sg:province":"SC",
    "wof:name":"Carolina First Bank",
    "wof:placetype":"venue"
},
  "geometry": {"coordinates":[-82.16494299999999,34.195667],"type":"Point"}
}