{
  "type": "Feature",
  "properties": {
    "iso:country":"US",
    "sg:address":"2037 Dearborn Dr",
    "sg:city":"Rock Hill",
    "sg:classifiers":[
        {
            "category":"Building & Trades",
            "subcategory":"Construction",
            "type":"Services"
        }
    ],
    "sg:phone":"+1 803 329 0592",
    "sg:postcode":"29732",
    "sg:province":"SC",
    "sg:tags":[
        "general",
        "contractor"
    ],
    "wof:name":"Townsend Construction Co",
    "wof:placetype":"venue"
},
  "geometry": {"coordinates":[-81.064628,34.991093],"type":"Point"}
}