{
  "type": "Feature",
  "properties": {
    "addr:full":"601 Front St Georgetown SC 29440",
    "addr:housenumber":"601",
    "addr:postcode":"29440",
    "addr:street":"Front St",
    "iso:country":"US",
    "sg:address":"601 Front St",
    "sg:city":"Georgetown",
    "sg:classifiers":[
        {
            "category":"Professional",
            "subcategory":"Lawyer & Legal Services",
            "type":"Services"
        }
    ],
    "sg:phone":"+1 843 546 8691",
    "sg:postcode":"29440",
    "sg:province":"SC",
    "sg:tags":[
        "attorney"
    ],
    "wof:name":"O'Donnell Law Firm",
    "wof:placetype":"venue"
},
  "geometry": {"coordinates":[-79.28233,33.36568],"type":"Point"}
}