{
  "type": "Feature",
  "properties": {
    "addr:full":"681 Buck Hall Ct Mount Pleasant SC 29464",
    "addr:housenumber":"681",
    "addr:postcode":"29464",
    "addr:street":"Buck Hall Ct",
    "iso:country":"US",
    "sg:address":"681 Buck Hall Ct",
    "sg:city":"Mount Pleasant",
    "sg:classifiers":[
        {
            "category":"Building & Trades",
            "subcategory":"Construction",
            "type":"Services"
        }
    ],
    "sg:phone":"+1 843 216 1295",
    "sg:postcode":"29464",
    "sg:province":"SC",
    "sg:tags":[
        "hanging",
        "contractor"
    ],
    "wof:name":"Mayfield Associates",
    "wof:placetype":"venue"
},
  "geometry": {"coordinates":[-79.878781,32.805302],"type":"Point"}
}