{
  "type": "Feature",
  "properties": {
    "iso:country":"US",
    "sg:address":"2032 Robert H Kirk Rd",
    "sg:city":"Lancaster",
    "sg:classifiers":[
        {
            "category":"Arts & Performance",
            "subcategory":"Theater",
            "type":"Entertainment"
        }
    ],
    "sg:phone":"+1 803 289 0771",
    "sg:postcode":"29720",
    "sg:province":"SC",
    "sg:tags":[
        "live",
        "music"
    ],
    "wof:name":"Sounds Familiar DJ Co",
    "wof:placetype":"venue"
},
  "geometry": {"coordinates":[-80.77172899999999,34.650763],"type":"Point"}
}