{
  "type": "Feature",
  "properties": {
    "iso:country":"US",
    "sg:address":"4341 Charlotte Hwy",
    "sg:city":"Clover",
    "sg:classifiers":[
        {
            "category":"Professional",
            "type":"Services"
        }
    ],
    "sg:phone":"+1 803 631 1109",
    "sg:postcode":"29710",
    "sg:province":"SC",
    "sg:tags":[
        "establishment"
    ],
    "wof:name":"Carolina Site Works",
    "wof:placetype":"venue"
},
  "geometry": {"coordinates":[-81.119874,35.062576],"type":"Point"}
}