{
  "type": "Feature",
  "properties": {
    "iso:country":"US",
    "sg:address":"7692 Midwood Dr",
    "sg:city":"North Charleston",
    "sg:classifiers":[
        {
            "category":"Wholesale",
            "subcategory":"Vending Machines",
            "type":"Manufacturing & Wholesale Goods"
        }
    ],
    "sg:phone":"+1 843 552 1392",
    "sg:postcode":"29420",
    "sg:province":"SC",
    "sg:tags":[
        "operator"
    ],
    "wof:name":"Marks Vending",
    "wof:placetype":"venue"
},
  "geometry": {"coordinates":[-80.06688800000001,32.93724],"type":"Point"}
}