{
  "type": "Feature",
  "properties": {
    "iso:country":"US",
    "sg:address":"101 Watson St",
    "sg:city":"Clover",
    "sg:classifiers":[
        {
            "category":"Organizations",
            "subcategory":"Religious Organization",
            "type":"Services"
        }
    ],
    "sg:phone":"+1 803 222 2296",
    "sg:postcode":"29710",
    "sg:province":"SC",
    "sg:tags":[
        "church"
    ],
    "wof:name":"Mars Tabernacle Fire Baptized",
    "wof:placetype":"venue"
},
  "geometry": {"coordinates":[-81.235171,35.116441],"type":"Point"}
}