{
  "type": "Feature",
  "properties": {
    "iso:country":"US",
    "sg:address":"2607 Woodruff Rd",
    "sg:city":"Simpsonville",
    "sg:classifiers":[
        {
            "category":"Shopping",
            "subcategory":"Clothing, Apparel, & Fashions",
            "type":"Retail Goods"
        }
    ],
    "sg:phone":"+1 864 275 4519",
    "sg:postcode":"29681",
    "sg:province":"SC",
    "wof:name":"A Professional Look LLC",
    "wof:placetype":"venue"
},
  "geometry": {"coordinates":[-82.230375,34.805708],"type":"Point"}
}