{
  "type": "Feature",
  "properties": {
    "iso:country":"US",
    "sg:address":"1148 Blossom Ter",
    "sg:city":"Fort Mill",
    "sg:classifiers":[
        {
            "category":"Personal",
            "subcategory":"Beauty Salon",
            "type":"Services"
        }
    ],
    "sg:phone":"+1 803 329 2918",
    "sg:postcode":"29715",
    "sg:province":"SC",
    "wof:name":"Aristocrat Styling Salon",
    "wof:placetype":"venue"
},
  "geometry": {"coordinates":[-80.957557,35.002995],"type":"Point"}
}