{
  "type": "Feature",
  "properties": {
    "iso:country":"US",
    "sg:address":"213 Wade Hampton Blvd",
    "sg:city":"Greenville",
    "sg:classifiers":[
        {
            "category":"Home & Garden",
            "subcategory":"Hardware",
            "type":"Retail Goods"
        }
    ],
    "sg:phone":"+1 864 235 3491",
    "sg:postcode":"29609",
    "sg:province":"SC",
    "sg:tags":[
        "equipment",
        "fireplace"
    ],
    "wof:name":"Greenville True Value Hdwr Co",
    "wof:placetype":"venue"
},
  "geometry": {"coordinates":[-82.38223000000001,34.864716],"type":"Point"}
}