{
  "type": "Feature",
  "properties": {
    "iso:country":"US",
    "sg:address":"200 Conway Ave",
    "sg:city":"Laurens",
    "sg:classifiers":[
        {
            "category":"Personal",
            "subcategory":"Beauty Salon",
            "type":"Services"
        }
    ],
    "sg:phone":"+1 864 681 3716",
    "sg:postcode":"29360",
    "sg:province":"SC",
    "wof:name":"Conway Avenue Beauty Shop",
    "wof:placetype":"venue"
},
  "geometry": {"coordinates":[-81.99460500000001,34.504536],"type":"Point"}
}