{
  "type": "Feature",
  "properties": {
    "iso:country":"US",
    "sg:address":"420 Epting Ave",
    "sg:city":"Greenwood",
    "sg:classifiers":[
        {
            "category":"Shopping",
            "subcategory":"Pharmacy",
            "type":"Retail Goods"
        }
    ],
    "sg:phone":"+1 864 227 6646",
    "sg:postcode":"29646",
    "sg:province":"SC",
    "sg:website":"www.medicinedropper.com",
    "wof:name":"Medicine Dropper Inc",
    "wof:placetype":"venue"
},
  "geometry": {"coordinates":[-82.157843,34.1714],"type":"Point"}
}