{
  "type": "Feature",
  "properties": {
    "iso:country":"US",
    "sg:address":"504 Beaufort St",
    "sg:city":"Dillon",
    "sg:classifiers":[
        {
            "category":"Organizations",
            "subcategory":"Religious Organization",
            "type":"Services"
        }
    ],
    "sg:phone":"+1 843 774 0109",
    "sg:postcode":"29536",
    "sg:province":"SC",
    "sg:tags":[
        "church"
    ],
    "wof:name":"New Covenant Assembly Church",
    "wof:placetype":"venue"
},
  "geometry": {"coordinates":[-79.383559,34.410306],"type":"Point"}
}