{
  "type": "Feature",
  "properties": {
    "iso:country":"US",
    "sg:address":"19 Hunters Point Dr",
    "sg:city":"Lugoff",
    "sg:classifiers":[
        {
            "category":"Professional",
            "subcategory":"Computer Services",
            "type":"Services"
        }
    ],
    "sg:phone":"+1 803 438 1913",
    "sg:postcode":"29078",
    "sg:province":"SC",
    "sg:tags":[
        "internet"
    ],
    "sg:website":"www.sgunited.com",
    "wof:name":"Sgunited Inc",
    "wof:placetype":"venue"
},
  "geometry": {"coordinates":[-80.721911,34.222106],"type":"Point"}
}