{
  "type": "Feature",
  "properties": {
    "addr:full":"198 Fish Hatchery Rd Mountain Rest SC 29691",
    "addr:housenumber":"198",
    "addr:postcode":"29691",
    "addr:street":"Fish Hatchery Rd",
    "iso:country":"US",
    "sg:address":"198 Fish Hatchery Rd",
    "sg:city":"Mountain Rest",
    "sg:classifiers":[
        {
            "category":"Government",
            "subcategory":"Office",
            "type":"Public Place"
        }
    ],
    "sg:phone":"+1 864 638 2866",
    "sg:postcode":"29691",
    "sg:province":"SC",
    "sg:tags":[
        "federal"
    ],
    "wof:name":"US Fish & Wildlife Dept Svc",
    "wof:placetype":"venue"
},
  "geometry": {"coordinates":[-83.07116499999999,34.976828],"type":"Point"}
}