{
  "type": "Feature",
  "properties": {
    "iso:country":"US",
    "sg:address":"1605 Executive Ave",
    "sg:city":"Myrtle Beach",
    "sg:classifiers":[
        {
            "category":"Manufacturing",
            "subcategory":"Tools & Machinery",
            "type":"Manufacturing & Wholesale Goods"
        }
    ],
    "sg:phone":"+1 843 626 9977",
    "sg:postcode":"29577",
    "sg:province":"SC",
    "sg:tags":[
        "furniture"
    ],
    "wof:name":"Crescent Crafts East",
    "wof:placetype":"venue"
},
  "geometry": {"coordinates":[-78.90115900000001,33.702402],"type":"Point"}
}