{
  "type": "Feature",
  "properties": {
    "addr:full":"124 Whitwood Cir Columbia SC 29212",
    "addr:housenumber":"124",
    "addr:postcode":"29212",
    "addr:street":"Whitwood Cir",
    "iso:country":"US",
    "sg:address":"124 Whitwood Cir",
    "sg:city":"Columbia",
    "sg:classifiers":[
        {
            "category":"Freight",
            "type":"Transportation"
        }
    ],
    "sg:phone":"+1 803 407 0334",
    "sg:postcode":"29212",
    "sg:province":"SC",
    "sg:tags":[
        "operator",
        "local",
        "trucking"
    ],
    "wof:name":"C&D Trucking LLC",
    "wof:placetype":"venue"
},
  "geometry": {"coordinates":[-81.135301,34.075265],"type":"Point"}
}