{
  "type": "Feature",
  "properties": {
    "iso:country":"US",
    "sg:address":"290 Mount Pisgah Rd",
    "sg:city":"Reevesville",
    "sg:classifiers":[
        {
            "category":"Organizations",
            "subcategory":"Religious Organization",
            "type":"Services"
        }
    ],
    "sg:phone":"+1 843 563 4939",
    "sg:postcode":"29471",
    "sg:province":"SC",
    "sg:tags":[
        "church"
    ],
    "wof:name":"Mt Pisgah Baptist Church",
    "wof:placetype":"venue"
},
  "geometry": {"coordinates":[-80.724147,33.215841],"type":"Point"}
}