{
  "type": "Feature",
  "properties": {
    "iso:country":"US",
    "sg:address":"3504 Earle E Morris Jr Hwy",
    "sg:city":"Greenville",
    "sg:classifiers":[
        {
            "category":"Professional",
            "subcategory":"Advertising",
            "type":"Services"
        }
    ],
    "sg:phone":"+1 864 220 5000",
    "sg:postcode":"29611",
    "sg:province":"SC",
    "sg:tags":[
        "mailing",
        "shipping"
    ],
    "wof:name":"UPS Store",
    "wof:placetype":"venue"
},
  "geometry": {"coordinates":[-82.48249300000001,34.788836],"type":"Point"}
}