{
  "type": "Feature",
  "properties": {
    "addr:full":"1011 US Hwy 501 Myrtle Beach SC 29577",
    "addr:housenumber":"1011",
    "addr:postcode":"29577",
    "addr:street":"Us Hwy 501",
    "iso:country":"US",
    "sg:address":"1011 US Hwy 501",
    "sg:city":"Myrtle Beach",
    "sg:classifiers":[
        {
            "category":"Banks & Credit Unions",
            "subcategory":"Bank",
            "type":"Services"
        }
    ],
    "sg:phone":"+1 843 445 6113",
    "sg:postcode":"29577",
    "sg:province":"SC",
    "sg:tags":[
        "cashing",
        "check"
    ],
    "wof:name":"Advance America",
    "wof:placetype":"venue"
},
  "geometry": {"coordinates":[-78.89120800000001,33.695295],"type":"Point"}
}