{
  "type": "Feature",
  "properties": {
    "addr:full":"3 Azalea St Hilton Head Island SC 29928",
    "addr:housenumber":"3",
    "addr:postcode":"29928",
    "addr:street":"Azalea St",
    "iso:country":"US",
    "sg:address":"3 Azalea St",
    "sg:city":"Hilton Head Island",
    "sg:classifiers":[
        {
            "category":"Building & Trades",
            "subcategory":"Construction",
            "type":"Services"
        }
    ],
    "sg:phone":"+1 843 785 2492",
    "sg:postcode":"29928",
    "sg:province":"SC",
    "sg:tags":[
        "carpentry",
        "contractor"
    ],
    "wof:name":"David Sease Co",
    "wof:placetype":"venue"
},
  "geometry": {"coordinates":[-80.696984,32.204062],"type":"Point"}
}