{
  "type": "Feature",
  "properties": {
    "iso:country":"US",
    "sg:address":"137 N Howard Ave",
    "sg:city":"Landrum",
    "sg:classifiers":[
        {
            "category":"Wholesale",
            "subcategory":"Petroleum",
            "type":"Manufacturing & Wholesale Goods"
        }
    ],
    "sg:phone":"+1 864 457 2507",
    "sg:postcode":"29356",
    "sg:province":"SC",
    "sg:tags":[
        "bulk",
        "station"
    ],
    "wof:name":"Brown Oil Co",
    "wof:placetype":"venue"
},
  "geometry": {"coordinates":[-82.190595,35.176129],"type":"Point"}
}