{
  "type": "Feature",
  "properties": {
    "iso:country":"US",
    "sg:address":"3108 Whiskey Rd",
    "sg:city":"Aiken",
    "sg:classifiers":[
        {
            "category":"Utilities",
            "subcategory":"Electric",
            "type":"Services"
        }
    ],
    "sg:phone":"+1 803 649 6433",
    "sg:postcode":"29803",
    "sg:province":"SC",
    "sg:tags":[
        "company"
    ],
    "wof:name":"Aiken Electric Cooperative",
    "wof:placetype":"venue"
},
  "geometry": {"coordinates":[-81.700011,33.491033],"type":"Point"}
}