{
  "type": "Feature",
  "properties": {
    "iso:country":"US",
    "sg:address":"25 Woods Lake Rd",
    "sg:city":"Greenville",
    "sg:classifiers":[
        {
            "category":"Shopping",
            "subcategory":"Computers & Home Electronics",
            "type":"Retail Goods"
        }
    ],
    "sg:phone":"+1 864 370 8091",
    "sg:postcode":"29607",
    "sg:province":"SC",
    "sg:tags":[
        "software"
    ],
    "wof:name":"Control Enterprises",
    "wof:placetype":"venue"
},
  "geometry": {"coordinates":[-82.354372,34.856445],"type":"Point"}
}