{
  "type": "Feature",
  "properties": {
    "addr:full":"8 Bessie Rd Piedmont SC 29673",
    "addr:housenumber":"8",
    "addr:postcode":"29673",
    "addr:street":"Bessie Rd",
    "iso:country":"US",
    "sg:address":"8 Bessie Rd",
    "sg:city":"Piedmont",
    "sg:classifiers":[
        {
            "category":"Home & Garden",
            "subcategory":"Garden Supply",
            "type":"Retail Goods"
        }
    ],
    "sg:phone":"+1 864 845 5774",
    "sg:postcode":"29673",
    "sg:province":"SC",
    "sg:tags":[
        "sprinkler"
    ],
    "wof:name":"Southeastern Sprinklers",
    "wof:placetype":"venue"
},
  "geometry": {"coordinates":[-82.452388,34.706376],"type":"Point"}
}