{
  "type": "Feature",
  "properties": {
    "addr:full":"1327 Jeffords St Charleston SC 29412",
    "addr:housenumber":"1327",
    "addr:postcode":"29412",
    "addr:street":"Jeffords St",
    "iso:country":"US",
    "sg:address":"1327 Jeffords St",
    "sg:city":"Charleston",
    "sg:classifiers":[
        {
            "category":"Building & Trades",
            "subcategory":"Plumbing",
            "type":"Services"
        }
    ],
    "sg:phone":"+1 843 296 6108",
    "sg:postcode":"29412",
    "sg:province":"SC",
    "sg:tags":[
        "contractor"
    ],
    "wof:name":"Southeast Plumbing",
    "wof:placetype":"venue"
},
  "geometry": {"coordinates":[-79.964224,32.71757],"type":"Point"}
}