{
  "type": "Feature",
  "properties": {
    "iso:country":"US",
    "sg:address":"105 E McIntyre St",
    "sg:city":"Mullins",
    "sg:classifiers":[
        {
            "category":"Real Estate",
            "subcategory":"Real Estate Services",
            "type":"Services"
        }
    ],
    "sg:phone":"+1 843 464 6747",
    "sg:postcode":"29574",
    "sg:province":"SC",
    "sg:tags":[
        "company",
        "title"
    ],
    "wof:name":"Titlemax Of Mullins",
    "wof:placetype":"venue"
},
  "geometry": {"coordinates":[-79.2434,34.201481],"type":"Point"}
}