{
  "type": "Feature",
  "properties": {
    "addr:full":"1906 Belgrade Ave Charleston SC 29407",
    "addr:housenumber":"1906",
    "addr:postcode":"29407",
    "addr:street":"Belgrade Ave",
    "iso:country":"US",
    "sg:address":"1906 Belgrade Ave",
    "sg:city":"Charleston",
    "sg:classifiers":[
        {
            "category":"Building & Trades",
            "subcategory":"Plumbing",
            "type":"Services"
        }
    ],
    "sg:phone":"+1 843 769 4771",
    "sg:postcode":"29407",
    "sg:province":"SC",
    "sg:tags":[
        "heating",
        "contractor",
        "air",
        "system",
        "conditioning"
    ],
    "wof:name":"Myatt & Bates Heating & Air",
    "wof:placetype":"venue"
},
  "geometry": {"coordinates":[-80.024748,32.796734],"type":"Point"}
}