{
  "type": "Feature",
  "properties": {
    "iso:country":"US",
    "sg:address":"157 Warley St",
    "sg:city":"Florence",
    "sg:classifiers":[
        {
            "category":"Real Estate",
            "subcategory":"Real Estate Agent",
            "type":"Services"
        }
    ],
    "sg:phone":"+1 843 662 9595",
    "sg:postcode":"29501",
    "sg:province":"SC",
    "wof:name":"Mc Innes Realty Co",
    "wof:placetype":"venue"
},
  "geometry": {"coordinates":[-79.77483599999999,34.196132],"type":"Point"}
}