{
  "type": "Feature",
  "properties": {
    "iso:country":"US",
    "sg:address":"101 Verdae Blvd",
    "sg:city":"Greenville",
    "sg:classifiers":[
        {
            "category":"Shopping",
            "subcategory":"Clothing, Apparel, & Fashions",
            "type":"Retail Goods"
        }
    ],
    "sg:phone":"+1 864 281 0810",
    "sg:postcode":"29607",
    "sg:province":"SC",
    "wof:name":"Avenue",
    "wof:placetype":"venue"
},
  "geometry": {"coordinates":[-82.340667,34.8193],"type":"Point"}
}