{
  "type": "Feature",
  "properties": {
    "iso:country":"US",
    "sg:address":"6800 Rivers Ave",
    "sg:city":"North Charleston",
    "sg:classifiers":[
        {
            "category":"Autos & Motor Vehicles",
            "subcategory":"Fuel & Gas Station",
            "type":"Retail Goods"
        }
    ],
    "sg:phone":"+1 843 553 7720",
    "sg:postcode":"29406",
    "sg:province":"SC",
    "sg:tags":[
        "oil"
    ],
    "sg:website":"www.sunoco.com",
    "wof:name":"Speedway/Sunoco",
    "wof:placetype":"venue"
},
  "geometry": {"coordinates":[-80.028263,32.91834],"type":"Point"}
}