{
  "type": "Feature",
  "properties": {
    "iso:country":"US",
    "sg:address":"911 Seaboard St",
    "sg:city":"Myrtle Beach",
    "sg:classifiers":[
        {
            "category":"Retail",
            "subcategory":"Auto Repair",
            "type":"Services"
        }
    ],
    "sg:phone":"+1 843 448 8622",
    "sg:postcode":"29577",
    "sg:province":"SC",
    "sg:tags":[
        "repairing",
        "automobile"
    ],
    "wof:name":"Dayvault Automotive Inc",
    "wof:placetype":"venue"
},
  "geometry": {"coordinates":[-78.89963,33.710128],"type":"Point"}
}