{
  "type": "Feature",
  "properties": {
    "iso:country":"US",
    "sg:address":"331 Lyle St",
    "sg:city":"Rock Hill",
    "sg:classifiers":[
        {
            "category":"Building & Trades",
            "subcategory":"Construction",
            "type":"Services"
        }
    ],
    "sg:phone":"+1 803 328 9622",
    "sg:postcode":"29730",
    "sg:province":"SC",
    "sg:tags":[
        "house",
        "construct",
        "contractor"
    ],
    "wof:name":"Weather Tite Siding & Roofing",
    "wof:placetype":"venue"
},
  "geometry": {"coordinates":[-81.00985300000001,34.922266],"type":"Point"}
}