{
  "type": "Feature",
  "properties": {
    "iso:country":"US",
    "sg:address":"400 Lake Forest Dr",
    "sg:city":"Spartanburg",
    "sg:classifiers":[
        {
            "category":"Building & Trades",
            "subcategory":"Construction",
            "type":"Services"
        }
    ],
    "sg:phone":"+1 864 579 8876",
    "sg:postcode":"29307",
    "sg:province":"SC",
    "sg:tags":[
        "house"
    ],
    "wof:name":"Kunak Enterprises LLC",
    "wof:placetype":"venue"
},
  "geometry": {"coordinates":[-81.85650099999999,34.960911],"type":"Point"}
}