{
  "type": "Feature",
  "properties": {
    "iso:country":"US",
    "sg:address":"600 N Fant St",
    "sg:city":"Anderson",
    "sg:classifiers":[
        {
            "category":"Health Services",
            "subcategory":"Doctor",
            "type":"Services"
        }
    ],
    "sg:phone":"+1 864 261 1475",
    "sg:postcode":"29621",
    "sg:province":"SC",
    "sg:tags":[
        "physician",
        "surgeon"
    ],
    "wof:name":"Anderson Family Practice Ctr",
    "wof:placetype":"venue"
},
  "geometry": {"coordinates":[-82.647263,34.510883],"type":"Point"}
}