{
  "type": "Feature",
  "properties": {
    "iso:country":"US",
    "sg:address":"1016 S Main St",
    "sg:city":"Lancaster",
    "sg:classifiers":[
        {
            "category":"Retail",
            "subcategory":"Repair Shop",
            "type":"Services"
        }
    ],
    "sg:phone":"+1 803 283 2388",
    "sg:postcode":"29720",
    "sg:province":"SC",
    "sg:tags":[
        "appliance"
    ],
    "wof:name":"Bud's Appliance & Repair Co",
    "wof:placetype":"venue"
},
  "geometry": {"coordinates":[-80.762064,34.707005],"type":"Point"}
}