{
  "type": "Feature",
  "properties": {
    "iso:country":"US",
    "sg:address":"699 Hopewell Rd",
    "sg:city":"Blacksburg",
    "sg:classifiers":[
        {
            "category":"Building & Trades",
            "subcategory":"Landscaping Services",
            "type":"Services"
        }
    ],
    "sg:phone":"+1 864 839 4389",
    "sg:postcode":"29702",
    "sg:province":"SC",
    "sg:tags":[
        "sell",
        "farm",
        "contractor",
        "landscape",
        "equipment"
    ],
    "wof:name":"T & L Farms & Equipment",
    "wof:placetype":"venue"
},
  "geometry": {"coordinates":[-81.47874299999999,35.086034],"type":"Point"}
}