{
  "type": "Feature",
  "properties": {
    "iso:country":"US",
    "sg:address":"8009 Garners Ferry Rd",
    "sg:city":"Columbia",
    "sg:classifiers":[
        {
            "category":"Organizations",
            "subcategory":"Religious Organization",
            "type":"Services"
        }
    ],
    "sg:phone":"+1 803 776 9966",
    "sg:postcode":"29209",
    "sg:province":"SC",
    "sg:tags":[
        "church"
    ],
    "wof:name":"Foundation Of Faith",
    "wof:placetype":"venue"
},
  "geometry": {"coordinates":[-80.920753,33.952413],"type":"Point"}
}