{
  "type": "Feature",
  "properties": {
    "addr:full":"240 Harbison Blvd Columbia SC 29212",
    "addr:housenumber":"240",
    "addr:postcode":"29212",
    "addr:street":"Harbison Blvd",
    "iso:country":"US",
    "sg:address":"240 Harbison Blvd",
    "sg:city":"Columbia",
    "sg:classifiers":[
        {
            "category":"Home & Garden",
            "subcategory":"Furniture",
            "type":"Retail Goods"
        }
    ],
    "sg:phone":"+1 803 749 8874",
    "sg:postcode":"29212",
    "sg:province":"SC",
    "wof:name":"Casual Living Inc",
    "wof:placetype":"venue"
},
  "geometry": {"coordinates":[-81.16060400000001,34.071639],"type":"Point"}
}