{
  "type": "Feature",
  "properties": {
    "addr:full":"1314 Lincoln St Ste 302 Columbia SC 29201",
    "addr:housenumber":"1314",
    "addr:postcode":"29201",
    "addr:street":"Lincoln St Ste 302",
    "iso:country":"US",
    "sg:address":"1314 Lincoln St Ste 302",
    "sg:city":"Columbia",
    "sg:classifiers":[
        {
            "category":"Professional",
            "subcategory":"Lawyer & Legal Services",
            "type":"Services"
        }
    ],
    "sg:phone":"+1 803 252 2029",
    "sg:postcode":"29201",
    "sg:province":"SC",
    "wof:name":"Smith Larry C Atty",
    "wof:placetype":"venue"
},
  "geometry": {"coordinates":[-81.03919999999999,34.001301],"type":"Point"}
}