{
  "type": "Feature",
  "properties": {
    "iso:country":"US",
    "sg:address":"2402 Anderson Hwy",
    "sg:city":"Williamston",
    "sg:classifiers":[
        {
            "category":"Banks & Credit Unions",
            "subcategory":"Bank",
            "type":"Services"
        }
    ],
    "sg:phone":"+1 864 847 6922",
    "sg:postcode":"29697",
    "sg:province":"SC",
    "sg:tags":[
        "broker",
        "mortgage"
    ],
    "wof:name":"Sunset",
    "wof:placetype":"venue"
},
  "geometry": {"coordinates":[-82.535691,34.604795],"type":"Point"}
}