{
  "type": "Feature",
  "properties": {
    "iso:country":"US",
    "sg:address":"1957 Mount Gallant Rd",
    "sg:city":"Rock Hill",
    "sg:classifiers":[
        {
            "category":"Building & Trades",
            "subcategory":"Construction",
            "type":"Services"
        }
    ],
    "sg:phone":"+1 803 324 1985",
    "sg:postcode":"29732",
    "sg:province":"SC",
    "sg:tags":[
        "residential",
        "house"
    ],
    "wof:name":"May Ra Construction Co",
    "wof:placetype":"venue"
},
  "geometry": {"coordinates":[-81.004401,34.976557],"type":"Point"}
}