{
  "type": "Feature",
  "properties": {
    "iso:country":"US",
    "sg:address":"216 Beaver Dam Rd",
    "sg:city":"Columbia",
    "sg:classifiers":[
        {
            "category":"Real Estate",
            "subcategory":"Real Estate Agent",
            "type":"Services"
        }
    ],
    "sg:phone":"+1 803 788 4111",
    "sg:postcode":"29223",
    "sg:province":"SC",
    "sg:tags":[
        "appraiser"
    ],
    "wof:name":"Southern Appraisal Svc",
    "wof:placetype":"venue"
},
  "geometry": {"coordinates":[-80.88919300000001,34.09912],"type":"Point"}
}