{
  "type": "Feature",
  "properties": {
    "addr:full":"1201 Main St Ste 200 Columbia SC 29201",
    "addr:housenumber":"1201",
    "addr:postcode":"29201",
    "addr:street":"Main St Ste 200",
    "iso:country":"US",
    "sg:address":"1201 Main St Ste 200",
    "sg:city":"Columbia",
    "sg:classifiers":[
        {
            "category":"Banks & Credit Unions",
            "subcategory":"Financial Services",
            "type":"Services"
        }
    ],
    "sg:phone":"+1 803 758 2770",
    "sg:postcode":"29201",
    "sg:province":"SC",
    "sg:tags":[
        "broker",
        "mortgage"
    ],
    "sg:website":"www.suntrust.com",
    "wof:name":"Suntrust Mortgage Inc",
    "wof:placetype":"venue"
},
  "geometry": {"coordinates":[-81.03371199999999,34.001287],"type":"Point"}
}