{
  "type": "Feature",
  "properties": {
    "addr:full":"3923 Redbird Rd Florence SC 29505",
    "addr:housenumber":"3923",
    "addr:postcode":"29505",
    "addr:street":"Redbird Rd",
    "iso:country":"US",
    "sg:address":"3923 Redbird Rd",
    "sg:city":"Florence",
    "sg:classifiers":[
        {
            "category":"Farming",
            "subcategory":"Farm",
            "type":"Manufacturing & Wholesale Goods"
        }
    ],
    "sg:phone":"+1 843 669 4902",
    "sg:postcode":"29505",
    "sg:province":"SC",
    "sg:tags":[
        "crop",
        "general"
    ],
    "wof:name":"Smith Fork Farms LLP",
    "wof:placetype":"venue"
},
  "geometry": {"coordinates":[-79.680132,34.107916],"type":"Point"}
}