{
  "type": "Feature",
  "properties": {
    "addr:full":"5938 Westmoreland Rd Conway SC 29526",
    "addr:housenumber":"5938",
    "addr:postcode":"29526",
    "addr:street":"Westmoreland Rd",
    "iso:country":"US",
    "sg:address":"5938 Westmoreland Rd",
    "sg:city":"Conway",
    "sg:classifiers":[
        {
            "category":"Farming",
            "subcategory":"Livestock Farm",
            "type":"Manufacturing & Wholesale Goods"
        }
    ],
    "sg:phone":"+1 843 365 3203",
    "sg:postcode":"29526",
    "sg:province":"SC",
    "sg:tags":[
        "feedlot",
        "corn",
        "soybean",
        "beef",
        "cattle"
    ],
    "wof:name":"Floyd Lewis",
    "wof:placetype":"venue"
},
  "geometry": {"coordinates":[-78.95401200000001,33.961458],"type":"Point"}
}