{
  "type": "Feature",
  "properties": {
    "iso:country":"US",
    "sg:address":"135 Belvedere Dr",
    "sg:city":"Spartanburg",
    "sg:classifiers":[
        {
            "category":"Wholesale",
            "subcategory":"Non-durable Goods",
            "type":"Manufacturing & Wholesale Goods"
        }
    ],
    "sg:phone":"+1 864 574 6635",
    "sg:postcode":"29301",
    "sg:province":"SC",
    "sg:tags":[
        "merchandise",
        "general"
    ],
    "wof:name":"Dije Enterprise Inc",
    "wof:placetype":"venue"
},
  "geometry": {"coordinates":[-81.99047400000001,34.967545],"type":"Point"}
}