{
  "type": "Feature",
  "properties": {
    "addr:full":"329 Jordan St Greenwood SC 29649",
    "addr:housenumber":"329",
    "addr:postcode":"29649",
    "addr:street":"Jordan St",
    "iso:country":"US",
    "sg:address":"329 Jordan St",
    "sg:city":"Greenwood",
    "sg:classifiers":[
        {
            "category":"Organizations",
            "subcategory":"Religious Organization",
            "type":"Services"
        }
    ],
    "sg:phone":"+1 864 227 6138",
    "sg:postcode":"29649",
    "sg:province":"SC",
    "sg:tags":[
        "church"
    ],
    "wof:name":"Zion Tabernacle Faith Church",
    "wof:placetype":"venue"
},
  "geometry": {"coordinates":[-82.151528,34.200509],"type":"Point"}
}