{
  "type": "Feature",
  "properties": {
    "iso:country":"US",
    "sg:address":"1915 N Governor Williams Hwy",
    "sg:city":"Darlington",
    "sg:phone":"+1 843 393 7987",
    "sg:postcode":"29532",
    "sg:province":"SC",
    "sg:tags":[
        "farm",
        "soybean",
        "cotton"
    ],
    "wof:name":"Rhett Gleason",
    "wof:placetype":"venue"
},
  "geometry": {"coordinates":[-79.90583599999999,34.354023],"type":"Point"}
}