{
  "type": "Feature",
  "properties": {
    "iso:country":"US",
    "sg:address":"11610 Asheville Hwy",
    "sg:city":"Inman",
    "sg:classifiers":[
        {
            "category":"Utilities",
            "subcategory":"Cable",
            "type":"Services"
        }
    ],
    "sg:phone":"+1 864 472 6774",
    "sg:postcode":"29349",
    "sg:province":"SC",
    "sg:tags":[
        "television"
    ],
    "wof:name":"Fantasy Stitches & Tans",
    "wof:placetype":"venue"
},
  "geometry": {"coordinates":[-82.08447700000001,35.040128],"type":"Point"}
}