{
  "type": "Feature",
  "properties": {
    "addr:full":"4449 S Fraser St Georgetown SC 29440",
    "addr:housenumber":"4449",
    "addr:postcode":"29440",
    "addr:street":"S Fraser St",
    "iso:country":"US",
    "sg:address":"4449 S Fraser St",
    "sg:city":"Georgetown",
    "sg:classifiers":[
        {
            "category":"Farming",
            "subcategory":"Nursery",
            "type":"Manufacturing & Wholesale Goods"
        }
    ],
    "sg:phone":"+1 843 546 7733",
    "sg:postcode":"29440",
    "sg:province":"SC",
    "sg:tags":[
        "ornamental"
    ],
    "wof:name":"Midway Nursery Inc",
    "wof:placetype":"venue"
},
  "geometry": {"coordinates":[-79.304231,33.338909],"type":"Point"}
}