{
  "type": "Feature",
  "properties": {
    "iso:country":"US",
    "sg:address":"102 E Main St",
    "sg:city":"Lamar",
    "sg:classifiers":[
        {
            "category":"Organizations",
            "subcategory":"Religious Organization",
            "type":"Services"
        }
    ],
    "sg:phone":"+1 843 326 8335",
    "sg:postcode":"29069",
    "sg:province":"SC",
    "sg:tags":[
        "church"
    ],
    "wof:name":"Gods Prayer House",
    "wof:placetype":"venue"
},
  "geometry": {"coordinates":[-80.06265,34.168599],"type":"Point"}
}