{
  "type": "Feature",
  "properties": {
    "iso:country":"US",
    "sg:address":"1338 Antioch Amez Church Rd",
    "sg:city":"Eastover",
    "sg:classifiers":[
        {
            "category":"Manufacturing",
            "subcategory":"Chemicals & Compounds",
            "type":"Manufacturing & Wholesale Goods"
        }
    ],
    "sg:phone":"+1 803 353 8063",
    "sg:postcode":"29044",
    "sg:province":"SC",
    "sg:tags":[
        "preparation",
        "mfg"
    ],
    "wof:name":"Macfreeze Inc",
    "wof:placetype":"venue"
},
  "geometry": {"coordinates":[-80.71965299999999,33.92563],"type":"Point"}
}