{
  "type": "Feature",
  "properties": {
    "iso:country":"US",
    "sg:address":"1333 Theater Dr",
    "sg:city":"Mt Pleasant",
    "sg:classifiers":[
        {
            "category":"Shopping",
            "subcategory":"Shoes",
            "type":"Retail Goods"
        }
    ],
    "sg:phone":"+1 843 971 8383",
    "sg:postcode":"29464",
    "sg:province":"SC",
    "wof:name":"Oscar Thompson Shoes",
    "wof:placetype":"venue"
},
  "geometry": {"coordinates":[-79.826213,32.831927],"type":"Point"}
}