{
  "type": "Feature",
  "properties": {
    "iso:country":"US",
    "sg:address":"490 Brickyard Point Rd S",
    "sg:city":"Beaufort",
    "sg:classifiers":[
        {
            "category":"Utilities",
            "subcategory":"Refuse",
            "type":"Services"
        }
    ],
    "sg:phone":"+1 843 525 6137",
    "sg:postcode":"29907",
    "sg:province":"SC",
    "sg:tags":[
        "landfill"
    ],
    "wof:name":"Barnwell Resources Inc",
    "wof:placetype":"venue"
},
  "geometry": {"coordinates":[-80.647977,32.477494],"type":"Point"}
}