{
  "type": "Feature",
  "properties": {
    "iso:country":"US",
    "sg:address":"4630 Augusta Rd",
    "sg:city":"Greenville",
    "sg:classifiers":[
        {
            "category":"Food & Beverages",
            "subcategory":"Liquor & Beverages",
            "type":"Retail Goods"
        }
    ],
    "sg:phone":"+1 864 277 5658",
    "sg:postcode":"29605",
    "sg:province":"SC",
    "sg:tags":[
        "alcoholic"
    ],
    "wof:name":"Collins Liquor Mart",
    "wof:placetype":"venue"
},
  "geometry": {"coordinates":[-82.389809,34.762616],"type":"Point"}
}