{
  "type": "Feature",
  "properties": {
    "addr:full":"5 Alva St Greenville SC 29605",
    "addr:housenumber":"5",
    "addr:postcode":"29605",
    "addr:street":"Alva St",
    "iso:country":"US",
    "sg:address":"5 Alva St",
    "sg:city":"Greenville",
    "sg:classifiers":[
        {
            "category":"Retail",
            "subcategory":"Auto Repair",
            "type":"Services"
        }
    ],
    "sg:phone":"+1 864 422 0802",
    "sg:postcode":"29605",
    "sg:province":"SC",
    "sg:tags":[
        "repairing",
        "automobile"
    ],
    "wof:name":"G & T Automotive Inc",
    "wof:placetype":"venue"
},
  "geometry": {"coordinates":[-82.39078499999999,34.772875],"type":"Point"}
}