{
  "type": "Feature",
  "properties": {
    "addr:full":"3700 Forest Dr Columbia SC 29204",
    "addr:housenumber":"3700",
    "addr:postcode":"29204",
    "addr:street":"Forest Dr",
    "iso:country":"US",
    "sg:address":"3700 Forest Dr",
    "sg:city":"Columbia",
    "sg:classifiers":[
        {
            "category":"Insurance",
            "subcategory":"Title Insurance",
            "type":"Services"
        }
    ],
    "sg:phone":"+1 803 790 5620",
    "sg:postcode":"29204",
    "sg:province":"SC",
    "wof:name":"Chicago Title Insurance Co",
    "wof:placetype":"venue"
},
  "geometry": {"coordinates":[-80.98705699999999,34.019678],"type":"Point"}
}