{
  "type": "Feature",
  "properties": {
    "iso:country":"US",
    "sg:address":"206 Chamblin St",
    "sg:city":"Woodruff",
    "sg:classifiers":[
        {
            "category":"Organizations",
            "subcategory":"Non-profit Organization",
            "type":"Services"
        }
    ],
    "sg:phone":"+1 864 476 2401",
    "sg:postcode":"29388",
    "sg:province":"SC",
    "sg:tags":[
        "charitable",
        "institution"
    ],
    "wof:name":"Helping Hands Ministries",
    "wof:placetype":"venue"
},
  "geometry": {"coordinates":[-82.035263,34.745234],"type":"Point"}
}