{
  "type": "Feature",
  "properties": {
    "iso:country":"US",
    "sg:address":"753 Bultman Dr",
    "sg:city":"Sumter",
    "sg:classifiers":[
        {
            "category":"Building & Trades",
            "subcategory":"Cleaning & Sanitation",
            "type":"Services"
        }
    ],
    "sg:phone":"+1 803 773 5376",
    "sg:postcode":"29150",
    "sg:province":"SC",
    "sg:tags":[
        "janitor"
    ],
    "wof:name":"Joy's Unique Cleaning Svc",
    "wof:placetype":"venue"
},
  "geometry": {"coordinates":[-80.37219399999999,33.942379],"type":"Point"}
}