{
  "type": "Feature",
  "properties": {
    "iso:country":"US",
    "sg:address":"107 Kiser St",
    "sg:city":"Walterboro",
    "sg:classifiers":[
        {
            "category":"Manufacturing",
            "subcategory":"Building Materials",
            "type":"Manufacturing & Wholesale Goods"
        }
    ],
    "sg:phone":"+1 843 538 6424",
    "sg:postcode":"29488",
    "sg:province":"SC",
    "sg:tags":[
        "mfg",
        "wood",
        "kitchen",
        "cabinet"
    ],
    "wof:name":"South East Cabinet",
    "wof:placetype":"venue"
},
  "geometry": {"coordinates":[-80.692859,32.886512],"type":"Point"}
}