{
  "type": "Feature",
  "properties": {
    "addr:full":"2077 Dorange Rd Branchville SC 29432",
    "addr:housenumber":"2077",
    "addr:postcode":"29432",
    "addr:street":"Dorange Rd",
    "iso:country":"US",
    "sg:address":"2077 Dorange Rd",
    "sg:city":"Branchville",
    "sg:classifiers":[
        {
            "category":"Retail",
            "subcategory":"Auto Repair",
            "type":"Services"
        }
    ],
    "sg:phone":"+1 803 274 8777",
    "sg:postcode":"29432",
    "sg:province":"SC",
    "sg:tags":[
        "repairing",
        "automobile"
    ],
    "wof:name":"Ricky's Auto Repair",
    "wof:placetype":"venue"
},
  "geometry": {"coordinates":[-80.763964,33.237101],"type":"Point"}
}