{
  "type": "Feature",
  "properties": {
    "iso:country":"US",
    "sg:address":"1215 Celebrity Cir",
    "sg:city":"Myrtle Beach",
    "sg:classifiers":[
        {
            "category":"Shopping",
            "subcategory":"Hobbies, Toys, & Games",
            "type":"Retail Goods"
        }
    ],
    "sg:phone":"+1 843 448 7261",
    "sg:postcode":"29577",
    "sg:province":"SC",
    "sg:tags":[
        "kite"
    ],
    "sg:website":"www.kligs.com",
    "wof:name":"Klig's Kites",
    "wof:placetype":"venue"
},
  "geometry": {"coordinates":[-78.88577600000001,33.715613],"type":"Point"}
}