{
  "type": "Feature",
  "properties": {
    "iso:country":"US",
    "sg:address":"5202 Augusta Hwy",
    "sg:city":"Leesville",
    "sg:classifiers":[
        {
            "category":"Retail",
            "subcategory":"Auto Repair",
            "type":"Services"
        }
    ],
    "sg:phone":"+1 803 892 5205",
    "sg:postcode":"29070",
    "sg:province":"SC",
    "sg:tags":[
        "body",
        "automobile",
        "painting"
    ],
    "wof:name":"Gilbert Paint & Body",
    "wof:placetype":"venue"
},
  "geometry": {"coordinates":[-81.43394600000001,33.947724],"type":"Point"}
}