{
  "type": "Feature",
  "properties": {
    "iso:country":"US",
    "sg:address":"114 E Carolina Ave",
    "sg:city":"Hartsville",
    "sg:classifiers":[
        {
            "category":"Utilities",
            "subcategory":"Mobile Phone",
            "type":"Services"
        }
    ],
    "sg:phone":"+1 843 332 5117",
    "sg:postcode":"29550",
    "sg:province":"SC",
    "sg:tags":[
        "telephone",
        "cellular"
    ],
    "wof:name":"Wireless Cafe",
    "wof:placetype":"venue"
},
  "geometry": {"coordinates":[-80.074022,34.374071],"type":"Point"}
}