{
  "type": "Feature",
  "properties": {
    "addr:full":"1720 Union St Spartanburg SC 29302",
    "addr:housenumber":"1720",
    "addr:postcode":"29302",
    "addr:street":"Union St",
    "iso:country":"US",
    "sg:address":"1720 Union St",
    "sg:city":"Spartanburg",
    "sg:classifiers":[
        {
            "category":"Banks & Credit Unions",
            "subcategory":"Financial Services",
            "type":"Services"
        }
    ],
    "sg:phone":"+1 864 596 1430",
    "sg:postcode":"29302",
    "sg:province":"SC",
    "sg:tags":[
        "company",
        "holding"
    ],
    "wof:name":"Littlejohn Holding Co",
    "wof:placetype":"venue"
},
  "geometry": {"coordinates":[-81.88630999999999,34.924144],"type":"Point"}
}