{
  "type": "Feature",
  "properties": {
    "iso:country":"US",
    "sg:address":"2740 Beulah Cuttino Rd",
    "sg:city":"Sumter",
    "sg:classifiers":[
        {
            "category":"Building & Trades",
            "subcategory":"Construction",
            "type":"Services"
        }
    ],
    "sg:phone":"+1 803 481 5693",
    "sg:postcode":"29150",
    "sg:province":"SC",
    "sg:tags":[
        "house"
    ],
    "wof:name":"Johnny Morris Construction Co",
    "wof:placetype":"venue"
},
  "geometry": {"coordinates":[-80.348046,33.819397],"type":"Point"}
}