{
  "type": "Feature",
  "properties": {
    "addr:full":"1433 Pearman Dairy Rd Anderson SC 29625",
    "addr:housenumber":"1433",
    "addr:postcode":"29625",
    "addr:street":"Pearman Dairy Rd",
    "iso:country":"US",
    "sg:address":"1433 Pearman Dairy Rd",
    "sg:city":"Anderson",
    "sg:classifiers":[
        {
            "category":"Farming",
            "subcategory":"Nursery",
            "type":"Manufacturing & Wholesale Goods"
        },
        {
            "category":"Home & Garden",
            "subcategory":"Garden Supply",
            "type":"Retail Goods"
        }
    ],
    "sg:phone":"+1 864 231 0910",
    "sg:postcode":"29625",
    "sg:province":"SC",
    "sg:tags":[
        "ornamental",
        "nurseryman"
    ],
    "wof:name":"Plant It Nursery",
    "wof:placetype":"venue"
},
  "geometry": {"coordinates":[-82.69447,34.526284],"type":"Point"}
}