{
  "type": "Feature",
  "properties": {
    "iso:country":"US",
    "sg:address":"915 Liberty Dr",
    "sg:city":"Easley",
    "sg:classifiers":[
        {
            "category":"Autos & Motor Vehicles",
            "subcategory":"Automobile Sales",
            "type":"Retail Goods"
        }
    ],
    "sg:phone":"+1 864 306 6241",
    "sg:postcode":"29640",
    "sg:province":"SC",
    "sg:tags":[
        "car",
        "dealer"
    ],
    "wof:name":"Pratt's Auto Sales",
    "wof:placetype":"venue"
},
  "geometry": {"coordinates":[-82.624619,34.817559],"type":"Point"}
}