{
  "type": "Feature",
  "properties": {
    "iso:country":"US",
    "sg:address":"128 S Main St",
    "sg:city":"Travelers Rest",
    "sg:classifiers":[
        {
            "category":"Professional",
            "subcategory":"Lawyer & Legal Services",
            "type":"Services"
        }
    ],
    "sg:phone":"+1 864 834 7090",
    "sg:postcode":"29690",
    "sg:province":"SC",
    "sg:tags":[
        "attorney"
    ],
    "wof:name":"W Benjamin Mc Clain Jr",
    "wof:placetype":"venue"
},
  "geometry": {"coordinates":[-82.441036,34.963714],"type":"Point"}
}