{
  "type": "Feature",
  "properties": {
    "addr:full":"1214 Sunset Blvd West Columbia SC 29169",
    "addr:housenumber":"1214",
    "addr:postcode":"29169",
    "addr:street":"Sunset Blvd",
    "iso:country":"US",
    "sg:address":"1214 Sunset Blvd",
    "sg:city":"West Columbia",
    "sg:classifiers":[
        {
            "category":"Shopping",
            "type":"Retail Goods"
        }
    ],
    "sg:phone":"+1 803 939 0590",
    "sg:postcode":"29169",
    "sg:province":"SC",
    "sg:tags":[
        "art",
        "gallery",
        "dealer"
    ],
    "wof:name":"Appleby Creation & Gifts",
    "wof:placetype":"venue"
},
  "geometry": {"coordinates":[-81.08006,33.998316],"type":"Point"}
}