{
  "type": "Feature",
  "properties": {
    "iso:country":"US",
    "sg:address":"307 Smith St",
    "sg:city":"Conway",
    "sg:classifiers":[
        {
            "category":"Recreation",
            "type":"Entertainment"
        }
    ],
    "sg:phone":"+1 843 248 1864",
    "sg:postcode":"29526",
    "sg:province":"SC",
    "sg:tags":[
        "parks"
    ],
    "wof:name":"Horry County Parks & Rec Dept",
    "wof:placetype":"venue"
},
  "geometry": {"coordinates":[-79.056833,33.831828],"type":"Point"}
}