{
  "type": "Feature",
  "properties": {
    "iso:country":"US",
    "sg:address":"30 New Bethel Rd",
    "sg:city":"Piedmont",
    "sg:classifiers":[
        {
            "category":"Organizations",
            "subcategory":"Religious Organization",
            "type":"Services"
        }
    ],
    "sg:phone":"+1 864 947 9966",
    "sg:postcode":"29673",
    "sg:province":"SC",
    "sg:tags":[
        "church"
    ],
    "wof:name":"New Mount Bethel Baptist Chr",
    "wof:placetype":"venue"
},
  "geometry": {"coordinates":[-82.445827,34.665169],"type":"Point"}
}