{
  "type": "Feature",
  "properties": {
    "iso:country":"US",
    "sg:address":"185 S Liberty St",
    "sg:city":"Spartanburg",
    "sg:classifiers":[
        {
            "category":"Banks & Credit Unions",
            "subcategory":"Bank",
            "type":"Services"
        }
    ],
    "sg:phone":"+1 864 582 4146",
    "sg:postcode":"29306",
    "sg:province":"SC",
    "sg:tags":[
        "loan",
        "real estate"
    ],
    "wof:name":"Unity Financial Svc",
    "wof:placetype":"venue"
},
  "geometry": {"coordinates":[-81.928665,34.947771],"type":"Point"}
}