{
  "type": "Feature",
  "properties": {
    "addr:full":"2231 Cheyenne Rd Smyrna SC 29743",
    "addr:housenumber":"2231",
    "addr:postcode":"29743",
    "addr:street":"Cheyenne Rd",
    "iso:country":"US",
    "sg:address":"2231 Cheyenne Rd",
    "sg:city":"Smyrna",
    "sg:classifiers":[
        {
            "category":"Retail",
            "subcategory":"Animal Services",
            "type":"Services"
        }
    ],
    "sg:phone":"+1 803 925 9560",
    "sg:postcode":"29743",
    "sg:province":"SC",
    "wof:name":"Circle T Ranch Inc",
    "wof:placetype":"venue"
},
  "geometry": {"coordinates":[-81.446061,35.024909],"type":"Point"}
}