{
  "type": "Feature",
  "properties": {
    "addr:full":"1946 Brookstone Way Rock Hill SC 29732",
    "addr:housenumber":"1946",
    "addr:postcode":"29732",
    "addr:street":"Brookstone Way",
    "iso:country":"US",
    "sg:address":"1946 Brookstone Way",
    "sg:city":"Rock Hill",
    "sg:classifiers":[
        {
            "category":"Manufacturing",
            "subcategory":"Printing",
            "type":"Manufacturing & Wholesale Goods"
        }
    ],
    "sg:phone":"+1 803 366 6270",
    "sg:postcode":"29732",
    "sg:province":"SC",
    "sg:tags":[
        "book",
        "sales",
        "order"
    ],
    "wof:name":"Wright Group/Mc Graw Hill",
    "wof:placetype":"venue"
},
  "geometry": {"coordinates":[-81.00958300000001,34.966901],"type":"Point"}
}