{
  "type": "Feature",
  "properties": {
    "iso:country":"US",
    "sg:address":"6328 Old State Rd",
    "sg:city":"Holly Hill",
    "sg:classifiers":[
        {
            "category":"Building & Trades",
            "subcategory":"Construction",
            "type":"Services"
        }
    ],
    "sg:phone":"+1 803 496 3335",
    "sg:postcode":"29059",
    "sg:province":"SC",
    "sg:tags":[
        "road",
        "contractor"
    ],
    "wof:name":"South Carolina Highways Dept",
    "wof:placetype":"venue"
},
  "geometry": {"coordinates":[-80.478585,33.369968],"type":"Point"}
}