{
  "type": "Feature",
  "properties": {
    "iso:country":"US",
    "sg:address":"151 Clearwater Dr",
    "sg:city":"Liberty",
    "sg:classifiers":[
        {
            "category":"Government",
            "subcategory":"Office",
            "type":"Public Place"
        }
    ],
    "sg:phone":"+1 864 843 5808",
    "sg:postcode":"29672",
    "sg:province":"SC",
    "wof:name":"Pickens County Public Svc Dept",
    "wof:placetype":"venue"
},
  "geometry": {"coordinates":[-82.946246,34.714832],"type":"Point"}
}