{
  "type": "Feature",
  "properties": {
    "iso:country":"US",
    "sg:address":"1047 W Dekalb St",
    "sg:city":"Camden",
    "sg:classifiers":[
        {
            "category":"Insurance",
            "subcategory":"Insurance Agent",
            "type":"Services"
        }
    ],
    "sg:phone":"+1 803 432 9045",
    "sg:postcode":"29020",
    "sg:province":"SC",
    "wof:name":"Grimm Agency",
    "wof:placetype":"venue"
},
  "geometry": {"coordinates":[-80.62318,34.246582],"type":"Point"}
}