{
  "type": "Feature",
  "properties": {
    "iso:country":"US",
    "sg:address":"9753 Ocean Hwy",
    "sg:city":"Pawleys Island",
    "sg:classifiers":[
        {
            "category":"Building & Trades",
            "subcategory":"Landscaping Services",
            "type":"Services"
        }
    ],
    "sg:phone":"+1 843 235 9619",
    "sg:postcode":"29585",
    "sg:province":"SC",
    "sg:tags":[
        "lawn",
        "maintenance",
        "grounds"
    ],
    "wof:name":"Sweet Grass Nursery Inc",
    "wof:placetype":"venue"
},
  "geometry": {"coordinates":[-79.137834,33.433625],"type":"Point"}
}