{
  "type": "Feature",
  "properties": {
    "addr:full":"1025 Campton Rd Inman SC 29349",
    "addr:housenumber":"1025",
    "addr:postcode":"29349",
    "addr:street":"Campton Rd",
    "iso:country":"US",
    "sg:address":"1025 Campton Rd",
    "sg:city":"Inman",
    "sg:classifiers":[
        {
            "category":"Autos & Motor Vehicles",
            "subcategory":"Fuel & Gas Station",
            "type":"Retail Goods"
        }
    ],
    "sg:phone":"+1 864 472 3525",
    "sg:postcode":"29349",
    "sg:province":"SC",
    "sg:tags":[
        "station",
        "gasoline"
    ],
    "wof:name":"Crown Central Petro Stn 543",
    "wof:placetype":"venue"
},
  "geometry": {"coordinates":[-82.068894,35.033888],"type":"Point"}
}