{
  "type": "Feature",
  "properties": {
    "addr:full":"1319 Hampton Ave Exd Greenville SC 29601",
    "addr:housenumber":"1319",
    "addr:postcode":"29601",
    "addr:street":"Hampton Ave Exd",
    "iso:country":"US",
    "sg:address":"1319 Hampton Ave Exd",
    "sg:city":"Greenville",
    "sg:classifiers":[
        {
            "category":"Food & Beverages",
            "subcategory":"Groceries & Convenience Stores",
            "type":"Retail Goods"
        }
    ],
    "sg:phone":"+1 864 271 0879",
    "sg:postcode":"29601",
    "sg:province":"SC",
    "wof:name":"Cripple Creek Grocery",
    "wof:placetype":"venue"
},
  "geometry": {"coordinates":[-82.416477,34.865605],"type":"Point"}
}