{
  "type": "Feature",
  "properties": {
    "iso:country":"US",
    "sg:address":"634 William Hilton Pkwy",
    "sg:city":"Hilton Head Isle",
    "sg:classifiers":[
        {
            "category":"Professional",
            "type":"Services"
        }
    ],
    "sg:phone":"+1 843 686 2863",
    "sg:postcode":"29928",
    "sg:province":"SC",
    "sg:tags":[
        "establishment"
    ],
    "wof:name":"Ferguson Community",
    "wof:placetype":"venue"
},
  "geometry": {"coordinates":[-80.705372,32.194399],"type":"Point"}
}