{
  "type": "Feature",
  "properties": {
    "addr:full":"1028 Saint Andrews Blvd Charleston SC 29407",
    "addr:housenumber":"1028",
    "addr:postcode":"29407",
    "addr:street":"Saint Andrews Blvd",
    "iso:country":"US",
    "sg:address":"1028 Saint Andrews Blvd",
    "sg:city":"Charleston",
    "sg:classifiers":[
        {
            "category":"Restaurant",
            "type":"Food & Drink"
        }
    ],
    "sg:menulink":"http://www.allmenus.com/sc/charleston-north-charleston/91983-back-yard-burgers/menu/",
    "sg:phone":"+1 843 766 9223",
    "sg:postcode":"29407",
    "sg:province":"SC",
    "sg:tags":[
        "american"
    ],
    "wof:name":"Back Yard Burgers",
    "wof:placetype":"venue"
},
  "geometry": {"coordinates":[-79.99189699999999,32.794872],"type":"Point"}
}