{
  "type": "Feature",
  "properties": {
    "addr:full":"21 S Main St Travelers Rest SC 29690",
    "addr:housenumber":"21",
    "addr:postcode":"29690",
    "addr:street":"S Main St",
    "iso:country":"US",
    "sg:address":"21 S Main St",
    "sg:city":"Travelers Rest",
    "sg:classifiers":[
        {
            "category":"Banks & Credit Unions",
            "subcategory":"Bank",
            "type":"Services"
        }
    ],
    "sg:phone":"+1 864 834 5364",
    "sg:postcode":"29690",
    "sg:province":"SC",
    "sg:tags":[
        "depository",
        "banking"
    ],
    "wof:name":"King Fish Enterprise",
    "wof:placetype":"venue"
},
  "geometry": {"coordinates":[-82.441213,34.965607],"type":"Point"}
}