{
  "type": "Feature",
  "properties": {
    "addr:full":"5912 Campbell St Hanahan SC 29410",
    "addr:housenumber":"5912",
    "addr:postcode":"29410",
    "addr:street":"Campbell St",
    "iso:country":"US",
    "sg:address":"5912 Campbell St",
    "sg:city":"Hanahan",
    "sg:classifiers":[
        {
            "category":"Utilities",
            "type":"Services"
        }
    ],
    "sg:phone":"+1 843 747 5101",
    "sg:postcode":"29410",
    "sg:province":"SC",
    "sg:tags":[
        "locating"
    ],
    "wof:name":"West Locating Svc Inc",
    "wof:placetype":"venue"
},
  "geometry": {"coordinates":[-80.00886800000001,32.903603],"type":"Point"}
}