{
  "type": "Feature",
  "properties": {
    "iso:country":"US",
    "sg:address":"120 Hill Dr",
    "sg:city":"Pawleys Island",
    "sg:classifiers":[
        {
            "category":"Building & Trades",
            "subcategory":"Electrical",
            "type":"Services"
        }
    ],
    "sg:phone":"+1 843 237 9821",
    "sg:postcode":"29585",
    "sg:province":"SC",
    "sg:tags":[
        "electric",
        "contractor"
    ],
    "wof:name":"Mcclary Electric Co",
    "wof:placetype":"venue"
},
  "geometry": {"coordinates":[-79.158823,33.429325],"type":"Point"}
}