{
  "type": "Feature",
  "properties": {
    "iso:country":"US",
    "sg:address":"4010 Wesley St",
    "sg:city":"Myrtle Beach",
    "sg:classifiers":[
        {
            "category":"Wholesale",
            "subcategory":"Auto Parts",
            "type":"Manufacturing & Wholesale Goods"
        }
    ],
    "sg:phone":"+1 843 236 8651",
    "sg:postcode":"29579",
    "sg:province":"SC",
    "sg:tags":[
        "automobile",
        "rebuilt"
    ],
    "wof:name":"Brooks Used Parts",
    "wof:placetype":"venue"
},
  "geometry": {"coordinates":[-78.93425999999999,33.717345],"type":"Point"}
}