{
  "type": "Feature",
  "properties": {
    "iso:country":"US",
    "sg:address":"109 Bee St",
    "sg:city":"Charleston",
    "sg:classifiers":[
        {
            "category":"Health Services",
            "subcategory":"Doctor",
            "type":"Services"
        }
    ],
    "sg:phone":"+1 843 849 8354",
    "sg:postcode":"29401",
    "sg:province":"SC",
    "sg:tags":[
        "physician",
        "surgeon"
    ],
    "wof:name":"Veterans Admin Medical Ctr",
    "wof:placetype":"venue"
},
  "geometry": {"coordinates":[-79.9548,32.784769],"type":"Point"}
}