{
  "type": "Feature",
  "properties": {
    "iso:country":"US",
    "sg:address":"150 McDowell St",
    "sg:city":"Pacolet",
    "sg:classifiers":[
        {
            "category":"Education",
            "subcategory":"School",
            "type":"Public Place"
        }
    ],
    "sg:phone":"+1 864 474 4060",
    "sg:postcode":"29372",
    "sg:province":"SC",
    "wof:name":"Pacolet Elementary School",
    "wof:placetype":"venue"
},
  "geometry": {"coordinates":[-81.768309,34.903693],"type":"Point"}
}