{
  "type": "Feature",
  "properties": {
    "addr:full":"36 Spanish Pointe Dr Hilton Head Isle SC 29926",
    "addr:housenumber":"36",
    "addr:postcode":"29926",
    "addr:street":"Spanish Pointe Dr",
    "iso:country":"US",
    "sg:address":"36 Spanish Pointe Dr",
    "sg:city":"Hilton Head Isle",
    "sg:classifiers":[
        {
            "category":"Real Estate",
            "subcategory":"Real Estate Agent",
            "type":"Services"
        }
    ],
    "sg:phone":"+1 843 689 9898",
    "sg:postcode":"29926",
    "sg:province":"SC",
    "wof:name":"Seashore Realty Inc",
    "wof:placetype":"venue"
},
  "geometry": {"coordinates":[-80.77943500000001,32.194834],"type":"Point"}
}