{
  "type": "Feature",
  "properties": {
    "iso:country":"US",
    "sg:address":"206 Riverside Ct",
    "sg:city":"Greer",
    "sg:classifiers":[
        {
            "category":"Banks & Credit Unions",
            "subcategory":"Investment Brokerage",
            "type":"Services"
        }
    ],
    "sg:phone":"+1 864 879 7639",
    "sg:postcode":"29650",
    "sg:province":"SC",
    "sg:tags":[
        "trade",
        "barter",
        "exchange"
    ],
    "wof:name":"Tradebank Of The Piedmont",
    "wof:placetype":"venue"
},
  "geometry": {"coordinates":[-82.24605,34.873271],"type":"Point"}
}