{
  "type": "Feature",
  "properties": {
    "addr:full":"508 S Church St Manning SC 29102",
    "addr:housenumber":"508",
    "addr:postcode":"29102",
    "addr:street":"S Church St",
    "iso:country":"US",
    "sg:address":"508 S Church St",
    "sg:city":"Manning",
    "sg:classifiers":[
        {
            "category":"Personal",
            "subcategory":"Beauty Salon",
            "type":"Services"
        }
    ],
    "sg:phone":"+1 803 435 8153",
    "sg:postcode":"29102",
    "sg:province":"SC",
    "wof:name":"Todays Look",
    "wof:placetype":"venue"
},
  "geometry": {"coordinates":[-80.209301,33.687708],"type":"Point"}
}