{
  "type": "Feature",
  "properties": {
    "iso:country":"US",
    "sg:address":"11103 Augusta Hwy",
    "sg:city":"Walterboro",
    "sg:classifiers":[
        {
            "category":"Retail",
            "subcategory":"Repair Shop",
            "type":"Services"
        }
    ],
    "sg:phone":"+1 843 538 3696",
    "sg:postcode":"29488",
    "sg:province":"SC",
    "sg:tags":[
        "related"
    ],
    "wof:name":"C B Repair Shop",
    "wof:placetype":"venue"
},
  "geometry": {"coordinates":[-80.650919,33.083734],"type":"Point"}
}