{
  "type": "Feature",
  "properties": {
    "iso:country":"US",
    "sg:address":"2816 Devine St",
    "sg:city":"Columbia",
    "sg:classifiers":[
        {
            "category":"Shopping",
            "subcategory":"Gifts & Souvenirs",
            "type":"Retail Goods"
        }
    ],
    "sg:phone":"+1 803 252 2902",
    "sg:postcode":"29205",
    "sg:province":"SC",
    "sg:tags":[
        "party",
        "supply"
    ],
    "wof:name":"Posh",
    "wof:placetype":"venue"
},
  "geometry": {"coordinates":[-81.001439,33.997919],"type":"Point"}
}