{
  "type": "Feature",
  "properties": {
    "addr:full":"634 Bacons Bridge Rd Summerville SC 29485",
    "addr:housenumber":"634",
    "addr:postcode":"29485",
    "addr:street":"Bacons Bridge Rd",
    "iso:country":"US",
    "sg:address":"634 Bacons Bridge Rd",
    "sg:city":"Summerville",
    "sg:classifiers":[
        {
            "category":"Social Services",
            "subcategory":"Job Training",
            "type":"Services"
        }
    ],
    "sg:phone":"+1 843 821 2272",
    "sg:postcode":"29485",
    "sg:province":"SC",
    "sg:tags":[
        "rehabilitation"
    ],
    "wof:name":"Pro Active Therapy Inc",
    "wof:placetype":"venue"
},
  "geometry": {"coordinates":[-80.201049,32.961916],"type":"Point"}
}