{
  "type": "Feature",
  "properties": {
    "iso:country":"US",
    "sg:address":"398 Summerwind Ct",
    "sg:city":"Pelion",
    "sg:classifiers":[
        {
            "category":"Wholesale",
            "subcategory":"Office Equipment",
            "type":"Manufacturing & Wholesale Goods"
        }
    ],
    "sg:phone":"+1 803 894 5797",
    "sg:postcode":"29123",
    "sg:province":"SC",
    "sg:tags":[
        "machine"
    ],
    "wof:name":"Pelion Office Products",
    "wof:placetype":"venue"
},
  "geometry": {"coordinates":[-81.255498,33.7715],"type":"Point"}
}