{
  "type": "Feature",
  "properties": {
    "addr:full":"7741 N Kings Hwy Myrtle Beach SC 29577",
    "addr:housenumber":"7741",
    "addr:postcode":"29577",
    "addr:street":"N Kings Hwy",
    "iso:country":"US",
    "sg:address":"7741 N Kings Hwy",
    "sg:city":"Myrtle Beach",
    "sg:classifiers":[
        {
            "category":"Shopping",
            "type":"Retail Goods"
        }
    ],
    "sg:phone":"+1 843 449 4555",
    "sg:postcode":"29577",
    "sg:province":"SC",
    "sg:tags":[
        "merchandise"
    ],
    "wof:name":"Wild Birds Unlimited",
    "wof:placetype":"venue"
},
  "geometry": {"coordinates":[-78.816642,33.748903],"type":"Point"}
}