{
  "type": "Feature",
  "properties": {
    "addr:full":"306 Freiday Ln Aiken SC 29801",
    "addr:housenumber":"306",
    "addr:postcode":"29801",
    "addr:street":"Freiday Ln",
    "iso:country":"US",
    "sg:address":"306 Freiday Ln",
    "sg:city":"Aiken",
    "sg:classifiers":[
        {
            "category":"Social Services",
            "subcategory":"Child Care",
            "type":"Services"
        }
    ],
    "sg:phone":"+1 803 644 4079",
    "sg:postcode":"29801",
    "sg:province":"SC",
    "wof:name":"TTS Daycare",
    "wof:placetype":"venue"
},
  "geometry": {"coordinates":[-81.722025,33.573294],"type":"Point"}
}