{
  "type": "Feature",
  "properties": {
    "iso:country":"US",
    "sg:address":"505 Powdersville Rd",
    "sg:city":"Easley",
    "sg:phone":"+1 864 855 1176",
    "sg:postcode":"29642",
    "sg:province":"SC",
    "sg:tags":[
        "farm"
    ],
    "wof:name":"Winslett Produce",
    "wof:placetype":"venue"
},
  "geometry": {"coordinates":[-82.56012699999999,34.822401],"type":"Point"}
}