{
  "type": "Feature",
  "properties": {
    "iso:country":"US",
    "sg:address":"526 E Savannah St",
    "sg:city":"Calhoun Falls",
    "sg:classifiers":[
        {
            "category":"Retail",
            "subcategory":"Funeral Services",
            "type":"Services"
        }
    ],
    "sg:phone":"+1 864 447 8566",
    "sg:postcode":"29628",
    "sg:province":"SC",
    "sg:tags":[
        "director"
    ],
    "wof:name":"Calhoun Falls Funeral Home",
    "wof:placetype":"venue"
},
  "geometry": {"coordinates":[-82.586237,34.090199],"type":"Point"}
}