{
  "type": "Feature",
  "properties": {
    "iso:country":"US",
    "sg:address":"7340 Peppermill Pkwy",
    "sg:city":"North Charleston",
    "sg:classifiers":[
        {
            "category":"Home & Garden",
            "subcategory":"Furniture",
            "type":"Retail Goods"
        }
    ],
    "sg:phone":"+1 843 760 9020",
    "sg:postcode":"29418",
    "sg:province":"SC",
    "sg:website":"www.familysaversonline.com",
    "wof:name":"Family Savers Inc",
    "wof:placetype":"venue"
},
  "geometry": {"coordinates":[-80.076574,32.923046],"type":"Point"}
}