{
  "type": "Feature",
  "properties": {
    "addr:full":"1320 Gilead Rd Mount Pleasant SC 29466",
    "addr:housenumber":"1320",
    "addr:postcode":"29466",
    "addr:street":"Gilead Rd",
    "iso:country":"US",
    "sg:address":"1320 Gilead Rd",
    "sg:city":"Mount Pleasant",
    "sg:classifiers":[
        {
            "category":"Banks & Credit Unions",
            "subcategory":"Financial Services",
            "type":"Services"
        }
    ],
    "sg:phone":"+1 843 849 5932",
    "sg:postcode":"29466",
    "sg:province":"SC",
    "sg:tags":[
        "investor"
    ],
    "wof:name":"P3 Investment Group Inc",
    "wof:placetype":"venue"
},
  "geometry": {"coordinates":[-79.790679,32.866456],"type":"Point"}
}