{
  "type": "Feature",
  "properties": {
    "addr:full":"508 Poinsett Hwy Greenville SC 29609",
    "addr:housenumber":"508",
    "addr:postcode":"29609",
    "addr:street":"Poinsett Hwy",
    "iso:country":"US",
    "sg:address":"508 Poinsett Hwy",
    "sg:city":"Greenville",
    "sg:classifiers":[
        {
            "category":"Professional",
            "subcategory":"Lawyer & Legal Services",
            "type":"Services"
        }
    ],
    "sg:phone":"+1 864 370 1550",
    "sg:postcode":"29609",
    "sg:province":"SC",
    "sg:tags":[
        "attorney"
    ],
    "wof:name":"Mc Call Environmental",
    "wof:placetype":"venue"
},
  "geometry": {"coordinates":[-82.404298,34.87657],"type":"Point"}
}