{
  "type": "Feature",
  "properties": {
    "iso:country":"US",
    "sg:address":"300 Pond Branch Rd",
    "sg:city":"Lexington",
    "sg:classifiers":[
        {
            "category":"Building & Trades",
            "subcategory":"Landscaping Services",
            "type":"Services"
        }
    ],
    "sg:phone":"+1 803 894 6053",
    "sg:postcode":"29073",
    "sg:province":"SC",
    "sg:tags":[
        "landscape"
    ],
    "wof:name":"Industrial Property Maint Co",
    "wof:placetype":"venue"
},
  "geometry": {"coordinates":[-81.30309,33.859163],"type":"Point"}
}