{
  "type": "Feature",
  "properties": {
    "addr:full":"1401 Hwy 301 N Dillon SC 29536",
    "addr:housenumber":"1401",
    "addr:postcode":"29536",
    "addr:street":"Hwy 301 N",
    "iso:country":"US",
    "sg:address":"1401 Hwy 301 N",
    "sg:city":"Dillon",
    "sg:classifiers":[
        {
            "category":"Bus Charters",
            "type":"Transportation"
        }
    ],
    "sg:phone":"+1 843 774 7090",
    "sg:postcode":"29536",
    "sg:province":"SC",
    "sg:tags":[
        "rental"
    ],
    "wof:name":"Coast To Coast Busline",
    "wof:placetype":"venue"
},
  "geometry": {"coordinates":[-79.361739,34.428872],"type":"Point"}
}