{
  "type": "Feature",
  "properties": {
    "addr:full":"3208 Two Notch Rd Columbia SC 29204",
    "addr:housenumber":"3208",
    "addr:postcode":"29204",
    "addr:street":"Two Notch Rd",
    "iso:country":"US",
    "sg:address":"3208 Two Notch Rd",
    "sg:city":"Columbia",
    "sg:classifiers":[
        {
            "category":"Food & Beverages",
            "subcategory":"Groceries & Convenience Stores",
            "type":"Retail Goods"
        }
    ],
    "sg:phone":"+1 803 786 0692",
    "sg:postcode":"29204",
    "sg:province":"SC",
    "wof:name":"E-Z Food Mart",
    "wof:placetype":"venue"
},
  "geometry": {"coordinates":[-81.001198,34.038898],"type":"Point"}
}