{
  "type": "Feature",
  "properties": {
    "iso:country":"US",
    "sg:address":"412 Saluda Rd",
    "sg:city":"Williamston",
    "sg:classifiers":[
        {
            "category":"Food & Beverages",
            "subcategory":"Liquor & Beverages",
            "type":"Retail Goods"
        }
    ],
    "sg:phone":"+1 864 847 7762",
    "sg:postcode":"29697",
    "sg:province":"SC",
    "sg:tags":[
        "drinking",
        "alcoholic"
    ],
    "wof:name":"Majors Party Shop",
    "wof:placetype":"venue"
},
  "geometry": {"coordinates":[-82.456026,34.619217],"type":"Point"}
}