{
  "type": "Feature",
  "properties": {
    "iso:country":"US",
    "sg:address":"756 Clearview Dr",
    "sg:city":"Charleston",
    "sg:classifiers":[
        {
            "category":"Professional",
            "subcategory":"Research",
            "type":"Services"
        }
    ],
    "sg:phone":"+1 843 795 4301",
    "sg:postcode":"29412",
    "sg:province":"SC",
    "wof:name":"Katherine Duffy & Assoc",
    "wof:placetype":"venue"
},
  "geometry": {"coordinates":[-79.91724600000001,32.750941],"type":"Point"}
}