{
  "type": "Feature",
  "properties": {
    "iso:country":"US",
    "sg:address":"102 Shelor Ferry Rd",
    "sg:city":"Fair Play",
    "sg:classifiers":[
        {
            "category":"Building & Trades",
            "subcategory":"Construction",
            "type":"Services"
        }
    ],
    "sg:phone":"+1 864 972 2720",
    "sg:postcode":"29643",
    "sg:province":"SC",
    "sg:tags":[
        "painter"
    ],
    "wof:name":"Wagner Painting",
    "wof:placetype":"venue"
},
  "geometry": {"coordinates":[-83.06675,34.520437],"type":"Point"}
}