{
  "type": "Feature",
  "properties": {
    "iso:country":"US",
    "sg:address":"3800 Fernandina Rd",
    "sg:city":"Columbia",
    "sg:classifiers":[
        {
            "category":"Utilities",
            "subcategory":"Refuse",
            "type":"Services"
        }
    ],
    "sg:phone":"+1 803 214 5800",
    "sg:postcode":"29210",
    "sg:province":"SC",
    "sg:tags":[
        "decommissioning",
        "waste",
        "radioactive",
        "shipment"
    ],
    "wof:name":"Rwe Nukem Corporation",
    "wof:placetype":"venue"
},
  "geometry": {"coordinates":[-81.136243,34.062013],"type":"Point"}
}