{
  "type": "Feature",
  "properties": {
    "addr:full":"5522 Buskirk Ave Charleston SC 29406",
    "addr:housenumber":"5522",
    "addr:postcode":"29406",
    "addr:street":"Buskirk Ave",
    "iso:country":"US",
    "sg:address":"5522 Buskirk Ave",
    "sg:city":"Charleston",
    "sg:classifiers":[
        {
            "category":"Restaurant",
            "type":"Food & Drink"
        }
    ],
    "sg:phone":"+1 843 744 1533",
    "sg:postcode":"29406",
    "sg:province":"SC",
    "sg:tags":[
        "eating",
        "caterer"
    ],
    "wof:name":"BBQ To Banquets",
    "wof:placetype":"venue"
},
  "geometry": {"coordinates":[-79.997052,32.900857],"type":"Point"}
}