{
  "type": "Feature",
  "properties": {
    "iso:country":"US",
    "sg:address":"2000 N Kings Hwy",
    "sg:city":"Myrtle Beach",
    "sg:classifiers":[
        {
            "category":"Bars & Pubs",
            "type":"Food & Drink"
        }
    ],
    "sg:phone":"+1 843 626 3855",
    "sg:postcode":"29577",
    "sg:province":"SC",
    "sg:tags":[
        "lounge",
        "drinking",
        "cocktail"
    ],
    "wof:name":"Studebaker's",
    "wof:placetype":"venue"
},
  "geometry": {"coordinates":[-78.872124,33.702341],"type":"Point"}
}