{
  "type": "Feature",
  "properties": {
    "iso:country":"US",
    "sg:address":"200 Elm St",
    "sg:city":"Conway",
    "sg:classifiers":[
        {
            "category":"Professional",
            "subcategory":"Lawyer & Legal Services",
            "type":"Services"
        }
    ],
    "sg:phone":"+1 843 248 7135",
    "sg:postcode":"29526",
    "sg:province":"SC",
    "sg:tags":[
        "attorney"
    ],
    "wof:name":"Johnny Gardner",
    "wof:placetype":"venue"
},
  "geometry": {"coordinates":[-79.048294,33.834165],"type":"Point"}
}