{
  "type": "Feature",
  "properties": {
    "iso:country":"US",
    "sg:address":"1502 E North St",
    "sg:city":"Greenville",
    "sg:classifiers":[
        {
            "category":"Personal",
            "subcategory":"Beauty Salon",
            "type":"Services"
        }
    ],
    "sg:phone":"+1 864 233 8301",
    "sg:postcode":"29607",
    "sg:province":"SC",
    "wof:name":"Richards Salon",
    "wof:placetype":"venue"
},
  "geometry": {"coordinates":[-82.378025,34.859407],"type":"Point"}
}