{
  "type": "Feature",
  "properties": {
    "iso:country":"US",
    "sg:address":"1945 Mister Joe White Ave",
    "sg:city":"Myrtle Beach",
    "sg:classifiers":[
        {
            "category":"Restaurant",
            "type":"Food & Drink"
        }
    ],
    "sg:menulink":"http://www.allmenus.com/sc/myrtle-beach/129226-subway/menu/",
    "sg:phone":"+1 843 448 6643",
    "sg:postcode":"29577",
    "sg:province":"SC",
    "sg:tags":[
        "american",
        "sandwich"
    ],
    "wof:name":"Subway",
    "wof:placetype":"venue"
},
  "geometry": {"coordinates":[-78.89939099999999,33.712721],"type":"Point"}
}