{
  "type": "Feature",
  "properties": {
    "addr:full":"5432 Augusta Rd Lexington SC 29072",
    "addr:housenumber":"5432",
    "addr:postcode":"29072",
    "addr:street":"Augusta Rd",
    "iso:country":"US",
    "sg:address":"5432 Augusta Rd",
    "sg:city":"Lexington",
    "sg:classifiers":[
        {
            "category":"Sports & Exercise",
            "subcategory":"Gym",
            "type":"Entertainment"
        }
    ],
    "sg:phone":"+1 803 356 6400",
    "sg:postcode":"29072",
    "sg:province":"SC",
    "sg:tags":[
        "club",
        "health",
        "studio",
        "gymnasium"
    ],
    "wof:name":"Wolf's Fitness Ctr",
    "wof:placetype":"venue"
},
  "geometry": {"coordinates":[-81.21535299999999,33.974764],"type":"Point"}
}