{
  "type": "Feature",
  "properties": {
    "iso:country":"US",
    "sg:address":"243 Providence Rd",
    "sg:city":"Lancaster",
    "sg:classifiers":[
        {
            "category":"Farming",
            "subcategory":"Nursery",
            "type":"Manufacturing & Wholesale Goods"
        }
    ],
    "sg:phone":"+1 803 286 4494",
    "sg:postcode":"29720",
    "sg:province":"SC",
    "sg:tags":[
        "ornamental",
        "greenhouse"
    ],
    "wof:name":"Bailey's Greenhouse",
    "wof:placetype":"venue"
},
  "geometry": {"coordinates":[-80.723927,34.672571],"type":"Point"}
}