{
  "type": "Feature",
  "properties": {
    "iso:country":"US",
    "sg:address":"3650 Fernandina Rd",
    "sg:city":"Columbia",
    "sg:classifiers":[
        {
            "category":"Autos & Motor Vehicles",
            "subcategory":"Recreational Vehicle Sales",
            "type":"Retail Goods"
        }
    ],
    "sg:phone":"+1 803 744 7600",
    "sg:postcode":"29210",
    "sg:province":"SC",
    "wof:name":"Coachmen Of Carolina",
    "wof:placetype":"venue"
},
  "geometry": {"coordinates":[-81.127537,34.053668],"type":"Point"}
}