{
  "type": "Feature",
  "properties": {
    "iso:country":"US",
    "sg:address":"3545 Raven Hill Rd",
    "sg:city":"Columbia",
    "sg:classifiers":[
        {
            "category":"Organizations",
            "subcategory":"Religious Organization",
            "type":"Services"
        }
    ],
    "sg:phone":"+1 803 782 1617",
    "sg:postcode":"29204",
    "sg:province":"SC",
    "sg:tags":[
        "church"
    ],
    "wof:name":"Ravenwood Baptist Church",
    "wof:placetype":"venue"
},
  "geometry": {"coordinates":[-80.983119,34.032853],"type":"Point"}
}