{
  "type": "Feature",
  "properties": {
    "addr:full":"2846 Wade Hampton Blvd Taylors SC 29687",
    "addr:housenumber":"2846",
    "addr:postcode":"29687",
    "addr:street":"Wade Hampton Blvd",
    "iso:country":"US",
    "sg:address":"2846 Wade Hampton Blvd",
    "sg:city":"Taylors",
    "sg:classifiers":[
        {
            "category":"Food & Beverages",
            "subcategory":"Bakery",
            "type":"Retail Goods"
        }
    ],
    "sg:phone":"+1 864 322 5212",
    "sg:postcode":"29687",
    "sg:province":"SC",
    "sg:tags":[
        "baker"
    ],
    "wof:name":"LA Especial",
    "wof:placetype":"venue"
},
  "geometry": {"coordinates":[-82.33660999999999,34.900438],"type":"Point"}
}