{
  "type": "Feature",
  "properties": {
    "iso:country":"US",
    "sg:address":"965 Dougherty Rd",
    "sg:city":"Aiken",
    "sg:classifiers":[
        {
            "category":"Insurance",
            "subcategory":"Insurance Agent",
            "type":"Services"
        }
    ],
    "sg:phone":"+1 803 642 4551",
    "sg:postcode":"29803",
    "sg:province":"SC",
    "wof:name":"Mark Taylor Assoc LLC",
    "wof:placetype":"venue"
},
  "geometry": {"coordinates":[-81.726485,33.515496],"type":"Point"}
}