{
  "type": "Feature",
  "properties": {
    "iso:country":"US",
    "sg:address":"103 Wall St",
    "sg:city":"Barnwell",
    "sg:classifiers":[
        {
            "category":"Wholesale",
            "subcategory":"Machinery & Supplies",
            "type":"Manufacturing & Wholesale Goods"
        }
    ],
    "sg:phone":"+1 803 671 0488",
    "sg:postcode":"29812",
    "sg:province":"SC",
    "sg:tags":[
        "industrial"
    ],
    "wof:name":"Ace Distributing and Supply Co",
    "wof:placetype":"venue"
},
  "geometry": {"coordinates":[-81.365302,33.245914],"type":"Point"}
}