{
  "type": "Feature",
  "properties": {
    "addr:full":"5920 Savannah Hwy Ravenel SC 29470",
    "addr:housenumber":"5920",
    "addr:postcode":"29470",
    "addr:street":"Savannah Hwy",
    "iso:country":"US",
    "sg:address":"5920 Savannah Hwy",
    "sg:city":"Ravenel",
    "sg:classifiers":[
        {
            "category":"Freight",
            "type":"Transportation"
        }
    ],
    "sg:phone":"+1 843 889 9473",
    "sg:postcode":"29470",
    "sg:province":"SC",
    "sg:tags":[
        "commercial",
        "storage",
        "general"
    ],
    "wof:name":"Ravenel Self Storage",
    "wof:placetype":"venue"
},
  "geometry": {"coordinates":[-80.22839999999999,32.780007],"type":"Point"}
}