{
  "type": "Feature",
  "properties": {
    "iso:country":"US",
    "sg:address":"2441 Lang Rd",
    "sg:city":"Columbia",
    "sg:classifiers":[
        {
            "category":"Manufacturing",
            "subcategory":"Printing",
            "type":"Manufacturing & Wholesale Goods"
        }
    ],
    "sg:phone":"+1 803 771 4361",
    "sg:postcode":"29204",
    "sg:province":"SC",
    "sg:tags":[
        "screen"
    ],
    "wof:name":"Mozart",
    "wof:placetype":"venue"
},
  "geometry": {"coordinates":[-81.018411,34.026314],"type":"Point"}
}