{
  "type": "Feature",
  "properties": {
    "iso:country":"US",
    "sg:address":"6941 Trenholm Rd",
    "sg:city":"Columbia",
    "sg:classifiers":[
        {
            "category":"Personal",
            "subcategory":"Beauty Salon",
            "type":"Services"
        }
    ],
    "sg:phone":"+1 803 787 9419",
    "sg:postcode":"29206",
    "sg:province":"SC",
    "sg:tags":[
        "manicuring"
    ],
    "wof:name":"Kay's Salon",
    "wof:placetype":"venue"
},
  "geometry": {"coordinates":[-80.956953,34.061372],"type":"Point"}
}