{
  "type": "Feature",
  "properties": {
    "iso:country":"US",
    "sg:address":"4675 Franchise St",
    "sg:city":"North Charleston",
    "sg:classifiers":[
        {
            "category":"Wholesale",
            "subcategory":"Auto Parts",
            "type":"Manufacturing & Wholesale Goods"
        }
    ],
    "sg:phone":"+1 843 552 0424",
    "sg:postcode":"29418",
    "sg:province":"SC",
    "sg:tags":[
        "automotive"
    ],
    "wof:name":"Automotive Parts Express Inc",
    "wof:placetype":"venue"
},
  "geometry": {"coordinates":[-80.091366,32.913764],"type":"Point"}
}