{
  "type": "Feature",
  "properties": {
    "iso:country":"US",
    "sg:address":"115 Boy St",
    "sg:city":"Spartanburg",
    "sg:classifiers":[
        {
            "category":"Professional",
            "subcategory":"Accounting & Tax Preparation",
            "type":"Services"
        }
    ],
    "sg:phone":"+1 864 503 8500",
    "sg:postcode":"29303",
    "sg:province":"SC",
    "sg:tags":[
        "return",
        "filing"
    ],
    "wof:name":"By The Numbers",
    "wof:placetype":"venue"
},
  "geometry": {"coordinates":[-81.968852,34.988379],"type":"Point"}
}