{
  "type": "Feature",
  "properties": {
    "iso:country":"US",
    "sg:address":"1835 Pint Cir",
    "sg:city":"Longs",
    "sg:classifiers":[
        {
            "category":"Social Services",
            "subcategory":"Child Care",
            "type":"Services"
        }
    ],
    "sg:phone":"+1 843 399 0419",
    "sg:postcode":"29568",
    "sg:province":"SC",
    "wof:name":"Tina's Tots Cdc Inc",
    "wof:placetype":"venue"
},
  "geometry": {"coordinates":[-78.763126,33.86707],"type":"Point"}
}