{
  "type": "Feature",
  "properties": {
    "iso:country":"US",
    "sg:address":"721 W Liberty St",
    "sg:city":"Marion",
    "sg:classifiers":[
        {
            "category":"Home & Garden",
            "subcategory":"Hardware",
            "type":"Retail Goods"
        }
    ],
    "sg:phone":"+1 843 423 1781",
    "sg:postcode":"29571",
    "sg:province":"SC",
    "wof:name":"Thomas Supply Co",
    "wof:placetype":"venue"
},
  "geometry": {"coordinates":[-79.41283799999999,34.17234],"type":"Point"}
}