{
  "type": "Feature",
  "properties": {
    "iso:country":"US",
    "sg:address":"1092 Johnnie Dodds Blvd",
    "sg:city":"Mount Pleasant",
    "sg:classifiers":[
        {
            "category":"Real Estate",
            "subcategory":"Real Estate Agent",
            "type":"Services"
        }
    ],
    "sg:phone":"+1 843 856 6556",
    "sg:postcode":"29464",
    "sg:province":"SC",
    "wof:name":"A-Plus Property Management",
    "wof:placetype":"venue"
},
  "geometry": {"coordinates":[-79.861476,32.812136],"type":"Point"}
}