{
  "type": "Feature",
  "properties": {
    "iso:country":"US",
    "sg:address":"1433 Lockhart Hwy",
    "sg:city":"Union",
    "sg:classifiers":[
        {
            "category":"Social Services",
            "subcategory":"Child Care",
            "type":"Services"
        }
    ],
    "sg:phone":"+1 864 427 2017",
    "sg:postcode":"29379",
    "sg:province":"SC",
    "wof:name":"Mon-Aetna Child Enrichment Ctr",
    "wof:placetype":"venue"
},
  "geometry": {"coordinates":[-81.60046800000001,34.716966],"type":"Point"}
}