{
  "type": "Feature",
  "properties": {
    "iso:country":"US",
    "sg:address":"860 S Church St",
    "sg:city":"Greenville",
    "sg:classifiers":[
        {
            "category":"Retail",
            "subcategory":"Laundry & Dry Cleaning",
            "type":"Services"
        }
    ],
    "sg:phone":"+1 864 242 6325",
    "sg:postcode":"29605",
    "sg:province":"SC",
    "wof:name":"Bell Tower Coin Laundry",
    "wof:placetype":"venue"
},
  "geometry": {"coordinates":[-82.40036000000001,34.838665],"type":"Point"}
}