{
  "type": "Feature",
  "properties": {
    "addr:full":"213 Loch Rd Columbia SC 29210",
    "addr:housenumber":"213",
    "addr:postcode":"29210",
    "addr:street":"Loch Rd",
    "iso:country":"US",
    "sg:address":"213 Loch Rd",
    "sg:city":"Columbia",
    "sg:classifiers":[
        {
            "category":"Building & Trades",
            "subcategory":"Construction",
            "type":"Services"
        }
    ],
    "sg:phone":"+1 803 216 9500",
    "sg:postcode":"29210",
    "sg:province":"SC",
    "sg:tags":[
        "steel"
    ],
    "wof:name":"Steel Services",
    "wof:placetype":"venue"
},
  "geometry": {"coordinates":[-81.13255700000001,34.052567],"type":"Point"}
}