{
  "type": "Feature",
  "properties": {
    "iso:country":"US",
    "sg:address":"217 Saint Awdry St",
    "sg:city":"Summerville",
    "sg:classifiers":[
        {
            "category":"Utilities",
            "subcategory":"Telephone",
            "type":"Services"
        }
    ],
    "sg:phone":"+1 843 875 4787",
    "sg:postcode":"29485",
    "sg:province":"SC",
    "sg:tags":[
        "communications"
    ],
    "wof:name":"Tel Net Corp",
    "wof:placetype":"venue"
},
  "geometry": {"coordinates":[-80.134408,32.986763],"type":"Point"}
}