{
  "type": "Feature",
  "properties": {
    "iso:country":"US",
    "sg:address":"109 Latour Way",
    "sg:city":"Greer",
    "sg:classifiers":[
        {
            "category":"Professional",
            "type":"Services"
        }
    ],
    "sg:phone":"+1 864 877 3303",
    "sg:postcode":"29650",
    "sg:province":"SC",
    "sg:tags":[
        "establishment"
    ],
    "wof:name":"Alek Vare",
    "wof:placetype":"venue"
},
  "geometry": {"coordinates":[-82.258659,34.870204],"type":"Point"}
}