{
  "type": "Feature",
  "properties": {
    "iso:country":"US",
    "sg:address":"279 Gramling Rd",
    "sg:city":"Cameron",
    "sg:classifiers":[
        {
            "category":"Restaurant",
            "type":"Food & Drink"
        }
    ],
    "sg:phone":"+1 803 534 1158",
    "sg:postcode":"29030",
    "sg:province":"SC",
    "sg:tags":[
        "eating"
    ],
    "wof:name":"Lauras Catering",
    "wof:placetype":"venue"
},
  "geometry": {"coordinates":[-80.722568,33.510559],"type":"Point"}
}