{
  "type": "Feature",
  "properties": {
    "iso:country":"US",
    "sg:address":"59 Woodruff Industrial Ln",
    "sg:city":"Greenville",
    "sg:classifiers":[
        {
            "category":"Utilities",
            "subcategory":"Mobile Phone",
            "type":"Services"
        }
    ],
    "sg:phone":"+1 864 288 6516",
    "sg:postcode":"29607",
    "sg:province":"SC",
    "sg:tags":[
        "telephone",
        "cellular"
    ],
    "wof:name":"Wireless Retail Inc",
    "wof:placetype":"venue"
},
  "geometry": {"coordinates":[-82.30716099999999,34.829802],"type":"Point"}
}