{
  "type": "Feature",
  "properties": {
    "iso:country":"US",
    "sg:address":"5720 Weston Ave",
    "sg:city":"Columbia",
    "sg:classifiers":[
        {
            "category":"Retail",
            "subcategory":"Auto Repair",
            "type":"Services"
        }
    ],
    "sg:phone":"+1 803 754 2625",
    "sg:postcode":"29203",
    "sg:province":"SC",
    "sg:tags":[
        "body",
        "automobile",
        "painting"
    ],
    "wof:name":"Smith & Sons Body & Paint Shop",
    "wof:placetype":"venue"
},
  "geometry": {"coordinates":[-81.01806000000001,34.059976],"type":"Point"}
}