{
  "type": "Feature",
  "properties": {
    "iso:country":"US",
    "sg:address":"133 Columbia St",
    "sg:city":"Chester",
    "sg:classifiers":[
        {
            "category":"Food & Beverages",
            "subcategory":"Groceries & Convenience Stores",
            "type":"Retail Goods"
        }
    ],
    "sg:phone":"+1 803 581 4581",
    "sg:postcode":"29706",
    "sg:province":"SC",
    "wof:name":"Bob's Food Mart",
    "wof:placetype":"venue"
},
  "geometry": {"coordinates":[-81.212301,34.702748],"type":"Point"}
}