{
  "type": "Feature",
  "properties": {
    "iso:country":"US",
    "sg:address":"145 County Camp Rd",
    "sg:city":"Kingstree",
    "sg:classifiers":[
        {
            "category":"Health Services",
            "subcategory":"Nursing And Care Facility",
            "type":"Services"
        }
    ],
    "sg:phone":"+1 843 382 8893",
    "sg:postcode":"29556",
    "sg:province":"SC",
    "sg:tags":[
        "home",
        "convalescent"
    ],
    "wof:name":"Williamsburg Cares Inc",
    "wof:placetype":"venue"
},
  "geometry": {"coordinates":[-79.80897400000001,33.704536],"type":"Point"}
}