{
  "type": "Feature",
  "properties": {
    "iso:country":"US",
    "sg:address":"110 Mathews Dr",
    "sg:city":"Hilton Head Isle",
    "sg:classifiers":[
        {
            "category":"Personal",
            "subcategory":"Beauty Salon",
            "type":"Services"
        }
    ],
    "sg:phone":"+1 843 681 7070",
    "sg:postcode":"29926",
    "sg:province":"SC",
    "wof:name":"Hhits Tanning & Beauty Salon",
    "wof:placetype":"venue"
},
  "geometry": {"coordinates":[-80.70266,32.208754],"type":"Point"}
}