{
  "type": "Feature",
  "properties": {
    "iso:country":"US",
    "sg:address":"1148 Pocalla Rd",
    "sg:city":"Sumter",
    "sg:classifiers":[
        {
            "category":"Shopping",
            "type":"Retail Goods"
        },
        {
            "category":"Manufacturing",
            "subcategory":"Apparel",
            "type":"Manufacturing & Wholesale Goods"
        }
    ],
    "sg:phone":"+1 803 934 9755",
    "sg:postcode":"29150",
    "sg:province":"SC",
    "sg:tags":[
        "factory",
        "outlet",
        "mfg"
    ],
    "wof:name":"Factory Discount",
    "wof:placetype":"venue"
},
  "geometry": {"coordinates":[-80.345387,33.888307],"type":"Point"}
}