{
  "type": "Feature",
  "properties": {
    "addr:full":"12 N Congress St York SC 29745",
    "addr:housenumber":"12",
    "addr:postcode":"29745",
    "addr:street":"N Congress St",
    "iso:country":"US",
    "sg:address":"12 N Congress St",
    "sg:city":"York",
    "sg:classifiers":[
        {
            "category":"Banks & Credit Unions",
            "subcategory":"Bank",
            "type":"Services"
        }
    ],
    "sg:phone":"+1 803 628 2010",
    "sg:postcode":"29745",
    "sg:province":"SC",
    "wof:name":"First Citizens Bank",
    "wof:placetype":"venue"
},
  "geometry": {"coordinates":[-81.241063,34.995247],"type":"Point"}
}