{
  "type": "Feature",
  "properties": {
    "iso:country":"US",
    "sg:address":"501 Rochester Hwy",
    "sg:city":"Seneca",
    "sg:classifiers":[
        {
            "category":"Retail",
            "subcategory":"Auto Rental",
            "type":"Services"
        },
        {
            "category":"Airport",
            "type":"Transportation"
        },
        {
            "category":"Local Transit",
            "type":"Transportation"
        }
    ],
    "sg:phone":"+1 864 653 5677",
    "sg:postcode":"29672",
    "sg:province":"SC",
    "sg:tags":[
        "shuttle",
        "limousine"
    ],
    "sg:website":"http://WWW.AAAIRPORTSERVICES.COM",
    "wof:name":"Mcgmyconcierge.com",
    "wof:placetype":"venue"
},
  "geometry": {"coordinates":[-82.926399,34.71035],"type":"Point"}
}