{
  "type": "Feature",
  "properties": {
    "iso:country":"US",
    "sg:address":"214 Sangaree Rd",
    "sg:city":"Summerville",
    "sg:classifiers":[
        {
            "category":"Retail",
            "subcategory":"Auto Rental",
            "type":"Services"
        }
    ],
    "sg:phone":"+1 843 863 9444",
    "sg:postcode":"29488",
    "sg:province":"SC",
    "sg:tags":[
        "renting",
        "truck",
        "leasing"
    ],
    "sg:website":"www.pensketruckleasing.com",
    "wof:name":"Penske Truck Leasing",
    "wof:placetype":"venue"
},
  "geometry": {"coordinates":[-80.672719,32.931676],"type":"Point"}
}