{
  "type": "Feature",
  "properties": {
    "iso:country":"US",
    "sg:address":"44 Tillersplow Ct",
    "sg:city":"Pawleys Island",
    "sg:classifiers":[
        {
            "category":"Building & Trades",
            "subcategory":"Construction",
            "type":"Services"
        }
    ],
    "sg:phone":"+1 843 235 0453",
    "sg:postcode":"29585",
    "sg:province":"SC",
    "sg:tags":[
        "contractor"
    ],
    "wof:name":"Estate Pools",
    "wof:placetype":"venue"
},
  "geometry": {"coordinates":[-79.14590699999999,33.460789],"type":"Point"}
}