{
  "type": "Feature",
  "properties": {
    "iso:country":"US",
    "sg:address":"2203 Marchbanks Ave",
    "sg:city":"Anderson",
    "sg:classifiers":[
        {
            "category":"Social Services",
            "subcategory":"Adult Care",
            "type":"Services"
        }
    ],
    "sg:phone":"+1 864 231 7786",
    "sg:postcode":"29621",
    "sg:province":"SC",
    "sg:tags":[
        "home",
        "residential"
    ],
    "wof:name":"Magnolias Of Anderson",
    "wof:placetype":"venue"
},
  "geometry": {"coordinates":[-82.629048,34.527499],"type":"Point"}
}