{
  "type": "Feature",
  "properties": {
    "addr:full":"172 Liberty Church Rd Loris SC 29569",
    "addr:housenumber":"172",
    "addr:postcode":"29569",
    "addr:street":"Liberty Church Rd",
    "iso:country":"US",
    "sg:address":"172 Liberty Church Rd",
    "sg:city":"Loris",
    "sg:classifiers":[
        {
            "category":"Autos & Motor Vehicles",
            "subcategory":"Automobile Sales",
            "type":"Retail Goods"
        }
    ],
    "sg:phone":"+1 843 756 2007",
    "sg:postcode":"29569",
    "sg:province":"SC",
    "sg:tags":[
        "car",
        "dealer"
    ],
    "wof:name":"Mark's Auto Sales",
    "wof:placetype":"venue"
},
  "geometry": {"coordinates":[-78.815545,34.028544],"type":"Point"}
}