{
  "type": "Feature",
  "properties": {
    "iso:country":"US",
    "sg:address":"718 York St NE",
    "sg:city":"Aiken",
    "sg:classifiers":[
        {
            "category":"Retail",
            "subcategory":"Car Wash",
            "type":"Services"
        }
    ],
    "sg:phone":"+1 803 641 0722",
    "sg:postcode":"29801",
    "sg:province":"SC",
    "sg:tags":[
        "polishing",
        "washing"
    ],
    "wof:name":"York Street Carwash",
    "wof:placetype":"venue"
},
  "geometry": {"coordinates":[-81.709473,33.570665],"type":"Point"}
}