{
  "type": "Feature",
  "properties": {
    "iso:country":"US",
    "sg:address":"3 Grayhawk Way",
    "sg:city":"Simpsonville",
    "sg:classifiers":[
        {
            "category":"Wholesale",
            "subcategory":"Stationery",
            "type":"Manufacturing & Wholesale Goods"
        }
    ],
    "sg:phone":"+1 864 284 0424",
    "sg:postcode":"29681",
    "sg:province":"SC",
    "sg:tags":[
        "supply"
    ],
    "wof:name":"Reynolds & Reynolds",
    "wof:placetype":"venue"
},
  "geometry": {"coordinates":[-82.21792499999999,34.799092],"type":"Point"}
}