{
  "type": "Feature",
  "properties": {
    "iso:country":"US",
    "sg:address":"692 S Grapevine Rd",
    "sg:city":"Pamplico",
    "sg:classifiers":[
        {
            "category":"Building & Trades",
            "subcategory":"Construction",
            "type":"Services"
        }
    ],
    "sg:phone":"+1 843 493 0292",
    "sg:postcode":"29583",
    "sg:province":"SC",
    "sg:tags":[
        "hanging",
        "contractor"
    ],
    "wof:name":"Mark Balmer Painting",
    "wof:placetype":"venue"
},
  "geometry": {"coordinates":[-79.599374,33.983633],"type":"Point"}
}