{
  "type": "Feature",
  "properties": {
    "iso:country":"US",
    "sg:address":"1441 US Hwy 501",
    "sg:city":"Myrtle Beach",
    "sg:classifiers":[
        {
            "category":"Autos & Motor Vehicles",
            "subcategory":"Automobile Sales",
            "type":"Retail Goods"
        }
    ],
    "sg:phone":"+1 843 626 8686",
    "sg:postcode":"29577",
    "sg:province":"SC",
    "sg:tags":[
        "used"
    ],
    "wof:name":"Myrtle Bch T-N-T Auto Sls LLC",
    "wof:placetype":"venue"
},
  "geometry": {"coordinates":[-78.901501,33.700239],"type":"Point"}
}