{
  "type": "Feature",
  "properties": {
    "iso:country":"US",
    "sg:address":"2733 Seibert Rd",
    "sg:city":"Prosperity",
    "sg:classifiers":[
        {
            "category":"Government",
            "subcategory":"Office",
            "type":"Public Place"
        }
    ],
    "sg:phone":"+1 803 364 0378",
    "sg:postcode":"29127",
    "sg:province":"SC",
    "wof:name":"Newberry County Collection Ctr",
    "wof:placetype":"venue"
},
  "geometry": {"coordinates":[-81.51097300000001,34.136655],"type":"Point"}
}