{
  "type": "Feature",
  "properties": {
    "iso:country":"US",
    "sg:address":"1012 State Hwy 38 Bus",
    "sg:city":"Bennettsville",
    "sg:classifiers":[
        {
            "category":"Food & Beverages",
            "subcategory":"Groceries & Convenience Stores",
            "type":"Retail Goods"
        }
    ],
    "sg:phone":"+1 843 479 4901",
    "sg:postcode":"29512",
    "sg:province":"SC",
    "wof:name":"Express Mart-B & M",
    "wof:placetype":"venue"
},
  "geometry": {"coordinates":[-79.69371,34.635833],"type":"Point"}
}