{
  "type": "Feature",
  "properties": {
    "addr:full":"527 E Carolina Ave Hartsville SC 29550",
    "addr:housenumber":"527",
    "addr:postcode":"29550",
    "addr:street":"E Carolina Ave",
    "iso:country":"US",
    "sg:address":"527 E Carolina Ave",
    "sg:city":"Hartsville",
    "sg:classifiers":[
        {
            "category":"Real Estate",
            "subcategory":"Architect",
            "type":"Services"
        }
    ],
    "sg:phone":"+1 843 383 5212",
    "sg:postcode":"29550",
    "sg:province":"SC",
    "wof:name":"Robert Goodson Architecture",
    "wof:placetype":"venue"
},
  "geometry": {"coordinates":[-80.064105,34.377703],"type":"Point"}
}