{
  "type": "Feature",
  "properties": {
    "iso:country":"US",
    "sg:address":"425 S 5th St",
    "sg:city":"Hartsville",
    "sg:classifiers":[
        {
            "category":"Autos & Motor Vehicles",
            "subcategory":"Auto Supplies",
            "type":"Retail Goods"
        }
    ],
    "sg:phone":"+1 843 332 1191",
    "sg:postcode":"29550",
    "sg:province":"SC",
    "sg:tags":[
        "automobile",
        "parts"
    ],
    "wof:name":"Evans Parts Co",
    "wof:placetype":"venue"
},
  "geometry": {"coordinates":[-80.068504,34.366082],"type":"Point"}
}