{
  "type": "Feature",
  "properties": {
    "iso:country":"US",
    "sg:address":"1348 Fulmer Rd",
    "sg:city":"Blythewood",
    "sg:classifiers":[
        {
            "category":"Building & Trades",
            "subcategory":"Construction",
            "type":"Services"
        }
    ],
    "sg:phone":"+1 803 754 3673",
    "sg:postcode":"29016",
    "sg:province":"SC",
    "sg:tags":[
        "excavation",
        "contractor"
    ],
    "wof:name":"Kenneth McLean Construction Co",
    "wof:placetype":"venue"
},
  "geometry": {"coordinates":[-81.001194,34.15178],"type":"Point"}
}