{
  "type": "Feature",
  "properties": {
    "iso:country":"US",
    "sg:address":"1295 Wilson Hall Rd",
    "sg:city":"Sumter",
    "sg:classifiers":[
        {
            "category":"Manufacturing",
            "subcategory":"Printing",
            "type":"Manufacturing & Wholesale Goods"
        }
    ],
    "sg:phone":"+1 803 905 4444",
    "sg:postcode":"29150",
    "sg:province":"SC",
    "sg:tags":[
        "printer"
    ],
    "sg:website":"www.sumterprinting.com",
    "wof:name":"Sumter Printing Co Inc",
    "wof:placetype":"venue"
},
  "geometry": {"coordinates":[-80.39851,33.956307],"type":"Point"}
}