{
  "type": "Feature",
  "properties": {
    "addr:full":"360 Freedom Trl Roebuck SC 29376",
    "addr:housenumber":"360",
    "addr:postcode":"29376",
    "addr:street":"Freedom Trl",
    "iso:country":"US",
    "sg:address":"360 Freedom Trl",
    "sg:city":"Roebuck",
    "sg:classifiers":[
        {
            "category":"Building & Trades",
            "subcategory":"Construction",
            "type":"Services"
        }
    ],
    "sg:phone":"+1 864 303 5084",
    "sg:postcode":"29376",
    "sg:province":"SC",
    "sg:tags":[
        "insulation",
        "contractor"
    ],
    "wof:name":"East Coast Insulation Inc",
    "wof:placetype":"venue"
},
  "geometry": {"coordinates":[-81.93768799999999,34.859365],"type":"Point"}
}