{
  "type": "Feature",
  "properties": {
    "iso:country":"US",
    "sg:address":"4513 S Irby St",
    "sg:city":"Effingham",
    "sg:classifiers":[
        {
            "category":"Retail",
            "subcategory":"Auto Repair",
            "type":"Services"
        }
    ],
    "sg:phone":"+1 843 669 0971",
    "sg:postcode":"29541",
    "sg:province":"SC",
    "sg:tags":[
        "transmission"
    ],
    "wof:name":"AAA Transmission Svc",
    "wof:placetype":"venue"
},
  "geometry": {"coordinates":[-79.77762,34.096797],"type":"Point"}
}