{
  "type": "Feature",
  "properties": {
    "iso:country":"US",
    "sg:address":"106 S Catherine St",
    "sg:city":"Pickens",
    "sg:classifiers":[
        {
            "category":"Shopping",
            "subcategory":"Computers & Home Electronics",
            "type":"Retail Goods"
        }
    ],
    "sg:phone":"+1 864 898 0099",
    "sg:postcode":"29671",
    "sg:province":"SC",
    "sg:tags":[
        "equipment",
        "satellite",
        "system"
    ],
    "wof:name":"Custom Cable Etc",
    "wof:placetype":"venue"
},
  "geometry": {"coordinates":[-82.710476,34.882776],"type":"Point"}
}