{
  "type": "Feature",
  "properties": {
    "addr:full":"1005 Old Cherokee Rd Lexington SC 29072",
    "addr:housenumber":"1005",
    "addr:postcode":"29072",
    "addr:street":"Old Cherokee Rd",
    "iso:country":"US",
    "sg:address":"1005 Old Cherokee Rd",
    "sg:city":"Lexington",
    "sg:classifiers":[
        {
            "category":"Deli",
            "type":"Food & Drink"
        }
    ],
    "sg:menulink":"http://www.allmenus.com/sc/lexington/126638-blimpie-subs--sandwiches/menu/",
    "sg:phone":"+1 803 356 1897",
    "sg:postcode":"29072",
    "sg:province":"SC",
    "sg:tags":[
        "wrap",
        "american",
        "sandwich"
    ],
    "wof:name":"Blimpie Subs & Sandwiches",
    "wof:placetype":"venue"
},
  "geometry": {"coordinates":[-81.259901,34.009946],"type":"Point"}
}