{
  "type": "Feature",
  "properties": {
    "addr:full":"5 Park Ave Salem SC 29676",
    "addr:housenumber":"5",
    "addr:postcode":"29676",
    "addr:street":"Park Ave",
    "iso:country":"US",
    "sg:address":"5 Park Ave",
    "sg:city":"Salem",
    "sg:classifiers":[
        {
            "category":"Government",
            "subcategory":"Office",
            "type":"Public Place"
        }
    ],
    "sg:phone":"+1 864 944 2819",
    "sg:postcode":"29676",
    "sg:province":"SC",
    "sg:tags":[
        "city"
    ],
    "wof:name":"Town Hall",
    "wof:placetype":"venue"
},
  "geometry": {"coordinates":[-82.97591300000001,34.891126],"type":"Point"}
}