{
  "type": "Feature",
  "properties": {
    "addr:full":"4214 Domino Ave North Charleston SC 29405",
    "addr:housenumber":"4214",
    "addr:postcode":"29405",
    "addr:street":"Domino Ave",
    "iso:country":"US",
    "sg:address":"4214 Domino Ave",
    "sg:city":"North Charleston",
    "sg:classifiers":[
        {
            "category":"Wholesale",
            "subcategory":"Vending Machines",
            "type":"Manufacturing & Wholesale Goods"
        }
    ],
    "sg:phone":"+1 843 554 8845",
    "sg:postcode":"29405",
    "sg:province":"SC",
    "wof:name":"R & T Snack Time Inc",
    "wof:placetype":"venue"
},
  "geometry": {"coordinates":[-80.003376,32.844177],"type":"Point"}
}