{
  "type": "Feature",
  "properties": {
    "addr:full":"153 Main St N Wagener SC 29164",
    "addr:housenumber":"153",
    "addr:postcode":"29164",
    "addr:street":"Main St N",
    "iso:country":"US",
    "sg:address":"153 Main St N",
    "sg:city":"Wagener",
    "sg:classifiers":[
        {
            "category":"Banks & Credit Unions",
            "subcategory":"Bank",
            "type":"Services"
        }
    ],
    "sg:phone":"+1 803 564 5101",
    "sg:postcode":"29164",
    "sg:province":"SC",
    "sg:tags":[
        "loan"
    ],
    "wof:name":"Delta Loans",
    "wof:placetype":"venue"
},
  "geometry": {"coordinates":[-81.361797,33.651696],"type":"Point"}
}