{
  "type": "Feature",
  "properties": {
    "iso:country":"US",
    "sg:address":"7 Craftsman Ct",
    "sg:city":"Greer",
    "sg:classifiers":[
        {
            "category":"Social Services",
            "type":"Services"
        }
    ],
    "sg:phone":"+1 864 968 0016",
    "sg:postcode":"29650",
    "sg:province":"SC",
    "sg:tags":[
        "counseling"
    ],
    "wof:name":"Brewer Center-Psychiatry & Fam",
    "wof:placetype":"venue"
},
  "geometry": {"coordinates":[-82.236996,34.895047],"type":"Point"}
}