{
  "type": "Feature",
  "properties": {
    "iso:country":"US",
    "sg:address":"1082 Sarvis Farm Rd",
    "sg:city":"Longs",
    "sg:classifiers":[
        {
            "category":"Building & Trades",
            "subcategory":"Landscaping Services",
            "type":"Services"
        }
    ],
    "sg:phone":"+1 843 399 1820",
    "sg:postcode":"29568",
    "sg:province":"SC",
    "sg:tags":[
        "lawn",
        "maintenance",
        "grounds"
    ],
    "wof:name":"Bobby's Lawn Care",
    "wof:placetype":"venue"
},
  "geometry": {"coordinates":[-78.701776,33.950692],"type":"Point"}
}