{
  "type": "Feature",
  "properties": {
    "addr:full":"6659 US Hwy 76 Nichols SC 29581",
    "addr:housenumber":"6659",
    "addr:postcode":"29581",
    "addr:street":"Us Hwy 76",
    "iso:country":"US",
    "sg:address":"6659 US Hwy 76",
    "sg:city":"Nichols",
    "sg:phone":"+1 843 392 3500",
    "sg:postcode":"29581",
    "sg:province":"SC",
    "sg:tags":[
        "farm",
        "corn",
        "soybean",
        "tobacco"
    ],
    "wof:name":"Sally Loveland",
    "wof:placetype":"venue"
},
  "geometry": {"coordinates":[-79.04450300000001,34.254203],"type":"Point"}
}