{
  "type": "Feature",
  "properties": {
    "addr:full":"1230 Pendleton St Columbia SC 29201",
    "addr:housenumber":"1230",
    "addr:postcode":"29201",
    "addr:street":"Pendleton St",
    "iso:country":"US",
    "sg:address":"1230 Pendleton St",
    "sg:city":"Columbia",
    "sg:classifiers":[
        {
            "category":"Communications",
            "subcategory":"Newspaper",
            "type":"Services"
        }
    ],
    "sg:phone":"+1 803 799 9051",
    "sg:postcode":"29201",
    "sg:province":"SC",
    "sg:tags":[
        "print",
        "medium"
    ],
    "wof:name":"Post & Courier Charleston",
    "wof:placetype":"venue"
},
  "geometry": {"coordinates":[-81.031047,33.998677],"type":"Point"}
}