{
  "type": "Feature",
  "properties": {
    "addr:full":"100 Fox Hollow Ct Simpsonville SC 29680",
    "addr:housenumber":"100",
    "addr:postcode":"29680",
    "addr:street":"Fox Hollow Ct",
    "iso:country":"US",
    "sg:address":"100 Fox Hollow Ct",
    "sg:city":"Simpsonville",
    "sg:classifiers":[
        {
            "category":"Real Estate",
            "subcategory":"Real Estate Agent",
            "type":"Services"
        }
    ],
    "sg:phone":"+1 864 967 0837",
    "sg:postcode":"29680",
    "sg:province":"SC",
    "wof:name":"Scott Property Management LLC",
    "wof:placetype":"venue"
},
  "geometry": {"coordinates":[-82.261758,34.71301],"type":"Point"}
}