{
  "type": "Feature",
  "properties": {
    "iso:country":"US",
    "sg:address":"119 Dares Ferry Rd",
    "sg:city":"Spartanburg",
    "sg:classifiers":[
        {
            "category":"Farming",
            "subcategory":"Farm",
            "type":"Manufacturing & Wholesale Goods"
        }
    ],
    "sg:phone":"+1 864 583 5950",
    "sg:postcode":"29302",
    "sg:province":"SC",
    "sg:tags":[
        "crop",
        "general"
    ],
    "wof:name":"Lancaster Farm LLC",
    "wof:placetype":"venue"
},
  "geometry": {"coordinates":[-81.845952,34.933656],"type":"Point"}
}