{
  "type": "Feature",
  "properties": {
    "iso:country":"US",
    "sg:address":"1510 N Main St",
    "sg:city":"Sumter",
    "sg:classifiers":[
        {
            "category":"Retail",
            "subcategory":"Auto Repair",
            "type":"Services"
        }
    ],
    "sg:phone":"+1 803 773 9499",
    "sg:postcode":"29153",
    "sg:province":"SC",
    "sg:tags":[
        "repairing",
        "automobile"
    ],
    "wof:name":"North Main Automotive",
    "wof:placetype":"venue"
},
  "geometry": {"coordinates":[-80.340397,33.965593],"type":"Point"}
}