{
  "type": "Feature",
  "properties": {
    "iso:country":"US",
    "sg:address":"4949 Two Notch Rd Ste 201B",
    "sg:city":"Columbia",
    "sg:classifiers":[
        {
            "category":"Banks & Credit Unions",
            "subcategory":"Investment Brokerage",
            "type":"Services"
        }
    ],
    "sg:phone":"+1 803 754 2350",
    "sg:postcode":"29204",
    "sg:province":"SC",
    "sg:tags":[
        "investing"
    ],
    "wof:name":"Chase Capital Management Group",
    "wof:placetype":"venue"
},
  "geometry": {"coordinates":[-80.993622,34.042428],"type":"Point"}
}