{
  "type": "Feature",
  "properties": {
    "iso:country":"US",
    "sg:address":"763 E Main St",
    "sg:city":"Spartanburg",
    "sg:classifiers":[
        {
            "category":"Real Estate",
            "subcategory":"Real Estate Agent",
            "type":"Services"
        }
    ],
    "sg:phone":"+1 864 597 1800",
    "sg:postcode":"29302",
    "sg:province":"SC",
    "wof:name":"Len Brock Co",
    "wof:placetype":"venue"
},
  "geometry": {"coordinates":[-81.91200000000001,34.956863],"type":"Point"}
}