{
  "type": "Feature",
  "properties": {
    "addr:full":"8283 Wild Indigo Bluff North Charleston SC 29418",
    "addr:housenumber":"8283",
    "addr:postcode":"29418",
    "addr:street":"Wild Indigo Bluff",
    "iso:country":"US",
    "sg:address":"8283 Wild Indigo Bluff",
    "sg:city":"North Charleston",
    "sg:classifiers":[
        {
            "category":"Shopping",
            "subcategory":"Bicycles & Sporting Goods",
            "type":"Retail Goods"
        }
    ],
    "sg:phone":"+1 843 224 1997",
    "sg:postcode":"29418",
    "sg:province":"SC",
    "wof:name":"On The Spot Paintball",
    "wof:placetype":"venue"
},
  "geometry": {"coordinates":[-80.10837600000001,32.901047],"type":"Point"}
}