{
  "type": "Feature",
  "properties": {
    "iso:country":"US",
    "sg:address":"1316 R L Coward Rd",
    "sg:city":"Hopkins",
    "sg:classifiers":[
        {
            "category":"Home & Garden",
            "subcategory":"Garden Supply",
            "type":"Retail Goods"
        }
    ],
    "sg:phone":"+1 803 783 1928",
    "sg:postcode":"29061",
    "sg:province":"SC",
    "sg:tags":[
        "fountain",
        "display"
    ],
    "sg:website":"www.absoluteaquatics.com",
    "wof:name":"Absolute Aquatics",
    "wof:placetype":"venue"
},
  "geometry": {"coordinates":[-80.786215,33.952761],"type":"Point"}
}