{
  "type": "Feature",
  "properties": {
    "addr:full":"2421 Dutch Fork Rd Chapin SC 29036",
    "addr:housenumber":"2421",
    "addr:postcode":"29036",
    "addr:street":"Dutch Fork Rd",
    "iso:country":"US",
    "sg:address":"2421 Dutch Fork Rd",
    "sg:city":"Chapin",
    "sg:classifiers":[
        {
            "category":"Wholesale",
            "subcategory":"Machinery & Supplies",
            "type":"Manufacturing & Wholesale Goods"
        },
        {
            "category":"Home & Garden",
            "subcategory":"Garden Supply",
            "type":"Retail Goods"
        }
    ],
    "sg:phone":"+1 803 732 1782",
    "sg:postcode":"29036",
    "sg:province":"SC",
    "sg:tags":[
        "nurseryman"
    ],
    "wof:name":"Native Plants Garden Center",
    "wof:placetype":"venue"
},
  "geometry": {"coordinates":[-81.291549,34.13848],"type":"Point"}
}