{
  "type": "Feature",
  "properties": {
    "iso:country":"US",
    "sg:address":"4454 Bluffton Park Cres # 108",
    "sg:city":"Bluffton",
    "sg:classifiers":[
        {
            "category":"Communications",
            "type":"Services"
        },
        {
            "category":"Shopping",
            "subcategory":"Computers & Home Electronics",
            "type":"Retail Goods"
        }
    ],
    "sg:phone":"+1 843 706 9495",
    "sg:postcode":"29910",
    "sg:province":"SC",
    "sg:tags":[
        "sound",
        "television",
        "system",
        "equipment",
        "radio",
        "store",
        "audio-visual"
    ],
    "wof:name":"A V E/ Audio Video Experts",
    "wof:placetype":"venue"
},
  "geometry": {"coordinates":[-80.86669500000001,32.258656],"type":"Point"}
}