{
  "type": "Feature",
  "properties": {
    "iso:country":"US",
    "sg:address":"3457 Rum Gully Rd",
    "sg:city":"Islandton",
    "sg:classifiers":[
        {
            "category":"Building & Trades",
            "subcategory":"Construction",
            "type":"Services"
        }
    ],
    "sg:phone":"+1 843 866 2030",
    "sg:postcode":"29929",
    "sg:province":"SC",
    "sg:tags":[
        "water",
        "well",
        "drilling"
    ],
    "wof:name":"Johnny Martin Jr Well Drill",
    "wof:placetype":"venue"
},
  "geometry": {"coordinates":[-80.904709,32.961091],"type":"Point"}
}