{
  "type": "Feature",
  "properties": {
    "iso:country":"US",
    "sg:address":"1500 Winburn St",
    "sg:city":"Conway",
    "sg:classifiers":[
        {
            "category":"Insurance",
            "subcategory":"Insurance Agent",
            "type":"Services"
        }
    ],
    "sg:phone":"+1 843 397 7799",
    "sg:postcode":"29527",
    "sg:province":"SC",
    "wof:name":"Ing Life Of Georgia",
    "wof:placetype":"venue"
},
  "geometry": {"coordinates":[-79.105081,33.729563],"type":"Point"}
}