{
  "type": "Feature",
  "properties": {
    "addr:full":"1135 Baywater Dr West Columbia SC 29170",
    "addr:housenumber":"1135",
    "addr:postcode":"29170",
    "addr:street":"Baywater Dr",
    "iso:country":"US",
    "sg:address":"1135 Baywater Dr",
    "sg:city":"West Columbia",
    "sg:classifiers":[
        {
            "category":"Building & Trades",
            "subcategory":"Construction",
            "type":"Services"
        }
    ],
    "sg:phone":"+1 803 796 2933",
    "sg:postcode":"29170",
    "sg:province":"SC",
    "sg:tags":[
        "contractor"
    ],
    "wof:name":"Lyn-Rich Contracting Company Inc",
    "wof:placetype":"venue"
},
  "geometry": {"coordinates":[-81.0998,33.9599],"type":"Point"}
}