{
  "type": "Feature",
  "properties": {
    "iso:country":"US",
    "sg:address":"841 William Hilton Pkwy",
    "sg:city":"Hilton Head Island",
    "sg:classifiers":[
        {
            "category":"Shopping",
            "type":"Retail Goods"
        }
    ],
    "sg:phone":"+1 843 785 5075",
    "sg:postcode":"29928",
    "sg:province":"SC",
    "sg:tags":[
        "art",
        "gallery"
    ],
    "wof:name":"Endangered Arts Ltd",
    "wof:placetype":"venue"
},
  "geometry": {"coordinates":[-80.732305,32.174462],"type":"Point"}
}