{
  "type": "Feature",
  "properties": {
    "iso:country":"US",
    "sg:address":"236 Drawdebil Ct",
    "sg:city":"Gilbert",
    "sg:classifiers":[
        {
            "category":"Building & Trades",
            "subcategory":"Landscaping Services",
            "type":"Services"
        }
    ],
    "sg:phone":"+1 803 466 5521",
    "sg:postcode":"29054",
    "sg:province":"SC",
    "sg:tags":[
        "tree"
    ],
    "wof:name":"Complete Tree Svc",
    "wof:placetype":"venue"
},
  "geometry": {"coordinates":[-81.357366,33.928305],"type":"Point"}
}