{
  "type": "Feature",
  "properties": {
    "iso:country":"US",
    "sg:address":"228 E Main St",
    "sg:city":"Walhalla",
    "sg:classifiers":[
        {
            "category":"Recreation",
            "type":"Entertainment"
        }
    ],
    "sg:phone":"+1 864 638 2326",
    "sg:postcode":"29691",
    "sg:province":"SC",
    "sg:tags":[
        "parlor",
        "billiard"
    ],
    "wof:name":"Jim's Pool Room",
    "wof:placetype":"venue"
},
  "geometry": {"coordinates":[-83.063762,34.76461],"type":"Point"}
}