{
  "type": "Feature",
  "properties": {
    "iso:country":"US",
    "sg:address":"112 N Main St",
    "sg:city":"Greer",
    "sg:classifiers":[
        {
            "category":"Building & Trades",
            "subcategory":"Plumbing",
            "type":"Services"
        }
    ],
    "sg:phone":"+1 864 877 7277",
    "sg:postcode":"29650",
    "sg:province":"SC",
    "sg:tags":[
        "contractor"
    ],
    "wof:name":"Staggs Plumbing",
    "wof:placetype":"venue"
},
  "geometry": {"coordinates":[-82.22618900000001,34.939727],"type":"Point"}
}