{
  "type": "Feature",
  "properties": {
    "iso:country":"US",
    "sg:address":"912 Chapin Rd",
    "sg:city":"Chapin",
    "sg:classifiers":[
        {
            "category":"Home & Garden",
            "subcategory":"Building Materials",
            "type":"Retail Goods"
        }
    ],
    "sg:phone":"+1 803 256 9550",
    "sg:postcode":"29036",
    "sg:province":"SC",
    "sg:tags":[
        "mixed",
        "concrete"
    ],
    "sg:website":"www.readymixedconcrete.com",
    "wof:name":"Ready Mixed Concrete Co",
    "wof:placetype":"venue"
},
  "geometry": {"coordinates":[-81.345347,34.162485],"type":"Point"}
}