{
  "type": "Feature",
  "properties": {
    "iso:country":"US",
    "sg:address":"212 E Main St",
    "sg:city":"Rock Hill",
    "sg:classifiers":[
        {
            "category":"Shopping",
            "subcategory":"Gifts & Souvenirs",
            "type":"Retail Goods"
        }
    ],
    "sg:phone":"+1 803 327 6332",
    "sg:postcode":"29730",
    "sg:province":"SC",
    "wof:name":"Overhead Station Gift Shop",
    "wof:placetype":"venue"
},
  "geometry": {"coordinates":[-81.025735,34.924746],"type":"Point"}
}