{
  "type": "Feature",
  "properties": {
    "iso:country":"US",
    "sg:address":"2071 Great Falls Rd",
    "sg:city":"Lancaster",
    "sg:classifiers":[
        {
            "category":"Building & Trades",
            "subcategory":"Cleaning & Sanitation",
            "type":"Services"
        }
    ],
    "sg:phone":"+1 803 286 6080",
    "sg:postcode":"29720",
    "sg:province":"SC",
    "sg:tags":[
        "janitor"
    ],
    "wof:name":"L & S Janitorial Svc & Distr",
    "wof:placetype":"venue"
},
  "geometry": {"coordinates":[-80.811678,34.663522],"type":"Point"}
}