{
  "type": "Feature",
  "properties": {
    "iso:country":"US",
    "sg:address":"141 Fernwood Dr",
    "sg:city":"Spartanburg",
    "sg:classifiers":[
        {
            "category":"Shopping",
            "subcategory":"Gifts & Souvenirs",
            "type":"Retail Goods"
        }
    ],
    "sg:phone":"+1 864 582 5153",
    "sg:postcode":"29307",
    "sg:province":"SC",
    "sg:tags":[
        "shop"
    ],
    "wof:name":"Tuesday Morning 467",
    "wof:placetype":"venue"
},
  "geometry": {"coordinates":[-81.89458399999999,34.961779],"type":"Point"}
}