{
  "type": "Feature",
  "properties": {
    "iso:country":"US",
    "sg:address":"2445 Devine St",
    "sg:city":"Columbia",
    "sg:classifiers":[
        {
            "category":"Banks & Credit Unions",
            "subcategory":"Investment Brokerage",
            "type":"Services"
        }
    ],
    "sg:phone":"+1 803 799 9203",
    "sg:postcode":"29205",
    "sg:province":"SC",
    "sg:tags":[
        "consultant",
        "planning",
        "financial"
    ],
    "sg:website":"www.jewilsonadvisors.com",
    "wof:name":"J E Wilson Advisors Inc",
    "wof:placetype":"venue"
},
  "geometry": {"coordinates":[-81.009653,33.998618],"type":"Point"}
}