{
  "type": "Feature",
  "properties": {
    "iso:country":"US",
    "sg:address":"2 Bathurst Ln",
    "sg:city":"Simpsonville",
    "sg:classifiers":[
        {
            "category":"Building & Trades",
            "subcategory":"Construction",
            "type":"Services"
        }
    ],
    "sg:phone":"+1 864 962 0380",
    "sg:postcode":"29681",
    "sg:province":"SC",
    "sg:tags":[
        "house"
    ],
    "wof:name":"House Doctors",
    "wof:placetype":"venue"
},
  "geometry": {"coordinates":[-82.226979,34.787047],"type":"Point"}
}