{
  "type": "Feature",
  "properties": {
    "addr:full":"1100 Meeting St West Columbia SC 29169",
    "addr:housenumber":"1100",
    "addr:postcode":"29169",
    "addr:street":"Meeting St",
    "iso:country":"US",
    "sg:address":"1100 Meeting St",
    "sg:city":"West Columbia",
    "sg:classifiers":[
        {
            "category":"Food & Beverages",
            "subcategory":"Liquor & Beverages",
            "type":"Retail Goods"
        }
    ],
    "sg:phone":"+1 803 794 5382",
    "sg:postcode":"29169",
    "sg:province":"SC",
    "sg:tags":[
        "beer",
        "spirit",
        "wine"
    ],
    "wof:name":"J & F Package Store",
    "wof:placetype":"venue"
},
  "geometry": {"coordinates":[-81.071198,33.989799],"type":"Point"}
}