{
  "type": "Feature",
  "properties": {
    "iso:country":"US",
    "sg:address":"304 Springcrest Dr",
    "sg:city":"Fort Mill",
    "sg:classifiers":[
        {
            "category":"Shopping",
            "subcategory":"Pharmacy",
            "type":"Retail Goods"
        },
        {
            "category":"Government",
            "subcategory":"Office",
            "type":"Public Place"
        }
    ],
    "sg:phone":"+1 803 548 2851",
    "sg:postcode":"29715",
    "sg:province":"SC",
    "sg:tags":[
        "county"
    ],
    "wof:name":"Vital Care Of York County",
    "wof:placetype":"venue"
},
  "geometry": {"coordinates":[-80.960415,35.021767],"type":"Point"}
}