{
  "type": "Feature",
  "properties": {
    "iso:country":"US",
    "sg:address":"8 First Baptist Church Rd",
    "sg:city":"Piedmont",
    "sg:classifiers":[
        {
            "category":"Organizations",
            "subcategory":"Religious Organization",
            "type":"Services"
        }
    ],
    "sg:phone":"+1 864 845 7801",
    "sg:postcode":"29673",
    "sg:province":"SC",
    "sg:tags":[
        "church"
    ],
    "wof:name":"First Baptist Church",
    "wof:placetype":"venue"
},
  "geometry": {"coordinates":[-82.456518,34.706057],"type":"Point"}
}