{
  "type": "Feature",
  "properties": {
    "iso:country":"US",
    "sg:address":"1200 Woodruff Rd",
    "sg:city":"Greenville",
    "sg:classifiers":[
        {
            "category":"Insurance",
            "subcategory":"Insurance Agent",
            "type":"Services"
        }
    ],
    "sg:phone":"+1 864 627 3119",
    "sg:postcode":"29607",
    "sg:province":"SC",
    "wof:name":"Carolina Insurance Advisors",
    "wof:placetype":"venue"
},
  "geometry": {"coordinates":[-82.297354,34.82599],"type":"Point"}
}