{
  "type": "Feature",
  "properties": {
    "iso:country":"US",
    "sg:address":"498 Garlington Rd",
    "sg:city":"Greenville",
    "sg:classifiers":[
        {
            "category":"Personal",
            "subcategory":"Beauty Salon",
            "type":"Services"
        }
    ],
    "sg:phone":"+1 864 329 9989",
    "sg:postcode":"29615",
    "sg:province":"SC",
    "wof:name":"Studio M Inc",
    "wof:placetype":"venue"
},
  "geometry": {"coordinates":[-82.287886,34.835245],"type":"Point"}
}