{
  "type": "Feature",
  "properties": {
    "iso:country":"US",
    "sg:address":"1020 W Dekalb St",
    "sg:city":"Camden",
    "sg:classifiers":[
        {
            "category":"Retail",
            "subcategory":"Auto Repair",
            "type":"Services"
        }
    ],
    "sg:phone":"+1 803 432 7233",
    "sg:postcode":"29020",
    "sg:province":"SC",
    "sg:tags":[
        "repairing",
        "automobile"
    ],
    "wof:name":"J P Automotive",
    "wof:placetype":"venue"
},
  "geometry": {"coordinates":[-80.615826,34.245819],"type":"Point"}
}