{
  "type": "Feature",
  "properties": {
    "iso:country":"US",
    "sg:address":"120 Franklin St",
    "sg:city":"Walterboro",
    "sg:classifiers":[
        {
            "category":"Building & Trades",
            "subcategory":"Construction",
            "type":"Services"
        }
    ],
    "sg:phone":"+1 843 893 2584",
    "sg:postcode":"29488",
    "sg:province":"SC",
    "sg:tags":[
        "contractor"
    ],
    "wof:name":"Polites Masonry",
    "wof:placetype":"venue"
},
  "geometry": {"coordinates":[-80.63516199999999,32.882897],"type":"Point"}
}