{
  "type": "Feature",
  "properties": {
    "iso:country":"US",
    "sg:address":"407 Paradise Pt",
    "sg:city":"Abbeville",
    "sg:classifiers":[
        {
            "category":"Manufacturing",
            "subcategory":"Tools & Machinery",
            "type":"Manufacturing & Wholesale Goods"
        }
    ],
    "sg:phone":"+1 864 446 8929",
    "sg:postcode":"29620",
    "sg:province":"SC",
    "sg:tags":[
        "packaging",
        "mfg"
    ],
    "wof:name":"Computer Engraving Inc",
    "wof:placetype":"venue"
},
  "geometry": {"coordinates":[-82.596159,34.262343],"type":"Point"}
}