{
  "type": "Feature",
  "properties": {
    "addr:full":"2333 Augusta Rd West Columbia SC 29169",
    "addr:housenumber":"2333",
    "addr:postcode":"29169",
    "addr:street":"Augusta Rd",
    "iso:country":"US",
    "sg:address":"2333 Augusta Rd",
    "sg:city":"West Columbia",
    "sg:classifiers":[
        {
            "category":"Cinema",
            "subcategory":"Movie Rental",
            "type":"Entertainment"
        }
    ],
    "sg:phone":"+1 803 791 4222",
    "sg:postcode":"29169",
    "sg:province":"SC",
    "sg:tags":[
        "game",
        "video"
    ],
    "sg:website":"www.gamestop.com",
    "wof:name":"Gamestop",
    "wof:placetype":"venue"
},
  "geometry": {"coordinates":[-81.097273,33.98304],"type":"Point"}
}