{
  "type": "Feature",
  "properties": {
    "iso:country":"US",
    "sg:address":"258 Old Reservoir Rd",
    "sg:city":"Winnsboro",
    "sg:classifiers":[
        {
            "category":"Building & Trades",
            "subcategory":"Construction",
            "type":"Services"
        }
    ],
    "sg:phone":"+1 803 635 7695",
    "sg:postcode":"29180",
    "sg:province":"SC",
    "sg:tags":[
        "house"
    ],
    "wof:name":"Roseborough Builders LLC",
    "wof:placetype":"venue"
},
  "geometry": {"coordinates":[-81.133093,34.337168],"type":"Point"}
}