{
  "type": "Feature",
  "properties": {
    "iso:country":"US",
    "sg:address":"104 E Church St",
    "sg:city":"Bishopville",
    "sg:classifiers":[
        {
            "category":"Utilities",
            "subcategory":"Mobile Phone",
            "type":"Services"
        }
    ],
    "sg:phone":"+1 803 428 4327",
    "sg:postcode":"29010",
    "sg:province":"SC",
    "sg:tags":[
        "telephone",
        "cellular"
    ],
    "wof:name":"FTC Wireless",
    "wof:placetype":"venue"
},
  "geometry": {"coordinates":[-80.248565,34.218058],"type":"Point"}
}