{
  "type": "Feature",
  "properties": {
    "iso:country":"US",
    "sg:address":"1945 Drayton Rd",
    "sg:city":"Spartanburg",
    "sg:classifiers":[
        {
            "category":"Restaurant",
            "type":"Food & Drink"
        }
    ],
    "sg:phone":"+1 864 598 9730",
    "sg:postcode":"29307",
    "sg:province":"SC",
    "wof:name":"Spankys",
    "wof:placetype":"venue"
},
  "geometry": {"coordinates":[-81.912361,34.969893],"type":"Point"}
}