{
  "type": "Feature",
  "properties": {
    "iso:country":"US",
    "sg:address":"220 Sunbeam Rd",
    "sg:city":"Spartanburg",
    "sg:classifiers":[
        {
            "category":"Wholesale",
            "subcategory":"Groceries",
            "type":"Manufacturing & Wholesale Goods"
        }
    ],
    "sg:phone":"+1 864 578 6516",
    "sg:postcode":"29303",
    "sg:province":"SC",
    "sg:tags":[
        "baker"
    ],
    "sg:website":"www.saralee.com",
    "wof:name":"Sara Lee Bakery Group",
    "wof:placetype":"venue"
},
  "geometry": {"coordinates":[-81.93182899999999,35.000214],"type":"Point"}
}