{
  "type": "Feature",
  "properties": {
    "iso:country":"US",
    "sg:address":"320 S Dargan St",
    "sg:city":"Florence",
    "sg:classifiers":[
        {
            "category":"Shopping",
            "subcategory":"Used Merchandise",
            "type":"Retail Goods"
        }
    ],
    "sg:phone":"+1 843 665 7161",
    "sg:postcode":"29506",
    "sg:province":"SC",
    "sg:tags":[
        "antique"
    ],
    "wof:name":"Hamilton House Antiques",
    "wof:placetype":"venue"
},
  "geometry": {"coordinates":[-79.76561599999999,34.192339],"type":"Point"}
}