{
  "type": "Feature",
  "properties": {
    "iso:country":"US",
    "sg:address":"359 Howle Ave",
    "sg:city":"Charleston",
    "sg:classifiers":[
        {
            "category":"Building & Trades",
            "subcategory":"Construction",
            "type":"Services"
        }
    ],
    "sg:phone":"+1 843 762 9018",
    "sg:postcode":"29412",
    "sg:province":"SC",
    "sg:tags":[
        "woodworker"
    ],
    "wof:name":"Stairs Of Charleston",
    "wof:placetype":"venue"
},
  "geometry": {"coordinates":[-79.98468,32.758319],"type":"Point"}
}