{
  "type": "Feature",
  "properties": {
    "addr:full":"1401 Washington St Columbia SC 29201",
    "addr:housenumber":"1401",
    "addr:postcode":"29201",
    "addr:street":"Washington St",
    "iso:country":"US",
    "sg:address":"1401 Washington St",
    "sg:city":"Columbia",
    "sg:classifiers":[
        {
            "category":"Organizations",
            "subcategory":"Religious Organization",
            "type":"Services"
        }
    ],
    "sg:phone":"+1 803 256 2417",
    "sg:postcode":"29201",
    "sg:province":"SC",
    "wof:name":"Westerkam Diana C Rev",
    "wof:placetype":"venue"
},
  "geometry": {"coordinates":[-81.031097,34.005199],"type":"Point"}
}