{
  "type": "Feature",
  "properties": {
    "iso:country":"US",
    "sg:address":"1737 US Hwy 76",
    "sg:city":"Little Mountain",
    "sg:classifiers":[
        {
            "category":"Manufacturing",
            "subcategory":"Tools & Machinery",
            "type":"Manufacturing & Wholesale Goods"
        }
    ],
    "sg:phone":"+1 803 345 1337",
    "sg:postcode":"29075",
    "sg:province":"SC",
    "sg:tags":[
        "engine",
        "internal",
        "combustion"
    ],
    "wof:name":"Pleasurecraft Marine En",
    "wof:placetype":"venue"
},
  "geometry": {"coordinates":[-81.387167,34.194566],"type":"Point"}
}