{
  "type": "Feature",
  "properties": {
    "addr:full":"2501 Woods Rd York SC 29745",
    "addr:housenumber":"2501",
    "addr:postcode":"29745",
    "addr:street":"Woods Rd",
    "iso:country":"US",
    "sg:address":"2501 Woods Rd",
    "sg:city":"York",
    "sg:classifiers":[
        {
            "category":"Building & Trades",
            "subcategory":"Plumbing",
            "type":"Services"
        }
    ],
    "sg:phone":"+1 803 684 5472",
    "sg:postcode":"29745",
    "sg:province":"SC",
    "sg:tags":[
        "septic"
    ],
    "wof:name":"Wood's Septic Tank Cleaning",
    "wof:placetype":"venue"
},
  "geometry": {"coordinates":[-81.185749,35.043234],"type":"Point"}
}