{
  "type": "Feature",
  "properties": {
    "addr:full":"591 Rembert C Dennis Blvd Moncks Corner SC 29461",
    "addr:housenumber":"591;c",
    "addr:postcode":"29461",
    "addr:street":"Rembert;Dennis Blvd",
    "iso:country":"US",
    "sg:address":"591 Rembert C Dennis Blvd",
    "sg:city":"Moncks Corner",
    "sg:classifiers":[
        {
            "category":"Manufacturing",
            "subcategory":"Metals",
            "type":"Manufacturing & Wholesale Goods"
        }
    ],
    "sg:phone":"+1 843 761 8496",
    "sg:postcode":"29461",
    "sg:province":"SC",
    "wof:name":"Cannon Welding & Machine Shop",
    "wof:placetype":"venue"
},
  "geometry": {"coordinates":[-79.982916,33.203361],"type":"Point"}
}