{
  "type": "Feature",
  "properties": {
    "iso:country":"US",
    "sg:address":"113 King Rd",
    "sg:city":"Pelzer",
    "sg:classifiers":[
        {
            "category":"Professional",
            "subcategory":"Computer Services",
            "type":"Services"
        }
    ],
    "sg:phone":"+1 864 243 2423",
    "sg:postcode":"29669",
    "sg:province":"SC",
    "sg:tags":[
        "repair"
    ],
    "wof:name":"Affordable Computers Solutions",
    "wof:placetype":"venue"
},
  "geometry": {"coordinates":[-82.394797,34.672922],"type":"Point"}
}