{
  "type": "Feature",
  "properties": {
    "addr:full":"6954 Buckhorn Rd Ravenel SC 29470",
    "addr:housenumber":"6954",
    "addr:postcode":"29470",
    "addr:street":"Buckhorn Rd",
    "iso:country":"US",
    "sg:address":"6954 Buckhorn Rd",
    "sg:city":"Ravenel",
    "sg:classifiers":[
        {
            "category":"Building & Trades",
            "subcategory":"Electrical",
            "type":"Services"
        }
    ],
    "sg:phone":"+1 843 889 3298",
    "sg:postcode":"29470",
    "sg:province":"SC",
    "sg:tags":[
        "electrical",
        "contractor"
    ],
    "wof:name":"Gorman Electrical Inc",
    "wof:placetype":"venue"
},
  "geometry": {"coordinates":[-80.28918,32.760216],"type":"Point"}
}