{
  "type": "Feature",
  "properties": {
    "iso:country":"US",
    "sg:address":"110 W Shockley Ferry Rd",
    "sg:city":"Anderson",
    "sg:classifiers":[
        {
            "category":"Utilities",
            "subcategory":"Cable",
            "type":"Services"
        }
    ],
    "sg:phone":"+1 864 375 1488",
    "sg:postcode":"29624",
    "sg:province":"SC",
    "sg:tags":[
        "satellite",
        "carrier"
    ],
    "wof:name":"Telecom One Tone",
    "wof:placetype":"venue"
},
  "geometry": {"coordinates":[-82.650578,34.477569],"type":"Point"}
}