{
  "type": "Feature",
  "properties": {
    "addr:full":"110 Court Sq Abbeville SC 29620",
    "addr:housenumber":"110",
    "addr:postcode":"29620",
    "addr:street":"Court Sq",
    "iso:country":"US",
    "sg:address":"110 Court Sq",
    "sg:city":"Abbeville",
    "sg:classifiers":[
        {
            "category":"Building & Trades",
            "subcategory":"Construction",
            "type":"Services"
        }
    ],
    "sg:phone":"+1 864 459 4894",
    "sg:postcode":"29620",
    "sg:province":"SC",
    "sg:tags":[
        "residential",
        "builder",
        "d",
        "operative"
    ],
    "wof:name":"Bra",
    "wof:placetype":"venue"
},
  "geometry": {"coordinates":[-82.37835699999999,34.178],"type":"Point"}
}