{
  "type": "Feature",
  "properties": {
    "addr:full":"731 Sandy Ln Surfside Beach SC 29575",
    "addr:housenumber":"731",
    "addr:postcode":"29575",
    "addr:street":"Sandy Ln",
    "iso:country":"US",
    "sg:address":"731 Sandy Ln",
    "sg:city":"Surfside Beach",
    "sg:classifiers":[
        {
            "category":"Retail",
            "subcategory":"Auto Repair",
            "type":"Services"
        }
    ],
    "sg:phone":"+1 843 477 1613",
    "sg:postcode":"29575",
    "sg:province":"SC",
    "sg:tags":[
        "repairing",
        "automobile"
    ],
    "wof:name":"Legacy Automotive Corp",
    "wof:placetype":"venue"
},
  "geometry": {"coordinates":[-78.989524,33.606636],"type":"Point"}
}