{
  "type": "Feature",
  "properties": {
    "iso:country":"US",
    "sg:address":"1238 S Lenevar Dr",
    "sg:city":"Charleston",
    "sg:classifiers":[
        {
            "category":"Building & Trades",
            "subcategory":"Plumbing",
            "type":"Services"
        }
    ],
    "sg:phone":"+1 843 870 3614",
    "sg:postcode":"29407",
    "sg:province":"SC",
    "sg:tags":[
        "plumbing",
        "contractor"
    ],
    "wof:name":"Behrens Plumbing",
    "wof:placetype":"venue"
},
  "geometry": {"coordinates":[-80.000553,32.805006],"type":"Point"}
}