{
  "type": "Feature",
  "properties": {
    "iso:country":"US",
    "sg:address":"610 Blackwell Rd",
    "sg:city":"Greer",
    "sg:classifiers":[
        {
            "category":"Wholesale",
            "subcategory":"Auto Parts",
            "type":"Manufacturing & Wholesale Goods"
        }
    ],
    "sg:phone":"+1 864 801 3399",
    "sg:postcode":"29651",
    "sg:province":"SC",
    "sg:tags":[
        "automobile",
        "rebuilt"
    ],
    "wof:name":"Waddell's Used Auto Parts",
    "wof:placetype":"venue"
},
  "geometry": {"coordinates":[-82.192261,34.938426],"type":"Point"}
}