{
  "type": "Feature",
  "properties": {
    "iso:country":"US",
    "sg:address":"205 Oak Creek Cir",
    "sg:city":"Columbia",
    "sg:classifiers":[
        {
            "category":"Insurance",
            "subcategory":"Hazard Insurance",
            "type":"Services"
        }
    ],
    "sg:phone":"+1 803 736 9071",
    "sg:postcode":"29223",
    "sg:province":"SC",
    "sg:tags":[
        "bond"
    ],
    "wof:name":"Apex Bail Bonding",
    "wof:placetype":"venue"
},
  "geometry": {"coordinates":[-80.909792,34.125712],"type":"Point"}
}