{
  "type": "Feature",
  "properties": {
    "iso:country":"US",
    "sg:address":"2009 Devine St",
    "sg:city":"Columbia",
    "sg:classifiers":[
        {
            "category":"Restaurant",
            "type":"Food & Drink"
        }
    ],
    "sg:phone":"+1 803 252 8646",
    "sg:postcode":"29205",
    "sg:province":"SC",
    "sg:tags":[
        "pizza"
    ],
    "sg:website":"www.villageidiotpizza.com",
    "wof:name":"The Village Idiot",
    "wof:placetype":"venue"
},
  "geometry": {"coordinates":[-81.017239,33.99853],"type":"Point"}
}