{
  "type": "Feature",
  "properties": {
    "iso:country":"US",
    "sg:address":"810 Elm St E",
    "sg:city":"Hampton",
    "sg:classifiers":[
        {
            "category":"Food & Beverages",
            "subcategory":"Groceries & Convenience Stores",
            "type":"Retail Goods"
        }
    ],
    "sg:phone":"+1 803 943 2556",
    "sg:postcode":"29924",
    "sg:province":"SC",
    "wof:name":"Piggly Wiggly",
    "wof:placetype":"venue"
},
  "geometry": {"coordinates":[-81.095073,32.859377],"type":"Point"}
}