{
  "type": "Feature",
  "properties": {
    "iso:country":"US",
    "sg:address":"3801 Wannamaker Rd",
    "sg:city":"Nichols",
    "sg:phone":"+1 843 392 4830",
    "sg:postcode":"29581",
    "sg:province":"SC",
    "sg:tags":[
        "farm",
        "corn",
        "wheat",
        "soybean"
    ],
    "wof:name":"Henry Drew",
    "wof:placetype":"venue"
},
  "geometry": {"coordinates":[-79.06956,34.196572],"type":"Point"}
}