{
  "type": "Feature",
  "properties": {
    "iso:country":"US",
    "sg:address":"2611 River Dr",
    "sg:city":"Columbia",
    "sg:classifiers":[
        {
            "category":"Social Services",
            "type":"Services"
        }
    ],
    "sg:phone":"+1 803 255 0999",
    "sg:postcode":"29201",
    "sg:province":"SC",
    "sg:tags":[
        "counseling"
    ],
    "wof:name":"Susan Connolly",
    "wof:placetype":"venue"
},
  "geometry": {"coordinates":[-81.041901,34.020131],"type":"Point"}
}