{
  "type": "Feature",
  "properties": {
    "iso:country":"US",
    "sg:address":"309 N Dargan St",
    "sg:city":"Florence",
    "sg:classifiers":[
        {
            "category":"Personal",
            "subcategory":"Barber",
            "type":"Services"
        }
    ],
    "sg:phone":"+1 843 679 5454",
    "sg:postcode":"29506",
    "sg:province":"SC",
    "wof:name":"Williamson's Barber Shop",
    "wof:placetype":"venue"
},
  "geometry": {"coordinates":[-79.766277,34.201938],"type":"Point"}
}