{
  "type": "Feature",
  "properties": {
    "addr:full":"609 E Main St Dillon SC 29536",
    "addr:housenumber":"609",
    "addr:postcode":"29536",
    "addr:street":"E Main St",
    "iso:country":"US",
    "sg:address":"609 E Main St",
    "sg:city":"Dillon",
    "sg:classifiers":[
        {
            "category":"Wholesale",
            "subcategory":"Drugs",
            "type":"Manufacturing & Wholesale Goods"
        }
    ],
    "sg:phone":"+1 843 774 5107",
    "sg:postcode":"29536",
    "sg:province":"SC",
    "sg:tags":[
        "cosmetic"
    ],
    "wof:name":"Annette 2 Cosmetiques",
    "wof:placetype":"venue"
},
  "geometry": {"coordinates":[-79.366861,34.414467],"type":"Point"}
}