{
  "type": "Feature",
  "properties": {
    "iso:country":"US",
    "sg:address":"419 W Main St",
    "sg:city":"Moncks Corner",
    "sg:classifiers":[
        {
            "category":"Organizations",
            "subcategory":"Religious Organization",
            "type":"Services"
        }
    ],
    "sg:phone":"+1 843 761 8469",
    "sg:postcode":"29461",
    "sg:province":"SC",
    "sg:tags":[
        "church"
    ],
    "wof:name":"First Presbyterian Church",
    "wof:placetype":"venue"
},
  "geometry": {"coordinates":[-80.03084200000001,33.201685],"type":"Point"}
}