{
  "type": "Feature",
  "properties": {
    "addr:full":"4035 Sunset Blvd Lexington SC 29073",
    "addr:housenumber":"4035",
    "addr:postcode":"29073",
    "addr:street":"Sunset Blvd",
    "iso:country":"US",
    "sg:address":"4035 Sunset Blvd",
    "sg:city":"Lexington",
    "sg:classifiers":[
        {
            "category":"Food & Beverages",
            "subcategory":"Groceries & Convenience Stores",
            "type":"Retail Goods"
        }
    ],
    "sg:phone":"+1 803 794 2712",
    "sg:postcode":"29073",
    "sg:province":"SC",
    "wof:name":"Cromer Road Amoco",
    "wof:placetype":"venue"
},
  "geometry": {"coordinates":[-81.146202,34.008801],"type":"Point"}
}