{
  "type": "Feature",
  "properties": {
    "iso:country":"US",
    "sg:address":"114 Main St",
    "sg:city":"Leesville",
    "sg:classifiers":[
        {
            "category":"Shopping",
            "subcategory":"Gifts & Souvenirs",
            "type":"Retail Goods"
        }
    ],
    "sg:phone":"+1 803 532 3016",
    "sg:postcode":"29070",
    "sg:province":"SC",
    "sg:tags":[
        "shop"
    ],
    "wof:name":"Attic",
    "wof:placetype":"venue"
},
  "geometry": {"coordinates":[-81.511887,33.917051],"type":"Point"}
}