{
  "type": "Feature",
  "properties": {
    "iso:country":"US",
    "sg:address":"5495 Sunset Blvd",
    "sg:city":"Lexington",
    "sg:classifiers":[
        {
            "category":"Personal",
            "subcategory":"Beauty Salon",
            "type":"Services"
        }
    ],
    "sg:phone":"+1 803 356 7179",
    "sg:postcode":"29072",
    "sg:province":"SC",
    "sg:tags":[
        "manicuring"
    ],
    "wof:name":"Today's Nail's",
    "wof:placetype":"venue"
},
  "geometry": {"coordinates":[-81.21911,33.998094],"type":"Point"}
}