{
  "type": "Feature",
  "properties": {
    "addr:full":"628 Chestnut Rd Myrtle Beach SC 29572",
    "addr:housenumber":"628",
    "addr:postcode":"29572",
    "addr:street":"Chestnut Rd",
    "iso:country":"US",
    "sg:address":"628 Chestnut Rd",
    "sg:city":"Myrtle Beach",
    "sg:classifiers":[
        {
            "category":"Health Services",
            "subcategory":"Chiropractor",
            "type":"Services"
        }
    ],
    "sg:phone":"+1 843 692 0900",
    "sg:postcode":"29572",
    "sg:province":"SC",
    "wof:name":"Robert Guardino DC",
    "wof:placetype":"venue"
},
  "geometry": {"coordinates":[-78.783157,33.776759],"type":"Point"}
}