{
  "type": "Feature",
  "properties": {
    "addr:full":"104 Broad St Charleston SC 29401",
    "addr:housenumber":"104",
    "addr:postcode":"29401",
    "addr:street":"Broad St",
    "iso:country":"US",
    "sg:address":"104 Broad St",
    "sg:city":"Charleston",
    "sg:classifiers":[
        {
            "category":"Professional",
            "subcategory":"Lawyer & Legal Services",
            "type":"Services"
        }
    ],
    "sg:phone":"+1 843 577 7210",
    "sg:postcode":"29401",
    "sg:province":"SC",
    "sg:tags":[
        "attorney"
    ],
    "wof:name":"Joseph S Mendelsohn",
    "wof:placetype":"venue"
},
  "geometry": {"coordinates":[-79.933251,32.776315],"type":"Point"}
}