{
  "type": "Feature",
  "properties": {
    "iso:country":"US",
    "sg:address":"5935 Hemlock Rd",
    "sg:city":"Galivants Ferry",
    "sg:classifiers":[
        {
            "category":"Retail",
            "subcategory":"Repair Shop",
            "type":"Services"
        }
    ],
    "sg:phone":"+1 843 358 8863",
    "sg:postcode":"29544",
    "sg:province":"SC",
    "sg:tags":[
        "repairing",
        "piano",
        "refinishing"
    ],
    "wof:name":"Henson's Piano Svc",
    "wof:placetype":"venue"
},
  "geometry": {"coordinates":[-79.19050300000001,33.91339],"type":"Point"}
}