{
  "type": "Feature",
  "properties": {
    "iso:country":"US",
    "sg:address":"4799 Wilkinsville Hwy",
    "sg:city":"Gaffney",
    "sg:classifiers":[
        {
            "category":"Organizations",
            "subcategory":"Religious Organization",
            "type":"Services"
        }
    ],
    "sg:phone":"+1 864 487 4888",
    "sg:postcode":"29340",
    "sg:province":"SC",
    "sg:tags":[
        "church"
    ],
    "wof:name":"Mt Tabor Baptist Church",
    "wof:placetype":"venue"
},
  "geometry": {"coordinates":[-81.505746,34.949671],"type":"Point"}
}