{
  "type": "Feature",
  "properties": {
    "iso:country":"US",
    "sg:address":"2142 Adams Cir",
    "sg:city":"Little River",
    "sg:classifiers":[
        {
            "category":"Home & Garden",
            "subcategory":"Building Materials",
            "type":"Retail Goods"
        }
    ],
    "sg:phone":"+1 843 280 8684",
    "sg:postcode":"29566",
    "sg:province":"SC",
    "sg:tags":[
        "door"
    ],
    "wof:name":"Garage Doors Of Wilkes",
    "wof:placetype":"venue"
},
  "geometry": {"coordinates":[-78.593396,33.882671],"type":"Point"}
}