{
  "type": "Feature",
  "properties": {
    "iso:country":"US",
    "sg:address":"306 Laurel Ave",
    "sg:city":"Goose Creek",
    "sg:classifiers":[
        {
            "category":"Manufacturing",
            "subcategory":"Tools & Machinery",
            "type":"Manufacturing & Wholesale Goods"
        }
    ],
    "sg:phone":"+1 843 797 7941",
    "sg:postcode":"29445",
    "sg:province":"SC",
    "sg:tags":[
        "mfg"
    ],
    "wof:name":"Out of Norm",
    "wof:placetype":"venue"
},
  "geometry": {"coordinates":[-80.050896,32.998575],"type":"Point"}
}