{
  "type": "Feature",
  "properties": {
    "addr:full":"1201 Main St Columbia SC 29201",
    "addr:housenumber":"1201",
    "addr:postcode":"29201",
    "addr:street":"Main St",
    "iso:country":"US",
    "sg:address":"1201 Main St",
    "sg:city":"Columbia",
    "sg:classifiers":[
        {
            "category":"Real Estate",
            "subcategory":"Architect",
            "type":"Services"
        }
    ],
    "sg:phone":"+1 803 256 0000",
    "sg:postcode":"29201",
    "sg:province":"SC",
    "sg:website":"www.gmka.com",
    "wof:name":"Architectural Div",
    "wof:placetype":"venue"
},
  "geometry": {"coordinates":[-81.034098,34.002621],"type":"Point"}
}