{
  "type": "Feature",
  "properties": {
    "addr:full":"3 Chinaberry Cir Hilton Head Isle SC 29926",
    "addr:housenumber":"3",
    "addr:postcode":"29926",
    "addr:street":"Chinaberry Cir",
    "iso:country":"US",
    "sg:address":"3 Chinaberry Cir",
    "sg:city":"Hilton Head Isle",
    "sg:classifiers":[
        {
            "category":"Building & Trades",
            "subcategory":"Electrical",
            "type":"Services"
        }
    ],
    "sg:phone":"+1 843 681 9536",
    "sg:postcode":"29926",
    "sg:province":"SC",
    "sg:tags":[
        "electrical",
        "electric",
        "contractor"
    ],
    "wof:name":"Tolliver Electric Inc",
    "wof:placetype":"venue"
},
  "geometry": {"coordinates":[-80.744292,32.230517],"type":"Point"}
}