{
  "type": "Feature",
  "properties": {
    "addr:full":"3455 Maybank Hwy Johns Island SC 29455",
    "addr:housenumber":"3455",
    "addr:postcode":"29455",
    "addr:street":"Maybank Hwy",
    "iso:country":"US",
    "sg:address":"3455 Maybank Hwy",
    "sg:city":"Johns Island",
    "sg:classifiers":[
        {
            "category":"Wholesale",
            "subcategory":"Farm Supplies",
            "type":"Manufacturing & Wholesale Goods"
        },
        {
            "category":"Shopping",
            "type":"Retail Goods"
        }
    ],
    "sg:phone":"+1 843 559 0102",
    "sg:postcode":"29455",
    "sg:province":"SC",
    "sg:tags":[
        "feed",
        "merchandise"
    ],
    "wof:name":"Cordray's Grocery & Feed",
    "wof:placetype":"venue"
},
  "geometry": {"coordinates":[-80.07261099999999,32.725484],"type":"Point"}
}