{
  "type": "Feature",
  "properties": {
    "addr:full":"240 Stoneridge Dr Columbia SC 29210",
    "addr:housenumber":"240",
    "addr:postcode":"29210",
    "addr:street":"Stoneridge Dr",
    "iso:country":"US",
    "sg:address":"240 Stoneridge Dr",
    "sg:city":"Columbia",
    "sg:classifiers":[
        {
            "category":"Manufacturing",
            "subcategory":"Printing",
            "type":"Manufacturing & Wholesale Goods"
        }
    ],
    "sg:phone":"+1 803 771 0018",
    "sg:postcode":"29210",
    "sg:province":"SC",
    "sg:tags":[
        "news",
        "publication"
    ],
    "wof:name":"Sports Media Group LLC",
    "wof:placetype":"venue"
},
  "geometry": {"coordinates":[-81.08102100000001,34.015977],"type":"Point"}
}