{
  "type": "Feature",
  "properties": {
    "iso:country":"US",
    "sg:address":"631 Upper Valley Falls Rd",
    "sg:city":"Spartanburg",
    "sg:classifiers":[
        {
            "category":"Building & Trades",
            "subcategory":"Construction",
            "type":"Services"
        }
    ],
    "sg:phone":"+1 864 599 5505",
    "sg:postcode":"29316",
    "sg:province":"SC",
    "sg:tags":[
        "home",
        "builder"
    ],
    "wof:name":"P Th Stonewood Crossing Constr",
    "wof:placetype":"venue"
},
  "geometry": {"coordinates":[-81.988691,35.006465],"type":"Point"}
}