{
  "type": "Feature",
  "properties": {
    "addr:full":"213 Corley Mill Rd Lexington SC 29072",
    "addr:housenumber":"213",
    "addr:postcode":"29072",
    "addr:street":"Corley Mill Rd",
    "iso:country":"US",
    "sg:address":"213 Corley Mill Rd",
    "sg:city":"Lexington",
    "sg:classifiers":[
        {
            "category":"Professional",
            "subcategory":"Computer Services",
            "type":"Services"
        }
    ],
    "sg:phone":"+1 803 957 3145",
    "sg:postcode":"29072",
    "sg:province":"SC",
    "sg:tags":[
        "repair"
    ],
    "sg:website":"www.ob-one.com",
    "wof:name":"O B One Communications",
    "wof:placetype":"venue"
},
  "geometry": {"coordinates":[-81.153801,34.019299],"type":"Point"}
}