{
  "type": "Feature",
  "properties": {
    "iso:country":"US",
    "sg:address":"10597 Dorchester Rd",
    "sg:city":"Summerville",
    "sg:classifiers":[
        {
            "category":"Insurance",
            "subcategory":"Insurance Agent",
            "type":"Services"
        }
    ],
    "sg:phone":"+1 843 871 9700",
    "sg:postcode":"29485",
    "sg:province":"SC",
    "wof:name":"State Farm Insurance",
    "wof:placetype":"venue"
},
  "geometry": {"coordinates":[-80.198323,32.966955],"type":"Point"}
}