{
  "type": "Feature",
  "properties": {
    "addr:full":"177 Wingo Spartanburg SC 29303",
    "addr:housenumber":"177",
    "addr:postcode":"29303",
    "addr:street":"Wingo",
    "iso:country":"US",
    "sg:address":"177 Wingo",
    "sg:city":"Spartanburg",
    "sg:classifiers":[
        {
            "category":"Organizations",
            "subcategory":"Religious Organization",
            "type":"Services"
        }
    ],
    "sg:phone":"+1 864 583 7252",
    "sg:postcode":"29303",
    "sg:province":"SC",
    "sg:tags":[
        "church"
    ],
    "wof:name":"Hope Freewill Baptist Church",
    "wof:placetype":"venue"
},
  "geometry": {"coordinates":[-82.052229,34.997976],"type":"Point"}
}