{
  "type": "Feature",
  "properties": {
    "iso:country":"US",
    "sg:address":"109 Century Oaks Dr",
    "sg:city":"Easley",
    "sg:classifiers":[
        {
            "category":"Building & Trades",
            "subcategory":"Construction",
            "type":"Services"
        }
    ],
    "sg:phone":"+1 864 414 5364",
    "sg:postcode":"29642",
    "sg:province":"SC",
    "sg:tags":[
        "handyman"
    ],
    "wof:name":"A Job Well Done Handyman Svc",
    "wof:placetype":"venue"
},
  "geometry": {"coordinates":[-82.517505,34.769636],"type":"Point"}
}