{
  "type": "Feature",
  "properties": {
    "addr:full":"526 Cheraw St Bennettsville SC 29512",
    "addr:housenumber":"526",
    "addr:postcode":"29512",
    "addr:street":"Cheraw St",
    "iso:country":"US",
    "sg:address":"526 Cheraw St",
    "sg:city":"Bennettsville",
    "sg:classifiers":[
        {
            "category":"Food & Beverages",
            "subcategory":"Liquor & Beverages",
            "type":"Retail Goods"
        }
    ],
    "sg:phone":"+1 843 479 7805",
    "sg:postcode":"29512",
    "sg:province":"SC",
    "wof:name":"Thomas Liquor Store",
    "wof:placetype":"venue"
},
  "geometry": {"coordinates":[-79.689729,34.622503],"type":"Point"}
}