{
  "type": "Feature",
  "properties": {
    "iso:country":"US",
    "sg:address":"825 S 5th St",
    "sg:city":"Hartsville",
    "sg:classifiers":[
        {
            "category":"Banks & Credit Unions",
            "subcategory":"Bank",
            "type":"Services"
        }
    ],
    "sg:phone":"+1 843 383 1931",
    "sg:postcode":"29550",
    "sg:province":"SC",
    "sg:tags":[
        "national",
        "commercial"
    ],
    "wof:name":"Bank Of America",
    "wof:placetype":"venue"
},
  "geometry": {"coordinates":[-80.06899900000001,34.354738],"type":"Point"}
}