{
  "type": "Feature",
  "properties": {
    "iso:country":"US",
    "sg:address":"1082 Courtyard Dr",
    "sg:city":"Conway",
    "sg:classifiers":[
        {
            "category":"Building & Trades",
            "subcategory":"Electrical",
            "type":"Services"
        }
    ],
    "sg:phone":"+1 843 488 3812",
    "sg:postcode":"29526",
    "sg:province":"SC",
    "sg:tags":[
        "electric",
        "contractor"
    ],
    "wof:name":"Wayne's Electric Svc",
    "wof:placetype":"venue"
},
  "geometry": {"coordinates":[-79.011156,33.761824],"type":"Point"}
}