{
  "type": "Feature",
  "properties": {
    "iso:country":"US",
    "sg:address":"1859 Summerville Ave",
    "sg:city":"Charleston",
    "sg:classifiers":[
        {
            "category":"Building & Trades",
            "subcategory":"Construction",
            "type":"Services"
        }
    ],
    "sg:phone":"+1 843 554 2065",
    "sg:postcode":"29405",
    "sg:province":"SC",
    "sg:tags":[
        "general",
        "contractor"
    ],
    "sg:website":"www.atlanticbuilders.com",
    "wof:name":"Atlantic Builders Inc",
    "wof:placetype":"venue"
},
  "geometry": {"coordinates":[-79.954368,32.829212],"type":"Point"}
}