{
  "type": "Feature",
  "properties": {
    "iso:country":"US",
    "sg:address":"108 Mendenhall Rd",
    "sg:city":"Newberry",
    "sg:classifiers":[
        {
            "category":"Building & Trades",
            "subcategory":"Landscaping Services",
            "type":"Services"
        }
    ],
    "sg:phone":"+1 803 276 6642",
    "sg:postcode":"29108",
    "sg:province":"SC",
    "sg:tags":[
        "landscape",
        "contractor"
    ],
    "wof:name":"Newberry Lawn Care",
    "wof:placetype":"venue"
},
  "geometry": {"coordinates":[-81.613339,34.230864],"type":"Point"}
}