{
  "type": "Feature",
  "properties": {
    "iso:country":"US",
    "sg:address":"5225 W Montague Ave",
    "sg:city":"North Charleston",
    "sg:classifiers":[
        {
            "category":"Real Estate",
            "subcategory":"Real Estate Operator",
            "type":"Services"
        }
    ],
    "sg:phone":"+1 843 552 5730",
    "sg:postcode":"29418",
    "sg:province":"SC",
    "sg:tags":[
        "mobile",
        "home",
        "site"
    ],
    "wof:name":"Trailmore Park Number Two",
    "wof:placetype":"venue"
},
  "geometry": {"coordinates":[-80.042019,32.855371],"type":"Point"}
}