{
  "type": "Feature",
  "properties": {
    "iso:country":"US",
    "sg:address":"805 W Greenwood St",
    "sg:city":"Abbeville",
    "sg:classifiers":[
        {
            "category":"Insurance",
            "subcategory":"Insurance Agent",
            "type":"Services"
        }
    ],
    "sg:phone":"+1 864 366 4706",
    "sg:postcode":"29620",
    "sg:province":"SC",
    "wof:name":"Nationwide Insurance",
    "wof:placetype":"venue"
},
  "geometry": {"coordinates":[-82.38188599999999,34.164249],"type":"Point"}
}