{
  "type": "Feature",
  "properties": {
    "iso:country":"US",
    "sg:address":"14 Manly St",
    "sg:city":"Greenville",
    "sg:classifiers":[
        {
            "category":"Insurance",
            "subcategory":"Insurance Agent",
            "type":"Services"
        }
    ],
    "sg:phone":"+1 864 370 0706",
    "sg:postcode":"29601",
    "sg:province":"SC",
    "wof:name":"Phoenix Life Insurance Co",
    "wof:placetype":"venue"
},
  "geometry": {"coordinates":[-82.390467,34.848441],"type":"Point"}
}