{
  "type": "Feature",
  "properties": {
    "addr:full":"123 Washington St Abbeville SC 29620",
    "addr:housenumber":"123",
    "addr:postcode":"29620",
    "addr:street":"Washington St",
    "iso:country":"US",
    "sg:address":"123 Washington St",
    "sg:city":"Abbeville",
    "sg:classifiers":[
        {
            "category":"Organizations",
            "subcategory":"Non-profit Organization",
            "type":"Services"
        }
    ],
    "sg:phone":"+1 864 366 9494",
    "sg:postcode":"29620",
    "sg:province":"SC",
    "sg:tags":[
        "human"
    ],
    "wof:name":"United Way",
    "wof:placetype":"venue"
},
  "geometry": {"coordinates":[-82.379105,34.178171],"type":"Point"}
}