{
  "type": "Feature",
  "properties": {
    "iso:country":"US",
    "sg:address":"503 Pinewood Rd",
    "sg:city":"Myrtle Beach",
    "sg:classifiers":[
        {
            "category":"Professional",
            "subcategory":"Advertising",
            "type":"Services"
        }
    ],
    "sg:phone":"+1 843 449 3259",
    "sg:postcode":"29577",
    "sg:province":"SC",
    "sg:tags":[
        "counselor"
    ],
    "wof:name":"Atb Graphics",
    "wof:placetype":"venue"
},
  "geometry": {"coordinates":[-78.845074,33.727924],"type":"Point"}
}