{
  "type": "Feature",
  "properties": {
    "iso:country":"US",
    "sg:address":"3315 Broad River Rd",
    "sg:city":"Columbia",
    "sg:classifiers":[
        {
            "category":"Restaurant",
            "type":"Food & Drink"
        }
    ],
    "sg:menulink":"http://www.allmenus.com/sc/dutch-fork/219384-larrys-giant-subs/menu/",
    "sg:phone":"+1 803 750 2300",
    "sg:postcode":"29210",
    "sg:province":"SC",
    "sg:tags":[
        "wrap",
        "american",
        "sandwich"
    ],
    "wof:name":"Larry's Giant Subs",
    "wof:placetype":"venue"
},
  "geometry": {"coordinates":[-81.108824,34.053098],"type":"Point"}
}