{
  "type": "Feature",
  "properties": {
    "iso:country":"US",
    "sg:address":"219 W Whitner St",
    "sg:city":"Anderson",
    "sg:classifiers":[
        {
            "category":"Organizations",
            "subcategory":"Non-profit Organization",
            "type":"Services"
        }
    ],
    "sg:phone":"+1 864 226 0009",
    "sg:postcode":"29624",
    "sg:province":"SC",
    "sg:tags":[
        "human"
    ],
    "wof:name":"Haven Of Rest Ministries Inc",
    "wof:placetype":"venue"
},
  "geometry": {"coordinates":[-82.653086,34.503008],"type":"Point"}
}