{
  "type": "Feature",
  "properties": {
    "iso:country":"US",
    "sg:address":"2955 Cains Mill Rd",
    "sg:city":"Sumter",
    "sg:classifiers":[
        {
            "category":"Manufacturing",
            "subcategory":"Tools & Machinery",
            "type":"Manufacturing & Wholesale Goods"
        }
    ],
    "sg:phone":"+1 803 481 3535",
    "sg:postcode":"29154",
    "sg:province":"SC",
    "sg:tags":[
        "machine",
        "shop"
    ],
    "wof:name":"C J's Machine Shop",
    "wof:placetype":"venue"
},
  "geometry": {"coordinates":[-80.40826,33.861454],"type":"Point"}
}