{
  "type": "Feature",
  "properties": {
    "iso:country":"US",
    "sg:address":"1727 Charleston Hwy",
    "sg:city":"Orangeburg",
    "sg:classifiers":[
        {
            "category":"Retail",
            "subcategory":"Auto Repair",
            "type":"Services"
        }
    ],
    "sg:phone":"+1 803 536 2626",
    "sg:postcode":"29115",
    "sg:province":"SC",
    "sg:tags":[
        "body",
        "automobile",
        "painting"
    ],
    "wof:name":"Stillinger Brothers Body Shop",
    "wof:placetype":"venue"
},
  "geometry": {"coordinates":[-80.845966,33.470957],"type":"Point"}
}