{
  "type": "Feature",
  "properties": {
    "iso:country":"US",
    "sg:address":"300 Alliance Rd",
    "sg:city":"Lexington",
    "sg:classifiers":[
        {
            "category":"Organizations",
            "subcategory":"Religious Organization",
            "type":"Services"
        }
    ],
    "sg:phone":"+1 803 356 2803",
    "sg:postcode":"29073",
    "sg:province":"SC",
    "sg:tags":[
        "church"
    ],
    "sg:website":"www.gracebiblealliance.org",
    "wof:name":"Grace Bible Alliance Church",
    "wof:placetype":"venue"
},
  "geometry": {"coordinates":[-81.197226,33.969857],"type":"Point"}
}