{
  "type": "Feature",
  "properties": {
    "iso:country":"US",
    "sg:address":"1021 Bankton Cir",
    "sg:city":"Hanahan",
    "sg:classifiers":[
        {
            "category":"Shopping",
            "subcategory":"Computers & Home Electronics",
            "type":"Retail Goods"
        }
    ],
    "sg:phone":"+1 843 744 5002",
    "sg:postcode":"29410",
    "sg:province":"SC",
    "sg:tags":[
        "equipment",
        "dealer"
    ],
    "sg:website":"www.data-line.com",
    "wof:name":"Dataline Inc",
    "wof:placetype":"venue"
},
  "geometry": {"coordinates":[-79.988522,32.913873],"type":"Point"}
}