{
  "type": "Feature",
  "properties": {
    "iso:country":"US",
    "sg:address":"355 Old Greenville Rd",
    "sg:city":"Spartanburg",
    "sg:classifiers":[
        {
            "category":"Restaurant",
            "type":"Food & Drink"
        }
    ],
    "sg:phone":"+1 864 595 0931",
    "sg:postcode":"29301",
    "sg:province":"SC",
    "sg:tags":[
        "contract"
    ],
    "wof:name":"Sodexho Inc",
    "wof:placetype":"venue"
},
  "geometry": {"coordinates":[-81.979622,34.967248],"type":"Point"}
}