{
  "type": "Feature",
  "properties": {
    "iso:country":"US",
    "sg:address":"1811 S Ocean Blvd",
    "sg:city":"Myrtle Beach",
    "sg:classifiers":[
        {
            "category":"Travel",
            "subcategory":"Hotels & Motels",
            "type":"Entertainment"
        }
    ],
    "sg:phone":"+1 843 448 4355",
    "sg:postcode":"29577",
    "sg:province":"SC",
    "sg:website":"www.vikingmotel.com",
    "wof:name":"Viking Motel",
    "wof:placetype":"venue"
},
  "geometry": {"coordinates":[-78.903302,33.671664],"type":"Point"}
}