{
  "type": "Feature",
  "properties": {
    "addr:full":"2620 Hwy 9 W Dillon SC 29536",
    "addr:housenumber":"2620",
    "addr:postcode":"29536",
    "addr:street":"Hwy 9 W",
    "iso:country":"US",
    "sg:address":"2620 Hwy 9 W",
    "sg:city":"Dillon",
    "sg:classifiers":[
        {
            "category":"Food & Beverages",
            "subcategory":"Groceries & Convenience Stores",
            "type":"Retail Goods"
        }
    ],
    "sg:phone":"+1 843 774 4771",
    "sg:postcode":"29536",
    "sg:province":"SC",
    "wof:name":"Britt's Grocery",
    "wof:placetype":"venue"
},
  "geometry": {"coordinates":[-79.40568399999999,34.477998],"type":"Point"}
}