{
  "type": "Feature",
  "properties": {
    "iso:country":"US",
    "sg:address":"1514 Bourne St",
    "sg:city":"Georgetown",
    "sg:classifiers":[
        {
            "category":"Manufacturing",
            "subcategory":"Paper Products",
            "type":"Manufacturing & Wholesale Goods"
        }
    ],
    "sg:phone":"+1 843 546 2487",
    "sg:postcode":"29440",
    "sg:province":"SC",
    "wof:name":"International Paper Co",
    "wof:placetype":"venue"
},
  "geometry": {"coordinates":[-79.297388,33.365038],"type":"Point"}
}