{
  "type": "Feature",
  "properties": {
    "iso:country":"US",
    "sg:address":"1943 Glenns Bay Rd",
    "sg:city":"Surfside Beach",
    "sg:classifiers":[
        {
            "category":"Social Services",
            "type":"Services"
        }
    ],
    "sg:phone":"+1 843 902 6063",
    "sg:postcode":"29575",
    "sg:province":"SC",
    "sg:tags":[
        "counseling"
    ],
    "wof:name":"Tomothy W Loebs",
    "wof:placetype":"venue"
},
  "geometry": {"coordinates":[-78.99423,33.618722],"type":"Point"}
}