{
  "type": "Feature",
  "properties": {
    "addr:full":"100 Century Plaza Dr Seneca SC 29678",
    "addr:housenumber":"100",
    "addr:postcode":"29678",
    "addr:street":"Century Plaza Dr",
    "iso:country":"US",
    "sg:address":"100 Century Plaza Dr",
    "sg:city":"Seneca",
    "sg:classifiers":[
        {
            "category":"Banks & Credit Unions",
            "subcategory":"Investment Brokerage",
            "type":"Services"
        }
    ],
    "sg:phone":"+1 864 888 8700",
    "sg:postcode":"29678",
    "sg:province":"SC",
    "sg:tags":[
        "security"
    ],
    "wof:name":"Investment Center",
    "wof:placetype":"venue"
},
  "geometry": {"coordinates":[-82.938801,34.700897],"type":"Point"}
}