{
  "type": "Feature",
  "properties": {
    "iso:country":"US",
    "sg:address":"3651 State Hwy 37",
    "sg:city":"Williston",
    "sg:classifiers":[
        {
            "category":"Home & Garden",
            "subcategory":"Building Materials",
            "type":"Retail Goods"
        }
    ],
    "sg:phone":"+1 803 259 1626",
    "sg:postcode":"29853",
    "sg:province":"SC",
    "sg:tags":[
        "lumber"
    ],
    "wof:name":"Rays Lumber",
    "wof:placetype":"venue"
},
  "geometry": {"coordinates":[-81.388469,33.325715],"type":"Point"}
}