{
  "type": "Feature",
  "properties": {
    "iso:country":"US",
    "sg:address":"2189 Cattle Creek Rd",
    "sg:city":"Rowesville",
    "sg:classifiers":[
        {
            "category":"Farming",
            "subcategory":"Poultry Farm",
            "type":"Manufacturing & Wholesale Goods"
        }
    ],
    "sg:phone":"+1 803 829 2485",
    "sg:postcode":"29133",
    "sg:province":"SC",
    "sg:tags":[
        "hatchery",
        "soybean"
    ],
    "wof:name":"J Wimberly",
    "wof:placetype":"venue"
},
  "geometry": {"coordinates":[-80.74298,33.316564],"type":"Point"}
}