{
  "type": "Feature",
  "properties": {
    "iso:country":"US",
    "sg:address":"1 1st St",
    "sg:city":"Bluffton",
    "sg:classifiers":[
        {
            "category":"Sports & Exercise",
            "subcategory":"Gym",
            "type":"Entertainment"
        }
    ],
    "sg:phone":"+1 843 757 0732",
    "sg:postcode":"29910",
    "sg:province":"SC",
    "sg:tags":[
        "club",
        "health",
        "studio",
        "gymnasium"
    ],
    "wof:name":"Belfair Activity Ctr",
    "wof:placetype":"venue"
},
  "geometry": {"coordinates":[-80.85086099999999,32.214734],"type":"Point"}
}