{
  "type": "Feature",
  "properties": {
    "iso:country":"US",
    "sg:address":"1156 Edgefield St",
    "sg:city":"Greenwood",
    "sg:classifiers":[
        {
            "category":"Health Services",
            "subcategory":"Doctor",
            "type":"Services"
        }
    ],
    "sg:phone":"+1 864 943 2170",
    "sg:postcode":"29646",
    "sg:province":"SC",
    "sg:tags":[
        "physician",
        "surgeon"
    ],
    "wof:name":"Upper Savannah Radiology",
    "wof:placetype":"venue"
},
  "geometry": {"coordinates":[-82.157212,34.179413],"type":"Point"}
}