{
  "type": "Feature",
  "properties": {
    "iso:country":"US",
    "sg:address":"1301 E Washington St",
    "sg:city":"Greenville",
    "sg:classifiers":[
        {
            "category":"Personal",
            "subcategory":"Beauty Salon",
            "type":"Services"
        }
    ],
    "sg:phone":"+1 864 235 8136",
    "sg:postcode":"29607",
    "sg:province":"SC",
    "wof:name":"Zelma's Beauty Salon",
    "wof:placetype":"venue"
},
  "geometry": {"coordinates":[-82.383309,34.849897],"type":"Point"}
}