{
  "type": "Feature",
  "properties": {
    "iso:country":"US",
    "sg:address":"1203 US Hwy 501 Bus",
    "sg:city":"Conway",
    "sg:classifiers":[
        {
            "category":"Communications",
            "type":"Services"
        }
    ],
    "sg:phone":"+1 843 347 8580",
    "sg:postcode":"29526",
    "sg:province":"SC",
    "sg:tags":[
        "carrier"
    ],
    "wof:name":"Waccamaw Wireless",
    "wof:placetype":"venue"
},
  "geometry": {"coordinates":[-79.059171,33.848363],"type":"Point"}
}