{
  "type": "Feature",
  "properties": {
    "addr:full":"1289 Bell Rd Iva SC 29655",
    "addr:housenumber":"1289",
    "addr:postcode":"29655",
    "addr:street":"Bell Rd",
    "iso:country":"US",
    "sg:address":"1289 Bell Rd",
    "sg:city":"Iva",
    "sg:classifiers":[
        {
            "category":"Building & Trades",
            "subcategory":"Construction",
            "type":"Services"
        }
    ],
    "sg:phone":"+1 864 348 3348",
    "sg:postcode":"29655",
    "sg:province":"SC",
    "sg:tags":[
        "designer",
        "dealer",
        "pool",
        "swimming"
    ],
    "wof:name":"Leveland Pool & Games",
    "wof:placetype":"venue"
},
  "geometry": {"coordinates":[-82.505842,34.316852],"type":"Point"}
}