{
  "type": "Feature",
  "properties": {
    "iso:country":"US",
    "sg:address":"199 Bluffton Rd",
    "sg:city":"Bluffton",
    "sg:classifiers":[
        {
            "category":"Professional",
            "subcategory":"Lawyer & Legal Services",
            "type":"Services"
        }
    ],
    "sg:phone":"+1 843 757 8020",
    "sg:postcode":"29910",
    "sg:province":"SC",
    "sg:tags":[
        "attorney"
    ],
    "wof:name":"Bowers & Siren",
    "wof:placetype":"venue"
},
  "geometry": {"coordinates":[-80.859948,32.238974],"type":"Point"}
}