{
  "type": "Feature",
  "properties": {
    "addr:full":"1080 E Montague Ave North Charleston SC 29405",
    "addr:housenumber":"1080",
    "addr:postcode":"29405",
    "addr:street":"E Montague Ave",
    "iso:country":"US",
    "sg:address":"1080 E Montague Ave",
    "sg:city":"North Charleston",
    "sg:classifiers":[
        {
            "category":"Arts & Performance",
            "subcategory":"Theater",
            "type":"Entertainment"
        }
    ],
    "sg:phone":"+1 843 745 0317",
    "sg:postcode":"29405",
    "sg:province":"SC",
    "wof:name":"South Of Broadway Theatre Co",
    "wof:placetype":"venue"
},
  "geometry": {"coordinates":[-79.97766,32.881589],"type":"Point"}
}