{
  "type": "Feature",
  "properties": {
    "iso:country":"US",
    "sg:address":"1316 Eden Rd",
    "sg:city":"Awendaw",
    "sg:classifiers":[
        {
            "category":"Wholesale",
            "subcategory":"Toys & Hobbies",
            "type":"Manufacturing & Wholesale Goods"
        }
    ],
    "sg:phone":"+1 843 856 0167",
    "sg:postcode":"29429",
    "sg:province":"SC",
    "wof:name":"W&J Imports Inc",
    "wof:placetype":"venue"
},
  "geometry": {"coordinates":[-79.742187,32.916749],"type":"Point"}
}