{
  "type": "Feature",
  "properties": {
    "addr:full":"516 S Walnut St Pamplico SC 29583",
    "addr:housenumber":"516",
    "addr:postcode":"29583",
    "addr:street":"S Walnut St",
    "iso:country":"US",
    "sg:address":"516 S Walnut St",
    "sg:city":"Pamplico",
    "sg:classifiers":[
        {
            "category":"Wholesale",
            "subcategory":"Construction Materials",
            "type":"Manufacturing & Wholesale Goods"
        }
    ],
    "sg:phone":"+1 843 493 2206",
    "sg:postcode":"29583",
    "sg:province":"SC",
    "sg:tags":[
        "timberland",
        "company",
        "timber"
    ],
    "wof:name":"Inland Timber Co",
    "wof:placetype":"venue"
},
  "geometry": {"coordinates":[-79.56707299999999,33.991204],"type":"Point"}
}