{
  "type": "Feature",
  "properties": {
    "iso:country":"US",
    "sg:address":"5800 Mountain View Rd",
    "sg:city":"Taylors",
    "sg:classifiers":[
        {
            "category":"Food & Beverages",
            "subcategory":"Groceries & Convenience Stores",
            "type":"Retail Goods"
        }
    ],
    "sg:phone":"+1 864 895 5502",
    "sg:postcode":"29687",
    "sg:province":"SC",
    "wof:name":"W E Willis Convenience Store",
    "wof:placetype":"venue"
},
  "geometry": {"coordinates":[-82.346484,35.02286],"type":"Point"}
}