{
  "type": "Feature",
  "properties": {
    "iso:country":"US",
    "sg:address":"920 W Main St",
    "sg:city":"Laurens",
    "sg:classifiers":[
        {
            "category":"Professional",
            "subcategory":"Secretarial Services",
            "type":"Services"
        }
    ],
    "sg:phone":"+1 864 984 2118",
    "sg:postcode":"29360",
    "sg:province":"SC",
    "sg:tags":[
        "convention",
        "court",
        "reporter"
    ],
    "wof:name":"Sandra K Brown & Assoc",
    "wof:placetype":"venue"
},
  "geometry": {"coordinates":[-82.030901,34.493515],"type":"Point"}
}