{
  "type": "Feature",
  "properties": {
    "iso:country":"US",
    "sg:address":"800 Bush River Rd",
    "sg:city":"Columbia",
    "sg:classifiers":[
        {
            "category":"Autos & Motor Vehicles",
            "subcategory":"Boat Sales",
            "type":"Retail Goods"
        }
    ],
    "sg:phone":"+1 803 750 5034",
    "sg:postcode":"29210",
    "sg:province":"SC",
    "wof:name":"West Marine Inc",
    "wof:placetype":"venue"
},
  "geometry": {"coordinates":[-81.101142,34.030219],"type":"Point"}
}