{
  "type": "Feature",
  "properties": {
    "iso:country":"US",
    "sg:address":"2714 Old Woodruff Rd",
    "sg:city":"Greer",
    "sg:classifiers":[
        {
            "category":"Building & Trades",
            "subcategory":"Construction",
            "type":"Services"
        }
    ],
    "sg:phone":"+1 864 879 7508",
    "sg:postcode":"29651",
    "sg:province":"SC",
    "sg:website":"www.hooverbuilding.com",
    "wof:name":"Hoover Building Systems Inc",
    "wof:placetype":"venue"
},
  "geometry": {"coordinates":[-82.17254800000001,34.902947],"type":"Point"}
}