{
  "type": "Feature",
  "properties": {
    "iso:country":"US",
    "sg:address":"308 Adams Scott Rd",
    "sg:city":"Gadsden",
    "sg:classifiers":[
        {
            "category":"Manufacturing",
            "subcategory":"Tools & Machinery",
            "type":"Manufacturing & Wholesale Goods"
        }
    ],
    "sg:phone":"+1 803 353 0809",
    "sg:postcode":"29052",
    "sg:province":"SC",
    "sg:tags":[
        "farm",
        "forestry",
        "mfg"
    ],
    "wof:name":"Smith Timber Inc",
    "wof:placetype":"venue"
},
  "geometry": {"coordinates":[-80.711827,33.840343],"type":"Point"}
}