{
  "type": "Feature",
  "properties": {
    "addr:full":"3750 US Hwy 17 Bus Murrells Inlet SC 29577",
    "addr:housenumber":"3750",
    "addr:postcode":"29577",
    "addr:street":"Us Hwy 17 Bus",
    "iso:country":"US",
    "sg:address":"3750 US Hwy 17 Bus",
    "sg:city":"Murrells Inlet",
    "sg:classifiers":[
        {
            "category":"Restaurant",
            "type":"Food & Drink"
        }
    ],
    "sg:phone":"+1 843 651 0622",
    "sg:postcode":"29577",
    "sg:province":"SC",
    "sg:tags":[
        "eating"
    ],
    "wof:name":"Inlet House Cafe",
    "wof:placetype":"venue"
},
  "geometry": {"coordinates":[-79.025582,33.575114],"type":"Point"}
}