{
  "type": "Feature",
  "properties": {
    "addr:full":"1156 Shoreham Rd Charleston SC 29412",
    "addr:housenumber":"1156",
    "addr:postcode":"29412",
    "addr:street":"Shoreham Rd",
    "iso:country":"US",
    "sg:address":"1156 Shoreham Rd",
    "sg:city":"Charleston",
    "sg:classifiers":[
        {
            "category":"Manufacturing",
            "subcategory":"Retail Goods",
            "type":"Manufacturing & Wholesale Goods"
        }
    ],
    "sg:phone":"+1 843 762 4594",
    "sg:postcode":"29412",
    "sg:province":"SC",
    "sg:tags":[
        "product",
        "mfg"
    ],
    "wof:name":"Alley Art",
    "wof:placetype":"venue"
},
  "geometry": {"coordinates":[-79.959698,32.722784],"type":"Point"}
}