{
  "type": "Feature",
  "properties": {
    "addr:full":"847 Peach Place Dr Fort Mill SC 29715",
    "addr:housenumber":"847",
    "addr:postcode":"29715",
    "addr:street":"Peach Place Dr",
    "iso:country":"US",
    "sg:address":"847 Peach Place Dr",
    "sg:city":"Fort Mill",
    "sg:classifiers":[
        {
            "category":"Building & Trades",
            "subcategory":"Cleaning & Sanitation",
            "type":"Services"
        }
    ],
    "sg:phone":"+1 803 547 4335",
    "sg:postcode":"29715",
    "sg:province":"SC",
    "sg:tags":[
        "janitor"
    ],
    "wof:name":"Pierce Wallace & Pierce",
    "wof:placetype":"venue"
},
  "geometry": {"coordinates":[-80.96235900000001,35.018801],"type":"Point"}
}