{
  "type": "Feature",
  "properties": {
    "addr:full":"605 Center St Mt Pleasant SC 29464",
    "addr:housenumber":"605",
    "addr:postcode":"29464",
    "addr:street":"Center St",
    "iso:country":"US",
    "sg:address":"605 Center St",
    "sg:city":"Mt Pleasant",
    "sg:classifiers":[
        {
            "category":"Education",
            "subcategory":"School",
            "type":"Public Place"
        }
    ],
    "sg:phone":"+1 843 849 2826",
    "sg:postcode":"29464",
    "sg:province":"SC",
    "wof:name":"Mt Pleasant Academy",
    "wof:placetype":"venue"
},
  "geometry": {"coordinates":[-79.86303100000001,32.781554],"type":"Point"}
}