{
  "type": "Feature",
  "properties": {
    "addr:full":"1200 Glenns Bay Rd Myrtle Beach SC 29575",
    "addr:housenumber":"1200",
    "addr:postcode":"29575",
    "addr:street":"Glenns Bay Rd",
    "iso:country":"US",
    "sg:address":"1200 Glenns Bay Rd",
    "sg:city":"Myrtle Beach",
    "sg:classifiers":[
        {
            "category":"Retail",
            "subcategory":"Repair Shop",
            "type":"Services"
        }
    ],
    "sg:phone":"+1 843 215 0686",
    "sg:postcode":"29575",
    "sg:province":"SC",
    "sg:tags":[
        "scooter",
        "motorcycle",
        "motor"
    ],
    "wof:name":"Maximum Velocity Motorsports",
    "wof:placetype":"venue"
},
  "geometry": {"coordinates":[-78.98469,33.615819],"type":"Point"}
}