{
  "type": "Feature",
  "properties": {
    "addr:full":"1180 Sam Rittenberg Blvd Charleston SC 29407",
    "addr:housenumber":"1180",
    "addr:postcode":"29407",
    "addr:street":"Sam Rittenberg Blvd",
    "iso:country":"US",
    "sg:address":"1180 Sam Rittenberg Blvd",
    "sg:city":"Charleston",
    "sg:classifiers":[
        {
            "category":"Professional",
            "subcategory":"Lawyer & Legal Services",
            "type":"Services"
        }
    ],
    "sg:phone":"+1 843 573 1867",
    "sg:postcode":"29407",
    "sg:province":"SC",
    "sg:tags":[
        "attorney"
    ],
    "wof:name":"Theodore L Hostetter PA",
    "wof:placetype":"venue"
},
  "geometry": {"coordinates":[-79.993819,32.817447],"type":"Point"}
}