{
  "type": "Feature",
  "properties": {
    "addr:full":"644 Bosmith Rd Lamar SC 29069",
    "addr:housenumber":"644",
    "addr:postcode":"29069",
    "addr:street":"Bosmith Rd",
    "iso:country":"US",
    "sg:address":"644 Bosmith Rd",
    "sg:city":"Lamar",
    "sg:classifiers":[
        {
            "category":"Building & Trades",
            "subcategory":"Electrical",
            "type":"Services"
        }
    ],
    "sg:phone":"+1 843 326 1040",
    "sg:postcode":"29069",
    "sg:province":"SC",
    "sg:tags":[
        "electrical",
        "contractor"
    ],
    "wof:name":"GE Electric Co Inc",
    "wof:placetype":"venue"
},
  "geometry": {"coordinates":[-80.078788,34.141518],"type":"Point"}
}