{
  "type": "Feature",
  "properties": {
    "addr:full":"507 Broad St Sumter SC 29150",
    "addr:housenumber":"507",
    "addr:postcode":"29150",
    "addr:street":"Broad St",
    "iso:country":"US",
    "sg:address":"507 Broad St",
    "sg:city":"Sumter",
    "sg:classifiers":[
        {
            "category":"Professional",
            "subcategory":"Accounting & Tax Preparation",
            "type":"Services"
        }
    ],
    "sg:phone":"+1 803 773 1515",
    "sg:postcode":"29150",
    "sg:province":"SC",
    "sg:tags":[
        "return",
        "filing"
    ],
    "wof:name":"Joyner Tax Svc",
    "wof:placetype":"venue"
},
  "geometry": {"coordinates":[-80.361073,33.938054],"type":"Point"}
}