{
  "type": "Feature",
  "properties": {
    "iso:country":"US",
    "sg:address":"402 Pearl St",
    "sg:city":"Darlington",
    "sg:classifiers":[
        {
            "category":"Social Services",
            "type":"Services"
        }
    ],
    "sg:phone":"+1 843 393 4371",
    "sg:postcode":"29532",
    "sg:province":"SC",
    "sg:tags":[
        "info",
        "program",
        "referral"
    ],
    "wof:name":"Information Referral & Asstnc",
    "wof:placetype":"venue"
},
  "geometry": {"coordinates":[-79.87588,34.300297],"type":"Point"}
}