{
  "type": "Feature",
  "properties": {
    "addr:full":"1103 Trammell Rd Anderson SC 29621",
    "addr:housenumber":"1103",
    "addr:postcode":"29621",
    "addr:street":"Trammell Rd",
    "iso:country":"US",
    "sg:address":"1103 Trammell Rd",
    "sg:city":"Anderson",
    "sg:classifiers":[
        {
            "category":"Wholesale",
            "subcategory":"Machinery & Supplies",
            "type":"Manufacturing & Wholesale Goods"
        }
    ],
    "sg:phone":"+1 864 226 1588",
    "sg:postcode":"29621",
    "sg:province":"SC",
    "sg:tags":[
        "janitor"
    ],
    "wof:name":"IPC Supply Inc",
    "wof:placetype":"venue"
},
  "geometry": {"coordinates":[-82.622917,34.513269],"type":"Point"}
}