{
  "type": "Feature",
  "properties": {
    "addr:full":"4 Hood Rd Greenville SC 29611",
    "addr:housenumber":"4",
    "addr:postcode":"29611",
    "addr:street":"Hood Rd",
    "iso:country":"US",
    "sg:address":"4 Hood Rd",
    "sg:city":"Greenville",
    "sg:classifiers":[
        {
            "category":"Banks & Credit Unions",
            "subcategory":"Bank",
            "type":"Services"
        }
    ],
    "sg:phone":"+1 864 295 1106",
    "sg:postcode":"29611",
    "sg:province":"SC",
    "sg:tags":[
        "national",
        "commercial"
    ],
    "wof:name":"Peoples National Bank",
    "wof:placetype":"venue"
},
  "geometry": {"coordinates":[-82.486571,34.791265],"type":"Point"}
}