{
  "type": "Feature",
  "properties": {
    "addr:full":"633 Leatherdale Rd Iva SC 29624",
    "addr:housenumber":"633",
    "addr:postcode":"29624",
    "addr:street":"Leatherdale Rd",
    "iso:country":"US",
    "sg:address":"633 Leatherdale Rd",
    "sg:city":"Iva",
    "sg:classifiers":[
        {
            "category":"Building & Trades",
            "subcategory":"Landscaping Services",
            "type":"Services"
        }
    ],
    "sg:phone":"+1 864 296 6667",
    "sg:postcode":"29624",
    "sg:province":"SC",
    "sg:tags":[
        "landscape",
        "contractor"
    ],
    "wof:name":"Alexander's Grading & Landscpg",
    "wof:placetype":"venue"
},
  "geometry": {"coordinates":[-82.626454,34.38034],"type":"Point"}
}