{
  "type": "Feature",
  "properties": {
    "addr:full":"1510 Inman Rd Wellford SC 29385",
    "addr:housenumber":"1510",
    "addr:postcode":"29385",
    "addr:street":"Inman Rd",
    "iso:country":"US",
    "sg:address":"1510 Inman Rd",
    "sg:city":"Wellford",
    "sg:classifiers":[
        {
            "category":"Building & Trades",
            "subcategory":"Landscaping Services",
            "type":"Services"
        }
    ],
    "sg:phone":"+1 864 439 8522",
    "sg:postcode":"29385",
    "sg:province":"SC",
    "sg:tags":[
        "landscape",
        "contractor"
    ],
    "wof:name":"Nicholson Inc",
    "wof:placetype":"venue"
},
  "geometry": {"coordinates":[-82.111034,34.993064],"type":"Point"}
}