{
  "type": "Feature",
  "properties": {
    "iso:country":"US",
    "sg:address":"557 Edgefield Rd",
    "sg:city":"Belvedere",
    "sg:classifiers":[
        {
            "category":"Wholesale",
            "subcategory":"Medical Equipment & Supplies",
            "type":"Manufacturing & Wholesale Goods"
        }
    ],
    "sg:phone":"+1 803 278 3891",
    "sg:postcode":"29841",
    "sg:province":"SC",
    "sg:tags":[
        "sun",
        "goggles",
        "sunglasses"
    ],
    "wof:name":"Day-Vue Sunglasses Co Inc",
    "wof:placetype":"venue"
},
  "geometry": {"coordinates":[-81.951009,33.525753],"type":"Point"}
}