{
  "type": "Feature",
  "properties": {
    "iso:country":"US",
    "sg:address":"1101 Belvedere Ct",
    "sg:city":"Charleston",
    "sg:classifiers":[
        {
            "category":"Building & Trades",
            "subcategory":"Construction",
            "type":"Services"
        }
    ],
    "sg:phone":"+1 843 345 3567",
    "sg:postcode":"29410",
    "sg:province":"SC",
    "sg:tags":[
        "hanging",
        "contractor"
    ],
    "wof:name":"Regional Painting Cont",
    "wof:placetype":"venue"
},
  "geometry": {"coordinates":[-80.00533,32.913351],"type":"Point"}
}