{
  "type": "Feature",
  "properties": {
    "addr:full":"1104 Sam Rittenberg Blvd Charleston SC 29407",
    "addr:housenumber":"1104",
    "addr:postcode":"29407",
    "addr:street":"Sam Rittenberg Blvd",
    "iso:country":"US",
    "sg:address":"1104 Sam Rittenberg Blvd",
    "sg:city":"Charleston",
    "sg:classifiers":[
        {
            "category":"Restaurant",
            "type":"Food & Drink"
        }
    ],
    "sg:phone":"+1 843 556 9420",
    "sg:postcode":"29407",
    "sg:province":"SC",
    "sg:tags":[
        "eating"
    ],
    "wof:name":"S & S Cafeteria Inc",
    "wof:placetype":"venue"
},
  "geometry": {"coordinates":[-79.991958,32.821827],"type":"Point"}
}