{
  "type": "Feature",
  "properties": {
    "addr:full":"109 Chalice Ln Columbia SC 29229",
    "addr:housenumber":"109",
    "addr:postcode":"29229",
    "addr:street":"Chalice Ln",
    "iso:country":"US",
    "sg:address":"109 Chalice Ln",
    "sg:city":"Columbia",
    "sg:classifiers":[
        {
            "category":"Shopping",
            "subcategory":"Music",
            "type":"Retail Goods"
        }
    ],
    "sg:phone":"+1 803 699 9409",
    "sg:postcode":"29229",
    "sg:province":"SC",
    "wof:name":"Shondeau Records Inc",
    "wof:placetype":"venue"
},
  "geometry": {"coordinates":[-80.854,34.091601],"type":"Point"}
}