{
  "type": "Feature",
  "properties": {
    "iso:country":"US",
    "sg:address":"1679 E Main St",
    "sg:city":"Easley",
    "sg:classifiers":[
        {
            "category":"Autos & Motor Vehicles",
            "subcategory":"Auto Supplies",
            "type":"Retail Goods"
        }
    ],
    "sg:phone":"+1 864 859 2222",
    "sg:postcode":"29640",
    "sg:province":"SC",
    "sg:tags":[
        "parts"
    ],
    "wof:name":"Ace Auto Parts",
    "wof:placetype":"venue"
},
  "geometry": {"coordinates":[-82.570052,34.828078],"type":"Point"}
}