{
  "type": "Feature",
  "properties": {
    "iso:country":"US",
    "sg:address":"319 S Mill St",
    "sg:city":"Manning",
    "sg:classifiers":[
        {
            "category":"Wholesale",
            "subcategory":"Machinery & Supplies",
            "type":"Manufacturing & Wholesale Goods"
        }
    ],
    "sg:phone":"+1 803 435 4045",
    "sg:postcode":"29102",
    "sg:province":"SC",
    "sg:tags":[
        "equipment",
        "log",
        "splitting"
    ],
    "wof:name":"Woods Plus Inc",
    "wof:placetype":"venue"
},
  "geometry": {"coordinates":[-80.21207099999999,33.690112],"type":"Point"}
}