{
  "type": "Feature",
  "properties": {
    "addr:full":"911 Lady St Columbia SC 29201",
    "addr:housenumber":"911",
    "addr:postcode":"29201",
    "addr:street":"Lady St",
    "iso:country":"US",
    "sg:address":"911 Lady St",
    "sg:city":"Columbia",
    "sg:classifiers":[
        {
            "category":"Restaurant",
            "type":"Food & Drink"
        }
    ],
    "sg:phone":"+1 803 771 2005",
    "sg:postcode":"29201",
    "sg:province":"SC",
    "sg:tags":[
        "pizza"
    ],
    "wof:name":"Pizza Joint Corporate Office the",
    "wof:placetype":"venue"
},
  "geometry": {"coordinates":[-81.038889,34.001281],"type":"Point"}
}