{
  "type": "Feature",
  "properties": {
    "addr:full":"827 82nd Pkwy Myrtle Beach SC 29572",
    "addr:housenumber":"827",
    "addr:postcode":"29572",
    "addr:street":"82Nd Pkwy",
    "iso:country":"US",
    "sg:address":"827 82nd Pkwy",
    "sg:city":"Myrtle Beach",
    "sg:classifiers":[
        {
            "category":"Health Services",
            "subcategory":"Doctor",
            "type":"Services"
        }
    ],
    "sg:phone":"+1 843 286 2020",
    "sg:postcode":"29572",
    "sg:province":"SC",
    "sg:tags":[
        "physician",
        "surgeon"
    ],
    "wof:name":"Parkway Surgery Ctr",
    "wof:placetype":"venue"
},
  "geometry": {"coordinates":[-78.817075,33.755494],"type":"Point"}
}