{
  "type": "Feature",
  "properties": {
    "iso:country":"US",
    "sg:address":"8676 Palmetto Rd",
    "sg:city":"Edisto Island",
    "sg:classifiers":[
        {
            "category":"Building & Trades",
            "subcategory":"Electrical",
            "type":"Services"
        }
    ],
    "sg:phone":"+1 843 869 5262",
    "sg:postcode":"29438",
    "sg:province":"SC",
    "sg:tags":[
        "electrical",
        "contractor"
    ],
    "wof:name":"B&B Electrical Inc",
    "wof:placetype":"venue"
},
  "geometry": {"coordinates":[-80.3264,32.512206],"type":"Point"}
}