{
  "type": "Feature",
  "properties": {
    "iso:country":"US",
    "sg:address":"609 N Main St",
    "sg:city":"Darlington",
    "sg:classifiers":[
        {
            "category":"Banks & Credit Unions",
            "subcategory":"Bank",
            "type":"Services"
        }
    ],
    "sg:phone":"+1 843 395 9669",
    "sg:postcode":"29532",
    "sg:province":"SC",
    "wof:name":"SPC Cooperative Credit",
    "wof:placetype":"venue"
},
  "geometry": {"coordinates":[-79.884483,34.31664],"type":"Point"}
}