{
  "type": "Feature",
  "properties": {
    "iso:country":"US",
    "sg:address":"218 S Main St",
    "sg:city":"Fountain Inn",
    "sg:classifiers":[
        {
            "category":"Banks & Credit Unions",
            "subcategory":"Bank",
            "type":"Services"
        }
    ],
    "sg:phone":"+1 864 862 1957",
    "sg:postcode":"29644",
    "sg:province":"SC",
    "sg:tags":[
        "loan"
    ],
    "wof:name":"Cash Inn",
    "wof:placetype":"venue"
},
  "geometry": {"coordinates":[-82.198043,34.691684],"type":"Point"}
}