{
  "type": "Feature",
  "properties": {
    "iso:country":"US",
    "sg:address":"134 State St",
    "sg:city":"West Columbia",
    "sg:classifiers":[
        {
            "category":"Personal",
            "subcategory":"Beauty Salon",
            "type":"Services"
        }
    ],
    "sg:phone":"+1 803 794 2357",
    "sg:postcode":"29169",
    "sg:province":"SC",
    "wof:name":"Moda",
    "wof:placetype":"venue"
},
  "geometry": {"coordinates":[-81.055933,33.993199],"type":"Point"}
}