{
  "type": "Feature",
  "properties": {
    "addr:full":"103 Assembly St Columbia SC 29201",
    "addr:housenumber":"103",
    "addr:postcode":"29201",
    "addr:street":"Assembly St",
    "iso:country":"US",
    "sg:address":"103 Assembly St",
    "sg:city":"Columbia",
    "sg:classifiers":[
        {
            "category":"Wholesale",
            "subcategory":"Auto Parts",
            "type":"Manufacturing & Wholesale Goods"
        }
    ],
    "sg:phone":"+1 803 771 4044",
    "sg:postcode":"29201",
    "sg:province":"SC",
    "sg:tags":[
        "engine"
    ],
    "sg:website":"www.magnetoinc.com",
    "wof:name":"Magneto & Electric Svc Inc",
    "wof:placetype":"venue"
},
  "geometry": {"coordinates":[-81.029301,33.987183],"type":"Point"}
}