{
  "type": "Feature",
  "properties": {
    "addr:full":"119 E 4th St S Summerville SC 29483",
    "addr:housenumber":"119",
    "addr:postcode":"29483",
    "addr:street":"E 4Th St S",
    "iso:country":"US",
    "sg:address":"119 E 4th St S",
    "sg:city":"Summerville",
    "sg:classifiers":[
        {
            "category":"Personal",
            "subcategory":"Beauty Salon",
            "type":"Services"
        }
    ],
    "sg:phone":"+1 843 873 1131",
    "sg:postcode":"29483",
    "sg:province":"SC",
    "wof:name":"Slightly East Of Main Inc",
    "wof:placetype":"venue"
},
  "geometry": {"coordinates":[-80.17755099999999,33.014389],"type":"Point"}
}