{
  "type": "Feature",
  "properties": {
    "iso:country":"US",
    "sg:address":"1238 Silverbrook Rd",
    "sg:city":"Chester",
    "sg:classifiers":[
        {
            "category":"Building & Trades",
            "subcategory":"Electrical",
            "type":"Services"
        }
    ],
    "sg:phone":"+1 803 789 7782",
    "sg:postcode":"29706",
    "sg:province":"SC",
    "sg:tags":[
        "electrical",
        "contractor"
    ],
    "wof:name":"Farpoint Electric Company",
    "wof:placetype":"venue"
},
  "geometry": {"coordinates":[-81.053201,34.745973],"type":"Point"}
}