{
  "type": "Feature",
  "properties": {
    "addr:full":"2410 Augusta Rd West Columbia SC 29169",
    "addr:housenumber":"2410",
    "addr:postcode":"29169",
    "addr:street":"Augusta Rd",
    "iso:country":"US",
    "sg:address":"2410 Augusta Rd",
    "sg:city":"West Columbia",
    "sg:classifiers":[
        {
            "category":"Food & Beverages",
            "subcategory":"Liquor & Beverages",
            "type":"Retail Goods"
        }
    ],
    "sg:phone":"+1 803 926 4764",
    "sg:postcode":"29169",
    "sg:province":"SC",
    "sg:tags":[
        "beer",
        "spirit",
        "wine"
    ],
    "wof:name":"Grog Shoppe # 3",
    "wof:placetype":"venue"
},
  "geometry": {"coordinates":[-81.09929700000001,33.9828],"type":"Point"}
}