{
  "type": "Feature",
  "properties": {
    "iso:country":"US",
    "sg:address":"109 Dearborn St",
    "sg:city":"Great Falls",
    "sg:classifiers":[
        {
            "category":"Retail",
            "subcategory":"Auto Repair",
            "type":"Services"
        }
    ],
    "sg:phone":"+1 803 482 3800",
    "sg:postcode":"29055",
    "sg:province":"SC",
    "sg:tags":[
        "muffler",
        "exhaust",
        "system"
    ],
    "wof:name":"Max Broome's Garage & Wrecker",
    "wof:placetype":"venue"
},
  "geometry": {"coordinates":[-80.901442,34.574949],"type":"Point"}
}