{
  "type": "Feature",
  "properties": {
    "addr:full":"208 S Green St Ridgeland SC 29936",
    "addr:housenumber":"208",
    "addr:postcode":"29936",
    "addr:street":"S Green St",
    "iso:country":"US",
    "sg:address":"208 S Green St",
    "sg:city":"Ridgeland",
    "sg:classifiers":[
        {
            "category":"Banks & Credit Unions",
            "subcategory":"Bank",
            "type":"Services"
        }
    ],
    "sg:phone":"+1 843 726 5222",
    "sg:postcode":"29936",
    "sg:province":"SC",
    "sg:tags":[
        "loan"
    ],
    "wof:name":"Low Country Finance Co",
    "wof:placetype":"venue"
},
  "geometry": {"coordinates":[-80.982288,32.480081],"type":"Point"}
}