{
  "type": "Feature",
  "properties": {
    "iso:country":"US",
    "sg:address":"1101 Elmwood Ave",
    "sg:city":"Columbia",
    "sg:classifiers":[
        {
            "category":"Shopping",
            "subcategory":"Florist",
            "type":"Retail Goods"
        }
    ],
    "sg:phone":"+1 803 252 4620",
    "sg:postcode":"29201",
    "sg:province":"SC",
    "wof:name":"Eison's Florist",
    "wof:placetype":"venue"
},
  "geometry": {"coordinates":[-81.038889,34.013359],"type":"Point"}
}