{
  "type": "Feature",
  "properties": {
    "iso:country":"US",
    "sg:address":"9 Stockton Ln",
    "sg:city":"Bluffton",
    "sg:classifiers":[
        {
            "category":"Building & Trades",
            "subcategory":"Construction",
            "type":"Services"
        }
    ],
    "sg:phone":"+1 843 757 5314",
    "sg:postcode":"29909",
    "sg:province":"SC",
    "sg:tags":[
        "contractor"
    ],
    "wof:name":"South Pointe Building Corp",
    "wof:placetype":"venue"
},
  "geometry": {"coordinates":[-80.89433,32.294082],"type":"Point"}
}