{
  "type": "Feature",
  "properties": {
    "iso:country":"US",
    "sg:address":"303 E Wood St",
    "sg:city":"Spartanburg",
    "sg:classifiers":[
        {
            "category":"Health Services",
            "subcategory":"Doctor",
            "type":"Services"
        }
    ],
    "sg:phone":"+1 864 560 4567",
    "sg:postcode":"29303",
    "sg:province":"SC",
    "sg:tags":[
        "physician",
        "surgeon"
    ],
    "wof:name":"Orthopaedic Specialties",
    "wof:placetype":"venue"
},
  "geometry": {"coordinates":[-81.93449099999999,34.967246],"type":"Point"}
}