{
  "type": "Feature",
  "properties": {
    "iso:country":"US",
    "sg:address":"1496 Central Shiloh Rd",
    "sg:city":"Abbeville",
    "sg:classifiers":[
        {
            "category":"Building & Trades",
            "subcategory":"Construction",
            "type":"Services"
        }
    ],
    "sg:phone":"+1 864 446 3370",
    "sg:postcode":"29620",
    "sg:province":"SC",
    "sg:tags":[
        "excavating",
        "contractor"
    ],
    "wof:name":"Overholt Excavating & Grading",
    "wof:placetype":"venue"
},
  "geometry": {"coordinates":[-82.36209599999999,34.273496],"type":"Point"}
}