{
  "type": "Feature",
  "properties": {
    "addr:full":"845 Old Furnace Rd Spartanburg SC 29316",
    "addr:housenumber":"845",
    "addr:postcode":"29316",
    "addr:street":"Old Furnace Rd",
    "iso:country":"US",
    "sg:address":"845 Old Furnace Rd",
    "sg:city":"Spartanburg",
    "sg:classifiers":[
        {
            "category":"Organizations",
            "subcategory":"Religious Organization",
            "type":"Services"
        }
    ],
    "sg:phone":"+1 864 578 7650",
    "sg:postcode":"29316",
    "sg:province":"SC",
    "sg:tags":[
        "church"
    ],
    "wof:name":"Victory Temple Christian Chr",
    "wof:placetype":"venue"
},
  "geometry": {"coordinates":[-82.01601599999999,35.034516],"type":"Point"}
}