{
  "type": "Feature",
  "properties": {
    "iso:country":"US",
    "sg:address":"200 Kensington Rd",
    "sg:city":"Taylors",
    "sg:classifiers":[
        {
            "category":"Home & Garden",
            "subcategory":"Furniture",
            "type":"Retail Goods"
        }
    ],
    "sg:phone":"+1 864 322 2989",
    "sg:postcode":"29687",
    "sg:province":"SC",
    "wof:name":"Jo Mar Sales",
    "wof:placetype":"venue"
},
  "geometry": {"coordinates":[-82.310593,34.917105],"type":"Point"}
}