{
  "type": "Feature",
  "properties": {
    "iso:country":"US",
    "sg:address":"224 N Main St",
    "sg:city":"Simpsonville",
    "sg:classifiers":[
        {
            "category":"Health Services",
            "subcategory":"Health Practitioner",
            "type":"Services"
        }
    ],
    "sg:phone":"+1 864 963 7070",
    "sg:postcode":"29681",
    "sg:province":"SC",
    "sg:tags":[
        "occupational",
        "safety"
    ],
    "wof:name":"Thomas A Malone Pa",
    "wof:placetype":"venue"
},
  "geometry": {"coordinates":[-82.256154,34.739666],"type":"Point"}
}