{
  "type": "Feature",
  "properties": {
    "iso:country":"US",
    "sg:address":"112 Hidden Lake Cir",
    "sg:city":"Duncan",
    "sg:classifiers":[
        {
            "category":"Manufacturing",
            "subcategory":"Electronics",
            "type":"Manufacturing & Wholesale Goods"
        },
        {
            "category":"Wholesale",
            "subcategory":"Durable Goods & Equipment",
            "type":"Manufacturing & Wholesale Goods"
        }
    ],
    "sg:phone":"+1 864 433 5000",
    "sg:postcode":"29334",
    "sg:province":"SC",
    "sg:tags":[
        "prerecorded",
        "importer",
        "mfg"
    ],
    "wof:name":"B M G Distribution",
    "wof:placetype":"venue"
},
  "geometry": {"coordinates":[-82.099751,34.914945],"type":"Point"}
}