{
  "type": "Feature",
  "properties": {
    "iso:country":"US",
    "sg:address":"213 Carn St",
    "sg:city":"Walterboro",
    "sg:classifiers":[
        {
            "category":"Government",
            "subcategory":"Fire Station",
            "type":"Public Place"
        }
    ],
    "sg:phone":"+1 843 549 5731",
    "sg:postcode":"29488",
    "sg:province":"SC",
    "sg:tags":[
        "department"
    ],
    "wof:name":"Walterboro Fire Dept",
    "wof:placetype":"venue"
},
  "geometry": {"coordinates":[-80.666174,32.901018],"type":"Point"}
}