{
  "type": "Feature",
  "properties": {
    "addr:full":"3407 Earle E Morris Jr Hwy Piedmont SC 29673",
    "addr:housenumber":"3407",
    "addr:postcode":"29673",
    "addr:street":"Earle E;Jr Hwy",
    "iso:country":"US",
    "sg:address":"3407 Earle E Morris Jr Hwy",
    "sg:city":"Piedmont",
    "sg:classifiers":[
        {
            "category":"Health Services",
            "subcategory":"Health Practitioner",
            "type":"Services"
        }
    ],
    "sg:phone":"+1 864 295 8700",
    "sg:postcode":"29673",
    "sg:province":"SC",
    "sg:tags":[
        "therapist",
        "physical"
    ],
    "wof:name":"Powdersville Rehab Ctr",
    "wof:placetype":"venue"
},
  "geometry": {"coordinates":[-82.476731,34.784478],"type":"Point"}
}