{
  "type": "Feature",
  "properties": {
    "iso:country":"US",
    "sg:address":"3614 Ashley Phosphate Rd",
    "sg:city":"North Charleston",
    "sg:classifiers":[
        {
            "category":"Building & Trades",
            "subcategory":"Pest Control",
            "type":"Services"
        }
    ],
    "sg:phone":"+1 843 767 5678",
    "sg:postcode":"29418",
    "sg:province":"SC",
    "wof:name":"Gregory's Pest Control",
    "wof:placetype":"venue"
},
  "geometry": {"coordinates":[-80.079252,32.926973],"type":"Point"}
}