{
  "type": "Feature",
  "properties": {
    "iso:country":"US",
    "sg:address":"44 Line St",
    "sg:city":"Charleston",
    "sg:classifiers":[
        {
            "category":"Retail",
            "subcategory":"Auto Rental",
            "type":"Services"
        }
    ],
    "sg:phone":"+1 843 853 3400",
    "sg:postcode":"29403",
    "sg:province":"SC",
    "sg:tags":[
        "renting",
        "truck",
        "leasing"
    ],
    "wof:name":"Budget Truck Rental",
    "wof:placetype":"venue"
},
  "geometry": {"coordinates":[-79.940887,32.796025],"type":"Point"}
}