{
  "type": "Feature",
  "properties": {
    "addr:full":"2791 David H McLeod Blvd Florence SC 29501",
    "addr:housenumber":"2791",
    "addr:postcode":"29501",
    "addr:street":"David H Mcleod Blvd",
    "iso:country":"US",
    "sg:address":"2791 David H McLeod Blvd",
    "sg:city":"Florence",
    "sg:classifiers":[
        {
            "category":"Shopping",
            "subcategory":"Department Store",
            "type":"Retail Goods"
        }
    ],
    "sg:phone":"+1 843 667 6731",
    "sg:postcode":"29501",
    "sg:province":"SC",
    "wof:name":"Target",
    "wof:placetype":"venue"
},
  "geometry": {"coordinates":[-79.832618,34.189273],"type":"Point"}
}