{
  "type": "Feature",
  "properties": {
    "iso:country":"US",
    "sg:address":"5018 Tara Tea Dr",
    "sg:city":"Fort Mill",
    "sg:classifiers":[
        {
            "category":"Banks & Credit Unions",
            "subcategory":"Bank",
            "type":"Services"
        }
    ],
    "sg:phone":"+1 803 548 8636",
    "sg:postcode":"29708",
    "sg:province":"SC",
    "sg:tags":[
        "mortgage"
    ],
    "wof:name":"Pritchard Mortgage Inc",
    "wof:placetype":"venue"
},
  "geometry": {"coordinates":[-81.02539,35.033663],"type":"Point"}
}