{
  "type": "Feature",
  "properties": {
    "iso:country":"US",
    "sg:address":"571 Banning St",
    "sg:city":"Cope",
    "sg:classifiers":[
        {
            "category":"Real Estate",
            "subcategory":"Real Estate Operator",
            "type":"Services"
        }
    ],
    "sg:phone":"+1 803 536 2269",
    "sg:postcode":"29038",
    "sg:province":"SC",
    "sg:tags":[
        "property",
        "lessor"
    ],
    "wof:name":"Marion Proctor",
    "wof:placetype":"venue"
},
  "geometry": {"coordinates":[-80.926211,33.314742],"type":"Point"}
}