{
  "type": "Feature",
  "properties": {
    "iso:country":"US",
    "sg:address":"930 US Hwy 123",
    "sg:city":"Seneca",
    "sg:classifiers":[
        {
            "category":"Professional",
            "subcategory":"Business Services",
            "type":"Services"
        }
    ],
    "sg:phone":"+1 864 882 8850",
    "sg:postcode":"29678",
    "sg:province":"SC",
    "sg:tags":[
        "packaging"
    ],
    "wof:name":"Golden Corner Shipping & More",
    "wof:placetype":"venue"
},
  "geometry": {"coordinates":[-82.97689099999999,34.693223],"type":"Point"}
}