{
  "type": "Feature",
  "properties": {
    "iso:country":"US",
    "sg:address":"8410 Rivers Ave",
    "sg:city":"North Charleston",
    "sg:classifiers":[
        {
            "category":"Insurance",
            "subcategory":"Insurance Agent",
            "type":"Services"
        }
    ],
    "sg:phone":"+1 843 569 0537",
    "sg:postcode":"29406",
    "sg:province":"SC",
    "wof:name":"Allstate Insurance",
    "wof:placetype":"venue"
},
  "geometry": {"coordinates":[-80.043004,32.959042],"type":"Point"}
}