{
  "type": "Feature",
  "properties": {
    "iso:country":"US",
    "sg:address":"3076 Locust Hill Rd",
    "sg:city":"York",
    "sg:classifiers":[
        {
            "category":"Building & Trades",
            "subcategory":"Construction",
            "type":"Services"
        }
    ],
    "sg:phone":"+1 803 927 1624",
    "sg:postcode":"29745",
    "sg:province":"SC",
    "sg:tags":[
        "concrete",
        "contractor"
    ],
    "wof:name":"Lail Asphalt",
    "wof:placetype":"venue"
},
  "geometry": {"coordinates":[-81.336713,34.988798],"type":"Point"}
}