{
  "type": "Feature",
  "properties": {
    "iso:country":"US",
    "sg:address":"276 N Ron McNair Blvd",
    "sg:city":"Lake City",
    "sg:classifiers":[
        {
            "category":"Health Services",
            "subcategory":"Doctor",
            "type":"Services"
        }
    ],
    "sg:phone":"+1 843 394 1051",
    "sg:postcode":"29560",
    "sg:province":"SC",
    "sg:tags":[
        "physician",
        "surgeon"
    ],
    "wof:name":"Mc Leod Family Medicine Ctr",
    "wof:placetype":"venue"
},
  "geometry": {"coordinates":[-79.758807,33.881062],"type":"Point"}
}