{
  "type": "Feature",
  "properties": {
    "iso:country":"US",
    "sg:address":"1707 Bernardin Ave",
    "sg:city":"Columbia",
    "sg:classifiers":[
        {
            "category":"Health Services",
            "subcategory":"Doctor",
            "type":"Services"
        }
    ],
    "sg:phone":"+1 803 779 0277",
    "sg:postcode":"29204",
    "sg:province":"SC",
    "sg:tags":[
        "physician",
        "surgeon"
    ],
    "wof:name":"Surgical Services Of Columbia",
    "wof:placetype":"venue"
},
  "geometry": {"coordinates":[-81.01350600000001,34.015714],"type":"Point"}
}