{
  "type": "Feature",
  "properties": {
    "addr:full":"7201 Notch Rd Columbia SC 29223",
    "addr:housenumber":"7201",
    "addr:postcode":"29223",
    "addr:street":"Notch Rd",
    "iso:country":"US",
    "sg:address":"7201 Notch Rd",
    "sg:city":"Columbia",
    "sg:classifiers":[
        {
            "category":"Restaurant",
            "type":"Food & Drink"
        }
    ],
    "sg:phone":"+1 803 699 4330",
    "sg:postcode":"29223",
    "sg:province":"SC",
    "wof:name":"Mc Donald's",
    "wof:placetype":"venue"
},
  "geometry": {"coordinates":[-80.956811,34.065152],"type":"Point"}
}