{
  "type": "Feature",
  "properties": {
    "addr:full":"11 E Augusta Pl Greenville SC 29605",
    "addr:housenumber":"11",
    "addr:postcode":"29605",
    "addr:street":"E Augusta Pl",
    "iso:country":"US",
    "sg:address":"11 E Augusta Pl",
    "sg:city":"Greenville",
    "sg:classifiers":[
        {
            "category":"Health Services",
            "subcategory":"Nursing And Care Facility",
            "type":"Services"
        }
    ],
    "sg:phone":"+1 864 370 9030",
    "sg:postcode":"29605",
    "sg:province":"SC",
    "sg:tags":[
        "home",
        "retirement",
        "community"
    ],
    "sg:website":"www.holidaytouch.com",
    "wof:name":"Westminster Retirement",
    "wof:placetype":"venue"
},
  "geometry": {"coordinates":[-82.38835899999999,34.822851],"type":"Point"}
}