{
  "type": "Feature",
  "properties": {
    "addr:full":"13334 State Hwy 3 Blackville SC 29817",
    "addr:housenumber":"13334",
    "addr:postcode":"29817",
    "addr:street":"State Hwy 3;Sc",
    "iso:country":"US",
    "sg:address":"13334 State Hwy 3",
    "sg:city":"Blackville",
    "sg:classifiers":[
        {
            "category":"Wholesale",
            "subcategory":"Auto Parts",
            "type":"Manufacturing & Wholesale Goods"
        }
    ],
    "sg:phone":"+1 803 259 3305",
    "sg:postcode":"29817",
    "sg:province":"SC",
    "sg:tags":[
        "automobile",
        "wrecking"
    ],
    "wof:name":"Smoak's Auto Salvage",
    "wof:placetype":"venue"
},
  "geometry": {"coordinates":[-81.34008,33.284799],"type":"Point"}
}