{
  "type": "Feature",
  "properties": {
    "addr:full":"12 Marsh Dr Beaufort SC 29907",
    "addr:housenumber":"12",
    "addr:postcode":"29907",
    "addr:street":"Marsh Dr",
    "iso:country":"US",
    "sg:address":"12 Marsh Dr",
    "sg:city":"Beaufort",
    "sg:classifiers":[
        {
            "category":"Manufacturing",
            "subcategory":"Apparel",
            "type":"Manufacturing & Wholesale Goods"
        }
    ],
    "sg:phone":"+1 843 982 0900",
    "sg:postcode":"29907",
    "sg:province":"SC",
    "wof:name":"Lets Embroider It LLC",
    "wof:placetype":"venue"
},
  "geometry": {"coordinates":[-80.649162,32.455198],"type":"Point"}
}