{
  "type": "Feature",
  "properties": {
    "iso:country":"US",
    "sg:address":"3835 Lesslie Hwy",
    "sg:city":"Rock Hill",
    "sg:classifiers":[
        {
            "category":"Personal",
            "subcategory":"Beauty Salon",
            "type":"Services"
        }
    ],
    "sg:phone":"+1 803 329 4279",
    "sg:postcode":"29730",
    "sg:province":"SC",
    "wof:name":"Del Mar Styling Salon",
    "wof:placetype":"venue"
},
  "geometry": {"coordinates":[-80.94142600000001,34.874215],"type":"Point"}
}