{
  "type": "Feature",
  "properties": {
    "iso:country":"US",
    "sg:address":"108 S Blackstock Rd",
    "sg:city":"Spartanburg",
    "sg:classifiers":[
        {
            "category":"Building & Trades",
            "subcategory":"Construction",
            "type":"Services"
        }
    ],
    "sg:phone":"+1 864 574 7702",
    "sg:postcode":"29301",
    "sg:province":"SC",
    "sg:tags":[
        "home",
        "builder"
    ],
    "wof:name":"RCB Development",
    "wof:placetype":"venue"
},
  "geometry": {"coordinates":[-82.001621,34.931948],"type":"Point"}
}