{
  "type": "Feature",
  "properties": {
    "iso:country":"US",
    "sg:address":"1606 N Main St",
    "sg:city":"Anderson",
    "sg:classifiers":[
        {
            "category":"Restaurant",
            "type":"Food & Drink"
        }
    ],
    "sg:phone":"+1 864 224 1695",
    "sg:postcode":"29621",
    "sg:province":"SC",
    "sg:tags":[
        "parlor",
        "ice",
        "cream"
    ],
    "wof:name":"Besto",
    "wof:placetype":"venue"
},
  "geometry": {"coordinates":[-82.654825,34.518085],"type":"Point"}
}