{
  "type": "Feature",
  "properties": {
    "iso:country":"US",
    "sg:address":"7220 Hwy 544",
    "sg:city":"Myrtle Beach",
    "sg:classifiers":[
        {
            "category":"Manufacturing",
            "subcategory":"Tools & Machinery",
            "type":"Manufacturing & Wholesale Goods"
        }
    ],
    "sg:phone":"+1 843 236 5800",
    "sg:postcode":"29578",
    "sg:province":"SC",
    "sg:tags":[
        "industrial",
        "mfg"
    ],
    "wof:name":"Custom Machine & Design Inc",
    "wof:placetype":"venue"
},
  "geometry": {"coordinates":[-79.009471,33.690549],"type":"Point"}
}