{
  "type": "Feature",
  "properties": {
    "iso:country":"US",
    "sg:address":"1140 State Hwy 55 E",
    "sg:city":"Clover",
    "sg:classifiers":[
        {
            "category":"Food & Beverages",
            "subcategory":"Liquor & Beverages",
            "type":"Retail Goods"
        }
    ],
    "sg:phone":"+1 803 222 7575",
    "sg:postcode":"29710",
    "sg:province":"SC",
    "sg:tags":[
        "alcoholic"
    ],
    "wof:name":"Bradford of The Carolinas",
    "wof:placetype":"venue"
},
  "geometry": {"coordinates":[-81.203653,35.104634],"type":"Point"}
}