{
  "type": "Feature",
  "properties": {
    "addr:full":"1005 Ninety Six Hwy Greenwood SC 29646",
    "addr:housenumber":"1005",
    "addr:postcode":"29646",
    "addr:street":"Ninety Six Hwy",
    "iso:country":"US",
    "sg:address":"1005 Ninety Six Hwy",
    "sg:city":"Greenwood",
    "sg:classifiers":[
        {
            "category":"Autos & Motor Vehicles",
            "subcategory":"Automobile Sales",
            "type":"Retail Goods"
        }
    ],
    "sg:phone":"+1 864 227 3863",
    "sg:postcode":"29646",
    "sg:province":"SC",
    "wof:name":"Kingsmore Enterprises",
    "wof:placetype":"venue"
},
  "geometry": {"coordinates":[-82.110432,34.164007],"type":"Point"}
}