{
  "type": "Feature",
  "properties": {
    "iso:country":"US",
    "sg:address":"113 Pinckney Dr",
    "sg:city":"Columbia",
    "sg:classifiers":[
        {
            "category":"Retail",
            "subcategory":"Portrait Studio",
            "type":"Services"
        }
    ],
    "sg:phone":"+1 803 783 3071",
    "sg:postcode":"29209",
    "sg:province":"SC",
    "sg:tags":[
        "photographer"
    ],
    "wof:name":"Chiles & Chiles Studio & Video",
    "wof:placetype":"venue"
},
  "geometry": {"coordinates":[-80.888464,33.962291],"type":"Point"}
}