{
  "type": "Feature",
  "properties": {
    "iso:country":"US",
    "sg:address":"946 Sand Bar Rd",
    "sg:city":"Chapin",
    "sg:classifiers":[
        {
            "category":"Shopping",
            "subcategory":"Bicycles & Sporting Goods",
            "type":"Retail Goods"
        }
    ],
    "sg:phone":"+1 803 345 1909",
    "sg:postcode":"29036",
    "sg:province":"SC",
    "wof:name":"Chafin Guns",
    "wof:placetype":"venue"
},
  "geometry": {"coordinates":[-81.363891,34.129806],"type":"Point"}
}