{
  "type": "Feature",
  "properties": {
    "iso:country":"US",
    "sg:address":"806 Broad River Rd",
    "sg:city":"Columbia",
    "sg:classifiers":[
        {
            "category":"Professional",
            "type":"Services"
        }
    ],
    "sg:phone":"+1 803 798 4992",
    "sg:postcode":"29210",
    "sg:province":"SC",
    "sg:tags":[
        "establishment"
    ],
    "wof:name":"TRM",
    "wof:placetype":"venue"
},
  "geometry": {"coordinates":[-81.07998499999999,34.025348],"type":"Point"}
}