{
  "type": "Feature",
  "properties": {
    "iso:country":"US",
    "sg:address":"3041 Old Camp Long Rd",
    "sg:city":"Aiken",
    "sg:classifiers":[
        {
            "category":"Building & Trades",
            "subcategory":"Construction",
            "type":"Services"
        }
    ],
    "sg:phone":"+1 803 644 0286",
    "sg:postcode":"29805",
    "sg:province":"SC",
    "sg:tags":[
        "contractor"
    ],
    "wof:name":"Hunter Masonry",
    "wof:placetype":"venue"
},
  "geometry": {"coordinates":[-81.63559,33.680469],"type":"Point"}
}