{
  "type": "Feature",
  "properties": {
    "iso:country":"US",
    "sg:address":"125 E Broad St",
    "sg:city":"Darlington",
    "sg:classifiers":[
        {
            "category":"Home & Garden",
            "subcategory":"Hardware",
            "type":"Retail Goods"
        }
    ],
    "sg:phone":"+1 843 393 9061",
    "sg:postcode":"29532",
    "sg:province":"SC",
    "wof:name":"Carolina Hardware Mini Wrhs",
    "wof:placetype":"venue"
},
  "geometry": {"coordinates":[-79.867329,34.300537],"type":"Point"}
}