{
  "type": "Feature",
  "properties": {
    "iso:country":"US",
    "sg:address":"1654 Camden Rd",
    "sg:city":"Holly Hill",
    "sg:classifiers":[
        {
            "category":"Education",
            "subcategory":"School",
            "type":"Public Place"
        }
    ],
    "sg:phone":"+1 803 496 3288",
    "sg:postcode":"29059",
    "sg:province":"SC",
    "wof:name":"Orangeburg District 3",
    "wof:placetype":"venue"
},
  "geometry": {"coordinates":[-80.422952,33.385597],"type":"Point"}
}