{
  "type": "Feature",
  "properties": {
    "iso:country":"US",
    "sg:address":"602 Bush River Rd",
    "sg:city":"Columbia",
    "sg:classifiers":[
        {
            "category":"Autos & Motor Vehicles",
            "subcategory":"Auto Supplies",
            "type":"Retail Goods"
        }
    ],
    "sg:phone":"+1 803 798 1231",
    "sg:postcode":"29210",
    "sg:province":"SC",
    "sg:tags":[
        "automobile",
        "stereo",
        "installation",
        "radio"
    ],
    "wof:name":"Ultimate Audio",
    "wof:placetype":"venue"
},
  "geometry": {"coordinates":[-81.09670300000001,34.030602],"type":"Point"}
}