{
  "type": "Feature",
  "properties": {
    "iso:country":"US",
    "sg:address":"709 Joy St",
    "sg:city":"Fort Mill",
    "sg:classifiers":[
        {
            "category":"Autos & Motor Vehicles",
            "subcategory":"Fuel & Gas Station",
            "type":"Retail Goods"
        }
    ],
    "sg:phone":"+1 803 547 5766",
    "sg:postcode":"29715",
    "sg:province":"SC",
    "sg:tags":[
        "station",
        "gasoline"
    ],
    "wof:name":"Patterson Full Service Gas Stn",
    "wof:placetype":"venue"
},
  "geometry": {"coordinates":[-80.967855,35.002834],"type":"Point"}
}