{
  "type": "Feature",
  "properties": {
    "addr:full":"9 Trachelle Ln Charleston SC 29407",
    "addr:housenumber":"9",
    "addr:postcode":"29407",
    "addr:street":"Trachelle Ln",
    "iso:country":"US",
    "sg:address":"9 Trachelle Ln",
    "sg:city":"Charleston",
    "sg:classifiers":[
        {
            "category":"Travel",
            "subcategory":"Travel Agent",
            "type":"Entertainment"
        }
    ],
    "sg:phone":"+1 843 763 7551",
    "sg:postcode":"29407",
    "sg:province":"SC",
    "sg:tags":[
        "operator",
        "tour"
    ],
    "wof:name":"Gullah Tours",
    "wof:placetype":"venue"
},
  "geometry": {"coordinates":[-79.98250899999999,32.822299],"type":"Point"}
}