{
  "type": "Feature",
  "properties": {
    "addr:full":"655 Old Greenville Hwy Spartanburg SC 29301",
    "addr:housenumber":"655",
    "addr:postcode":"29301",
    "addr:street":"Old Greenville Hwy",
    "iso:country":"US",
    "sg:address":"655 Old Greenville Hwy",
    "sg:city":"Spartanburg",
    "sg:classifiers":[
        {
            "category":"Manufacturing",
            "subcategory":"Textiles",
            "type":"Manufacturing & Wholesale Goods"
        }
    ],
    "sg:phone":"+1 864 439 1870",
    "sg:postcode":"29301",
    "sg:province":"SC",
    "sg:tags":[
        "spinning",
        "mills",
        "mill",
        "yarn"
    ],
    "wof:name":"Ameritex Yarn LLC",
    "wof:placetype":"venue"
},
  "geometry": {"coordinates":[-82.052285,34.938953],"type":"Point"}
}