{
  "type": "Feature",
  "properties": {
    "addr:full":"5895 Chesnee Hwy Chesnee SC 29323",
    "addr:housenumber":"5895",
    "addr:postcode":"29323",
    "addr:street":"Chesnee Hwy",
    "iso:country":"US",
    "sg:address":"5895 Chesnee Hwy",
    "sg:city":"Chesnee",
    "sg:classifiers":[
        {
            "category":"Health Services",
            "subcategory":"Chiropractor",
            "type":"Services"
        }
    ],
    "sg:phone":"+1 864 461 2313",
    "sg:postcode":"29323",
    "sg:province":"SC",
    "wof:name":"Ehlich Chiropractic Clinic",
    "wof:placetype":"venue"
},
  "geometry": {"coordinates":[-81.863792,35.123429],"type":"Point"}
}