{
  "type": "Feature",
  "properties": {
    "addr:full":"201 S Jennings St Saluda SC 29138",
    "addr:housenumber":"201",
    "addr:postcode":"29138",
    "addr:street":"S Jennings St",
    "iso:country":"US",
    "sg:address":"201 S Jennings St",
    "sg:city":"Saluda",
    "sg:classifiers":[
        {
            "category":"Organizations",
            "subcategory":"Religious Organization",
            "type":"Services"
        }
    ],
    "sg:phone":"+1 864 445 8841",
    "sg:postcode":"29138",
    "sg:province":"SC",
    "sg:tags":[
        "church"
    ],
    "wof:name":"Saluda Church Of God",
    "wof:placetype":"venue"
},
  "geometry": {"coordinates":[-81.76895500000001,33.997759],"type":"Point"}
}