{
  "type": "Feature",
  "properties": {
    "addr:full":"2322 Railroad Ave Scranton SC 29591",
    "addr:housenumber":"2322",
    "addr:postcode":"29591",
    "addr:street":"Railroad Ave",
    "iso:country":"US",
    "sg:address":"2322 Railroad Ave",
    "sg:city":"Scranton",
    "sg:classifiers":[
        {
            "category":"Organizations",
            "subcategory":"Religious Organization",
            "type":"Services"
        }
    ],
    "sg:phone":"+1 843 389 1907",
    "sg:postcode":"29591",
    "sg:province":"SC",
    "sg:tags":[
        "church"
    ],
    "wof:name":"Mt Moriah Baptist Church",
    "wof:placetype":"venue"
},
  "geometry": {"coordinates":[-79.744777,33.924435],"type":"Point"}
}