{
  "type": "Feature",
  "properties": {
    "iso:country":"US",
    "sg:address":"515 N Limestone St",
    "sg:city":"Gaffney",
    "sg:classifiers":[
        {
            "category":"Banks & Credit Unions",
            "subcategory":"Bank",
            "type":"Services"
        }
    ],
    "sg:phone":"+1 864 487 0231",
    "sg:postcode":"29340",
    "sg:province":"SC",
    "sg:tags":[
        "small",
        "loan",
        "company"
    ],
    "wof:name":"Regional Finance Corp",
    "wof:placetype":"venue"
},
  "geometry": {"coordinates":[-81.646666,35.075983],"type":"Point"}
}