{
  "type": "Feature",
  "properties": {
    "addr:full":"2885 W 5th St N Summerville SC 29483",
    "addr:housenumber":"2885",
    "addr:postcode":"29483",
    "addr:street":"W 5Th St N",
    "iso:country":"US",
    "sg:address":"2885 W 5th St N",
    "sg:city":"Summerville",
    "sg:classifiers":[
        {
            "category":"Professional",
            "subcategory":"Employment Agencies",
            "type":"Services"
        }
    ],
    "sg:phone":"+1 843 873 7775",
    "sg:postcode":"29483",
    "sg:province":"SC",
    "sg:tags":[
        "opportunity"
    ],
    "wof:name":"Alternative Staffing Inc",
    "wof:placetype":"venue"
},
  "geometry": {"coordinates":[-80.18267899999999,33.033004],"type":"Point"}
}