{
  "type": "Feature",
  "properties": {
    "addr:full":"1651 Gold Hill Rd Fort Mill SC 29708",
    "addr:housenumber":"1651",
    "addr:postcode":"29708",
    "addr:street":"Gold Hill Rd",
    "iso:country":"US",
    "sg:address":"1651 Gold Hill Rd",
    "sg:city":"Fort Mill",
    "sg:classifiers":[
        {
            "category":"Restaurant",
            "type":"Food & Drink"
        }
    ],
    "sg:phone":"+1 803 547 7770",
    "sg:postcode":"29708",
    "sg:province":"SC",
    "sg:tags":[
        "eating"
    ],
    "wof:name":"Village Pizza & Italian Rest",
    "wof:placetype":"venue"
},
  "geometry": {"coordinates":[-80.99042900000001,35.061304],"type":"Point"}
}