{
  "type": "Feature",
  "properties": {
    "addr:full":"1538 Westwood Dr Charleston SC 29412",
    "addr:housenumber":"1538",
    "addr:postcode":"29412",
    "addr:street":"Westwood Dr",
    "iso:country":"US",
    "sg:address":"1538 Westwood Dr",
    "sg:city":"Charleston",
    "sg:classifiers":[
        {
            "category":"Freight",
            "type":"Transportation"
        }
    ],
    "sg:phone":"+1 843 795 4102",
    "sg:postcode":"29412",
    "sg:province":"SC",
    "sg:tags":[
        "delivery",
        "container",
        "hauling"
    ],
    "wof:name":"Bessie Mae Inc",
    "wof:placetype":"venue"
},
  "geometry": {"coordinates":[-79.960691,32.714784],"type":"Point"}
}