{
  "type": "Feature",
  "properties": {
    "addr:full":"129 Silvercreek Dr Lexington SC 29072",
    "addr:housenumber":"129",
    "addr:postcode":"29072",
    "addr:street":"Silvercreek Dr",
    "iso:country":"US",
    "sg:address":"129 Silvercreek Dr",
    "sg:city":"Lexington",
    "sg:classifiers":[
        {
            "category":"Professional",
            "type":"Services"
        }
    ],
    "sg:phone":"+1 803 808 0168",
    "sg:postcode":"29072",
    "sg:province":"SC",
    "sg:tags":[
        "establishment"
    ],
    "wof:name":"Design Works",
    "wof:placetype":"venue"
},
  "geometry": {"coordinates":[-81.27923699999999,34.010796],"type":"Point"}
}