{
  "type": "Feature",
  "properties": {
    "iso:country":"US",
    "sg:address":"360 Cobbleview Dr",
    "sg:city":"Lexington",
    "sg:classifiers":[
        {
            "category":"Retail",
            "subcategory":"Repair Shop",
            "type":"Services"
        }
    ],
    "sg:phone":"+1 803 951 2700",
    "sg:postcode":"29072",
    "sg:province":"SC",
    "sg:tags":[
        "lighting",
        "fixture"
    ],
    "wof:name":"Maintenance Pros",
    "wof:placetype":"venue"
},
  "geometry": {"coordinates":[-81.245574,34.007556],"type":"Point"}
}