{
  "type": "Feature",
  "properties": {
    "addr:full":"240 N Creek Blvd Greenwood SC 29649",
    "addr:housenumber":"240",
    "addr:postcode":"29649",
    "addr:street":"N Creek Blvd",
    "iso:country":"US",
    "sg:address":"240 N Creek Blvd",
    "sg:city":"Greenwood",
    "sg:classifiers":[
        {
            "category":"Government",
            "subcategory":"Post Office",
            "type":"Public Place"
        }
    ],
    "sg:phone":"+1 864 223 2321",
    "sg:postcode":"29649",
    "sg:province":"SC",
    "wof:name":"US Post Office",
    "wof:placetype":"venue"
},
  "geometry": {"coordinates":[-82.183797,34.213076],"type":"Point"}
}