{
  "type": "Feature",
  "properties": {
    "iso:country":"US",
    "sg:address":"3517 Leigh Ln",
    "sg:city":"Florence",
    "sg:classifiers":[
        {
            "category":"Personal",
            "subcategory":"Beauty Salon",
            "type":"Services"
        }
    ],
    "sg:phone":"+1 843 662 7654",
    "sg:postcode":"29505",
    "sg:province":"SC",
    "wof:name":"Pleasures Hair Salon",
    "wof:placetype":"venue"
},
  "geometry": {"coordinates":[-79.749009,34.127973],"type":"Point"}
}