{
  "type": "Feature",
  "properties": {
    "iso:country":"US",
    "sg:address":"2101 Saint James Dr",
    "sg:city":"Charleston",
    "sg:classifiers":[
        {
            "category":"Insurance",
            "subcategory":"Insurance Agent",
            "type":"Services"
        }
    ],
    "sg:phone":"+1 843 886 3939",
    "sg:postcode":"29412",
    "sg:province":"SC",
    "wof:name":"A-AAA Affordable Health Ins",
    "wof:placetype":"venue"
},
  "geometry": {"coordinates":[-79.99526,32.763913],"type":"Point"}
}