{
  "type": "Feature",
  "properties": {
    "iso:country":"US",
    "sg:address":"1838 Bluff Rd",
    "sg:city":"Columbia",
    "sg:classifiers":[
        {
            "category":"Wholesale",
            "subcategory":"Fruits & Vegetables",
            "type":"Manufacturing & Wholesale Goods"
        }
    ],
    "sg:phone":"+1 803 252 7121",
    "sg:postcode":"29201",
    "sg:province":"SC",
    "wof:name":"Judy Phillips Apple Orchard",
    "wof:placetype":"venue"
},
  "geometry": {"coordinates":[-81.001975,33.963371],"type":"Point"}
}