{
  "type": "Feature",
  "properties": {
    "iso:country":"US",
    "sg:address":"2104 Augusta Rd",
    "sg:city":"Greenville",
    "sg:classifiers":[
        {
            "category":"Professional",
            "subcategory":"Art Services",
            "type":"Services"
        }
    ],
    "sg:phone":"+1 864 331 3777",
    "sg:postcode":"29605",
    "sg:province":"SC",
    "sg:tags":[
        "graphic",
        "designer"
    ],
    "wof:name":"Andy Pickens Design",
    "wof:placetype":"venue"
},
  "geometry": {"coordinates":[-82.376721,34.77903],"type":"Point"}
}