{
  "type": "Feature",
  "properties": {
    "addr:full":"320 Stanley Ave Greenwood SC 29649",
    "addr:housenumber":"320",
    "addr:postcode":"29649",
    "addr:street":"Stanley Ave",
    "iso:country":"US",
    "sg:address":"320 Stanley Ave",
    "sg:city":"Greenwood",
    "sg:classifiers":[
        {
            "category":"Organizations",
            "subcategory":"Professional Association",
            "type":"Services"
        }
    ],
    "sg:phone":"+1 864 942 0674",
    "sg:postcode":"29649",
    "sg:province":"SC",
    "wof:name":"Education Enrichment Fndtn",
    "wof:placetype":"venue"
},
  "geometry": {"coordinates":[-82.166487,34.197854],"type":"Point"}
}