{
  "type": "Feature",
  "properties": {
    "iso:country":"US",
    "sg:address":"1004 Chester St",
    "sg:city":"Myrtle Beach",
    "sg:classifiers":[
        {
            "category":"Shopping",
            "subcategory":"Discount & Variety Stores",
            "type":"Retail Goods"
        }
    ],
    "sg:phone":"+1 843 445 7858",
    "sg:postcode":"29577",
    "sg:province":"SC",
    "wof:name":"Two Dollar Bills",
    "wof:placetype":"venue"
},
  "geometry": {"coordinates":[-78.879441,33.694816],"type":"Point"}
}