{
  "type": "Feature",
  "properties": {
    "iso:country":"US",
    "sg:address":"407 Church St",
    "sg:city":"Georgetown",
    "sg:classifiers":[
        {
            "category":"Organizations",
            "subcategory":"Non-profit Organization",
            "type":"Services"
        }
    ],
    "sg:phone":"+1 843 545 1271",
    "sg:postcode":"29440",
    "sg:province":"SC",
    "sg:tags":[
        "information",
        "alcoholism",
        "treatment"
    ],
    "wof:name":"Counseling Associates",
    "wof:placetype":"venue"
},
  "geometry": {"coordinates":[-79.27558,33.36831],"type":"Point"}
}