{
  "type": "Feature",
  "properties": {
    "iso:country":"US",
    "sg:address":"300 Hearon Cir",
    "sg:city":"Spartanburg",
    "sg:classifiers":[
        {
            "category":"Wholesale",
            "subcategory":"Auto Parts",
            "type":"Manufacturing & Wholesale Goods"
        }
    ],
    "sg:phone":"+1 864 583 3123",
    "sg:postcode":"29303",
    "sg:province":"SC",
    "sg:tags":[
        "tire"
    ],
    "wof:name":"Fix A Flat",
    "wof:placetype":"venue"
},
  "geometry": {"coordinates":[-81.971926,34.984375],"type":"Point"}
}