{
  "type": "Feature",
  "properties": {
    "iso:country":"US",
    "sg:address":"16 Fiddlerville Cove",
    "sg:city":"Beaufort",
    "sg:classifiers":[
        {
            "category":"Travel",
            "subcategory":"Campground",
            "type":"Entertainment"
        }
    ],
    "sg:phone":"+1 843 846 4360",
    "sg:postcode":"29906",
    "sg:province":"SC",
    "wof:name":"Driftwood Apts & Campsite",
    "wof:placetype":"venue"
},
  "geometry": {"coordinates":[-80.746565,32.50384],"type":"Point"}
}