{
  "type": "Feature",
  "properties": {
    "iso:country":"US",
    "sg:address":"101 E Lydia Hwy",
    "sg:city":"Hartsville",
    "sg:classifiers":[
        {
            "category":"Bars & Pubs",
            "type":"Food & Drink"
        }
    ],
    "sg:phone":"+1 843 332 4412",
    "sg:postcode":"29550",
    "sg:province":"SC",
    "sg:tags":[
        "drinking"
    ],
    "wof:name":"Crossroad Bar",
    "wof:placetype":"venue"
},
  "geometry": {"coordinates":[-80.08414399999999,34.300653],"type":"Point"}
}