{
  "type": "Feature",
  "properties": {
    "iso:country":"US",
    "sg:address":"1826 Hayword Ln",
    "sg:city":"Fort Mill",
    "sg:classifiers":[
        {
            "category":"Banks & Credit Unions",
            "subcategory":"Financial Services",
            "type":"Services"
        }
    ],
    "sg:phone":"+1 704 239 5320",
    "sg:postcode":"29715",
    "sg:province":"SC",
    "sg:tags":[
        "investor"
    ],
    "wof:name":"Will Strong Investments Inc",
    "wof:placetype":"venue"
},
  "geometry": {"coordinates":[-80.89884499999999,35.001072],"type":"Point"}
}