{
  "type": "Feature",
  "properties": {
    "iso:country":"US",
    "sg:address":"121 S Jones Rd",
    "sg:city":"Olanta",
    "sg:classifiers":[
        {
            "category":"Shopping",
            "subcategory":"Gifts & Souvenirs",
            "type":"Retail Goods"
        }
    ],
    "sg:phone":"+1 843 396 9132",
    "sg:postcode":"29114",
    "sg:province":"SC",
    "sg:tags":[
        "collectible"
    ],
    "wof:name":"Coker's Game Room/Collectibles",
    "wof:placetype":"venue"
},
  "geometry": {"coordinates":[-79.935176,33.936445],"type":"Point"}
}