{
  "type": "Feature",
  "properties": {
    "addr:full":"1544 Hwy 9 W Dillon SC 29536",
    "addr:housenumber":"1544",
    "addr:postcode":"29536",
    "addr:street":"Hwy 9 W",
    "iso:country":"US",
    "sg:address":"1544 Hwy 9 W",
    "sg:city":"Dillon",
    "sg:classifiers":[
        {
            "category":"Manufacturing",
            "subcategory":"Textiles",
            "type":"Manufacturing & Wholesale Goods"
        }
    ],
    "sg:phone":"+1 843 774 2775",
    "sg:postcode":"29536",
    "sg:province":"SC",
    "sg:tags":[
        "mills",
        "yarn"
    ],
    "sg:website":"www.mohawkind.com",
    "wof:name":"Mohawk Industries Inc",
    "wof:placetype":"venue"
},
  "geometry": {"coordinates":[-79.377095,34.449225],"type":"Point"}
}