{
  "type": "Feature",
  "properties": {
    "iso:country":"US",
    "sg:address":"2854 Wade Hampton Blvd",
    "sg:city":"Taylors",
    "sg:classifiers":[
        {
            "category":"Manufacturing",
            "subcategory":"Paper Products",
            "type":"Manufacturing & Wholesale Goods"
        }
    ],
    "sg:phone":"+1 864 268 3664",
    "sg:postcode":"29687",
    "sg:province":"SC",
    "sg:tags":[
        "mill"
    ],
    "wof:name":"International Paper",
    "wof:placetype":"venue"
},
  "geometry": {"coordinates":[-82.33660999999999,34.900438],"type":"Point"}
}