{
  "type": "Feature",
  "properties": {
    "iso:country":"US",
    "sg:address":"8603 Old State Rd",
    "sg:city":"Holly Hill",
    "sg:classifiers":[
        {
            "category":"Organizations",
            "subcategory":"Professional Association",
            "type":"Services"
        }
    ],
    "sg:phone":"+1 803 496 3831",
    "sg:postcode":"29059",
    "sg:province":"SC",
    "sg:tags":[
        "chambers",
        "commerce"
    ],
    "wof:name":"Tri-County Regional Chamber",
    "wof:placetype":"venue"
},
  "geometry": {"coordinates":[-80.411909,33.321708],"type":"Point"}
}