{
  "type": "Feature",
  "properties": {
    "iso:country":"US",
    "sg:address":"116 Ballentine Ln",
    "sg:city":"Chapin",
    "sg:classifiers":[
        {
            "category":"Shopping",
            "type":"Retail Goods"
        }
    ],
    "sg:phone":"+1 803 345 1290",
    "sg:postcode":"29036",
    "sg:province":"SC",
    "sg:tags":[
        "merchandise"
    ],
    "wof:name":"Beautiful Bargains",
    "wof:placetype":"venue"
},
  "geometry": {"coordinates":[-81.354131,34.083422],"type":"Point"}
}