{
  "type": "Feature",
  "properties": {
    "iso:country":"US",
    "sg:address":"3991 Dick Pond Rd",
    "sg:city":"Myrtle Beach",
    "sg:classifiers":[
        {
            "category":"Real Estate",
            "subcategory":"Real Estate Agent",
            "type":"Services"
        }
    ],
    "sg:phone":"+1 843 215 1886",
    "sg:postcode":"29588",
    "sg:province":"SC",
    "wof:name":"Bigham Winn",
    "wof:placetype":"venue"
},
  "geometry": {"coordinates":[-78.992535,33.657086],"type":"Point"}
}