{
  "type": "Feature",
  "properties": {
    "addr:full":"50 Commerce Center Greenville SC 29615",
    "addr:housenumber":"50",
    "addr:postcode":"29615",
    "addr:street":"Commerce Center",
    "iso:country":"US",
    "sg:address":"50 Commerce Center",
    "sg:city":"Greenville",
    "sg:classifiers":[
        {
            "category":"Wholesale",
            "subcategory":"Apparel",
            "type":"Manufacturing & Wholesale Goods"
        }
    ],
    "sg:phone":"+1 864 234 0322",
    "sg:postcode":"29615",
    "sg:province":"SC",
    "sg:tags":[
        "mill",
        "piece",
        "fabric",
        "cotton"
    ],
    "sg:website":"www.soltexinternational.com",
    "wof:name":"Radici Soltex Inc",
    "wof:placetype":"venue"
},
  "geometry": {"coordinates":[-82.24610199999999,34.852268],"type":"Point"}
}