{
  "type": "Feature",
  "properties": {
    "iso:country":"US",
    "sg:address":"2431 Pinckney Rd",
    "sg:city":"Chester",
    "sg:classifiers":[
        {
            "category":"Utilities",
            "subcategory":"Refuse",
            "type":"Services"
        }
    ],
    "sg:phone":"+1 803 385 6826",
    "sg:postcode":"29706",
    "sg:province":"SC",
    "sg:tags":[
        "system"
    ],
    "wof:name":"Recycling Center",
    "wof:placetype":"venue"
},
  "geometry": {"coordinates":[-81.34537899999999,34.749849],"type":"Point"}
}