{
  "type": "Feature",
  "properties": {
    "iso:country":"US",
    "sg:address":"116 Airport Rd",
    "sg:city":"Bishopville",
    "sg:classifiers":[
        {
            "category":"Building & Trades",
            "subcategory":"Construction",
            "type":"Services"
        }
    ],
    "sg:phone":"+1 803 484 6196",
    "sg:postcode":"29010",
    "sg:province":"SC",
    "sg:tags":[
        "grading",
        "contractor"
    ],
    "wof:name":"Lee County Public Works",
    "wof:placetype":"venue"
},
  "geometry": {"coordinates":[-80.23870100000001,34.240382],"type":"Point"}
}