{
  "type": "Feature",
  "properties": {
    "addr:full":"4229 Savannah Hwy Ravenel SC 29470",
    "addr:housenumber":"4229",
    "addr:postcode":"29470",
    "addr:street":"Savannah Hwy",
    "iso:country":"US",
    "sg:address":"4229 Savannah Hwy",
    "sg:city":"Ravenel",
    "sg:classifiers":[
        {
            "category":"Wholesale",
            "subcategory":"Scrap",
            "type":"Manufacturing & Wholesale Goods"
        }
    ],
    "sg:phone":"+1 843 766 3827",
    "sg:postcode":"29470",
    "sg:province":"SC",
    "sg:tags":[
        "material"
    ],
    "wof:name":"Charleston Steel & Metal Co",
    "wof:placetype":"venue"
},
  "geometry": {"coordinates":[-80.145841,32.786405],"type":"Point"}
}