{
  "type": "Feature",
  "properties": {
    "iso:country":"US",
    "sg:address":"3275 Merlene Nixon Rd",
    "sg:city":"Rembert",
    "sg:classifiers":[
        {
            "category":"Building & Trades",
            "subcategory":"Construction",
            "type":"Services"
        }
    ],
    "sg:phone":"+1 803 499 7884",
    "sg:postcode":"29128",
    "sg:province":"SC",
    "sg:tags":[
        "painter"
    ],
    "wof:name":"James Paint Co",
    "wof:placetype":"venue"
},
  "geometry": {"coordinates":[-80.532775,34.030975],"type":"Point"}
}