{
  "type": "Feature",
  "properties": {
    "iso:country":"US",
    "sg:address":"201 Ivy Acres Dr",
    "sg:city":"Piedmont",
    "sg:classifiers":[
        {
            "category":"Travel",
            "subcategory":"Campground",
            "type":"Entertainment"
        }
    ],
    "sg:phone":"+1 864 220 9680",
    "sg:postcode":"29673",
    "sg:province":"SC",
    "wof:name":"Ivy Acres",
    "wof:placetype":"venue"
},
  "geometry": {"coordinates":[-82.47173,34.741191],"type":"Point"}
}