{
  "type": "Feature",
  "properties": {
    "iso:country":"US",
    "sg:address":"1800 State St",
    "sg:city":"Cayce",
    "sg:classifiers":[
        {
            "category":"Recreation",
            "subcategory":"Marina",
            "type":"Entertainment"
        }
    ],
    "sg:phone":"+1 803 796 1983",
    "sg:postcode":"29033",
    "sg:province":"SC",
    "sg:tags":[
        "repairing",
        "boat"
    ],
    "wof:name":"R B Marine Svc",
    "wof:placetype":"venue"
},
  "geometry": {"coordinates":[-81.053232,33.9764],"type":"Point"}
}