{
  "type": "Feature",
  "properties": {
    "addr:full":"1117 Augusta St West Columbia SC 29169",
    "addr:housenumber":"1117",
    "addr:postcode":"29169",
    "addr:street":"Augusta St",
    "iso:country":"US",
    "sg:address":"1117 Augusta St",
    "sg:city":"West Columbia",
    "sg:classifiers":[
        {
            "category":"Manufacturing",
            "subcategory":"Signs",
            "type":"Manufacturing & Wholesale Goods"
        }
    ],
    "sg:phone":"+1 803 939 9007",
    "sg:postcode":"29169",
    "sg:province":"SC",
    "sg:tags":[
        "specialty",
        "mfg"
    ],
    "wof:name":"Signature Signs",
    "wof:placetype":"venue"
},
  "geometry": {"coordinates":[-81.069791,33.988361],"type":"Point"}
}