{
  "type": "Feature",
  "properties": {
    "iso:country":"US",
    "sg:address":"905 Sand Bar Ferry Rd",
    "sg:city":"Beech Island",
    "sg:classifiers":[
        {
            "category":"Farming",
            "subcategory":"Nursery",
            "type":"Manufacturing & Wholesale Goods"
        },
        {
            "category":"Building & Trades",
            "subcategory":"Landscaping Services",
            "type":"Services"
        }
    ],
    "sg:phone":"+1 803 827 0331",
    "sg:postcode":"29842",
    "sg:province":"SC",
    "sg:tags":[
        "farm",
        "christmas",
        "tree",
        "sodding",
        "sod"
    ],
    "wof:name":"Mason's Master Turf Inc",
    "wof:placetype":"venue"
},
  "geometry": {"coordinates":[-81.910251,33.439719],"type":"Point"}
}