{
  "type": "Feature",
  "properties": {
    "addr:full":"1048 Hilton Sound Dr Chapin SC 29036",
    "addr:housenumber":"1048",
    "addr:postcode":"29036",
    "addr:street":"Hilton Sound Dr",
    "iso:country":"US",
    "sg:address":"1048 Hilton Sound Dr",
    "sg:city":"Chapin",
    "sg:classifiers":[
        {
            "category":"Manufacturing",
            "subcategory":"Tools & Machinery",
            "type":"Manufacturing & Wholesale Goods"
        }
    ],
    "sg:phone":"+1 803 345 3038",
    "sg:postcode":"29036",
    "sg:province":"SC",
    "sg:tags":[
        "construction",
        "industrial",
        "mfg"
    ],
    "wof:name":"Gradall Industries The",
    "wof:placetype":"venue"
},
  "geometry": {"coordinates":[-81.34041999999999,34.091998],"type":"Point"}
}