{
  "type": "Feature",
  "properties": {
    "iso:country":"US",
    "sg:address":"1025 Dorothy St",
    "sg:city":"Rock Hill",
    "sg:classifiers":[
        {
            "category":"Shopping",
            "subcategory":"Bicycles & Sporting Goods",
            "type":"Retail Goods"
        }
    ],
    "sg:phone":"+1 803 327 9969",
    "sg:postcode":"29732",
    "sg:province":"SC",
    "wof:name":"Sports Shack",
    "wof:placetype":"venue"
},
  "geometry": {"coordinates":[-81.015646,34.954837],"type":"Point"}
}