{
  "type": "Feature",
  "properties": {
    "iso:country":"US",
    "sg:address":"1071 Morrison Dr",
    "sg:city":"Charleston",
    "sg:classifiers":[
        {
            "category":"Marine",
            "type":"Transportation"
        }
    ],
    "sg:phone":"+1 843 577 7714",
    "sg:postcode":"29403",
    "sg:province":"SC",
    "sg:tags":[
        "harbor",
        "launch"
    ],
    "wof:name":"Harbor Launch Linehandling Svc",
    "wof:placetype":"venue"
},
  "geometry": {"coordinates":[-79.94778599999999,32.810443],"type":"Point"}
}