{
  "type": "Feature",
  "properties": {
    "iso:country":"US",
    "sg:address":"4253 Sea Mountain Hwy",
    "sg:city":"Little River",
    "sg:classifiers":[
        {
            "category":"Personal",
            "subcategory":"Tanning Parlor",
            "type":"Services"
        }
    ],
    "sg:phone":"+1 843 399 6692",
    "sg:postcode":"29566",
    "sg:province":"SC",
    "sg:tags":[
        "salon"
    ],
    "wof:name":"Savage Tan",
    "wof:placetype":"venue"
},
  "geometry": {"coordinates":[-78.668296,33.866244],"type":"Point"}
}