{
  "type": "Feature",
  "properties": {
    "iso:country":"US",
    "sg:address":"3025 Ashley Phosphate Rd",
    "sg:city":"North Charleston",
    "sg:classifiers":[
        {
            "category":"Personal",
            "subcategory":"Beauty Salon",
            "type":"Services"
        }
    ],
    "sg:phone":"+1 843 767 2273",
    "sg:postcode":"29418",
    "sg:province":"SC",
    "sg:tags":[
        "cosmetologist"
    ],
    "wof:name":"Angie's Hair Salon",
    "wof:placetype":"venue"
},
  "geometry": {"coordinates":[-80.06167499999999,32.931243],"type":"Point"}
}