{
  "type": "Feature",
  "properties": {
    "iso:country":"US",
    "sg:address":"5563 W Shirley Dr",
    "sg:city":"North Charleston",
    "sg:classifiers":[
        {
            "category":"Wholesale",
            "subcategory":"Vending Machines",
            "type":"Manufacturing & Wholesale Goods"
        }
    ],
    "sg:phone":"+1 843 554 8845",
    "sg:postcode":"29418",
    "sg:province":"SC",
    "wof:name":"R & T Snack Time Inc",
    "wof:placetype":"venue"
},
  "geometry": {"coordinates":[-80.054248,32.857753],"type":"Point"}
}