{
  "type": "Feature",
  "properties": {
    "iso:country":"US",
    "sg:address":"264 Mount Calvary Rd",
    "sg:city":"Dillon",
    "sg:classifiers":[
        {
            "category":"Food & Beverages",
            "subcategory":"Groceries & Convenience Stores",
            "type":"Retail Goods"
        }
    ],
    "sg:phone":"+1 843 841 1612",
    "sg:postcode":"29536",
    "sg:province":"SC",
    "wof:name":"Kwic Shop",
    "wof:placetype":"venue"
},
  "geometry": {"coordinates":[-79.327849,34.410767],"type":"Point"}
}