{
  "type": "Feature",
  "properties": {
    "iso:country":"US",
    "sg:address":"2306 Chesnee Hwy",
    "sg:city":"Spartanburg",
    "sg:classifiers":[
        {
            "category":"Professional",
            "subcategory":"Accounting & Tax Preparation",
            "type":"Services"
        }
    ],
    "sg:phone":"+1 864 583 5422",
    "sg:postcode":"29303",
    "sg:province":"SC",
    "sg:tags":[
        "return",
        "filing"
    ],
    "wof:name":"Handy Tax & Bookkeeping Svc",
    "wof:placetype":"venue"
},
  "geometry": {"coordinates":[-81.895274,35.024532],"type":"Point"}
}