{
  "type": "Feature",
  "properties": {
    "iso:country":"US",
    "sg:address":"134 Owens Dr",
    "sg:city":"Ridgeville",
    "sg:classifiers":[
        {
            "category":"Restaurant",
            "type":"Food & Drink"
        }
    ],
    "sg:phone":"+1 843 871 1131",
    "sg:postcode":"29472",
    "sg:province":"SC",
    "sg:tags":[
        "eating"
    ],
    "wof:name":"Gbc Partnership LLC",
    "wof:placetype":"venue"
},
  "geometry": {"coordinates":[-80.299091,33.101176],"type":"Point"}
}