{
  "type": "Feature",
  "properties": {
    "iso:country":"US",
    "sg:address":"410 Oakland Ave",
    "sg:city":"Rock Hill",
    "sg:classifiers":[
        {
            "category":"Personal",
            "type":"Services"
        }
    ],
    "sg:phone":"+1 803 328 6659",
    "sg:postcode":"29730",
    "sg:province":"SC",
    "sg:tags":[
        "therapist",
        "massage"
    ],
    "wof:name":"Bodyworks Therapeutic Massage",
    "wof:placetype":"venue"
},
  "geometry": {"coordinates":[-81.027308,34.936266],"type":"Point"}
}