{
  "type": "Feature",
  "properties": {
    "addr:full":"100 Lee St West Columbia SC 29170",
    "addr:housenumber":"100",
    "addr:postcode":"29170",
    "addr:street":"Lee St",
    "iso:country":"US",
    "sg:address":"100 Lee St",
    "sg:city":"West Columbia",
    "sg:classifiers":[
        {
            "category":"Bars & Pubs",
            "type":"Food & Drink"
        }
    ],
    "sg:phone":"+1 803 822 8608",
    "sg:postcode":"29170",
    "sg:province":"SC",
    "sg:tags":[
        "drinking",
        "nightlife"
    ],
    "wof:name":"Skyline Club the",
    "wof:placetype":"venue"
},
  "geometry": {"coordinates":[-81.110703,33.9464],"type":"Point"}
}