{
  "type": "Feature",
  "properties": {
    "iso:country":"US",
    "sg:address":"1509 King St",
    "sg:city":"Beaufort",
    "sg:classifiers":[
        {
            "category":"Arts & Performance",
            "subcategory":"Theater",
            "type":"Entertainment"
        }
    ],
    "sg:phone":"+1 843 524 1117",
    "sg:postcode":"29902",
    "sg:province":"SC",
    "wof:name":"Byrne Miller Dance Theatre",
    "wof:placetype":"venue"
},
  "geometry": {"coordinates":[-80.67951499999999,32.434573],"type":"Point"}
}