{
  "type": "Feature",
  "properties": {
    "iso:country":"US",
    "sg:address":"210 State Hwy 90 E",
    "sg:city":"Little River",
    "sg:classifiers":[
        {
            "category":"Restaurant",
            "type":"Food & Drink"
        }
    ],
    "sg:phone":"+1 843 249 5533",
    "sg:postcode":"29566",
    "sg:province":"SC",
    "wof:name":"Mama Jean Restaurant",
    "wof:placetype":"venue"
},
  "geometry": {"coordinates":[-78.664827,33.855738],"type":"Point"}
}