{
  "type": "Feature",
  "properties": {
    "addr:full":"2320 Cosgrove Ave Charleston SC 29405",
    "addr:housenumber":"2320",
    "addr:postcode":"29405",
    "addr:street":"Cosgrove Ave",
    "iso:country":"US",
    "sg:address":"2320 Cosgrove Ave",
    "sg:city":"Charleston",
    "sg:classifiers":[
        {
            "category":"Health Services",
            "subcategory":"Doctor",
            "type":"Services"
        }
    ],
    "sg:phone":"+1 843 554 5003",
    "sg:postcode":"29405",
    "sg:province":"SC",
    "sg:tags":[
        "dentist"
    ],
    "wof:name":"Oral & Maxillofacial Surgery",
    "wof:placetype":"venue"
},
  "geometry": {"coordinates":[-79.97937400000001,32.84697],"type":"Point"}
}