{
  "type": "Feature",
  "properties": {
    "addr:full":"101 S Shelby St Blacksburg SC 29702",
    "addr:housenumber":"101",
    "addr:postcode":"29702",
    "addr:street":"S Shelby St",
    "iso:country":"US",
    "sg:address":"101 S Shelby St",
    "sg:city":"Blacksburg",
    "sg:classifiers":[
        {
            "category":"Government",
            "subcategory":"Police Station",
            "type":"Public Place"
        }
    ],
    "sg:phone":"+1 864 839 2331",
    "sg:postcode":"29702",
    "sg:province":"SC",
    "sg:tags":[
        "department"
    ],
    "wof:name":"Blacksburg Police Dept",
    "wof:placetype":"venue"
},
  "geometry": {"coordinates":[-81.515788,35.121221],"type":"Point"}
}