{
  "type": "Feature",
  "properties": {
    "addr:full":"800 Wright Ave Greenwood SC 29646",
    "addr:housenumber":"800",
    "addr:postcode":"29646",
    "addr:street":"Wright Ave",
    "iso:country":"US",
    "sg:address":"800 Wright Ave",
    "sg:city":"Greenwood",
    "sg:classifiers":[
        {
            "category":"Organizations",
            "subcategory":"Religious Organization",
            "type":"Services"
        }
    ],
    "sg:phone":"+1 864 227 2963",
    "sg:postcode":"29646",
    "sg:province":"SC",
    "sg:tags":[
        "church"
    ],
    "wof:name":"Mathews United Methodist Chr",
    "wof:placetype":"venue"
},
  "geometry": {"coordinates":[-82.148657,34.157489],"type":"Point"}
}