{
  "type": "Feature",
  "properties": {
    "addr:full":"4172 Olanta Hwy Timmonsville SC 29591",
    "addr:housenumber":"4172",
    "addr:postcode":"29591",
    "addr:street":"Olanta Hwy",
    "iso:country":"US",
    "sg:address":"4172 Olanta Hwy",
    "sg:city":"Timmonsville",
    "sg:classifiers":[
        {
            "category":"Wholesale",
            "subcategory":"Electrical",
            "type":"Manufacturing & Wholesale Goods"
        }
    ],
    "sg:phone":"+1 843 346 7777",
    "sg:postcode":"29591",
    "sg:province":"SC",
    "sg:tags":[
        "parts",
        "electric",
        "motor"
    ],
    "wof:name":"Riverside Electric Motors Inc",
    "wof:placetype":"venue"
},
  "geometry": {"coordinates":[-79.880306,33.994251],"type":"Point"}
}