{
  "type": "Feature",
  "properties": {
    "iso:country":"US",
    "sg:address":"1680 Scuffletown Rd",
    "sg:city":"Fountain Inn",
    "sg:classifiers":[
        {
            "category":"Sports & Exercise",
            "subcategory":"Golf",
            "type":"Entertainment"
        }
    ],
    "sg:phone":"+1 864 862 4642",
    "sg:postcode":"29644",
    "sg:province":"SC",
    "sg:tags":[
        "course"
    ],
    "wof:name":"Carolina Springs Golf",
    "wof:placetype":"venue"
},
  "geometry": {"coordinates":[-82.188362,34.736876],"type":"Point"}
}