{
  "type": "Feature",
  "properties": {
    "iso:country":"US",
    "sg:address":"4812 Rivers Ave",
    "sg:city":"North Charleston",
    "sg:classifiers":[
        {
            "category":"Autos & Motor Vehicles",
            "subcategory":"Automobile Sales",
            "type":"Retail Goods"
        }
    ],
    "sg:phone":"+1 843 747 8060",
    "sg:postcode":"29406",
    "sg:province":"SC",
    "sg:tags":[
        "car",
        "dealer"
    ],
    "wof:name":"Big D's Auto Sales",
    "wof:placetype":"venue"
},
  "geometry": {"coordinates":[-80.005526,32.879555],"type":"Point"}
}