{
  "type": "Feature",
  "properties": {
    "addr:full":"324 Robert Smalls Pkwy Beaufort SC 29906",
    "addr:housenumber":"324",
    "addr:postcode":"29906",
    "addr:street":"Robert Smalls Pkwy",
    "iso:country":"US",
    "sg:address":"324 Robert Smalls Pkwy",
    "sg:city":"Beaufort",
    "sg:classifiers":[
        {
            "category":"Shopping",
            "subcategory":"Music",
            "type":"Retail Goods"
        }
    ],
    "sg:phone":"+1 843 522 6800",
    "sg:postcode":"29906",
    "sg:province":"SC",
    "sg:tags":[
        "compact",
        "record",
        "disc",
        "tape"
    ],
    "wof:name":"Sam Goody",
    "wof:placetype":"venue"
},
  "geometry": {"coordinates":[-80.730327,32.424684],"type":"Point"}
}