{
  "type": "Feature",
  "properties": {
    "iso:country":"US",
    "sg:address":"193 Bamert St",
    "sg:city":"Summerville",
    "sg:classifiers":[
        {
            "category":"Professional",
            "subcategory":"Business Services",
            "type":"Services"
        }
    ],
    "sg:phone":"+1 843 832 9150",
    "sg:postcode":"29483",
    "sg:province":"SC",
    "sg:tags":[
        "embroidery"
    ],
    "wof:name":"Bunka Embroidery Intl Inc",
    "wof:placetype":"venue"
},
  "geometry": {"coordinates":[-80.153213,33.022881],"type":"Point"}
}