{
  "type": "Feature",
  "properties": {
    "iso:country":"US",
    "sg:address":"367 S Georgetown Hwy",
    "sg:city":"Johnsonville",
    "sg:classifiers":[
        {
            "category":"Restaurant",
            "type":"Food & Drink"
        }
    ],
    "sg:menulink":"http://www.allmenus.com/sc/johnsonville/200919-mcdonalds/menu/",
    "sg:postcode":"29555",
    "sg:province":"SC",
    "sg:tags":[
        "burger",
        "american"
    ],
    "wof:name":"McDonald's",
    "wof:placetype":"venue"
},
  "geometry": {"coordinates":[-79.442454,33.809554],"type":"Point"}
}