{
  "type": "Feature",
  "properties": {
    "addr:full":"1305 Laurens Rd Greenville SC 29607",
    "addr:housenumber":"1305",
    "addr:postcode":"29607",
    "addr:street":"Laurens Rd",
    "iso:country":"US",
    "sg:address":"1305 Laurens Rd",
    "sg:city":"Greenville",
    "sg:classifiers":[
        {
            "category":"Professional",
            "subcategory":"Accounting & Tax Preparation",
            "type":"Services"
        }
    ],
    "sg:phone":"+1 864 232 6611",
    "sg:postcode":"29607",
    "sg:province":"SC",
    "sg:tags":[
        "return",
        "filing"
    ],
    "wof:name":"Action Tax Svc",
    "wof:placetype":"venue"
},
  "geometry": {"coordinates":[-82.363512,34.84395],"type":"Point"}
}