{
  "type": "Feature",
  "properties": {
    "iso:country":"US",
    "sg:address":"7612 Asheville Hwy",
    "sg:city":"Spartanburg",
    "sg:classifiers":[
        {
            "category":"Food & Beverages",
            "subcategory":"Groceries & Convenience Stores",
            "type":"Retail Goods"
        }
    ],
    "sg:phone":"+1 864 503 9081",
    "sg:postcode":"29303",
    "sg:province":"SC",
    "sg:tags":[
        "grocer"
    ],
    "wof:name":"Mi Tierra",
    "wof:placetype":"venue"
},
  "geometry": {"coordinates":[-81.982902,34.989145],"type":"Point"}
}