{
  "type": "Feature",
  "properties": {
    "addr:full":"2223 Bull St Columbia SC 29201",
    "addr:housenumber":"2223",
    "addr:postcode":"29201",
    "addr:street":"Bull St",
    "iso:country":"US",
    "sg:address":"2223 Bull St",
    "sg:city":"Columbia",
    "sg:classifiers":[
        {
            "category":"Real Estate",
            "subcategory":"Surveying",
            "type":"Services"
        }
    ],
    "sg:phone":"+1 803 252 1797",
    "sg:postcode":"29201",
    "sg:province":"SC",
    "sg:tags":[
        "surveyor"
    ],
    "wof:name":"Inman Land Surveying Co",
    "wof:placetype":"venue"
},
  "geometry": {"coordinates":[-81.035239,34.017371],"type":"Point"}
}