{
  "type": "Feature",
  "properties": {
    "iso:country":"US",
    "sg:address":"1224 State Hwy 72 Bus",
    "sg:city":"Greenwood",
    "sg:classifiers":[
        {
            "category":"Retail",
            "subcategory":"Laundry & Dry Cleaning",
            "type":"Services"
        }
    ],
    "sg:phone":"+1 864 223 7524",
    "sg:postcode":"29649",
    "sg:province":"SC",
    "sg:tags":[
        "cleaners"
    ],
    "wof:name":"Cambridge Pro Dry Cleaning",
    "wof:placetype":"venue"
},
  "geometry": {"coordinates":[-82.146294,34.208713],"type":"Point"}
}