{
  "type": "Feature",
  "properties": {
    "iso:country":"US",
    "sg:address":"13 Bent Oak Rd",
    "sg:city":"Beaufort",
    "sg:classifiers":[
        {
            "category":"Building & Trades",
            "subcategory":"Construction",
            "type":"Services"
        }
    ],
    "sg:phone":"+1 843 575 2444",
    "sg:postcode":"29907",
    "sg:province":"SC",
    "sg:tags":[
        "tile",
        "dealer"
    ],
    "wof:name":"A Smooth Edge Flooring",
    "wof:placetype":"venue"
},
  "geometry": {"coordinates":[-80.639412,32.422306],"type":"Point"}
}