{
  "type": "Feature",
  "properties": {
    "iso:country":"US",
    "sg:address":"4458 Fire Tower Rd",
    "sg:city":"Latta",
    "sg:phone":"+1 843 774 4629",
    "sg:postcode":"29565",
    "sg:province":"SC",
    "sg:tags":[
        "farm",
        "tobacco"
    ],
    "wof:name":"Long Farms Inc",
    "wof:placetype":"venue"
},
  "geometry": {"coordinates":[-79.540088,34.446776],"type":"Point"}
}