{
  "type": "Feature",
  "properties": {
    "iso:country":"US",
    "sg:address":"217 Lee Ave",
    "sg:city":"Hampton",
    "sg:classifiers":[
        {
            "category":"Personal",
            "subcategory":"Beauty Salon",
            "type":"Services"
        }
    ],
    "sg:phone":"+1 803 943 4112",
    "sg:postcode":"29924",
    "sg:province":"SC",
    "wof:name":"Mishonn's Platinum Beauty",
    "wof:placetype":"venue"
},
  "geometry": {"coordinates":[-81.107696,32.867656],"type":"Point"}
}