{
  "type": "Feature",
  "properties": {
    "addr:full":"3937 Sunset Blvd Ste G West Columbia SC 29169",
    "addr:housenumber":"3937",
    "addr:postcode":"29169",
    "addr:street":"Sunset Blvd Ste G",
    "iso:country":"US",
    "sg:address":"3937 Sunset Blvd Ste G",
    "sg:city":"West Columbia",
    "sg:classifiers":[
        {
            "category":"Health Services",
            "subcategory":"Doctor",
            "type":"Services"
        }
    ],
    "sg:phone":"+1 803 794 8776",
    "sg:postcode":"29169",
    "sg:province":"SC",
    "sg:tags":[
        "practice",
        "family"
    ],
    "wof:name":"Margalit Gal MD PA",
    "wof:placetype":"venue"
},
  "geometry": {"coordinates":[-81.14290699999999,34.007392],"type":"Point"}
}