{
  "type": "Feature",
  "properties": {
    "iso:country":"US",
    "sg:address":"532 Haywood Rd",
    "sg:city":"Greenville",
    "sg:classifiers":[
        {
            "category":"Shopping",
            "subcategory":"Jewelry",
            "type":"Retail Goods"
        }
    ],
    "sg:phone":"+1 864 297 5600",
    "sg:postcode":"29607",
    "sg:province":"SC",
    "sg:tags":[
        "jeweler"
    ],
    "sg:website":"www.halesjewelers.com",
    "wof:name":"Hale's Jewelers & Diamond",
    "wof:placetype":"venue"
},
  "geometry": {"coordinates":[-82.33857399999999,34.848262],"type":"Point"}
}