{
  "type": "Feature",
  "properties": {
    "iso:country":"US",
    "sg:address":"2632 Decker Blvd",
    "sg:city":"Columbia",
    "sg:classifiers":[
        {
            "category":"Restaurant",
            "type":"Food & Drink"
        }
    ],
    "sg:menulink":"http://www.allmenus.com/sc/columbia/215141-taco-bell/menu/",
    "sg:phone":"+1 803 736 0876",
    "sg:postcode":"29206",
    "sg:province":"SC",
    "sg:tags":[
        "mexican"
    ],
    "wof:name":"Taco Bell",
    "wof:placetype":"venue"
},
  "geometry": {"coordinates":[-80.952263,34.061507],"type":"Point"}
}