{
  "type": "Feature",
  "properties": {
    "iso:country":"US",
    "sg:address":"140 Waxhaws Trce",
    "sg:city":"Chapin",
    "sg:classifiers":[
        {
            "category":"Real Estate",
            "subcategory":"Real Estate Agent",
            "type":"Services"
        }
    ],
    "sg:phone":"+1 803 749 6753",
    "sg:postcode":"29036",
    "sg:province":"SC",
    "sg:tags":[
        "appraiser"
    ],
    "wof:name":"Sandspur Appraisal Svc Inc",
    "wof:placetype":"venue"
},
  "geometry": {"coordinates":[-81.29763,34.115257],"type":"Point"}
}