{
  "type": "Feature",
  "properties": {
    "addr:full":"1860 Woodruff Rd Greenville SC 29607",
    "addr:housenumber":"1860",
    "addr:postcode":"29607",
    "addr:street":"Woodruff Rd",
    "iso:country":"US",
    "sg:address":"1860 Woodruff Rd",
    "sg:city":"Greenville",
    "sg:classifiers":[
        {
            "category":"Shopping",
            "subcategory":"Computers & Home Electronics",
            "type":"Retail Goods"
        }
    ],
    "sg:phone":"+1 864 281 7902",
    "sg:postcode":"29607",
    "sg:province":"SC",
    "wof:name":"Radio Shack",
    "wof:placetype":"venue"
},
  "geometry": {"coordinates":[-82.272594,34.819445],"type":"Point"}
}