{
  "type": "Feature",
  "properties": {
    "iso:country":"US",
    "sg:address":"812 N Ocean Blvd",
    "sg:city":"Myrtle Beach",
    "sg:classifiers":[
        {
            "category":"Recreation",
            "subcategory":"Amusement Park",
            "type":"Entertainment"
        }
    ],
    "sg:phone":"+1 843 913 8200",
    "sg:postcode":"29577",
    "sg:province":"SC",
    "wof:name":"Myrtle Beach Pavilion",
    "wof:placetype":"venue"
},
  "geometry": {"coordinates":[-78.879829,33.691953],"type":"Point"}
}