{
  "type": "Feature",
  "properties": {
    "iso:country":"US",
    "sg:address":"760 Ship Wreck Pl",
    "sg:city":"Inman",
    "sg:classifiers":[
        {
            "category":"Insurance",
            "subcategory":"Insurance Agent",
            "type":"Services"
        }
    ],
    "sg:phone":"+1 864 472 9909",
    "sg:postcode":"29349",
    "sg:province":"SC",
    "wof:name":"Sam Copeland Insurance Svc",
    "wof:placetype":"venue"
},
  "geometry": {"coordinates":[-82.062605,35.041909],"type":"Point"}
}