{
  "type": "Feature",
  "properties": {
    "addr:full":"2115 Boundary St Beaufort SC 29902",
    "addr:housenumber":"2115",
    "addr:postcode":"29902",
    "addr:street":"Boundary St",
    "iso:country":"US",
    "sg:address":"2115 Boundary St",
    "sg:city":"Beaufort",
    "sg:classifiers":[
        {
            "category":"Banks & Credit Unions",
            "subcategory":"Bank",
            "type":"Services"
        }
    ],
    "sg:phone":"+1 843 521 6071",
    "sg:postcode":"29902",
    "sg:province":"SC",
    "wof:name":"Bank Of America",
    "wof:placetype":"venue"
},
  "geometry": {"coordinates":[-80.69237200000001,32.441425],"type":"Point"}
}