{
  "type": "Feature",
  "properties": {
    "iso:country":"US",
    "sg:address":"213 Atlantic Ave",
    "sg:city":"Murrells Inlet",
    "sg:classifiers":[
        {
            "category":"Restaurant",
            "type":"Food & Drink"
        }
    ],
    "sg:phone":"+1 843 357 7047",
    "sg:postcode":"29576",
    "sg:province":"SC",
    "wof:name":"Causeway Grill & Raw Bar",
    "wof:placetype":"venue"
},
  "geometry": {"coordinates":[-79.003075,33.579619],"type":"Point"}
}