{
  "type": "Feature",
  "properties": {
    "addr:full":"1529 Horseshoe Dr Columbia SC 29223",
    "addr:housenumber":"1529",
    "addr:postcode":"29223",
    "addr:street":"Horseshoe Dr",
    "iso:country":"US",
    "sg:address":"1529 Horseshoe Dr",
    "sg:city":"Columbia",
    "sg:classifiers":[
        {
            "category":"Banks & Credit Unions",
            "subcategory":"Investment Brokerage",
            "type":"Services"
        }
    ],
    "sg:phone":"+1 803 736 8989",
    "sg:postcode":"29223",
    "sg:province":"SC",
    "sg:tags":[
        "consultant",
        "financing"
    ],
    "wof:name":"GMS Consulting",
    "wof:placetype":"venue"
},
  "geometry": {"coordinates":[-80.946365,34.07517],"type":"Point"}
}