{
  "type": "Feature",
  "properties": {
    "addr:full":"5134 Calhoun Memorial Hwy Easley SC 29640",
    "addr:housenumber":"5134",
    "addr:postcode":"29640",
    "addr:street":"Calhoun Memorial Hwy",
    "iso:country":"US",
    "sg:address":"5134 Calhoun Memorial Hwy",
    "sg:city":"Easley",
    "sg:classifiers":[
        {
            "category":"Building & Trades",
            "subcategory":"Equipment Rental",
            "type":"Services"
        }
    ],
    "sg:phone":"+1 864 855 1173",
    "sg:postcode":"29640",
    "sg:province":"SC",
    "sg:tags":[
        "contractor"
    ],
    "wof:name":"Blue Ridge Rent-All",
    "wof:placetype":"venue"
},
  "geometry": {"coordinates":[-82.55484,34.824813],"type":"Point"}
}