{
  "type": "Feature",
  "properties": {
    "iso:country":"US",
    "sg:address":"400 Mallet Hill Rd",
    "sg:city":"Columbia",
    "sg:classifiers":[
        {
            "category":"Building & Trades",
            "subcategory":"Construction",
            "type":"Services"
        }
    ],
    "sg:phone":"+1 803 725 3623",
    "sg:postcode":"29223",
    "sg:province":"SC",
    "sg:tags":[
        "hanging",
        "contractor"
    ],
    "wof:name":"Savannah",
    "wof:placetype":"venue"
},
  "geometry": {"coordinates":[-80.88542,34.088049],"type":"Point"}
}