{
  "type": "Feature",
  "properties": {
    "iso:country":"US",
    "sg:address":"914 Chester St",
    "sg:city":"Myrtle Beach",
    "sg:classifiers":[
        {
            "category":"Retail",
            "subcategory":"Laundry & Dry Cleaning",
            "type":"Services"
        }
    ],
    "sg:phone":"+1 843 448 8148",
    "sg:postcode":"29577",
    "sg:province":"SC",
    "sg:tags":[
        "cleaners",
        "rug",
        "carpet"
    ],
    "wof:name":"Clean Rite Steamway",
    "wof:placetype":"venue"
},
  "geometry": {"coordinates":[-78.88033299999999,33.694039],"type":"Point"}
}