{
  "type": "Feature",
  "properties": {
    "addr:full":"2306 Chesnee Hwy Spartanburg SC 29303",
    "addr:housenumber":"2306",
    "addr:postcode":"29303",
    "addr:street":"Chesnee Hwy",
    "iso:country":"US",
    "sg:address":"2306 Chesnee Hwy",
    "sg:city":"Spartanburg",
    "sg:classifiers":[
        {
            "category":"Shopping",
            "subcategory":"Pharmacy",
            "type":"Retail Goods"
        }
    ],
    "sg:phone":"+1 864 577 0087",
    "sg:postcode":"29303",
    "sg:province":"SC",
    "wof:name":"Peach Valley Pharmacy Inc",
    "wof:placetype":"venue"
},
  "geometry": {"coordinates":[-81.895274,35.024532],"type":"Point"}
}