{
  "type": "Feature",
  "properties": {
    "iso:country":"US",
    "sg:address":"2450 Whitestone Glendale Rd",
    "sg:city":"Spartanburg",
    "sg:classifiers":[
        {
            "category":"Retail",
            "subcategory":"Auto Repair",
            "type":"Services"
        }
    ],
    "sg:phone":"+1 864 585 8739",
    "sg:postcode":"29302",
    "sg:province":"SC",
    "sg:tags":[
        "repairing",
        "automobile"
    ],
    "wof:name":"Automotive Associates",
    "wof:placetype":"venue"
},
  "geometry": {"coordinates":[-81.837636,34.926468],"type":"Point"}
}