{
  "type": "Feature",
  "properties": {
    "iso:country":"US",
    "sg:address":"3445 Hebron Rd",
    "sg:city":"Lake City",
    "sg:classifiers":[
        {
            "category":"Professional",
            "type":"Services"
        }
    ],
    "sg:phone":"+1 843 389 7729",
    "sg:postcode":"29560",
    "sg:province":"SC",
    "sg:tags":[
        "establishment"
    ],
    "wof:name":"Driggers Tax Svc",
    "wof:placetype":"venue"
},
  "geometry": {"coordinates":[-79.874521,33.854745],"type":"Point"}
}