{
  "type": "Feature",
  "properties": {
    "iso:country":"US",
    "sg:address":"205 Carolina Ave",
    "sg:city":"Moncks Corner",
    "sg:classifiers":[
        {
            "category":"Health Services",
            "subcategory":"Doctor",
            "type":"Services"
        }
    ],
    "sg:phone":"+1 843 761 8720",
    "sg:postcode":"29461",
    "sg:province":"SC",
    "sg:tags":[
        "dentist"
    ],
    "wof:name":"Michael C Hill DDS",
    "wof:placetype":"venue"
},
  "geometry": {"coordinates":[-80.006548,33.195008],"type":"Point"}
}