{
  "type": "Feature",
  "properties": {
    "iso:country":"US",
    "sg:address":"1911 Marshall St",
    "sg:city":"Columbia",
    "sg:classifiers":[
        {
            "category":"Health Services",
            "subcategory":"Doctor",
            "type":"Services"
        }
    ],
    "sg:phone":"+1 803 748 9658",
    "sg:postcode":"29203",
    "sg:province":"SC",
    "sg:tags":[
        "physician",
        "surgeon"
    ],
    "wof:name":"Hall Healthcare Of Carolinas",
    "wof:placetype":"venue"
},
  "geometry": {"coordinates":[-81.029158,34.030964],"type":"Point"}
}