{
  "type": "Feature",
  "properties": {
    "addr:full":"308 Dantzler St Saint Matthews SC 29115",
    "addr:housenumber":"308",
    "addr:postcode":"29115",
    "addr:street":"Dantzler St",
    "iso:country":"US",
    "sg:address":"308 Dantzler St",
    "sg:city":"Saint Matthews",
    "sg:classifiers":[
        {
            "category":"Manufacturing",
            "subcategory":"Lumber",
            "type":"Manufacturing & Wholesale Goods"
        }
    ],
    "sg:phone":"+1 803 655 5393",
    "sg:postcode":"29115",
    "sg:province":"SC",
    "sg:tags":[
        "operation",
        "timber",
        "tract"
    ],
    "wof:name":"Montgomery Forest Products",
    "wof:placetype":"venue"
},
  "geometry": {"coordinates":[-80.869866,33.501745],"type":"Point"}
}