{
  "type": "Feature",
  "properties": {
    "addr:full":"224 Briarcliff Rd Central SC 29630",
    "addr:housenumber":"224",
    "addr:postcode":"29630",
    "addr:street":"Briarcliff Rd",
    "iso:country":"US",
    "sg:address":"224 Briarcliff Rd",
    "sg:city":"Central",
    "sg:classifiers":[
        {
            "category":"Building & Trades",
            "subcategory":"Construction",
            "type":"Services"
        }
    ],
    "sg:phone":"+1 864 654 9624",
    "sg:postcode":"29630",
    "sg:province":"SC",
    "sg:tags":[
        "hanging",
        "contractor"
    ],
    "wof:name":"Sun Design",
    "wof:placetype":"venue"
},
  "geometry": {"coordinates":[-82.832072,34.729071],"type":"Point"}
}