{
  "type": "Feature",
  "properties": {
    "addr:full":"440 State Hwy 90 E Little River SC 29566",
    "addr:housenumber":"440",
    "addr:postcode":"29566",
    "addr:street":"State Hwy 90 E",
    "iso:country":"US",
    "sg:address":"440 State Hwy 90 E",
    "sg:city":"Little River",
    "sg:classifiers":[
        {
            "category":"Building & Trades",
            "subcategory":"Construction",
            "type":"Services"
        }
    ],
    "sg:phone":"+1 843 280 7105",
    "sg:postcode":"29566",
    "sg:province":"SC",
    "sg:tags":[
        "home",
        "builder"
    ],
    "wof:name":"Majestic Homes",
    "wof:placetype":"venue"
},
  "geometry": {"coordinates":[-78.647361,33.863252],"type":"Point"}
}