{
  "type": "Feature",
  "properties": {
    "iso:country":"US",
    "sg:address":"4304 Hard Scrabble Rd",
    "sg:city":"Columbia",
    "sg:classifiers":[
        {
            "category":"Banks & Credit Unions",
            "subcategory":"Bank",
            "type":"Services"
        }
    ],
    "sg:phone":"+1 803 419 3424",
    "sg:postcode":"29223",
    "sg:province":"SC",
    "wof:name":"First Palmetto Savings Bank",
    "wof:placetype":"venue"
},
  "geometry": {"coordinates":[-80.913581,34.14049],"type":"Point"}
}