{
  "type": "Feature",
  "properties": {
    "addr:full":"2537 Mack Arthur Rd Mullins SC 29574",
    "addr:housenumber":"2537",
    "addr:postcode":"29574",
    "addr:street":"Mack Arthur Rd",
    "iso:country":"US",
    "sg:address":"2537 Mack Arthur Rd",
    "sg:city":"Mullins",
    "sg:classifiers":[
        {
            "category":"Food & Beverages",
            "subcategory":"Fruits & Vegetables",
            "type":"Retail Goods"
        }
    ],
    "sg:phone":"+1 843 464 6583",
    "sg:postcode":"29574",
    "sg:province":"SC",
    "sg:tags":[
        "produce"
    ],
    "wof:name":"Wilson Produce",
    "wof:placetype":"venue"
},
  "geometry": {"coordinates":[-79.276126,34.155455],"type":"Point"}
}