{
  "type": "Feature",
  "properties": {
    "addr:full":"365 Bettis Academy Rd Graniteville SC 29829",
    "addr:housenumber":"365",
    "addr:postcode":"29829",
    "addr:street":"Rd",
    "iso:country":"US",
    "sg:address":"365 Bettis Academy Rd",
    "sg:city":"Graniteville",
    "sg:classifiers":[
        {
            "category":"Government",
            "subcategory":"Office",
            "type":"Public Place"
        }
    ],
    "sg:phone":"+1 803 663 7011",
    "sg:postcode":"29829",
    "sg:province":"SC",
    "sg:tags":[
        "federal",
        "security"
    ],
    "wof:name":"US Army National Guard",
    "wof:placetype":"venue"
},
  "geometry": {"coordinates":[-81.836749,33.591938],"type":"Point"}
}