{
  "type": "Feature",
  "properties": {
    "addr:full":"417 Pemberton St Waterloo SC 29384",
    "addr:housenumber":"417",
    "addr:postcode":"29384",
    "addr:street":"Pemberton St",
    "iso:country":"US",
    "sg:address":"417 Pemberton St",
    "sg:city":"Waterloo",
    "sg:classifiers":[
        {
            "category":"Building & Trades",
            "subcategory":"Construction",
            "type":"Services"
        }
    ],
    "sg:phone":"+1 864 677 3215",
    "sg:postcode":"29384",
    "sg:province":"SC",
    "sg:tags":[
        "hanging",
        "painter",
        "contractor"
    ],
    "wof:name":"R & L Painting & Home Imprvmnt",
    "wof:placetype":"venue"
},
  "geometry": {"coordinates":[-82.115284,34.31623],"type":"Point"}
}