{
  "type": "Feature",
  "properties": {
    "iso:country":"US",
    "sg:address":"1975 Magwood Dr",
    "sg:city":"Charleston",
    "sg:classifiers":[
        {
            "category":"Restaurant",
            "type":"Food & Drink"
        }
    ],
    "sg:phone":"+1 843 573 0100",
    "sg:postcode":"29414",
    "sg:province":"SC",
    "wof:name":"Baroni's Pizza",
    "wof:placetype":"venue"
},
  "geometry": {"coordinates":[-80.04133400000001,32.814821],"type":"Point"}
}