{
  "type": "Feature",
  "properties": {
    "iso:country":"US",
    "sg:address":"6941 Trenholm Rd",
    "sg:city":"Columbia",
    "sg:classifiers":[
        {
            "category":"Professional",
            "subcategory":"Management & Consulting",
            "type":"Services"
        }
    ],
    "sg:phone":"+1 803 622 4713",
    "sg:postcode":"29206",
    "sg:province":"SC",
    "sg:tags":[
        "consultant",
        "business"
    ],
    "wof:name":"Alan Abraham & Assoc",
    "wof:placetype":"venue"
},
  "geometry": {"coordinates":[-80.956953,34.061372],"type":"Point"}
}