{
  "type": "Feature",
  "properties": {
    "iso:country":"US",
    "sg:address":"38 Sheridan Park Cir",
    "sg:city":"Bluffton",
    "sg:classifiers":[
        {
            "category":"Wholesale",
            "subcategory":"Wine & Distilled Alcoholic Beverages",
            "type":"Manufacturing & Wholesale Goods"
        }
    ],
    "sg:phone":"+1 843 815 3020",
    "sg:postcode":"29910",
    "sg:province":"SC",
    "sg:website":"www.southernwine.com",
    "wof:name":"Southern Wine & Spirits of SC",
    "wof:placetype":"venue"
},
  "geometry": {"coordinates":[-80.859016,32.265499],"type":"Point"}
}