{
  "type": "Feature",
  "properties": {
    "iso:country":"US",
    "sg:address":"3 Town Center Ct",
    "sg:city":"Hilton Head Isle",
    "sg:classifiers":[
        {
            "category":"Government",
            "subcategory":"Court House",
            "type":"Public Place"
        }
    ],
    "sg:phone":"+1 843 842 4260",
    "sg:postcode":"29928",
    "sg:province":"SC",
    "sg:tags":[
        "county"
    ],
    "wof:name":"Magistrate Office",
    "wof:placetype":"venue"
},
  "geometry": {"coordinates":[-80.75411200000001,32.160224],"type":"Point"}
}