{
  "type": "Feature",
  "properties": {
    "iso:country":"US",
    "sg:address":"201 E Broad St",
    "sg:city":"Greenville",
    "sg:classifiers":[
        {
            "category":"Insurance",
            "subcategory":"Insurance Agent",
            "type":"Services"
        }
    ],
    "sg:phone":"+1 864 233 0222",
    "sg:postcode":"29601",
    "sg:province":"SC",
    "wof:name":"Samuel C McGee",
    "wof:placetype":"venue"
},
  "geometry": {"coordinates":[-82.39687000000001,34.846508],"type":"Point"}
}