{
  "type": "Feature",
  "properties": {
    "iso:country":"US",
    "sg:address":"135 Paddocks Bend",
    "sg:city":"Aiken",
    "sg:classifiers":[
        {
            "category":"Food & Beverages",
            "subcategory":"Groceries & Convenience Stores",
            "type":"Retail Goods"
        }
    ],
    "sg:phone":"+1 803 644 7244",
    "sg:postcode":"29803",
    "sg:province":"SC",
    "sg:tags":[
        "station",
        "gasoline"
    ],
    "wof:name":"Triple S LLC",
    "wof:placetype":"venue"
},
  "geometry": {"coordinates":[-81.768847,33.507431],"type":"Point"}
}