{
  "type": "Feature",
  "properties": {
    "iso:country":"US",
    "sg:address":"804 Meeting St",
    "sg:city":"Charleston",
    "sg:phone":"+1 843 723 9806",
    "sg:postcode":"29403",
    "sg:province":"SC",
    "sg:tags":[
        "equipment",
        "supply"
    ],
    "wof:name":"Acme Restaurant Supplies",
    "wof:placetype":"venue"
},
  "geometry": {"coordinates":[-79.94940200000001,32.810799],"type":"Point"}
}