{
  "type": "Feature",
  "properties": {
    "iso:country":"US",
    "sg:address":"630 E Washington St",
    "sg:city":"Greenville",
    "sg:classifiers":[
        {
            "category":"Professional",
            "subcategory":"Lawyer & Legal Services",
            "type":"Services"
        }
    ],
    "sg:phone":"+1 864 242 4050",
    "sg:postcode":"29601",
    "sg:province":"SC",
    "sg:tags":[
        "attorney"
    ],
    "wof:name":"Devlin & Parkinson",
    "wof:placetype":"venue"
},
  "geometry": {"coordinates":[-82.39298599999999,34.848876],"type":"Point"}
}