{
  "type": "Feature",
  "properties": {
    "iso:country":"US",
    "sg:address":"308 W Yellow Wood Dr",
    "sg:city":"Simpsonville",
    "sg:classifiers":[
        {
            "category":"Wholesale",
            "subcategory":"Electrical",
            "type":"Manufacturing & Wholesale Goods"
        }
    ],
    "sg:phone":"+1 864 963 4003",
    "sg:postcode":"29680",
    "sg:province":"SC",
    "sg:tags":[
        "wire",
        "cable"
    ],
    "wof:name":"A E Petsche Company Inc",
    "wof:placetype":"venue"
},
  "geometry": {"coordinates":[-82.274872,34.718508],"type":"Point"}
}