{
  "type": "Feature",
  "properties": {
    "iso:country":"US",
    "sg:address":"729 Beauregard St",
    "sg:city":"Charleston",
    "sg:classifiers":[
        {
            "category":"Building & Trades",
            "subcategory":"Construction",
            "type":"Services"
        }
    ],
    "sg:phone":"+1 843 762 4800",
    "sg:postcode":"29412",
    "sg:province":"SC",
    "sg:tags":[
        "house"
    ],
    "wof:name":"Els Construction",
    "wof:placetype":"venue"
},
  "geometry": {"coordinates":[-79.921864,32.751019],"type":"Point"}
}