{
  "type": "Feature",
  "properties": {
    "iso:country":"US",
    "sg:address":"2530 Millwood Ave",
    "sg:city":"Columbia",
    "sg:classifiers":[
        {
            "category":"Personal",
            "subcategory":"Beauty Salon",
            "type":"Services"
        }
    ],
    "sg:phone":"+1 803 933 0120",
    "sg:postcode":"29205",
    "sg:province":"SC",
    "wof:name":"Foxy's Ladies",
    "wof:placetype":"venue"
},
  "geometry": {"coordinates":[-81.006608,34.00438],"type":"Point"}
}