{
  "type": "Feature",
  "properties": {
    "addr:full":"7 Memorial Medical Dr Greenville SC 29605",
    "addr:housenumber":"7",
    "addr:postcode":"29605",
    "addr:street":"Medical Dr",
    "iso:country":"US",
    "sg:address":"7 Memorial Medical Dr",
    "sg:city":"Greenville",
    "sg:classifiers":[
        {
            "category":"Health Services",
            "subcategory":"Doctor",
            "type":"Services"
        }
    ],
    "sg:phone":"+1 864 295 2492",
    "sg:postcode":"29605",
    "sg:province":"SC",
    "sg:tags":[
        "physician",
        "surgeon"
    ],
    "wof:name":"Allergic Disease & Asthma Ctr",
    "wof:placetype":"venue"
},
  "geometry": {"coordinates":[-82.421204,34.816553],"type":"Point"}
}