{
  "type": "Feature",
  "properties": {
    "addr:full":"808 Powdersville Rd Easley SC 29642",
    "addr:housenumber":"808",
    "addr:postcode":"29642",
    "addr:street":"Powdersville Rd",
    "iso:country":"US",
    "sg:address":"808 Powdersville Rd",
    "sg:city":"Easley",
    "sg:classifiers":[
        {
            "category":"Real Estate",
            "subcategory":"Real Estate Agent",
            "type":"Services"
        }
    ],
    "sg:phone":"+1 864 306 3314",
    "sg:postcode":"29642",
    "sg:province":"SC",
    "wof:name":"Walsh Realty",
    "wof:placetype":"venue"
},
  "geometry": {"coordinates":[-82.55468,34.817376],"type":"Point"}
}