{
  "type": "Feature",
  "properties": {
    "iso:country":"US",
    "sg:address":"101 Barnado Rd",
    "sg:city":"Union",
    "sg:classifiers":[
        {
            "category":"Retail",
            "subcategory":"Repair Shop",
            "type":"Services"
        }
    ],
    "sg:phone":"+1 864 427 2644",
    "sg:postcode":"29379",
    "sg:province":"SC",
    "sg:tags":[
        "upholsterer"
    ],
    "wof:name":"Coleman Upholstery",
    "wof:placetype":"venue"
},
  "geometry": {"coordinates":[-81.634245,34.736883],"type":"Point"}
}