{
  "type": "Feature",
  "properties": {
    "iso:country":"US",
    "sg:address":"396 Water Tank Rd",
    "sg:city":"Pelion",
    "sg:classifiers":[
        {
            "category":"Building & Trades",
            "subcategory":"Construction",
            "type":"Services"
        }
    ],
    "sg:phone":"+1 803 413 2272",
    "sg:postcode":"29123",
    "sg:province":"SC",
    "sg:tags":[
        "heavy"
    ],
    "wof:name":"Franklin Owen Inc",
    "wof:placetype":"venue"
},
  "geometry": {"coordinates":[-81.325333,33.78598],"type":"Point"}
}