{
  "type": "Feature",
  "properties": {
    "addr:full":"4010 College St Newberry SC 29108",
    "addr:housenumber":"4010",
    "addr:postcode":"29108",
    "addr:street":"College St",
    "iso:country":"US",
    "sg:address":"4010 College St",
    "sg:city":"Newberry",
    "sg:classifiers":[
        {
            "category":"Autos & Motor Vehicles",
            "subcategory":"Auto Supplies",
            "type":"Retail Goods"
        }
    ],
    "sg:phone":"+1 803 276 5104",
    "sg:postcode":"29108",
    "sg:province":"SC",
    "sg:tags":[
        "tire"
    ],
    "wof:name":"GCR Tire Ctr",
    "wof:placetype":"venue"
},
  "geometry": {"coordinates":[-81.620063,34.301061],"type":"Point"}
}