{
  "type": "Feature",
  "properties": {
    "iso:country":"US",
    "sg:address":"1143 Counts Ferry Rd",
    "sg:city":"Lexington",
    "sg:classifiers":[
        {
            "category":"Building & Trades",
            "subcategory":"Plumbing",
            "type":"Services"
        }
    ],
    "sg:phone":"+1 803 359 9550",
    "sg:postcode":"29072",
    "sg:province":"SC",
    "sg:tags":[
        "refrigeration",
        "contractor"
    ],
    "wof:name":"All Star Air",
    "wof:placetype":"venue"
},
  "geometry": {"coordinates":[-81.347128,34.017792],"type":"Point"}
}