{
  "type": "Feature",
  "properties": {
    "addr:full":"955 Park St Columbia SC 29201",
    "addr:housenumber":"955",
    "addr:postcode":"29201",
    "addr:street":"Park St",
    "iso:country":"US",
    "sg:address":"955 Park St",
    "sg:city":"Columbia",
    "sg:classifiers":[
        {
            "category":"Government",
            "subcategory":"Office",
            "type":"Public Place"
        }
    ],
    "sg:phone":"+1 803 737 2314",
    "sg:postcode":"29201",
    "sg:province":"SC",
    "sg:tags":[
        "state",
        "program"
    ],
    "wof:name":"Transportation Dept",
    "wof:placetype":"venue"
},
  "geometry": {"coordinates":[-81.035416,33.996657],"type":"Point"}
}