{
  "type": "Feature",
  "properties": {
    "iso:country":"US",
    "sg:address":"21 Professional Ln",
    "sg:city":"Pawleys Island",
    "sg:classifiers":[
        {
            "category":"Real Estate",
            "subcategory":"Real Estate Agent",
            "type":"Services"
        }
    ],
    "sg:phone":"+1 843 979 2002",
    "sg:postcode":"29585",
    "sg:province":"SC",
    "sg:website":"www.remax.com",
    "wof:name":"Re/Max By The Sea",
    "wof:placetype":"venue"
},
  "geometry": {"coordinates":[-79.124892,33.441871],"type":"Point"}
}