{
  "type": "Feature",
  "properties": {
    "iso:country":"US",
    "sg:address":"615 Simuel Rd",
    "sg:city":"Spartanburg",
    "sg:classifiers":[
        {
            "category":"Autos & Motor Vehicles",
            "subcategory":"Auto Supplies",
            "type":"Retail Goods"
        }
    ],
    "sg:phone":"+1 864 587 1584",
    "sg:postcode":"29301",
    "sg:province":"SC",
    "sg:tags":[
        "tire"
    ],
    "wof:name":"White Tire",
    "wof:placetype":"venue"
},
  "geometry": {"coordinates":[-81.98506399999999,34.974081],"type":"Point"}
}