{
  "type": "Feature",
  "properties": {
    "iso:country":"US",
    "sg:address":"102 Two Gait Ln",
    "sg:city":"Simpsonville",
    "sg:classifiers":[
        {
            "category":"Real Estate",
            "subcategory":"Real Estate Operator",
            "type":"Services"
        }
    ],
    "sg:phone":"+1 864 228 6471",
    "sg:postcode":"29680",
    "sg:province":"SC",
    "sg:tags":[
        "building",
        "nonresidential"
    ],
    "wof:name":"T & S Properties Upstate LLC",
    "wof:placetype":"venue"
},
  "geometry": {"coordinates":[-82.26078699999999,34.707621],"type":"Point"}
}