{
  "type": "Feature",
  "properties": {
    "addr:full":"6 Poe St Greenville SC 29611",
    "addr:housenumber":"6",
    "addr:postcode":"29611",
    "addr:street":"Poe St",
    "iso:country":"US",
    "sg:address":"6 Poe St",
    "sg:city":"Greenville",
    "sg:classifiers":[
        {
            "category":"Wholesale",
            "subcategory":"Machinery & Supplies",
            "type":"Manufacturing & Wholesale Goods"
        },
        {
            "category":"Freight",
            "type":"Transportation"
        }
    ],
    "sg:phone":"+1 864 578 0900",
    "sg:postcode":"29611",
    "sg:province":"SC",
    "sg:tags":[
        "equipment",
        "commercial",
        "storage",
        "establishment"
    ],
    "wof:name":"Cardinal Moving & Storage Inc",
    "wof:placetype":"venue"
},
  "geometry": {"coordinates":[-82.42607700000001,34.870206],"type":"Point"}
}