{
  "type": "Feature",
  "properties": {
    "addr:full":"816 S Main St Lancaster SC 29720",
    "addr:housenumber":"816",
    "addr:postcode":"29720",
    "addr:street":"S Main St",
    "iso:country":"US",
    "sg:address":"816 S Main St",
    "sg:city":"Lancaster",
    "sg:classifiers":[
        {
            "category":"Autos & Motor Vehicles",
            "subcategory":"Auto Supplies",
            "type":"Retail Goods"
        }
    ],
    "sg:phone":"+1 803 283 3300",
    "sg:postcode":"29720",
    "sg:province":"SC",
    "sg:tags":[
        "tire"
    ],
    "wof:name":"Cody Tire Svc",
    "wof:placetype":"venue"
},
  "geometry": {"coordinates":[-80.765151,34.709458],"type":"Point"}
}