{
  "type": "Feature",
  "properties": {
    "iso:country":"US",
    "sg:address":"9922 N Kings Hwy",
    "sg:city":"Myrtle Beach",
    "sg:classifiers":[
        {
            "category":"Restaurant",
            "type":"Food & Drink"
        }
    ],
    "sg:phone":"+1 843 449 3984",
    "sg:postcode":"29572",
    "sg:province":"SC",
    "wof:name":"Chestnut Hill Restaurant",
    "wof:placetype":"venue"
},
  "geometry": {"coordinates":[-78.785993,33.783356],"type":"Point"}
}