{
  "type": "Feature",
  "properties": {
    "iso:country":"US",
    "sg:address":"104 Cliff Ridge Dr",
    "sg:city":"Cleveland",
    "sg:classifiers":[
        {
            "category":"Organizations",
            "subcategory":"Professional Association",
            "type":"Services"
        }
    ],
    "sg:phone":"+1 864 836 6845",
    "sg:postcode":"29635",
    "sg:province":"SC",
    "wof:name":"Cliff Ridge Colony",
    "wof:placetype":"venue"
},
  "geometry": {"coordinates":[-82.61701100000001,35.108251],"type":"Point"}
}