{
  "type": "Feature",
  "properties": {
    "addr:full":"922 Sunset Blvd West Columbia SC 29169",
    "addr:housenumber":"922",
    "addr:postcode":"29169",
    "addr:street":"Sunset Blvd",
    "iso:country":"US",
    "sg:address":"922 Sunset Blvd",
    "sg:city":"West Columbia",
    "sg:classifiers":[
        {
            "category":"Retail",
            "subcategory":"Laundry & Dry Cleaning",
            "type":"Services"
        }
    ],
    "sg:phone":"+1 803 936 9366",
    "sg:postcode":"29169",
    "sg:province":"SC",
    "wof:name":"My Best Cleaners",
    "wof:placetype":"venue"
},
  "geometry": {"coordinates":[-81.071297,33.997601],"type":"Point"}
}