{
  "type": "Feature",
  "properties": {
    "addr:full":"727 W Meeting St Lancaster SC 29720",
    "addr:housenumber":"727",
    "addr:postcode":"29720",
    "addr:street":"W Meeting St",
    "iso:country":"US",
    "sg:address":"727 W Meeting St",
    "sg:city":"Lancaster",
    "sg:classifiers":[
        {
            "category":"Health Services",
            "subcategory":"Doctor",
            "type":"Services"
        }
    ],
    "sg:phone":"+1 803 283 3461",
    "sg:postcode":"29720",
    "sg:province":"SC",
    "sg:tags":[
        "dentist"
    ],
    "wof:name":"Ira J Adams DDS",
    "wof:placetype":"venue"
},
  "geometry": {"coordinates":[-80.786205,34.716867],"type":"Point"}
}