{
  "type": "Feature",
  "properties": {
    "iso:country":"US",
    "sg:address":"2135 Devine St",
    "sg:city":"Columbia",
    "sg:classifiers":[
        {
            "category":"Restaurant",
            "type":"Food & Drink"
        }
    ],
    "sg:phone":"+1 803 252 8992",
    "sg:postcode":"29205",
    "sg:province":"SC",
    "sg:tags":[
        "thai"
    ],
    "sg:website":"baansawan.blogspot.com",
    "wof:name":"Baan Sawan Thai Bistro",
    "wof:placetype":"venue"
},
  "geometry": {"coordinates":[-81.01518299999999,33.998887],"type":"Point"}
}