{
  "type": "Feature",
  "properties": {
    "addr:full":"216 Caulder Cir Spartanburg SC 29306",
    "addr:housenumber":"216",
    "addr:postcode":"29306",
    "addr:street":"Caulder Cir",
    "iso:country":"US",
    "sg:address":"216 Caulder Cir",
    "sg:city":"Spartanburg",
    "sg:classifiers":[
        {
            "category":"Personal",
            "subcategory":"Beauty Salon",
            "type":"Services"
        }
    ],
    "sg:phone":"+1 864 583 0874",
    "sg:postcode":"29306",
    "sg:province":"SC",
    "wof:name":"Brina's Beauty Salon",
    "wof:placetype":"venue"
},
  "geometry": {"coordinates":[-81.923732,34.934047],"type":"Point"}
}