{
  "type": "Feature",
  "properties": {
    "addr:full":"4265 Augusta Rd Ste D Lexington SC 29073",
    "addr:housenumber":"4265",
    "addr:postcode":"29073",
    "addr:street":"Augusta Rd Ste D",
    "iso:country":"US",
    "sg:address":"4265 Augusta Rd Ste D",
    "sg:city":"Lexington",
    "sg:classifiers":[
        {
            "category":"Building & Trades",
            "subcategory":"Construction",
            "type":"Services"
        }
    ],
    "sg:phone":"+1 803 996 0112",
    "sg:postcode":"29073",
    "sg:province":"SC",
    "sg:tags":[
        "contractor"
    ],
    "wof:name":"Milan Homes Inc",
    "wof:placetype":"venue"
},
  "geometry": {"coordinates":[-81.148591,33.972209],"type":"Point"}
}