{
  "type": "Feature",
  "properties": {
    "addr:full":"1857 State Hwy 14 Greer SC 29650",
    "addr:housenumber":"1857",
    "addr:postcode":"29650",
    "addr:street":"State Hwy 14",
    "iso:country":"US",
    "sg:address":"1857 State Hwy 14",
    "sg:city":"Greer",
    "sg:classifiers":[
        {
            "category":"Manufacturing",
            "subcategory":"Glass & Minerals",
            "type":"Manufacturing & Wholesale Goods"
        }
    ],
    "sg:phone":"+1 864 879 4191",
    "sg:postcode":"29650",
    "sg:province":"SC",
    "sg:tags":[
        "ready"
    ],
    "wof:name":"Chapman Concrete Products Inc",
    "wof:placetype":"venue"
},
  "geometry": {"coordinates":[-82.234193,34.894948],"type":"Point"}
}