{
  "type": "Feature",
  "properties": {
    "iso:country":"US",
    "sg:address":"302 Berkshire Dr",
    "sg:city":"Columbia",
    "sg:classifiers":[
        {
            "category":"Freight",
            "type":"Transportation"
        }
    ],
    "sg:phone":"+1 803 788 8452",
    "sg:postcode":"29223",
    "sg:province":"SC",
    "sg:tags":[
        "commercial",
        "storage"
    ],
    "wof:name":"AAA Acme Storage/Shops",
    "wof:placetype":"venue"
},
  "geometry": {"coordinates":[-80.946878,34.073772],"type":"Point"}
}