{
  "type": "Feature",
  "properties": {
    "iso:country":"US",
    "sg:address":"1605 S Kings Hwy",
    "sg:city":"Myrtle Beach",
    "sg:classifiers":[
        {
            "category":"Shopping",
            "subcategory":"Clothing, Apparel, & Fashions",
            "type":"Retail Goods"
        }
    ],
    "sg:phone":"+1 843 448 6515",
    "sg:postcode":"29577",
    "sg:province":"SC",
    "sg:tags":[
        "beachwear"
    ],
    "wof:name":"Five Star Department Store",
    "wof:placetype":"venue"
},
  "geometry": {"coordinates":[-78.904185,33.675499],"type":"Point"}
}