{
  "type": "Feature",
  "properties": {
    "addr:full":"180 Columbia St Chester SC 29706",
    "addr:housenumber":"180",
    "addr:postcode":"29706",
    "addr:street":"Columbia St",
    "iso:country":"US",
    "sg:address":"180 Columbia St",
    "sg:city":"Chester",
    "sg:classifiers":[
        {
            "category":"Personal",
            "subcategory":"Beauty Salon",
            "type":"Services"
        }
    ],
    "sg:phone":"+1 803 581 5400",
    "sg:postcode":"29706",
    "sg:province":"SC",
    "wof:name":"Hair Connection",
    "wof:placetype":"venue"
},
  "geometry": {"coordinates":[-81.20855,34.69918],"type":"Point"}
}