{
  "type": "Feature",
  "properties": {
    "addr:full":"202 Anthony Dr Warrenville SC 29816",
    "addr:housenumber":"202",
    "addr:postcode":"29816",
    "addr:street":"Anthony Dr",
    "iso:country":"US",
    "sg:address":"202 Anthony Dr",
    "sg:city":"Warrenville",
    "sg:classifiers":[
        {
            "category":"Shopping",
            "type":"Retail Goods"
        }
    ],
    "sg:phone":"+1 803 593 6268",
    "sg:postcode":"29816",
    "sg:province":"SC",
    "sg:tags":[
        "monument"
    ],
    "wof:name":"First Impressions Building Svc",
    "wof:placetype":"venue"
},
  "geometry": {"coordinates":[-81.86244499999999,33.505739],"type":"Point"}
}