{
  "type": "Feature",
  "properties": {
    "iso:country":"US",
    "sg:address":"490 State Hwy 9 E",
    "sg:city":"Longs",
    "sg:classifiers":[
        {
            "category":"Restaurant",
            "type":"Food & Drink"
        }
    ],
    "sg:phone":"+1 843 399 5665",
    "sg:postcode":"29568",
    "sg:province":"SC",
    "wof:name":"Chris' Pizza & Subs & Salads",
    "wof:placetype":"venue"
},
  "geometry": {"coordinates":[-78.725916,33.923815],"type":"Point"}
}