{
  "type": "Feature",
  "properties": {
    "iso:country":"US",
    "sg:address":"108 Wilde Dr",
    "sg:city":"North Augusta",
    "sg:classifiers":[
        {
            "category":"Building & Trades",
            "subcategory":"Pest Control",
            "type":"Services"
        }
    ],
    "sg:phone":"+1 803 278 1131",
    "sg:postcode":"29841",
    "sg:province":"SC",
    "wof:name":"Mountaineer Pest Svc",
    "wof:placetype":"venue"
},
  "geometry": {"coordinates":[-81.945762,33.531649],"type":"Point"}
}