{
  "type": "Feature",
  "properties": {
    "addr:full":"330 N Fraser St Georgetown SC 29440",
    "addr:housenumber":"330",
    "addr:postcode":"29440",
    "addr:street":"N Fraser St",
    "iso:country":"US",
    "sg:address":"330 N Fraser St",
    "sg:city":"Georgetown",
    "sg:classifiers":[
        {
            "category":"Shopping",
            "subcategory":"Hobbies, Toys, & Games",
            "type":"Retail Goods"
        }
    ],
    "sg:phone":"+1 843 545 8324",
    "sg:postcode":"29440",
    "sg:province":"SC",
    "sg:tags":[
        "supply"
    ],
    "wof:name":"Scientific Games Intl Inc",
    "wof:placetype":"venue"
},
  "geometry": {"coordinates":[-79.287873,33.374587],"type":"Point"}
}