{
  "type": "Feature",
  "properties": {
    "iso:country":"US",
    "sg:address":"710 Albright Rd",
    "sg:city":"Rock Hill",
    "sg:classifiers":[
        {
            "category":"Shopping",
            "subcategory":"Computers & Home Electronics",
            "type":"Retail Goods"
        }
    ],
    "sg:phone":"+1 803 328 6177",
    "sg:postcode":"29730",
    "sg:province":"SC",
    "sg:tags":[
        "radio"
    ],
    "wof:name":"Custom Car Audio Inc",
    "wof:placetype":"venue"
},
  "geometry": {"coordinates":[-81.017094,34.909994],"type":"Point"}
}