{
  "type": "Feature",
  "properties": {
    "iso:country":"US",
    "sg:address":"6701 Notch Rd",
    "sg:city":"Columbia",
    "sg:classifiers":[
        {
            "category":"Personal",
            "subcategory":"Beauty Salon",
            "type":"Services"
        }
    ],
    "sg:phone":"+1 803 736 7640",
    "sg:postcode":"29223",
    "sg:province":"SC",
    "wof:name":"New Life",
    "wof:placetype":"venue"
},
  "geometry": {"coordinates":[-80.963787,34.059247],"type":"Point"}
}