{
  "type": "Feature",
  "properties": {
    "iso:country":"US",
    "sg:address":"2070 Columbia Rd NE",
    "sg:city":"Orangeburg",
    "sg:classifiers":[
        {
            "category":"Shopping",
            "subcategory":"Discount & Variety Stores",
            "type":"Retail Goods"
        },
        {
            "category":"Shopping",
            "subcategory":"Department Store",
            "type":"Retail Goods"
        }
    ],
    "sg:phone":"+1 803 536 0848",
    "sg:postcode":"29118",
    "sg:province":"SC",
    "sg:tags":[
        "shop"
    ],
    "wof:name":"Dollar General",
    "wof:placetype":"venue"
},
  "geometry": {"coordinates":[-80.865846,33.517042],"type":"Point"}
}