{
  "type": "Feature",
  "properties": {
    "addr:full":"24 Broad Oaks Cir Ridgeland SC 29906",
    "addr:housenumber":"24",
    "addr:postcode":"29906",
    "addr:street":"Broad Oaks Cir",
    "iso:country":"US",
    "sg:address":"24 Broad Oaks Cir",
    "sg:city":"Ridgeland",
    "sg:classifiers":[
        {
            "category":"Utilities",
            "subcategory":"Mobile Phone",
            "type":"Services"
        }
    ],
    "sg:phone":"+1 843 987 3913",
    "sg:postcode":"29906",
    "sg:province":"SC",
    "sg:tags":[
        "telephone",
        "cellular"
    ],
    "wof:name":"Alltel Communications",
    "wof:placetype":"venue"
},
  "geometry": {"coordinates":[-80.76466000000001,32.394479],"type":"Point"}
}