{
  "type": "Feature",
  "properties": {
    "iso:country":"US",
    "sg:address":"916 E Main St",
    "sg:city":"Spartanburg",
    "sg:classifiers":[
        {
            "category":"Shopping",
            "subcategory":"Used Merchandise",
            "type":"Retail Goods"
        }
    ],
    "sg:phone":"+1 864 582 7910",
    "sg:postcode":"29302",
    "sg:province":"SC",
    "wof:name":"New Second Imag Ladis Cnsgnmnt",
    "wof:placetype":"venue"
},
  "geometry": {"coordinates":[-81.908897,34.958596],"type":"Point"}
}