{
  "type": "Feature",
  "properties": {
    "iso:country":"US",
    "sg:address":"2755 Exchange Landing Rd",
    "sg:city":"Johns Island",
    "sg:classifiers":[
        {
            "category":"Farming",
            "subcategory":"Farm",
            "type":"Manufacturing & Wholesale Goods"
        }
    ],
    "sg:phone":"+1 843 768 8464",
    "sg:postcode":"29455",
    "sg:province":"SC",
    "sg:tags":[
        "crop",
        "general"
    ],
    "wof:name":"Valentine Farms LLC",
    "wof:placetype":"venue"
},
  "geometry": {"coordinates":[-80.019367,32.719797],"type":"Point"}
}