{
  "type": "Feature",
  "properties": {
    "iso:country":"US",
    "sg:address":"103 S Railroad Ave",
    "sg:city":"Lamar",
    "sg:classifiers":[
        {
            "category":"Home & Garden",
            "subcategory":"Hardware",
            "type":"Retail Goods"
        }
    ],
    "sg:phone":"+1 843 326 5131",
    "sg:postcode":"29069",
    "sg:province":"SC",
    "wof:name":"Andrews & Sons Inc",
    "wof:placetype":"venue"
},
  "geometry": {"coordinates":[-80.066244,34.169133],"type":"Point"}
}