{
  "type": "Feature",
  "properties": {
    "iso:country":"US",
    "sg:address":"601 S Parler Ave",
    "sg:city":"St George",
    "sg:classifiers":[
        {
            "category":"Government",
            "subcategory":"Police Station",
            "type":"Public Place"
        }
    ],
    "sg:phone":"+1 843 563 3643",
    "sg:postcode":"29477",
    "sg:province":"SC",
    "sg:tags":[
        "department"
    ],
    "wof:name":"St George Police Dept",
    "wof:placetype":"venue"
},
  "geometry": {"coordinates":[-80.57510600000001,33.172745],"type":"Point"}
}