{
  "type": "Feature",
  "properties": {
    "addr:full":"123 W Public Sq Laurens SC 29360",
    "addr:housenumber":"123",
    "addr:postcode":"29360",
    "addr:street":"W Public Sq",
    "iso:country":"US",
    "sg:address":"123 W Public Sq",
    "sg:city":"Laurens",
    "sg:classifiers":[
        {
            "category":"Real Estate",
            "subcategory":"Real Estate Agent",
            "type":"Services"
        }
    ],
    "sg:phone":"+1 864 681 6251",
    "sg:postcode":"29360",
    "sg:province":"SC",
    "wof:name":"MBL Properties LLC",
    "wof:placetype":"venue"
},
  "geometry": {"coordinates":[-82.015241,34.499103],"type":"Point"}
}