{
  "type": "Feature",
  "properties": {
    "addr:full":"52 Ginger Ln Kingstree SC 29556",
    "addr:housenumber":"52",
    "addr:postcode":"29556",
    "addr:street":"Ginger Ln",
    "iso:country":"US",
    "sg:address":"52 Ginger Ln",
    "sg:city":"Kingstree",
    "sg:classifiers":[
        {
            "category":"Freight",
            "type":"Transportation"
        }
    ],
    "sg:phone":"+1 843 382 3826",
    "sg:postcode":"29556",
    "sg:province":"SC",
    "sg:tags":[
        "operator",
        "local",
        "trucking"
    ],
    "wof:name":"R & V Hauling",
    "wof:placetype":"venue"
},
  "geometry": {"coordinates":[-79.877218,33.711773],"type":"Point"}
}