{
  "type": "Feature",
  "properties": {
    "iso:country":"US",
    "sg:address":"777 Reidville Rd",
    "sg:city":"Spartanburg",
    "sg:classifiers":[
        {
            "category":"Banks & Credit Unions",
            "subcategory":"Bank",
            "type":"Services"
        }
    ],
    "sg:phone":"+1 864 587 0044",
    "sg:postcode":"29306",
    "sg:province":"SC",
    "sg:tags":[
        "cashing",
        "check"
    ],
    "wof:name":"Money Line",
    "wof:placetype":"venue"
},
  "geometry": {"coordinates":[-81.95394,34.930296],"type":"Point"}
}