{
  "type": "Feature",
  "properties": {
    "addr:full":"401 Western Ln Irmo SC 29063",
    "addr:housenumber":"401",
    "addr:postcode":"29063",
    "addr:street":"Western Ln",
    "iso:country":"US",
    "sg:address":"401 Western Ln",
    "sg:city":"Irmo",
    "sg:classifiers":[
        {
            "category":"Professional",
            "subcategory":"Computer Services",
            "type":"Services"
        }
    ],
    "sg:phone":"+1 803 781 8977",
    "sg:postcode":"29063",
    "sg:province":"SC",
    "wof:name":"RSI",
    "wof:placetype":"venue"
},
  "geometry": {"coordinates":[-81.18938799999999,34.113588],"type":"Point"}
}