{
  "type": "Feature",
  "properties": {
    "addr:full":"2894 Moores Mill Rd Aynor SC 29511",
    "addr:housenumber":"2894",
    "addr:postcode":"29511",
    "addr:street":"Moores Mill Rd",
    "iso:country":"US",
    "sg:address":"2894 Moores Mill Rd",
    "sg:city":"Aynor",
    "sg:classifiers":[
        {
            "category":"Freight",
            "type":"Transportation"
        }
    ],
    "sg:phone":"+1 843 358 6501",
    "sg:postcode":"29511",
    "sg:province":"SC",
    "sg:tags":[
        "operator",
        "trucking"
    ],
    "wof:name":"Martin Services",
    "wof:placetype":"venue"
},
  "geometry": {"coordinates":[-79.09756400000001,33.969886],"type":"Point"}
}