{
  "type": "Feature",
  "properties": {
    "iso:country":"US",
    "sg:address":"154 E Main St",
    "sg:city":"Spartanburg",
    "sg:classifiers":[
        {
            "category":"Banks & Credit Unions",
            "subcategory":"Bank",
            "type":"Services"
        }
    ],
    "sg:phone":"+1 864 585 3428",
    "sg:postcode":"29306",
    "sg:province":"SC",
    "sg:tags":[
        "loan"
    ],
    "wof:name":"Hub City Finance Co",
    "wof:placetype":"venue"
},
  "geometry": {"coordinates":[-81.930969,34.949757],"type":"Point"}
}