{
  "type": "Feature",
  "properties": {
    "addr:full":"365 Cannon Rd Chapin SC 29036",
    "addr:housenumber":"365",
    "addr:postcode":"29036",
    "addr:street":"Cannon Rd",
    "iso:country":"US",
    "sg:address":"365 Cannon Rd",
    "sg:city":"Chapin",
    "sg:classifiers":[
        {
            "category":"Building & Trades",
            "subcategory":"Plumbing",
            "type":"Services"
        }
    ],
    "sg:phone":"+1 803 345 3047",
    "sg:postcode":"29036",
    "sg:province":"SC",
    "sg:tags":[
        "plumbing",
        "contractor"
    ],
    "wof:name":"Elkins David Plumbing Co Inc",
    "wof:placetype":"venue"
},
  "geometry": {"coordinates":[-81.313813,34.132639],"type":"Point"}
}