{
  "type": "Feature",
  "properties": {
    "addr:full":"3440 Rental Car Ln North Charleston SC 29418",
    "addr:housenumber":"3440",
    "addr:postcode":"29418",
    "addr:street":"Rental Car Ln",
    "iso:country":"US",
    "sg:address":"3440 Rental Car Ln",
    "sg:city":"North Charleston",
    "sg:classifiers":[
        {
            "category":"Retail",
            "subcategory":"Auto Rental",
            "type":"Services"
        }
    ],
    "sg:phone":"+1 843 552 3415",
    "sg:postcode":"29418",
    "sg:province":"SC",
    "sg:tags":[
        "renting",
        "car",
        "automobile"
    ],
    "sg:website":"www.nationalcar.com",
    "wof:name":"National Car Rental",
    "wof:placetype":"venue"
},
  "geometry": {"coordinates":[-80.03510300000001,32.877499],"type":"Point"}
}