{
  "type": "Feature",
  "properties": {
    "iso:country":"US",
    "sg:address":"74 Heritage Lakes Dr",
    "sg:city":"Bluffton",
    "sg:classifiers":[
        {
            "category":"Building & Trades",
            "subcategory":"Construction",
            "type":"Services"
        }
    ],
    "sg:phone":"+1 843 837 8545",
    "sg:postcode":"29910",
    "sg:province":"SC",
    "sg:tags":[
        "contractor"
    ],
    "wof:name":"Island Concrete & Masonry",
    "wof:placetype":"venue"
},
  "geometry": {"coordinates":[-80.83847900000001,32.239218],"type":"Point"}
}