{
  "type": "Feature",
  "properties": {
    "iso:country":"US",
    "sg:address":"7810 Garners Ferry Rd",
    "sg:city":"Columbia",
    "sg:classifiers":[
        {
            "category":"Shopping",
            "subcategory":"Bicycles & Sporting Goods",
            "type":"Retail Goods"
        }
    ],
    "sg:phone":"+1 803 695 0045",
    "sg:postcode":"29209",
    "sg:province":"SC",
    "sg:tags":[
        "used",
        "merchandise"
    ],
    "wof:name":"Palmetto Gold & Pawn",
    "wof:placetype":"venue"
},
  "geometry": {"coordinates":[-80.92732599999999,33.95567],"type":"Point"}
}