{
  "type": "Feature",
  "properties": {
    "iso:country":"US",
    "sg:address":"2157 Dorchester Rd",
    "sg:city":"Charleston",
    "sg:classifiers":[
        {
            "category":"Insurance",
            "subcategory":"Hazard Insurance",
            "type":"Services"
        }
    ],
    "sg:phone":"+1 843 554 1151",
    "sg:postcode":"29405",
    "sg:province":"SC",
    "sg:tags":[
        "bond"
    ],
    "wof:name":"Home Quick Bail Bonds",
    "wof:placetype":"venue"
},
  "geometry": {"coordinates":[-79.97956499999999,32.854939],"type":"Point"}
}