{
  "type": "Feature",
  "properties": {
    "iso:country":"US",
    "sg:address":"3316 Ashley Phosphate Rd",
    "sg:city":"North Charleston",
    "sg:classifiers":[
        {
            "category":"Personal",
            "subcategory":"Beauty Salon",
            "type":"Services"
        }
    ],
    "sg:phone":"+1 843 767 2722",
    "sg:postcode":"29418",
    "sg:province":"SC",
    "wof:name":"Dynasty Hair Skin Nails",
    "wof:placetype":"venue"
},
  "geometry": {"coordinates":[-80.072574,32.929449],"type":"Point"}
}