{
  "type": "Feature",
  "properties": {
    "iso:country":"US",
    "sg:address":"28 Purple Martin Ln",
    "sg:city":"Hilton Head Island",
    "sg:classifiers":[
        {
            "category":"Building & Trades",
            "subcategory":"Construction",
            "type":"Services"
        }
    ],
    "sg:phone":"+1 843 681 5569",
    "sg:postcode":"29926",
    "sg:province":"SC",
    "sg:tags":[
        "house"
    ],
    "wof:name":"Boyd Builders",
    "wof:placetype":"venue"
},
  "geometry": {"coordinates":[-80.727588,32.240606],"type":"Point"}
}