{
  "type": "Feature",
  "properties": {
    "addr:full":"231 Hillcrest Dr Laurens SC 29360",
    "addr:housenumber":"231",
    "addr:postcode":"29360",
    "addr:street":"Hillcrest Dr",
    "iso:country":"US",
    "sg:address":"231 Hillcrest Dr",
    "sg:city":"Laurens",
    "sg:classifiers":[
        {
            "category":"Professional",
            "subcategory":"Accounting & Tax Preparation",
            "type":"Services"
        }
    ],
    "sg:phone":"+1 864 984 6115",
    "sg:postcode":"29360",
    "sg:province":"SC",
    "sg:tags":[
        "return",
        "filing"
    ],
    "wof:name":"M & M Income Tax Svc",
    "wof:placetype":"venue"
},
  "geometry": {"coordinates":[-82.01305499999999,34.504943],"type":"Point"}
}