{
  "type": "Feature",
  "properties": {
    "addr:full":"3247 N Pleasantburg Dr Greenville SC 29609",
    "addr:housenumber":"3247",
    "addr:postcode":"29609",
    "addr:street":"N Pleasantburg Dr",
    "iso:country":"US",
    "sg:address":"3247 N Pleasantburg Dr",
    "sg:city":"Greenville",
    "sg:classifiers":[
        {
            "category":"Shopping",
            "subcategory":"Shoes",
            "type":"Retail Goods"
        }
    ],
    "sg:phone":"+1 864 232 3718",
    "sg:postcode":"29609",
    "sg:province":"SC",
    "wof:name":"Shoe Carnival",
    "wof:placetype":"venue"
},
  "geometry": {"coordinates":[-82.39993,34.889368],"type":"Point"}
}