{
  "type": "Feature",
  "properties": {
    "iso:country":"US",
    "sg:address":"308 N McQueen St",
    "sg:city":"Florence",
    "sg:classifiers":[
        {
            "category":"Professional",
            "subcategory":"Accounting & Tax Preparation",
            "type":"Services"
        }
    ],
    "sg:phone":"+1 843 662 0406",
    "sg:postcode":"29501",
    "sg:province":"SC",
    "sg:tags":[
        "accountant"
    ],
    "wof:name":"Duncan & Floyd",
    "wof:placetype":"venue"
},
  "geometry": {"coordinates":[-79.772474,34.201642],"type":"Point"}
}