{
  "type": "Feature",
  "properties": {
    "addr:full":"8540 Pelham Rd Greenville SC 29615",
    "addr:housenumber":"8540",
    "addr:postcode":"29615",
    "addr:street":"Pelham Rd",
    "iso:country":"US",
    "sg:address":"8540 Pelham Rd",
    "sg:city":"Greenville",
    "sg:classifiers":[
        {
            "category":"Personal",
            "subcategory":"Beauty Salon",
            "type":"Services"
        }
    ],
    "sg:phone":"+1 864 288 3330",
    "sg:postcode":"29615",
    "sg:province":"SC",
    "wof:name":"David George Salon",
    "wof:placetype":"venue"
},
  "geometry": {"coordinates":[-82.23332000000001,34.853492],"type":"Point"}
}