{
  "type": "Feature",
  "properties": {
    "iso:country":"US",
    "sg:address":"760 Travelers Blvd",
    "sg:city":"Summerville",
    "sg:classifiers":[
        {
            "category":"Organizations",
            "subcategory":"Religious Organization",
            "type":"Services"
        }
    ],
    "sg:phone":"+1 843 832 1600",
    "sg:postcode":"29485",
    "sg:province":"SC",
    "sg:tags":[
        "church"
    ],
    "sg:website":"www.familyofmessiah.net",
    "wof:name":"Family Of Messiah Fellowship",
    "wof:placetype":"venue"
},
  "geometry": {"coordinates":[-80.168066,32.955937],"type":"Point"}
}