{
  "type": "Feature",
  "properties": {
    "iso:country":"US",
    "sg:address":"6 Fantail Ln",
    "sg:city":"Hilton Head Isle",
    "sg:classifiers":[
        {
            "category":"Autos & Motor Vehicles",
            "subcategory":"Automobile Sales",
            "type":"Retail Goods"
        }
    ],
    "sg:phone":"+1 843 681 3113",
    "sg:postcode":"29926",
    "sg:province":"SC",
    "sg:tags":[
        "aircraft"
    ],
    "wof:name":"Beaufort Aircraft Sales",
    "wof:placetype":"venue"
},
  "geometry": {"coordinates":[-80.765696,32.217133],"type":"Point"}
}