{
  "type": "Feature",
  "properties": {
    "iso:country":"US",
    "sg:address":"333 Williams Rd",
    "sg:city":"Travelers Rest",
    "sg:classifiers":[
        {
            "category":"Wholesale",
            "subcategory":"Machinery & Supplies",
            "type":"Manufacturing & Wholesale Goods"
        }
    ],
    "sg:phone":"+1 864 834 3386",
    "sg:postcode":"29690",
    "sg:province":"SC",
    "sg:tags":[
        "machine",
        "sewing",
        "parts"
    ],
    "wof:name":"Penn Sewing Equipment Company",
    "wof:placetype":"venue"
},
  "geometry": {"coordinates":[-82.447971,34.979774],"type":"Point"}
}