{
  "type": "Feature",
  "properties": {
    "addr:full":"700 Blue Ridge Ave Belton SC 29627",
    "addr:housenumber":"700",
    "addr:postcode":"29627",
    "addr:street":"Blue Ridge Ave",
    "iso:country":"US",
    "sg:address":"700 Blue Ridge Ave",
    "sg:city":"Belton",
    "sg:classifiers":[
        {
            "category":"Shopping",
            "subcategory":"Clothing, Apparel, & Fashions",
            "type":"Retail Goods"
        }
    ],
    "sg:phone":"+1 864 338 7688",
    "sg:postcode":"29627",
    "sg:province":"SC",
    "sg:tags":[
        "navy",
        "army"
    ],
    "wof:name":"South Carolina Army",
    "wof:placetype":"venue"
},
  "geometry": {"coordinates":[-82.515468,34.525181],"type":"Point"}
}