{
  "type": "Feature",
  "properties": {
    "iso:country":"US",
    "sg:address":"116 Ripley Point Dr",
    "sg:city":"Charleston",
    "sg:classifiers":[
        {
            "category":"Restaurant",
            "type":"Food & Drink"
        }
    ],
    "sg:phone":"+1 843 573 0066",
    "sg:postcode":"29407",
    "sg:province":"SC",
    "sg:tags":[
        "eating"
    ],
    "wof:name":"Crabhouse",
    "wof:placetype":"venue"
},
  "geometry": {"coordinates":[-79.963863,32.777722],"type":"Point"}
}