{
  "type": "Feature",
  "properties": {
    "addr:full":"2401 Augusta Rd West Columbia SC 29169",
    "addr:housenumber":"2401",
    "addr:postcode":"29169",
    "addr:street":"Augusta Rd",
    "iso:country":"US",
    "sg:address":"2401 Augusta Rd",
    "sg:city":"West Columbia",
    "sg:classifiers":[
        {
            "category":"Health Services",
            "subcategory":"Optometrist",
            "type":"Services"
        }
    ],
    "sg:phone":"+1 803 796 2021",
    "sg:postcode":"29169",
    "sg:province":"SC",
    "wof:name":"Kennedy Bill Dr",
    "wof:placetype":"venue"
},
  "geometry": {"coordinates":[-81.098602,33.9828],"type":"Point"}
}