{
  "type": "Feature",
  "properties": {
    "addr:full":"319 Society Hill Rd Darlington SC 29532",
    "addr:housenumber":"319",
    "addr:postcode":"29532",
    "addr:street":"Society Hill Rd",
    "iso:country":"US",
    "sg:address":"319 Society Hill Rd",
    "sg:city":"Darlington",
    "sg:classifiers":[
        {
            "category":"Wholesale",
            "subcategory":"Meat",
            "type":"Manufacturing & Wholesale Goods"
        }
    ],
    "sg:phone":"+1 843 393 5801",
    "sg:postcode":"29532",
    "sg:province":"SC",
    "sg:tags":[
        "packer"
    ],
    "wof:name":"Darlington Packing Co",
    "wof:placetype":"venue"
},
  "geometry": {"coordinates":[-79.859641,34.317024],"type":"Point"}
}