{
  "type": "Feature",
  "properties": {
    "iso:country":"US",
    "sg:address":"2304 Hertford Dr",
    "sg:city":"Columbia",
    "sg:classifiers":[
        {
            "category":"Organizations",
            "subcategory":"Non-profit Organization",
            "type":"Services"
        }
    ],
    "sg:phone":"+1 803 772 7010",
    "sg:postcode":"29210",
    "sg:province":"SC",
    "sg:tags":[
        "information",
        "alcoholism",
        "treatment"
    ],
    "wof:name":"Oxford House Valley",
    "wof:placetype":"venue"
},
  "geometry": {"coordinates":[-81.087208,34.054181],"type":"Point"}
}