{
  "type": "Feature",
  "properties": {
    "iso:country":"US",
    "sg:address":"4646 Buffalo-West Springs Hwy",
    "sg:city":"Pauline",
    "sg:classifiers":[
        {
            "category":"Wholesale",
            "subcategory":"Machinery & Supplies",
            "type":"Manufacturing & Wholesale Goods"
        }
    ],
    "sg:phone":"+1 864 427 0890",
    "sg:postcode":"29374",
    "sg:province":"SC",
    "sg:tags":[
        "repair",
        "forklift",
        "material",
        "sales",
        "equipment",
        "handling"
    ],
    "wof:name":"Upstate Forklift Inc",
    "wof:placetype":"venue"
},
  "geometry": {"coordinates":[-81.786079,34.772473],"type":"Point"}
}