{
  "type": "Feature",
  "properties": {
    "iso:country":"US",
    "sg:address":"1050 Broad St",
    "sg:city":"Sumter",
    "sg:classifiers":[
        {
            "category":"Travel",
            "subcategory":"Hotels & Motels",
            "type":"Entertainment"
        }
    ],
    "sg:phone":"+1 803 773 8110",
    "sg:postcode":"29150",
    "sg:province":"SC",
    "wof:name":"Best Western Inn",
    "wof:placetype":"venue"
},
  "geometry": {"coordinates":[-80.37569999999999,33.949173],"type":"Point"}
}