{
  "type": "Feature",
  "properties": {
    "addr:full":"120 E Main St Walhalla SC 29691",
    "addr:housenumber":"120",
    "addr:postcode":"29691",
    "addr:street":"E Main St",
    "iso:country":"US",
    "sg:address":"120 E Main St",
    "sg:city":"Walhalla",
    "sg:classifiers":[
        {
            "category":"Shopping",
            "type":"Retail Goods"
        }
    ],
    "sg:phone":"+1 864 638 7700",
    "sg:postcode":"29691",
    "sg:province":"SC",
    "sg:tags":[
        "picture",
        "frame"
    ],
    "wof:name":"Village Framer",
    "wof:placetype":"venue"
},
  "geometry": {"coordinates":[-83.065443,34.764913],"type":"Point"}
}