{
  "type": "Feature",
  "properties": {
    "iso:country":"US",
    "sg:address":"2910 Thomas Sumter Hwy",
    "sg:city":"Sumter",
    "sg:classifiers":[
        {
            "category":"Building & Trades",
            "subcategory":"Construction",
            "type":"Services"
        }
    ],
    "sg:phone":"+1 803 469 7208",
    "sg:postcode":"29153",
    "sg:province":"SC",
    "sg:tags":[
        "insulation",
        "heat",
        "contractor"
    ],
    "wof:name":"Sumter Home Insulators",
    "wof:placetype":"venue"
},
  "geometry": {"coordinates":[-80.41725099999999,33.994707],"type":"Point"}
}