{
  "type": "Feature",
  "properties": {
    "iso:country":"US",
    "sg:address":"1812 Frink St",
    "sg:city":"Cayce",
    "sg:classifiers":[
        {
            "category":"Freight",
            "type":"Transportation"
        }
    ],
    "sg:phone":"+1 803 739 6800",
    "sg:postcode":"29033",
    "sg:province":"SC",
    "sg:tags":[
        "arrangement"
    ],
    "wof:name":"Eagle Freight Services",
    "wof:placetype":"venue"
},
  "geometry": {"coordinates":[-81.073567,33.958578],"type":"Point"}
}