{
  "type": "Feature",
  "properties": {
    "iso:country":"US",
    "sg:address":"21 Spears Dr",
    "sg:city":"Greenville",
    "sg:classifiers":[
        {
            "category":"Building & Trades",
            "subcategory":"Construction",
            "type":"Services"
        }
    ],
    "sg:phone":"+1 803 865 1301",
    "sg:postcode":"29605",
    "sg:province":"SC",
    "sg:tags":[
        "home",
        "builder"
    ],
    "wof:name":"KB Home",
    "wof:placetype":"venue"
},
  "geometry": {"coordinates":[-82.40721600000001,34.768282],"type":"Point"}
}