{
  "type": "Feature",
  "properties": {
    "iso:country":"US",
    "sg:address":"661 Silver Bluff Rd",
    "sg:city":"Aiken",
    "sg:classifiers":[
        {
            "category":"Building & Trades",
            "subcategory":"Electrical",
            "type":"Services"
        }
    ],
    "sg:phone":"+1 803 649 5828",
    "sg:postcode":"29803",
    "sg:province":"SC",
    "sg:tags":[
        "home",
        "system",
        "automation"
    ],
    "wof:name":"Whole House Audio & Video",
    "wof:placetype":"venue"
},
  "geometry": {"coordinates":[-81.740485,33.506963],"type":"Point"}
}