{
  "type": "Feature",
  "properties": {
    "addr:full":"650 9th St Winnsboro SC 29180",
    "addr:housenumber":"650",
    "addr:postcode":"29180",
    "addr:street":"9Th St",
    "iso:country":"US",
    "sg:address":"650 9th St",
    "sg:city":"Winnsboro",
    "sg:classifiers":[
        {
            "category":"Organizations",
            "subcategory":"Religious Organization",
            "type":"Services"
        }
    ],
    "sg:phone":"+1 803 635 4463",
    "sg:postcode":"29180",
    "sg:province":"SC",
    "sg:tags":[
        "church"
    ],
    "sg:website":"www.winnsboronazarene.com",
    "wof:name":"Church Of The Nazarene",
    "wof:placetype":"venue"
},
  "geometry": {"coordinates":[-81.087992,34.358455],"type":"Point"}
}