{
  "type": "Feature",
  "properties": {
    "iso:country":"US",
    "sg:address":"2903 Millwood Ave",
    "sg:city":"Columbia",
    "sg:classifiers":[
        {
            "category":"Professional",
            "subcategory":"Lawyer & Legal Services",
            "type":"Services"
        }
    ],
    "sg:phone":"+1 803 748 9695",
    "sg:postcode":"29205",
    "sg:province":"SC",
    "wof:name":"Stgc National Legal Dept",
    "wof:placetype":"venue"
},
  "geometry": {"coordinates":[-80.999028,34.002298],"type":"Point"}
}