{
  "type": "Feature",
  "properties": {
    "addr:full":"420 Live Oak Dr Mt Pleasant SC 29464",
    "addr:housenumber":"420",
    "addr:postcode":"29464",
    "addr:street":"Live Oak Dr",
    "iso:country":"US",
    "sg:address":"420 Live Oak Dr",
    "sg:city":"Mt Pleasant",
    "sg:classifiers":[
        {
            "category":"Building & Trades",
            "subcategory":"Construction",
            "type":"Services"
        },
        {
            "category":"Wholesale",
            "subcategory":"Electrical",
            "type":"Manufacturing & Wholesale Goods"
        },
        {
            "category":"Professional",
            "subcategory":"Advertising",
            "type":"Services"
        }
    ],
    "sg:phone":"+1 843 971 3830",
    "sg:postcode":"29464",
    "sg:province":"SC",
    "sg:tags":[
        "fixture",
        "planning",
        "distribution",
        "remodeling",
        "store",
        "kitchen"
    ],
    "wof:name":"E Dc Distribution Inc",
    "wof:placetype":"venue"
},
  "geometry": {"coordinates":[-79.87664599999999,32.791627],"type":"Point"}
}