{
  "type": "Feature",
  "properties": {
    "addr:full":"7800 Rivers Ave North Charleston SC 29406",
    "addr:housenumber":"7800",
    "addr:postcode":"29406",
    "addr:street":"Rivers Ave",
    "iso:country":"US",
    "sg:address":"7800 Rivers Ave",
    "sg:city":"North Charleston",
    "sg:classifiers":[
        {
            "category":"Shopping",
            "subcategory":"Clothing, Apparel, & Fashions",
            "type":"Retail Goods"
        }
    ],
    "sg:phone":"+1 843 553 0214",
    "sg:postcode":"29406",
    "sg:province":"SC",
    "sg:tags":[
        "furnishing"
    ],
    "wof:name":"S&K Famous Brand Menswear",
    "wof:placetype":"venue"
},
  "geometry": {"coordinates":[-80.040707,32.944486],"type":"Point"}
}