{
  "type": "Feature",
  "properties": {
    "addr:full":"6 Bee St Charleston SC 29403",
    "addr:housenumber":"6",
    "addr:postcode":"29403",
    "addr:street":"Bee St",
    "iso:country":"US",
    "sg:address":"6 Bee St",
    "sg:city":"Charleston",
    "sg:classifiers":[
        {
            "category":"Professional",
            "subcategory":"Art Services",
            "type":"Services"
        }
    ],
    "sg:phone":"+1 843 720 4264",
    "sg:postcode":"29403",
    "sg:province":"SC",
    "sg:tags":[
        "photographer"
    ],
    "wof:name":"Imagine Images Photography",
    "wof:placetype":"venue"
},
  "geometry": {"coordinates":[-79.94694800000001,32.787454],"type":"Point"}
}