{
  "type": "Feature",
  "properties": {
    "iso:country":"US",
    "sg:address":"929 S Main St",
    "sg:city":"Greenville",
    "sg:phone":"+1 864 282 8945",
    "sg:postcode":"29601",
    "sg:province":"SC",
    "wof:name":"Compadres Mex Mex Grill",
    "wof:placetype":"venue"
},
  "geometry": {"coordinates":[-82.407916,34.84347],"type":"Point"}
}