{
  "type": "Feature",
  "properties": {
    "iso:country":"US",
    "sg:address":"284 Hope Ln",
    "sg:city":"Little River",
    "sg:classifiers":[
        {
            "category":"Retail",
            "subcategory":"Animal Services",
            "type":"Services"
        }
    ],
    "sg:phone":"+1 843 249 1714",
    "sg:postcode":"29566",
    "sg:province":"SC",
    "wof:name":"Antara Boarding & Grooming",
    "wof:placetype":"venue"
},
  "geometry": {"coordinates":[-78.654538,33.861839],"type":"Point"}
}