{
  "type": "Feature",
  "properties": {
    "addr:full":"465 N Guignard Dr Sumter SC 29150",
    "addr:housenumber":"465",
    "addr:postcode":"29150",
    "addr:street":"N Guignard Dr",
    "iso:country":"US",
    "sg:address":"465 N Guignard Dr",
    "sg:city":"Sumter",
    "sg:classifiers":[
        {
            "category":"Health Services",
            "subcategory":"Medical Lab",
            "type":"Services"
        }
    ],
    "sg:phone":"+1 803 778 2247",
    "sg:postcode":"29150",
    "sg:province":"SC",
    "sg:tags":[
        "laboratory"
    ],
    "wof:name":"Palmetto Dental Lab",
    "wof:placetype":"venue"
},
  "geometry": {"coordinates":[-80.36906999999999,33.932624],"type":"Point"}
}