{
  "type": "Feature",
  "properties": {
    "addr:full":"1344 Knox Abbott Dr Cayce SC 29033",
    "addr:housenumber":"1344",
    "addr:postcode":"29033",
    "addr:street":"Knox Abbott Dr",
    "iso:country":"US",
    "sg:address":"1344 Knox Abbott Dr",
    "sg:city":"Cayce",
    "sg:classifiers":[
        {
            "category":"Banks & Credit Unions",
            "subcategory":"Financial Services",
            "type":"Services"
        }
    ],
    "sg:phone":"+1 803 791 4254",
    "sg:postcode":"29033",
    "sg:province":"SC",
    "sg:tags":[
        "broker",
        "mortgage"
    ],
    "wof:name":"American General Financial Services",
    "wof:placetype":"venue"
},
  "geometry": {"coordinates":[-81.072502,33.978802],"type":"Point"}
}