{
  "type": "Feature",
  "properties": {
    "iso:country":"US",
    "sg:address":"1200 Glenns Bay Rd",
    "sg:city":"Surfside Beach",
    "sg:classifiers":[
        {
            "category":"Retail",
            "subcategory":"Auto Repair",
            "type":"Services"
        }
    ],
    "sg:phone":"+1 843 215 8785",
    "sg:postcode":"29575",
    "sg:province":"SC",
    "sg:tags":[
        "automobile",
        "customizing"
    ],
    "wof:name":"All Terrain Customs",
    "wof:placetype":"venue"
},
  "geometry": {"coordinates":[-78.98469,33.615819],"type":"Point"}
}