{
  "type": "Feature",
  "properties": {
    "iso:country":"US",
    "sg:address":"16 Red Cedar Dr",
    "sg:city":"Columbia",
    "sg:classifiers":[
        {
            "category":"Professional",
            "subcategory":"Computer Services",
            "type":"Services"
        }
    ],
    "sg:phone":"+1 803 699 1946",
    "sg:postcode":"29229",
    "sg:province":"SC",
    "sg:tags":[
        "communications",
        "design",
        "system",
        "telephone"
    ],
    "wof:name":"E&P Assoc",
    "wof:placetype":"venue"
},
  "geometry": {"coordinates":[-80.888103,34.153254],"type":"Point"}
}