{
  "type": "Feature",
  "properties": {
    "iso:country":"US",
    "sg:address":"3448 Forestbrook Rd",
    "sg:city":"Myrtle Beach",
    "sg:classifiers":[
        {
            "category":"Health Services",
            "subcategory":"Chiropractor",
            "type":"Services"
        }
    ],
    "sg:phone":"+1 843 241 8556",
    "sg:postcode":"29588",
    "sg:province":"SC",
    "wof:name":"Chiropractic Center-Families",
    "wof:placetype":"venue"
},
  "geometry": {"coordinates":[-79.00108299999999,33.695289],"type":"Point"}
}