{
  "type": "Feature",
  "properties": {
    "iso:country":"US",
    "sg:address":"32 Vendue Range St",
    "sg:city":"Charleston",
    "sg:classifiers":[
        {
            "category":"Professional",
            "subcategory":"Art Services",
            "type":"Services"
        }
    ],
    "sg:phone":"+1 843 579 9691",
    "sg:postcode":"29401",
    "sg:province":"SC",
    "sg:tags":[
        "graphic",
        "designer"
    ],
    "wof:name":"David Carson Design",
    "wof:placetype":"venue"
},
  "geometry": {"coordinates":[-79.92700000000001,32.778782],"type":"Point"}
}