{
  "type": "Feature",
  "properties": {
    "addr:full":"2500 Winchester Pl Spartanburg SC 29301",
    "addr:housenumber":"2500",
    "addr:postcode":"29301",
    "addr:street":"Winchester Pl",
    "iso:country":"US",
    "sg:address":"2500 Winchester Pl",
    "sg:city":"Spartanburg",
    "sg:classifiers":[
        {
            "category":"Health Services",
            "subcategory":"Health Practitioner",
            "type":"Services"
        }
    ],
    "sg:phone":"+1 864 574 7282",
    "sg:postcode":"29301",
    "sg:province":"SC",
    "sg:tags":[
        "therapist",
        "physical"
    ],
    "wof:name":"Advanced Therapy Solutions Inc",
    "wof:placetype":"venue"
},
  "geometry": {"coordinates":[-81.98311,34.936583],"type":"Point"}
}