{
  "type": "Feature",
  "properties": {
    "iso:country":"US",
    "sg:address":"565 Belle Station Blvd",
    "sg:city":"Mount Pleasant",
    "sg:classifiers":[
        {
            "category":"Restaurant",
            "type":"Food & Drink"
        }
    ],
    "sg:menulink":"http://www.allmenus.com/sc/mount-pleasant/73268-pizza-hut/menu/",
    "sg:phone":"+1 843 856 4002",
    "sg:postcode":"29464",
    "sg:province":"SC",
    "sg:tags":[
        "american",
        "pizza"
    ],
    "wof:name":"Pizza Hut",
    "wof:placetype":"venue"
},
  "geometry": {"coordinates":[-79.85459299999999,32.843448],"type":"Point"}
}