{
  "type": "Feature",
  "properties": {
    "iso:country":"US",
    "sg:address":"100 Gloucester Ferry Rd",
    "sg:city":"Greenville",
    "sg:classifiers":[
        {
            "category":"Real Estate",
            "subcategory":"Real Estate Operator",
            "type":"Services"
        }
    ],
    "sg:phone":"+1 864 458 7840",
    "sg:postcode":"29607",
    "sg:province":"SC",
    "sg:tags":[
        "building",
        "apartment"
    ],
    "wof:name":"Paces Court",
    "wof:placetype":"venue"
},
  "geometry": {"coordinates":[-82.320613,34.842964],"type":"Point"}
}