{
  "type": "Feature",
  "properties": {
    "iso:country":"US",
    "sg:address":"2722 Decker Blvd",
    "sg:city":"Columbia",
    "sg:classifiers":[
        {
            "category":"Personal",
            "subcategory":"Beauty Salon",
            "type":"Services"
        }
    ],
    "sg:phone":"+1 803 865 0861",
    "sg:postcode":"29206",
    "sg:province":"SC",
    "sg:tags":[
        "manicuring"
    ],
    "wof:name":"Lee Nails",
    "wof:placetype":"venue"
},
  "geometry": {"coordinates":[-80.953547,34.062053],"type":"Point"}
}