{
  "type": "Feature",
  "properties": {
    "addr:full":"810 W Lydia Hwy Hartsville SC 29550",
    "addr:housenumber":"810",
    "addr:postcode":"29550",
    "addr:street":"W Lydia Hwy",
    "iso:country":"US",
    "sg:address":"810 W Lydia Hwy",
    "sg:city":"Hartsville",
    "sg:classifiers":[
        {
            "category":"Insurance",
            "subcategory":"Hazard Insurance",
            "type":"Services"
        }
    ],
    "sg:phone":"+1 843 332 4711",
    "sg:postcode":"29550",
    "sg:province":"SC",
    "sg:tags":[
        "casualty"
    ],
    "wof:name":"Lydia Insurance",
    "wof:placetype":"venue"
},
  "geometry": {"coordinates":[-80.110001,34.286984],"type":"Point"}
}