{
  "type": "Feature",
  "properties": {
    "iso:country":"US",
    "sg:address":"997 Asheville Hwy",
    "sg:city":"Spartanburg",
    "sg:classifiers":[
        {
            "category":"Bars & Pubs",
            "type":"Food & Drink"
        }
    ],
    "sg:phone":"+1 864 597 0115",
    "sg:postcode":"29303",
    "sg:province":"SC",
    "sg:tags":[
        "drinking"
    ],
    "wof:name":"Bikini Bay",
    "wof:placetype":"venue"
},
  "geometry": {"coordinates":[-81.95052800000001,34.968362],"type":"Point"}
}