{
  "type": "Feature",
  "properties": {
    "addr:full":"162 Berry Dr Gaffney SC 29340",
    "addr:housenumber":"162",
    "addr:postcode":"29340",
    "addr:street":"Berry Dr",
    "iso:country":"US",
    "sg:address":"162 Berry Dr",
    "sg:city":"Gaffney",
    "sg:classifiers":[
        {
            "category":"Building & Trades",
            "subcategory":"Construction",
            "type":"Services"
        }
    ],
    "sg:phone":"+1 864 488 1332",
    "sg:postcode":"29340",
    "sg:province":"SC",
    "sg:tags":[
        "contractor"
    ],
    "wof:name":"Herron Roofg Siding & Windows",
    "wof:placetype":"venue"
},
  "geometry": {"coordinates":[-81.64573300000001,35.030865],"type":"Point"}
}