{
  "type": "Feature",
  "properties": {
    "iso:country":"US",
    "sg:address":"315 Kingsboro Rd",
    "sg:city":"Anderson",
    "sg:classifiers":[
        {
            "category":"Personal",
            "type":"Services"
        }
    ],
    "sg:phone":"+1 864 222 1695",
    "sg:postcode":"29626",
    "sg:province":"SC",
    "sg:tags":[
        "therapist",
        "massage"
    ],
    "wof:name":"Hazel's Massage Therapy",
    "wof:placetype":"venue"
},
  "geometry": {"coordinates":[-82.680975,34.488788],"type":"Point"}
}