{
  "type": "Feature",
  "properties": {
    "addr:full":"840 W O Ezell Blvd Spartanburg SC 29301",
    "addr:housenumber":"840",
    "addr:postcode":"29301",
    "addr:street":"W O Ezell Blvd",
    "iso:country":"US",
    "sg:address":"840 W O Ezell Blvd",
    "sg:city":"Spartanburg",
    "sg:classifiers":[
        {
            "category":"Wholesale",
            "subcategory":"Motor Vehicles",
            "type":"Manufacturing & Wholesale Goods"
        }
    ],
    "sg:phone":"+1 864 573 6800",
    "sg:postcode":"29301",
    "sg:province":"SC",
    "sg:tags":[
        "automobile",
        "used"
    ],
    "wof:name":"Bargens Auto Sales and Leasing",
    "wof:placetype":"venue"
},
  "geometry": {"coordinates":[-81.953073,34.941876],"type":"Point"}
}