{
  "type": "Feature",
  "properties": {
    "iso:country":"US",
    "sg:address":"103 Wood Creek Dr",
    "sg:city":"Greenwood",
    "sg:classifiers":[
        {
            "category":"Retail",
            "subcategory":"Repair Shop",
            "type":"Services"
        }
    ],
    "sg:phone":"+1 864 942 0219",
    "sg:postcode":"29649",
    "sg:province":"SC",
    "sg:tags":[
        "refinishing",
        "furniture"
    ],
    "wof:name":"Wood Co",
    "wof:placetype":"venue"
},
  "geometry": {"coordinates":[-82.159633,34.229769],"type":"Point"}
}