{
  "type": "Feature",
  "properties": {
    "addr:full":"12 Walnut St E Hampton SC 29924",
    "addr:housenumber":"12",
    "addr:postcode":"29924",
    "addr:street":"Walnut St E",
    "iso:country":"US",
    "sg:address":"12 Walnut St E",
    "sg:city":"Hampton",
    "sg:classifiers":[
        {
            "category":"Professional",
            "subcategory":"Employment Agencies",
            "type":"Services"
        }
    ],
    "sg:phone":"+1 803 943 3291",
    "sg:postcode":"29924",
    "sg:province":"SC",
    "sg:tags":[
        "consultant",
        "outplacement"
    ],
    "wof:name":"Employment Service",
    "wof:placetype":"venue"
},
  "geometry": {"coordinates":[-81.110801,32.86538],"type":"Point"}
}