{
  "type": "Feature",
  "properties": {
    "iso:country":"US",
    "sg:address":"363 Wildlife Rd",
    "sg:city":"Lexington",
    "sg:classifiers":[
        {
            "category":"Building & Trades",
            "subcategory":"Construction",
            "type":"Services"
        }
    ],
    "sg:phone":"+1 803 808 3550",
    "sg:postcode":"29072",
    "sg:province":"SC",
    "sg:tags":[
        "grading",
        "contractor"
    ],
    "wof:name":"Wiley Easton Construction Inc",
    "wof:placetype":"venue"
},
  "geometry": {"coordinates":[-81.257501,33.956953],"type":"Point"}
}