{
  "type": "Feature",
  "properties": {
    "addr:full":"650 Coleman Blvd Mount Pleasant SC 29464",
    "addr:housenumber":"650",
    "addr:postcode":"29464",
    "addr:street":"Coleman Blvd",
    "iso:country":"US",
    "sg:address":"650 Coleman Blvd",
    "sg:city":"Mount Pleasant",
    "sg:classifiers":[
        {
            "category":"Autos & Motor Vehicles",
            "subcategory":"Fuel & Gas Station",
            "type":"Retail Goods"
        }
    ],
    "sg:phone":"+1 843 881 0508",
    "sg:postcode":"29464",
    "sg:province":"SC",
    "sg:tags":[
        "station",
        "gasoline"
    ],
    "wof:name":"Palmetto Oil Charleston LLC",
    "wof:placetype":"venue"
},
  "geometry": {"coordinates":[-79.87397199999999,32.791089],"type":"Point"}
}