{
  "type": "Feature",
  "properties": {
    "addr:full":"307 N Main St Abbeville SC 29620",
    "addr:housenumber":"307",
    "addr:postcode":"29620",
    "addr:street":"N Main St",
    "iso:country":"US",
    "sg:address":"307 N Main St",
    "sg:city":"Abbeville",
    "sg:classifiers":[
        {
            "category":"Organizations",
            "subcategory":"Religious Organization",
            "type":"Services"
        }
    ],
    "sg:phone":"+1 864 366 2597",
    "sg:postcode":"29620",
    "sg:province":"SC",
    "sg:tags":[
        "church"
    ],
    "wof:name":"First Baptist Church",
    "wof:placetype":"venue"
},
  "geometry": {"coordinates":[-82.383796,34.181039],"type":"Point"}
}