{
  "type": "Feature",
  "properties": {
    "iso:country":"US",
    "sg:address":"603 10th Ave N",
    "sg:city":"Myrtle Beach",
    "sg:classifiers":[
        {
            "category":"Real Estate",
            "subcategory":"Real Estate Agent",
            "type":"Services"
        }
    ],
    "sg:phone":"+1 843 918 1525",
    "sg:postcode":"29577",
    "sg:province":"SC",
    "sg:tags":[
        "authorities",
        "housing"
    ],
    "wof:name":"Housing Authority - Myrtle Bch",
    "wof:placetype":"venue"
},
  "geometry": {"coordinates":[-78.883566,33.697403],"type":"Point"}
}