{
  "type": "Feature",
  "properties": {
    "iso:country":"US",
    "sg:address":"1140 York St NE",
    "sg:city":"Aiken",
    "sg:classifiers":[
        {
            "category":"Restaurant",
            "type":"Food & Drink"
        }
    ],
    "sg:menulink":"http://www.allmenus.com/sc/aiken/85527-dominos-pizza/menu/",
    "sg:phone":"+1 803 641 0300",
    "sg:postcode":"29801",
    "sg:province":"SC",
    "sg:tags":[
        "american",
        "wing",
        "pizza"
    ],
    "wof:name":"Domino's Pizza",
    "wof:placetype":"venue"
},
  "geometry": {"coordinates":[-81.702732,33.577503],"type":"Point"}
}