{
  "type": "Feature",
  "properties": {
    "iso:country":"US",
    "sg:address":"115 Hickory Trace Dr",
    "sg:city":"Goose Creek",
    "sg:classifiers":[
        {
            "category":"Building & Trades",
            "subcategory":"Landscaping Services",
            "type":"Services"
        }
    ],
    "sg:phone":"+1 843 863 9071",
    "sg:postcode":"29445",
    "sg:province":"SC",
    "sg:tags":[
        "contractor"
    ],
    "wof:name":"Prestige Landscaping",
    "wof:placetype":"venue"
},
  "geometry": {"coordinates":[-80.05854600000001,33.001703],"type":"Point"}
}