{
  "type": "Feature",
  "properties": {
    "iso:country":"US",
    "sg:address":"3425 Bombing Range Rd",
    "sg:city":"Longs",
    "sg:classifiers":[
        {
            "category":"Social Services",
            "subcategory":"Child Care",
            "type":"Services"
        }
    ],
    "sg:phone":"+1 843 399 7882",
    "sg:postcode":"29568",
    "sg:province":"SC",
    "wof:name":"Wonderland Daycare",
    "wof:placetype":"venue"
},
  "geometry": {"coordinates":[-78.760494,33.848108],"type":"Point"}
}