{
  "type": "Feature",
  "properties": {
    "iso:country":"US",
    "sg:address":"1750 US Hwy 15 S",
    "sg:city":"Sumter",
    "sg:classifiers":[
        {
            "category":"Retail",
            "subcategory":"Animal Services",
            "type":"Services"
        }
    ],
    "sg:phone":"+1 803 481 2053",
    "sg:postcode":"29150",
    "sg:province":"SC",
    "sg:tags":[
        "pet",
        "grooming",
        "washing"
    ],
    "wof:name":"Poodle Salon",
    "wof:placetype":"venue"
},
  "geometry": {"coordinates":[-80.35593,33.869894],"type":"Point"}
}