{
  "type": "Feature",
  "properties": {
    "iso:country":"US",
    "sg:address":"281 Coolers Dairy Rd",
    "sg:city":"Walterboro",
    "sg:classifiers":[
        {
            "category":"Food & Beverages",
            "subcategory":"Specialty",
            "type":"Retail Goods"
        }
    ],
    "sg:phone":"+1 843 538 8809",
    "sg:postcode":"29488",
    "sg:province":"SC",
    "sg:tags":[
        "health",
        "diet"
    ],
    "wof:name":"No Junk Julie's",
    "wof:placetype":"venue"
},
  "geometry": {"coordinates":[-80.597472,32.938288],"type":"Point"}
}