{
  "type": "Feature",
  "properties": {
    "iso:country":"US",
    "sg:address":"4904 Locust Hill Rd",
    "sg:city":"Taylors",
    "sg:classifiers":[
        {
            "category":"Building & Trades",
            "subcategory":"Construction",
            "type":"Services"
        }
    ],
    "sg:phone":"+1 864 895 9199",
    "sg:postcode":"29687",
    "sg:province":"SC",
    "sg:tags":[
        "house"
    ],
    "wof:name":"A1 Awning",
    "wof:placetype":"venue"
},
  "geometry": {"coordinates":[-82.361712,35.005912],"type":"Point"}
}