{
  "type": "Feature",
  "properties": {
    "addr:full":"5630 McConnells Hwy Mc Connells SC 29726",
    "addr:housenumber":"5630",
    "addr:postcode":"29726",
    "addr:street":"Mcconnells Hwy Mc",
    "iso:country":"US",
    "sg:address":"5630 McConnells Hwy",
    "sg:city":"Mc Connells",
    "sg:classifiers":[
        {
            "category":"Shopping",
            "subcategory":"Florist",
            "type":"Retail Goods"
        }
    ],
    "sg:phone":"+1 803 684 6145",
    "sg:postcode":"29726",
    "sg:province":"SC",
    "wof:name":"Johnnie's Florist & Rental",
    "wof:placetype":"venue"
},
  "geometry": {"coordinates":[-81.200638,34.879996],"type":"Point"}
}