{
  "type": "Feature",
  "properties": {
    "iso:country":"US",
    "sg:address":"70 Pennington Dr",
    "sg:city":"Bluffton",
    "sg:classifiers":[
        {
            "category":"Health Services",
            "subcategory":"Health Practitioner",
            "type":"Services"
        }
    ],
    "sg:phone":"+1 843 815 3131",
    "sg:postcode":"29910",
    "sg:province":"SC",
    "sg:tags":[
        "therapist",
        "physical"
    ],
    "wof:name":"Healthsouth Sports Medicine",
    "wof:placetype":"venue"
},
  "geometry": {"coordinates":[-80.857879,32.263191],"type":"Point"}
}