{
  "type": "Feature",
  "properties": {
    "addr:full":"5513 Rivers Ave North Charleston SC 29406",
    "addr:housenumber":"5513",
    "addr:postcode":"29406",
    "addr:street":"Rivers Ave",
    "iso:country":"US",
    "sg:address":"5513 Rivers Ave",
    "sg:city":"North Charleston",
    "sg:classifiers":[
        {
            "category":"Shopping",
            "subcategory":"Computers & Home Electronics",
            "type":"Retail Goods"
        }
    ],
    "sg:phone":"+1 843 747 3203",
    "sg:postcode":"29406",
    "sg:province":"SC",
    "sg:tags":[
        "high",
        "fidelity",
        "stereophonic"
    ],
    "wof:name":"Pleasant Sounds Pro Audio",
    "wof:placetype":"venue"
},
  "geometry": {"coordinates":[-80.015401,32.896231],"type":"Point"}
}