{
  "type": "Feature",
  "properties": {
    "iso:country":"US",
    "sg:address":"408 Azalea Dr",
    "sg:city":"Walterboro",
    "sg:classifiers":[
        {
            "category":"Real Estate",
            "subcategory":"Real Estate Agent",
            "type":"Services"
        }
    ],
    "sg:phone":"+1 843 538 5686",
    "sg:postcode":"29488",
    "sg:province":"SC",
    "wof:name":"Murdaugh & Crapse LLC",
    "wof:placetype":"venue"
},
  "geometry": {"coordinates":[-80.674099,32.927635],"type":"Point"}
}