{
  "type": "Feature",
  "properties": {
    "addr:full":"6943 Dorchester Rd North Charleston SC 29418",
    "addr:housenumber":"6943",
    "addr:postcode":"29418",
    "addr:street":"Dorchester Rd",
    "iso:country":"US",
    "sg:address":"6943 Dorchester Rd",
    "sg:city":"North Charleston",
    "sg:classifiers":[
        {
            "category":"Retail",
            "subcategory":"Portrait Studio",
            "type":"Services"
        }
    ],
    "sg:phone":"+1 843 207 8989",
    "sg:postcode":"29418",
    "sg:province":"SC",
    "sg:tags":[
        "photographer"
    ],
    "wof:name":"Cyber Studios",
    "wof:placetype":"venue"
},
  "geometry": {"coordinates":[-80.068584,32.888334],"type":"Point"}
}