{
  "type": "Feature",
  "properties": {
    "iso:country":"US",
    "sg:address":"157 Connector Rd",
    "sg:city":"Union",
    "sg:classifiers":[
        {
            "category":"Retail",
            "subcategory":"Auto Repair",
            "type":"Services"
        }
    ],
    "sg:phone":"+1 864 427 5793",
    "sg:postcode":"29379",
    "sg:province":"SC",
    "sg:tags":[
        "body",
        "automobile",
        "painting"
    ],
    "wof:name":"Brian's Body Shop",
    "wof:placetype":"venue"
},
  "geometry": {"coordinates":[-81.635397,34.739188],"type":"Point"}
}