{
  "type": "Feature",
  "properties": {
    "iso:country":"US",
    "sg:address":"33 N Congress St",
    "sg:city":"York",
    "sg:classifiers":[
        {
            "category":"Health Services",
            "subcategory":"Chiropractor",
            "type":"Services"
        }
    ],
    "sg:phone":"+1 803 628 6800",
    "sg:postcode":"29745",
    "sg:province":"SC",
    "wof:name":"Advanced Chiropractic Sltns",
    "wof:placetype":"venue"
},
  "geometry": {"coordinates":[-81.241494,34.994815],"type":"Point"}
}