{
  "type": "Feature",
  "properties": {
    "addr:full":"1754 SC-160 W Fort Mill SC 29708",
    "addr:postcode":"1754;29708",
    "addr:street":"W",
    "iso:country":"US",
    "sg:address":"1754 SC-160 W",
    "sg:city":"Fort Mill",
    "sg:classifiers":[
        {
            "category":"Restaurant",
            "type":"Food & Drink"
        }
    ],
    "sg:menulink":"http://www.allmenus.com/sc/fort-mill/73220-pizza-hut/menu/",
    "sg:phone":"+1 803 802 0888",
    "sg:postcode":"29708",
    "sg:province":"SC",
    "sg:tags":[
        "american",
        "pizza"
    ],
    "wof:name":"Pizza Hut",
    "wof:placetype":"venue"
},
  "geometry": {"coordinates":[-80.970384,35.033326],"type":"Point"}
}