{
  "type": "Feature",
  "properties": {
    "addr:full":"165 Ashley Ave Charleston SC 29425",
    "addr:housenumber":"165",
    "addr:postcode":"29425",
    "addr:street":"Ashley Ave",
    "iso:country":"US",
    "sg:address":"165 Ashley Ave",
    "sg:city":"Charleston",
    "sg:classifiers":[
        {
            "category":"Health Services",
            "subcategory":"Doctor",
            "type":"Services"
        }
    ],
    "sg:phone":"+1 843 792 2322",
    "sg:postcode":"29425",
    "sg:province":"SC",
    "sg:tags":[
        "physician",
        "surgeon"
    ],
    "wof:name":"Medical University Of Sc",
    "wof:placetype":"venue"
},
  "geometry": {"coordinates":[-79.946167,32.78436],"type":"Point"}
}