{
  "type": "Feature",
  "properties": {
    "iso:country":"US",
    "sg:address":"412 Columbia Ave",
    "sg:city":"Lexington",
    "sg:classifiers":[
        {
            "category":"Home & Garden",
            "subcategory":"Building Materials",
            "type":"Retail Goods"
        }
    ],
    "sg:phone":"+1 803 957 5036",
    "sg:postcode":"29072",
    "sg:province":"SC",
    "sg:tags":[
        "paint",
        "decorating",
        "supply"
    ],
    "wof:name":"Sherwin-Williams Paints",
    "wof:placetype":"venue"
},
  "geometry": {"coordinates":[-81.23885300000001,33.988536],"type":"Point"}
}