{
  "type": "Feature",
  "properties": {
    "iso:country":"US",
    "sg:address":"550 Lawson St",
    "sg:city":"Florence",
    "sg:classifiers":[
        {
            "category":"Personal",
            "subcategory":"Beauty Salon",
            "type":"Services"
        }
    ],
    "sg:phone":"+1 843 665 2848",
    "sg:postcode":"29501",
    "sg:province":"SC",
    "wof:name":"Beauty Studio",
    "wof:placetype":"venue"
},
  "geometry": {"coordinates":[-79.778129,34.204224],"type":"Point"}
}