{
  "type": "Feature",
  "properties": {
    "iso:country":"US",
    "sg:address":"1004 29th Ave N",
    "sg:city":"Myrtle Beach",
    "sg:classifiers":[
        {
            "category":"Insurance",
            "subcategory":"Insurance Agent",
            "type":"Services"
        }
    ],
    "sg:phone":"+1 843 448 2003",
    "sg:postcode":"29577",
    "sg:province":"SC",
    "wof:name":"Hogan & Assoc",
    "wof:placetype":"venue"
},
  "geometry": {"coordinates":[-78.868835,33.712937],"type":"Point"}
}