{
  "type": "Feature",
  "properties": {
    "iso:country":"US",
    "sg:address":"3735 E North Corner Rd",
    "sg:city":"Lancaster",
    "sg:classifiers":[
        {
            "category":"Utilities",
            "subcategory":"Refuse",
            "type":"Services"
        }
    ],
    "sg:phone":"+1 803 285 8385",
    "sg:postcode":"29720",
    "sg:province":"SC",
    "sg:tags":[
        "garbage",
        "collection"
    ],
    "wof:name":"Carolina Trash & Rubbish",
    "wof:placetype":"venue"
},
  "geometry": {"coordinates":[-80.798389,34.816008],"type":"Point"}
}