{
  "type": "Feature",
  "properties": {
    "iso:country":"US",
    "sg:address":"406 Colonial Dr",
    "sg:city":"Greenwood",
    "sg:classifiers":[
        {
            "category":"Building & Trades",
            "subcategory":"Construction",
            "type":"Services"
        }
    ],
    "sg:phone":"+1 864 229 2183",
    "sg:postcode":"29649",
    "sg:province":"SC",
    "sg:tags":[
        "house"
    ],
    "wof:name":"Justus Builders",
    "wof:placetype":"venue"
},
  "geometry": {"coordinates":[-82.165724,34.226684],"type":"Point"}
}