{
  "type": "Feature",
  "properties": {
    "iso:country":"US",
    "sg:address":"14 Roslyn Cir",
    "sg:city":"Aiken",
    "sg:classifiers":[
        {
            "category":"Retail",
            "subcategory":"Portrait Studio",
            "type":"Services"
        }
    ],
    "sg:phone":"+1 803 649 9400",
    "sg:postcode":"29803",
    "sg:province":"SC",
    "sg:tags":[
        "photographer"
    ],
    "wof:name":"Aiken Photography",
    "wof:placetype":"venue"
},
  "geometry": {"coordinates":[-81.728776,33.525638],"type":"Point"}
}