{
  "type": "Feature",
  "properties": {
    "addr:full":"2183 N Hwy 17 Mt Pleasant SC 29466",
    "addr:housenumber":"2183",
    "addr:postcode":"29466",
    "addr:street":"N Hwy 17",
    "iso:country":"US",
    "sg:address":"2183 N Hwy 17",
    "sg:city":"Mt Pleasant",
    "sg:classifiers":[
        {
            "category":"Real Estate",
            "subcategory":"Real Estate Agent",
            "type":"Services"
        }
    ],
    "sg:phone":"+1 843 388 2500",
    "sg:postcode":"29466",
    "sg:province":"SC",
    "wof:name":"Real Estate Information Ctr",
    "wof:placetype":"venue"
},
  "geometry": {"coordinates":[-79.818535,32.840029],"type":"Point"}
}