{
  "type": "Feature",
  "properties": {
    "addr:full":"2 Amherst St Charleston SC 29403",
    "addr:housenumber":"2",
    "addr:postcode":"29403",
    "addr:street":"Amherst St",
    "iso:country":"US",
    "sg:address":"2 Amherst St",
    "sg:city":"Charleston",
    "sg:classifiers":[
        {
            "category":"Professional",
            "subcategory":"Accounting & Tax Preparation",
            "type":"Services"
        }
    ],
    "sg:phone":"+1 843 722 7676",
    "sg:postcode":"29403",
    "sg:province":"SC",
    "sg:tags":[
        "accountant"
    ],
    "wof:name":"Ferira Ainsworth & Co",
    "wof:placetype":"venue"
},
  "geometry": {"coordinates":[-79.93389999999999,32.795133],"type":"Point"}
}