{
  "type": "Feature",
  "properties": {
    "iso:country":"US",
    "sg:address":"498 Old York Rd",
    "sg:city":"Chester",
    "sg:classifiers":[
        {
            "category":"Retail",
            "subcategory":"Laundry & Dry Cleaning",
            "type":"Services"
        }
    ],
    "sg:phone":"+1 803 385 9309",
    "sg:postcode":"29706",
    "sg:province":"SC",
    "wof:name":"Carolina Clean Machine",
    "wof:placetype":"venue"
},
  "geometry": {"coordinates":[-81.205665,34.718286],"type":"Point"}
}