{
  "type": "Feature",
  "properties": {
    "addr:full":"578 Woodruff Rd Greenville SC 29607",
    "addr:housenumber":"578",
    "addr:postcode":"29607",
    "addr:street":"Woodruff Rd",
    "iso:country":"US",
    "sg:address":"578 Woodruff Rd",
    "sg:city":"Greenville",
    "sg:classifiers":[
        {
            "category":"Shopping",
            "type":"Retail Goods"
        }
    ],
    "sg:phone":"+1 864 591 1849",
    "sg:postcode":"29607",
    "sg:province":"SC",
    "sg:tags":[
        "spa",
        "hot",
        "tub"
    ],
    "sg:website":"www.hotspringspools.net",
    "wof:name":"Hot Spring Pools & Spas",
    "wof:placetype":"venue"
},
  "geometry": {"coordinates":[-82.327521,34.837259],"type":"Point"}
}