{
  "type": "Feature",
  "properties": {
    "iso:country":"US",
    "sg:address":"690 Duncan Reidville Rd",
    "sg:city":"Duncan",
    "sg:classifiers":[
        {
            "category":"Building & Trades",
            "subcategory":"Construction",
            "type":"Services"
        },
        {
            "category":"Manufacturing",
            "subcategory":"Tools & Machinery",
            "type":"Manufacturing & Wholesale Goods"
        }
    ],
    "sg:phone":"+1 864 949 3741",
    "sg:postcode":"29334",
    "sg:province":"SC",
    "sg:tags":[
        "fabricator",
        "industrial",
        "metal",
        "mfg"
    ],
    "sg:website":"www.wrightmetalproducts.com",
    "wof:name":"Wright Metal Products Inc",
    "wof:placetype":"venue"
},
  "geometry": {"coordinates":[-82.145544,34.908992],"type":"Point"}
}