{
  "type": "Feature",
  "properties": {
    "iso:country":"US",
    "sg:address":"2729 E Palmetto St",
    "sg:city":"Florence",
    "sg:classifiers":[
        {
            "category":"Organizations",
            "subcategory":"Non-profit Organization",
            "type":"Services"
        }
    ],
    "sg:phone":"+1 843 413 9533",
    "sg:postcode":"29506",
    "sg:province":"SC",
    "sg:tags":[
        "fund",
        "counselor",
        "raising"
    ],
    "wof:name":"Network Members Only",
    "wof:placetype":"venue"
},
  "geometry": {"coordinates":[-79.717787,34.197148],"type":"Point"}
}