{
  "type": "Feature",
  "properties": {
    "iso:country":"US",
    "sg:address":"1107 Gray Mare Hollow Rd",
    "sg:city":"Aiken",
    "sg:classifiers":[
        {
            "category":"Building & Trades",
            "subcategory":"Construction",
            "type":"Services"
        }
    ],
    "sg:phone":"+1 803 652 3427",
    "sg:postcode":"29803",
    "sg:province":"SC",
    "sg:tags":[
        "house"
    ],
    "wof:name":"Brooks Contracting",
    "wof:placetype":"venue"
},
  "geometry": {"coordinates":[-81.77251699999999,33.437747],"type":"Point"}
}