{
  "type": "Feature",
  "properties": {
    "iso:country":"US",
    "sg:address":"2627 Millwood Ave",
    "sg:city":"Columbia",
    "sg:classifiers":[
        {
            "category":"Sports & Exercise",
            "subcategory":"Gym",
            "type":"Entertainment"
        }
    ],
    "sg:phone":"+1 803 251 4450",
    "sg:postcode":"29205",
    "sg:province":"SC",
    "sg:tags":[
        "trainer"
    ],
    "sg:website":"www.curves.com",
    "wof:name":"Curves For Women",
    "wof:placetype":"venue"
},
  "geometry": {"coordinates":[-81.005933,34.004532],"type":"Point"}
}