{
  "type": "Feature",
  "properties": {
    "iso:country":"US",
    "sg:address":"701 S Kings Hwy",
    "sg:city":"Myrtle Beach",
    "sg:classifiers":[
        {
            "category":"Restaurant",
            "type":"Food & Drink"
        }
    ],
    "sg:menulink":"http://www.allmenus.com/sc/myrtle-beach/87154-pizza-romana/menu/",
    "sg:phone":"+1 843 448 5271",
    "sg:postcode":"29577",
    "sg:province":"SC",
    "sg:tags":[
        "american",
        "pizza"
    ],
    "wof:name":"Pizza Romana",
    "wof:placetype":"venue"
},
  "geometry": {"coordinates":[-78.896255,33.681205],"type":"Point"}
}