{
  "type": "Feature",
  "properties": {
    "iso:country":"US",
    "sg:address":"203 Concord Rd",
    "sg:city":"Anderson",
    "sg:classifiers":[
        {
            "category":"Real Estate",
            "subcategory":"Real Estate Agent",
            "type":"Services"
        },
        {
            "category":"Real Estate",
            "subcategory":"Real Estate Operator",
            "type":"Services"
        }
    ],
    "sg:phone":"+1 864 224 6003",
    "sg:postcode":"29621",
    "sg:province":"SC",
    "sg:tags":[
        "building",
        "appraiser",
        "nonresidential"
    ],
    "wof:name":"Meridian Property Advisors Inc",
    "wof:placetype":"venue"
},
  "geometry": {"coordinates":[-82.663334,34.53298],"type":"Point"}
}