{
  "type": "Feature",
  "properties": {
    "addr:full":"2207 Lebanon Rd Anderson SC 29670",
    "addr:housenumber":"2207",
    "addr:postcode":"29670",
    "addr:street":"Lebanon Rd",
    "iso:country":"US",
    "sg:address":"2207 Lebanon Rd",
    "sg:city":"Anderson",
    "sg:classifiers":[
        {
            "category":"Food & Beverages",
            "subcategory":"Groceries & Convenience Stores",
            "type":"Retail Goods"
        }
    ],
    "sg:phone":"+1 864 224 9759",
    "sg:postcode":"29670",
    "sg:province":"SC",
    "wof:name":"Mac Smith's Country Store",
    "wof:placetype":"venue"
},
  "geometry": {"coordinates":[-82.72117299999999,34.619478],"type":"Point"}
}