{
  "type": "Feature",
  "properties": {
    "iso:country":"US",
    "sg:address":"1507 Ebenezer Rd",
    "sg:city":"Rock Hill",
    "sg:classifiers":[
        {
            "category":"Health Services",
            "subcategory":"Doctor",
            "type":"Services"
        }
    ],
    "sg:phone":"+1 803 327 1144",
    "sg:postcode":"29732",
    "sg:province":"SC",
    "sg:tags":[
        "dentist"
    ],
    "wof:name":"Orthodontic Associates",
    "wof:placetype":"venue"
},
  "geometry": {"coordinates":[-81.043661,34.952761],"type":"Point"}
}