{
  "type": "Feature",
  "properties": {
    "addr:full":"3266 Chester Hwy York SC 29745",
    "addr:housenumber":"3266",
    "addr:postcode":"29745",
    "addr:street":"Chester Hwy",
    "iso:country":"US",
    "sg:address":"3266 Chester Hwy",
    "sg:city":"York",
    "sg:classifiers":[
        {
            "category":"Real Estate",
            "subcategory":"Real Estate Agent",
            "type":"Services"
        }
    ],
    "sg:phone":"+1 803 684 4212",
    "sg:postcode":"29745",
    "sg:province":"SC",
    "sg:tags":[
        "farm",
        "cotton",
        "crop",
        "general"
    ],
    "wof:name":"Daves Land & Cattle",
    "wof:placetype":"venue"
},
  "geometry": {"coordinates":[-81.20649299999999,34.894334],"type":"Point"}
}