{
  "type": "Feature",
  "properties": {
    "iso:country":"US",
    "sg:address":"35 Office Park Rd",
    "sg:city":"Hilton Head Isle",
    "sg:classifiers":[
        {
            "category":"Restaurant",
            "type":"Food & Drink"
        }
    ],
    "sg:phone":"+1 843 686 5800",
    "sg:postcode":"29928",
    "sg:province":"SC",
    "sg:tags":[
        "eating"
    ],
    "sg:website":"www.hiltonheadfun.com",
    "wof:name":"Marleys Island Grille",
    "wof:placetype":"venue"
},
  "geometry": {"coordinates":[-80.763514,32.15331],"type":"Point"}
}