{
  "type": "Feature",
  "properties": {
    "iso:country":"US",
    "sg:address":"613 S Pinckney St",
    "sg:city":"Union",
    "sg:classifiers":[
        {
            "category":"Autos & Motor Vehicles",
            "subcategory":"Auto Supplies",
            "type":"Retail Goods"
        }
    ],
    "sg:phone":"+1 864 427 2806",
    "sg:postcode":"29379",
    "sg:province":"SC",
    "sg:tags":[
        "tire"
    ],
    "wof:name":"Union Wholesale Tire Co",
    "wof:placetype":"venue"
},
  "geometry": {"coordinates":[-81.619511,34.708731],"type":"Point"}
}