{
  "type": "Feature",
  "properties": {
    "iso:country":"US",
    "sg:address":"1960 Riviera Dr",
    "sg:city":"Mt Pleasant",
    "sg:classifiers":[
        {
            "category":"Shopping",
            "type":"Retail Goods"
        }
    ],
    "sg:phone":"+1 843 971 4001",
    "sg:postcode":"29464",
    "sg:province":"SC",
    "sg:tags":[
        "art",
        "gallery",
        "dealer"
    ],
    "wof:name":"Artists' Loft",
    "wof:placetype":"venue"
},
  "geometry": {"coordinates":[-79.81694400000001,32.821453],"type":"Point"}
}