{
  "type": "Feature",
  "properties": {
    "addr:full":"1577 Eastland Ave Kingstree SC 29556",
    "addr:housenumber":"1577",
    "addr:postcode":"29556",
    "addr:street":"Eastland Ave",
    "iso:country":"US",
    "sg:address":"1577 Eastland Ave",
    "sg:city":"Kingstree",
    "sg:classifiers":[
        {
            "category":"Retail",
            "subcategory":"Auto Repair",
            "type":"Services"
        }
    ],
    "sg:phone":"+1 843 201 4360",
    "sg:postcode":"29556",
    "sg:province":"SC",
    "sg:tags":[
        "repairing",
        "automobile"
    ],
    "wof:name":"B J's Truckin' Svc",
    "wof:placetype":"venue"
},
  "geometry": {"coordinates":[-79.810761,33.702741],"type":"Point"}
}