{
  "type": "Feature",
  "properties": {
    "addr:full":"1687 Chestnut St Orangeburg SC 29115",
    "addr:housenumber":"1687",
    "addr:postcode":"29115",
    "addr:street":"Chestnut St",
    "iso:country":"US",
    "sg:address":"1687 Chestnut St",
    "sg:city":"Orangeburg",
    "sg:classifiers":[
        {
            "category":"Building & Trades",
            "subcategory":"Construction",
            "type":"Services"
        }
    ],
    "sg:phone":"+1 803 516 0555",
    "sg:postcode":"29115",
    "sg:province":"SC",
    "sg:tags":[
        "home",
        "builder"
    ],
    "wof:name":"Shur-Bilt Building Systems",
    "wof:placetype":"venue"
},
  "geometry": {"coordinates":[-80.866349,33.51614],"type":"Point"}
}