{
  "type": "Feature",
  "properties": {
    "addr:full":"1865 E Main St Duncan SC 29334",
    "addr:housenumber":"1865",
    "addr:postcode":"29334",
    "addr:street":"E Main St",
    "iso:country":"US",
    "sg:address":"1865 E Main St",
    "sg:city":"Duncan",
    "sg:classifiers":[
        {
            "category":"Health Services",
            "subcategory":"Health Practitioner",
            "type":"Services"
        }
    ],
    "sg:phone":"+1 864 486 1105",
    "sg:postcode":"29334",
    "sg:province":"SC",
    "sg:tags":[
        "therapist",
        "physical"
    ],
    "wof:name":"Pro Physical Therapy Inc",
    "wof:placetype":"venue"
},
  "geometry": {"coordinates":[-82.084902,34.894466],"type":"Point"}
}