{
  "type": "Feature",
  "properties": {
    "addr:full":"2953 Harristown Rd St Stephen SC 29479",
    "addr:housenumber":"2953",
    "addr:postcode":"29479",
    "addr:street":"Harristown Rd",
    "iso:country":"US",
    "sg:address":"2953 Harristown Rd",
    "sg:city":"St Stephen",
    "sg:classifiers":[
        {
            "category":"Organizations",
            "subcategory":"Religious Organization",
            "type":"Services"
        }
    ],
    "sg:phone":"+1 843 567 3057",
    "sg:postcode":"29479",
    "sg:province":"SC",
    "sg:tags":[
        "church"
    ],
    "wof:name":"Harristown Road Baptist Church",
    "wof:placetype":"venue"
},
  "geometry": {"coordinates":[-79.914646,33.389455],"type":"Point"}
}