{
  "type": "Feature",
  "properties": {
    "iso:country":"US",
    "sg:address":"111 Levi Ln",
    "sg:city":"Georgetown",
    "sg:classifiers":[
        {
            "category":"Building & Trades",
            "subcategory":"Electrical",
            "type":"Services"
        }
    ],
    "sg:phone":"+1 843 546 4804",
    "sg:postcode":"29440",
    "sg:province":"SC",
    "sg:tags":[
        "electrical",
        "contractor"
    ],
    "wof:name":"H & D Electrical Contractors",
    "wof:placetype":"venue"
},
  "geometry": {"coordinates":[-79.325615,33.400939],"type":"Point"}
}