{
  "type": "Feature",
  "properties": {
    "iso:country":"US",
    "sg:address":"1233 Washington St",
    "sg:city":"Columbia",
    "sg:classifiers":[
        {
            "category":"Communications",
            "type":"Services"
        }
    ],
    "sg:phone":"+1 803 233 0533",
    "sg:postcode":"29201",
    "sg:province":"SC",
    "sg:tags":[
        "web",
        "design"
    ],
    "wof:name":"Justinsane Design",
    "wof:placetype":"venue"
},
  "geometry": {"coordinates":[-81.03420300000001,34.004101],"type":"Point"}
}