{
  "type": "Feature",
  "properties": {
    "addr:full":"211 N Main St Summerville SC 29483",
    "addr:housenumber":"211",
    "addr:postcode":"29483",
    "addr:street":"N Main St",
    "iso:country":"US",
    "sg:address":"211 N Main St",
    "sg:city":"Summerville",
    "sg:classifiers":[
        {
            "category":"Shopping",
            "subcategory":"Florist",
            "type":"Retail Goods"
        }
    ],
    "sg:phone":"+1 843 873 3681",
    "sg:postcode":"29483",
    "sg:province":"SC",
    "wof:name":"O K Florist",
    "wof:placetype":"venue"
},
  "geometry": {"coordinates":[-80.17386500000001,33.021664],"type":"Point"}
}