{
  "type": "Feature",
  "properties": {
    "addr:full":"110 Shirley Store Rd Anderson SC 29621",
    "addr:housenumber":"110",
    "addr:postcode":"29621",
    "addr:street":"Shirley Store Rd",
    "iso:country":"US",
    "sg:address":"110 Shirley Store Rd",
    "sg:city":"Anderson",
    "sg:classifiers":[
        {
            "category":"Building & Trades",
            "subcategory":"Construction",
            "type":"Services"
        }
    ],
    "sg:phone":"+1 864 225 6906",
    "sg:postcode":"29621",
    "sg:province":"SC",
    "sg:tags":[
        "fabricator",
        "metal"
    ],
    "sg:website":"www.darbymetalinc.com",
    "wof:name":"Darby Metalworks Inc",
    "wof:placetype":"venue"
},
  "geometry": {"coordinates":[-82.580681,34.476207],"type":"Point"}
}