{
  "type": "Feature",
  "properties": {
    "iso:country":"US",
    "sg:address":"3800 Forest Dr",
    "sg:city":"Columbia",
    "sg:classifiers":[
        {
            "category":"Professional",
            "type":"Services"
        }
    ],
    "sg:phone":"+1 803 782 1744",
    "sg:postcode":"29204",
    "sg:province":"SC",
    "sg:tags":[
        "establishment"
    ],
    "wof:name":"Summertide Corp",
    "wof:placetype":"venue"
},
  "geometry": {"coordinates":[-80.986422,34.01973],"type":"Point"}
}