{
  "type": "Feature",
  "properties": {
    "iso:country":"US",
    "sg:address":"623 Sweet William Way",
    "sg:city":"Fountain Inn",
    "sg:classifiers":[
        {
            "category":"Food & Beverages",
            "subcategory":"Specialty",
            "type":"Retail Goods"
        }
    ],
    "sg:phone":"+1 864 862 2678",
    "sg:postcode":"29644",
    "sg:province":"SC",
    "wof:name":"Your Life",
    "wof:placetype":"venue"
},
  "geometry": {"coordinates":[-82.180841,34.709734],"type":"Point"}
}