{
  "type": "Feature",
  "properties": {
    "addr:full":"208 Thomas Dr Summerville SC 29483",
    "addr:housenumber":"208",
    "addr:postcode":"29483",
    "addr:street":"Thomas Dr",
    "iso:country":"US",
    "sg:address":"208 Thomas Dr",
    "sg:city":"Summerville",
    "sg:classifiers":[
        {
            "category":"Building & Trades",
            "subcategory":"Plumbing",
            "type":"Services"
        }
    ],
    "sg:phone":"+1 843 851 7333",
    "sg:postcode":"29483",
    "sg:province":"SC",
    "sg:tags":[
        "conditioning",
        "air",
        "system",
        "contractor"
    ],
    "wof:name":"A & E Heating & Air Inc",
    "wof:placetype":"venue"
},
  "geometry": {"coordinates":[-80.241058,33.049609],"type":"Point"}
}