{
  "type": "Feature",
  "properties": {
    "iso:country":"US",
    "sg:address":"336 King St",
    "sg:city":"Charleston",
    "sg:classifiers":[
        {
            "category":"Shopping",
            "subcategory":"Bicycles & Sporting Goods",
            "type":"Retail Goods"
        }
    ],
    "sg:phone":"+1 843 853 9987",
    "sg:postcode":"29401",
    "sg:province":"SC",
    "sg:website":"www.theextramileinc.com",
    "wof:name":"Extra Mile",
    "wof:placetype":"venue"
},
  "geometry": {"coordinates":[-79.935782,32.785023],"type":"Point"}
}