{
  "type": "Feature",
  "properties": {
    "iso:country":"US",
    "sg:address":"137 Gadsden St",
    "sg:city":"Chester",
    "sg:classifiers":[
        {
            "category":"Shopping",
            "subcategory":"Florist",
            "type":"Retail Goods"
        }
    ],
    "sg:phone":"+1 803 385 5556",
    "sg:postcode":"29706",
    "sg:province":"SC",
    "wof:name":"Blossom Shop",
    "wof:placetype":"venue"
},
  "geometry": {"coordinates":[-81.212,34.705164],"type":"Point"}
}