{
  "type": "Feature",
  "properties": {
    "iso:country":"US",
    "sg:address":"2645 Red Bluff Rd",
    "sg:city":"Loris",
    "sg:classifiers":[
        {
            "category":"Professional",
            "subcategory":"Business Services",
            "type":"Services"
        },
        {
            "category":"Building & Trades",
            "subcategory":"Landscaping Services",
            "type":"Services"
        }
    ],
    "sg:phone":"+1 843 756 4815",
    "sg:postcode":"29569",
    "sg:province":"SC",
    "sg:tags":[
        "lawn",
        "maintenance",
        "grounds"
    ],
    "wof:name":"Drake's Lawn & Pool Care",
    "wof:placetype":"venue"
},
  "geometry": {"coordinates":[-78.86535600000001,33.995027],"type":"Point"}
}