{
  "type": "Feature",
  "properties": {
    "iso:country":"US",
    "sg:address":"4712 Broad St",
    "sg:city":"Sumter",
    "sg:classifiers":[
        {
            "category":"Retail",
            "subcategory":"Auto Repair",
            "type":"Services"
        }
    ],
    "sg:phone":"+1 803 494 2836",
    "sg:postcode":"29154",
    "sg:province":"SC",
    "sg:tags":[
        "body",
        "automobile",
        "painting"
    ],
    "wof:name":"E & J Auto Body Shop",
    "wof:placetype":"venue"
},
  "geometry": {"coordinates":[-80.468324,33.961331],"type":"Point"}
}