{
  "type": "Feature",
  "properties": {
    "addr:full":"805 E Greenwood St Abbeville SC 29620",
    "addr:housenumber":"805",
    "addr:postcode":"29620",
    "addr:street":"E Greenwood St",
    "iso:country":"US",
    "sg:address":"805 E Greenwood St",
    "sg:city":"Abbeville",
    "sg:classifiers":[
        {
            "category":"Shopping",
            "subcategory":"Clothing, Apparel, & Fashions",
            "type":"Retail Goods"
        }
    ],
    "sg:phone":"+1 864 366 0100",
    "sg:postcode":"29620",
    "sg:province":"SC",
    "sg:tags":[
        "infant",
        "wear"
    ],
    "wof:name":"Children's Closet",
    "wof:placetype":"venue"
},
  "geometry": {"coordinates":[-82.36174099999999,34.180768],"type":"Point"}
}