{
  "type": "Feature",
  "properties": {
    "addr:full":"104 Corporate Blvd West Columbia SC 29169",
    "addr:housenumber":"104",
    "addr:postcode":"29169",
    "addr:street":"Corporate Blvd",
    "iso:country":"US",
    "sg:address":"104 Corporate Blvd",
    "sg:city":"West Columbia",
    "sg:classifiers":[
        {
            "category":"Communications",
            "subcategory":"Film & Video Production",
            "type":"Services"
        }
    ],
    "sg:phone":"+1 803 739 0929",
    "sg:postcode":"29169",
    "sg:province":"SC",
    "sg:tags":[
        "taping"
    ],
    "sg:website":"www.kalincorp.com",
    "wof:name":"Communications Group",
    "wof:placetype":"venue"
},
  "geometry": {"coordinates":[-81.102979,33.995354],"type":"Point"}
}