{
  "type": "Feature",
  "properties": {
    "addr:full":"1510 N Fant St Anderson SC 29621",
    "addr:housenumber":"1510",
    "addr:postcode":"29621",
    "addr:street":"N Fant St",
    "iso:country":"US",
    "sg:address":"1510 N Fant St",
    "sg:city":"Anderson",
    "sg:classifiers":[
        {
            "category":"Shopping",
            "subcategory":"Pharmacy",
            "type":"Retail Goods"
        }
    ],
    "sg:phone":"+1 864 226 8331",
    "sg:postcode":"29621",
    "sg:province":"SC",
    "wof:name":"Bryants Pharmacy",
    "wof:placetype":"venue"
},
  "geometry": {"coordinates":[-82.650779,34.519331],"type":"Point"}
}