{
  "type": "Feature",
  "properties": {
    "iso:country":"US",
    "sg:address":"1319 Bethelfields Trce",
    "sg:city":"York",
    "sg:classifiers":[
        {
            "category":"Building & Trades",
            "subcategory":"Construction",
            "type":"Services"
        }
    ],
    "sg:phone":"+1 803 631 4873",
    "sg:postcode":"29745",
    "sg:province":"SC",
    "sg:tags":[
        "home",
        "builder",
        "contractor"
    ],
    "wof:name":"Westminster Homes",
    "wof:placetype":"venue"
},
  "geometry": {"coordinates":[-81.09591,35.090024],"type":"Point"}
}