{
  "type": "Feature",
  "properties": {
    "iso:country":"US",
    "sg:address":"208 Frontage Rd",
    "sg:city":"Aiken",
    "sg:classifiers":[
        {
            "category":"Building & Trades",
            "subcategory":"Construction",
            "type":"Services"
        }
    ],
    "sg:phone":"+1 803 642 9975",
    "sg:postcode":"29801",
    "sg:province":"SC",
    "sg:tags":[
        "painter"
    ],
    "wof:name":"Davis Painting Contr Shop",
    "wof:placetype":"venue"
},
  "geometry": {"coordinates":[-81.734481,33.640618],"type":"Point"}
}