{
  "type": "Feature",
  "properties": {
    "iso:country":"US",
    "sg:address":"1601 Shop Rd",
    "sg:city":"Columbia",
    "sg:classifiers":[
        {
            "category":"Wholesale",
            "subcategory":"Groceries",
            "type":"Manufacturing & Wholesale Goods"
        }
    ],
    "sg:phone":"+1 803 771 0970",
    "sg:postcode":"29201",
    "sg:province":"SC",
    "sg:tags":[
        "baker"
    ],
    "wof:name":"Rising High Wholesale",
    "wof:placetype":"venue"
},
  "geometry": {"coordinates":[-81.007145,33.970744],"type":"Point"}
}