{
  "type": "Feature",
  "properties": {
    "iso:country":"US",
    "sg:address":"212 Beltline Rd",
    "sg:city":"Union",
    "sg:classifiers":[
        {
            "category":"Food & Beverages",
            "subcategory":"Liquor & Beverages",
            "type":"Retail Goods"
        }
    ],
    "sg:phone":"+1 864 429 4811",
    "sg:postcode":"29379",
    "sg:province":"SC",
    "wof:name":"Dawkins Liquor Store",
    "wof:placetype":"venue"
},
  "geometry": {"coordinates":[-81.611591,34.699082],"type":"Point"}
}