{
  "type": "Feature",
  "properties": {
    "iso:country":"US",
    "sg:address":"5697 Chesnee Hwy",
    "sg:city":"Chesnee",
    "sg:classifiers":[
        {
            "category":"Autos & Motor Vehicles",
            "subcategory":"Automobile Sales",
            "type":"Retail Goods"
        }
    ],
    "sg:phone":"+1 864 461 7515",
    "sg:postcode":"29323",
    "sg:province":"SC",
    "sg:tags":[
        "used"
    ],
    "wof:name":"Gregory Motor Co",
    "wof:placetype":"venue"
},
  "geometry": {"coordinates":[-81.85655199999999,35.115189],"type":"Point"}
}