{
  "type": "Feature",
  "properties": {
    "addr:full":"592 E Main St Laurens SC 29360",
    "addr:housenumber":"592",
    "addr:postcode":"29360",
    "addr:street":"E Main St",
    "iso:country":"US",
    "sg:address":"592 E Main St",
    "sg:city":"Laurens",
    "sg:classifiers":[
        {
            "category":"Retail",
            "subcategory":"Auto Repair",
            "type":"Services"
        }
    ],
    "sg:phone":"+1 864 984 9616",
    "sg:postcode":"29360",
    "sg:province":"SC",
    "sg:tags":[
        "repairing",
        "automobile"
    ],
    "wof:name":"Jim's Auto Repair",
    "wof:placetype":"venue"
},
  "geometry": {"coordinates":[-81.99890499999999,34.498892],"type":"Point"}
}