{
  "type": "Feature",
  "properties": {
    "addr:full":"1824 E Main St Easley SC 29640",
    "addr:housenumber":"1824",
    "addr:postcode":"29640",
    "addr:street":"E Main St",
    "iso:country":"US",
    "sg:address":"1824 E Main St",
    "sg:city":"Easley",
    "sg:classifiers":[
        {
            "category":"Manufacturing",
            "subcategory":"Printing",
            "type":"Manufacturing & Wholesale Goods"
        }
    ],
    "sg:phone":"+1 864 859 0048",
    "sg:postcode":"29640",
    "sg:province":"SC",
    "sg:tags":[
        "printer",
        "commercial"
    ],
    "wof:name":"First Choice Printing",
    "wof:placetype":"venue"
},
  "geometry": {"coordinates":[-82.56876200000001,34.827517],"type":"Point"}
}