{
  "type": "Feature",
  "properties": {
    "addr:full":"101 S John St Blacksburg SC 29702",
    "addr:housenumber":"101",
    "addr:postcode":"29702",
    "addr:street":"S John St",
    "iso:country":"US",
    "sg:address":"101 S John St",
    "sg:city":"Blacksburg",
    "sg:classifiers":[
        {
            "category":"Sports & Exercise",
            "subcategory":"Gym",
            "type":"Entertainment"
        }
    ],
    "sg:phone":"+1 864 839 3505",
    "sg:postcode":"29702",
    "sg:province":"SC",
    "sg:tags":[
        "spa",
        "health"
    ],
    "wof:name":"Great Vine Day Spa",
    "wof:placetype":"venue"
},
  "geometry": {"coordinates":[-81.52032699999999,35.119102],"type":"Point"}
}