{
  "type": "Feature",
  "properties": {
    "addr:full":"1175 S Guignard Dr Sumter SC 29150",
    "addr:housenumber":"1175",
    "addr:postcode":"29150",
    "addr:street":"S Guignard Dr",
    "iso:country":"US",
    "sg:address":"1175 S Guignard Dr",
    "sg:city":"Sumter",
    "sg:classifiers":[
        {
            "category":"Retail",
            "subcategory":"Repair Shop",
            "type":"Services"
        }
    ],
    "sg:phone":"+1 803 773 6347",
    "sg:postcode":"29150",
    "sg:province":"SC",
    "sg:tags":[
        "welding"
    ],
    "wof:name":"Southern Welding & Body Works",
    "wof:placetype":"venue"
},
  "geometry": {"coordinates":[-80.350827,33.888849],"type":"Point"}
}