{
  "type": "Feature",
  "properties": {
    "iso:country":"US",
    "sg:address":"2300 Church St",
    "sg:city":"Conway",
    "sg:classifiers":[
        {
            "category":"Home & Garden",
            "subcategory":"Furniture",
            "type":"Retail Goods"
        }
    ],
    "sg:phone":"+1 843 369 1441",
    "sg:postcode":"29526",
    "sg:province":"SC",
    "wof:name":"Badcock Home Furnishings Ctr",
    "wof:placetype":"venue"
},
  "geometry": {"coordinates":[-79.075572,33.852591],"type":"Point"}
}