{
  "type": "Feature",
  "properties": {
    "iso:country":"US",
    "sg:address":"55 Forest Oaks Way",
    "sg:city":"Spartanburg",
    "sg:classifiers":[
        {
            "category":"Retail",
            "subcategory":"Portrait Studio",
            "type":"Services"
        }
    ],
    "sg:phone":"+1 803 782 1151",
    "sg:postcode":"29307",
    "sg:province":"SC",
    "sg:tags":[
        "photographer"
    ],
    "wof:name":"Portrait Group",
    "wof:placetype":"venue"
},
  "geometry": {"coordinates":[-81.882746,34.954049],"type":"Point"}
}