{
  "type": "Feature",
  "properties": {
    "iso:country":"US",
    "sg:address":"1353 Springdale Rd",
    "sg:city":"Lancaster",
    "sg:classifiers":[
        {
            "category":"Government",
            "subcategory":"Office",
            "type":"Public Place"
        }
    ],
    "sg:phone":"+1 803 283 4191",
    "sg:postcode":"29720",
    "sg:province":"SC",
    "wof:name":"Lancaster County Drug Task",
    "wof:placetype":"venue"
},
  "geometry": {"coordinates":[-80.788359,34.695243],"type":"Point"}
}