{
  "type": "Feature",
  "properties": {
    "iso:country":"US",
    "sg:address":"108 Marietta St",
    "sg:city":"Pageland",
    "sg:classifiers":[
        {
            "category":"Building & Trades",
            "subcategory":"Landscaping Services",
            "type":"Services"
        }
    ],
    "sg:phone":"+1 843 672 3296",
    "sg:postcode":"29710",
    "sg:province":"SC",
    "sg:tags":[
        "landscape",
        "contractor"
    ],
    "wof:name":"Barrett's Nursery",
    "wof:placetype":"venue"
},
  "geometry": {"coordinates":[-81.23126999999999,35.114558],"type":"Point"}
}