{
  "type": "Feature",
  "properties": {
    "addr:full":"249 W Main St Lake City SC 29560",
    "addr:housenumber":"249",
    "addr:postcode":"29560",
    "addr:street":"W Main St",
    "iso:country":"US",
    "sg:address":"249 W Main St",
    "sg:city":"Lake City",
    "sg:classifiers":[
        {
            "category":"Health Services",
            "subcategory":"Clinic",
            "type":"Services"
        }
    ],
    "sg:phone":"+1 843 394 9964",
    "sg:postcode":"29560",
    "sg:province":"SC",
    "sg:tags":[
        "home"
    ],
    "wof:name":"Florence Visiting Nurses",
    "wof:placetype":"venue"
},
  "geometry": {"coordinates":[-79.759291,33.876028],"type":"Point"}
}