{
  "type": "Feature",
  "properties": {
    "iso:country":"US",
    "sg:address":"3010 N Main St",
    "sg:city":"Anderson",
    "sg:classifiers":[
        {
            "category":"Professional",
            "subcategory":"Accounting & Tax Preparation",
            "type":"Services"
        }
    ],
    "sg:phone":"+1 864 224 0804",
    "sg:postcode":"29621",
    "sg:province":"SC",
    "sg:tags":[
        "return",
        "filing"
    ],
    "wof:name":"M & M Income Tax Svc",
    "wof:placetype":"venue"
},
  "geometry": {"coordinates":[-82.66604599999999,34.534875],"type":"Point"}
}