{
  "type": "Feature",
  "properties": {
    "iso:country":"US",
    "sg:address":"101 Bennington Way",
    "sg:city":"Greer",
    "sg:classifiers":[
        {
            "category":"Banks & Credit Unions",
            "subcategory":"Financial Services",
            "type":"Services"
        }
    ],
    "sg:phone":"+1 864 244 7165",
    "sg:postcode":"29650",
    "sg:province":"SC",
    "sg:tags":[
        "company",
        "holding"
    ],
    "wof:name":"DFL Holdings",
    "wof:placetype":"venue"
},
  "geometry": {"coordinates":[-82.27883199999999,34.872416],"type":"Point"}
}