{
  "type": "Feature",
  "properties": {
    "addr:full":"185 S Main St Gaston SC 29053",
    "addr:housenumber":"185",
    "addr:postcode":"29053",
    "addr:street":"S Main St",
    "iso:country":"US",
    "sg:address":"185 S Main St",
    "sg:city":"Gaston",
    "sg:classifiers":[
        {
            "category":"Food & Beverages",
            "subcategory":"Groceries & Convenience Stores",
            "type":"Retail Goods"
        }
    ],
    "sg:phone":"+1 803 794 3920",
    "sg:postcode":"29053",
    "sg:province":"SC",
    "sg:tags":[
        "grocer"
    ],
    "wof:name":"Gaston Iga",
    "wof:placetype":"venue"
},
  "geometry": {"coordinates":[-81.101815,33.812319],"type":"Point"}
}