{
  "type": "Feature",
  "properties": {
    "iso:country":"US",
    "sg:address":"514 S 5th St",
    "sg:city":"Hartsville",
    "sg:classifiers":[
        {
            "category":"Restaurant",
            "type":"Food & Drink"
        }
    ],
    "sg:phone":"+1 843 332 7031",
    "sg:postcode":"29550",
    "sg:province":"SC",
    "sg:tags":[
        "eating"
    ],
    "wof:name":"Yogi Bear Honey Fried Chicken",
    "wof:placetype":"venue"
},
  "geometry": {"coordinates":[-80.067538,34.363691],"type":"Point"}
}