{
  "type": "Feature",
  "properties": {
    "addr:full":"2950 E North St Greenville SC 29615",
    "addr:housenumber":"2950",
    "addr:postcode":"29615",
    "addr:street":"E North St",
    "iso:country":"US",
    "sg:address":"2950 E North St",
    "sg:city":"Greenville",
    "sg:classifiers":[
        {
            "category":"Shopping",
            "subcategory":"Clothing, Apparel, & Fashions",
            "type":"Retail Goods"
        }
    ],
    "sg:phone":"+1 864 268 0133",
    "sg:postcode":"29615",
    "sg:province":"SC",
    "wof:name":"Lady's V Fashion",
    "wof:placetype":"venue"
},
  "geometry": {"coordinates":[-82.344949,34.87062],"type":"Point"}
}