{
  "type": "Feature",
  "properties": {
    "addr:full":"1623 Enterprise Ln Seneca SC 29672",
    "addr:housenumber":"1623",
    "addr:postcode":"29672",
    "addr:street":"Enterprise Ln",
    "iso:country":"US",
    "sg:address":"1623 Enterprise Ln",
    "sg:city":"Seneca",
    "sg:classifiers":[
        {
            "category":"Education",
            "subcategory":"Special Training",
            "type":"Public Place"
        }
    ],
    "sg:phone":"+1 864 882 9800",
    "sg:postcode":"29672",
    "sg:province":"SC",
    "sg:tags":[
        "program"
    ],
    "wof:name":"Wheless Communications",
    "wof:placetype":"venue"
},
  "geometry": {"coordinates":[-82.948859,34.705775],"type":"Point"}
}