{
  "type": "Feature",
  "properties": {
    "iso:country":"US",
    "sg:address":"3955 Southeastern Way",
    "sg:city":"West Columbia",
    "sg:classifiers":[
        {
            "category":"Banks & Credit Unions",
            "subcategory":"Bank",
            "type":"Services"
        }
    ],
    "sg:phone":"+1 803 796 7500",
    "sg:postcode":"29169",
    "sg:province":"SC",
    "sg:tags":[
        "loan",
        "real estate"
    ],
    "wof:name":"Premier Mortgage Funding",
    "wof:placetype":"venue"
},
  "geometry": {"coordinates":[-81.14307700000001,34.007079],"type":"Point"}
}