{
  "type": "Feature",
  "properties": {
    "iso:country":"US",
    "sg:address":"1450 Lafayette Ave",
    "sg:city":"Cayce",
    "sg:classifiers":[
        {
            "category":"Building & Trades",
            "subcategory":"Plumbing",
            "type":"Services"
        }
    ],
    "sg:phone":"+1 803 791 9906",
    "sg:postcode":"29033",
    "sg:province":"SC",
    "sg:tags":[
        "plumbing",
        "contractor"
    ],
    "wof:name":"Puntnam Plumbing Co",
    "wof:placetype":"venue"
},
  "geometry": {"coordinates":[-81.0732,33.975481],"type":"Point"}
}