{
  "type": "Feature",
  "properties": {
    "iso:country":"US",
    "sg:address":"110 Medical Cir",
    "sg:city":"West Columbia",
    "sg:classifiers":[
        {
            "category":"Health Services",
            "subcategory":"Medical Lab",
            "type":"Services"
        }
    ],
    "sg:phone":"+1 803 791 0273",
    "sg:postcode":"29169",
    "sg:province":"SC",
    "sg:tags":[
        "laboratory"
    ],
    "wof:name":"Lexington Medical Labs",
    "wof:placetype":"venue"
},
  "geometry": {"coordinates":[-81.112641,34.004176],"type":"Point"}
}