{
  "type": "Feature",
  "properties": {
    "iso:country":"US",
    "sg:address":"1519 Executive Ave",
    "sg:city":"Myrtle Beach",
    "sg:classifiers":[
        {
            "category":"Wholesale",
            "subcategory":"Beer",
            "type":"Manufacturing & Wholesale Goods"
        }
    ],
    "sg:phone":"+1 843 448 9492",
    "sg:postcode":"29577",
    "sg:province":"SC",
    "sg:tags":[
        "ale"
    ],
    "wof:name":"Benchmark Distribuing",
    "wof:placetype":"venue"
},
  "geometry": {"coordinates":[-78.901159,33.702402],"type":"Point"}
}