{
  "type": "Feature",
  "properties": {
    "iso:country":"US",
    "sg:address":"2614 Warm Ave",
    "sg:city":"Charleston",
    "sg:classifiers":[
        {
            "category":"Retail",
            "subcategory":"Auto Repair",
            "type":"Services"
        }
    ],
    "sg:phone":"+1 843 797 2405",
    "sg:postcode":"29420",
    "sg:province":"SC",
    "sg:tags":[
        "repairing",
        "automobile"
    ],
    "wof:name":"Hilbourn Garage",
    "wof:placetype":"venue"
},
  "geometry": {"coordinates":[-80.05370600000001,32.935713],"type":"Point"}
}