{
  "type": "Feature",
  "properties": {
    "iso:country":"US",
    "sg:address":"10 Toy St",
    "sg:city":"Greenville",
    "sg:classifiers":[
        {
            "category":"Social Services",
            "type":"Services"
        }
    ],
    "sg:phone":"+1 864 235 9491",
    "sg:postcode":"29601",
    "sg:province":"SC",
    "sg:tags":[
        "youth",
        "organization",
        "center"
    ],
    "wof:name":"Junior Achievement-Greenville",
    "wof:placetype":"venue"
},
  "geometry": {"coordinates":[-82.38859600000001,34.850343],"type":"Point"}
}