{
  "type": "Feature",
  "properties": {
    "iso:country":"US",
    "sg:address":"702 Glenwood Ave",
    "sg:city":"Anderson",
    "sg:classifiers":[
        {
            "category":"Retail",
            "subcategory":"Laundry & Dry Cleaning",
            "type":"Services"
        }
    ],
    "sg:phone":"+1 864 222 2132",
    "sg:postcode":"29625",
    "sg:province":"SC",
    "sg:tags":[
        "cleaners",
        "rug",
        "carpet"
    ],
    "wof:name":"Anderson Chem-Dry",
    "wof:placetype":"venue"
},
  "geometry": {"coordinates":[-82.670781,34.523263],"type":"Point"}
}