{
  "type": "Feature",
  "properties": {
    "addr:full":"306 W Stall St Summerville SC 29485",
    "addr:housenumber":"306",
    "addr:postcode":"29485",
    "addr:street":"W Stall St",
    "iso:country":"US",
    "sg:address":"306 W Stall St",
    "sg:city":"Summerville",
    "sg:classifiers":[
        {
            "category":"Autos & Motor Vehicles",
            "subcategory":"Automobile Sales",
            "type":"Retail Goods"
        }
    ],
    "sg:phone":"+1 843 851 7388",
    "sg:postcode":"29485",
    "sg:province":"SC",
    "sg:tags":[
        "used"
    ],
    "wof:name":"Auto Clean Used Cars",
    "wof:placetype":"venue"
},
  "geometry": {"coordinates":[-80.162184,33.008772],"type":"Point"}
}