{
  "type": "Feature",
  "properties": {
    "iso:country":"US",
    "sg:address":"3600 Main St",
    "sg:city":"Hilton Head Isle",
    "sg:classifiers":[
        {
            "category":"Professional",
            "subcategory":"Lawyer & Legal Services",
            "type":"Services"
        }
    ],
    "sg:phone":"+1 843 689 2661",
    "sg:postcode":"29926",
    "sg:province":"SC",
    "sg:tags":[
        "attorney"
    ],
    "wof:name":"Thomas L Brooks",
    "wof:placetype":"venue"
},
  "geometry": {"coordinates":[-80.72886200000001,32.214377],"type":"Point"}
}