{
  "type": "Feature",
  "properties": {
    "iso:country":"US",
    "sg:address":"301 S Dargan St",
    "sg:city":"Florence",
    "sg:classifiers":[
        {
            "category":"Education",
            "subcategory":"School",
            "type":"Public Place"
        }
    ],
    "sg:phone":"+1 843 664 8152",
    "sg:postcode":"29506",
    "sg:province":"SC",
    "wof:name":"Florence Adult Education Dept",
    "wof:placetype":"venue"
},
  "geometry": {"coordinates":[-79.765652,34.191959],"type":"Point"}
}