{
  "type": "Feature",
  "properties": {
    "addr:full":"5361 E Jim Bilton Blvd St George SC 29477",
    "addr:housenumber":"5361",
    "addr:postcode":"29477",
    "addr:street":"E Jim Bilton Blvd",
    "iso:country":"US",
    "sg:address":"5361 E Jim Bilton Blvd",
    "sg:city":"St George",
    "sg:classifiers":[
        {
            "category":"Government",
            "subcategory":"Office",
            "type":"Public Place"
        }
    ],
    "sg:phone":"+1 843 563 3709",
    "sg:postcode":"29477",
    "sg:province":"SC",
    "sg:tags":[
        "village"
    ],
    "wof:name":"St George Senior Citizens Home",
    "wof:placetype":"venue"
},
  "geometry": {"coordinates":[-80.559067,33.180328],"type":"Point"}
}