{
  "type": "Feature",
  "properties": {
    "iso:country":"US",
    "sg:address":"2147 Hwy 9 E",
    "sg:city":"Dillon",
    "sg:classifiers":[
        {
            "category":"Food & Beverages",
            "subcategory":"Liquor & Beverages",
            "type":"Retail Goods"
        }
    ],
    "sg:phone":"+1 843 841 2544",
    "sg:postcode":"29536",
    "sg:province":"SC",
    "sg:tags":[
        "alcoholic"
    ],
    "wof:name":"Blue Meadow's Fine Wines",
    "wof:placetype":"venue"
},
  "geometry": {"coordinates":[-79.326804,34.404776],"type":"Point"}
}