{
  "type": "Feature",
  "properties": {
    "iso:country":"US",
    "sg:address":"1721 White Horse Rd",
    "sg:city":"Greenville",
    "sg:classifiers":[
        {
            "category":"Manufacturing",
            "subcategory":"Motor Vehicles & Parts",
            "type":"Manufacturing & Wholesale Goods"
        }
    ],
    "sg:phone":"+1 864 220 1010",
    "sg:postcode":"29605",
    "sg:province":"SC",
    "sg:tags":[
        "automobile",
        "supply"
    ],
    "sg:website":"www.prettl.com",
    "wof:name":"Prettl Electric Corp",
    "wof:placetype":"venue"
},
  "geometry": {"coordinates":[-82.412088,34.785516],"type":"Point"}
}