{
  "type": "Feature",
  "properties": {
    "addr:full":"211 S Ocean Blvd Surfside Beach SC 29575",
    "addr:housenumber":"211",
    "addr:postcode":"29575",
    "addr:street":"S Ocean Blvd",
    "iso:country":"US",
    "sg:address":"211 S Ocean Blvd",
    "sg:city":"Surfside Beach",
    "sg:classifiers":[
        {
            "category":"Travel",
            "subcategory":"Hotels & Motels",
            "type":"Entertainment"
        }
    ],
    "sg:phone":"+1 843 448 5524",
    "sg:postcode":"29575",
    "sg:province":"SC",
    "wof:name":"Columbus Inn",
    "wof:placetype":"venue"
},
  "geometry": {"coordinates":[-78.974075,33.603841],"type":"Point"}
}