{
  "type": "Feature",
  "properties": {
    "iso:country":"US",
    "sg:address":"528 Haywood Rd",
    "sg:city":"Greenville",
    "sg:classifiers":[
        {
            "category":"Restaurant",
            "type":"Food & Drink"
        }
    ],
    "sg:phone":"+1 864 234 0103",
    "sg:postcode":"29607",
    "sg:province":"SC",
    "sg:website":"www.buffaloscafe.com",
    "wof:name":"Buffalos Cafe Greenville",
    "wof:placetype":"venue"
},
  "geometry": {"coordinates":[-82.33845599999999,34.848439],"type":"Point"}
}