{
  "type": "Feature",
  "properties": {
    "iso:country":"US",
    "sg:address":"410 Magnolia St",
    "sg:city":"Spartanburg",
    "sg:classifiers":[
        {
            "category":"Banks & Credit Unions",
            "subcategory":"Bank",
            "type":"Services"
        }
    ],
    "sg:phone":"+1 864 585 5891",
    "sg:postcode":"29303",
    "sg:province":"SC",
    "sg:tags":[
        "broker",
        "mortgage"
    ],
    "wof:name":"New Beginnings Deed & Trust",
    "wof:placetype":"venue"
},
  "geometry": {"coordinates":[-81.939628,34.957073],"type":"Point"}
}