{
  "type": "Feature",
  "properties": {
    "iso:country":"US",
    "sg:address":"400 Agnew Rd",
    "sg:city":"Greenville",
    "sg:classifiers":[
        {
            "category":"Professional",
            "subcategory":"Business Services",
            "type":"Services"
        }
    ],
    "sg:phone":"+1 864 246 2128",
    "sg:postcode":"29617",
    "sg:province":"SC",
    "sg:tags":[
        "interior",
        "consultant",
        "design",
        "decorator"
    ],
    "sg:website":"www.harleybutzsilktrees.com",
    "wof:name":"Harley Butz Silk Trees",
    "wof:placetype":"venue"
},
  "geometry": {"coordinates":[-82.448115,34.866169],"type":"Point"}
}