{
  "type": "Feature",
  "properties": {
    "iso:country":"US",
    "sg:address":"1916 W Evans St",
    "sg:city":"Florence",
    "sg:classifiers":[
        {
            "category":"Home & Garden",
            "subcategory":"Furniture",
            "type":"Retail Goods"
        }
    ],
    "sg:phone":"+1 843 662 7272",
    "sg:postcode":"29501",
    "sg:province":"SC",
    "wof:name":"Highpoint Sofa Factory",
    "wof:placetype":"venue"
},
  "geometry": {"coordinates":[-79.803443,34.195368],"type":"Point"}
}