{
  "type": "Feature",
  "properties": {
    "addr:full":"7833 Broad River Rd Irmo SC 29063",
    "addr:housenumber":"7833",
    "addr:postcode":"29063",
    "addr:street":"Broad River Rd",
    "iso:country":"US",
    "sg:address":"7833 Broad River Rd",
    "sg:city":"Irmo",
    "sg:classifiers":[
        {
            "category":"Insurance",
            "subcategory":"Insurance Agent",
            "type":"Services"
        }
    ],
    "sg:phone":"+1 803 781 1045",
    "sg:postcode":"29063",
    "sg:province":"SC",
    "wof:name":"Aid Association For Lutherans",
    "wof:placetype":"venue"
},
  "geometry": {"coordinates":[-81.183584,34.103393],"type":"Point"}
}