{
  "type": "Feature",
  "properties": {
    "iso:country":"US",
    "sg:address":"555 Beaudrot Rd",
    "sg:city":"Greenwood",
    "sg:classifiers":[
        {
            "category":"Building & Trades",
            "subcategory":"Landscaping Services",
            "type":"Services"
        }
    ],
    "sg:phone":"+1 864 229 0803",
    "sg:postcode":"29649",
    "sg:province":"SC",
    "sg:tags":[
        "landscape",
        "contractor"
    ],
    "wof:name":"Martin Construction Co",
    "wof:placetype":"venue"
},
  "geometry": {"coordinates":[-82.19577,34.20677],"type":"Point"}
}