{
  "type": "Feature",
  "properties": {
    "iso:country":"US",
    "sg:address":"680 Kent St",
    "sg:city":"Mount Pleasant",
    "sg:classifiers":[
        {
            "category":"Autos & Motor Vehicles",
            "subcategory":"Fuel & Gas Station",
            "type":"Retail Goods"
        }
    ],
    "sg:phone":"+1 843 884 4878",
    "sg:postcode":"29464",
    "sg:province":"SC",
    "sg:tags":[
        "repair",
        "station",
        "gasoline"
    ],
    "wof:name":"Texaco",
    "wof:placetype":"venue"
},
  "geometry": {"coordinates":[-79.868158,32.816079],"type":"Point"}
}