{
  "type": "Feature",
  "properties": {
    "iso:country":"US",
    "sg:address":"3545 Dreher Shoals Rd",
    "sg:city":"Irmo",
    "sg:classifiers":[
        {
            "category":"Autos & Motor Vehicles",
            "subcategory":"Automobile Sales",
            "type":"Retail Goods"
        }
    ],
    "sg:phone":"+1 803 749 7873",
    "sg:postcode":"29063",
    "sg:province":"SC",
    "sg:tags":[
        "used"
    ],
    "wof:name":"United Car Sales",
    "wof:placetype":"venue"
},
  "geometry": {"coordinates":[-81.231042,34.122819],"type":"Point"}
}