{
  "type": "Feature",
  "properties": {
    "iso:country":"US",
    "sg:address":"633 Society Hill Rd",
    "sg:city":"Darlington",
    "sg:classifiers":[
        {
            "category":"Building & Trades",
            "subcategory":"Electrical",
            "type":"Services"
        }
    ],
    "sg:phone":"+1 843 393 5601",
    "sg:postcode":"29540",
    "sg:province":"SC",
    "sg:tags":[
        "electric",
        "contractor"
    ],
    "wof:name":"Tiller's Electric Svc",
    "wof:placetype":"venue"
},
  "geometry": {"coordinates":[-79.857463,34.334521],"type":"Point"}
}