{
  "type": "Feature",
  "properties": {
    "iso:country":"US",
    "sg:address":"2 Mountain Side Way",
    "sg:city":"Greenville",
    "sg:classifiers":[
        {
            "category":"Real Estate",
            "subcategory":"Real Estate Operator",
            "type":"Services"
        }
    ],
    "sg:phone":"+1 864 282 1954",
    "sg:postcode":"29609",
    "sg:province":"SC",
    "sg:tags":[
        "building",
        "nonresidential"
    ],
    "wof:name":"Morgan Willis Properties Inc",
    "wof:placetype":"venue"
},
  "geometry": {"coordinates":[-82.394488,34.904914],"type":"Point"}
}