{
  "type": "Feature",
  "properties": {
    "addr:full":"140 Access Rd Gaston SC 29053",
    "addr:housenumber":"140",
    "addr:postcode":"29053",
    "addr:street":"Access Rd",
    "iso:country":"US",
    "sg:address":"140 Access Rd",
    "sg:city":"Gaston",
    "sg:classifiers":[
        {
            "category":"Freight",
            "type":"Transportation"
        }
    ],
    "sg:phone":"+1 803 739 6289",
    "sg:postcode":"29053",
    "sg:province":"SC",
    "sg:tags":[
        "trucking"
    ],
    "sg:website":"www.standardcorp.com",
    "wof:name":"UTI Integrated Logistics",
    "wof:placetype":"venue"
},
  "geometry": {"coordinates":[-81.036873,33.876345],"type":"Point"}
}