{
  "type": "Feature",
  "properties": {
    "addr:full":"239 Rocky Creek Rd Simpsonville SC 29680",
    "addr:housenumber":"239",
    "addr:postcode":"29680",
    "addr:street":"Rocky Creek Rd",
    "iso:country":"US",
    "sg:address":"239 Rocky Creek Rd",
    "sg:city":"Simpsonville",
    "sg:classifiers":[
        {
            "category":"Organizations",
            "subcategory":"Religious Organization",
            "type":"Services"
        }
    ],
    "sg:phone":"+1 864 967 7905",
    "sg:postcode":"29680",
    "sg:province":"SC",
    "sg:tags":[
        "church"
    ],
    "wof:name":"Rocky Creek Baptist Church",
    "wof:placetype":"venue"
},
  "geometry": {"coordinates":[-82.29997400000001,34.702608],"type":"Point"}
}