{
  "type": "Feature",
  "properties": {
    "iso:country":"US",
    "sg:address":"208 W Hampton Ave",
    "sg:city":"Sumter",
    "sg:classifiers":[
        {
            "category":"Health Services",
            "subcategory":"Doctor",
            "type":"Services"
        }
    ],
    "sg:phone":"+1 803 775 2421",
    "sg:postcode":"29150",
    "sg:province":"SC",
    "sg:tags":[
        "physician",
        "surgeon"
    ],
    "wof:name":"Sumter Asthma & Allergy Ctr",
    "wof:placetype":"venue"
},
  "geometry": {"coordinates":[-80.346569,33.92193],"type":"Point"}
}