{
  "type": "Feature",
  "properties": {
    "iso:country":"US",
    "sg:address":"3955 Southeastern Way",
    "sg:city":"West Columbia",
    "sg:classifiers":[
        {
            "category":"Professional",
            "subcategory":"Management & Consulting",
            "type":"Services"
        }
    ],
    "sg:phone":"+1 803 779 4199",
    "sg:postcode":"29169",
    "sg:province":"SC",
    "sg:tags":[
        "marketing",
        "consultant"
    ],
    "wof:name":"I 2 Medic Group",
    "wof:placetype":"venue"
},
  "geometry": {"coordinates":[-81.14307700000001,34.007079],"type":"Point"}
}