{
  "type": "Feature",
  "properties": {
    "iso:country":"US",
    "sg:address":"800 Miller Rd",
    "sg:city":"Sumter",
    "sg:classifiers":[
        {
            "category":"Shopping",
            "subcategory":"Gifts & Souvenirs",
            "type":"Retail Goods"
        }
    ],
    "sg:phone":"+1 803 775 7178",
    "sg:postcode":"29150",
    "sg:province":"SC",
    "sg:tags":[
        "shop"
    ],
    "wof:name":"Fine Things",
    "wof:placetype":"venue"
},
  "geometry": {"coordinates":[-80.35709300000001,33.94298],"type":"Point"}
}