{
  "type": "Feature",
  "properties": {
    "iso:country":"US",
    "sg:address":"1510 Blacksburg Hwy",
    "sg:city":"Blacksburg",
    "sg:classifiers":[
        {
            "category":"Building & Trades",
            "subcategory":"Plumbing",
            "type":"Services"
        }
    ],
    "sg:phone":"+1 864 839 4356",
    "sg:postcode":"29702",
    "sg:province":"SC",
    "sg:tags":[
        "conditioning",
        "air",
        "system",
        "contractor"
    ],
    "wof:name":"Ambassador Heating & Air Cond",
    "wof:placetype":"venue"
},
  "geometry": {"coordinates":[-81.559832,35.14174],"type":"Point"}
}