{
  "type": "Feature",
  "properties": {
    "iso:country":"US",
    "sg:address":"2225 Ashley Crossing Dr",
    "sg:city":"Charleston",
    "sg:classifiers":[
        {
            "category":"Banks & Credit Unions",
            "subcategory":"Bank",
            "type":"Services"
        }
    ],
    "sg:phone":"+1 843 744 2441",
    "sg:postcode":"29414",
    "sg:province":"SC",
    "sg:tags":[
        "loan",
        "real estate"
    ],
    "wof:name":"Investors Mortgage-Charleston",
    "wof:placetype":"venue"
},
  "geometry": {"coordinates":[-80.03901999999999,32.812571],"type":"Point"}
}