{
  "type": "Feature",
  "properties": {
    "addr:full":"4678 Camden Hwy Bishopville SC 29010",
    "addr:housenumber":"4678",
    "addr:postcode":"29010",
    "addr:street":"Camden Hwy",
    "iso:country":"US",
    "sg:address":"4678 Camden Hwy",
    "sg:city":"Bishopville",
    "sg:classifiers":[
        {
            "category":"Personal",
            "subcategory":"Beauty Salon",
            "type":"Services"
        }
    ],
    "sg:phone":"+1 803 428 2777",
    "sg:postcode":"29010",
    "sg:province":"SC",
    "wof:name":"Dada's Hair Hut",
    "wof:placetype":"venue"
},
  "geometry": {"coordinates":[-80.431665,34.221868],"type":"Point"}
}