{
  "type": "Feature",
  "properties": {
    "iso:country":"US",
    "sg:address":"5422 Forest Dr",
    "sg:city":"Columbia",
    "sg:classifiers":[
        {
            "category":"Shopping",
            "subcategory":"Hobbies, Toys, & Games",
            "type":"Retail Goods"
        }
    ],
    "sg:phone":"+1 803 787 2509",
    "sg:postcode":"29204",
    "sg:province":"SC",
    "sg:tags":[
        "craft",
        "supply"
    ],
    "sg:website":"www.hobbylobby.com",
    "wof:name":"Hobby Lobby Creative Ctr",
    "wof:placetype":"venue"
},
  "geometry": {"coordinates":[-80.95206899999999,34.023524],"type":"Point"}
}