{
  "type": "Feature",
  "properties": {
    "iso:country":"US",
    "sg:address":"2109 N Pleasantburg Dr",
    "sg:city":"Greenville",
    "sg:classifiers":[
        {
            "category":"Autos & Motor Vehicles",
            "subcategory":"Auto Supplies",
            "type":"Retail Goods"
        }
    ],
    "sg:phone":"+1 864 232 8995",
    "sg:postcode":"29609",
    "sg:province":"SC",
    "sg:tags":[
        "automobile",
        "parts"
    ],
    "wof:name":"Advance Auto Parts Inc",
    "wof:placetype":"venue"
},
  "geometry": {"coordinates":[-82.37521599999999,34.889645],"type":"Point"}
}