{
  "type": "Feature",
  "properties": {
    "iso:country":"US",
    "sg:address":"205 N Longstreet St",
    "sg:city":"Kingstree",
    "sg:classifiers":[
        {
            "category":"Restaurant",
            "type":"Food & Drink"
        }
    ],
    "sg:phone":"+1 843 354 3020",
    "sg:postcode":"29556",
    "sg:province":"SC",
    "wof:name":"Cantontown Express",
    "wof:placetype":"venue"
},
  "geometry": {"coordinates":[-79.834301,33.6657],"type":"Point"}
}