{
  "type": "Feature",
  "properties": {
    "addr:full":"8 W Marsh Dr St Helena Island SC 29920",
    "addr:housenumber":"8",
    "addr:postcode":"29920",
    "addr:street":"W Marsh Dr St",
    "iso:country":"US",
    "sg:address":"8 W Marsh Dr",
    "sg:city":"St Helena Island",
    "sg:classifiers":[
        {
            "category":"Travel",
            "subcategory":"Hotels & Motels",
            "type":"Entertainment"
        }
    ],
    "sg:phone":"+1 843 838 9751",
    "sg:postcode":"29920",
    "sg:province":"SC",
    "wof:name":"Inn At Harbor Island",
    "wof:placetype":"venue"
},
  "geometry": {"coordinates":[-80.44417900000001,32.402048],"type":"Point"}
}