{
  "type": "Feature",
  "properties": {
    "addr:full":"1442 Corbett Dr Conway SC 29526",
    "addr:housenumber":"1442",
    "addr:postcode":"29526",
    "addr:street":"Corbett Dr",
    "iso:country":"US",
    "sg:address":"1442 Corbett Dr",
    "sg:city":"Conway",
    "sg:classifiers":[
        {
            "category":"Food & Beverages",
            "subcategory":"Specialty",
            "type":"Retail Goods"
        }
    ],
    "sg:phone":"+1 843 488 0484",
    "sg:postcode":"29526",
    "sg:province":"SC",
    "wof:name":"Abundant Life Whole Foods Mkt",
    "wof:placetype":"venue"
},
  "geometry": {"coordinates":[-79.02286700000001,33.746565],"type":"Point"}
}