{
  "type": "Feature",
  "properties": {
    "iso:country":"US",
    "sg:address":"200 Monarch Pl",
    "sg:city":"Wellford",
    "sg:classifiers":[
        {
            "category":"Real Estate",
            "subcategory":"Real Estate Operator",
            "type":"Services"
        }
    ],
    "sg:phone":"+1 864 439 1080",
    "sg:postcode":"29385",
    "sg:province":"SC",
    "sg:tags":[
        "apartment"
    ],
    "wof:name":"Monarch Place Apartments",
    "wof:placetype":"venue"
},
  "geometry": {"coordinates":[-82.107473,34.953477],"type":"Point"}
}