{
  "type": "Feature",
  "properties": {
    "iso:country":"US",
    "sg:address":"221 E Main St",
    "sg:city":"Dillon",
    "sg:classifiers":[
        {
            "category":"Shopping",
            "subcategory":"Clothing, Apparel, & Fashions",
            "type":"Retail Goods"
        }
    ],
    "sg:phone":"+1 843 774 6761",
    "sg:postcode":"29536",
    "sg:province":"SC",
    "wof:name":"Young World Childrens Shop",
    "wof:placetype":"venue"
},
  "geometry": {"coordinates":[-79.370901,34.416543],"type":"Point"}
}