{
  "type": "Feature",
  "properties": {
    "iso:country":"US",
    "sg:address":"6 Ponce de Leon Ave",
    "sg:city":"Charleston",
    "sg:classifiers":[
        {
            "category":"Health Services",
            "subcategory":"Dentist",
            "type":"Services"
        }
    ],
    "sg:phone":"+1 843 556 4774",
    "sg:postcode":"29407",
    "sg:province":"SC",
    "wof:name":"Toporek Stanley D Dds Pa/Dntst",
    "wof:placetype":"venue"
},
  "geometry": {"coordinates":[-79.993493,32.801793],"type":"Point"}
}