{
  "type": "Feature",
  "properties": {
    "addr:full":"12 W Liberty St Sumter SC 29150",
    "addr:housenumber":"12",
    "addr:postcode":"29150",
    "addr:street":"W Liberty St",
    "iso:country":"US",
    "sg:address":"12 W Liberty St",
    "sg:city":"Sumter",
    "sg:classifiers":[
        {
            "category":"Museum",
            "type":"Entertainment"
        }
    ],
    "sg:phone":"+1 803 774 4005",
    "sg:postcode":"29150",
    "sg:province":"SC",
    "sg:tags":[
        "organization",
        "arts",
        "information"
    ],
    "wof:name":"Caroline Mack Ctr For Arts",
    "wof:placetype":"venue"
},
  "geometry": {"coordinates":[-80.34341999999999,33.920515],"type":"Point"}
}