{
  "type": "Feature",
  "properties": {
    "iso:country":"US",
    "sg:address":"11 Hillside Dr",
    "sg:city":"Taylors",
    "sg:classifiers":[
        {
            "category":"Home & Garden",
            "subcategory":"Garden Supply",
            "type":"Retail Goods"
        }
    ],
    "sg:phone":"+1 864 244 4878",
    "sg:postcode":"29687",
    "sg:province":"SC",
    "sg:tags":[
        "lawn",
        "mower"
    ],
    "wof:name":"Hap's Repair Shop",
    "wof:placetype":"venue"
},
  "geometry": {"coordinates":[-82.30656999999999,34.922385],"type":"Point"}
}