{
  "type": "Feature",
  "properties": {
    "iso:country":"US",
    "sg:address":"137 Patio Pl",
    "sg:city":"Columbia",
    "sg:classifiers":[
        {
            "category":"Real Estate",
            "subcategory":"Real Estate Agent",
            "type":"Services"
        }
    ],
    "sg:phone":"+1 803 732 0868",
    "sg:postcode":"29212",
    "sg:province":"SC",
    "wof:name":"Lajack Realty",
    "wof:placetype":"venue"
},
  "geometry": {"coordinates":[-81.14018,34.105131],"type":"Point"}
}