{
  "type": "Feature",
  "properties": {
    "iso:country":"US",
    "sg:address":"167 Hurricane Rd",
    "sg:city":"Anderson",
    "sg:classifiers":[
        {
            "category":"Home & Garden",
            "subcategory":"Carpets & Floor Coverings",
            "type":"Retail Goods"
        }
    ],
    "sg:phone":"+1 864 261 7072",
    "sg:postcode":"29621",
    "sg:province":"SC",
    "sg:tags":[
        "dealer",
        "rug"
    ],
    "wof:name":"Anderson Custom Floors",
    "wof:placetype":"venue"
},
  "geometry": {"coordinates":[-82.701357,34.573027],"type":"Point"}
}