{
  "type": "Feature",
  "properties": {
    "addr:full":"255 King St Charleston SC 29401",
    "addr:housenumber":"255",
    "addr:postcode":"29401",
    "addr:street":"King St",
    "iso:country":"US",
    "sg:address":"255 King St",
    "sg:city":"Charleston",
    "sg:classifiers":[
        {
            "category":"Manufacturing",
            "subcategory":"Printing",
            "type":"Manufacturing & Wholesale Goods"
        }
    ],
    "sg:phone":"+1 843 723 8070",
    "sg:postcode":"29401",
    "sg:province":"SC",
    "sg:tags":[
        "publisher",
        "guide",
        "publishing"
    ],
    "sg:website":"www.charlestongateway.com",
    "wof:name":"Gateway Publications Inc",
    "wof:placetype":"venue"
},
  "geometry": {"coordinates":[-79.93402,32.78226],"type":"Point"}
}