{
  "type": "Feature",
  "properties": {
    "addr:full":"507 Walnut St Camden SC 29020",
    "addr:housenumber":"507",
    "addr:postcode":"29020",
    "addr:street":"Walnut St",
    "iso:country":"US",
    "sg:address":"507 Walnut St",
    "sg:city":"Camden",
    "sg:classifiers":[
        {
            "category":"Health Services",
            "subcategory":"Doctor",
            "type":"Services"
        }
    ],
    "sg:phone":"+1 803 432 9300",
    "sg:postcode":"29020",
    "sg:province":"SC",
    "sg:tags":[
        "physician",
        "surgeon"
    ],
    "wof:name":"Camden Orthopaedic Assoc",
    "wof:placetype":"venue"
},
  "geometry": {"coordinates":[-80.606196,34.248732],"type":"Point"}
}