{
  "type": "Feature",
  "properties": {
    "iso:country":"US",
    "sg:address":"5495 Sunset Blvd",
    "sg:city":"Lexington",
    "sg:classifiers":[
        {
            "category":"Home & Garden",
            "subcategory":"Furniture",
            "type":"Retail Goods"
        }
    ],
    "sg:phone":"+1 803 358 0836",
    "sg:postcode":"29072",
    "sg:province":"SC",
    "sg:tags":[
        "mattress"
    ],
    "wof:name":"Mattress Max",
    "wof:placetype":"venue"
},
  "geometry": {"coordinates":[-81.21911,33.998094],"type":"Point"}
}