{
  "type": "Feature",
  "properties": {
    "iso:country":"US",
    "sg:address":"1816 Jefferson Davis Hwy",
    "sg:city":"Camden",
    "sg:classifiers":[
        {
            "category":"Food & Beverages",
            "subcategory":"Groceries & Convenience Stores",
            "type":"Retail Goods"
        }
    ],
    "sg:phone":"+1 803 432 2571",
    "sg:postcode":"29020",
    "sg:province":"SC",
    "sg:tags":[
        "grocer"
    ],
    "wof:name":"Camden IGA Food Store",
    "wof:placetype":"venue"
},
  "geometry": {"coordinates":[-80.56883,34.26589],"type":"Point"}
}