{
  "type": "Feature",
  "properties": {
    "iso:country":"US",
    "sg:address":"816 Johnnie Dodds Blvd",
    "sg:city":"Mount Pleasant",
    "sg:classifiers":[
        {
            "category":"Bars & Pubs",
            "type":"Food & Drink"
        }
    ],
    "sg:phone":"+1 843 216 1442",
    "sg:postcode":"29464",
    "sg:province":"SC",
    "sg:tags":[
        "bar"
    ],
    "wof:name":"Charlestons Original Spt Bar",
    "wof:placetype":"venue"
},
  "geometry": {"coordinates":[-79.870741,32.81038],"type":"Point"}
}