{
  "type": "Feature",
  "properties": {
    "addr:full":"227 Edwin Rd Lane SC 29564",
    "addr:housenumber":"227",
    "addr:postcode":"29564",
    "addr:street":"Edwin Rd Lane",
    "iso:country":"US",
    "sg:address":"227 Edwin Rd",
    "sg:city":"Lane",
    "sg:classifiers":[
        {
            "category":"Manufacturing",
            "subcategory":"Apparel",
            "type":"Manufacturing & Wholesale Goods"
        }
    ],
    "sg:phone":"+1 843 387 6992",
    "sg:postcode":"29564",
    "sg:province":"SC",
    "sg:tags":[
        "flag",
        "banner"
    ],
    "sg:website":"www.valleyforgeflag.com",
    "wof:name":"Lane Manufacturing",
    "wof:placetype":"venue"
},
  "geometry": {"coordinates":[-79.888502,33.538726],"type":"Point"}
}