{
  "type": "Feature",
  "properties": {
    "addr:full":"1208 W Evans St Florence SC 29501",
    "addr:housenumber":"1208",
    "addr:postcode":"29501",
    "addr:street":"W Evans St",
    "iso:country":"US",
    "sg:address":"1208 W Evans St",
    "sg:city":"Florence",
    "sg:classifiers":[
        {
            "category":"Wholesale",
            "subcategory":"Machinery & Supplies",
            "type":"Manufacturing & Wholesale Goods"
        },
        {
            "category":"Manufacturing",
            "subcategory":"Retail Goods",
            "type":"Manufacturing & Wholesale Goods"
        }
    ],
    "sg:phone":"+1 843 661 6300",
    "sg:postcode":"29501",
    "sg:province":"SC",
    "sg:tags":[
        "salon",
        "beauty"
    ],
    "wof:name":"Palmetto Beauty Supply Inc",
    "wof:placetype":"venue"
},
  "geometry": {"coordinates":[-79.789117,34.196101],"type":"Point"}
}