{
  "type": "Feature",
  "properties": {
    "iso:country":"US",
    "sg:address":"2602 Delhi Rd",
    "sg:city":"Charleston",
    "sg:classifiers":[
        {
            "category":"Autos & Motor Vehicles",
            "subcategory":"Fuel & Gas Station",
            "type":"Retail Goods"
        }
    ],
    "sg:phone":"+1 843 824 5856",
    "sg:postcode":"29406",
    "sg:province":"SC",
    "sg:tags":[
        "station",
        "gasoline"
    ],
    "wof:name":"Aviation & Rivers Amoco",
    "wof:placetype":"venue"
},
  "geometry": {"coordinates":[-80.057134,32.955714],"type":"Point"}
}