{
  "type": "Feature",
  "properties": {
    "iso:country":"US",
    "sg:address":"711 Hillbrook Cir",
    "sg:city":"Pacolet",
    "sg:classifiers":[
        {
            "category":"Building & Trades",
            "subcategory":"Electrical",
            "type":"Services"
        }
    ],
    "sg:phone":"+1 864 474 2944",
    "sg:postcode":"29372",
    "sg:province":"SC",
    "sg:tags":[
        "electrical",
        "contractor"
    ],
    "wof:name":"Night Guard Associates",
    "wof:placetype":"venue"
},
  "geometry": {"coordinates":[-81.767393,34.88827],"type":"Point"}
}