{
  "type": "Feature",
  "properties": {
    "iso:country":"US",
    "sg:address":"162 S Potter Rd",
    "sg:city":"Lancaster",
    "sg:classifiers":[
        {
            "category":"Autos & Motor Vehicles",
            "subcategory":"Automobile Sales",
            "type":"Retail Goods"
        }
    ],
    "sg:phone":"+1 803 283 2758",
    "sg:postcode":"29720",
    "sg:province":"SC",
    "sg:tags":[
        "used"
    ],
    "wof:name":"S & G Motors LLC",
    "wof:placetype":"venue"
},
  "geometry": {"coordinates":[-80.695544,34.737046],"type":"Point"}
}