{
  "type": "Feature",
  "properties": {
    "iso:country":"US",
    "sg:address":"2440 Meeting Street Rd",
    "sg:city":"North Charleston",
    "sg:classifiers":[
        {
            "category":"Home & Garden",
            "subcategory":"Building Materials",
            "type":"Retail Goods"
        }
    ],
    "sg:phone":"+1 843 744 2575",
    "sg:postcode":"29405",
    "sg:province":"SC",
    "sg:tags":[
        "other",
        "lumber"
    ],
    "wof:name":"Carolina Bldg Mtls & Salv Co",
    "wof:placetype":"venue"
},
  "geometry": {"coordinates":[-79.96216200000001,32.839537],"type":"Point"}
}