{
  "type": "Feature",
  "properties": {
    "addr:full":"112 Halter Dr Piedmont SC 29673",
    "addr:housenumber":"112",
    "addr:postcode":"29673",
    "addr:street":"Halter Dr",
    "iso:country":"US",
    "sg:address":"112 Halter Dr",
    "sg:city":"Piedmont",
    "sg:classifiers":[
        {
            "category":"Personal",
            "subcategory":"Beauty Salon",
            "type":"Services"
        }
    ],
    "sg:phone":"+1 864 269 5739",
    "sg:postcode":"29673",
    "sg:province":"SC",
    "wof:name":"Hans J Salon",
    "wof:placetype":"venue"
},
  "geometry": {"coordinates":[-82.47548,34.783189],"type":"Point"}
}