{
  "type": "Feature",
  "properties": {
    "iso:country":"US",
    "sg:address":"1021 Maxwell Mill Rd",
    "sg:city":"Fort Mill",
    "sg:classifiers":[
        {
            "category":"Social Services",
            "type":"Services"
        }
    ],
    "sg:phone":"+1 803 548 4673",
    "sg:postcode":"29708",
    "sg:province":"SC",
    "sg:tags":[
        "counselor",
        "marriage",
        "family"
    ],
    "wof:name":"Hope Counseling",
    "wof:placetype":"venue"
},
  "geometry": {"coordinates":[-80.95697699999999,35.075618],"type":"Point"}
}