{
  "type": "Feature",
  "properties": {
    "iso:country":"US",
    "sg:address":"370 Flatwood Rd",
    "sg:city":"Spartanburg",
    "sg:classifiers":[
        {
            "category":"Farming",
            "subcategory":"Berry Farm",
            "type":"Manufacturing & Wholesale Goods"
        }
    ],
    "sg:phone":"+1 864 578 3788",
    "sg:postcode":"29303",
    "sg:province":"SC",
    "sg:tags":[
        "crop"
    ],
    "wof:name":"Ken Seay",
    "wof:placetype":"venue"
},
  "geometry": {"coordinates":[-81.902638,35.033881],"type":"Point"}
}