{
  "type": "Feature",
  "properties": {
    "iso:country":"US",
    "sg:address":"325 Harrison Bridge Rd",
    "sg:city":"Simpsonville",
    "sg:classifiers":[
        {
            "category":"Restaurant",
            "type":"Food & Drink"
        }
    ],
    "sg:menulink":"http://www.allmenus.com/sc/simpsonville/228896-jersey-mikes/menu/",
    "sg:phone":"+1 864 963 2400",
    "sg:postcode":"29680",
    "sg:province":"SC",
    "sg:tags":[
        "american",
        "sandwich"
    ],
    "wof:name":"Jersey Mike's",
    "wof:placetype":"venue"
},
  "geometry": {"coordinates":[-82.24426699999999,34.704601],"type":"Point"}
}