{
  "type": "Feature",
  "properties": {
    "iso:country":"US",
    "sg:address":"20 Trafalgar Ct",
    "sg:city":"Columbia",
    "sg:classifiers":[
        {
            "category":"Professional",
            "type":"Services"
        }
    ],
    "sg:phone":"+1 803 776 6877",
    "sg:postcode":"29209",
    "sg:province":"SC",
    "sg:tags":[
        "establishment"
    ],
    "wof:name":"Sea Master Primetimers",
    "wof:placetype":"venue"
},
  "geometry": {"coordinates":[-80.972363,33.970122],"type":"Point"}
}