{
  "type": "Feature",
  "properties": {
    "addr:full":"316 N Main St Bishopville SC 29010",
    "addr:housenumber":"316",
    "addr:postcode":"29010",
    "addr:street":"N Main St",
    "iso:country":"US",
    "sg:address":"316 N Main St",
    "sg:city":"Bishopville",
    "sg:classifiers":[
        {
            "category":"Retail",
            "subcategory":"Auto Repair",
            "type":"Services"
        }
    ],
    "sg:phone":"+1 803 484 6312",
    "sg:postcode":"29010",
    "sg:province":"SC",
    "sg:tags":[
        "repairing",
        "automobile"
    ],
    "wof:name":"Stoudenmire Inc",
    "wof:placetype":"venue"
},
  "geometry": {"coordinates":[-80.24481,34.220922],"type":"Point"}
}