{
  "type": "Feature",
  "properties": {
    "iso:country":"US",
    "sg:address":"4340 Alligator Rd",
    "sg:city":"Timmonsville",
    "sg:classifiers":[
        {
            "category":"Professional",
            "subcategory":"Engineering",
            "type":"Services"
        }
    ],
    "sg:phone":"+1 843 346 5800",
    "sg:postcode":"29161",
    "sg:province":"SC",
    "sg:tags":[
        "engineer"
    ],
    "wof:name":"Robert L Weaver Engineering",
    "wof:placetype":"venue"
},
  "geometry": {"coordinates":[-79.893873,34.148178],"type":"Point"}
}