{
  "type": "Feature",
  "properties": {
    "iso:country":"US",
    "sg:address":"2380 US Hwy 501 W",
    "sg:city":"Conway",
    "sg:classifiers":[
        {
            "category":"Wholesale",
            "subcategory":"Vending Machines",
            "type":"Manufacturing & Wholesale Goods"
        }
    ],
    "sg:phone":"+1 843 365 1603",
    "sg:postcode":"29526",
    "sg:province":"SC",
    "wof:name":"Total Vending",
    "wof:placetype":"venue"
},
  "geometry": {"coordinates":[-79.079471,33.854625],"type":"Point"}
}