{
  "type": "Feature",
  "properties": {
    "addr:full":"116 E Main St Lake City SC 29560",
    "addr:housenumber":"116",
    "addr:postcode":"29560",
    "addr:street":"E Main St",
    "iso:country":"US",
    "sg:address":"116 E Main St",
    "sg:city":"Lake City",
    "sg:classifiers":[
        {
            "category":"Shopping",
            "subcategory":"Florist",
            "type":"Retail Goods"
        }
    ],
    "sg:phone":"+1 843 374 5510",
    "sg:postcode":"29560",
    "sg:province":"SC",
    "wof:name":"Petals & Bows",
    "wof:placetype":"venue"
},
  "geometry": {"coordinates":[-79.75442099999999,33.872749],"type":"Point"}
}