{
  "type": "Feature",
  "properties": {
    "addr:full":"4023 Byrnes Dr St Stephen SC 29479",
    "addr:housenumber":"4023",
    "addr:postcode":"29479",
    "addr:street":"Byrnes Dr",
    "iso:country":"US",
    "sg:address":"4023 Byrnes Dr",
    "sg:city":"St Stephen",
    "sg:classifiers":[
        {
            "category":"Shopping",
            "subcategory":"Music",
            "type":"Retail Goods"
        }
    ],
    "sg:phone":"+1 843 567 2935",
    "sg:postcode":"29479",
    "sg:province":"SC",
    "sg:tags":[
        "video",
        "disc",
        "tape",
        "cassette"
    ],
    "wof:name":"Judy's Video Inc",
    "wof:placetype":"venue"
},
  "geometry": {"coordinates":[-79.93071999999999,33.409485],"type":"Point"}
}