{
  "type": "Feature",
  "properties": {
    "addr:full":"13016 W Oak Hwy Townville SC 29689",
    "addr:housenumber":"13016",
    "addr:postcode":"29689",
    "addr:street":"W Oak Hwy",
    "iso:country":"US",
    "sg:address":"13016 W Oak Hwy",
    "sg:city":"Townville",
    "sg:classifiers":[
        {
            "category":"Autos & Motor Vehicles",
            "subcategory":"Automobile Sales",
            "type":"Retail Goods"
        }
    ],
    "sg:phone":"+1 864 972 0046",
    "sg:postcode":"29689",
    "sg:province":"SC",
    "sg:tags":[
        "car",
        "dealer"
    ],
    "wof:name":"A J's Auto Sales",
    "wof:placetype":"venue"
},
  "geometry": {"coordinates":[-82.90940999999999,34.572362],"type":"Point"}
}