{
  "type": "Feature",
  "properties": {
    "iso:country":"US",
    "sg:address":"549 New Market St",
    "sg:city":"Greenwood",
    "sg:classifiers":[
        {
            "category":"Organizations",
            "subcategory":"Religious Organization",
            "type":"Services"
        }
    ],
    "sg:phone":"+1 864 227 9190",
    "sg:postcode":"29646",
    "sg:province":"SC",
    "sg:tags":[
        "church"
    ],
    "wof:name":"New Beginning Deliverance",
    "wof:placetype":"venue"
},
  "geometry": {"coordinates":[-82.145984,34.185375],"type":"Point"}
}