{
  "type": "Feature",
  "properties": {
    "addr:full":"6826 Johnston Ave Reevesville SC 29471",
    "addr:housenumber":"6826",
    "addr:postcode":"29471",
    "addr:street":"Johnston Ave",
    "iso:country":"US",
    "sg:address":"6826 Johnston Ave",
    "sg:city":"Reevesville",
    "sg:classifiers":[
        {
            "category":"Shopping",
            "subcategory":"Florist",
            "type":"Retail Goods"
        }
    ],
    "sg:phone":"+1 843 563 3009",
    "sg:postcode":"29471",
    "sg:province":"SC",
    "sg:tags":[
        "plant"
    ],
    "wof:name":"Bub's Flower Shed",
    "wof:placetype":"venue"
},
  "geometry": {"coordinates":[-80.651302,33.208467],"type":"Point"}
}