{
  "type": "Feature",
  "properties": {
    "iso:country":"US",
    "sg:address":"503 S Duncan Byp",
    "sg:city":"Union",
    "sg:classifiers":[
        {
            "category":"Retail",
            "subcategory":"Animal Services",
            "type":"Services"
        }
    ],
    "sg:phone":"+1 864 427 4228",
    "sg:postcode":"29379",
    "sg:province":"SC",
    "wof:name":"Coats & Tails Dog Grooming",
    "wof:placetype":"venue"
},
  "geometry": {"coordinates":[-81.632707,34.704587],"type":"Point"}
}