{
  "type": "Feature",
  "properties": {
    "addr:full":"419 Rudy Rd Manning SC 29102",
    "addr:housenumber":"419",
    "addr:postcode":"29102",
    "addr:street":"Rudy Rd",
    "iso:country":"US",
    "sg:address":"419 Rudy Rd",
    "sg:city":"Manning",
    "sg:classifiers":[
        {
            "category":"Insurance",
            "subcategory":"Insurance Agent",
            "type":"Services"
        }
    ],
    "sg:phone":"+1 803 435 9080",
    "sg:postcode":"29102",
    "sg:province":"SC",
    "wof:name":"Woodmen Of World",
    "wof:placetype":"venue"
},
  "geometry": {"coordinates":[-80.22227700000001,33.686105],"type":"Point"}
}