{
  "type": "Feature",
  "properties": {
    "addr:full":"113 Moorcroft Way Greer SC 29650",
    "addr:housenumber":"113",
    "addr:postcode":"29650",
    "addr:street":"Moorcroft Way",
    "iso:country":"US",
    "sg:address":"113 Moorcroft Way",
    "sg:city":"Greer",
    "sg:classifiers":[
        {
            "category":"Health Services",
            "subcategory":"Doctor",
            "type":"Services"
        }
    ],
    "sg:phone":"+1 864 268 3509",
    "sg:postcode":"29650",
    "sg:province":"SC",
    "sg:tags":[
        "physician",
        "surgeon"
    ],
    "wof:name":"Vashi Sunit",
    "wof:placetype":"venue"
},
  "geometry": {"coordinates":[-82.285675,34.887463],"type":"Point"}
}