{
  "type": "Feature",
  "properties": {
    "addr:full":"1248 Windfall Farm Ln Hartsville SC 29550",
    "addr:housenumber":"1248",
    "addr:postcode":"29550",
    "addr:street":"Windfall Farm Ln",
    "iso:country":"US",
    "sg:address":"1248 Windfall Farm Ln",
    "sg:city":"Hartsville",
    "sg:classifiers":[
        {
            "category":"Travel",
            "subcategory":"Hotels & Motels",
            "type":"Entertainment"
        }
    ],
    "sg:phone":"+1 843 383 6677",
    "sg:postcode":"29550",
    "sg:province":"SC",
    "sg:tags":[
        "breakfast",
        "accommodation",
        "bed"
    ],
    "wof:name":"Nealcrest Farm Bed & Breakfast",
    "wof:placetype":"venue"
},
  "geometry": {"coordinates":[-80.033956,34.354489],"type":"Point"}
}