{
  "type": "Feature",
  "properties": {
    "addr:full":"104 Cashua Ferry Rd Darlington SC 29532",
    "addr:housenumber":"104",
    "addr:postcode":"29532",
    "addr:street":"Cashua Ferry Rd",
    "iso:country":"US",
    "sg:address":"104 Cashua Ferry Rd",
    "sg:city":"Darlington",
    "sg:classifiers":[
        {
            "category":"Food & Beverages",
            "subcategory":"Groceries & Convenience Stores",
            "type":"Retail Goods"
        }
    ],
    "sg:phone":"+1 843 395 1939",
    "sg:postcode":"29532",
    "sg:province":"SC",
    "wof:name":"Markette",
    "wof:placetype":"venue"
},
  "geometry": {"coordinates":[-79.85871,34.312462],"type":"Point"}
}