{
  "type": "Feature",
  "properties": {
    "addr:full":"400 Ridgecrest Dr Clemson SC 29631",
    "addr:housenumber":"400",
    "addr:postcode":"29631",
    "addr:street":"Ridgecrest Dr",
    "iso:country":"US",
    "sg:address":"400 Ridgecrest Dr",
    "sg:city":"Clemson",
    "sg:classifiers":[
        {
            "category":"Banks & Credit Unions",
            "subcategory":"Financial Services",
            "type":"Services"
        }
    ],
    "sg:phone":"+1 864 654 6625",
    "sg:postcode":"29631",
    "sg:province":"SC",
    "sg:tags":[
        "trust",
        "investment",
        "real estate"
    ],
    "wof:name":"Abbey Point Flp",
    "wof:placetype":"venue"
},
  "geometry": {"coordinates":[-82.822788,34.663341],"type":"Point"}
}