{
  "type": "Feature",
  "properties": {
    "addr:full":"113 Old Pros Rd Gaffney SC 29341",
    "addr:housenumber":"113",
    "addr:postcode":"29341",
    "addr:street":"Old Pros Rd",
    "iso:country":"US",
    "sg:address":"113 Old Pros Rd",
    "sg:city":"Gaffney",
    "sg:classifiers":[
        {
            "category":"Building & Trades",
            "subcategory":"Construction",
            "type":"Services"
        }
    ],
    "sg:phone":"+1 864 489 7966",
    "sg:postcode":"29341",
    "sg:province":"SC",
    "sg:tags":[
        "house"
    ],
    "wof:name":"Andy Wallace Remodeling",
    "wof:placetype":"venue"
},
  "geometry": {"coordinates":[-81.693331,35.133227],"type":"Point"}
}