{
  "type": "Feature",
  "properties": {
    "iso:country":"US",
    "sg:address":"5522 Charter Oaks Ln",
    "sg:city":"York",
    "sg:classifiers":[
        {
            "category":"Retail",
            "subcategory":"Animal Services",
            "type":"Services"
        }
    ],
    "sg:phone":"+1 803 831 6587",
    "sg:postcode":"29745",
    "sg:province":"SC",
    "sg:tags":[
        "breeder",
        "cat"
    ],
    "wof:name":"Gentile Giant",
    "wof:placetype":"venue"
},
  "geometry": {"coordinates":[-81.11174,35.081942],"type":"Point"}
}