{
  "type": "Feature",
  "properties": {
    "addr:full":"204 Lenwood Dr Summerville SC 29485",
    "addr:housenumber":"204",
    "addr:postcode":"29485",
    "addr:street":"Lenwood Dr",
    "iso:country":"US",
    "sg:address":"204 Lenwood Dr",
    "sg:city":"Summerville",
    "sg:classifiers":[
        {
            "category":"Shopping",
            "subcategory":"Jewelry",
            "type":"Retail Goods"
        }
    ],
    "sg:phone":"+1 843 821 7835",
    "sg:postcode":"29485",
    "sg:province":"SC",
    "sg:tags":[
        "mill",
        "knit",
        "outerwear"
    ],
    "wof:name":"Nine By Thirteen",
    "wof:placetype":"venue"
},
  "geometry": {"coordinates":[-80.177537,32.999171],"type":"Point"}
}