{
  "type": "Feature",
  "properties": {
    "addr:full":"1007 Tiger Blvd Clemson SC 29631",
    "addr:housenumber":"1007",
    "addr:postcode":"29631",
    "addr:street":"Tiger Blvd",
    "iso:country":"US",
    "sg:address":"1007 Tiger Blvd",
    "sg:city":"Clemson",
    "sg:classifiers":[
        {
            "category":"Building & Trades",
            "subcategory":"Construction",
            "type":"Services"
        }
    ],
    "sg:phone":"+1 864 654 0344",
    "sg:postcode":"29631",
    "sg:province":"SC",
    "sg:tags":[
        "tile",
        "dealer"
    ],
    "wof:name":"Tile Council Of America",
    "wof:placetype":"venue"
},
  "geometry": {"coordinates":[-82.844435,34.692503],"type":"Point"}
}