{
  "type": "Feature",
  "properties": {
    "addr:full":"608 William Hilton Pkwy Hilton Head Isle SC 29928",
    "addr:housenumber":"608",
    "addr:postcode":"29928",
    "addr:street":"William Hilton Pkwy",
    "iso:country":"US",
    "sg:address":"608 William Hilton Pkwy",
    "sg:city":"Hilton Head Isle",
    "sg:classifiers":[
        {
            "category":"Home & Garden",
            "subcategory":"Building Materials",
            "type":"Retail Goods"
        }
    ],
    "sg:phone":"+1 843 842 7600",
    "sg:postcode":"29928",
    "sg:province":"SC",
    "sg:tags":[
        "paint"
    ],
    "wof:name":"Sherwin-Williams Paints",
    "wof:placetype":"venue"
},
  "geometry": {"coordinates":[-80.701965,32.196925],"type":"Point"}
}