{
  "type": "Feature",
  "properties": {
    "iso:country":"US",
    "sg:address":"975 Bacons Bridge Rd",
    "sg:city":"Summerville",
    "sg:classifiers":[
        {
            "category":"Banks & Credit Unions",
            "subcategory":"Bank",
            "type":"Services"
        }
    ],
    "sg:phone":"+1 843 871 2382",
    "sg:postcode":"29485",
    "sg:province":"SC",
    "wof:name":"First Federal Of Charleston",
    "wof:placetype":"venue"
},
  "geometry": {"coordinates":[-80.20215,32.965087],"type":"Point"}
}