{
  "type": "Feature",
  "properties": {
    "addr:full":"4103 Dorchester Rd Charleston SC 29405",
    "addr:housenumber":"4103",
    "addr:postcode":"29405",
    "addr:street":"Dorchester Rd",
    "iso:country":"US",
    "sg:address":"4103 Dorchester Rd",
    "sg:city":"Charleston",
    "sg:classifiers":[
        {
            "category":"Shopping",
            "subcategory":"Discount & Variety Stores",
            "type":"Retail Goods"
        }
    ],
    "sg:phone":"+1 843 744 4442",
    "sg:postcode":"29405",
    "sg:province":"SC",
    "sg:tags":[
        "merchandise",
        "general"
    ],
    "wof:name":"Horizon Forest Products",
    "wof:placetype":"venue"
},
  "geometry": {"coordinates":[-80.000269,32.85362],"type":"Point"}
}