{
  "type": "Feature",
  "properties": {
    "iso:country":"US",
    "sg:address":"1410 Colonial Life Blvd W Ste 200",
    "sg:city":"Columbia",
    "sg:classifiers":[
        {
            "category":"Shopping",
            "subcategory":"Tobacco",
            "type":"Retail Goods"
        }
    ],
    "sg:phone":"+1 803 772 2217",
    "sg:postcode":"29210",
    "sg:province":"SC",
    "sg:tags":[
        "shop"
    ],
    "sg:website":"www.modernagetobacco.com",
    "wof:name":"Modern Age Tobacco and Gift",
    "wof:placetype":"venue"
},
  "geometry": {"coordinates":[-81.093017,34.027559],"type":"Point"}
}