{
  "type": "Feature",
  "properties": {
    "iso:country":"US",
    "sg:address":"8011 Greenville Hwy",
    "sg:city":"Spartanburg",
    "sg:classifiers":[
        {
            "category":"Wholesale",
            "subcategory":"Machinery & Supplies",
            "type":"Manufacturing & Wholesale Goods"
        }
    ],
    "sg:phone":"+1 864 587 1118",
    "sg:postcode":"29301",
    "sg:province":"SC",
    "sg:tags":[
        "salon",
        "beauty"
    ],
    "wof:name":"Davidson Beauty Systems",
    "wof:placetype":"venue"
},
  "geometry": {"coordinates":[-82.003893,34.935375],"type":"Point"}
}