{
  "type": "Feature",
  "properties": {
    "iso:country":"US",
    "sg:address":"1 Smallwood Cir",
    "sg:city":"Columbia",
    "sg:classifiers":[
        {
            "category":"Real Estate",
            "subcategory":"Real Estate Agent",
            "type":"Services"
        }
    ],
    "sg:phone":"+1 803 419 3511",
    "sg:postcode":"29223",
    "sg:province":"SC",
    "wof:name":"Signature Realty",
    "wof:placetype":"venue"
},
  "geometry": {"coordinates":[-80.88417200000001,34.090225],"type":"Point"}
}