{
  "type": "Feature",
  "properties": {
    "addr:full":"6 S Congress St York SC 29745",
    "addr:housenumber":"6",
    "addr:postcode":"29745",
    "addr:street":"S Congress St",
    "iso:country":"US",
    "sg:address":"6 S Congress St",
    "sg:city":"York",
    "sg:classifiers":[
        {
            "category":"Government",
            "subcategory":"Office",
            "type":"Public Place"
        }
    ],
    "sg:phone":"+1 803 684 8544",
    "sg:postcode":"29745",
    "sg:province":"SC",
    "wof:name":"York County Public Information",
    "wof:placetype":"venue"
},
  "geometry": {"coordinates":[-81.241997,34.993981],"type":"Point"}
}