{
  "type": "Feature",
  "properties": {
    "iso:country":"US",
    "sg:address":"3277 Clover Hill Rd",
    "sg:city":"Green Pond",
    "sg:classifiers":[
        {
            "category":"Social Services",
            "type":"Services"
        }
    ],
    "sg:phone":"+1 843 549 0516",
    "sg:postcode":"29446",
    "sg:province":"SC",
    "sg:tags":[
        "organization",
        "welfare"
    ],
    "wof:name":"Mothers Against Drunk Driving",
    "wof:placetype":"venue"
},
  "geometry": {"coordinates":[-80.587183,32.757559],"type":"Point"}
}