{
  "type": "Feature",
  "properties": {
    "iso:country":"US",
    "sg:address":"637 Congaree Rd",
    "sg:city":"Greenville",
    "sg:classifiers":[
        {
            "category":"Real Estate",
            "subcategory":"Real Estate Agent",
            "type":"Services"
        }
    ],
    "sg:phone":"+1 864 254 0000",
    "sg:postcode":"29607",
    "sg:province":"SC",
    "wof:name":"Greenville East Inc",
    "wof:placetype":"venue"
},
  "geometry": {"coordinates":[-82.32498,34.846238],"type":"Point"}
}