{
  "type": "Feature",
  "properties": {
    "iso:country":"US",
    "sg:address":"166 Parrott Dr",
    "sg:city":"Six Mile",
    "sg:classifiers":[
        {
            "category":"Home & Garden",
            "subcategory":"Hardware",
            "type":"Retail Goods"
        }
    ],
    "sg:phone":"+1 864 868 5753",
    "sg:postcode":"29682",
    "sg:province":"SC",
    "wof:name":"Tc Enterprises",
    "wof:placetype":"venue"
},
  "geometry": {"coordinates":[-82.799594,34.814693],"type":"Point"}
}