{
  "type": "Feature",
  "properties": {
    "addr:full":"307 Timbergate Ct Lexington SC 29073",
    "addr:housenumber":"307",
    "addr:postcode":"29073",
    "addr:street":"Timbergate Ct",
    "iso:country":"US",
    "sg:address":"307 Timbergate Ct",
    "sg:city":"Lexington",
    "sg:classifiers":[
        {
            "category":"Professional",
            "type":"Services"
        }
    ],
    "sg:phone":"+1 803 808 1950",
    "sg:postcode":"29073",
    "sg:province":"SC",
    "sg:tags":[
        "establishment"
    ],
    "wof:name":"AAA Sales & Engineering",
    "wof:placetype":"venue"
},
  "geometry": {"coordinates":[-81.171785,33.992567],"type":"Point"}
}