{
  "type": "Feature",
  "properties": {
    "iso:country":"US",
    "sg:address":"320 N Main St",
    "sg:city":"Saluda",
    "sg:classifiers":[
        {
            "category":"Food & Beverages",
            "subcategory":"Groceries & Convenience Stores",
            "type":"Retail Goods"
        }
    ],
    "sg:phone":"+1 864 445 2510",
    "sg:postcode":"29138",
    "sg:province":"SC",
    "wof:name":"Stop 'N' Shop",
    "wof:placetype":"venue"
},
  "geometry": {"coordinates":[-81.77198799999999,34.008702],"type":"Point"}
}