{
  "type": "Feature",
  "properties": {
    "iso:country":"US",
    "sg:address":"126 E Main St",
    "sg:city":"Lexington",
    "sg:classifiers":[
        {
            "category":"Banks & Credit Unions",
            "subcategory":"Bank",
            "type":"Services"
        }
    ],
    "sg:phone":"+1 803 359 1725",
    "sg:postcode":"29072",
    "sg:province":"SC",
    "sg:website":"www.bbandt.com",
    "wof:name":"B B & T",
    "wof:placetype":"venue"
},
  "geometry": {"coordinates":[-81.237156,33.981933],"type":"Point"}
}