{
  "type": "Feature",
  "properties": {
    "addr:full":"1297 Professional Dr Myrtle Beach SC 29577",
    "addr:housenumber":"1297",
    "addr:postcode":"29577",
    "addr:street":"Professional Dr",
    "iso:country":"US",
    "sg:address":"1297 Professional Dr",
    "sg:city":"Myrtle Beach",
    "sg:classifiers":[
        {
            "category":"Real Estate",
            "subcategory":"Real Estate Agent",
            "type":"Services"
        }
    ],
    "sg:phone":"+1 843 839 2700",
    "sg:postcode":"29577",
    "sg:province":"SC",
    "sg:tags":[
        "appraiser"
    ],
    "sg:website":"www.cox-beall.com",
    "wof:name":"Cox Beall & Assoc",
    "wof:placetype":"venue"
},
  "geometry": {"coordinates":[-78.858771,33.731944],"type":"Point"}
}