{
  "type": "Feature",
  "properties": {
    "addr:full":"1227 Kingswood Dr Conway SC 29526",
    "addr:housenumber":"1227",
    "addr:postcode":"29526",
    "addr:street":"Kingswood Dr",
    "iso:country":"US",
    "sg:address":"1227 Kingswood Dr",
    "sg:city":"Conway",
    "sg:classifiers":[
        {
            "category":"Real Estate",
            "subcategory":"Real Estate Agent",
            "type":"Services"
        }
    ],
    "sg:phone":"+1 843 347 7351",
    "sg:postcode":"29526",
    "sg:province":"SC",
    "wof:name":"Valerino's Satisfied Property",
    "wof:placetype":"venue"
},
  "geometry": {"coordinates":[-79.01449,33.751551],"type":"Point"}
}