{
  "type": "Feature",
  "properties": {
    "iso:country":"US",
    "sg:address":"2111 Red Bank Rd",
    "sg:city":"Goose Creek",
    "sg:classifiers":[
        {
            "category":"Professional",
            "type":"Services"
        }
    ],
    "sg:phone":"+1 843 863 0660",
    "sg:postcode":"29445",
    "sg:province":"SC",
    "sg:tags":[
        "establishment"
    ],
    "wof:name":"South Atlantic Co",
    "wof:placetype":"venue"
},
  "geometry": {"coordinates":[-79.952625,32.961188],"type":"Point"}
}