{
  "type": "Feature",
  "properties": {
    "iso:country":"US",
    "sg:address":"4 Woodland Ln",
    "sg:city":"Greenville",
    "sg:classifiers":[
        {
            "category":"Professional",
            "subcategory":"Computer Services",
            "type":"Services"
        }
    ],
    "sg:phone":"+1 864 292 5888",
    "sg:postcode":"29615",
    "sg:province":"SC",
    "sg:tags":[
        "consultant",
        "designer"
    ],
    "wof:name":"D V Brown Co",
    "wof:placetype":"venue"
},
  "geometry": {"coordinates":[-82.34856499999999,34.891713],"type":"Point"}
}