{
  "type": "Feature",
  "properties": {
    "iso:country":"US",
    "sg:address":"335 Pelion Rd",
    "sg:city":"Pelion",
    "sg:classifiers":[
        {
            "category":"Retail",
            "subcategory":"Portrait Studio",
            "type":"Services"
        }
    ],
    "sg:phone":"+1 803 894 5852",
    "sg:postcode":"29123",
    "sg:province":"SC",
    "sg:tags":[
        "photographer"
    ],
    "wof:name":"Photographs & Memories",
    "wof:placetype":"venue"
},
  "geometry": {"coordinates":[-81.231888,33.773485],"type":"Point"}
}