{
  "type": "Feature",
  "properties": {
    "iso:country":"US",
    "sg:address":"124 W Poinsett St",
    "sg:city":"Greer",
    "sg:classifiers":[
        {
            "category":"Professional",
            "type":"Services"
        }
    ],
    "sg:phone":"+1 864 879 4312",
    "sg:postcode":"29650",
    "sg:province":"SC",
    "sg:tags":[
        "establishment"
    ],
    "wof:name":"Bst Amatpts",
    "wof:placetype":"venue"
},
  "geometry": {"coordinates":[-82.227411,34.938908],"type":"Point"}
}