{
  "type": "Feature",
  "properties": {
    "iso:country":"US",
    "sg:address":"6005 Wade Hampton Blvd",
    "sg:city":"Taylors",
    "sg:classifiers":[
        {
            "category":"Restaurant",
            "type":"Food & Drink"
        }
    ],
    "sg:menulink":"http://www.allmenus.com/sc/taylors/235126-roly-poly-sandwiches/menu/",
    "sg:phone":"+1 864 877 0550",
    "sg:postcode":"29687",
    "sg:province":"SC",
    "sg:tags":[
        "wrap",
        "american",
        "sandwich"
    ],
    "wof:name":"Roly Poly Sandwiches",
    "wof:placetype":"venue"
},
  "geometry": {"coordinates":[-82.27546599999999,34.936328],"type":"Point"}
}