{
  "type": "Feature",
  "properties": {
    "iso:country":"US",
    "sg:address":"1057 Broughton St",
    "sg:city":"Orangeburg",
    "sg:classifiers":[
        {
            "category":"Home & Garden",
            "subcategory":"Furniture",
            "type":"Retail Goods"
        }
    ],
    "sg:phone":"+1 803 536 5536",
    "sg:postcode":"29115",
    "sg:province":"SC",
    "wof:name":"Cliches",
    "wof:placetype":"venue"
},
  "geometry": {"coordinates":[-80.86451599999999,33.48789],"type":"Point"}
}