{
  "type": "Feature",
  "properties": {
    "iso:country":"US",
    "sg:address":"137 Broad St",
    "sg:city":"Bennettsville",
    "sg:classifiers":[
        {
            "category":"Shopping",
            "subcategory":"Optical Goods",
            "type":"Retail Goods"
        }
    ],
    "sg:phone":"+1 843 479 7788",
    "sg:postcode":"29512",
    "sg:province":"SC",
    "wof:name":"Cade Vision Ctr",
    "wof:placetype":"venue"
},
  "geometry": {"coordinates":[-79.68363100000001,34.615466],"type":"Point"}
}