{
  "type": "Feature",
  "properties": {
    "iso:country":"US",
    "sg:address":"590 Ecology Rd",
    "sg:city":"Chester",
    "sg:classifiers":[
        {
            "category":"Education",
            "subcategory":"School",
            "type":"Public Place"
        }
    ],
    "sg:phone":"+1 803 581 7016",
    "sg:postcode":"29706",
    "sg:province":"SC",
    "wof:name":"Be&K Superintendent's Office",
    "wof:placetype":"venue"
},
  "geometry": {"coordinates":[-81.13391,34.706432],"type":"Point"}
}