{
  "type": "Feature",
  "properties": {
    "iso:country":"US",
    "sg:address":"710 Dewitt Rd",
    "sg:city":"Lugoff",
    "sg:classifiers":[
        {
            "category":"Health Services",
            "subcategory":"Doctor",
            "type":"Services"
        }
    ],
    "sg:phone":"+1 803 438 0100",
    "sg:postcode":"29078",
    "sg:province":"SC",
    "sg:tags":[
        "clinic"
    ],
    "wof:name":"Carolina Diabetes Clinic",
    "wof:placetype":"venue"
},
  "geometry": {"coordinates":[-80.669815,34.233594],"type":"Point"}
}