{
  "type": "Feature",
  "properties": {
    "iso:country":"US",
    "sg:address":"109 Sweetland Ct",
    "sg:city":"Greenville",
    "sg:classifiers":[
        {
            "category":"Shopping",
            "subcategory":"Computers & Home Electronics",
            "type":"Retail Goods"
        }
    ],
    "sg:phone":"+1 864 676 2060",
    "sg:postcode":"29607",
    "sg:province":"SC",
    "sg:tags":[
        "equipment",
        "satellite",
        "system"
    ],
    "wof:name":"Satellites N More",
    "wof:placetype":"venue"
},
  "geometry": {"coordinates":[-82.305395,34.811036],"type":"Point"}
}