{
  "type": "Feature",
  "properties": {
    "iso:country":"US",
    "sg:address":"3300 Sunset Blvd",
    "sg:city":"West Columbia",
    "sg:classifiers":[
        {
            "category":"Health Services",
            "subcategory":"Nursing And Care Facility",
            "type":"Services"
        }
    ],
    "sg:phone":"+1 803 791 1119",
    "sg:postcode":"29169",
    "sg:province":"SC",
    "sg:tags":[
        "hospice"
    ],
    "wof:name":"Heartland Hospice",
    "wof:placetype":"venue"
},
  "geometry": {"coordinates":[-81.134275,34.008018],"type":"Point"}
}