{
  "type": "Feature",
  "properties": {
    "iso:country":"US",
    "sg:address":"230 Munn Rd E",
    "sg:city":"Fort Mill",
    "sg:classifiers":[
        {
            "category":"Personal",
            "subcategory":"Barber",
            "type":"Services"
        }
    ],
    "sg:phone":"+1 803 547 7444",
    "sg:postcode":"29715",
    "sg:province":"SC",
    "wof:name":"Fort Mill Barber Shop",
    "wof:placetype":"venue"
},
  "geometry": {"coordinates":[-80.965063,35.020341],"type":"Point"}
}