{
  "type": "Feature",
  "properties": {
    "iso:country":"US",
    "sg:address":"5773 Dewsbury Ln",
    "sg:city":"North Charleston",
    "sg:classifiers":[
        {
            "category":"Real Estate",
            "subcategory":"Real Estate Operator",
            "type":"Services"
        }
    ],
    "sg:phone":"+1 843 767 2177",
    "sg:postcode":"29418",
    "sg:province":"SC",
    "sg:tags":[
        "apartment"
    ],
    "wof:name":"Collins Park Villas",
    "wof:placetype":"venue"
},
  "geometry": {"coordinates":[-80.04864000000001,32.867724],"type":"Point"}
}