{
  "type": "Feature",
  "properties": {
    "iso:country":"US",
    "sg:address":"2025 Howard St",
    "sg:city":"Spartanburg",
    "sg:classifiers":[
        {
            "category":"Autos & Motor Vehicles",
            "subcategory":"Auto Supplies",
            "type":"Retail Goods"
        }
    ],
    "sg:phone":"+1 864 582 8599",
    "sg:postcode":"29303",
    "sg:province":"SC",
    "sg:tags":[
        "accessories-wholesale",
        "automobile",
        "part",
        "parts",
        "manufacturer"
    ],
    "wof:name":"Wadell's Used",
    "wof:placetype":"venue"
},
  "geometry": {"coordinates":[-81.963308,34.969065],"type":"Point"}
}