{
  "type": "Feature",
  "properties": {
    "iso:country":"US",
    "sg:address":"1034 Chestnut St",
    "sg:city":"Orangeburg",
    "sg:classifiers":[
        {
            "category":"Restaurant",
            "type":"Food & Drink"
        }
    ],
    "sg:phone":"+1 803 535 4302",
    "sg:postcode":"29115",
    "sg:province":"SC",
    "sg:tags":[
        "eating"
    ],
    "wof:name":"La Cabana",
    "wof:placetype":"venue"
},
  "geometry": {"coordinates":[-80.855448,33.510053],"type":"Point"}
}