{
  "type": "Feature",
  "properties": {
    "iso:country":"US",
    "sg:address":"2603 E Spring St",
    "sg:city":"Florence",
    "sg:classifiers":[
        {
            "category":"Building & Trades",
            "subcategory":"Construction",
            "type":"Services"
        }
    ],
    "sg:phone":"+1 843 676 0420",
    "sg:postcode":"29505",
    "sg:province":"SC",
    "sg:tags":[
        "painter"
    ],
    "wof:name":"Painting Co",
    "wof:placetype":"venue"
},
  "geometry": {"coordinates":[-79.728748,34.149654],"type":"Point"}
}