{
  "type": "Feature",
  "properties": {
    "addr:full":"1003 Gervais St Columbia SC 29201",
    "addr:housenumber":"1003",
    "addr:postcode":"29201",
    "addr:street":"Gervais St",
    "iso:country":"US",
    "sg:address":"1003 Gervais St",
    "sg:city":"Columbia",
    "sg:classifiers":[
        {
            "category":"Government",
            "subcategory":"Office",
            "type":"Public Place"
        }
    ],
    "sg:phone":"+1 803 343 0765",
    "sg:postcode":"29201",
    "sg:province":"SC",
    "wof:name":"Prosecution Coordination Comm",
    "wof:placetype":"venue"
},
  "geometry": {"coordinates":[-81.035257,34.000818],"type":"Point"}
}