{
  "type": "Feature",
  "properties": {
    "iso:country":"US",
    "sg:address":"1335 Hayne St",
    "sg:city":"Spartanburg",
    "sg:classifiers":[
        {
            "category":"Professional",
            "subcategory":"Business Services",
            "type":"Services"
        }
    ],
    "sg:phone":"+1 864 574 8433",
    "sg:postcode":"29301",
    "sg:province":"SC",
    "sg:tags":[
        "appraiser"
    ],
    "sg:website":"www.atkinsmachinery.com",
    "wof:name":"Atkins Appraisals LLC",
    "wof:placetype":"venue"
},
  "geometry": {"coordinates":[-81.980011,34.961105],"type":"Point"}
}