{
  "type": "Feature",
  "properties": {
    "addr:full":"904 W Liberty St York SC 29745",
    "addr:housenumber":"904",
    "addr:postcode":"29745",
    "addr:street":"W Liberty St",
    "iso:country":"US",
    "sg:address":"904 W Liberty St",
    "sg:city":"York",
    "sg:classifiers":[
        {
            "category":"Government",
            "subcategory":"Office",
            "type":"Public Place"
        }
    ],
    "sg:phone":"+1 803 684 6048",
    "sg:postcode":"29745",
    "sg:province":"SC",
    "sg:tags":[
        "federal",
        "security"
    ],
    "wof:name":"US Army Reserve Ctr",
    "wof:placetype":"venue"
},
  "geometry": {"coordinates":[-81.256643,35.000926],"type":"Point"}
}