{
  "type": "Feature",
  "properties": {
    "iso:country":"US",
    "sg:address":"1850 Charleston Hwy",
    "sg:city":"Orangeburg",
    "sg:classifiers":[
        {
            "category":"Government",
            "subcategory":"Police Station",
            "type":"Public Place"
        }
    ],
    "sg:phone":"+1 803 531 6840",
    "sg:postcode":"29115",
    "sg:province":"SC",
    "sg:tags":[
        "state"
    ],
    "wof:name":"Highway Patrol",
    "wof:placetype":"venue"
},
  "geometry": {"coordinates":[-80.843869,33.469591],"type":"Point"}
}