{
  "type": "Feature",
  "properties": {
    "addr:full":"9728 Kershaw Camden Hwy Kershaw SC 29067",
    "addr:housenumber":"9728",
    "addr:postcode":"29067",
    "addr:street":"Kershaw Camden Hwy",
    "iso:country":"US",
    "sg:address":"9728 Kershaw Camden Hwy",
    "sg:city":"Kershaw",
    "sg:classifiers":[
        {
            "category":"Personal",
            "subcategory":"Beauty Salon",
            "type":"Services"
        }
    ],
    "sg:phone":"+1 803 475 2226",
    "sg:postcode":"29067",
    "sg:province":"SC",
    "wof:name":"Perfect Touch",
    "wof:placetype":"venue"
},
  "geometry": {"coordinates":[-80.598197,34.498149],"type":"Point"}
}