{
  "type": "Feature",
  "properties": {
    "addr:full":"969 Ridge Rd Ridgeville SC 29472",
    "addr:housenumber":"969",
    "addr:postcode":"29472",
    "addr:street":"Ridge Rd",
    "iso:country":"US",
    "sg:address":"969 Ridge Rd",
    "sg:city":"Ridgeville",
    "sg:classifiers":[
        {
            "category":"Organizations",
            "subcategory":"Religious Organization",
            "type":"Services"
        }
    ],
    "sg:phone":"+1 843 871 5690",
    "sg:postcode":"29472",
    "sg:province":"SC",
    "sg:tags":[
        "church"
    ],
    "wof:name":"St John Baptist Church",
    "wof:placetype":"venue"
},
  "geometry": {"coordinates":[-80.367214,33.072202],"type":"Point"}
}