{
  "type": "Feature",
  "properties": {
    "addr:full":"34 Wells East Dr Hilton Head Isle SC 29926",
    "addr:housenumber":"34",
    "addr:postcode":"29926",
    "addr:street":"Wells East Dr",
    "iso:country":"US",
    "sg:address":"34 Wells East Dr",
    "sg:city":"Hilton Head Isle",
    "sg:classifiers":[
        {
            "category":"Building & Trades",
            "subcategory":"Construction",
            "type":"Services"
        }
    ],
    "sg:phone":"+1 843 342 3188",
    "sg:postcode":"29926",
    "sg:province":"SC",
    "sg:tags":[
        "painter"
    ],
    "wof:name":"Paramount Painting/Greg Ford",
    "wof:placetype":"venue"
},
  "geometry": {"coordinates":[-80.77774700000001,32.190241],"type":"Point"}
}