{
  "type": "Feature",
  "properties": {
    "addr:full":"949 Sams Point Rd Beaufort SC 29907",
    "addr:housenumber":"949",
    "addr:postcode":"29907",
    "addr:street":"Sams Point Rd",
    "iso:country":"US",
    "sg:address":"949 Sams Point Rd",
    "sg:city":"Beaufort",
    "sg:classifiers":[
        {
            "category":"Organizations",
            "subcategory":"Religious Organization",
            "type":"Services"
        }
    ],
    "sg:phone":"+1 843 770 0667",
    "sg:postcode":"29907",
    "sg:province":"SC",
    "sg:tags":[
        "church"
    ],
    "wof:name":"New Direction Community Church",
    "wof:placetype":"venue"
},
  "geometry": {"coordinates":[-80.609717,32.485966],"type":"Point"}
}