{
  "type": "Feature",
  "properties": {
    "iso:country":"US",
    "sg:address":"371 Conrad Cir",
    "sg:city":"Columbia",
    "sg:classifiers":[
        {
            "category":"Shopping",
            "subcategory":"Department Store",
            "type":"Retail Goods"
        }
    ],
    "sg:phone":"+1 803 781 6008",
    "sg:postcode":"29212",
    "sg:province":"SC",
    "wof:name":"Maharam Store 041",
    "wof:placetype":"venue"
},
  "geometry": {"coordinates":[-81.188942,34.059688],"type":"Point"}
}