{
  "type": "Feature",
  "properties": {
    "addr:full":"500 Ball Park Rd Gaston SC 29053",
    "addr:housenumber":"500",
    "addr:postcode":"29053",
    "addr:street":"Ball Park Rd",
    "iso:country":"US",
    "sg:address":"500 Ball Park Rd",
    "sg:city":"Gaston",
    "sg:classifiers":[
        {
            "category":"Building & Trades",
            "subcategory":"Construction",
            "type":"Services"
        }
    ],
    "sg:phone":"+1 803 794 7900",
    "sg:postcode":"29053",
    "sg:province":"SC",
    "sg:tags":[
        "general",
        "contractor"
    ],
    "sg:website":"www.tobycosc.com",
    "wof:name":"Tobyco",
    "wof:placetype":"venue"
},
  "geometry": {"coordinates":[-81.093566,33.830332],"type":"Point"}
}