{
  "type": "Feature",
  "properties": {
    "addr:full":"2775 Montague Ave Exd Greenwood SC 29649",
    "addr:housenumber":"2775",
    "addr:postcode":"29649",
    "addr:street":"Montague Ave Exd",
    "iso:country":"US",
    "sg:address":"2775 Montague Ave Exd",
    "sg:city":"Greenwood",
    "sg:classifiers":[
        {
            "category":"Social Services",
            "subcategory":"Child Care",
            "type":"Services"
        }
    ],
    "sg:phone":"+1 864 229 6553",
    "sg:postcode":"29649",
    "sg:province":"SC",
    "sg:tags":[
        "kindergarten",
        "academic",
        "school"
    ],
    "wof:name":"Calvary Baptist Christian Schl",
    "wof:placetype":"venue"
},
  "geometry": {"coordinates":[-82.215065,34.24659],"type":"Point"}
}