{
  "type": "Feature",
  "properties": {
    "addr:full":"1964 Davant Cir Mt Pleasant SC 29464",
    "addr:housenumber":"1964",
    "addr:postcode":"29464",
    "addr:street":"Davant Cir",
    "iso:country":"US",
    "sg:address":"1964 Davant Cir",
    "sg:city":"Mt Pleasant",
    "sg:classifiers":[
        {
            "category":"Building & Trades",
            "subcategory":"Construction",
            "type":"Services"
        }
    ],
    "sg:phone":"+1 843 514 7109",
    "sg:postcode":"29464",
    "sg:province":"SC",
    "sg:tags":[
        "general",
        "contractor"
    ],
    "wof:name":"Tompkins & Assoc",
    "wof:placetype":"venue"
},
  "geometry": {"coordinates":[-79.834502,32.856289],"type":"Point"}
}