{
  "type": "Feature",
  "properties": {
    "addr:full":"35 Hunter Rd Hilton Head Isle SC 29926",
    "addr:housenumber":"35",
    "addr:postcode":"29926",
    "addr:street":"Hunter Rd",
    "iso:country":"US",
    "sg:address":"35 Hunter Rd",
    "sg:city":"Hilton Head Isle",
    "sg:classifiers":[
        {
            "category":"Autos & Motor Vehicles",
            "subcategory":"Auto Supplies",
            "type":"Retail Goods"
        }
    ],
    "sg:phone":"+1 843 681 8863",
    "sg:postcode":"29926",
    "sg:province":"SC",
    "sg:tags":[
        "automobile",
        "stereo",
        "radio"
    ],
    "wof:name":"Car Tunes",
    "wof:placetype":"venue"
},
  "geometry": {"coordinates":[-80.70176499999999,32.220623],"type":"Point"}
}