{
  "type": "Feature",
  "properties": {
    "iso:country":"US",
    "sg:address":"707 Greenwood St",
    "sg:city":"Columbia",
    "sg:classifiers":[
        {
            "category":"Professional",
            "type":"Services"
        }
    ],
    "sg:phone":"+1 803 794 4767",
    "sg:postcode":"29205",
    "sg:province":"SC",
    "sg:tags":[
        "mineral"
    ],
    "wof:name":"Complete H20 Minerals",
    "wof:placetype":"venue"
},
  "geometry": {"coordinates":[-80.997035,33.998963],"type":"Point"}
}