{
  "type": "Feature",
  "properties": {
    "addr:full":"1001 Harden St Columbia SC 29205",
    "addr:housenumber":"1001",
    "addr:postcode":"29205",
    "addr:street":"Harden St",
    "iso:country":"US",
    "sg:address":"1001 Harden St",
    "sg:city":"Columbia",
    "sg:classifiers":[
        {
            "category":"Food & Beverages",
            "subcategory":"Groceries & Convenience Stores",
            "type":"Retail Goods"
        }
    ],
    "sg:phone":"+1 803 312 0082",
    "sg:postcode":"29205",
    "sg:province":"SC",
    "sg:tags":[
        "market"
    ],
    "wof:name":"Market Place At Harden",
    "wof:placetype":"venue"
},
  "geometry": {"coordinates":[-81.018513,34.004255],"type":"Point"}
}