{
  "type": "Feature",
  "properties": {
    "addr:full":"1639 E Main St Easley SC 29640",
    "addr:housenumber":"1639",
    "addr:postcode":"29640",
    "addr:street":"E Main St",
    "iso:country":"US",
    "sg:address":"1639 E Main St",
    "sg:city":"Easley",
    "sg:classifiers":[
        {
            "category":"Autos & Motor Vehicles",
            "subcategory":"Automobile Sales",
            "type":"Retail Goods"
        }
    ],
    "sg:phone":"+1 864 306 0204",
    "sg:postcode":"29640",
    "sg:province":"SC",
    "sg:tags":[
        "car",
        "used",
        "dealership"
    ],
    "wof:name":"Front Line Auto Sales",
    "wof:placetype":"venue"
},
  "geometry": {"coordinates":[-82.57196,34.828662],"type":"Point"}
}