{
  "type": "Feature",
  "properties": {
    "iso:country":"US",
    "sg:address":"1420 Blanding St",
    "sg:city":"Columbia",
    "sg:classifiers":[
        {
            "category":"Health Services",
            "subcategory":"Doctor",
            "type":"Services"
        }
    ],
    "sg:phone":"+1 803 779 8870",
    "sg:postcode":"29201",
    "sg:province":"SC",
    "sg:tags":[
        "physician",
        "surgeon"
    ],
    "wof:name":"Southeastern Fertility Ctr",
    "wof:placetype":"venue"
},
  "geometry": {"coordinates":[-81.031997,34.009254],"type":"Point"}
}