{
  "type": "Feature",
  "properties": {
    "addr:full":"212 Phoenix St Greenwood SC 29646",
    "addr:housenumber":"212",
    "addr:postcode":"29646",
    "addr:street":"Phoenix St",
    "iso:country":"US",
    "sg:address":"212 Phoenix St",
    "sg:city":"Greenwood",
    "sg:classifiers":[
        {
            "category":"Personal",
            "type":"Services"
        }
    ],
    "sg:phone":"+1 864 388 0388",
    "sg:postcode":"29646",
    "sg:province":"SC",
    "sg:tags":[
        "therapist",
        "massage"
    ],
    "wof:name":"Theracare Of Greenwood",
    "wof:placetype":"venue"
},
  "geometry": {"coordinates":[-82.158586,34.190758],"type":"Point"}
}