{
  "type": "Feature",
  "properties": {
    "addr:full":"129 Schoolhouse St Pickens SC 29671",
    "addr:housenumber":"129",
    "addr:postcode":"29671",
    "addr:street":"Schoolhouse St",
    "iso:country":"US",
    "sg:address":"129 Schoolhouse St",
    "sg:city":"Pickens",
    "sg:classifiers":[
        {
            "category":"Organizations",
            "subcategory":"Non-profit Organization",
            "type":"Services"
        }
    ],
    "sg:phone":"+1 864 878 0013",
    "sg:postcode":"29671",
    "sg:province":"SC",
    "sg:tags":[
        "human"
    ],
    "wof:name":"Pickens Senior Ctr",
    "wof:placetype":"venue"
},
  "geometry": {"coordinates":[-82.69803400000001,34.887663],"type":"Point"}
}