{
  "type": "Feature",
  "properties": {
    "iso:country":"US",
    "sg:address":"4328 Wade Hampton Blvd",
    "sg:city":"Taylors",
    "sg:classifiers":[
        {
            "category":"Professional",
            "subcategory":"Management & Consulting",
            "type":"Services"
        }
    ],
    "sg:phone":"+1 864 244 4220",
    "sg:postcode":"29687",
    "sg:province":"SC",
    "sg:tags":[
        "personnel",
        "consultant"
    ],
    "sg:website":"www.daniel-associates.com",
    "wof:name":"Daniel Associates",
    "wof:placetype":"venue"
},
  "geometry": {"coordinates":[-82.30504500000001,34.923878],"type":"Point"}
}