{
  "type": "Feature",
  "properties": {
    "iso:country":"US",
    "sg:address":"1808 Laurens Rd",
    "sg:city":"Greenville",
    "sg:classifiers":[
        {
            "category":"Food & Beverages",
            "subcategory":"Liquor & Beverages",
            "type":"Retail Goods"
        }
    ],
    "sg:phone":"+1 864 233 8610",
    "sg:postcode":"29607",
    "sg:province":"SC",
    "wof:name":"Wines & Liquors Inc",
    "wof:placetype":"venue"
},
  "geometry": {"coordinates":[-82.356871,34.839393],"type":"Point"}
}