{
  "type": "Feature",
  "properties": {
    "addr:full":"1415 N Main St Summerville SC 29483",
    "addr:housenumber":"1415",
    "addr:postcode":"29483",
    "addr:street":"N Main St",
    "iso:country":"US",
    "sg:address":"1415 N Main St",
    "sg:city":"Summerville",
    "sg:classifiers":[
        {
            "category":"Restaurant",
            "type":"Food & Drink"
        }
    ],
    "sg:menulink":"http://www.allmenus.com/sc/goose-creek-hanahan/107766-waffle-house/menu/",
    "sg:phone":"+1 843 873 7016",
    "sg:postcode":"29483",
    "sg:province":"SC",
    "sg:tags":[
        "american"
    ],
    "wof:name":"Waffle House",
    "wof:placetype":"venue"
},
  "geometry": {"coordinates":[-80.15249,33.036945],"type":"Point"}
}