{
  "type": "Feature",
  "properties": {
    "addr:full":"400 S Hudson St Greenville SC 29601",
    "addr:housenumber":"400",
    "addr:postcode":"29601",
    "addr:street":"S Hudson St",
    "iso:country":"US",
    "sg:address":"400 S Hudson St",
    "sg:city":"Greenville",
    "sg:classifiers":[
        {
            "category":"Organizations",
            "subcategory":"Religious Organization",
            "type":"Services"
        }
    ],
    "sg:phone":"+1 864 235 3201",
    "sg:postcode":"29601",
    "sg:province":"SC",
    "sg:tags":[
        "church"
    ],
    "wof:name":"Tabernacle Baptist Church",
    "wof:placetype":"venue"
},
  "geometry": {"coordinates":[-82.41162,34.847602],"type":"Point"}
}