{
  "type": "Feature",
  "properties": {
    "iso:country":"US",
    "sg:address":"1451 E Main St",
    "sg:city":"Spartanburg",
    "sg:classifiers":[
        {
            "category":"Professional",
            "subcategory":"Lawyer & Legal Services",
            "type":"Services"
        }
    ],
    "sg:phone":"+1 864 582 4365",
    "sg:postcode":"29307",
    "sg:province":"SC",
    "sg:tags":[
        "attorney"
    ],
    "wof:name":"Leatherwood Walker Todd & Mann",
    "wof:placetype":"venue"
},
  "geometry": {"coordinates":[-81.900982,34.963159],"type":"Point"}
}