{
  "type": "Feature",
  "properties": {
    "iso:country":"US",
    "sg:address":"2583 Aspen Ter",
    "sg:city":"Rock Hill",
    "sg:classifiers":[
        {
            "category":"Recreation",
            "type":"Entertainment"
        }
    ],
    "sg:phone":"+1 803 366 5772",
    "sg:postcode":"29732",
    "sg:province":"SC",
    "sg:tags":[
        "tennis",
        "instruction"
    ],
    "wof:name":"Shiland Hills Racquet & Swim",
    "wof:placetype":"venue"
},
  "geometry": {"coordinates":[-81.022893,34.972703],"type":"Point"}
}