{
  "type": "Feature",
  "properties": {
    "addr:full":"2850 Commerce Dr Rock Hill SC 29730",
    "addr:housenumber":"2850",
    "addr:postcode":"29730",
    "addr:street":"Commerce Dr",
    "iso:country":"US",
    "sg:address":"2850 Commerce Dr",
    "sg:city":"Rock Hill",
    "sg:classifiers":[
        {
            "category":"Shopping",
            "subcategory":"Bicycles & Sporting Goods",
            "type":"Retail Goods"
        }
    ],
    "sg:phone":"+1 803 366 5028",
    "sg:postcode":"29730",
    "sg:province":"SC",
    "sg:website":"www.innovadiscgolf.com",
    "wof:name":"Innova Disc Golf",
    "wof:placetype":"venue"
},
  "geometry": {"coordinates":[-80.970775,34.949681],"type":"Point"}
}