{
  "type": "Feature",
  "properties": {
    "addr:full":"3204 Lancaster Hwy Richburg SC 29729",
    "addr:housenumber":"3204",
    "addr:postcode":"29729",
    "addr:street":"Lancaster Hwy",
    "iso:country":"US",
    "sg:address":"3204 Lancaster Hwy",
    "sg:city":"Richburg",
    "sg:classifiers":[
        {
            "category":"Restaurant",
            "type":"Food & Drink"
        }
    ],
    "sg:menulink":"http://www.allmenus.com/sc/richburg/141897-waffle-house/menu/",
    "sg:phone":"+1 803 789 5535",
    "sg:postcode":"29729",
    "sg:province":"SC",
    "sg:tags":[
        "american"
    ],
    "wof:name":"Waffle House",
    "wof:placetype":"venue"
},
  "geometry": {"coordinates":[-81.024783,34.739325],"type":"Point"}
}