{
  "type": "Feature",
  "properties": {
    "iso:country":"US",
    "sg:address":"1834 Morninglo Ln",
    "sg:city":"Columbia",
    "sg:classifiers":[
        {
            "category":"Organizations",
            "subcategory":"Religious Organization",
            "type":"Services"
        }
    ],
    "sg:phone":"+1 803 787 0678",
    "sg:postcode":"29223",
    "sg:province":"SC",
    "sg:tags":[
        "church"
    ],
    "wof:name":"Woodfield Park Baptist Church",
    "wof:placetype":"venue"
},
  "geometry": {"coordinates":[-80.931717,34.052943],"type":"Point"}
}