{
  "type": "Feature",
  "properties": {
    "addr:full":"1517 Cedar Lane Rd Greenville SC 29617",
    "addr:housenumber":"1517",
    "addr:postcode":"29617",
    "addr:street":"Cedar Lane Rd",
    "iso:country":"US",
    "sg:address":"1517 Cedar Lane Rd",
    "sg:city":"Greenville",
    "sg:classifiers":[
        {
            "category":"Retail",
            "subcategory":"Auto Repair",
            "type":"Services"
        }
    ],
    "sg:phone":"+1 864 246 2576",
    "sg:postcode":"29617",
    "sg:province":"SC",
    "sg:tags":[
        "general"
    ],
    "wof:name":"Berea Automotive",
    "wof:placetype":"venue"
},
  "geometry": {"coordinates":[-82.446423,34.878564],"type":"Point"}
}