{
  "type": "Feature",
  "properties": {
    "iso:country":"US",
    "sg:address":"2313 Sumter Hwy",
    "sg:city":"Bishopville",
    "sg:classifiers":[
        {
            "category":"Building & Trades",
            "subcategory":"Construction",
            "type":"Services"
        }
    ],
    "sg:phone":"+1 803 428 5880",
    "sg:postcode":"29010",
    "sg:province":"SC",
    "sg:tags":[
        "home",
        "improvement"
    ],
    "wof:name":"H & G Home Improvements",
    "wof:placetype":"venue"
},
  "geometry": {"coordinates":[-80.302453,34.155615],"type":"Point"}
}