{
  "type": "Feature",
  "properties": {
    "iso:country":"US",
    "sg:address":"1564 Hwy 41",
    "sg:city":"Mount Pleasant",
    "sg:classifiers":[
        {
            "category":"Building & Trades",
            "subcategory":"Construction",
            "type":"Services"
        }
    ],
    "sg:phone":"+1 843 884 5524",
    "sg:postcode":"29466",
    "sg:province":"SC",
    "sg:tags":[
        "contractor"
    ],
    "wof:name":"Coaxum Stucco Co",
    "wof:placetype":"venue"
},
  "geometry": {"coordinates":[-79.808042,32.878708],"type":"Point"}
}