{
  "type": "Feature",
  "properties": {
    "iso:country":"US",
    "sg:address":"210 Broad St",
    "sg:city":"Sumter",
    "sg:classifiers":[
        {
            "category":"Shopping",
            "subcategory":"Used Merchandise",
            "type":"Retail Goods"
        }
    ],
    "sg:phone":"+1 803 773 4214",
    "sg:postcode":"29150",
    "sg:province":"SC",
    "sg:tags":[
        "antique",
        "clocks"
    ],
    "wof:name":"Estate Antiques Gifts & Acces",
    "wof:placetype":"venue"
},
  "geometry": {"coordinates":[-80.348875,33.930043],"type":"Point"}
}