{
  "type": "Feature",
  "properties": {
    "iso:country":"US",
    "sg:address":"104 Colonial Plaza Dr",
    "sg:city":"Seneca",
    "sg:classifiers":[
        {
            "category":"Home & Garden",
            "subcategory":"Furniture",
            "type":"Retail Goods"
        }
    ],
    "sg:phone":"+1 864 882 8000",
    "sg:postcode":"29678",
    "sg:province":"SC",
    "sg:tags":[
        "mattress"
    ],
    "wof:name":"Arvin's Bargains At Dobson",
    "wof:placetype":"venue"
},
  "geometry": {"coordinates":[-82.97974499999999,34.693884],"type":"Point"}
}