{
  "type": "Feature",
  "properties": {
    "iso:country":"US",
    "sg:address":"851 Santa Fe Trl",
    "sg:city":"Sumter",
    "sg:classifiers":[
        {
            "category":"Building & Trades",
            "subcategory":"Construction",
            "type":"Services"
        }
    ],
    "sg:phone":"+1 803 494 9810",
    "sg:postcode":"29154",
    "sg:province":"SC",
    "sg:tags":[
        "water",
        "well",
        "drilling"
    ],
    "wof:name":"Williams Well Drilling",
    "wof:placetype":"venue"
},
  "geometry": {"coordinates":[-80.425407,33.897051],"type":"Point"}
}