{
  "type": "Feature",
  "properties": {
    "iso:country":"US",
    "sg:address":"8 Hillington Pl",
    "sg:city":"Greer",
    "sg:classifiers":[
        {
            "category":"Real Estate",
            "subcategory":"Developer",
            "type":"Services"
        }
    ],
    "sg:phone":"+1 864 879 8194",
    "sg:postcode":"29651",
    "sg:province":"SC",
    "wof:name":"CSS LLC",
    "wof:placetype":"venue"
},
  "geometry": {"coordinates":[-82.241314,34.953216],"type":"Point"}
}