{
  "type": "Feature",
  "properties": {
    "addr:full":"650 E Cheval Dr Fort Mill SC 29708",
    "addr:housenumber":"650",
    "addr:postcode":"29708",
    "addr:street":"E Cheval Dr",
    "iso:country":"US",
    "sg:address":"650 E Cheval Dr",
    "sg:city":"Fort Mill",
    "sg:classifiers":[
        {
            "category":"Building & Trades",
            "subcategory":"Construction",
            "type":"Services"
        }
    ],
    "sg:phone":"+1 803 547 6424",
    "sg:postcode":"29708",
    "sg:province":"SC",
    "sg:tags":[
        "home",
        "builder"
    ],
    "wof:name":"Ryan Homes",
    "wof:placetype":"venue"
},
  "geometry": {"coordinates":[-80.967585,35.067421],"type":"Point"}
}