{
  "type": "Feature",
  "properties": {
    "iso:country":"US",
    "sg:address":"600 Bacons Bridge Rd",
    "sg:city":"Summerville",
    "sg:classifiers":[
        {
            "category":"Autos & Motor Vehicles",
            "subcategory":"Fuel & Gas Station",
            "type":"Retail Goods"
        }
    ],
    "sg:phone":"+1 843 871 1545",
    "sg:postcode":"29485",
    "sg:province":"SC",
    "sg:tags":[
        "oil"
    ],
    "wof:name":"Speedway",
    "wof:placetype":"venue"
},
  "geometry": {"coordinates":[-80.20088,32.961533],"type":"Point"}
}