{
  "type": "Feature",
  "properties": {
    "iso:country":"US",
    "sg:address":"1800 Asheville Hwy",
    "sg:city":"Spartanburg",
    "sg:classifiers":[
        {
            "category":"Restaurant",
            "type":"Food & Drink"
        }
    ],
    "sg:menulink":"http://www.allmenus.com/sc/spartanburg/153420-bojangles/menu/",
    "sg:phone":"+1 864 582 3915",
    "sg:postcode":"29303",
    "sg:province":"SC",
    "sg:tags":[
        "chicken",
        "sandwich",
        "american"
    ],
    "wof:name":"Bojangle's",
    "wof:placetype":"venue"
},
  "geometry": {"coordinates":[-81.970676,34.982312],"type":"Point"}
}