{
  "type": "Feature",
  "properties": {
    "iso:country":"US",
    "sg:address":"708 Main St",
    "sg:city":"Myrtle Beach",
    "sg:classifiers":[
        {
            "category":"Professional",
            "subcategory":"Management & Consulting",
            "type":"Services"
        }
    ],
    "sg:phone":"+1 843 448 9483",
    "sg:postcode":"29577",
    "sg:province":"SC",
    "sg:tags":[
        "party",
        "planning"
    ],
    "wof:name":"Leisure Time Unlimited Inc",
    "wof:placetype":"venue"
},
  "geometry": {"coordinates":[-78.883588,33.693412],"type":"Point"}
}