{
  "type": "Feature",
  "properties": {
    "iso:country":"US",
    "sg:address":"1200 E Main St",
    "sg:city":"Spartanburg",
    "sg:classifiers":[
        {
            "category":"Ice Cream",
            "type":"Food & Drink"
        }
    ],
    "sg:menulink":"http://www.allmenus.com/sc/spartanburg/230162-marble-slab-creamery/menu/",
    "sg:phone":"+1 864 598 0001",
    "sg:postcode":"29307",
    "sg:province":"SC",
    "sg:tags":[
        "american"
    ],
    "wof:name":"Marble Slab Creamery",
    "wof:placetype":"venue"
},
  "geometry": {"coordinates":[-81.90275800000001,34.962012],"type":"Point"}
}