{
  "type": "Feature",
  "properties": {
    "iso:country":"US",
    "sg:address":"1929 Wilson Rd",
    "sg:city":"Newberry",
    "sg:classifiers":[
        {
            "category":"Home & Garden",
            "subcategory":"Furniture",
            "type":"Retail Goods"
        }
    ],
    "sg:phone":"+1 803 276 3444",
    "sg:postcode":"29108",
    "sg:province":"SC",
    "wof:name":"Parker Furniture",
    "wof:placetype":"venue"
},
  "geometry": {"coordinates":[-81.605857,34.293649],"type":"Point"}
}