{
  "type": "Feature",
  "properties": {
    "addr:full":"628 Hiers Corner Rd Walterboro SC 29488",
    "addr:housenumber":"628",
    "addr:postcode":"29488",
    "addr:street":"Hiers Corner Rd",
    "iso:country":"US",
    "sg:address":"628 Hiers Corner Rd",
    "sg:city":"Walterboro",
    "sg:classifiers":[
        {
            "category":"Social Services",
            "subcategory":"Child Care",
            "type":"Services"
        }
    ],
    "sg:phone":"+1 843 549 1991",
    "sg:postcode":"29488",
    "sg:province":"SC",
    "wof:name":"Forest Hills Daycare",
    "wof:placetype":"venue"
},
  "geometry": {"coordinates":[-80.67936899999999,32.913879],"type":"Point"}
}