{
  "type": "Feature",
  "properties": {
    "iso:country":"US",
    "sg:address":"155 Jonas Rd",
    "sg:city":"Islandton",
    "sg:classifiers":[
        {
            "category":"Farming",
            "subcategory":"Farm",
            "type":"Manufacturing & Wholesale Goods"
        }
    ],
    "sg:phone":"+1 843 866 7641",
    "sg:postcode":"29929",
    "sg:province":"SC",
    "sg:tags":[
        "crop",
        "general"
    ],
    "wof:name":"Willis Kinard",
    "wof:placetype":"venue"
},
  "geometry": {"coordinates":[-80.973819,32.927884],"type":"Point"}
}