{
  "type": "Feature",
  "properties": {
    "iso:country":"US",
    "sg:address":"5314 US Hwy 321",
    "sg:city":"Gaston",
    "sg:classifiers":[
        {
            "category":"Building & Trades",
            "subcategory":"Construction",
            "type":"Services"
        }
    ],
    "sg:phone":"+1 803 794 7697",
    "sg:postcode":"29053",
    "sg:province":"SC",
    "sg:tags":[
        "general",
        "contractor"
    ],
    "wof:name":"Sunshine Builders Inc",
    "wof:placetype":"venue"
},
  "geometry": {"coordinates":[-81.092286,33.833747],"type":"Point"}
}