{
  "type": "Feature",
  "properties": {
    "addr:full":"6701 Notch Rd Columbia SC 29223",
    "addr:housenumber":"6701",
    "addr:postcode":"29223",
    "addr:street":"Notch Rd",
    "iso:country":"US",
    "sg:address":"6701 Notch Rd",
    "sg:city":"Columbia",
    "sg:classifiers":[
        {
            "category":"Real Estate",
            "subcategory":"Surveying",
            "type":"Services"
        }
    ],
    "sg:phone":"+1 803 788 1177",
    "sg:postcode":"29223",
    "sg:province":"SC",
    "sg:tags":[
        "surveyor"
    ],
    "wof:name":"Polson Surveying",
    "wof:placetype":"venue"
},
  "geometry": {"coordinates":[-80.963787,34.059247],"type":"Point"}
}