{
  "type": "Feature",
  "properties": {
    "iso:country":"US",
    "sg:address":"616 Camp Rd",
    "sg:city":"Latta",
    "sg:classifiers":[
        {
            "category":"Wholesale",
            "subcategory":"Construction Materials",
            "type":"Manufacturing & Wholesale Goods"
        }
    ],
    "sg:phone":"+1 843 752 4208",
    "sg:postcode":"29565",
    "sg:province":"SC",
    "sg:tags":[
        "timberland",
        "company",
        "timber"
    ],
    "wof:name":"Keels Land & Timber",
    "wof:placetype":"venue"
},
  "geometry": {"coordinates":[-79.482986,34.318061],"type":"Point"}
}