{
  "type": "Feature",
  "properties": {
    "addr:full":"113 Chelsea Ct Union SC 29379",
    "addr:housenumber":"113",
    "addr:postcode":"29379",
    "addr:street":"Chelsea Ct",
    "iso:country":"US",
    "sg:address":"113 Chelsea Ct",
    "sg:city":"Union",
    "sg:classifiers":[
        {
            "category":"Social Services",
            "subcategory":"Job Training",
            "type":"Services"
        }
    ],
    "sg:phone":"+1 864 429 5667",
    "sg:postcode":"29379",
    "sg:province":"SC",
    "sg:tags":[
        "retardation",
        "disabled",
        "mental",
        "dev"
    ],
    "wof:name":"Union County Disabilities Brd",
    "wof:placetype":"venue"
},
  "geometry": {"coordinates":[-81.610371,34.720994],"type":"Point"}
}