{
  "type": "Feature",
  "properties": {
    "iso:country":"US",
    "sg:address":"921 Magnolia Bluff Cir",
    "sg:city":"Beaufort",
    "sg:classifiers":[
        {
            "category":"Social Services",
            "subcategory":"Child Care",
            "type":"Services"
        }
    ],
    "sg:phone":"+1 843 525 1731",
    "sg:postcode":"29902",
    "sg:province":"SC",
    "sg:website":"www.hobbithill.com",
    "wof:name":"Hobbit Hill Preschool",
    "wof:placetype":"venue"
},
  "geometry": {"coordinates":[-80.729246,32.381691],"type":"Point"}
}