{
  "type": "Feature",
  "properties": {
    "iso:country":"US",
    "sg:address":"744 W Main St",
    "sg:city":"Lexington",
    "sg:classifiers":[
        {
            "category":"Banks & Credit Unions",
            "subcategory":"Bank",
            "type":"Services"
        }
    ],
    "sg:phone":"+1 803 957 1367",
    "sg:postcode":"29072",
    "sg:province":"SC",
    "sg:tags":[
        "personal",
        "institution"
    ],
    "wof:name":"Citifinancial",
    "wof:placetype":"venue"
},
  "geometry": {"coordinates":[-81.249591,33.98482],"type":"Point"}
}