{
  "type": "Feature",
  "properties": {
    "iso:country":"US",
    "sg:address":"1833 Pageland Hwy",
    "sg:city":"Lancaster",
    "sg:classifiers":[
        {
            "category":"Government",
            "subcategory":"Office",
            "type":"Public Place"
        }
    ],
    "sg:phone":"+1 803 285 7628",
    "sg:postcode":"29720",
    "sg:province":"SC",
    "wof:name":"Lancaster Children's Rehab",
    "wof:placetype":"venue"
},
  "geometry": {"coordinates":[-80.725725,34.723575],"type":"Point"}
}