{
  "type": "Feature",
  "properties": {
    "addr:full":"1233 W Wade Hampton Blvd Greer SC 29650",
    "addr:housenumber":"1233",
    "addr:postcode":"29650",
    "addr:street":"W Wade Hampton Blvd",
    "iso:country":"US",
    "sg:address":"1233 W Wade Hampton Blvd",
    "sg:city":"Greer",
    "sg:classifiers":[
        {
            "category":"Autos & Motor Vehicles",
            "subcategory":"Fuel & Gas Station",
            "type":"Retail Goods"
        }
    ],
    "sg:phone":"+1 864 879 8435",
    "sg:postcode":"29650",
    "sg:province":"SC",
    "sg:tags":[
        "station",
        "gasoline"
    ],
    "wof:name":"Spinx 108c",
    "wof:placetype":"venue"
},
  "geometry": {"coordinates":[-82.260424,34.941376],"type":"Point"}
}