{
  "type": "Feature",
  "properties": {
    "iso:country":"US",
    "sg:address":"96 Cool Stream Dr",
    "sg:city":"Winnsboro",
    "sg:classifiers":[
        {
            "category":"Shopping",
            "type":"Retail Goods"
        }
    ],
    "sg:phone":"+1 803 754 4542",
    "sg:postcode":"29180",
    "sg:province":"SC",
    "sg:tags":[
        "merchandise"
    ],
    "wof:name":"Helping Hands Concept",
    "wof:placetype":"venue"
},
  "geometry": {"coordinates":[-81.131367,34.18137],"type":"Point"}
}