{
  "type": "Feature",
  "properties": {
    "iso:country":"US",
    "sg:address":"206 S Main St",
    "sg:city":"Greenville",
    "sg:classifiers":[
        {
            "category":"Government",
            "subcategory":"Office",
            "type":"Public Place"
        }
    ],
    "sg:phone":"+1 864 467 4545",
    "sg:postcode":"29601",
    "sg:province":"SC",
    "sg:tags":[
        "village"
    ],
    "sg:website":"www.greenearthinc.com",
    "wof:name":"Greenville City Purchasing",
    "wof:placetype":"venue"
},
  "geometry": {"coordinates":[-82.40046,34.847668],"type":"Point"}
}