{
  "type": "Feature",
  "properties": {
    "iso:country":"US",
    "sg:address":"1724 Charleston Hwy",
    "sg:city":"Orangeburg",
    "sg:classifiers":[
        {
            "category":"Government",
            "subcategory":"Office",
            "type":"Public Place"
        }
    ],
    "sg:phone":"+1 803 531 6850",
    "sg:postcode":"29115",
    "sg:province":"SC",
    "wof:name":"Engineering District Office",
    "wof:placetype":"venue"
},
  "geometry": {"coordinates":[-80.846093,33.47086],"type":"Point"}
}