{
  "type": "Feature",
  "properties": {
    "iso:country":"US",
    "sg:address":"840 Wofford St",
    "sg:city":"Spartanburg",
    "sg:classifiers":[
        {
            "category":"Communications",
            "subcategory":"Radio Station",
            "type":"Services"
        }
    ],
    "sg:phone":"+1 864 585 1530",
    "sg:postcode":"29301",
    "sg:province":"SC",
    "sg:tags":[
        "company",
        "broadcasting"
    ],
    "wof:name":"WASC",
    "wof:placetype":"venue"
},
  "geometry": {"coordinates":[-81.951474,34.949593],"type":"Point"}
}