{
  "type": "Feature",
  "properties": {
    "iso:country":"US",
    "sg:address":"420 Jessen Ln",
    "sg:city":"Charleston",
    "sg:classifiers":[
        {
            "category":"Home & Garden",
            "subcategory":"Building Materials",
            "type":"Retail Goods"
        }
    ],
    "sg:phone":"+1 843 971 4236",
    "sg:postcode":"29492",
    "sg:province":"SC",
    "wof:name":"Bradco Supply Corp",
    "wof:placetype":"venue"
},
  "geometry": {"coordinates":[-79.919815,32.904138],"type":"Point"}
}