{
  "type": "Feature",
  "properties": {
    "iso:country":"US",
    "sg:address":"4180 US Hwy 15 S",
    "sg:city":"Sumter",
    "sg:classifiers":[
        {
            "category":"Building & Trades",
            "subcategory":"Construction",
            "type":"Services"
        },
        {
            "category":"Building & Trades",
            "subcategory":"Plumbing",
            "type":"Services"
        }
    ],
    "sg:phone":"+1 803 481 4721",
    "sg:postcode":"29150",
    "sg:province":"SC",
    "sg:tags":[
        "mechanical",
        "piping",
        "contractor"
    ],
    "sg:website":"www.industrialpipecontractors.com",
    "wof:name":"Industrial Pipe Contractors",
    "wof:placetype":"venue"
},
  "geometry": {"coordinates":[-80.357573,33.799254],"type":"Point"}
}