{
  "type": "Feature",
  "properties": {
    "iso:country":"US",
    "sg:address":"304 W Montgomery St",
    "sg:city":"Gaffney",
    "sg:classifiers":[
        {
            "category":"Recreation",
            "type":"Entertainment"
        }
    ],
    "sg:phone":"+1 864 487 2734",
    "sg:postcode":"29340",
    "sg:province":"SC",
    "sg:tags":[
        "parks"
    ],
    "wof:name":"Irene Ball Park",
    "wof:placetype":"venue"
},
  "geometry": {"coordinates":[-81.65438,35.072259],"type":"Point"}
}