{
  "type": "Feature",
  "properties": {
    "iso:country":"US",
    "sg:address":"1495 Remount Rd",
    "sg:city":"North Charleston",
    "sg:classifiers":[
        {
            "category":"Professional",
            "subcategory":"Lawyer & Legal Services",
            "type":"Services"
        }
    ],
    "sg:phone":"+1 843 364 8555",
    "sg:postcode":"29406",
    "sg:province":"SC",
    "sg:tags":[
        "attorney"
    ],
    "wof:name":"George Gatgounis",
    "wof:placetype":"venue"
},
  "geometry": {"coordinates":[-80.000695,32.900855],"type":"Point"}
}