{
  "type": "Feature",
  "properties": {
    "addr:full":"35 W Court St Greenville SC 29601",
    "addr:housenumber":"35",
    "addr:postcode":"29601",
    "addr:street":"W Court St",
    "iso:country":"US",
    "sg:address":"35 W Court St",
    "sg:city":"Greenville",
    "sg:classifiers":[
        {
            "category":"Building & Trades",
            "subcategory":"Construction",
            "type":"Services"
        }
    ],
    "sg:phone":"+1 864 527 2500",
    "sg:postcode":"29601",
    "sg:province":"SC",
    "sg:tags":[
        "contractor"
    ],
    "sg:website":"www.harpercorp.com",
    "wof:name":"Harper Corp",
    "wof:placetype":"venue"
},
  "geometry": {"coordinates":[-82.40086599999999,34.848696],"type":"Point"}
}