{
  "type": "Feature",
  "properties": {
    "iso:country":"US",
    "sg:address":"435 Georgetown Rd",
    "sg:city":"Darlington",
    "sg:classifiers":[
        {
            "category":"Building & Trades",
            "subcategory":"Plumbing",
            "type":"Services"
        }
    ],
    "sg:phone":"+1 843 393 6310",
    "sg:postcode":"29532",
    "sg:province":"SC",
    "sg:tags":[
        "plumbing",
        "contractor"
    ],
    "wof:name":"Stuckey Plumbing & Supplies",
    "wof:placetype":"venue"
},
  "geometry": {"coordinates":[-79.736557,34.342761],"type":"Point"}
}