{
  "type": "Feature",
  "properties": {
    "iso:country":"US",
    "sg:address":"1205 48th Ave N",
    "sg:city":"Myrtle Beach",
    "sg:classifiers":[
        {
            "category":"Utilities",
            "subcategory":"Telephone",
            "type":"Services"
        }
    ],
    "sg:phone":"+1 843 497 1080",
    "sg:postcode":"29577",
    "sg:province":"SC",
    "sg:tags":[
        "a",
        "acting",
        "communications",
        "as",
        "provides",
        "local",
        "or"
    ],
    "wof:name":"Ameritel Communications",
    "wof:placetype":"venue"
},
  "geometry": {"coordinates":[-78.860128,33.733648],"type":"Point"}
}