{
  "type": "Feature",
  "properties": {
    "iso:country":"US",
    "sg:address":"456 Main St",
    "sg:city":"Blackville",
    "sg:classifiers":[
        {
            "category":"Banks & Credit Unions",
            "subcategory":"Bank",
            "type":"Services"
        }
    ],
    "sg:phone":"+1 803 284 1015",
    "sg:postcode":"29817",
    "sg:province":"SC",
    "sg:tags":[
        "loan"
    ],
    "wof:name":"Delta Loans",
    "wof:placetype":"venue"
},
  "geometry": {"coordinates":[-81.26870700000001,33.354832],"type":"Point"}
}