{
  "type": "Feature",
  "properties": {
    "iso:country":"US",
    "sg:address":"862 Shiloh Unity Rd",
    "sg:city":"Lancaster",
    "sg:classifiers":[
        {
            "category":"Building & Trades",
            "subcategory":"Construction",
            "type":"Services"
        }
    ],
    "sg:phone":"+1 803 285 5771",
    "sg:postcode":"29720",
    "sg:province":"SC",
    "sg:tags":[
        "downspouts",
        "gutter"
    ],
    "wof:name":"Gutter Guys",
    "wof:placetype":"venue"
},
  "geometry": {"coordinates":[-80.768975,34.778736],"type":"Point"}
}