{
  "type": "Feature",
  "properties": {
    "iso:country":"US",
    "sg:address":"305 N Hwy 52",
    "sg:city":"Moncks Corner",
    "sg:classifiers":[
        {
            "category":"Shopping",
            "subcategory":"Used Merchandise",
            "type":"Retail Goods"
        }
    ],
    "sg:phone":"+1 843 899 9100",
    "sg:postcode":"29461",
    "sg:province":"SC",
    "wof:name":"Jolin Enterprises",
    "wof:placetype":"venue"
},
  "geometry": {"coordinates":[-79.99260200000001,33.198001],"type":"Point"}
}