{
  "type": "Feature",
  "properties": {
    "addr:full":"2784 US Hwy 501 W Aynor SC 29511",
    "addr:housenumber":"2784",
    "addr:postcode":"29511",
    "addr:street":"Us Hwy 501 W",
    "iso:country":"US",
    "sg:address":"2784 US Hwy 501 W",
    "sg:city":"Aynor",
    "sg:classifiers":[
        {
            "category":"Restaurant",
            "type":"Food & Drink"
        }
    ],
    "sg:phone":"+1 843 358 0624",
    "sg:postcode":"29511",
    "sg:province":"SC",
    "wof:name":"Hardee's",
    "wof:placetype":"venue"
},
  "geometry": {"coordinates":[-79.204885,33.997232],"type":"Point"}
}