{
  "type": "Feature",
  "properties": {
    "addr:full":"1517 Ebenezer Rd Rock Hill SC 29732",
    "addr:housenumber":"1517",
    "addr:postcode":"29732",
    "addr:street":"Ebenezer Rd",
    "iso:country":"US",
    "sg:address":"1517 Ebenezer Rd",
    "sg:city":"Rock Hill",
    "sg:classifiers":[
        {
            "category":"Personal",
            "type":"Services"
        }
    ],
    "sg:phone":"+1 803 448 4344",
    "sg:postcode":"29732",
    "sg:province":"SC",
    "sg:tags":[
        "therapist",
        "massage"
    ],
    "wof:name":"Rock Hill Therapeutic Massage",
    "wof:placetype":"venue"
},
  "geometry": {"coordinates":[-81.043481,34.952441],"type":"Point"}
}