{
  "type": "Feature",
  "properties": {
    "addr:full":"916 W Ocean View Rd Charleston SC 29412",
    "addr:housenumber":"916",
    "addr:postcode":"29412",
    "addr:street":"W Ocean View Rd",
    "iso:country":"US",
    "sg:address":"916 W Ocean View Rd",
    "sg:city":"Charleston",
    "sg:classifiers":[
        {
            "category":"Autos & Motor Vehicles",
            "subcategory":"Fuel & Gas Station",
            "type":"Retail Goods"
        }
    ],
    "sg:phone":"+1 843 795 5185",
    "sg:postcode":"29412",
    "sg:province":"SC",
    "sg:tags":[
        "station"
    ],
    "wof:name":"Skippers Amoco",
    "wof:placetype":"venue"
},
  "geometry": {"coordinates":[-79.93107500000001,32.718249],"type":"Point"}
}