{
  "type": "Feature",
  "properties": {
    "iso:country":"US",
    "sg:address":"6646 Windyrun Ln",
    "sg:city":"York",
    "sg:classifiers":[
        {
            "category":"Retail",
            "subcategory":"Repair Shop",
            "type":"Services"
        }
    ],
    "sg:phone":"+1 803 329 2589",
    "sg:postcode":"29745",
    "sg:province":"SC",
    "sg:tags":[
        "lock",
        "locksmith"
    ],
    "wof:name":"Davis Locksmith Shop",
    "wof:placetype":"venue"
},
  "geometry": {"coordinates":[-81.11609199999999,35.006106],"type":"Point"}
}