{
  "type": "Feature",
  "properties": {
    "iso:country":"US",
    "sg:address":"3619 Devine St",
    "sg:city":"Columbia",
    "sg:classifiers":[
        {
            "category":"Health Services",
            "subcategory":"Doctor",
            "type":"Services"
        }
    ],
    "sg:phone":"+1 803 252 7147",
    "sg:postcode":"29205",
    "sg:province":"SC",
    "wof:name":"Hindersman John C Phys",
    "wof:placetype":"venue"
},
  "geometry": {"coordinates":[-80.989304,33.997101],"type":"Point"}
}