{
  "type": "Feature",
  "properties": {
    "iso:country":"US",
    "sg:address":"735 N Main St",
    "sg:city":"Sumter",
    "sg:classifiers":[
        {
            "category":"Personal",
            "subcategory":"Beauty Salon",
            "type":"Services"
        }
    ],
    "sg:phone":"+1 803 773 7945",
    "sg:postcode":"29150",
    "sg:province":"SC",
    "wof:name":"Paradise Beauty Salon",
    "wof:placetype":"venue"
},
  "geometry": {"coordinates":[-80.34324599999999,33.935184],"type":"Point"}
}