{
  "type": "Feature",
  "properties": {
    "iso:country":"US",
    "sg:address":"322 Longstreet Dr",
    "sg:city":"Greer",
    "sg:classifiers":[
        {
            "category":"Manufacturing",
            "subcategory":"Tools & Machinery",
            "type":"Manufacturing & Wholesale Goods"
        }
    ],
    "sg:phone":"+1 864 322 8449",
    "sg:postcode":"29650",
    "sg:province":"SC",
    "sg:tags":[
        "computer",
        "electronic",
        "mfg"
    ],
    "wof:name":"Gorilla Networks Inc",
    "wof:placetype":"venue"
},
  "geometry": {"coordinates":[-82.29297099999999,34.871159],"type":"Point"}
}