{
  "type": "Feature",
  "properties": {
    "addr:full":"919 E Liberty St York SC 29745",
    "addr:housenumber":"919",
    "addr:postcode":"29745",
    "addr:street":"E Liberty St",
    "iso:country":"US",
    "sg:address":"919 E Liberty St",
    "sg:city":"York",
    "sg:classifiers":[
        {
            "category":"Autos & Motor Vehicles",
            "subcategory":"Automobile Sales",
            "type":"Retail Goods"
        }
    ],
    "sg:phone":"+1 803 684 4271",
    "sg:postcode":"29745",
    "sg:province":"SC",
    "sg:tags":[
        "car",
        "dealer"
    ],
    "wof:name":"Dunlap-Johnson Chevrolet Co",
    "wof:placetype":"venue"
},
  "geometry": {"coordinates":[-81.213076,34.985603],"type":"Point"}
}