{
  "type": "Feature",
  "properties": {
    "addr:full":"705 N Anderson Rd Rock Hill SC 29730",
    "addr:housenumber":"705",
    "addr:postcode":"29730",
    "addr:street":"N Anderson Rd",
    "iso:country":"US",
    "sg:address":"705 N Anderson Rd",
    "sg:city":"Rock Hill",
    "sg:classifiers":[
        {
            "category":"Building & Trades",
            "subcategory":"Equipment Rental",
            "type":"Services"
        }
    ],
    "sg:phone":"+1 803 366 3141",
    "sg:postcode":"29730",
    "sg:province":"SC",
    "sg:website":"www.unitedrentals.com",
    "wof:name":"United Rentals",
    "wof:placetype":"venue"
},
  "geometry": {"coordinates":[-80.995716,34.957856],"type":"Point"}
}