{
  "type": "Feature",
  "properties": {
    "iso:country":"US",
    "sg:address":"120 Sunset Dr",
    "sg:city":"Chester",
    "sg:classifiers":[
        {
            "category":"Retail",
            "subcategory":"Repair Shop",
            "type":"Services"
        }
    ],
    "sg:phone":"+1 803 581 5008",
    "sg:postcode":"29706",
    "sg:province":"SC",
    "sg:tags":[
        "clocks",
        "parts"
    ],
    "wof:name":"Don's Clock Repair",
    "wof:placetype":"venue"
},
  "geometry": {"coordinates":[-81.20877299999999,34.693897],"type":"Point"}
}