{
  "type": "Feature",
  "properties": {
    "addr:full":"2500 Cashua Ferry Rd Darlington SC 29532",
    "addr:postcode":"2500;29532",
    "addr:street":"Cashua Ferry Rd",
    "iso:country":"US",
    "sg:address":"2500 Cashua Ferry Rd",
    "sg:city":"Darlington",
    "sg:classifiers":[
        {
            "category":"Food & Beverages",
            "subcategory":"Groceries & Convenience Stores",
            "type":"Retail Goods"
        }
    ],
    "sg:phone":"+1 843 395 2254",
    "sg:postcode":"29532",
    "sg:province":"SC",
    "wof:name":"Weatherford's Country Corner",
    "wof:placetype":"venue"
},
  "geometry": {"coordinates":[-79.751159,34.348237],"type":"Point"}
}