{
  "type": "Feature",
  "properties": {
    "iso:country":"US",
    "sg:address":"3332 Earle E Morris Jr Hwy",
    "sg:city":"Piedmont",
    "sg:classifiers":[
        {
            "category":"Real Estate",
            "subcategory":"Real Estate Agent",
            "type":"Services"
        }
    ],
    "sg:phone":"+1 864 269 7281",
    "sg:postcode":"29673",
    "sg:province":"SC",
    "sg:website":"www.barnesandtripp.com",
    "wof:name":"Barnes & Tripp Real Estate",
    "wof:placetype":"venue"
},
  "geometry": {"coordinates":[-82.474152,34.782103],"type":"Point"}
}