{
  "type": "Feature",
  "properties": {
    "addr:full":"812 Laurens St Camden SC 29020",
    "addr:housenumber":"812",
    "addr:postcode":"29020",
    "addr:street":"Laurens St",
    "iso:country":"US",
    "sg:address":"812 Laurens St",
    "sg:city":"Camden",
    "sg:classifiers":[
        {
            "category":"Wholesale",
            "subcategory":"Durable Goods & Equipment",
            "type":"Manufacturing & Wholesale Goods"
        }
    ],
    "sg:phone":"+1 803 432 0260",
    "sg:postcode":"29020",
    "sg:province":"SC",
    "sg:tags":[
        "merchandise"
    ],
    "wof:name":"TWC Art",
    "wof:placetype":"venue"
},
  "geometry": {"coordinates":[-80.61193900000001,34.251369],"type":"Point"}
}