{
  "type": "Feature",
  "properties": {
    "iso:country":"US",
    "sg:address":"4960 Fulton Pl",
    "sg:city":"Murrells Inlet",
    "sg:classifiers":[
        {
            "category":"Professional",
            "type":"Services"
        },
        {
            "category":"Wholesale",
            "subcategory":"Sporting Goods",
            "type":"Manufacturing & Wholesale Goods"
        }
    ],
    "sg:phone":"+1 843 602 4659",
    "sg:postcode":"29576",
    "sg:province":"SC",
    "sg:tags":[
        "establishment",
        "tub",
        "soft",
        "spa"
    ],
    "wof:name":"Soft Tubbin' Inc",
    "wof:placetype":"venue"
},
  "geometry": {"coordinates":[-79.06982000000001,33.551497],"type":"Point"}
}