{
  "type": "Feature",
  "properties": {
    "iso:country":"US",
    "sg:address":"1707 S Ocean Blvd",
    "sg:city":"Myrtle Beach",
    "sg:classifiers":[
        {
            "category":"Real Estate",
            "subcategory":"Real Estate Agent",
            "type":"Services"
        }
    ],
    "sg:phone":"+1 843 272 0484",
    "sg:postcode":"29577",
    "sg:province":"SC",
    "sg:tags":[
        "manager"
    ],
    "wof:name":"San A Bel Towers Maint Off",
    "wof:placetype":"venue"
},
  "geometry": {"coordinates":[-78.902408,33.672435],"type":"Point"}
}