{
  "type": "Feature",
  "properties": {
    "iso:country":"US",
    "sg:address":"1312 Williamston Rd",
    "sg:city":"Anderson",
    "sg:classifiers":[
        {
            "category":"Food & Beverages",
            "subcategory":"Groceries & Convenience Stores",
            "type":"Retail Goods"
        }
    ],
    "sg:phone":"+1 864 260 0202",
    "sg:postcode":"29621",
    "sg:province":"SC",
    "wof:name":"Ken Moorehead Oil Co",
    "wof:placetype":"venue"
},
  "geometry": {"coordinates":[-82.610024,34.504346],"type":"Point"}
}