{
  "type": "Feature",
  "properties": {
    "addr:full":"2461 Saint Phillips Church Rd Newberry SC 29108",
    "addr:housenumber":"2461",
    "addr:postcode":"29108",
    "addr:street":"Saint Phillips Church Rd",
    "iso:country":"US",
    "sg:address":"2461 Saint Phillips Church Rd",
    "sg:city":"Newberry",
    "sg:classifiers":[
        {
            "category":"Building & Trades",
            "subcategory":"Construction",
            "type":"Services"
        }
    ],
    "sg:phone":"+1 803 405 1411",
    "sg:postcode":"29108",
    "sg:province":"SC",
    "sg:tags":[
        "general",
        "contractor"
    ],
    "wof:name":"Mashburn Construction Co",
    "wof:placetype":"venue"
},
  "geometry": {"coordinates":[-81.507631,34.298634],"type":"Point"}
}