{
  "type": "Feature",
  "properties": {
    "iso:country":"US",
    "sg:address":"763 Travelers Blvd",
    "sg:city":"Summerville",
    "sg:classifiers":[
        {
            "category":"Manufacturing",
            "subcategory":"Printing",
            "type":"Manufacturing & Wholesale Goods"
        }
    ],
    "sg:phone":"+1 843 871 8495",
    "sg:postcode":"29485",
    "sg:province":"SC",
    "sg:tags":[
        "printer"
    ],
    "wof:name":"Ink Spot",
    "wof:placetype":"venue"
},
  "geometry": {"coordinates":[-80.168065,32.956095],"type":"Point"}
}