{
  "type": "Feature",
  "properties": {
    "iso:country":"US",
    "sg:address":"1840 New Zion Rd",
    "sg:city":"Lake City",
    "sg:classifiers":[
        {
            "category":"Organizations",
            "subcategory":"Religious Organization",
            "type":"Services"
        }
    ],
    "sg:phone":"+1 843 389 4376",
    "sg:postcode":"29560",
    "sg:province":"SC",
    "sg:tags":[
        "church"
    ],
    "wof:name":"Floyd's Chapel",
    "wof:placetype":"venue"
},
  "geometry": {"coordinates":[-79.882003,33.845426],"type":"Point"}
}