{
  "type": "Feature",
  "properties": {
    "addr:full":"1922 State Hwy 441 Sumter SC 29154",
    "addr:housenumber":"1922",
    "addr:postcode":"29154",
    "addr:street":"State Hwy 441",
    "iso:country":"US",
    "sg:address":"1922 State Hwy 441",
    "sg:city":"Sumter",
    "sg:classifiers":[
        {
            "category":"Shopping",
            "subcategory":"Clothing, Apparel, & Fashions",
            "type":"Retail Goods"
        }
    ],
    "sg:phone":"+1 803 499 9122",
    "sg:postcode":"29154",
    "sg:province":"SC",
    "sg:tags":[
        "tailor"
    ],
    "wof:name":"Silver Threads & Gold Needles",
    "wof:placetype":"venue"
},
  "geometry": {"coordinates":[-80.489875,33.973074],"type":"Point"}
}