{
  "type": "Feature",
  "properties": {
    "iso:country":"US",
    "sg:address":"1908 Pawnee St",
    "sg:city":"Aiken",
    "sg:classifiers":[
        {
            "category":"Professional",
            "subcategory":"Accounting & Tax Preparation",
            "type":"Services"
        }
    ],
    "sg:phone":"+1 803 649 6645",
    "sg:postcode":"29803",
    "sg:province":"SC",
    "sg:tags":[
        "return",
        "filing"
    ],
    "wof:name":"Smith Tax Advisory Group",
    "wof:placetype":"venue"
},
  "geometry": {"coordinates":[-81.721656,33.521088],"type":"Point"}
}