{
  "type": "Feature",
  "properties": {
    "iso:country":"US",
    "sg:address":"1280 Sam Rittenberg Blvd",
    "sg:city":"Charleston",
    "sg:classifiers":[
        {
            "category":"Restaurant",
            "type":"Food & Drink"
        }
    ],
    "sg:phone":"+1 843 763 8773",
    "sg:postcode":"29407",
    "sg:province":"SC",
    "wof:name":"Senor Tequila",
    "wof:placetype":"venue"
},
  "geometry": {"coordinates":[-79.996716,32.815165],"type":"Point"}
}