{
  "type": "Feature",
  "properties": {
    "iso:country":"US",
    "sg:address":"355 Woodruff Rd",
    "sg:city":"Greenville",
    "sg:classifiers":[
        {
            "category":"Professional",
            "subcategory":"Management & Consulting",
            "type":"Services"
        },
        {
            "category":"Structure",
            "subcategory":"Warehouse",
            "type":"Public Place"
        }
    ],
    "sg:phone":"+1 864 288 8595",
    "sg:postcode":"29607",
    "sg:province":"SC",
    "sg:tags":[
        "logistics",
        "warehouses-merchandise",
        "warehouses-public-commercial"
    ],
    "sg:website":"http://www.go2uti.com/",
    "wof:name":"UTi Contract Logistics & Distribution",
    "wof:placetype":"venue"
},
  "geometry": {"coordinates":[-82.34033599999999,34.833922],"type":"Point"}
}