{
  "type": "Feature",
  "properties": {
    "iso:country":"US",
    "sg:address":"2553 Saluda Rd",
    "sg:city":"Rock Hill",
    "sg:classifiers":[
        {
            "category":"Shopping",
            "subcategory":"Used Merchandise",
            "type":"Retail Goods"
        }
    ],
    "sg:phone":"+1 803 324 4077",
    "sg:postcode":"29730",
    "sg:province":"SC",
    "sg:tags":[
        "shop",
        "thrift"
    ],
    "sg:website":"www.restorationranch.com",
    "wof:name":"Restoration Thrift Shop",
    "wof:placetype":"venue"
},
  "geometry": {"coordinates":[-81.051315,34.880017],"type":"Point"}
}