{
  "type": "Feature",
  "properties": {
    "iso:country":"US",
    "sg:address":"37 New Orleans Rd",
    "sg:city":"Hilton Head Island",
    "sg:classifiers":[
        {
            "category":"Restaurant",
            "type":"Food & Drink"
        }
    ],
    "sg:menulink":"http://www.allmenus.com/sc/hilton-head-island/114128-hinoki/menu/",
    "sg:phone":"+1 843 785 9800",
    "sg:postcode":"29928",
    "sg:province":"SC",
    "sg:tags":[
        "japanese",
        "asian"
    ],
    "wof:name":"Hinoki",
    "wof:placetype":"venue"
},
  "geometry": {"coordinates":[-80.758438,32.155752],"type":"Point"}
}