{
  "type": "Feature",
  "properties": {
    "iso:country":"US",
    "sg:address":"1348 Griffin Mill Rd",
    "sg:city":"Easley",
    "sg:classifiers":[
        {
            "category":"Education",
            "subcategory":"School",
            "type":"Public Place"
        }
    ],
    "sg:phone":"+1 864 855 8150",
    "sg:postcode":"29640",
    "sg:province":"SC",
    "wof:name":"Pickens County School District",
    "wof:placetype":"venue"
},
  "geometry": {"coordinates":[-82.66758299999999,34.841786],"type":"Point"}
}