{
  "type": "Feature",
  "properties": {
    "iso:country":"US",
    "sg:address":"609 Sims Ave",
    "sg:city":"Columbia",
    "sg:classifiers":[
        {
            "category":"Professional",
            "subcategory":"Lawyer & Legal Services",
            "type":"Services"
        }
    ],
    "sg:phone":"+1 803 252 1500",
    "sg:postcode":"29205",
    "sg:province":"SC",
    "sg:website":"www.toddandjohnson.com",
    "wof:name":"Clark Dawn Atty",
    "wof:placetype":"venue"
},
  "geometry": {"coordinates":[-80.9991,33.997501],"type":"Point"}
}