{
  "type": "Feature",
  "properties": {
    "iso:country":"US",
    "sg:address":"455 E Frontage Rd",
    "sg:city":"Campobello",
    "sg:classifiers":[
        {
            "category":"Wholesale",
            "subcategory":"Medical Equipment & Supplies",
            "type":"Manufacturing & Wholesale Goods"
        }
    ],
    "sg:phone":"+1 864 457 5510",
    "sg:postcode":"29322",
    "sg:province":"SC",
    "sg:tags":[
        "datum",
        "imaging",
        "transport"
    ],
    "wof:name":"Health Care Imaging",
    "wof:placetype":"venue"
},
  "geometry": {"coordinates":[-82.108895,35.148225],"type":"Point"}
}