{
  "type": "Feature",
  "properties": {
    "iso:country":"US",
    "sg:address":"3902 Race Ct",
    "sg:city":"Mullins",
    "sg:classifiers":[
        {
            "category":"Retail",
            "subcategory":"Auto Repair",
            "type":"Services"
        }
    ],
    "sg:phone":"+1 843 464 8966",
    "sg:postcode":"29574",
    "sg:province":"SC",
    "sg:tags":[
        "transmission"
    ],
    "wof:name":"Huggins Auto Svc",
    "wof:placetype":"venue"
},
  "geometry": {"coordinates":[-79.23143399999999,34.222064],"type":"Point"}
}