{
  "type": "Feature",
  "properties": {
    "iso:country":"US",
    "sg:address":"108 W Harrison St",
    "sg:city":"Dillon",
    "sg:classifiers":[
        {
            "category":"Wholesale",
            "subcategory":"Construction Materials",
            "type":"Manufacturing & Wholesale Goods"
        }
    ],
    "sg:phone":"+1 843 774 5151",
    "sg:postcode":"29536",
    "sg:province":"SC",
    "sg:tags":[
        "timberland",
        "company",
        "timber"
    ],
    "wof:name":"Canal Wood Corporation-Dillon",
    "wof:placetype":"venue"
},
  "geometry": {"coordinates":[-79.372726,34.418813],"type":"Point"}
}