{
  "type": "Feature",
  "properties": {
    "addr:full":"1707 W Evans St Florence SC 29501",
    "addr:housenumber":"1707",
    "addr:postcode":"29501",
    "addr:street":"W Evans St",
    "iso:country":"US",
    "sg:address":"1707 W Evans St",
    "sg:city":"Florence",
    "sg:classifiers":[
        {
            "category":"Shopping",
            "subcategory":"Computers & Home Electronics",
            "type":"Retail Goods"
        }
    ],
    "sg:phone":"+1 843 629 1665",
    "sg:postcode":"29501",
    "sg:province":"SC",
    "sg:tags":[
        "car",
        "stereo"
    ],
    "wof:name":"Dr Dashboard of SC",
    "wof:placetype":"venue"
},
  "geometry": {"coordinates":[-79.799707,34.195714],"type":"Point"}
}