{
  "type": "Feature",
  "properties": {
    "iso:country":"US",
    "sg:address":"1261 Powdersville Rd",
    "sg:city":"Easley",
    "sg:classifiers":[
        {
            "category":"Manufacturing",
            "subcategory":"Chemicals & Compounds",
            "type":"Manufacturing & Wholesale Goods"
        }
    ],
    "sg:phone":"+1 864 855 4663",
    "sg:postcode":"29642",
    "sg:province":"SC",
    "wof:name":"Fran Tex Chemical",
    "wof:placetype":"venue"
},
  "geometry": {"coordinates":[-82.544482,34.809991],"type":"Point"}
}