{
  "type": "Feature",
  "properties": {
    "iso:country":"US",
    "sg:address":"1321 3rd Ave",
    "sg:city":"Conway",
    "sg:classifiers":[
        {
            "category":"Manufacturing",
            "subcategory":"Printing",
            "type":"Manufacturing & Wholesale Goods"
        }
    ],
    "sg:phone":"+1 843 488 2788",
    "sg:postcode":"29526",
    "sg:province":"SC",
    "sg:tags":[
        "engraver",
        "wood"
    ],
    "wof:name":"Landmark Engraving",
    "wof:placetype":"venue"
},
  "geometry": {"coordinates":[-79.049789,33.833328],"type":"Point"}
}