{
  "type": "Feature",
  "properties": {
    "addr:full":"2105 Old Spartanburg Rd Greer SC 29650",
    "addr:housenumber":"2105",
    "addr:postcode":"29650",
    "addr:street":"Old Spartanburg Rd",
    "iso:country":"US",
    "sg:address":"2105 Old Spartanburg Rd",
    "sg:city":"Greer",
    "sg:classifiers":[
        {
            "category":"Restaurant",
            "type":"Food & Drink"
        }
    ],
    "sg:phone":"+1 864 244 0950",
    "sg:postcode":"29650",
    "sg:province":"SC",
    "sg:tags":[
        "eating"
    ],
    "wof:name":"Mediterranean Espresso Cafe",
    "wof:placetype":"venue"
},
  "geometry": {"coordinates":[-82.29007799999999,34.892453],"type":"Point"}
}