{
  "type": "Feature",
  "properties": {
    "addr:full":"3249 S Highway 11 Westminster SC 29693",
    "addr:housenumber":"3249",
    "addr:postcode":"29693",
    "addr:street":"S Highway 11",
    "iso:country":"US",
    "sg:address":"3249 S Highway 11",
    "sg:city":"Westminster",
    "sg:classifiers":[
        {
            "category":"Manufacturing",
            "subcategory":"Glass & Minerals",
            "type":"Manufacturing & Wholesale Goods"
        },
        {
            "category":"Retail",
            "subcategory":"Auto Repair",
            "type":"Services"
        }
    ],
    "sg:phone":"+1 864 638 5588",
    "sg:postcode":"29693",
    "sg:province":"SC",
    "sg:tags":[
        "plate",
        "shape",
        "glass-wholesale",
        "window",
        "special",
        "circle",
        "windshield",
        "glass-auto",
        "manufacturer"
    ],
    "wof:name":"Reflections Auto Glass",
    "wof:placetype":"venue"
},
  "geometry": {"coordinates":[-83.052035,34.713268],"type":"Point"}
}