{
  "type": "Feature",
  "properties": {
    "iso:country":"US",
    "sg:address":"215 E Bay St",
    "sg:city":"Charleston",
    "sg:classifiers":[
        {
            "category":"Insurance",
            "subcategory":"Health Insurance",
            "type":"Services"
        }
    ],
    "sg:phone":"+1 843 805 3240",
    "sg:postcode":"29401",
    "sg:province":"SC",
    "sg:tags":[
        "carrier"
    ],
    "wof:name":"United Healthcare",
    "wof:placetype":"venue"
},
  "geometry": {"coordinates":[-79.927235,32.780558],"type":"Point"}
}