{
  "type": "Feature",
  "properties": {
    "addr:full":"323 S Cherry Rd Rock Hill SC 29732",
    "addr:housenumber":"323",
    "addr:postcode":"29732",
    "addr:street":"S Cherry Rd",
    "iso:country":"US",
    "sg:address":"323 S Cherry Rd",
    "sg:city":"Rock Hill",
    "sg:classifiers":[
        {
            "category":"Banks & Credit Unions",
            "subcategory":"Bank",
            "type":"Services"
        }
    ],
    "sg:phone":"+1 803 980 1066",
    "sg:postcode":"29732",
    "sg:province":"SC",
    "sg:tags":[
        "depository",
        "banking"
    ],
    "wof:name":"Security Fin Corp Spartanburg",
    "wof:placetype":"venue"
},
  "geometry": {"coordinates":[-81.042896,34.936629],"type":"Point"}
}