{
  "type": "Feature",
  "properties": {
    "addr:full":"402 Marina Dr Georgetown SC 29440",
    "addr:housenumber":"402",
    "addr:postcode":"29440",
    "addr:street":"Marina Dr",
    "iso:country":"US",
    "sg:address":"402 Marina Dr",
    "sg:city":"Georgetown",
    "sg:classifiers":[
        {
            "category":"Health Services",
            "subcategory":"Doctor",
            "type":"Services"
        }
    ],
    "sg:phone":"+1 843 527 1331",
    "sg:postcode":"29440",
    "sg:province":"SC",
    "sg:tags":[
        "physician",
        "surgeon"
    ],
    "wof:name":"Low Country Surgical Assoc",
    "wof:placetype":"venue"
},
  "geometry": {"coordinates":[-79.26932499999999,33.366639],"type":"Point"}
}