{
  "type": "Feature",
  "properties": {
    "iso:country":"US",
    "sg:address":"1701 Rosewood Dr",
    "sg:city":"Columbia",
    "sg:classifiers":[
        {
            "category":"Food & Beverages",
            "subcategory":"Groceries & Convenience Stores",
            "type":"Retail Goods"
        }
    ],
    "sg:phone":"+1 803 771 2497",
    "sg:postcode":"29205",
    "sg:province":"SC",
    "wof:name":"Fast Point Food Store",
    "wof:placetype":"venue"
},
  "geometry": {"coordinates":[-81.017403,33.9837],"type":"Point"}
}