{
  "type": "Feature",
  "properties": {
    "iso:country":"US",
    "sg:address":"231 Hwy 544",
    "sg:city":"Conway",
    "sg:classifiers":[
        {
            "category":"Freight",
            "type":"Transportation"
        }
    ],
    "sg:phone":"+1 843 347 5222",
    "sg:postcode":"29526",
    "sg:province":"SC",
    "sg:tags":[
        "trucking"
    ],
    "wof:name":"Sandlapper Contractor",
    "wof:placetype":"venue"
},
  "geometry": {"coordinates":[-79.018563,33.809688],"type":"Point"}
}