{
  "type": "Feature",
  "properties": {
    "iso:country":"US",
    "sg:address":"158 Cabana Rd",
    "sg:city":"Myrtle Beach",
    "sg:classifiers":[
        {
            "category":"Home & Garden",
            "subcategory":"Garden Supply",
            "type":"Retail Goods"
        }
    ],
    "sg:phone":"+1 843 361 1482",
    "sg:postcode":"29572",
    "sg:province":"SC",
    "sg:tags":[
        "sprinkler"
    ],
    "wof:name":"Atlantic Irrigation",
    "wof:placetype":"venue"
},
  "geometry": {"coordinates":[-78.743482,33.788227],"type":"Point"}
}