{
  "type": "Feature",
  "properties": {
    "iso:country":"US",
    "sg:address":"111 Green St",
    "sg:city":"Hartsville",
    "sg:classifiers":[
        {
            "category":"Wholesale",
            "subcategory":"Hardware",
            "type":"Manufacturing & Wholesale Goods"
        }
    ],
    "sg:phone":"+1 843 857 0869",
    "sg:postcode":"29550",
    "sg:province":"SC",
    "sg:tags":[
        "equipment",
        "locksmith",
        "supply"
    ],
    "wof:name":"Rob's Towing",
    "wof:placetype":"venue"
},
  "geometry": {"coordinates":[-80.095495,34.366918],"type":"Point"}
}