{
  "type": "Feature",
  "properties": {
    "iso:country":"US",
    "sg:address":"4552 Carriage Run Cir",
    "sg:city":"Murrells Inlet",
    "sg:classifiers":[
        {
            "category":"Shopping",
            "subcategory":"Bicycles & Sporting Goods",
            "type":"Retail Goods"
        }
    ],
    "sg:phone":"+1 919 606 0636",
    "sg:postcode":"29576",
    "sg:province":"SC",
    "wof:name":"Forever Sports",
    "wof:placetype":"venue"
},
  "geometry": {"coordinates":[-79.068151,33.551442],"type":"Point"}
}