{
  "type": "Feature",
  "properties": {
    "iso:country":"US",
    "sg:address":"517 Red Bank Rd",
    "sg:city":"Goose Creek",
    "sg:classifiers":[
        {
            "category":"Personal",
            "subcategory":"Beauty Salon",
            "type":"Services"
        }
    ],
    "sg:phone":"+1 843 863 0161",
    "sg:postcode":"29445",
    "sg:province":"SC",
    "wof:name":"Split Ends",
    "wof:placetype":"venue"
},
  "geometry": {"coordinates":[-80.031048,32.982544],"type":"Point"}
}