{
  "type": "Feature",
  "properties": {
    "iso:country":"US",
    "sg:address":"7228 Woodrow St",
    "sg:city":"Irmo",
    "sg:classifiers":[
        {
            "category":"Banks & Credit Unions",
            "subcategory":"Bank",
            "type":"Services"
        }
    ],
    "sg:phone":"+1 803 407 2120",
    "sg:postcode":"29063",
    "sg:province":"SC",
    "sg:tags":[
        "loan",
        "broker",
        "mortgage"
    ],
    "wof:name":"Allied Home Mrtg Capitl Corp",
    "wof:placetype":"venue"
},
  "geometry": {"coordinates":[-81.180595,34.081386],"type":"Point"}
}