{
  "type": "Feature",
  "properties": {
    "iso:country":"US",
    "sg:address":"300 W Mcintyre St",
    "sg:city":"Mullins",
    "sg:classifiers":[
        {
            "category":"Ice Cream",
            "type":"Food & Drink"
        }
    ],
    "sg:menulink":"http://www.allmenus.com/sc/mullins/243699-baskin-robbins/menu/",
    "sg:phone":"+1 843 464 4214",
    "sg:postcode":"29574",
    "sg:province":"SC",
    "sg:tags":[
        "american"
    ],
    "wof:name":"Baskin-Robbins",
    "wof:placetype":"venue"
},
  "geometry": {"coordinates":[-79.257733,34.199497],"type":"Point"}
}