{
  "type": "Feature",
  "properties": {
    "iso:country":"US",
    "sg:address":"1202 N Cashua Dr",
    "sg:city":"Florence",
    "sg:classifiers":[
        {
            "category":"Banks & Credit Unions",
            "subcategory":"Bank",
            "type":"Services"
        }
    ],
    "sg:phone":"+1 843 665 7303",
    "sg:postcode":"29501",
    "sg:province":"SC",
    "wof:name":"Nucor Federal Credit Union",
    "wof:placetype":"venue"
},
  "geometry": {"coordinates":[-79.796755,34.218154],"type":"Point"}
}