{
  "type": "Feature",
  "properties": {
    "iso:country":"US",
    "sg:address":"4706 Spruill Ave",
    "sg:city":"North Charleston",
    "sg:classifiers":[
        {
            "category":"Organizations",
            "subcategory":"Labor Organization",
            "type":"Services"
        }
    ],
    "sg:phone":"+1 843 744 5088",
    "sg:postcode":"29405",
    "sg:province":"SC",
    "wof:name":"MEBA",
    "wof:placetype":"venue"
},
  "geometry": {"coordinates":[-79.98009399999999,32.88007],"type":"Point"}
}