{
  "type": "Feature",
  "properties": {
    "iso:country":"US",
    "sg:address":"5 Cordes St",
    "sg:city":"Charleston",
    "sg:classifiers":[
        {
            "category":"Banks & Credit Unions",
            "subcategory":"Investment Brokerage",
            "type":"Services"
        }
    ],
    "sg:phone":"+1 843 853 2797",
    "sg:postcode":"29401",
    "sg:province":"SC",
    "sg:tags":[
        "security"
    ],
    "wof:name":"Raymond James",
    "wof:placetype":"venue"
},
  "geometry": {"coordinates":[-79.92693199999999,32.778009],"type":"Point"}
}