{
  "type": "Feature",
  "properties": {
    "addr:full":"306 Haviland Ave Greenville SC 29607",
    "addr:housenumber":"306",
    "addr:postcode":"29607",
    "addr:street":"Haviland Ave",
    "iso:country":"US",
    "sg:address":"306 Haviland Ave",
    "sg:city":"Greenville",
    "sg:classifiers":[
        {
            "category":"Organizations",
            "subcategory":"Religious Organization",
            "type":"Services"
        }
    ],
    "sg:phone":"+1 864 235 2213",
    "sg:postcode":"29607",
    "sg:province":"SC",
    "sg:tags":[
        "church"
    ],
    "wof:name":"Macedonia Holiness Church",
    "wof:placetype":"venue"
},
  "geometry": {"coordinates":[-82.380017,34.847201],"type":"Point"}
}