{
  "type": "Feature",
  "properties": {
    "iso:country":"US",
    "sg:address":"1425 W Market St",
    "sg:city":"Anderson",
    "sg:classifiers":[
        {
            "category":"Personal",
            "subcategory":"Beauty Salon",
            "type":"Services"
        }
    ],
    "sg:phone":"+1 864 375 1717",
    "sg:postcode":"29624",
    "sg:province":"SC",
    "wof:name":"Ebony",
    "wof:placetype":"venue"
},
  "geometry": {"coordinates":[-82.673289,34.500597],"type":"Point"}
}