{
  "type": "Feature",
  "properties": {
    "addr:full":"126 Odom Rd Easley SC 29642",
    "addr:housenumber":"126",
    "addr:postcode":"29642",
    "addr:street":"Odom Rd",
    "iso:country":"US",
    "sg:address":"126 Odom Rd",
    "sg:city":"Easley",
    "sg:classifiers":[
        {
            "category":"Home & Garden",
            "subcategory":"Furniture",
            "type":"Retail Goods"
        }
    ],
    "sg:phone":"+1 864 220 2744",
    "sg:postcode":"29642",
    "sg:province":"SC",
    "sg:tags":[
        "top",
        "counter"
    ],
    "wof:name":"Carolina Stone Works Inc",
    "wof:placetype":"venue"
},
  "geometry": {"coordinates":[-82.505066,34.830767],"type":"Point"}
}