{
  "type": "Feature",
  "properties": {
    "iso:country":"US",
    "sg:address":"233 N Main St",
    "sg:city":"Greenville",
    "sg:classifiers":[
        {
            "category":"Restaurant",
            "type":"Food & Drink"
        }
    ],
    "sg:menulink":"http://www.allmenus.com/sc/greenville/228900-jersey-mikes/menu/",
    "sg:phone":"+1 864 242 2223",
    "sg:postcode":"29601",
    "sg:province":"SC",
    "sg:tags":[
        "american",
        "sandwich"
    ],
    "wof:name":"Jersey Mike's",
    "wof:placetype":"venue"
},
  "geometry": {"coordinates":[-82.39793899999999,34.852983],"type":"Point"}
}