{
  "type": "Feature",
  "properties": {
    "iso:country":"US",
    "sg:address":"127 Main St N",
    "sg:city":"Bethune",
    "sg:classifiers":[
        {
            "category":"Wholesale",
            "subcategory":"Machinery & Supplies",
            "type":"Manufacturing & Wholesale Goods"
        }
    ],
    "sg:phone":"+1 843 334 6012",
    "sg:postcode":"29009",
    "sg:province":"SC",
    "sg:tags":[
        "salon",
        "beauty"
    ],
    "wof:name":"Swan Elegence",
    "wof:placetype":"venue"
},
  "geometry": {"coordinates":[-80.349127,34.415757],"type":"Point"}
}