{
  "type": "Feature",
  "properties": {
    "iso:country":"US",
    "sg:address":"958 Honda Way",
    "sg:city":"Timmonsville",
    "sg:classifiers":[
        {
            "category":"Shopping",
            "subcategory":"Computers & Home Electronics",
            "type":"Retail Goods"
        }
    ],
    "sg:phone":"+1 843 346 3026",
    "sg:postcode":"29161",
    "sg:province":"SC",
    "sg:tags":[
        "equipment",
        "dealer"
    ],
    "wof:name":"Meltronics Computer Systems",
    "wof:placetype":"venue"
},
  "geometry": {"coordinates":[-79.909514,34.110577],"type":"Point"}
}