{
  "type": "Feature",
  "properties": {
    "addr:full":"8320 Delhi Rd Charleston SC 29406",
    "addr:postcode":"8320;29406",
    "addr:street":"Delhi Rd",
    "iso:country":"US",
    "sg:address":"8320 Delhi Rd",
    "sg:city":"Charleston",
    "sg:classifiers":[
        {
            "category":"Restaurant",
            "type":"Food & Drink"
        }
    ],
    "sg:phone":"+1 843 824 9280",
    "sg:postcode":"29406",
    "sg:province":"SC",
    "sg:tags":[
        "eating"
    ],
    "wof:name":"Hunngry Mikes Catering",
    "wof:placetype":"venue"
},
  "geometry": {"coordinates":[-80.065684,32.956689],"type":"Point"}
}