{
  "type": "Feature",
  "properties": {
    "iso:country":"US",
    "sg:address":"135 W Main St",
    "sg:city":"Pickens",
    "sg:classifiers":[
        {
            "category":"Personal",
            "subcategory":"Beauty Salon",
            "type":"Services"
        }
    ],
    "sg:phone":"+1 864 878 1403",
    "sg:postcode":"29671",
    "sg:province":"SC",
    "wof:name":"Southern Styles Salon",
    "wof:placetype":"venue"
},
  "geometry": {"coordinates":[-82.708133,34.88348],"type":"Point"}
}