{
  "type": "Feature",
  "properties": {
    "iso:country":"US",
    "sg:address":"148 Canterfield Rd",
    "sg:city":"Columbia",
    "sg:classifiers":[
        {
            "category":"Arts & Performance",
            "subcategory":"Theater",
            "type":"Entertainment"
        }
    ],
    "sg:phone":"+1 803 749 9443",
    "sg:postcode":"29212",
    "sg:province":"SC",
    "sg:tags":[
        "musician"
    ],
    "wof:name":"Sandlapper Singers",
    "wof:placetype":"venue"
},
  "geometry": {"coordinates":[-81.19601400000001,34.068814],"type":"Point"}
}