{
  "type": "Feature",
  "properties": {
    "addr:full":"212 N 5th St Hartsville SC 29550",
    "addr:housenumber":"212",
    "addr:postcode":"29550",
    "addr:street":"N 5Th St",
    "iso:country":"US",
    "sg:address":"212 N 5th St",
    "sg:city":"Hartsville",
    "sg:classifiers":[
        {
            "category":"Recreation",
            "type":"Entertainment"
        }
    ],
    "sg:phone":"+1 843 332 5721",
    "sg:postcode":"29550",
    "sg:province":"SC",
    "sg:tags":[
        "hall",
        "auditorium"
    ],
    "wof:name":"Hartsville Community Ctr",
    "wof:placetype":"venue"
},
  "geometry": {"coordinates":[-80.07521199999999,34.377528],"type":"Point"}
}