{
  "type": "Feature",
  "properties": {
    "iso:country":"US",
    "sg:address":"101 N Main St",
    "sg:city":"Lancaster",
    "sg:classifiers":[
        {
            "category":"Government",
            "subcategory":"Office",
            "type":"Public Place"
        }
    ],
    "sg:phone":"+1 803 285 1969",
    "sg:postcode":"29720",
    "sg:province":"SC",
    "sg:tags":[
        "county",
        "planning",
        "dev"
    ],
    "sg:website":"www.lancastercounty.net",
    "wof:name":"Lancaster Building & Zoning",
    "wof:placetype":"venue"
},
  "geometry": {"coordinates":[-80.77189199999999,34.722359],"type":"Point"}
}