{
  "type": "Feature",
  "properties": {
    "iso:country":"US",
    "sg:address":"3070 Pleasant Rd",
    "sg:city":"Fort Mill",
    "sg:classifiers":[
        {
            "category":"Social Services",
            "subcategory":"Child Care",
            "type":"Services"
        }
    ],
    "sg:phone":"+1 803 548 3131",
    "sg:postcode":"29708",
    "sg:province":"SC",
    "wof:name":"Pleasant Road Child Dvlpmt Ctr",
    "wof:placetype":"venue"
},
  "geometry": {"coordinates":[-80.95976,35.067496],"type":"Point"}
}