{
  "type": "Feature",
  "properties": {
    "addr:full":"9 Bobwhite Ln Hilton Head Isle SC 29928",
    "addr:housenumber":"9",
    "addr:postcode":"29928",
    "addr:street":"Bobwhite Ln",
    "iso:country":"US",
    "sg:address":"9 Bobwhite Ln",
    "sg:city":"Hilton Head Isle",
    "sg:classifiers":[
        {
            "category":"Building & Trades",
            "subcategory":"Construction",
            "type":"Services"
        }
    ],
    "sg:phone":"+1 843 785 7333",
    "sg:postcode":"29928",
    "sg:province":"SC",
    "sg:tags":[
        "coping",
        "plastering",
        "tiling",
        "pool",
        "swimming"
    ],
    "wof:name":"Coral Reef Pool Co Inc",
    "wof:placetype":"venue"
},
  "geometry": {"coordinates":[-80.779309,32.167286],"type":"Point"}
}