{
  "type": "Feature",
  "properties": {
    "iso:country":"US",
    "sg:address":"15990 US Hwy 221",
    "sg:city":"Enoree",
    "sg:classifiers":[
        {
            "category":"Building & Trades",
            "subcategory":"Cleaning & Sanitation",
            "type":"Services"
        }
    ],
    "sg:phone":"+1 864 969 9585",
    "sg:postcode":"29335",
    "sg:province":"SC",
    "sg:tags":[
        "janitor"
    ],
    "wof:name":"Diversco",
    "wof:placetype":"venue"
},
  "geometry": {"coordinates":[-81.96422099999999,34.650747],"type":"Point"}
}