{
  "type": "Feature",
  "properties": {
    "iso:country":"US",
    "sg:address":"296 Meeting St",
    "sg:city":"Charleston",
    "sg:classifiers":[
        {
            "category":"Real Estate",
            "subcategory":"Architect",
            "type":"Services"
        }
    ],
    "sg:phone":"+1 843 577 3431",
    "sg:postcode":"29401",
    "sg:province":"SC",
    "sg:website":"www.datatrustllc.com",
    "wof:name":"Riesberg Architects",
    "wof:placetype":"venue"
},
  "geometry": {"coordinates":[-79.933399,32.785492],"type":"Point"}
}