{
  "type": "Feature",
  "properties": {
    "iso:country":"US",
    "sg:address":"112 Chaunticleer Rd",
    "sg:city":"Columbia",
    "sg:classifiers":[
        {
            "category":"Restaurant",
            "type":"Food & Drink"
        }
    ],
    "sg:phone":"+1 803 788 6874",
    "sg:postcode":"29223",
    "sg:province":"SC",
    "sg:tags":[
        "eating"
    ],
    "wof:name":"Coney John",
    "wof:placetype":"venue"
},
  "geometry": {"coordinates":[-80.927222,34.121563],"type":"Point"}
}