{
  "type": "Feature",
  "properties": {
    "iso:country":"US",
    "sg:address":"3003 Keowee School Rd",
    "sg:city":"Seneca",
    "sg:classifiers":[
        {
            "category":"Building & Trades",
            "subcategory":"Construction",
            "type":"Services"
        }
    ],
    "sg:phone":"+1 864 882 1204",
    "sg:postcode":"29672",
    "sg:province":"SC",
    "sg:tags":[
        "contractor"
    ],
    "wof:name":"Southridge",
    "wof:placetype":"venue"
},
  "geometry": {"coordinates":[-82.954802,34.758353],"type":"Point"}
}