{
  "type": "Feature",
  "properties": {
    "addr:full":"160 McDowell Rd Inman SC 29349",
    "addr:housenumber":"160",
    "addr:postcode":"29349",
    "addr:street":"Mcdowell Rd",
    "iso:country":"US",
    "sg:address":"160 McDowell Rd",
    "sg:city":"Inman",
    "sg:classifiers":[
        {
            "category":"Retail",
            "subcategory":"Auto Repair",
            "type":"Services"
        }
    ],
    "sg:phone":"+1 864 578 1222",
    "sg:postcode":"29349",
    "sg:province":"SC",
    "sg:tags":[
        "automobile",
        "customizing"
    ],
    "wof:name":"HODGES Restoration",
    "wof:placetype":"venue"
},
  "geometry": {"coordinates":[-82.02525,35.078168],"type":"Point"}
}