{
  "type": "Feature",
  "properties": {
    "iso:country":"US",
    "sg:address":"6941 Trenholm Rd",
    "sg:city":"Columbia",
    "sg:classifiers":[
        {
            "category":"Professional",
            "subcategory":"Accounting & Tax Preparation",
            "type":"Services"
        }
    ],
    "sg:phone":"+1 803 787 3185",
    "sg:postcode":"29206",
    "sg:province":"SC",
    "sg:tags":[
        "accountant"
    ],
    "wof:name":"Gary W Suggs CPA",
    "wof:placetype":"venue"
},
  "geometry": {"coordinates":[-80.956953,34.061372],"type":"Point"}
}