{
  "type": "Feature",
  "properties": {
    "iso:country":"US",
    "sg:address":"129 Francis Marion Rd",
    "sg:city":"Florence",
    "sg:classifiers":[
        {
            "category":"Restaurant",
            "type":"Food & Drink"
        }
    ],
    "sg:phone":"+1 843 669 2367",
    "sg:postcode":"29506",
    "sg:province":"SC",
    "sg:tags":[
        "eating"
    ],
    "wof:name":"Wendys",
    "wof:placetype":"venue"
},
  "geometry": {"coordinates":[-79.655422,34.195975],"type":"Point"}
}