{
  "type": "Feature",
  "properties": {
    "addr:full":"2017 Creekwood Dr York SC 29745",
    "addr:housenumber":"2017",
    "addr:postcode":"29745",
    "addr:street":"Creekwood Dr",
    "iso:country":"US",
    "sg:address":"2017 Creekwood Dr",
    "sg:city":"York",
    "sg:classifiers":[
        {
            "category":"Banks & Credit Unions",
            "subcategory":"Financial Services",
            "type":"Services"
        }
    ],
    "sg:phone":"+1 803 684 6736",
    "sg:postcode":"29745",
    "sg:province":"SC",
    "sg:tags":[
        "trust",
        "management"
    ],
    "wof:name":"Sherer Family LLC of Caro",
    "wof:placetype":"venue"
},
  "geometry": {"coordinates":[-81.218104,34.96787],"type":"Point"}
}