{
  "type": "Feature",
  "properties": {
    "iso:country":"US",
    "sg:address":"1022 Pine Logging Rd",
    "sg:city":"Aiken",
    "sg:classifiers":[
        {
            "category":"Personal",
            "subcategory":"Beauty Salon",
            "type":"Services"
        }
    ],
    "sg:phone":"+1 803 648 5761",
    "sg:postcode":"29803",
    "sg:province":"SC",
    "wof:name":"Beauty Shop",
    "wof:placetype":"venue"
},
  "geometry": {"coordinates":[-81.737709,33.516239],"type":"Point"}
}