{
  "type": "Feature",
  "properties": {
    "iso:country":"US",
    "sg:address":"128 W Hamilton St",
    "sg:city":"Summerville",
    "sg:classifiers":[
        {
            "category":"Organizations",
            "subcategory":"Religious Organization",
            "type":"Services"
        }
    ],
    "sg:phone":"+1 843 871 6848",
    "sg:postcode":"29485",
    "sg:province":"SC",
    "sg:tags":[
        "church"
    ],
    "wof:name":"Church-God Friendship Insprtnl",
    "wof:placetype":"venue"
},
  "geometry": {"coordinates":[-80.15646,33.008899],"type":"Point"}
}