{
  "type": "Feature",
  "properties": {
    "iso:country":"US",
    "sg:address":"1205 N Main St",
    "sg:city":"Summerville",
    "sg:classifiers":[
        {
            "category":"Restaurant",
            "type":"Food & Drink"
        }
    ],
    "sg:menulink":"http://www.allmenus.com/sc/goose-creek-hanahan/84300-papa-johns-pizza/menu/",
    "sg:phone":"+1 843 871 1663",
    "sg:postcode":"29483",
    "sg:province":"SC",
    "sg:tags":[
        "american",
        "pizza"
    ],
    "wof:name":"Papa John's Pizza",
    "wof:placetype":"venue"
},
  "geometry": {"coordinates":[-80.15927499999999,33.034371],"type":"Point"}
}