{
  "type": "Feature",
  "properties": {
    "iso:country":"US",
    "sg:address":"3544 Humphrey St",
    "sg:city":"Columbia",
    "sg:classifiers":[
        {
            "category":"Organizations",
            "subcategory":"Religious Organization",
            "type":"Services"
        }
    ],
    "sg:phone":"+1 803 714 7754",
    "sg:postcode":"29223",
    "sg:province":"SC",
    "sg:tags":[
        "church"
    ],
    "wof:name":"Imani Temple",
    "wof:placetype":"venue"
},
  "geometry": {"coordinates":[-80.973401,34.060213],"type":"Point"}
}