{
  "type": "Feature",
  "properties": {
    "addr:full":"301 University Ridge Greenville SC 29601",
    "addr:housenumber":"301",
    "addr:postcode":"29601",
    "addr:street":"University Ridge",
    "iso:country":"US",
    "sg:address":"301 University Ridge",
    "sg:city":"Greenville",
    "sg:classifiers":[
        {
            "category":"Banks & Credit Unions",
            "subcategory":"Bank",
            "type":"Services"
        }
    ],
    "sg:phone":"+1 864 467 7149",
    "sg:postcode":"29601",
    "sg:province":"SC",
    "wof:name":"Greenville County Credit Union",
    "wof:placetype":"venue"
},
  "geometry": {"coordinates":[-82.39975699999999,34.839943],"type":"Point"}
}