{
  "type": "Feature",
  "properties": {
    "addr:full":"780 Yaupon Dr Charleston SC 29492",
    "addr:housenumber":"780",
    "addr:postcode":"29492",
    "addr:street":"Yaupon Dr",
    "iso:country":"US",
    "sg:address":"780 Yaupon Dr",
    "sg:city":"Charleston",
    "sg:classifiers":[
        {
            "category":"Restaurant",
            "type":"Food & Drink"
        }
    ],
    "sg:phone":"+1 843 881 5041",
    "sg:postcode":"29492",
    "sg:province":"SC",
    "wof:name":"Wando Grill",
    "wof:placetype":"venue"
},
  "geometry": {"coordinates":[-79.81283000000001,32.933829],"type":"Point"}
}