{
  "type": "Feature",
  "properties": {
    "iso:country":"US",
    "sg:address":"727 Cooper Rd",
    "sg:city":"Piedmont",
    "sg:classifiers":[
        {
            "category":"Building & Trades",
            "subcategory":"Landscaping Services",
            "type":"Services"
        }
    ],
    "sg:phone":"+1 864 269 2025",
    "sg:postcode":"29673",
    "sg:province":"SC",
    "sg:website":"www.ldginc.com",
    "wof:name":"Landscape Development Group",
    "wof:placetype":"venue"
},
  "geometry": {"coordinates":[-82.47059299999999,34.765927],"type":"Point"}
}