{
  "type": "Feature",
  "properties": {
    "addr:full":"2810 Ashley Phosphate Rd North Charleston SC 29418",
    "addr:housenumber":"2810",
    "addr:postcode":"29418",
    "addr:street":"Ashley Phosphate Rd",
    "iso:country":"US",
    "sg:address":"2810 Ashley Phosphate Rd",
    "sg:city":"North Charleston",
    "sg:classifiers":[
        {
            "category":"Food & Beverages",
            "subcategory":"Groceries & Convenience Stores",
            "type":"Retail Goods"
        }
    ],
    "sg:phone":"+1 843 797 3128",
    "sg:postcode":"29418",
    "sg:province":"SC",
    "sg:tags":[
        "grocer"
    ],
    "wof:name":"Supermarket Jalisco",
    "wof:placetype":"venue"
},
  "geometry": {"coordinates":[-80.055633,32.93223],"type":"Point"}
}