{
  "type": "Feature",
  "properties": {
    "iso:country":"US",
    "sg:address":"1541 W Floyd Baker Blvd",
    "sg:city":"Gaffney",
    "sg:classifiers":[
        {
            "category":"Restaurant",
            "type":"Food & Drink"
        }
    ],
    "sg:phone":"+1 864 487 7350",
    "sg:postcode":"29341",
    "sg:province":"SC",
    "wof:name":"Sagebrush Steakhouse & Saloon",
    "wof:placetype":"venue"
},
  "geometry": {"coordinates":[-81.66268599999999,35.090781],"type":"Point"}
}