{
  "type": "Feature",
  "properties": {
    "iso:country":"US",
    "sg:address":"912 S Cashua Dr",
    "sg:city":"Florence",
    "sg:classifiers":[
        {
            "category":"Professional",
            "subcategory":"Business Services",
            "type":"Services"
        }
    ],
    "sg:phone":"+1 843 665 6755",
    "sg:postcode":"29501",
    "sg:province":"SC",
    "sg:tags":[
        "embroidery"
    ],
    "wof:name":"Stitch It & More",
    "wof:placetype":"venue"
},
  "geometry": {"coordinates":[-79.814965,34.173115],"type":"Point"}
}