{
  "type": "Feature",
  "properties": {
    "addr:full":"101 Pumpkin Ln Sumter SC 29150",
    "addr:housenumber":"101",
    "addr:postcode":"29150",
    "addr:street":"Pumpkin Ln",
    "iso:country":"US",
    "sg:address":"101 Pumpkin Ln",
    "sg:city":"Sumter",
    "sg:classifiers":[
        {
            "category":"Professional",
            "type":"Services"
        }
    ],
    "sg:phone":"+1 803 494 3028",
    "sg:postcode":"29150",
    "sg:province":"SC",
    "sg:tags":[
        "bones"
    ],
    "wof:name":"J B Richburg Inc",
    "wof:placetype":"venue"
},
  "geometry": {"coordinates":[-80.38863600000001,33.917743],"type":"Point"}
}