{
  "type": "Feature",
  "properties": {
    "addr:full":"117 Mulberry St Inman SC 29349",
    "addr:housenumber":"117",
    "addr:postcode":"29349",
    "addr:street":"Mulberry St",
    "iso:country":"US",
    "sg:address":"117 Mulberry St",
    "sg:city":"Inman",
    "sg:classifiers":[
        {
            "category":"Manufacturing",
            "subcategory":"Tools & Machinery",
            "type":"Manufacturing & Wholesale Goods"
        }
    ],
    "sg:phone":"+1 864 578 9297",
    "sg:postcode":"29349",
    "sg:province":"SC",
    "sg:tags":[
        "machine",
        "mfg"
    ],
    "wof:name":"Lipe Automation",
    "wof:placetype":"venue"
},
  "geometry": {"coordinates":[-82.03185999999999,35.030083],"type":"Point"}
}