{
  "type": "Feature",
  "properties": {
    "iso:country":"US",
    "sg:address":"1001 N Main St",
    "sg:city":"Mullins",
    "sg:classifiers":[
        {
            "category":"Travel",
            "subcategory":"Hotels & Motels",
            "type":"Entertainment"
        }
    ],
    "sg:phone":"+1 843 464 7894",
    "sg:postcode":"29574",
    "sg:province":"SC",
    "wof:name":"Martin's Motel & Restaurant",
    "wof:placetype":"venue"
},
  "geometry": {"coordinates":[-79.258218,34.220691],"type":"Point"}
}