{
  "type": "Feature",
  "properties": {
    "iso:country":"US",
    "sg:address":"105 Forest Ridge Ct",
    "sg:city":"Goose Creek",
    "sg:classifiers":[
        {
            "category":"Banks & Credit Unions",
            "subcategory":"Financial Services",
            "type":"Services"
        }
    ],
    "sg:phone":"+1 843 572 7453",
    "sg:postcode":"29445",
    "sg:province":"SC",
    "sg:tags":[
        "trust",
        "investment",
        "real estate"
    ],
    "wof:name":"J L Baird LLC",
    "wof:placetype":"venue"
},
  "geometry": {"coordinates":[-80.060849,32.999291],"type":"Point"}
}