{
  "type": "Feature",
  "properties": {
    "iso:country":"US",
    "sg:address":"1112 Cornelia Rd",
    "sg:city":"Anderson",
    "sg:classifiers":[
        {
            "category":"Health Services",
            "subcategory":"Doctor",
            "type":"Services"
        }
    ],
    "sg:phone":"+1 864 225 5611",
    "sg:postcode":"29621",
    "sg:province":"SC",
    "sg:tags":[
        "dentist"
    ],
    "wof:name":"Todd Hamilton DDS",
    "wof:placetype":"venue"
},
  "geometry": {"coordinates":[-82.62921799999999,34.527498],"type":"Point"}
}