{
  "type": "Feature",
  "properties": {
    "addr:full":"2001 E Blackstock Rd Roebuck SC 29376",
    "addr:housenumber":"2001",
    "addr:postcode":"29376",
    "addr:street":"E Blackstock Rd",
    "iso:country":"US",
    "sg:address":"2001 E Blackstock Rd",
    "sg:city":"Roebuck",
    "sg:classifiers":[
        {
            "category":"Wholesale",
            "subcategory":"Machinery & Supplies",
            "type":"Manufacturing & Wholesale Goods"
        }
    ],
    "sg:phone":"+1 864 587 6745",
    "sg:postcode":"29376",
    "sg:province":"SC",
    "sg:tags":[
        "equipment",
        "plastic",
        "industry",
        "industrial",
        "mfg"
    ],
    "wof:name":"Plastic Machinery Controls",
    "wof:placetype":"venue"
},
  "geometry": {"coordinates":[-81.96614700000001,34.879342],"type":"Point"}
}