{
  "type": "Feature",
  "properties": {
    "iso:country":"US",
    "sg:address":"1293 Broad St",
    "sg:city":"Sumter",
    "sg:classifiers":[
        {
            "category":"Retail",
            "subcategory":"Auto Repair",
            "type":"Services"
        }
    ],
    "sg:phone":"+1 803 469 8077",
    "sg:postcode":"29150",
    "sg:province":"SC",
    "sg:tags":[
        "repairing",
        "automobile"
    ],
    "wof:name":"Wells Automotive & Repair",
    "wof:placetype":"venue"
},
  "geometry": {"coordinates":[-80.389461,33.956925],"type":"Point"}
}