{
  "type": "Feature",
  "properties": {
    "iso:country":"US",
    "sg:address":"306 14th Ave N",
    "sg:city":"Myrtle Beach",
    "sg:classifiers":[
        {
            "category":"Travel",
            "subcategory":"Hotels & Motels",
            "type":"Entertainment"
        }
    ],
    "sg:phone":"+1 843 448 6714",
    "sg:postcode":"29577",
    "sg:province":"SC",
    "wof:name":"Lamplighter Inn",
    "wof:placetype":"venue"
},
  "geometry": {"coordinates":[-78.876622,33.696546],"type":"Point"}
}