{
  "type": "Feature",
  "properties": {
    "addr:full":"801 S Howard Ave Landrum SC 29356",
    "addr:housenumber":"801",
    "addr:postcode":"29356",
    "addr:street":"S Howard Ave",
    "iso:country":"US",
    "sg:address":"801 S Howard Ave",
    "sg:city":"Landrum",
    "sg:classifiers":[
        {
            "category":"Retail",
            "subcategory":"Auto Repair",
            "type":"Services"
        }
    ],
    "sg:phone":"+1 864 457 4026",
    "sg:postcode":"29356",
    "sg:province":"SC",
    "sg:tags":[
        "body",
        "automobile",
        "painting"
    ],
    "wof:name":"S & J Frame Alignment",
    "wof:placetype":"venue"
},
  "geometry": {"coordinates":[-82.18246000000001,35.164521],"type":"Point"}
}