{
  "type": "Feature",
  "properties": {
    "iso:country":"US",
    "sg:address":"2280 Sandy Bay Rd",
    "sg:city":"Kingstree",
    "sg:classifiers":[
        {
            "category":"Organizations",
            "subcategory":"Professional Association",
            "type":"Services"
        }
    ],
    "sg:phone":"+1 843 354 6507",
    "sg:postcode":"29556",
    "sg:province":"SC",
    "wof:name":"Loyal Order Of Moose",
    "wof:placetype":"venue"
},
  "geometry": {"coordinates":[-79.837431,33.689581],"type":"Point"}
}