{
  "type": "Feature",
  "properties": {
    "iso:country":"US",
    "sg:address":"104 E Main St",
    "sg:city":"Westminster",
    "sg:classifiers":[
        {
            "category":"Personal",
            "subcategory":"Beauty Salon",
            "type":"Services"
        }
    ],
    "sg:phone":"+1 864 647 2793",
    "sg:postcode":"29693",
    "sg:province":"SC",
    "wof:name":"LA Donna Beauty Salon",
    "wof:placetype":"venue"
},
  "geometry": {"coordinates":[-83.097031,34.666048],"type":"Point"}
}