{
  "type": "Feature",
  "properties": {
    "iso:country":"US",
    "sg:address":"12059 US Hwy 17 Byp",
    "sg:city":"Murrells Inlet",
    "sg:classifiers":[
        {
            "category":"Home & Garden",
            "subcategory":"Furniture",
            "type":"Retail Goods"
        }
    ],
    "sg:phone":"+1 843 357 9626",
    "sg:postcode":"29576",
    "sg:province":"SC",
    "sg:tags":[
        "mattress"
    ],
    "wof:name":"Bedding World Inc",
    "wof:placetype":"venue"
},
  "geometry": {"coordinates":[-79.029734,33.573332],"type":"Point"}
}