{
  "type": "Feature",
  "properties": {
    "iso:country":"US",
    "sg:address":"12 Charleston Hwy",
    "sg:city":"Yemassee",
    "sg:classifiers":[
        {
            "category":"Restaurant",
            "type":"Food & Drink"
        }
    ],
    "sg:phone":"+1 843 846 4493",
    "sg:postcode":"29945",
    "sg:province":"SC",
    "wof:name":"Garden's Corner Seafood Market",
    "wof:placetype":"venue"
},
  "geometry": {"coordinates":[-80.758829,32.601931],"type":"Point"}
}