{
  "type": "Feature",
  "properties": {
    "iso:country":"US",
    "sg:address":"121 Village Dr",
    "sg:city":"Greer",
    "sg:classifiers":[
        {
            "category":"Utilities",
            "subcategory":"Electric",
            "type":"Services"
        }
    ],
    "sg:phone":"+1 864 877 9632",
    "sg:postcode":"29651",
    "sg:province":"SC",
    "sg:tags":[
        "supplier",
        "to",
        "participating",
        "power"
    ],
    "wof:name":"PMPA",
    "wof:placetype":"venue"
},
  "geometry": {"coordinates":[-82.23476599999999,34.950754],"type":"Point"}
}