{
  "type": "Feature",
  "properties": {
    "addr:full":"1300 Cedar Creek Rd Blythewood SC 29016",
    "addr:housenumber":"1300",
    "addr:postcode":"29016",
    "addr:street":"Cedar Creek Rd",
    "iso:country":"US",
    "sg:address":"1300 Cedar Creek Rd",
    "sg:city":"Blythewood",
    "sg:classifiers":[
        {
            "category":"Building & Trades",
            "subcategory":"Construction",
            "type":"Services"
        }
    ],
    "sg:phone":"+1 803 714 7115",
    "sg:postcode":"29016",
    "sg:province":"SC",
    "sg:tags":[
        "carpentry",
        "contractor"
    ],
    "wof:name":"Dmt Company Inc",
    "wof:placetype":"venue"
},
  "geometry": {"coordinates":[-81.114299,34.189389],"type":"Point"}
}