{
  "type": "Feature",
  "properties": {
    "iso:country":"US",
    "sg:address":"1624 Broad River Rd",
    "sg:city":"Columbia",
    "sg:classifiers":[
        {
            "category":"Banks & Credit Unions",
            "subcategory":"Bank",
            "type":"Services"
        }
    ],
    "sg:phone":"+1 803 216 8646",
    "sg:postcode":"29210",
    "sg:province":"SC",
    "sg:tags":[
        "cashing",
        "check"
    ],
    "wof:name":"A 1 Instant Check Advance",
    "wof:placetype":"venue"
},
  "geometry": {"coordinates":[-81.087788,34.03271],"type":"Point"}
}