{
  "type": "Feature",
  "properties": {
    "iso:country":"US",
    "sg:address":"625 Wallace Rd",
    "sg:city":"Bennettsville",
    "sg:classifiers":[
        {
            "category":"Government",
            "subcategory":"Office",
            "type":"Public Place"
        }
    ],
    "sg:phone":"+1 843 479 2442",
    "sg:postcode":"29512",
    "sg:province":"SC",
    "sg:tags":[
        "village"
    ],
    "wof:name":"Bennettsville Water Plant",
    "wof:placetype":"venue"
},
  "geometry": {"coordinates":[-79.669197,34.642189],"type":"Point"}
}