{
  "type": "Feature",
  "properties": {
    "iso:country":"US",
    "sg:address":"242 Howe Hall Rd",
    "sg:city":"Goose Creek",
    "sg:classifiers":[
        {
            "category":"Building & Trades",
            "subcategory":"Construction",
            "type":"Services"
        }
    ],
    "sg:phone":"+1 843 553 9674",
    "sg:postcode":"29445",
    "sg:province":"SC",
    "sg:tags":[
        "house",
        "contractor",
        "family",
        "concrete"
    ],
    "wof:name":"Randolph Concrete & Stucco",
    "wof:placetype":"venue"
},
  "geometry": {"coordinates":[-80.02387299999999,32.979382],"type":"Point"}
}