{
  "type": "Feature",
  "properties": {
    "iso:country":"US",
    "sg:address":"1451 Ribaut Rd",
    "sg:city":"Port Royal",
    "sg:classifiers":[
        {
            "category":"Food & Beverages",
            "subcategory":"Groceries & Convenience Stores",
            "type":"Retail Goods"
        }
    ],
    "sg:phone":"+1 843 525 6062",
    "sg:postcode":"29935",
    "sg:province":"SC",
    "wof:name":"Happy Mart",
    "wof:placetype":"venue"
},
  "geometry": {"coordinates":[-80.68561099999999,32.395391],"type":"Point"}
}