{
  "type": "Feature",
  "properties": {
    "iso:country":"US",
    "sg:address":"219 W Main St",
    "sg:city":"Rock Hill",
    "sg:classifiers":[
        {
            "category":"Professional",
            "type":"Services"
        }
    ],
    "sg:phone":"+1 803 324 3175",
    "sg:postcode":"29730",
    "sg:province":"SC",
    "sg:tags":[
        "establishment"
    ],
    "wof:name":"Unity Outreach",
    "wof:placetype":"venue"
},
  "geometry": {"coordinates":[-81.031684,34.928521],"type":"Point"}
}