{
  "type": "Feature",
  "properties": {
    "iso:country":"US",
    "sg:address":"117 Thornblade Blvd",
    "sg:city":"Greer",
    "sg:classifiers":[
        {
            "category":"Banks & Credit Unions",
            "subcategory":"Bank",
            "type":"Services"
        }
    ],
    "sg:phone":"+1 864 329 9700",
    "sg:postcode":"29650",
    "sg:province":"SC",
    "sg:tags":[
        "financing"
    ],
    "wof:name":"Us Business Financial",
    "wof:placetype":"venue"
},
  "geometry": {"coordinates":[-82.273217,34.872141],"type":"Point"}
}