{
  "type": "Feature",
  "properties": {
    "iso:country":"US",
    "sg:address":"550 Orangeburg Rd",
    "sg:city":"Summerville",
    "sg:classifiers":[
        {
            "category":"Real Estate",
            "subcategory":"Real Estate Operator",
            "type":"Services"
        }
    ],
    "sg:phone":"+1 843 873 1971",
    "sg:postcode":"29483",
    "sg:province":"SC",
    "sg:tags":[
        "mobile",
        "home",
        "site"
    ],
    "wof:name":"Hershey Park",
    "wof:placetype":"venue"
},
  "geometry": {"coordinates":[-80.23683200000001,33.009386],"type":"Point"}
}