{
  "type": "Feature",
  "properties": {
    "iso:country":"US",
    "sg:address":"2776 S Jim McCarter Rd",
    "sg:city":"York",
    "sg:classifiers":[
        {
            "category":"Shopping",
            "subcategory":"Clothing, Apparel, & Fashions",
            "type":"Retail Goods"
        }
    ],
    "sg:phone":"+1 803 222 1043",
    "sg:postcode":"29710",
    "sg:province":"SC",
    "sg:tags":[
        "family"
    ],
    "wof:name":"Hook ME Up Fashions",
    "wof:placetype":"venue"
},
  "geometry": {"coordinates":[-81.207589,35.064734],"type":"Point"}
}