{
  "type": "Feature",
  "properties": {
    "iso:country":"US",
    "sg:address":"11 Silver Meadow Ln",
    "sg:city":"Greer",
    "sg:classifiers":[
        {
            "category":"Wholesale",
            "subcategory":"Machinery & Supplies",
            "type":"Manufacturing & Wholesale Goods"
        }
    ],
    "sg:phone":"+1 864 801 0567",
    "sg:postcode":"29651",
    "sg:province":"SC",
    "sg:tags":[
        "machine",
        "tool"
    ],
    "wof:name":"Machine Tool Systems",
    "wof:placetype":"venue"
},
  "geometry": {"coordinates":[-82.288709,34.966742],"type":"Point"}
}