{
  "type": "Feature",
  "properties": {
    "iso:country":"US",
    "sg:address":"1231 Folly Rd",
    "sg:city":"Charleston",
    "sg:classifiers":[
        {
            "category":"Shopping",
            "subcategory":"Department Store",
            "type":"Retail Goods"
        }
    ],
    "sg:phone":"+1 843 762 9034",
    "sg:postcode":"29412",
    "sg:province":"SC",
    "wof:name":"Wal-Mart",
    "wof:placetype":"venue"
},
  "geometry": {"coordinates":[-79.966517,32.720603],"type":"Point"}
}