{
  "type": "Feature",
  "properties": {
    "addr:full":"62 Queen St Charleston SC 29401",
    "addr:housenumber":"62",
    "addr:postcode":"29401",
    "addr:street":"Queen St",
    "iso:country":"US",
    "sg:address":"62 Queen St",
    "sg:city":"Charleston",
    "sg:classifiers":[
        {
            "category":"Home & Garden",
            "subcategory":"Building Materials",
            "type":"Retail Goods"
        }
    ],
    "sg:phone":"+1 843 722 9041",
    "sg:postcode":"29401",
    "sg:province":"SC",
    "wof:name":"Hubble Bubble Gallery",
    "wof:placetype":"venue"
},
  "geometry": {"coordinates":[-79.929693,32.778342],"type":"Point"}
}