{
  "type": "Feature",
  "properties": {
    "iso:country":"US",
    "sg:address":"191 Meeting St",
    "sg:city":"Charleston",
    "sg:classifiers":[
        {
            "category":"Shopping",
            "subcategory":"Clothing, Apparel, & Fashions",
            "type":"Retail Goods"
        }
    ],
    "sg:phone":"+1 843 937 9142",
    "sg:postcode":"29401",
    "sg:province":"SC",
    "wof:name":"Signature Boutique",
    "wof:placetype":"venue"
},
  "geometry": {"coordinates":[-79.931621,32.780813],"type":"Point"}
}