{
  "type": "Feature",
  "properties": {
    "iso:country":"US",
    "sg:address":"29 Plantation Park Dr # 103",
    "sg:city":"Bluffton",
    "sg:classifiers":[
        {
            "category":"Professional",
            "subcategory":"Employment Agencies",
            "type":"Services"
        },
        {
            "category":"Health Services",
            "subcategory":"Nursing And Care Facility",
            "type":"Services"
        },
        {
            "category":"Health Services",
            "subcategory":"Health Practitioner",
            "type":"Services"
        }
    ],
    "sg:phone":"+1 843 837 3773",
    "sg:postcode":"29910",
    "sg:province":"SC",
    "sg:tags":[
        "home",
        "nurse"
    ],
    "sg:website":"http://www.brightstarcare.com/find-a-location/sc/hilton-head/",
    "wof:name":"BrightStar LifeCare",
    "wof:placetype":"venue"
},
  "geometry": {"coordinates":[-80.867897,32.27161],"type":"Point"}
}