{
  "type": "Feature",
  "properties": {
    "addr:full":"1741 Gold Hill Rd Fort Mill SC 29708",
    "addr:housenumber":"1741",
    "addr:postcode":"29708",
    "addr:street":"Gold Hill Rd",
    "iso:country":"US",
    "sg:address":"1741 Gold Hill Rd",
    "sg:city":"Fort Mill",
    "sg:classifiers":[
        {
            "category":"Food & Beverages",
            "subcategory":"Specialty",
            "type":"Retail Goods"
        }
    ],
    "sg:phone":"+1 803 547 1142",
    "sg:postcode":"29708",
    "sg:province":"SC",
    "sg:tags":[
        "health",
        "diet"
    ],
    "wof:name":"Natural Choice",
    "wof:placetype":"venue"
},
  "geometry": {"coordinates":[-80.991029,35.061278],"type":"Point"}
}