{
  "type": "Feature",
  "properties": {
    "addr:full":"3915 Clemson Blvd Anderson SC 29621",
    "addr:housenumber":"3915",
    "addr:postcode":"29621",
    "addr:street":"Clemson Blvd",
    "iso:country":"US",
    "sg:address":"3915 Clemson Blvd",
    "sg:city":"Anderson",
    "sg:classifiers":[
        {
            "category":"Banks & Credit Unions",
            "subcategory":"Bank",
            "type":"Services"
        }
    ],
    "sg:phone":"+1 864 226 3007",
    "sg:postcode":"29621",
    "sg:province":"SC",
    "sg:tags":[
        "mortgage"
    ],
    "wof:name":"Upstate Carolina Mortgage",
    "wof:placetype":"venue"
},
  "geometry": {"coordinates":[-82.685883,34.556412],"type":"Point"}
}