{
  "type": "Feature",
  "properties": {
    "addr:full":"1048 Peake St Holly Hill SC 29059",
    "addr:housenumber":"1048",
    "addr:postcode":"29059",
    "addr:street":"Peake St",
    "iso:country":"US",
    "sg:address":"1048 Peake St",
    "sg:city":"Holly Hill",
    "sg:classifiers":[
        {
            "category":"Organizations",
            "subcategory":"Religious Organization",
            "type":"Services"
        }
    ],
    "sg:phone":"+1 803 496 3819",
    "sg:postcode":"29059",
    "sg:province":"SC",
    "sg:tags":[
        "church"
    ],
    "wof:name":"Holly Hill Methodist Church",
    "wof:placetype":"venue"
},
  "geometry": {"coordinates":[-80.41349200000001,33.324558],"type":"Point"}
}