{
  "type": "Feature",
  "properties": {
    "addr:full":"103 Shaw St Greenville SC 29609",
    "addr:housenumber":"103",
    "addr:postcode":"29609",
    "addr:street":"Shaw St",
    "iso:country":"US",
    "sg:address":"103 Shaw St",
    "sg:city":"Greenville",
    "sg:classifiers":[
        {
            "category":"Freight",
            "type":"Transportation"
        }
    ],
    "sg:phone":"+1 864 271 0098",
    "sg:postcode":"29609",
    "sg:province":"SC",
    "sg:tags":[
        "delivery"
    ],
    "wof:name":"Delivery Plus",
    "wof:placetype":"venue"
},
  "geometry": {"coordinates":[-82.405655,34.867613],"type":"Point"}
}