{
  "type": "Feature",
  "properties": {
    "addr:full":"234 State Hwy 72 Bus Greenwood SC 29649",
    "addr:housenumber":"234",
    "addr:postcode":"29649",
    "addr:street":"State Hwy 72 Bus",
    "iso:country":"US",
    "sg:address":"234 State Hwy 72 Bus",
    "sg:city":"Greenwood",
    "sg:classifiers":[
        {
            "category":"Restaurant",
            "type":"Food & Drink"
        }
    ],
    "sg:phone":"+1 864 223 6442",
    "sg:postcode":"29649",
    "sg:province":"SC",
    "wof:name":"Great Wall",
    "wof:placetype":"venue"
},
  "geometry": {"coordinates":[-82.160479,34.198043],"type":"Point"}
}