{
  "type": "Feature",
  "properties": {
    "addr:full":"2338 Notch Rd Columbia SC 29204",
    "addr:postcode":"2338;29204",
    "addr:street":"Notch Rd",
    "iso:country":"US",
    "sg:address":"2338 Notch Rd",
    "sg:city":"Columbia",
    "sg:classifiers":[
        {
            "category":"Food & Beverages",
            "subcategory":"Meat & Fish",
            "type":"Retail Goods"
        }
    ],
    "sg:phone":"+1 803 254 7681",
    "sg:postcode":"29204",
    "sg:province":"SC",
    "sg:tags":[
        "seafood",
        "eating"
    ],
    "wof:name":"Phil's Seafood",
    "wof:placetype":"venue"
},
  "geometry": {"coordinates":[-81.011842,34.024694],"type":"Point"}
}