{
  "type": "Feature",
  "properties": {
    "iso:country":"US",
    "sg:address":"106 Quail Creek Ln",
    "sg:city":"Greenville",
    "sg:classifiers":[
        {
            "category":"Shopping",
            "subcategory":"Florist",
            "type":"Retail Goods"
        }
    ],
    "sg:phone":"+1 864 297 5770",
    "sg:postcode":"29615",
    "sg:province":"SC",
    "wof:name":"Ellen Martin Designs",
    "wof:placetype":"venue"
},
  "geometry": {"coordinates":[-82.296939,34.853336],"type":"Point"}
}