{
  "type": "Feature",
  "properties": {
    "iso:country":"US",
    "sg:address":"1027 3rd Ave",
    "sg:city":"Conway",
    "sg:classifiers":[
        {
            "category":"Manufacturing",
            "subcategory":"Jewelry",
            "type":"Manufacturing & Wholesale Goods"
        }
    ],
    "sg:phone":"+1 843 248 9824",
    "sg:postcode":"29526",
    "sg:province":"SC",
    "sg:tags":[
        "trophy",
        "mfg"
    ],
    "wof:name":"Trophy Place",
    "wof:placetype":"venue"
},
  "geometry": {"coordinates":[-79.046286,33.835071],"type":"Point"}
}