{
  "type": "Feature",
  "properties": {
    "iso:country":"US",
    "sg:address":"212 3rd St",
    "sg:city":"Cheraw",
    "sg:classifiers":[
        {
            "category":"Health Services",
            "subcategory":"Doctor",
            "type":"Services"
        }
    ],
    "sg:phone":"+1 843 537 0961",
    "sg:postcode":"29520",
    "sg:province":"SC",
    "sg:tags":[
        "physician",
        "surgeon"
    ],
    "wof:name":"Caresouth Carolina Inc",
    "wof:placetype":"venue"
},
  "geometry": {"coordinates":[-79.885578,34.696904],"type":"Point"}
}