{
  "type": "Feature",
  "properties": {
    "iso:country":"US",
    "sg:address":"16 Miller Rd",
    "sg:city":"Sumter",
    "sg:classifiers":[
        {
            "category":"Health Services",
            "subcategory":"Clinic",
            "type":"Services"
        }
    ],
    "sg:phone":"+1 803 938 8426",
    "sg:postcode":"29150",
    "sg:province":"SC",
    "sg:tags":[
        "home"
    ],
    "wof:name":"Winyah Home Health Care",
    "wof:placetype":"venue"
},
  "geometry": {"coordinates":[-80.379581,33.930788],"type":"Point"}
}