{
  "type": "Feature",
  "properties": {
    "iso:country":"US",
    "sg:address":"635 W. N. 1st St",
    "sg:city":"Seneca",
    "sg:classifiers":[
        {
            "category":"Restaurant",
            "type":"Food & Drink"
        }
    ],
    "sg:menulink":"http://www.allmenus.com/sc/seneca/53993-b-j-blues/menu/",
    "sg:phone":"+1 864 885 0410",
    "sg:postcode":"29678",
    "sg:province":"SC",
    "sg:tags":[
        "italian"
    ],
    "wof:name":"B J Blues",
    "wof:placetype":"venue"
},
  "geometry": {"coordinates":[-82.968806,34.688295],"type":"Point"}
}