{
  "type": "Feature",
  "properties": {
    "iso:country":"US",
    "sg:address":"954 N Logan St",
    "sg:city":"Gaffney",
    "sg:classifiers":[
        {
            "category":"Retail",
            "subcategory":"Auto Repair",
            "type":"Services"
        }
    ],
    "sg:phone":"+1 864 489 3441",
    "sg:postcode":"29341",
    "sg:province":"SC",
    "sg:tags":[
        "repairing",
        "automobile"
    ],
    "wof:name":"Central Alignment",
    "wof:placetype":"venue"
},
  "geometry": {"coordinates":[-81.644961,35.082088],"type":"Point"}
}