{
  "type": "Feature",
  "properties": {
    "iso:country":"US",
    "sg:address":"124 Streater Ln",
    "sg:city":"Anderson",
    "sg:classifiers":[
        {
            "category":"Real Estate",
            "subcategory":"Real Estate Operator",
            "type":"Services"
        }
    ],
    "sg:phone":"+1 864 287 1124",
    "sg:postcode":"29625",
    "sg:province":"SC",
    "sg:tags":[
        "building",
        "nonresidential"
    ],
    "wof:name":"D&D Properties of Anderson",
    "wof:placetype":"venue"
},
  "geometry": {"coordinates":[-82.7611,34.551159],"type":"Point"}
}