{
  "type": "Feature",
  "properties": {
    "iso:country":"US",
    "sg:address":"1119 Pick Pocket Plantation Dr",
    "sg:city":"Beaufort",
    "sg:classifiers":[
        {
            "category":"Social Services",
            "subcategory":"Adult Care",
            "type":"Services"
        }
    ],
    "sg:phone":"+1 843 770 0105",
    "sg:postcode":"29902",
    "sg:province":"SC",
    "sg:tags":[
        "home",
        "residential"
    ],
    "wof:name":"Summit Place Of Beaufort",
    "wof:placetype":"venue"
},
  "geometry": {"coordinates":[-80.702749,32.439217],"type":"Point"}
}