{
  "type": "Feature",
  "properties": {
    "iso:country":"US",
    "sg:address":"2693 Ninety Six Hwy",
    "sg:city":"Ninety Six",
    "sg:classifiers":[
        {
            "category":"Utilities",
            "subcategory":"Cable",
            "type":"Services"
        }
    ],
    "sg:phone":"+1 864 445 7217",
    "sg:postcode":"29666",
    "sg:province":"SC",
    "sg:tags":[
        "television"
    ],
    "wof:name":"New Wave Satellites",
    "wof:placetype":"venue"
},
  "geometry": {"coordinates":[-82.055922,34.174113],"type":"Point"}
}