{
  "type": "Feature",
  "properties": {
    "iso:country":"US",
    "sg:address":"103 International Ct",
    "sg:city":"Greenville",
    "sg:classifiers":[
        {
            "category":"Shopping",
            "subcategory":"Clothing, Apparel, & Fashions",
            "type":"Retail Goods"
        }
    ],
    "sg:phone":"+1 864 286 0609",
    "sg:postcode":"29607",
    "sg:province":"SC",
    "sg:tags":[
        "uniform"
    ],
    "wof:name":"Plus Uniforms",
    "wof:placetype":"venue"
},
  "geometry": {"coordinates":[-82.308505,34.794153],"type":"Point"}
}