{
  "type": "Feature",
  "properties": {
    "addr:full":"753 Crossroads Plz Fort Mill SC 29708",
    "addr:housenumber":"753",
    "addr:postcode":"29708",
    "addr:street":"Crossroads Plz",
    "iso:country":"US",
    "sg:address":"753 Crossroads Plz",
    "sg:city":"Fort Mill",
    "sg:classifiers":[
        {
            "category":"Ice Cream",
            "type":"Food & Drink"
        }
    ],
    "sg:menulink":"http://www.allmenus.com/sc/fort-mill/232296-maggie-moos/menu/",
    "sg:phone":"+1 803 548 6244",
    "sg:postcode":"29708",
    "sg:province":"SC",
    "sg:tags":[
        "american"
    ],
    "wof:name":"Maggie Moo's",
    "wof:placetype":"venue"
},
  "geometry": {"coordinates":[-80.989619,35.060427],"type":"Point"}
}