{
  "type": "Feature",
  "properties": {
    "iso:country":"US",
    "sg:address":"165 Wall St",
    "sg:city":"Orangeburg",
    "sg:classifiers":[
        {
            "category":"Retail",
            "subcategory":"Repair Shop",
            "type":"Services"
        }
    ],
    "sg:phone":"+1 803 534 6591",
    "sg:postcode":"29115",
    "sg:province":"SC",
    "sg:tags":[
        "ice",
        "equipment",
        "refrigeration",
        "clean",
        "making",
        "mach"
    ],
    "wof:name":"Culler R L Refrigeration Svc",
    "wof:placetype":"venue"
},
  "geometry": {"coordinates":[-80.86261399999999,33.49076],"type":"Point"}
}