{
  "type": "Feature",
  "properties": {
    "iso:country":"US",
    "sg:address":"200 S Buncombe Rd",
    "sg:city":"Greer",
    "sg:classifiers":[
        {
            "category":"Autos & Motor Vehicles",
            "subcategory":"Automobile Sales",
            "type":"Retail Goods"
        }
    ],
    "sg:phone":"+1 864 968 9398",
    "sg:postcode":"29650",
    "sg:province":"SC",
    "sg:tags":[
        "used"
    ],
    "wof:name":"Goldjin Auto Inc",
    "wof:placetype":"venue"
},
  "geometry": {"coordinates":[-82.257841,34.940636],"type":"Point"}
}