{
  "type": "Feature",
  "properties": {
    "iso:country":"US",
    "sg:address":"339 Swampfox Dr",
    "sg:city":"Fort Mill",
    "sg:classifiers":[
        {
            "category":"Retail",
            "subcategory":"Repair Shop",
            "type":"Services"
        }
    ],
    "sg:phone":"+1 803 547 7611",
    "sg:postcode":"29715",
    "sg:province":"SC",
    "sg:tags":[
        "upholsterer"
    ],
    "wof:name":"Chaplin Upholstery",
    "wof:placetype":"venue"
},
  "geometry": {"coordinates":[-80.90809299999999,35.029162],"type":"Point"}
}