{
  "type": "Feature",
  "properties": {
    "iso:country":"US",
    "sg:address":"825 Weybourne Dr",
    "sg:city":"Greer",
    "sg:classifiers":[
        {
            "category":"Insurance",
            "subcategory":"Insurance Agent",
            "type":"Services"
        }
    ],
    "sg:phone":"+1 864 297 3693",
    "sg:postcode":"29650",
    "sg:province":"SC",
    "wof:name":"Affordable Health & Life",
    "wof:placetype":"venue"
},
  "geometry": {"coordinates":[-82.283413,34.864517],"type":"Point"}
}