{
  "type": "Feature",
  "properties": {
    "addr:full":"673 W Liberty St Sumter SC 29150",
    "addr:housenumber":"673",
    "addr:postcode":"29150",
    "addr:street":"W Liberty St",
    "iso:country":"US",
    "sg:address":"673 W Liberty St",
    "sg:city":"Sumter",
    "sg:classifiers":[
        {
            "category":"Shopping",
            "subcategory":"Used Merchandise",
            "type":"Retail Goods"
        }
    ],
    "sg:phone":"+1 803 773 2124",
    "sg:postcode":"29150",
    "sg:province":"SC",
    "wof:name":"Odds & Ends",
    "wof:placetype":"venue"
},
  "geometry": {"coordinates":[-80.35996400000001,33.920017],"type":"Point"}
}