{
  "type": "Feature",
  "properties": {
    "iso:country":"US",
    "sg:address":"728 Dewitt Rd",
    "sg:city":"Lugoff",
    "sg:classifiers":[
        {
            "category":"Personal",
            "subcategory":"Tanning Parlor",
            "type":"Services"
        }
    ],
    "sg:phone":"+1 803 408 9848",
    "sg:postcode":"29078",
    "sg:province":"SC",
    "sg:tags":[
        "salon"
    ],
    "wof:name":"Electric Sun",
    "wof:placetype":"venue"
},
  "geometry": {"coordinates":[-80.670516,34.233442],"type":"Point"}
}