{
  "type": "Feature",
  "properties": {
    "iso:country":"US",
    "sg:address":"806 College Ave",
    "sg:city":"Clemson",
    "sg:classifiers":[
        {
            "category":"Real Estate",
            "subcategory":"Real Estate Operator",
            "type":"Services"
        }
    ],
    "sg:phone":"+1 864 653 9921",
    "sg:postcode":"29631",
    "sg:province":"SC",
    "sg:tags":[
        "building",
        "apartment"
    ],
    "wof:name":"Barefoot Properties",
    "wof:placetype":"venue"
},
  "geometry": {"coordinates":[-82.832855,34.695456],"type":"Point"}
}