{
  "type": "Feature",
  "properties": {
    "iso:country":"US",
    "sg:address":"2853 Cains Mill Rd",
    "sg:city":"Sumter",
    "sg:classifiers":[
        {
            "category":"Retail",
            "subcategory":"Repair Shop",
            "type":"Services"
        }
    ],
    "sg:phone":"+1 803 481 7592",
    "sg:postcode":"29154",
    "sg:province":"SC",
    "sg:tags":[
        "upholsterer"
    ],
    "wof:name":"Quick's Upholstery",
    "wof:placetype":"venue"
},
  "geometry": {"coordinates":[-80.406288,33.861312],"type":"Point"}
}