{
  "type": "Feature",
  "properties": {
    "iso:country":"US",
    "sg:address":"9026 Possum Hollow Rd",
    "sg:city":"Fort Mill",
    "sg:classifiers":[
        {
            "category":"Building & Trades",
            "subcategory":"Construction",
            "type":"Services"
        }
    ],
    "sg:phone":"+1 803 547 7306",
    "sg:postcode":"29707",
    "sg:province":"SC",
    "sg:tags":[
        "site",
        "clean"
    ],
    "wof:name":"Ray's Cleaning Svc",
    "wof:placetype":"venue"
},
  "geometry": {"coordinates":[-80.96971000000001,35.07007],"type":"Point"}
}