{
  "type": "Feature",
  "properties": {
    "iso:country":"US",
    "sg:address":"2230 Taylor St Ste A",
    "sg:city":"Columbia",
    "sg:classifiers":[
        {
            "category":"Health Services",
            "subcategory":"Optometrist",
            "type":"Services"
        }
    ],
    "sg:phone":"+1 803 254 7099",
    "sg:postcode":"29204",
    "sg:province":"SC",
    "wof:name":"Randolph Lonnie Jr Dr",
    "wof:placetype":"venue"
},
  "geometry": {"coordinates":[-81.019019,34.011826],"type":"Point"}
}