{
  "type": "Feature",
  "properties": {
    "addr:full":"3618 Sunset Blvd West Columbia SC 29169",
    "addr:housenumber":"3618",
    "addr:postcode":"29169",
    "addr:street":"Sunset Blvd",
    "iso:country":"US",
    "sg:address":"3618 Sunset Blvd",
    "sg:city":"West Columbia",
    "sg:classifiers":[
        {
            "category":"Utilities",
            "subcategory":"Refuse",
            "type":"Services"
        },
        {
            "category":"Professional",
            "subcategory":"Management & Consulting",
            "type":"Services"
        }
    ],
    "sg:phone":"+1 843 869 2930",
    "sg:postcode":"29169",
    "sg:province":"SC",
    "sg:tags":[
        "marketing",
        "program",
        "system"
    ],
    "sg:website":"www.sefagroup.com",
    "wof:name":"Seafa Group",
    "wof:placetype":"venue"
},
  "geometry": {"coordinates":[-81.13599000000001,34.00801],"type":"Point"}
}