{
  "type": "Feature",
  "properties": {
    "iso:country":"US",
    "sg:address":"3030 Lesslie Hwy",
    "sg:city":"Rock Hill",
    "sg:classifiers":[
        {
            "category":"Wholesale",
            "subcategory":"Machinery & Supplies",
            "type":"Manufacturing & Wholesale Goods"
        }
    ],
    "sg:phone":"+1 803 324 3342",
    "sg:postcode":"29730",
    "sg:province":"SC",
    "sg:tags":[
        "truck"
    ],
    "sg:website":"www.wholesaleforklift.com",
    "wof:name":"Wholesale Forklifts Inc",
    "wof:placetype":"venue"
},
  "geometry": {"coordinates":[-80.960858,34.895676],"type":"Point"}
}