{
  "type": "Feature",
  "properties": {
    "iso:country":"US",
    "sg:address":"661 Bultman Dr",
    "sg:city":"Sumter",
    "sg:classifiers":[
        {
            "category":"Shopping",
            "subcategory":"Books",
            "type":"Retail Goods"
        }
    ],
    "sg:phone":"+1 803 934 1199",
    "sg:postcode":"29150",
    "sg:province":"SC",
    "sg:tags":[
        "bible"
    ],
    "wof:name":"Gideons International",
    "wof:placetype":"venue"
},
  "geometry": {"coordinates":[-80.371858,33.940887],"type":"Point"}
}