{
  "type": "Feature",
  "properties": {
    "iso:country":"US",
    "sg:address":"800 Archer Rd",
    "sg:city":"Spartanburg",
    "sg:classifiers":[
        {
            "category":"Organizations",
            "subcategory":"Religious Organization",
            "type":"Services"
        }
    ],
    "sg:phone":"+1 864 583 2847",
    "sg:postcode":"29303",
    "sg:province":"SC",
    "sg:tags":[
        "church"
    ],
    "wof:name":"Davis Memorial Baptist Church",
    "wof:placetype":"venue"
},
  "geometry": {"coordinates":[-81.91261799999999,34.986138],"type":"Point"}
}