{
  "type": "Feature",
  "properties": {
    "iso:country":"US",
    "sg:address":"6710 US Hwy 221",
    "sg:city":"Moore",
    "sg:classifiers":[
        {
            "category":"Professional",
            "subcategory":"Business Services",
            "type":"Services"
        }
    ],
    "sg:phone":"+1 864 574 2151",
    "sg:postcode":"29369",
    "sg:province":"SC",
    "sg:tags":[
        "embroidery"
    ],
    "wof:name":"Melton Embroidery",
    "wof:placetype":"venue"
},
  "geometry": {"coordinates":[-81.99368,34.824786],"type":"Point"}
}