{
  "type": "Feature",
  "properties": {
    "addr:full":"614 Morris Pond Rd Aiken SC 29801",
    "addr:housenumber":"614",
    "addr:postcode":"29801",
    "addr:street":"Morris Pond Rd",
    "iso:country":"US",
    "sg:address":"614 Morris Pond Rd",
    "sg:city":"Aiken",
    "sg:classifiers":[
        {
            "category":"Building & Trades",
            "subcategory":"Plumbing",
            "type":"Services"
        }
    ],
    "sg:phone":"+1 803 641 4900",
    "sg:postcode":"29801",
    "sg:province":"SC",
    "sg:tags":[
        "septic"
    ],
    "wof:name":"Cantrell Septic Tank Svc",
    "wof:placetype":"venue"
},
  "geometry": {"coordinates":[-81.721934,33.628621],"type":"Point"}
}