{
  "type": "Feature",
  "properties": {
    "addr:full":"42 Montis Dr Greenville SC 29617",
    "addr:housenumber":"42",
    "addr:postcode":"29617",
    "addr:street":"Montis Dr",
    "iso:country":"US",
    "sg:address":"42 Montis Dr",
    "sg:city":"Greenville",
    "sg:classifiers":[
        {
            "category":"Building & Trades",
            "subcategory":"Electrical",
            "type":"Services"
        }
    ],
    "sg:phone":"+1 864 246 2634",
    "sg:postcode":"29617",
    "sg:province":"SC",
    "sg:tags":[
        "electric",
        "contractor"
    ],
    "wof:name":"Ward Electrical Inc",
    "wof:placetype":"venue"
},
  "geometry": {"coordinates":[-82.42534000000001,34.896193],"type":"Point"}
}