{
  "type": "Feature",
  "properties": {
    "addr:full":"221 Bell Cir Clinton SC 29325",
    "addr:housenumber":"221",
    "addr:postcode":"29325",
    "addr:street":"Bell Cir",
    "iso:country":"US",
    "sg:address":"221 Bell Cir",
    "sg:city":"Clinton",
    "sg:classifiers":[
        {
            "category":"Manufacturing",
            "subcategory":"Printing",
            "type":"Manufacturing & Wholesale Goods"
        }
    ],
    "sg:phone":"+1 864 833 3074",
    "sg:postcode":"29325",
    "sg:province":"SC",
    "sg:tags":[
        "commercial"
    ],
    "wof:name":"T Shirt Express",
    "wof:placetype":"venue"
},
  "geometry": {"coordinates":[-81.895268,34.46308],"type":"Point"}
}