{
  "type": "Feature",
  "properties": {
    "iso:country":"US",
    "sg:address":"368 Duckett Ave",
    "sg:city":"Whitmire",
    "sg:classifiers":[
        {
            "category":"Government",
            "subcategory":"Fire Station",
            "type":"Public Place"
        }
    ],
    "sg:phone":"+1 803 000 1111",
    "sg:postcode":"29178",
    "sg:province":"SC",
    "sg:tags":[
        "department"
    ],
    "wof:name":"Rescue Squad",
    "wof:placetype":"venue"
},
  "geometry": {"coordinates":[-81.62785,34.502363],"type":"Point"}
}