{
  "type": "Feature",
  "properties": {
    "iso:country":"US",
    "sg:address":"1023 N Seabridge Ct",
    "sg:city":"Myrtle Beach",
    "sg:classifiers":[
        {
            "category":"Wholesale",
            "subcategory":"Dairy",
            "type":"Manufacturing & Wholesale Goods"
        },
        {
            "category":"Wholesale",
            "subcategory":"Groceries",
            "type":"Manufacturing & Wholesale Goods"
        }
    ],
    "sg:phone":"+1 843 238 2916",
    "sg:postcode":"29575",
    "sg:province":"SC",
    "sg:tags":[
        "frozen",
        "dessert",
        "ice",
        "food",
        "treat",
        "cream"
    ],
    "wof:name":"R-Jg Enterprises",
    "wof:placetype":"venue"
},
  "geometry": {"coordinates":[-78.96495299999999,33.614005],"type":"Point"}
}