{
  "type": "Feature",
  "properties": {
    "iso:country":"US",
    "sg:address":"145 Market St",
    "sg:city":"Charleston",
    "sg:classifiers":[
        {
            "category":"Professional",
            "type":"Services"
        }
    ],
    "sg:phone":"+1 843 577 2004",
    "sg:postcode":"29401",
    "sg:province":"SC",
    "sg:tags":[
        "establishment"
    ],
    "wof:name":"Unitech",
    "wof:placetype":"venue"
},
  "geometry": {"coordinates":[-79.931696,32.78062],"type":"Point"}
}