{
  "type": "Feature",
  "properties": {
    "addr:full":"599 Giff St Newberry SC 29108",
    "addr:housenumber":"599",
    "addr:postcode":"29108",
    "addr:street":"Giff St",
    "iso:country":"US",
    "sg:address":"599 Giff St",
    "sg:city":"Newberry",
    "sg:classifiers":[
        {
            "category":"Organizations",
            "subcategory":"Religious Organization",
            "type":"Services"
        }
    ],
    "sg:phone":"+1 803 276 4658",
    "sg:postcode":"29108",
    "sg:province":"SC",
    "sg:tags":[
        "church"
    ],
    "wof:name":"Little Beaver Dam Baptist Chr",
    "wof:placetype":"venue"
},
  "geometry": {"coordinates":[-81.643956,34.276868],"type":"Point"}
}