{
  "type": "Feature",
  "properties": {
    "addr:full":"1007 Broadway St Myrtle Beach SC 29577",
    "addr:housenumber":"1007",
    "addr:postcode":"29577",
    "addr:street":"Broadway St",
    "iso:country":"US",
    "sg:address":"1007 Broadway St",
    "sg:city":"Myrtle Beach",
    "sg:classifiers":[
        {
            "category":"Shopping",
            "subcategory":"Used Merchandise",
            "type":"Retail Goods"
        }
    ],
    "sg:phone":"+1 843 448 4547",
    "sg:postcode":"29577",
    "sg:province":"SC",
    "sg:tags":[
        "pawnbroker"
    ],
    "wof:name":"Louie's Pawnshop",
    "wof:placetype":"venue"
},
  "geometry": {"coordinates":[-78.880289,33.695587],"type":"Point"}
}