{
  "type": "Feature",
  "properties": {
    "iso:country":"US",
    "sg:address":"701 Assembly St",
    "sg:city":"Columbia",
    "sg:classifiers":[
        {
            "category":"Recreation",
            "type":"Entertainment"
        }
    ],
    "sg:phone":"+1 803 251 2222",
    "sg:postcode":"29201",
    "sg:province":"SC",
    "sg:tags":[
        "ticket"
    ],
    "wof:name":"Capital Tickets",
    "wof:placetype":"venue"
},
  "geometry": {"coordinates":[-81.032793,33.99527],"type":"Point"}
}