{
  "type": "Feature",
  "properties": {
    "addr:full":"3907 Aaron Temple Church Rd Bennettsville SC 29512",
    "addr:housenumber":"3907",
    "addr:postcode":"29512",
    "addr:street":"Aaron Temple Church Rd",
    "iso:country":"US",
    "sg:address":"3907 Aaron Temple Church Rd",
    "sg:city":"Bennettsville",
    "sg:classifiers":[
        {
            "category":"Social Services",
            "type":"Services"
        }
    ],
    "sg:phone":"+1 843 454 9022",
    "sg:postcode":"29512",
    "sg:province":"SC",
    "sg:tags":[
        "care",
        "center",
        "day"
    ],
    "wof:name":"Sandhill Helping Hand Daycare",
    "wof:placetype":"venue"
},
  "geometry": {"coordinates":[-79.732445,34.759029],"type":"Point"}
}