{
  "type": "Feature",
  "properties": {
    "iso:country":"US",
    "sg:address":"2375 Restview Rd",
    "sg:city":"Florence",
    "sg:classifiers":[
        {
            "category":"Building & Trades",
            "subcategory":"Construction",
            "type":"Services"
        }
    ],
    "sg:phone":"+1 843 669 9997",
    "sg:postcode":"29506",
    "sg:province":"SC",
    "sg:tags":[
        "nonresidential"
    ],
    "wof:name":"Crowder Construction Company",
    "wof:placetype":"venue"
},
  "geometry": {"coordinates":[-79.698916,34.267444],"type":"Point"}
}