{
  "type": "Feature",
  "properties": {
    "iso:country":"US",
    "sg:address":"122 N Railroad Ave",
    "sg:city":"Kingstree",
    "sg:classifiers":[
        {
            "category":"Retail",
            "subcategory":"Auto Repair",
            "type":"Services"
        }
    ],
    "sg:phone":"+1 843 354 5001",
    "sg:postcode":"29556",
    "sg:province":"SC",
    "sg:tags":[
        "repairing",
        "automobile"
    ],
    "wof:name":"Charles Automotive",
    "wof:placetype":"venue"
},
  "geometry": {"coordinates":[-79.82732799999999,33.66733],"type":"Point"}
}