{
  "type": "Feature",
  "properties": {
    "addr:full":"3904 Augusta Rd Greenville SC 29605",
    "addr:housenumber":"3904",
    "addr:postcode":"29605",
    "addr:street":"Augusta Rd",
    "iso:country":"US",
    "sg:address":"3904 Augusta Rd",
    "sg:city":"Greenville",
    "sg:classifiers":[
        {
            "category":"Personal",
            "subcategory":"Massage",
            "type":"Services"
        }
    ],
    "sg:phone":"+1 864 299 0238",
    "sg:postcode":"29605",
    "sg:province":"SC",
    "wof:name":"Far East Health Spa",
    "wof:placetype":"venue"
},
  "geometry": {"coordinates":[-82.388266,34.767949],"type":"Point"}
}