{
  "type": "Feature",
  "properties": {
    "addr:full":"531 Roe Rd Greenville SC 29611",
    "addr:housenumber":"531",
    "addr:postcode":"29611",
    "addr:street":"Roe Rd",
    "iso:country":"US",
    "sg:address":"531 Roe Rd",
    "sg:city":"Greenville",
    "sg:classifiers":[
        {
            "category":"Building & Trades",
            "subcategory":"Construction",
            "type":"Services"
        }
    ],
    "sg:phone":"+1 864 605 0080",
    "sg:postcode":"29611",
    "sg:province":"SC",
    "sg:tags":[
        "grading",
        "utility"
    ],
    "wof:name":"Chambers Grading Company Inc",
    "wof:placetype":"venue"
},
  "geometry": {"coordinates":[-82.494553,34.7983],"type":"Point"}
}