{
  "type": "Feature",
  "properties": {
    "iso:country":"US",
    "sg:address":"903 Park St Exd",
    "sg:city":"Mullins",
    "sg:classifiers":[
        {
            "category":"Building & Trades",
            "subcategory":"Construction",
            "type":"Services"
        }
    ],
    "sg:phone":"+1 843 464 6345",
    "sg:postcode":"29574",
    "sg:province":"SC",
    "sg:tags":[
        "house"
    ],
    "wof:name":"Ards Repair Service",
    "wof:placetype":"venue"
},
  "geometry": {"coordinates":[-79.254283,34.219508],"type":"Point"}
}