{
  "type": "Feature",
  "properties": {
    "iso:country":"US",
    "sg:address":"1146 Jackson St",
    "sg:city":"Anderson",
    "sg:classifiers":[
        {
            "category":"Restaurant",
            "type":"Food & Drink"
        }
    ],
    "sg:phone":"+1 864 225 4965",
    "sg:postcode":"29625",
    "sg:province":"SC",
    "wof:name":"Hungry Jax",
    "wof:placetype":"venue"
},
  "geometry": {"coordinates":[-82.691962,34.521096],"type":"Point"}
}