{
  "type": "Feature",
  "properties": {
    "iso:country":"US",
    "sg:address":"363 Creek Rd",
    "sg:city":"Georgetown",
    "sg:classifiers":[
        {
            "category":"Organizations",
            "subcategory":"Religious Organization",
            "type":"Services"
        }
    ],
    "sg:phone":"+1 843 546 2884",
    "sg:postcode":"29471",
    "sg:province":"SC",
    "sg:tags":[
        "church"
    ],
    "wof:name":"Chester Hill Baptist Church",
    "wof:placetype":"venue"
},
  "geometry": {"coordinates":[-80.68391099999999,33.1538],"type":"Point"}
}