{
  "type": "Feature",
  "properties": {
    "iso:country":"US",
    "sg:address":"132 Campton Cir",
    "sg:city":"Inman",
    "sg:classifiers":[
        {
            "category":"Organizations",
            "subcategory":"Religious Organization",
            "type":"Services"
        }
    ],
    "sg:phone":"+1 864 472 6479",
    "sg:postcode":"29349",
    "sg:province":"SC",
    "sg:tags":[
        "clergy"
    ],
    "wof:name":"Ray Lanford",
    "wof:placetype":"venue"
},
  "geometry": {"coordinates":[-82.054907,35.030794],"type":"Point"}
}