{
  "type": "Feature",
  "properties": {
    "addr:full":"863 Timber Creek Dr York SC 29745",
    "addr:housenumber":"863",
    "addr:postcode":"29745",
    "addr:street":"Timber Creek Dr",
    "iso:country":"US",
    "sg:address":"863 Timber Creek Dr",
    "sg:city":"York",
    "sg:classifiers":[
        {
            "category":"Home & Garden",
            "subcategory":"Building Materials",
            "type":"Retail Goods"
        }
    ],
    "sg:phone":"+1 803 628 0703",
    "sg:postcode":"29745",
    "sg:province":"SC",
    "wof:name":"Ed Clarke",
    "wof:placetype":"venue"
},
  "geometry": {"coordinates":[-81.130095,35.046472],"type":"Point"}
}