{
  "type": "Feature",
  "properties": {
    "addr:full":"2161 India Hook Rd Rock Hill SC 29732",
    "addr:housenumber":"2161",
    "addr:postcode":"29732",
    "addr:street":"India Hook Rd",
    "iso:country":"US",
    "sg:address":"2161 India Hook Rd",
    "sg:city":"Rock Hill",
    "sg:classifiers":[
        {
            "category":"Retail",
            "subcategory":"Auto Repair",
            "type":"Services"
        }
    ],
    "sg:phone":"+1 803 324 0740",
    "sg:postcode":"29732",
    "sg:province":"SC",
    "sg:tags":[
        "repairing",
        "automobile"
    ],
    "wof:name":"Carl's Radiator Repair Svc",
    "wof:placetype":"venue"
},
  "geometry": {"coordinates":[-81.03003,34.970651],"type":"Point"}
}