{
  "type": "Feature",
  "properties": {
    "iso:country":"US",
    "sg:address":"4611 Hard Scrabble Rd",
    "sg:city":"Columbia",
    "sg:classifiers":[
        {
            "category":"Health Services",
            "subcategory":"Chiropractor",
            "type":"Services"
        }
    ],
    "sg:phone":"+1 803 462 6110",
    "sg:postcode":"29223",
    "sg:province":"SC",
    "wof:name":"Ky Borgstadt DC",
    "wof:placetype":"venue"
},
  "geometry": {"coordinates":[-80.91167900000001,34.151375],"type":"Point"}
}