{
  "type": "Feature",
  "properties": {
    "addr:full":"1913 College St Columbia SC 29201",
    "addr:housenumber":"1913",
    "addr:postcode":"29201",
    "addr:street":"College St",
    "iso:country":"US",
    "sg:address":"1913 College St",
    "sg:city":"Columbia",
    "sg:classifiers":[
        {
            "category":"Professional",
            "subcategory":"Lawyer & Legal Services",
            "type":"Services"
        }
    ],
    "sg:phone":"+1 803 799 3744",
    "sg:postcode":"29201",
    "sg:province":"SC",
    "wof:name":"Childs Kenneth L Atty",
    "wof:placetype":"venue"
},
  "geometry": {"coordinates":[-81.019813,34.001004],"type":"Point"}
}