{
  "type": "Feature",
  "properties": {
    "iso:country":"US",
    "sg:address":"601 W Church St",
    "sg:city":"Batesburg",
    "sg:classifiers":[
        {
            "category":"Organizations",
            "subcategory":"Religious Organization",
            "type":"Services"
        }
    ],
    "sg:phone":"+1 803 532 6944",
    "sg:postcode":"29006",
    "sg:province":"SC",
    "sg:tags":[
        "church"
    ],
    "wof:name":"Ridge Branch Baptist Church",
    "wof:placetype":"venue"
},
  "geometry": {"coordinates":[-81.55327699999999,33.90566],"type":"Point"}
}