{
  "type": "Feature",
  "properties": {
    "iso:country":"US",
    "sg:address":"302 Woodward St",
    "sg:city":"Bishopville",
    "sg:classifiers":[
        {
            "category":"Organizations",
            "subcategory":"Religious Organization",
            "type":"Services"
        }
    ],
    "sg:phone":"+1 803 484 6023",
    "sg:postcode":"29010",
    "sg:province":"SC",
    "sg:tags":[
        "church"
    ],
    "wof:name":"Mt Hermon Baptist Church",
    "wof:placetype":"venue"
},
  "geometry": {"coordinates":[-80.24578,34.225279],"type":"Point"}
}