{
  "type": "Feature",
  "properties": {
    "iso:country":"US",
    "sg:address":"802 Cockfield Rd",
    "sg:city":"Scranton",
    "sg:classifiers":[
        {
            "category":"Organizations",
            "subcategory":"Religious Organization",
            "type":"Services"
        }
    ],
    "sg:phone":"+1 843 389 9595",
    "sg:postcode":"29560",
    "sg:province":"SC",
    "sg:tags":[
        "church"
    ],
    "sg:website":"www.gileadfwb.com",
    "wof:name":"Gilead Freewill Baptist Church",
    "wof:placetype":"venue"
},
  "geometry": {"coordinates":[-79.711939,33.879315],"type":"Point"}
}