{
  "type": "Feature",
  "properties": {
    "addr:full":"602 State Rd Cheraw SC 29520",
    "addr:housenumber":"602",
    "addr:postcode":"29520",
    "addr:street":"State Rd",
    "iso:country":"US",
    "sg:address":"602 State Rd",
    "sg:city":"Cheraw",
    "sg:classifiers":[
        {
            "category":"Manufacturing",
            "subcategory":"Tools & Machinery",
            "type":"Manufacturing & Wholesale Goods"
        }
    ],
    "sg:phone":"+1 843 537 5192",
    "sg:postcode":"29520",
    "sg:province":"SC",
    "sg:tags":[
        "shop",
        "repair",
        "industrial",
        "mfg",
        "machine",
        "welding"
    ],
    "wof:name":"Quick's Machine Works Inc",
    "wof:placetype":"venue"
},
  "geometry": {"coordinates":[-79.90546399999999,34.703637],"type":"Point"}
}