{
  "type": "Feature",
  "properties": {
    "iso:country":"US",
    "sg:address":"200 Industrial Dr",
    "sg:city":"Greenville",
    "sg:classifiers":[
        {
            "category":"Home & Garden",
            "subcategory":"Building Materials",
            "type":"Retail Goods"
        }
    ],
    "sg:phone":"+1 864 232 2545",
    "sg:postcode":"29607",
    "sg:province":"SC",
    "sg:tags":[
        "plumbing",
        "fixture",
        "supply"
    ],
    "sg:website":"www.prosourcesupply.com",
    "wof:name":"Prosource",
    "wof:placetype":"venue"
},
  "geometry": {"coordinates":[-82.35057500000001,34.837548],"type":"Point"}
}