{
  "type": "Feature",
  "properties": {
    "addr:full":"6851 State Hwy 917 Nichols SC 29581",
    "addr:housenumber":"6851",
    "addr:postcode":"29581",
    "addr:street":"State Hwy 917",
    "iso:country":"US",
    "sg:address":"6851 State Hwy 917",
    "sg:city":"Nichols",
    "sg:classifiers":[
        {
            "category":"Home & Garden",
            "subcategory":"Garden Supply",
            "type":"Retail Goods"
        }
    ],
    "sg:phone":"+1 843 392 4769",
    "sg:postcode":"29581",
    "sg:province":"SC",
    "sg:tags":[
        "nurseryman"
    ],
    "wof:name":"Planters Exchange",
    "wof:placetype":"venue"
},
  "geometry": {"coordinates":[-79.091331,34.099097],"type":"Point"}
}