{
  "type": "Feature",
  "properties": {
    "iso:country":"US",
    "sg:address":"965 Westfield Ct",
    "sg:city":"Sumter",
    "sg:classifiers":[
        {
            "category":"Building & Trades",
            "subcategory":"Construction",
            "type":"Services"
        }
    ],
    "sg:phone":"+1 803 494 3441",
    "sg:postcode":"29154",
    "sg:province":"SC",
    "sg:tags":[
        "hanging",
        "contractor"
    ],
    "wof:name":"Mac Master Co",
    "wof:placetype":"venue"
},
  "geometry": {"coordinates":[-80.432324,33.893396],"type":"Point"}
}