{
  "type": "Feature",
  "properties": {
    "addr:full":"1901 Main St Columbia SC 29201",
    "addr:housenumber":"1901",
    "addr:postcode":"29201",
    "addr:street":"Main St",
    "iso:country":"US",
    "sg:address":"1901 Main St",
    "sg:city":"Columbia",
    "sg:classifiers":[
        {
            "category":"Professional",
            "subcategory":"Lawyer & Legal Services",
            "type":"Services"
        }
    ],
    "sg:phone":"+1 803 254 2200",
    "sg:postcode":"29201",
    "sg:province":"SC",
    "sg:tags":[
        "attorney"
    ],
    "sg:website":"www.tpgl.com",
    "wof:name":"Turner Padget Graham & Laney",
    "wof:placetype":"venue"
},
  "geometry": {"coordinates":[-81.03826599999999,34.011962],"type":"Point"}
}