{
  "type": "Feature",
  "properties": {
    "addr:full":"6040 Rivers Ave North Charleston SC 29406",
    "addr:housenumber":"6040",
    "addr:postcode":"29406",
    "addr:street":"Rivers Ave",
    "iso:country":"US",
    "sg:address":"6040 Rivers Ave",
    "sg:city":"North Charleston",
    "sg:classifiers":[
        {
            "category":"Government",
            "subcategory":"Office",
            "type":"Public Place"
        }
    ],
    "sg:phone":"+1 843 764 1951",
    "sg:postcode":"29406",
    "sg:province":"SC",
    "sg:tags":[
        "armed",
        "force",
        "recruiting"
    ],
    "wof:name":"Army Recruiting US",
    "wof:placetype":"venue"
},
  "geometry": {"coordinates":[-80.020855,32.905826],"type":"Point"}
}