{
  "type": "Feature",
  "properties": {
    "iso:country":"US",
    "sg:address":"1735 Heckle Blvd",
    "sg:city":"Rock Hill",
    "sg:classifiers":[
        {
            "category":"Personal",
            "subcategory":"Beauty Salon",
            "type":"Services"
        }
    ],
    "sg:phone":"+1 803 324 5252",
    "sg:postcode":"29732",
    "sg:province":"SC",
    "wof:name":"Cuts & Curls",
    "wof:placetype":"venue"
},
  "geometry": {"coordinates":[-81.064655,34.953183],"type":"Point"}
}