{
  "type": "Feature",
  "properties": {
    "addr:full":"154 Winyah Rd Conway SC 29526",
    "addr:housenumber":"154",
    "addr:postcode":"29526",
    "addr:street":"Winyah Rd",
    "iso:country":"US",
    "sg:address":"154 Winyah Rd",
    "sg:city":"Conway",
    "sg:classifiers":[
        {
            "category":"Building & Trades",
            "subcategory":"Construction",
            "type":"Services"
        }
    ],
    "sg:phone":"+1 843 448 3521",
    "sg:postcode":"29526",
    "sg:province":"SC",
    "sg:tags":[
        "paving",
        "contractor"
    ],
    "wof:name":"APAC Inc",
    "wof:placetype":"venue"
},
  "geometry": {"coordinates":[-78.991184,33.793046],"type":"Point"}
}