{
  "type": "Feature",
  "properties": {
    "iso:country":"US",
    "sg:address":"3836 Ladson Rd",
    "sg:city":"Ladson",
    "sg:classifiers":[
        {
            "category":"Organizations",
            "subcategory":"Religious Organization",
            "type":"Services"
        }
    ],
    "sg:phone":"+1 843 875 6505",
    "sg:postcode":"29456",
    "sg:province":"SC",
    "sg:tags":[
        "church"
    ],
    "wof:name":"Heritage Holiness Church",
    "wof:placetype":"venue"
},
  "geometry": {"coordinates":[-80.135068,32.976065],"type":"Point"}
}