{
  "type": "Feature",
  "properties": {
    "iso:country":"US",
    "sg:address":"4123 W Beltline Blvd",
    "sg:city":"Columbia",
    "sg:classifiers":[
        {
            "category":"Home & Garden",
            "subcategory":"Furniture",
            "type":"Retail Goods"
        }
    ],
    "sg:phone":"+1 803 252 8200",
    "sg:postcode":"29204",
    "sg:province":"SC",
    "sg:tags":[
        "store"
    ],
    "wof:name":"Nationwide Warehouse & Storage Inc",
    "wof:placetype":"venue"
},
  "geometry": {"coordinates":[-81.007698,34.0369],"type":"Point"}
}