{
  "type": "Feature",
  "properties": {
    "addr:full":"4226 Leeds St Columbia SC 29210",
    "addr:housenumber":"4226",
    "addr:postcode":"29210",
    "addr:street":"Leeds St",
    "iso:country":"US",
    "sg:address":"4226 Leeds St",
    "sg:city":"Columbia",
    "sg:classifiers":[
        {
            "category":"Manufacturing",
            "subcategory":"Tools & Machinery",
            "type":"Manufacturing & Wholesale Goods"
        }
    ],
    "sg:phone":"+1 803 798 0443",
    "sg:postcode":"29210",
    "sg:province":"SC",
    "sg:tags":[
        "farm",
        "durable",
        "mfg"
    ],
    "wof:name":"Brights Tree Service",
    "wof:placetype":"venue"
},
  "geometry": {"coordinates":[-81.119215,34.061896],"type":"Point"}
}