{
  "type": "Feature",
  "properties": {
    "addr:full":"3005 N Main St Anderson SC 29621",
    "addr:housenumber":"3005",
    "addr:postcode":"29621",
    "addr:street":"N Main St",
    "iso:country":"US",
    "sg:address":"3005 N Main St",
    "sg:city":"Anderson",
    "sg:classifiers":[
        {
            "category":"Banks & Credit Unions",
            "subcategory":"Bank",
            "type":"Services"
        }
    ],
    "sg:phone":"+1 864 226 9111",
    "sg:postcode":"29621",
    "sg:province":"SC",
    "wof:name":"Bank Of America",
    "wof:placetype":"venue"
},
  "geometry": {"coordinates":[-82.665841,34.534324],"type":"Point"}
}