{
  "type": "Feature",
  "properties": {
    "addr:full":"203 S Main St Darlington SC 29532",
    "addr:housenumber":"203",
    "addr:postcode":"29532",
    "addr:street":"S Main St",
    "iso:country":"US",
    "sg:address":"203 S Main St",
    "sg:city":"Darlington",
    "sg:classifiers":[
        {
            "category":"Shopping",
            "subcategory":"Pharmacy",
            "type":"Retail Goods"
        }
    ],
    "sg:phone":"+1 843 395 6020",
    "sg:postcode":"29532",
    "sg:province":"SC",
    "wof:name":"Medicap Pharmacy",
    "wof:placetype":"venue"
},
  "geometry": {"coordinates":[-79.869917,34.301304],"type":"Point"}
}