{
  "type": "Feature",
  "properties": {
    "addr:full":"611 Woodward Blvd Summerville SC 29483",
    "addr:housenumber":"611",
    "addr:postcode":"29483",
    "addr:street":"Woodward Blvd",
    "iso:country":"US",
    "sg:address":"611 Woodward Blvd",
    "sg:city":"Summerville",
    "sg:classifiers":[
        {
            "category":"Building & Trades",
            "subcategory":"Construction",
            "type":"Services"
        }
    ],
    "sg:phone":"+1 843 871 8753",
    "sg:postcode":"29483",
    "sg:province":"SC",
    "sg:tags":[
        "contractor"
    ],
    "wof:name":"Atlantic Coast Tile Inc",
    "wof:placetype":"venue"
},
  "geometry": {"coordinates":[-80.21713699999999,33.01812],"type":"Point"}
}