{
  "type": "Feature",
  "properties": {
    "iso:country":"US",
    "sg:address":"112 New Hope Rd",
    "sg:city":"Pelzer",
    "sg:classifiers":[
        {
            "category":"Social Services",
            "subcategory":"Child Care",
            "type":"Services"
        }
    ],
    "sg:phone":"+1 864 947 2579",
    "sg:postcode":"29669",
    "sg:province":"SC",
    "sg:tags":[
        "kindergarten",
        "academic",
        "school"
    ],
    "wof:name":"New Hope Day Care",
    "wof:placetype":"venue"
},
  "geometry": {"coordinates":[-82.495392,34.655422],"type":"Point"}
}