{
  "type": "Feature",
  "properties": {
    "iso:country":"US",
    "sg:address":"1549 Gsp Dr",
    "sg:city":"Greer",
    "sg:classifiers":[
        {
            "category":"Professional",
            "type":"Services"
        }
    ],
    "sg:phone":"+1 864 848 9970",
    "sg:postcode":"29651",
    "sg:province":"SC",
    "sg:tags":[
        "agency",
        "government"
    ],
    "wof:name":"National Oceanic & Atmospheric",
    "wof:placetype":"venue"
},
  "geometry": {"coordinates":[-82.21977,34.883252],"type":"Point"}
}