{
  "type": "Feature",
  "properties": {
    "addr:full":"10 Oak Forest Rd Bluffton SC 29910",
    "addr:housenumber":"10",
    "addr:postcode":"29910",
    "addr:street":"Oak Forest Rd",
    "iso:country":"US",
    "sg:address":"10 Oak Forest Rd",
    "sg:city":"Bluffton",
    "sg:classifiers":[
        {
            "category":"Banks & Credit Unions",
            "subcategory":"Investment Brokerage",
            "type":"Services"
        }
    ],
    "sg:phone":"+1 843 815 4322",
    "sg:postcode":"29910",
    "sg:province":"SC",
    "sg:tags":[
        "stock",
        "bond"
    ],
    "wof:name":"Wachovia Securities",
    "wof:placetype":"venue"
},
  "geometry": {"coordinates":[-80.85894999999999,32.266954],"type":"Point"}
}