{
  "type": "Feature",
  "properties": {
    "iso:country":"US",
    "sg:address":"1905 Belgrade Ave",
    "sg:city":"Charleston",
    "sg:classifiers":[
        {
            "category":"Retail",
            "subcategory":"Auto Repair",
            "type":"Services"
        }
    ],
    "sg:phone":"+1 843 573 4927",
    "sg:postcode":"29407",
    "sg:province":"SC",
    "sg:tags":[
        "body",
        "automobile",
        "painting"
    ],
    "wof:name":"Signature Collision Specialist",
    "wof:placetype":"venue"
},
  "geometry": {"coordinates":[-80.024758,32.79675],"type":"Point"}
}