{
  "type": "Feature",
  "properties": {
    "addr:full":"1601 Anderson Dr Williamston SC 29697",
    "addr:housenumber":"1601",
    "addr:postcode":"29697",
    "addr:street":"Anderson Dr",
    "iso:country":"US",
    "sg:address":"1601 Anderson Dr",
    "sg:city":"Williamston",
    "sg:classifiers":[
        {
            "category":"Food & Beverages",
            "subcategory":"Groceries & Convenience Stores",
            "type":"Retail Goods"
        }
    ],
    "sg:phone":"+1 864 847 7232",
    "sg:postcode":"29697",
    "sg:province":"SC",
    "wof:name":"Little General Food Store",
    "wof:placetype":"venue"
},
  "geometry": {"coordinates":[-82.500789,34.614495],"type":"Point"}
}