{
  "type": "Feature",
  "properties": {
    "addr:full":"5676 Ellington School Rd Ravenel SC 29470",
    "addr:housenumber":"5676",
    "addr:postcode":"29470",
    "addr:street":"Ellington School Rd",
    "iso:country":"US",
    "sg:address":"5676 Ellington School Rd",
    "sg:city":"Ravenel",
    "sg:classifiers":[
        {
            "category":"Organizations",
            "subcategory":"Religious Organization",
            "type":"Services"
        }
    ],
    "sg:phone":"+1 843 889 8861",
    "sg:postcode":"29470",
    "sg:province":"SC",
    "sg:tags":[
        "church"
    ],
    "wof:name":"St John Baptist Church",
    "wof:placetype":"venue"
},
  "geometry": {"coordinates":[-80.217873,32.769243],"type":"Point"}
}