{
  "type": "Feature",
  "properties": {
    "iso:country":"US",
    "sg:address":"4149 Main St",
    "sg:city":"Loris",
    "sg:classifiers":[
        {
            "category":"Food & Beverages",
            "subcategory":"Specialty",
            "type":"Retail Goods"
        }
    ],
    "sg:phone":"+1 843 756 6706",
    "sg:postcode":"29569",
    "sg:province":"SC",
    "sg:tags":[
        "health",
        "diet"
    ],
    "wof:name":"Nature's Health",
    "wof:placetype":"venue"
},
  "geometry": {"coordinates":[-78.889574,34.056155],"type":"Point"}
}