{
  "type": "Feature",
  "properties": {
    "iso:country":"US",
    "sg:address":"2229 Decker Blvd",
    "sg:city":"Columbia",
    "sg:classifiers":[
        {
            "category":"Organizations",
            "subcategory":"Religious Organization",
            "type":"Services"
        }
    ],
    "sg:phone":"+1 803 699 9346",
    "sg:postcode":"29206",
    "sg:province":"SC",
    "sg:tags":[
        "church"
    ],
    "wof:name":"Living Water Christian Outrch",
    "wof:placetype":"venue"
},
  "geometry": {"coordinates":[-80.945695,34.052245],"type":"Point"}
}