{
  "type": "Feature",
  "properties": {
    "addr:full":"230 Greystone Blvd Columbia SC 29210",
    "addr:housenumber":"230",
    "addr:postcode":"29210",
    "addr:street":"Greystone Blvd",
    "iso:country":"US",
    "sg:address":"230 Greystone Blvd",
    "sg:city":"Columbia",
    "sg:classifiers":[
        {
            "category":"Travel",
            "subcategory":"Hotels & Motels",
            "type":"Entertainment"
        }
    ],
    "sg:phone":"+1 803 239 4663",
    "sg:postcode":"29210",
    "sg:province":"SC",
    "wof:name":"Homewood Suites",
    "wof:placetype":"venue"
},
  "geometry": {"coordinates":[-81.076302,34.019402],"type":"Point"}
}