{
  "type": "Feature",
  "properties": {
    "addr:full":"108 Airport Rd Greenville SC 29607",
    "addr:housenumber":"108",
    "addr:postcode":"29607",
    "addr:street":"Airport Rd",
    "iso:country":"US",
    "sg:address":"108 Airport Rd",
    "sg:city":"Greenville",
    "sg:classifiers":[
        {
            "category":"Manufacturing",
            "subcategory":"Jewelry",
            "type":"Manufacturing & Wholesale Goods"
        },
        {
            "category":"Professional",
            "type":"Services"
        }
    ],
    "sg:phone":"+1 864 235 6055",
    "sg:postcode":"29607",
    "sg:province":"SC",
    "sg:tags":[
        "establishment",
        "costume",
        "mfg"
    ],
    "wof:name":"L F Le Master Inc",
    "wof:placetype":"venue"
},
  "geometry": {"coordinates":[-82.356746,34.843837],"type":"Point"}
}