{
  "type": "Feature",
  "properties": {
    "iso:country":"US",
    "sg:address":"105 Norman Dr",
    "sg:city":"Roebuck",
    "sg:classifiers":[
        {
            "category":"Building & Trades",
            "subcategory":"Construction",
            "type":"Services"
        }
    ],
    "sg:phone":"+1 864 576 5101",
    "sg:postcode":"29376",
    "sg:province":"SC",
    "sg:tags":[
        "contractor"
    ],
    "wof:name":"Lenard Goodwin",
    "wof:placetype":"venue"
},
  "geometry": {"coordinates":[-81.956022,34.906624],"type":"Point"}
}