{
  "type": "Feature",
  "properties": {
    "iso:country":"US",
    "sg:address":"550 Garrison Rd",
    "sg:city":"Pelzer",
    "sg:classifiers":[
        {
            "category":"Manufacturing",
            "subcategory":"Pet Food",
            "type":"Manufacturing & Wholesale Goods"
        }
    ],
    "sg:phone":"+1 864 243 2620",
    "sg:postcode":"29669",
    "sg:province":"SC",
    "sg:tags":[
        "mfg",
        "starches",
        "modified",
        "resin",
        "pol",
        "acrylic",
        "chemically"
    ],
    "wof:name":"Actol Industries Inc",
    "wof:placetype":"venue"
},
  "geometry": {"coordinates":[-82.392934,34.661763],"type":"Point"}
}