{
  "type": "Feature",
  "properties": {
    "addr:full":"484 Runnymeade Dr Rock Hill SC 29732",
    "addr:housenumber":"484",
    "addr:postcode":"29732",
    "addr:street":"Runnymeade Dr",
    "iso:country":"US",
    "sg:address":"484 Runnymeade Dr",
    "sg:city":"Rock Hill",
    "sg:classifiers":[
        {
            "category":"Restaurant",
            "type":"Food & Drink"
        }
    ],
    "sg:phone":"+1 803 366 1050",
    "sg:postcode":"29732",
    "sg:province":"SC",
    "sg:tags":[
        "parlor",
        "ice",
        "cream"
    ],
    "wof:name":"Baskin-Robbins",
    "wof:placetype":"venue"
},
  "geometry": {"coordinates":[-81.05716200000001,34.949078],"type":"Point"}
}