{
  "type": "Feature",
  "properties": {
    "iso:country":"US",
    "sg:address":"4312 Alligator Rd",
    "sg:city":"Timmonsville",
    "sg:classifiers":[
        {
            "category":"Building & Trades",
            "subcategory":"Construction",
            "type":"Services"
        }
    ],
    "sg:phone":"+1 843 346 3163",
    "sg:postcode":"29161",
    "sg:province":"SC",
    "sg:tags":[
        "house",
        "builder",
        "operative"
    ],
    "wof:name":"Home Resource Center",
    "wof:placetype":"venue"
},
  "geometry": {"coordinates":[-79.892903,34.147735],"type":"Point"}
}