{
  "type": "Feature",
  "properties": {
    "addr:full":"1930 Cedar Petal Ln Charleston SC 29414",
    "addr:housenumber":"1930",
    "addr:postcode":"29414",
    "addr:street":"Cedar Petal Ln",
    "iso:country":"US",
    "sg:address":"1930 Cedar Petal Ln",
    "sg:city":"Charleston",
    "sg:classifiers":[
        {
            "category":"Professional",
            "subcategory":"Management & Consulting",
            "type":"Services"
        }
    ],
    "sg:phone":"+1 843 556 5207",
    "sg:postcode":"29414",
    "sg:province":"SC",
    "sg:tags":[
        "consultant",
        "educational"
    ],
    "wof:name":"Educational Training Consult",
    "wof:placetype":"venue"
},
  "geometry": {"coordinates":[-80.040066,32.819979],"type":"Point"}
}