{
  "type": "Feature",
  "properties": {
    "addr:full":"323 E Main St Moncks Corner SC 29461",
    "addr:housenumber":"323",
    "addr:postcode":"29461",
    "addr:street":"E Main St",
    "iso:country":"US",
    "sg:address":"323 E Main St",
    "sg:city":"Moncks Corner",
    "sg:classifiers":[
        {
            "category":"Shopping",
            "type":"Retail Goods"
        }
    ],
    "sg:phone":"+1 843 761 3099",
    "sg:postcode":"29461",
    "sg:province":"SC",
    "sg:tags":[
        "picture",
        "frame",
        "merchandise"
    ],
    "wof:name":"Lowcountry Prints & Frames",
    "wof:placetype":"venue"
},
  "geometry": {"coordinates":[-80.004144,33.192593],"type":"Point"}
}