{
  "type": "Feature",
  "properties": {
    "iso:country":"US",
    "sg:address":"153 Tram Rd",
    "sg:city":"Columbia",
    "sg:classifiers":[
        {
            "category":"Insurance",
            "subcategory":"Insurance Agent",
            "type":"Services"
        }
    ],
    "sg:phone":"+1 803 772 5208",
    "sg:postcode":"29210",
    "sg:province":"SC",
    "wof:name":"W Gary Bradham & Assoc",
    "wof:placetype":"venue"
},
  "geometry": {"coordinates":[-81.14613,34.045949],"type":"Point"}
}