{
  "type": "Feature",
  "properties": {
    "addr:full":"412 Hemingford Grey Fort Mill SC 29708",
    "addr:housenumber":"412",
    "addr:postcode":"29708",
    "addr:street":"Hemingford Grey",
    "iso:country":"US",
    "sg:address":"412 Hemingford Grey",
    "sg:city":"Fort Mill",
    "sg:classifiers":[
        {
            "category":"Home & Garden",
            "subcategory":"Home Furnishings",
            "type":"Retail Goods"
        }
    ],
    "sg:phone":"+1 803 547 2618",
    "sg:postcode":"29708",
    "sg:province":"SC",
    "wof:name":"Elaine Tarleton Designs",
    "wof:placetype":"venue"
},
  "geometry": {"coordinates":[-80.957171,35.076869],"type":"Point"}
}