{
  "type": "Feature",
  "properties": {
    "iso:country":"US",
    "sg:address":"1428 Hawkins St",
    "sg:city":"Georgetown",
    "sg:classifiers":[
        {
            "category":"Building & Trades",
            "subcategory":"Construction",
            "type":"Services"
        }
    ],
    "sg:phone":"+1 843 527 1071",
    "sg:postcode":"29440",
    "sg:province":"SC",
    "sg:tags":[
        "contractor"
    ],
    "wof:name":"J & J Contracting",
    "wof:placetype":"venue"
},
  "geometry": {"coordinates":[-79.295053,33.365409],"type":"Point"}
}