{
  "type": "Feature",
  "properties": {
    "iso:country":"US",
    "sg:address":"613 Knox Abbott Dr",
    "sg:city":"Cayce",
    "sg:classifiers":[
        {
            "category":"Travel",
            "subcategory":"Hotels & Motels",
            "type":"Entertainment"
        }
    ],
    "sg:phone":"+1 803 796 4300",
    "sg:postcode":"29033",
    "sg:province":"SC",
    "sg:website":"www.mastersinn.com",
    "wof:name":"Masters Economy Inn",
    "wof:placetype":"venue"
},
  "geometry": {"coordinates":[-81.058403,33.983898],"type":"Point"}
}