{
  "type": "Feature",
  "properties": {
    "iso:country":"US",
    "sg:address":"106 May St",
    "sg:city":"Walterboro",
    "sg:classifiers":[
        {
            "category":"Organizations",
            "subcategory":"Religious Organization",
            "type":"Services"
        }
    ],
    "sg:phone":"+1 843 549 5353",
    "sg:postcode":"29488",
    "sg:province":"SC",
    "sg:tags":[
        "church"
    ],
    "wof:name":"Good Shepherd Lutheran Church",
    "wof:placetype":"venue"
},
  "geometry": {"coordinates":[-80.672932,32.897729],"type":"Point"}
}