{
  "type": "Feature",
  "properties": {
    "addr:full":"113 Bombay Dr Columbia SC 29209",
    "addr:housenumber":"113",
    "addr:postcode":"29209",
    "addr:street":"Bombay Dr",
    "iso:country":"US",
    "sg:address":"113 Bombay Dr",
    "sg:city":"Columbia",
    "sg:classifiers":[
        {
            "category":"Freight",
            "type":"Transportation"
        }
    ],
    "sg:phone":"+1 803 783 5468",
    "sg:postcode":"29209",
    "sg:province":"SC",
    "sg:tags":[
        "moving",
        "household",
        "good",
        "storage"
    ],
    "wof:name":"Movemart Inc",
    "wof:placetype":"venue"
},
  "geometry": {"coordinates":[-80.96626500000001,33.926782],"type":"Point"}
}