{
  "type": "Feature",
  "properties": {
    "iso:country":"US",
    "sg:address":"2409 Percival Rd",
    "sg:city":"Columbia",
    "sg:classifiers":[
        {
            "category":"Food & Beverages",
            "subcategory":"Groceries & Convenience Stores",
            "type":"Retail Goods"
        }
    ],
    "sg:phone":"+1 803 782 2221",
    "sg:postcode":"29223",
    "sg:province":"SC",
    "wof:name":"Express Way 4",
    "wof:placetype":"venue"
},
  "geometry": {"coordinates":[-80.911091,34.060106],"type":"Point"}
}