{
  "type": "Feature",
  "properties": {
    "addr:full":"743 Carolina Ave Rock Hill SC 29730",
    "addr:housenumber":"743",
    "addr:postcode":"29730",
    "addr:street":"Carolina Ave",
    "iso:country":"US",
    "sg:address":"743 Carolina Ave",
    "sg:city":"Rock Hill",
    "sg:classifiers":[
        {
            "category":"Building & Trades",
            "subcategory":"Cleaning & Sanitation",
            "type":"Services"
        }
    ],
    "sg:phone":"+1 803 366 8513",
    "sg:postcode":"29730",
    "sg:province":"SC",
    "wof:name":"Excel Commercial Cleaning Svc",
    "wof:placetype":"venue"
},
  "geometry": {"coordinates":[-81.030174,34.917346],"type":"Point"}
}