{
  "type": "Feature",
  "properties": {
    "addr:full":"3586 Bombing Range Rd Longs SC 29568",
    "addr:housenumber":"3586",
    "addr:postcode":"29568",
    "addr:street":"Bombing Range Rd",
    "iso:country":"US",
    "sg:address":"3586 Bombing Range Rd",
    "sg:city":"Longs",
    "sg:classifiers":[
        {
            "category":"Restaurant",
            "type":"Food & Drink"
        }
    ],
    "sg:phone":"+1 843 399 8253",
    "sg:postcode":"29568",
    "sg:province":"SC",
    "sg:tags":[
        "eating"
    ],
    "wof:name":"Lacy S Place",
    "wof:placetype":"venue"
},
  "geometry": {"coordinates":[-78.764584,33.848985],"type":"Point"}
}