{
  "type": "Feature",
  "properties": {
    "addr:full":"216 Latonea Dr Columbia SC 29210",
    "addr:housenumber":"216",
    "addr:postcode":"29210",
    "addr:street":"Latonea Dr",
    "iso:country":"US",
    "sg:address":"216 Latonea Dr",
    "sg:city":"Columbia",
    "sg:classifiers":[
        {
            "category":"Building & Trades",
            "subcategory":"Landscaping Services",
            "type":"Services"
        }
    ],
    "sg:phone":"+1 803 608 1321",
    "sg:postcode":"29210",
    "sg:province":"SC",
    "sg:tags":[
        "irrigation",
        "tree",
        "removal"
    ],
    "wof:name":"Clean Cut Lawn Maintenance LLC",
    "wof:placetype":"venue"
},
  "geometry": {"coordinates":[-81.09967899999999,34.027717],"type":"Point"}
}