{
  "type": "Feature",
  "properties": {
    "iso:country":"US",
    "sg:address":"197 Wren Dr",
    "sg:city":"Cheraw",
    "sg:classifiers":[
        {
            "category":"Taxi",
            "type":"Transportation"
        }
    ],
    "sg:phone":"+1 843 537 5333",
    "sg:postcode":"29520",
    "sg:province":"SC",
    "sg:tags":[
        "taxicab"
    ],
    "wof:name":"Robinson's Courier Freight",
    "wof:placetype":"venue"
},
  "geometry": {"coordinates":[-79.95898099999999,34.703264],"type":"Point"}
}