{
  "type": "Feature",
  "properties": {
    "iso:country":"US",
    "sg:address":"2480 Main St",
    "sg:city":"Elgin",
    "sg:classifiers":[
        {
            "category":"Banks & Credit Unions",
            "subcategory":"Bank",
            "type":"Services"
        }
    ],
    "sg:phone":"+1 803 438 6236",
    "sg:postcode":"29045",
    "sg:province":"SC",
    "sg:tags":[
        "mortgage"
    ],
    "wof:name":"First Palmetto Savings Bank",
    "wof:placetype":"venue"
},
  "geometry": {"coordinates":[-80.792331,34.170396],"type":"Point"}
}