{
  "type": "Feature",
  "properties": {
    "iso:country":"US",
    "sg:address":"1703 Elm St W",
    "sg:city":"Hampton",
    "sg:classifiers":[
        {
            "category":"Food & Beverages",
            "subcategory":"Groceries & Convenience Stores",
            "type":"Retail Goods"
        }
    ],
    "sg:phone":"+1 803 943 0483",
    "sg:postcode":"29924",
    "sg:province":"SC",
    "sg:tags":[
        "grocer"
    ],
    "wof:name":"Winn-Dixie",
    "wof:placetype":"venue"
},
  "geometry": {"coordinates":[-81.129509,32.884143],"type":"Point"}
}