{
  "type": "Feature",
  "properties": {
    "iso:country":"US",
    "sg:address":"2730 Pageland Hwy",
    "sg:city":"Lancaster",
    "sg:classifiers":[
        {
            "category":"Autos & Motor Vehicles",
            "subcategory":"Auto Supplies",
            "type":"Retail Goods"
        }
    ],
    "sg:phone":"+1 803 286 6112",
    "sg:postcode":"29720",
    "sg:province":"SC",
    "sg:tags":[
        "automobile",
        "used",
        "tire"
    ],
    "wof:name":"Bud's Tire & Auto Sales",
    "wof:placetype":"venue"
},
  "geometry": {"coordinates":[-80.694622,34.731323],"type":"Point"}
}