{
  "type": "Feature",
  "properties": {
    "iso:country":"US",
    "sg:address":"6136 Belton Hwy",
    "sg:city":"Belton",
    "sg:classifiers":[
        {
            "category":"Home & Garden",
            "subcategory":"Garden Supply",
            "type":"Retail Goods"
        }
    ],
    "sg:phone":"+1 864 338 0739",
    "sg:postcode":"29627",
    "sg:province":"SC",
    "sg:tags":[
        "mulch"
    ],
    "wof:name":"Latimer Discount Mulch",
    "wof:placetype":"venue"
},
  "geometry": {"coordinates":[-82.535699,34.494979],"type":"Point"}
}