{
  "type": "Feature",
  "properties": {
    "addr:full":"1759 Whetstone Rd Swansea SC 29160",
    "addr:housenumber":"1759",
    "addr:postcode":"29160",
    "addr:street":"Whetstone Rd",
    "iso:country":"US",
    "sg:address":"1759 Whetstone Rd",
    "sg:city":"Swansea",
    "sg:classifiers":[
        {
            "category":"Freight",
            "type":"Transportation"
        }
    ],
    "sg:phone":"+1 803 568 3759",
    "sg:postcode":"29160",
    "sg:province":"SC",
    "sg:tags":[
        "distance",
        "broker",
        "long",
        "trucking"
    ],
    "wof:name":"3-D Leasing",
    "wof:placetype":"venue"
},
  "geometry": {"coordinates":[-81.16052999999999,33.677519],"type":"Point"}
}