{
  "type": "Feature",
  "properties": {
    "iso:country":"US",
    "sg:address":"609 W Warehouse Ct",
    "sg:city":"Taylors",
    "sg:classifiers":[
        {
            "category":"Manufacturing",
            "subcategory":"Chemicals & Compounds",
            "type":"Manufacturing & Wholesale Goods"
        }
    ],
    "sg:phone":"+1 864 268 8967",
    "sg:postcode":"29687",
    "sg:province":"SC",
    "wof:name":"Janed Enterprises Inc",
    "wof:placetype":"venue"
},
  "geometry": {"coordinates":[-82.35820099999999,34.89922],"type":"Point"}
}