{
  "type": "Feature",
  "properties": {
    "addr:full":"652 State Hwy 381 S Mc Coll SC 29570",
    "addr:housenumber":"652",
    "addr:postcode":"29570",
    "addr:street":"State Hwy 381 S Mc Coll",
    "iso:country":"US",
    "sg:address":"652 State Hwy 381 S",
    "sg:city":"Mc Coll",
    "sg:classifiers":[
        {
            "category":"Organizations",
            "subcategory":"Religious Organization",
            "type":"Services"
        }
    ],
    "sg:phone":"+1 843 523 6001",
    "sg:postcode":"29570",
    "sg:province":"SC",
    "sg:tags":[
        "church"
    ],
    "wof:name":"Liberty Christian Community",
    "wof:placetype":"venue"
},
  "geometry": {"coordinates":[-79.539309,34.661654],"type":"Point"}
}