{
  "type": "Feature",
  "properties": {
    "iso:country":"US",
    "sg:address":"30 E Butler Rd",
    "sg:city":"Mauldin",
    "sg:classifiers":[
        {
            "category":"Building & Trades",
            "subcategory":"Construction",
            "type":"Services"
        }
    ],
    "sg:phone":"+1 864 281 9411",
    "sg:postcode":"29662",
    "sg:province":"SC",
    "sg:tags":[
        "general",
        "contractor"
    ],
    "wof:name":"Seay's Construction Inc",
    "wof:placetype":"venue"
},
  "geometry": {"coordinates":[-82.308538,34.778643],"type":"Point"}
}