{
  "type": "Feature",
  "properties": {
    "iso:country":"US",
    "sg:address":"1696 Richland Ave E",
    "sg:city":"Aiken",
    "sg:classifiers":[
        {
            "category":"Food & Beverages",
            "subcategory":"Groceries & Convenience Stores",
            "type":"Retail Goods"
        }
    ],
    "sg:phone":"+1 803 642 1870",
    "sg:postcode":"29801",
    "sg:province":"SC",
    "sg:tags":[
        "market"
    ],
    "wof:name":"Hay Market Stone Ctr",
    "wof:placetype":"venue"
},
  "geometry": {"coordinates":[-81.695815,33.552942],"type":"Point"}
}