{
  "type": "Feature",
  "properties": {
    "addr:full":"411 Mills Ave Spartanburg SC 29302",
    "addr:housenumber":"411",
    "addr:postcode":"29302",
    "addr:street":"Mills Ave",
    "iso:country":"US",
    "sg:address":"411 Mills Ave",
    "sg:city":"Spartanburg",
    "sg:classifiers":[
        {
            "category":"Building & Trades",
            "subcategory":"Construction",
            "type":"Services"
        }
    ],
    "sg:phone":"+1 864 542 0855",
    "sg:postcode":"29302",
    "sg:province":"SC",
    "sg:tags":[
        "carpentry",
        "contractor"
    ],
    "wof:name":"Thomas Cuathen",
    "wof:placetype":"venue"
},
  "geometry": {"coordinates":[-81.90961799999999,34.946527],"type":"Point"}
}