{
  "type": "Feature",
  "properties": {
    "addr:full":"5365 Hwy 24 Anderson SC 29625",
    "addr:housenumber":"5365",
    "addr:postcode":"29625",
    "addr:street":"Hwy 24",
    "iso:country":"US",
    "sg:address":"5365 Hwy 24",
    "sg:city":"Anderson",
    "sg:classifiers":[
        {
            "category":"Shopping",
            "subcategory":"Bicycles & Sporting Goods",
            "type":"Retail Goods"
        }
    ],
    "sg:phone":"+1 864 287 9782",
    "sg:postcode":"29625",
    "sg:province":"SC",
    "sg:tags":[
        "bait",
        "fishing"
    ],
    "wof:name":"Lake Hartwell Fishing &Marine",
    "wof:placetype":"venue"
},
  "geometry": {"coordinates":[-82.799779,34.529288],"type":"Point"}
}