{
  "type": "Feature",
  "properties": {
    "addr:full":"460 Slab Landing Rd North SC 29112",
    "addr:housenumber":"460",
    "addr:postcode":"29112",
    "addr:street":"Slab Landing Rd",
    "iso:country":"US",
    "sg:address":"460 Slab Landing Rd",
    "sg:city":"North",
    "sg:classifiers":[
        {
            "category":"Manufacturing",
            "subcategory":"Lumber",
            "type":"Manufacturing & Wholesale Goods"
        }
    ],
    "sg:phone":"+1 803 247 5797",
    "sg:postcode":"29112",
    "sg:province":"SC",
    "sg:tags":[
        "logging"
    ],
    "wof:name":"Williams Ronnie J Logging Co",
    "wof:placetype":"venue"
},
  "geometry": {"coordinates":[-81.062819,33.621728],"type":"Point"}
}