{
  "type": "Feature",
  "properties": {
    "iso:country":"US",
    "sg:address":"111 N Main St",
    "sg:city":"Greenville",
    "sg:classifiers":[
        {
            "category":"Shopping",
            "subcategory":"Department Store",
            "type":"Retail Goods"
        }
    ],
    "sg:phone":"+1 864 235 1883",
    "sg:postcode":"29601",
    "sg:province":"SC",
    "sg:website":"www.mastgeneralstore.com",
    "wof:name":"Mast General Store",
    "wof:placetype":"venue"
},
  "geometry": {"coordinates":[-82.39827,34.852417],"type":"Point"}
}