{
  "type": "Feature",
  "properties": {
    "addr:full":"309 Butler Ave Greenville SC 29601",
    "addr:housenumber":"309",
    "addr:postcode":"29601",
    "addr:street":"Butler Ave",
    "iso:country":"US",
    "sg:address":"309 Butler Ave",
    "sg:city":"Greenville",
    "sg:classifiers":[
        {
            "category":"Building & Trades",
            "subcategory":"Construction",
            "type":"Services"
        }
    ],
    "sg:phone":"+1 864 242 1238",
    "sg:postcode":"29601",
    "sg:province":"SC",
    "sg:tags":[
        "contractor"
    ],
    "wof:name":"Carolina Building & Rstrtn",
    "wof:placetype":"venue"
},
  "geometry": {"coordinates":[-82.403592,34.856904],"type":"Point"}
}