{
  "type": "Feature",
  "properties": {
    "iso:country":"US",
    "sg:address":"521 Peach Orchard Rd",
    "sg:city":"Union",
    "sg:classifiers":[
        {
            "category":"Organizations",
            "subcategory":"Religious Organization",
            "type":"Services"
        }
    ],
    "sg:phone":"+1 864 429 0787",
    "sg:postcode":"29379",
    "sg:province":"SC",
    "sg:tags":[
        "church"
    ],
    "wof:name":"Calvary Free Will Baptist Chr",
    "wof:placetype":"venue"
},
  "geometry": {"coordinates":[-81.592963,34.726752],"type":"Point"}
}