{
  "type": "Feature",
  "properties": {
    "iso:country":"US",
    "sg:address":"7410 Northside Dr",
    "sg:city":"North Charleston",
    "sg:classifiers":[
        {
            "category":"Building & Trades",
            "subcategory":"Construction",
            "type":"Services"
        }
    ],
    "sg:phone":"+1 843 824 8667",
    "sg:postcode":"29420",
    "sg:province":"SC",
    "sg:tags":[
        "residential",
        "contractor"
    ],
    "wof:name":"Portrait Homes",
    "wof:placetype":"venue"
},
  "geometry": {"coordinates":[-80.050094,32.935314],"type":"Point"}
}