{
  "type": "Feature",
  "properties": {
    "iso:country":"US",
    "sg:address":"110 N Ames St",
    "sg:city":"Greenwood",
    "sg:classifiers":[
        {
            "category":"Shopping",
            "subcategory":"Clothing, Apparel, & Fashions",
            "type":"Retail Goods"
        }
    ],
    "sg:phone":"+1 864 388 9555",
    "sg:postcode":"29646",
    "sg:province":"SC",
    "sg:tags":[
        "wig",
        "toupee",
        "hairpiece"
    ],
    "wof:name":"New Looks",
    "wof:placetype":"venue"
},
  "geometry": {"coordinates":[-82.144338,34.197836],"type":"Point"}
}