{
  "type": "Feature",
  "properties": {
    "addr:full":"208 Claude Bundrick Rd Blythewood SC 29016",
    "addr:housenumber":"208",
    "addr:postcode":"29016",
    "addr:street":"Claude Bundrick Rd",
    "iso:country":"US",
    "sg:address":"208 Claude Bundrick Rd",
    "sg:city":"Blythewood",
    "sg:classifiers":[
        {
            "category":"Travel",
            "subcategory":"Campground",
            "type":"Entertainment"
        }
    ],
    "sg:phone":"+1 803 754 2008",
    "sg:postcode":"29016",
    "sg:province":"SC",
    "sg:tags":[
        "camp"
    ],
    "sg:website":"www.campdiscoverysc.org",
    "wof:name":"Camp Discovery At His Acres",
    "wof:placetype":"venue"
},
  "geometry": {"coordinates":[-80.92093800000001,34.213954],"type":"Point"}
}