{
  "type": "Feature",
  "properties": {
    "iso:country":"US",
    "sg:address":"714 US Hwy 17",
    "sg:city":"Little River",
    "sg:classifiers":[
        {
            "category":"Recreation",
            "subcategory":"Marina",
            "type":"Entertainment"
        }
    ],
    "sg:phone":"+1 843 249 5376",
    "sg:postcode":"29566",
    "sg:province":"SC",
    "sg:website":"www.myrtlebeachyachtclub.com",
    "wof:name":"Myrtle Beach Yacht Club",
    "wof:placetype":"venue"
},
  "geometry": {"coordinates":[-78.640361,33.865871],"type":"Point"}
}