{
  "type": "Feature",
  "properties": {
    "iso:country":"US",
    "sg:address":"2578 Tuckaway Rd",
    "sg:city":"Rock Hill",
    "sg:classifiers":[
        {
            "category":"Recreation",
            "type":"Entertainment"
        }
    ],
    "sg:phone":"+1 803 327 1141",
    "sg:postcode":"29730",
    "sg:province":"SC",
    "sg:tags":[
        "course",
        "golf"
    ],
    "wof:name":"Pinetuck Golf Club Inc",
    "wof:placetype":"venue"
},
  "geometry": {"coordinates":[-81.01137900000001,34.834046],"type":"Point"}
}