{
  "type": "Feature",
  "properties": {
    "iso:country":"US",
    "sg:address":"1908 Piedmont Hwy",
    "sg:city":"Greenville",
    "sg:classifiers":[
        {
            "category":"Building & Trades",
            "subcategory":"Construction",
            "type":"Services"
        }
    ],
    "sg:phone":"+1 864 277 8612",
    "sg:postcode":"29605",
    "sg:province":"SC",
    "sg:tags":[
        "house"
    ],
    "wof:name":"Walton Builders Inc",
    "wof:placetype":"venue"
},
  "geometry": {"coordinates":[-82.42468599999999,34.790543],"type":"Point"}
}