{
  "type": "Feature",
  "properties": {
    "iso:country":"US",
    "sg:address":"1020 Bill Jones Rd",
    "sg:city":"Aynor",
    "sg:classifiers":[
        {
            "category":"Farming",
            "subcategory":"Farm",
            "type":"Manufacturing & Wholesale Goods"
        }
    ],
    "sg:phone":"+1 843 358 6688",
    "sg:postcode":"29511",
    "sg:province":"SC",
    "sg:tags":[
        "crop",
        "general"
    ],
    "wof:name":"Sandhill Farms LLC",
    "wof:placetype":"venue"
},
  "geometry": {"coordinates":[-79.163389,33.976322],"type":"Point"}
}