{
  "type": "Feature",
  "properties": {
    "addr:full":"112 E Main St Lamar SC 29069",
    "addr:housenumber":"112",
    "addr:postcode":"29069",
    "addr:street":"E Main St",
    "iso:country":"US",
    "sg:address":"112 E Main St",
    "sg:city":"Lamar",
    "sg:classifiers":[
        {
            "category":"Banks & Credit Unions",
            "subcategory":"Bank",
            "type":"Services"
        }
    ],
    "sg:phone":"+1 843 326 5557",
    "sg:postcode":"29069",
    "sg:province":"SC",
    "wof:name":"Carolina Bank & Trust Co",
    "wof:placetype":"venue"
},
  "geometry": {"coordinates":[-80.062579,34.168514],"type":"Point"}
}