{
  "type": "Feature",
  "properties": {
    "iso:country":"US",
    "sg:address":"931 Broad St",
    "sg:city":"Camden",
    "sg:classifiers":[
        {
            "category":"Professional",
            "subcategory":"Lawyer & Legal Services",
            "type":"Services"
        }
    ],
    "sg:phone":"+1 803 432 7111",
    "sg:postcode":"29020",
    "sg:province":"SC",
    "sg:tags":[
        "attorney"
    ],
    "wof:name":"Patrick D Partin Law Offices",
    "wof:placetype":"venue"
},
  "geometry": {"coordinates":[-80.60698499999999,34.244666],"type":"Point"}
}