{
  "type": "Feature",
  "properties": {
    "iso:country":"US",
    "sg:address":"2099 S Pine St",
    "sg:city":"Spartanburg",
    "sg:classifiers":[
        {
            "category":"Personal",
            "type":"Services"
        }
    ],
    "sg:phone":"+1 864 598 9966",
    "sg:postcode":"29302",
    "sg:province":"SC",
    "sg:tags":[
        "therapist",
        "massage"
    ],
    "wof:name":"Therapeutics Inc",
    "wof:placetype":"venue"
},
  "geometry": {"coordinates":[-81.895302,34.934394],"type":"Point"}
}