{
  "type": "Feature",
  "properties": {
    "addr:full":"1665 Main St Turbeville SC 29145",
    "addr:housenumber":"1665",
    "addr:postcode":"29145",
    "addr:street":"Main St",
    "iso:country":"US",
    "sg:address":"1665 Main St",
    "sg:city":"Turbeville",
    "sg:classifiers":[
        {
            "category":"Restaurant",
            "type":"Food & Drink"
        }
    ],
    "sg:phone":"+1 843 659 8788",
    "sg:postcode":"29145",
    "sg:province":"SC",
    "wof:name":"New Dragon Chinese Restaurant",
    "wof:placetype":"venue"
},
  "geometry": {"coordinates":[-81.722764,34.222048],"type":"Point"}
}