{
  "type": "Feature",
  "properties": {
    "iso:country":"US",
    "sg:address":"188 Clear Springs Ln",
    "sg:city":"Georgetown",
    "sg:classifiers":[
        {
            "category":"Building & Trades",
            "subcategory":"Construction",
            "type":"Services"
        }
    ],
    "sg:phone":"+1 843 240 9639",
    "sg:postcode":"29440",
    "sg:province":"SC",
    "sg:tags":[
        "house"
    ],
    "wof:name":"Quality Home Improvement",
    "wof:placetype":"venue"
},
  "geometry": {"coordinates":[-79.42224299999999,33.571465],"type":"Point"}
}