{
  "type": "Feature",
  "properties": {
    "iso:country":"US",
    "sg:address":"334 E Bay St",
    "sg:city":"Charleston",
    "sg:classifiers":[
        {
            "category":"Personal",
            "subcategory":"Tanning Parlor",
            "type":"Services"
        }
    ],
    "sg:phone":"+1 843 723 6292",
    "sg:postcode":"29401",
    "sg:province":"SC",
    "sg:tags":[
        "salon"
    ],
    "wof:name":"Ultra Tan",
    "wof:placetype":"venue"
},
  "geometry": {"coordinates":[-79.929047,32.786267],"type":"Point"}
}