{
  "type": "Feature",
  "properties": {
    "addr:full":"1605 Horry St Conway SC 29527",
    "addr:housenumber":"1605",
    "addr:postcode":"29527",
    "addr:street":"Horry St",
    "iso:country":"US",
    "sg:address":"1605 Horry St",
    "sg:city":"Conway",
    "sg:classifiers":[
        {
            "category":"Education",
            "subcategory":"School",
            "type":"Public Place"
        }
    ],
    "sg:phone":"+1 843 488 6700",
    "sg:postcode":"29527",
    "sg:province":"SC",
    "sg:tags":[
        "educational",
        "program"
    ],
    "wof:name":"Horry County Schools",
    "wof:placetype":"venue"
},
  "geometry": {"coordinates":[-79.071352,33.835139],"type":"Point"}
}