{
  "type": "Feature",
  "properties": {
    "addr:full":"10076 Calvin Hall Rd Fort Mill SC 29707",
    "addr:housenumber":"10076",
    "addr:postcode":"29707",
    "addr:street":"Calvin Hall Rd",
    "iso:country":"US",
    "sg:address":"10076 Calvin Hall Rd",
    "sg:city":"Fort Mill",
    "sg:classifiers":[
        {
            "category":"Wholesale",
            "subcategory":"Machinery & Supplies",
            "type":"Manufacturing & Wholesale Goods"
        }
    ],
    "sg:phone":"+1 803 548 2289",
    "sg:postcode":"29707",
    "sg:province":"SC",
    "sg:tags":[
        "industrial",
        "miscellaneous"
    ],
    "wof:name":"D & O Equipment Co Inc",
    "wof:placetype":"venue"
},
  "geometry": {"coordinates":[-80.96971000000001,35.07007],"type":"Point"}
}