{
  "type": "Feature",
  "properties": {
    "iso:country":"US",
    "sg:address":"1570 US Hwy 501 S",
    "sg:city":"Marion",
    "sg:classifiers":[
        {
            "category":"Manufacturing",
            "subcategory":"Chemicals & Compounds",
            "type":"Manufacturing & Wholesale Goods"
        }
    ],
    "sg:phone":"+1 843 423 6400",
    "sg:postcode":"29571",
    "sg:province":"SC",
    "sg:tags":[
        "preparation",
        "mfg"
    ],
    "wof:name":"Atlas Importers",
    "wof:placetype":"venue"
},
  "geometry": {"coordinates":[-79.36572700000001,34.128793],"type":"Point"}
}