{
  "type": "Feature",
  "properties": {
    "iso:country":"US",
    "sg:address":"570 US Hwy 25",
    "sg:city":"Travelers Rest",
    "sg:classifiers":[
        {
            "category":"Restaurant",
            "type":"Food & Drink"
        }
    ],
    "sg:phone":"+1 864 834 3909",
    "sg:postcode":"29690",
    "sg:province":"SC",
    "sg:tags":[
        "eating"
    ],
    "wof:name":"El Rancho Grande Mexican Rest",
    "wof:placetype":"venue"
},
  "geometry": {"coordinates":[-82.426405,34.980228],"type":"Point"}
}