{
  "type": "Feature",
  "properties": {
    "addr:full":"1184 Sherwood St North Charleston SC 29405",
    "addr:housenumber":"1184",
    "addr:postcode":"29405",
    "addr:street":"Sherwood St",
    "iso:country":"US",
    "sg:address":"1184 Sherwood St",
    "sg:city":"North Charleston",
    "sg:classifiers":[
        {
            "category":"Wholesale",
            "subcategory":"Vending Machines",
            "type":"Manufacturing & Wholesale Goods"
        }
    ],
    "sg:phone":"+1 843 744 6995",
    "sg:postcode":"29405",
    "sg:province":"SC",
    "sg:tags":[
        "operator"
    ],
    "wof:name":"Gore Vending",
    "wof:placetype":"venue"
},
  "geometry": {"coordinates":[-79.98469799999999,32.891335],"type":"Point"}
}