{
  "type": "Feature",
  "properties": {
    "iso:country":"US",
    "sg:address":"1206 Red Bank Rd",
    "sg:city":"Goose Creek",
    "sg:classifiers":[
        {
            "category":"Building & Trades",
            "subcategory":"Construction",
            "type":"Services"
        }
    ],
    "sg:phone":"+1 843 569 2229",
    "sg:postcode":"29445",
    "sg:province":"SC",
    "sg:tags":[
        "insulation",
        "heat",
        "contractor"
    ],
    "wof:name":"Carolina Custom Insulation",
    "wof:placetype":"venue"
},
  "geometry": {"coordinates":[-80.012834,32.970841],"type":"Point"}
}