{
  "type": "Feature",
  "properties": {
    "iso:country":"US",
    "sg:address":"1420 State St",
    "sg:city":"Cayce",
    "sg:classifiers":[
        {
            "category":"Organizations",
            "subcategory":"Religious Organization",
            "type":"Services"
        }
    ],
    "sg:phone":"+1 803 796 6123",
    "sg:postcode":"29033",
    "sg:province":"SC",
    "sg:tags":[
        "church"
    ],
    "wof:name":"State Street Baptist Church",
    "wof:placetype":"venue"
},
  "geometry": {"coordinates":[-81.054866,33.980331],"type":"Point"}
}