{
  "type": "Feature",
  "properties": {
    "addr:full":"1736 Augusta Rd North Augusta SC 29822",
    "addr:housenumber":"1736",
    "addr:postcode":"29822",
    "addr:street":"Augusta Rd",
    "iso:country":"US",
    "sg:address":"1736 Augusta Rd",
    "sg:city":"North Augusta",
    "sg:classifiers":[
        {
            "category":"Building & Trades",
            "subcategory":"Pest Control",
            "type":"Services"
        }
    ],
    "sg:phone":"+1 803 441 0007",
    "sg:postcode":"29822",
    "sg:province":"SC",
    "wof:name":"Jury Pest Control Svc",
    "wof:placetype":"venue"
},
  "geometry": {"coordinates":[-81.891949,33.496943],"type":"Point"}
}