{
  "type": "Feature",
  "properties": {
    "iso:country":"US",
    "sg:address":"6405 Laney Rd",
    "sg:city":"Lancaster",
    "sg:classifiers":[
        {
            "category":"Building & Trades",
            "subcategory":"Construction",
            "type":"Services"
        }
    ],
    "sg:phone":"+1 803 547 6583",
    "sg:postcode":"29720",
    "sg:province":"SC",
    "sg:tags":[
        "maker",
        "cabinet"
    ],
    "wof:name":"Collins Wood Cabinetry",
    "wof:placetype":"venue"
},
  "geometry": {"coordinates":[-80.828633,34.918215],"type":"Point"}
}