{
  "type": "Feature",
  "properties": {
    "addr:full":"3386 Hands Mill Hwy York SC 29745",
    "addr:housenumber":"3386",
    "addr:postcode":"29745",
    "addr:street":"Hands Mill Hwy",
    "iso:country":"US",
    "sg:address":"3386 Hands Mill Hwy",
    "sg:city":"York",
    "sg:classifiers":[
        {
            "category":"Manufacturing",
            "subcategory":"Motor Vehicles & Parts",
            "type":"Manufacturing & Wholesale Goods"
        }
    ],
    "sg:phone":"+1 803 831 1486",
    "sg:postcode":"29745",
    "sg:province":"SC",
    "sg:tags":[
        "mfg",
        "industrial",
        "mach"
    ],
    "wof:name":"A & K Rebuilders Company",
    "wof:placetype":"venue"
},
  "geometry": {"coordinates":[-81.092156,35.071982],"type":"Point"}
}