{
  "type": "Feature",
  "properties": {
    "iso:country":"US",
    "sg:address":"107 Westfield St",
    "sg:city":"Hartsville",
    "sg:classifiers":[
        {
            "category":"Shopping",
            "subcategory":"Department Store",
            "type":"Retail Goods"
        }
    ],
    "sg:phone":"+1 843 857 0909",
    "sg:postcode":"29550",
    "sg:province":"SC",
    "wof:name":"Sears Roebuck & Co",
    "wof:placetype":"venue"
},
  "geometry": {"coordinates":[-80.063243,34.362025],"type":"Point"}
}