{
  "type": "Feature",
  "properties": {
    "iso:country":"US",
    "sg:address":"3506 Bush River Rd",
    "sg:city":"Columbia",
    "sg:classifiers":[
        {
            "category":"Retail",
            "subcategory":"Portrait Studio",
            "type":"Services"
        }
    ],
    "sg:phone":"+1 803 791 4154",
    "sg:postcode":"29210",
    "sg:province":"SC",
    "sg:tags":[
        "photographer"
    ],
    "wof:name":"Barber Photography",
    "wof:placetype":"venue"
},
  "geometry": {"coordinates":[-81.141825,34.041153],"type":"Point"}
}