{
  "type": "Feature",
  "properties": {
    "iso:country":"US",
    "sg:address":"2229 Robinson View Dr",
    "sg:city":"Hartsville",
    "sg:classifiers":[
        {
            "category":"Farming",
            "subcategory":"Livestock Farm",
            "type":"Manufacturing & Wholesale Goods"
        }
    ],
    "sg:phone":"+1 843 332 9810",
    "sg:postcode":"29550",
    "sg:province":"SC",
    "sg:tags":[
        "beef",
        "feedlot",
        "cattle"
    ],
    "wof:name":"Haywood L Easterling",
    "wof:placetype":"venue"
},
  "geometry": {"coordinates":[-80.141742,34.424051],"type":"Point"}
}