{
  "type": "Feature",
  "properties": {
    "iso:country":"US",
    "sg:address":"2844 State Park Rd",
    "sg:city":"Greenville",
    "sg:classifiers":[
        {
            "category":"Building & Trades",
            "subcategory":"Construction",
            "type":"Services"
        }
    ],
    "sg:phone":"+1 864 322 8327",
    "sg:postcode":"29609",
    "sg:province":"SC",
    "sg:tags":[
        "house"
    ],
    "wof:name":"Woodworkers of Greenville",
    "wof:placetype":"venue"
},
  "geometry": {"coordinates":[-82.376649,34.939468],"type":"Point"}
}