{
  "type": "Feature",
  "properties": {
    "addr:full":"370 Pack Rd Sumter SC 29150",
    "addr:housenumber":"370",
    "addr:postcode":"29150",
    "addr:street":"Pack Rd",
    "iso:country":"US",
    "sg:address":"370 Pack Rd",
    "sg:city":"Sumter",
    "sg:classifiers":[
        {
            "category":"Building & Trades",
            "subcategory":"Landscaping Services",
            "type":"Services"
        }
    ],
    "sg:phone":"+1 803 481 8377",
    "sg:postcode":"29150",
    "sg:province":"SC",
    "sg:tags":[
        "tree"
    ],
    "wof:name":"L L Gore Burdick's Tree",
    "wof:placetype":"venue"
},
  "geometry": {"coordinates":[-80.343672,33.854282],"type":"Point"}
}