{
  "type": "Feature",
  "properties": {
    "iso:country":"US",
    "sg:address":"218 Quaker Rd",
    "sg:city":"Saint George",
    "sg:classifiers":[
        {
            "category":"Building & Trades",
            "subcategory":"Construction",
            "type":"Services"
        }
    ],
    "sg:phone":"+1 843 563 9195",
    "sg:postcode":"29477",
    "sg:province":"SC",
    "sg:tags":[
        "residential"
    ],
    "wof:name":"Arnold E Jones",
    "wof:placetype":"venue"
},
  "geometry": {"coordinates":[-80.57934,33.18029],"type":"Point"}
}