{
  "type": "Feature",
  "properties": {
    "addr:full":"341 Glenn Rd West Columbia SC 29172",
    "addr:housenumber":"341",
    "addr:postcode":"29172",
    "addr:street":"Glenn Rd",
    "iso:country":"US",
    "sg:address":"341 Glenn Rd",
    "sg:city":"West Columbia",
    "sg:classifiers":[
        {
            "category":"Real Estate",
            "subcategory":"Surveying",
            "type":"Services"
        }
    ],
    "sg:phone":"+1 803 796 5384",
    "sg:postcode":"29172",
    "sg:province":"SC",
    "sg:tags":[
        "surveyor"
    ],
    "wof:name":"Donald G Platt & Assoc",
    "wof:placetype":"venue"
},
  "geometry": {"coordinates":[-81.07583,33.87807],"type":"Point"}
}