{
  "type": "Feature",
  "properties": {
    "iso:country":"US",
    "sg:address":"1426 Geiger Ave",
    "sg:city":"Columbia",
    "sg:classifiers":[
        {
            "category":"Real Estate",
            "subcategory":"Architect",
            "type":"Services"
        }
    ],
    "sg:phone":"+1 803 771 6862",
    "sg:postcode":"29201",
    "sg:province":"SC",
    "sg:tags":[
        "building",
        "construction"
    ],
    "wof:name":"Pareto Associates Inc",
    "wof:placetype":"venue"
},
  "geometry": {"coordinates":[-81.03946,34.0221],"type":"Point"}
}