{
  "type": "Feature",
  "properties": {
    "iso:country":"US",
    "sg:address":"684 County Line Rd",
    "sg:city":"Cross",
    "sg:classifiers":[
        {
            "category":"Freight",
            "type":"Transportation"
        }
    ],
    "sg:phone":"+1 843 753 3287",
    "sg:postcode":"29436",
    "sg:province":"SC",
    "sg:tags":[
        "operator",
        "local",
        "trucking"
    ],
    "wof:name":"Low Country Trucking",
    "wof:placetype":"venue"
},
  "geometry": {"coordinates":[-80.240202,33.365406],"type":"Point"}
}