{
  "type": "Feature",
  "properties": {
    "addr:full":"792 Folly Rd Charleston SC 29412",
    "addr:housenumber":"792",
    "addr:postcode":"29412",
    "addr:street":"Folly Rd",
    "iso:country":"US",
    "sg:address":"792 Folly Rd",
    "sg:city":"Charleston",
    "sg:classifiers":[
        {
            "category":"Professional",
            "subcategory":"Accounting & Tax Preparation",
            "type":"Services"
        }
    ],
    "sg:phone":"+1 843 795 2242",
    "sg:postcode":"29412",
    "sg:province":"SC",
    "sg:tags":[
        "accountant"
    ],
    "wof:name":"Edward Mack CPA",
    "wof:placetype":"venue"
},
  "geometry": {"coordinates":[-79.967192,32.740199],"type":"Point"}
}