{
  "type": "Feature",
  "properties": {
    "addr:full":"1026 Broad St Camden SC 29020",
    "addr:housenumber":"1026",
    "addr:postcode":"29020",
    "addr:street":"Broad St",
    "iso:country":"US",
    "sg:address":"1026 Broad St",
    "sg:city":"Camden",
    "sg:classifiers":[
        {
            "category":"Shopping",
            "subcategory":"Clothing, Apparel, & Fashions",
            "type":"Retail Goods"
        }
    ],
    "sg:phone":"+1 803 432 9169",
    "sg:postcode":"29020",
    "sg:province":"SC",
    "sg:tags":[
        "furnishing"
    ],
    "wof:name":"G Q Fashions",
    "wof:placetype":"venue"
},
  "geometry": {"coordinates":[-80.606965,34.24591],"type":"Point"}
}