{
  "type": "Feature",
  "properties": {
    "iso:country":"US",
    "sg:address":"2600 Hunters Ridge Dr",
    "sg:city":"Florence",
    "sg:classifiers":[
        {
            "category":"Professional",
            "type":"Services"
        }
    ],
    "sg:phone":"+1 843 667 9275",
    "sg:postcode":"29506",
    "sg:province":"SC",
    "wof:name":"Walker Industrial Svc",
    "wof:placetype":"venue"
},
  "geometry": {"coordinates":[-79.69171,34.295327],"type":"Point"}
}