{
  "type": "Feature",
  "properties": {
    "addr:full":"508 Pearl St Darlington SC 29532",
    "addr:housenumber":"508",
    "addr:postcode":"29532",
    "addr:street":"Pearl St",
    "iso:country":"US",
    "sg:address":"508 Pearl St",
    "sg:city":"Darlington",
    "sg:classifiers":[
        {
            "category":"Banks & Credit Unions",
            "subcategory":"Bank",
            "type":"Services"
        }
    ],
    "sg:phone":"+1 843 395 6004",
    "sg:postcode":"29532",
    "sg:province":"SC",
    "sg:tags":[
        "cashing",
        "check"
    ],
    "wof:name":"Check 'n Go",
    "wof:placetype":"venue"
},
  "geometry": {"coordinates":[-79.87747299999999,34.299476],"type":"Point"}
}