{
  "type": "Feature",
  "properties": {
    "addr:full":"361 W Pine St Varnville SC 29944",
    "addr:housenumber":"361",
    "addr:postcode":"29944",
    "addr:street":"W Pine St",
    "iso:country":"US",
    "sg:address":"361 W Pine St",
    "sg:city":"Varnville",
    "sg:classifiers":[
        {
            "category":"Recreation",
            "type":"Entertainment"
        }
    ],
    "sg:phone":"+1 803 943 2857",
    "sg:postcode":"29944",
    "sg:province":"SC",
    "sg:tags":[
        "parks"
    ],
    "wof:name":"Hampton Recreation Dept",
    "wof:placetype":"venue"
},
  "geometry": {"coordinates":[-81.082514,32.854981],"type":"Point"}
}