{
  "type": "Feature",
  "properties": {
    "iso:country":"US",
    "sg:address":"466 W Cheves St",
    "sg:city":"Florence",
    "sg:classifiers":[
        {
            "category":"Manufacturing",
            "subcategory":"Printing",
            "type":"Manufacturing & Wholesale Goods"
        }
    ],
    "sg:phone":"+1 843 667 1818",
    "sg:postcode":"29501",
    "sg:province":"SC",
    "sg:tags":[
        "publisher"
    ],
    "wof:name":"Dbs Communications Inc",
    "wof:placetype":"venue"
},
  "geometry": {"coordinates":[-79.773463,34.195126],"type":"Point"}
}