{
  "type": "Feature",
  "properties": {
    "iso:country":"US",
    "sg:address":"258 S Church St",
    "sg:city":"Spartanburg",
    "sg:classifiers":[
        {
            "category":"Government",
            "subcategory":"Office",
            "type":"Public Place"
        }
    ],
    "sg:phone":"+1 864 596 2561",
    "sg:postcode":"29306",
    "sg:province":"SC",
    "wof:name":"Spartanburg County Defenders",
    "wof:placetype":"venue"
},
  "geometry": {"coordinates":[-81.928978,34.944346],"type":"Point"}
}