{
  "type": "Feature",
  "properties": {
    "addr:full":"5019 Wesley Rd Murrells Inlet SC 29576",
    "addr:housenumber":"5019",
    "addr:postcode":"29576",
    "addr:street":"Wesley Rd",
    "iso:country":"US",
    "sg:address":"5019 Wesley Rd",
    "sg:city":"Murrells Inlet",
    "sg:classifiers":[
        {
            "category":"Utilities",
            "subcategory":"Refuse",
            "type":"Services"
        }
    ],
    "sg:phone":"+1 843 651 0872",
    "sg:postcode":"29576",
    "sg:province":"SC",
    "sg:tags":[
        "system"
    ],
    "wof:name":"Murrell Inlet Recycling Center",
    "wof:placetype":"venue"
},
  "geometry": {"coordinates":[-79.057723,33.546538],"type":"Point"}
}