{
  "type": "Feature",
  "properties": {
    "addr:full":"705 S Oak St Seneca SC 29678",
    "addr:housenumber":"705",
    "addr:postcode":"29678",
    "addr:street":"S Oak St",
    "iso:country":"US",
    "sg:address":"705 S Oak St",
    "sg:city":"Seneca",
    "sg:classifiers":[
        {
            "category":"Food & Beverages",
            "subcategory":"Groceries & Convenience Stores",
            "type":"Retail Goods"
        }
    ],
    "sg:phone":"+1 864 882 7617",
    "sg:postcode":"29678",
    "sg:province":"SC",
    "sg:tags":[
        "grocer"
    ],
    "wof:name":"Rudy's",
    "wof:placetype":"venue"
},
  "geometry": {"coordinates":[-82.95524,34.676457],"type":"Point"}
}