{
  "type": "Feature",
  "properties": {
    "iso:country":"US",
    "sg:address":"1010 Renwood Dr",
    "sg:city":"Charleston",
    "sg:classifiers":[
        {
            "category":"Building & Trades",
            "subcategory":"Landscaping Services",
            "type":"Services"
        }
    ],
    "sg:phone":"+1 843 795 3063",
    "sg:postcode":"29412",
    "sg:province":"SC",
    "sg:tags":[
        "landscape",
        "contractor"
    ],
    "wof:name":"Suncoast Irrigation",
    "wof:placetype":"venue"
},
  "geometry": {"coordinates":[-79.958573,32.730315],"type":"Point"}
}