{
  "type": "Feature",
  "properties": {
    "addr:full":"410 Charles St Charleston SC 29432",
    "addr:housenumber":"410",
    "addr:postcode":"29432",
    "addr:street":"Charles St",
    "iso:country":"US",
    "sg:address":"410 Charles St",
    "sg:city":"Charleston",
    "sg:classifiers":[
        {
            "category":"Building & Trades",
            "subcategory":"Construction",
            "type":"Services"
        }
    ],
    "sg:phone":"+1 843 556 6530",
    "sg:postcode":"29432",
    "sg:province":"SC",
    "sg:tags":[
        "painter"
    ],
    "wof:name":"Mike's Painting",
    "wof:placetype":"venue"
},
  "geometry": {"coordinates":[-80.822014,33.253515],"type":"Point"}
}