{
  "type": "Feature",
  "properties": {
    "addr:full":"408 Hibben St Mt Pleasant SC 29464",
    "addr:housenumber":"408",
    "addr:postcode":"29464",
    "addr:street":"Hibben St",
    "iso:country":"US",
    "sg:address":"408 Hibben St",
    "sg:city":"Mt Pleasant",
    "sg:classifiers":[
        {
            "category":"Personal",
            "subcategory":"Beauty Salon",
            "type":"Services"
        }
    ],
    "sg:phone":"+1 843 388 0100",
    "sg:postcode":"29464",
    "sg:province":"SC",
    "wof:name":"Pink House Salon",
    "wof:placetype":"venue"
},
  "geometry": {"coordinates":[-79.87746799999999,32.789815],"type":"Point"}
}