{
  "type": "Feature",
  "properties": {
    "iso:country":"US",
    "sg:address":"133 Baker St",
    "sg:city":"Blackville",
    "sg:classifiers":[
        {
            "category":"Personal",
            "subcategory":"Beauty Salon",
            "type":"Services"
        }
    ],
    "sg:phone":"+1 803 284 2858",
    "sg:postcode":"29817",
    "sg:province":"SC",
    "wof:name":"Vogue Beauty Shop",
    "wof:placetype":"venue"
},
  "geometry": {"coordinates":[-81.266398,33.355098],"type":"Point"}
}