{
  "type": "Feature",
  "properties": {
    "iso:country":"US",
    "sg:address":"430 Tannenbaum Rd",
    "sg:city":"Ravenel",
    "sg:classifiers":[
        {
            "category":"Insurance",
            "subcategory":"Insurance Agent",
            "type":"Services"
        }
    ],
    "sg:phone":"+1 843 769 2336",
    "sg:postcode":"29470",
    "sg:province":"SC",
    "wof:name":"Allstate",
    "wof:placetype":"venue"
},
  "geometry": {"coordinates":[-80.23715900000001,32.847141],"type":"Point"}
}