{
  "type": "Feature",
  "properties": {
    "addr:full":"1749 Marshall St Columbia SC 29203",
    "addr:housenumber":"1749",
    "addr:postcode":"29203",
    "addr:street":"Marshall St",
    "iso:country":"US",
    "sg:address":"1749 Marshall St",
    "sg:city":"Columbia",
    "sg:classifiers":[
        {
            "category":"Health Services",
            "subcategory":"Doctor",
            "type":"Services"
        }
    ],
    "sg:phone":"+1 803 252 1801",
    "sg:postcode":"29203",
    "sg:province":"SC",
    "wof:name":"Hutchinson Kyllan MD",
    "wof:placetype":"venue"
},
  "geometry": {"coordinates":[-81.032917,34.0302],"type":"Point"}
}