{
  "type": "Feature",
  "properties": {
    "addr:full":"1620 Hemingway Hwy Hemingway SC 29554",
    "addr:housenumber":"1620",
    "addr:postcode":"29554",
    "addr:street":"Hemingway Hwy",
    "iso:country":"US",
    "sg:address":"1620 Hemingway Hwy",
    "sg:city":"Hemingway",
    "sg:classifiers":[
        {
            "category":"Autos & Motor Vehicles",
            "subcategory":"Automobile Sales",
            "type":"Retail Goods"
        }
    ],
    "sg:phone":"+1 843 558 5243",
    "sg:postcode":"29554",
    "sg:province":"SC",
    "sg:tags":[
        "car",
        "dealer"
    ],
    "wof:name":"Mutt's Used Cars",
    "wof:placetype":"venue"
},
  "geometry": {"coordinates":[-79.43028099999999,33.754032],"type":"Point"}
}