{
  "type": "Feature",
  "properties": {
    "iso:country":"US",
    "sg:address":"609 N Townville St",
    "sg:city":"Seneca",
    "sg:classifiers":[
        {
            "category":"Government",
            "subcategory":"Office",
            "type":"Public Place"
        }
    ],
    "sg:phone":"+1 864 882 2245",
    "sg:postcode":"29678",
    "sg:province":"SC",
    "sg:tags":[
        "county",
        "program",
        "health"
    ],
    "wof:name":"Oconee County Health Dept",
    "wof:placetype":"venue"
},
  "geometry": {"coordinates":[-82.954009,34.691395],"type":"Point"}
}