{
  "type": "Feature",
  "properties": {
    "iso:country":"US",
    "sg:address":"1594 State Rd",
    "sg:city":"Summerville",
    "sg:classifiers":[
        {
            "category":"Manufacturing",
            "subcategory":"Metals",
            "type":"Manufacturing & Wholesale Goods"
        }
    ],
    "sg:phone":"+1 843 761 2990",
    "sg:postcode":"29483",
    "sg:province":"SC",
    "sg:tags":[
        "foundry"
    ],
    "wof:name":"J & M Foundry Inc",
    "wof:placetype":"venue"
},
  "geometry": {"coordinates":[-80.119433,33.095182],"type":"Point"}
}