{
  "type": "Feature",
  "properties": {
    "iso:country":"US",
    "sg:address":"3000 W Blue Ridge Dr",
    "sg:city":"Greenville",
    "sg:classifiers":[
        {
            "category":"Shopping",
            "subcategory":"Hobbies, Toys, & Games",
            "type":"Retail Goods"
        }
    ],
    "sg:phone":"+1 864 269 7176",
    "sg:postcode":"29611",
    "sg:province":"SC",
    "sg:tags":[
        "supply"
    ],
    "wof:name":"Scientific Games",
    "wof:placetype":"venue"
},
  "geometry": {"coordinates":[-82.441975,34.857445],"type":"Point"}
}