{
  "type": "Feature",
  "properties": {
    "iso:country":"US",
    "sg:address":"6080 Garners Ferry Rd",
    "sg:city":"Columbia",
    "sg:classifiers":[
        {
            "category":"Restaurant",
            "type":"Food & Drink"
        },
        {
            "category":"Bakery",
            "type":"Food & Drink"
        }
    ],
    "sg:menulink":"http://www.allmenus.com/sc/columbia/93687-panera-bread/menu/",
    "sg:phone":"+1 803 647 9722",
    "sg:postcode":"29209",
    "sg:province":"SC",
    "sg:tags":[
        "american",
        "sandwich",
        "bakery",
        "pastry"
    ],
    "wof:name":"Panera Bread",
    "wof:placetype":"venue"
},
  "geometry": {"coordinates":[-80.964803,33.98216],"type":"Point"}
}