{
  "type": "Feature",
  "properties": {
    "addr:full":"607 Maple St Columbia SC 29205",
    "addr:housenumber":"607",
    "addr:postcode":"29205",
    "addr:street":"Maple St",
    "iso:country":"US",
    "sg:address":"607 Maple St",
    "sg:city":"Columbia",
    "sg:classifiers":[
        {
            "category":"Organizations",
            "subcategory":"Professional Association",
            "type":"Services"
        }
    ],
    "sg:phone":"+1 803 256 3869",
    "sg:postcode":"29205",
    "sg:province":"SC",
    "wof:name":"Alpha ETA State",
    "wof:placetype":"venue"
},
  "geometry": {"coordinates":[-81.003444,33.997354],"type":"Point"}
}