{
  "type": "Feature",
  "properties": {
    "iso:country":"US",
    "sg:address":"1325 Lamar Hwy",
    "sg:city":"Darlington",
    "sg:classifiers":[
        {
            "category":"Autos & Motor Vehicles",
            "subcategory":"Automobile Sales",
            "type":"Retail Goods"
        }
    ],
    "sg:phone":"+1 843 393 0404",
    "sg:postcode":"29532",
    "sg:province":"SC",
    "sg:tags":[
        "car",
        "dealer"
    ],
    "wof:name":"Victory Auto Sales",
    "wof:placetype":"venue"
},
  "geometry": {"coordinates":[-79.90583100000001,34.279812],"type":"Point"}
}