{
  "type": "Feature",
  "properties": {
    "iso:country":"US",
    "sg:address":"1909 N Highway 17",
    "sg:city":"Mount Pleasant",
    "sg:classifiers":[
        {
            "category":"Restaurant",
            "type":"Food & Drink"
        }
    ],
    "sg:menulink":"http://www.allmenus.com/sc/mount-pleasant/215161-taco-bell/menu/",
    "sg:phone":"+1 843 971 5444",
    "sg:postcode":"29464",
    "sg:province":"SC",
    "sg:tags":[
        "mexican"
    ],
    "wof:name":"Taco Bell",
    "wof:placetype":"venue"
},
  "geometry": {"coordinates":[-79.826492,32.831187],"type":"Point"}
}