{
  "type": "Feature",
  "properties": {
    "iso:country":"US",
    "sg:address":"644 Bultman Dr",
    "sg:city":"Sumter",
    "sg:classifiers":[
        {
            "category":"Professional",
            "subcategory":"Testing Lab",
            "type":"Services"
        }
    ],
    "sg:phone":"+1 803 775 5899",
    "sg:postcode":"29150",
    "sg:province":"SC",
    "sg:tags":[
        "laboratory"
    ],
    "wof:name":"Sumter Industrial Diagnostics",
    "wof:placetype":"venue"
},
  "geometry": {"coordinates":[-80.371689,33.939213],"type":"Point"}
}