{
  "type": "Feature",
  "properties": {
    "addr:full":"3507 Main St Columbia SC 29203",
    "addr:housenumber":"3507",
    "addr:postcode":"29203",
    "addr:street":"Main St",
    "iso:country":"US",
    "sg:address":"3507 Main St",
    "sg:city":"Columbia",
    "sg:classifiers":[
        {
            "category":"Restaurant",
            "type":"Food & Drink"
        }
    ],
    "sg:menulink":"http://www.allmenus.com/sc/columbia/176673-kfc---kentucky-fried-chicken/menu/",
    "sg:phone":"+1 803 252 2257",
    "sg:postcode":"29203",
    "sg:province":"SC",
    "sg:tags":[
        "american",
        "chicken"
    ],
    "wof:name":"KFC - Kentucky Fried Chicken",
    "wof:placetype":"venue"
},
  "geometry": {"coordinates":[-81.04250500000001,34.032348],"type":"Point"}
}