{
  "type": "Feature",
  "properties": {
    "iso:country":"US",
    "sg:address":"1094 US Hwy 123",
    "sg:city":"Seneca",
    "sg:classifiers":[
        {
            "category":"Banks & Credit Unions",
            "subcategory":"Bank",
            "type":"Services"
        }
    ],
    "sg:phone":"+1 864 882 3992",
    "sg:postcode":"29678",
    "sg:province":"SC",
    "wof:name":"Palmetto Bank",
    "wof:placetype":"venue"
},
  "geometry": {"coordinates":[-82.980177,34.693188],"type":"Point"}
}