{
  "type": "Feature",
  "properties": {
    "iso:country":"US",
    "sg:address":"524 Grove Rd",
    "sg:city":"Greenville",
    "sg:classifiers":[
        {
            "category":"Real Estate",
            "subcategory":"Real Estate Agent",
            "type":"Services"
        }
    ],
    "sg:phone":"+1 864 380 7278",
    "sg:postcode":"29605",
    "sg:province":"SC",
    "wof:name":"S & H of South Carolina LLC",
    "wof:placetype":"venue"
},
  "geometry": {"coordinates":[-82.41028300000001,34.822861],"type":"Point"}
}