{
  "type": "Feature",
  "properties": {
    "iso:country":"US",
    "sg:address":"1006 6th Ave S",
    "sg:city":"North Myrtle Bch",
    "sg:classifiers":[
        {
            "category":"Professional",
            "subcategory":"Engineering",
            "type":"Services"
        }
    ],
    "sg:phone":"+1 843 272 6599",
    "sg:postcode":"29582",
    "sg:province":"SC",
    "sg:tags":[
        "engineer"
    ],
    "wof:name":"Weaver Engineering Corp",
    "wof:placetype":"venue"
},
  "geometry": {"coordinates":[-78.686513,33.826021],"type":"Point"}
}