{
  "type": "Feature",
  "properties": {
    "iso:country":"US",
    "sg:address":"2150 Northwoods Blvd",
    "sg:city":"North Charleston",
    "sg:classifiers":[
        {
            "category":"Personal",
            "subcategory":"Beauty Salon",
            "type":"Services"
        }
    ],
    "sg:phone":"+1 843 863 0766",
    "sg:postcode":"29406",
    "sg:province":"SC",
    "sg:tags":[
        "treatment",
        "skin"
    ],
    "wof:name":"Proactiv",
    "wof:placetype":"venue"
},
  "geometry": {"coordinates":[-80.045611,32.942437],"type":"Point"}
}