{
  "type": "Feature",
  "properties": {
    "addr:full":"309 E Main St Bennettsville SC 29512",
    "addr:housenumber":"309",
    "addr:postcode":"29512",
    "addr:street":"E Main St",
    "iso:country":"US",
    "sg:address":"309 E Main St",
    "sg:city":"Bennettsville",
    "sg:classifiers":[
        {
            "category":"Organizations",
            "subcategory":"Non-profit Organization",
            "type":"Services"
        }
    ],
    "sg:phone":"+1 843 479 5979",
    "sg:postcode":"29512",
    "sg:province":"SC",
    "sg:website":"www.marlborohospice.org",
    "wof:name":"Helping Hands Hospice",
    "wof:placetype":"venue"
},
  "geometry": {"coordinates":[-79.68167699999999,34.617768],"type":"Point"}
}