{
  "type": "Feature",
  "properties": {
    "addr:full":"7709 Wilson Blvd Columbia SC 29203",
    "addr:housenumber":"7709",
    "addr:postcode":"29203",
    "addr:street":"Wilson Blvd",
    "iso:country":"US",
    "sg:address":"7709 Wilson Blvd",
    "sg:city":"Columbia",
    "sg:classifiers":[
        {
            "category":"Organizations",
            "subcategory":"Religious Organization",
            "type":"Services"
        }
    ],
    "sg:phone":"+1 803 786 2800",
    "sg:postcode":"29203",
    "sg:province":"SC",
    "sg:tags":[
        "church"
    ],
    "wof:name":"Ephesus Seventh Day Adventist",
    "wof:placetype":"venue"
},
  "geometry": {"coordinates":[-80.99722800000001,34.078902],"type":"Point"}
}