{
  "type": "Feature",
  "properties": {
    "iso:country":"US",
    "sg:address":"1011 Seay Rd",
    "sg:city":"Inman",
    "sg:classifiers":[
        {
            "category":"Building & Trades",
            "subcategory":"Construction",
            "type":"Services"
        }
    ],
    "sg:phone":"+1 864 599 9374",
    "sg:postcode":"29349",
    "sg:province":"SC",
    "sg:tags":[
        "siding",
        "contractor"
    ],
    "wof:name":"Tim Miller's Siding & Constr",
    "wof:placetype":"venue"
},
  "geometry": {"coordinates":[-82.013087,35.065443],"type":"Point"}
}