{
  "type": "Feature",
  "properties": {
    "addr:full":"115 Rochester Hwy Seneca SC 29672",
    "addr:housenumber":"115",
    "addr:postcode":"29672",
    "addr:street":"Rochester Hwy",
    "iso:country":"US",
    "sg:address":"115 Rochester Hwy",
    "sg:city":"Seneca",
    "sg:classifiers":[
        {
            "category":"Food & Beverages",
            "subcategory":"Groceries & Convenience Stores",
            "type":"Retail Goods"
        }
    ],
    "sg:phone":"+1 864 882 8420",
    "sg:postcode":"29672",
    "sg:province":"SC",
    "sg:tags":[
        "supermarket",
        "chain"
    ],
    "wof:name":"Bi-Lo 419",
    "wof:placetype":"venue"
},
  "geometry": {"coordinates":[-82.93829700000001,34.700833],"type":"Point"}
}