{
  "type": "Feature",
  "properties": {
    "iso:country":"US",
    "sg:address":"1532 Berkeley Rd",
    "sg:city":"Columbia",
    "sg:classifiers":[
        {
            "category":"Real Estate",
            "subcategory":"Real Estate Agent",
            "type":"Services"
        }
    ],
    "sg:phone":"+1 803 360 8031",
    "sg:postcode":"29205",
    "sg:province":"SC",
    "wof:name":"Andrew Keenan Real Estate Co",
    "wof:placetype":"venue"
},
  "geometry": {"coordinates":[-80.99161700000001,34.007698],"type":"Point"}
}