{
  "type": "Feature",
  "properties": {
    "addr:full":"2042 Woodstock Dr Columbia SC 29223",
    "addr:housenumber":"2042",
    "addr:postcode":"29223",
    "addr:street":"Woodstock Dr",
    "iso:country":"US",
    "sg:address":"2042 Woodstock Dr",
    "sg:city":"Columbia",
    "sg:classifiers":[
        {
            "category":"Personal",
            "type":"Services"
        }
    ],
    "sg:phone":"+1 803 736 9878",
    "sg:postcode":"29223",
    "sg:province":"SC",
    "sg:tags":[
        "control",
        "weight"
    ],
    "wof:name":"Overeaters Anonymous",
    "wof:placetype":"venue"
},
  "geometry": {"coordinates":[-80.91756100000001,34.064882],"type":"Point"}
}