{
  "type": "Feature",
  "properties": {
    "addr:full":"2360 Celanese Rd Rock Hill SC 29732",
    "addr:housenumber":"2360",
    "addr:postcode":"29732",
    "addr:street":"Celanese Rd",
    "iso:country":"US",
    "sg:address":"2360 Celanese Rd",
    "sg:city":"Rock Hill",
    "sg:classifiers":[
        {
            "category":"Restaurant",
            "type":"Food & Drink"
        }
    ],
    "sg:menulink":"http://www.allmenus.com/sc/rock-hill/56019-la-fiesta/menu/",
    "sg:phone":"+1 803 329 0313",
    "sg:postcode":"29732",
    "sg:province":"SC",
    "sg:tags":[
        "mexican"
    ],
    "wof:name":"La Fiesta",
    "wof:placetype":"venue"
},
  "geometry": {"coordinates":[-81.015811,34.976678],"type":"Point"}
}