{
  "type": "Feature",
  "properties": {
    "iso:country":"US",
    "sg:address":"160 Shuler Belt Rd",
    "sg:city":"Holly Hill",
    "sg:phone":"+1 803 496 5116",
    "sg:postcode":"29059",
    "sg:province":"SC",
    "sg:tags":[
        "farm"
    ],
    "wof:name":"Hutto R Barry Farm",
    "wof:placetype":"venue"
},
  "geometry": {"coordinates":[-80.527492,33.380294],"type":"Point"}
}