{
  "type": "Feature",
  "properties": {
    "iso:country":"US",
    "sg:address":"10383 Dunbarton Blvd",
    "sg:city":"Barnwell",
    "sg:classifiers":[
        {
            "category":"Professional",
            "subcategory":"Accounting & Tax Preparation",
            "type":"Services"
        }
    ],
    "sg:phone":"+1 803 259 1335",
    "sg:postcode":"29812",
    "sg:province":"SC",
    "sg:tags":[
        "return",
        "filing"
    ],
    "wof:name":"H & R Block Tax Svc",
    "wof:placetype":"venue"
},
  "geometry": {"coordinates":[-81.374523,33.244088],"type":"Point"}
}