{
  "type": "Feature",
  "properties": {
    "iso:country":"US",
    "sg:address":"41 S Beach Lagoon Dr",
    "sg:city":"Hilton Head Isle",
    "sg:classifiers":[
        {
            "category":"Professional",
            "type":"Services"
        }
    ],
    "sg:phone":"+1 843 671 4982",
    "sg:postcode":"29928",
    "sg:province":"SC",
    "sg:tags":[
        "establishment"
    ],
    "wof:name":"T Beach Lagoon",
    "wof:placetype":"venue"
},
  "geometry": {"coordinates":[-80.79524000000001,32.120635],"type":"Point"}
}