{
  "type": "Feature",
  "properties": {
    "iso:country":"US",
    "sg:address":"981 Chinaberry Rd",
    "sg:city":"Johnsonville",
    "sg:classifiers":[
        {
            "category":"Organizations",
            "subcategory":"Religious Organization",
            "type":"Services"
        }
    ],
    "sg:phone":"+1 843 493 2645",
    "sg:postcode":"29555",
    "sg:province":"SC",
    "sg:tags":[
        "church"
    ],
    "wof:name":"Pentecostal United Church",
    "wof:placetype":"venue"
},
  "geometry": {"coordinates":[-79.485108,33.903707],"type":"Point"}
}