{
  "type": "Feature",
  "properties": {
    "addr:full":"766 Daniel Ellis Dr Charleston SC 29412",
    "addr:housenumber":"766",
    "addr:postcode":"29412",
    "addr:street":"Daniel Ellis Dr",
    "iso:country":"US",
    "sg:address":"766 Daniel Ellis Dr",
    "sg:city":"Charleston",
    "sg:classifiers":[
        {
            "category":"Banks & Credit Unions",
            "subcategory":"Bank",
            "type":"Services"
        }
    ],
    "sg:phone":"+1 843 000 1111",
    "sg:postcode":"29412",
    "sg:province":"SC",
    "wof:name":"Heritage Trust Federal CU",
    "wof:placetype":"venue"
},
  "geometry": {"coordinates":[-79.96990099999999,32.748448],"type":"Point"}
}