{
  "type": "Feature",
  "properties": {
    "iso:country":"US",
    "sg:address":"130 Church St",
    "sg:city":"Honea Path",
    "sg:classifiers":[
        {
            "category":"Real Estate",
            "subcategory":"Real Estate Operator",
            "type":"Services"
        }
    ],
    "sg:phone":"+1 864 369 2444",
    "sg:postcode":"29654",
    "sg:province":"SC",
    "sg:tags":[
        "building",
        "nonresidential"
    ],
    "wof:name":"Corner Creek Properties",
    "wof:placetype":"venue"
},
  "geometry": {"coordinates":[-82.390964,34.444338],"type":"Point"}
}