{
  "type": "Feature",
  "properties": {
    "iso:country":"US",
    "sg:address":"99 S Harris Rd",
    "sg:city":"Piedmont",
    "sg:classifiers":[
        {
            "category":"Wholesale",
            "subcategory":"Auto Parts",
            "type":"Manufacturing & Wholesale Goods"
        }
    ],
    "sg:phone":"+1 864 299 5011",
    "sg:postcode":"29673",
    "sg:province":"SC",
    "sg:tags":[
        "laboratory",
        "testing"
    ],
    "wof:name":"Smithers Greenville Test Ctr",
    "wof:placetype":"venue"
},
  "geometry": {"coordinates":[-82.380527,34.729367],"type":"Point"}
}