{
  "type": "Feature",
  "properties": {
    "addr:full":"92 Spring St Charleston SC 29403",
    "addr:housenumber":"92",
    "addr:postcode":"29403",
    "addr:street":"Spring St",
    "iso:country":"US",
    "sg:address":"92 Spring St",
    "sg:city":"Charleston",
    "sg:classifiers":[
        {
            "category":"Personal",
            "subcategory":"Beauty Salon",
            "type":"Services"
        }
    ],
    "sg:phone":"+1 843 722 6865",
    "sg:postcode":"29403",
    "sg:province":"SC",
    "wof:name":"Casa Bella Beauty Salon",
    "wof:placetype":"venue"
},
  "geometry": {"coordinates":[-79.94546099999999,32.791196],"type":"Point"}
}