{
  "type": "Feature",
  "properties": {
    "iso:country":"US",
    "sg:address":"1108 Lykes Ln",
    "sg:city":"Irmo",
    "sg:classifiers":[
        {
            "category":"Wholesale",
            "subcategory":"Furniture",
            "type":"Manufacturing & Wholesale Goods"
        }
    ],
    "sg:phone":"+1 803 749 0419",
    "sg:postcode":"29063",
    "sg:province":"SC",
    "wof:name":"Interior Dimensions",
    "wof:placetype":"venue"
},
  "geometry": {"coordinates":[-81.152933,34.101131],"type":"Point"}
}