{
  "type": "Feature",
  "properties": {
    "iso:country":"US",
    "sg:address":"1397 S University Dr",
    "sg:city":"Ladson",
    "sg:classifiers":[
        {
            "category":"Shopping",
            "subcategory":"Clothing, Apparel, & Fashions",
            "type":"Retail Goods"
        }
    ],
    "sg:phone":"+1 843 747 6756",
    "sg:postcode":"29456",
    "sg:province":"SC",
    "sg:tags":[
        "uniform"
    ],
    "wof:name":"Frank's Uniforms",
    "wof:placetype":"venue"
},
  "geometry": {"coordinates":[-80.088672,33.021008],"type":"Point"}
}