{
  "type": "Feature",
  "properties": {
    "addr:full":"1040 Gardner Rd Charleston SC 29407",
    "addr:housenumber":"1040",
    "addr:postcode":"29407",
    "addr:street":"Gardner Rd",
    "iso:country":"US",
    "sg:address":"1040 Gardner Rd",
    "sg:city":"Charleston",
    "sg:classifiers":[
        {
            "category":"Home & Garden",
            "subcategory":"Carpets & Floor Coverings",
            "type":"Retail Goods"
        }
    ],
    "sg:phone":"+1 843 571 2885",
    "sg:postcode":"29407",
    "sg:province":"SC",
    "sg:tags":[
        "material",
        "laying",
        "contractor"
    ],
    "wof:name":"Flanders Carpet LLC",
    "wof:placetype":"venue"
},
  "geometry": {"coordinates":[-80.01921900000001,32.79929],"type":"Point"}
}