{
  "type": "Feature",
  "properties": {
    "addr:full":"8657 Laurel Grove Ln North Charleston SC 29420",
    "addr:housenumber":"8657",
    "addr:postcode":"29420",
    "addr:street":"Laurel Grove Ln",
    "iso:country":"US",
    "sg:address":"8657 Laurel Grove Ln",
    "sg:city":"North Charleston",
    "sg:classifiers":[
        {
            "category":"Building & Trades",
            "subcategory":"Construction",
            "type":"Services"
        }
    ],
    "sg:phone":"+1 843 207 1957",
    "sg:postcode":"29420",
    "sg:province":"SC",
    "wof:name":"Don Galloway Homes LLC",
    "wof:placetype":"venue"
},
  "geometry": {"coordinates":[-80.128276,32.91455],"type":"Point"}
}