{
  "type": "Feature",
  "properties": {
    "addr:full":"4508 White Horse Rd Greenville SC 29611",
    "addr:housenumber":"4508",
    "addr:postcode":"29611",
    "addr:street":"White Horse Rd",
    "iso:country":"US",
    "sg:address":"4508 White Horse Rd",
    "sg:city":"Greenville",
    "sg:classifiers":[
        {
            "category":"Autos & Motor Vehicles",
            "subcategory":"Automobile Sales",
            "type":"Retail Goods"
        }
    ],
    "sg:phone":"+1 864 295 9304",
    "sg:postcode":"29611",
    "sg:province":"SC",
    "sg:tags":[
        "car",
        "used",
        "dealer"
    ],
    "wof:name":"Philbeck's Used Cars",
    "wof:placetype":"venue"
},
  "geometry": {"coordinates":[-82.461332,34.859024],"type":"Point"}
}