{
  "type": "Feature",
  "properties": {
    "iso:country":"US",
    "sg:address":"509 Main St",
    "sg:city":"Blythewood",
    "sg:classifiers":[
        {
            "category":"Manufacturing",
            "subcategory":"Printing",
            "type":"Manufacturing & Wholesale Goods"
        }
    ],
    "sg:phone":"+1 803 786 5681",
    "sg:postcode":"29016",
    "sg:province":"SC",
    "sg:tags":[
        "newspaper"
    ],
    "wof:name":"Country Chronicle",
    "wof:placetype":"venue"
},
  "geometry": {"coordinates":[-80.973294,34.216049],"type":"Point"}
}