{
  "type": "Feature",
  "properties": {
    "iso:country":"US",
    "sg:address":"1465 Ball Park Rd",
    "sg:city":"Enoree",
    "sg:classifiers":[
        {
            "category":"Freight",
            "type":"Transportation"
        }
    ],
    "sg:phone":"+1 864 969 3811",
    "sg:postcode":"29335",
    "sg:province":"SC",
    "sg:tags":[
        "operator",
        "trucking"
    ],
    "wof:name":"Joe K Trucking",
    "wof:placetype":"venue"
},
  "geometry": {"coordinates":[-81.955139,34.683385],"type":"Point"}
}