{
  "type": "Feature",
  "properties": {
    "iso:country":"US",
    "sg:address":"3662 Kershaw Hwy",
    "sg:city":"Kershaw",
    "sg:classifiers":[
        {
            "category":"Education",
            "subcategory":"Special Training",
            "type":"Public Place"
        }
    ],
    "sg:phone":"+1 803 475 5006",
    "sg:postcode":"29067",
    "sg:province":"SC",
    "sg:tags":[
        "instruction",
        "driving"
    ],
    "wof:name":"Turn One Motor Sports",
    "wof:placetype":"venue"
},
  "geometry": {"coordinates":[-80.599188,34.494491],"type":"Point"}
}