{
  "type": "Feature",
  "properties": {
    "addr:full":"5 Market Hill Ct Irmo SC 29063",
    "addr:housenumber":"5",
    "addr:postcode":"29063",
    "addr:street":"Market Hill Ct",
    "iso:country":"US",
    "sg:address":"5 Market Hill Ct",
    "sg:city":"Irmo",
    "sg:classifiers":[
        {
            "category":"Wholesale",
            "subcategory":"Construction Materials",
            "type":"Manufacturing & Wholesale Goods"
        }
    ],
    "sg:phone":"+1 803 605 5417",
    "sg:postcode":"29063",
    "sg:province":"SC",
    "sg:tags":[
        "fence"
    ],
    "wof:name":"Pdf",
    "wof:placetype":"venue"
},
  "geometry": {"coordinates":[-81.213658,34.109212],"type":"Point"}
}