{
  "type": "Feature",
  "properties": {
    "addr:full":"1545 Muller Rd Blythewood SC 29016",
    "addr:housenumber":"1545",
    "addr:postcode":"29016",
    "addr:street":"Muller Rd",
    "iso:country":"US",
    "sg:address":"1545 Muller Rd",
    "sg:city":"Blythewood",
    "sg:classifiers":[
        {
            "category":"Building & Trades",
            "subcategory":"Construction",
            "type":"Services"
        }
    ],
    "sg:phone":"+1 803 786 6116",
    "sg:postcode":"29016",
    "sg:province":"SC",
    "sg:tags":[
        "excavating",
        "work",
        "demolition",
        "contractor"
    ],
    "wof:name":"Bill Broach Company",
    "wof:placetype":"venue"
},
  "geometry": {"coordinates":[-81.025755,34.218719],"type":"Point"}
}