{
  "type": "Feature",
  "properties": {
    "addr:full":"2316 Cosgrove Ave North Charleston SC 29405",
    "addr:housenumber":"2316",
    "addr:postcode":"29405",
    "addr:street":"Cosgrove Ave",
    "iso:country":"US",
    "sg:address":"2316 Cosgrove Ave",
    "sg:city":"North Charleston",
    "sg:classifiers":[
        {
            "category":"Health Services",
            "subcategory":"Doctor",
            "type":"Services"
        }
    ],
    "sg:phone":"+1 843 554 9313",
    "sg:postcode":"29405",
    "sg:province":"SC",
    "sg:tags":[
        "physician",
        "surgeon"
    ],
    "wof:name":"Trident Nephrology Assoc",
    "wof:placetype":"venue"
},
  "geometry": {"coordinates":[-79.979389,32.846559],"type":"Point"}
}