{
  "type": "Feature",
  "properties": {
    "addr:full":"1688 Old Towne Rd Charleston SC 29407",
    "addr:housenumber":"1688",
    "addr:postcode":"29407",
    "addr:street":"Old Towne Rd",
    "iso:country":"US",
    "sg:address":"1688 Old Towne Rd",
    "sg:city":"Charleston",
    "sg:classifiers":[
        {
            "category":"Shopping",
            "type":"Retail Goods"
        }
    ],
    "sg:phone":"+1 843 556 4255",
    "sg:postcode":"29407",
    "sg:province":"SC",
    "sg:tags":[
        "cosmetic",
        "perfume"
    ],
    "wof:name":"Merle Norman Cosmetics",
    "wof:placetype":"venue"
},
  "geometry": {"coordinates":[-79.993105,32.817513],"type":"Point"}
}