{
  "type": "Feature",
  "properties": {
    "iso:country":"US",
    "sg:address":"124 Earle St N",
    "sg:city":"Wagener",
    "sg:classifiers":[
        {
            "category":"Government",
            "subcategory":"Fire Station",
            "type":"Public Place"
        }
    ],
    "sg:phone":"+1 803 564 5450",
    "sg:postcode":"29164",
    "sg:province":"SC",
    "sg:tags":[
        "department"
    ],
    "wof:name":"Wagener Fire Dept",
    "wof:placetype":"venue"
},
  "geometry": {"coordinates":[-81.360953,33.650891],"type":"Point"}
}