{
  "type": "Feature",
  "properties": {
    "iso:country":"US",
    "sg:address":"1542 Ashley River Rd",
    "sg:city":"Charleston",
    "sg:classifiers":[
        {
            "category":"Autos & Motor Vehicles",
            "subcategory":"Automobile Sales",
            "type":"Retail Goods"
        }
    ],
    "sg:phone":"+1 843 766 9070",
    "sg:postcode":"29407",
    "sg:province":"SC",
    "sg:tags":[
        "used"
    ],
    "wof:name":"Yonco Enterprises Inc",
    "wof:placetype":"venue"
},
  "geometry": {"coordinates":[-80.009497,32.799289],"type":"Point"}
}