{
  "type": "Feature",
  "properties": {
    "iso:country":"US",
    "sg:address":"110 W Pine St",
    "sg:city":"Florence",
    "sg:classifiers":[
        {
            "category":"Health Services",
            "subcategory":"Doctor",
            "type":"Services"
        }
    ],
    "sg:phone":"+1 843 662 8468",
    "sg:postcode":"29501",
    "sg:province":"SC",
    "sg:tags":[
        "physician",
        "surgeon"
    ],
    "wof:name":"John J Kirkland MD",
    "wof:placetype":"venue"
},
  "geometry": {"coordinates":[-79.76762100000001,34.191768],"type":"Point"}
}