{
  "type": "Feature",
  "properties": {
    "iso:country":"US",
    "sg:address":"6650 Rivers Ave",
    "sg:city":"Charleston",
    "sg:classifiers":[
        {
            "category":"Professional",
            "subcategory":"Management & Consulting",
            "type":"Services"
        }
    ],
    "sg:phone":"+1 843 576 1471",
    "sg:postcode":"29406",
    "sg:province":"SC",
    "sg:tags":[
        "investments",
        "long-term-investing",
        "financing",
        "sales",
        "consultant",
        "oil-and-energy",
        "real-estate",
        "films"
    ],
    "sg:website":"http://www.LTINVESTMENTSINC.com",
    "wof:name":"LT Investments",
    "wof:placetype":"venue"
},
  "geometry": {"coordinates":[-80.027851,32.917619],"type":"Point"}
}