{
  "type": "Feature",
  "properties": {
    "addr:full":"1596 Hwy 17 North Myrtle Bch SC 29582",
    "addr:housenumber":"1596",
    "addr:postcode":"29582",
    "addr:street":"Hwy 17 North Myrtle",
    "iso:country":"US",
    "sg:address":"1596 Hwy 17",
    "sg:city":"North Myrtle Bch",
    "sg:classifiers":[
        {
            "category":"Restaurant",
            "type":"Food & Drink"
        }
    ],
    "sg:phone":"+1 843 272 1414",
    "sg:postcode":"29582",
    "sg:province":"SC",
    "sg:tags":[
        "eating"
    ],
    "wof:name":"Benitos Brick Oven Pizza Pasta",
    "wof:placetype":"venue"
},
  "geometry": {"coordinates":[-78.659502,33.844739],"type":"Point"}
}