{
  "type": "Feature",
  "properties": {
    "iso:country":"US",
    "sg:address":"1103 Hampton St",
    "sg:city":"Walterboro",
    "sg:classifiers":[
        {
            "category":"Organizations",
            "subcategory":"Religious Organization",
            "type":"Services"
        }
    ],
    "sg:phone":"+1 843 549 6282",
    "sg:postcode":"29488",
    "sg:province":"SC",
    "sg:tags":[
        "church"
    ],
    "wof:name":"Rock Of Ages CME Church",
    "wof:placetype":"venue"
},
  "geometry": {"coordinates":[-80.650261,32.898639],"type":"Point"}
}