{
  "type": "Feature",
  "properties": {
    "iso:country":"US",
    "sg:address":"115 Willbrook Rd",
    "sg:city":"Pawleys Island",
    "sg:classifiers":[
        {
            "category":"Banks & Credit Unions",
            "subcategory":"Investment Brokerage",
            "type":"Services"
        }
    ],
    "sg:phone":"+1 843 237 1007",
    "sg:postcode":"29577",
    "sg:province":"SC",
    "sg:tags":[
        "stock",
        "bond"
    ],
    "wof:name":"H & R Block Financial Advisors",
    "wof:placetype":"venue"
},
  "geometry": {"coordinates":[-78.877207,33.732865],"type":"Point"}
}