{
  "type": "Feature",
  "properties": {
    "iso:country":"US",
    "sg:address":"1561 Wilkinsville Hwy",
    "sg:city":"Gaffney",
    "sg:classifiers":[
        {
            "category":"Building & Trades",
            "subcategory":"Construction",
            "type":"Services"
        }
    ],
    "sg:phone":"+1 864 487 7872",
    "sg:postcode":"29340",
    "sg:province":"SC",
    "sg:tags":[
        "contractor"
    ],
    "wof:name":"CGD Developers Inc",
    "wof:placetype":"venue"
},
  "geometry": {"coordinates":[-81.604444,35.04632],"type":"Point"}
}