{
  "type": "Feature",
  "properties": {
    "iso:country":"US",
    "sg:address":"439 Charming Cir",
    "sg:city":"Winnsboro",
    "sg:classifiers":[
        {
            "category":"Building & Trades",
            "subcategory":"Construction",
            "type":"Services"
        }
    ],
    "sg:phone":"+1 803 635 5472",
    "sg:postcode":"29180",
    "sg:province":"SC",
    "sg:tags":[
        "contractor"
    ],
    "wof:name":"H & H Masonry",
    "wof:placetype":"venue"
},
  "geometry": {"coordinates":[-81.079717,34.305501],"type":"Point"}
}