{
  "type": "Feature",
  "properties": {
    "iso:country":"US",
    "sg:address":"3516 Southborough Rd",
    "sg:city":"Florence",
    "sg:classifiers":[
        {
            "category":"Social Services",
            "subcategory":"Child Care",
            "type":"Services"
        }
    ],
    "sg:phone":"+1 843 665 0202",
    "sg:postcode":"29501",
    "sg:province":"SC",
    "wof:name":"Little Scholars' Academy",
    "wof:placetype":"venue"
},
  "geometry": {"coordinates":[-79.86633399999999,34.180173],"type":"Point"}
}