{
  "type": "Feature",
  "properties": {
    "iso:country":"US",
    "sg:address":"411 S Main St",
    "sg:city":"Mullins",
    "sg:classifiers":[
        {
            "category":"Personal",
            "subcategory":"Beauty Salon",
            "type":"Services"
        }
    ],
    "sg:phone":"+1 843 464 8539",
    "sg:postcode":"29574",
    "sg:province":"SC",
    "wof:name":"Creative Touch",
    "wof:placetype":"venue"
},
  "geometry": {"coordinates":[-79.25344,34.201508],"type":"Point"}
}