{
  "type": "Feature",
  "properties": {
    "iso:country":"US",
    "sg:address":"332 Main St",
    "sg:city":"Greenwood",
    "sg:classifiers":[
        {
            "category":"Professional",
            "type":"Services"
        }
    ],
    "sg:phone":"+1 864 223 3426",
    "sg:postcode":"29646",
    "sg:province":"SC",
    "sg:tags":[
        "establishment"
    ],
    "wof:name":"Capsugel",
    "wof:placetype":"venue"
},
  "geometry": {"coordinates":[-82.160174,34.189906],"type":"Point"}
}