{
  "type": "Feature",
  "properties": {
    "addr:full":"208 Carteret St Beaufort SC 29902",
    "addr:housenumber":"208",
    "addr:postcode":"29902",
    "addr:street":"Carteret St",
    "iso:country":"US",
    "sg:address":"208 Carteret St",
    "sg:city":"Beaufort",
    "sg:classifiers":[
        {
            "category":"Shopping",
            "subcategory":"Hobbies, Toys, & Games",
            "type":"Retail Goods"
        }
    ],
    "sg:phone":"+1 843 521 4909",
    "sg:postcode":"29902",
    "sg:province":"SC",
    "sg:tags":[
        "doll"
    ],
    "wof:name":"Expressions Doll Store",
    "wof:placetype":"venue"
},
  "geometry": {"coordinates":[-80.66999300000001,32.431593],"type":"Point"}
}