{
  "type": "Feature",
  "properties": {
    "iso:country":"US",
    "sg:address":"1100 Highway 9 Byp W",
    "sg:city":"Lancaster",
    "sg:classifiers":[
        {
            "category":"Restaurant",
            "type":"Food & Drink"
        }
    ],
    "sg:menulink":"http://www.allmenus.com/sc/lancaster/73199-pizza-hut/menu/",
    "sg:phone":"+1 803 285 8436",
    "sg:postcode":"29720",
    "sg:province":"SC",
    "sg:tags":[
        "american",
        "pizza"
    ],
    "wof:name":"Pizza Hut",
    "wof:placetype":"venue"
},
  "geometry": {"coordinates":[-80.790178,34.734892],"type":"Point"}
}