{
  "type": "Feature",
  "properties": {
    "iso:country":"US",
    "sg:address":"2070 New Cut Rd",
    "sg:city":"Spartanburg",
    "sg:classifiers":[
        {
            "category":"Travel",
            "subcategory":"Hotels & Motels",
            "type":"Entertainment"
        }
    ],
    "sg:phone":"+1 864 576 2992",
    "sg:postcode":"29303",
    "sg:province":"SC",
    "wof:name":"Quality Inn",
    "wof:placetype":"venue"
},
  "geometry": {"coordinates":[-82.023197,34.991545],"type":"Point"}
}