{
  "type": "Feature",
  "properties": {
    "iso:country":"US",
    "sg:address":"11263 N Jacob Smart Blvd",
    "sg:city":"Ridgeland",
    "sg:classifiers":[
        {
            "category":"Autos & Motor Vehicles",
            "subcategory":"Auto Supplies",
            "type":"Retail Goods"
        },
        {
            "category":"Personal",
            "type":"Services"
        },
        {
            "category":"Retail",
            "subcategory":"Auto Repair",
            "type":"Services"
        }
    ],
    "sg:phone":"+1 843 726 8771",
    "sg:postcode":"29936",
    "sg:province":"SC",
    "sg:tags":[
        "automobile",
        "part",
        "towing",
        "tire",
        "accessory"
    ],
    "sg:website":"http://www.acccridgeland.com",
    "wof:name":"American Car Care Ctr",
    "wof:placetype":"venue"
},
  "geometry": {"coordinates":[-80.979742,32.481964],"type":"Point"}
}