{
  "type": "Feature",
  "properties": {
    "addr:full":"1038 William Hilton Pkwy Hilton Head Island SC 29928",
    "addr:housenumber":"1038",
    "addr:postcode":"29928",
    "addr:street":"William Hilton Pkwy",
    "iso:country":"US",
    "sg:address":"1038 William Hilton Pkwy",
    "sg:city":"Hilton Head Island",
    "sg:classifiers":[
        {
            "category":"Restaurant",
            "type":"Food & Drink"
        }
    ],
    "sg:phone":"+1 843 785 2266",
    "sg:postcode":"29928",
    "sg:province":"SC",
    "sg:tags":[
        "eating"
    ],
    "wof:name":"Hardees",
    "wof:placetype":"venue"
},
  "geometry": {"coordinates":[-80.76019100000001,32.156402],"type":"Point"}
}