{
  "type": "Feature",
  "properties": {
    "iso:country":"US",
    "sg:address":"369 Gowdeysville Rd",
    "sg:city":"Gaffney",
    "sg:classifiers":[
        {
            "category":"Farming",
            "subcategory":"Livestock Farm",
            "type":"Manufacturing & Wholesale Goods"
        }
    ],
    "sg:phone":"+1 864 489 6888",
    "sg:postcode":"29340",
    "sg:province":"SC",
    "sg:tags":[
        "beef",
        "feedlot",
        "cattle"
    ],
    "wof:name":"Jack McAbee",
    "wof:placetype":"venue"
},
  "geometry": {"coordinates":[-81.613379,34.915186],"type":"Point"}
}