{
  "type": "Feature",
  "properties": {
    "addr:full":"2 Buckingham Plantation Dr Bluffton SC 29910",
    "addr:housenumber":"2",
    "addr:postcode":"29910",
    "addr:street":"Buckingham Plantation Dr",
    "iso:country":"US",
    "sg:address":"2 Buckingham Plantation Dr",
    "sg:city":"Bluffton",
    "sg:classifiers":[
        {
            "category":"Home & Garden",
            "subcategory":"Furniture",
            "type":"Retail Goods"
        }
    ],
    "sg:phone":"+1 843 837 5500",
    "sg:postcode":"29910",
    "sg:province":"SC",
    "wof:name":"Havertys Furniture",
    "wof:placetype":"venue"
},
  "geometry": {"coordinates":[-80.81249099999999,32.234251],"type":"Point"}
}