{
  "type": "Feature",
  "properties": {
    "iso:country":"US",
    "sg:address":"309 Main St",
    "sg:city":"Conway",
    "sg:classifiers":[
        {
            "category":"Banks & Credit Unions",
            "subcategory":"Bank",
            "type":"Services"
        }
    ],
    "sg:phone":"+1 843 248 4008",
    "sg:postcode":"29526",
    "sg:province":"SC",
    "wof:name":"Conway National Bank",
    "wof:placetype":"venue"
},
  "geometry": {"coordinates":[-79.04631000000001,33.835535],"type":"Point"}
}