{
  "type": "Feature",
  "properties": {
    "addr:full":"129 Shadowpine Rd Columbia SC 29212",
    "addr:housenumber":"129",
    "addr:postcode":"29212",
    "addr:street":"Shadowpine Rd",
    "iso:country":"US",
    "sg:address":"129 Shadowpine Rd",
    "sg:city":"Columbia",
    "sg:classifiers":[
        {
            "category":"Utilities",
            "subcategory":"Natural Gas",
            "type":"Services"
        }
    ],
    "sg:phone":"+1 803 749 6872",
    "sg:postcode":"29212",
    "sg:province":"SC",
    "sg:tags":[
        "company"
    ],
    "wof:name":"South Carolina Electric & Gas",
    "wof:placetype":"venue"
},
  "geometry": {"coordinates":[-81.137102,34.078542],"type":"Point"}
}