{
  "type": "Feature",
  "properties": {
    "addr:full":"1555 Riddle Rd Exd Clover SC 29710",
    "addr:housenumber":"1555",
    "addr:postcode":"29710",
    "addr:street":"Riddle Rd Exd",
    "iso:country":"US",
    "sg:address":"1555 Riddle Rd Exd",
    "sg:city":"Clover",
    "sg:classifiers":[
        {
            "category":"Building & Trades",
            "subcategory":"Construction",
            "type":"Services"
        }
    ],
    "sg:phone":"+1 803 962 2110",
    "sg:postcode":"29710",
    "sg:province":"SC",
    "sg:tags":[
        "remodeling"
    ],
    "wof:name":"Beavers Home Improvement",
    "wof:placetype":"venue"
},
  "geometry": {"coordinates":[-81.163708,35.151482],"type":"Point"}
}