{
  "type": "Feature",
  "properties": {
    "iso:country":"US",
    "sg:address":"2373 Chestnut St",
    "sg:city":"Orangeburg",
    "sg:classifiers":[
        {
            "category":"Restaurant",
            "type":"Food & Drink"
        }
    ],
    "sg:menulink":"http://www.allmenus.com/sc/orangeburg/84293-papa-johns-pizza/menu/",
    "sg:phone":"+1 803 531 7272",
    "sg:postcode":"29115",
    "sg:province":"SC",
    "sg:tags":[
        "american",
        "pizza"
    ],
    "wof:name":"Papa John's Pizza",
    "wof:placetype":"venue"
},
  "geometry": {"coordinates":[-80.881833,33.520555],"type":"Point"}
}