{
  "type": "Feature",
  "properties": {
    "iso:country":"US",
    "sg:address":"120 Mount Gallant Rd",
    "sg:city":"Rock Hill",
    "sg:classifiers":[
        {
            "category":"Mining & Drilling",
            "type":"Manufacturing & Wholesale Goods"
        }
    ],
    "sg:phone":"+1 803 329 8400",
    "sg:postcode":"29730",
    "sg:province":"SC",
    "sg:tags":[
        "oil",
        "gas",
        "producer"
    ],
    "wof:name":"Nobile Oil Svc",
    "wof:placetype":"venue"
},
  "geometry": {"coordinates":[-80.988775,34.950196],"type":"Point"}
}