{
  "type": "Feature",
  "properties": {
    "addr:full":"1345 Lake Murray Blvd Irmo SC 29212",
    "addr:housenumber":"1345",
    "addr:postcode":"29212",
    "addr:street":"Lake Murray Blvd",
    "iso:country":"US",
    "sg:address":"1345 Lake Murray Blvd",
    "sg:city":"Irmo",
    "sg:classifiers":[
        {
            "category":"Insurance",
            "subcategory":"Insurance Agent",
            "type":"Services"
        }
    ],
    "sg:phone":"+1 803 781 4700",
    "sg:postcode":"29212",
    "sg:province":"SC",
    "sg:website":"www.irmoinsuranceagency.com",
    "wof:name":"Irmo Insurance Inc",
    "wof:placetype":"venue"
},
  "geometry": {"coordinates":[-81.185652,34.084961],"type":"Point"}
}