{
  "type": "Feature",
  "properties": {
    "iso:country":"US",
    "sg:address":"1829 Senate St",
    "sg:city":"Columbia",
    "sg:classifiers":[
        {
            "category":"Real Estate",
            "subcategory":"Real Estate Agent",
            "type":"Services"
        }
    ],
    "sg:phone":"+1 803 736 7007",
    "sg:postcode":"29201",
    "sg:province":"SC",
    "wof:name":"Coastal Communities Inc",
    "wof:placetype":"venue"
},
  "geometry": {"coordinates":[-81.022904,34.002938],"type":"Point"}
}