{
  "type": "Feature",
  "properties": {
    "iso:country":"US",
    "sg:address":"804 S 5th St",
    "sg:city":"Hartsville",
    "sg:classifiers":[
        {
            "category":"Restaurant",
            "type":"Food & Drink"
        }
    ],
    "sg:phone":"+1 843 332 0904",
    "sg:postcode":"29550",
    "sg:province":"SC",
    "sg:tags":[
        "eating"
    ],
    "wof:name":"Shrimper",
    "wof:placetype":"venue"
},
  "geometry": {"coordinates":[-80.069011,34.355342],"type":"Point"}
}