{
  "type": "Feature",
  "properties": {
    "iso:country":"US",
    "sg:address":"3818 River Dr",
    "sg:city":"Columbia",
    "sg:classifiers":[
        {
            "category":"Professional",
            "subcategory":"Accounting & Tax Preparation",
            "type":"Services"
        }
    ],
    "sg:phone":"+1 803 799 9823",
    "sg:postcode":"29201",
    "sg:province":"SC",
    "sg:tags":[
        "accountant"
    ],
    "wof:name":"Hummers Steve CPA",
    "wof:placetype":"venue"
},
  "geometry": {"coordinates":[-81.06109600000001,34.028099],"type":"Point"}
}