{
  "type": "Feature",
  "properties": {
    "iso:country":"US",
    "sg:address":"5771 Rosewood Dr",
    "sg:city":"Myrtle Beach",
    "sg:classifiers":[
        {
            "category":"Personal",
            "subcategory":"Massage",
            "type":"Services"
        }
    ],
    "sg:phone":"+1 843 293 7874",
    "sg:postcode":"29588",
    "sg:province":"SC",
    "sg:website":"www.umaone.com",
    "wof:name":"Jenway Enterprises",
    "wof:placetype":"venue"
},
  "geometry": {"coordinates":[-78.992696,33.690541],"type":"Point"}
}