{
  "type": "Feature",
  "properties": {
    "addr:full":"2040 Bear Village Ct Newberry SC 29108",
    "addr:housenumber":"2040",
    "addr:postcode":"29108",
    "addr:street":"Bear Village Ct",
    "iso:country":"US",
    "sg:address":"2040 Bear Village Ct",
    "sg:city":"Newberry",
    "sg:classifiers":[
        {
            "category":"Banks & Credit Unions",
            "subcategory":"Bank",
            "type":"Services"
        }
    ],
    "sg:phone":"+1 803 405 0800",
    "sg:postcode":"29108",
    "sg:province":"SC",
    "sg:tags":[
        "institution",
        "business"
    ],
    "wof:name":"1st Franklin Financial Corp",
    "wof:placetype":"venue"
},
  "geometry": {"coordinates":[-81.608617,34.296258],"type":"Point"}
}