{
  "type": "Feature",
  "properties": {
    "iso:country":"US",
    "sg:address":"8082 Rivers Ave",
    "sg:city":"North Charleston",
    "sg:classifiers":[
        {
            "category":"Travel",
            "subcategory":"Hotels & Motels",
            "type":"Entertainment"
        }
    ],
    "sg:phone":"+1 843 569 1417",
    "sg:postcode":"29406",
    "sg:province":"SC",
    "wof:name":"In Town Suites N Charleston",
    "wof:placetype":"venue"
},
  "geometry": {"coordinates":[-80.042579,32.956625],"type":"Point"}
}