{
  "type": "Feature",
  "properties": {
    "iso:country":"US",
    "sg:address":"5600 Dorchester Rd",
    "sg:city":"Charleston",
    "sg:classifiers":[
        {
            "category":"Shopping",
            "type":"Retail Goods"
        }
    ],
    "sg:phone":"+1 843 552 8355",
    "sg:postcode":"29418",
    "sg:province":"SC",
    "sg:tags":[
        "art",
        "gallery",
        "dealer"
    ],
    "wof:name":"Shona Art Gallery",
    "wof:placetype":"venue"
},
  "geometry": {"coordinates":[-80.04863899999999,32.86282],"type":"Point"}
}