{
  "type": "Feature",
  "properties": {
    "iso:country":"US",
    "sg:address":"1724 Main St",
    "sg:city":"Newberry",
    "sg:classifiers":[
        {
            "category":"Retail",
            "subcategory":"Funeral Services",
            "type":"Services"
        }
    ],
    "sg:phone":"+1 803 276 0610",
    "sg:postcode":"29108",
    "sg:province":"SC",
    "sg:tags":[
        "director"
    ],
    "wof:name":"Mc Swain-Evans Funeral Home",
    "wof:placetype":"venue"
},
  "geometry": {"coordinates":[-81.613582,34.276687],"type":"Point"}
}