{
  "type": "Feature",
  "properties": {
    "iso:country":"US",
    "sg:address":"4125 Payne Rd",
    "sg:city":"Kershaw",
    "sg:classifiers":[
        {
            "category":"Government",
            "subcategory":"Office",
            "type":"Public Place"
        }
    ],
    "sg:phone":"+1 803 475 4835",
    "sg:postcode":"29067",
    "sg:province":"SC",
    "wof:name":"Lancaster County Midway Site",
    "wof:placetype":"venue"
},
  "geometry": {"coordinates":[-80.497574,34.612601],"type":"Point"}
}