{
  "type": "Feature",
  "properties": {
    "iso:country":"US",
    "sg:address":"2150 Oakway Rd",
    "sg:city":"Westminster",
    "sg:classifiers":[
        {
            "category":"Organizations",
            "subcategory":"Religious Organization",
            "type":"Services"
        }
    ],
    "sg:phone":"+1 864 972 1133",
    "sg:postcode":"29693",
    "sg:province":"SC",
    "sg:tags":[
        "church"
    ],
    "wof:name":"Strait Gate Worship Ctr",
    "wof:placetype":"venue"
},
  "geometry": {"coordinates":[-83.020458,34.595562],"type":"Point"}
}