{
  "type": "Feature",
  "properties": {
    "iso:country":"US",
    "sg:address":"1875 Savage Rd",
    "sg:city":"Charleston",
    "sg:classifiers":[
        {
            "category":"Health Services",
            "subcategory":"Doctor",
            "type":"Services"
        }
    ],
    "sg:phone":"+1 843 766 0721",
    "sg:postcode":"29407",
    "sg:province":"SC",
    "sg:tags":[
        "dentist"
    ],
    "wof:name":"Charleston Dental Assoc",
    "wof:placetype":"venue"
},
  "geometry": {"coordinates":[-80.026712,32.806509],"type":"Point"}
}