{
  "type": "Feature",
  "properties": {
    "iso:country":"US",
    "sg:address":"2580 Whiskey Rd",
    "sg:city":"Aiken",
    "sg:classifiers":[
        {
            "category":"Home & Garden",
            "subcategory":"Carpets & Floor Coverings",
            "type":"Retail Goods"
        }
    ],
    "sg:phone":"+1 803 643 3643",
    "sg:postcode":"29803",
    "sg:province":"SC",
    "sg:tags":[
        "dealer",
        "rug"
    ],
    "wof:name":"GCO Carpet Outlet",
    "wof:placetype":"venue"
},
  "geometry": {"coordinates":[-81.70779400000001,33.503522],"type":"Point"}
}