{
  "type": "Feature",
  "properties": {
    "addr:full":"1472 Morrisville Rd Andrews SC 29510",
    "addr:housenumber":"1472",
    "addr:postcode":"29510",
    "addr:street":"Morrisville Rd",
    "iso:country":"US",
    "sg:address":"1472 Morrisville Rd",
    "sg:city":"Andrews",
    "sg:classifiers":[
        {
            "category":"Building & Trades",
            "subcategory":"Construction",
            "type":"Services"
        }
    ],
    "sg:phone":"+1 843 221 5408",
    "sg:postcode":"29510",
    "sg:province":"SC",
    "sg:tags":[
        "maintenance",
        "contractor"
    ],
    "wof:name":"Cox Maintenance Inc",
    "wof:placetype":"venue"
},
  "geometry": {"coordinates":[-79.54391800000001,33.559872],"type":"Point"}
}