{
  "type": "Feature",
  "properties": {
    "addr:full":"354 Industrial Park Rd Union SC 29379",
    "addr:housenumber":"354",
    "addr:postcode":"29379",
    "addr:street":"Industrial Park Rd",
    "iso:country":"US",
    "sg:address":"354 Industrial Park Rd",
    "sg:city":"Union",
    "sg:classifiers":[
        {
            "category":"Manufacturing",
            "subcategory":"Metals",
            "type":"Manufacturing & Wholesale Goods"
        }
    ],
    "sg:phone":"+1 843 784 2251",
    "sg:postcode":"29379",
    "sg:province":"SC",
    "sg:tags":[
        "gray",
        "ductile",
        "foundry",
        "iron"
    ],
    "wof:name":"Carolina Casting Corp",
    "wof:placetype":"venue"
},
  "geometry": {"coordinates":[-81.64991499999999,34.716816],"type":"Point"}
}