{
  "type": "Feature",
  "properties": {
    "addr:full":"7122 Edmund Hwy Pelion SC 29123",
    "addr:housenumber":"7122",
    "addr:postcode":"29123",
    "addr:street":"Edmund Hwy",
    "iso:country":"US",
    "sg:address":"7122 Edmund Hwy",
    "sg:city":"Pelion",
    "sg:classifiers":[
        {
            "category":"Health Services",
            "subcategory":"Nursing And Care Facility",
            "type":"Services"
        }
    ],
    "sg:phone":"+1 803 894 3309",
    "sg:postcode":"29123",
    "sg:province":"SC",
    "sg:tags":[
        "home",
        "retirement",
        "community"
    ],
    "wof:name":"J B Guest Home Inc",
    "wof:placetype":"venue"
},
  "geometry": {"coordinates":[-81.22519200000001,33.808786],"type":"Point"}
}