{
  "type": "Feature",
  "properties": {
    "addr:full":"1007 Bower Pkwy Columbia SC 29212",
    "addr:housenumber":"1007",
    "addr:postcode":"29212",
    "addr:street":"Bower Pkwy",
    "iso:country":"US",
    "sg:address":"1007 Bower Pkwy",
    "sg:city":"Columbia",
    "sg:classifiers":[
        {
            "category":"Bakery",
            "type":"Food & Drink"
        }
    ],
    "sg:menulink":"http://www.allmenus.com/sc/irmo/54609-panera-bread/menu/",
    "sg:phone":"+1 803 407 5773",
    "sg:postcode":"29212",
    "sg:province":"SC",
    "sg:tags":[
        "american",
        "sandwich",
        "pastry"
    ],
    "wof:name":"Panera Bread",
    "wof:placetype":"venue"
},
  "geometry": {"coordinates":[-81.16274799999999,34.070132],"type":"Point"}
}