{
  "type": "Feature",
  "properties": {
    "iso:country":"US",
    "sg:address":"1000 William Hilton Pkwy",
    "sg:city":"Hilton Head Isle",
    "sg:classifiers":[
        {
            "category":"Restaurant",
            "type":"Food & Drink"
        }
    ],
    "sg:phone":"+1 843 842 2822",
    "sg:postcode":"29928",
    "sg:province":"SC",
    "sg:tags":[
        "parlor",
        "ice",
        "cream"
    ],
    "wof:name":"Pino Gelato",
    "wof:placetype":"venue"
},
  "geometry": {"coordinates":[-80.755616,32.15793],"type":"Point"}
}