{
  "type": "Feature",
  "properties": {
    "iso:country":"US",
    "sg:address":"8 Bish Ln",
    "sg:city":"Walterboro",
    "sg:classifiers":[
        {
            "category":"Shopping",
            "subcategory":"Computers & Home Electronics",
            "type":"Retail Goods"
        }
    ],
    "sg:phone":"+1 843 844 7195",
    "sg:postcode":"29488",
    "sg:province":"SC",
    "sg:tags":[
        "equipment",
        "satellite",
        "system"
    ],
    "wof:name":"Greenwave Communication Tech",
    "wof:placetype":"venue"
},
  "geometry": {"coordinates":[-80.668159,32.781104],"type":"Point"}
}