{
  "type": "Feature",
  "properties": {
    "addr:full":"1305 Sandifer Blvd Seneca SC 29678",
    "addr:housenumber":"1305",
    "addr:postcode":"29678",
    "addr:street":"Sandifer Blvd",
    "iso:country":"US",
    "sg:address":"1305 Sandifer Blvd",
    "sg:city":"Seneca",
    "sg:classifiers":[
        {
            "category":"Restaurant",
            "type":"Food & Drink"
        }
    ],
    "sg:menulink":"http://www.allmenus.com/sc/seneca/200972-mcdonalds/menu/",
    "sg:postcode":"29678",
    "sg:province":"SC",
    "sg:tags":[
        "burger",
        "american"
    ],
    "wof:name":"McDonald's",
    "wof:placetype":"venue"
},
  "geometry": {"coordinates":[-82.984903,34.692723],"type":"Point"}
}