{
  "type": "Feature",
  "properties": {
    "addr:full":"790 Wolf Creek Rd Pickens SC 29671",
    "addr:housenumber":"790",
    "addr:postcode":"29671",
    "addr:street":"Wolf Creek Rd",
    "iso:country":"US",
    "sg:address":"790 Wolf Creek Rd",
    "sg:city":"Pickens",
    "sg:classifiers":[
        {
            "category":"Organizations",
            "subcategory":"Religious Organization",
            "type":"Services"
        }
    ],
    "sg:phone":"+1 864 855 9260",
    "sg:postcode":"29671",
    "sg:province":"SC",
    "sg:tags":[
        "church"
    ],
    "wof:name":"Blue Ridge View Baptist Church",
    "wof:placetype":"venue"
},
  "geometry": {"coordinates":[-82.625816,34.917342],"type":"Point"}
}