{
  "type": "Feature",
  "properties": {
    "iso:country":"US",
    "sg:address":"4137 Dobys Bridge Rd",
    "sg:city":"Fort Mill",
    "sg:classifiers":[
        {
            "category":"Education",
            "subcategory":"School",
            "type":"Public Place"
        }
    ],
    "sg:phone":"+1 803 548 3770",
    "sg:postcode":"29715",
    "sg:province":"SC",
    "sg:website":"www.lcsd.k12.sc.us",
    "wof:name":"Indian Land Elementary School",
    "wof:placetype":"venue"
},
  "geometry": {"coordinates":[-80.860283,34.955381],"type":"Point"}
}