{
  "type": "Feature",
  "properties": {
    "addr:full":"200 Lucy P Edwards Rd Woodruff SC 29388",
    "addr:housenumber":"200;p",
    "addr:postcode":"29388",
    "addr:street":"Lucy;Edwards Rd",
    "iso:country":"US",
    "sg:address":"200 Lucy P Edwards Rd",
    "sg:city":"Woodruff",
    "sg:classifiers":[
        {
            "category":"Education",
            "subcategory":"School",
            "type":"Public Place"
        }
    ],
    "sg:phone":"+1 864 476 3174",
    "sg:postcode":"29388",
    "sg:province":"SC",
    "wof:name":"Woodruff Primary School",
    "wof:placetype":"venue"
},
  "geometry": {"coordinates":[-82.011304,34.731459],"type":"Point"}
}