{
  "type": "Feature",
  "properties": {
    "iso:country":"US",
    "sg:address":"21 Ferebee Ct",
    "sg:city":"Bluffton",
    "sg:classifiers":[
        {
            "category":"Building & Trades",
            "subcategory":"Construction",
            "type":"Services"
        }
    ],
    "sg:phone":"+1 843 683 2852",
    "sg:postcode":"29910",
    "sg:province":"SC",
    "sg:tags":[
        "carpentry",
        "contractor"
    ],
    "wof:name":"Northern Eagle Enterprises",
    "wof:placetype":"venue"
},
  "geometry": {"coordinates":[-80.841183,32.243765],"type":"Point"}
}