{
  "type": "Feature",
  "properties": {
    "iso:country":"US",
    "sg:address":"615 Hammett Bridge Rd",
    "sg:city":"Greer",
    "sg:classifiers":[
        {
            "category":"Education",
            "subcategory":"School",
            "type":"Public Place"
        }
    ],
    "sg:phone":"+1 864 848 2465",
    "sg:postcode":"29650",
    "sg:province":"SC",
    "wof:name":"Riverside Middle School",
    "wof:placetype":"venue"
},
  "geometry": {"coordinates":[-82.245679,34.909567],"type":"Point"}
}