{
  "type": "Feature",
  "properties": {
    "iso:country":"US",
    "sg:address":"211 Athol St",
    "sg:city":"Darlington",
    "sg:classifiers":[
        {
            "category":"Retail",
            "subcategory":"Repair Shop",
            "type":"Services"
        }
    ],
    "sg:phone":"+1 843 393 6125",
    "sg:postcode":"29532",
    "sg:province":"SC",
    "sg:tags":[
        "television",
        "radio"
    ],
    "wof:name":"O'Neal TV",
    "wof:placetype":"venue"
},
  "geometry": {"coordinates":[-79.885886,34.321198],"type":"Point"}
}