{
  "type": "Feature",
  "properties": {
    "addr:full":"395 Old Buncombe Rd Union SC 29379",
    "addr:housenumber":"395",
    "addr:postcode":"29379",
    "addr:street":"Old Buncombe Rd",
    "iso:country":"US",
    "sg:address":"395 Old Buncombe Rd",
    "sg:city":"Union",
    "sg:classifiers":[
        {
            "category":"Farming",
            "subcategory":"Livestock Farm",
            "type":"Manufacturing & Wholesale Goods"
        }
    ],
    "sg:phone":"+1 864 427 5855",
    "sg:postcode":"29379",
    "sg:province":"SC",
    "sg:tags":[
        "beef",
        "feedlot",
        "cattle"
    ],
    "wof:name":"Jr Jack Burnett",
    "wof:placetype":"venue"
},
  "geometry": {"coordinates":[-81.76458599999999,34.629035],"type":"Point"}
}