{
  "type": "Feature",
  "properties": {
    "iso:country":"US",
    "sg:address":"914 S Broad St",
    "sg:city":"Clinton",
    "sg:classifiers":[
        {
            "category":"Retail",
            "subcategory":"Laundry & Dry Cleaning",
            "type":"Services"
        }
    ],
    "sg:phone":"+1 864 833 2330",
    "sg:postcode":"29325",
    "sg:province":"SC",
    "sg:tags":[
        "cleaners"
    ],
    "wof:name":"Quality Plus Dry Cleaners",
    "wof:placetype":"venue"
},
  "geometry": {"coordinates":[-81.878489,34.458561],"type":"Point"}
}