{
  "type": "Feature",
  "properties": {
    "addr:full":"656 Cain Dr Mount Pleasant SC 29464",
    "addr:housenumber":"656",
    "addr:postcode":"29464",
    "addr:street":"Cain Dr",
    "iso:country":"US",
    "sg:address":"656 Cain Dr",
    "sg:city":"Mount Pleasant",
    "sg:classifiers":[
        {
            "category":"Marine",
            "type":"Transportation"
        }
    ],
    "sg:phone":"+1 843 884 8266",
    "sg:postcode":"29464",
    "sg:province":"SC",
    "sg:tags":[
        "water",
        "engineering",
        "transport"
    ],
    "wof:name":"Chandler Marine Inc",
    "wof:placetype":"venue"
},
  "geometry": {"coordinates":[-79.86597,32.820232],"type":"Point"}
}