{
  "type": "Feature",
  "properties": {
    "addr:full":"2926 US Hwy 378 Conway SC 29527",
    "addr:housenumber":"2926",
    "addr:postcode":"29527",
    "addr:street":"Us Hwy 378",
    "iso:country":"US",
    "sg:address":"2926 US Hwy 378",
    "sg:city":"Conway",
    "sg:classifiers":[
        {
            "category":"Retail",
            "subcategory":"Auto Repair",
            "type":"Services"
        }
    ],
    "sg:phone":"+1 843 397 2585",
    "sg:postcode":"29527",
    "sg:province":"SC",
    "sg:tags":[
        "body",
        "automobile",
        "painting"
    ],
    "wof:name":"L G Todd Body Shop",
    "wof:placetype":"venue"
},
  "geometry": {"coordinates":[-79.110207,33.840689],"type":"Point"}
}