{
  "type": "Feature",
  "properties": {
    "iso:country":"US",
    "sg:address":"132 Harbison Blvd",
    "sg:city":"Columbia",
    "sg:classifiers":[
        {
            "category":"Professional",
            "subcategory":"Lawyer & Legal Services",
            "type":"Services"
        }
    ],
    "sg:phone":"+1 803 454 1000",
    "sg:postcode":"29212",
    "sg:province":"SC",
    "sg:tags":[
        "attorney"
    ],
    "wof:name":"Dallas D Ball Law Offices",
    "wof:placetype":"venue"
},
  "geometry": {"coordinates":[-81.163357,34.069679],"type":"Point"}
}