{
  "type": "Feature",
  "properties": {
    "iso:country":"US",
    "sg:address":"1002 W Dekalb St",
    "sg:city":"Camden",
    "sg:classifiers":[
        {
            "category":"Autos & Motor Vehicles",
            "subcategory":"Fuel & Gas Station",
            "type":"Retail Goods"
        }
    ],
    "sg:phone":"+1 803 425 5136",
    "sg:postcode":"29020",
    "sg:province":"SC",
    "sg:tags":[
        "oil"
    ],
    "wof:name":"BP Food Shop",
    "wof:placetype":"venue"
},
  "geometry": {"coordinates":[-80.618491,34.246106],"type":"Point"}
}