{
  "type": "Feature",
  "properties": {
    "iso:country":"US",
    "sg:address":"170 E Blackstock Rd",
    "sg:city":"Spartanburg",
    "sg:classifiers":[
        {
            "category":"Restaurant",
            "type":"Food & Drink"
        }
    ],
    "sg:phone":"+1 864 576 8418",
    "sg:postcode":"29301",
    "sg:province":"SC",
    "sg:website":"www.redlobster.com",
    "wof:name":"Red Lobster",
    "wof:placetype":"venue"
},
  "geometry": {"coordinates":[-81.986437,34.920502],"type":"Point"}
}