{
  "type": "Feature",
  "properties": {
    "addr:full":"1335 Wilson Rd Newberry SC 29108",
    "addr:housenumber":"1335",
    "addr:postcode":"29108",
    "addr:street":"Wilson Rd",
    "iso:country":"US",
    "sg:address":"1335 Wilson Rd",
    "sg:city":"Newberry",
    "sg:classifiers":[
        {
            "category":"Banks & Credit Unions",
            "subcategory":"Bank",
            "type":"Services"
        }
    ],
    "sg:phone":"+1 803 405 1608",
    "sg:postcode":"29108",
    "sg:province":"SC",
    "sg:tags":[
        "cashing",
        "check"
    ],
    "wof:name":"Check Into Cash",
    "wof:placetype":"venue"
},
  "geometry": {"coordinates":[-81.599363,34.286351],"type":"Point"}
}