{
  "type": "Feature",
  "properties": {
    "iso:country":"US",
    "sg:address":"1123 Sandy Bluff Rd",
    "sg:city":"Mullins",
    "sg:classifiers":[
        {
            "category":"Education",
            "subcategory":"School",
            "type":"Public Place"
        }
    ],
    "sg:phone":"+1 843 464 3760",
    "sg:postcode":"29574",
    "sg:province":"SC",
    "wof:name":"Mc Cormick Elementary School",
    "wof:placetype":"venue"
},
  "geometry": {"coordinates":[-79.245479,34.192615],"type":"Point"}
}