{
  "type": "Feature",
  "properties": {
    "iso:country":"US",
    "sg:address":"280 Harbison Blvd",
    "sg:city":"Columbia",
    "sg:classifiers":[
        {
            "category":"Restaurant",
            "type":"Food & Drink"
        }
    ],
    "sg:menulink":"http://www.allmenus.com/sc/irmo/54606-chilis/menu/",
    "sg:phone":"+1 803 732 2911",
    "sg:postcode":"29212",
    "sg:province":"SC",
    "sg:tags":[
        "burger",
        "american",
        "sandwich",
        "tex-mex",
        "soup"
    ],
    "wof:name":"Chili's",
    "wof:placetype":"venue"
},
  "geometry": {"coordinates":[-81.157867,34.07315],"type":"Point"}
}