{
  "type": "Feature",
  "properties": {
    "addr:full":"104 State Hwy 201 Abbeville SC 29620",
    "addr:housenumber":"104",
    "addr:postcode":"29620",
    "addr:street":"State Hwy 201",
    "iso:country":"US",
    "sg:address":"104 State Hwy 201",
    "sg:city":"Abbeville",
    "sg:classifiers":[
        {
            "category":"Home & Garden",
            "subcategory":"Furniture",
            "type":"Retail Goods"
        }
    ],
    "sg:phone":"+1 864 446 2154",
    "sg:postcode":"29620",
    "sg:province":"SC",
    "sg:tags":[
        "top",
        "counter"
    ],
    "sg:website":"www.merlsinc.com",
    "wof:name":"Merl's Inc",
    "wof:placetype":"venue"
},
  "geometry": {"coordinates":[-82.39546300000001,34.236867],"type":"Point"}
}