{
  "type": "Feature",
  "properties": {
    "iso:country":"US",
    "sg:address":"421 Seneca St",
    "sg:city":"Calhoun Falls",
    "sg:classifiers":[
        {
            "category":"Personal",
            "subcategory":"Beauty Salon",
            "type":"Services"
        }
    ],
    "sg:phone":"+1 864 447 8637",
    "sg:postcode":"29628",
    "sg:province":"SC",
    "wof:name":"Community Salon",
    "wof:placetype":"venue"
},
  "geometry": {"coordinates":[-82.590447,34.088927],"type":"Point"}
}