{
  "type": "Feature",
  "properties": {
    "addr:full":"2300 Taylor St Columbia SC 29204",
    "addr:housenumber":"2300",
    "addr:postcode":"29204",
    "addr:street":"Taylor St",
    "iso:country":"US",
    "sg:address":"2300 Taylor St",
    "sg:city":"Columbia",
    "sg:classifiers":[
        {
            "category":"Shopping",
            "subcategory":"Department Store",
            "type":"Retail Goods"
        }
    ],
    "sg:phone":"+1 803 779 1213",
    "sg:postcode":"29204",
    "sg:province":"SC",
    "sg:website":"www.familydollar.com",
    "wof:name":"Family Dollar Stores",
    "wof:placetype":"venue"
},
  "geometry": {"coordinates":[-81.018192,34.011869],"type":"Point"}
}