{
  "type": "Feature",
  "properties": {
    "addr:full":"112 S Ron McNair Blvd Lake City SC 29560",
    "addr:housenumber":"112",
    "addr:postcode":"29560",
    "addr:street":"S Ron Mcnair Blvd",
    "iso:country":"US",
    "sg:address":"112 S Ron McNair Blvd",
    "sg:city":"Lake City",
    "sg:classifiers":[
        {
            "category":"Autos & Motor Vehicles",
            "subcategory":"Fuel & Gas Station",
            "type":"Retail Goods"
        }
    ],
    "sg:phone":"+1 843 394 3268",
    "sg:postcode":"29560",
    "sg:province":"SC",
    "sg:tags":[
        "oil"
    ],
    "wof:name":"Bell's Convenience Store",
    "wof:placetype":"venue"
},
  "geometry": {"coordinates":[-79.760656,33.875582],"type":"Point"}
}