{
  "type": "Feature",
  "properties": {
    "iso:country":"US",
    "sg:address":"615 N Pine St",
    "sg:city":"Seneca",
    "sg:classifiers":[
        {
            "category":"Utilities",
            "subcategory":"Cable",
            "type":"Services"
        }
    ],
    "sg:phone":"+1 864 882 0002",
    "sg:postcode":"29678",
    "sg:province":"SC",
    "sg:tags":[
        "television"
    ],
    "wof:name":"Northland Cable Television",
    "wof:placetype":"venue"
},
  "geometry": {"coordinates":[-82.958476,34.693549],"type":"Point"}
}