{
  "type": "Feature",
  "properties": {
    "addr:full":"5225 Fairfield Rd Columbia SC 29203",
    "addr:housenumber":"5225",
    "addr:postcode":"29203",
    "addr:street":"Fairfield Rd",
    "iso:country":"US",
    "sg:address":"5225 Fairfield Rd",
    "sg:city":"Columbia",
    "sg:classifiers":[
        {
            "category":"Retail",
            "subcategory":"Auto Repair",
            "type":"Services"
        }
    ],
    "sg:phone":"+1 803 786 0763",
    "sg:postcode":"29203",
    "sg:province":"SC",
    "sg:tags":[
        "repairing",
        "automobile"
    ],
    "wof:name":"Total Tech Automotive",
    "wof:placetype":"venue"
},
  "geometry": {"coordinates":[-81.027856,34.054514],"type":"Point"}
}