{
  "type": "Feature",
  "properties": {
    "addr:full":"3262 S Brandy Cir Florence SC 29505",
    "addr:housenumber":"3262",
    "addr:postcode":"29505",
    "addr:street":"S Brandy Cir",
    "iso:country":"US",
    "sg:address":"3262 S Brandy Cir",
    "sg:city":"Florence",
    "sg:classifiers":[
        {
            "category":"Professional",
            "subcategory":"Detective & Security Services",
            "type":"Services"
        }
    ],
    "sg:phone":"+1 843 665 7944",
    "sg:postcode":"29505",
    "sg:province":"SC",
    "sg:website":"www.marionbrown.com",
    "wof:name":"Brown's Detective Agency",
    "wof:placetype":"venue"
},
  "geometry": {"coordinates":[-79.752816,34.133233],"type":"Point"}
}