{
  "type": "Feature",
  "properties": {
    "iso:country":"US",
    "sg:address":"10300 Old White Horse Rd",
    "sg:city":"Travelers Rest",
    "sg:classifiers":[
        {
            "category":"Food & Beverages",
            "subcategory":"Groceries & Convenience Stores",
            "type":"Retail Goods"
        }
    ],
    "sg:phone":"+1 864 834 7588",
    "sg:postcode":"29690",
    "sg:province":"SC",
    "sg:tags":[
        "grocer"
    ],
    "wof:name":"Handee Mart Food Stores Inc",
    "wof:placetype":"venue"
},
  "geometry": {"coordinates":[-82.473908,34.951766],"type":"Point"}
}