{
  "type": "Feature",
  "properties": {
    "iso:country":"US",
    "sg:address":"213 W Cedar Rock St",
    "sg:city":"Pickens",
    "sg:classifiers":[
        {
            "category":"Home & Garden",
            "subcategory":"Garden Supply",
            "type":"Retail Goods"
        }
    ],
    "sg:phone":"+1 864 878 4911",
    "sg:postcode":"29671",
    "sg:province":"SC",
    "sg:tags":[
        "lawn",
        "mower"
    ],
    "wof:name":"Buddy's Chain Saw Svc",
    "wof:placetype":"venue"
},
  "geometry": {"coordinates":[-82.70854300000001,34.881898],"type":"Point"}
}