{
  "type": "Feature",
  "properties": {
    "iso:country":"US",
    "sg:address":"3007 John G Richards Rd",
    "sg:city":"Camden",
    "sg:classifiers":[
        {
            "category":"Wholesale",
            "subcategory":"Scrap",
            "type":"Manufacturing & Wholesale Goods"
        }
    ],
    "sg:phone":"+1 803 475 7724",
    "sg:postcode":"29020",
    "sg:province":"SC",
    "sg:tags":[
        "recycling",
        "center"
    ],
    "wof:name":"Kershaw County Solid Waste",
    "wof:placetype":"venue"
},
  "geometry": {"coordinates":[-80.734866,34.399583],"type":"Point"}
}