{
  "type": "Feature",
  "properties": {
    "iso:country":"US",
    "sg:address":"3612 Broad River Rd",
    "sg:city":"Columbia",
    "sg:classifiers":[
        {
            "category":"Shopping",
            "subcategory":"Department Store",
            "type":"Retail Goods"
        }
    ],
    "sg:phone":"+1 803 772 2903",
    "sg:postcode":"29210",
    "sg:province":"SC",
    "sg:tags":[
        "shop"
    ],
    "wof:name":"Family Dollar Store",
    "wof:placetype":"venue"
},
  "geometry": {"coordinates":[-81.11068299999999,34.056455],"type":"Point"}
}