{
  "type": "Feature",
  "properties": {
    "iso:country":"US",
    "sg:address":"102 Trammell Rd",
    "sg:city":"Greenville",
    "sg:classifiers":[
        {
            "category":"Building & Trades",
            "subcategory":"Construction",
            "type":"Services"
        }
    ],
    "sg:phone":"+1 864 294 8036",
    "sg:postcode":"29617",
    "sg:province":"SC",
    "sg:tags":[
        "house"
    ],
    "wof:name":"Ben Construction",
    "wof:placetype":"venue"
},
  "geometry": {"coordinates":[-82.467851,34.903445],"type":"Point"}
}