{
  "type": "Feature",
  "properties": {
    "addr:full":"3131 Ora Rd Gray Court SC 29645",
    "addr:housenumber":"3131",
    "addr:postcode":"29645",
    "addr:street":"Ora Rd",
    "iso:country":"US",
    "sg:address":"3131 Ora Rd",
    "sg:city":"Gray Court",
    "sg:classifiers":[
        {
            "category":"Health Services",
            "subcategory":"Chiropractor",
            "type":"Services"
        }
    ],
    "sg:phone":"+1 864 682 3300",
    "sg:postcode":"29645",
    "sg:province":"SC",
    "wof:name":"Kenneth Bryson DC",
    "wof:placetype":"venue"
},
  "geometry": {"coordinates":[-82.048755,34.635058],"type":"Point"}
}