{
  "type": "Feature",
  "properties": {
    "iso:country":"US",
    "sg:address":"904 Laurens Rd",
    "sg:city":"Greenville",
    "sg:classifiers":[
        {
            "category":"Autos & Motor Vehicles",
            "subcategory":"Motorcycle Sales",
            "type":"Retail Goods"
        }
    ],
    "sg:phone":"+1 864 232 7223",
    "sg:postcode":"29607",
    "sg:province":"SC",
    "sg:tags":[
        "scooter"
    ],
    "wof:name":"Upstate Cycle",
    "wof:placetype":"venue"
},
  "geometry": {"coordinates":[-82.370953,34.847913],"type":"Point"}
}