{
  "type": "Feature",
  "properties": {
    "iso:country":"US",
    "sg:address":"4301 Meeting Street Rd",
    "sg:city":"North Charleston",
    "sg:classifiers":[
        {
            "category":"Wholesale",
            "subcategory":"Scrap",
            "type":"Manufacturing & Wholesale Goods"
        }
    ],
    "sg:phone":"+1 843 744 7032",
    "sg:postcode":"29405",
    "sg:province":"SC",
    "sg:tags":[
        "metal",
        "iron"
    ],
    "wof:name":"American Metals",
    "wof:placetype":"venue"
},
  "geometry": {"coordinates":[-79.995683,32.872327],"type":"Point"}
}