{
  "type": "Feature",
  "properties": {
    "iso:country":"US",
    "sg:address":"2388 Otranto Rd",
    "sg:city":"Charleston",
    "sg:classifiers":[
        {
            "category":"Food & Beverages",
            "subcategory":"Groceries & Convenience Stores",
            "type":"Retail Goods"
        }
    ],
    "sg:phone":"+1 843 797 0450",
    "sg:postcode":"29406",
    "sg:province":"SC",
    "sg:tags":[
        "grocer"
    ],
    "wof:name":"Li' L Cricket Store",
    "wof:placetype":"venue"
},
  "geometry": {"coordinates":[-80.054017,32.964363],"type":"Point"}
}