{
  "type": "Feature",
  "properties": {
    "iso:country":"US",
    "sg:address":"3321 N Main St",
    "sg:city":"Anderson",
    "sg:classifiers":[
        {
            "category":"Personal",
            "subcategory":"Tanning Parlor",
            "type":"Services"
        }
    ],
    "sg:phone":"+1 864 261 3474",
    "sg:postcode":"29621",
    "sg:province":"SC",
    "sg:tags":[
        "salon"
    ],
    "wof:name":"Super Tan",
    "wof:placetype":"venue"
},
  "geometry": {"coordinates":[-82.668655,34.543092],"type":"Point"}
}