{
  "type": "Feature",
  "properties": {
    "iso:country":"US",
    "sg:address":"1020 US Hwy 378 W",
    "sg:city":"Lexington",
    "sg:classifiers":[
        {
            "category":"Shopping",
            "subcategory":"Computers & Home Electronics",
            "type":"Retail Goods"
        }
    ],
    "sg:phone":"+1 803 951 3159",
    "sg:postcode":"29072",
    "sg:province":"SC",
    "wof:name":"Mobileenergy",
    "wof:placetype":"venue"
},
  "geometry": {"coordinates":[-81.316905,33.996203],"type":"Point"}
}