{
  "type": "Feature",
  "properties": {
    "addr:full":"123 McIntosh Ln Inman SC 29349",
    "addr:housenumber":"123",
    "addr:postcode":"29349",
    "addr:street":"Mcintosh Ln",
    "iso:country":"US",
    "sg:address":"123 McIntosh Ln",
    "sg:city":"Inman",
    "sg:classifiers":[
        {
            "category":"Shopping",
            "subcategory":"Shoes",
            "type":"Retail Goods"
        }
    ],
    "sg:phone":"+1 864 457 3517",
    "sg:postcode":"29349",
    "sg:province":"SC",
    "wof:name":"Service Shoe Store & Shop",
    "wof:placetype":"venue"
},
  "geometry": {"coordinates":[-82.10623099999999,35.056891],"type":"Point"}
}