{
  "type": "Feature",
  "properties": {
    "iso:country":"US",
    "sg:address":"3208 Port Dr",
    "sg:city":"Myrtle Beach",
    "sg:classifiers":[
        {
            "category":"Manufacturing",
            "subcategory":"Metals",
            "type":"Manufacturing & Wholesale Goods"
        },
        {
            "category":"Shopping",
            "type":"Retail Goods"
        }
    ],
    "sg:phone":"+1 843 293 1166",
    "sg:postcode":"29577",
    "sg:province":"SC",
    "sg:tags":[
        "installs",
        "awning",
        "canopy",
        "fabrication",
        "mfg"
    ],
    "wof:name":"Southern Sun Awnings & Constr",
    "wof:placetype":"venue"
},
  "geometry": {"coordinates":[-78.952471,33.689985],"type":"Point"}
}