{
  "type": "Feature",
  "properties": {
    "addr:full":"421 Dogear Ln Cordesville SC 29434",
    "addr:housenumber":"421",
    "addr:postcode":"29434",
    "addr:street":"Dogear Ln",
    "iso:country":"US",
    "sg:address":"421 Dogear Ln",
    "sg:city":"Cordesville",
    "sg:classifiers":[
        {
            "category":"Building & Trades",
            "subcategory":"Construction",
            "type":"Services"
        }
    ],
    "sg:phone":"+1 843 336 3570",
    "sg:postcode":"29434",
    "sg:province":"SC",
    "sg:tags":[
        "home",
        "improvement"
    ],
    "wof:name":"Turner Home Maintenance & Rpr",
    "wof:placetype":"venue"
},
  "geometry": {"coordinates":[-79.85862,33.143309],"type":"Point"}
}