{
  "type": "Feature",
  "properties": {
    "iso:country":"US",
    "sg:address":"118 W Richardson Ave",
    "sg:city":"Summerville",
    "sg:classifiers":[
        {
            "category":"Real Estate",
            "subcategory":"Real Estate Agent",
            "type":"Services"
        }
    ],
    "sg:phone":"+1 843 871 2121",
    "sg:postcode":"29483",
    "sg:province":"SC",
    "sg:website":"www.century21properties.com",
    "wof:name":"Properties Plus Inc",
    "wof:placetype":"venue"
},
  "geometry": {"coordinates":[-80.176273,33.019206],"type":"Point"}
}