{
  "type": "Feature",
  "properties": {
    "iso:country":"US",
    "sg:address":"406 McDonald Farms Dr",
    "sg:city":"Chesnee",
    "sg:classifiers":[
        {
            "category":"Professional",
            "type":"Services"
        }
    ],
    "sg:phone":"+1 864 703 3297",
    "sg:postcode":"29323",
    "sg:province":"SC",
    "wof:name":"Broadspire Mgt Svc Sharon Clrk",
    "wof:placetype":"venue"
},
  "geometry": {"coordinates":[-81.859901,35.166619],"type":"Point"}
}