{
  "type": "Feature",
  "properties": {
    "iso:country":"US",
    "sg:address":"1303 S Batesville Rd",
    "sg:city":"Greer",
    "sg:classifiers":[
        {
            "category":"Manufacturing",
            "subcategory":"Chemicals & Compounds",
            "type":"Manufacturing & Wholesale Goods"
        }
    ],
    "sg:phone":"+1 864 848 3340",
    "sg:postcode":"29650",
    "sg:province":"SC",
    "sg:tags":[
        "plastic"
    ],
    "sg:website":"www.unimarkplastics.com",
    "wof:name":"Yorker Closures",
    "wof:placetype":"venue"
},
  "geometry": {"coordinates":[-82.23580699999999,34.860458],"type":"Point"}
}