{
  "type": "Feature",
  "properties": {
    "iso:country":"US",
    "sg:address":"69 Meridian Rd",
    "sg:city":"Beaufort",
    "sg:classifiers":[
        {
            "category":"Manufacturing",
            "subcategory":"Jewelry",
            "type":"Manufacturing & Wholesale Goods"
        }
    ],
    "sg:phone":"+1 843 524 9428",
    "sg:postcode":"29907",
    "sg:province":"SC",
    "sg:tags":[
        "precious",
        "metal",
        "mfg"
    ],
    "wof:name":"Jewelry By Barbara",
    "wof:placetype":"venue"
},
  "geometry": {"coordinates":[-80.66314199999999,32.412897],"type":"Point"}
}