{
  "type": "Feature",
  "properties": {
    "addr:full":"110 Howard Ln Anderson SC 29621",
    "addr:housenumber":"110",
    "addr:postcode":"29621",
    "addr:street":"Howard Ln",
    "iso:country":"US",
    "sg:address":"110 Howard Ln",
    "sg:city":"Anderson",
    "sg:classifiers":[
        {
            "category":"Real Estate",
            "subcategory":"Real Estate Services",
            "type":"Services"
        },
        {
            "category":"Real Estate",
            "subcategory":"Real Estate Operator",
            "type":"Services"
        }
    ],
    "sg:phone":"+1 864 226 2475",
    "sg:postcode":"29621",
    "sg:province":"SC",
    "sg:tags":[
        "vacancy",
        "apartment",
        "rental",
        "finder",
        "listing"
    ],
    "wof:name":"Belton Woods Apartments",
    "wof:placetype":"venue"
},
  "geometry": {"coordinates":[-82.618678,34.488294],"type":"Point"}
}