{
  "type": "Feature",
  "properties": {
    "iso:country":"US",
    "sg:address":"478 US Hwy 321 Bus",
    "sg:city":"Winnsboro",
    "sg:classifiers":[
        {
            "category":"Retail",
            "subcategory":"Repair Shop",
            "type":"Services"
        }
    ],
    "sg:phone":"+1 803 712 2000",
    "sg:postcode":"29180",
    "sg:province":"SC",
    "sg:tags":[
        "welding"
    ],
    "wof:name":"Martins Welding Svc",
    "wof:placetype":"venue"
},
  "geometry": {"coordinates":[-81.08623,34.359576],"type":"Point"}
}