{
  "type": "Feature",
  "properties": {
    "iso:country":"US",
    "sg:address":"4189 Neeses Hwy",
    "sg:city":"Neeses",
    "sg:classifiers":[
        {
            "category":"Government",
            "subcategory":"Fire Station",
            "type":"Public Place"
        }
    ],
    "sg:phone":"+1 803 533 1245",
    "sg:postcode":"29107",
    "sg:province":"SC",
    "sg:tags":[
        "department"
    ],
    "wof:name":"Pine Hill Fire Dept",
    "wof:placetype":"venue"
},
  "geometry": {"coordinates":[-81.054203,33.52084],"type":"Point"}
}