{
  "type": "Feature",
  "properties": {
    "addr:full":"244 Scott St Greenville SC 29609",
    "addr:housenumber":"244",
    "addr:postcode":"29609",
    "addr:street":"Scott St",
    "iso:country":"US",
    "sg:address":"244 Scott St",
    "sg:city":"Greenville",
    "sg:classifiers":[
        {
            "category":"Freight",
            "type":"Transportation"
        }
    ],
    "sg:phone":"+1 864 243 0314",
    "sg:postcode":"29609",
    "sg:province":"SC",
    "sg:tags":[
        "mobile",
        "home"
    ],
    "wof:name":"Campbell Enterprises & Assoc",
    "wof:placetype":"venue"
},
  "geometry": {"coordinates":[-82.39908,34.874506],"type":"Point"}
}