{
  "type": "Feature",
  "properties": {
    "iso:country":"US",
    "sg:address":"1107 Wilcox Ave",
    "sg:city":"Gaffney",
    "sg:classifiers":[
        {
            "category":"Autos & Motor Vehicles",
            "subcategory":"Fuel & Gas Station",
            "type":"Retail Goods"
        }
    ],
    "sg:phone":"+1 864 489 9159",
    "sg:postcode":"29341",
    "sg:province":"SC",
    "sg:tags":[
        "plaza",
        "truck",
        "stops"
    ],
    "wof:name":"Normals Truck Stop",
    "wof:placetype":"venue"
},
  "geometry": {"coordinates":[-81.613249,35.106923],"type":"Point"}
}