{
  "type": "Feature",
  "properties": {
    "addr:full":"250 Van Patton Rd Woodruff SC 29388",
    "addr:housenumber":"250",
    "addr:postcode":"29388",
    "addr:street":"Van Patton Rd",
    "iso:country":"US",
    "sg:address":"250 Van Patton Rd",
    "sg:city":"Woodruff",
    "sg:classifiers":[
        {
            "category":"Building & Trades",
            "subcategory":"Landscaping Services",
            "type":"Services"
        }
    ],
    "sg:phone":"+1 864 476 7083",
    "sg:postcode":"29388",
    "sg:province":"SC",
    "wof:name":"Continental Lawn Construction",
    "wof:placetype":"venue"
},
  "geometry": {"coordinates":[-82.102198,34.758261],"type":"Point"}
}