{
  "type": "Feature",
  "properties": {
    "addr:full":"104 Holly Tree Ln Simpsonville SC 29681",
    "addr:housenumber":"104",
    "addr:postcode":"29681",
    "addr:street":"Holly Tree Ln",
    "iso:country":"US",
    "sg:address":"104 Holly Tree Ln",
    "sg:city":"Simpsonville",
    "sg:classifiers":[
        {
            "category":"Wholesale",
            "subcategory":"Books, Periodicals, & Newspapers",
            "type":"Manufacturing & Wholesale Goods"
        }
    ],
    "sg:phone":"+1 864 963 9172",
    "sg:postcode":"29681",
    "sg:province":"SC",
    "wof:name":"High Country Press",
    "wof:placetype":"venue"
},
  "geometry": {"coordinates":[-82.25228300000001,34.782026],"type":"Point"}
}