{
  "type": "Feature",
  "properties": {
    "iso:country":"US",
    "sg:address":"109 Woolbright Cir",
    "sg:city":"Townville",
    "sg:classifiers":[
        {
            "category":"Home & Garden",
            "subcategory":"Building Materials",
            "type":"Retail Goods"
        }
    ],
    "sg:phone":"+1 864 972 1815",
    "sg:postcode":"29689",
    "sg:province":"SC",
    "wof:name":"A1 Fence Co",
    "wof:placetype":"venue"
},
  "geometry": {"coordinates":[-82.91147599999999,34.57469],"type":"Point"}
}