{
  "type": "Feature",
  "properties": {
    "iso:country":"US",
    "sg:address":"488 W Boyce St",
    "sg:city":"Manning",
    "sg:phone":"+1 803 435 2334",
    "sg:postcode":"29102",
    "sg:province":"SC",
    "sg:tags":[
        "oil"
    ],
    "wof:name":"Sprott Oil",
    "wof:placetype":"venue"
},
  "geometry": {"coordinates":[-80.22341900000001,33.696837],"type":"Point"}
}