{
  "type": "Feature",
  "properties": {
    "iso:country":"US",
    "sg:address":"119 N Cox Ave",
    "sg:city":"Calhoun Falls",
    "sg:classifiers":[
        {
            "category":"Insurance",
            "subcategory":"Insurance Agent",
            "type":"Services"
        }
    ],
    "sg:phone":"+1 864 447 0031",
    "sg:postcode":"29628",
    "sg:province":"SC",
    "wof:name":"Woodmen Of The World Insurance",
    "wof:placetype":"venue"
},
  "geometry": {"coordinates":[-82.594082,34.09352],"type":"Point"}
}