{
  "type": "Feature",
  "properties": {
    "addr:full":"411 E Main St Kingstree SC 29556",
    "addr:housenumber":"411",
    "addr:postcode":"29556",
    "addr:street":"E Main St",
    "iso:country":"US",
    "sg:address":"411 E Main St",
    "sg:city":"Kingstree",
    "sg:classifiers":[
        {
            "category":"Wholesale",
            "subcategory":"Auto Parts",
            "type":"Manufacturing & Wholesale Goods"
        }
    ],
    "sg:phone":"+1 843 355 5701",
    "sg:postcode":"29556",
    "sg:province":"SC",
    "sg:tags":[
        "tire"
    ],
    "wof:name":"Hicks Used Tires",
    "wof:placetype":"venue"
},
  "geometry": {"coordinates":[-79.822642,33.665775],"type":"Point"}
}