{
  "type": "Feature",
  "properties": {
    "iso:country":"US",
    "sg:address":"24 Potomac Ave",
    "sg:city":"Greenville",
    "sg:classifiers":[
        {
            "category":"Health Services",
            "subcategory":"Optometrist",
            "type":"Services"
        }
    ],
    "sg:phone":"+1 864 277 4420",
    "sg:postcode":"29605",
    "sg:province":"SC",
    "wof:name":"We Care Eye Care",
    "wof:placetype":"venue"
},
  "geometry": {"coordinates":[-82.38243900000001,34.806415],"type":"Point"}
}