{
  "type": "Feature",
  "properties": {
    "addr:full":"1702 Senate St Columbia SC 29201",
    "addr:housenumber":"1702",
    "addr:postcode":"29201",
    "addr:street":"Senate St",
    "iso:country":"US",
    "sg:address":"1702 Senate St",
    "sg:city":"Columbia",
    "sg:classifiers":[
        {
            "category":"Shopping",
            "subcategory":"Clothing, Apparel, & Fashions",
            "type":"Retail Goods"
        }
    ],
    "sg:phone":"+1 803 771 7996",
    "sg:postcode":"29201",
    "sg:province":"SC",
    "sg:tags":[
        "tailor"
    ],
    "wof:name":"Tailor Sewer Co",
    "wof:placetype":"venue"
},
  "geometry": {"coordinates":[-81.024068,34.002435],"type":"Point"}
}