{
  "type": "Feature",
  "properties": {
    "iso:country":"US",
    "sg:address":"7 Frame Ave",
    "sg:city":"Beaufort",
    "sg:classifiers":[
        {
            "category":"Building & Trades",
            "subcategory":"Construction",
            "type":"Services"
        }
    ],
    "sg:phone":"+1 843 846 1929",
    "sg:postcode":"29906",
    "sg:province":"SC",
    "sg:tags":[
        "roofing",
        "contractor"
    ],
    "wof:name":"Coastal Roofing",
    "wof:placetype":"venue"
},
  "geometry": {"coordinates":[-80.698671,32.513143],"type":"Point"}
}