{
  "type": "Feature",
  "properties": {
    "iso:country":"US",
    "sg:address":"124 Mallard St",
    "sg:city":"Greenville",
    "sg:classifiers":[
        {
            "category":"Shopping",
            "subcategory":"Pharmacy",
            "type":"Retail Goods"
        }
    ],
    "sg:phone":"+1 864 233 5744",
    "sg:postcode":"29601",
    "sg:province":"SC",
    "wof:name":"PSC Med Supply",
    "wof:placetype":"venue"
},
  "geometry": {"coordinates":[-82.414514,34.839209],"type":"Point"}
}