{
  "type": "Feature",
  "properties": {
    "iso:country":"US",
    "sg:address":"217 Campground Rd",
    "sg:city":"Liberty",
    "sg:classifiers":[
        {
            "category":"Retail",
            "subcategory":"Repair Shop",
            "type":"Services"
        }
    ],
    "sg:phone":"+1 864 843 5911",
    "sg:postcode":"29657",
    "sg:province":"SC",
    "sg:tags":[
        "water",
        "heater"
    ],
    "wof:name":"B & M Plumbing",
    "wof:placetype":"venue"
},
  "geometry": {"coordinates":[-82.706796,34.801225],"type":"Point"}
}