{
  "type": "Feature",
  "properties": {
    "addr:full":"100 N Railroad Ave Lamar SC 29069",
    "addr:housenumber":"100",
    "addr:postcode":"29069",
    "addr:street":"N Railroad Ave",
    "iso:country":"US",
    "sg:address":"100 N Railroad Ave",
    "sg:city":"Lamar",
    "sg:classifiers":[
        {
            "category":"Shopping",
            "subcategory":"Pharmacy",
            "type":"Retail Goods"
        }
    ],
    "sg:phone":"+1 843 326 5231",
    "sg:postcode":"29069",
    "sg:province":"SC",
    "wof:name":"Price Wise Pharmacy",
    "wof:placetype":"venue"
},
  "geometry": {"coordinates":[-80.06180500000001,34.171783],"type":"Point"}
}