{
  "type": "Feature",
  "properties": {
    "iso:country":"US",
    "sg:address":"427 Old Trolley Rd",
    "sg:city":"Summerville",
    "sg:classifiers":[
        {
            "category":"Retail",
            "subcategory":"Auto Repair",
            "type":"Services"
        }
    ],
    "sg:phone":"+1 843 873 5900",
    "sg:postcode":"29485",
    "sg:province":"SC",
    "sg:tags":[
        "repairing",
        "automobile"
    ],
    "wof:name":"All Tune & Lube Motormate",
    "wof:placetype":"venue"
},
  "geometry": {"coordinates":[-80.179414,32.990715],"type":"Point"}
}