{
  "type": "Feature",
  "properties": {
    "iso:country":"US",
    "sg:address":"104 Hillcrest Ave",
    "sg:city":"Simpsonville",
    "sg:classifiers":[
        {
            "category":"Building & Trades",
            "subcategory":"Construction",
            "type":"Services"
        }
    ],
    "sg:phone":"+1 864 962 8166",
    "sg:postcode":"29681",
    "sg:province":"SC",
    "sg:tags":[
        "home",
        "builder"
    ],
    "wof:name":"Ike Construction Inc",
    "wof:placetype":"venue"
},
  "geometry": {"coordinates":[-82.25939099999999,34.7434],"type":"Point"}
}