{
  "type": "Feature",
  "properties": {
    "addr:full":"863 Bay Blossom Ave Sumter SC 29150",
    "addr:housenumber":"863",
    "addr:postcode":"29150",
    "addr:street":"Bay Blossom Ave",
    "iso:country":"US",
    "sg:address":"863 Bay Blossom Ave",
    "sg:city":"Sumter",
    "sg:classifiers":[
        {
            "category":"Wholesale",
            "subcategory":"Construction Materials",
            "type":"Manufacturing & Wholesale Goods"
        }
    ],
    "sg:phone":"+1 803 905 1900",
    "sg:postcode":"29150",
    "sg:province":"SC",
    "sg:tags":[
        "lumber"
    ],
    "wof:name":"Crawford Wood Products",
    "wof:placetype":"venue"
},
  "geometry": {"coordinates":[-80.38699699999999,33.94307],"type":"Point"}
}