{
  "type": "Feature",
  "properties": {
    "addr:full":"307 Johns St Florence SC 29506",
    "addr:housenumber":"307",
    "addr:postcode":"29506",
    "addr:street":"Johns St",
    "iso:country":"US",
    "sg:address":"307 Johns St",
    "sg:city":"Florence",
    "sg:classifiers":[
        {
            "category":"Retail",
            "subcategory":"Funeral Services",
            "type":"Services"
        }
    ],
    "sg:phone":"+1 843 662 7192",
    "sg:postcode":"29506",
    "sg:province":"SC",
    "sg:tags":[
        "director"
    ],
    "wof:name":"Smith's Funeral Svc Inc",
    "wof:placetype":"venue"
},
  "geometry": {"coordinates":[-79.7538,34.193508],"type":"Point"}
}