{
  "type": "Feature",
  "properties": {
    "addr:full":"1024 Belle Dr North Myrtle Bch SC 29582",
    "addr:housenumber":"1024",
    "addr:postcode":"29582",
    "addr:street":"Belle Dr North Myrtle",
    "iso:country":"US",
    "sg:address":"1024 Belle Dr",
    "sg:city":"North Myrtle Bch",
    "sg:classifiers":[
        {
            "category":"Professional",
            "subcategory":"Advertising",
            "type":"Services"
        }
    ],
    "sg:phone":"+1 843 272 1120",
    "sg:postcode":"29582",
    "sg:province":"SC",
    "sg:tags":[
        "distribution"
    ],
    "wof:name":"Carolina Group Distributors",
    "wof:placetype":"venue"
},
  "geometry": {"coordinates":[-78.69010900000001,33.825383],"type":"Point"}
}