{
  "type": "Feature",
  "properties": {
    "iso:country":"US",
    "sg:address":"101 Dutch Square Blvd",
    "sg:city":"Columbia",
    "sg:classifiers":[
        {
            "category":"Banks & Credit Unions",
            "subcategory":"Bank",
            "type":"Services"
        }
    ],
    "sg:phone":"+1 803 750 7804",
    "sg:postcode":"29210",
    "sg:province":"SC",
    "sg:website":"www.wachovia.com",
    "wof:name":"Wachovia Bank",
    "wof:placetype":"venue"
},
  "geometry": {"coordinates":[-81.09624100000001,34.032001],"type":"Point"}
}