{
  "type": "Feature",
  "properties": {
    "iso:country":"US",
    "sg:address":"500 Harbison Blvd",
    "sg:city":"Columbia",
    "sg:classifiers":[
        {
            "category":"Real Estate",
            "subcategory":"Real Estate Operator",
            "type":"Services"
        }
    ],
    "sg:phone":"+1 803 781 9541",
    "sg:postcode":"29212",
    "sg:province":"SC",
    "sg:tags":[
        "building",
        "apartment"
    ],
    "wof:name":"Well Spring Apts",
    "wof:placetype":"venue"
},
  "geometry": {"coordinates":[-81.14432600000001,34.08179],"type":"Point"}
}