{
  "type": "Feature",
  "properties": {
    "addr:full":"309 Three and Twenty Rd Easley SC 29642",
    "addr:housenumber":"309",
    "addr:postcode":"29642",
    "addr:street":"Three And Twenty Rd",
    "iso:country":"US",
    "sg:address":"309 Three and Twenty Rd",
    "sg:city":"Easley",
    "sg:classifiers":[
        {
            "category":"Retail",
            "subcategory":"Repair Shop",
            "type":"Services"
        }
    ],
    "sg:phone":"+1 864 859 8596",
    "sg:postcode":"29642",
    "sg:province":"SC",
    "sg:tags":[
        "blacksmith"
    ],
    "wof:name":"Curtis Hamilton Blcksmth Supl",
    "wof:placetype":"venue"
},
  "geometry": {"coordinates":[-82.59469900000001,34.719506],"type":"Point"}
}