{
  "type": "Feature",
  "properties": {
    "iso:country":"US",
    "sg:address":"621 Bluff Rd",
    "sg:city":"Columbia",
    "sg:classifiers":[
        {
            "category":"Education",
            "subcategory":"School",
            "type":"Public Place"
        }
    ],
    "sg:phone":"+1 803 400 1650",
    "sg:postcode":"29201",
    "sg:province":"SC",
    "wof:name":"Olympia High School",
    "wof:placetype":"venue"
},
  "geometry": {"coordinates":[-81.028114,33.978655],"type":"Point"}
}