{
  "type": "Feature",
  "properties": {
    "addr:full":"2870 Reidville Rd Spartanburg SC 29301",
    "addr:postcode":"2870;29301",
    "addr:street":"Reidville Rd",
    "iso:country":"US",
    "sg:address":"2870 Reidville Rd",
    "sg:city":"Spartanburg",
    "sg:classifiers":[
        {
            "category":"Professional",
            "subcategory":"Research",
            "type":"Services"
        }
    ],
    "sg:phone":"+1 864 595 7046",
    "sg:postcode":"29301",
    "sg:province":"SC",
    "sg:tags":[
        "environmental",
        "ecological"
    ],
    "wof:name":"ESTI",
    "wof:placetype":"venue"
},
  "geometry": {"coordinates":[-82.005053,34.916523],"type":"Point"}
}