{
  "type": "Feature",
  "properties": {
    "iso:country":"US",
    "sg:address":"542 College Ave",
    "sg:city":"Clemson",
    "sg:classifiers":[
        {
            "category":"Personal",
            "subcategory":"Beauty Salon",
            "type":"Services"
        }
    ],
    "sg:phone":"+1 864 624 8266",
    "sg:postcode":"29631",
    "sg:province":"SC",
    "wof:name":"Cuttin' Up",
    "wof:placetype":"venue"
},
  "geometry": {"coordinates":[-82.833879,34.690596],"type":"Point"}
}