{
  "type": "Feature",
  "properties": {
    "iso:country":"US",
    "sg:address":"170 Old Barnwell Rd",
    "sg:city":"Aiken",
    "sg:classifiers":[
        {
            "category":"Organizations",
            "subcategory":"Religious Organization",
            "type":"Services"
        }
    ],
    "sg:phone":"+1 803 648 2290",
    "sg:postcode":"29803",
    "sg:province":"SC",
    "sg:tags":[
        "church"
    ],
    "wof:name":"Montmorenci Missionary Baptist",
    "wof:placetype":"venue"
},
  "geometry": {"coordinates":[-81.623654,33.502291],"type":"Point"}
}