{
  "type": "Feature",
  "properties": {
    "iso:country":"US",
    "sg:address":"606 N Woods Dr",
    "sg:city":"Fountain Inn",
    "sg:classifiers":[
        {
            "category":"Freight",
            "type":"Transportation"
        }
    ],
    "sg:phone":"+1 864 862 0086",
    "sg:postcode":"29644",
    "sg:province":"SC",
    "sg:tags":[
        "mover"
    ],
    "wof:name":"Five 0 Moving & Storage",
    "wof:placetype":"venue"
},
  "geometry": {"coordinates":[-82.22927799999999,34.695584],"type":"Point"}
}