{
  "type": "Feature",
  "properties": {
    "iso:country":"US",
    "sg:address":"8308 Dye Makers Ridge",
    "sg:city":"North Charleston",
    "sg:classifiers":[
        {
            "category":"Real Estate",
            "subcategory":"Developer",
            "type":"Services"
        }
    ],
    "sg:phone":"+1 843 552 8013",
    "sg:postcode":"29418",
    "sg:province":"SC",
    "wof:name":"Maverick Development Realty",
    "wof:placetype":"venue"
},
  "geometry": {"coordinates":[-80.106612,32.902473],"type":"Point"}
}