{
  "type": "Feature",
  "properties": {
    "iso:country":"US",
    "sg:address":"824 S Main St",
    "sg:city":"Marion",
    "sg:classifiers":[
        {
            "category":"Autos & Motor Vehicles",
            "subcategory":"Fuel & Gas Station",
            "type":"Retail Goods"
        }
    ],
    "sg:phone":"+1 843 423 5831",
    "sg:postcode":"29571",
    "sg:province":"SC",
    "sg:tags":[
        "station",
        "gasoline"
    ],
    "wof:name":"Sav-Way",
    "wof:placetype":"venue"
},
  "geometry": {"coordinates":[-79.399396,34.16894],"type":"Point"}
}