{
  "type": "Feature",
  "properties": {
    "iso:country":"US",
    "sg:address":"102 Pleasent View Rd",
    "sg:city":"Tamassee",
    "sg:classifiers":[
        {
            "category":"Building & Trades",
            "subcategory":"Construction",
            "type":"Services"
        }
    ],
    "sg:phone":"+1 864 944 7325",
    "sg:postcode":"29686",
    "sg:province":"SC",
    "sg:tags":[
        "paving",
        "contractor"
    ],
    "wof:name":"Asphalt Seal Coating Service",
    "wof:placetype":"venue"
},
  "geometry": {"coordinates":[-83.033708,34.886619],"type":"Point"}
}