{
  "type": "Feature",
  "properties": {
    "iso:country":"US",
    "sg:address":"353 Valley View Dr",
    "sg:city":"Woodruff",
    "sg:classifiers":[
        {
            "category":"Retail",
            "subcategory":"Repair Shop",
            "type":"Services"
        }
    ],
    "sg:phone":"+1 864 476 0773",
    "sg:postcode":"29388",
    "sg:province":"SC",
    "sg:tags":[
        "appliance",
        "household",
        "electrical"
    ],
    "wof:name":"Doctor Vacuum",
    "wof:placetype":"venue"
},
  "geometry": {"coordinates":[-82.016802,34.7741],"type":"Point"}
}