{
  "type": "Feature",
  "properties": {
    "iso:country":"US",
    "sg:address":"53 Pleasant Retreat Rd",
    "sg:city":"Travelers Rest",
    "sg:classifiers":[
        {
            "category":"Home & Garden",
            "subcategory":"Carpets & Floor Coverings",
            "type":"Retail Goods"
        }
    ],
    "sg:phone":"+1 864 834 5245",
    "sg:postcode":"29690",
    "sg:province":"SC",
    "wof:name":"T&D Carpet Service",
    "wof:placetype":"venue"
},
  "geometry": {"coordinates":[-82.46166100000001,35.00799],"type":"Point"}
}