{
  "type": "Feature",
  "properties": {
    "iso:country":"US",
    "sg:address":"1510 State Hwy 55 E",
    "sg:city":"Clover",
    "sg:classifiers":[
        {
            "category":"Food & Beverages",
            "subcategory":"Groceries & Convenience Stores",
            "type":"Retail Goods"
        }
    ],
    "sg:phone":"+1 803 222 2970",
    "sg:postcode":"29710",
    "sg:province":"SC",
    "wof:name":"Nichols Food Store",
    "wof:placetype":"venue"
},
  "geometry": {"coordinates":[-81.189319,35.100082],"type":"Point"}
}