{
  "type": "Feature",
  "properties": {
    "iso:country":"US",
    "sg:address":"552 Old Howell Rd",
    "sg:city":"Greenville",
    "sg:classifiers":[
        {
            "category":"Restaurant",
            "type":"Food & Drink"
        }
    ],
    "sg:phone":"+1 864 292 3410",
    "sg:postcode":"29615",
    "sg:province":"SC",
    "wof:name":"Wedgy's Pizza Delivery",
    "wof:placetype":"venue"
},
  "geometry": {"coordinates":[-82.330412,34.874025],"type":"Point"}
}