{
  "type": "Feature",
  "properties": {
    "iso:country":"US",
    "sg:address":"2810 Shop Rd",
    "sg:city":"Columbia",
    "sg:classifiers":[
        {
            "category":"Wholesale",
            "subcategory":"Stationery",
            "type":"Manufacturing & Wholesale Goods"
        }
    ],
    "sg:phone":"+1 803 476 1600",
    "sg:postcode":"29201",
    "sg:province":"SC",
    "sg:tags":[
        "all",
        "paper",
        "type",
        "product"
    ],
    "wof:name":"International Paper",
    "wof:placetype":"venue"
},
  "geometry": {"coordinates":[-80.95657799999999,33.940743],"type":"Point"}
}