{
  "type": "Feature",
  "properties": {
    "iso:country":"US",
    "sg:address":"280d W Coleman Blvd",
    "sg:city":"Mount Pleasant",
    "sg:classifiers":[
        {
            "category":"Restaurant",
            "type":"Food & Drink"
        }
    ],
    "sg:menulink":"http://www.allmenus.com/sc/mount-pleasant/228885-jersey-mikes/menu/",
    "sg:phone":"+1 843 881 7996",
    "sg:postcode":"29464",
    "sg:province":"SC",
    "sg:tags":[
        "american",
        "sandwich"
    ],
    "wof:name":"Jersey Mike's",
    "wof:placetype":"venue"
},
  "geometry": {"coordinates":[-79.891964,32.797577],"type":"Point"}
}