{
  "type": "Feature",
  "properties": {
    "iso:country":"US",
    "sg:address":"1474 E Main St",
    "sg:city":"Rock Hill",
    "sg:classifiers":[
        {
            "category":"Bars & Pubs",
            "type":"Food & Drink"
        }
    ],
    "sg:phone":"+1 803 325 8434",
    "sg:postcode":"29730",
    "sg:province":"SC",
    "sg:tags":[
        "club",
        "night"
    ],
    "wof:name":"Pub",
    "wof:placetype":"venue"
},
  "geometry": {"coordinates":[-80.99696900000001,34.918161],"type":"Point"}
}