{
  "type": "Feature",
  "properties": {
    "iso:country":"US",
    "sg:address":"1278 Pridgen Rd",
    "sg:city":"Myrtle Beach",
    "sg:classifiers":[
        {
            "category":"Professional",
            "subcategory":"Accounting & Tax Preparation",
            "type":"Services"
        }
    ],
    "sg:phone":"+1 843 449 1827",
    "sg:postcode":"29577",
    "sg:province":"SC",
    "sg:tags":[
        "bookkeeping",
        "general"
    ],
    "wof:name":"Ram's Bookkeeping & Tax Svc",
    "wof:placetype":"venue"
},
  "geometry": {"coordinates":[-78.906575,33.683572],"type":"Point"}
}