{
  "type": "Feature",
  "properties": {
    "iso:country":"US",
    "sg:address":"125 Herlong Ave",
    "sg:city":"St Matthews",
    "sg:classifiers":[
        {
            "category":"Education",
            "subcategory":"School",
            "type":"Public Place"
        }
    ],
    "sg:phone":"+1 803 874 3314",
    "sg:postcode":"29135",
    "sg:province":"SC",
    "sg:website":"www.calhoun.k12.sc.us",
    "wof:name":"Guinyard Elementary School",
    "wof:placetype":"venue"
},
  "geometry": {"coordinates":[-80.784643,33.671115],"type":"Point"}
}