{
  "type": "Feature",
  "properties": {
    "addr:full":"516 King St Charleston SC 29403",
    "addr:housenumber":"516",
    "addr:postcode":"29403",
    "addr:street":"King St",
    "iso:country":"US",
    "sg:address":"516 King St",
    "sg:city":"Charleston",
    "sg:classifiers":[
        {
            "category":"Shopping",
            "subcategory":"Used Merchandise",
            "type":"Retail Goods"
        }
    ],
    "sg:phone":"+1 843 723 1051",
    "sg:postcode":"29403",
    "sg:province":"SC",
    "sg:tags":[
        "instrument",
        "musical",
        "pawnshop"
    ],
    "wof:name":"Georges Loan",
    "wof:placetype":"venue"
},
  "geometry": {"coordinates":[-79.94025999999999,32.791643],"type":"Point"}
}