{
  "type": "Feature",
  "properties": {
    "iso:country":"US",
    "sg:address":"1653 Remount Rd",
    "sg:city":"North Charleston",
    "sg:classifiers":[
        {
            "category":"Professional",
            "subcategory":"Employment Agencies",
            "type":"Services"
        }
    ],
    "sg:phone":"+1 843 308 9663",
    "sg:postcode":"29406",
    "sg:province":"SC",
    "sg:tags":[
        "opportunity"
    ],
    "wof:name":"Staff Zone",
    "wof:placetype":"venue"
},
  "geometry": {"coordinates":[-80.006514,32.900327],"type":"Point"}
}