{
  "type": "Feature",
  "properties": {
    "addr:full":"2302 Bush River Rd Columbia SC 29210",
    "addr:housenumber":"2302",
    "addr:postcode":"29210",
    "addr:street":"Bush River Rd",
    "iso:country":"US",
    "sg:address":"2302 Bush River Rd",
    "sg:city":"Columbia",
    "sg:classifiers":[
        {
            "category":"Health Services",
            "subcategory":"Dentist",
            "type":"Services"
        }
    ],
    "sg:phone":"+1 803 798 8675",
    "sg:postcode":"29210",
    "sg:province":"SC",
    "sg:tags":[
        "pediatric"
    ],
    "wof:name":"Sasnett Richard M Dr PA Dntst",
    "wof:placetype":"venue"
},
  "geometry": {"coordinates":[-81.1241,34.033001],"type":"Point"}
}