{
  "type": "Feature",
  "properties": {
    "iso:country":"US",
    "sg:address":"115 Ron Ln",
    "sg:city":"Greenville",
    "sg:classifiers":[
        {
            "category":"Building & Trades",
            "subcategory":"Plumbing",
            "type":"Services"
        }
    ],
    "sg:phone":"+1 864 220 1046",
    "sg:postcode":"29611",
    "sg:province":"SC",
    "sg:tags":[
        "contractor",
        "drainage"
    ],
    "wof:name":"Al's Plumbing",
    "wof:placetype":"venue"
},
  "geometry": {"coordinates":[-82.479055,34.826543],"type":"Point"}
}