{
  "type": "Feature",
  "properties": {
    "addr:full":"1525 Wire Rd Aiken SC 29805",
    "addr:housenumber":"1525",
    "addr:postcode":"29805",
    "addr:street":"Wire Rd",
    "iso:country":"US",
    "sg:address":"1525 Wire Rd",
    "sg:city":"Aiken",
    "sg:classifiers":[
        {
            "category":"Building & Trades",
            "subcategory":"Construction",
            "type":"Services"
        }
    ],
    "sg:phone":"+1 803 648 7649",
    "sg:postcode":"29805",
    "sg:province":"SC",
    "sg:tags":[
        "equipment",
        "installation"
    ],
    "wof:name":"William C Doolittle Builders",
    "wof:placetype":"venue"
},
  "geometry": {"coordinates":[-81.643106,33.658649],"type":"Point"}
}