{
  "type": "Feature",
  "properties": {
    "iso:country":"US",
    "sg:address":"211 B St",
    "sg:city":"Anderson",
    "sg:classifiers":[
        {
            "category":"Banks & Credit Unions",
            "subcategory":"Bank",
            "type":"Services"
        }
    ],
    "sg:phone":"+1 864 260 9211",
    "sg:postcode":"29625",
    "sg:province":"SC",
    "sg:tags":[
        "cashing",
        "sell",
        "money",
        "order",
        "check"
    ],
    "wof:name":"Ace Cash Express",
    "wof:placetype":"venue"
},
  "geometry": {"coordinates":[-82.658894,34.507089],"type":"Point"}
}