{
  "type": "Feature",
  "properties": {
    "iso:country":"US",
    "sg:address":"1171 Pope St",
    "sg:city":"Turbeville",
    "sg:classifiers":[
        {
            "category":"Education",
            "subcategory":"School",
            "type":"Public Place"
        }
    ],
    "sg:phone":"+1 843 659 2185",
    "sg:postcode":"29108",
    "sg:province":"SC",
    "wof:name":"East Claredon High School",
    "wof:placetype":"venue"
},
  "geometry": {"coordinates":[-81.626417,34.284406],"type":"Point"}
}