{
  "type": "Feature",
  "properties": {
    "iso:country":"US",
    "sg:address":"2991 Whitestone Glendale Rd",
    "sg:city":"Spartanburg",
    "sg:classifiers":[
        {
            "category":"Building & Trades",
            "subcategory":"Construction",
            "type":"Services"
        }
    ],
    "sg:phone":"+1 864 582 3050",
    "sg:postcode":"29302",
    "sg:province":"SC",
    "sg:tags":[
        "general",
        "contractor"
    ],
    "wof:name":"D R Construction LLC",
    "wof:placetype":"venue"
},
  "geometry": {"coordinates":[-81.840991,34.939971],"type":"Point"}
}