{
  "type": "Feature",
  "properties": {
    "iso:country":"US",
    "sg:address":"6411 State Hwy 908",
    "sg:city":"Gresham",
    "sg:classifiers":[
        {
            "category":"Organizations",
            "subcategory":"Religious Organization",
            "type":"Services"
        }
    ],
    "sg:phone":"+1 843 362 0440",
    "sg:postcode":"29546",
    "sg:province":"SC",
    "sg:tags":[
        "church"
    ],
    "wof:name":"Nebo Baptist Church",
    "wof:placetype":"venue"
},
  "geometry": {"coordinates":[-79.343761,33.943131],"type":"Point"}
}