{
  "type": "Feature",
  "properties": {
    "iso:country":"US",
    "sg:address":"701 US Hwy 701 N",
    "sg:city":"Loris",
    "sg:classifiers":[
        {
            "category":"Food & Beverages",
            "subcategory":"Groceries & Convenience Stores",
            "type":"Retail Goods"
        }
    ],
    "sg:phone":"+1 843 756 6090",
    "sg:postcode":"29569",
    "sg:province":"SC",
    "wof:name":"Cash & Dash",
    "wof:placetype":"venue"
},
  "geometry": {"coordinates":[-78.87717499999999,34.072663],"type":"Point"}
}