{
  "type": "Feature",
  "properties": {
    "addr:full":"27 N Georgia Ave Greenville SC 29611",
    "addr:housenumber":"27",
    "addr:postcode":"29611",
    "addr:street":"N Georgia Ave",
    "iso:country":"US",
    "sg:address":"27 N Georgia Ave",
    "sg:city":"Greenville",
    "sg:classifiers":[
        {
            "category":"Home & Garden",
            "subcategory":"Home Furnishings",
            "type":"Retail Goods"
        }
    ],
    "sg:phone":"+1 864 295 0803",
    "sg:postcode":"29611",
    "sg:province":"SC",
    "sg:tags":[
        "pillow"
    ],
    "wof:name":"Lane's Pillows Wholesale",
    "wof:placetype":"venue"
},
  "geometry": {"coordinates":[-82.437076,34.838364],"type":"Point"}
}