{
  "type": "Feature",
  "properties": {
    "iso:country":"US",
    "sg:address":"1401 Main St",
    "sg:city":"Columbia",
    "sg:classifiers":[
        {
            "category":"Real Estate",
            "subcategory":"Real Estate Services",
            "type":"Services"
        }
    ],
    "sg:phone":"+1 803 799 9443",
    "sg:postcode":"29201",
    "sg:province":"SC",
    "wof:name":"Smith John C Rl Est",
    "wof:placetype":"venue"
},
  "geometry": {"coordinates":[-81.034897,34.003899],"type":"Point"}
}