{
  "type": "Feature",
  "properties": {
    "addr:full":"3455 Southport Rd Spartanburg SC 29302",
    "addr:housenumber":"3455",
    "addr:postcode":"29302",
    "addr:street":"Southport Rd",
    "iso:country":"US",
    "sg:address":"3455 Southport Rd",
    "sg:city":"Spartanburg",
    "sg:classifiers":[
        {
            "category":"Wholesale",
            "subcategory":"Chemicals & Plastics",
            "type":"Manufacturing & Wholesale Goods"
        }
    ],
    "sg:phone":"+1 864 585 3411",
    "sg:postcode":"29302",
    "sg:province":"SC",
    "sg:website":"www.dass.com",
    "wof:name":"BASF Corp",
    "wof:placetype":"venue"
},
  "geometry": {"coordinates":[-81.814967,34.902943],"type":"Point"}
}