{
  "type": "Feature",
  "properties": {
    "iso:country":"US",
    "sg:address":"664 Emily Ln",
    "sg:city":"Piedmont",
    "sg:classifiers":[
        {
            "category":"Insurance",
            "subcategory":"Insurance Agent",
            "type":"Services"
        }
    ],
    "sg:phone":"+1 864 236 9406",
    "sg:postcode":"29673",
    "sg:province":"SC",
    "wof:name":"Insurance Nationwide",
    "wof:placetype":"venue"
},
  "geometry": {"coordinates":[-82.392082,34.718043],"type":"Point"}
}