{
  "type": "Feature",
  "properties": {
    "iso:country":"US",
    "sg:address":"3009 Magnolia St",
    "sg:city":"Beaufort",
    "sg:classifiers":[
        {
            "category":"Bus Charters",
            "type":"Transportation"
        }
    ],
    "sg:phone":"+1 843 986 0633",
    "sg:postcode":"29906",
    "sg:province":"SC",
    "sg:tags":[
        "rental"
    ],
    "wof:name":"Fidelis Coach",
    "wof:placetype":"venue"
},
  "geometry": {"coordinates":[-80.74002400000001,32.384033],"type":"Point"}
}