{
  "type": "Feature",
  "properties": {
    "addr:full":"131 Ridge Glen Simpsonville SC 29680",
    "addr:housenumber":"131",
    "addr:postcode":"29680",
    "addr:street":"Ridge Glen",
    "iso:country":"US",
    "sg:address":"131 Ridge Glen",
    "sg:city":"Simpsonville",
    "sg:classifiers":[
        {
            "category":"Manufacturing",
            "subcategory":"Apparel",
            "type":"Manufacturing & Wholesale Goods"
        }
    ],
    "sg:phone":"+1 864 862 1312",
    "sg:postcode":"29680",
    "sg:province":"SC",
    "sg:tags":[
        "curtain",
        "drapery",
        "mfg"
    ],
    "wof:name":"Bearden Contract Draperies",
    "wof:placetype":"venue"
},
  "geometry": {"coordinates":[-82.280134,34.667358],"type":"Point"}
}