{
  "type": "Feature",
  "properties": {
    "iso:country":"US",
    "sg:address":"1663 Ebinport Rd",
    "sg:city":"Rock Hill",
    "sg:classifiers":[
        {
            "category":"Building & Trades",
            "subcategory":"Landscaping Services",
            "type":"Services"
        }
    ],
    "sg:phone":"+1 803 328 6767",
    "sg:postcode":"29732",
    "sg:province":"SC",
    "sg:tags":[
        "landscape",
        "contractor"
    ],
    "wof:name":"Jimmy O'Connor & Sons",
    "wof:placetype":"venue"
},
  "geometry": {"coordinates":[-81.026332,34.967867],"type":"Point"}
}