{
  "type": "Feature",
  "properties": {
    "addr:full":"1703 White Horse Rd Greenville SC 29605",
    "addr:housenumber":"1703",
    "addr:postcode":"29605",
    "addr:street":"White Horse Rd",
    "iso:country":"US",
    "sg:address":"1703 White Horse Rd",
    "sg:city":"Greenville",
    "sg:classifiers":[
        {
            "category":"Restaurant",
            "type":"Food & Drink"
        }
    ],
    "sg:phone":"+1 864 295 0282",
    "sg:postcode":"29605",
    "sg:province":"SC",
    "sg:tags":[
        "eating"
    ],
    "wof:name":"Captain Ds",
    "wof:placetype":"venue"
},
  "geometry": {"coordinates":[-82.41242200000001,34.785639],"type":"Point"}
}