{
  "type": "Feature",
  "properties": {
    "iso:country":"US",
    "sg:address":"1703 White Horse Rd",
    "sg:city":"Greenville",
    "sg:classifiers":[
        {
            "category":"Restaurant",
            "type":"Food & Drink"
        }
    ],
    "sg:phone":"+1 864 295 0282",
    "sg:postcode":"29605",
    "sg:province":"SC",
    "sg:tags":[
        "eating"
    ],
    "wof:name":"Captain Ds",
    "wof:placetype":"venue"
},
  "geometry": {"coordinates":[-82.412422,34.785639],"type":"Point"}
}