{
  "type": "Feature",
  "properties": {
    "iso:country":"US",
    "sg:address":"391 Serpentine Dr",
    "sg:city":"Spartanburg",
    "sg:classifiers":[
        {
            "category":"Health Services",
            "subcategory":"Clinic",
            "type":"Services"
        }
    ],
    "sg:phone":"+1 864 583 8190",
    "sg:postcode":"29303",
    "sg:province":"SC",
    "sg:tags":[
        "home"
    ],
    "wof:name":"Primecare Infusion Svc",
    "wof:placetype":"venue"
},
  "geometry": {"coordinates":[-81.93799799999999,34.965173],"type":"Point"}
}