{
  "type": "Feature",
  "properties": {
    "iso:country":"US",
    "sg:address":"915 Laurens Rd",
    "sg:city":"Greenville",
    "sg:classifiers":[
        {
            "category":"Retail",
            "subcategory":"Auto Repair",
            "type":"Services"
        }
    ],
    "sg:phone":"+1 864 232 2345",
    "sg:postcode":"29607",
    "sg:province":"SC",
    "sg:tags":[
        "repairing",
        "automobile"
    ],
    "wof:name":"Global Cars Repair & Svc",
    "wof:placetype":"venue"
},
  "geometry": {"coordinates":[-82.370948,34.84809],"type":"Point"}
}