{
  "type": "Feature",
  "properties": {
    "iso:country":"US",
    "sg:address":"2620 S Main St",
    "sg:city":"Anderson",
    "sg:classifiers":[
        {
            "category":"Organizations",
            "subcategory":"Religious Organization",
            "type":"Services"
        }
    ],
    "sg:phone":"+1 864 224 6980",
    "sg:postcode":"29624",
    "sg:province":"SC",
    "sg:tags":[
        "church"
    ],
    "wof:name":"Orrville Baptist Church",
    "wof:placetype":"venue"
},
  "geometry": {"coordinates":[-82.647727,34.482073],"type":"Point"}
}