{
  "type": "Feature",
  "properties": {
    "iso:country":"US",
    "sg:address":"511 63rd Ave N",
    "sg:city":"Myrtle Beach",
    "sg:classifiers":[
        {
            "category":"Taxi",
            "type":"Transportation"
        }
    ],
    "sg:phone":"+1 843 467 2694",
    "sg:postcode":"29572",
    "sg:province":"SC",
    "sg:tags":[
        "taxicab"
    ],
    "wof:name":"A&A Taxi Inc",
    "wof:placetype":"venue"
},
  "geometry": {"coordinates":[-78.83260199999999,33.738336],"type":"Point"}
}