{
  "type": "Feature",
  "properties": {
    "addr:full":"1413 Commerce Dr Dillon SC 29536",
    "addr:housenumber":"1413",
    "addr:postcode":"29536",
    "addr:street":"Commerce Dr",
    "iso:country":"US",
    "sg:address":"1413 Commerce Dr",
    "sg:city":"Dillon",
    "sg:classifiers":[
        {
            "category":"Social Services",
            "subcategory":"Child Care",
            "type":"Services"
        }
    ],
    "sg:phone":"+1 843 774 0890",
    "sg:postcode":"29536",
    "sg:province":"SC",
    "sg:tags":[
        "kindergarten",
        "academic",
        "school"
    ],
    "wof:name":"Dillon Christian Preschool",
    "wof:placetype":"venue"
},
  "geometry": {"coordinates":[-79.36314900000001,34.439803],"type":"Point"}
}