{
  "type": "Feature",
  "properties": {
    "iso:country":"US",
    "sg:address":"1189 Iron Bridge Dr",
    "sg:city":"Mt Pleasant",
    "sg:classifiers":[
        {
            "category":"Government",
            "subcategory":"Office",
            "type":"Public Place"
        }
    ],
    "sg:phone":"+1 843 856 1214",
    "sg:postcode":"29466",
    "sg:province":"SC",
    "wof:name":"Charleston County Bldg Inspctn",
    "wof:placetype":"venue"
},
  "geometry": {"coordinates":[-79.82235,32.831779],"type":"Point"}
}