{
  "type": "Feature",
  "properties": {
    "addr:full":"209 N 5th St Hartsville SC 29550",
    "addr:housenumber":"209",
    "addr:postcode":"29550",
    "addr:street":"N 5Th St",
    "iso:country":"US",
    "sg:address":"209 N 5th St",
    "sg:city":"Hartsville",
    "sg:classifiers":[
        {
            "category":"Retail",
            "subcategory":"Laundry & Dry Cleaning",
            "type":"Services"
        }
    ],
    "sg:phone":"+1 843 332 6671",
    "sg:postcode":"29550",
    "sg:province":"SC",
    "sg:tags":[
        "cleaners"
    ],
    "wof:name":"Sanitary Cleaners & Laundry",
    "wof:placetype":"venue"
},
  "geometry": {"coordinates":[-80.07512,34.37769],"type":"Point"}
}