{
  "type": "Feature",
  "properties": {
    "iso:country":"US",
    "sg:address":"601 W Greer St",
    "sg:city":"Honea Path",
    "sg:classifiers":[
        {
            "category":"Food & Beverages",
            "subcategory":"Groceries & Convenience Stores",
            "type":"Retail Goods"
        }
    ],
    "sg:phone":"+1 864 369 0189",
    "sg:postcode":"29654",
    "sg:province":"SC",
    "wof:name":"Stop A Minute II",
    "wof:placetype":"venue"
},
  "geometry": {"coordinates":[-82.407034,34.444327],"type":"Point"}
}