{
  "type": "Feature",
  "properties": {
    "iso:country":"US",
    "sg:address":"700 Gervais St",
    "sg:city":"Columbia",
    "sg:classifiers":[
        {
            "category":"Professional",
            "subcategory":"Lawyer & Legal Services",
            "type":"Services"
        }
    ],
    "sg:phone":"+1 803 771 7900",
    "sg:postcode":"29201",
    "sg:province":"SC",
    "wof:name":"Hewson Stacey L",
    "wof:placetype":"venue"
},
  "geometry": {"coordinates":[-81.04160299999999,33.998798],"type":"Point"}
}