{
  "type": "Feature",
  "properties": {
    "iso:country":"US",
    "sg:address":"605 Whaley St",
    "sg:city":"Columbia",
    "sg:classifiers":[
        {
            "category":"Real Estate",
            "subcategory":"Real Estate Operator",
            "type":"Services"
        }
    ],
    "sg:phone":"+1 803 799 4009",
    "sg:postcode":"29201",
    "sg:province":"SC",
    "wof:name":"Chase",
    "wof:placetype":"venue"
},
  "geometry": {"coordinates":[-81.035974,33.985209],"type":"Point"}
}