{
  "type": "Feature",
  "properties": {
    "iso:country":"US",
    "sg:address":"4109 E North St",
    "sg:city":"Greenville",
    "sg:classifiers":[
        {
            "category":"Insurance",
            "subcategory":"Hazard Insurance",
            "type":"Services"
        },
        {
            "category":"Insurance",
            "subcategory":"Insurance Agent",
            "type":"Services"
        }
    ],
    "sg:phone":"+1 864 244 8087",
    "sg:postcode":"29615",
    "sg:province":"SC",
    "sg:tags":[
        "carrier",
        "surety"
    ],
    "wof:name":"Stewart Financial Group",
    "wof:placetype":"venue"
},
  "geometry": {"coordinates":[-82.319483,34.877788],"type":"Point"}
}