{
  "type": "Feature",
  "properties": {
    "addr:full":"107 S Alabama Ave Chesnee SC 29323",
    "addr:housenumber":"107",
    "addr:postcode":"29323",
    "addr:street":"S Alabama Ave",
    "iso:country":"US",
    "sg:address":"107 S Alabama Ave",
    "sg:city":"Chesnee",
    "sg:classifiers":[
        {
            "category":"Home & Garden",
            "subcategory":"Household Appliances",
            "type":"Retail Goods"
        }
    ],
    "sg:phone":"+1 864 461 7317",
    "sg:postcode":"29323",
    "sg:province":"SC",
    "wof:name":"Watson's Furniture Co",
    "wof:placetype":"venue"
},
  "geometry": {"coordinates":[-81.86035099999999,35.148539],"type":"Point"}
}