{
  "type": "Feature",
  "properties": {
    "iso:country":"US",
    "sg:address":"305 Hunters Hill Rd",
    "sg:city":"Simpsonville",
    "sg:classifiers":[
        {
            "category":"Building & Trades",
            "subcategory":"Construction",
            "type":"Services"
        }
    ],
    "sg:phone":"+1 864 963 4580",
    "sg:postcode":"29680",
    "sg:province":"SC",
    "sg:tags":[
        "house"
    ],
    "wof:name":"Smith Renovations",
    "wof:placetype":"venue"
},
  "geometry": {"coordinates":[-82.26388799999999,34.71257],"type":"Point"}
}