{
  "type": "Feature",
  "properties": {
    "addr:full":"1045 Munsen Spring Dr Columbia SC 29209",
    "addr:housenumber":"1045",
    "addr:postcode":"29209",
    "addr:street":"Munsen Spring Dr",
    "iso:country":"US",
    "sg:address":"1045 Munsen Spring Dr",
    "sg:city":"Columbia",
    "sg:classifiers":[
        {
            "category":"Building & Trades",
            "subcategory":"Plumbing",
            "type":"Services"
        }
    ],
    "sg:phone":"+1 803 783 5354",
    "sg:postcode":"29209",
    "sg:province":"SC",
    "sg:tags":[
        "plumbing",
        "contractor"
    ],
    "wof:name":"J P PLUMBING-Heating & AC Svc",
    "wof:placetype":"venue"
},
  "geometry": {"coordinates":[-80.960347,33.985635],"type":"Point"}
}