{
  "type": "Feature",
  "properties": {
    "iso:country":"US",
    "sg:address":"424 Bayne St SE",
    "sg:city":"Orangeburg",
    "sg:classifiers":[
        {
            "category":"Shopping",
            "type":"Retail Goods"
        }
    ],
    "sg:phone":"+1 803 516 9183",
    "sg:postcode":"29115",
    "sg:province":"SC",
    "sg:tags":[
        "merchandise"
    ],
    "wof:name":"Pretty Punch of Orangeburg",
    "wof:placetype":"venue"
},
  "geometry": {"coordinates":[-80.85071499999999,33.485689],"type":"Point"}
}