{
  "type": "Feature",
  "properties": {
    "addr:full":"100 Asbury Ln West Columbia SC 29169",
    "addr:housenumber":"100",
    "addr:postcode":"29169",
    "addr:street":"Asbury Ln",
    "iso:country":"US",
    "sg:address":"100 Asbury Ln",
    "sg:city":"West Columbia",
    "sg:classifiers":[
        {
            "category":"Real Estate",
            "subcategory":"Real Estate Operator",
            "type":"Services"
        }
    ],
    "sg:phone":"+1 803 794 8052",
    "sg:postcode":"29169",
    "sg:province":"SC",
    "sg:tags":[
        "apartment"
    ],
    "wof:name":"Asbury Arms Apartments",
    "wof:placetype":"venue"
},
  "geometry": {"coordinates":[-81.11340300000001,34.009602],"type":"Point"}
}