{
  "type": "Feature",
  "properties": {
    "iso:country":"US",
    "sg:address":"1012 W Sumter St",
    "sg:city":"Florence",
    "sg:classifiers":[
        {
            "category":"Personal",
            "subcategory":"Beauty Salon",
            "type":"Services"
        }
    ],
    "sg:phone":"+1 843 665 8895",
    "sg:postcode":"29501",
    "sg:province":"SC",
    "wof:name":"Creative Hair Designs By Sing",
    "wof:placetype":"venue"
},
  "geometry": {"coordinates":[-79.785628,34.202651],"type":"Point"}
}