{
  "type": "Feature",
  "properties": {
    "iso:country":"US",
    "sg:address":"715 Prince St",
    "sg:city":"Georgetown",
    "sg:classifiers":[
        {
            "category":"Government",
            "subcategory":"Office",
            "type":"Public Place"
        }
    ],
    "sg:phone":"+1 843 545 3092",
    "sg:postcode":"29440",
    "sg:province":"SC",
    "sg:tags":[
        "county",
        "taxation"
    ],
    "wof:name":"Georgetown Cnty Tax Collector",
    "wof:placetype":"venue"
},
  "geometry": {"coordinates":[-79.282347,33.36745],"type":"Point"}
}