{
  "type": "Feature",
  "properties": {
    "iso:country":"US",
    "sg:address":"210 E Savannah St",
    "sg:city":"Calhoun Falls",
    "sg:classifiers":[
        {
            "category":"Food & Beverages",
            "subcategory":"Groceries & Convenience Stores",
            "type":"Retail Goods"
        }
    ],
    "sg:phone":"+1 864 447 8516",
    "sg:postcode":"29628",
    "sg:province":"SC",
    "wof:name":"Hickory Point Calhoun FLS 18",
    "wof:placetype":"venue"
},
  "geometry": {"coordinates":[-82.593946,34.091307],"type":"Point"}
}