{
  "type": "Feature",
  "properties": {
    "addr:full":"246 Captains Dr Longs SC 29566",
    "addr:housenumber":"246",
    "addr:postcode":"29566",
    "addr:street":"Captains Dr",
    "iso:country":"US",
    "sg:address":"246 Captains Dr",
    "sg:city":"Longs",
    "sg:classifiers":[
        {
            "category":"Retail",
            "subcategory":"Repair Shop",
            "type":"Services"
        }
    ],
    "sg:phone":"+1 843 399 8877",
    "sg:postcode":"29566",
    "sg:province":"SC",
    "sg:tags":[
        "equipment",
        "conditioning",
        "air"
    ],
    "wof:name":"Callari Heating & Cooling",
    "wof:placetype":"venue"
},
  "geometry": {"coordinates":[-78.666082,33.871766],"type":"Point"}
}