{
  "type": "Feature",
  "properties": {
    "addr:full":"201 Hammett Grove Ln Greer SC 29650",
    "addr:housenumber":"201",
    "addr:postcode":"29650",
    "addr:street":"Hammett Grove Ln",
    "iso:country":"US",
    "sg:address":"201 Hammett Grove Ln",
    "sg:city":"Greer",
    "sg:classifiers":[
        {
            "category":"Building & Trades",
            "subcategory":"Electrical",
            "type":"Services"
        }
    ],
    "sg:phone":"+1 864 329 1787",
    "sg:postcode":"29650",
    "sg:province":"SC",
    "sg:tags":[
        "home",
        "system",
        "automation"
    ],
    "wof:name":"Automated Technology Systems",
    "wof:placetype":"venue"
},
  "geometry": {"coordinates":[-82.258545,34.896616],"type":"Point"}
}