{
  "type": "Feature",
  "properties": {
    "addr:full":"1515 9th Ave Conway SC 29526",
    "addr:housenumber":"1515",
    "addr:postcode":"29526",
    "addr:street":"9Th Ave",
    "iso:country":"US",
    "sg:address":"1515 9th Ave",
    "sg:city":"Conway",
    "sg:classifiers":[
        {
            "category":"Health Services",
            "subcategory":"Doctor",
            "type":"Services"
        }
    ],
    "sg:phone":"+1 843 248 3843",
    "sg:postcode":"29526",
    "sg:province":"SC",
    "sg:tags":[
        "dentist"
    ],
    "wof:name":"Carolina Center For Cosmetic",
    "wof:placetype":"venue"
},
  "geometry": {"coordinates":[-79.05803400000001,33.838876],"type":"Point"}
}