{
  "type": "Feature",
  "properties": {
    "addr:full":"204 Stonemede Dr Irmo SC 29063",
    "addr:housenumber":"204",
    "addr:postcode":"29063",
    "addr:street":"Stonemede Dr",
    "iso:country":"US",
    "sg:address":"204 Stonemede Dr",
    "sg:city":"Irmo",
    "sg:classifiers":[
        {
            "category":"Organizations",
            "subcategory":"Professional Association",
            "type":"Services"
        }
    ],
    "sg:phone":"+1 803 233 1781",
    "sg:postcode":"29063",
    "sg:province":"SC",
    "wof:name":"American Cancer Society",
    "wof:placetype":"venue"
},
  "geometry": {"coordinates":[-81.204769,34.148564],"type":"Point"}
}