{
  "type": "Feature",
  "properties": {
    "iso:country":"US",
    "sg:address":"207 Chime Bell Church Rd",
    "sg:city":"Aiken",
    "sg:classifiers":[
        {
            "category":"Building & Trades",
            "subcategory":"Construction",
            "type":"Services"
        }
    ],
    "sg:phone":"+1 803 502 0692",
    "sg:postcode":"29803",
    "sg:province":"SC",
    "sg:tags":[
        "clearing",
        "land",
        "leveling"
    ],
    "wof:name":"Luc Godard Trucking & Landscpg",
    "wof:placetype":"venue"
},
  "geometry": {"coordinates":[-81.70188400000001,33.461376],"type":"Point"}
}