{
  "type": "Feature",
  "properties": {
    "iso:country":"US",
    "sg:address":"3106 Broad River Rd",
    "sg:city":"Columbia",
    "sg:classifiers":[
        {
            "category":"Personal",
            "subcategory":"Beauty Salon",
            "type":"Services"
        }
    ],
    "sg:phone":"+1 803 772 4331",
    "sg:postcode":"29210",
    "sg:province":"SC",
    "wof:name":"Nadine's Hair Studio",
    "wof:placetype":"venue"
},
  "geometry": {"coordinates":[-81.10692299999999,34.051312],"type":"Point"}
}