{
  "type": "Feature",
  "properties": {
    "iso:country":"US",
    "sg:address":"1548 Nazareth Church Rd",
    "sg:city":"Spartanburg",
    "sg:classifiers":[
        {
            "category":"Building & Trades",
            "subcategory":"Construction",
            "type":"Services"
        },
        {
            "category":"Home & Garden",
            "subcategory":"Furniture",
            "type":"Retail Goods"
        }
    ],
    "sg:phone":"+1 864 439 7317",
    "sg:postcode":"29301",
    "sg:province":"SC",
    "sg:tags":[
        "cabinet",
        "mfg",
        "maker",
        "custom"
    ],
    "wof:name":"Trail Cabinet Works Inc",
    "wof:placetype":"venue"
},
  "geometry": {"coordinates":[-82.056858,34.912991],"type":"Point"}
}