{
  "type": "Feature",
  "properties": {
    "addr:full":"300 Rainbow Dr Florence SC 29501",
    "addr:housenumber":"300",
    "addr:postcode":"29501",
    "addr:street":"Rainbow Dr",
    "iso:country":"US",
    "sg:address":"300 Rainbow Dr",
    "sg:city":"Florence",
    "sg:classifiers":[
        {
            "category":"Real Estate",
            "subcategory":"Real Estate Agent",
            "type":"Services"
        },
        {
            "category":"Real Estate",
            "subcategory":"Real Estate Operator",
            "type":"Services"
        }
    ],
    "sg:phone":"+1 843 662 1771",
    "sg:postcode":"29501",
    "sg:province":"SC",
    "sg:tags":[
        "building",
        "apartment"
    ],
    "wof:name":"Harris Brown Management",
    "wof:placetype":"venue"
},
  "geometry": {"coordinates":[-79.802137,34.188142],"type":"Point"}
}