{
  "type": "Feature",
  "properties": {
    "iso:country":"US",
    "sg:address":"3480 Lakemont Blvd",
    "sg:city":"Fort Mill",
    "sg:classifiers":[
        {
            "category":"Manufacturing",
            "subcategory":"Tools & Machinery",
            "type":"Manufacturing & Wholesale Goods"
        }
    ],
    "sg:phone":"+1 803 548 3772",
    "sg:postcode":"29708",
    "sg:province":"SC",
    "sg:tags":[
        "textile",
        "mfg"
    ],
    "wof:name":"Grob LLC",
    "wof:placetype":"venue"
},
  "geometry": {"coordinates":[-80.940477,35.092973],"type":"Point"}
}