{
  "type": "Feature",
  "properties": {
    "addr:full":"679 3rd St Estill SC 29918",
    "addr:housenumber":"679",
    "addr:postcode":"29918",
    "addr:street":"3Rd St",
    "iso:country":"US",
    "sg:address":"679 3rd St",
    "sg:city":"Estill",
    "sg:classifiers":[
        {
            "category":"Organizations",
            "subcategory":"Community Association",
            "type":"Services"
        }
    ],
    "sg:phone":"+1 803 625 2355",
    "sg:postcode":"29918",
    "sg:province":"SC",
    "sg:tags":[
        "club"
    ],
    "wof:name":"Boys & Girls Club-Hampton Cnty",
    "wof:placetype":"venue"
},
  "geometry": {"coordinates":[-81.230214,32.753625],"type":"Point"}
}