{
  "type": "Feature",
  "properties": {
    "iso:country":"US",
    "sg:address":"115 N Matthews Rd",
    "sg:city":"Lake City",
    "sg:classifiers":[
        {
            "category":"Health Services",
            "subcategory":"Doctor",
            "type":"Services"
        }
    ],
    "sg:phone":"+1 843 394 2476",
    "sg:postcode":"29560",
    "sg:province":"SC",
    "sg:tags":[
        "physician",
        "surgeon"
    ],
    "wof:name":"Stokes Regional Eye Ctr",
    "wof:placetype":"venue"
},
  "geometry": {"coordinates":[-79.761872,33.877272],"type":"Point"}
}