{
  "type": "Feature",
  "properties": {
    "addr:full":"1340 N Fraser St Georgetown SC 29440",
    "addr:housenumber":"1340",
    "addr:postcode":"29440",
    "addr:street":"N Fraser St",
    "iso:country":"US",
    "sg:address":"1340 N Fraser St",
    "sg:city":"Georgetown",
    "sg:classifiers":[
        {
            "category":"Restaurant",
            "type":"Food & Drink"
        }
    ],
    "sg:menulink":"http://www.allmenus.com/sc/georgetown/173104-wendys/menu/",
    "sg:phone":"+1 843 527 3493",
    "sg:postcode":"29440",
    "sg:province":"SC",
    "sg:tags":[
        "burger",
        "american",
        "soup"
    ],
    "wof:name":"Wendy's",
    "wof:placetype":"venue"
},
  "geometry": {"coordinates":[-79.289011,33.391649],"type":"Point"}
}