{
  "type": "Feature",
  "properties": {
    "iso:country":"US",
    "sg:address":"140 Stoneridge Dr Ste 130",
    "sg:city":"Columbia",
    "sg:classifiers":[
        {
            "category":"Banks & Credit Unions",
            "subcategory":"Financial Services",
            "type":"Services"
        }
    ],
    "sg:phone":"+1 803 731 4847",
    "sg:postcode":"29210",
    "sg:province":"SC",
    "sg:tags":[
        "broker",
        "mortgage"
    ],
    "wof:name":"Jgi Financial Services Inc",
    "wof:placetype":"venue"
},
  "geometry": {"coordinates":[-81.106796,34.0448],"type":"Point"}
}