{
  "type": "Feature",
  "properties": {
    "addr:full":"614 36th Ave N Myrtle Beach SC 29577",
    "addr:housenumber":"614",
    "addr:postcode":"29577",
    "addr:street":"36Th Ave N",
    "iso:country":"US",
    "sg:address":"614 36th Ave N",
    "sg:city":"Myrtle Beach",
    "sg:classifiers":[
        {
            "category":"Home & Garden",
            "subcategory":"Carpets & Floor Coverings",
            "type":"Retail Goods"
        }
    ],
    "sg:phone":"+1 843 446 0993",
    "sg:postcode":"29577",
    "sg:province":"SC",
    "wof:name":"Floor Tec Systems",
    "wof:placetype":"venue"
},
  "geometry": {"coordinates":[-78.86119600000001,33.716536],"type":"Point"}
}