{
  "type": "Feature",
  "properties": {
    "iso:country":"US",
    "sg:address":"122 Powell Dr",
    "sg:city":"Lexington",
    "sg:classifiers":[
        {
            "category":"Health Services",
            "subcategory":"Doctor",
            "type":"Services"
        }
    ],
    "sg:phone":"+1 803 957 8400",
    "sg:postcode":"29072",
    "sg:province":"SC",
    "sg:tags":[
        "physician",
        "surgeon"
    ],
    "wof:name":"Lexington Family Practice",
    "wof:placetype":"venue"
},
  "geometry": {"coordinates":[-81.206242,34.003311],"type":"Point"}
}