{
  "type": "Feature",
  "properties": {
    "iso:country":"US",
    "sg:address":"14 Stallings Rd",
    "sg:city":"Taylors",
    "sg:classifiers":[
        {
            "category":"Retail",
            "subcategory":"Auto Repair",
            "type":"Services"
        }
    ],
    "sg:phone":"+1 864 268 7620",
    "sg:postcode":"29687",
    "sg:province":"SC",
    "sg:tags":[
        "wrecker"
    ],
    "wof:name":"Sullivan's Towing",
    "wof:placetype":"venue"
},
  "geometry": {"coordinates":[-82.317582,34.944794],"type":"Point"}
}