{
  "type": "Feature",
  "properties": {
    "iso:country":"US",
    "sg:address":"1807 Holly Ridge Dr",
    "sg:city":"Longs",
    "sg:classifiers":[
        {
            "category":"Building & Trades",
            "subcategory":"Construction",
            "type":"Services"
        }
    ],
    "sg:phone":"+1 843 399 3732",
    "sg:postcode":"29568",
    "sg:province":"SC",
    "sg:tags":[
        "masonry",
        "contractor"
    ],
    "wof:name":"Carl Hester Masonary Inc",
    "wof:placetype":"venue"
},
  "geometry": {"coordinates":[-78.804136,33.867865],"type":"Point"}
}