{
  "type": "Feature",
  "properties": {
    "iso:country":"US",
    "sg:address":"1122 Lady St",
    "sg:city":"Columbia",
    "sg:classifiers":[
        {
            "category":"Manufacturing",
            "subcategory":"Tools & Machinery",
            "type":"Manufacturing & Wholesale Goods"
        }
    ],
    "sg:phone":"+1 803 376 8988",
    "sg:postcode":"29201",
    "sg:province":"SC",
    "sg:tags":[
        "equipment",
        "hospital",
        "supply"
    ],
    "wof:name":"Hill Rom",
    "wof:placetype":"venue"
},
  "geometry": {"coordinates":[-81.034449,34.002433],"type":"Point"}
}