{
  "type": "Feature",
  "properties": {
    "iso:country":"US",
    "sg:address":"1032 W County Line Rd",
    "sg:city":"Hemingway",
    "sg:classifiers":[
        {
            "category":"Retail",
            "subcategory":"Auto Repair",
            "type":"Services"
        }
    ],
    "sg:phone":"+1 843 558 1300",
    "sg:postcode":"29554",
    "sg:province":"SC",
    "sg:tags":[
        "repairing",
        "automobile"
    ],
    "wof:name":"David's Auto Repair",
    "wof:placetype":"venue"
},
  "geometry": {"coordinates":[-79.492634,33.77742],"type":"Point"}
}