{
  "type": "Feature",
  "properties": {
    "addr:full":"223 Tugtown Rd Holly Hill SC 29059",
    "addr:housenumber":"223",
    "addr:postcode":"29059",
    "addr:street":"Tugtown Rd",
    "iso:country":"US",
    "sg:address":"223 Tugtown Rd",
    "sg:city":"Holly Hill",
    "sg:classifiers":[
        {
            "category":"Building & Trades",
            "subcategory":"Construction",
            "type":"Services"
        }
    ],
    "sg:phone":"+1 803 496 2538",
    "sg:postcode":"29059",
    "sg:province":"SC",
    "sg:tags":[
        "carpentry",
        "contractor"
    ],
    "wof:name":"Wayne Rodgers",
    "wof:placetype":"venue"
},
  "geometry": {"coordinates":[-80.339315,33.318212],"type":"Point"}
}