{
  "type": "Feature",
  "properties": {
    "addr:full":"504 S Mechanic St Pendleton SC 29670",
    "addr:housenumber":"504",
    "addr:postcode":"29670",
    "addr:street":"S Mechanic St",
    "iso:country":"US",
    "sg:address":"504 S Mechanic St",
    "sg:city":"Pendleton",
    "sg:classifiers":[
        {
            "category":"Manufacturing",
            "subcategory":"Food",
            "type":"Manufacturing & Wholesale Goods"
        },
        {
            "category":"Food & Beverages",
            "subcategory":"Bakery",
            "type":"Retail Goods"
        }
    ],
    "sg:phone":"+1 864 646 3907",
    "sg:postcode":"29670",
    "sg:province":"SC",
    "sg:tags":[
        "baker",
        "product",
        "mfg"
    ],
    "wof:name":"Granny Zuercher's Bakery",
    "wof:placetype":"venue"
},
  "geometry": {"coordinates":[-82.783722,34.646872],"type":"Point"}
}