{
  "type": "Feature",
  "properties": {
    "addr:full":"300 Serene Dr Gaffney SC 29340",
    "addr:housenumber":"300",
    "addr:postcode":"29340",
    "addr:street":"Serene Dr",
    "iso:country":"US",
    "sg:address":"300 Serene Dr",
    "sg:city":"Gaffney",
    "sg:classifiers":[
        {
            "category":"Organizations",
            "subcategory":"Religious Organization",
            "type":"Services"
        }
    ],
    "sg:phone":"+1 864 487 7025",
    "sg:postcode":"29340",
    "sg:province":"SC",
    "sg:tags":[
        "church"
    ],
    "wof:name":"Antioch Baptist Church",
    "wof:placetype":"venue"
},
  "geometry": {"coordinates":[-81.633827,35.059672],"type":"Point"}
}