{
  "type": "Feature",
  "properties": {
    "iso:country":"US",
    "sg:address":"1709 Lyttleton St",
    "sg:city":"Camden",
    "sg:classifiers":[
        {
            "category":"Organizations",
            "subcategory":"Religious Organization",
            "type":"Services"
        }
    ],
    "sg:phone":"+1 803 432 6131",
    "sg:postcode":"29020",
    "sg:province":"SC",
    "sg:tags":[
        "church"
    ],
    "sg:website":"www.catholic-doc.org/ourlady",
    "wof:name":"Our Lady Of Perpetual Help Chr",
    "wof:placetype":"venue"
},
  "geometry": {"coordinates":[-80.60439100000001,34.259636],"type":"Point"}
}