{
  "type": "Feature",
  "properties": {
    "iso:country":"US",
    "sg:address":"117 Old Forge Rd",
    "sg:city":"Chapin",
    "sg:classifiers":[
        {
            "category":"Wholesale",
            "subcategory":"Electrical",
            "type":"Manufacturing & Wholesale Goods"
        }
    ],
    "sg:phone":"+1 803 345 1031",
    "sg:postcode":"29036",
    "sg:province":"SC",
    "sg:tags":[
        "home",
        "electronics"
    ],
    "wof:name":"Market Support Associates",
    "wof:placetype":"venue"
},
  "geometry": {"coordinates":[-81.287664,34.108174],"type":"Point"}
}