{
  "type": "Feature",
  "properties": {
    "iso:country":"US",
    "sg:address":"3714 Betsy Kerrison Pkwy",
    "sg:city":"Johns Island",
    "sg:classifiers":[
        {
            "category":"Personal",
            "subcategory":"Beauty Salon",
            "type":"Services"
        }
    ],
    "sg:phone":"+1 843 768 0911",
    "sg:postcode":"29455",
    "sg:province":"SC",
    "wof:name":"Prime Cuts",
    "wof:placetype":"venue"
},
  "geometry": {"coordinates":[-80.13789199999999,32.646085],"type":"Point"}
}