{
  "type": "Feature",
  "properties": {
    "iso:country":"US",
    "sg:address":"1851 Ribaut Rd",
    "sg:city":"Port Royal",
    "sg:classifiers":[
        {
            "category":"Building & Trades",
            "subcategory":"Plumbing",
            "type":"Services"
        }
    ],
    "sg:phone":"+1 843 525 1703",
    "sg:postcode":"29935",
    "sg:province":"SC",
    "sg:tags":[
        "plumbing",
        "contractor"
    ],
    "wof:name":"Pender Brothers Inc",
    "wof:placetype":"venue"
},
  "geometry": {"coordinates":[-80.699672,32.383838],"type":"Point"}
}