{
  "type": "Feature",
  "properties": {
    "addr:full":"1850 Williams Rd Fort Mill SC 29715",
    "addr:housenumber":"1850",
    "addr:postcode":"29715",
    "addr:street":"Williams Rd",
    "iso:country":"US",
    "sg:address":"1850 Williams Rd",
    "sg:city":"Fort Mill",
    "sg:classifiers":[
        {
            "category":"Building & Trades",
            "subcategory":"Construction",
            "type":"Services"
        }
    ],
    "sg:phone":"+1 803 548 3986",
    "sg:postcode":"29715",
    "sg:province":"SC",
    "sg:tags":[
        "paving",
        "contractor"
    ],
    "sg:website":"www.atkinsasphaltpaving.com",
    "wof:name":"Atkins Asphalt Paving Co",
    "wof:placetype":"venue"
},
  "geometry": {"coordinates":[-80.904471,34.999659],"type":"Point"}
}