{
  "type": "Feature",
  "properties": {
    "iso:country":"US",
    "sg:address":"450 John C Calhoun Dr",
    "sg:city":"Orangeburg",
    "sg:classifiers":[
        {
            "category":"Autos & Motor Vehicles",
            "subcategory":"Auto Supplies",
            "type":"Retail Goods"
        }
    ],
    "sg:phone":"+1 803 533 1111",
    "sg:postcode":"29115",
    "sg:province":"SC",
    "wof:name":"Kick Booty Auto Parts",
    "wof:placetype":"venue"
},
  "geometry": {"coordinates":[-80.843108,33.489467],"type":"Point"}
}