{
  "type": "Feature",
  "properties": {
    "addr:full":"9654 N Kings Hwy Myrtle Beach SC 29572",
    "addr:housenumber":"9654",
    "addr:postcode":"29572",
    "addr:street":"N Kings Hwy",
    "iso:country":"US",
    "sg:address":"9654 N Kings Hwy",
    "sg:city":"Myrtle Beach",
    "sg:classifiers":[
        {
            "category":"Local Transit",
            "type":"Transportation"
        }
    ],
    "sg:phone":"+1 843 333 7773",
    "sg:postcode":"29572",
    "sg:province":"SC",
    "sg:tags":[
        "passenger"
    ],
    "wof:name":"Starz Limousine LLC",
    "wof:placetype":"venue"
},
  "geometry": {"coordinates":[-78.777834,33.786318],"type":"Point"}
}