{
  "type": "Feature",
  "properties": {
    "addr:full":"806 W Greenwood St Abbeville SC 29620",
    "addr:housenumber":"806",
    "addr:postcode":"29620",
    "addr:street":"W Greenwood St",
    "iso:country":"US",
    "sg:address":"806 W Greenwood St",
    "sg:city":"Abbeville",
    "sg:classifiers":[
        {
            "category":"Retail",
            "subcategory":"Car Wash",
            "type":"Services"
        }
    ],
    "sg:phone":"+1 864 366 6730",
    "sg:postcode":"29620",
    "sg:province":"SC",
    "sg:tags":[
        "polishing",
        "washing"
    ],
    "wof:name":"Upstate Carwash",
    "wof:placetype":"venue"
},
  "geometry": {"coordinates":[-82.38431799999999,34.159953],"type":"Point"}
}