{
  "type": "Feature",
  "properties": {
    "addr:full":"2516 Martintown Rd Edgefield SC 29824",
    "addr:housenumber":"2516",
    "addr:postcode":"29824",
    "addr:street":"Martintown Rd",
    "iso:country":"US",
    "sg:address":"2516 Martintown Rd",
    "sg:city":"Edgefield",
    "sg:classifiers":[
        {
            "category":"Home & Garden",
            "subcategory":"Home Furnishings",
            "type":"Retail Goods"
        }
    ],
    "sg:phone":"+1 803 279 5245",
    "sg:postcode":"29824",
    "sg:province":"SC",
    "wof:name":"Drapery Nook",
    "wof:placetype":"venue"
},
  "geometry": {"coordinates":[-82.063827,33.658717],"type":"Point"}
}