{
  "type": "Feature",
  "properties": {
    "addr:full":"701 Gervais St Columbia SC 29201",
    "addr:housenumber":"701",
    "addr:postcode":"29201",
    "addr:street":"Gervais St",
    "iso:country":"US",
    "sg:address":"701 Gervais St",
    "sg:city":"Columbia",
    "sg:classifiers":[
        {
            "category":"Real Estate",
            "subcategory":"Real Estate Operator",
            "type":"Services"
        }
    ],
    "sg:phone":"+1 803 739 4892",
    "sg:postcode":"29201",
    "sg:province":"SC",
    "sg:tags":[
        "apartment"
    ],
    "wof:name":"Vista Lofts",
    "wof:placetype":"venue"
},
  "geometry": {"coordinates":[-81.04159300000001,33.998796],"type":"Point"}
}