{
  "type": "Feature",
  "properties": {
    "iso:country":"US",
    "sg:address":"520 Woodland Shores Rd",
    "sg:city":"Charleston",
    "sg:classifiers":[
        {
            "category":"Building & Trades",
            "subcategory":"Construction",
            "type":"Services"
        }
    ],
    "sg:phone":"+1 843 406 2935",
    "sg:postcode":"29412",
    "sg:province":"SC",
    "sg:tags":[
        "carpentry",
        "contractor"
    ],
    "wof:name":"M C O LLC",
    "wof:placetype":"venue"
},
  "geometry": {"coordinates":[-79.988536,32.755598],"type":"Point"}
}