{
  "type": "Feature",
  "properties": {
    "addr:full":"420 Epting Ave Greenwood SC 29646",
    "addr:housenumber":"420",
    "addr:postcode":"29646",
    "addr:street":"Epting Ave",
    "iso:country":"US",
    "sg:address":"420 Epting Ave",
    "sg:city":"Greenwood",
    "sg:classifiers":[
        {
            "category":"Shopping",
            "subcategory":"Gifts & Souvenirs",
            "type":"Retail Goods"
        }
    ],
    "sg:phone":"+1 864 227 0295",
    "sg:postcode":"29646",
    "sg:province":"SC",
    "wof:name":"Memorable Gifts",
    "wof:placetype":"venue"
},
  "geometry": {"coordinates":[-82.157843,34.1714],"type":"Point"}
}