{
  "type": "Feature",
  "properties": {
    "iso:country":"US",
    "sg:address":"235 Meeting St",
    "sg:city":"Charleston",
    "sg:classifiers":[
        {
            "category":"Travel",
            "subcategory":"Hotels & Motels",
            "type":"Entertainment"
        }
    ],
    "sg:phone":"+1 843 720 5915",
    "sg:postcode":"29401",
    "sg:province":"SC",
    "wof:name":"Meeting Street Suites",
    "wof:placetype":"venue"
},
  "geometry": {"coordinates":[-79.931704,32.78203],"type":"Point"}
}