{
  "type": "Feature",
  "properties": {
    "addr:full":"1377 Suttle Rd Lancaster SC 29720",
    "addr:housenumber":"1377",
    "addr:postcode":"29720",
    "addr:street":"Suttle Rd",
    "iso:country":"US",
    "sg:address":"1377 Suttle Rd",
    "sg:city":"Lancaster",
    "sg:classifiers":[
        {
            "category":"Retail",
            "subcategory":"Auto Repair",
            "type":"Services"
        }
    ],
    "sg:phone":"+1 803 283 8157",
    "sg:postcode":"29720",
    "sg:province":"SC",
    "sg:tags":[
        "repairing",
        "automobile"
    ],
    "wof:name":"Sistare's Garage",
    "wof:placetype":"venue"
},
  "geometry": {"coordinates":[-80.76552599999999,34.650825],"type":"Point"}
}