{
  "type": "Feature",
  "properties": {
    "iso:country":"US",
    "sg:address":"160 Quail Ridge Ln",
    "sg:city":"Fort Mill",
    "sg:classifiers":[
        {
            "category":"Building & Trades",
            "subcategory":"Construction",
            "type":"Services"
        }
    ],
    "sg:phone":"+1 803 547 4517",
    "sg:postcode":"29708",
    "sg:province":"SC",
    "sg:tags":[
        "house"
    ],
    "wof:name":"G L Johnson Construction",
    "wof:placetype":"venue"
},
  "geometry": {"coordinates":[-80.974079,35.007754],"type":"Point"}
}