{
  "type": "Feature",
  "properties": {
    "iso:country":"US",
    "sg:address":"19 Professional Village Cir",
    "sg:city":"Beaufort",
    "sg:classifiers":[
        {
            "category":"Banks & Credit Unions",
            "subcategory":"Investment Brokerage",
            "type":"Services"
        }
    ],
    "sg:phone":"+1 843 770 0111",
    "sg:postcode":"29907",
    "sg:province":"SC",
    "sg:tags":[
        "consultant",
        "planning",
        "financial"
    ],
    "wof:name":"Henriette M Huybregts",
    "wof:placetype":"venue"
},
  "geometry": {"coordinates":[-80.65218,32.416005],"type":"Point"}
}