{
  "type": "Feature",
  "properties": {
    "iso:country":"US",
    "sg:address":"1395 E Poinsett St Exd",
    "sg:city":"Greer",
    "sg:classifiers":[
        {
            "category":"Manufacturing",
            "subcategory":"Tools & Machinery",
            "type":"Manufacturing & Wholesale Goods"
        }
    ],
    "sg:phone":"+1 864 877 3515",
    "sg:postcode":"29651",
    "sg:province":"SC",
    "sg:tags":[
        "compressor"
    ],
    "sg:website":"www.airfloinc.com",
    "wof:name":"Air-Flo Inc",
    "wof:placetype":"venue"
},
  "geometry": {"coordinates":[-82.193563,34.935463],"type":"Point"}
}