{
  "type": "Feature",
  "properties": {
    "addr:full":"719 S Lake Dr Lexington SC 29072",
    "addr:housenumber":"719",
    "addr:postcode":"29072",
    "addr:street":"S Lake Dr",
    "iso:country":"US",
    "sg:address":"719 S Lake Dr",
    "sg:city":"Lexington",
    "sg:classifiers":[
        {
            "category":"Health Services",
            "subcategory":"Doctor",
            "type":"Services"
        }
    ],
    "sg:phone":"+1 803 957 8000",
    "sg:postcode":"29072",
    "sg:province":"SC",
    "sg:tags":[
        "physician",
        "surgeon"
    ],
    "wof:name":"Lexington Internal Medicine",
    "wof:placetype":"venue"
},
  "geometry": {"coordinates":[-81.235063,33.969061],"type":"Point"}
}