{
  "type": "Feature",
  "properties": {
    "iso:country":"US",
    "sg:address":"415 Memorial Ave S",
    "sg:city":"Allendale",
    "sg:classifiers":[
        {
            "category":"Government",
            "subcategory":"Office",
            "type":"Public Place"
        }
    ],
    "sg:phone":"+1 803 584 3818",
    "sg:postcode":"29810",
    "sg:province":"SC",
    "sg:tags":[
        "county",
        "program",
        "health"
    ],
    "wof:name":"Allendale County Health Dept",
    "wof:placetype":"venue"
},
  "geometry": {"coordinates":[-81.312147,33.006762],"type":"Point"}
}