{
  "type": "Feature",
  "properties": {
    "addr:full":"168 Church St Charleston SC 29401",
    "addr:housenumber":"168",
    "addr:postcode":"29401",
    "addr:street":"Church St",
    "iso:country":"US",
    "sg:address":"168 Church St",
    "sg:city":"Charleston",
    "sg:classifiers":[
        {
            "category":"Shopping",
            "type":"Retail Goods"
        }
    ],
    "sg:phone":"+1 843 579 9833",
    "sg:postcode":"29401",
    "sg:province":"SC",
    "sg:tags":[
        "art",
        "gallery",
        "dealer"
    ],
    "wof:name":"Passionate Collector",
    "wof:placetype":"venue"
},
  "geometry": {"coordinates":[-79.929492,32.780557],"type":"Point"}
}