{
  "type": "Feature",
  "properties": {
    "iso:country":"US",
    "sg:address":"636 Whitland Rd",
    "sg:city":"Lexington",
    "sg:classifiers":[
        {
            "category":"Banks & Credit Unions",
            "subcategory":"Bank",
            "type":"Services"
        }
    ],
    "sg:phone":"+1 803 926 3777",
    "sg:postcode":"29072",
    "sg:province":"SC",
    "sg:tags":[
        "loan",
        "real estate"
    ],
    "wof:name":"Matthew Isola",
    "wof:placetype":"venue"
},
  "geometry": {"coordinates":[-81.218438,34.008181],"type":"Point"}
}