{
  "type": "Feature",
  "properties": {
    "addr:full":"1416 Calhoun St Columbia SC 29201",
    "addr:housenumber":"1416",
    "addr:postcode":"29201",
    "addr:street":"Calhoun St",
    "iso:country":"US",
    "sg:address":"1416 Calhoun St",
    "sg:city":"Columbia",
    "sg:classifiers":[
        {
            "category":"Health Services",
            "subcategory":"Health Practitioner",
            "type":"Services"
        }
    ],
    "sg:phone":"+1 803 212 1000",
    "sg:postcode":"29201",
    "sg:province":"SC",
    "sg:tags":[
        "therapy",
        "physical"
    ],
    "wof:name":"First Choice Rehabilitation Center",
    "wof:placetype":"venue"
},
  "geometry": {"coordinates":[-81.034094,34.012942],"type":"Point"}
}