{
  "type": "Feature",
  "properties": {
    "iso:country":"US",
    "sg:address":"211 York St NE",
    "sg:city":"Aiken",
    "sg:classifiers":[
        {
            "category":"Organizations",
            "subcategory":"Membership Organization",
            "type":"Services"
        }
    ],
    "sg:phone":"+1 803 642 5180",
    "sg:postcode":"29801",
    "sg:province":"SC",
    "wof:name":"American Red Cross",
    "wof:placetype":"venue"
},
  "geometry": {"coordinates":[-81.716925,33.562386],"type":"Point"}
}