{
  "type": "Feature",
  "properties": {
    "iso:country":"US",
    "sg:address":"2228 McCutchen Rd",
    "sg:city":"Cades",
    "sg:classifiers":[
        {
            "category":"Retail",
            "subcategory":"Car Wash",
            "type":"Services"
        }
    ],
    "sg:phone":"+1 843 382 4900",
    "sg:postcode":"29518",
    "sg:province":"SC",
    "sg:tags":[
        "polishing",
        "washing"
    ],
    "wof:name":"On The Spot Car Detailing",
    "wof:placetype":"venue"
},
  "geometry": {"coordinates":[-79.89247899999999,33.737828],"type":"Point"}
}