{
  "type": "Feature",
  "properties": {
    "iso:country":"US",
    "sg:address":"104 Azalea Ct",
    "sg:city":"Spartanburg",
    "sg:classifiers":[
        {
            "category":"Health Services",
            "subcategory":"Chiropractor",
            "type":"Services"
        }
    ],
    "sg:phone":"+1 864 574 1642",
    "sg:postcode":"29301",
    "sg:province":"SC",
    "wof:name":"Cotheran Chiropractic Clinic",
    "wof:placetype":"venue"
},
  "geometry": {"coordinates":[-82.003355,34.937986],"type":"Point"}
}