{
  "type": "Feature",
  "properties": {
    "iso:country":"US",
    "sg:address":"500 S Coit St",
    "sg:city":"Florence",
    "sg:classifiers":[
        {
            "category":"Health Services",
            "subcategory":"Doctor",
            "type":"Services"
        }
    ],
    "sg:phone":"+1 843 665 2246",
    "sg:postcode":"29501",
    "sg:province":"SC",
    "sg:tags":[
        "physician",
        "surgeon"
    ],
    "wof:name":"Florence Internal Medicine",
    "wof:placetype":"venue"
},
  "geometry": {"coordinates":[-79.769785,34.188435],"type":"Point"}
}