{
  "type": "Feature",
  "properties": {
    "iso:country":"US",
    "sg:address":"106 N Macarthur Ave",
    "sg:city":"Dillon",
    "sg:classifiers":[
        {
            "category":"Professional",
            "subcategory":"Business Services",
            "type":"Services"
        },
        {
            "category":"Home & Garden",
            "subcategory":"Home Furnishings",
            "type":"Retail Goods"
        }
    ],
    "sg:phone":"+1 843 841 1500",
    "sg:postcode":"29536",
    "sg:province":"SC",
    "sg:tags":[
        "interior",
        "consultant",
        "design",
        "decorator",
        "merchandise"
    ],
    "wof:name":"Framer's Market",
    "wof:placetype":"venue"
},
  "geometry": {"coordinates":[-79.37142900000001,34.417963],"type":"Point"}
}