{
  "type": "Feature",
  "properties": {
    "addr:full":"1504 Fording Island Rd Bluffton SC 29910",
    "addr:housenumber":"1504",
    "addr:postcode":"29910",
    "addr:street":"Fording Island Rd",
    "iso:country":"US",
    "sg:address":"1504 Fording Island Rd",
    "sg:city":"Bluffton",
    "sg:classifiers":[
        {
            "category":"Museum",
            "type":"Entertainment"
        }
    ],
    "sg:phone":"+1 843 837 4410",
    "sg:postcode":"29910",
    "sg:province":"SC",
    "wof:name":"Hilton Head Classic Car Museum",
    "wof:placetype":"venue"
},
  "geometry": {"coordinates":[-80.813667,32.239646],"type":"Point"}
}