{
  "type": "Feature",
  "properties": {
    "iso:country":"US",
    "sg:address":"270 Salisberry Rd",
    "sg:city":"Holly Hill",
    "sg:classifiers":[
        {
            "category":"Building & Trades",
            "subcategory":"Construction",
            "type":"Services"
        }
    ],
    "sg:phone":"+1 803 496 3816",
    "sg:postcode":"29059",
    "sg:province":"SC",
    "sg:tags":[
        "residential"
    ],
    "wof:name":"S & M Construction",
    "wof:placetype":"venue"
},
  "geometry": {"coordinates":[-80.36970100000001,33.313468],"type":"Point"}
}