{
  "type": "Feature",
  "properties": {
    "iso:country":"US",
    "sg:address":"115 Pelham Rd",
    "sg:city":"Greenville",
    "sg:classifiers":[
        {
            "category":"Restaurant",
            "type":"Food & Drink"
        }
    ],
    "sg:phone":"+1 864 370 1857",
    "sg:postcode":"29615",
    "sg:province":"SC",
    "wof:name":"Alley Gator Raw Bar & Grille",
    "wof:placetype":"venue"
},
  "geometry": {"coordinates":[-82.349721,34.866769],"type":"Point"}
}