{
  "type": "Feature",
  "properties": {
    "iso:country":"US",
    "sg:address":"13302 Ocean Hwy",
    "sg:city":"Pawleys Island",
    "sg:classifiers":[
        {
            "category":"Professional",
            "subcategory":"Business Services",
            "type":"Services"
        }
    ],
    "sg:phone":"+1 843 237 3326",
    "sg:postcode":"29585",
    "sg:province":"SC",
    "sg:tags":[
        "interior",
        "retail",
        "design",
        "furniture"
    ],
    "wof:name":"Mc Elveen Designs & Antiques",
    "wof:placetype":"venue"
},
  "geometry": {"coordinates":[-79.10427799999999,33.472567],"type":"Point"}
}