{
  "type": "Feature",
  "properties": {
    "iso:country":"US",
    "sg:address":"402 Singleton Ridge Rd",
    "sg:city":"Conway",
    "sg:classifiers":[
        {
            "category":"Health Services",
            "subcategory":"Doctor",
            "type":"Services"
        }
    ],
    "sg:phone":"+1 843 347 5111",
    "sg:postcode":"29526",
    "sg:province":"SC",
    "sg:tags":[
        "clinic"
    ],
    "wof:name":"Conway Dialysis Ctr",
    "wof:placetype":"venue"
},
  "geometry": {"coordinates":[-79.006683,33.784912],"type":"Point"}
}