{
  "type": "Feature",
  "properties": {
    "iso:country":"US",
    "sg:address":"2400 Augusta Rd",
    "sg:city":"West Columbia",
    "sg:classifiers":[
        {
            "category":"Home & Garden",
            "subcategory":"Building Materials",
            "type":"Retail Goods"
        },
        {
            "category":"Retail",
            "subcategory":"Auto Repair",
            "type":"Services"
        }
    ],
    "sg:phone":"+1 803 799 0888",
    "sg:postcode":"29169",
    "sg:province":"SC",
    "sg:tags":[
        "plate",
        "contractor",
        "glass",
        "window",
        "trade",
        "replacement"
    ],
    "wof:name":"Glass Masters",
    "wof:placetype":"venue"
},
  "geometry": {"coordinates":[-81.100706,33.982375],"type":"Point"}
}