{
  "type": "Feature",
  "properties": {
    "iso:country":"US",
    "sg:address":"115 Willbrook Rd",
    "sg:city":"Pawleys Island",
    "sg:classifiers":[
        {
            "category":"Shopping",
            "subcategory":"Hobbies, Toys, & Games",
            "type":"Retail Goods"
        }
    ],
    "sg:phone":"+1 843 235 0158",
    "sg:postcode":"29577",
    "sg:province":"SC",
    "sg:tags":[
        "supply"
    ],
    "wof:name":"Scientific Games Intl Inc",
    "wof:placetype":"venue"
},
  "geometry": {"coordinates":[-78.877207,33.732865],"type":"Point"}
}