{
  "type": "Feature",
  "properties": {
    "iso:country":"US",
    "sg:address":"607 S Coit St",
    "sg:city":"Florence",
    "sg:classifiers":[
        {
            "category":"Professional",
            "subcategory":"Management & Consulting",
            "type":"Services"
        }
    ],
    "sg:phone":"+1 843 662 0728",
    "sg:postcode":"29501",
    "sg:province":"SC",
    "sg:tags":[
        "consultant",
        "business"
    ],
    "wof:name":"Performance Management Group",
    "wof:placetype":"venue"
},
  "geometry": {"coordinates":[-79.769784,34.187405],"type":"Point"}
}