{
  "type": "Feature",
  "properties": {
    "iso:country":"US",
    "sg:address":"2708 S Ocean Blvd",
    "sg:city":"Myrtle Beach",
    "sg:classifiers":[
        {
            "category":"Real Estate",
            "subcategory":"Real Estate Agent",
            "type":"Services"
        }
    ],
    "sg:phone":"+1 843 444 1007",
    "sg:postcode":"29577",
    "sg:province":"SC",
    "wof:name":"South End Properties",
    "wof:placetype":"venue"
},
  "geometry": {"coordinates":[-78.913281,33.663514],"type":"Point"}
}