{
  "type": "Feature",
  "properties": {
    "addr:full":"203 Pigg St Pageland SC 29728",
    "addr:housenumber":"203",
    "addr:postcode":"29728",
    "addr:street":"Pigg St",
    "iso:country":"US",
    "sg:address":"203 Pigg St",
    "sg:city":"Pageland",
    "sg:classifiers":[
        {
            "category":"Organizations",
            "subcategory":"Religious Organization",
            "type":"Services"
        }
    ],
    "sg:phone":"+1 843 672 7462",
    "sg:postcode":"29728",
    "sg:province":"SC",
    "sg:tags":[
        "church"
    ],
    "sg:website":"www.fbcpageland.com",
    "wof:name":"First Baptist Church",
    "wof:placetype":"venue"
},
  "geometry": {"coordinates":[-80.387039,34.767856],"type":"Point"}
}