{
  "type": "Feature",
  "properties": {
    "addr:full":"1297 US Hwy 501 Myrtle Beach SC 29577",
    "addr:housenumber":"1297",
    "addr:postcode":"29577",
    "addr:street":"Us Hwy 501",
    "iso:country":"US",
    "sg:address":"1297 US Hwy 501",
    "sg:city":"Myrtle Beach",
    "sg:classifiers":[
        {
            "category":"Autos & Motor Vehicles",
            "subcategory":"Automobile Sales",
            "type":"Retail Goods"
        }
    ],
    "sg:phone":"+1 843 444 8000",
    "sg:postcode":"29577",
    "sg:province":"SC",
    "sg:tags":[
        "car",
        "dealer"
    ],
    "wof:name":"KIA Time Myrtle Beach",
    "wof:placetype":"venue"
},
  "geometry": {"coordinates":[-78.896745,33.697786],"type":"Point"}
}