{
  "type": "Feature",
  "properties": {
    "addr:full":"1384 Eastland Ave Kingstree SC 29556",
    "addr:housenumber":"1384",
    "addr:postcode":"29556",
    "addr:street":"Eastland Ave",
    "iso:country":"US",
    "sg:address":"1384 Eastland Ave",
    "sg:city":"Kingstree",
    "sg:classifiers":[
        {
            "category":"Social Services",
            "subcategory":"Child Care",
            "type":"Services"
        }
    ],
    "sg:phone":"+1 843 382 2115",
    "sg:postcode":"29556",
    "sg:province":"SC",
    "wof:name":"Graham Enhancement Daycare",
    "wof:placetype":"venue"
},
  "geometry": {"coordinates":[-79.81156799999999,33.699437],"type":"Point"}
}