{
  "type": "Feature",
  "properties": {
    "addr:full":"520 Calhoun St Johnston SC 29832",
    "addr:housenumber":"520",
    "addr:postcode":"29832",
    "addr:street":"Calhoun St",
    "iso:country":"US",
    "sg:address":"520 Calhoun St",
    "sg:city":"Johnston",
    "sg:classifiers":[
        {
            "category":"Restaurant",
            "type":"Food & Drink"
        }
    ],
    "sg:phone":"+1 803 275 5697",
    "sg:postcode":"29832",
    "sg:province":"SC",
    "sg:tags":[
        "shop",
        "coffee"
    ],
    "wof:name":"Morning Noon & Night Coffee",
    "wof:placetype":"venue"
},
  "geometry": {"coordinates":[-81.800344,33.833007],"type":"Point"}
}