{
  "type": "Feature",
  "properties": {
    "iso:country":"US",
    "sg:address":"5 State Hwy 86",
    "sg:city":"Piedmont",
    "sg:classifiers":[
        {
            "category":"Government",
            "subcategory":"Post Office",
            "type":"Public Place"
        }
    ],
    "sg:phone":"+1 864 845 7211",
    "sg:postcode":"29673",
    "sg:province":"SC",
    "sg:tags":[
        "postal",
        "us"
    ],
    "wof:name":"US Post Office",
    "wof:placetype":"venue"
},
  "geometry": {"coordinates":[-82.457036,34.705895],"type":"Point"}
}