{
  "type": "Feature",
  "properties": {
    "iso:country":"US",
    "sg:address":"1500 Fairview Dr",
    "sg:city":"Columbia",
    "sg:classifiers":[
        {
            "category":"Recreation",
            "type":"Entertainment"
        }
    ],
    "sg:phone":"+1 803 733 8493",
    "sg:postcode":"29205",
    "sg:province":"SC",
    "sg:tags":[
        "parks"
    ],
    "wof:name":"Melrose Park",
    "wof:placetype":"venue"
},
  "geometry": {"coordinates":[-81.00330099999999,34.00965],"type":"Point"}
}