{
  "type": "Feature",
  "properties": {
    "addr:full":"2 Corpus Christie Hilton Head Island SC 29928",
    "addr:housenumber":"2",
    "addr:postcode":"29928",
    "addr:street":"Corpus Christie",
    "iso:country":"US",
    "sg:address":"2 Corpus Christie",
    "sg:city":"Hilton Head Island",
    "sg:classifiers":[
        {
            "category":"Professional",
            "subcategory":"Lawyer & Legal Services",
            "type":"Services"
        }
    ],
    "sg:phone":"+1 843 686 0450",
    "sg:postcode":"29928",
    "sg:province":"SC",
    "sg:tags":[
        "communication",
        "mfg"
    ],
    "wof:name":"R & B Associates",
    "wof:placetype":"venue"
},
  "geometry": {"coordinates":[-80.76093,32.155093],"type":"Point"}
}