{
  "type": "Feature",
  "properties": {
    "iso:country":"US",
    "sg:address":"3674 US Hwy 52",
    "sg:city":"St Stephen",
    "sg:classifiers":[
        {
            "category":"Social Services",
            "subcategory":"Child Care",
            "type":"Services"
        }
    ],
    "sg:phone":"+1 843 567 7190",
    "sg:postcode":"29479",
    "sg:province":"SC",
    "wof:name":"St Stephen Head Start Ctr",
    "wof:placetype":"venue"
},
  "geometry": {"coordinates":[-79.928606,33.389463],"type":"Point"}
}