{
  "type": "Feature",
  "properties": {
    "iso:country":"US",
    "sg:address":"1980 Pageland Hwy",
    "sg:city":"Lancaster",
    "sg:classifiers":[
        {
            "category":"Building & Trades",
            "subcategory":"Construction",
            "type":"Services"
        }
    ],
    "sg:phone":"+1 803 283 2101",
    "sg:postcode":"29720",
    "sg:province":"SC",
    "sg:tags":[
        "grading",
        "contractor"
    ],
    "wof:name":"Lancaster Public Works",
    "wof:placetype":"venue"
},
  "geometry": {"coordinates":[-80.720241,34.721433],"type":"Point"}
}