{
  "type": "Feature",
  "properties": {
    "addr:full":"140 4th Ave Gaffney SC 29340",
    "addr:housenumber":"140",
    "addr:postcode":"29340",
    "addr:street":"4Th Ave",
    "iso:country":"US",
    "sg:address":"140 4th Ave",
    "sg:city":"Gaffney",
    "sg:classifiers":[
        {
            "category":"Health Services",
            "subcategory":"Doctor",
            "type":"Services"
        }
    ],
    "sg:phone":"+1 864 487 5124",
    "sg:postcode":"29340",
    "sg:province":"SC",
    "sg:tags":[
        "physician",
        "surgeon"
    ],
    "wof:name":"Gaffney Urology",
    "wof:placetype":"venue"
},
  "geometry": {"coordinates":[-81.635576,35.084723],"type":"Point"}
}