{
  "type": "Feature",
  "properties": {
    "addr:full":"100 Old Farm Rd Columbia SC 29223",
    "addr:housenumber":"100",
    "addr:postcode":"29223",
    "addr:street":"Old Farm Rd",
    "iso:country":"US",
    "sg:address":"100 Old Farm Rd",
    "sg:city":"Columbia",
    "sg:classifiers":[
        {
            "category":"Banks & Credit Unions",
            "subcategory":"Bank",
            "type":"Services"
        }
    ],
    "sg:phone":"+1 803 419 2374",
    "sg:postcode":"29223",
    "sg:province":"SC",
    "wof:name":"Safe Federal Credit Union",
    "wof:placetype":"venue"
},
  "geometry": {"coordinates":[-80.887271,34.131807],"type":"Point"}
}