{
  "type": "Feature",
  "properties": {
    "addr:full":"515 S Main St Anderson SC 29624",
    "addr:housenumber":"515",
    "addr:postcode":"29624",
    "addr:street":"S Main St",
    "iso:country":"US",
    "sg:address":"515 S Main St",
    "sg:city":"Anderson",
    "sg:classifiers":[
        {
            "category":"Autos & Motor Vehicles",
            "subcategory":"Fuel & Gas Station",
            "type":"Retail Goods"
        }
    ],
    "sg:phone":"+1 864 225 3030",
    "sg:postcode":"29624",
    "sg:province":"SC",
    "sg:tags":[
        "oil"
    ],
    "wof:name":"Floyd Clinkscales Gulf",
    "wof:placetype":"venue"
},
  "geometry": {"coordinates":[-82.6494,34.500229],"type":"Point"}
}