{
  "type": "Feature",
  "properties": {
    "addr:full":"975 Brookhaven Dr Aiken SC 29803",
    "addr:housenumber":"975",
    "addr:postcode":"29803",
    "addr:street":"Brookhaven Dr",
    "iso:country":"US",
    "sg:address":"975 Brookhaven Dr",
    "sg:city":"Aiken",
    "sg:classifiers":[
        {
            "category":"Building & Trades",
            "subcategory":"Plumbing",
            "type":"Services"
        }
    ],
    "sg:phone":"+1 803 648 3837",
    "sg:postcode":"29803",
    "sg:province":"SC",
    "sg:tags":[
        "plumbing",
        "contractor"
    ],
    "wof:name":"Anderson Plumbing Co Inc",
    "wof:placetype":"venue"
},
  "geometry": {"coordinates":[-81.710261,33.502623],"type":"Point"}
}