{
  "type": "Feature",
  "properties": {
    "addr:full":"2630 Bonds Ave North Charleston SC 29405",
    "addr:postcode":"2630;29405",
    "addr:street":"Bonds Ave",
    "iso:country":"US",
    "sg:address":"2630 Bonds Ave",
    "sg:city":"North Charleston",
    "sg:classifiers":[
        {
            "category":"Building & Trades",
            "subcategory":"Electrical",
            "type":"Services"
        }
    ],
    "sg:phone":"+1 843 552 9923",
    "sg:postcode":"29405",
    "sg:province":"SC",
    "sg:tags":[
        "electric",
        "contractor"
    ],
    "wof:name":"Allsouth Electrical Contractor",
    "wof:placetype":"venue"
},
  "geometry": {"coordinates":[-79.99656299999999,32.850364],"type":"Point"}
}