{
  "type": "Feature",
  "properties": {
    "iso:country":"US",
    "sg:address":"801 Crawford Rd",
    "sg:city":"Rock Hill",
    "sg:classifiers":[
        {
            "category":"Organizations",
            "subcategory":"Community Association",
            "type":"Services"
        }
    ],
    "sg:phone":"+1 803 366 2500",
    "sg:postcode":"29730",
    "sg:province":"SC",
    "sg:tags":[
        "club"
    ],
    "wof:name":"Boys & Girls Clubs Of Rock Hl",
    "wof:placetype":"venue"
},
  "geometry": {"coordinates":[-81.039405,34.916817],"type":"Point"}
}