{
  "type": "Feature",
  "properties": {
    "iso:country":"US",
    "sg:address":"115 Upton Rd",
    "sg:city":"St Stephen",
    "sg:classifiers":[
        {
            "category":"Organizations",
            "subcategory":"Religious Organization",
            "type":"Services"
        }
    ],
    "sg:phone":"+1 843 567 2641",
    "sg:postcode":"29479",
    "sg:province":"SC",
    "sg:tags":[
        "clergy"
    ],
    "wof:name":"W H Broome",
    "wof:placetype":"venue"
},
  "geometry": {"coordinates":[-79.913157,33.40641],"type":"Point"}
}