{
  "type": "Feature",
  "properties": {
    "iso:country":"US",
    "sg:address":"497 Saint Andrews Blvd",
    "sg:city":"Charleston",
    "sg:classifiers":[
        {
            "category":"Health Services",
            "subcategory":"Doctor",
            "type":"Services"
        }
    ],
    "sg:phone":"+1 843 763 0543",
    "sg:postcode":"29407",
    "sg:province":"SC",
    "sg:tags":[
        "physician",
        "surgeon"
    ],
    "wof:name":"Charleston Ent & Assoc",
    "wof:placetype":"venue"
},
  "geometry": {"coordinates":[-79.97395,32.781694],"type":"Point"}
}