{
  "type": "Feature",
  "properties": {
    "iso:country":"US",
    "sg:address":"123 Broad St",
    "sg:city":"Bennettsville",
    "sg:classifiers":[
        {
            "category":"Personal",
            "subcategory":"Beauty Salon",
            "type":"Services"
        }
    ],
    "sg:phone":"+1 843 479 6300",
    "sg:postcode":"29512",
    "sg:province":"SC",
    "wof:name":"Doug's Hair Style",
    "wof:placetype":"venue"
},
  "geometry": {"coordinates":[-79.683843,34.615791],"type":"Point"}
}