{
  "type": "Feature",
  "properties": {
    "addr:full":"9 Beth Dr Greenville SC 29609",
    "addr:housenumber":"9",
    "addr:postcode":"29609",
    "addr:street":"Beth Dr",
    "iso:country":"US",
    "sg:address":"9 Beth Dr",
    "sg:city":"Greenville",
    "sg:classifiers":[
        {
            "category":"Organizations",
            "subcategory":"Religious Organization",
            "type":"Services"
        }
    ],
    "sg:phone":"+1 864 232 1515",
    "sg:postcode":"29609",
    "sg:province":"SC",
    "sg:tags":[
        "church"
    ],
    "wof:name":"EVANGELISTIC Temple",
    "wof:placetype":"venue"
},
  "geometry": {"coordinates":[-82.40343900000001,34.891952],"type":"Point"}
}