{
  "type": "Feature",
  "properties": {
    "iso:country":"US",
    "sg:address":"122 Estates Dr",
    "sg:city":"Summerville",
    "sg:classifiers":[
        {
            "category":"Bars & Pubs",
            "type":"Food & Drink"
        }
    ],
    "sg:phone":"+1 843 873 6107",
    "sg:postcode":"29483",
    "sg:province":"SC",
    "sg:tags":[
        "drinking"
    ],
    "wof:name":"Mvps Neighborhood Bar & Grill",
    "wof:placetype":"venue"
},
  "geometry": {"coordinates":[-80.277885,33.023464],"type":"Point"}
}