{
  "type": "Feature",
  "properties": {
    "iso:country":"US",
    "sg:address":"225 4th St",
    "sg:city":"Darlington",
    "sg:classifiers":[
        {
            "category":"Manufacturing",
            "subcategory":"Building Materials",
            "type":"Manufacturing & Wholesale Goods"
        }
    ],
    "sg:phone":"+1 843 393 3861",
    "sg:postcode":"29532",
    "sg:province":"SC",
    "sg:tags":[
        "plywood",
        "veneer"
    ],
    "wof:name":"Darlington Veneer Co Inc",
    "wof:placetype":"venue"
},
  "geometry": {"coordinates":[-79.86254599999999,34.301],"type":"Point"}
}