{
  "type": "Feature",
  "properties": {
    "iso:country":"US",
    "sg:address":"3016 Millwood Ave",
    "sg:city":"Columbia",
    "sg:classifiers":[
        {
            "category":"Professional",
            "subcategory":"Lawyer & Legal Services",
            "type":"Services"
        }
    ],
    "sg:phone":"+1 803 252 1800",
    "sg:postcode":"29205",
    "sg:province":"SC",
    "wof:name":"Best and Flatt PA Attys",
    "wof:placetype":"venue"
},
  "geometry": {"coordinates":[-80.998497,34.001701],"type":"Point"}
}