{
  "type": "Feature",
  "properties": {
    "iso:country":"US",
    "sg:address":"1011 S Cashua Dr",
    "sg:city":"Florence",
    "sg:classifiers":[
        {
            "category":"Autos & Motor Vehicles",
            "subcategory":"Automobile Sales",
            "type":"Retail Goods"
        }
    ],
    "sg:phone":"+1 843 665 1243",
    "sg:postcode":"29501",
    "sg:province":"SC",
    "sg:tags":[
        "car",
        "used",
        "dealer"
    ],
    "wof:name":"Craig's Used Cars",
    "wof:placetype":"venue"
},
  "geometry": {"coordinates":[-79.816034,34.172604],"type":"Point"}
}