{
  "type": "Feature",
  "properties": {
    "iso:country":"US",
    "sg:address":"6250 White Horse Rd",
    "sg:city":"Greenville",
    "sg:classifiers":[
        {
            "category":"Manufacturing",
            "subcategory":"Glass & Minerals",
            "type":"Manufacturing & Wholesale Goods"
        }
    ],
    "sg:phone":"+1 864 246 4015",
    "sg:postcode":"29611",
    "sg:province":"SC",
    "sg:tags":[
        "abrasive",
        "product",
        "mfg"
    ],
    "wof:name":"Abrasive Source LLC",
    "wof:placetype":"venue"
},
  "geometry": {"coordinates":[-82.453472,34.853346],"type":"Point"}
}