{
  "type": "Feature",
  "properties": {
    "iso:country":"US",
    "sg:address":"117 E Washington St",
    "sg:city":"Winnsboro",
    "sg:classifiers":[
        {
            "category":"Social Services",
            "type":"Services"
        }
    ],
    "sg:phone":"+1 803 635 5779",
    "sg:postcode":"29180",
    "sg:province":"SC",
    "sg:tags":[
        "local"
    ],
    "wof:name":"Red Cross",
    "wof:placetype":"venue"
},
  "geometry": {"coordinates":[-81.08455499999999,34.381005],"type":"Point"}
}