{
  "type": "Feature",
  "properties": {
    "iso:country":"US",
    "sg:address":"8 Sayle Rd",
    "sg:city":"Charleston",
    "sg:classifiers":[
        {
            "category":"Farming",
            "subcategory":"Orchard",
            "type":"Manufacturing & Wholesale Goods"
        }
    ],
    "sg:phone":"+1 843 766 0353",
    "sg:postcode":"29407",
    "sg:province":"SC",
    "sg:tags":[
        "citrus",
        "grove",
        "fruit"
    ],
    "wof:name":"Jim Aichele",
    "wof:placetype":"venue"
},
  "geometry": {"coordinates":[-79.971171,32.774528],"type":"Point"}
}