{
  "type": "Feature",
  "properties": {
    "iso:country":"US",
    "sg:address":"911 State Park Rd",
    "sg:city":"Greenville",
    "sg:classifiers":[
        {
            "category":"Wholesale",
            "subcategory":"Machinery & Supplies",
            "type":"Manufacturing & Wholesale Goods"
        }
    ],
    "sg:phone":"+1 864 250 2001",
    "sg:postcode":"29609",
    "sg:province":"SC",
    "sg:tags":[
        "sprinkler"
    ],
    "wof:name":"American Fire Protection",
    "wof:placetype":"venue"
},
  "geometry": {"coordinates":[-82.393996,34.898023],"type":"Point"}
}