{
  "type": "Feature",
  "properties": {
    "iso:country":"US",
    "sg:address":"150 University Pkwy",
    "sg:city":"Aiken",
    "sg:classifiers":[
        {
            "category":"Health Services",
            "subcategory":"Doctor",
            "type":"Services"
        }
    ],
    "sg:phone":"+1 803 641 5100",
    "sg:postcode":"29801",
    "sg:province":"SC",
    "sg:tags":[
        "physician",
        "surgeon"
    ],
    "wof:name":"Aiken Emergency Medicine Phys",
    "wof:placetype":"venue"
},
  "geometry": {"coordinates":[-81.765495,33.57494],"type":"Point"}
}