{
  "type": "Feature",
  "properties": {
    "iso:country":"US",
    "sg:address":"155 Crestview Ln",
    "sg:city":"Walterboro",
    "sg:classifiers":[
        {
            "category":"Professional",
            "subcategory":"Business Services",
            "type":"Services"
        }
    ],
    "sg:phone":"+1 843 538 5503",
    "sg:postcode":"29488",
    "sg:province":"SC",
    "sg:tags":[
        "embroidery"
    ],
    "wof:name":"Monograms & Etc",
    "wof:placetype":"venue"
},
  "geometry": {"coordinates":[-80.648397,32.94655],"type":"Point"}
}