{
  "type": "Feature",
  "properties": {
    "iso:country":"US",
    "sg:address":"5154 US Hwy 78",
    "sg:city":"St George",
    "sg:classifiers":[
        {
            "category":"Manufacturing",
            "subcategory":"Tools & Machinery",
            "type":"Manufacturing & Wholesale Goods"
        }
    ],
    "sg:phone":"+1 843 563 9281",
    "sg:postcode":"29477",
    "sg:province":"SC",
    "sg:tags":[
        "control"
    ],
    "sg:website":"www.ittconoflow.com",
    "wof:name":"ITT Conoflow",
    "wof:placetype":"venue"
},
  "geometry": {"coordinates":[-80.554233,33.178772],"type":"Point"}
}