{
  "type": "Feature",
  "properties": {
    "iso:country":"US",
    "sg:address":"103 Ram Cat Aly",
    "sg:city":"Seneca",
    "sg:classifiers":[
        {
            "category":"Communications",
            "subcategory":"Radio Station",
            "type":"Services"
        }
    ],
    "sg:phone":"+1 864 886 0082",
    "sg:postcode":"29678",
    "sg:province":"SC",
    "sg:tags":[
        "company",
        "broadcasting"
    ],
    "wof:name":"WSNW Radio Station",
    "wof:placetype":"venue"
},
  "geometry": {"coordinates":[-82.953125,34.684912],"type":"Point"}
}