{
  "type": "Feature",
  "properties": {
    "addr:full":"910 Dougherty Rd Aiken SC 29803",
    "addr:housenumber":"910",
    "addr:postcode":"29803",
    "addr:street":"Dougherty Rd",
    "iso:country":"US",
    "sg:address":"910 Dougherty Rd",
    "sg:city":"Aiken",
    "sg:classifiers":[
        {
            "category":"Food & Beverages",
            "subcategory":"Groceries & Convenience Stores",
            "type":"Retail Goods"
        }
    ],
    "sg:phone":"+1 803 641 2241",
    "sg:postcode":"29803",
    "sg:province":"SC",
    "wof:name":"Howard Enterprises",
    "wof:placetype":"venue"
},
  "geometry": {"coordinates":[-81.71700199999999,33.513898],"type":"Point"}
}