{
  "type": "Feature",
  "properties": {
    "addr:full":"802 Gold Hill Rd Fort Mill SC 29708",
    "addr:housenumber":"802",
    "addr:postcode":"29708",
    "addr:street":"Gold Hill Rd",
    "iso:country":"US",
    "sg:address":"802 Gold Hill Rd",
    "sg:city":"Fort Mill",
    "sg:classifiers":[
        {
            "category":"Autos & Motor Vehicles",
            "subcategory":"Fuel & Gas Station",
            "type":"Retail Goods"
        }
    ],
    "sg:phone":"+1 803 548 3713",
    "sg:postcode":"29708",
    "sg:province":"SC",
    "sg:tags":[
        "oil"
    ],
    "wof:name":"Shell",
    "wof:placetype":"venue"
},
  "geometry": {"coordinates":[-80.95624100000001,35.061033],"type":"Point"}
}