{
  "type": "Feature",
  "properties": {
    "addr:full":"480 Brunson Spring Rd Galivants Ferry SC 29544",
    "addr:housenumber":"480",
    "addr:postcode":"29544",
    "addr:street":"Brunson Spring Rd",
    "iso:country":"US",
    "sg:address":"480 Brunson Spring Rd",
    "sg:city":"Galivants Ferry",
    "sg:classifiers":[
        {
            "category":"Personal",
            "subcategory":"Beauty Salon",
            "type":"Services"
        }
    ],
    "sg:phone":"+1 843 365 9209",
    "sg:postcode":"29544",
    "sg:province":"SC",
    "wof:name":"Brenda's Stylette",
    "wof:placetype":"venue"
},
  "geometry": {"coordinates":[-79.164249,33.919988],"type":"Point"}
}