{
  "type": "Feature",
  "properties": {
    "iso:country":"US",
    "sg:address":"1701 Broadway Lake Rd",
    "sg:city":"Anderson",
    "sg:classifiers":[
        {
            "category":"Retail",
            "subcategory":"Portrait Studio",
            "type":"Services"
        }
    ],
    "sg:phone":"+1 864 296 8662",
    "sg:postcode":"29621",
    "sg:province":"SC",
    "sg:tags":[
        "photographer"
    ],
    "wof:name":"Rick Caperton Photography",
    "wof:placetype":"venue"
},
  "geometry": {"coordinates":[-82.59596999999999,34.451198],"type":"Point"}
}