{
  "type": "Feature",
  "properties": {
    "iso:country":"US",
    "sg:address":"197 Alton Ave",
    "sg:city":"Andrews",
    "sg:classifiers":[
        {
            "category":"Health Services",
            "subcategory":"Health Practitioner",
            "type":"Services"
        }
    ],
    "sg:phone":"+1 843 221 4441",
    "sg:postcode":"29510",
    "sg:province":"SC",
    "sg:tags":[
        "nurse",
        "registry"
    ],
    "wof:name":"Winyah Nursing Svc",
    "wof:placetype":"venue"
},
  "geometry": {"coordinates":[-79.625255,33.471992],"type":"Point"}
}