{
  "type": "Feature",
  "properties": {
    "addr:full":"2418 Laurens Rd Greenville SC 29607",
    "addr:housenumber":"2418",
    "addr:postcode":"29607",
    "addr:street":"Laurens Rd",
    "iso:country":"US",
    "sg:address":"2418 Laurens Rd",
    "sg:city":"Greenville",
    "sg:classifiers":[
        {
            "category":"Autos & Motor Vehicles",
            "subcategory":"Auto Supplies",
            "type":"Retail Goods"
        }
    ],
    "sg:phone":"+1 864 676 1365",
    "sg:postcode":"29607",
    "sg:province":"SC",
    "sg:tags":[
        "automobile",
        "parts"
    ],
    "sg:website":"www.pepboys.com",
    "wof:name":"Pep Boys Supercenter",
    "wof:placetype":"venue"
},
  "geometry": {"coordinates":[-82.34831,34.831121],"type":"Point"}
}