{
  "type": "Feature",
  "properties": {
    "iso:country":"US",
    "sg:address":"617 Lancaster Byp E",
    "sg:city":"Lancaster",
    "sg:classifiers":[
        {
            "category":"Banks & Credit Unions",
            "subcategory":"Bank",
            "type":"Services"
        }
    ],
    "sg:phone":"+1 803 285 0405",
    "sg:postcode":"29720",
    "sg:province":"SC",
    "sg:tags":[
        "loan",
        "real estate"
    ],
    "wof:name":"Charlotte Home Equity",
    "wof:placetype":"venue"
},
  "geometry": {"coordinates":[-80.766778,34.732639],"type":"Point"}
}