{
  "type": "Feature",
  "properties": {
    "addr:full":"102 Central Ave Summerville SC 29483",
    "addr:housenumber":"102",
    "addr:postcode":"29483",
    "addr:street":"Central Ave",
    "iso:country":"US",
    "sg:address":"102 Central Ave",
    "sg:city":"Summerville",
    "sg:classifiers":[
        {
            "category":"Shopping",
            "type":"Retail Goods"
        }
    ],
    "sg:phone":"+1 843 871 0297",
    "sg:postcode":"29483",
    "sg:province":"SC",
    "sg:tags":[
        "merchandise"
    ],
    "wof:name":"Art Central LTD",
    "wof:placetype":"venue"
},
  "geometry": {"coordinates":[-80.176722,33.019383],"type":"Point"}
}