{
  "type": "Feature",
  "properties": {
    "addr:full":"645 SE Main St Simpsonville SC 29681",
    "addr:housenumber":"645",
    "addr:postcode":"29681",
    "addr:street":"Se Main St",
    "iso:country":"US",
    "sg:address":"645 SE Main St",
    "sg:city":"Simpsonville",
    "sg:classifiers":[
        {
            "category":"Restaurant",
            "type":"Food & Drink"
        }
    ],
    "sg:phone":"+1 864 963 7050",
    "sg:postcode":"29681",
    "sg:province":"SC",
    "wof:name":"LA Herradura",
    "wof:placetype":"venue"
},
  "geometry": {"coordinates":[-82.25017,34.719142],"type":"Point"}
}