{
  "type": "Feature",
  "properties": {
    "iso:country":"US",
    "sg:address":"325 W Washington St",
    "sg:city":"Hartsville",
    "sg:classifiers":[
        {
            "category":"Education",
            "subcategory":"School",
            "type":"Public Place"
        }
    ],
    "sg:phone":"+1 843 383 3141",
    "sg:postcode":"29550",
    "sg:province":"SC",
    "wof:name":"Washington Street Elementary",
    "wof:placetype":"venue"
},
  "geometry": {"coordinates":[-80.074459,34.361352],"type":"Point"}
}