{
  "type": "Feature",
  "properties": {
    "addr:full":"1101 Cedar Lane Rd Greenville SC 29617",
    "addr:housenumber":"1101",
    "addr:postcode":"29617",
    "addr:street":"Cedar Lane Rd",
    "iso:country":"US",
    "sg:address":"1101 Cedar Lane Rd",
    "sg:city":"Greenville",
    "sg:classifiers":[
        {
            "category":"Real Estate",
            "subcategory":"Real Estate Agent",
            "type":"Services"
        }
    ],
    "sg:phone":"+1 864 246 0571",
    "sg:postcode":"29617",
    "sg:province":"SC",
    "wof:name":"Williams Realty Co",
    "wof:placetype":"venue"
},
  "geometry": {"coordinates":[-82.43814999999999,34.872969],"type":"Point"}
}