{
  "type": "Feature",
  "properties": {
    "iso:country":"US",
    "sg:address":"10813 Sidneys Rd",
    "sg:city":"Round O",
    "sg:classifiers":[
        {
            "category":"Building & Trades",
            "subcategory":"Plumbing",
            "type":"Services"
        }
    ],
    "sg:phone":"+1 843 835 2612",
    "sg:postcode":"29474",
    "sg:province":"SC",
    "sg:tags":[
        "contractor"
    ],
    "wof:name":"Bridge Heating & Air",
    "wof:placetype":"venue"
},
  "geometry": {"coordinates":[-80.527718,33.043749],"type":"Point"}
}