{
  "type": "Feature",
  "properties": {
    "iso:country":"US",
    "sg:address":"132 S Main St",
    "sg:city":"Woodruff",
    "sg:classifiers":[
        {
            "category":"Shopping",
            "subcategory":"Used Merchandise",
            "type":"Retail Goods"
        }
    ],
    "sg:phone":"+1 864 476 0725",
    "sg:postcode":"29388",
    "sg:province":"SC",
    "wof:name":"Pickity Picks",
    "wof:placetype":"venue"
},
  "geometry": {"coordinates":[-82.03705,34.739363],"type":"Point"}
}