{
  "type": "Feature",
  "properties": {
    "addr:full":"2068 Emery Rd Loris SC 29569",
    "addr:housenumber":"2068",
    "addr:postcode":"29569",
    "addr:street":"Emery Rd",
    "iso:country":"US",
    "sg:address":"2068 Emery Rd",
    "sg:city":"Loris",
    "sg:classifiers":[
        {
            "category":"Building & Trades",
            "subcategory":"Plumbing",
            "type":"Services"
        }
    ],
    "sg:phone":"+1 843 716 0862",
    "sg:postcode":"29569",
    "sg:province":"SC",
    "sg:tags":[
        "plumbing",
        "contractor"
    ],
    "wof:name":"Boyd's Plumbing Inc",
    "wof:placetype":"venue"
},
  "geometry": {"coordinates":[-78.846189,33.941968],"type":"Point"}
}