{
  "type": "Feature",
  "properties": {
    "iso:country":"US",
    "sg:address":"107 Autumn Ln",
    "sg:city":"Williamston",
    "sg:classifiers":[
        {
            "category":"Manufacturing",
            "subcategory":"Tools & Machinery",
            "type":"Manufacturing & Wholesale Goods"
        }
    ],
    "sg:phone":"+1 864 847 1602",
    "sg:postcode":"29697",
    "sg:province":"SC",
    "sg:tags":[
        "photographic",
        "mfg"
    ],
    "wof:name":"Kathy Cannon",
    "wof:placetype":"venue"
},
  "geometry": {"coordinates":[-82.514644,34.633727],"type":"Point"}
}