{
  "type": "Feature",
  "properties": {
    "iso:country":"US",
    "sg:address":"407 30th Ave N",
    "sg:city":"Myrtle Beach",
    "sg:classifiers":[
        {
            "category":"Manufacturing",
            "subcategory":"Printing",
            "type":"Manufacturing & Wholesale Goods"
        }
    ],
    "sg:phone":"+1 843 448 2928",
    "sg:postcode":"29577",
    "sg:province":"SC",
    "sg:tags":[
        "catalog",
        "printer",
        "publication"
    ],
    "sg:website":"www.netbookpro.com",
    "wof:name":"BCI Catalog Group",
    "wof:placetype":"venue"
},
  "geometry": {"coordinates":[-78.862995,33.709599],"type":"Point"}
}