{
  "type": "Feature",
  "properties": {
    "iso:country":"US",
    "sg:address":"2200 Greenpines Rd",
    "sg:city":"Columbia",
    "sg:classifiers":[
        {
            "category":"Professional",
            "subcategory":"Engineering",
            "type":"Services"
        }
    ],
    "sg:phone":"+1 803 736 0711",
    "sg:postcode":"29206",
    "sg:province":"SC",
    "sg:tags":[
        "engineer"
    ],
    "wof:name":"Triplett King & Assoc",
    "wof:placetype":"venue"
},
  "geometry": {"coordinates":[-80.947287,34.050533],"type":"Point"}
}