{
  "type": "Feature",
  "properties": {
    "iso:country":"US",
    "sg:address":"398 Riverside Dr SW",
    "sg:city":"Orangeburg",
    "sg:classifiers":[
        {
            "category":"Shopping",
            "subcategory":"Shoes",
            "type":"Retail Goods"
        }
    ],
    "sg:phone":"+1 803 535 3534",
    "sg:postcode":"29115",
    "sg:province":"SC",
    "wof:name":"Shoe Time South Carolina Inc",
    "wof:placetype":"venue"
},
  "geometry": {"coordinates":[-80.875445,33.490474],"type":"Point"}
}