{
  "type": "Feature",
  "properties": {
    "addr:full":"2110 Nettles Rd Sumter SC 29154",
    "addr:housenumber":"2110",
    "addr:postcode":"29154",
    "addr:street":"Nettles Rd",
    "iso:country":"US",
    "sg:address":"2110 Nettles Rd",
    "sg:city":"Sumter",
    "sg:classifiers":[
        {
            "category":"Farming",
            "subcategory":"Poultry Farm",
            "type":"Manufacturing & Wholesale Goods"
        }
    ],
    "sg:phone":"+1 803 481 2640",
    "sg:postcode":"29154",
    "sg:province":"SC",
    "sg:tags":[
        "hatchery"
    ],
    "wof:name":"Hill Poultry",
    "wof:placetype":"venue"
},
  "geometry": {"coordinates":[-80.382578,33.826194],"type":"Point"}
}