{
  "type": "Feature",
  "properties": {
    "addr:full":"8508 Old State Rd Holly Hill SC 29059",
    "addr:housenumber":"8508",
    "addr:postcode":"29059",
    "addr:street":"Old State Rd",
    "iso:country":"US",
    "sg:address":"8508 Old State Rd",
    "sg:city":"Holly Hill",
    "sg:classifiers":[
        {
            "category":"Food & Beverages",
            "subcategory":"Groceries & Convenience Stores",
            "type":"Retail Goods"
        }
    ],
    "sg:phone":"+1 803 496 3315",
    "sg:postcode":"29059",
    "sg:province":"SC",
    "sg:tags":[
        "grocer"
    ],
    "sg:website":"www.pignet.com",
    "wof:name":"Piggly Wiggly",
    "wof:placetype":"venue"
},
  "geometry": {"coordinates":[-80.41434700000001,33.323252],"type":"Point"}
}