{
  "type": "Feature",
  "properties": {
    "iso:country":"US",
    "sg:address":"3374 Broughton St",
    "sg:city":"Orangeburg",
    "sg:classifiers":[
        {
            "category":"Personal",
            "subcategory":"Beauty Salon",
            "type":"Services"
        }
    ],
    "sg:phone":"+1 803 531 0227",
    "sg:postcode":"29115",
    "sg:province":"SC",
    "wof:name":"Signatures Hair Design",
    "wof:placetype":"venue"
},
  "geometry": {"coordinates":[-80.881209,33.519199],"type":"Point"}
}