{
  "type": "Feature",
  "properties": {
    "iso:country":"US",
    "sg:address":"1020 30th Ave S",
    "sg:city":"Atlantic Beach",
    "sg:classifiers":[
        {
            "category":"Real Estate",
            "subcategory":"Real Estate Agent",
            "type":"Services"
        }
    ],
    "sg:phone":"+1 843 272 4189",
    "sg:postcode":"29582",
    "sg:province":"SC",
    "sg:tags":[
        "authorities",
        "housing"
    ],
    "wof:name":"Housing Authority-Atlantic Bch",
    "wof:placetype":"venue"
},
  "geometry": {"coordinates":[-78.719487,33.807435],"type":"Point"}
}