{
  "type": "Feature",
  "properties": {
    "addr:full":"3131 N Main St Anderson SC 29621",
    "addr:housenumber":"3131",
    "addr:postcode":"29621",
    "addr:street":"N Main St",
    "iso:country":"US",
    "sg:address":"3131 N Main St",
    "sg:city":"Anderson",
    "sg:classifiers":[
        {
            "category":"Personal",
            "subcategory":"Beauty Salon",
            "type":"Services"
        }
    ],
    "sg:phone":"+1 864 226 2000",
    "sg:postcode":"29621",
    "sg:province":"SC",
    "wof:name":"Trade Secret",
    "wof:placetype":"venue"
},
  "geometry": {"coordinates":[-82.66766699999999,34.539113],"type":"Point"}
}