{
  "type": "Feature",
  "properties": {
    "iso:country":"US",
    "sg:address":"406 State Hwy 174",
    "sg:city":"Edisto Island",
    "sg:classifiers":[
        {
            "category":"Shopping",
            "subcategory":"Gifts & Souvenirs",
            "type":"Retail Goods"
        }
    ],
    "sg:phone":"+1 843 869 4466",
    "sg:postcode":"29438",
    "sg:province":"SC",
    "sg:tags":[
        "shop"
    ],
    "wof:name":"Edistonain Gift Shop & Gallery",
    "wof:placetype":"venue"
},
  "geometry": {"coordinates":[-80.299747,32.521221],"type":"Point"}
}