{
  "type": "Feature",
  "properties": {
    "addr:full":"45 Millwright Dr Hilton Head Isle SC 29926",
    "addr:housenumber":"45",
    "addr:postcode":"29926",
    "addr:street":"Millwright Dr",
    "iso:country":"US",
    "sg:address":"45 Millwright Dr",
    "sg:city":"Hilton Head Isle",
    "sg:classifiers":[
        {
            "category":"Professional",
            "type":"Services"
        }
    ],
    "sg:phone":"+1 843 689 9080",
    "sg:postcode":"29926",
    "sg:province":"SC",
    "sg:tags":[
        "arts",
        "artist"
    ],
    "wof:name":"Kimpton & Blais",
    "wof:placetype":"venue"
},
  "geometry": {"coordinates":[-80.76809,32.217165],"type":"Point"}
}