{
  "type": "Feature",
  "properties": {
    "iso:country":"US",
    "sg:address":"556 Macedonia Church Rd",
    "sg:city":"Prosperity",
    "sg:classifiers":[
        {
            "category":"Real Estate",
            "subcategory":"Real Estate Services",
            "type":"Services"
        }
    ],
    "sg:phone":"+1 803 364 1886",
    "sg:postcode":"29127",
    "sg:province":"SC",
    "sg:tags":[
        "abstract",
        "title"
    ],
    "wof:name":"Vicki Eaves",
    "wof:placetype":"venue"
},
  "geometry": {"coordinates":[-81.438031,34.098086],"type":"Point"}
}