{
  "type": "Feature",
  "properties": {
    "iso:country":"US",
    "sg:address":"3855 Fork Hill Rd",
    "sg:city":"Kershaw",
    "sg:classifiers":[
        {
            "category":"Government",
            "subcategory":"Police Station",
            "type":"Public Place"
        }
    ],
    "sg:phone":"+1 803 475 4470",
    "sg:postcode":"29067",
    "sg:province":"SC",
    "sg:tags":[
        "sheriff"
    ],
    "wof:name":"Lancaster County Sheriffs Dept",
    "wof:placetype":"venue"
},
  "geometry": {"coordinates":[-80.586423,34.5714],"type":"Point"}
}