{
  "type": "Feature",
  "properties": {
    "iso:country":"US",
    "sg:address":"680 E Black Creek Rd",
    "sg:city":"Florence",
    "sg:classifiers":[
        {
            "category":"Building & Trades",
            "subcategory":"Construction",
            "type":"Services"
        }
    ],
    "sg:phone":"+1 843 662 8175",
    "sg:postcode":"29506",
    "sg:province":"SC",
    "sg:tags":[
        "general",
        "contractor"
    ],
    "wof:name":"Dudley H Courtney Gen Contrs",
    "wof:placetype":"venue"
},
  "geometry": {"coordinates":[-79.73223900000001,34.24518],"type":"Point"}
}