{
  "type": "Feature",
  "properties": {
    "iso:country":"US",
    "sg:address":"Columbia Metropolitan",
    "sg:city":"West Columbia",
    "sg:classifiers":[
        {
            "category":"Airline",
            "type":"Transportation"
        }
    ],
    "sg:phone":"+1 803 822 8873",
    "sg:postcode":"29170",
    "sg:province":"SC",
    "sg:tags":[
        "airport"
    ],
    "wof:name":"Travel Incorporated",
    "wof:placetype":"venue"
},
  "geometry": {"coordinates":[-81.125235,33.946007],"type":"Point"}
}