{
  "type": "Feature",
  "properties": {
    "iso:country":"US",
    "sg:address":"4046 Fernandina Rd",
    "sg:city":"Columbia",
    "sg:classifiers":[
        {
            "category":"Recreation",
            "type":"Entertainment"
        }
    ],
    "sg:phone":"+1 803 561 9682",
    "sg:postcode":"29210",
    "sg:province":"SC",
    "sg:tags":[
        "instruction",
        "gymnastic"
    ],
    "wof:name":"All Star Gymnastics",
    "wof:placetype":"venue"
},
  "geometry": {"coordinates":[-81.140314,34.065928],"type":"Point"}
}