{
  "type": "Feature",
  "properties": {
    "iso:country":"US",
    "sg:address":"6 Collins Creek Rd",
    "sg:city":"Greenville",
    "sg:classifiers":[
        {
            "category":"Manufacturing",
            "subcategory":"Lumber",
            "type":"Manufacturing & Wholesale Goods"
        }
    ],
    "sg:phone":"+1 864 675 9146",
    "sg:postcode":"29607",
    "sg:province":"SC",
    "sg:tags":[
        "forestry"
    ],
    "wof:name":"Sustainable Resource System",
    "wof:placetype":"venue"
},
  "geometry": {"coordinates":[-82.350978,34.813889],"type":"Point"}
}