{
  "type": "Feature",
  "properties": {
    "iso:country":"US",
    "sg:address":"2395 Cains Mill Rd",
    "sg:city":"Sumter",
    "sg:classifiers":[
        {
            "category":"Manufacturing",
            "subcategory":"Chemicals & Compounds",
            "type":"Manufacturing & Wholesale Goods"
        }
    ],
    "sg:phone":"+1 803 481 8528",
    "sg:postcode":"29154",
    "sg:province":"SC",
    "sg:tags":[
        "inorganic",
        "industrial"
    ],
    "wof:name":"Phibro-Tech Inc",
    "wof:placetype":"venue"
},
  "geometry": {"coordinates":[-80.39298700000001,33.853569],"type":"Point"}
}