{
  "type": "Feature",
  "properties": {
    "iso:country":"US",
    "sg:address":"2155 W Croft Cir",
    "sg:city":"Spartanburg",
    "sg:classifiers":[
        {
            "category":"Wholesale",
            "subcategory":"Chemicals & Plastics",
            "type":"Manufacturing & Wholesale Goods"
        }
    ],
    "sg:phone":"+1 864 585 3661",
    "sg:postcode":"29302",
    "sg:province":"SC",
    "wof:name":"Blackman Uhler LLC",
    "wof:placetype":"venue"
},
  "geometry": {"coordinates":[-81.856014,34.920066],"type":"Point"}
}