{
  "type": "Feature",
  "properties": {
    "addr:full":"1115 Cedar Lane Rd Greenville SC 29617",
    "addr:housenumber":"1115",
    "addr:postcode":"29617",
    "addr:street":"Cedar Lane Rd",
    "iso:country":"US",
    "sg:address":"1115 Cedar Lane Rd",
    "sg:city":"Greenville",
    "sg:classifiers":[
        {
            "category":"Restaurant",
            "type":"Food & Drink"
        }
    ],
    "sg:phone":"+1 864 294 7977",
    "sg:postcode":"29617",
    "sg:province":"SC",
    "sg:tags":[
        "eating"
    ],
    "wof:name":"El Rancho",
    "wof:placetype":"venue"
},
  "geometry": {"coordinates":[-82.438001,34.872792],"type":"Point"}
}