{
  "type": "Feature",
  "properties": {
    "addr:full":"2601 David H McLeod Blvd Florence SC 29501",
    "addr:housenumber":"2601",
    "addr:postcode":"29501",
    "addr:street":"David H Mcleod Blvd",
    "iso:country":"US",
    "sg:address":"2601 David H McLeod Blvd",
    "sg:city":"Florence",
    "sg:classifiers":[
        {
            "category":"Shopping",
            "subcategory":"Gifts & Souvenirs",
            "type":"Retail Goods"
        }
    ],
    "sg:phone":"+1 843 665 7897",
    "sg:postcode":"29501",
    "sg:province":"SC",
    "wof:name":"Pier 1",
    "wof:placetype":"venue"
},
  "geometry": {"coordinates":[-79.825861,34.188272],"type":"Point"}
}