{
  "type": "Feature",
  "properties": {
    "addr:full":"614 Duncan Reidville Rd Duncan SC 29334",
    "addr:housenumber":"614",
    "addr:postcode":"29334",
    "addr:street":"Duncan Reidville Rd",
    "iso:country":"US",
    "sg:address":"614 Duncan Reidville Rd",
    "sg:city":"Duncan",
    "sg:classifiers":[
        {
            "category":"Home & Garden",
            "subcategory":"Furniture",
            "type":"Retail Goods"
        }
    ],
    "sg:phone":"+1 864 949 3504",
    "sg:postcode":"29334",
    "sg:province":"SC",
    "sg:tags":[
        "cabinet"
    ],
    "wof:name":"Rick's Custom Cabinets-Crating",
    "wof:placetype":"venue"
},
  "geometry": {"coordinates":[-82.14769099999999,34.90242],"type":"Point"}
}