{
  "type": "Feature",
  "properties": {
    "iso:country":"US",
    "sg:address":"104 S Hampton St",
    "sg:city":"Kershaw",
    "sg:classifiers":[
        {
            "category":"Real Estate",
            "subcategory":"Real Estate Agent",
            "type":"Services"
        }
    ],
    "sg:phone":"+1 803 475 8555",
    "sg:postcode":"29067",
    "sg:province":"SC",
    "wof:name":"Bill Clyburn Realty Inc",
    "wof:placetype":"venue"
},
  "geometry": {"coordinates":[-80.58208999999999,34.547435],"type":"Point"}
}