{
  "type": "Feature",
  "properties": {
    "addr:full":"931 Old Back River Rd Goose Creek SC 29445",
    "addr:housenumber":"931",
    "addr:postcode":"29445",
    "addr:street":"Old Back River Rd",
    "iso:country":"US",
    "sg:address":"931 Old Back River Rd",
    "sg:city":"Goose Creek",
    "sg:classifiers":[
        {
            "category":"Building & Trades",
            "subcategory":"Landscaping Services",
            "type":"Services"
        }
    ],
    "sg:phone":"+1 843 553 5906",
    "sg:postcode":"29445",
    "sg:province":"SC",
    "sg:tags":[
        "lawn",
        "landscape",
        "maintenance",
        "grounds"
    ],
    "wof:name":"Irving Landscaping",
    "wof:placetype":"venue"
},
  "geometry": {"coordinates":[-80.011456,32.985163],"type":"Point"}
}