{
  "type": "Feature",
  "properties": {
    "iso:country":"US",
    "sg:address":"700 Cantey Ln",
    "sg:city":"Rembert",
    "sg:classifiers":[
        {
            "category":"Banks & Credit Unions",
            "subcategory":"Financial Services",
            "type":"Services"
        }
    ],
    "sg:phone":"+1 803 432 8978",
    "sg:postcode":"29020",
    "sg:province":"SC",
    "sg:tags":[
        "trust",
        "management"
    ],
    "wof:name":"Burdell John",
    "wof:placetype":"venue"
},
  "geometry": {"coordinates":[-80.52825199999999,34.182953],"type":"Point"}
}