{
  "type": "Feature",
  "properties": {
    "addr:full":"141 Industrial Park Dr Greenwood SC 29646",
    "addr:housenumber":"141",
    "addr:postcode":"29646",
    "addr:street":"Industrial Park Dr",
    "iso:country":"US",
    "sg:address":"141 Industrial Park Dr",
    "sg:city":"Greenwood",
    "sg:classifiers":[
        {
            "category":"Manufacturing",
            "subcategory":"Metals",
            "type":"Manufacturing & Wholesale Goods"
        }
    ],
    "sg:phone":"+1 864 223 3350",
    "sg:postcode":"29646",
    "sg:province":"SC",
    "sg:tags":[
        "foundry"
    ],
    "wof:name":"Greenwood Foundry Co",
    "wof:placetype":"venue"
},
  "geometry": {"coordinates":[-82.13388500000001,34.204927],"type":"Point"}
}