{
  "type": "Feature",
  "properties": {
    "iso:country":"US",
    "sg:address":"40 Klein St",
    "sg:city":"Walterboro",
    "sg:classifiers":[
        {
            "category":"Government",
            "subcategory":"Court House",
            "type":"Public Place"
        }
    ],
    "sg:phone":"+1 843 549 1122",
    "sg:postcode":"29488",
    "sg:province":"SC",
    "sg:tags":[
        "county"
    ],
    "wof:name":"Colleton County Magistrate",
    "wof:placetype":"venue"
},
  "geometry": {"coordinates":[-80.668605,32.902376],"type":"Point"}
}