{
  "type": "Feature",
  "properties": {
    "addr:full":"5 Radcliffe St Charleston SC 29403",
    "addr:housenumber":"5",
    "addr:postcode":"29403",
    "addr:street":"Radcliffe St",
    "iso:country":"US",
    "sg:address":"5 Radcliffe St",
    "sg:city":"Charleston",
    "sg:classifiers":[
        {
            "category":"Real Estate",
            "subcategory":"Developer",
            "type":"Services"
        },
        {
            "category":"Real Estate",
            "subcategory":"Real Estate Agent",
            "type":"Services"
        }
    ],
    "sg:phone":"+1 843 722 1188",
    "sg:postcode":"29403",
    "sg:province":"SC",
    "sg:tags":[
        "builder",
        "operative"
    ],
    "wof:name":"Greenhill Properties Inc",
    "wof:placetype":"venue"
},
  "geometry": {"coordinates":[-79.939542,32.788571],"type":"Point"}
}