{
  "type": "Feature",
  "properties": {
    "iso:country":"US",
    "sg:address":"114 W Cherokee St",
    "sg:city":"Blacksburg",
    "sg:classifiers":[
        {
            "category":"Restaurant",
            "type":"Food & Drink"
        }
    ],
    "sg:phone":"+1 864 839 6654",
    "sg:postcode":"29702",
    "sg:province":"SC",
    "sg:tags":[
        "eating"
    ],
    "wof:name":"Bantam Chef Pizza",
    "wof:placetype":"venue"
},
  "geometry": {"coordinates":[-81.516215,35.121027],"type":"Point"}
}