{
  "type": "Feature",
  "properties": {
    "iso:country":"US",
    "sg:address":"4113 Society Hill Rd",
    "sg:city":"Society Hill",
    "sg:classifiers":[
        {
            "category":"Organizations",
            "subcategory":"Religious Organization",
            "type":"Services"
        }
    ],
    "sg:phone":"+1 843 378 4496",
    "sg:postcode":"29593",
    "sg:province":"SC",
    "sg:tags":[
        "church"
    ],
    "wof:name":"St James Holiness Church",
    "wof:placetype":"venue"
},
  "geometry": {"coordinates":[-79.851158,34.483255],"type":"Point"}
}