{
  "type": "Feature",
  "properties": {
    "iso:country":"US",
    "sg:address":"4 Crest Rd",
    "sg:city":"Edgefield",
    "sg:classifiers":[
        {
            "category":"Professional",
            "type":"Services"
        }
    ],
    "sg:phone":"+1 803 637 3500",
    "sg:postcode":"29824",
    "sg:province":"SC",
    "sg:tags":[
        "establishment"
    ],
    "wof:name":"Plastex Inc",
    "wof:placetype":"venue"
},
  "geometry": {"coordinates":[-81.93052900000001,33.805473],"type":"Point"}
}