{
  "type": "Feature",
  "properties": {
    "iso:country":"US",
    "sg:address":"1291 Falls Rd",
    "sg:city":"Rock Hill",
    "sg:classifiers":[
        {
            "category":"Real Estate",
            "subcategory":"Developer",
            "type":"Services"
        }
    ],
    "sg:phone":"+1 803 366 6665",
    "sg:postcode":"29730",
    "sg:province":"SC",
    "wof:name":"Southern Development Group",
    "wof:placetype":"venue"
},
  "geometry": {"coordinates":[-81.088505,34.920622],"type":"Point"}
}