{
  "type": "Feature",
  "properties": {
    "addr:full":"807 Meeting St West Columbia SC 29169",
    "addr:housenumber":"807",
    "addr:postcode":"29169",
    "addr:street":"Meeting St",
    "iso:country":"US",
    "sg:address":"807 Meeting St",
    "sg:city":"West Columbia",
    "sg:classifiers":[
        {
            "category":"Sports & Exercise",
            "subcategory":"Gym",
            "type":"Entertainment"
        }
    ],
    "sg:phone":"+1 803 926 4000",
    "sg:postcode":"29169",
    "sg:province":"SC",
    "sg:tags":[
        "spa",
        "health"
    ],
    "wof:name":"Omaggio Salon Spa & Galleria",
    "wof:placetype":"venue"
},
  "geometry": {"coordinates":[-81.067492,33.990817],"type":"Point"}
}