{
  "type": "Feature",
  "properties": {
    "addr:full":"748 Main St West Columbia SC 29170",
    "addr:housenumber":"748",
    "addr:postcode":"29170",
    "addr:street":"Main St",
    "iso:country":"US",
    "sg:address":"748 Main St",
    "sg:city":"West Columbia",
    "sg:classifiers":[
        {
            "category":"Shopping",
            "subcategory":"Discount & Variety Stores",
            "type":"Retail Goods"
        }
    ],
    "sg:phone":"+1 803 955 0250",
    "sg:postcode":"29170",
    "sg:province":"SC",
    "sg:tags":[
        "merchandise",
        "general"
    ],
    "wof:name":"Dynamite Dollar",
    "wof:placetype":"venue"
},
  "geometry": {"coordinates":[-81.134992,33.911669],"type":"Point"}
}