{
  "type": "Feature",
  "properties": {
    "addr:full":"401 N Pearl St Pageland SC 29728",
    "addr:housenumber":"401",
    "addr:postcode":"29728",
    "addr:street":"N Pearl St",
    "iso:country":"US",
    "sg:address":"401 N Pearl St",
    "sg:city":"Pageland",
    "sg:classifiers":[
        {
            "category":"Retail",
            "subcategory":"Auto Repair",
            "type":"Services"
        }
    ],
    "sg:phone":"+1 843 672 9503",
    "sg:postcode":"29728",
    "sg:province":"SC",
    "sg:tags":[
        "repairing",
        "automobile"
    ],
    "wof:name":"Hubbard Automotive",
    "wof:placetype":"venue"
},
  "geometry": {"coordinates":[-80.39339,34.777112],"type":"Point"}
}