{
  "type": "Feature",
  "properties": {
    "addr:full":"2769 Rosewood Dr Columbia SC 29205",
    "addr:housenumber":"2769",
    "addr:postcode":"29205",
    "addr:street":"Rosewood Dr",
    "iso:country":"US",
    "sg:address":"2769 Rosewood Dr",
    "sg:city":"Columbia",
    "sg:classifiers":[
        {
            "category":"Shopping",
            "subcategory":"Florist",
            "type":"Retail Goods"
        }
    ],
    "sg:phone":"+1 803 779 6186",
    "sg:postcode":"29205",
    "sg:province":"SC",
    "wof:name":"Flowers Forever & Etc",
    "wof:placetype":"venue"
},
  "geometry": {"coordinates":[-81.00491,33.987473],"type":"Point"}
}