{
  "type": "Feature",
  "properties": {
    "iso:country":"US",
    "sg:address":"5 Hilander Ct",
    "sg:city":"Travelers Rest",
    "sg:classifiers":[
        {
            "category":"Real Estate",
            "subcategory":"Developer",
            "type":"Services"
        }
    ],
    "sg:phone":"+1 864 834 5237",
    "sg:postcode":"29690",
    "sg:province":"SC",
    "wof:name":"STC Properties Inc",
    "wof:placetype":"venue"
},
  "geometry": {"coordinates":[-82.447507,34.952305],"type":"Point"}
}