{
  "type": "Feature",
  "properties": {
    "addr:full":"130 Center Dr Elgin SC 29072",
    "addr:housenumber":"130",
    "addr:postcode":"29072",
    "addr:street":"Center Dr",
    "iso:country":"US",
    "sg:address":"130 Center Dr",
    "sg:city":"Elgin",
    "sg:classifiers":[
        {
            "category":"Recreation",
            "type":"Entertainment"
        }
    ],
    "sg:phone":"+1 803 736 4777",
    "sg:postcode":"29072",
    "sg:province":"SC",
    "sg:tags":[
        "martial",
        "arts",
        "instruction"
    ],
    "wof:name":"Genova Family Karate",
    "wof:placetype":"venue"
},
  "geometry": {"coordinates":[-81.186222,34.04331],"type":"Point"}
}