{
  "type": "Feature",
  "properties": {
    "iso:country":"US",
    "sg:address":"4201 Main St",
    "sg:city":"Columbia",
    "sg:classifiers":[
        {
            "category":"Education",
            "subcategory":"University",
            "type":"Public Place"
        }
    ],
    "sg:phone":"+1 803 786 5150",
    "sg:postcode":"29203",
    "sg:province":"SC",
    "sg:tags":[
        "college"
    ],
    "sg:website":"www.ltss.edu",
    "wof:name":"Lutheran Theological Southern Seminary",
    "wof:placetype":"venue"
},
  "geometry": {"coordinates":[-81.039001,34.041401],"type":"Point"}
}