{
  "type": "Feature",
  "properties": {
    "addr:full":"207 Cedar Springs Rd Spartanburg SC 29302",
    "addr:housenumber":"207",
    "addr:postcode":"29302",
    "addr:street":"Cedar Springs Rd",
    "iso:country":"US",
    "sg:address":"207 Cedar Springs Rd",
    "sg:city":"Spartanburg",
    "sg:classifiers":[
        {
            "category":"Restaurant",
            "type":"Food & Drink"
        }
    ],
    "sg:phone":"+1 864 583 7997",
    "sg:postcode":"29302",
    "sg:province":"SC",
    "sg:tags":[
        "eating"
    ],
    "wof:name":"Turner Foods East Inc",
    "wof:placetype":"venue"
},
  "geometry": {"coordinates":[-81.885976,34.91894],"type":"Point"}
}