{
  "type": "Feature",
  "properties": {
    "iso:country":"US",
    "sg:address":"93 Heritage Dr",
    "sg:city":"Clover",
    "sg:classifiers":[
        {
            "category":"Restaurant",
            "type":"Food & Drink"
        }
    ],
    "sg:phone":"+1 803 831 7173",
    "sg:postcode":"29710",
    "sg:province":"SC",
    "sg:tags":[
        "eating"
    ],
    "wof:name":"McDonalds",
    "wof:placetype":"venue"
},
  "geometry": {"coordinates":[-81.054405,35.102732],"type":"Point"}
}