{
  "type": "Feature",
  "properties": {
    "addr:full":"310 E Main St Williamston SC 29697",
    "addr:housenumber":"310",
    "addr:postcode":"29697",
    "addr:street":"E Main St",
    "iso:country":"US",
    "sg:address":"310 E Main St",
    "sg:city":"Williamston",
    "sg:classifiers":[
        {
            "category":"Shopping",
            "subcategory":"Pharmacy",
            "type":"Retail Goods"
        }
    ],
    "sg:phone":"+1 864 847 4700",
    "sg:postcode":"29697",
    "sg:province":"SC",
    "wof:name":"Anmed Pharmacy",
    "wof:placetype":"venue"
},
  "geometry": {"coordinates":[-82.47164600000001,34.620669],"type":"Point"}
}