{
  "type": "Feature",
  "properties": {
    "addr:full":"217 Hunters Rd Hopkins SC 29061",
    "addr:housenumber":"217",
    "addr:postcode":"29061",
    "addr:street":"Hunters Rd",
    "iso:country":"US",
    "sg:address":"217 Hunters Rd",
    "sg:city":"Hopkins",
    "sg:classifiers":[
        {
            "category":"Building & Trades",
            "subcategory":"Plumbing",
            "type":"Services"
        }
    ],
    "sg:phone":"+1 803 776 6336",
    "sg:postcode":"29061",
    "sg:province":"SC",
    "sg:tags":[
        "plumbing",
        "contractor"
    ],
    "wof:name":"Rainbow Plumbing",
    "wof:placetype":"venue"
},
  "geometry": {"coordinates":[-80.87600500000001,33.961948],"type":"Point"}
}