{
  "type": "Feature",
  "properties": {
    "iso:country":"US",
    "sg:address":"4226 State Hwy 184",
    "sg:city":"Due West",
    "sg:classifiers":[
        {
            "category":"Organizations",
            "subcategory":"Religious Organization",
            "type":"Services"
        }
    ],
    "sg:phone":"+1 864 379 8240",
    "sg:postcode":"29639",
    "sg:province":"SC",
    "sg:tags":[
        "church"
    ],
    "wof:name":"New Hope Baptist Church",
    "wof:placetype":"venue"
},
  "geometry": {"coordinates":[-82.408816,34.322506],"type":"Point"}
}