{
  "type": "Feature",
  "properties": {
    "addr:full":"64 Research St Blackville SC 29817",
    "addr:housenumber":"64",
    "addr:postcode":"29817",
    "addr:street":"Research St",
    "iso:country":"US",
    "sg:address":"64 Research St",
    "sg:city":"Blackville",
    "sg:classifiers":[
        {
            "category":"Government",
            "subcategory":"Office",
            "type":"Public Place"
        }
    ],
    "sg:phone":"+1 803 284 3343",
    "sg:postcode":"29817",
    "sg:province":"SC",
    "wof:name":"Clemson Univ Edisto Research",
    "wof:placetype":"venue"
},
  "geometry": {"coordinates":[-81.329739,33.365349],"type":"Point"}
}