{
  "type": "Feature",
  "properties": {
    "iso:country":"US",
    "sg:address":"308 Lexington Place Way",
    "sg:city":"Greenville",
    "sg:classifiers":[
        {
            "category":"Wholesale",
            "subcategory":"Non-durable Goods",
            "type":"Manufacturing & Wholesale Goods"
        }
    ],
    "sg:phone":"+1 864 297 7729",
    "sg:postcode":"29615",
    "sg:province":"SC",
    "wof:name":"Trade Street Workout Corp",
    "wof:placetype":"venue"
},
  "geometry": {"coordinates":[-82.286,34.859885],"type":"Point"}
}