{
  "type": "Feature",
  "properties": {
    "iso:country":"US",
    "sg:address":"290 Rocky Creek Rd",
    "sg:city":"Greenville",
    "sg:classifiers":[
        {
            "category":"Wholesale",
            "subcategory":"Hardware",
            "type":"Manufacturing & Wholesale Goods"
        }
    ],
    "sg:phone":"+1 864 254 9490",
    "sg:postcode":"29615",
    "sg:province":"SC",
    "sg:tags":[
        "lock",
        "locksmith"
    ],
    "sg:website":"www.portertechnologies.com",
    "wof:name":"Porter Technologies",
    "wof:placetype":"venue"
},
  "geometry": {"coordinates":[-82.27388,34.820604],"type":"Point"}
}