{
  "type": "Feature",
  "properties": {
    "iso:country":"US",
    "sg:address":"145 S Church St",
    "sg:city":"Spartanburg",
    "sg:classifiers":[
        {
            "category":"Professional",
            "subcategory":"Accounting & Tax Preparation",
            "type":"Services"
        }
    ],
    "sg:phone":"+1 864 560 6551",
    "sg:postcode":"29306",
    "sg:province":"SC",
    "sg:tags":[
        "billing"
    ],
    "wof:name":"Sharon K Peek",
    "wof:placetype":"venue"
},
  "geometry": {"coordinates":[-81.930915,34.948309],"type":"Point"}
}