{
  "type": "Feature",
  "properties": {
    "iso:country":"US",
    "sg:address":"1070 US Hwy 501 Bus",
    "sg:city":"Conway",
    "sg:classifiers":[
        {
            "category":"Health Services",
            "subcategory":"Doctor",
            "type":"Services"
        }
    ],
    "sg:phone":"+1 843 234 1172",
    "sg:postcode":"29526",
    "sg:province":"SC",
    "sg:tags":[
        "dentist"
    ],
    "wof:name":"Carolina Orthodontic Ctr",
    "wof:placetype":"venue"
},
  "geometry": {"coordinates":[-79.056709,33.849598],"type":"Point"}
}