{
  "type": "Feature",
  "properties": {
    "iso:country":"US",
    "sg:address":"806 Railroad Ave",
    "sg:city":"Mc Cormick",
    "sg:classifiers":[
        {
            "category":"Bus Charters",
            "type":"Transportation"
        }
    ],
    "sg:phone":"+1 864 465 2385",
    "sg:postcode":"29835",
    "sg:province":"SC",
    "sg:tags":[
        "rental"
    ],
    "wof:name":"Avery's Bus Line",
    "wof:placetype":"venue"
},
  "geometry": {"coordinates":[-82.30526,33.916596],"type":"Point"}
}