{
  "type": "Feature",
  "properties": {
    "iso:country":"US",
    "sg:address":"228 Braewick Rd",
    "sg:city":"Columbia",
    "sg:classifiers":[
        {
            "category":"Restaurant",
            "type":"Food & Drink"
        }
    ],
    "sg:phone":"+1 803 781 0018",
    "sg:postcode":"29212",
    "sg:province":"SC",
    "wof:name":"Speedy Reedys Pizza In NC",
    "wof:placetype":"venue"
},
  "geometry": {"coordinates":[-81.215841,34.091696],"type":"Point"}
}