{
  "type": "Feature",
  "properties": {
    "addr:full":"140 Lawrence St Aiken SC 29803",
    "addr:housenumber":"140",
    "addr:postcode":"29803",
    "addr:street":"Lawrence St",
    "iso:country":"US",
    "sg:address":"140 Lawrence St",
    "sg:city":"Aiken",
    "sg:classifiers":[
        {
            "category":"Restaurant",
            "type":"Food & Drink"
        }
    ],
    "sg:phone":"+1 803 502 0707",
    "sg:postcode":"29803",
    "sg:province":"SC",
    "sg:tags":[
        "micro",
        "brewery"
    ],
    "wof:name":"Aiken Brewing Co",
    "wof:placetype":"venue"
},
  "geometry": {"coordinates":[-81.719284,33.437362],"type":"Point"}
}