{
  "type": "Feature",
  "properties": {
    "iso:country":"US",
    "sg:address":"203 Dillard Dr",
    "sg:city":"Goose Creek",
    "sg:classifiers":[
        {
            "category":"Personal",
            "type":"Services"
        }
    ],
    "sg:phone":"+1 843 797 7709",
    "sg:postcode":"29445",
    "sg:province":"SC",
    "sg:tags":[
        "paying",
        "bill"
    ],
    "wof:name":"Professional Bill Paying Svc",
    "wof:placetype":"venue"
},
  "geometry": {"coordinates":[-80.021754,32.954862],"type":"Point"}
}