{
  "type": "Feature",
  "properties": {
    "iso:country":"US",
    "sg:address":"511 Jackson Ave E",
    "sg:city":"Hampton",
    "sg:classifiers":[
        {
            "category":"Organizations",
            "subcategory":"Religious Organization",
            "type":"Services"
        }
    ],
    "sg:phone":"+1 803 943 2300",
    "sg:postcode":"29924",
    "sg:province":"SC",
    "sg:tags":[
        "church"
    ],
    "wof:name":"All Saints Episcopal Church",
    "wof:placetype":"venue"
},
  "geometry": {"coordinates":[-81.10527999999999,32.863471],"type":"Point"}
}