{
  "type": "Feature",
  "properties": {
    "iso:country":"US",
    "sg:address":"55 Mathews Dr",
    "sg:city":"Hilton Head Isle",
    "sg:classifiers":[
        {
            "category":"Professional",
            "subcategory":"Accounting & Tax Preparation",
            "type":"Services"
        }
    ],
    "sg:phone":"+1 843 682 2202",
    "sg:postcode":"29926",
    "sg:province":"SC",
    "sg:tags":[
        "bookkeeping",
        "general"
    ],
    "wof:name":"Professional Services",
    "wof:placetype":"venue"
},
  "geometry": {"coordinates":[-80.70316699999999,32.21803],"type":"Point"}
}