{
  "type": "Feature",
  "properties": {
    "iso:country":"US",
    "sg:address":"111 Market St",
    "sg:city":"Cheraw",
    "sg:classifiers":[
        {
            "category":"Building & Trades",
            "subcategory":"Pest Control",
            "type":"Services"
        }
    ],
    "sg:phone":"+1 843 479 2158",
    "sg:postcode":"29520",
    "sg:province":"SC",
    "wof:name":"Yarbrough Termite & Pest Cntrl",
    "wof:placetype":"venue"
},
  "geometry": {"coordinates":[-79.881507,34.698369],"type":"Point"}
}