{
  "type": "Feature",
  "properties": {
    "iso:country":"US",
    "sg:address":"2031 W Evans St",
    "sg:city":"Florence",
    "sg:classifiers":[
        {
            "category":"Restaurant",
            "type":"Food & Drink"
        }
    ],
    "sg:phone":"+1 843 665 2842",
    "sg:postcode":"29501",
    "sg:province":"SC",
    "sg:tags":[
        "eating"
    ],
    "wof:name":"Sub Station 2 of Florence",
    "wof:placetype":"venue"
},
  "geometry": {"coordinates":[-79.80659,34.194293],"type":"Point"}
}