{
  "type": "Feature",
  "properties": {
    "addr:full":"516 College Park Rd Ladson SC 29456",
    "addr:housenumber":"516",
    "addr:postcode":"29456",
    "addr:street":"College Park Rd",
    "iso:country":"US",
    "sg:address":"516 College Park Rd",
    "sg:city":"Ladson",
    "sg:classifiers":[
        {
            "category":"Autos & Motor Vehicles",
            "subcategory":"Auto Supplies",
            "type":"Retail Goods"
        }
    ],
    "sg:phone":"+1 843 797 8482",
    "sg:postcode":"29456",
    "sg:province":"SC",
    "sg:tags":[
        "equipment",
        "air",
        "conditioning",
        "automobile"
    ],
    "wof:name":"Atlantic Air & Accessories Inc",
    "wof:placetype":"venue"
},
  "geometry": {"coordinates":[-80.08859200000001,33.009857],"type":"Point"}
}