{
  "type": "Feature",
  "properties": {
    "addr:full":"1819 State Hwy 6 Pinopolis SC 29469",
    "addr:housenumber":"1819",
    "addr:postcode":"29469",
    "addr:street":"State Hwy 6",
    "iso:country":"US",
    "sg:address":"1819 State Hwy 6",
    "sg:city":"Pinopolis",
    "sg:classifiers":[
        {
            "category":"Retail",
            "subcategory":"Auto Repair",
            "type":"Services"
        }
    ],
    "sg:phone":"+1 843 753 3200",
    "sg:postcode":"29469",
    "sg:province":"SC",
    "sg:tags":[
        "wrecker"
    ],
    "wof:name":"Jim's Towing",
    "wof:placetype":"venue"
},
  "geometry": {"coordinates":[-80.102023,33.258171],"type":"Point"}
}