{
  "type": "Feature",
  "properties": {
    "addr:full":"195 Old Greenville Hwy Clemson SC 29631",
    "addr:housenumber":"195",
    "addr:postcode":"29631",
    "addr:street":"Old Greenville Hwy",
    "iso:country":"US",
    "sg:address":"195 Old Greenville Hwy",
    "sg:city":"Clemson",
    "sg:classifiers":[
        {
            "category":"Organizations",
            "subcategory":"Religious Organization",
            "type":"Services"
        }
    ],
    "sg:phone":"+1 864 654 4547",
    "sg:postcode":"29631",
    "sg:province":"SC",
    "sg:tags":[
        "church"
    ],
    "wof:name":"Wesley Foundation",
    "wof:placetype":"venue"
},
  "geometry": {"coordinates":[-82.838044,34.682459],"type":"Point"}
}