{
  "type": "Feature",
  "properties": {
    "iso:country":"US",
    "sg:address":"108 N Mauldin St",
    "sg:city":"Latta",
    "sg:classifiers":[
        {
            "category":"Health Services",
            "subcategory":"Doctor",
            "type":"Services"
        }
    ],
    "sg:phone":"+1 843 662 4600",
    "sg:postcode":"29565",
    "sg:province":"SC",
    "sg:tags":[
        "clinic"
    ],
    "wof:name":"Carolina Medcare Inc",
    "wof:placetype":"venue"
},
  "geometry": {"coordinates":[-79.433082,34.339264],"type":"Point"}
}