{
  "type": "Feature",
  "properties": {
    "iso:country":"US",
    "sg:address":"1952 Pinebrook St",
    "sg:city":"Orangeburg",
    "sg:classifiers":[
        {
            "category":"Building & Trades",
            "subcategory":"Landscaping Services",
            "type":"Services"
        }
    ],
    "sg:phone":"+1 803 516 8935",
    "sg:postcode":"29118",
    "sg:province":"SC",
    "sg:tags":[
        "lawn",
        "garden"
    ],
    "wof:name":"S&S Lawn Service/Property Mgmt",
    "wof:placetype":"venue"
},
  "geometry": {"coordinates":[-80.871359,33.518534],"type":"Point"}
}