{
  "type": "Feature",
  "properties": {
    "addr:full":"1601 N Kings Hwy Myrtle Beach SC 29577",
    "addr:housenumber":"1601",
    "addr:postcode":"29577",
    "addr:street":"N Kings Hwy",
    "iso:country":"US",
    "sg:address":"1601 N Kings Hwy",
    "sg:city":"Myrtle Beach",
    "sg:classifiers":[
        {
            "category":"Food & Beverages",
            "subcategory":"Groceries & Convenience Stores",
            "type":"Retail Goods"
        }
    ],
    "sg:phone":"+1 843 626 9205",
    "sg:postcode":"29577",
    "sg:province":"SC",
    "wof:name":"Quik Mart",
    "wof:placetype":"venue"
},
  "geometry": {"coordinates":[-78.87547600000001,33.699526],"type":"Point"}
}