{
  "type": "Feature",
  "properties": {
    "iso:country":"US",
    "sg:address":"929 Bowman Rd",
    "sg:city":"Mt Pleasant",
    "sg:classifiers":[
        {
            "category":"Health Services",
            "subcategory":"Doctor",
            "type":"Services"
        }
    ],
    "sg:phone":"+1 843 884 1777",
    "sg:postcode":"29464",
    "sg:province":"SC",
    "sg:tags":[
        "physician",
        "surgeon"
    ],
    "wof:name":"East Cooper Internal Medicine",
    "wof:placetype":"venue"
},
  "geometry": {"coordinates":[-79.857863,32.814684],"type":"Point"}
}