{
  "type": "Feature",
  "properties": {
    "iso:country":"US",
    "sg:address":"555 N Pleasantburg Dr",
    "sg:city":"Greenville",
    "sg:classifiers":[
        {
            "category":"Government",
            "subcategory":"Office",
            "type":"Public Place"
        }
    ],
    "sg:phone":"+1 864 271 1976",
    "sg:postcode":"29607",
    "sg:province":"SC",
    "sg:tags":[
        "federal",
        "program",
        "adm"
    ],
    "wof:name":"US Commerce Dept",
    "wof:placetype":"venue"
},
  "geometry": {"coordinates":[-82.356803,34.855501],"type":"Point"}
}