{
  "type": "Feature",
  "properties": {
    "addr:full":"225 W Stone Ave Greenville SC 29609",
    "addr:housenumber":"225",
    "addr:postcode":"29609",
    "addr:street":"W Stone Ave",
    "iso:country":"US",
    "sg:address":"225 W Stone Ave",
    "sg:city":"Greenville",
    "sg:classifiers":[
        {
            "category":"Insurance",
            "subcategory":"Insurance Agent",
            "type":"Services"
        }
    ],
    "sg:phone":"+1 864 242 4071",
    "sg:postcode":"29609",
    "sg:province":"SC",
    "wof:name":"Sam J Crain Insurance Co Inc",
    "wof:placetype":"venue"
},
  "geometry": {"coordinates":[-82.40034900000001,34.862019],"type":"Point"}
}