{
  "type": "Feature",
  "properties": {
    "iso:country":"US",
    "sg:address":"106 Woodlawn Dr",
    "sg:city":"Abbeville",
    "sg:classifiers":[
        {
            "category":"Professional",
            "subcategory":"Management & Consulting",
            "type":"Services"
        }
    ],
    "sg:phone":"+1 864 366 6430",
    "sg:postcode":"29620",
    "sg:province":"SC",
    "sg:tags":[
        "consultant",
        "energy",
        "conservation"
    ],
    "wof:name":"Greater Resources For America",
    "wof:placetype":"venue"
},
  "geometry": {"coordinates":[-82.39590200000001,34.180878],"type":"Point"}
}