{
  "type": "Feature",
  "properties": {
    "addr:full":"1518 Hawkins St Georgetown SC 29440",
    "addr:housenumber":"1518",
    "addr:postcode":"29440",
    "addr:street":"Hawkins St",
    "iso:country":"US",
    "sg:address":"1518 Hawkins St",
    "sg:city":"Georgetown",
    "sg:classifiers":[
        {
            "category":"Organizations",
            "subcategory":"Religious Organization",
            "type":"Services"
        }
    ],
    "sg:phone":"+1 843 527 4158",
    "sg:postcode":"29440",
    "sg:province":"SC",
    "sg:tags":[
        "church"
    ],
    "wof:name":"Greater Bibleway Church",
    "wof:placetype":"venue"
},
  "geometry": {"coordinates":[-79.297332,33.366639],"type":"Point"}
}