{
  "type": "Feature",
  "properties": {
    "iso:country":"US",
    "sg:address":"100 Brigade St",
    "sg:city":"Charleston",
    "sg:classifiers":[
        {
            "category":"Professional",
            "subcategory":"Accounting & Tax Preparation",
            "type":"Services"
        }
    ],
    "sg:phone":"+1 843 722 0049",
    "sg:postcode":"29403",
    "sg:province":"SC",
    "sg:tags":[
        "accountant"
    ],
    "wof:name":"Gambrell & Assoc",
    "wof:placetype":"venue"
},
  "geometry": {"coordinates":[-79.946472,32.810882],"type":"Point"}
}