{
  "type": "Feature",
  "properties": {
    "iso:country":"US",
    "sg:address":"2036 Bear Village Ct",
    "sg:city":"Newberry",
    "sg:classifiers":[
        {
            "category":"Banks & Credit Unions",
            "subcategory":"Bank",
            "type":"Services"
        }
    ],
    "sg:phone":"+1 803 276 1392",
    "sg:postcode":"29108",
    "sg:province":"SC",
    "sg:tags":[
        "lender",
        "loan"
    ],
    "wof:name":"National Finance Co Inc",
    "wof:placetype":"venue"
},
  "geometry": {"coordinates":[-81.60866900000001,34.296259],"type":"Point"}
}