{
  "type": "Feature",
  "properties": {
    "iso:country":"US",
    "sg:address":"219 1st St",
    "sg:city":"Moncks Corner",
    "sg:classifiers":[
        {
            "category":"Health Services",
            "subcategory":"Doctor",
            "type":"Services"
        }
    ],
    "sg:phone":"+1 843 761 8142",
    "sg:postcode":"29461",
    "sg:province":"SC",
    "sg:tags":[
        "dentist"
    ],
    "wof:name":"Sam N Pratt Jr DDS",
    "wof:placetype":"venue"
},
  "geometry": {"coordinates":[-80.007796,33.195203],"type":"Point"}
}