{
  "type": "Feature",
  "properties": {
    "addr:full":"1035 Hobby Ln Anderson SC 29621",
    "addr:housenumber":"1035",
    "addr:postcode":"29621",
    "addr:street":"Hobby Ln",
    "iso:country":"US",
    "sg:address":"1035 Hobby Ln",
    "sg:city":"Anderson",
    "sg:classifiers":[
        {
            "category":"Building & Trades",
            "subcategory":"Plumbing",
            "type":"Services"
        }
    ],
    "sg:phone":"+1 864 716 0050",
    "sg:postcode":"29621",
    "sg:province":"SC",
    "sg:tags":[
        "plumbing",
        "contractor"
    ],
    "wof:name":"Mountainview Mechanical",
    "wof:placetype":"venue"
},
  "geometry": {"coordinates":[-82.65622999999999,34.590648],"type":"Point"}
}