{
  "type": "Feature",
  "properties": {
    "iso:country":"US",
    "sg:address":"244 John St",
    "sg:city":"Lake City",
    "sg:classifiers":[
        {
            "category":"Banks & Credit Unions",
            "subcategory":"Bank",
            "type":"Services"
        }
    ],
    "sg:phone":"+1 843 394 7801",
    "sg:postcode":"29560",
    "sg:province":"SC",
    "sg:tags":[
        "loan"
    ],
    "wof:name":"Delta Loans",
    "wof:placetype":"venue"
},
  "geometry": {"coordinates":[-79.759291,33.875009],"type":"Point"}
}