{
  "type": "Feature",
  "properties": {
    "iso:country":"US",
    "sg:address":"816 Jonesville Lockhart Hwy",
    "sg:city":"Union",
    "sg:classifiers":[
        {
            "category":"Retail",
            "subcategory":"Repair Shop",
            "type":"Services"
        }
    ],
    "sg:phone":"+1 864 674 0990",
    "sg:postcode":"29379",
    "sg:province":"SC",
    "sg:tags":[
        "equipment",
        "hydraulic"
    ],
    "wof:name":"Express Hydraulics",
    "wof:placetype":"venue"
},
  "geometry": {"coordinates":[-81.631159,34.8172],"type":"Point"}
}