{
  "type": "Feature",
  "properties": {
    "iso:country":"US",
    "sg:address":"104 Garrett St",
    "sg:city":"Laurens",
    "sg:classifiers":[
        {
            "category":"Home & Garden",
            "subcategory":"Building Materials",
            "type":"Retail Goods"
        }
    ],
    "sg:phone":"+1 864 682 6032",
    "sg:postcode":"29360",
    "sg:province":"SC",
    "sg:tags":[
        "builder",
        "supply"
    ],
    "wof:name":"Don Belue Builders Supply",
    "wof:placetype":"venue"
},
  "geometry": {"coordinates":[-81.997434,34.512501],"type":"Point"}
}