{
  "type": "Feature",
  "properties": {
    "iso:country":"US",
    "sg:address":"6102 Rockefeller Rd",
    "sg:city":"Wadmalaw Island",
    "sg:classifiers":[
        {
            "category":"Shopping",
            "subcategory":"Clothing, Apparel, & Fashions",
            "type":"Retail Goods"
        }
    ],
    "sg:phone":"+1 843 559 1404",
    "sg:postcode":"29487",
    "sg:province":"SC",
    "sg:tags":[
        "clergy",
        "vestment"
    ],
    "wof:name":"St Silouan Retreat",
    "wof:placetype":"venue"
},
  "geometry": {"coordinates":[-80.208148,32.646379],"type":"Point"}
}