{
  "type": "Feature",
  "properties": {
    "iso:country":"US",
    "sg:address":"1116 Cherokee Ave",
    "sg:city":"Gaffney",
    "sg:classifiers":[
        {
            "category":"Retail",
            "subcategory":"Laundry & Dry Cleaning",
            "type":"Services"
        }
    ],
    "sg:phone":"+1 864 489 6914",
    "sg:postcode":"29340",
    "sg:province":"SC",
    "wof:name":"Daisy Fresh Coin Laundry",
    "wof:placetype":"venue"
},
  "geometry": {"coordinates":[-81.633953,35.079787],"type":"Point"}
}