{
  "type": "Feature",
  "properties": {
    "addr:full":"3980 Byrnes Dr Saint Stephen SC 29479",
    "addr:housenumber":"3980",
    "addr:postcode":"29479",
    "addr:street":"Byrnes Dr Saint",
    "iso:country":"US",
    "sg:address":"3980 Byrnes Dr",
    "sg:city":"Saint Stephen",
    "sg:classifiers":[
        {
            "category":"Restaurant",
            "type":"Food & Drink"
        }
    ],
    "sg:menulink":"http://www.allmenus.com/sc/st-stephen/101911-huddle-house/menu/",
    "sg:phone":"+1 843 567 3733",
    "sg:postcode":"29479",
    "sg:province":"SC",
    "sg:tags":[
        "american",
        "diner"
    ],
    "wof:name":"Huddle House",
    "wof:placetype":"venue"
},
  "geometry": {"coordinates":[-79.929067,33.408155],"type":"Point"}
}