{
  "type": "Feature",
  "properties": {
    "iso:country":"US",
    "sg:address":"3320 US Hwy 15 S",
    "sg:city":"Sumter",
    "sg:classifiers":[
        {
            "category":"Bars & Pubs",
            "type":"Food & Drink"
        }
    ],
    "sg:phone":"+1 803 481 5869",
    "sg:postcode":"29150",
    "sg:province":"SC",
    "wof:name":"Jack's",
    "wof:placetype":"venue"
},
  "geometry": {"coordinates":[-80.368583,33.821933],"type":"Point"}
}