{
  "type": "Feature",
  "properties": {
    "iso:country":"US",
    "sg:address":"520 Mize Rd",
    "sg:city":"Belton",
    "sg:classifiers":[
        {
            "category":"Building & Trades",
            "subcategory":"Electrical",
            "type":"Services"
        }
    ],
    "sg:phone":"+1 864 338 3001",
    "sg:postcode":"29627",
    "sg:province":"SC",
    "sg:tags":[
        "electric",
        "contractor"
    ],
    "wof:name":"Pro Ventures Elec Contr Inc",
    "wof:placetype":"venue"
},
  "geometry": {"coordinates":[-82.510817,34.565454],"type":"Point"}
}