{
  "type": "Feature",
  "properties": {
    "iso:country":"US",
    "sg:address":"1262 Main St",
    "sg:city":"West Columbia",
    "sg:classifiers":[
        {
            "category":"Food & Beverages",
            "subcategory":"Groceries & Convenience Stores",
            "type":"Retail Goods"
        }
    ],
    "sg:phone":"+1 803 755 9170",
    "sg:postcode":"29170",
    "sg:province":"SC",
    "sg:tags":[
        "grocer"
    ],
    "wof:name":"Hilltop Grocery",
    "wof:placetype":"venue"
},
  "geometry": {"coordinates":[-81.14769699999999,33.9007],"type":"Point"}
}