{
  "type": "Feature",
  "properties": {
    "iso:country":"US",
    "sg:address":"541 Haywood Rd",
    "sg:city":"Greenville",
    "sg:classifiers":[
        {
            "category":"Restaurant",
            "type":"Food & Drink"
        }
    ],
    "sg:phone":"+1 864 297 0113",
    "sg:postcode":"29607",
    "sg:province":"SC",
    "wof:name":"Cheeseburger In Paradise",
    "wof:placetype":"venue"
},
  "geometry": {"coordinates":[-82.33883899999999,34.847864],"type":"Point"}
}