{
  "type": "Feature",
  "properties": {
    "addr:full":"1580 E Main St Duncan SC 29334",
    "addr:housenumber":"1580",
    "addr:postcode":"29334",
    "addr:street":"E Main St",
    "iso:country":"US",
    "sg:address":"1580 E Main St",
    "sg:city":"Duncan",
    "sg:classifiers":[
        {
            "category":"Restaurant",
            "type":"Food & Drink"
        }
    ],
    "sg:phone":"+1 864 486 0226",
    "sg:postcode":"29334",
    "sg:province":"SC",
    "sg:tags":[
        "eating"
    ],
    "wof:name":"Thai Cuisine",
    "wof:placetype":"venue"
},
  "geometry": {"coordinates":[-82.101562,34.907908],"type":"Point"}
}