{
  "type": "Feature",
  "properties": {
    "iso:country":"US",
    "sg:address":"137 Ball Park Rd",
    "sg:city":"Lexington",
    "sg:classifiers":[
        {
            "category":"Retail",
            "subcategory":"Repair Shop",
            "type":"Services"
        }
    ],
    "sg:phone":"+1 803 359 7443",
    "sg:postcode":"29072",
    "sg:province":"SC",
    "sg:tags":[
        "scooter",
        "motorcycle",
        "motor"
    ],
    "wof:name":"Cook's Cycle Svc & Repair Inc",
    "wof:placetype":"venue"
},
  "geometry": {"coordinates":[-81.28849,33.974597],"type":"Point"}
}