{
  "type": "Feature",
  "properties": {
    "addr:full":"3851 Hickory Grove Rd Sharon SC 29742",
    "addr:housenumber":"3851",
    "addr:postcode":"29742",
    "addr:street":"Hickory Grove Rd",
    "iso:country":"US",
    "sg:address":"3851 Hickory Grove Rd",
    "sg:city":"Sharon",
    "sg:classifiers":[
        {
            "category":"Wholesale",
            "subcategory":"Durable Goods & Equipment",
            "type":"Manufacturing & Wholesale Goods"
        }
    ],
    "sg:phone":"+1 803 927 0222",
    "sg:postcode":"29742",
    "sg:province":"SC",
    "wof:name":"Dennis Lemoine Plumbing",
    "wof:placetype":"venue"
},
  "geometry": {"coordinates":[-81.37430500000001,34.955585],"type":"Point"}
}