{
  "type": "Feature",
  "properties": {
    "iso:country":"US",
    "sg:address":"6 Rutherford Rd",
    "sg:city":"Greenville",
    "sg:classifiers":[
        {
            "category":"Shopping",
            "subcategory":"Discount & Variety Stores",
            "type":"Retail Goods"
        }
    ],
    "sg:phone":"+1 864 250 0076",
    "sg:postcode":"29609",
    "sg:province":"SC",
    "sg:tags":[
        "merchandise",
        "general"
    ],
    "wof:name":"Shaw's Store & More",
    "wof:placetype":"venue"
},
  "geometry": {"coordinates":[-82.40387200000001,34.867949],"type":"Point"}
}