{
  "type": "Feature",
  "properties": {
    "iso:country":"US",
    "sg:address":"1424 Pearman Dairy Rd",
    "sg:city":"Anderson",
    "sg:classifiers":[
        {
            "category":"Professional",
            "type":"Services"
        }
    ],
    "sg:phone":"+1 864 224 3220",
    "sg:postcode":"29625",
    "sg:province":"SC",
    "sg:tags":[
        "establishment"
    ],
    "wof:name":"SBP",
    "wof:placetype":"venue"
},
  "geometry": {"coordinates":[-82.69464499999999,34.52704],"type":"Point"}
}