{
  "type": "Feature",
  "properties": {
    "iso:country":"US",
    "sg:address":"402 N Murray Ave",
    "sg:city":"Anderson",
    "sg:classifiers":[
        {
            "category":"Government",
            "subcategory":"Office",
            "type":"Public Place"
        }
    ],
    "sg:phone":"+1 864 231 1924",
    "sg:postcode":"29625",
    "sg:province":"SC",
    "wof:name":"Anderson County Farmers Market",
    "wof:placetype":"venue"
},
  "geometry": {"coordinates":[-82.65264,34.50706],"type":"Point"}
}