{
  "type": "Feature",
  "properties": {
    "iso:country":"US",
    "sg:address":"616 Carriage Lake Dr",
    "sg:city":"Lexington",
    "sg:classifiers":[
        {
            "category":"Building & Trades",
            "subcategory":"Landscaping Services",
            "type":"Services"
        }
    ],
    "sg:phone":"+1 803 957 4880",
    "sg:postcode":"29072",
    "sg:province":"SC",
    "sg:tags":[
        "lawn",
        "maintenance",
        "grounds"
    ],
    "wof:name":"TMS Svc Inc",
    "wof:placetype":"venue"
},
  "geometry": {"coordinates":[-81.23061199999999,34.010449],"type":"Point"}
}