{
  "type": "Feature",
  "properties": {
    "iso:country":"US",
    "sg:address":"212 NE Main St",
    "sg:city":"Simpsonville",
    "sg:classifiers":[
        {
            "category":"Real Estate",
            "subcategory":"Real Estate Agent",
            "type":"Services"
        }
    ],
    "sg:phone":"+1 864 962 6636",
    "sg:postcode":"29681",
    "sg:province":"SC",
    "sg:website":"www.dickenscompany.com",
    "wof:name":"Dickens Co",
    "wof:placetype":"venue"
},
  "geometry": {"coordinates":[-82.256016,34.739375],"type":"Point"}
}