{
  "type": "Feature",
  "properties": {
    "iso:country":"US",
    "sg:address":"2419 Forest Dr",
    "sg:city":"Columbia",
    "sg:classifiers":[
        {
            "category":"Restaurant",
            "type":"Food & Drink"
        }
    ],
    "sg:phone":"+1 803 254 7800",
    "sg:postcode":"29204",
    "sg:province":"SC",
    "sg:tags":[
        "chinese"
    ],
    "wof:name":"China Kitchen Chinese Restaurant",
    "wof:placetype":"venue"
},
  "geometry": {"coordinates":[-81.0158,34.013],"type":"Point"}
}