{
  "type": "Feature",
  "properties": {
    "iso:country":"US",
    "sg:address":"205 Miller Rd",
    "sg:city":"Anderson",
    "sg:classifiers":[
        {
            "category":"Building & Trades",
            "subcategory":"Construction",
            "type":"Services"
        }
    ],
    "sg:phone":"+1 864 338 6020",
    "sg:postcode":"29625",
    "sg:province":"SC",
    "sg:tags":[
        "grading",
        "contractor"
    ],
    "wof:name":"Pepper Grading",
    "wof:placetype":"venue"
},
  "geometry": {"coordinates":[-82.788078,34.587106],"type":"Point"}
}