{
  "type": "Feature",
  "properties": {
    "addr:full":"524 Main St N New Ellenton SC 29803",
    "addr:housenumber":"524",
    "addr:postcode":"29803",
    "addr:street":"Main St N",
    "iso:country":"US",
    "sg:address":"524 Main St N",
    "sg:city":"New Ellenton",
    "sg:classifiers":[
        {
            "category":"Building & Trades",
            "subcategory":"Construction",
            "type":"Services"
        }
    ],
    "sg:phone":"+1 803 652 3353",
    "sg:postcode":"29803",
    "sg:province":"SC",
    "sg:tags":[
        "general",
        "contractor"
    ],
    "wof:name":"Wolf Construction",
    "wof:placetype":"venue"
},
  "geometry": {"coordinates":[-81.68559500000001,33.424828],"type":"Point"}
}