{
  "type": "Feature",
  "properties": {
    "iso:country":"US",
    "sg:address":"101 N Howard Ave",
    "sg:city":"Landrum",
    "sg:classifiers":[
        {
            "category":"Shopping",
            "type":"Retail Goods"
        }
    ],
    "sg:phone":"+1 864 457 4995",
    "sg:postcode":"29356",
    "sg:province":"SC",
    "sg:tags":[
        "hearing",
        "equipment",
        "supply",
        "impaired"
    ],
    "wof:name":"Richards Hearing Aid Ctr",
    "wof:placetype":"venue"
},
  "geometry": {"coordinates":[-82.191441,35.176775],"type":"Point"}
}