{
  "type": "Feature",
  "properties": {
    "iso:country":"US",
    "sg:address":"122 E Main St",
    "sg:city":"Union",
    "sg:classifiers":[
        {
            "category":"Personal",
            "subcategory":"Beauty Salon",
            "type":"Services"
        }
    ],
    "sg:phone":"+1 864 427 5227",
    "sg:postcode":"29379",
    "sg:province":"SC",
    "wof:name":"Beauty Care",
    "wof:placetype":"venue"
},
  "geometry": {"coordinates":[-81.62280800000001,34.715349],"type":"Point"}
}