{
  "type": "Feature",
  "properties": {
    "addr:full":"10497 N Kings Hwy Myrtle Beach SC 29572",
    "addr:housenumber":"10497",
    "addr:postcode":"29572",
    "addr:street":"N Kings Hwy",
    "iso:country":"US",
    "sg:address":"10497 N Kings Hwy",
    "sg:city":"Myrtle Beach",
    "sg:classifiers":[
        {
            "category":"Shopping",
            "subcategory":"Books",
            "type":"Retail Goods"
        }
    ],
    "sg:phone":"+1 843 272 2607",
    "sg:postcode":"29572",
    "sg:province":"SC",
    "sg:tags":[
        "used",
        "merchandise"
    ],
    "wof:name":"Bookstall",
    "wof:placetype":"venue"
},
  "geometry": {"coordinates":[-78.744788,33.797053],"type":"Point"}
}