{
  "type": "Feature",
  "properties": {
    "addr:full":"1023 S Pendleton St Easley SC 29642",
    "addr:housenumber":"1023",
    "addr:postcode":"29642",
    "addr:street":"S Pendleton St",
    "iso:country":"US",
    "sg:address":"1023 S Pendleton St",
    "sg:city":"Easley",
    "sg:classifiers":[
        {
            "category":"Deli",
            "type":"Food & Drink"
        }
    ],
    "sg:menulink":"http://www.allmenus.com/sc/easley/126594-blimpie-subs--sandwiches/menu/",
    "sg:phone":"+1 864 859 9552",
    "sg:postcode":"29642",
    "sg:province":"SC",
    "sg:tags":[
        "wrap",
        "american",
        "sandwich"
    ],
    "wof:name":"Blimpie Subs & Sandwiches",
    "wof:placetype":"venue"
},
  "geometry": {"coordinates":[-82.601758,34.814738],"type":"Point"}
}