{
  "type": "Feature",
  "properties": {
    "iso:country":"US",
    "sg:address":"715 Church St",
    "sg:city":"Central",
    "sg:classifiers":[
        {
            "category":"Restaurant",
            "type":"Food & Drink"
        }
    ],
    "sg:menulink":"http://www.allmenus.com/sc/central/283956-jerrys-pizza/menu/",
    "sg:phone":"+1 864 639 0101",
    "sg:postcode":"29630",
    "sg:province":"SC",
    "sg:tags":[
        "american",
        "pizza"
    ],
    "wof:name":"Jerry's Pizza",
    "wof:placetype":"venue"
},
  "geometry": {"coordinates":[-82.778417,34.719705],"type":"Point"}
}