{
  "type": "Feature",
  "properties": {
    "addr:full":"17 Hillshire Ct Aiken SC 29803",
    "addr:housenumber":"17",
    "addr:postcode":"29803",
    "addr:street":"Hillshire Ct",
    "iso:country":"US",
    "sg:address":"17 Hillshire Ct",
    "sg:city":"Aiken",
    "sg:classifiers":[
        {
            "category":"Professional",
            "subcategory":"Management & Consulting",
            "type":"Services"
        }
    ],
    "sg:phone":"+1 803 649 6976",
    "sg:postcode":"29803",
    "sg:province":"SC",
    "sg:tags":[
        "marketing",
        "consultant"
    ],
    "wof:name":"Market America",
    "wof:placetype":"venue"
},
  "geometry": {"coordinates":[-81.767708,33.485533],"type":"Point"}
}