{
  "type": "Feature",
  "properties": {
    "iso:country":"US",
    "sg:address":"24 N Sweetbriar Ln",
    "sg:city":"Columbia",
    "sg:classifiers":[
        {
            "category":"Real Estate",
            "subcategory":"Real Estate Agent",
            "type":"Services"
        }
    ],
    "sg:phone":"+1 803 462 0606",
    "sg:postcode":"29223",
    "sg:province":"SC",
    "sg:tags":[
        "agency",
        "rental"
    ],
    "wof:name":"Express Rentals",
    "wof:placetype":"venue"
},
  "geometry": {"coordinates":[-80.88783,34.092408],"type":"Point"}
}