{
  "type": "Feature",
  "properties": {
    "iso:country":"US",
    "sg:address":"517 S Pleasantburg Dr",
    "sg:city":"Greenville",
    "sg:classifiers":[
        {
            "category":"Shopping",
            "subcategory":"Clothing, Apparel, & Fashions",
            "type":"Retail Goods"
        }
    ],
    "sg:phone":"+1 864 271 0073",
    "sg:postcode":"29607",
    "sg:province":"SC",
    "sg:tags":[
        "nurse",
        "supply"
    ],
    "wof:name":"Uniform Advantage",
    "wof:placetype":"venue"
},
  "geometry": {"coordinates":[-82.370063,34.828398],"type":"Point"}
}