{
  "type": "Feature",
  "properties": {
    "iso:country":"US",
    "sg:address":"220 Farrs Rd",
    "sg:city":"Easley",
    "sg:classifiers":[
        {
            "category":"Retail",
            "subcategory":"Portrait Studio",
            "type":"Services"
        }
    ],
    "sg:phone":"+1 864 859 7711",
    "sg:postcode":"29640",
    "sg:province":"SC",
    "sg:tags":[
        "photographer"
    ],
    "wof:name":"Bill's Photography",
    "wof:placetype":"venue"
},
  "geometry": {"coordinates":[-82.559136,34.893046],"type":"Point"}
}