{
  "type": "Feature",
  "properties": {
    "iso:country":"US",
    "sg:address":"3131 N Main St",
    "sg:city":"Anderson",
    "sg:classifiers":[
        {
            "category":"Personal",
            "type":"Services"
        }
    ],
    "sg:phone":"+1 864 224 5412",
    "sg:postcode":"29621",
    "sg:province":"SC",
    "sg:tags":[
        "wear",
        "formal"
    ],
    "wof:name":"Gregory's Formal Wear For Men",
    "wof:placetype":"venue"
},
  "geometry": {"coordinates":[-82.66766699999999,34.539113],"type":"Point"}
}