{
  "type": "Feature",
  "properties": {
    "iso:country":"US",
    "sg:address":"2006 Rockland Rd",
    "sg:city":"Columbia",
    "sg:classifiers":[
        {
            "category":"Personal",
            "type":"Services"
        }
    ],
    "sg:phone":"+1 803 731 7775",
    "sg:postcode":"29210",
    "sg:province":"SC",
    "sg:tags":[
        "mover"
    ],
    "wof:name":"Two Men and A Truck-Greater Columbia Inc",
    "wof:placetype":"venue"
},
  "geometry": {"coordinates":[-81.116302,34.033901],"type":"Point"}
}