{
  "type": "Feature",
  "properties": {
    "addr:full":"300 Monticello Rd Columbia SC 29203",
    "addr:housenumber":"300",
    "addr:postcode":"29203",
    "addr:street":"Monticello Rd",
    "iso:country":"US",
    "sg:address":"300 Monticello Rd",
    "sg:city":"Columbia",
    "sg:classifiers":[
        {
            "category":"Building & Trades",
            "subcategory":"Construction",
            "type":"Services"
        }
    ],
    "sg:phone":"+1 803 786 9609",
    "sg:postcode":"29203",
    "sg:province":"SC",
    "sg:tags":[
        "general",
        "contractor"
    ],
    "wof:name":"REA Contracting",
    "wof:placetype":"venue"
},
  "geometry": {"coordinates":[-81.069384,34.081293],"type":"Point"}
}