{
  "type": "Feature",
  "properties": {
    "iso:country":"US",
    "sg:address":"3006 E North St",
    "sg:city":"Greenville",
    "sg:classifiers":[
        {
            "category":"Autos & Motor Vehicles",
            "subcategory":"Fuel & Gas Station",
            "type":"Retail Goods"
        }
    ],
    "sg:phone":"+1 864 244 0843",
    "sg:postcode":"29615",
    "sg:province":"SC",
    "sg:tags":[
        "station",
        "gasoline"
    ],
    "wof:name":"Butch Taylor Phillips 66",
    "wof:placetype":"venue"
},
  "geometry": {"coordinates":[-82.341346,34.8713],"type":"Point"}
}