{
  "type": "Feature",
  "properties": {
    "iso:country":"US",
    "sg:address":"19 Eastpine Ct",
    "sg:city":"Columbia",
    "sg:classifiers":[
        {
            "category":"Professional",
            "subcategory":"Management & Consulting",
            "type":"Services"
        }
    ],
    "sg:phone":"+1 803 781 5934",
    "sg:postcode":"29212",
    "sg:province":"SC",
    "sg:tags":[
        "consultant"
    ],
    "wof:name":"Health Ed Consults Inc",
    "wof:placetype":"venue"
},
  "geometry": {"coordinates":[-81.142439,34.083117],"type":"Point"}
}