{
  "type": "Feature",
  "properties": {
    "addr:full":"3927 Cripple Creek Rd Greer SC 29651",
    "addr:housenumber":"3927",
    "addr:postcode":"29651",
    "addr:street":"Cripple Creek Rd",
    "iso:country":"US",
    "sg:address":"3927 Cripple Creek Rd",
    "sg:city":"Greer",
    "sg:classifiers":[
        {
            "category":"Retail",
            "subcategory":"Animal Services",
            "type":"Services"
        }
    ],
    "sg:phone":"+1 864 895 5355",
    "sg:postcode":"29651",
    "sg:province":"SC",
    "sg:tags":[
        "training",
        "dog"
    ],
    "wof:name":"Upstate Dog Training & Pet",
    "wof:placetype":"venue"
},
  "geometry": {"coordinates":[-82.255321,35.022466],"type":"Point"}
}