{
  "type": "Feature",
  "properties": {
    "addr:full":"3824 Ladson Rd Ladson SC 29456",
    "addr:housenumber":"3824",
    "addr:postcode":"29456",
    "addr:street":"Ladson Rd",
    "iso:country":"US",
    "sg:address":"3824 Ladson Rd",
    "sg:city":"Ladson",
    "sg:classifiers":[
        {
            "category":"Home & Garden",
            "subcategory":"Carpets & Floor Coverings",
            "type":"Retail Goods"
        }
    ],
    "sg:phone":"+1 843 851 0026",
    "sg:postcode":"29456",
    "sg:province":"SC",
    "sg:tags":[
        "material"
    ],
    "sg:website":"www.woodboys.com",
    "wof:name":"Woodboys-Wood Floors",
    "wof:placetype":"venue"
},
  "geometry": {"coordinates":[-80.13505600000001,32.976072],"type":"Point"}
}