{
  "type": "Feature",
  "properties": {
    "addr:full":"229 Craig Manor Rd Lancaster SC 29720",
    "addr:housenumber":"229",
    "addr:postcode":"29720",
    "addr:street":"Craig Manor Rd",
    "iso:country":"US",
    "sg:address":"229 Craig Manor Rd",
    "sg:city":"Lancaster",
    "sg:classifiers":[
        {
            "category":"Utilities",
            "subcategory":"Electric",
            "type":"Services"
        }
    ],
    "sg:phone":"+1 803 283 5230",
    "sg:postcode":"29720",
    "sg:province":"SC",
    "wof:name":"Duke Power",
    "wof:placetype":"venue"
},
  "geometry": {"coordinates":[-80.774011,34.747819],"type":"Point"}
}