{
  "type": "Feature",
  "properties": {
    "iso:country":"US",
    "sg:address":"1408 Boonehill Rd",
    "sg:city":"Summerville",
    "sg:classifiers":[
        {
            "category":"Autos & Motor Vehicles",
            "subcategory":"Auto Supplies",
            "type":"Retail Goods"
        }
    ],
    "sg:phone":"+1 843 871 0001",
    "sg:postcode":"29483",
    "sg:province":"SC",
    "sg:tags":[
        "home",
        "store"
    ],
    "wof:name":"Advance Auto Parts",
    "wof:placetype":"venue"
},
  "geometry": {"coordinates":[-80.22244000000001,32.991084],"type":"Point"}
}