{
  "type": "Feature",
  "properties": {
    "iso:country":"US",
    "sg:address":"905 N Pearl St",
    "sg:city":"Pageland",
    "sg:classifiers":[
        {
            "category":"Health Services",
            "subcategory":"Doctor",
            "type":"Services"
        }
    ],
    "sg:phone":"+1 843 672 3100",
    "sg:postcode":"29728",
    "sg:province":"SC",
    "sg:tags":[
        "physician",
        "surgeon"
    ],
    "wof:name":"Ameri Care Health Family Med",
    "wof:placetype":"venue"
},
  "geometry": {"coordinates":[-80.397162,34.785233],"type":"Point"}
}