{
  "type": "Feature",
  "properties": {
    "iso:country":"US",
    "sg:address":"467 Harvest Moon Dr",
    "sg:city":"Georgetown",
    "sg:classifiers":[
        {
            "category":"Home & Garden",
            "subcategory":"Garden Supply",
            "type":"Retail Goods"
        }
    ],
    "sg:phone":"+1 843 527 6767",
    "sg:postcode":"29440",
    "sg:province":"SC",
    "sg:tags":[
        "sprinkler"
    ],
    "wof:name":"Coastal Waterworks",
    "wof:placetype":"venue"
},
  "geometry": {"coordinates":[-79.297634,33.272683],"type":"Point"}
}