{
  "type": "Feature",
  "properties": {
    "addr:full":"744 Dexter Ln Conway SC 29526",
    "addr:housenumber":"744",
    "addr:postcode":"29526",
    "addr:street":"Dexter Ln",
    "iso:country":"US",
    "sg:address":"744 Dexter Ln",
    "sg:city":"Conway",
    "sg:classifiers":[
        {
            "category":"Retail",
            "subcategory":"Repair Shop",
            "type":"Services"
        }
    ],
    "sg:phone":"+1 843 236 4576",
    "sg:postcode":"29526",
    "sg:province":"SC",
    "sg:tags":[
        "pressure",
        "washing"
    ],
    "wof:name":"Longbay Cleaning Systems",
    "wof:placetype":"venue"
},
  "geometry": {"coordinates":[-78.923102,33.912601],"type":"Point"}
}