{
  "type": "Feature",
  "properties": {
    "iso:country":"US",
    "sg:address":"201 S Kings Hwy",
    "sg:city":"Myrtle Beach",
    "sg:classifiers":[
        {
            "category":"Restaurant",
            "type":"Food & Drink"
        }
    ],
    "sg:phone":"+1 843 448 8044",
    "sg:postcode":"29577",
    "sg:province":"SC",
    "wof:name":"Country Kitchen",
    "wof:placetype":"venue"
},
  "geometry": {"coordinates":[-78.891076,33.685286],"type":"Point"}
}