{
  "type": "Feature",
  "properties": {
    "addr:full":"123 Medical Cir West Columbia SC 29169",
    "addr:housenumber":"123",
    "addr:postcode":"29169",
    "addr:street":"Medical Cir",
    "iso:country":"US",
    "sg:address":"123 Medical Cir",
    "sg:city":"West Columbia",
    "sg:classifiers":[
        {
            "category":"Health Services",
            "subcategory":"Health Practitioner",
            "type":"Services"
        }
    ],
    "sg:phone":"+1 803 791 2155",
    "sg:postcode":"29169",
    "sg:province":"SC",
    "sg:tags":[
        "therapist",
        "physical"
    ],
    "wof:name":"Lexington Medical Ctr Physical",
    "wof:placetype":"venue"
},
  "geometry": {"coordinates":[-81.11253000000001,34.003572],"type":"Point"}
}