{
  "type": "Feature",
  "properties": {
    "addr:full":"4609 Charlotte Hwy Lake Wylie SC 29710",
    "addr:housenumber":"4609",
    "addr:postcode":"29710",
    "addr:street":"Charlotte Hwy Lake",
    "iso:country":"US",
    "sg:address":"4609 Charlotte Hwy",
    "sg:city":"Lake Wylie",
    "sg:classifiers":[
        {
            "category":"Professional",
            "subcategory":"Lawyer & Legal Services",
            "type":"Services"
        }
    ],
    "sg:phone":"+1 803 831 2738",
    "sg:postcode":"29710",
    "sg:province":"SC",
    "sg:tags":[
        "attorney"
    ],
    "wof:name":"Haselden Owen & Boloyan",
    "wof:placetype":"venue"
},
  "geometry": {"coordinates":[-81.109602,35.076265],"type":"Point"}
}