{
  "type": "Feature",
  "properties": {
    "iso:country":"US",
    "sg:address":"800 Stonewyck Dr",
    "sg:city":"Simpsonville",
    "sg:classifiers":[
        {
            "category":"Building & Trades",
            "subcategory":"Construction",
            "type":"Services"
        }
    ],
    "sg:phone":"+1 864 284 6106",
    "sg:postcode":"29681",
    "sg:province":"SC",
    "sg:tags":[
        "home",
        "builder"
    ],
    "wof:name":"Ryan Homes Stonewyck",
    "wof:placetype":"venue"
},
  "geometry": {"coordinates":[-82.257455,34.801261],"type":"Point"}
}