{
  "type": "Feature",
  "properties": {
    "iso:country":"US",
    "sg:address":"1251 Boiling Springs Rd",
    "sg:city":"Spartanburg",
    "sg:classifiers":[
        {
            "category":"Shopping",
            "subcategory":"Clothing, Apparel, & Fashions",
            "type":"Retail Goods"
        }
    ],
    "sg:phone":"+1 864 573 1484",
    "sg:postcode":"29303",
    "sg:province":"SC",
    "sg:tags":[
        "uniform"
    ],
    "wof:name":"Simply Uniforms",
    "wof:placetype":"venue"
},
  "geometry": {"coordinates":[-81.946459,34.988085],"type":"Point"}
}