{
  "type": "Feature",
  "properties": {
    "addr:full":"7244 Patterson Rd Columbia SC 29209",
    "addr:housenumber":"7244",
    "addr:postcode":"29209",
    "addr:street":"Patterson Rd",
    "iso:country":"US",
    "sg:address":"7244 Patterson Rd",
    "sg:city":"Columbia",
    "sg:classifiers":[
        {
            "category":"Organizations",
            "subcategory":"Religious Organization",
            "type":"Services"
        }
    ],
    "sg:phone":"+1 803 776 1864",
    "sg:postcode":"29209",
    "sg:province":"SC",
    "sg:tags":[
        "church"
    ],
    "wof:name":"Church Of The Cross",
    "wof:placetype":"venue"
},
  "geometry": {"coordinates":[-80.93713099999999,33.97087],"type":"Point"}
}