{
  "type": "Feature",
  "properties": {
    "iso:country":"US",
    "sg:address":"1233 Savannah Hwy",
    "sg:city":"Charleston",
    "sg:classifiers":[
        {
            "category":"Travel",
            "subcategory":"Hotels & Motels",
            "type":"Entertainment"
        }
    ],
    "sg:phone":"+1 843 573 1200",
    "sg:postcode":"29407",
    "sg:province":"SC",
    "wof:name":"Hampton Inn",
    "wof:placetype":"venue"
},
  "geometry": {"coordinates":[-79.99912999999999,32.784279],"type":"Point"}
}