{
  "type": "Feature",
  "properties": {
    "addr:full":"151 Ole Woodward Ave Conway SC 29526",
    "addr:housenumber":"151",
    "addr:postcode":"29526",
    "addr:street":"Ole Woodward Ave",
    "iso:country":"US",
    "sg:address":"151 Ole Woodward Ave",
    "sg:city":"Conway",
    "sg:classifiers":[
        {
            "category":"Building & Trades",
            "subcategory":"Construction",
            "type":"Services"
        }
    ],
    "sg:phone":"+1 843 347 4224",
    "sg:postcode":"29526",
    "sg:province":"SC",
    "sg:tags":[
        "contractor"
    ],
    "wof:name":"Builders First Source",
    "wof:placetype":"venue"
},
  "geometry": {"coordinates":[-79.014132,33.813709],"type":"Point"}
}