{
  "type": "Feature",
  "properties": {
    "addr:full":"286 Aviation Blvd Lancaster SC 29720",
    "addr:housenumber":"286",
    "addr:postcode":"29720",
    "addr:street":"Aviation Blvd",
    "iso:country":"US",
    "sg:address":"286 Aviation Blvd",
    "sg:city":"Lancaster",
    "sg:classifiers":[
        {
            "category":"Retail",
            "subcategory":"Repair Shop",
            "type":"Services"
        }
    ],
    "sg:phone":"+1 803 283 2099",
    "sg:postcode":"29720",
    "sg:province":"SC",
    "wof:name":"Carolina Aero Service",
    "wof:placetype":"venue"
},
  "geometry": {"coordinates":[-80.85658599999999,34.713214],"type":"Point"}
}