{
  "type": "Feature",
  "properties": {
    "addr:full":"946 Orleans Rd Charleston SC 29407",
    "addr:housenumber":"946",
    "addr:postcode":"29407",
    "addr:street":"Orleans Rd",
    "iso:country":"US",
    "sg:address":"946 Orleans Rd",
    "sg:city":"Charleston",
    "sg:classifiers":[
        {
            "category":"Professional",
            "subcategory":"Business Services",
            "type":"Services"
        }
    ],
    "sg:phone":"+1 843 763 9240",
    "sg:postcode":"29407",
    "sg:province":"SC",
    "sg:tags":[
        "water",
        "treatment"
    ],
    "wof:name":"Southeastern Equipment & Svc",
    "wof:placetype":"venue"
},
  "geometry": {"coordinates":[-80.028561,32.798206],"type":"Point"}
}