{
  "type": "Feature",
  "properties": {
    "iso:country":"US",
    "sg:address":"716 Bultman Dr",
    "sg:city":"Sumter",
    "sg:classifiers":[
        {
            "category":"Personal",
            "subcategory":"Beauty Salon",
            "type":"Services"
        }
    ],
    "sg:phone":"+1 803 418 5072",
    "sg:postcode":"29150",
    "sg:province":"SC",
    "wof:name":"Izola's Hair Care",
    "wof:placetype":"venue"
},
  "geometry": {"coordinates":[-80.372626,33.943953],"type":"Point"}
}