{
  "type": "Feature",
  "properties": {
    "addr:full":"102 Metro Dr Spartanburg SC 29303",
    "addr:housenumber":"102",
    "addr:postcode":"29303",
    "addr:street":"Metro Dr",
    "iso:country":"US",
    "sg:address":"102 Metro Dr",
    "sg:city":"Spartanburg",
    "sg:classifiers":[
        {
            "category":"Building & Trades",
            "subcategory":"Construction",
            "type":"Services"
        }
    ],
    "sg:phone":"+1 864 583 1090",
    "sg:postcode":"29303",
    "sg:province":"SC",
    "sg:tags":[
        "home",
        "builder"
    ],
    "wof:name":"Autorino Construction Inc",
    "wof:placetype":"venue"
},
  "geometry": {"coordinates":[-81.94801200000001,34.977185],"type":"Point"}
}