{
  "type": "Feature",
  "properties": {
    "iso:country":"US",
    "sg:address":"420 W Milestone Rd",
    "sg:city":"Florence",
    "sg:classifiers":[
        {
            "category":"Real Estate",
            "subcategory":"Real Estate Agent",
            "type":"Services"
        }
    ],
    "sg:phone":"+1 843 669 4252",
    "sg:postcode":"29505",
    "sg:province":"SC",
    "wof:name":"Rdl Properties LLC",
    "wof:placetype":"venue"
},
  "geometry": {"coordinates":[-79.774877,34.141045],"type":"Point"}
}