{
  "type": "Feature",
  "properties": {
    "iso:country":"US",
    "sg:address":"109 Southwest Dr",
    "sg:city":"Spartanburg",
    "sg:classifiers":[
        {
            "category":"Wholesale",
            "subcategory":"Durable Goods & Equipment",
            "type":"Manufacturing & Wholesale Goods"
        }
    ],
    "sg:phone":"+1 864 595 9930",
    "sg:postcode":"29303",
    "sg:province":"SC",
    "sg:tags":[
        "importer"
    ],
    "wof:name":"A & R Trading Co",
    "wof:placetype":"venue"
},
  "geometry": {"coordinates":[-82.022899,34.96651],"type":"Point"}
}