{
  "type": "Feature",
  "properties": {
    "addr:full":"185 Ridgeland Dr Six Mile SC 29682",
    "addr:housenumber":"185",
    "addr:postcode":"29682",
    "addr:street":"Ridgeland Dr",
    "iso:country":"US",
    "sg:address":"185 Ridgeland Dr",
    "sg:city":"Six Mile",
    "sg:classifiers":[
        {
            "category":"Organizations",
            "subcategory":"Religious Organization",
            "type":"Services"
        }
    ],
    "sg:phone":"+1 864 868 5050",
    "sg:postcode":"29682",
    "sg:province":"SC",
    "sg:tags":[
        "church"
    ],
    "wof:name":"Ridgland Drive Baptist Church",
    "wof:placetype":"venue"
},
  "geometry": {"coordinates":[-82.79689999999999,34.808359],"type":"Point"}
}