{
  "type": "Feature",
  "properties": {
    "iso:country":"US",
    "sg:address":"332 E Main St",
    "sg:city":"Spartanburg",
    "sg:classifiers":[
        {
            "category":"Manufacturing",
            "subcategory":"Furniture",
            "type":"Manufacturing & Wholesale Goods"
        }
    ],
    "sg:phone":"+1 864 591 0916",
    "sg:postcode":"29306",
    "sg:province":"SC",
    "sg:tags":[
        "repair",
        "drapery",
        "reupholster",
        "mfg"
    ],
    "wof:name":"American Upholstery & Blinds",
    "wof:placetype":"venue"
},
  "geometry": {"coordinates":[-81.923974,34.951376],"type":"Point"}
}