{
  "type": "Feature",
  "properties": {
    "addr:full":"2650 W Palmetto St Florence SC 29501",
    "addr:housenumber":"2650",
    "addr:postcode":"29501",
    "addr:street":"W Palmetto St",
    "iso:country":"US",
    "sg:address":"2650 W Palmetto St",
    "sg:city":"Florence",
    "sg:classifiers":[
        {
            "category":"Shopping",
            "subcategory":"Discount & Variety Stores",
            "type":"Retail Goods"
        }
    ],
    "sg:phone":"+1 843 673 9988",
    "sg:postcode":"29501",
    "sg:province":"SC",
    "wof:name":"Buck-A-Roos Dollar Store",
    "wof:placetype":"venue"
},
  "geometry": {"coordinates":[-79.82731,34.177855],"type":"Point"}
}