{
  "type": "Feature",
  "properties": {
    "iso:country":"US",
    "sg:address":"101 E Main St",
    "sg:city":"Latta",
    "sg:classifiers":[
        {
            "category":"Shopping",
            "subcategory":"Jewelry",
            "type":"Retail Goods"
        }
    ],
    "sg:phone":"+1 843 752 5625",
    "sg:postcode":"29565",
    "sg:province":"SC",
    "sg:tags":[
        "clocks"
    ],
    "wof:name":"Treasures From The Attic",
    "wof:placetype":"venue"
},
  "geometry": {"coordinates":[-79.432372,34.337724],"type":"Point"}
}