{
  "type": "Feature",
  "properties": {
    "addr:full":"23 W Pine Cir Wagener SC 29164",
    "addr:housenumber":"23",
    "addr:postcode":"29164",
    "addr:street":"W Pine Cir",
    "iso:country":"US",
    "sg:address":"23 W Pine Cir",
    "sg:city":"Wagener",
    "sg:classifiers":[
        {
            "category":"Retail",
            "subcategory":"Auto Repair",
            "type":"Services"
        }
    ],
    "sg:phone":"+1 803 564 5326",
    "sg:postcode":"29164",
    "sg:province":"SC",
    "sg:tags":[
        "repairing",
        "automobile"
    ],
    "wof:name":"G & T Auto Repair",
    "wof:placetype":"venue"
},
  "geometry": {"coordinates":[-81.339821,33.631001],"type":"Point"}
}