{
  "type": "Feature",
  "properties": {
    "addr:full":"21 Carrie Dr Greenville SC 29615",
    "addr:housenumber":"21",
    "addr:postcode":"29615",
    "addr:street":"Carrie Dr",
    "iso:country":"US",
    "sg:address":"21 Carrie Dr",
    "sg:city":"Greenville",
    "sg:classifiers":[
        {
            "category":"Building & Trades",
            "subcategory":"Construction",
            "type":"Services"
        }
    ],
    "sg:phone":"+1 864 281 0930",
    "sg:postcode":"29615",
    "sg:province":"SC",
    "sg:tags":[
        "contractor"
    ],
    "wof:name":"McGee Brothers Co Inc",
    "wof:placetype":"venue"
},
  "geometry": {"coordinates":[-82.276168,34.838603],"type":"Point"}
}