{
  "type": "Feature",
  "properties": {
    "addr:full":"620 Giga Dr Rock Hill SC 29730",
    "addr:housenumber":"620",
    "addr:postcode":"29730",
    "addr:street":"Giga Dr",
    "iso:country":"US",
    "sg:address":"620 Giga Dr",
    "sg:city":"Rock Hill",
    "sg:classifiers":[
        {
            "category":"Building & Trades",
            "subcategory":"Landscaping Services",
            "type":"Services"
        }
    ],
    "sg:phone":"+1 803 328 5087",
    "sg:postcode":"29730",
    "sg:province":"SC",
    "wof:name":"AAA Tree Stump",
    "wof:placetype":"venue"
},
  "geometry": {"coordinates":[-81.01192399999999,34.928694],"type":"Point"}
}