{
  "type": "Feature",
  "properties": {
    "iso:country":"US",
    "sg:address":"811 Savannah Hwy",
    "sg:city":"Charleston",
    "sg:classifiers":[
        {
            "category":"Shopping",
            "subcategory":"Jewelry",
            "type":"Retail Goods"
        }
    ],
    "sg:phone":"+1 843 769 5995",
    "sg:postcode":"29407",
    "sg:province":"SC",
    "sg:tags":[
        "jeweler"
    ],
    "wof:name":"Gem & Goldsmith Shop",
    "wof:placetype":"venue"
},
  "geometry": {"coordinates":[-79.98548700000001,32.781957],"type":"Point"}
}