{
  "type": "Feature",
  "properties": {
    "addr:full":"213 Whitsett St Greenville SC 29601",
    "addr:housenumber":"213",
    "addr:postcode":"29601",
    "addr:street":"Whitsett St",
    "iso:country":"US",
    "sg:address":"213 Whitsett St",
    "sg:city":"Greenville",
    "sg:classifiers":[
        {
            "category":"Insurance",
            "subcategory":"Insurance Agent",
            "type":"Services"
        }
    ],
    "sg:phone":"+1 864 233 2551",
    "sg:postcode":"29601",
    "sg:province":"SC",
    "wof:name":"John K McCallum",
    "wof:placetype":"venue"
},
  "geometry": {"coordinates":[-82.384587,34.852245],"type":"Point"}
}