{
  "type": "Feature",
  "properties": {
    "addr:full":"203 Anderson St Belton SC 29627",
    "addr:housenumber":"203",
    "addr:postcode":"29627",
    "addr:street":"Anderson St",
    "iso:country":"US",
    "sg:address":"203 Anderson St",
    "sg:city":"Belton",
    "sg:classifiers":[
        {
            "category":"Autos & Motor Vehicles",
            "subcategory":"Auto Supplies",
            "type":"Retail Goods"
        }
    ],
    "sg:phone":"+1 864 338 8952",
    "sg:postcode":"29627",
    "sg:province":"SC",
    "wof:name":"Belton Tire Service Inc",
    "wof:placetype":"venue"
},
  "geometry": {"coordinates":[-82.49497,34.521817],"type":"Point"}
}