{
  "type": "Feature",
  "properties": {
    "addr:full":"155 Johnston St Rock Hill SC 29730",
    "addr:housenumber":"155",
    "addr:postcode":"29730",
    "addr:street":"Johnston St",
    "iso:country":"US",
    "sg:address":"155 Johnston St",
    "sg:city":"Rock Hill",
    "sg:classifiers":[
        {
            "category":"Government",
            "subcategory":"Office",
            "type":"Public Place"
        }
    ],
    "sg:phone":"+1 803 329 7234",
    "sg:postcode":"29730",
    "sg:province":"SC",
    "sg:tags":[
        "village"
    ],
    "wof:name":"Video Production",
    "wof:placetype":"venue"
},
  "geometry": {"coordinates":[-81.02852799999999,34.923101],"type":"Point"}
}