{
  "type": "Feature",
  "properties": {
    "addr:full":"1537 Ashley River Rd Charleston SC 29407",
    "addr:housenumber":"1537",
    "addr:postcode":"29407",
    "addr:street":"Ashley River Rd",
    "iso:country":"US",
    "sg:address":"1537 Ashley River Rd",
    "sg:city":"Charleston",
    "sg:classifiers":[
        {
            "category":"Building & Trades",
            "subcategory":"Construction",
            "type":"Services"
        }
    ],
    "sg:phone":"+1 843 766 2363",
    "sg:postcode":"29407",
    "sg:province":"SC",
    "sg:tags":[
        "paving",
        "contractor"
    ],
    "wof:name":"Landscape Pavers LLC",
    "wof:placetype":"venue"
},
  "geometry": {"coordinates":[-80.008043,32.799027],"type":"Point"}
}