{
  "type": "Feature",
  "properties": {
    "iso:country":"US",
    "sg:address":"3812 Liberty Hwy",
    "sg:city":"Anderson",
    "sg:classifiers":[
        {
            "category":"Restaurant",
            "type":"Food & Drink"
        }
    ],
    "sg:menulink":"http://www.allmenus.com/sc/anderson/129312-subway/menu/",
    "sg:phone":"+1 864 222 8080",
    "sg:postcode":"29621",
    "sg:province":"SC",
    "sg:tags":[
        "american",
        "sandwich"
    ],
    "wof:name":"Subway",
    "wof:placetype":"venue"
},
  "geometry": {"coordinates":[-82.680459,34.55423],"type":"Point"}
}