{
  "type": "Feature",
  "properties": {
    "iso:country":"US",
    "sg:address":"416 Vista Dr",
    "sg:city":"Murrells Inlet",
    "sg:classifiers":[
        {
            "category":"Manufacturing",
            "subcategory":"Tools & Machinery",
            "type":"Manufacturing & Wholesale Goods"
        }
    ],
    "sg:phone":"+1 843 357 0784",
    "sg:postcode":"29576",
    "sg:province":"SC",
    "sg:tags":[
        "mfg"
    ],
    "wof:name":"Nu-TEC Products Inc",
    "wof:placetype":"venue"
},
  "geometry": {"coordinates":[-78.99787000000001,33.592575],"type":"Point"}
}