{
  "type": "Feature",
  "properties": {
    "iso:country":"US",
    "sg:address":"2104 Raven Trl",
    "sg:city":"West Columbia",
    "sg:classifiers":[
        {
            "category":"Retail",
            "subcategory":"Portrait Studio",
            "type":"Services"
        }
    ],
    "sg:phone":"+1 803 791 7482",
    "sg:postcode":"29169",
    "sg:province":"SC",
    "sg:tags":[
        "photographer"
    ],
    "wof:name":"Dominick's Photography",
    "wof:placetype":"venue"
},
  "geometry": {"coordinates":[-81.125168,34.015943],"type":"Point"}
}