{
  "type": "Feature",
  "properties": {
    "iso:country":"US",
    "sg:address":"1304 Chapin Rd",
    "sg:city":"Chapin",
    "sg:classifiers":[
        {
            "category":"Home & Garden",
            "subcategory":"Hardware",
            "type":"Retail Goods"
        }
    ],
    "sg:phone":"+1 803 345 1336",
    "sg:postcode":"29036",
    "sg:province":"SC",
    "sg:website":"www.truevalue.com",
    "wof:name":"Boland's True Value Hardware",
    "wof:placetype":"venue"
},
  "geometry": {"coordinates":[-81.358062,34.167706],"type":"Point"}
}