{
  "type": "Feature",
  "properties": {
    "iso:country":"US",
    "sg:address":"203 N Herndon St",
    "sg:city":"Union",
    "sg:classifiers":[
        {
            "category":"Government",
            "subcategory":"Office",
            "type":"Public Place"
        }
    ],
    "sg:phone":"+1 864 429 1650",
    "sg:postcode":"29379",
    "sg:province":"SC",
    "sg:tags":[
        "county",
        "taxation"
    ],
    "wof:name":"Union County Tax Assessor",
    "wof:placetype":"venue"
},
  "geometry": {"coordinates":[-81.62517800000001,34.7162],"type":"Point"}
}