{
  "type": "Feature",
  "properties": {
    "iso:country":"US",
    "sg:address":"11075 Watson Dr",
    "sg:city":"Seneca",
    "sg:classifiers":[
        {
            "category":"Organizations",
            "subcategory":"Religious Organization",
            "type":"Services"
        }
    ],
    "sg:phone":"+1 864 882 8546",
    "sg:postcode":"29672",
    "sg:province":"SC",
    "sg:tags":[
        "church"
    ],
    "sg:website":"www.unitedassembly.com",
    "wof:name":"United Assembly Of God",
    "wof:placetype":"venue"
},
  "geometry": {"coordinates":[-82.917249,34.702046],"type":"Point"}
}