{
  "type": "Feature",
  "properties": {
    "iso:country":"US",
    "sg:address":"407 Red Bluff Rd",
    "sg:city":"Loris",
    "sg:classifiers":[
        {
            "category":"Organizations",
            "subcategory":"Religious Organization",
            "type":"Services"
        }
    ],
    "sg:phone":"+1 843 716 1463",
    "sg:postcode":"29569",
    "sg:province":"SC",
    "sg:tags":[
        "church"
    ],
    "wof:name":"Wayside Baptist Church",
    "wof:placetype":"venue"
},
  "geometry": {"coordinates":[-78.887711,34.04628],"type":"Point"}
}