{
  "type": "Feature",
  "properties": {
    "iso:country":"US",
    "sg:address":"2386 Chesnee Hwy",
    "sg:city":"Gaffney",
    "sg:classifiers":[
        {
            "category":"Building & Trades",
            "subcategory":"Construction",
            "type":"Services"
        }
    ],
    "sg:phone":"+1 864 489 5201",
    "sg:postcode":"29341",
    "sg:province":"SC",
    "sg:tags":[
        "roofing",
        "contractor"
    ],
    "wof:name":"Martin Hubert Roofing",
    "wof:placetype":"venue"
},
  "geometry": {"coordinates":[-81.82098000000001,35.143027],"type":"Point"}
}