{
  "type": "Feature",
  "properties": {
    "iso:country":"US",
    "sg:address":"208 W McGregor St",
    "sg:city":"Pageland",
    "sg:phone":"+1 843 672 7037",
    "sg:postcode":"29728",
    "sg:province":"SC",
    "sg:tags":[
        "oil"
    ],
    "wof:name":"Clark Gas & Oil Co",
    "wof:placetype":"venue"
},
  "geometry": {"coordinates":[-80.392771,34.771678],"type":"Point"}
}