{
  "type": "Feature",
  "properties": {
    "iso:country":"US",
    "sg:address":"75 W Wesmark Blvd",
    "sg:city":"Sumter",
    "sg:classifiers":[
        {
            "category":"Shopping",
            "subcategory":"Gifts & Souvenirs",
            "type":"Retail Goods"
        }
    ],
    "sg:phone":"+1 803 905 5570",
    "sg:postcode":"29150",
    "sg:province":"SC",
    "sg:tags":[
        "shop"
    ],
    "wof:name":"Doolallies LLC",
    "wof:placetype":"venue"
},
  "geometry": {"coordinates":[-80.38045,33.950985],"type":"Point"}
}