{
  "type": "Feature",
  "properties": {
    "iso:country":"US",
    "sg:address":"110 Sparkman Dr",
    "sg:city":"Columbia",
    "sg:classifiers":[
        {
            "category":"Wholesale",
            "subcategory":"Electrical",
            "type":"Manufacturing & Wholesale Goods"
        }
    ],
    "sg:phone":"+1 803 647 1384",
    "sg:postcode":"29209",
    "sg:province":"SC",
    "wof:name":"On Time Services Inc",
    "wof:placetype":"venue"
},
  "geometry": {"coordinates":[-80.968053,33.943934],"type":"Point"}
}