{
  "type": "Feature",
  "properties": {
    "iso:country":"US",
    "sg:address":"320 E Boyce St",
    "sg:city":"Manning",
    "sg:classifiers":[
        {
            "category":"Government",
            "subcategory":"Jail",
            "type":"Public Place"
        }
    ],
    "sg:phone":"+1 803 435 8831",
    "sg:postcode":"29102",
    "sg:province":"SC",
    "sg:tags":[
        "county",
        "govt",
        "institution"
    ],
    "wof:name":"Clarendon County Correctional",
    "wof:placetype":"venue"
},
  "geometry": {"coordinates":[-80.204565,33.693429],"type":"Point"}
}