{
  "type": "Feature",
  "properties": {
    "iso:country":"US",
    "sg:address":"1121 Broad St",
    "sg:city":"Sumter",
    "sg:classifiers":[
        {
            "category":"Home & Garden",
            "subcategory":"Home Furnishings",
            "type":"Retail Goods"
        }
    ],
    "sg:phone":"+1 803 773 6224",
    "sg:postcode":"29150",
    "sg:province":"SC",
    "sg:tags":[
        "linen"
    ],
    "wof:name":"Plejs Linen Supermarket 78",
    "wof:placetype":"venue"
},
  "geometry": {"coordinates":[-80.378128,33.952971],"type":"Point"}
}