{
  "type": "Feature",
  "properties": {
    "addr:full":"1708 Main St Columbia SC 29201",
    "addr:housenumber":"1708",
    "addr:postcode":"29201",
    "addr:street":"Main St",
    "iso:country":"US",
    "sg:address":"1708 Main St",
    "sg:city":"Columbia",
    "sg:classifiers":[
        {
            "category":"Professional",
            "subcategory":"Lawyer & Legal Services",
            "type":"Services"
        }
    ],
    "sg:phone":"+1 803 252 7656",
    "sg:postcode":"29201",
    "sg:province":"SC",
    "sg:tags":[
        "attorney"
    ],
    "wof:name":"John B Shupper",
    "wof:placetype":"venue"
},
  "geometry": {"coordinates":[-81.036974,34.009205],"type":"Point"}
}