{
  "type": "Feature",
  "properties": {
    "iso:country":"US",
    "sg:address":"233 Applewood Center Pl",
    "sg:city":"Seneca",
    "sg:classifiers":[
        {
            "category":"Shopping",
            "subcategory":"Department Store",
            "type":"Retail Goods"
        }
    ],
    "sg:phone":"+1 864 888 2664",
    "sg:postcode":"29678",
    "sg:province":"SC",
    "sg:tags":[
        "shop",
        "merchandise"
    ],
    "sg:website":"http://www.dollartree.com/",
    "wof:name":"Dollar Tree",
    "wof:placetype":"venue"
},
  "geometry": {"coordinates":[-82.989052,34.690552],"type":"Point"}
}