{
  "type": "Feature",
  "properties": {
    "iso:country":"US",
    "sg:address":"606 W Main St",
    "sg:city":"Easley",
    "sg:classifiers":[
        {
            "category":"Retail",
            "subcategory":"Funeral Services",
            "type":"Services"
        }
    ],
    "sg:phone":"+1 864 859 5811",
    "sg:postcode":"29640",
    "sg:province":"SC",
    "sg:tags":[
        "director"
    ],
    "wof:name":"J C Moore Funeral Home",
    "wof:placetype":"venue"
},
  "geometry": {"coordinates":[-82.61272,34.829399],"type":"Point"}
}