{
  "type": "Feature",
  "properties": {
    "addr:full":"768 Travelers Blvd Summerville SC 29485",
    "addr:housenumber":"768",
    "addr:postcode":"29485",
    "addr:street":"Travelers Blvd",
    "iso:country":"US",
    "sg:address":"768 Travelers Blvd",
    "sg:city":"Summerville",
    "sg:classifiers":[
        {
            "category":"Real Estate",
            "subcategory":"Developer",
            "type":"Services"
        }
    ],
    "sg:phone":"+1 843 832 4378",
    "sg:postcode":"29485",
    "sg:province":"SC",
    "sg:website":"www.sunburstlakes.com",
    "wof:name":"Sunburst Properties Inc",
    "wof:placetype":"venue"
},
  "geometry": {"coordinates":[-80.168307,32.956019],"type":"Point"}
}