{
  "type": "Feature",
  "properties": {
    "iso:country":"US",
    "sg:address":"2098 Centerville Rd",
    "sg:city":"Anderson",
    "sg:classifiers":[
        {
            "category":"Food & Beverages",
            "subcategory":"Groceries & Convenience Stores",
            "type":"Retail Goods"
        }
    ],
    "sg:phone":"+1 864 224 2814",
    "sg:postcode":"29625",
    "sg:province":"SC",
    "sg:tags":[
        "grocer"
    ],
    "wof:name":"Surfside Store Inc",
    "wof:placetype":"venue"
},
  "geometry": {"coordinates":[-82.740165,34.535711],"type":"Point"}
}