{
  "type": "Feature",
  "properties": {
    "addr:full":"123 E Main St Lake City SC 29560",
    "addr:housenumber":"123",
    "addr:postcode":"29560",
    "addr:street":"E Main St",
    "iso:country":"US",
    "sg:address":"123 E Main St",
    "sg:city":"Lake City",
    "sg:classifiers":[
        {
            "category":"Personal",
            "subcategory":"Beauty Salon",
            "type":"Services"
        }
    ],
    "sg:phone":"+1 843 374 3638",
    "sg:postcode":"29560",
    "sg:province":"SC",
    "wof:name":"Brenda's Beauty Supply",
    "wof:placetype":"venue"
},
  "geometry": {"coordinates":[-79.754396,33.872629],"type":"Point"}
}