{
  "type": "Feature",
  "properties": {
    "iso:country":"US",
    "sg:address":"136 Park Ave",
    "sg:city":"Walterboro",
    "sg:classifiers":[
        {
            "category":"Health Services",
            "subcategory":"Doctor",
            "type":"Services"
        }
    ],
    "sg:phone":"+1 843 549 2479",
    "sg:postcode":"29488",
    "sg:province":"SC",
    "sg:tags":[
        "physician",
        "surgeon"
    ],
    "wof:name":"Walterboro Orthopaedic",
    "wof:placetype":"venue"
},
  "geometry": {"coordinates":[-80.655157,32.908518],"type":"Point"}
}