{
  "type": "Feature",
  "properties": {
    "iso:country":"US",
    "sg:address":"69 Edith Dr",
    "sg:city":"Taylors",
    "sg:classifiers":[
        {
            "category":"Professional",
            "subcategory":"Management & Consulting",
            "type":"Services"
        }
    ],
    "sg:phone":"+1 864 879 0777",
    "sg:postcode":"29687",
    "sg:province":"SC",
    "sg:tags":[
        "marketing",
        "program"
    ],
    "wof:name":"Professional Financial Dev",
    "wof:placetype":"venue"
},
  "geometry": {"coordinates":[-82.317133,34.972453],"type":"Point"}
}