{
  "type": "Feature",
  "properties": {
    "addr:full":"141 Oakland Ave Rock Hill SC 29730",
    "addr:housenumber":"141",
    "addr:postcode":"29730",
    "addr:street":"Oakland Ave",
    "iso:country":"US",
    "sg:address":"141 Oakland Ave",
    "sg:city":"Rock Hill",
    "sg:classifiers":[
        {
            "category":"Building & Trades",
            "subcategory":"Construction",
            "type":"Services"
        }
    ],
    "sg:phone":"+1 803 328 6231",
    "sg:postcode":"29730",
    "sg:province":"SC",
    "sg:tags":[
        "painter"
    ],
    "wof:name":"SA-J Inc",
    "wof:placetype":"venue"
},
  "geometry": {"coordinates":[-81.02475699999999,34.93117],"type":"Point"}
}