{
  "type": "Feature",
  "properties": {
    "iso:country":"US",
    "sg:address":"108 W Church St",
    "sg:city":"Greer",
    "sg:classifiers":[
        {
            "category":"Health Services",
            "subcategory":"Doctor",
            "type":"Services"
        }
    ],
    "sg:phone":"+1 864 801 9736",
    "sg:postcode":"29650",
    "sg:province":"SC",
    "sg:tags":[
        "physician",
        "surgeon"
    ],
    "wof:name":"Upstate Surgical Specialists",
    "wof:placetype":"venue"
},
  "geometry": {"coordinates":[-82.228571,34.940964],"type":"Point"}
}