{
  "type": "Feature",
  "properties": {
    "addr:full":"6460 Savannah Hwy Ravenel SC 29470",
    "addr:housenumber":"6460",
    "addr:postcode":"29470",
    "addr:street":"Savannah Hwy",
    "iso:country":"US",
    "sg:address":"6460 Savannah Hwy",
    "sg:city":"Ravenel",
    "sg:classifiers":[
        {
            "category":"Restaurant",
            "type":"Food & Drink"
        }
    ],
    "sg:phone":"+1 843 889 2448",
    "sg:postcode":"29470",
    "sg:province":"SC",
    "sg:tags":[
        "dist",
        "mfg",
        "ice",
        "freshly",
        "roasted",
        "cream"
    ],
    "wof:name":"Iccb",
    "wof:placetype":"venue"
},
  "geometry": {"coordinates":[-80.257182,32.774378],"type":"Point"}
}