{
  "type": "Feature",
  "properties": {
    "iso:country":"US",
    "sg:address":"313 Sessions Dr",
    "sg:city":"Aiken",
    "sg:classifiers":[
        {
            "category":"Professional",
            "type":"Services"
        }
    ],
    "sg:phone":"+1 803 641 9731",
    "sg:postcode":"29803",
    "sg:province":"SC",
    "sg:tags":[
        "establishment"
    ],
    "wof:name":"Stratford Hall Pool",
    "wof:placetype":"venue"
},
  "geometry": {"coordinates":[-81.712683,33.495913],"type":"Point"}
}