{
  "type": "Feature",
  "properties": {
    "iso:country":"US",
    "sg:address":"695 Old Wire Rd",
    "sg:city":"West Columbia",
    "sg:classifiers":[
        {
            "category":"Manufacturing",
            "subcategory":"Tools & Machinery",
            "type":"Manufacturing & Wholesale Goods"
        }
    ],
    "sg:phone":"+1 803 796 2681",
    "sg:postcode":"29172",
    "sg:province":"SC",
    "sg:tags":[
        "mill",
        "paper"
    ],
    "wof:name":"R & K Industries",
    "wof:placetype":"venue"
},
  "geometry": {"coordinates":[-81.053732,33.883167],"type":"Point"}
}