{
  "type": "Feature",
  "properties": {
    "iso:country":"US",
    "sg:address":"110 Dillon St",
    "sg:city":"Chesnee",
    "sg:classifiers":[
        {
            "category":"Organizations",
            "subcategory":"Religious Organization",
            "type":"Services"
        }
    ],
    "sg:phone":"+1 864 461 5256",
    "sg:postcode":"29323",
    "sg:province":"SC",
    "sg:tags":[
        "church"
    ],
    "wof:name":"Chesnee Free Will Baptist Chr",
    "wof:placetype":"venue"
},
  "geometry": {"coordinates":[-81.82999700000001,35.146692],"type":"Point"}
}