{
  "type": "Feature",
  "properties": {
    "iso:country":"US",
    "sg:address":"18845 Asheville Hwy",
    "sg:city":"Campobello",
    "sg:classifiers":[
        {
            "category":"Wholesale",
            "subcategory":"Jewelry",
            "type":"Manufacturing & Wholesale Goods"
        }
    ],
    "sg:phone":"+1 864 457 2422",
    "sg:postcode":"29322",
    "sg:province":"SC",
    "sg:tags":[
        "beads"
    ],
    "wof:name":"Horse Feathers",
    "wof:placetype":"venue"
},
  "geometry": {"coordinates":[-82.16694699999999,35.141463],"type":"Point"}
}