{
  "type": "Feature",
  "properties": {
    "iso:country":"US",
    "sg:address":"608 S Walnut St",
    "sg:city":"Pamplico",
    "sg:classifiers":[
        {
            "category":"Home & Garden",
            "subcategory":"Furniture",
            "type":"Retail Goods"
        }
    ],
    "sg:phone":"+1 843 493 2608",
    "sg:postcode":"29583",
    "sg:province":"SC",
    "wof:name":"Furniture Shoppe & Accessories",
    "wof:placetype":"venue"
},
  "geometry": {"coordinates":[-79.56646,33.99015],"type":"Point"}
}