{
  "type": "Feature",
  "properties": {
    "addr:full":"397 N Hwy 52 Moncks Corner SC 29461",
    "addr:housenumber":"397",
    "addr:postcode":"29461",
    "addr:street":"N Hwy 52",
    "iso:country":"US",
    "sg:address":"397 N Hwy 52",
    "sg:city":"Moncks Corner",
    "sg:classifiers":[
        {
            "category":"Personal",
            "subcategory":"Beauty Salon",
            "type":"Services"
        }
    ],
    "sg:phone":"+1 843 761 8725",
    "sg:postcode":"29461",
    "sg:province":"SC",
    "wof:name":"Berkeley Beauty Salon",
    "wof:placetype":"venue"
},
  "geometry": {"coordinates":[-79.990464,33.201233],"type":"Point"}
}