{
  "type": "Feature",
  "properties": {
    "addr:full":"1232 Blythewood Rd Blythewood SC 29016",
    "addr:housenumber":"1232",
    "addr:postcode":"29016",
    "addr:street":"Blythewood Rd",
    "iso:country":"US",
    "sg:address":"1232 Blythewood Rd",
    "sg:city":"Blythewood",
    "sg:classifiers":[
        {
            "category":"Building & Trades",
            "subcategory":"Plumbing",
            "type":"Services"
        }
    ],
    "sg:phone":"+1 803 754 9409",
    "sg:postcode":"29016",
    "sg:province":"SC",
    "sg:tags":[
        "conditioning",
        "air",
        "system",
        "contractor"
    ],
    "sg:website":"www.broomheating.com",
    "wof:name":"Broom Heating & Air Cond",
    "wof:placetype":"venue"
},
  "geometry": {"coordinates":[-81.020595,34.194049],"type":"Point"}
}