{
  "type": "Feature",
  "properties": {
    "iso:country":"US",
    "sg:address":"111 Tarrar Springs Rd",
    "sg:city":"Lexington",
    "sg:classifiers":[
        {
            "category":"Real Estate",
            "subcategory":"Architect",
            "type":"Services"
        }
    ],
    "sg:phone":"+1 803 356 6123",
    "sg:postcode":"29072",
    "sg:province":"SC",
    "wof:name":"LCM Design Group Inc",
    "wof:placetype":"venue"
},
  "geometry": {"coordinates":[-81.210672,33.977404],"type":"Point"}
}