{
  "type": "Feature",
  "properties": {
    "iso:country":"US",
    "sg:address":"564 Greenbriar Dr",
    "sg:city":"Seneca",
    "sg:classifiers":[
        {
            "category":"Building & Trades",
            "subcategory":"Landscaping Services",
            "type":"Services"
        }
    ],
    "sg:phone":"+1 864 723 4451",
    "sg:postcode":"29678",
    "sg:province":"SC",
    "sg:tags":[
        "landscape"
    ],
    "wof:name":"Nelms Lawn Service LLC",
    "wof:placetype":"venue"
},
  "geometry": {"coordinates":[-82.90967999999999,34.639778],"type":"Point"}
}