{
  "type": "Feature",
  "properties": {
    "iso:country":"US",
    "sg:address":"106 Arden Chase",
    "sg:city":"Anderson",
    "sg:classifiers":[
        {
            "category":"Shopping",
            "subcategory":"Jewelry",
            "type":"Retail Goods"
        }
    ],
    "sg:phone":"+1 864 225 7752",
    "sg:postcode":"29621",
    "sg:province":"SC",
    "wof:name":"Diamond Lils",
    "wof:placetype":"venue"
},
  "geometry": {"coordinates":[-82.647913,34.547724],"type":"Point"}
}