{
  "type": "Feature",
  "properties": {
    "iso:country":"US",
    "sg:address":"1898 Calhoun St",
    "sg:city":"Columbia",
    "sg:classifiers":[
        {
            "category":"Insurance",
            "subcategory":"Insurance Agent",
            "type":"Services"
        }
    ],
    "sg:phone":"+1 803 765 2420",
    "sg:postcode":"29201",
    "sg:province":"SC",
    "wof:name":"Brennecke Agency",
    "wof:placetype":"venue"
},
  "geometry": {"coordinates":[-81.028683,34.014919],"type":"Point"}
}