{
  "type": "Feature",
  "properties": {
    "iso:country":"US",
    "sg:address":"207 Oak Knoll Dr",
    "sg:city":"Easley",
    "sg:classifiers":[
        {
            "category":"Professional",
            "subcategory":"Computer Services",
            "type":"Services"
        }
    ],
    "sg:phone":"+1 864 855 3175",
    "sg:postcode":"29640",
    "sg:province":"SC",
    "sg:tags":[
        "consultant",
        "designer"
    ],
    "wof:name":"Firestorm Technology Group",
    "wof:placetype":"venue"
},
  "geometry": {"coordinates":[-82.593645,34.886048],"type":"Point"}
}