{
  "type": "Feature",
  "properties": {
    "iso:country":"US",
    "sg:address":"829 Mayo Rd",
    "sg:city":"Cowpens",
    "sg:classifiers":[
        {
            "category":"Autos & Motor Vehicles",
            "subcategory":"Automobile Sales",
            "type":"Retail Goods"
        }
    ],
    "sg:phone":"+1 864 461 2318",
    "sg:postcode":"29330",
    "sg:province":"SC",
    "sg:tags":[
        "cart"
    ],
    "wof:name":"Osborne Kart Shop",
    "wof:placetype":"venue"
},
  "geometry": {"coordinates":[-81.85730100000001,35.070893],"type":"Point"}
}