{
  "type": "Feature",
  "properties": {
    "iso:country":"US",
    "sg:address":"237 Bay View Dr",
    "sg:city":"Mount Pleasant",
    "sg:classifiers":[
        {
            "category":"Bars & Pubs",
            "type":"Food & Drink"
        }
    ],
    "sg:phone":"+1 843 884 9095",
    "sg:postcode":"29464",
    "sg:province":"SC",
    "sg:tags":[
        "drinking",
        "billiard",
        "eating",
        "hall"
    ],
    "wof:name":"Bees Knees Inc",
    "wof:placetype":"venue"
},
  "geometry": {"coordinates":[-79.89460800000001,32.79721],"type":"Point"}
}