{
  "type": "Feature",
  "properties": {
    "addr:full":"2010 Clemson Rd Columbia SC 29229",
    "addr:housenumber":"2010",
    "addr:postcode":"29229",
    "addr:street":"Clemson Rd",
    "iso:country":"US",
    "sg:address":"2010 Clemson Rd",
    "sg:city":"Columbia",
    "sg:classifiers":[
        {
            "category":"Banks & Credit Unions",
            "subcategory":"Bank",
            "type":"Services"
        }
    ],
    "sg:phone":"+1 803 788 7845",
    "sg:postcode":"29229",
    "sg:province":"SC",
    "wof:name":"South Carolina Bank & Trust",
    "wof:placetype":"venue"
},
  "geometry": {"coordinates":[-80.911779,34.14011],"type":"Point"}
}