{
  "type": "Feature",
  "properties": {
    "iso:country":"US",
    "sg:address":"338 Manning Ave",
    "sg:city":"Sumter",
    "sg:classifiers":[
        {
            "category":"Shopping",
            "subcategory":"Department Store",
            "type":"Retail Goods"
        }
    ],
    "sg:phone":"+1 803 436 9981",
    "sg:postcode":"29150",
    "sg:province":"SC",
    "sg:tags":[
        "shop"
    ],
    "wof:name":"Family Dollar Store",
    "wof:placetype":"venue"
},
  "geometry": {"coordinates":[-80.341165,33.909598],"type":"Point"}
}