{
  "type": "Feature",
  "properties": {
    "iso:country":"US",
    "sg:address":"859 Victory Trail Rd",
    "sg:city":"Gaffney",
    "sg:classifiers":[
        {
            "category":"Shopping",
            "subcategory":"Crafts & Fabrics",
            "type":"Retail Goods"
        }
    ],
    "sg:phone":"+1 864 206 0556",
    "sg:postcode":"29340",
    "sg:province":"SC",
    "sg:tags":[
        "shop"
    ],
    "wof:name":"Metropolis Fabrics LLC",
    "wof:placetype":"venue"
},
  "geometry": {"coordinates":[-81.578411,35.089691],"type":"Point"}
}