{
  "type": "Feature",
  "properties": {
    "addr:full":"1487 Pound Rd Effingham SC 29541",
    "addr:housenumber":"1487",
    "addr:postcode":"29541",
    "addr:street":"Pound Rd",
    "iso:country":"US",
    "sg:address":"1487 Pound Rd",
    "sg:city":"Effingham",
    "sg:classifiers":[
        {
            "category":"Government",
            "subcategory":"Office",
            "type":"Public Place"
        }
    ],
    "sg:phone":"+1 843 665 3053",
    "sg:postcode":"29541",
    "sg:province":"SC",
    "sg:tags":[
        "county",
        "program"
    ],
    "wof:name":"Florence County Environmental",
    "wof:placetype":"venue"
},
  "geometry": {"coordinates":[-79.73119199999999,34.056278],"type":"Point"}
}