{
  "type": "Feature",
  "properties": {
    "iso:country":"US",
    "sg:address":"5001 Notch Rd",
    "sg:city":"Columbia",
    "sg:classifiers":[
        {
            "category":"Autos & Motor Vehicles",
            "subcategory":"Automobile Sales",
            "type":"Retail Goods"
        }
    ],
    "sg:phone":"+1 803 333 0514",
    "sg:postcode":"29204",
    "sg:province":"SC",
    "sg:tags":[
        "car",
        "dealer"
    ],
    "sg:website":"www.hilineautos.com",
    "wof:name":"Hi Line Imports",
    "wof:placetype":"venue"
},
  "geometry": {"coordinates":[-80.989151,34.045718],"type":"Point"}
}