{
  "type": "Feature",
  "properties": {
    "iso:country":"US",
    "sg:address":"2425 New Easley Hwy",
    "sg:city":"Greenville",
    "sg:classifiers":[
        {
            "category":"Retail",
            "subcategory":"Auto Repair",
            "type":"Services"
        }
    ],
    "sg:phone":"+1 864 295 0260",
    "sg:postcode":"29611",
    "sg:province":"SC",
    "sg:tags":[
        "body",
        "automobile",
        "painting"
    ],
    "wof:name":"Matthews Body Shop",
    "wof:placetype":"venue"
},
  "geometry": {"coordinates":[-82.453506,34.833164],"type":"Point"}
}