{
  "type": "Feature",
  "properties": {
    "iso:country":"US",
    "sg:address":"108 Hollyridge Rd",
    "sg:city":"Spartanburg",
    "sg:classifiers":[
        {
            "category":"Shopping",
            "subcategory":"Clothing, Apparel, & Fashions",
            "type":"Retail Goods"
        }
    ],
    "sg:phone":"+1 864 949 1307",
    "sg:postcode":"29301",
    "sg:province":"SC",
    "wof:name":"Dots Sizes Generous Portions",
    "wof:placetype":"venue"
},
  "geometry": {"coordinates":[-82.050271,34.942921],"type":"Point"}
}