{
  "type": "Feature",
  "properties": {
    "addr:full":"522 Community Ln Lancaster SC 29720",
    "addr:housenumber":"522",
    "addr:postcode":"29720",
    "addr:street":"Community Ln",
    "iso:country":"US",
    "sg:address":"522 Community Ln",
    "sg:city":"Lancaster",
    "sg:classifiers":[
        {
            "category":"Building & Trades",
            "subcategory":"Construction",
            "type":"Services"
        }
    ],
    "sg:phone":"+1 803 286 4484",
    "sg:postcode":"29720",
    "sg:province":"SC",
    "sg:tags":[
        "excavation",
        "excavating",
        "contractor"
    ],
    "wof:name":"Bailey Basil Construction Co",
    "wof:placetype":"venue"
},
  "geometry": {"coordinates":[-80.70672399999999,34.686461],"type":"Point"}
}