{
  "type": "Feature",
  "properties": {
    "iso:country":"US",
    "sg:address":"950 Main Rd",
    "sg:city":"Johns Island",
    "sg:classifiers":[
        {
            "category":"Building & Trades",
            "subcategory":"Construction",
            "type":"Services"
        }
    ],
    "sg:phone":"+1 843 559 1155",
    "sg:postcode":"29455",
    "sg:province":"SC",
    "sg:tags":[
        "contractor"
    ],
    "wof:name":"R M Buck Builders",
    "wof:placetype":"venue"
},
  "geometry": {"coordinates":[-80.106285,32.755807],"type":"Point"}
}