{
  "type": "Feature",
  "properties": {
    "iso:country":"US",
    "sg:address":"1320 John C Calhoun Dr",
    "sg:city":"Orangeburg",
    "sg:classifiers":[
        {
            "category":"Shopping",
            "subcategory":"Music",
            "type":"Retail Goods"
        }
    ],
    "sg:phone":"+1 803 531 1026",
    "sg:postcode":"29115",
    "sg:province":"SC",
    "sg:tags":[
        "video",
        "disc",
        "tape",
        "cassette"
    ],
    "wof:name":"Home Video II",
    "wof:placetype":"venue"
},
  "geometry": {"coordinates":[-80.866483,33.484563],"type":"Point"}
}