{
  "type": "Feature",
  "properties": {
    "iso:country":"US",
    "sg:address":"1913 Grandview Ct",
    "sg:city":"Mount Pleasant",
    "sg:classifiers":[
        {
            "category":"Restaurant",
            "type":"Food & Drink"
        }
    ],
    "sg:phone":"+1 843 881 1006",
    "sg:postcode":"29464",
    "sg:province":"SC",
    "sg:tags":[
        "eating"
    ],
    "wof:name":"Ouhllas Fine Fd Caterers LLC",
    "wof:placetype":"venue"
},
  "geometry": {"coordinates":[-79.811443,32.815648],"type":"Point"}
}