{
  "type": "Feature",
  "properties": {
    "iso:country":"US",
    "sg:address":"111 Tiffany Ter",
    "sg:city":"Gaffney",
    "sg:classifiers":[
        {
            "category":"Insurance",
            "subcategory":"Insurance Agent",
            "type":"Services"
        }
    ],
    "sg:phone":"+1 864 489 5757",
    "sg:postcode":"29341",
    "sg:province":"SC",
    "wof:name":"CWS Insurance",
    "wof:placetype":"venue"
},
  "geometry": {"coordinates":[-81.67232799999999,35.062025],"type":"Point"}
}