{
  "type": "Feature",
  "properties": {
    "addr:full":"10 E Dorchester Blvd Greenville SC 29605",
    "addr:housenumber":"10",
    "addr:postcode":"29605",
    "addr:street":"E Dorchester Blvd",
    "iso:country":"US",
    "sg:address":"10 E Dorchester Blvd",
    "sg:city":"Greenville",
    "sg:classifiers":[
        {
            "category":"Professional",
            "subcategory":"Engineering",
            "type":"Services"
        }
    ],
    "sg:phone":"+1 864 277 8287",
    "sg:postcode":"29605",
    "sg:province":"SC",
    "sg:tags":[
        "engineer"
    ],
    "wof:name":"Peritus Engineers & Assoc Inc",
    "wof:placetype":"venue"
},
  "geometry": {"coordinates":[-82.388487,34.794056],"type":"Point"}
}