{
  "type": "Feature",
  "properties": {
    "iso:country":"US",
    "sg:address":"1578 Boiling Springs Rd",
    "sg:city":"Spartanburg",
    "sg:classifiers":[
        {
            "category":"Travel",
            "subcategory":"Hotels & Motels",
            "type":"Entertainment"
        }
    ],
    "sg:phone":"+1 864 814 7663",
    "sg:postcode":"29316",
    "sg:province":"SC",
    "wof:name":"Red Roof Inn",
    "wof:placetype":"venue"
},
  "geometry": {"coordinates":[-81.954077,35.009274],"type":"Point"}
}