{
  "type": "Feature",
  "properties": {
    "iso:country":"US",
    "sg:address":"3700 Shawnee Ave",
    "sg:city":"Anderson",
    "sg:classifiers":[
        {
            "category":"Building & Trades",
            "subcategory":"Landscaping Services",
            "type":"Services"
        }
    ],
    "sg:phone":"+1 864 261 3894",
    "sg:postcode":"29626",
    "sg:province":"SC",
    "sg:tags":[
        "lawn",
        "maintenance",
        "grounds"
    ],
    "wof:name":"AAA Price Breaker Mntnc",
    "wof:placetype":"venue"
},
  "geometry": {"coordinates":[-82.668216,34.465407],"type":"Point"}
}