{
  "type": "Feature",
  "properties": {
    "addr:full":"2204 E Bobo Newsome Hwy Hartsville SC 29550",
    "addr:housenumber":"2204",
    "addr:postcode":"29550",
    "addr:street":"E Bobo Newsome Hwy",
    "iso:country":"US",
    "sg:address":"2204 E Bobo Newsome Hwy",
    "sg:city":"Hartsville",
    "sg:classifiers":[
        {
            "category":"Retail",
            "subcategory":"Auto Repair",
            "type":"Services"
        }
    ],
    "sg:phone":"+1 843 383 0504",
    "sg:postcode":"29550",
    "sg:province":"SC",
    "sg:tags":[
        "transmission"
    ],
    "wof:name":"A 1 Transmission",
    "wof:placetype":"venue"
},
  "geometry": {"coordinates":[-79.988185,34.304075],"type":"Point"}
}