{
  "type": "Feature",
  "properties": {
    "addr:full":"300 E Church St Bishopville SC 29010",
    "addr:housenumber":"300",
    "addr:postcode":"29010",
    "addr:street":"E Church St",
    "iso:country":"US",
    "sg:address":"300 E Church St",
    "sg:city":"Bishopville",
    "sg:phone":"+1 803 428 4726",
    "sg:postcode":"29010",
    "sg:province":"SC",
    "sg:tags":[
        "farm",
        "cotton"
    ],
    "wof:name":"Woody Beasley",
    "wof:placetype":"venue"
},
  "geometry": {"coordinates":[-80.24515100000001,34.215343],"type":"Point"}
}