{
  "type": "Feature",
  "properties": {
    "iso:country":"US",
    "sg:address":"2617 Clements Ferry Rd",
    "sg:city":"Wando",
    "sg:classifiers":[
        {
            "category":"Building & Trades",
            "subcategory":"Electrical",
            "type":"Services"
        }
    ],
    "sg:phone":"+1 843 849 6565",
    "sg:postcode":"29492",
    "sg:province":"SC",
    "sg:tags":[
        "electric",
        "contractor"
    ],
    "wof:name":"Osborne Electric Inc",
    "wof:placetype":"venue"
},
  "geometry": {"coordinates":[-79.92924,32.887951],"type":"Point"}
}