{
  "type": "Feature",
  "properties": {
    "iso:country":"US",
    "sg:address":"1000 William Hilton Pkwy",
    "sg:city":"Hilton Head Isle",
    "sg:classifiers":[
        {
            "category":"Shopping",
            "subcategory":"Crafts & Fabrics",
            "type":"Retail Goods"
        }
    ],
    "sg:phone":"+1 843 842 8488",
    "sg:postcode":"29928",
    "sg:province":"SC",
    "sg:tags":[
        "material",
        "needlework"
    ],
    "wof:name":"Needlepoint Junction",
    "wof:placetype":"venue"
},
  "geometry": {"coordinates":[-80.755616,32.15793],"type":"Point"}
}