{
  "type": "Feature",
  "properties": {
    "iso:country":"US",
    "sg:address":"800 N Church St",
    "sg:city":"Spartanburg",
    "sg:classifiers":[
        {
            "category":"Shopping",
            "subcategory":"Florist",
            "type":"Retail Goods"
        }
    ],
    "sg:phone":"+1 864 585 6266",
    "sg:postcode":"29303",
    "sg:province":"SC",
    "wof:name":"Coggins Flowers and Gifts",
    "wof:placetype":"venue"
},
  "geometry": {"coordinates":[-81.941715,34.965655],"type":"Point"}
}