{
  "type": "Feature",
  "properties": {
    "iso:country":"US",
    "sg:address":"338 Broad St",
    "sg:city":"Sumter",
    "sg:classifiers":[
        {
            "category":"Personal",
            "subcategory":"Beauty Salon",
            "type":"Services"
        }
    ],
    "sg:phone":"+1 803 775 7562",
    "sg:postcode":"29150",
    "sg:province":"SC",
    "wof:name":"Perfect Touch Hair Salon",
    "wof:placetype":"venue"
},
  "geometry": {"coordinates":[-80.356737,33.935179],"type":"Point"}
}