{
  "type": "Feature",
  "properties": {
    "addr:full":"3645 Sandra Ln Fort Mill SC 29715",
    "addr:housenumber":"3645",
    "addr:postcode":"29715",
    "addr:street":"Sandra Ln",
    "iso:country":"US",
    "sg:address":"3645 Sandra Ln",
    "sg:city":"Fort Mill",
    "sg:classifiers":[
        {
            "category":"Manufacturing",
            "subcategory":"Tools & Machinery",
            "type":"Manufacturing & Wholesale Goods"
        },
        {
            "category":"Wholesale",
            "subcategory":"Electrical",
            "type":"Manufacturing & Wholesale Goods"
        }
    ],
    "sg:phone":"+1 803 802 7260",
    "sg:postcode":"29715",
    "sg:province":"SC",
    "sg:tags":[
        "generator",
        "mfg"
    ],
    "wof:name":"Careco Services",
    "wof:placetype":"venue"
},
  "geometry": {"coordinates":[-80.85404,35.014458],"type":"Point"}
}