{
  "type": "Feature",
  "properties": {
    "addr:full":"77 Creekside Dr Summerville SC 29485",
    "addr:housenumber":"77",
    "addr:postcode":"29485",
    "addr:street":"Creekside Dr",
    "iso:country":"US",
    "sg:address":"77 Creekside Dr",
    "sg:city":"Summerville",
    "sg:classifiers":[
        {
            "category":"Autos & Motor Vehicles",
            "subcategory":"Automobile Sales",
            "type":"Retail Goods"
        }
    ],
    "sg:phone":"+1 843 871 9281",
    "sg:postcode":"29485",
    "sg:province":"SC",
    "sg:tags":[
        "new",
        "car"
    ],
    "wof:name":"Avomot & Robinson Enterprises",
    "wof:placetype":"venue"
},
  "geometry": {"coordinates":[-80.15203700000001,32.971117],"type":"Point"}
}