{
  "type": "Feature",
  "properties": {
    "iso:country":"US",
    "sg:address":"663 William Hilton Pkwy",
    "sg:city":"Hilton Head Isle",
    "sg:classifiers":[
        {
            "category":"Home & Garden",
            "subcategory":"Home Furnishings",
            "type":"Retail Goods"
        }
    ],
    "sg:phone":"+1 843 342 2923",
    "sg:postcode":"29928",
    "sg:province":"SC",
    "sg:tags":[
        "pottery"
    ],
    "wof:name":"Dillons Pottery",
    "wof:placetype":"venue"
},
  "geometry": {"coordinates":[-80.708955,32.191718],"type":"Point"}
}