{
  "type": "Feature",
  "properties": {
    "iso:country":"US",
    "sg:address":"1510 Orange Grove Rd",
    "sg:city":"Charleston",
    "sg:classifiers":[
        {
            "category":"Building & Trades",
            "subcategory":"Construction",
            "type":"Services"
        }
    ],
    "sg:phone":"+1 843 225 2261",
    "sg:postcode":"29407",
    "sg:province":"SC",
    "sg:tags":[
        "industrial"
    ],
    "wof:name":"Andria Construction",
    "wof:placetype":"venue"
},
  "geometry": {"coordinates":[-80.006226,32.812993],"type":"Point"}
}