{
  "type": "Feature",
  "properties": {
    "addr:full":"875 Riverview Rd Rock Hill SC 29730",
    "addr:housenumber":"875",
    "addr:postcode":"29730",
    "addr:street":"Riverview Rd",
    "iso:country":"US",
    "sg:address":"875 Riverview Rd",
    "sg:city":"Rock Hill",
    "sg:classifiers":[
        {
            "category":"Travel",
            "subcategory":"Hotels & Motels",
            "type":"Entertainment"
        }
    ],
    "sg:phone":"+1 803 329 2171",
    "sg:postcode":"29730",
    "sg:province":"SC",
    "wof:name":"Comfort Inn",
    "wof:placetype":"venue"
},
  "geometry": {"coordinates":[-80.986503,34.969015],"type":"Point"}
}