{
  "type": "Feature",
  "properties": {
    "iso:country":"US",
    "sg:address":"1708 Cherokee Ave",
    "sg:city":"Gaffney",
    "sg:classifiers":[
        {
            "category":"Shopping",
            "subcategory":"Used Merchandise",
            "type":"Retail Goods"
        }
    ],
    "sg:phone":"+1 864 489 8747",
    "sg:postcode":"29340",
    "sg:province":"SC",
    "sg:tags":[
        "shop",
        "consignment"
    ],
    "wof:name":"Toy Barn",
    "wof:placetype":"venue"
},
  "geometry": {"coordinates":[-81.62545,35.081317],"type":"Point"}
}