{
  "type": "Feature",
  "properties": {
    "addr:full":"1 Riverwood Dr Moncks Corner SC 29461",
    "addr:housenumber":"1",
    "addr:postcode":"29461",
    "addr:street":"Riverwood Dr",
    "iso:country":"US",
    "sg:address":"1 Riverwood Dr",
    "sg:city":"Moncks Corner",
    "sg:classifiers":[
        {
            "category":"Banks & Credit Unions",
            "subcategory":"Bank",
            "type":"Services"
        }
    ],
    "sg:phone":"+1 843 761 4001",
    "sg:postcode":"29461",
    "sg:province":"SC",
    "sg:tags":[
        "state"
    ],
    "wof:name":"Santee Cooper Employees Cr Un",
    "wof:placetype":"venue"
},
  "geometry": {"coordinates":[-79.98248599999999,33.201476],"type":"Point"}
}