{
  "type": "Feature",
  "properties": {
    "addr:full":"116 S Main St Mc Cormick SC 29835",
    "addr:housenumber":"116",
    "addr:postcode":"29835",
    "addr:street":"S Main St Mc Cormick",
    "iso:country":"US",
    "sg:address":"116 S Main St",
    "sg:city":"Mc Cormick",
    "sg:classifiers":[
        {
            "category":"Home & Garden",
            "subcategory":"Furniture",
            "type":"Retail Goods"
        }
    ],
    "sg:phone":"+1 864 465 2003",
    "sg:postcode":"29835",
    "sg:province":"SC",
    "wof:name":"B & B Furniture",
    "wof:placetype":"venue"
},
  "geometry": {"coordinates":[-82.285456,33.905951],"type":"Point"}
}