{
  "type": "Feature",
  "properties": {
    "addr:full":"2385 Washington St Columbia SC 29204",
    "addr:housenumber":"2385",
    "addr:postcode":"29204",
    "addr:street":"Washington St",
    "iso:country":"US",
    "sg:address":"2385 Washington St",
    "sg:city":"Columbia",
    "sg:classifiers":[
        {
            "category":"Retail",
            "subcategory":"Self-service Laundry",
            "type":"Services"
        }
    ],
    "sg:phone":"+1 803 254 3464",
    "sg:postcode":"29204",
    "sg:province":"SC",
    "wof:name":"Corbin's Grocery & Laundromat",
    "wof:placetype":"venue"
},
  "geometry": {"coordinates":[-81.01398500000001,34.010586],"type":"Point"}
}