{
  "type": "Feature",
  "properties": {
    "addr:full":"7634 Southrail Rd North Charleston SC 29420",
    "addr:housenumber":"7634",
    "addr:postcode":"29420",
    "addr:street":"Southrail Rd",
    "iso:country":"US",
    "sg:address":"7634 Southrail Rd",
    "sg:city":"North Charleston",
    "sg:classifiers":[
        {
            "category":"Home & Garden",
            "subcategory":"Building Materials",
            "type":"Retail Goods"
        }
    ],
    "sg:phone":"+1 843 764 2888",
    "sg:postcode":"29420",
    "sg:province":"SC",
    "sg:tags":[
        "glass",
        "window",
        "plate"
    ],
    "wof:name":"Atlantic Glass Inc",
    "wof:placetype":"venue"
},
  "geometry": {"coordinates":[-80.061477,32.936878],"type":"Point"}
}