{
  "type": "Feature",
  "properties": {
    "iso:country":"US",
    "sg:address":"9314 Bennetts Point Rd",
    "sg:city":"Green Pond",
    "sg:classifiers":[
        {
            "category":"Wholesale",
            "subcategory":"Groceries",
            "type":"Manufacturing & Wholesale Goods"
        }
    ],
    "sg:phone":"+1 843 844 2935",
    "sg:postcode":"29446",
    "sg:province":"SC",
    "wof:name":"Ashepoo Plantation Gate House",
    "wof:placetype":"venue"
},
  "geometry": {"coordinates":[-80.500683,32.638864],"type":"Point"}
}