{
  "type": "Feature",
  "properties": {
    "addr:full":"107 McQueen St West Columbia SC 29172",
    "addr:housenumber":"107",
    "addr:postcode":"29172",
    "addr:street":"Mcqueen St",
    "iso:country":"US",
    "sg:address":"107 McQueen St",
    "sg:city":"West Columbia",
    "sg:classifiers":[
        {
            "category":"Professional",
            "subcategory":"Advertising",
            "type":"Services"
        }
    ],
    "sg:phone":"+1 803 796 0882",
    "sg:postcode":"29172",
    "sg:province":"SC",
    "sg:tags":[
        "distribution"
    ],
    "wof:name":"Mitsui Machinery Distribution",
    "wof:placetype":"venue"
},
  "geometry": {"coordinates":[-81.09566,33.932804],"type":"Point"}
}