{
  "type": "Feature",
  "properties": {
    "addr:full":"912 E Main St Laurens SC 29360",
    "addr:housenumber":"912",
    "addr:postcode":"29360",
    "addr:street":"E Main St",
    "iso:country":"US",
    "sg:address":"912 E Main St",
    "sg:city":"Laurens",
    "sg:classifiers":[
        {
            "category":"Autos & Motor Vehicles",
            "subcategory":"Auto Supplies",
            "type":"Retail Goods"
        }
    ],
    "sg:phone":"+1 864 682 4401",
    "sg:postcode":"29360",
    "sg:province":"SC",
    "sg:tags":[
        "automobile",
        "parts"
    ],
    "wof:name":"Advance Auto Parts Inc",
    "wof:placetype":"venue"
},
  "geometry": {"coordinates":[-81.983054,34.493189],"type":"Point"}
}