{
  "type": "Feature",
  "properties": {
    "iso:country":"US",
    "sg:address":"512 Augusta Rd",
    "sg:city":"North Augusta",
    "sg:classifiers":[
        {
            "category":"Building & Trades",
            "subcategory":"Landscaping Services",
            "type":"Services"
        }
    ],
    "sg:phone":"+1 803 279 2038",
    "sg:postcode":"29822",
    "sg:province":"SC",
    "sg:tags":[
        "lawn",
        "care"
    ],
    "wof:name":"Mikes Lawn Service",
    "wof:placetype":"venue"
},
  "geometry": {"coordinates":[-81.892122,33.49684],"type":"Point"}
}