{
  "type": "Feature",
  "properties": {
    "iso:country":"US",
    "sg:address":"803 Parkwood Dr",
    "sg:city":"Anderson",
    "sg:classifiers":[
        {
            "category":"Real Estate",
            "subcategory":"Real Estate Operator",
            "type":"Services"
        }
    ],
    "sg:phone":"+1 864 964 0959",
    "sg:postcode":"29625",
    "sg:province":"SC",
    "sg:tags":[
        "building",
        "nonresidential"
    ],
    "wof:name":"Moon Properties LLC",
    "wof:placetype":"venue"
},
  "geometry": {"coordinates":[-82.724338,34.537397],"type":"Point"}
}