{
  "type": "Feature",
  "properties": {
    "addr:full":"622 Sunset Blvd West Columbia SC 29169",
    "addr:housenumber":"622",
    "addr:postcode":"29169",
    "addr:street":"Sunset Blvd",
    "iso:country":"US",
    "sg:address":"622 Sunset Blvd",
    "sg:city":"West Columbia",
    "sg:classifiers":[
        {
            "category":"Personal",
            "subcategory":"Beauty Salon",
            "type":"Services"
        }
    ],
    "sg:phone":"+1 803 939 0430",
    "sg:postcode":"29169",
    "sg:province":"SC",
    "wof:name":"Simply Beautiful Hair Salon",
    "wof:placetype":"venue"
},
  "geometry": {"coordinates":[-81.060225,33.996617],"type":"Point"}
}