{
  "type": "Feature",
  "properties": {
    "addr:full":"2205 Middle St Sullivans Island SC 29482",
    "addr:housenumber":"2205",
    "addr:postcode":"29482",
    "addr:street":"Middle St",
    "iso:country":"US",
    "sg:address":"2205 Middle St",
    "sg:city":"Sullivans Island",
    "sg:classifiers":[
        {
            "category":"Home & Garden",
            "subcategory":"Furniture",
            "type":"Retail Goods"
        }
    ],
    "sg:phone":"+1 843 883 9777",
    "sg:postcode":"29482",
    "sg:province":"SC",
    "sg:tags":[
        "cabinet"
    ],
    "wof:name":"Mc Cabe's Cabinets & Woodworks",
    "wof:placetype":"venue"
},
  "geometry": {"coordinates":[-79.83628400000001,32.762771],"type":"Point"}
}