{
  "type": "Feature",
  "properties": {
    "iso:country":"US",
    "sg:address":"919 Washington St",
    "sg:city":"Columbia",
    "sg:classifiers":[
        {
            "category":"Home & Garden",
            "subcategory":"Furniture",
            "type":"Retail Goods"
        }
    ],
    "sg:phone":"+1 803 252 1338",
    "sg:postcode":"29201",
    "sg:province":"SC",
    "sg:tags":[
        "sell",
        "kitchen",
        "design",
        "bath"
    ],
    "wof:name":"Metro Design Inc",
    "wof:placetype":"venue"
},
  "geometry": {"coordinates":[-81.03876099999999,34.002743],"type":"Point"}
}