{
  "type": "Feature",
  "properties": {
    "iso:country":"US",
    "sg:address":"100 Vienna St",
    "sg:city":"Abbeville",
    "sg:classifiers":[
        {
            "category":"Autos & Motor Vehicles",
            "subcategory":"Fuel & Gas Station",
            "type":"Retail Goods"
        }
    ],
    "sg:phone":"+1 864 366 4338",
    "sg:postcode":"29620",
    "sg:province":"SC",
    "sg:tags":[
        "oil"
    ],
    "wof:name":"Smith's Service Ctr",
    "wof:placetype":"venue"
},
  "geometry": {"coordinates":[-82.380017,34.176641],"type":"Point"}
}