{
  "type": "Feature",
  "properties": {
    "iso:country":"US",
    "sg:address":"842 Mount Zion Rd",
    "sg:city":"Spartanburg",
    "sg:classifiers":[
        {
            "category":"Organizations",
            "subcategory":"Religious Organization",
            "type":"Services"
        }
    ],
    "sg:phone":"+1 864 949 7000",
    "sg:postcode":"29303",
    "sg:province":"SC",
    "sg:tags":[
        "church"
    ],
    "wof:name":"Mount Zion Baptist Church",
    "wof:placetype":"venue"
},
  "geometry": {"coordinates":[-82.057884,34.979013],"type":"Point"}
}