{
  "type": "Feature",
  "properties": {
    "iso:country":"US",
    "sg:address":"1317 Corley Ford Rd",
    "sg:city":"Columbia",
    "sg:classifiers":[
        {
            "category":"Building & Trades",
            "subcategory":"Landscaping Services",
            "type":"Services"
        }
    ],
    "sg:phone":"+1 803 754 6689",
    "sg:postcode":"29203",
    "sg:province":"SC",
    "sg:tags":[
        "lawn"
    ],
    "wof:name":"Corley Lawn & Construction",
    "wof:placetype":"venue"
},
  "geometry": {"coordinates":[-81.04855499999999,34.108218],"type":"Point"}
}