{
  "type": "Feature",
  "properties": {
    "iso:country":"US",
    "sg:address":"900 N Main St",
    "sg:city":"Greer",
    "sg:classifiers":[
        {
            "category":"Organizations",
            "subcategory":"Religious Organization",
            "type":"Services"
        }
    ],
    "sg:phone":"+1 864 877 2288",
    "sg:postcode":"29651",
    "sg:province":"SC",
    "sg:tags":[
        "church"
    ],
    "sg:website":"www.cheritage.org",
    "wof:name":"Christian Heritage Church",
    "wof:placetype":"venue"
},
  "geometry": {"coordinates":[-82.22620999999999,34.952107],"type":"Point"}
}