{
  "type": "Feature",
  "properties": {
    "iso:country":"US",
    "sg:address":"8401 Moorefield Memorial Hwy",
    "sg:city":"Liberty",
    "sg:classifiers":[
        {
            "category":"Autos & Motor Vehicles",
            "subcategory":"Auto Supplies",
            "type":"Retail Goods"
        }
    ],
    "sg:phone":"+1 864 843 9226",
    "sg:postcode":"29657",
    "sg:province":"SC",
    "sg:tags":[
        "tire"
    ],
    "wof:name":"Jessie's Tire & Lube",
    "wof:placetype":"venue"
},
  "geometry": {"coordinates":[-82.660906,34.746296],"type":"Point"}
}