{
  "type": "Feature",
  "properties": {
    "addr:full":"910 Craft St West Columbia SC 29169",
    "addr:housenumber":"910",
    "addr:postcode":"29169",
    "addr:street":"Craft St",
    "iso:country":"US",
    "sg:address":"910 Craft St",
    "sg:city":"West Columbia",
    "sg:classifiers":[
        {
            "category":"Wholesale",
            "subcategory":"Hardware",
            "type":"Manufacturing & Wholesale Goods"
        }
    ],
    "sg:phone":"+1 803 794 8585",
    "sg:postcode":"29169",
    "sg:province":"SC",
    "sg:tags":[
        "refrigerating"
    ],
    "wof:name":"Lacons Refrigeration & AC",
    "wof:placetype":"venue"
},
  "geometry": {"coordinates":[-81.069811,33.99963],"type":"Point"}
}