{
  "type": "Feature",
  "properties": {
    "addr:full":"1727 Augusta Rd West Columbia SC 29169",
    "addr:housenumber":"1727",
    "addr:postcode":"29169",
    "addr:street":"Augusta Rd",
    "iso:country":"US",
    "sg:address":"1727 Augusta Rd",
    "sg:city":"West Columbia",
    "sg:classifiers":[
        {
            "category":"Banks & Credit Unions",
            "subcategory":"Bank",
            "type":"Services"
        }
    ],
    "sg:phone":"+1 803 739 2092",
    "sg:postcode":"29169",
    "sg:province":"SC",
    "sg:tags":[
        "mortgage",
        "loan",
        "broker",
        "real estate"
    ],
    "wof:name":"Statewide Mortgage",
    "wof:placetype":"venue"
},
  "geometry": {"coordinates":[-81.08214700000001,33.985704],"type":"Point"}
}