{
  "type": "Feature",
  "properties": {
    "iso:country":"US",
    "sg:address":"1620 Cypress Gardens Rd",
    "sg:city":"Moncks Corner",
    "sg:classifiers":[
        {
            "category":"Manufacturing",
            "subcategory":"Rubber & Plastics",
            "type":"Manufacturing & Wholesale Goods"
        }
    ],
    "sg:phone":"+1 843 761 7955",
    "sg:postcode":"29461",
    "sg:province":"SC",
    "sg:tags":[
        "product"
    ],
    "wof:name":"Rubber Recovery Inc",
    "wof:placetype":"venue"
},
  "geometry": {"coordinates":[-80.024461,33.089366],"type":"Point"}
}