{
  "type": "Feature",
  "properties": {
    "addr:full":"1445 Winton Rd Mount Pleasant SC 29464",
    "addr:housenumber":"1445",
    "addr:postcode":"29464",
    "addr:street":"Winton Rd",
    "iso:country":"US",
    "sg:address":"1445 Winton Rd",
    "sg:city":"Mount Pleasant",
    "sg:classifiers":[
        {
            "category":"Wholesale",
            "subcategory":"Groceries",
            "type":"Manufacturing & Wholesale Goods"
        }
    ],
    "sg:phone":"+1 843 760 1348",
    "sg:postcode":"29464",
    "sg:province":"SC",
    "sg:tags":[
        "general"
    ],
    "wof:name":"East Bay",
    "wof:placetype":"venue"
},
  "geometry": {"coordinates":[-79.837439,32.80302],"type":"Point"}
}