{
  "type": "Feature",
  "properties": {
    "addr:full":"1005 Pocalla Rd Sumter SC 29150",
    "addr:housenumber":"1005",
    "addr:postcode":"29150",
    "addr:street":"Pocalla Rd",
    "iso:country":"US",
    "sg:address":"1005 Pocalla Rd",
    "sg:city":"Sumter",
    "sg:classifiers":[
        {
            "category":"Autos & Motor Vehicles",
            "subcategory":"Automobile Sales",
            "type":"Retail Goods"
        }
    ],
    "sg:phone":"+1 803 773 7722",
    "sg:postcode":"29150",
    "sg:province":"SC",
    "sg:tags":[
        "car",
        "dealer"
    ],
    "wof:name":"S & W Used Cars",
    "wof:placetype":"venue"
},
  "geometry": {"coordinates":[-80.33928400000001,33.895612],"type":"Point"}
}