{
  "type": "Feature",
  "properties": {
    "iso:country":"US",
    "sg:address":"2 Tanglewood Dr",
    "sg:city":"Hilton Head Isle",
    "sg:classifiers":[
        {
            "category":"Recreation",
            "subcategory":"Amusement Park",
            "type":"Entertainment"
        }
    ],
    "sg:phone":"+1 843 842 8108",
    "sg:postcode":"29928",
    "sg:province":"SC",
    "wof:name":"Waterfun Park & Mini-Golf",
    "wof:placetype":"venue"
},
  "geometry": {"coordinates":[-80.756033,32.142243],"type":"Point"}
}