{
  "type": "Feature",
  "properties": {
    "iso:country":"US",
    "sg:address":"3 Gamecock Ave",
    "sg:city":"Charleston",
    "sg:classifiers":[
        {
            "category":"Shopping",
            "subcategory":"Computers & Home Electronics",
            "type":"Retail Goods"
        }
    ],
    "sg:phone":"+1 843 571 2108",
    "sg:postcode":"29407",
    "sg:province":"SC",
    "sg:tags":[
        "software"
    ],
    "sg:website":"www.comdirections.com",
    "wof:name":"Computer Directions",
    "wof:placetype":"venue"
},
  "geometry": {"coordinates":[-79.993536,32.8197],"type":"Point"}
}