{
  "type": "Feature",
  "properties": {
    "iso:country":"US",
    "sg:address":"3025 Wade Hampton Blvd",
    "sg:city":"Taylors",
    "sg:classifiers":[
        {
            "category":"Building & Trades",
            "subcategory":"Construction",
            "type":"Services"
        }
    ],
    "sg:phone":"+1 864 322 6848",
    "sg:postcode":"29687",
    "sg:province":"SC",
    "sg:tags":[
        "general",
        "contractor"
    ],
    "wof:name":"Worthington Construction Co",
    "wof:placetype":"venue"
},
  "geometry": {"coordinates":[-82.330213,34.906374],"type":"Point"}
}