{
  "type": "Feature",
  "properties": {
    "iso:country":"US",
    "sg:address":"1441 Main St",
    "sg:city":"Columbia",
    "sg:classifiers":[
        {
            "category":"Banks & Credit Unions",
            "subcategory":"Investment Brokerage",
            "type":"Services"
        }
    ],
    "sg:phone":"+1 803 432 8782",
    "sg:postcode":"29201",
    "sg:province":"SC",
    "sg:tags":[
        "security"
    ],
    "wof:name":"Frederick D Iselin",
    "wof:placetype":"venue"
},
  "geometry": {"coordinates":[-81.035167,34.004709],"type":"Point"}
}