{
  "type": "Feature",
  "properties": {
    "iso:country":"US",
    "sg:address":"8035 Asheville Hwy",
    "sg:city":"Spartanburg",
    "sg:classifiers":[
        {
            "category":"Restaurant",
            "type":"Food & Drink"
        }
    ],
    "sg:phone":"+1 864 503 4004",
    "sg:postcode":"29303",
    "sg:province":"SC",
    "wof:name":"Captain's Table",
    "wof:placetype":"venue"
},
  "geometry": {"coordinates":[-81.993139,34.991997],"type":"Point"}
}