{
  "type": "Feature",
  "properties": {
    "iso:country":"US",
    "sg:address":"211 Woolbright Cir",
    "sg:city":"Townville",
    "sg:classifiers":[
        {
            "category":"Retail",
            "subcategory":"Auto Repair",
            "type":"Services"
        }
    ],
    "sg:phone":"+1 864 419 6277",
    "sg:postcode":"29689",
    "sg:province":"SC",
    "sg:tags":[
        "body",
        "automobile",
        "painting",
        "repairing"
    ],
    "wof:name":"Mobile Auto Restoration Services",
    "wof:placetype":"venue"
},
  "geometry": {"coordinates":[-82.911373,34.570696],"type":"Point"}
}