{
  "type": "Feature",
  "properties": {
    "iso:country":"US",
    "sg:address":"7215 Palmetto Pl",
    "sg:city":"Fort Mill",
    "sg:classifiers":[
        {
            "category":"Food & Beverages",
            "subcategory":"Bakery",
            "type":"Retail Goods"
        }
    ],
    "sg:phone":"+1 803 329 9259",
    "sg:postcode":"29708",
    "sg:province":"SC",
    "sg:tags":[
        "doughnut"
    ],
    "wof:name":"Dunkin Donuts",
    "wof:placetype":"venue"
},
  "geometry": {"coordinates":[-80.992823,35.057962],"type":"Point"}
}