{
  "type": "Feature",
  "properties": {
    "addr:full":"226 W Main St Spartanburg SC 29306",
    "addr:housenumber":"226",
    "addr:postcode":"29306",
    "addr:street":"W Main St",
    "iso:country":"US",
    "sg:address":"226 W Main St",
    "sg:city":"Spartanburg",
    "sg:classifiers":[
        {
            "category":"Bars & Pubs",
            "type":"Food & Drink"
        }
    ],
    "sg:phone":"+1 864 585 2337",
    "sg:postcode":"29306",
    "sg:province":"SC",
    "sg:tags":[
        "brew"
    ],
    "wof:name":"R J Rockers Inc",
    "wof:placetype":"venue"
},
  "geometry": {"coordinates":[-81.935627,34.948323],"type":"Point"}
}