{
  "type": "Feature",
  "properties": {
    "iso:country":"US",
    "sg:address":"3108 Notch Rd",
    "sg:city":"Columbia",
    "sg:classifiers":[
        {
            "category":"Autos & Motor Vehicles",
            "subcategory":"Auto Supplies",
            "type":"Retail Goods"
        }
    ],
    "sg:phone":"+1 803 786 4200",
    "sg:postcode":"29204",
    "sg:province":"SC",
    "sg:tags":[
        "equipment",
        "electrical"
    ],
    "sg:website":"www.autozone.com",
    "wof:name":"Autozone",
    "wof:placetype":"venue"
},
  "geometry": {"coordinates":[-81.002026,34.038417],"type":"Point"}
}