{
  "type": "Feature",
  "properties": {
    "iso:country":"US",
    "sg:address":"4722 Othello Rd",
    "sg:city":"Coward",
    "sg:classifiers":[
        {
            "category":"Shopping",
            "subcategory":"Books",
            "type":"Retail Goods"
        }
    ],
    "sg:phone":"+1 843 389 4761",
    "sg:postcode":"29530",
    "sg:province":"SC",
    "sg:tags":[
        "bible"
    ],
    "wof:name":"Gideons International",
    "wof:placetype":"venue"
},
  "geometry": {"coordinates":[-79.73490099999999,33.997723],"type":"Point"}
}