{
  "type": "Feature",
  "properties": {
    "iso:country":"US",
    "sg:address":"5449 Sunset Blvd",
    "sg:city":"Lexington",
    "sg:classifiers":[
        {
            "category":"Retail",
            "subcategory":"Veterinary Services",
            "type":"Services"
        }
    ],
    "sg:phone":"+1 803 359 6611",
    "sg:postcode":"29072",
    "sg:province":"SC",
    "sg:tags":[
        "veterinarian"
    ],
    "wof:name":"Cherokee Trail Veterinary",
    "wof:placetype":"venue"
},
  "geometry": {"coordinates":[-81.215666,33.999032],"type":"Point"}
}