{
  "type": "Feature",
  "properties": {
    "iso:country":"US",
    "sg:address":"1501 S Main St",
    "sg:city":"Darlington",
    "sg:classifiers":[
        {
            "category":"Restaurant",
            "type":"Food & Drink"
        }
    ],
    "sg:phone":"+1 843 393 9733",
    "sg:postcode":"29532",
    "sg:province":"SC",
    "wof:name":"Mc Donald's",
    "wof:placetype":"venue"
},
  "geometry": {"coordinates":[-79.857277,34.282455],"type":"Point"}
}