{
  "type": "Feature",
  "properties": {
    "addr:full":"220 Stoneridge Dr Columbia SC 29210",
    "addr:housenumber":"220",
    "addr:postcode":"29210",
    "addr:street":"Stoneridge Dr",
    "iso:country":"US",
    "sg:address":"220 Stoneridge Dr",
    "sg:city":"Columbia",
    "sg:classifiers":[
        {
            "category":"Organizations",
            "subcategory":"Non-profit Organization",
            "type":"Services"
        }
    ],
    "sg:phone":"+1 803 771 2810",
    "sg:postcode":"29210",
    "sg:province":"SC",
    "sg:website":"www.schealthcare.com",
    "wof:name":"Sc Office Of Rural Health",
    "wof:placetype":"venue"
},
  "geometry": {"coordinates":[-81.07785199999999,34.015397],"type":"Point"}
}