{
  "type": "Feature",
  "properties": {
    "addr:full":"2406 Decker Blvd Columbia SC 29206",
    "addr:housenumber":"2406",
    "addr:postcode":"29206",
    "addr:street":"Decker Blvd",
    "iso:country":"US",
    "sg:address":"2406 Decker Blvd",
    "sg:city":"Columbia",
    "sg:classifiers":[
        {
            "category":"Health Services",
            "subcategory":"Doctor",
            "type":"Services"
        }
    ],
    "sg:phone":"+1 803 736 2530",
    "sg:postcode":"29206",
    "sg:province":"SC",
    "sg:tags":[
        "physician",
        "surgeon"
    ],
    "sg:website":"www.firstcaresc.com",
    "wof:name":"First Care",
    "wof:placetype":"venue"
},
  "geometry": {"coordinates":[-80.948339,34.055388],"type":"Point"}
}