{
  "type": "Feature",
  "properties": {
    "iso:country":"US",
    "sg:address":"62 Arrow Rd",
    "sg:city":"Hilton Head Isle",
    "sg:classifiers":[
        {
            "category":"Professional",
            "subcategory":"Accounting & Tax Preparation",
            "type":"Services"
        }
    ],
    "sg:phone":"+1 843 785 4655",
    "sg:postcode":"29928",
    "sg:province":"SC",
    "sg:tags":[
        "accountant"
    ],
    "wof:name":"Aikman & Roberts",
    "wof:placetype":"venue"
},
  "geometry": {"coordinates":[-80.7595,32.156868],"type":"Point"}
}