{
  "type": "Feature",
  "properties": {
    "iso:country":"US",
    "sg:address":"631 Columbia Rd",
    "sg:city":"Chester",
    "sg:classifiers":[
        {
            "category":"Retail",
            "subcategory":"Auto Repair",
            "type":"Services"
        }
    ],
    "sg:phone":"+1 803 385 6023",
    "sg:postcode":"29706",
    "sg:province":"SC",
    "sg:tags":[
        "repairing",
        "automobile"
    ],
    "wof:name":"Mike's Auto Clinic",
    "wof:placetype":"venue"
},
  "geometry": {"coordinates":[-81.19662599999999,34.689858],"type":"Point"}
}