{
  "type": "Feature",
  "properties": {
    "iso:country":"US",
    "sg:address":"111 James Rd",
    "sg:city":"Allendale",
    "sg:classifiers":[
        {
            "category":"Government",
            "subcategory":"Office",
            "type":"Public Place"
        }
    ],
    "sg:phone":"+1 803 584 4234",
    "sg:postcode":"29803",
    "sg:province":"SC",
    "sg:tags":[
        "federal"
    ],
    "wof:name":"Natural Resources Conservation",
    "wof:placetype":"venue"
},
  "geometry": {"coordinates":[-81.73835200000001,33.397241],"type":"Point"}
}