{
  "type": "Feature",
  "properties": {
    "addr:full":"5150 Hwy 81 N Williamston SC 29697",
    "addr:housenumber":"5150",
    "addr:postcode":"29697",
    "addr:street":"Hwy 81 N",
    "iso:country":"US",
    "sg:address":"5150 Hwy 81 N",
    "sg:city":"Williamston",
    "sg:classifiers":[
        {
            "category":"Government",
            "subcategory":"Fire Station",
            "type":"Public Place"
        }
    ],
    "sg:phone":"+1 864 224 6679",
    "sg:postcode":"29697",
    "sg:province":"SC",
    "sg:tags":[
        "department"
    ],
    "wof:name":"Piercetown Fire Department",
    "wof:placetype":"venue"
},
  "geometry": {"coordinates":[-82.593277,34.65622],"type":"Point"}
}