{
  "type": "Feature",
  "properties": {
    "iso:country":"US",
    "sg:address":"249 Old Summerville Rd",
    "sg:city":"Summerville",
    "sg:classifiers":[
        {
            "category":"Retail",
            "subcategory":"Auto Repair",
            "type":"Services"
        }
    ],
    "sg:phone":"+1 843 832 6880",
    "sg:postcode":"29483",
    "sg:province":"SC",
    "sg:tags":[
        "wrecker"
    ],
    "wof:name":"Professional Auto Recovery",
    "wof:placetype":"venue"
},
  "geometry": {"coordinates":[-80.113626,33.04789],"type":"Point"}
}