{
  "type": "Feature",
  "properties": {
    "addr:full":"10 Sea Olive Rd Beaufort SC 29928",
    "addr:housenumber":"10",
    "addr:postcode":"29928",
    "addr:street":"Sea Olive Rd",
    "iso:country":"US",
    "sg:address":"10 Sea Olive Rd",
    "sg:city":"Beaufort",
    "sg:classifiers":[
        {
            "category":"Freight",
            "type":"Transportation"
        }
    ],
    "sg:phone":"+1 843 846 9497",
    "sg:postcode":"29928",
    "sg:province":"SC",
    "sg:tags":[
        "commercial",
        "storage"
    ],
    "wof:name":"Atlantic Self Storage",
    "wof:placetype":"venue"
},
  "geometry": {"coordinates":[-80.786461,32.15962],"type":"Point"}
}