{
  "type": "Feature",
  "properties": {
    "addr:full":"252 Harbison Blvd Columbia SC 29212",
    "addr:housenumber":"252",
    "addr:postcode":"29212",
    "addr:street":"Harbison Blvd",
    "iso:country":"US",
    "sg:address":"252 Harbison Blvd",
    "sg:city":"Columbia",
    "sg:classifiers":[
        {
            "category":"Shopping",
            "subcategory":"Stationery & Office Supplies",
            "type":"Retail Goods"
        }
    ],
    "sg:phone":"+1 803 749 2777",
    "sg:postcode":"29212",
    "sg:province":"SC",
    "wof:name":"Office Max",
    "wof:placetype":"venue"
},
  "geometry": {"coordinates":[-81.16111600000001,34.071337],"type":"Point"}
}