{
  "type": "Feature",
  "properties": {
    "addr:full":"1 Manus Cir Lexington SC 29073",
    "addr:housenumber":"1",
    "addr:postcode":"29073",
    "addr:street":"Manus Cir",
    "iso:country":"US",
    "sg:address":"1 Manus Cir",
    "sg:city":"Lexington",
    "sg:classifiers":[
        {
            "category":"Organizations",
            "subcategory":"Non-profit Organization",
            "type":"Services"
        }
    ],
    "sg:phone":"+1 803 356 6610",
    "sg:postcode":"29073",
    "sg:province":"SC",
    "sg:tags":[
        "information",
        "alcoholism",
        "treatment"
    ],
    "wof:name":"Tabs Ministries",
    "wof:placetype":"venue"
},
  "geometry": {"coordinates":[-81.231326,33.940388],"type":"Point"}
}