{
  "type": "Feature",
  "properties": {
    "iso:country":"US",
    "sg:address":"354 Riverchase Way",
    "sg:city":"Lexington",
    "sg:classifiers":[
        {
            "category":"Building & Trades",
            "subcategory":"Construction",
            "type":"Services"
        }
    ],
    "sg:phone":"+1 803 796 8447",
    "sg:postcode":"29072",
    "sg:province":"SC",
    "sg:tags":[
        "concrete",
        "contractor"
    ],
    "wof:name":"Hydroshield",
    "wof:placetype":"venue"
},
  "geometry": {"coordinates":[-81.133605,34.022916],"type":"Point"}
}