{
  "type": "Feature",
  "properties": {
    "addr:full":"1320 Richland Ave W Aiken SC 29801",
    "addr:housenumber":"1320",
    "addr:postcode":"29801",
    "addr:street":"Richland Ave W",
    "iso:country":"US",
    "sg:address":"1320 Richland Ave W",
    "sg:city":"Aiken",
    "sg:classifiers":[
        {
            "category":"Real Estate",
            "subcategory":"Real Estate Services",
            "type":"Services"
        }
    ],
    "sg:phone":"+1 803 502 2435",
    "sg:postcode":"29801",
    "sg:province":"SC",
    "sg:tags":[
        "company",
        "title"
    ],
    "wof:name":"Titlemax Of Aiken",
    "wof:placetype":"venue"
},
  "geometry": {"coordinates":[-81.736868,33.565963],"type":"Point"}
}