{
  "type": "Feature",
  "properties": {
    "iso:country":"US",
    "sg:address":"2070 Sam Rittenberg Blvd",
    "sg:city":"Charleston",
    "sg:classifiers":[
        {
            "category":"Shopping",
            "type":"Retail Goods"
        }
    ],
    "sg:phone":"+1 843 852 9157",
    "sg:postcode":"29407",
    "sg:province":"SC",
    "sg:tags":[
        "sunglasses",
        "accessory"
    ],
    "wof:name":"Sunglass Hut 2344",
    "wof:placetype":"venue"
},
  "geometry": {"coordinates":[-80.03057099999999,32.792449],"type":"Point"}
}