{
  "type": "Feature",
  "properties": {
    "addr:full":"784 Easley Bridge Rd Greenville SC 29611",
    "addr:housenumber":"784",
    "addr:postcode":"29611",
    "addr:street":"Easley Bridge Rd",
    "iso:country":"US",
    "sg:address":"784 Easley Bridge Rd",
    "sg:city":"Greenville",
    "sg:classifiers":[
        {
            "category":"Autos & Motor Vehicles",
            "subcategory":"Fuel & Gas Station",
            "type":"Retail Goods"
        }
    ],
    "sg:phone":"+1 864 269 7124",
    "sg:postcode":"29611",
    "sg:province":"SC",
    "sg:tags":[
        "grocery",
        "station",
        "gasoline",
        "oil"
    ],
    "wof:name":"Piedmont Petroleum Corp",
    "wof:placetype":"venue"
},
  "geometry": {"coordinates":[-82.428231,34.838807],"type":"Point"}
}