{
  "type": "Feature",
  "properties": {
    "iso:country":"US",
    "sg:address":"14 Flint Hill Rd",
    "sg:city":"Irmo",
    "sg:classifiers":[
        {
            "category":"Building & Trades",
            "subcategory":"Landscaping Services",
            "type":"Services"
        }
    ],
    "sg:phone":"+1 803 732 8955",
    "sg:postcode":"29063",
    "sg:province":"SC",
    "sg:tags":[
        "landscape"
    ],
    "wof:name":"Baxter Landscaping",
    "wof:placetype":"venue"
},
  "geometry": {"coordinates":[-81.156786,34.138269],"type":"Point"}
}