{
  "type": "Feature",
  "properties": {
    "iso:country":"US",
    "sg:address":"1212 Kershaw Camden Hwy",
    "sg:city":"Lancaster",
    "sg:classifiers":[
        {
            "category":"Retail",
            "subcategory":"Auto Repair",
            "type":"Services"
        }
    ],
    "sg:phone":"+1 803 285 4005",
    "sg:postcode":"29720",
    "sg:province":"SC",
    "sg:tags":[
        "repairing",
        "automobile"
    ],
    "wof:name":"Kelley's Automotive",
    "wof:placetype":"venue"
},
  "geometry": {"coordinates":[-80.757225,34.70331],"type":"Point"}
}