{
  "type": "Feature",
  "properties": {
    "addr:full":"510 W Cheves St Florence SC 29501",
    "addr:housenumber":"510",
    "addr:postcode":"29501",
    "addr:street":"W Cheves St",
    "iso:country":"US",
    "sg:address":"510 W Cheves St",
    "sg:city":"Florence",
    "sg:classifiers":[
        {
            "category":"Shopping",
            "subcategory":"Gifts & Souvenirs",
            "type":"Retail Goods"
        }
    ],
    "sg:phone":"+1 843 676 9077",
    "sg:postcode":"29501",
    "sg:province":"SC",
    "sg:tags":[
        "announcement",
        "invitation"
    ],
    "wof:name":"News Flash Affordable Printing",
    "wof:placetype":"venue"
},
  "geometry": {"coordinates":[-79.775841,34.195],"type":"Point"}
}