{
  "type": "Feature",
  "properties": {
    "iso:country":"US",
    "sg:address":"501 Worchester Pl",
    "sg:city":"Simpsonville",
    "sg:classifiers":[
        {
            "category":"Shopping",
            "subcategory":"Pharmacy",
            "type":"Retail Goods"
        }
    ],
    "sg:phone":"+1 864 967 2351",
    "sg:postcode":"29680",
    "sg:province":"SC",
    "wof:name":"Walgreens",
    "wof:placetype":"venue"
},
  "geometry": {"coordinates":[-82.28191099999999,34.706965],"type":"Point"}
}