{
  "type": "Feature",
  "properties": {
    "iso:country":"US",
    "sg:address":"85 Vincent Dr",
    "sg:city":"Mount Pleasant",
    "sg:classifiers":[
        {
            "category":"Shopping",
            "subcategory":"Crafts & Fabrics",
            "type":"Retail Goods"
        }
    ],
    "sg:phone":"+1 843 881 3771",
    "sg:postcode":"29464",
    "sg:province":"SC",
    "sg:tags":[
        "piece"
    ],
    "wof:name":"B Picky",
    "wof:placetype":"venue"
},
  "geometry": {"coordinates":[-79.866619,32.793446],"type":"Point"}
}