{
  "type": "Feature",
  "properties": {
    "iso:country":"US",
    "sg:address":"3729 Rosewood Dr",
    "sg:city":"Columbia",
    "sg:classifiers":[
        {
            "category":"Shopping",
            "subcategory":"Pharmacy",
            "type":"Retail Goods"
        }
    ],
    "sg:phone":"+1 803 231 2003",
    "sg:postcode":"29205",
    "sg:province":"SC",
    "sg:tags":[
        "drugstore"
    ],
    "wof:name":"Medicine Mart Pharmacy",
    "wof:placetype":"venue"
},
  "geometry": {"coordinates":[-80.988899,33.987999],"type":"Point"}
}