{
  "type": "Feature",
  "properties": {
    "addr:full":"3392 Phillis Blvd Myrtle Beach SC 29577",
    "addr:housenumber":"3392",
    "addr:postcode":"29577",
    "addr:street":"Phillis Blvd",
    "iso:country":"US",
    "sg:address":"3392 Phillis Blvd",
    "sg:city":"Myrtle Beach",
    "sg:classifiers":[
        {
            "category":"Government",
            "subcategory":"Office",
            "type":"Public Place"
        }
    ],
    "sg:phone":"+1 843 477 8727",
    "sg:postcode":"29577",
    "sg:province":"SC",
    "sg:tags":[
        "federal",
        "security"
    ],
    "wof:name":"US Army Reserve",
    "wof:placetype":"venue"
},
  "geometry": {"coordinates":[-78.93687,33.672135],"type":"Point"}
}