{
  "type": "Feature",
  "properties": {
    "addr:full":"311 Academy St Williston SC 29853",
    "addr:housenumber":"311",
    "addr:postcode":"29853",
    "addr:street":"Academy St",
    "iso:country":"US",
    "sg:address":"311 Academy St",
    "sg:city":"Williston",
    "sg:classifiers":[
        {
            "category":"Organizations",
            "subcategory":"Non-profit Organization",
            "type":"Services"
        }
    ],
    "sg:phone":"+1 803 266 4582",
    "sg:postcode":"29853",
    "sg:province":"SC",
    "sg:tags":[
        "disability"
    ],
    "wof:name":"Barnwell Iv Inc",
    "wof:placetype":"venue"
},
  "geometry": {"coordinates":[-81.42030200000001,33.403708],"type":"Point"}
}