{
  "type": "Feature",
  "properties": {
    "addr:full":"318 E Smith St Timmonsville SC 29161",
    "addr:housenumber":"318",
    "addr:postcode":"29161",
    "addr:street":"E Smith St",
    "iso:country":"US",
    "sg:address":"318 E Smith St",
    "sg:city":"Timmonsville",
    "sg:classifiers":[
        {
            "category":"Home & Garden",
            "subcategory":"Garden Supply",
            "type":"Retail Goods"
        }
    ],
    "sg:phone":"+1 843 346 3947",
    "sg:postcode":"29161",
    "sg:province":"SC",
    "sg:tags":[
        "lawn",
        "mower"
    ],
    "wof:name":"Depot",
    "wof:placetype":"venue"
},
  "geometry": {"coordinates":[-79.937371,34.13286],"type":"Point"}
}