{
  "type": "Feature",
  "properties": {
    "iso:country":"US",
    "sg:address":"46 N Jacob Smart Blvd",
    "sg:city":"Ridgeland",
    "sg:classifiers":[
        {
            "category":"Retail",
            "subcategory":"Auto Repair",
            "type":"Services"
        }
    ],
    "sg:phone":"+1 843 684 0426",
    "sg:postcode":"29936",
    "sg:province":"SC",
    "sg:tags":[
        "windshield"
    ],
    "wof:name":"White Water Auto Glass Service",
    "wof:placetype":"venue"
},
  "geometry": {"coordinates":[-80.975227,32.493641],"type":"Point"}
}