{
  "type": "Feature",
  "properties": {
    "iso:country":"US",
    "sg:address":"1752 Fulmer Rd",
    "sg:city":"Blythewood",
    "sg:classifiers":[
        {
            "category":"Building & Trades",
            "subcategory":"Construction",
            "type":"Services"
        }
    ],
    "sg:phone":"+1 803 691 0029",
    "sg:postcode":"29016",
    "sg:province":"SC",
    "sg:tags":[
        "house"
    ],
    "wof:name":"Boyd GL Construction Inc",
    "wof:placetype":"venue"
},
  "geometry": {"coordinates":[-81.011223,34.184611],"type":"Point"}
}