{
  "type": "Feature",
  "properties": {
    "addr:full":"5117 Great Falls Hwy Great Falls SC 29055",
    "addr:housenumber":"5117",
    "addr:postcode":"29055",
    "addr:street":"Great Falls Hwy",
    "iso:country":"US",
    "sg:address":"5117 Great Falls Hwy",
    "sg:city":"Great Falls",
    "sg:classifiers":[
        {
            "category":"Retail",
            "subcategory":"Auto Repair",
            "type":"Services"
        }
    ],
    "sg:phone":"+1 803 482 2766",
    "sg:postcode":"29055",
    "sg:province":"SC",
    "sg:tags":[
        "repairing",
        "automobile"
    ],
    "wof:name":"Lee Automotive",
    "wof:placetype":"venue"
},
  "geometry": {"coordinates":[-80.932654,34.592366],"type":"Point"}
}