{
  "type": "Feature",
  "properties": {
    "iso:country":"US",
    "sg:address":"5219 Augusta Rd",
    "sg:city":"Lexington",
    "sg:classifiers":[
        {
            "category":"Building & Trades",
            "subcategory":"Construction",
            "type":"Services"
        }
    ],
    "sg:phone":"+1 803 957 6500",
    "sg:postcode":"29072",
    "sg:province":"SC",
    "sg:tags":[
        "masonry",
        "contractor"
    ],
    "wof:name":"Sam Temples Masonary Inc",
    "wof:placetype":"venue"
},
  "geometry": {"coordinates":[-81.209958,33.975978],"type":"Point"}
}