{
  "type": "Feature",
  "properties": {
    "iso:country":"US",
    "sg:address":"1665 Herlong Ct",
    "sg:city":"Rock Hill",
    "sg:classifiers":[
        {
            "category":"Health Services",
            "subcategory":"Health Practitioner",
            "type":"Services"
        }
    ],
    "sg:phone":"+1 803 328 0030",
    "sg:postcode":"29732",
    "sg:province":"SC",
    "sg:tags":[
        "psychologist"
    ],
    "wof:name":"Piedmont Psychological Counsel",
    "wof:placetype":"venue"
},
  "geometry": {"coordinates":[-81.05334000000001,34.954699],"type":"Point"}
}