{
  "type": "Feature",
  "properties": {
    "iso:country":"US",
    "sg:address":"11 Crosstree Ct",
    "sg:city":"Greenville",
    "sg:classifiers":[
        {
            "category":"Building & Trades",
            "subcategory":"Cleaning & Sanitation",
            "type":"Services"
        }
    ],
    "sg:phone":"+1 864 834 7828",
    "sg:postcode":"29609",
    "sg:province":"SC",
    "sg:tags":[
        "window"
    ],
    "wof:name":"Pro-Shine Window Cleaning",
    "wof:placetype":"venue"
},
  "geometry": {"coordinates":[-82.365045,34.961699],"type":"Point"}
}