{
  "type": "Feature",
  "properties": {
    "addr:full":"11 Crosstree Ct Greenville SC 29609",
    "addr:housenumber":"11",
    "addr:postcode":"29609",
    "addr:street":"Crosstree Ct",
    "iso:country":"US",
    "sg:address":"11 Crosstree Ct",
    "sg:city":"Greenville",
    "sg:classifiers":[
        {
            "category":"Building & Trades",
            "subcategory":"Cleaning & Sanitation",
            "type":"Services"
        }
    ],
    "sg:phone":"+1 864 834 7828",
    "sg:postcode":"29609",
    "sg:province":"SC",
    "sg:tags":[
        "window"
    ],
    "wof:name":"Pro-Shine Window Cleaning",
    "wof:placetype":"venue"
},
  "geometry": {"coordinates":[-82.36504499999999,34.961699],"type":"Point"}
}