{
  "type": "Feature",
  "properties": {
    "addr:full":"111 Glenmont Ln Greenville SC 29607",
    "addr:housenumber":"111",
    "addr:postcode":"29607",
    "addr:street":"Glenmont Ln",
    "iso:country":"US",
    "sg:address":"111 Glenmont Ln",
    "sg:city":"Greenville",
    "sg:classifiers":[
        {
            "category":"Food & Beverages",
            "subcategory":"Bakery",
            "type":"Retail Goods"
        }
    ],
    "sg:phone":"+1 864 286 8555",
    "sg:postcode":"29607",
    "sg:province":"SC",
    "wof:name":"Atlanta Bread Company",
    "wof:placetype":"venue"
},
  "geometry": {"coordinates":[-82.304613,34.811671],"type":"Point"}
}