{
  "type": "Feature",
  "properties": {
    "iso:country":"US",
    "sg:address":"144 Woodvine Rd",
    "sg:city":"Aiken",
    "sg:classifiers":[
        {
            "category":"Building & Trades",
            "subcategory":"Plumbing",
            "type":"Services"
        }
    ],
    "sg:phone":"+1 803 649 1260",
    "sg:postcode":"29803",
    "sg:province":"SC",
    "sg:tags":[
        "conditioning",
        "air",
        "system",
        "contractor"
    ],
    "wof:name":"Wayne's Heating & Air Cond",
    "wof:placetype":"venue"
},
  "geometry": {"coordinates":[-81.687721,33.463674],"type":"Point"}
}