{
  "type": "Feature",
  "properties": {
    "iso:country":"US",
    "sg:address":"799 Rutherfordton Hwy",
    "sg:city":"Chesnee",
    "sg:classifiers":[
        {
            "category":"Shopping",
            "type":"Retail Goods"
        }
    ],
    "sg:phone":"+1 864 461 5508",
    "sg:postcode":"29323",
    "sg:province":"SC",
    "sg:tags":[
        "merchandise"
    ],
    "wof:name":"Patriot Fireworks",
    "wof:placetype":"venue"
},
  "geometry": {"coordinates":[-81.844156,35.165249],"type":"Point"}
}