{
  "type": "Feature",
  "properties": {
    "addr:full":"2881 Main St Newberry SC 29108",
    "addr:housenumber":"2881",
    "addr:postcode":"29108",
    "addr:street":"Main St",
    "iso:country":"US",
    "sg:address":"2881 Main St",
    "sg:city":"Newberry",
    "sg:classifiers":[
        {
            "category":"Shopping",
            "subcategory":"Discount & Variety Stores",
            "type":"Retail Goods"
        }
    ],
    "sg:phone":"+1 803 276 0781",
    "sg:postcode":"29108",
    "sg:province":"SC",
    "wof:name":"Dollar Pit",
    "wof:placetype":"venue"
},
  "geometry": {"coordinates":[-81.59000399999999,34.282765],"type":"Point"}
}