{
  "type": "Feature",
  "properties": {
    "iso:country":"US",
    "sg:address":"163 Amanda Ct",
    "sg:city":"Aiken",
    "sg:classifiers":[
        {
            "category":"Building & Trades",
            "subcategory":"Landscaping Services",
            "type":"Services"
        }
    ],
    "sg:phone":"+1 803 648 7194",
    "sg:postcode":"29803",
    "sg:province":"SC",
    "sg:tags":[
        "designer",
        "landscape"
    ],
    "wof:name":"Custom Design Landscape & Lawn",
    "wof:placetype":"venue"
},
  "geometry": {"coordinates":[-81.671177,33.533018],"type":"Point"}
}