{
  "type": "Feature",
  "properties": {
    "iso:country":"US",
    "sg:address":"1503 Woodruff Rd",
    "sg:city":"Greenville",
    "sg:classifiers":[
        {
            "category":"Autos & Motor Vehicles",
            "subcategory":"Auto Supplies",
            "type":"Retail Goods"
        }
    ],
    "sg:phone":"+1 864 288 1116",
    "sg:postcode":"29607",
    "sg:province":"SC",
    "sg:tags":[
        "tire"
    ],
    "wof:name":"Tire Kingdom",
    "wof:placetype":"venue"
},
  "geometry": {"coordinates":[-82.278777,34.820178],"type":"Point"}
}