{
  "type": "Feature",
  "properties": {
    "iso:country":"US",
    "sg:address":"2404 Madison Dr",
    "sg:city":"North Myrtle Bch",
    "sg:classifiers":[
        {
            "category":"Manufacturing",
            "subcategory":"Printing",
            "type":"Manufacturing & Wholesale Goods"
        }
    ],
    "sg:phone":"+1 843 272 5776",
    "sg:postcode":"29582",
    "sg:province":"SC",
    "sg:tags":[
        "commercial"
    ],
    "wof:name":"Rountree Printing Co",
    "wof:placetype":"venue"
},
  "geometry": {"coordinates":[-78.713787,33.807038],"type":"Point"}
}