{
  "type": "Feature",
  "properties": {
    "iso:country":"US",
    "sg:address":"577 Bultman Dr",
    "sg:city":"Sumter",
    "sg:classifiers":[
        {
            "category":"Wholesale",
            "subcategory":"Non-durable Goods",
            "type":"Manufacturing & Wholesale Goods"
        },
        {
            "category":"Shopping",
            "subcategory":"Gifts & Souvenirs",
            "type":"Retail Goods"
        }
    ],
    "sg:phone":"+1 803 775 0274",
    "sg:postcode":"29150",
    "sg:province":"SC",
    "sg:tags":[
        "shop",
        "garden"
    ],
    "wof:name":"Window Box",
    "wof:placetype":"venue"
},
  "geometry": {"coordinates":[-80.370938,33.936325],"type":"Point"}
}