{
  "type": "Feature",
  "properties": {
    "addr:full":"4131 Flynn Dr North Charleston SC 29405",
    "addr:housenumber":"4131",
    "addr:postcode":"29405",
    "addr:street":"Flynn Dr",
    "iso:country":"US",
    "sg:address":"4131 Flynn Dr",
    "sg:city":"North Charleston",
    "sg:classifiers":[
        {
            "category":"Recreation",
            "type":"Entertainment"
        }
    ],
    "sg:phone":"+1 843 412 6776",
    "sg:postcode":"29405",
    "sg:province":"SC",
    "sg:tags":[
        "guide"
    ],
    "sg:website":"www.charlestonangler.com",
    "wof:name":"Captain Rick Hiott's Fishing",
    "wof:placetype":"venue"
},
  "geometry": {"coordinates":[-80.02729100000001,32.853778],"type":"Point"}
}