{
  "type": "Feature",
  "properties": {
    "iso:country":"US",
    "sg:address":"225 Ballpark Rd",
    "sg:city":"Scranton",
    "sg:classifiers":[
        {
            "category":"Organizations",
            "subcategory":"Religious Organization",
            "type":"Services"
        }
    ],
    "sg:phone":"+1 843 389 9801",
    "sg:postcode":"29591",
    "sg:province":"SC",
    "sg:tags":[
        "clergy"
    ],
    "wof:name":"Stoney Wrenn",
    "wof:placetype":"venue"
},
  "geometry": {"coordinates":[-79.74150299999999,33.918932],"type":"Point"}
}