{
  "type": "Feature",
  "properties": {
    "iso:country":"US",
    "sg:address":"133 Centerville Rd",
    "sg:city":"Gilbert",
    "sg:classifiers":[
        {
            "category":"Building & Trades",
            "subcategory":"Construction",
            "type":"Services"
        }
    ],
    "sg:phone":"+1 803 892 2979",
    "sg:postcode":"29054",
    "sg:province":"SC",
    "sg:tags":[
        "contractor"
    ],
    "wof:name":"Sids Cabinet & Interior Trim",
    "wof:placetype":"venue"
},
  "geometry": {"coordinates":[-81.397227,33.960802],"type":"Point"}
}