{
  "type": "Feature",
  "properties": {
    "iso:country":"US",
    "sg:address":"1944 W Evans St",
    "sg:city":"Florence",
    "sg:phone":"+1 843 662 7199",
    "sg:postcode":"29501",
    "sg:province":"SC",
    "sg:tags":[
        "gas"
    ],
    "wof:name":"Suburban Propane",
    "wof:placetype":"venue"
},
  "geometry": {"coordinates":[-79.80608599999999,34.194545],"type":"Point"}
}