{
  "type": "Feature",
  "properties": {
    "addr:full":"1065 Meadow Woods Rd Buffalo SC 29321",
    "addr:housenumber":"1065",
    "addr:postcode":"29321",
    "addr:street":"Meadow Woods Rd",
    "iso:country":"US",
    "sg:address":"1065 Meadow Woods Rd",
    "sg:city":"Buffalo",
    "sg:classifiers":[
        {
            "category":"Communications",
            "type":"Services"
        }
    ],
    "sg:phone":"+1 864 429 4975",
    "sg:postcode":"29321",
    "sg:province":"SC",
    "sg:tags":[
        "communication"
    ],
    "wof:name":"Webspyder Communications",
    "wof:placetype":"venue"
},
  "geometry": {"coordinates":[-81.735241,34.701146],"type":"Point"}
}