{
  "type": "Feature",
  "properties": {
    "iso:country":"US",
    "sg:address":"117 Ramsey Hts",
    "sg:city":"Gaffney",
    "sg:classifiers":[
        {
            "category":"Shopping",
            "subcategory":"Department Store",
            "type":"Retail Goods"
        }
    ],
    "sg:phone":"+1 864 489 7490",
    "sg:postcode":"29340",
    "sg:province":"SC",
    "wof:name":"Harrills Reloading Gun",
    "wof:placetype":"venue"
},
  "geometry": {"coordinates":[-81.610513,35.068774],"type":"Point"}
}