{
  "type": "Feature",
  "properties": {
    "iso:country":"US",
    "sg:address":"4617 Forest Dr",
    "sg:city":"Columbia",
    "sg:classifiers":[
        {
            "category":"Travel",
            "subcategory":"Travel Agent",
            "type":"Entertainment"
        }
    ],
    "sg:phone":"+1 803 738 1520",
    "sg:postcode":"29206",
    "sg:province":"SC",
    "sg:tags":[
        "agency",
        "bureau"
    ],
    "sg:website":"www.forestlaketravel.net",
    "wof:name":"Forest Lake Travel Svc",
    "wof:placetype":"venue"
},
  "geometry": {"coordinates":[-80.973632,34.020883],"type":"Point"}
}