{
  "type": "Feature",
  "properties": {
    "iso:country":"US",
    "sg:address":"9915 N Kings Hwy",
    "sg:city":"Myrtle Beach",
    "sg:classifiers":[
        {
            "category":"Professional",
            "type":"Services"
        }
    ],
    "sg:phone":"+1 843 449 5933",
    "sg:postcode":"29572",
    "sg:province":"SC",
    "sg:tags":[
        "establishment"
    ],
    "wof:name":"Farmer's Daughter Country",
    "wof:placetype":"venue"
},
  "geometry": {"coordinates":[-78.785847,33.783575],"type":"Point"}
}