{
  "type": "Feature",
  "properties": {
    "iso:country":"US",
    "sg:address":"1340 Libby Ariail Cir",
    "sg:city":"Chapin",
    "sg:classifiers":[
        {
            "category":"Wholesale",
            "subcategory":"Home Furnishings",
            "type":"Manufacturing & Wholesale Goods"
        }
    ],
    "sg:phone":"+1 803 932 2124",
    "sg:postcode":"29036",
    "sg:province":"SC",
    "wof:name":"Artes Ventures LLC",
    "wof:placetype":"venue"
},
  "geometry": {"coordinates":[-81.324671,34.084104],"type":"Point"}
}