{
  "type": "Feature",
  "properties": {
    "iso:country":"US",
    "sg:address":"205 Pineturn Ln",
    "sg:city":"Gaston",
    "sg:classifiers":[
        {
            "category":"Shopping",
            "subcategory":"Used Merchandise",
            "type":"Retail Goods"
        }
    ],
    "sg:phone":"+1 803 791 9600",
    "sg:postcode":"29053",
    "sg:province":"SC",
    "sg:tags":[
        "shop",
        "thrift"
    ],
    "wof:name":"Blessings Families Outreach",
    "wof:placetype":"venue"
},
  "geometry": {"coordinates":[-81.112008,33.834861],"type":"Point"}
}