{
  "type": "Feature",
  "properties": {
    "addr:full":"11353 Augusta Rd Honea Path SC 29669",
    "addr:housenumber":"11353",
    "addr:postcode":"29669",
    "addr:street":"Augusta Rd",
    "iso:country":"US",
    "sg:address":"11353 Augusta Rd",
    "sg:city":"Honea Path",
    "sg:classifiers":[
        {
            "category":"Government",
            "subcategory":"Fire Station",
            "type":"Public Place"
        }
    ],
    "sg:phone":"+1 864 369 9993",
    "sg:postcode":"29669",
    "sg:province":"SC",
    "sg:tags":[
        "department"
    ],
    "wof:name":"Dunklin Fire District",
    "wof:placetype":"venue"
},
  "geometry": {"coordinates":[-82.336521,34.577237],"type":"Point"}
}