{
  "type": "Feature",
  "properties": {
    "iso:country":"US",
    "sg:address":"800 Chevis St",
    "sg:city":"Columbia",
    "sg:classifiers":[
        {
            "category":"Building & Trades",
            "subcategory":"Construction",
            "type":"Services"
        }
    ],
    "sg:phone":"+1 803 771 7462",
    "sg:postcode":"29205",
    "sg:province":"SC",
    "sg:tags":[
        "concrete",
        "contractor"
    ],
    "wof:name":"Jjb Flooring LLC",
    "wof:placetype":"venue"
},
  "geometry": {"coordinates":[-80.985672,33.978908],"type":"Point"}
}