{
  "type": "Feature",
  "properties": {
    "iso:country":"US",
    "sg:address":"425 Thompson Rd",
    "sg:city":"Taylors",
    "sg:classifiers":[
        {
            "category":"Building & Trades",
            "subcategory":"Construction",
            "type":"Services"
        }
    ],
    "sg:phone":"+1 864 895 5111",
    "sg:postcode":"29687",
    "sg:province":"SC",
    "sg:tags":[
        "restoration",
        "cleaning",
        "patio",
        "deck"
    ],
    "wof:name":"Carolina Pressure Clean Inc",
    "wof:placetype":"venue"
},
  "geometry": {"coordinates":[-82.353374,35.013444],"type":"Point"}
}