{
  "type": "Feature",
  "properties": {
    "addr:full":"417 E Main St Union SC 29379",
    "addr:housenumber":"417",
    "addr:postcode":"29379",
    "addr:street":"E Main St",
    "iso:country":"US",
    "sg:address":"417 E Main St",
    "sg:city":"Union",
    "sg:classifiers":[
        {
            "category":"Health Services",
            "subcategory":"Doctor",
            "type":"Services"
        }
    ],
    "sg:phone":"+1 864 427 0311",
    "sg:postcode":"29379",
    "sg:province":"SC",
    "sg:tags":[
        "dentist"
    ],
    "wof:name":"Talmadge D Wilkins III DDS",
    "wof:placetype":"venue"
},
  "geometry": {"coordinates":[-81.61913,34.715692],"type":"Point"}
}