{
  "type": "Feature",
  "properties": {
    "iso:country":"US",
    "sg:address":"66 Hanover St",
    "sg:city":"Charleston",
    "sg:classifiers":[
        {
            "category":"Organizations",
            "subcategory":"Religious Organization",
            "type":"Services"
        }
    ],
    "sg:phone":"+1 843 723 3517",
    "sg:postcode":"29403",
    "sg:province":"SC",
    "sg:tags":[
        "church"
    ],
    "wof:name":"Vanderhorst Memorial Christian",
    "wof:placetype":"venue"
},
  "geometry": {"coordinates":[-79.937656,32.79579],"type":"Point"}
}