{
  "type": "Feature",
  "properties": {
    "iso:country":"US",
    "sg:address":"684 US Hwy 1",
    "sg:city":"Lugoff",
    "sg:classifiers":[
        {
            "category":"Banks & Credit Unions",
            "subcategory":"Bank",
            "type":"Services"
        }
    ],
    "sg:phone":"+1 803 438 5500",
    "sg:postcode":"29078",
    "sg:province":"SC",
    "sg:tags":[
        "financing"
    ],
    "wof:name":"Mortgage Finance Corp",
    "wof:placetype":"venue"
},
  "geometry": {"coordinates":[-80.664211,34.235775],"type":"Point"}
}