{
  "type": "Feature",
  "properties": {
    "iso:country":"US",
    "sg:address":"684 Fairview Rd",
    "sg:city":"Simpsonville",
    "sg:classifiers":[
        {
            "category":"Restaurant",
            "type":"Food & Drink"
        }
    ],
    "sg:phone":"+1 864 963 7353",
    "sg:postcode":"29680",
    "sg:province":"SC",
    "sg:tags":[
        "eating"
    ],
    "wof:name":"Morgan's Restaurant",
    "wof:placetype":"venue"
},
  "geometry": {"coordinates":[-82.257993,34.705192],"type":"Point"}
}