{
  "type": "Feature",
  "properties": {
    "addr:full":"109 Moore St Abbeville SC 29620",
    "addr:housenumber":"109",
    "addr:postcode":"29620",
    "addr:street":"Moore St",
    "iso:country":"US",
    "sg:address":"109 Moore St",
    "sg:city":"Abbeville",
    "sg:classifiers":[
        {
            "category":"Real Estate",
            "subcategory":"Developer",
            "type":"Services"
        }
    ],
    "sg:phone":"+1 864 459 4431",
    "sg:postcode":"29620",
    "sg:province":"SC",
    "sg:tags":[
        "cemetery"
    ],
    "wof:name":"Melrose Cemetery Assn",
    "wof:placetype":"venue"
},
  "geometry": {"coordinates":[-82.36936300000001,34.163803],"type":"Point"}
}