{
  "type": "Feature",
  "properties": {
    "addr:full":"709 Hwy 301 N Dillon SC 29536",
    "addr:housenumber":"709",
    "addr:postcode":"29536",
    "addr:street":"Hwy 301 N",
    "iso:country":"US",
    "sg:address":"709 Hwy 301 N",
    "sg:city":"Dillon",
    "sg:classifiers":[
        {
            "category":"Autos & Motor Vehicles",
            "subcategory":"Fuel & Gas Station",
            "type":"Retail Goods"
        }
    ],
    "sg:phone":"+1 843 774 2307",
    "sg:postcode":"29536",
    "sg:province":"SC",
    "sg:tags":[
        "oil"
    ],
    "wof:name":"Ed F Hodges Svc Station Inc",
    "wof:placetype":"venue"
},
  "geometry": {"coordinates":[-79.366574,34.422623],"type":"Point"}
}