{
  "type": "Feature",
  "properties": {
    "iso:country":"US",
    "sg:address":"5925 Savannah Hwy",
    "sg:city":"Ravenel",
    "sg:classifiers":[
        {
            "category":"Shopping",
            "subcategory":"Discount & Variety Stores",
            "type":"Retail Goods"
        }
    ],
    "sg:phone":"+1 843 889 1281",
    "sg:postcode":"29470",
    "sg:province":"SC",
    "wof:name":"Variety Shop",
    "wof:placetype":"venue"
},
  "geometry": {"coordinates":[-80.228737,32.779897],"type":"Point"}
}