{
  "type": "Feature",
  "properties": {
    "iso:country":"US",
    "sg:address":"65 Gadsden St",
    "sg:city":"Charleston",
    "sg:classifiers":[
        {
            "category":"Health Services",
            "subcategory":"Doctor",
            "type":"Services"
        }
    ],
    "sg:phone":"+1 843 723 9338",
    "sg:postcode":"29401",
    "sg:province":"SC",
    "sg:tags":[
        "physician",
        "surgeon"
    ],
    "wof:name":"Fredric D Schuh MD",
    "wof:placetype":"venue"
},
  "geometry": {"coordinates":[-79.946519,32.782128],"type":"Point"}
}