{
  "type": "Feature",
  "properties": {
    "addr:full":"12 Pine Knot Rd Lugoff SC 29078",
    "addr:housenumber":"12",
    "addr:postcode":"29078",
    "addr:street":"Pine Knot Rd",
    "iso:country":"US",
    "sg:address":"12 Pine Knot Rd",
    "sg:city":"Lugoff",
    "sg:classifiers":[
        {
            "category":"Building & Trades",
            "subcategory":"Electrical",
            "type":"Services"
        }
    ],
    "sg:phone":"+1 803 408 0935",
    "sg:postcode":"29078",
    "sg:province":"SC",
    "sg:tags":[
        "electrical",
        "contractor"
    ],
    "wof:name":"C Hedrick Contracting",
    "wof:placetype":"venue"
},
  "geometry": {"coordinates":[-80.73598200000001,34.216996],"type":"Point"}
}