{
  "type": "Feature",
  "properties": {
    "iso:country":"US",
    "sg:address":"1080 Fox Young Rd",
    "sg:city":"Wagener",
    "sg:classifiers":[
        {
            "category":"Retail",
            "subcategory":"Animal Services",
            "type":"Services"
        }
    ],
    "sg:phone":"+1 803 564 5931",
    "sg:postcode":"29164",
    "sg:province":"SC",
    "sg:tags":[
        "farm",
        "field",
        "crop"
    ],
    "wof:name":"Claddagh Farm",
    "wof:placetype":"venue"
},
  "geometry": {"coordinates":[-81.41319300000001,33.632769],"type":"Point"}
}