{
  "type": "Feature",
  "properties": {
    "iso:country":"US",
    "sg:address":"121 S Jones Rd",
    "sg:city":"Olanta",
    "sg:classifiers":[
        {
            "category":"Food & Beverages",
            "subcategory":"Meat & Fish",
            "type":"Retail Goods"
        }
    ],
    "sg:phone":"+1 843 396 4303",
    "sg:postcode":"29114",
    "sg:province":"SC",
    "sg:tags":[
        "seafood"
    ],
    "wof:name":"Olanta Fish Market LLC",
    "wof:placetype":"venue"
},
  "geometry": {"coordinates":[-79.935176,33.936445],"type":"Point"}
}