{
  "type": "Feature",
  "properties": {
    "iso:country":"US",
    "sg:address":"3745 Broad St",
    "sg:city":"Sumter",
    "sg:classifiers":[
        {
            "category":"Autos & Motor Vehicles",
            "subcategory":"Automobile Sales",
            "type":"Retail Goods"
        }
    ],
    "sg:phone":"+1 803 494 2201",
    "sg:postcode":"29154",
    "sg:province":"SC",
    "sg:tags":[
        "car",
        "dealer"
    ],
    "wof:name":"Roadhouse Customs",
    "wof:placetype":"venue"
},
  "geometry": {"coordinates":[-80.436851,33.964498],"type":"Point"}
}