{
  "type": "Feature",
  "properties": {
    "addr:full":"1136 E Blackstock Rd Moore SC 29369",
    "addr:housenumber":"1136",
    "addr:postcode":"29369",
    "addr:street":"E Blackstock Rd",
    "iso:country":"US",
    "sg:address":"1136 E Blackstock Rd",
    "sg:city":"Moore",
    "sg:classifiers":[
        {
            "category":"Restaurant",
            "type":"Food & Drink"
        }
    ],
    "sg:phone":"+1 864 576 0010",
    "sg:postcode":"29369",
    "sg:province":"SC",
    "wof:name":"Gwinn's Restaurant",
    "wof:placetype":"venue"
},
  "geometry": {"coordinates":[-81.97703300000001,34.905555],"type":"Point"}
}