{
  "type": "Feature",
  "properties": {
    "addr:full":"120 Station Dr Anderson SC 29624",
    "addr:housenumber":"120",
    "addr:postcode":"29624",
    "addr:street":"Station Dr",
    "iso:country":"US",
    "sg:address":"120 Station Dr",
    "sg:city":"Anderson",
    "sg:classifiers":[
        {
            "category":"Shopping",
            "subcategory":"Department Store",
            "type":"Retail Goods"
        }
    ],
    "sg:phone":"+1 864 222 1718",
    "sg:postcode":"29624",
    "sg:province":"SC",
    "sg:tags":[
        "shop"
    ],
    "wof:name":"Pier 1 Imports",
    "wof:placetype":"venue"
},
  "geometry": {"coordinates":[-82.695035,34.559573],"type":"Point"}
}