{
  "type": "Feature",
  "properties": {
    "iso:country":"US",
    "sg:address":"917 Atomic Rd",
    "sg:city":"North Augusta",
    "sg:classifiers":[
        {
            "category":"Manufacturing",
            "subcategory":"Building Materials",
            "type":"Manufacturing & Wholesale Goods"
        }
    ],
    "sg:phone":"+1 803 279 3520",
    "sg:postcode":"29841",
    "sg:province":"SC",
    "sg:tags":[
        "cabinet"
    ],
    "wof:name":"Cowart Cabinets Inc",
    "wof:placetype":"venue"
},
  "geometry": {"coordinates":[-81.942353,33.494672],"type":"Point"}
}