{
  "type": "Feature",
  "properties": {
    "addr:full":"671 Ellis St Mt Pleasant SC 29464",
    "addr:housenumber":"671",
    "addr:postcode":"29464",
    "addr:street":"Ellis St",
    "iso:country":"US",
    "sg:address":"671 Ellis St",
    "sg:city":"Mt Pleasant",
    "sg:classifiers":[
        {
            "category":"Real Estate",
            "subcategory":"Real Estate Agent",
            "type":"Services"
        }
    ],
    "sg:phone":"+1 843 849 8294",
    "sg:postcode":"29464",
    "sg:province":"SC",
    "wof:name":"Rae Properties LLC",
    "wof:placetype":"venue"
},
  "geometry": {"coordinates":[-79.869653,32.790852],"type":"Point"}
}