{
  "type": "Feature",
  "properties": {
    "addr:full":"306 Inverness Way Easley SC 29642",
    "addr:housenumber":"306",
    "addr:postcode":"29642",
    "addr:street":"Inverness Way",
    "iso:country":"US",
    "sg:address":"306 Inverness Way",
    "sg:city":"Easley",
    "sg:classifiers":[
        {
            "category":"Restaurant",
            "type":"Food & Drink"
        }
    ],
    "sg:phone":"+1 864 269 9653",
    "sg:postcode":"29642",
    "sg:province":"SC",
    "sg:tags":[
        "fast"
    ],
    "wof:name":"Arbys",
    "wof:placetype":"venue"
},
  "geometry": {"coordinates":[-82.567913,34.802711],"type":"Point"}
}