{
  "type": "Feature",
  "properties": {
    "addr:full":"2101 Pelham Rd Greenville SC 29615",
    "addr:housenumber":"2101",
    "addr:postcode":"29615",
    "addr:street":"Pelham Rd",
    "iso:country":"US",
    "sg:address":"2101 Pelham Rd",
    "sg:city":"Greenville",
    "sg:classifiers":[
        {
            "category":"Health Services",
            "subcategory":"Doctor",
            "type":"Services"
        }
    ],
    "sg:phone":"+1 864 284 6294",
    "sg:postcode":"29615",
    "sg:province":"SC",
    "sg:tags":[
        "dentist"
    ],
    "wof:name":"Wood Creek Dental Commons",
    "wof:placetype":"venue"
},
  "geometry": {"coordinates":[-82.31923999999999,34.85519],"type":"Point"}
}