{
  "type": "Feature",
  "properties": {
    "iso:country":"US",
    "sg:address":"79 Oyster Point Row",
    "sg:city":"Charleston",
    "sg:classifiers":[
        {
            "category":"Building & Trades",
            "subcategory":"Landscaping Services",
            "type":"Services"
        }
    ],
    "sg:phone":"+1 843 795 7992",
    "sg:postcode":"29412",
    "sg:province":"SC",
    "sg:tags":[
        "tree"
    ],
    "wof:name":"Jason T Ayers",
    "wof:placetype":"venue"
},
  "geometry": {"coordinates":[-79.961523,32.734835],"type":"Point"}
}