{
  "type": "Feature",
  "properties": {
    "iso:country":"US",
    "sg:address":"131 Frey Rd",
    "sg:city":"Spartanburg",
    "sg:classifiers":[
        {
            "category":"Manufacturing",
            "subcategory":"Rubber & Plastics",
            "type":"Manufacturing & Wholesale Goods"
        }
    ],
    "sg:phone":"+1 864 574 2697",
    "sg:postcode":"29301",
    "sg:province":"SC",
    "sg:tags":[
        "product"
    ],
    "wof:name":"Detroit Forming Inc",
    "wof:placetype":"venue"
},
  "geometry": {"coordinates":[-82.01643199999999,34.958177],"type":"Point"}
}