{
  "type": "Feature",
  "properties": {
    "addr:full":"221 Garden Springs Rd Columbia SC 29209",
    "addr:housenumber":"221",
    "addr:postcode":"29209",
    "addr:street":"Garden Springs Rd",
    "iso:country":"US",
    "sg:address":"221 Garden Springs Rd",
    "sg:city":"Columbia",
    "sg:classifiers":[
        {
            "category":"Real Estate",
            "subcategory":"Real Estate Operator",
            "type":"Services"
        }
    ],
    "sg:phone":"+1 803 776 4704",
    "sg:postcode":"29209",
    "sg:province":"SC",
    "sg:tags":[
        "property",
        "lessor"
    ],
    "wof:name":"A A Florence LLC",
    "wof:placetype":"venue"
},
  "geometry": {"coordinates":[-80.945228,33.977553],"type":"Point"}
}