{
  "type": "Feature",
  "properties": {
    "iso:country":"US",
    "sg:address":"609 Ross Ave",
    "sg:city":"Easley",
    "sg:classifiers":[
        {
            "category":"Restaurant",
            "type":"Food & Drink"
        }
    ],
    "sg:phone":"+1 864 306 0601",
    "sg:postcode":"29640",
    "sg:province":"SC",
    "wof:name":"Fat Cat Cafe",
    "wof:placetype":"venue"
},
  "geometry": {"coordinates":[-82.614361,34.817781],"type":"Point"}
}