{
  "type": "Feature",
  "properties": {
    "iso:country":"US",
    "sg:address":"159 Arrow Shores Cir",
    "sg:city":"Chapin",
    "sg:classifiers":[
        {
            "category":"Home & Garden",
            "subcategory":"Carpets & Floor Coverings",
            "type":"Retail Goods"
        }
    ],
    "sg:phone":"+1 803 345 5009",
    "sg:postcode":"29036",
    "sg:province":"SC",
    "sg:tags":[
        "installs"
    ],
    "wof:name":"Stephens Carpet Sales & Svc",
    "wof:placetype":"venue"
},
  "geometry": {"coordinates":[-81.423091,34.125006],"type":"Point"}
}