{
  "type": "Feature",
  "properties": {
    "iso:country":"US",
    "sg:address":"301 Milmont Shores Rd",
    "sg:city":"Chapin",
    "sg:classifiers":[
        {
            "category":"Professional",
            "subcategory":"Business Services",
            "type":"Services"
        }
    ],
    "sg:phone":"+1 803 345 9810",
    "sg:postcode":"29036",
    "sg:province":"SC",
    "sg:tags":[
        "embroidery"
    ],
    "wof:name":"M & M Tees",
    "wof:placetype":"venue"
},
  "geometry": {"coordinates":[-81.39876099999999,34.119121],"type":"Point"}
}