{
  "type": "Feature",
  "properties": {
    "iso:country":"US",
    "sg:address":"621 Rosewood Dr",
    "sg:city":"Columbia",
    "sg:classifiers":[
        {
            "category":"Building & Trades",
            "subcategory":"Construction",
            "type":"Services"
        }
    ],
    "sg:phone":"+1 803 771 6540",
    "sg:postcode":"29205",
    "sg:province":"SC",
    "sg:tags":[
        "paving",
        "contractor"
    ],
    "wof:name":"Sloan Construction Co",
    "wof:placetype":"venue"
},
  "geometry": {"coordinates":[-81.031547,33.969854],"type":"Point"}
}