{
  "type": "Feature",
  "properties": {
    "iso:country":"US",
    "sg:address":"2121 S Pamplico Hwy",
    "sg:city":"Pamplico",
    "sg:classifiers":[
        {
            "category":"Education",
            "subcategory":"School",
            "type":"Public Place"
        }
    ],
    "sg:phone":"+1 843 493 2502",
    "sg:postcode":"29583",
    "sg:province":"SC",
    "wof:name":"Florence Co District 2 Schools",
    "wof:placetype":"venue"
},
  "geometry": {"coordinates":[-79.54830800000001,33.943423],"type":"Point"}
}