{
  "type": "Feature",
  "properties": {
    "iso:country":"US",
    "sg:address":"2233 Decker Blvd",
    "sg:city":"Columbia",
    "sg:classifiers":[
        {
            "category":"Restaurant",
            "type":"Food & Drink"
        }
    ],
    "sg:phone":"+1 803 736 1998",
    "sg:postcode":"29206",
    "sg:province":"SC",
    "wof:name":"Taste Of China Hut",
    "wof:placetype":"venue"
},
  "geometry": {"coordinates":[-80.94527,34.051788],"type":"Point"}
}