{
  "type": "Feature",
  "properties": {
    "iso:country":"US",
    "sg:address":"1105 Lady St",
    "sg:city":"Columbia",
    "sg:classifiers":[
        {
            "category":"Shopping",
            "subcategory":"Bicycles & Sporting Goods",
            "type":"Retail Goods"
        }
    ],
    "sg:phone":"+1 803 252 7102",
    "sg:postcode":"29201",
    "sg:province":"SC",
    "sg:tags":[
        "outdoor",
        "gear"
    ],
    "sg:website":"www.yourstoretoexplore.com",
    "wof:name":"Moe Levy's Wilderness Station",
    "wof:placetype":"venue"
},
  "geometry": {"coordinates":[-81.035301,34.002399],"type":"Point"}
}