{
  "type": "Feature",
  "properties": {
    "addr:full":"1301 48th Ave N Myrtle Beach SC 29577",
    "addr:housenumber":"1301",
    "addr:postcode":"29577",
    "addr:street":"48Th Ave N",
    "iso:country":"US",
    "sg:address":"1301 48th Ave N",
    "sg:city":"Myrtle Beach",
    "sg:classifiers":[
        {
            "category":"Real Estate",
            "subcategory":"Real Estate Agent",
            "type":"Services"
        }
    ],
    "sg:phone":"+1 843 467 2242",
    "sg:postcode":"29577",
    "sg:province":"SC",
    "wof:name":"Realty One",
    "wof:placetype":"venue"
},
  "geometry": {"coordinates":[-78.86160599999999,33.735206],"type":"Point"}
}