{
  "type": "Feature",
  "properties": {
    "iso:country":"US",
    "sg:address":"4755 Lockwood Ln",
    "sg:city":"Columbia",
    "sg:classifiers":[
        {
            "category":"Banks & Credit Unions",
            "subcategory":"Investment Brokerage",
            "type":"Services"
        }
    ],
    "sg:phone":"+1 803 790 5800",
    "sg:postcode":"29206",
    "sg:province":"SC",
    "sg:tags":[
        "advisory",
        "financial"
    ],
    "wof:name":"Tangelwood Asset Mgmt LLC",
    "wof:placetype":"venue"
},
  "geometry": {"coordinates":[-80.956361,34.010197],"type":"Point"}
}