{
  "type": "Feature",
  "properties": {
    "addr:full":"131 Beck Taylor Pl Lexington SC 29073",
    "addr:housenumber":"131",
    "addr:postcode":"29073",
    "addr:street":"Beck Taylor Pl",
    "iso:country":"US",
    "sg:address":"131 Beck Taylor Pl",
    "sg:city":"Lexington",
    "sg:classifiers":[
        {
            "category":"Farming",
            "subcategory":"Livestock Farm",
            "type":"Manufacturing & Wholesale Goods"
        }
    ],
    "sg:phone":"+1 803 359 9323",
    "sg:postcode":"29073",
    "sg:province":"SC",
    "sg:tags":[
        "beef",
        "feedlot",
        "cattle"
    ],
    "wof:name":"B&D Feed & Specialty",
    "wof:placetype":"venue"
},
  "geometry": {"coordinates":[-81.20871699999999,33.954173],"type":"Point"}
}