{
  "type": "Feature",
  "properties": {
    "iso:country":"US",
    "sg:address":"159 Nello Dr",
    "sg:city":"Goose Creek",
    "sg:classifiers":[
        {
            "category":"Building & Trades",
            "subcategory":"Plumbing",
            "type":"Services"
        }
    ],
    "sg:phone":"+1 843 572 1649",
    "sg:postcode":"29445",
    "sg:province":"SC",
    "sg:tags":[
        "mechanical",
        "contractor"
    ],
    "wof:name":"Brown's Heating & AC",
    "wof:placetype":"venue"
},
  "geometry": {"coordinates":[-80.022942,33.016409],"type":"Point"}
}