{
  "type": "Feature",
  "properties": {
    "addr:full":"1313 3rd Ave Conway SC 29526",
    "addr:housenumber":"1313",
    "addr:postcode":"29526",
    "addr:street":"3Rd Ave",
    "iso:country":"US",
    "sg:address":"1313 3rd Ave",
    "sg:city":"Conway",
    "sg:classifiers":[
        {
            "category":"Insurance",
            "subcategory":"Insurance Agent",
            "type":"Services"
        }
    ],
    "sg:phone":"+1 843 248 9537",
    "sg:postcode":"29526",
    "sg:province":"SC",
    "wof:name":"Allstate Insurance",
    "wof:placetype":"venue"
},
  "geometry": {"coordinates":[-79.049644,33.83346],"type":"Point"}
}