{
  "type": "Feature",
  "properties": {
    "iso:country":"US",
    "sg:address":"144 Douglas Dr",
    "sg:city":"Beech Island",
    "sg:classifiers":[
        {
            "category":"Organizations",
            "subcategory":"Religious Organization",
            "type":"Services"
        }
    ],
    "sg:phone":"+1 803 827 3896",
    "sg:postcode":"29842",
    "sg:province":"SC",
    "sg:tags":[
        "church"
    ],
    "wof:name":"Park Baptist Church",
    "wof:placetype":"venue"
},
  "geometry": {"coordinates":[-81.831896,33.419316],"type":"Point"}
}