{
  "type": "Feature",
  "properties": {
    "iso:country":"US",
    "sg:address":"101 Owings Ave",
    "sg:city":"Saluda",
    "sg:classifiers":[
        {
            "category":"Real Estate",
            "subcategory":"Real Estate Agent",
            "type":"Services"
        }
    ],
    "sg:phone":"+1 864 445 3237",
    "sg:postcode":"29138",
    "sg:province":"SC",
    "sg:tags":[
        "appraiser"
    ],
    "wof:name":"Saluda Appraisal Svc",
    "wof:placetype":"venue"
},
  "geometry": {"coordinates":[-81.760768,34.01059],"type":"Point"}
}