{
  "type": "Feature",
  "properties": {
    "addr:full":"4551 State Hwy 41 Huger SC 29450",
    "addr:housenumber":"4551",
    "addr:postcode":"29450",
    "addr:street":"State Hwy 41",
    "iso:country":"US",
    "sg:address":"4551 State Hwy 41",
    "sg:city":"Huger",
    "sg:classifiers":[
        {
            "category":"Building & Trades",
            "subcategory":"Landscaping Services",
            "type":"Services"
        }
    ],
    "sg:phone":"+1 843 336 4460",
    "sg:postcode":"29450",
    "sg:province":"SC",
    "sg:tags":[
        "lawn",
        "maintenance",
        "grounds"
    ],
    "wof:name":"Chandler Landscaping",
    "wof:placetype":"venue"
},
  "geometry": {"coordinates":[-79.80604099999999,33.078697],"type":"Point"}
}