{
  "type": "Feature",
  "properties": {
    "iso:country":"US",
    "sg:address":"1722 Main St Ste 150",
    "sg:city":"Columbia",
    "sg:classifiers":[
        {
            "category":"Professional",
            "subcategory":"Lawyer & Legal Services",
            "type":"Services"
        }
    ],
    "sg:phone":"+1 803 771 4488",
    "sg:postcode":"29201",
    "sg:province":"SC",
    "wof:name":"Gibbons Carlos W Jr Atty",
    "wof:placetype":"venue"
},
  "geometry": {"coordinates":[-81.036697,34.008301],"type":"Point"}
}