{
  "type": "Feature",
  "properties": {
    "iso:country":"US",
    "sg:address":"733 Tallwood Rd",
    "sg:city":"Charleston",
    "sg:classifiers":[
        {
            "category":"Building & Trades",
            "subcategory":"Plumbing",
            "type":"Services"
        }
    ],
    "sg:phone":"+1 843 406 2800",
    "sg:postcode":"29412",
    "sg:province":"SC",
    "sg:tags":[
        "plumbing",
        "contractor"
    ],
    "wof:name":"Budget Mechanical Plumbing",
    "wof:placetype":"venue"
},
  "geometry": {"coordinates":[-79.92286300000001,32.734267],"type":"Point"}
}