{
  "type": "Feature",
  "properties": {
    "iso:country":"US",
    "sg:address":"920 Augusta Rd",
    "sg:city":"North Augusta",
    "sg:classifiers":[
        {
            "category":"Organizations",
            "subcategory":"Religious Organization",
            "type":"Services"
        }
    ],
    "sg:phone":"+1 803 593 5662",
    "sg:postcode":"29822",
    "sg:province":"SC",
    "sg:tags":[
        "church"
    ],
    "sg:website":"www.saintjohnsclearwater.org",
    "wof:name":"St John's Episcopal Church",
    "wof:placetype":"venue"
},
  "geometry": {"coordinates":[-81.892064,33.496875],"type":"Point"}
}