{
  "type": "Feature",
  "properties": {
    "addr:full":"2251 Salem Rd Scranton SC 29591",
    "addr:housenumber":"2251",
    "addr:postcode":"29591",
    "addr:street":"Salem Rd",
    "iso:country":"US",
    "sg:address":"2251 Salem Rd",
    "sg:city":"Scranton",
    "sg:classifiers":[
        {
            "category":"Building & Trades",
            "subcategory":"Construction",
            "type":"Services"
        }
    ],
    "sg:phone":"+1 843 389 0831",
    "sg:postcode":"29591",
    "sg:province":"SC",
    "sg:tags":[
        "asbestos",
        "removal"
    ],
    "wof:name":"A To Z Coatings & Insulation",
    "wof:placetype":"venue"
},
  "geometry": {"coordinates":[-79.848508,33.961007],"type":"Point"}
}