{
  "type": "Feature",
  "properties": {
    "addr:full":"112 E Hudson Ave Folly Beach SC 29439",
    "addr:housenumber":"112",
    "addr:postcode":"29439",
    "addr:street":"E Hudson Ave",
    "iso:country":"US",
    "sg:address":"112 E Hudson Ave",
    "sg:city":"Folly Beach",
    "sg:classifiers":[
        {
            "category":"Health Services",
            "subcategory":"Health Practitioner",
            "type":"Services"
        }
    ],
    "sg:phone":"+1 843 588 9462",
    "sg:postcode":"29439",
    "sg:province":"SC",
    "sg:tags":[
        "nurse",
        "registry"
    ],
    "wof:name":"Island Medical Ctr",
    "wof:placetype":"venue"
},
  "geometry": {"coordinates":[-79.939707,32.657844],"type":"Point"}
}