{
  "type": "Feature",
  "properties": {
    "iso:country":"US",
    "sg:address":"115 N Caroline St",
    "sg:city":"Laurens",
    "sg:classifiers":[
        {
            "category":"Sports & Exercise",
            "subcategory":"Gym",
            "type":"Entertainment"
        }
    ],
    "sg:phone":"+1 864 984 2092",
    "sg:postcode":"29360",
    "sg:province":"SC",
    "sg:tags":[
        "club",
        "health",
        "studio",
        "gymnasium"
    ],
    "wof:name":"Curves For Women",
    "wof:placetype":"venue"
},
  "geometry": {"coordinates":[-82.015851,34.499012],"type":"Point"}
}