{
  "type": "Feature",
  "properties": {
    "iso:country":"US",
    "sg:address":"2986 Twisted Antler Dr",
    "sg:city":"Charleston",
    "sg:classifiers":[
        {
            "category":"Manufacturing",
            "subcategory":"Printing",
            "type":"Manufacturing & Wholesale Goods"
        }
    ],
    "sg:phone":"+1 843 553 6631",
    "sg:postcode":"29406",
    "sg:province":"SC",
    "sg:tags":[
        "publishing"
    ],
    "wof:name":"Ch & Er Publishing & Developme",
    "wof:placetype":"venue"
},
  "geometry": {"coordinates":[-80.069996,32.964424],"type":"Point"}
}