{
  "type": "Feature",
  "properties": {
    "iso:country":"US",
    "sg:address":"6429 Cloverdale Dr",
    "sg:city":"Columbia",
    "sg:classifiers":[
        {
            "category":"Real Estate",
            "subcategory":"Real Estate Agent",
            "type":"Services"
        }
    ],
    "sg:phone":"+1 803 776 9641",
    "sg:postcode":"29209",
    "sg:province":"SC",
    "wof:name":"Headley Residential Appraisal",
    "wof:placetype":"venue"
},
  "geometry": {"coordinates":[-80.94242199999999,33.982189],"type":"Point"}
}