{
  "type": "Feature",
  "properties": {
    "iso:country":"US",
    "sg:address":"749 Jason Blvd",
    "sg:city":"Myrtle Beach",
    "sg:classifiers":[
        {
            "category":"Building & Trades",
            "subcategory":"Equipment Rental",
            "type":"Services"
        }
    ],
    "sg:phone":"+1 803 448 1562",
    "sg:postcode":"29577",
    "sg:province":"SC",
    "sg:tags":[
        "crane"
    ],
    "wof:name":"Richbourg Cranes",
    "wof:placetype":"venue"
},
  "geometry": {"coordinates":[-78.90858799999999,33.711113],"type":"Point"}
}