{
  "type": "Feature",
  "properties": {
    "iso:country":"US",
    "sg:address":"501 Gervais St",
    "sg:city":"Columbia",
    "sg:classifiers":[
        {
            "category":"Food & Beverages",
            "subcategory":"Groceries & Convenience Stores",
            "type":"Retail Goods"
        }
    ],
    "sg:phone":"+1 803 255 4351",
    "sg:postcode":"29201",
    "sg:province":"SC",
    "sg:website":"www.publix.com",
    "wof:name":"Publix Super Market",
    "wof:placetype":"venue"
},
  "geometry": {"coordinates":[-81.044827,33.997831],"type":"Point"}
}