{
  "type": "Feature",
  "properties": {
    "iso:country":"US",
    "sg:address":"2101 Main St",
    "sg:city":"Columbia",
    "sg:classifiers":[
        {
            "category":"Banks & Credit Unions",
            "subcategory":"Bank",
            "type":"Services"
        }
    ],
    "sg:phone":"+1 803 765 0950",
    "sg:postcode":"29201",
    "sg:province":"SC",
    "sg:tags":[
        "national",
        "commercial"
    ],
    "wof:name":"Nat L Finance Co Inc",
    "wof:placetype":"venue"
},
  "geometry": {"coordinates":[-81.03947100000001,34.014659],"type":"Point"}
}