{
  "type": "Feature",
  "properties": {
    "addr:full":"100 Cherokee Rd Florence SC 29501",
    "addr:housenumber":"100",
    "addr:postcode":"29501",
    "addr:street":"Cherokee Rd",
    "iso:country":"US",
    "sg:address":"100 Cherokee Rd",
    "sg:city":"Florence",
    "sg:classifiers":[
        {
            "category":"Real Estate",
            "subcategory":"Developer",
            "type":"Services"
        }
    ],
    "sg:phone":"+1 843 662 5145",
    "sg:postcode":"29501",
    "sg:province":"SC",
    "sg:tags":[
        "cemetery"
    ],
    "wof:name":"Mount Hope Cmtry & Mausoleum",
    "wof:placetype":"venue"
},
  "geometry": {"coordinates":[-79.767231,34.183735],"type":"Point"}
}