{
  "type": "Feature",
  "properties": {
    "iso:country":"US",
    "sg:address":"1111 State St",
    "sg:city":"Cayce",
    "sg:classifiers":[
        {
            "category":"Social Services",
            "type":"Services"
        }
    ],
    "sg:phone":"+1 803 791 3255",
    "sg:postcode":"29033",
    "sg:province":"SC",
    "sg:tags":[
        "care",
        "center",
        "day"
    ],
    "wof:name":"Hope Bridge",
    "wof:placetype":"venue"
},
  "geometry": {"coordinates":[-81.055487,33.983326],"type":"Point"}
}