{
  "type": "Feature",
  "properties": {
    "addr:full":"206 N Longstreet St Kingstree SC 29556",
    "addr:housenumber":"206",
    "addr:postcode":"29556",
    "addr:street":"N Longstreet St",
    "iso:country":"US",
    "sg:address":"206 N Longstreet St",
    "sg:city":"Kingstree",
    "sg:classifiers":[
        {
            "category":"Shopping",
            "subcategory":"Discount & Variety Stores",
            "type":"Retail Goods"
        }
    ],
    "sg:phone":"+1 843 354 5201",
    "sg:postcode":"29556",
    "sg:province":"SC",
    "wof:name":"SA Variety Store",
    "wof:placetype":"venue"
},
  "geometry": {"coordinates":[-79.834149,33.665713],"type":"Point"}
}