{
  "type": "Feature",
  "properties": {
    "iso:country":"US",
    "sg:address":"1053 Dominion Dr",
    "sg:city":"Charleston",
    "sg:classifiers":[
        {
            "category":"Communications",
            "subcategory":"Radio Station",
            "type":"Services"
        }
    ],
    "sg:phone":"+1 843 744 2942",
    "sg:postcode":"29410",
    "sg:province":"SC",
    "sg:tags":[
        "sport",
        "officiating",
        "activity"
    ],
    "wof:name":"Palmetto Officials Association",
    "wof:placetype":"venue"
},
  "geometry": {"coordinates":[-79.99851700000001,32.915752],"type":"Point"}
}