{
  "type": "Feature",
  "properties": {
    "iso:country":"US",
    "sg:address":"1947 Ferguson Rd",
    "sg:city":"Charleston",
    "sg:classifiers":[
        {
            "category":"Building & Trades",
            "subcategory":"Construction",
            "type":"Services"
        }
    ],
    "sg:phone":"+1 843 225 9903",
    "sg:postcode":"29412",
    "sg:province":"SC",
    "sg:tags":[
        "house"
    ],
    "wof:name":"Econo Construction",
    "wof:placetype":"venue"
},
  "geometry": {"coordinates":[-79.97944699999999,32.727878],"type":"Point"}
}