{
  "type": "Feature",
  "properties": {
    "addr:full":"281 Pk Terrace Dr Columbia SC 29201",
    "addr:postcode":"29201",
    "addr:street":"281 Pk Terrace Dr",
    "iso:country":"US",
    "sg:address":"281 Pk Terrace Dr",
    "sg:city":"Columbia",
    "sg:classifiers":[
        {
            "category":"Shopping",
            "subcategory":"Stationery & Office Supplies",
            "type":"Retail Goods"
        },
        {
            "category":"Professional",
            "subcategory":"Printing & Photocopies",
            "type":"Services"
        }
    ],
    "sg:phone":"+1 803 407 0254",
    "sg:postcode":"29201",
    "sg:province":"SC",
    "sg:tags":[
        "equipment"
    ],
    "wof:name":"Staples",
    "wof:placetype":"venue"
},
  "geometry": {"coordinates":[-81.037003,34.000301],"type":"Point"}
}