{
  "type": "Feature",
  "properties": {
    "iso:country":"US",
    "sg:address":"525 Sandfield Rd",
    "sg:city":"Blythewood",
    "sg:classifiers":[
        {
            "category":"Recreation",
            "type":"Entertainment"
        }
    ],
    "sg:phone":"+1 803 735 0470",
    "sg:postcode":"29016",
    "sg:province":"SC",
    "sg:tags":[
        "martial",
        "arts",
        "instruction"
    ],
    "wof:name":"Blythewood Tae KWON Do USA",
    "wof:placetype":"venue"
},
  "geometry": {"coordinates":[-80.95764,34.217554],"type":"Point"}
}