{
  "type": "Feature",
  "properties": {
    "iso:country":"US",
    "sg:address":"204 W Franklin St",
    "sg:city":"Anderson",
    "sg:classifiers":[
        {
            "category":"Food & Beverages",
            "subcategory":"Supermarket",
            "type":"Retail Goods"
        },
        {
            "category":"Food & Beverages",
            "subcategory":"Groceries & Convenience Stores",
            "type":"Retail Goods"
        }
    ],
    "sg:phone":"+1 864 260 9368",
    "sg:postcode":"29624",
    "sg:province":"SC",
    "sg:tags":[
        "super"
    ],
    "wof:name":"Action Foods",
    "wof:placetype":"venue"
},
  "geometry": {"coordinates":[-82.650572,34.496637],"type":"Point"}
}