{
  "type": "Feature",
  "properties": {
    "iso:country":"US",
    "sg:address":"5005 White City Park Rd",
    "sg:city":"Anderson",
    "sg:classifiers":[
        {
            "category":"Farming",
            "subcategory":"Livestock Farm",
            "type":"Manufacturing & Wholesale Goods"
        }
    ],
    "sg:phone":"+1 864 224 4211",
    "sg:postcode":"29625",
    "sg:province":"SC",
    "sg:tags":[
        "wheat",
        "beef",
        "cash",
        "grain",
        "cattle",
        "feedlot"
    ],
    "wof:name":"William A McClain",
    "wof:placetype":"venue"
},
  "geometry": {"coordinates":[-82.746828,34.539782],"type":"Point"}
}