{
  "type": "Feature",
  "properties": {
    "iso:country":"US",
    "sg:address":"3 Cardinal Ct",
    "sg:city":"Hilton Head Isle",
    "sg:classifiers":[
        {
            "category":"Building & Trades",
            "subcategory":"Construction",
            "type":"Services"
        }
    ],
    "sg:phone":"+1 843 689 6500",
    "sg:postcode":"29926",
    "sg:province":"SC",
    "sg:tags":[
        "concrete",
        "contractor"
    ],
    "wof:name":"Decorative Concrete & Design",
    "wof:placetype":"venue"
},
  "geometry": {"coordinates":[-80.70396,32.222265],"type":"Point"}
}