{
  "type": "Feature",
  "properties": {
    "iso:country":"US",
    "sg:address":"419 Augusta Rd",
    "sg:city":"North Augusta",
    "sg:classifiers":[
        {
            "category":"Home & Garden",
            "subcategory":"Building Materials",
            "type":"Retail Goods"
        }
    ],
    "sg:phone":"+1 803 279 2386",
    "sg:postcode":"29822",
    "sg:province":"SC",
    "sg:tags":[
        "paint"
    ],
    "wof:name":"Sherwin-Williams Paints",
    "wof:placetype":"venue"
},
  "geometry": {"coordinates":[-81.892059,33.496703],"type":"Point"}
}