{
  "type": "Feature",
  "properties": {
    "addr:full":"1194 Meeting Street Rd Edgefield SC 29824",
    "addr:housenumber":"1194",
    "addr:postcode":"29824",
    "addr:street":"Meeting Street Rd",
    "iso:country":"US",
    "sg:address":"1194 Meeting Street Rd",
    "sg:city":"Edgefield",
    "sg:classifiers":[
        {
            "category":"Organizations",
            "subcategory":"Religious Organization",
            "type":"Services"
        }
    ],
    "sg:phone":"+1 803 637 0340",
    "sg:postcode":"29824",
    "sg:province":"SC",
    "sg:tags":[
        "church"
    ],
    "wof:name":"Little Stevens Creek Baptist",
    "wof:placetype":"venue"
},
  "geometry": {"coordinates":[-81.92935900000001,33.932799],"type":"Point"}
}