{
  "type": "Feature",
  "properties": {
    "addr:full":"211 N Marlboro St Bennettsville SC 29512",
    "addr:housenumber":"211",
    "addr:postcode":"29512",
    "addr:street":"N Marlboro St",
    "iso:country":"US",
    "sg:address":"211 N Marlboro St",
    "sg:city":"Bennettsville",
    "sg:classifiers":[
        {
            "category":"Government",
            "subcategory":"Office",
            "type":"Public Place"
        }
    ],
    "sg:phone":"+1 843 479 5600",
    "sg:postcode":"29512",
    "sg:province":"SC",
    "sg:tags":[
        "state",
        "program",
        "health"
    ],
    "wof:name":"Behavioral Health Care Of Sc",
    "wof:placetype":"venue"
},
  "geometry": {"coordinates":[-79.68454300000001,34.618362],"type":"Point"}
}