{
  "type": "Feature",
  "properties": {
    "iso:country":"US",
    "sg:address":"1009 Garrett Patton Rd",
    "sg:city":"Fountain Inn",
    "sg:classifiers":[
        {
            "category":"Recreation",
            "type":"Entertainment"
        }
    ],
    "sg:phone":"+1 864 862 6969",
    "sg:postcode":"29644",
    "sg:province":"SC",
    "sg:tags":[
        "stable"
    ],
    "wof:name":"Terrace Hill Equestrian Ctr",
    "wof:placetype":"venue"
},
  "geometry": {"coordinates":[-82.156898,34.724528],"type":"Point"}
}