{
  "type": "Feature",
  "properties": {
    "iso:country":"US",
    "sg:address":"1327 Richland St",
    "sg:city":"Columbia",
    "sg:classifiers":[
        {
            "category":"Professional",
            "subcategory":"Lawyer & Legal Services",
            "type":"Services"
        }
    ],
    "sg:phone":"+1 803 931 0028",
    "sg:postcode":"29201",
    "sg:province":"SC",
    "sg:tags":[
        "attorney"
    ],
    "wof:name":"Thomas M Neal",
    "wof:placetype":"venue"
},
  "geometry": {"coordinates":[-81.034915,34.011556],"type":"Point"}
}