{
  "type": "Feature",
  "properties": {
    "addr:full":"218 Main St Barnwell SC 29812",
    "addr:housenumber":"218",
    "addr:postcode":"29812",
    "addr:street":"Main St",
    "iso:country":"US",
    "sg:address":"218 Main St",
    "sg:city":"Barnwell",
    "sg:classifiers":[
        {
            "category":"Organizations",
            "subcategory":"Non-profit Organization",
            "type":"Services"
        }
    ],
    "sg:phone":"+1 803 541 6555",
    "sg:postcode":"29812",
    "sg:province":"SC",
    "wof:name":"Barnwell Downtown Development",
    "wof:placetype":"venue"
},
  "geometry": {"coordinates":[-81.363184,33.243837],"type":"Point"}
}