{
  "type": "Feature",
  "properties": {
    "iso:country":"US",
    "sg:address":"1916 Camelot Forest",
    "sg:city":"Belton",
    "sg:classifiers":[
        {
            "category":"Wholesale",
            "subcategory":"Petroleum",
            "type":"Manufacturing & Wholesale Goods"
        }
    ],
    "sg:phone":"+1 864 338 9491",
    "sg:postcode":"29627",
    "sg:province":"SC",
    "sg:tags":[
        "pipe",
        "line",
        "company"
    ],
    "wof:name":"Colonial Pipeline Co",
    "wof:placetype":"venue"
},
  "geometry": {"coordinates":[-82.489565,34.552818],"type":"Point"}
}