{
  "type": "Feature",
  "properties": {
    "addr:full":"1241 Wilson Rd Newberry SC 29108",
    "addr:housenumber":"1241",
    "addr:postcode":"29108",
    "addr:street":"Wilson Rd",
    "iso:country":"US",
    "sg:address":"1241 Wilson Rd",
    "sg:city":"Newberry",
    "sg:classifiers":[
        {
            "category":"Restaurant",
            "type":"Food & Drink"
        }
    ],
    "sg:menulink":"http://www.allmenus.com/sc/newberry/200944-mcdonalds/menu/",
    "sg:postcode":"29108",
    "sg:province":"SC",
    "sg:tags":[
        "burger",
        "american"
    ],
    "wof:name":"McDonald's",
    "wof:placetype":"venue"
},
  "geometry": {"coordinates":[-81.596627,34.283288],"type":"Point"}
}