{
  "type": "Feature",
  "properties": {
    "iso:country":"US",
    "sg:address":"1919 Middleton Rd",
    "sg:city":"Anderson",
    "sg:classifiers":[
        {
            "category":"Building & Trades",
            "subcategory":"Construction",
            "type":"Services"
        }
    ],
    "sg:phone":"+1 864 296 8300",
    "sg:postcode":"29624",
    "sg:province":"SC",
    "sg:tags":[
        "contractor"
    ],
    "wof:name":"Charles Vickery Roofing",
    "wof:placetype":"venue"
},
  "geometry": {"coordinates":[-82.61991999999999,34.415642],"type":"Point"}
}