{
  "type": "Feature",
  "properties": {
    "iso:country":"US",
    "sg:address":"545 Old Metal Rd",
    "sg:city":"Gaffney",
    "sg:classifiers":[
        {
            "category":"Communications",
            "type":"Services"
        }
    ],
    "sg:phone":"+1 864 461 5541",
    "sg:postcode":"29341",
    "sg:province":"SC",
    "wof:name":"Total Communications Systems",
    "wof:placetype":"venue"
},
  "geometry": {"coordinates":[-81.779168,35.118466],"type":"Point"}
}