{
  "type": "Feature",
  "properties": {
    "iso:country":"US",
    "sg:address":"212 Ashmore Rd",
    "sg:city":"Greer",
    "sg:classifiers":[
        {
            "category":"Professional",
            "type":"Services"
        }
    ],
    "sg:phone":"+1 864 268 0162",
    "sg:postcode":"29650",
    "sg:province":"SC",
    "sg:tags":[
        "establishment"
    ],
    "wof:name":"Vern Peterson Inc",
    "wof:placetype":"venue"
},
  "geometry": {"coordinates":[-82.285758,34.880989],"type":"Point"}
}