{
  "type": "Feature",
  "properties": {
    "addr:full":"483 King St Charleston SC 29403",
    "addr:housenumber":"483",
    "addr:postcode":"29403",
    "addr:street":"King St",
    "iso:country":"US",
    "sg:address":"483 King St",
    "sg:city":"Charleston",
    "sg:classifiers":[
        {
            "category":"Shopping",
            "subcategory":"Department Store",
            "type":"Retail Goods"
        }
    ],
    "sg:phone":"+1 843 577 6786",
    "sg:postcode":"29403",
    "sg:province":"SC",
    "wof:name":"Citi Trends",
    "wof:placetype":"venue"
},
  "geometry": {"coordinates":[-79.939325,32.790166],"type":"Point"}
}