{
  "type": "Feature",
  "properties": {
    "addr:full":"3795 E North St Greenville SC 29615",
    "addr:housenumber":"3795",
    "addr:postcode":"29615",
    "addr:street":"E North St",
    "iso:country":"US",
    "sg:address":"3795 E North St",
    "sg:city":"Greenville",
    "sg:classifiers":[
        {
            "category":"Restaurant",
            "type":"Food & Drink"
        }
    ],
    "sg:phone":"+1 864 244 4141",
    "sg:postcode":"29615",
    "sg:province":"SC",
    "wof:name":"Wing Zone",
    "wof:placetype":"venue"
},
  "geometry": {"coordinates":[-82.327535,34.873398],"type":"Point"}
}