{
  "type": "Feature",
  "properties": {
    "iso:country":"US",
    "sg:address":"1420 Bourne St",
    "sg:city":"Georgetown",
    "sg:classifiers":[
        {
            "category":"Wholesale",
            "subcategory":"Sporting Goods",
            "type":"Manufacturing & Wholesale Goods"
        }
    ],
    "sg:phone":"+1 843 545 8707",
    "sg:postcode":"29440",
    "sg:province":"SC",
    "sg:tags":[
        "distributor",
        "boat"
    ],
    "wof:name":"Fast Craft Boats LLC",
    "wof:placetype":"venue"
},
  "geometry": {"coordinates":[-79.296093,33.364153],"type":"Point"}
}