{
  "type": "Feature",
  "properties": {
    "addr:full":"103 W George St St George SC 29477",
    "addr:housenumber":"103",
    "addr:postcode":"29477",
    "addr:street":"W George St",
    "iso:country":"US",
    "sg:address":"103 W George St",
    "sg:city":"St George",
    "sg:classifiers":[
        {
            "category":"Insurance",
            "subcategory":"Insurance Agent",
            "type":"Services"
        }
    ],
    "sg:phone":"+1 843 563 2963",
    "sg:postcode":"29477",
    "sg:province":"SC",
    "wof:name":"Utsey Insurance",
    "wof:placetype":"venue"
},
  "geometry": {"coordinates":[-80.575057,33.185408],"type":"Point"}
}