{
  "type": "Feature",
  "properties": {
    "addr:full":"2149 N Main St Summerville SC 29483",
    "addr:housenumber":"2149",
    "addr:postcode":"29483",
    "addr:street":"N Main St",
    "iso:country":"US",
    "sg:address":"2149 N Main St",
    "sg:city":"Summerville",
    "sg:classifiers":[
        {
            "category":"Retail",
            "subcategory":"Auto Repair",
            "type":"Services"
        }
    ],
    "sg:phone":"+1 843 832 3200",
    "sg:postcode":"29483",
    "sg:province":"SC",
    "sg:tags":[
        "transmission"
    ],
    "wof:name":"Palmetto Transmissions",
    "wof:placetype":"venue"
},
  "geometry": {"coordinates":[-80.110938,33.046004],"type":"Point"}
}