{
  "type": "Feature",
  "properties": {
    "addr:full":"500 Pamplico Hwy Florence SC 29505",
    "addr:housenumber":"500",
    "addr:postcode":"29505",
    "addr:street":"Pamplico Hwy",
    "iso:country":"US",
    "sg:address":"500 Pamplico Hwy",
    "sg:city":"Florence",
    "sg:classifiers":[
        {
            "category":"Restaurant",
            "type":"Food & Drink"
        }
    ],
    "sg:menulink":"http://www.allmenus.com/sc/florence/85554-dominos-pizza/menu/",
    "sg:phone":"+1 843 292 0499",
    "sg:postcode":"29505",
    "sg:province":"SC",
    "sg:tags":[
        "american",
        "wing",
        "pizza"
    ],
    "wof:name":"Domino's Pizza",
    "wof:placetype":"venue"
},
  "geometry": {"coordinates":[-79.757024,34.161813],"type":"Point"}
}