{
  "type": "Feature",
  "properties": {
    "iso:country":"US",
    "sg:address":"1632 Montague Ave Exd",
    "sg:city":"Greenwood",
    "sg:classifiers":[
        {
            "category":"Restaurant",
            "type":"Food & Drink"
        }
    ],
    "sg:phone":"+1 864 223 8292",
    "sg:postcode":"29649",
    "sg:province":"SC",
    "wof:name":"Pizza Hut",
    "wof:placetype":"venue"
},
  "geometry": {"coordinates":[-82.186897,34.221834],"type":"Point"}
}