{
  "type": "Feature",
  "properties": {
    "iso:country":"US",
    "sg:address":"905 D Ave",
    "sg:city":"West Columbia",
    "sg:classifiers":[
        {
            "category":"Building & Trades",
            "subcategory":"Construction",
            "type":"Services"
        }
    ],
    "sg:phone":"+1 803 939 7151",
    "sg:postcode":"29169",
    "sg:province":"SC",
    "sg:tags":[
        "carpentry",
        "contractor"
    ],
    "wof:name":"Carpenter Shop",
    "wof:placetype":"venue"
},
  "geometry": {"coordinates":[-81.067364,33.985733],"type":"Point"}
}