{
  "type": "Feature",
  "properties": {
    "iso:country":"US",
    "sg:address":"300 Winding Brook Ct",
    "sg:city":"Greenville",
    "sg:classifiers":[
        {
            "category":"Personal",
            "subcategory":"Adult",
            "type":"Services"
        }
    ],
    "sg:phone":"+1 864 294 0606",
    "sg:postcode":"29617",
    "sg:province":"SC",
    "sg:tags":[
        "escort"
    ],
    "wof:name":"Brittany's Escort Svc",
    "wof:placetype":"venue"
},
  "geometry": {"coordinates":[-82.470542,34.907659],"type":"Point"}
}