{
  "type": "Feature",
  "properties": {
    "addr:full":"1500 Sunset Blvd West Columbia SC 29169",
    "addr:housenumber":"1500",
    "addr:postcode":"29169",
    "addr:street":"Sunset Blvd",
    "iso:country":"US",
    "sg:address":"1500 Sunset Blvd",
    "sg:city":"West Columbia",
    "sg:classifiers":[
        {
            "category":"Organizations",
            "subcategory":"Religious Organization",
            "type":"Services"
        }
    ],
    "sg:phone":"+1 803 794 8180",
    "sg:postcode":"29169",
    "sg:province":"SC",
    "sg:tags":[
        "church"
    ],
    "sg:website":"www.oursaviour.net",
    "wof:name":"Our Saviour's Lutheran Church",
    "wof:placetype":"venue"
},
  "geometry": {"coordinates":[-81.08636199999999,33.99878],"type":"Point"}
}