{
  "type": "Feature",
  "properties": {
    "addr:full":"1267 Knox Ave North Augusta SC 29841",
    "addr:housenumber":"1267",
    "addr:postcode":"29841",
    "addr:street":"Knox Ave",
    "iso:country":"US",
    "sg:address":"1267 Knox Ave",
    "sg:city":"North Augusta",
    "sg:classifiers":[
        {
            "category":"Restaurant",
            "type":"Food & Drink"
        }
    ],
    "sg:menulink":"http://www.allmenus.com/sc/north-augusta/179931-chick-fil-a/menu/",
    "sg:phone":"+1 803 202 3202",
    "sg:postcode":"29841",
    "sg:province":"SC",
    "sg:tags":[
        "wrap",
        "soup",
        "american",
        "sandwich",
        "salad"
    ],
    "wof:name":"Chick-Fil-A",
    "wof:placetype":"venue"
},
  "geometry": {"coordinates":[-81.95920700000001,33.502379],"type":"Point"}
}