{
  "type": "Feature",
  "properties": {
    "iso:country":"US",
    "sg:address":"7034 Notch Rd",
    "sg:city":"Columbia",
    "sg:classifiers":[
        {
            "category":"Bars & Pubs",
            "type":"Food & Drink"
        }
    ],
    "sg:phone":"+1 803 419 2824",
    "sg:postcode":"29223",
    "sg:province":"SC",
    "sg:tags":[
        "club",
        "night"
    ],
    "wof:name":"Escape",
    "wof:placetype":"venue"
},
  "geometry": {"coordinates":[-80.959502,34.062537],"type":"Point"}
}