{
  "type": "Feature",
  "properties": {
    "iso:country":"US",
    "sg:address":"923 University Dr",
    "sg:city":"Lancaster",
    "sg:classifiers":[
        {
            "category":"Insurance",
            "subcategory":"Insurance Agent",
            "type":"Services"
        }
    ],
    "sg:phone":"+1 803 283 3317",
    "sg:postcode":"29720",
    "sg:province":"SC",
    "wof:name":"Howard Penegar Insurance",
    "wof:placetype":"venue"
},
  "geometry": {"coordinates":[-80.779605,34.743548],"type":"Point"}
}