{
  "type": "Feature",
  "properties": {
    "iso:country":"US",
    "sg:address":"8409 W Oak Hwy",
    "sg:city":"Seneca",
    "sg:classifiers":[
        {
            "category":"Wholesale",
            "subcategory":"Medical Equipment & Supplies",
            "type":"Manufacturing & Wholesale Goods"
        }
    ],
    "sg:phone":"+1 864 972 3774",
    "sg:postcode":"29678",
    "sg:province":"SC",
    "sg:tags":[
        "physician",
        "surgeon"
    ],
    "wof:name":"Absolute Medical Svc Corp",
    "wof:placetype":"venue"
},
  "geometry": {"coordinates":[-82.979122,34.596127],"type":"Point"}
}