{
  "type": "Feature",
  "properties": {
    "addr:full":"107 Silver Ridge Ct Greer SC 29651",
    "addr:housenumber":"107",
    "addr:postcode":"29651",
    "addr:street":"Silver Ridge Ct",
    "iso:country":"US",
    "sg:address":"107 Silver Ridge Ct",
    "sg:city":"Greer",
    "sg:classifiers":[
        {
            "category":"Professional",
            "subcategory":"Detective & Security Services",
            "type":"Services"
        }
    ],
    "sg:phone":"+1 864 968 1911",
    "sg:postcode":"29651",
    "sg:province":"SC",
    "sg:tags":[
        "guard",
        "patrol"
    ],
    "wof:name":"Pro Teck Security Guard Svc",
    "wof:placetype":"venue"
},
  "geometry": {"coordinates":[-82.28899800000001,34.962568],"type":"Point"}
}