{
  "type": "Feature",
  "properties": {
    "iso:country":"US",
    "sg:address":"920 Front St",
    "sg:city":"Georgetown",
    "sg:classifiers":[
        {
            "category":"Professional",
            "subcategory":"Business Services",
            "type":"Services"
        }
    ],
    "sg:phone":"+1 843 527 2000",
    "sg:postcode":"29440",
    "sg:province":"SC",
    "sg:tags":[
        "interior",
        "consultant",
        "design",
        "decorator"
    ],
    "wof:name":"Winyah Bay Finishing",
    "wof:placetype":"venue"
},
  "geometry": {"coordinates":[-79.28701,33.369062],"type":"Point"}
}