{
  "type": "Feature",
  "properties": {
    "addr:full":"1728 Hazelwood Rd Columbia SC 29209",
    "addr:housenumber":"1728",
    "addr:postcode":"29209",
    "addr:street":"Hazelwood Rd",
    "iso:country":"US",
    "sg:address":"1728 Hazelwood Rd",
    "sg:city":"Columbia",
    "sg:classifiers":[
        {
            "category":"Food & Beverages",
            "subcategory":"Groceries & Convenience Stores",
            "type":"Retail Goods"
        }
    ],
    "sg:phone":"+1 803 776 2823",
    "sg:postcode":"29209",
    "sg:province":"SC",
    "wof:name":"Other Store",
    "wof:placetype":"venue"
},
  "geometry": {"coordinates":[-80.924414,33.969885],"type":"Point"}
}