{
  "type": "Feature",
  "properties": {
    "addr:full":"112 Outrigger Greenwood SC 29649",
    "addr:housenumber":"112",
    "addr:postcode":"29649",
    "addr:street":"Outrigger",
    "iso:country":"US",
    "sg:address":"112 Outrigger",
    "sg:city":"Greenwood",
    "sg:classifiers":[
        {
            "category":"Organizations",
            "subcategory":"Community Association",
            "type":"Services"
        }
    ],
    "sg:phone":"+1 864 942 0007",
    "sg:postcode":"29649",
    "sg:province":"SC",
    "sg:tags":[
        "club"
    ],
    "wof:name":"Stoney Point Lake Club",
    "wof:placetype":"venue"
},
  "geometry": {"coordinates":[-82.08866500000001,34.297401],"type":"Point"}
}