{
  "type": "Feature",
  "properties": {
    "iso:country":"US",
    "sg:address":"509 Carriage Oaks Dr",
    "sg:city":"Columbia",
    "sg:classifiers":[
        {
            "category":"Retail",
            "subcategory":"Car Wash",
            "type":"Services"
        }
    ],
    "sg:phone":"+1 803 736 7669",
    "sg:postcode":"29229",
    "sg:province":"SC",
    "sg:tags":[
        "polishing",
        "washing"
    ],
    "wof:name":"Auto-Mobile Detailing Svc",
    "wof:placetype":"venue"
},
  "geometry": {"coordinates":[-80.892482,34.149235],"type":"Point"}
}