{
  "type": "Feature",
  "properties": {
    "iso:country":"US",
    "sg:address":"4360 Augusta Rd",
    "sg:city":"Lexington",
    "sg:classifiers":[
        {
            "category":"Organizations",
            "subcategory":"Professional Association",
            "type":"Services"
        }
    ],
    "sg:phone":"+1 803 356 2199",
    "sg:postcode":"29073",
    "sg:province":"SC",
    "wof:name":"Oak Grove Townhouse Assn",
    "wof:placetype":"venue"
},
  "geometry": {"coordinates":[-81.154319,33.973461],"type":"Point"}
}