{
  "type": "Feature",
  "properties": {
    "addr:full":"2335 State Hwy 9 Bus W Loris SC 29569",
    "addr:housenumber":"2335",
    "addr:postcode":"29569",
    "addr:street":"State Hwy 9 Bus W",
    "iso:country":"US",
    "sg:address":"2335 State Hwy 9 Bus W",
    "sg:city":"Loris",
    "sg:classifiers":[
        {
            "category":"Social Services",
            "type":"Services"
        }
    ],
    "sg:phone":"+1 843 756 4629",
    "sg:postcode":"29569",
    "sg:province":"SC",
    "sg:tags":[
        "shelter",
        "homeless"
    ],
    "wof:name":"Coastal Rescue Mission",
    "wof:placetype":"venue"
},
  "geometry": {"coordinates":[-78.94880000000001,34.08525],"type":"Point"}
}