{
  "type": "Feature",
  "properties": {
    "iso:country":"US",
    "sg:address":"323 Bypass 72 NW",
    "sg:city":"Greenwood",
    "sg:classifiers":[
        {
            "category":"Restaurant",
            "type":"Food & Drink"
        }
    ],
    "sg:menulink":"http://www.allmenus.com/sc/greenwood/84279-papa-johns-pizza/menu/",
    "sg:phone":"+1 864 223 7777",
    "sg:postcode":"29649",
    "sg:province":"SC",
    "sg:tags":[
        "american",
        "pizza"
    ],
    "wof:name":"Papa John's Pizza",
    "wof:placetype":"venue"
},
  "geometry": {"coordinates":[-82.17855400000001,34.210961],"type":"Point"}
}