{
  "type": "Feature",
  "properties": {
    "iso:country":"US",
    "sg:address":"111 E McGregor St",
    "sg:city":"Pageland",
    "sg:classifiers":[
        {
            "category":"Shopping",
            "subcategory":"Computers & Home Electronics",
            "type":"Retail Goods"
        }
    ],
    "sg:phone":"+1 843 672 6728",
    "sg:postcode":"29728",
    "sg:province":"SC",
    "sg:tags":[
        "equipment",
        "satellite",
        "system"
    ],
    "wof:name":"Harold's Satellite",
    "wof:placetype":"venue"
},
  "geometry": {"coordinates":[-80.39028,34.772332],"type":"Point"}
}