{
  "type": "Feature",
  "properties": {
    "iso:country":"US",
    "sg:address":"202 N Rudolph St",
    "sg:city":"Saluda",
    "sg:classifiers":[
        {
            "category":"Retail",
            "subcategory":"Funeral Services",
            "type":"Services"
        }
    ],
    "sg:phone":"+1 864 445 2366",
    "sg:postcode":"29138",
    "sg:province":"SC",
    "sg:tags":[
        "director"
    ],
    "wof:name":"Ramey Funeral Home",
    "wof:placetype":"venue"
},
  "geometry": {"coordinates":[-81.771083,34.003725],"type":"Point"}
}