{
  "type": "Feature",
  "properties": {
    "addr:full":"209 E Frederick St Gaffney SC 29340",
    "addr:housenumber":"209",
    "addr:postcode":"29340",
    "addr:street":"E Frederick St",
    "iso:country":"US",
    "sg:address":"209 E Frederick St",
    "sg:city":"Gaffney",
    "sg:classifiers":[
        {
            "category":"Insurance",
            "subcategory":"Insurance Agent",
            "type":"Services"
        }
    ],
    "sg:phone":"+1 864 487 4987",
    "sg:postcode":"29340",
    "sg:province":"SC",
    "wof:name":"Terry L White Insurance Inc",
    "wof:placetype":"venue"
},
  "geometry": {"coordinates":[-81.645686,35.07495],"type":"Point"}
}