{
  "type": "Feature",
  "properties": {
    "addr:full":"2760 Boiling Springs Rd Spartanburg SC 29316",
    "addr:postcode":"2760;29316",
    "addr:street":"Boiling Springs Rd",
    "iso:country":"US",
    "sg:address":"2760 Boiling Springs Rd",
    "sg:city":"Spartanburg",
    "sg:classifiers":[
        {
            "category":"Autos & Motor Vehicles",
            "subcategory":"Automobile Sales",
            "type":"Retail Goods"
        }
    ],
    "sg:phone":"+1 864 578 4116",
    "sg:postcode":"29316",
    "sg:province":"SC",
    "sg:tags":[
        "car",
        "dealer"
    ],
    "wof:name":"H W Sanders Used Cars & Svc",
    "wof:placetype":"venue"
},
  "geometry": {"coordinates":[-81.975454,35.040333],"type":"Point"}
}