{
  "type": "Feature",
  "properties": {
    "iso:country":"US",
    "sg:address":"132 W Main St",
    "sg:city":"Duncan",
    "sg:classifiers":[
        {
            "category":"Building & Trades",
            "subcategory":"Construction",
            "type":"Services"
        }
    ],
    "sg:phone":"+1 864 949 5008",
    "sg:postcode":"29334",
    "sg:province":"SC",
    "sg:tags":[
        "contractor"
    ],
    "wof:name":"Scott Construction Svc",
    "wof:placetype":"venue"
},
  "geometry": {"coordinates":[-82.14162899999999,34.937986],"type":"Point"}
}