{
  "type": "Feature",
  "properties": {
    "iso:country":"US",
    "sg:address":"828 Orleans Rd",
    "sg:city":"Charleston",
    "sg:classifiers":[
        {
            "category":"Banks & Credit Unions",
            "subcategory":"Bank",
            "type":"Services"
        }
    ],
    "sg:phone":"+1 843 724 5184",
    "sg:postcode":"29407",
    "sg:province":"SC",
    "sg:website":"www.wachovia.com",
    "wof:name":"Wachovia Bank",
    "wof:placetype":"venue"
},
  "geometry": {"coordinates":[-80.027624,32.793593],"type":"Point"}
}