{
  "type": "Feature",
  "properties": {
    "iso:country":"US",
    "sg:address":"450 W Henry St",
    "sg:city":"Spartanburg",
    "sg:classifiers":[
        {
            "category":"Health Services",
            "subcategory":"Nursing And Care Facility",
            "type":"Services"
        }
    ],
    "sg:phone":"+1 864 562 2470",
    "sg:postcode":"29306",
    "sg:province":"SC",
    "sg:tags":[
        "disabled",
        "independent",
        "for",
        "living"
    ],
    "wof:name":"Charles Lea Ctr Benchmark",
    "wof:placetype":"venue"
},
  "geometry": {"coordinates":[-81.94096,34.943303],"type":"Point"}
}