{
  "type": "Feature",
  "properties": {
    "addr:full":"317 Harden St Columbia SC 29205",
    "addr:housenumber":"317",
    "addr:postcode":"29205",
    "addr:street":"Harden St",
    "iso:country":"US",
    "sg:address":"317 Harden St",
    "sg:city":"Columbia",
    "sg:classifiers":[
        {
            "category":"Professional",
            "subcategory":"Computer Services",
            "type":"Services"
        }
    ],
    "sg:phone":"+1 803 799 5656",
    "sg:postcode":"29205",
    "sg:province":"SC",
    "sg:tags":[
        "consultant",
        "designer"
    ],
    "wof:name":"Woodside & Assoc",
    "wof:placetype":"venue"
},
  "geometry": {"coordinates":[-81.01388799999999,33.994536],"type":"Point"}
}