{
  "type": "Feature",
  "properties": {
    "iso:country":"US",
    "sg:address":"5051 Ammersee Ct",
    "sg:city":"Charleston",
    "sg:classifiers":[
        {
            "category":"Manufacturing",
            "subcategory":"Motor Vehicles & Parts",
            "type":"Manufacturing & Wholesale Goods"
        }
    ],
    "sg:phone":"+1 843 768 5080",
    "sg:postcode":"29414",
    "sg:province":"SC",
    "sg:tags":[
        "mfg"
    ],
    "sg:website":"www.seasidecycles.com",
    "wof:name":"Seaside Cycles",
    "wof:placetype":"venue"
},
  "geometry": {"coordinates":[-80.08578,32.849691],"type":"Point"}
}