{
  "type": "Feature",
  "properties": {
    "iso:country":"US",
    "sg:address":"210 S Memminger St",
    "sg:city":"Greenville",
    "sg:classifiers":[
        {
            "category":"Real Estate",
            "subcategory":"Real Estate Operator",
            "type":"Services"
        }
    ],
    "sg:phone":"+1 864 235 4950",
    "sg:postcode":"29601",
    "sg:province":"SC",
    "sg:tags":[
        "building",
        "apartment"
    ],
    "wof:name":"Gandy Allmon Manor",
    "wof:placetype":"venue"
},
  "geometry": {"coordinates":[-82.41605,34.839095],"type":"Point"}
}