{
  "type": "Feature",
  "properties": {
    "iso:country":"US",
    "sg:address":"1216 N Main St",
    "sg:city":"Summerville",
    "sg:classifiers":[
        {
            "category":"Restaurant",
            "type":"Food & Drink"
        }
    ],
    "sg:menulink":"http://www.allmenus.com/sc/goose-creek-hanahan/85605-dominos-pizza/menu/",
    "sg:phone":"+1 843 875 7300",
    "sg:postcode":"29483",
    "sg:province":"SC",
    "sg:tags":[
        "american",
        "wing",
        "pizza"
    ],
    "wof:name":"Domino's Pizza",
    "wof:placetype":"venue"
},
  "geometry": {"coordinates":[-80.158401,33.036084],"type":"Point"}
}