{
  "type": "Feature",
  "properties": {
    "addr:full":"114 Front St Cheraw SC 29520",
    "addr:housenumber":"114",
    "addr:postcode":"29520",
    "addr:street":"Front St",
    "iso:country":"US",
    "sg:address":"114 Front St",
    "sg:city":"Cheraw",
    "sg:classifiers":[
        {
            "category":"Manufacturing",
            "subcategory":"Printing",
            "type":"Manufacturing & Wholesale Goods"
        }
    ],
    "sg:phone":"+1 843 537 5261",
    "sg:postcode":"29520",
    "sg:province":"SC",
    "sg:tags":[
        "newspaper"
    ],
    "sg:website":"www.thecherawchronicle.com",
    "wof:name":"Cheraw Chronicle",
    "wof:placetype":"venue"
},
  "geometry": {"coordinates":[-79.881243,34.698448],"type":"Point"}
}