{
  "type": "Feature",
  "properties": {
    "addr:full":"2033 Reynolds Rd Barnwell SC 29812",
    "addr:housenumber":"2033",
    "addr:postcode":"29812",
    "addr:street":"Reynolds Rd",
    "iso:country":"US",
    "sg:address":"2033 Reynolds Rd",
    "sg:city":"Barnwell",
    "sg:classifiers":[
        {
            "category":"Retail",
            "subcategory":"Auto Repair",
            "type":"Services"
        }
    ],
    "sg:phone":"+1 803 259 2723",
    "sg:postcode":"29812",
    "sg:province":"SC",
    "sg:tags":[
        "body",
        "automobile",
        "painting"
    ],
    "wof:name":"Sunny Body Shop",
    "wof:placetype":"venue"
},
  "geometry": {"coordinates":[-81.351578,33.278388],"type":"Point"}
}