{
  "type": "Feature",
  "properties": {
    "addr:full":"112 Snow Rd Columbia SC 29223",
    "addr:housenumber":"112",
    "addr:postcode":"29223",
    "addr:street":"Snow Rd",
    "iso:country":"US",
    "sg:address":"112 Snow Rd",
    "sg:city":"Columbia",
    "sg:classifiers":[
        {
            "category":"Organizations",
            "subcategory":"Religious Organization",
            "type":"Services"
        }
    ],
    "sg:phone":"+1 803 419 9288",
    "sg:postcode":"29223",
    "sg:province":"SC",
    "sg:tags":[
        "church"
    ],
    "wof:name":"Korean Methodist Church",
    "wof:placetype":"venue"
},
  "geometry": {"coordinates":[-80.93826199999999,34.093981],"type":"Point"}
}