{
  "type": "Feature",
  "properties": {
    "iso:country":"US",
    "sg:address":"944 Harden St",
    "sg:city":"Columbia",
    "sg:classifiers":[
        {
            "category":"Education",
            "subcategory":"Special Training",
            "type":"Public Place"
        },
        {
            "category":"Shopping",
            "subcategory":"Musical Instruments",
            "type":"Retail Goods"
        }
    ],
    "sg:phone":"+1 803 256 3876",
    "sg:postcode":"29205",
    "sg:province":"SC",
    "sg:tags":[
        "instruction",
        "music"
    ],
    "wof:name":"Danny's Drumming Studio",
    "wof:placetype":"venue"
},
  "geometry": {"coordinates":[-81.017723,34.003091],"type":"Point"}
}