{
  "type": "Feature",
  "properties": {
    "iso:country":"US",
    "sg:address":"126 Wentworth St",
    "sg:city":"Charleston",
    "sg:classifiers":[
        {
            "category":"Travel",
            "subcategory":"Hotels & Motels",
            "type":"Entertainment"
        }
    ],
    "sg:phone":"+1 843 723 7166",
    "sg:postcode":"29401",
    "sg:province":"SC",
    "sg:tags":[
        "breakfast",
        "accommodation",
        "bed"
    ],
    "wof:name":"1837 Bed & Breakfast Tearoom",
    "wof:placetype":"venue"
},
  "geometry": {"coordinates":[-79.938829,32.780546],"type":"Point"}
}