{
  "type": "Feature",
  "properties": {
    "iso:country":"US",
    "sg:address":"107 Osborne St",
    "sg:city":"Union",
    "sg:classifiers":[
        {
            "category":"Building & Trades",
            "subcategory":"Electrical",
            "type":"Services"
        }
    ],
    "sg:phone":"+1 864 427 0100",
    "sg:postcode":"29379",
    "sg:province":"SC",
    "sg:tags":[
        "electric",
        "contractor"
    ],
    "wof:name":"Williford Electrical",
    "wof:placetype":"venue"
},
  "geometry": {"coordinates":[-81.59400599999999,34.720581],"type":"Point"}
}