{
  "type": "Feature",
  "properties": {
    "addr:full":"4811 Broad St Loris SC 29569",
    "addr:housenumber":"4811",
    "addr:postcode":"29569",
    "addr:street":"Broad St",
    "iso:country":"US",
    "sg:address":"4811 Broad St",
    "sg:city":"Loris",
    "sg:classifiers":[
        {
            "category":"Food & Beverages",
            "subcategory":"Groceries & Convenience Stores",
            "type":"Retail Goods"
        }
    ],
    "sg:phone":"+1 843 756 2626",
    "sg:postcode":"29569",
    "sg:province":"SC",
    "wof:name":"Tiger Mart",
    "wof:placetype":"venue"
},
  "geometry": {"coordinates":[-78.884372,34.061292],"type":"Point"}
}