{
  "type": "Feature",
  "properties": {
    "iso:country":"US",
    "sg:address":"1849 W Homewood Rd",
    "sg:city":"Conway",
    "sg:classifiers":[
        {
            "category":"Building & Trades",
            "subcategory":"Cleaning & Sanitation",
            "type":"Services"
        }
    ],
    "sg:phone":"+1 843 365 7948",
    "sg:postcode":"29526",
    "sg:province":"SC",
    "sg:tags":[
        "janitor"
    ],
    "wof:name":"A To Z Cleaning Inc",
    "wof:placetype":"venue"
},
  "geometry": {"coordinates":[-79.06658,33.909231],"type":"Point"}
}