{
  "type": "Feature",
  "properties": {
    "addr:full":"1908 S Main St Anderson SC 29624",
    "addr:housenumber":"1908",
    "addr:postcode":"29624",
    "addr:street":"S Main St",
    "iso:country":"US",
    "sg:address":"1908 S Main St",
    "sg:city":"Anderson",
    "sg:classifiers":[
        {
            "category":"Autos & Motor Vehicles",
            "subcategory":"Auto Supplies",
            "type":"Retail Goods"
        }
    ],
    "sg:phone":"+1 864 225 8442",
    "sg:postcode":"29624",
    "sg:province":"SC",
    "sg:tags":[
        "tire"
    ],
    "wof:name":"South Main Street Tire",
    "wof:placetype":"venue"
},
  "geometry": {"coordinates":[-82.66759500000001,34.45149],"type":"Point"}
}