{
  "type": "Feature",
  "properties": {
    "iso:country":"US",
    "sg:address":"16 S Lewis Plz",
    "sg:city":"Greenville",
    "sg:classifiers":[
        {
            "category":"Personal",
            "type":"Services"
        }
    ],
    "sg:phone":"+1 864 370 3325",
    "sg:postcode":"29605",
    "sg:province":"SC",
    "sg:tags":[
        "therapist",
        "massage"
    ],
    "wof:name":"Greenville Myotherapeutic",
    "wof:placetype":"venue"
},
  "geometry": {"coordinates":[-82.398799,34.826944],"type":"Point"}
}