{
  "type": "Feature",
  "properties": {
    "addr:full":"906 White Horse Rd Greenville SC 29605",
    "addr:housenumber":"906",
    "addr:postcode":"29605",
    "addr:street":"White Horse Rd",
    "iso:country":"US",
    "sg:address":"906 White Horse Rd",
    "sg:city":"Greenville",
    "sg:classifiers":[
        {
            "category":"Organizations",
            "subcategory":"Religious Organization",
            "type":"Services"
        }
    ],
    "sg:phone":"+1 864 422 0812",
    "sg:postcode":"29605",
    "sg:province":"SC",
    "sg:tags":[
        "church"
    ],
    "wof:name":"Resurrected Treasure Ministry",
    "wof:placetype":"venue"
},
  "geometry": {"coordinates":[-82.39713999999999,34.780898],"type":"Point"}
}