{
  "type": "Feature",
  "properties": {
    "iso:country":"US",
    "sg:address":"200 W Church St",
    "sg:city":"Bishopville",
    "sg:classifiers":[
        {
            "category":"Retail",
            "subcategory":"Funeral Services",
            "type":"Services"
        }
    ],
    "sg:phone":"+1 803 484 6116",
    "sg:postcode":"29010",
    "sg:province":"SC",
    "sg:tags":[
        "plan"
    ],
    "wof:name":"Hancock-Elmore-Hill Funeral Hm",
    "wof:placetype":"venue"
},
  "geometry": {"coordinates":[-80.250843,34.220026],"type":"Point"}
}