{
  "type": "Feature",
  "properties": {
    "iso:country":"US",
    "sg:address":"1222 Broughton St",
    "sg:city":"Orangeburg",
    "sg:classifiers":[
        {
            "category":"Banks & Credit Unions",
            "subcategory":"Investment Brokerage",
            "type":"Services"
        }
    ],
    "sg:phone":"+1 803 531 4405",
    "sg:postcode":"29115",
    "sg:province":"SC",
    "sg:tags":[
        "stock",
        "bond"
    ],
    "wof:name":"Zimmerman Co",
    "wof:placetype":"venue"
},
  "geometry": {"coordinates":[-80.867308,33.490549],"type":"Point"}
}