{
  "type": "Feature",
  "properties": {
    "iso:country":"US",
    "sg:address":"1128 E Main St",
    "sg:city":"Easley",
    "sg:classifiers":[
        {
            "category":"Professional",
            "subcategory":"Lawyer & Legal Services",
            "type":"Services"
        }
    ],
    "sg:phone":"+1 864 855 9666",
    "sg:postcode":"29640",
    "sg:province":"SC",
    "sg:tags":[
        "attorney"
    ],
    "wof:name":"Kelvin R Kearse",
    "wof:placetype":"venue"
},
  "geometry": {"coordinates":[-82.577696,34.830262],"type":"Point"}
}