{
  "type": "Feature",
  "properties": {
    "addr:full":"328 Main St Conway SC 29526",
    "addr:housenumber":"328",
    "addr:postcode":"29526",
    "addr:street":"Main St",
    "iso:country":"US",
    "sg:address":"328 Main St",
    "sg:city":"Conway",
    "sg:classifiers":[
        {
            "category":"Shopping",
            "subcategory":"Clothing, Apparel, & Fashions",
            "type":"Retail Goods"
        }
    ],
    "sg:phone":"+1 843 248 3277",
    "sg:postcode":"29526",
    "sg:province":"SC",
    "sg:tags":[
        "shop",
        "bridal"
    ],
    "wof:name":"Amandas Collection The",
    "wof:placetype":"venue"
},
  "geometry": {"coordinates":[-79.046042,33.835283],"type":"Point"}
}