{
  "type": "Feature",
  "properties": {
    "iso:country":"US",
    "sg:address":"120 Chesterfield St N",
    "sg:city":"Aiken",
    "sg:classifiers":[
        {
            "category":"Organizations",
            "subcategory":"Religious Organization",
            "type":"Services"
        }
    ],
    "sg:phone":"+1 803 648 5476",
    "sg:postcode":"29801",
    "sg:province":"SC",
    "sg:tags":[
        "church"
    ],
    "sg:website":"www.fbcaiken.org",
    "wof:name":"First Baptist Church",
    "wof:placetype":"venue"
},
  "geometry": {"coordinates":[-81.718868,33.560996],"type":"Point"}
}