{
  "type": "Feature",
  "properties": {
    "iso:country":"US",
    "sg:address":"148 Maxwell Ave",
    "sg:city":"Greenwood",
    "sg:classifiers":[
        {
            "category":"Health Services",
            "subcategory":"Doctor",
            "type":"Services"
        }
    ],
    "sg:phone":"+1 864 943 2010",
    "sg:postcode":"29646",
    "sg:province":"SC",
    "sg:tags":[
        "physician",
        "surgeon"
    ],
    "wof:name":"Galloway Regional Eye Ctr Pa",
    "wof:placetype":"venue"
},
  "geometry": {"coordinates":[-82.16194,34.190749],"type":"Point"}
}