{
  "type": "Feature",
  "properties": {
    "iso:country":"US",
    "sg:address":"5001 Camellia Dr",
    "sg:city":"Myrtle Beach",
    "sg:classifiers":[
        {
            "category":"Professional",
            "subcategory":"Lawyer & Legal Services",
            "type":"Services"
        }
    ],
    "sg:phone":"+1 843 449 4493",
    "sg:postcode":"29577",
    "sg:province":"SC",
    "sg:tags":[
        "attorney"
    ],
    "wof:name":"Melody Breeden",
    "wof:placetype":"venue"
},
  "geometry": {"coordinates":[-78.84823299999999,33.728145],"type":"Point"}
}