{
  "type": "Feature",
  "properties": {
    "addr:full":"180 Meeting St Charleston SC 29401",
    "addr:housenumber":"180",
    "addr:postcode":"29401",
    "addr:street":"Meeting St",
    "iso:country":"US",
    "sg:address":"180 Meeting St",
    "sg:city":"Charleston",
    "sg:classifiers":[
        {
            "category":"Real Estate",
            "subcategory":"Real Estate Agent",
            "type":"Services"
        }
    ],
    "sg:phone":"+1 843 720 2890",
    "sg:postcode":"29401",
    "sg:province":"SC",
    "wof:name":"Realti Corp",
    "wof:placetype":"venue"
},
  "geometry": {"coordinates":[-79.931348,32.779698],"type":"Point"}
}