{
  "type": "Feature",
  "properties": {
    "iso:country":"US",
    "sg:address":"104 Emery Ct",
    "sg:city":"Inman",
    "sg:classifiers":[
        {
            "category":"Real Estate",
            "subcategory":"Real Estate Operator",
            "type":"Services"
        }
    ],
    "sg:phone":"+1 864 592 9732",
    "sg:postcode":"29349",
    "sg:province":"SC",
    "sg:tags":[
        "building",
        "nonresidential"
    ],
    "wof:name":"Horseshoe Properties LLC",
    "wof:placetype":"venue"
},
  "geometry": {"coordinates":[-82.00329499999999,35.114223],"type":"Point"}
}