{
  "type": "Feature",
  "properties": {
    "iso:country":"US",
    "sg:address":"2401 N Ocean Blvd",
    "sg:city":"Myrtle Beach",
    "sg:classifiers":[
        {
            "category":"Travel",
            "subcategory":"Hotels & Motels",
            "type":"Entertainment"
        }
    ],
    "sg:phone":"+1 800 762 6729",
    "sg:postcode":"29577",
    "sg:province":"SC",
    "sg:tags":[
        "operation",
        "eating",
        "drinking"
    ],
    "wof:name":"Parker House Motel",
    "wof:placetype":"venue"
},
  "geometry": {"coordinates":[-78.86507899999999,33.704973],"type":"Point"}
}