{
  "type": "Feature",
  "properties": {
    "iso:country":"US",
    "sg:address":"2032 Pacolet Hwy",
    "sg:city":"Gaffney",
    "sg:classifiers":[
        {
            "category":"Organizations",
            "subcategory":"Religious Organization",
            "type":"Services"
        }
    ],
    "sg:phone":"+1 864 902 0200",
    "sg:postcode":"29340",
    "sg:province":"SC",
    "sg:tags":[
        "church"
    ],
    "wof:name":"Silica Springs Baptist Church",
    "wof:placetype":"venue"
},
  "geometry": {"coordinates":[-81.691577,35.002535],"type":"Point"}
}