{
  "type": "Feature",
  "properties": {
    "addr:full":"209 Alexander Ave Spartanburg SC 29306",
    "addr:housenumber":"209",
    "addr:postcode":"29306",
    "addr:street":"Alexander Ave",
    "iso:country":"US",
    "sg:address":"209 Alexander Ave",
    "sg:city":"Spartanburg",
    "sg:classifiers":[
        {
            "category":"Organizations",
            "subcategory":"Religious Organization",
            "type":"Services"
        }
    ],
    "sg:phone":"+1 864 585 7499",
    "sg:postcode":"29306",
    "sg:province":"SC",
    "sg:tags":[
        "church"
    ],
    "wof:name":"Shiloh Seventh Day Adventist",
    "wof:placetype":"venue"
},
  "geometry": {"coordinates":[-81.921373,34.939273],"type":"Point"}
}