{
  "type": "Feature",
  "properties": {
    "iso:country":"US",
    "sg:address":"254 Daylight Ln",
    "sg:city":"Georgetown",
    "sg:classifiers":[
        {
            "category":"Food & Beverages",
            "subcategory":"Groceries & Convenience Stores",
            "type":"Retail Goods"
        }
    ],
    "sg:phone":"+1 843 527 2606",
    "sg:postcode":"29488",
    "sg:province":"SC",
    "wof:name":"Beverage Depot",
    "wof:placetype":"venue"
},
  "geometry": {"coordinates":[-80.68821,33.029638],"type":"Point"}
}