{
  "type": "Feature",
  "properties": {
    "iso:country":"US",
    "sg:address":"1032 Abner Creek Rd",
    "sg:city":"Greer",
    "sg:classifiers":[
        {
            "category":"Organizations",
            "subcategory":"Religious Organization",
            "type":"Services"
        }
    ],
    "sg:phone":"+1 864 877 5017",
    "sg:postcode":"29651",
    "sg:province":"SC",
    "sg:tags":[
        "church"
    ],
    "wof:name":"Liberty Hill United Methodist",
    "wof:placetype":"venue"
},
  "geometry": {"coordinates":[-82.198387,34.874281],"type":"Point"}
}