{
  "type": "Feature",
  "properties": {
    "iso:country":"US",
    "sg:address":"30 Red Oak Rd",
    "sg:city":"Ridgeland",
    "sg:classifiers":[
        {
            "category":"Real Estate",
            "subcategory":"Real Estate Agent",
            "type":"Services"
        }
    ],
    "sg:phone":"+1 843 227 5700",
    "sg:postcode":"29928",
    "sg:province":"SC",
    "wof:name":"Resource Development Group",
    "wof:placetype":"venue"
},
  "geometry": {"coordinates":[-80.809566,32.128136],"type":"Point"}
}