{
  "type": "Feature",
  "properties": {
    "addr:full":"71 Shadowmoss Pkwy Charleston SC 29414",
    "addr:housenumber":"71",
    "addr:postcode":"29414",
    "addr:street":"Shadowmoss Pkwy",
    "iso:country":"US",
    "sg:address":"71 Shadowmoss Pkwy",
    "sg:city":"Charleston",
    "sg:classifiers":[
        {
            "category":"Professional",
            "subcategory":"Computer Services",
            "type":"Services"
        }
    ],
    "sg:phone":"+1 843 766 0782",
    "sg:postcode":"29414",
    "sg:province":"SC",
    "sg:tags":[
        "repair"
    ],
    "wof:name":"Computer Wrestlers",
    "wof:placetype":"venue"
},
  "geometry": {"coordinates":[-80.072231,32.845273],"type":"Point"}
}