{
  "type": "Feature",
  "properties": {
    "iso:country":"US",
    "sg:address":"59 Barre St",
    "sg:city":"Charleston",
    "sg:classifiers":[
        {
            "category":"Banks & Credit Unions",
            "subcategory":"Bank",
            "type":"Services"
        }
    ],
    "sg:phone":"+1 843 937 4923",
    "sg:postcode":"29401",
    "sg:province":"SC",
    "sg:tags":[
        "federal",
        "agency"
    ],
    "wof:name":"Ef International",
    "wof:placetype":"venue"
},
  "geometry": {"coordinates":[-79.946502,32.780093],"type":"Point"}
}