{
  "type": "Feature",
  "properties": {
    "iso:country":"US",
    "sg:address":"10231 N Kings Hwy",
    "sg:city":"Myrtle Beach",
    "sg:classifiers":[
        {
            "category":"Travel",
            "subcategory":"Hotels & Motels",
            "type":"Entertainment"
        }
    ],
    "sg:phone":"+1 843 361 8000",
    "sg:postcode":"29572",
    "sg:province":"SC",
    "sg:website":"www.myrtlebeachfairfield.com",
    "wof:name":"Fairfield Inn",
    "wof:placetype":"venue"
},
  "geometry": {"coordinates":[-78.75542799999999,33.793688],"type":"Point"}
}