{
  "type": "Feature",
  "properties": {
    "iso:country":"US",
    "sg:address":"880 Rutherfordton Hwy",
    "sg:city":"Chesnee",
    "sg:classifiers":[
        {
            "category":"Autos & Motor Vehicles",
            "subcategory":"Automobile Sales",
            "type":"Retail Goods"
        },
        {
            "category":"Wholesale",
            "subcategory":"Motor Vehicles",
            "type":"Manufacturing & Wholesale Goods"
        }
    ],
    "sg:phone":"+1 864 461 3107",
    "sg:postcode":"29323",
    "sg:province":"SC",
    "sg:tags":[
        "truck"
    ],
    "wof:name":"Greene Whitey Truck Ranch",
    "wof:placetype":"venue"
},
  "geometry": {"coordinates":[-81.844072,35.171412],"type":"Point"}
}