{
  "type": "Feature",
  "properties": {
    "iso:country":"US",
    "sg:address":"2700 Poinsett Hwy",
    "sg:city":"Greenville",
    "sg:classifiers":[
        {
            "category":"Food & Beverages",
            "subcategory":"Liquor & Beverages",
            "type":"Retail Goods"
        }
    ],
    "sg:phone":"+1 864 271 1032",
    "sg:postcode":"29609",
    "sg:province":"SC",
    "wof:name":"Poinsett Beverage",
    "wof:placetype":"venue"
},
  "geometry": {"coordinates":[-82.432884,34.919643],"type":"Point"}
}