{
  "type": "Feature",
  "properties": {
    "iso:country":"US",
    "sg:address":"820 Inlet Square Dr",
    "sg:city":"Murrells Inlet",
    "sg:classifiers":[
        {
            "category":"Shopping",
            "type":"Retail Goods"
        }
    ],
    "sg:phone":"+1 843 651 8593",
    "sg:postcode":"29576",
    "sg:province":"SC",
    "sg:tags":[
        "pet",
        "shop",
        "merchandise"
    ],
    "wof:name":"Animal Odyssey",
    "wof:placetype":"venue"
},
  "geometry": {"coordinates":[-79.02586599999999,33.58452],"type":"Point"}
}