{
  "type": "Feature",
  "properties": {
    "addr:full":"509 By Pass 123 Seneca SC 29678",
    "addr:housenumber":"509;123",
    "addr:postcode":"29678",
    "addr:street":"By Pass",
    "iso:country":"US",
    "sg:address":"509 By Pass 123",
    "sg:city":"Seneca",
    "sg:classifiers":[
        {
            "category":"Restaurant",
            "type":"Food & Drink"
        }
    ],
    "sg:menulink":"http://www.allmenus.com/sc/seneca/101914-huddle-house/menu/",
    "sg:phone":"+1 864 882 9525",
    "sg:postcode":"29678",
    "sg:province":"SC",
    "sg:tags":[
        "american",
        "diner"
    ],
    "wof:name":"Huddle House",
    "wof:placetype":"venue"
},
  "geometry": {"coordinates":[-82.954781,34.697444],"type":"Point"}
}