{
  "type": "Feature",
  "properties": {
    "iso:country":"US",
    "sg:address":"2259 Flint Hill Rd",
    "sg:city":"Camden",
    "sg:classifiers":[
        {
            "category":"Organizations",
            "subcategory":"Religious Organization",
            "type":"Services"
        }
    ],
    "sg:phone":"+1 803 713 9044",
    "sg:postcode":"29020",
    "sg:province":"SC",
    "sg:tags":[
        "reach",
        "ministry"
    ],
    "wof:name":"Shepherd's Fold Ministries",
    "wof:placetype":"venue"
},
  "geometry": {"coordinates":[-80.693173,34.382032],"type":"Point"}
}