{
  "type": "Feature",
  "properties": {
    "iso:country":"US",
    "sg:address":"819 Folly Rd",
    "sg:city":"Charleston",
    "sg:classifiers":[
        {
            "category":"Personal",
            "subcategory":"Barber",
            "type":"Services"
        }
    ],
    "sg:phone":"+1 843 762 9008",
    "sg:postcode":"29412",
    "sg:province":"SC",
    "wof:name":"Bushwhacker's",
    "wof:placetype":"venue"
},
  "geometry": {"coordinates":[-79.967105,32.739682],"type":"Point"}
}