{
  "type": "Feature",
  "properties": {
    "addr:full":"1766 Knox Ave North Augusta SC 29841",
    "addr:housenumber":"1766",
    "addr:postcode":"29841",
    "addr:street":"Knox Ave",
    "iso:country":"US",
    "sg:address":"1766 Knox Ave",
    "sg:city":"North Augusta",
    "sg:classifiers":[
        {
            "category":"Organizations",
            "subcategory":"Religious Organization",
            "type":"Services"
        }
    ],
    "sg:phone":"+1 803 279 6690",
    "sg:postcode":"29841",
    "sg:province":"SC",
    "sg:tags":[
        "church"
    ],
    "wof:name":"Riverside Church Of Christ",
    "wof:placetype":"venue"
},
  "geometry": {"coordinates":[-81.956534,33.515651],"type":"Point"}
}