{
  "type": "Feature",
  "properties": {
    "addr:full":"8861 Pee Dee Hwy Conway SC 29527",
    "addr:housenumber":"8861",
    "addr:postcode":"29527",
    "addr:street":"Pee Dee Hwy",
    "iso:country":"US",
    "sg:address":"8861 Pee Dee Hwy",
    "sg:city":"Conway",
    "sg:classifiers":[
        {
            "category":"Food & Beverages",
            "subcategory":"Specialty",
            "type":"Retail Goods"
        }
    ],
    "sg:phone":"+1 843 358 0986",
    "sg:postcode":"29527",
    "sg:province":"SC",
    "sg:tags":[
        "water",
        "bulk",
        "company"
    ],
    "wof:name":"Bucksport Water",
    "wof:placetype":"venue"
},
  "geometry": {"coordinates":[-79.233634,33.875071],"type":"Point"}
}