{
  "type": "Feature",
  "properties": {
    "iso:country":"US",
    "sg:address":"293 S Pine St",
    "sg:city":"Spartanburg",
    "sg:classifiers":[
        {
            "category":"Building & Trades",
            "subcategory":"Construction",
            "type":"Services"
        }
    ],
    "sg:phone":"+1 864 542 1442",
    "sg:postcode":"29302",
    "sg:province":"SC",
    "sg:tags":[
        "contractor"
    ],
    "wof:name":"Champion Parker Construction",
    "wof:placetype":"venue"
},
  "geometry": {"coordinates":[-81.916546,34.948761],"type":"Point"}
}