{
  "type": "Feature",
  "properties": {
    "addr:full":"107 Seven Oaks Ln Summerville SC 29485",
    "addr:housenumber":"107",
    "addr:postcode":"29485",
    "addr:street":"Seven Oaks Ln",
    "iso:country":"US",
    "sg:address":"107 Seven Oaks Ln",
    "sg:city":"Summerville",
    "sg:classifiers":[
        {
            "category":"Building & Trades",
            "subcategory":"Construction",
            "type":"Services"
        }
    ],
    "sg:phone":"+1 843 832 2929",
    "sg:postcode":"29485",
    "sg:province":"SC",
    "sg:tags":[
        "concrete",
        "contractor"
    ],
    "wof:name":"KWIK Kerb",
    "wof:placetype":"venue"
},
  "geometry": {"coordinates":[-80.15234100000001,32.940993],"type":"Point"}
}