{
  "type": "Feature",
  "properties": {
    "iso:country":"US",
    "sg:address":"4634 Broad St",
    "sg:city":"Sumter",
    "sg:classifiers":[
        {
            "category":"Restaurant",
            "type":"Food & Drink"
        }
    ],
    "sg:phone":"+1 803 494 8484",
    "sg:postcode":"29154",
    "sg:province":"SC",
    "sg:tags":[
        "eating"
    ],
    "wof:name":"Twin Dragon Chinese Restaurant",
    "wof:placetype":"venue"
},
  "geometry": {"coordinates":[-80.460729,33.964011],"type":"Point"}
}