{
  "type": "Feature",
  "properties": {
    "addr:full":"601 Silver Bluff Rd Suite 10 Aiken SC 29803",
    "addr:housenumber":"601;10",
    "addr:postcode":"29803",
    "addr:street":"Silver Bluff Rd Suite",
    "iso:country":"US",
    "sg:address":"601 Silver Bluff Rd Suite 10",
    "sg:city":"Aiken",
    "sg:classifiers":[
        {
            "category":"Exhibition Hall",
            "type":"Public Place"
        },
        {
            "category":"Recreation",
            "subcategory":"Dance Hall",
            "type":"Entertainment"
        },
        {
            "category":"Retail",
            "subcategory":"Event Space",
            "type":"Services"
        },
        {
            "category":"Arts & Performance",
            "subcategory":"Dance",
            "type":"Entertainment"
        }
    ],
    "sg:phone":"+1 803 641 4800",
    "sg:postcode":"29803",
    "sg:province":"SC",
    "sg:tags":[
        "ballroom",
        "dancing",
        "instruction",
        "halls",
        "facility",
        "reception",
        "banquet",
        "auditorium"
    ],
    "wof:name":"Aikens Palmetto Ballroom",
    "wof:placetype":"venue"
},
  "geometry": {"coordinates":[-81.729147,33.516419],"type":"Point"}
}