{
  "type": "Feature",
  "properties": {
    "iso:country":"US",
    "sg:address":"18 Big Oak St",
    "sg:city":"Hilton Head Island",
    "sg:classifiers":[
        {
            "category":"Building & Trades",
            "subcategory":"Landscaping Services",
            "type":"Services"
        }
    ],
    "sg:phone":"+1 843 341 5700",
    "sg:postcode":"29926",
    "sg:province":"SC",
    "sg:tags":[
        "lighting",
        "landscape",
        "contractor"
    ],
    "wof:name":"Sunset Landscape Lighting Inc",
    "wof:placetype":"venue"
},
  "geometry": {"coordinates":[-80.802718,32.22983],"type":"Point"}
}