{
  "type": "Feature",
  "properties": {
    "addr:full":"2416 Air Park Rd Charleston SC 29406",
    "addr:housenumber":"2416",
    "addr:postcode":"29406",
    "addr:street":"Air Park Rd",
    "iso:country":"US",
    "sg:address":"2416 Air Park Rd",
    "sg:city":"Charleston",
    "sg:classifiers":[
        {
            "category":"Manufacturing",
            "subcategory":"Printing",
            "type":"Manufacturing & Wholesale Goods"
        }
    ],
    "sg:phone":"+1 843 571 1214",
    "sg:postcode":"29406",
    "sg:province":"SC",
    "sg:tags":[
        "arts",
        "graphic",
        "design",
        "related",
        "offset"
    ],
    "wof:name":"Advantagegraphics",
    "wof:placetype":"venue"
},
  "geometry": {"coordinates":[-80.02066600000001,32.894657],"type":"Point"}
}