{
  "type": "Feature",
  "properties": {
    "iso:country":"US",
    "sg:address":"4501 Planer Rd",
    "sg:city":"Effingham",
    "sg:classifiers":[
        {
            "category":"Building & Trades",
            "subcategory":"Construction",
            "type":"Services"
        }
    ],
    "sg:phone":"+1 843 665 8893",
    "sg:postcode":"29505",
    "sg:province":"SC",
    "sg:tags":[
        "backhoe",
        "excavating",
        "pool",
        "contractor"
    ],
    "wof:name":"Hewitt Construction Inc",
    "wof:placetype":"venue"
},
  "geometry": {"coordinates":[-79.658959,34.080222],"type":"Point"}
}