{
  "type": "Feature",
  "properties": {
    "iso:country":"US",
    "sg:address":"11 Palmetto Bay Rd",
    "sg:city":"Hilton Head Island",
    "sg:classifiers":[
        {
            "category":"Coffee & Tea",
            "type":"Food & Drink"
        }
    ],
    "sg:menulink":"http://www.allmenus.com/sc/hilton-head-island/119149-starbucks-coffee/menu/",
    "sg:phone":"+1 843 341 5477",
    "sg:postcode":"29928",
    "sg:province":"SC",
    "sg:tags":[
        "american"
    ],
    "wof:name":"Starbucks Coffee",
    "wof:placetype":"venue"
},
  "geometry": {"coordinates":[-80.763408,32.156385],"type":"Point"}
}