{
  "type": "Feature",
  "properties": {
    "iso:country":"US",
    "sg:address":"502 Easley Bridge Rd",
    "sg:city":"Greenville",
    "sg:classifiers":[
        {
            "category":"Personal",
            "subcategory":"Barber",
            "type":"Services"
        }
    ],
    "sg:phone":"+1 864 295 1533",
    "sg:postcode":"29611",
    "sg:province":"SC",
    "wof:name":"Jimmy & Schoolboy Hair & Style",
    "wof:placetype":"venue"
},
  "geometry": {"coordinates":[-82.426389,34.840344],"type":"Point"}
}