{
  "type": "Feature",
  "properties": {
    "addr:full":"1605 Executive Ave Myrtle Beach SC 29577",
    "addr:housenumber":"1605",
    "addr:postcode":"29577",
    "addr:street":"Executive Ave",
    "iso:country":"US",
    "sg:address":"1605 Executive Ave",
    "sg:city":"Myrtle Beach",
    "sg:classifiers":[
        {
            "category":"Building & Trades",
            "subcategory":"Construction",
            "type":"Services"
        }
    ],
    "sg:phone":"+1 843 448 3916",
    "sg:postcode":"29577",
    "sg:province":"SC",
    "sg:tags":[
        "acoustical",
        "contractor"
    ],
    "wof:name":"Young Ceiling System Inc",
    "wof:placetype":"venue"
},
  "geometry": {"coordinates":[-78.90115900000001,33.702402],"type":"Point"}
}