{
  "type": "Feature",
  "properties": {
    "addr:full":"1810 2nd Loop Rd Florence SC 29501",
    "addr:housenumber":"1810",
    "addr:postcode":"29501",
    "addr:street":"2Nd Loop Rd",
    "iso:country":"US",
    "sg:address":"1810 2nd Loop Rd",
    "sg:city":"Florence",
    "sg:classifiers":[
        {
            "category":"Banks & Credit Unions",
            "subcategory":"Investment Brokerage",
            "type":"Services"
        }
    ],
    "sg:phone":"+1 843 667 8766",
    "sg:postcode":"29501",
    "sg:province":"SC",
    "sg:tags":[
        "security"
    ],
    "wof:name":"Edward Jones Co",
    "wof:placetype":"venue"
},
  "geometry": {"coordinates":[-79.797915,34.169507],"type":"Point"}
}