{
  "type": "Feature",
  "properties": {
    "iso:country":"US",
    "sg:address":"110 Hawk Rd",
    "sg:city":"Simpsonville",
    "sg:classifiers":[
        {
            "category":"Freight",
            "type":"Transportation"
        }
    ],
    "sg:phone":"+1 864 963 8110",
    "sg:postcode":"29681",
    "sg:province":"SC",
    "sg:tags":[
        "delivery"
    ],
    "wof:name":"Hawk Chassis",
    "wof:placetype":"venue"
},
  "geometry": {"coordinates":[-82.29158,34.76438],"type":"Point"}
}