{
  "type": "Feature",
  "properties": {
    "addr:full":"2611 Duncan Chapel Rd Greenville SC 29617",
    "addr:housenumber":"2611",
    "addr:postcode":"29617",
    "addr:street":"Duncan Chapel Rd",
    "iso:country":"US",
    "sg:address":"2611 Duncan Chapel Rd",
    "sg:city":"Greenville",
    "sg:classifiers":[
        {
            "category":"Building & Trades",
            "subcategory":"Electrical",
            "type":"Services"
        }
    ],
    "sg:phone":"+1 864 294 1204",
    "sg:postcode":"29617",
    "sg:province":"SC",
    "sg:tags":[
        "lawn",
        "electrical",
        "garden",
        "contractor"
    ],
    "wof:name":"Kaleidoscope Cnstr & Dev",
    "wof:placetype":"venue"
},
  "geometry": {"coordinates":[-82.451244,34.92568],"type":"Point"}
}