{
  "type": "Feature",
  "properties": {
    "addr:full":"214 N Main St Campobello SC 29322",
    "addr:housenumber":"214",
    "addr:postcode":"29322",
    "addr:street":"N Main St",
    "iso:country":"US",
    "sg:address":"214 N Main St",
    "sg:city":"Campobello",
    "sg:classifiers":[
        {
            "category":"Personal",
            "subcategory":"Barber",
            "type":"Services"
        }
    ],
    "sg:phone":"+1 864 468 4756",
    "sg:postcode":"29322",
    "sg:province":"SC",
    "wof:name":"Karen's Barber Shop",
    "wof:placetype":"venue"
},
  "geometry": {"coordinates":[-82.154393,35.11624],"type":"Point"}
}