{
  "type": "Feature",
  "properties": {
    "iso:country":"US",
    "sg:address":"681 Orleans Rd",
    "sg:city":"Charleston",
    "sg:classifiers":[
        {
            "category":"Health Services",
            "subcategory":"Clinic",
            "type":"Services"
        }
    ],
    "sg:phone":"+1 843 556 2784",
    "sg:postcode":"29407",
    "sg:province":"SC",
    "sg:tags":[
        "home"
    ],
    "sg:website":"www.nursehf.com",
    "wof:name":"Health Force",
    "wof:placetype":"venue"
},
  "geometry": {"coordinates":[-80.02753,32.792009],"type":"Point"}
}