{
  "type": "Feature",
  "properties": {
    "iso:country":"US",
    "sg:address":"720 Barrel Stave Rd",
    "sg:city":"Clinton",
    "sg:classifiers":[
        {
            "category":"Shopping",
            "subcategory":"Used Merchandise",
            "type":"Retail Goods"
        }
    ],
    "sg:phone":"+1 864 833 4907",
    "sg:postcode":"29325",
    "sg:province":"SC",
    "wof:name":"Lesas Variety Shop",
    "wof:placetype":"venue"
},
  "geometry": {"coordinates":[-81.841815,34.518142],"type":"Point"}
}