{
  "type": "Feature",
  "properties": {
    "addr:full":"402 E Railroad St Seneca SC 29678",
    "addr:housenumber":"402",
    "addr:postcode":"29678",
    "addr:street":"E Railroad St",
    "iso:country":"US",
    "sg:address":"402 E Railroad St",
    "sg:city":"Seneca",
    "sg:classifiers":[
        {
            "category":"Building & Trades",
            "subcategory":"Plumbing",
            "type":"Services"
        }
    ],
    "sg:phone":"+1 864 882 4905",
    "sg:postcode":"29678",
    "sg:province":"SC",
    "sg:tags":[
        "conditioning",
        "air",
        "system",
        "contractor"
    ],
    "wof:name":"Coster Heating & Air Cond Inc",
    "wof:placetype":"venue"
},
  "geometry": {"coordinates":[-82.948865,34.684623],"type":"Point"}
}