{
  "type": "Feature",
  "properties": {
    "addr:full":"175 Truck Stop Rd Cowpens SC 29330",
    "addr:housenumber":"175",
    "addr:postcode":"29330",
    "addr:street":"Stop Rd",
    "iso:country":"US",
    "sg:address":"175 Truck Stop Rd",
    "sg:city":"Cowpens",
    "sg:classifiers":[
        {
            "category":"Restaurant",
            "type":"Food & Drink"
        }
    ],
    "sg:phone":"+1 864 463 6464",
    "sg:postcode":"29330",
    "sg:province":"SC",
    "wof:name":"Mr Waffle Truck Stop",
    "wof:placetype":"venue"
},
  "geometry": {"coordinates":[-81.81249,35.045937],"type":"Point"}
}