{
  "type": "Feature",
  "properties": {
    "iso:country":"US",
    "sg:address":"106 Darby Rd",
    "sg:city":"Spartanburg",
    "sg:classifiers":[
        {
            "category":"Recreation",
            "type":"Entertainment"
        }
    ],
    "sg:phone":"+1 864 596 3501",
    "sg:postcode":"29306",
    "sg:province":"SC",
    "sg:tags":[
        "historical"
    ],
    "wof:name":"Seay House",
    "wof:placetype":"venue"
},
  "geometry": {"coordinates":[-81.941689,34.929964],"type":"Point"}
}