{
  "type": "Feature",
  "properties": {
    "iso:country":"US",
    "sg:address":"2309 Acie Ave",
    "sg:city":"Conway",
    "sg:classifiers":[
        {
            "category":"Manufacturing",
            "subcategory":"Retail Goods",
            "type":"Manufacturing & Wholesale Goods"
        }
    ],
    "sg:phone":"+1 843 488 5115",
    "sg:postcode":"29527",
    "sg:province":"SC",
    "sg:tags":[
        "manufacturer"
    ],
    "sg:website":"www.botanicalgardens.com",
    "wof:name":"Botanical Habitats",
    "wof:placetype":"venue"
},
  "geometry": {"coordinates":[-79.088283,33.847924],"type":"Point"}
}