{
  "type": "Feature",
  "properties": {
    "iso:country":"US",
    "sg:address":"303 Ross St",
    "sg:city":"Piedmont",
    "sg:classifiers":[
        {
            "category":"Retail",
            "subcategory":"Animal Services",
            "type":"Services"
        }
    ],
    "sg:phone":"+1 864 292 9281",
    "sg:postcode":"29673",
    "sg:province":"SC",
    "sg:tags":[
        "pet",
        "crematory",
        "cemetery"
    ],
    "sg:website":"www.gshep.com",
    "wof:name":"Good Shepherd Pet Svc Inc",
    "wof:placetype":"venue"
},
  "geometry": {"coordinates":[-82.47169700000001,34.707643],"type":"Point"}
}