{
  "type": "Feature",
  "properties": {
    "addr:full":"132 Barr Rd Lexington SC 29072",
    "addr:housenumber":"132",
    "addr:postcode":"29072",
    "addr:street":"Barr Rd",
    "iso:country":"US",
    "sg:address":"132 Barr Rd",
    "sg:city":"Lexington",
    "sg:classifiers":[
        {
            "category":"Personal",
            "subcategory":"Beauty Salon",
            "type":"Services"
        }
    ],
    "sg:phone":"+1 803 359 9854",
    "sg:postcode":"29072",
    "sg:province":"SC",
    "wof:name":"Unisex Styles",
    "wof:placetype":"venue"
},
  "geometry": {"coordinates":[-81.262502,33.980506],"type":"Point"}
}