{
  "type": "Feature",
  "properties": {
    "iso:country":"US",
    "sg:address":"590 Westmoreland Rd",
    "sg:city":"Woodruff",
    "sg:classifiers":[
        {
            "category":"Wholesale",
            "subcategory":"Machinery & Supplies",
            "type":"Manufacturing & Wholesale Goods"
        },
        {
            "category":"Manufacturing",
            "subcategory":"Tools & Machinery",
            "type":"Manufacturing & Wholesale Goods"
        }
    ],
    "sg:phone":"+1 864 476 3132",
    "sg:postcode":"29388",
    "sg:province":"SC",
    "sg:tags":[
        "shop",
        "repair",
        "industrial",
        "machine",
        "equipment",
        "welding"
    ],
    "wof:name":"C & F Machining Inc",
    "wof:placetype":"venue"
},
  "geometry": {"coordinates":[-82.111155,34.771123],"type":"Point"}
}