{
  "type": "Feature",
  "properties": {
    "iso:country":"US",
    "sg:address":"596 Hodgens Dr",
    "sg:city":"Travelers Rest",
    "sg:classifiers":[
        {
            "category":"Government",
            "subcategory":"Fire Station",
            "type":"Public Place"
        }
    ],
    "sg:phone":"+1 864 834 9332",
    "sg:postcode":"29690",
    "sg:province":"SC",
    "sg:tags":[
        "department"
    ],
    "wof:name":"North Greenville Fire District",
    "wof:placetype":"venue"
},
  "geometry": {"coordinates":[-82.476357,34.970711],"type":"Point"}
}