{
  "type": "Feature",
  "properties": {
    "iso:country":"US",
    "sg:address":"415 W Boyce St",
    "sg:city":"Manning",
    "sg:classifiers":[
        {
            "category":"Shopping",
            "type":"Retail Goods"
        }
    ],
    "sg:phone":"+1 803 435 4400",
    "sg:postcode":"29102",
    "sg:province":"SC",
    "sg:tags":[
        "telephone",
        "cellular"
    ],
    "wof:name":"Phone Smart",
    "wof:placetype":"venue"
},
  "geometry": {"coordinates":[-80.222026,33.696671],"type":"Point"}
}