{
  "type": "Feature",
  "properties": {
    "iso:country":"US",
    "sg:address":"797 Post Oak Dr",
    "sg:city":"Mount Pleasant",
    "sg:classifiers":[
        {
            "category":"Building & Trades",
            "subcategory":"Construction",
            "type":"Services"
        }
    ],
    "sg:phone":"+1 843 849 0470",
    "sg:postcode":"29464",
    "sg:province":"SC",
    "sg:tags":[
        "general",
        "contractor"
    ],
    "wof:name":"HM Smith Company LLC",
    "wof:placetype":"venue"
},
  "geometry": {"coordinates":[-79.857539,32.782232],"type":"Point"}
}