{
  "type": "Feature",
  "properties": {
    "addr:full":"1121 Woodruff Rd Greenville SC 29607",
    "addr:housenumber":"1121",
    "addr:postcode":"29607",
    "addr:street":"Woodruff Rd",
    "iso:country":"US",
    "sg:address":"1121 Woodruff Rd",
    "sg:city":"Greenville",
    "sg:classifiers":[
        {
            "category":"Deli",
            "type":"Food & Drink"
        }
    ],
    "sg:menulink":"http://www.allmenus.com/sc/greenville/126612-blimpie-subs--sandwiches/menu/",
    "sg:phone":"+1 864 676 0456",
    "sg:postcode":"29607",
    "sg:province":"SC",
    "sg:tags":[
        "wrap",
        "american",
        "sandwich"
    ],
    "wof:name":"Blimpie Subs & Sandwiches",
    "wof:placetype":"venue"
},
  "geometry": {"coordinates":[-82.304295,34.829899],"type":"Point"}
}