{
  "type": "Feature",
  "properties": {
    "iso:country":"US",
    "sg:address":"5600 Dorchester Rd",
    "sg:city":"North Charleston",
    "sg:classifiers":[
        {
            "category":"Real Estate",
            "subcategory":"Real Estate Operator",
            "type":"Services"
        }
    ],
    "sg:phone":"+1 843 552 3631",
    "sg:postcode":"29418",
    "sg:province":"SC",
    "sg:tags":[
        "apartment"
    ],
    "wof:name":"Bradford Apartments",
    "wof:placetype":"venue"
},
  "geometry": {"coordinates":[-80.048639,32.86282],"type":"Point"}
}