{
  "type": "Feature",
  "properties": {
    "iso:country":"US",
    "sg:address":"3731 Hwy 24",
    "sg:city":"Anderson",
    "sg:classifiers":[
        {
            "category":"Professional",
            "type":"Services"
        }
    ],
    "sg:phone":"+1 864 224 9502",
    "sg:postcode":"29626",
    "sg:province":"SC",
    "sg:tags":[
        "establishment"
    ],
    "wof:name":"Paws Unlimited II",
    "wof:placetype":"venue"
},
  "geometry": {"coordinates":[-82.728534,34.506281],"type":"Point"}
}