{
  "type": "Feature",
  "properties": {
    "addr:full":"109 Rosebank Dr Columbia SC 29209",
    "addr:housenumber":"109",
    "addr:postcode":"29209",
    "addr:street":"Rosebank Dr",
    "iso:country":"US",
    "sg:address":"109 Rosebank Dr",
    "sg:city":"Columbia",
    "sg:classifiers":[
        {
            "category":"Banks & Credit Unions",
            "subcategory":"Investment Brokerage",
            "type":"Services"
        }
    ],
    "sg:phone":"+1 803 479 9632",
    "sg:postcode":"29209",
    "sg:province":"SC",
    "sg:tags":[
        "advisory",
        "financial"
    ],
    "wof:name":"Todd Financial Solutions",
    "wof:placetype":"venue"
},
  "geometry": {"coordinates":[-80.972129,33.965692],"type":"Point"}
}