{
  "type": "Feature",
  "properties": {
    "iso:country":"US",
    "sg:address":"113 Powdersville Main",
    "sg:city":"Easley",
    "sg:classifiers":[
        {
            "category":"Professional",
            "subcategory":"Advertising",
            "type":"Services"
        }
    ],
    "sg:phone":"+1 864 295 6618",
    "sg:postcode":"29642",
    "sg:province":"SC",
    "wof:name":"Endless Ideas LLC",
    "wof:placetype":"venue"
},
  "geometry": {"coordinates":[-82.490798,34.788755],"type":"Point"}
}