{
  "type": "Feature",
  "properties": {
    "iso:country":"US",
    "sg:address":"1015 Charlotte Ave",
    "sg:city":"Rock Hill",
    "sg:classifiers":[
        {
            "category":"Wholesale",
            "subcategory":"Stationery",
            "type":"Manufacturing & Wholesale Goods"
        },
        {
            "category":"Professional",
            "subcategory":"Advertising",
            "type":"Services"
        }
    ],
    "sg:phone":"+1 803 980 7225",
    "sg:postcode":"29732",
    "sg:province":"SC",
    "sg:tags":[
        "paper",
        "mailing",
        "shipping",
        "business"
    ],
    "wof:name":"UPS Store The",
    "wof:placetype":"venue"
},
  "geometry": {"coordinates":[-81.029477,34.945574],"type":"Point"}
}