{
  "type": "Feature",
  "properties": {
    "addr:full":"580 E Main St Spartanburg SC 29302",
    "addr:housenumber":"580",
    "addr:postcode":"29302",
    "addr:street":"E Main St",
    "iso:country":"US",
    "sg:address":"580 E Main St",
    "sg:city":"Spartanburg",
    "sg:classifiers":[
        {
            "category":"Education",
            "subcategory":"Library",
            "type":"Public Place"
        }
    ],
    "sg:phone":"+1 864 596 9020",
    "sg:postcode":"29302",
    "sg:province":"SC",
    "sg:website":"www.converse.edu",
    "wof:name":"Mickel Library",
    "wof:placetype":"venue"
},
  "geometry": {"coordinates":[-81.915335,34.955113],"type":"Point"}
}