{
  "type": "Feature",
  "properties": {
    "iso:country":"US",
    "sg:address":"113 S Main St",
    "sg:city":"Fountain Inn",
    "sg:classifiers":[
        {
            "category":"Professional",
            "subcategory":"Management & Consulting",
            "type":"Services"
        }
    ],
    "sg:phone":"+1 864 862 8868",
    "sg:postcode":"29644",
    "sg:province":"SC",
    "sg:tags":[
        "consultant",
        "energy",
        "conservation"
    ],
    "wof:name":"Resource Group",
    "wof:placetype":"venue"
},
  "geometry": {"coordinates":[-82.19690300000001,34.690635],"type":"Point"}
}