{
  "type": "Feature",
  "properties": {
    "iso:country":"US",
    "sg:address":"435 King St",
    "sg:city":"Charleston",
    "sg:classifiers":[
        {
            "category":"Shopping",
            "subcategory":"Hobbies, Toys, & Games",
            "type":"Retail Goods"
        }
    ],
    "sg:phone":"+1 843 722 4527",
    "sg:postcode":"29403",
    "sg:province":"SC",
    "sg:tags":[
        "supply"
    ],
    "wof:name":"Scientific Games",
    "wof:placetype":"venue"
},
  "geometry": {"coordinates":[-79.93842600000001,32.788847],"type":"Point"}
}