{
  "type": "Feature",
  "properties": {
    "addr:full":"25 Cardinal Ln Okatie SC 29909",
    "addr:housenumber":"25",
    "addr:postcode":"29909",
    "addr:street":"Cardinal Ln",
    "iso:country":"US",
    "sg:address":"25 Cardinal Ln",
    "sg:city":"Okatie",
    "sg:classifiers":[
        {
            "category":"Building & Trades",
            "subcategory":"Electrical",
            "type":"Services"
        }
    ],
    "sg:phone":"+1 843 987 3247",
    "sg:postcode":"29909",
    "sg:province":"SC",
    "sg:tags":[
        "electric",
        "contractor"
    ],
    "wof:name":"G C Tillotson Electrical Contr",
    "wof:placetype":"venue"
},
  "geometry": {"coordinates":[-80.89203999999999,32.34802],"type":"Point"}
}