{
  "type": "Feature",
  "properties": {
    "addr:full":"415 E Church St Leesville SC 29070",
    "addr:housenumber":"415",
    "addr:postcode":"29070",
    "addr:street":"E Church St",
    "iso:country":"US",
    "sg:address":"415 E Church St",
    "sg:city":"Leesville",
    "sg:classifiers":[
        {
            "category":"Food & Beverages",
            "subcategory":"Groceries & Convenience Stores",
            "type":"Retail Goods"
        }
    ],
    "sg:phone":"+1 803 532 3851",
    "sg:postcode":"29070",
    "sg:province":"SC",
    "sg:tags":[
        "gasoline"
    ],
    "wof:name":"Wrightway Stores",
    "wof:placetype":"venue"
},
  "geometry": {"coordinates":[-81.513903,33.917829],"type":"Point"}
}