{
  "type": "Feature",
  "properties": {
    "iso:country":"US",
    "sg:address":"169 Holcombe Dr",
    "sg:city":"Liberty",
    "sg:classifiers":[
        {
            "category":"Building & Trades",
            "subcategory":"Pest Control",
            "type":"Services"
        }
    ],
    "sg:phone":"+1 864 843 3400",
    "sg:postcode":"29657",
    "sg:province":"SC",
    "wof:name":"Belan Pest Control Inc",
    "wof:placetype":"venue"
},
  "geometry": {"coordinates":[-82.657222,34.760708],"type":"Point"}
}