{
  "type": "Feature",
  "properties": {
    "iso:country":"US",
    "sg:address":"914 N Ocean Blvd",
    "sg:city":"Myrtle Beach",
    "sg:classifiers":[
        {
            "category":"Professional",
            "type":"Services"
        }
    ],
    "sg:phone":"+1 843 626 3750",
    "sg:postcode":"29577",
    "sg:province":"SC",
    "sg:tags":[
        "establishment"
    ],
    "wof:name":"Something Different",
    "wof:placetype":"venue"
},
  "geometry": {"coordinates":[-78.878119,33.693535],"type":"Point"}
}