{
  "type": "Feature",
  "properties": {
    "iso:country":"US",
    "sg:address":"1500 W Main St",
    "sg:city":"Laurens",
    "sg:classifiers":[
        {
            "category":"Shopping",
            "subcategory":"Clothing, Apparel, & Fashions",
            "type":"Retail Goods"
        }
    ],
    "sg:phone":"+1 864 984 6352",
    "sg:postcode":"29360",
    "sg:province":"SC",
    "sg:tags":[
        "family"
    ],
    "wof:name":"JD Fashions",
    "wof:placetype":"venue"
},
  "geometry": {"coordinates":[-82.04865599999999,34.499713],"type":"Point"}
}