{
  "type": "Feature",
  "properties": {
    "iso:country":"US",
    "sg:address":"290 Willis St",
    "sg:city":"Batesburg",
    "sg:classifiers":[
        {
            "category":"Shopping",
            "subcategory":"Department Store",
            "type":"Retail Goods"
        }
    ],
    "sg:phone":"+1 803 532 4526",
    "sg:postcode":"29006",
    "sg:province":"SC",
    "wof:name":"Dollar General",
    "wof:placetype":"venue"
},
  "geometry": {"coordinates":[-81.541524,33.896492],"type":"Point"}
}