{
  "type": "Feature",
  "properties": {
    "addr:full":"128 Marshland Rd Hilton Head Island SC 29926",
    "addr:housenumber":"128",
    "addr:postcode":"29926",
    "addr:street":"Marshland Rd",
    "iso:country":"US",
    "sg:address":"128 Marshland Rd",
    "sg:city":"Hilton Head Island",
    "sg:classifiers":[
        {
            "category":"Wholesale",
            "subcategory":"Hardware",
            "type":"Manufacturing & Wholesale Goods"
        }
    ],
    "sg:phone":"+1 843 683 0700",
    "sg:postcode":"29926",
    "sg:province":"SC",
    "wof:name":"R A Field Inc",
    "wof:placetype":"venue"
},
  "geometry": {"coordinates":[-80.721227,32.19933],"type":"Point"}
}