{
  "type": "Feature",
  "properties": {
    "addr:full":"1135 Columbia Rd Chester SC 29706",
    "addr:housenumber":"1135",
    "addr:postcode":"29706",
    "addr:street":"Columbia Rd",
    "iso:country":"US",
    "sg:address":"1135 Columbia Rd",
    "sg:city":"Chester",
    "sg:classifiers":[
        {
            "category":"Social Services",
            "subcategory":"Child Care",
            "type":"Services"
        }
    ],
    "sg:phone":"+1 803 377 2930",
    "sg:postcode":"29706",
    "sg:province":"SC",
    "wof:name":"Tiny Tot Day Care",
    "wof:placetype":"venue"
},
  "geometry": {"coordinates":[-81.192396,34.664924],"type":"Point"}
}