{
  "type": "Feature",
  "properties": {
    "iso:country":"US",
    "sg:address":"10417 Asheville Hwy",
    "sg:city":"Inman",
    "sg:classifiers":[
        {
            "category":"Insurance",
            "subcategory":"Insurance Agent",
            "type":"Services"
        }
    ],
    "sg:phone":"+1 864 583 1088",
    "sg:postcode":"29349",
    "sg:province":"SC",
    "wof:name":"Farm Bureau Insurance",
    "wof:placetype":"venue"
},
  "geometry": {"coordinates":[-82.061756,35.034217],"type":"Point"}
}