{
  "type": "Feature",
  "properties": {
    "iso:country":"US",
    "sg:address":"1228 Harden St",
    "sg:city":"Columbia",
    "sg:classifiers":[
        {
            "category":"Health Services",
            "subcategory":"Doctor",
            "type":"Services"
        }
    ],
    "sg:phone":"+1 803 733 5969",
    "sg:postcode":"29204",
    "sg:province":"SC",
    "sg:website":"www.ecchc.org",
    "wof:name":"Eau Claire Cooperative Health Centers Inc",
    "wof:placetype":"venue"
},
  "geometry": {"coordinates":[-81.01924699999999,34.006916],"type":"Point"}
}