{
  "type": "Feature",
  "properties": {
    "iso:country":"US",
    "sg:address":"312 Paschal Rd",
    "sg:city":"Elgin",
    "sg:classifiers":[
        {
            "category":"Building & Trades",
            "subcategory":"Construction",
            "type":"Services"
        }
    ],
    "sg:phone":"+1 803 691 1437",
    "sg:postcode":"29045",
    "sg:province":"SC",
    "sg:tags":[
        "house"
    ],
    "wof:name":"R&R Construction",
    "wof:placetype":"venue"
},
  "geometry": {"coordinates":[-80.862808,34.194444],"type":"Point"}
}