{
  "type": "Feature",
  "properties": {
    "iso:country":"US",
    "sg:address":"315 E Carolina Ave",
    "sg:city":"Hartsville",
    "sg:classifiers":[
        {
            "category":"Professional",
            "subcategory":"Lawyer & Legal Services",
            "type":"Services"
        }
    ],
    "sg:phone":"+1 843 332 7545",
    "sg:postcode":"29550",
    "sg:province":"SC",
    "sg:tags":[
        "attorney"
    ],
    "wof:name":"Ernest L Cook",
    "wof:placetype":"venue"
},
  "geometry": {"coordinates":[-80.067896,34.376244],"type":"Point"}
}