{
  "type": "Feature",
  "properties": {
    "iso:country":"US",
    "sg:address":"127 Old Salkehatchie Hwy",
    "sg:city":"Yemassee",
    "sg:classifiers":[
        {
            "category":"Organizations",
            "subcategory":"Religious Organization",
            "type":"Services"
        }
    ],
    "sg:phone":"+1 843 589 2345",
    "sg:postcode":"29945",
    "sg:province":"SC",
    "sg:tags":[
        "church"
    ],
    "wof:name":"Yemassee Baptist Church",
    "wof:placetype":"venue"
},
  "geometry": {"coordinates":[-80.850859,32.696363],"type":"Point"}
}