{
  "type": "Feature",
  "properties": {
    "iso:country":"US",
    "sg:address":"10 Burckmyer Dr",
    "sg:city":"Beaufort",
    "sg:classifiers":[
        {
            "category":"Manufacturing",
            "subcategory":"Printing",
            "type":"Manufacturing & Wholesale Goods"
        }
    ],
    "sg:phone":"+1 843 524 1705",
    "sg:postcode":"29907",
    "sg:province":"SC",
    "sg:tags":[
        "lithographic",
        "commercial"
    ],
    "wof:name":"J W H Printing",
    "wof:placetype":"venue"
},
  "geometry": {"coordinates":[-80.663291,32.398548],"type":"Point"}
}