{
  "type": "Feature",
  "properties": {
    "addr:full":"1155 Saint Matthews Rd Orangeburg SC 29115",
    "addr:housenumber":"1155",
    "addr:postcode":"matthews;29115",
    "addr:street":"Saint;Rd",
    "iso:country":"US",
    "sg:address":"1155 Saint Matthews Rd",
    "sg:city":"Orangeburg",
    "sg:classifiers":[
        {
            "category":"Restaurant",
            "type":"Food & Drink"
        }
    ],
    "sg:phone":"+1 803 534 5066",
    "sg:postcode":"29115",
    "sg:province":"SC",
    "sg:tags":[
        "eating"
    ],
    "wof:name":"Hardees",
    "wof:placetype":"venue"
},
  "geometry": {"coordinates":[-80.861987,33.50892],"type":"Point"}
}