{
  "type": "Feature",
  "properties": {
    "addr:full":"1901 Main St Ste 1500 Columbia SC 29201",
    "addr:housenumber":"1901",
    "addr:postcode":"29201",
    "addr:street":"Main St Ste 1500",
    "iso:country":"US",
    "sg:address":"1901 Main St Ste 1500",
    "sg:city":"Columbia",
    "sg:classifiers":[
        {
            "category":"Banks & Credit Unions",
            "subcategory":"Atm",
            "type":"Services"
        }
    ],
    "sg:phone":"+1 803 779 8900",
    "sg:postcode":"29201",
    "sg:province":"SC",
    "sg:tags":[
        "bankruptcy"
    ],
    "wof:name":"Robinson McFadden & Moore PC",
    "wof:placetype":"venue"
},
  "geometry": {"coordinates":[-81.03780399999999,34.010601],"type":"Point"}
}