{
  "type": "Feature",
  "properties": {
    "iso:country":"US",
    "sg:address":"828 Richland Ave W",
    "sg:city":"Aiken",
    "sg:classifiers":[
        {
            "category":"Government",
            "subcategory":"Office",
            "type":"Public Place"
        }
    ],
    "sg:phone":"+1 803 642 1656",
    "sg:postcode":"29801",
    "sg:province":"SC",
    "sg:tags":[
        "county",
        "program",
        "health"
    ],
    "wof:name":"Home Health Svc Of Aiken",
    "wof:placetype":"venue"
},
  "geometry": {"coordinates":[-81.730064,33.564015],"type":"Point"}
}