{
  "type": "Feature",
  "properties": {
    "iso:country":"US",
    "sg:address":"4515 Narrow Paved Rd",
    "sg:city":"Lynchburg",
    "sg:classifiers":[
        {
            "category":"Education",
            "subcategory":"School",
            "type":"Public Place"
        }
    ],
    "sg:phone":"+1 843 659 2689",
    "sg:postcode":"29080",
    "sg:province":"SC",
    "wof:name":"St Johns Elementary School",
    "wof:placetype":"venue"
},
  "geometry": {"coordinates":[-79.996828,33.98888],"type":"Point"}
}