{
  "type": "Feature",
  "properties": {
    "iso:country":"US",
    "sg:address":"1402 E River St",
    "sg:city":"Anderson",
    "sg:classifiers":[
        {
            "category":"Shopping",
            "subcategory":"Discount & Variety Stores",
            "type":"Retail Goods"
        }
    ],
    "sg:phone":"+1 864 224 2341",
    "sg:postcode":"29624",
    "sg:province":"SC",
    "wof:name":"Dollar General",
    "wof:placetype":"venue"
},
  "geometry": {"coordinates":[-82.631423,34.49558],"type":"Point"}
}