{
  "type": "Feature",
  "properties": {
    "iso:country":"US",
    "sg:address":"107 E Cheves St",
    "sg:city":"Florence",
    "sg:classifiers":[
        {
            "category":"Personal",
            "subcategory":"Beauty Salon",
            "type":"Services"
        }
    ],
    "sg:phone":"+1 843 669 0654",
    "sg:postcode":"29506",
    "sg:province":"SC",
    "wof:name":"Keith Pearly Hair Stylist",
    "wof:placetype":"venue"
},
  "geometry": {"coordinates":[-79.763897,34.195739],"type":"Point"}
}