{
  "type": "Feature",
  "properties": {
    "addr:full":"2005 Palmetto Blvd Edisto Island SC 29438",
    "addr:housenumber":"2005",
    "addr:postcode":"29438",
    "addr:street":"Palmetto Blvd",
    "iso:country":"US",
    "sg:address":"2005 Palmetto Blvd",
    "sg:city":"Edisto Island",
    "sg:classifiers":[
        {
            "category":"Professional",
            "subcategory":"Business Services",
            "type":"Services"
        }
    ],
    "sg:phone":"+1 843 869 3258",
    "sg:postcode":"29438",
    "sg:province":"SC",
    "sg:tags":[
        "interior",
        "consultant",
        "design",
        "decorator"
    ],
    "wof:name":"Lynn Benton Bagnal",
    "wof:placetype":"venue"
},
  "geometry": {"coordinates":[-80.32530300000001,32.484106],"type":"Point"}
}