{
  "type": "Feature",
  "properties": {
    "iso:country":"US",
    "sg:address":"42 Senn St",
    "sg:city":"Vaucluse",
    "sg:classifiers":[
        {
            "category":"Government",
            "subcategory":"Post Office",
            "type":"Public Place"
        }
    ],
    "sg:phone":"+1 803 663 7741",
    "sg:postcode":"29850",
    "sg:province":"SC",
    "wof:name":"US Post Office",
    "wof:placetype":"venue"
},
  "geometry": {"coordinates":[-81.805763,33.61061],"type":"Point"}
}