{
  "type": "Feature",
  "properties": {
    "iso:country":"US",
    "sg:address":"2184 Glenns Bay Rd",
    "sg:city":"Surfside Beach",
    "sg:classifiers":[
        {
            "category":"Personal",
            "subcategory":"Beauty Salon",
            "type":"Services"
        }
    ],
    "sg:phone":"+1 843 916 9998",
    "sg:postcode":"29575",
    "sg:province":"SC",
    "wof:name":"Backwoods Braids Beauty Salon",
    "wof:placetype":"venue"
},
  "geometry": {"coordinates":[-78.997421,33.617648],"type":"Point"}
}