{
  "type": "Feature",
  "properties": {
    "iso:country":"US",
    "sg:address":"1400 Blaney Rd",
    "sg:city":"Elgin",
    "sg:classifiers":[
        {
            "category":"Organizations",
            "subcategory":"Religious Organization",
            "type":"Services"
        }
    ],
    "sg:phone":"+1 803 438 3161",
    "sg:postcode":"29045",
    "sg:province":"SC",
    "sg:tags":[
        "church"
    ],
    "wof:name":"Blaney Baptist Church",
    "wof:placetype":"venue"
},
  "geometry": {"coordinates":[-80.792367,34.168942],"type":"Point"}
}