{
  "type": "Feature",
  "properties": {
    "addr:full":"46 Bell Rd Greenville SC 29607",
    "addr:housenumber":"46",
    "addr:postcode":"29607",
    "addr:street":"Bell Rd",
    "iso:country":"US",
    "sg:address":"46 Bell Rd",
    "sg:city":"Greenville",
    "sg:classifiers":[
        {
            "category":"Retail",
            "subcategory":"Auto Repair",
            "type":"Services"
        }
    ],
    "sg:phone":"+1 864 288 1387",
    "sg:postcode":"29607",
    "sg:province":"SC",
    "sg:tags":[
        "van",
        "conversion",
        "truck",
        "accessory"
    ],
    "wof:name":"Brannock's Custom Vans",
    "wof:placetype":"venue"
},
  "geometry": {"coordinates":[-82.26596000000001,34.816722],"type":"Point"}
}