{
  "type": "Feature",
  "properties": {
    "addr:full":"430 S Hampton Ct Columbia SC 29209",
    "addr:housenumber":"430",
    "addr:postcode":"29209",
    "addr:street":"S Hampton Ct",
    "iso:country":"US",
    "sg:address":"430 S Hampton Ct",
    "sg:city":"Columbia",
    "sg:classifiers":[
        {
            "category":"Autos & Motor Vehicles",
            "subcategory":"Auto Supplies",
            "type":"Retail Goods"
        },
        {
            "category":"Professional",
            "subcategory":"Computer Services",
            "type":"Services"
        }
    ],
    "sg:phone":"+1 864 840 8027",
    "sg:postcode":"29209",
    "sg:province":"SC",
    "sg:tags":[
        "stereo",
        "part",
        "installation"
    ],
    "sg:website":"car-audio-columbia-south.carolin...",
    "wof:name":"Mobile Stereo Electronics and Security",
    "wof:placetype":"venue"
},
  "geometry": {"coordinates":[-80.97615399999999,33.965147],"type":"Point"}
}