{
  "type": "Feature",
  "properties": {
    "iso:country":"US",
    "sg:address":"7800 Fairfield Rd",
    "sg:city":"Columbia",
    "sg:classifiers":[
        {
            "category":"Recreation",
            "type":"Entertainment"
        }
    ],
    "sg:phone":"+1 803 333 0040",
    "sg:postcode":"29203",
    "sg:province":"SC",
    "sg:tags":[
        "stable"
    ],
    "wof:name":"Hidden Pond Farm",
    "wof:placetype":"venue"
},
  "geometry": {"coordinates":[-81.029017,34.124531],"type":"Point"}
}