{
  "type": "Feature",
  "properties": {
    "addr:full":"1175 Lakeview Dr Greenville SC 29611",
    "addr:housenumber":"1175",
    "addr:postcode":"29611",
    "addr:street":"Lakeview Dr",
    "iso:country":"US",
    "sg:address":"1175 Lakeview Dr",
    "sg:city":"Greenville",
    "sg:classifiers":[
        {
            "category":"Professional",
            "subcategory":"Detective & Security Services",
            "type":"Services"
        }
    ],
    "sg:phone":"+1 864 295 2434",
    "sg:postcode":"29611",
    "sg:province":"SC",
    "sg:tags":[
        "agency"
    ],
    "wof:name":"Kiser Professional Invstgtn",
    "wof:placetype":"venue"
},
  "geometry": {"coordinates":[-82.476451,34.809721],"type":"Point"}
}