{
  "type": "Feature",
  "properties": {
    "iso:country":"US",
    "sg:address":"8310 Rivers Ave",
    "sg:city":"North Charleston",
    "sg:classifiers":[
        {
            "category":"Real Estate",
            "subcategory":"Developer",
            "type":"Services"
        }
    ],
    "sg:phone":"+1 843 572 4512",
    "sg:postcode":"29406",
    "sg:province":"SC",
    "wof:name":"Butler's Development",
    "wof:placetype":"venue"
},
  "geometry": {"coordinates":[-80.04311199999999,32.959808],"type":"Point"}
}