{
  "type": "Feature",
  "properties": {
    "iso:country":"US",
    "sg:address":"607 State Hwy 38 Bus",
    "sg:city":"Bennettsville",
    "sg:classifiers":[
        {
            "category":"Manufacturing",
            "subcategory":"Furniture",
            "type":"Manufacturing & Wholesale Goods"
        }
    ],
    "sg:phone":"+1 843 479 3511",
    "sg:postcode":"29512",
    "sg:province":"SC",
    "sg:tags":[
        "bed"
    ],
    "wof:name":"Bennettsville Mattress",
    "wof:placetype":"venue"
},
  "geometry": {"coordinates":[-79.690516,34.624412],"type":"Point"}
}