{
  "type": "Feature",
  "properties": {
    "iso:country":"US",
    "sg:address":"2001 Harrell Square Center",
    "sg:city":"Charleston",
    "sg:classifiers":[
        {
            "category":"Professional",
            "subcategory":"Lawyer & Legal Services",
            "type":"Services"
        }
    ],
    "sg:phone":"+1 843 766 4700",
    "sg:postcode":"29407",
    "sg:province":"SC",
    "sg:tags":[
        "attorney"
    ],
    "wof:name":"Harrell Law Firm",
    "wof:placetype":"venue"
},
  "geometry": {"coordinates":[-80.029207,32.795567],"type":"Point"}
}