{
  "type": "Feature",
  "properties": {
    "iso:country":"US",
    "sg:address":"3926 Charleston Hwy",
    "sg:city":"Orangeburg",
    "sg:classifiers":[
        {
            "category":"Home & Garden",
            "subcategory":"Building Materials",
            "type":"Retail Goods"
        }
    ],
    "sg:phone":"+1 803 531 5311",
    "sg:postcode":"29115",
    "sg:province":"SC",
    "sg:tags":[
        "contractor"
    ],
    "wof:name":"Eds Vinyl Siding",
    "wof:placetype":"venue"
},
  "geometry": {"coordinates":[-80.777889,33.428502],"type":"Point"}
}