{
  "type": "Feature",
  "properties": {
    "iso:country":"US",
    "sg:address":"416 US Hwy 278",
    "sg:city":"Hilton Head Island",
    "sg:classifiers":[
        {
            "category":"Restaurant",
            "type":"Food & Drink"
        }
    ],
    "sg:phone":"+1 843 689 6823",
    "sg:postcode":"29926",
    "sg:province":"SC",
    "sg:tags":[
        "eating"
    ],
    "wof:name":"Starbucks",
    "wof:placetype":"venue"
},
  "geometry": {"coordinates":[-80.707047,32.216076],"type":"Point"}
}