{
  "type": "Feature",
  "properties": {
    "iso:country":"US",
    "sg:address":"209 Main Rd",
    "sg:city":"Johns Island",
    "sg:classifiers":[
        {
            "category":"Retail",
            "subcategory":"Auto Repair",
            "type":"Services"
        }
    ],
    "sg:phone":"+1 843 763 4490",
    "sg:postcode":"29455",
    "sg:province":"SC",
    "sg:tags":[
        "body",
        "automobile",
        "painting"
    ],
    "wof:name":"Legare's Paint & Body Repairs",
    "wof:placetype":"venue"
},
  "geometry": {"coordinates":[-80.108788,32.800256],"type":"Point"}
}