{
  "type": "Feature",
  "properties": {
    "addr:full":"120 Heritage Ln Easley SC 29642",
    "addr:housenumber":"120",
    "addr:postcode":"29642",
    "addr:street":"Heritage Ln",
    "iso:country":"US",
    "sg:address":"120 Heritage Ln",
    "sg:city":"Easley",
    "sg:classifiers":[
        {
            "category":"Building & Trades",
            "subcategory":"Landscaping Services",
            "type":"Services"
        }
    ],
    "sg:phone":"+1 864 220 0870",
    "sg:postcode":"29642",
    "sg:province":"SC",
    "sg:tags":[
        "landscape",
        "contractor"
    ],
    "wof:name":"Tree Of Life Landscape & Maint",
    "wof:placetype":"venue"
},
  "geometry": {"coordinates":[-82.487651,34.759568],"type":"Point"}
}