{
  "type": "Feature",
  "properties": {
    "iso:country":"US",
    "sg:address":"3406 Chapman Cooper Rd",
    "sg:city":"Sellers",
    "sg:classifiers":[
        {
            "category":"Freight",
            "type":"Transportation"
        }
    ],
    "sg:phone":"+1 843 752 4400",
    "sg:postcode":"29592",
    "sg:province":"SC",
    "sg:tags":[
        "trucking"
    ],
    "wof:name":"Pop Dog Inc",
    "wof:placetype":"venue"
},
  "geometry": {"coordinates":[-79.493762,34.261326],"type":"Point"}
}