{
  "type": "Feature",
  "properties": {
    "addr:full":"1928 Cedar Lane Rd Greenville SC 29617",
    "addr:housenumber":"1928",
    "addr:postcode":"29617",
    "addr:street":"Cedar Lane Rd",
    "iso:country":"US",
    "sg:address":"1928 Cedar Lane Rd",
    "sg:city":"Greenville",
    "sg:classifiers":[
        {
            "category":"Insurance",
            "subcategory":"Insurance Agent",
            "type":"Services"
        }
    ],
    "sg:phone":"+1 864 246 2416",
    "sg:postcode":"29617",
    "sg:province":"SC",
    "wof:name":"State Farm Insurance",
    "wof:placetype":"venue"
},
  "geometry": {"coordinates":[-82.452636,34.882406],"type":"Point"}
}