{
  "type": "Feature",
  "properties": {
    "iso:country":"US",
    "sg:address":"39 Professional Village Cir",
    "sg:city":"Beaufort",
    "sg:classifiers":[
        {
            "category":"Banks & Credit Unions",
            "subcategory":"Investment Brokerage",
            "type":"Services"
        },
        {
            "category":"Insurance",
            "subcategory":"Insurance Agent",
            "type":"Services"
        }
    ],
    "sg:phone":"+1 843 524 6310",
    "sg:postcode":"29907",
    "sg:province":"SC",
    "sg:tags":[
        "consultant",
        "planning",
        "financial"
    ],
    "wof:name":"Hand & Tanner Financial Group",
    "wof:placetype":"venue"
},
  "geometry": {"coordinates":[-80.650717,32.41597],"type":"Point"}
}