{
  "type": "Feature",
  "properties": {
    "addr:full":"52 Sans Souci St Charleston SC 29403",
    "addr:housenumber":"52",
    "addr:postcode":"29403",
    "addr:street":"Sans Souci St",
    "iso:country":"US",
    "sg:address":"52 Sans Souci St",
    "sg:city":"Charleston",
    "sg:classifiers":[
        {
            "category":"Organizations",
            "subcategory":"Religious Organization",
            "type":"Services"
        }
    ],
    "sg:phone":"+1 843 722 1223",
    "sg:postcode":"29403",
    "sg:province":"SC",
    "sg:tags":[
        "church"
    ],
    "wof:name":"Kingdom Dominion Ministries",
    "wof:placetype":"venue"
},
  "geometry": {"coordinates":[-79.95165,32.81058],"type":"Point"}
}