{
  "type": "Feature",
  "properties": {
    "iso:country":"US",
    "sg:address":"3417 W Montague Ave",
    "sg:city":"North Charleston",
    "sg:classifiers":[
        {
            "category":"Recreation",
            "type":"Entertainment"
        }
    ],
    "sg:phone":"+1 843 566 0010",
    "sg:postcode":"29418",
    "sg:province":"SC",
    "sg:tags":[
        "instruction",
        "yoga"
    ],
    "wof:name":"Charleston Yoga LLC",
    "wof:placetype":"venue"
},
  "geometry": {"coordinates":[-80.022157,32.863375],"type":"Point"}
}