{
  "type": "Feature",
  "properties": {
    "iso:country":"US",
    "sg:address":"1877 Old Hwy 14 S",
    "sg:city":"Greer",
    "sg:classifiers":[
        {
            "category":"Shopping",
            "type":"Retail Goods"
        },
        {
            "category":"Building & Trades",
            "subcategory":"Construction",
            "type":"Services"
        }
    ],
    "sg:phone":"+1 864 877 7751",
    "sg:postcode":"29650",
    "sg:province":"SC",
    "sg:tags":[
        "concrete",
        "merchandise",
        "contractor"
    ],
    "wof:name":"Solid Designs LLC",
    "wof:placetype":"venue"
},
  "geometry": {"coordinates":[-82.23395499999999,34.894166],"type":"Point"}
}