{
  "type": "Feature",
  "properties": {
    "iso:country":"US",
    "sg:address":"7053 Savannah Hwy",
    "sg:city":"Ravenel",
    "sg:classifiers":[
        {
            "category":"Autos & Motor Vehicles",
            "subcategory":"Auto Supplies",
            "type":"Retail Goods"
        }
    ],
    "sg:phone":"+1 843 889 0300",
    "sg:postcode":"29470",
    "sg:province":"SC",
    "wof:name":"Tower Tire",
    "wof:placetype":"venue"
},
  "geometry": {"coordinates":[-80.292619,32.767136],"type":"Point"}
}