{
  "type": "Feature",
  "properties": {
    "iso:country":"US",
    "sg:address":"409 Barron St",
    "sg:city":"West Columbia",
    "sg:classifiers":[
        {
            "category":"Building & Trades",
            "subcategory":"Plumbing",
            "type":"Services"
        }
    ],
    "sg:phone":"+1 803 276 7394",
    "sg:postcode":"29169",
    "sg:province":"SC",
    "sg:tags":[
        "contractor"
    ],
    "wof:name":"Carolina Comfort Inc",
    "wof:placetype":"venue"
},
  "geometry": {"coordinates":[-81.06412899999999,33.997811],"type":"Point"}
}