{
  "type": "Feature",
  "properties": {
    "iso:country":"US",
    "sg:address":"1118 1st Street South Ext",
    "sg:city":"Columbia",
    "sg:classifiers":[
        {
            "category":"Autos & Motor Vehicles",
            "subcategory":"Auto Supplies",
            "type":"Retail Goods"
        }
    ],
    "sg:phone":"+1 803 776 4888",
    "sg:postcode":"29209",
    "sg:province":"SC",
    "sg:tags":[
        "tire"
    ],
    "sg:website":"www.jimwhiteheadtire.com",
    "wof:name":"Jim Whitehead Tire Service",
    "wof:placetype":"venue"
},
  "geometry": {"coordinates":[-81.03474300000001,34.000683],"type":"Point"}
}