{
  "type": "Feature",
  "properties": {
    "iso:country":"US",
    "sg:address":"1529 Old Williamston Rd",
    "sg:city":"Anderson",
    "sg:classifiers":[
        {
            "category":"Home & Garden",
            "subcategory":"Garden Supply",
            "type":"Retail Goods"
        }
    ],
    "sg:phone":"+1 864 224 3613",
    "sg:postcode":"29621",
    "sg:province":"SC",
    "sg:tags":[
        "sprinkler"
    ],
    "wof:name":"Rain Water Irrigation",
    "wof:placetype":"venue"
},
  "geometry": {"coordinates":[-82.61557999999999,34.521412],"type":"Point"}
}