{
  "type": "Feature",
  "properties": {
    "iso:country":"US",
    "sg:address":"129 Anderson Hwy",
    "sg:city":"Clemson",
    "sg:classifiers":[
        {
            "category":"Restaurant",
            "type":"Food & Drink"
        }
    ],
    "sg:phone":"+1 864 654 4422",
    "sg:postcode":"29631",
    "sg:province":"SC",
    "wof:name":"Skin Thrashers Hotdogs",
    "wof:placetype":"venue"
},
  "geometry": {"coordinates":[-82.826705,34.68892],"type":"Point"}
}