{
  "type": "Feature",
  "properties": {
    "iso:country":"US",
    "sg:address":"131 W Wine St",
    "sg:city":"Mullins",
    "sg:classifiers":[
        {
            "category":"Organizations",
            "subcategory":"Religious Organization",
            "type":"Services"
        }
    ],
    "sg:phone":"+1 843 464 1932",
    "sg:postcode":"29574",
    "sg:province":"SC",
    "sg:tags":[
        "church"
    ],
    "wof:name":"Perfect Peace Ministry",
    "wof:placetype":"venue"
},
  "geometry": {"coordinates":[-79.255003,34.206614],"type":"Point"}
}