{
  "type": "Feature",
  "properties": {
    "addr:full":"3353 Savannah Hwy North SC 29112",
    "addr:housenumber":"3353",
    "addr:postcode":"29112",
    "addr:street":"Savannah Hwy North",
    "iso:country":"US",
    "sg:address":"3353 Savannah Hwy",
    "sg:city":"North",
    "sg:classifiers":[
        {
            "category":"Organizations",
            "subcategory":"Religious Organization",
            "type":"Services"
        }
    ],
    "sg:phone":"+1 803 568 5080",
    "sg:postcode":"29112",
    "sg:province":"SC",
    "sg:tags":[
        "church"
    ],
    "wof:name":"Heaven Saints Church",
    "wof:placetype":"venue"
},
  "geometry": {"coordinates":[-81.111422,33.668424],"type":"Point"}
}