{
  "type": "Feature",
  "properties": {
    "iso:country":"US",
    "sg:address":"392 Farm View Rd",
    "sg:city":"Batesburg",
    "sg:classifiers":[
        {
            "category":"Personal",
            "subcategory":"Beauty Salon",
            "type":"Services"
        }
    ],
    "sg:phone":"+1 803 685 7049",
    "sg:postcode":"29006",
    "sg:province":"SC",
    "wof:name":"Images By Cyndi",
    "wof:placetype":"venue"
},
  "geometry": {"coordinates":[-81.58652600000001,33.850485],"type":"Point"}
}