{
  "type": "Feature",
  "properties": {
    "iso:country":"US",
    "sg:address":"1316 1st Ave",
    "sg:city":"Conway",
    "sg:classifiers":[
        {
            "category":"Government",
            "subcategory":"Office",
            "type":"Public Place"
        }
    ],
    "sg:phone":"+1 843 248 5863",
    "sg:postcode":"29526",
    "sg:province":"SC",
    "wof:name":"Us Plant Protection/Quarantine",
    "wof:placetype":"venue"
},
  "geometry": {"coordinates":[-79.04830800000001,33.831461],"type":"Point"}
}