{
  "type": "Feature",
  "properties": {
    "iso:country":"US",
    "sg:address":"253 Cabots Creek Dr",
    "sg:city":"Myrtle Beach",
    "sg:classifiers":[
        {
            "category":"Autos & Motor Vehicles",
            "subcategory":"Automobile Sales",
            "type":"Retail Goods"
        }
    ],
    "sg:phone":"+1 843 236 1722",
    "sg:postcode":"29526",
    "sg:province":"SC",
    "sg:tags":[
        "used"
    ],
    "wof:name":"A1 Cars",
    "wof:placetype":"venue"
},
  "geometry": {"coordinates":[-79.024456,33.739298],"type":"Point"}
}