{
  "type": "Feature",
  "properties": {
    "addr:full":"85 Montagu St Charleston SC 29401",
    "addr:housenumber":"85",
    "addr:postcode":"29401",
    "addr:street":"Montagu St",
    "iso:country":"US",
    "sg:address":"85 Montagu St",
    "sg:city":"Charleston",
    "sg:classifiers":[
        {
            "category":"Wholesale",
            "subcategory":"Stationery",
            "type":"Manufacturing & Wholesale Goods"
        }
    ],
    "sg:phone":"+1 843 723 2420",
    "sg:postcode":"29401",
    "sg:province":"SC",
    "sg:tags":[
        "business",
        "form",
        "system"
    ],
    "wof:name":"Professional Business Systems",
    "wof:placetype":"venue"
},
  "geometry": {"coordinates":[-79.945903,32.779007],"type":"Point"}
}