{
  "type": "Feature",
  "properties": {
    "iso:country":"US",
    "sg:address":"3301 Wade Hampton Blvd",
    "sg:city":"Taylors",
    "sg:classifiers":[
        {
            "category":"Food & Beverages",
            "subcategory":"Groceries & Convenience Stores",
            "type":"Retail Goods"
        }
    ],
    "sg:phone":"+1 864 292 3843",
    "sg:postcode":"29687",
    "sg:province":"SC",
    "wof:name":"Hickory Point",
    "wof:placetype":"venue"
},
  "geometry": {"coordinates":[-82.314413,34.918548],"type":"Point"}
}