{
  "type": "Feature",
  "properties": {
    "addr:full":"500 N Main St Summerville SC 29483",
    "addr:housenumber":"500",
    "addr:postcode":"29483",
    "addr:street":"N Main St",
    "iso:country":"US",
    "sg:address":"500 N Main St",
    "sg:city":"Summerville",
    "sg:classifiers":[
        {
            "category":"Government",
            "subcategory":"Office",
            "type":"Public Place"
        }
    ],
    "sg:phone":"+1 843 563 0040",
    "sg:postcode":"29483",
    "sg:province":"SC",
    "wof:name":"County Council",
    "wof:placetype":"venue"
},
  "geometry": {"coordinates":[-80.17119599999999,33.025216],"type":"Point"}
}