{
  "type": "Feature",
  "properties": {
    "addr:full":"475 E Main St Moncks Corner SC 29461",
    "addr:housenumber":"475",
    "addr:postcode":"29461",
    "addr:street":"E Main St",
    "iso:country":"US",
    "sg:address":"475 E Main St",
    "sg:city":"Moncks Corner",
    "sg:classifiers":[
        {
            "category":"Retail",
            "subcategory":"Car Wash",
            "type":"Services"
        }
    ],
    "sg:phone":"+1 843 899 4737",
    "sg:postcode":"29461",
    "sg:province":"SC",
    "sg:tags":[
        "polishing",
        "washing"
    ],
    "wof:name":"M C Auto & Marine Detail",
    "wof:placetype":"venue"
},
  "geometry": {"coordinates":[-80.00085199999999,33.192237],"type":"Point"}
}