{
  "type": "Feature",
  "properties": {
    "addr:full":"111 Cooks Pond Rd Windsor SC 29856",
    "addr:housenumber":"111",
    "addr:postcode":"29856",
    "addr:street":"Cooks Pond Rd",
    "iso:country":"US",
    "sg:address":"111 Cooks Pond Rd",
    "sg:city":"Windsor",
    "sg:classifiers":[
        {
            "category":"Building & Trades",
            "subcategory":"Construction",
            "type":"Services"
        }
    ],
    "sg:phone":"+1 803 266 4906",
    "sg:postcode":"29856",
    "sg:province":"SC",
    "sg:tags":[
        "floor",
        "laying",
        "contractor"
    ],
    "wof:name":"Wood Floors By Tutt & Tutt",
    "wof:placetype":"venue"
},
  "geometry": {"coordinates":[-81.551879,33.40042],"type":"Point"}
}