{
  "type": "Feature",
  "properties": {
    "iso:country":"US",
    "sg:address":"3897 Sherer Rd",
    "sg:city":"Sharon",
    "sg:classifiers":[
        {
            "category":"Retail",
            "subcategory":"Auto Repair",
            "type":"Services"
        }
    ],
    "sg:phone":"+1 803 927 7500",
    "sg:postcode":"29742",
    "sg:province":"SC",
    "sg:tags":[
        "muffler",
        "exhaust",
        "system"
    ],
    "wof:name":"Richard's Muffler & Brake Svc",
    "wof:placetype":"venue"
},
  "geometry": {"coordinates":[-81.358486,34.922975],"type":"Point"}
}