{
  "type": "Feature",
  "properties": {
    "iso:country":"US",
    "sg:address":"903 E Main St",
    "sg:city":"Laurens",
    "sg:classifiers":[
        {
            "category":"Home & Garden",
            "subcategory":"Furniture",
            "type":"Retail Goods"
        }
    ],
    "sg:phone":"+1 864 984 8013",
    "sg:postcode":"29360",
    "sg:province":"SC",
    "wof:name":"Farmers Furniture",
    "wof:placetype":"venue"
},
  "geometry": {"coordinates":[-81.982825,34.493271],"type":"Point"}
}