{
  "type": "Feature",
  "properties": {
    "iso:country":"US",
    "sg:address":"820 Lakeview Blvd",
    "sg:city":"Hartsville",
    "sg:classifiers":[
        {
            "category":"Organizations",
            "subcategory":"Religious Organization",
            "type":"Services"
        }
    ],
    "sg:phone":"+1 843 332 7632",
    "sg:postcode":"29550",
    "sg:province":"SC",
    "sg:tags":[
        "church"
    ],
    "wof:name":"First Southern Methodist Chr",
    "wof:placetype":"venue"
},
  "geometry": {"coordinates":[-80.092492,34.397738],"type":"Point"}
}