{
  "type": "Feature",
  "properties": {
    "addr:full":"114 Greenleaf Cir Chapin SC 29036",
    "addr:housenumber":"114",
    "addr:postcode":"29036",
    "addr:street":"Greenleaf Cir",
    "iso:country":"US",
    "sg:address":"114 Greenleaf Cir",
    "sg:city":"Chapin",
    "sg:classifiers":[
        {
            "category":"Real Estate",
            "subcategory":"Surveying",
            "type":"Services"
        }
    ],
    "sg:phone":"+1 803 345 0159",
    "sg:postcode":"29036",
    "sg:province":"SC",
    "sg:tags":[
        "surveyor"
    ],
    "wof:name":"J W Gee Surveying Co",
    "wof:placetype":"venue"
},
  "geometry": {"coordinates":[-81.368717,34.126418],"type":"Point"}
}