{
  "type": "Feature",
  "properties": {
    "addr:full":"65 Cherry Hills Dr Aiken SC 29803",
    "addr:housenumber":"65",
    "addr:postcode":"29803",
    "addr:street":"Cherry Hills Dr",
    "iso:country":"US",
    "sg:address":"65 Cherry Hills Dr",
    "sg:city":"Aiken",
    "sg:classifiers":[
        {
            "category":"Professional",
            "type":"Services"
        }
    ],
    "sg:phone":"+1 803 642 5545",
    "sg:postcode":"29803",
    "sg:province":"SC",
    "sg:tags":[
        "establishment"
    ],
    "wof:name":"Hertz Corp Commercial Sales",
    "wof:placetype":"venue"
},
  "geometry": {"coordinates":[-81.74847,33.522369],"type":"Point"}
}