{
  "type": "Feature",
  "properties": {
    "iso:country":"US",
    "sg:address":"102 E Carolina Ave",
    "sg:city":"Summerville",
    "sg:classifiers":[
        {
            "category":"Professional",
            "type":"Services"
        }
    ],
    "sg:phone":"+1 843 851 6968",
    "sg:postcode":"29483",
    "sg:province":"SC",
    "sg:tags":[
        "establishment"
    ],
    "wof:name":"Mike Reid Weeks Inc",
    "wof:placetype":"venue"
},
  "geometry": {"coordinates":[-80.187415,33.006373],"type":"Point"}
}