{
  "type": "Feature",
  "properties": {
    "addr:full":"247 Silas Ln Santee SC 29142",
    "addr:housenumber":"247",
    "addr:postcode":"29142",
    "addr:street":"Silas Ln",
    "iso:country":"US",
    "sg:address":"247 Silas Ln",
    "sg:city":"Santee",
    "sg:classifiers":[
        {
            "category":"Real Estate",
            "subcategory":"Real Estate Operator",
            "type":"Services"
        }
    ],
    "sg:phone":"+1 803 496 7065",
    "sg:postcode":"29142",
    "sg:province":"SC",
    "sg:tags":[
        "property",
        "lessor"
    ],
    "wof:name":"Hampton Jefferson",
    "wof:placetype":"venue"
},
  "geometry": {"coordinates":[-80.519834,33.428903],"type":"Point"}
}