{
  "type": "Feature",
  "properties": {
    "addr:full":"1138 Camp Creek Rd Lancaster SC 29720",
    "addr:housenumber":"1138",
    "addr:postcode":"29720",
    "addr:street":"Camp Creek Rd",
    "iso:country":"US",
    "sg:address":"1138 Camp Creek Rd",
    "sg:city":"Lancaster",
    "sg:classifiers":[
        {
            "category":"Social Services",
            "subcategory":"Job Training",
            "type":"Services"
        }
    ],
    "sg:phone":"+1 803 285 8474",
    "sg:postcode":"29720",
    "sg:province":"SC",
    "sg:tags":[
        "retardation",
        "disabled",
        "mental",
        "dev"
    ],
    "wof:name":"Lancaster Disabilities & Spcl",
    "wof:placetype":"venue"
},
  "geometry": {"coordinates":[-80.728624,34.735097],"type":"Point"}
}