{
  "type": "Feature",
  "properties": {
    "addr:full":"402 N Williamson Rd Florence SC 29506",
    "addr:housenumber":"402",
    "addr:postcode":"29506",
    "addr:street":"N Williamson Rd",
    "iso:country":"US",
    "sg:address":"402 N Williamson Rd",
    "sg:city":"Florence",
    "sg:classifiers":[
        {
            "category":"Insurance",
            "subcategory":"Insurance Agent",
            "type":"Services"
        }
    ],
    "sg:phone":"+1 843 667 8524",
    "sg:postcode":"29506",
    "sg:province":"SC",
    "wof:name":"Mitchams & Associates",
    "wof:placetype":"venue"
},
  "geometry": {"coordinates":[-79.702685,34.206842],"type":"Point"}
}