{
  "type": "Feature",
  "properties": {
    "iso:country":"US",
    "sg:address":"865 Fork Chapel Dr",
    "sg:city":"Lake View",
    "sg:classifiers":[
        {
            "category":"Organizations",
            "subcategory":"Religious Organization",
            "type":"Services"
        }
    ],
    "sg:phone":"+1 843 841 9090",
    "sg:postcode":"29536",
    "sg:province":"SC",
    "sg:tags":[
        "church"
    ],
    "wof:name":"Fork Chapel Baptist Church",
    "wof:placetype":"venue"
},
  "geometry": {"coordinates":[-79.376117,34.43484],"type":"Point"}
}