{
  "type": "Feature",
  "properties": {
    "addr:full":"3201 Bachman Rd Gaston SC 29053",
    "addr:housenumber":"3201",
    "addr:postcode":"29053",
    "addr:street":"Bachman Rd",
    "iso:country":"US",
    "sg:address":"3201 Bachman Rd",
    "sg:city":"Gaston",
    "sg:classifiers":[
        {
            "category":"Farming",
            "subcategory":"Livestock Farm",
            "type":"Manufacturing & Wholesale Goods"
        }
    ],
    "sg:phone":"+1 803 794 2578",
    "sg:postcode":"29053",
    "sg:province":"SC",
    "sg:tags":[
        "equine"
    ],
    "wof:name":"Horse Feathers Farm",
    "wof:placetype":"venue"
},
  "geometry": {"coordinates":[-81.092045,33.88474],"type":"Point"}
}