{
  "type": "Feature",
  "properties": {
    "iso:country":"US",
    "sg:address":"100 Haddrell St",
    "sg:city":"Mt Pleasant",
    "sg:classifiers":[
        {
            "category":"Recreation",
            "type":"Entertainment"
        }
    ],
    "sg:phone":"+1 843 696 6700",
    "sg:postcode":"29464",
    "sg:province":"SC",
    "sg:tags":[
        "guide"
    ],
    "wof:name":"Shem Creek Charters",
    "wof:placetype":"venue"
},
  "geometry": {"coordinates":[-79.884903,32.788776],"type":"Point"}
}