{
  "type": "Feature",
  "properties": {
    "iso:country":"US",
    "sg:address":"2437 Willwood Dr",
    "sg:city":"Florence",
    "sg:classifiers":[
        {
            "category":"Restaurant",
            "type":"Food & Drink"
        }
    ],
    "sg:phone":"+1 843 777 3131",
    "sg:postcode":"29501",
    "sg:province":"SC",
    "wof:name":"Jammie's Cafe",
    "wof:placetype":"venue"
},
  "geometry": {"coordinates":[-79.818932,34.185439],"type":"Point"}
}