{
  "type": "Feature",
  "properties": {
    "iso:country":"US",
    "sg:address":"4116 Clemson Blvd",
    "sg:city":"Anderson",
    "sg:classifiers":[
        {
            "category":"Retail",
            "subcategory":"Auto Rental",
            "type":"Services"
        }
    ],
    "sg:phone":"+1 864 226 5666",
    "sg:postcode":"29621",
    "sg:province":"SC",
    "sg:tags":[
        "renting",
        "automobile"
    ],
    "wof:name":"Thrifty Car Rental",
    "wof:placetype":"venue"
},
  "geometry": {"coordinates":[-82.695329,34.560908],"type":"Point"}
}