{
  "type": "Feature",
  "properties": {
    "addr:full":"1115 Augusta Rd North Augusta SC 29822",
    "addr:housenumber":"1115",
    "addr:postcode":"29822",
    "addr:street":"Augusta Rd",
    "iso:country":"US",
    "sg:address":"1115 Augusta Rd",
    "sg:city":"North Augusta",
    "sg:classifiers":[
        {
            "category":"Social Services",
            "subcategory":"Child Care",
            "type":"Services"
        }
    ],
    "sg:phone":"+1 803 278 0988",
    "sg:postcode":"29822",
    "sg:province":"SC",
    "wof:name":"Family Affair Day Care",
    "wof:placetype":"venue"
},
  "geometry": {"coordinates":[-81.89196099999999,33.496761],"type":"Point"}
}