{
  "type": "Feature",
  "properties": {
    "iso:country":"US",
    "sg:address":"1370 Ashley River Rd",
    "sg:city":"Charleston",
    "sg:classifiers":[
        {
            "category":"Health Services",
            "subcategory":"Health Practitioner",
            "type":"Services"
        }
    ],
    "sg:phone":"+1 843 556 2123",
    "sg:postcode":"29407",
    "sg:province":"SC",
    "sg:tags":[
        "nutritionist"
    ],
    "wof:name":"Biotherapy",
    "wof:placetype":"venue"
},
  "geometry": {"coordinates":[-80.00360999999999,32.798287],"type":"Point"}
}