{
  "type": "Feature",
  "properties": {
    "addr:full":"3506 Edwards Rd Taylors SC 29687",
    "addr:housenumber":"3506",
    "addr:postcode":"29687",
    "addr:street":"Edwards Rd",
    "iso:country":"US",
    "sg:address":"3506 Edwards Rd",
    "sg:city":"Taylors",
    "sg:classifiers":[
        {
            "category":"Organizations",
            "subcategory":"Religious Organization",
            "type":"Services"
        }
    ],
    "sg:phone":"+1 864 268 3777",
    "sg:postcode":"29687",
    "sg:province":"SC",
    "sg:tags":[
        "church"
    ],
    "wof:name":"Devotion & Prayer Connection",
    "wof:placetype":"venue"
},
  "geometry": {"coordinates":[-82.32594400000001,34.894565],"type":"Point"}
}