{
  "type": "Feature",
  "properties": {
    "addr:full":"820 Woods Crossing Rd Greenville SC 29607",
    "addr:housenumber":"820",
    "addr:postcode":"29607",
    "addr:street":"Woods Crossing Rd",
    "iso:country":"US",
    "sg:address":"820 Woods Crossing Rd",
    "sg:city":"Greenville",
    "sg:classifiers":[
        {
            "category":"Shopping",
            "subcategory":"Hobbies, Toys, & Games",
            "type":"Retail Goods"
        }
    ],
    "sg:phone":"+1 864 234 5867",
    "sg:postcode":"29607",
    "sg:province":"SC",
    "wof:name":"Toys R Us",
    "wof:placetype":"venue"
},
  "geometry": {"coordinates":[-82.33620999999999,34.847883],"type":"Point"}
}