{
  "type": "Feature",
  "properties": {
    "iso:country":"US",
    "sg:address":"830 Berry Shoals Rd",
    "sg:city":"Duncan",
    "sg:classifiers":[
        {
            "category":"Banks & Credit Unions",
            "subcategory":"Financial Services",
            "type":"Services"
        }
    ],
    "sg:phone":"+1 864 877 8620",
    "sg:postcode":"29334",
    "sg:province":"SC",
    "sg:tags":[
        "company",
        "holding"
    ],
    "wof:name":"Tc Holding Company Inc",
    "wof:placetype":"venue"
},
  "geometry": {"coordinates":[-82.133045,34.877576],"type":"Point"}
}