{
  "type": "Feature",
  "properties": {
    "iso:country":"US",
    "sg:address":"10203 Two Notch Rd",
    "sg:city":"Columbia",
    "sg:classifiers":[
        {
            "category":"Home & Garden",
            "subcategory":"Carpets & Floor Coverings",
            "type":"Retail Goods"
        }
    ],
    "sg:phone":"+1 803 736 8485",
    "sg:postcode":"29229",
    "sg:province":"SC",
    "sg:tags":[
        "dealer",
        "rug"
    ],
    "wof:name":"Carpet Shoppe",
    "wof:placetype":"venue"
},
  "geometry": {"coordinates":[-80.87875699999999,34.119335],"type":"Point"}
}