{
  "type": "Feature",
  "properties": {
    "iso:country":"US",
    "sg:address":"2145 N Main St",
    "sg:city":"Summerville",
    "sg:classifiers":[
        {
            "category":"Recreation",
            "subcategory":"Arcade",
            "type":"Entertainment"
        }
    ],
    "sg:phone":"+1 843 821 0025",
    "sg:postcode":"29483",
    "sg:province":"SC",
    "sg:tags":[
        "amusement",
        "devices"
    ],
    "wof:name":"Second Quarter Amusements",
    "wof:placetype":"venue"
},
  "geometry": {"coordinates":[-80.11111099999999,33.045961],"type":"Point"}
}