{
  "type": "Feature",
  "properties": {
    "iso:country":"US",
    "sg:address":"302 Bowdin Ct",
    "sg:city":"Ladson",
    "sg:classifiers":[
        {
            "category":"Building & Trades",
            "subcategory":"Construction",
            "type":"Services"
        }
    ],
    "sg:phone":"+1 843 824 2993",
    "sg:postcode":"29456",
    "sg:province":"SC",
    "sg:tags":[
        "contractor"
    ],
    "wof:name":"Island Roofing",
    "wof:placetype":"venue"
},
  "geometry": {"coordinates":[-80.100281,33.023916],"type":"Point"}
}