{
  "type": "Feature",
  "properties": {
    "iso:country":"US",
    "sg:address":"150 Oakland Ave",
    "sg:city":"Rock Hill",
    "sg:classifiers":[
        {
            "category":"Professional",
            "subcategory":"Secretarial Services",
            "type":"Services"
        }
    ],
    "sg:phone":"+1 803 328 2848",
    "sg:postcode":"29730",
    "sg:province":"SC",
    "sg:tags":[
        "resume",
        "writing"
    ],
    "wof:name":"College Secretarial Service",
    "wof:placetype":"venue"
},
  "geometry": {"coordinates":[-81.02453300000001,34.931035],"type":"Point"}
}