{
  "type": "Feature",
  "properties": {
    "iso:country":"US",
    "sg:address":"305 Black Oak Rd",
    "sg:city":"Bonneau",
    "sg:classifiers":[
        {
            "category":"Government",
            "subcategory":"Office",
            "type":"Public Place"
        }
    ],
    "sg:phone":"+1 843 825 3387",
    "sg:postcode":"29431",
    "sg:province":"SC",
    "wof:name":"South Carolina Natural Rsrcs",
    "wof:placetype":"venue"
},
  "geometry": {"coordinates":[-79.96316,33.306204],"type":"Point"}
}