{
  "type": "Feature",
  "properties": {
    "addr:full":"117 Chisolm Trl Greenville SC 29607",
    "addr:housenumber":"117",
    "addr:postcode":"29607",
    "addr:street":"Chisolm Trl",
    "iso:country":"US",
    "sg:address":"117 Chisolm Trl",
    "sg:city":"Greenville",
    "sg:classifiers":[
        {
            "category":"Autos & Motor Vehicles",
            "subcategory":"Fuel & Gas Station",
            "type":"Retail Goods"
        }
    ],
    "sg:phone":"+1 864 288 6848",
    "sg:postcode":"29607",
    "sg:province":"SC",
    "sg:tags":[
        "gasoline",
        "station",
        "foundry",
        "aluminum"
    ],
    "wof:name":"BP Products Inc",
    "wof:placetype":"venue"
},
  "geometry": {"coordinates":[-82.352583,34.807088],"type":"Point"}
}