{
  "type": "Feature",
  "properties": {
    "addr:full":"100 Edwards St Taylors SC 29687",
    "addr:housenumber":"100",
    "addr:postcode":"29687",
    "addr:street":"Edwards St",
    "iso:country":"US",
    "sg:address":"100 Edwards St",
    "sg:city":"Taylors",
    "sg:classifiers":[
        {
            "category":"Wholesale",
            "subcategory":"Machinery & Supplies",
            "type":"Manufacturing & Wholesale Goods"
        }
    ],
    "sg:phone":"+1 864 268 0679",
    "sg:postcode":"29687",
    "sg:province":"SC",
    "sg:tags":[
        "equipment",
        "industrial"
    ],
    "wof:name":"Cha-Tay Ind Supply",
    "wof:placetype":"venue"
},
  "geometry": {"coordinates":[-82.303764,34.918437],"type":"Point"}
}