{
  "type": "Feature",
  "properties": {
    "iso:country":"US",
    "sg:address":"1226 Pickens St",
    "sg:city":"Columbia",
    "sg:classifiers":[
        {
            "category":"Organizations",
            "subcategory":"Professional Association",
            "type":"Services"
        }
    ],
    "sg:phone":"+1 803 256 6473",
    "sg:postcode":"29201",
    "sg:province":"SC",
    "wof:name":"Professional Insurance Agents",
    "wof:placetype":"venue"
},
  "geometry": {"coordinates":[-81.02770599999999,34.004238],"type":"Point"}
}