{
  "type": "Feature",
  "properties": {
    "addr:full":"103 Quarter Mile Rd Salem SC 29676",
    "addr:housenumber":"103",
    "addr:postcode":"29676",
    "addr:street":"Quarter Mile Rd",
    "iso:country":"US",
    "sg:address":"103 Quarter Mile Rd",
    "sg:city":"Salem",
    "sg:classifiers":[
        {
            "category":"Building & Trades",
            "subcategory":"Construction",
            "type":"Services"
        }
    ],
    "sg:phone":"+1 864 944 2804",
    "sg:postcode":"29676",
    "sg:province":"SC",
    "sg:tags":[
        "general",
        "contractor"
    ],
    "wof:name":"C Cecil Houston Inc",
    "wof:placetype":"venue"
},
  "geometry": {"coordinates":[-82.973668,34.909893],"type":"Point"}
}