{
  "type": "Feature",
  "properties": {
    "iso:country":"US",
    "sg:address":"121 Deborah Ln",
    "sg:city":"Greenville",
    "sg:classifiers":[
        {
            "category":"Shopping",
            "subcategory":"Jewelry",
            "type":"Retail Goods"
        }
    ],
    "sg:phone":"+1 864 295 5775",
    "sg:postcode":"29611",
    "sg:province":"SC",
    "sg:tags":[
        "jeweler"
    ],
    "wof:name":"Silvermine",
    "wof:placetype":"venue"
},
  "geometry": {"coordinates":[-82.476608,34.857175],"type":"Point"}
}