{
  "type": "Feature",
  "properties": {
    "iso:country":"US",
    "sg:address":"106 Ellis Ferry Ave",
    "sg:city":"Gaffney",
    "sg:classifiers":[
        {
            "category":"Real Estate",
            "subcategory":"Real Estate Operator",
            "type":"Services"
        }
    ],
    "sg:phone":"+1 864 487 7088",
    "sg:postcode":"29341",
    "sg:province":"SC",
    "sg:tags":[
        "building",
        "apartment"
    ],
    "wof:name":"Grant U Trivett",
    "wof:placetype":"venue"
},
  "geometry": {"coordinates":[-81.660664,35.089302],"type":"Point"}
}