{
  "type": "Feature",
  "properties": {
    "iso:country":"US",
    "sg:address":"100 Old Cherokee Rd",
    "sg:city":"Lexington",
    "sg:classifiers":[
        {
            "category":"Building & Trades",
            "subcategory":"Construction",
            "type":"Services"
        }
    ],
    "sg:phone":"+1 803 808 5867",
    "sg:postcode":"29072",
    "sg:province":"SC",
    "sg:tags":[
        "contractor"
    ],
    "wof:name":"American Roof Care",
    "wof:placetype":"venue"
},
  "geometry": {"coordinates":[-81.21952400000001,33.998077],"type":"Point"}
}