{
  "type": "Feature",
  "properties": {
    "addr:full":"340 Vesper Ct Sumter SC 29150",
    "addr:housenumber":"340",
    "addr:postcode":"29150",
    "addr:street":"Vesper Ct",
    "iso:country":"US",
    "sg:address":"340 Vesper Ct",
    "sg:city":"Sumter",
    "sg:classifiers":[
        {
            "category":"Building & Trades",
            "subcategory":"Construction",
            "type":"Services"
        }
    ],
    "sg:phone":"+1 803 934 8126",
    "sg:postcode":"29150",
    "sg:province":"SC",
    "sg:tags":[
        "general",
        "contractor"
    ],
    "wof:name":"Morris Construction",
    "wof:placetype":"venue"
},
  "geometry": {"coordinates":[-80.347548,33.888558],"type":"Point"}
}