{
  "type": "Feature",
  "properties": {
    "iso:country":"US",
    "sg:address":"602 Mims St",
    "sg:city":"Edgefield",
    "sg:classifiers":[
        {
            "category":"Organizations",
            "subcategory":"Religious Organization",
            "type":"Services"
        }
    ],
    "sg:phone":"+1 803 637 6312",
    "sg:postcode":"29824",
    "sg:province":"SC",
    "sg:tags":[
        "god",
        "churches-pentecostal",
        "church"
    ],
    "wof:name":"Church Of God",
    "wof:placetype":"venue"
},
  "geometry": {"coordinates":[-81.920779,33.780678],"type":"Point"}
}