{
  "type": "Feature",
  "properties": {
    "addr:full":"330 Robert Smalls Pkwy Beaufort SC 29906",
    "addr:housenumber":"330",
    "addr:postcode":"29906",
    "addr:street":"Robert Smalls Pkwy",
    "iso:country":"US",
    "sg:address":"330 Robert Smalls Pkwy",
    "sg:city":"Beaufort",
    "sg:classifiers":[
        {
            "category":"Shopping",
            "subcategory":"Shoes",
            "type":"Retail Goods"
        }
    ],
    "sg:phone":"+1 843 524 0017",
    "sg:postcode":"29906",
    "sg:province":"SC",
    "wof:name":"Shoe Department",
    "wof:placetype":"venue"
},
  "geometry": {"coordinates":[-80.733193,32.42329],"type":"Point"}
}