{
  "type": "Feature",
  "properties": {
    "iso:country":"US",
    "sg:address":"2309 N Ocean Blvd",
    "sg:city":"Myrtle Beach",
    "sg:classifiers":[
        {
            "category":"Building & Trades",
            "subcategory":"Construction",
            "type":"Services"
        }
    ],
    "sg:phone":"+1 843 448 9701",
    "sg:postcode":"29577",
    "sg:province":"SC",
    "sg:tags":[
        "maintenance",
        "contractor"
    ],
    "wof:name":"Meridian Plaza Maintenance",
    "wof:placetype":"venue"
},
  "geometry": {"coordinates":[-78.867392,33.703654],"type":"Point"}
}