{
  "type": "Feature",
  "properties": {
    "iso:country":"US",
    "sg:address":"1111 10th Ave N",
    "sg:city":"Myrtle Beach",
    "sg:classifiers":[
        {
            "category":"Shopping",
            "subcategory":"Computers & Home Electronics",
            "type":"Retail Goods"
        }
    ],
    "sg:phone":"+1 843 916 1599",
    "sg:postcode":"29577",
    "sg:province":"SC",
    "wof:name":"Dream Makers",
    "wof:placetype":"venue"
},
  "geometry": {"coordinates":[-78.890131,33.703949],"type":"Point"}
}