{
  "type": "Feature",
  "properties": {
    "iso:country":"US",
    "sg:address":"308 N McQueen St",
    "sg:city":"Florence",
    "sg:classifiers":[
        {
            "category":"Building & Trades",
            "subcategory":"Pest Control",
            "type":"Services"
        }
    ],
    "sg:phone":"+1 843 662 7716",
    "sg:postcode":"29501",
    "sg:province":"SC",
    "wof:name":"Griffin Pest Control Svc",
    "wof:placetype":"venue"
},
  "geometry": {"coordinates":[-79.772474,34.201642],"type":"Point"}
}