{
  "type": "Feature",
  "properties": {
    "addr:full":"2540 David H Mcleod Blvd Florence SC 29501",
    "addr:housenumber":"2540",
    "addr:postcode":"29501",
    "addr:street":"David H Mcleod Blvd",
    "iso:country":"US",
    "sg:address":"2540 David H Mcleod Blvd",
    "sg:city":"Florence",
    "sg:classifiers":[
        {
            "category":"Restaurant",
            "type":"Food & Drink"
        }
    ],
    "sg:menulink":"http://www.allmenus.com/sc/florence/128216-red-lobster/menu/",
    "sg:phone":"+1 843 661 7130",
    "sg:postcode":"29501",
    "sg:province":"SC",
    "sg:tags":[
        "seafood",
        "american"
    ],
    "wof:name":"Red Lobster",
    "wof:placetype":"venue"
},
  "geometry": {"coordinates":[-79.82581500000001,34.188188],"type":"Point"}
}