{
  "type": "Feature",
  "properties": {
    "iso:country":"US",
    "sg:address":"21 N Harvin St",
    "sg:city":"Sumter",
    "sg:classifiers":[
        {
            "category":"Professional",
            "subcategory":"Lawyer & Legal Services",
            "type":"Services"
        }
    ],
    "sg:phone":"+1 803 934 9700",
    "sg:postcode":"29150",
    "sg:province":"SC",
    "sg:tags":[
        "attorney"
    ],
    "wof:name":"O Allen & Alexander",
    "wof:placetype":"venue"
},
  "geometry": {"coordinates":[-80.339881,33.921523],"type":"Point"}
}