{
  "type": "Feature",
  "properties": {
    "iso:country":"US",
    "sg:address":"2901 Anderson Rd",
    "sg:city":"Greenville",
    "sg:classifiers":[
        {
            "category":"Autos & Motor Vehicles",
            "subcategory":"Auto Supplies",
            "type":"Retail Goods"
        }
    ],
    "sg:phone":"+1 864 269 3535",
    "sg:postcode":"29611",
    "sg:province":"SC",
    "sg:tags":[
        "equipment",
        "racing"
    ],
    "wof:name":"Speed Shop",
    "wof:placetype":"venue"
},
  "geometry": {"coordinates":[-82.454429,34.806417],"type":"Point"}
}