{
  "type": "Feature",
  "properties": {
    "iso:country":"US",
    "sg:address":"901 Canal St",
    "sg:city":"Myrtle Beach",
    "sg:classifiers":[
        {
            "category":"Recreation",
            "type":"Entertainment"
        }
    ],
    "sg:phone":"+1 843 918 1465",
    "sg:postcode":"29577",
    "sg:province":"SC",
    "sg:tags":[
        "center"
    ],
    "wof:name":"Canal St Recreation Ctr",
    "wof:placetype":"venue"
},
  "geometry": {"coordinates":[-78.892612,33.702079],"type":"Point"}
}