{
  "type": "Feature",
  "properties": {
    "addr:full":"2253 State Hwy 11 Scn Walhalla SC 29691",
    "addr:housenumber":"2253",
    "addr:postcode":"29691",
    "addr:street":"State Hwy 11 Scn",
    "iso:country":"US",
    "sg:address":"2253 State Hwy 11 Scn",
    "sg:city":"Walhalla",
    "sg:classifiers":[
        {
            "category":"Retail",
            "subcategory":"Auto Repair",
            "type":"Services"
        }
    ],
    "sg:phone":"+1 864 638 7125",
    "sg:postcode":"29691",
    "sg:province":"SC",
    "sg:tags":[
        "body",
        "automobile",
        "painting"
    ],
    "wof:name":"Spearman Brothers Collision",
    "wof:placetype":"venue"
},
  "geometry": {"coordinates":[-83.055269,34.7216],"type":"Point"}
}