{
  "type": "Feature",
  "properties": {
    "iso:country":"US",
    "sg:address":"139 Batesview Dr",
    "sg:city":"Greenville",
    "sg:classifiers":[
        {
            "category":"Building & Trades",
            "subcategory":"Construction",
            "type":"Services"
        }
    ],
    "sg:phone":"+1 864 370 9491",
    "sg:postcode":"29607",
    "sg:province":"SC",
    "sg:tags":[
        "house"
    ],
    "wof:name":"Kent Home Repairs",
    "wof:placetype":"venue"
},
  "geometry": {"coordinates":[-82.37138,34.867978],"type":"Point"}
}