{
  "type": "Feature",
  "properties": {
    "addr:full":"3488 Augusta Rd Greenville SC 29605",
    "addr:housenumber":"3488",
    "addr:postcode":"29605",
    "addr:street":"Augusta Rd",
    "iso:country":"US",
    "sg:address":"3488 Augusta Rd",
    "sg:city":"Greenville",
    "sg:classifiers":[
        {
            "category":"Retail",
            "subcategory":"Auto Repair",
            "type":"Services"
        }
    ],
    "sg:phone":"+1 864 277 2928",
    "sg:postcode":"29605",
    "sg:province":"SC",
    "sg:tags":[
        "repairing",
        "automobile",
        "radiator"
    ],
    "wof:name":"Augusta Road Radiator Shop",
    "wof:placetype":"venue"
},
  "geometry": {"coordinates":[-82.38689599999999,34.770395],"type":"Point"}
}