{
  "type": "Feature",
  "properties": {
    "iso:country":"US",
    "sg:address":"1300 Winding Way",
    "sg:city":"Taylors",
    "sg:classifiers":[
        {
            "category":"Wholesale",
            "subcategory":"Office Equipment",
            "type":"Manufacturing & Wholesale Goods"
        }
    ],
    "sg:phone":"+1 864 268 8911",
    "sg:postcode":"29687",
    "sg:province":"SC",
    "sg:tags":[
        "credit"
    ],
    "wof:name":"Advanced Merchant Svc Inc",
    "wof:placetype":"venue"
},
  "geometry": {"coordinates":[-82.32367,34.936037],"type":"Point"}
}