{
  "type": "Feature",
  "properties": {
    "iso:country":"US",
    "sg:address":"47 Ferry Dr",
    "sg:city":"Ladys Island",
    "sg:classifiers":[
        {
            "category":"Bars & Pubs",
            "type":"Food & Drink"
        }
    ],
    "sg:menulink":"http://www.allmenus.com/sc/st-helena/237106-barbara-jeans-restaurant/menu/",
    "sg:phone":"+1 843 524 2400",
    "sg:postcode":"29907",
    "sg:province":"SC",
    "sg:tags":[
        "seafood",
        "american"
    ],
    "wof:name":"Barbara Jean's Restaurant",
    "wof:placetype":"venue"
},
  "geometry": {"coordinates":[-80.651259,32.411333],"type":"Point"}
}