{
  "type": "Feature",
  "properties": {
    "iso:country":"US",
    "sg:address":"307 W Walnut St",
    "sg:city":"Clinton",
    "sg:classifiers":[
        {
            "category":"Shopping",
            "subcategory":"Pharmacy",
            "type":"Retail Goods"
        }
    ],
    "sg:phone":"+1 864 833 1980",
    "sg:postcode":"29325",
    "sg:province":"SC",
    "wof:name":"Adair Apothecary LLC",
    "wof:placetype":"venue"
},
  "geometry": {"coordinates":[-81.882132,34.461793],"type":"Point"}
}