{
  "type": "Feature",
  "properties": {
    "addr:full":"162 Stone Bridge Dr Gaston SC 29053",
    "addr:housenumber":"162",
    "addr:postcode":"29053",
    "addr:street":"Stone Bridge Dr",
    "iso:country":"US",
    "sg:address":"162 Stone Bridge Dr",
    "sg:city":"Gaston",
    "sg:classifiers":[
        {
            "category":"Freight",
            "type":"Transportation"
        }
    ],
    "sg:phone":"+1 803 755 3865",
    "sg:postcode":"29053",
    "sg:province":"SC",
    "sg:tags":[
        "operator",
        "local",
        "trucking"
    ],
    "wof:name":"OCain Enterprises Inc",
    "wof:placetype":"venue"
},
  "geometry": {"coordinates":[-81.094657,33.884165],"type":"Point"}
}