{
  "type": "Feature",
  "properties": {
    "iso:country":"US",
    "sg:address":"120 Shanklin Rd",
    "sg:city":"Beaufort",
    "sg:classifiers":[
        {
            "category":"Government",
            "subcategory":"Office",
            "type":"Public Place"
        }
    ],
    "sg:phone":"+1 843 846 0770",
    "sg:postcode":"29906",
    "sg:province":"SC",
    "wof:name":"First Vehicle Svc",
    "wof:placetype":"venue"
},
  "geometry": {"coordinates":[-80.747032,32.462176],"type":"Point"}
}