{
  "type": "Feature",
  "properties": {
    "iso:country":"US",
    "sg:address":"775 Saint Andrews Rd",
    "sg:city":"Columbia",
    "sg:classifiers":[
        {
            "category":"Food & Beverages",
            "subcategory":"Groceries & Convenience Stores",
            "type":"Retail Goods"
        }
    ],
    "sg:phone":"+1 803 798 4630",
    "sg:postcode":"29210",
    "sg:province":"SC",
    "wof:name":"Circle K Store",
    "wof:placetype":"venue"
},
  "geometry": {"coordinates":[-81.120636,34.044298],"type":"Point"}
}