{
  "type": "Feature",
  "properties": {
    "iso:country":"US",
    "sg:address":"35 Varden Dr",
    "sg:city":"Aiken",
    "sg:classifiers":[
        {
            "category":"Professional",
            "subcategory":"Engineering",
            "type":"Services"
        }
    ],
    "sg:phone":"+1 803 642 8688",
    "sg:postcode":"29803",
    "sg:province":"SC",
    "sg:tags":[
        "engineer"
    ],
    "wof:name":"Legin Group Inc",
    "wof:placetype":"venue"
},
  "geometry": {"coordinates":[-81.746489,33.530211],"type":"Point"}
}