{
  "type": "Feature",
  "properties": {
    "iso:country":"US",
    "sg:address":"1360 Myers Rd",
    "sg:city":"Orangeburg",
    "sg:classifiers":[
        {
            "category":"Freight",
            "type":"Transportation"
        }
    ],
    "sg:phone":"+1 803 536 0517",
    "sg:postcode":"29115",
    "sg:province":"SC",
    "sg:tags":[
        "operator",
        "local",
        "trucking"
    ],
    "wof:name":"Oneway Express Trucking Inc",
    "wof:placetype":"venue"
},
  "geometry": {"coordinates":[-80.837559,33.489893],"type":"Point"}
}