{
  "type": "Feature",
  "properties": {
    "iso:country":"US",
    "sg:address":"1404 Gervais St",
    "sg:city":"Columbia",
    "sg:classifiers":[
        {
            "category":"Restaurant",
            "type":"Food & Drink"
        }
    ],
    "sg:phone":"+1 803 251 0255",
    "sg:postcode":"29204",
    "sg:province":"SC",
    "sg:tags":[
        "eating"
    ],
    "wof:name":"Palace Restaurant The",
    "wof:placetype":"venue"
},
  "geometry": {"coordinates":[-81.0288,34.002662],"type":"Point"}
}