{
  "type": "Feature",
  "properties": {
    "iso:country":"US",
    "sg:address":"1435 Bleckley St",
    "sg:city":"Anderson",
    "sg:classifiers":[
        {
            "category":"Building & Trades",
            "subcategory":"Construction",
            "type":"Services"
        }
    ],
    "sg:phone":"+1 864 224 6877",
    "sg:postcode":"29625",
    "sg:province":"SC",
    "sg:tags":[
        "general",
        "contractor"
    ],
    "wof:name":"Precision Concrete Inc",
    "wof:placetype":"venue"
},
  "geometry": {"coordinates":[-82.675247,34.520266],"type":"Point"}
}