{
  "type": "Feature",
  "properties": {
    "iso:country":"US",
    "sg:address":"207 Commerce St",
    "sg:city":"Manning",
    "sg:classifiers":[
        {
            "category":"Shopping",
            "subcategory":"Used Merchandise",
            "type":"Retail Goods"
        }
    ],
    "sg:phone":"+1 803 435 4111",
    "sg:postcode":"29102",
    "sg:province":"SC",
    "sg:tags":[
        "antique"
    ],
    "wof:name":"Southern Antiques",
    "wof:placetype":"venue"
},
  "geometry": {"coordinates":[-80.223454,33.696392],"type":"Point"}
}