{
  "type": "Feature",
  "properties": {
    "iso:country":"US",
    "sg:address":"5950 Tillman Nursery Rd",
    "sg:city":"Wedgefield",
    "sg:classifiers":[
        {
            "category":"Building & Trades",
            "subcategory":"Cleaning & Sanitation",
            "type":"Services"
        }
    ],
    "sg:phone":"+1 803 494 6146",
    "sg:postcode":"29168",
    "sg:province":"SC",
    "sg:tags":[
        "house"
    ],
    "wof:name":"A-Z Cleaning Svc",
    "wof:placetype":"venue"
},
  "geometry": {"coordinates":[-80.51082,33.883729],"type":"Point"}
}