{
  "type": "Feature",
  "properties": {
    "iso:country":"US",
    "sg:address":"1240 Colonial Commons Ct",
    "sg:city":"Lancaster",
    "sg:classifiers":[
        {
            "category":"Shopping",
            "subcategory":"Optical Goods",
            "type":"Retail Goods"
        }
    ],
    "sg:phone":"+1 803 285 3333",
    "sg:postcode":"29720",
    "sg:province":"SC",
    "wof:name":"Classic Glasses",
    "wof:placetype":"venue"
},
  "geometry": {"coordinates":[-80.79475499999999,34.721094],"type":"Point"}
}