{
  "type": "Feature",
  "properties": {
    "iso:country":"US",
    "sg:address":"1200 Hampton Street",
    "sg:city":"Columbia",
    "sg:classifiers":[
        {
            "category":"Travel",
            "subcategory":"Hotels & Motels",
            "type":"Entertainment"
        }
    ],
    "sg:phone":"+1 803 771 7000",
    "sg:postcode":"29201",
    "sg:province":"SC",
    "sg:website":"www.marriott.com",
    "wof:name":"Columbia Marriott",
    "wof:placetype":"venue"
},
  "geometry": {"coordinates":[-81.035312,34.005294],"type":"Point"}
}