{
  "type": "Feature",
  "properties": {
    "iso:country":"US",
    "sg:address":"306 Hampton Park",
    "sg:city":"Camden",
    "sg:classifiers":[
        {
            "category":"Professional",
            "subcategory":"Lawyer & Legal Services",
            "type":"Services"
        }
    ],
    "sg:phone":"+1 803 432 1780",
    "sg:postcode":"29020",
    "sg:province":"SC",
    "sg:tags":[
        "attorney"
    ],
    "wof:name":"David P Reuwer",
    "wof:placetype":"venue"
},
  "geometry": {"coordinates":[-80.601208,34.248336],"type":"Point"}
}