{
  "type": "Feature",
  "properties": {
    "iso:country":"US",
    "sg:address":"144 Garrett St",
    "sg:city":"Sumter",
    "sg:classifiers":[
        {
            "category":"Professional",
            "subcategory":"Accounting & Tax Preparation",
            "type":"Services"
        }
    ],
    "sg:phone":"+1 803 934 1206",
    "sg:postcode":"29150",
    "sg:province":"SC",
    "sg:tags":[
        "accountant"
    ],
    "wof:name":"P G Palmer & Co CPA'S LLP",
    "wof:placetype":"venue"
},
  "geometry": {"coordinates":[-80.378707,33.931068],"type":"Point"}
}