{
  "type": "Feature",
  "properties": {
    "iso:country":"US",
    "sg:address":"1 Meadow Ln",
    "sg:city":"Cheraw",
    "sg:classifiers":[
        {
            "category":"Freight",
            "type":"Transportation"
        }
    ],
    "sg:phone":"+1 843 537 6400",
    "sg:postcode":"29520",
    "sg:province":"SC",
    "sg:tags":[
        "trucking"
    ],
    "wof:name":"Waccamaw Transport",
    "wof:placetype":"venue"
},
  "geometry": {"coordinates":[-79.90054,34.677544],"type":"Point"}
}