{
  "type": "Feature",
  "properties": {
    "iso:country":"US",
    "sg:address":"1500 Main St",
    "sg:city":"Newberry",
    "sg:classifiers":[
        {
            "category":"Building & Trades",
            "subcategory":"Equipment Rental",
            "type":"Services"
        }
    ],
    "sg:phone":"+1 803 276 8810",
    "sg:postcode":"29108",
    "sg:province":"SC",
    "sg:tags":[
        "yard"
    ],
    "wof:name":"Good Cents Sales & Rentals",
    "wof:placetype":"venue"
},
  "geometry": {"coordinates":[-81.61657599999999,34.27558],"type":"Point"}
}