{
  "type": "Feature",
  "properties": {
    "iso:country":"US",
    "sg:address":"14 Burty Rd",
    "sg:city":"Greenville",
    "sg:classifiers":[
        {
            "category":"Autos & Motor Vehicles",
            "subcategory":"Boat Sales",
            "type":"Retail Goods"
        }
    ],
    "sg:phone":"+1 864 236 9005",
    "sg:postcode":"29605",
    "sg:province":"SC",
    "sg:tags":[
        "dealer",
        "sales"
    ],
    "wof:name":"Sea Ray Of Greenville",
    "wof:placetype":"venue"
},
  "geometry": {"coordinates":[-82.41889,34.791841],"type":"Point"}
}