{
  "type": "Feature",
  "properties": {
    "iso:country":"US",
    "sg:address":"2146 State Hwy 292",
    "sg:city":"Inman",
    "sg:classifiers":[
        {
            "category":"Real Estate",
            "subcategory":"Real Estate Agent",
            "type":"Services"
        }
    ],
    "sg:phone":"+1 864 472 4199",
    "sg:postcode":"29349",
    "sg:province":"SC",
    "wof:name":"Premier Real Estate",
    "wof:placetype":"venue"
},
  "geometry": {"coordinates":[-82.052374,35.084491],"type":"Point"}
}