{
  "type": "Feature",
  "properties": {
    "addr:full":"3840 Main St Loris SC 29569",
    "addr:housenumber":"3840",
    "addr:postcode":"29569",
    "addr:street":"Main St",
    "iso:country":"US",
    "sg:address":"3840 Main St",
    "sg:city":"Loris",
    "sg:classifiers":[
        {
            "category":"Autos & Motor Vehicles",
            "subcategory":"Boat Sales",
            "type":"Retail Goods"
        }
    ],
    "sg:phone":"+1 843 756 0156",
    "sg:postcode":"29569",
    "sg:province":"SC",
    "sg:tags":[
        "dealer",
        "sales"
    ],
    "wof:name":"Sammy's Boats & Motors",
    "wof:placetype":"venue"
},
  "geometry": {"coordinates":[-78.892481,34.057205],"type":"Point"}
}