{
  "type": "Feature",
  "properties": {
    "addr:full":"326 Oakland Ave Rock Hill SC 29730",
    "addr:housenumber":"326",
    "addr:postcode":"29730",
    "addr:street":"Oakland Ave",
    "iso:country":"US",
    "sg:address":"326 Oakland Ave",
    "sg:city":"Rock Hill",
    "sg:classifiers":[
        {
            "category":"Real Estate",
            "subcategory":"Real Estate Agent",
            "type":"Services"
        }
    ],
    "sg:phone":"+1 803 327 6539",
    "sg:postcode":"29730",
    "sg:province":"SC",
    "wof:name":"Eden Terrace Ltd Partners",
    "wof:placetype":"venue"
},
  "geometry": {"coordinates":[-81.025052,34.931658],"type":"Point"}
}