{
  "type": "Feature",
  "properties": {
    "iso:country":"US",
    "sg:address":"1315 Blanding St",
    "sg:city":"Columbia",
    "sg:classifiers":[
        {
            "category":"Banks & Credit Unions",
            "subcategory":"Financial Services",
            "type":"Services"
        }
    ],
    "sg:phone":"+1 803 799 9400",
    "sg:postcode":"29201",
    "sg:province":"SC",
    "sg:tags":[
        "company",
        "holding"
    ],
    "wof:name":"A&F Holdings LLC",
    "wof:placetype":"venue"
},
  "geometry": {"coordinates":[-81.033517,34.008939],"type":"Point"}
}