{
  "type": "Feature",
  "properties": {
    "addr:full":"1518 N Main St Summerville SC 29483",
    "addr:housenumber":"1518",
    "addr:postcode":"29483",
    "addr:street":"N Main St",
    "iso:country":"US",
    "sg:address":"1518 N Main St",
    "sg:city":"Summerville",
    "sg:classifiers":[
        {
            "category":"Food & Beverages",
            "subcategory":"Groceries & Convenience Stores",
            "type":"Retail Goods"
        }
    ],
    "sg:phone":"+1 843 821 7651",
    "sg:postcode":"29483",
    "sg:province":"SC",
    "wof:name":"Hess",
    "wof:placetype":"venue"
},
  "geometry": {"coordinates":[-80.143424,33.039268],"type":"Point"}
}