{
  "type": "Feature",
  "properties": {
    "addr:full":"3271 Carolina Country Club Rd Roebuck SC 29376",
    "addr:housenumber":"3271",
    "addr:postcode":"29376",
    "addr:street":"Carolina Country Club Rd",
    "iso:country":"US",
    "sg:address":"3271 Carolina Country Club Rd",
    "sg:city":"Roebuck",
    "sg:classifiers":[
        {
            "category":"Home & Garden",
            "subcategory":"Garden Supply",
            "type":"Retail Goods"
        }
    ],
    "sg:phone":"+1 864 574 1142",
    "sg:postcode":"29376",
    "sg:province":"SC",
    "sg:tags":[
        "lawn",
        "mower"
    ],
    "wof:name":"Lee's Lawnmower & Chain Saw",
    "wof:placetype":"venue"
},
  "geometry": {"coordinates":[-81.948852,34.86871],"type":"Point"}
}