{
  "type": "Feature",
  "properties": {
    "addr:full":"215 Arbor Rd Summerville SC 29485",
    "addr:housenumber":"215",
    "addr:postcode":"29485",
    "addr:street":"Arbor Rd",
    "iso:country":"US",
    "sg:address":"215 Arbor Rd",
    "sg:city":"Summerville",
    "sg:classifiers":[
        {
            "category":"Professional",
            "subcategory":"Secretarial Services",
            "type":"Services"
        }
    ],
    "sg:phone":"+1 843 832 0801",
    "sg:postcode":"29485",
    "sg:province":"SC",
    "sg:tags":[
        "reporting",
        "court"
    ],
    "wof:name":"Carolina Reporting",
    "wof:placetype":"venue"
},
  "geometry": {"coordinates":[-80.176789,32.993615],"type":"Point"}
}