{
  "type": "Feature",
  "properties": {
    "iso:country":"US",
    "sg:address":"1713 E Main St",
    "sg:city":"Westminster",
    "sg:classifiers":[
        {
            "category":"Building & Trades",
            "subcategory":"Construction",
            "type":"Services"
        }
    ],
    "sg:phone":"+1 864 647 6372",
    "sg:postcode":"29693",
    "sg:province":"SC",
    "sg:tags":[
        "contractor"
    ],
    "wof:name":"Advanced Construction",
    "wof:placetype":"venue"
},
  "geometry": {"coordinates":[-83.071173,34.665763],"type":"Point"}
}