{
  "type": "Feature",
  "properties": {
    "iso:country":"US",
    "sg:address":"1041 W Meeting St",
    "sg:city":"Lancaster",
    "sg:classifiers":[
        {
            "category":"Cinema",
            "subcategory":"Movie Theater",
            "type":"Entertainment"
        }
    ],
    "sg:phone":"+1 803 285 5554",
    "sg:postcode":"29720",
    "sg:province":"SC",
    "wof:name":"Crown Cinema Ofc",
    "wof:placetype":"venue"
},
  "geometry": {"coordinates":[-80.796338,34.714119],"type":"Point"}
}