{
  "type": "Feature",
  "properties": {
    "iso:country":"US",
    "sg:address":"210 Southern Oaks Ln",
    "sg:city":"Simpsonville",
    "sg:classifiers":[
        {
            "category":"Freight",
            "type":"Transportation"
        }
    ],
    "sg:phone":"+1 864 962 2285",
    "sg:postcode":"29681",
    "sg:province":"SC",
    "sg:tags":[
        "brokerage"
    ],
    "wof:name":"Liberty Logistics Inc",
    "wof:placetype":"venue"
},
  "geometry": {"coordinates":[-82.265685,34.739272],"type":"Point"}
}