{
  "type": "Feature",
  "properties": {
    "iso:country":"US",
    "sg:address":"105 Greenland Dr",
    "sg:city":"Goose Creek",
    "sg:classifiers":[
        {
            "category":"Health Services",
            "subcategory":"Chiropractor",
            "type":"Services"
        }
    ],
    "sg:phone":"+1 843 797 3290",
    "sg:postcode":"29445",
    "sg:province":"SC",
    "wof:name":"KIDD Chiropractic Clinic",
    "wof:placetype":"venue"
},
  "geometry": {"coordinates":[-80.05166199999999,33.009904],"type":"Point"}
}