{
  "type": "Feature",
  "properties": {
    "iso:country":"US",
    "sg:address":"1325 Dutch Fork Rd",
    "sg:city":"Irmo",
    "sg:classifiers":[
        {
            "category":"Restaurant",
            "type":"Food & Drink"
        }
    ],
    "sg:menulink":"http://www.allmenus.com/sc/dutch-fork/154793-hardees/menu/",
    "sg:phone":"+1 803 749 1513",
    "sg:postcode":"29063",
    "sg:province":"SC",
    "sg:tags":[
        "burger",
        "american"
    ],
    "wof:name":"Hardee's",
    "wof:placetype":"venue"
},
  "geometry": {"coordinates":[-81.235332,34.124558],"type":"Point"}
}