{
  "type": "Feature",
  "properties": {
    "iso:country":"US",
    "sg:address":"331 Stone Rd",
    "sg:city":"Williamston",
    "sg:classifiers":[
        {
            "category":"Home & Garden",
            "subcategory":"Garden Supply",
            "type":"Retail Goods"
        }
    ],
    "sg:phone":"+1 864 947 5555",
    "sg:postcode":"29697",
    "sg:province":"SC",
    "sg:tags":[
        "nurseryman"
    ],
    "wof:name":"Spring Hill Growers",
    "wof:placetype":"venue"
},
  "geometry": {"coordinates":[-82.554036,34.626792],"type":"Point"}
}