{
  "type": "Feature",
  "properties": {
    "iso:country":"US",
    "sg:address":"6800 Dorchester Rd",
    "sg:city":"Charleston",
    "sg:classifiers":[
        {
            "category":"Education",
            "subcategory":"School",
            "type":"Public Place"
        }
    ],
    "sg:phone":"+1 843 767 5900",
    "sg:postcode":"29418",
    "sg:province":"SC",
    "wof:name":"Lambs Elementary School",
    "wof:placetype":"venue"
},
  "geometry": {"coordinates":[-80.066467,32.884862],"type":"Point"}
}