{
  "type": "Feature",
  "properties": {
    "addr:full":"839 William Hilton Pkwy Hilton Head Island SC 29928",
    "addr:housenumber":"839",
    "addr:postcode":"29928",
    "addr:street":"William Hilton Pkwy",
    "iso:country":"US",
    "sg:address":"839 William Hilton Pkwy",
    "sg:city":"Hilton Head Island",
    "sg:classifiers":[
        {
            "category":"Real Estate",
            "subcategory":"Real Estate Agent",
            "type":"Services"
        }
    ],
    "sg:phone":"+1 843 686 3616",
    "sg:postcode":"29928",
    "sg:province":"SC",
    "wof:name":"Venable Group Property Mgt",
    "wof:placetype":"venue"
},
  "geometry": {"coordinates":[-80.731955,32.174586],"type":"Point"}
}