{
  "type": "Feature",
  "properties": {
    "iso:country":"US",
    "sg:address":"218 Main St",
    "sg:city":"North Myrtle Beach",
    "sg:classifiers":[
        {
            "category":"Real Estate",
            "subcategory":"Real Estate Agent",
            "type":"Services"
        }
    ],
    "sg:phone":"+1 843 249 0000",
    "sg:postcode":"29582",
    "sg:province":"SC",
    "sg:tags":[
        "rental",
        "property",
        "leasing"
    ],
    "wof:name":"Litus To Let",
    "wof:placetype":"venue"
},
  "geometry": {"coordinates":[-78.673137,33.820341],"type":"Point"}
}