{
  "type": "Feature",
  "properties": {
    "addr:full":"1313 Miller Rd Greenville SC 29607",
    "addr:housenumber":"1313",
    "addr:postcode":"29607",
    "addr:street":"Miller Rd",
    "iso:country":"US",
    "sg:address":"1313 Miller Rd",
    "sg:city":"Greenville",
    "sg:classifiers":[
        {
            "category":"Building & Trades",
            "subcategory":"Pest Control",
            "type":"Services"
        }
    ],
    "sg:phone":"+1 864 675 6226",
    "sg:postcode":"29607",
    "sg:province":"SC",
    "wof:name":"Gregory Pest & Lawn Solutions",
    "wof:placetype":"venue"
},
  "geometry": {"coordinates":[-82.29734000000001,34.82193],"type":"Point"}
}