{
  "type": "Feature",
  "properties": {
    "iso:country":"US",
    "sg:address":"40 Ellwood Ct",
    "sg:city":"Greenville",
    "sg:classifiers":[
        {
            "category":"Arts & Performance",
            "subcategory":"Theater",
            "type":"Entertainment"
        },
        {
            "category":"Manufacturing",
            "subcategory":"Tools & Machinery",
            "type":"Manufacturing & Wholesale Goods"
        }
    ],
    "sg:phone":"+1 864 288 2021",
    "sg:postcode":"29607",
    "sg:province":"SC",
    "sg:tags":[
        "equipment",
        "theatrical",
        "manufacturer",
        "electrical",
        "supply"
    ],
    "wof:name":"Performance Electric Inc",
    "wof:placetype":"venue"
},
  "geometry": {"coordinates":[-82.306365,34.79214],"type":"Point"}
}