{
  "type": "Feature",
  "properties": {
    "iso:country":"US",
    "sg:address":"2331 Elder Ave",
    "sg:city":"North Charleston",
    "sg:classifiers":[
        {
            "category":"Organizations",
            "subcategory":"Religious Organization",
            "type":"Services"
        }
    ],
    "sg:phone":"+1 843 745 0330",
    "sg:postcode":"29406",
    "sg:province":"SC",
    "sg:tags":[
        "church"
    ],
    "wof:name":"Bethel Pentecostal Holiness",
    "wof:placetype":"venue"
},
  "geometry": {"coordinates":[-80.017533,32.889359],"type":"Point"}
}