{
  "type": "Feature",
  "properties": {
    "iso:country":"US",
    "sg:address":"307 W Main St",
    "sg:city":"Spartanburg",
    "sg:classifiers":[
        {
            "category":"Shopping",
            "type":"Retail Goods"
        }
    ],
    "sg:phone":"+1 864 342 0805",
    "sg:postcode":"29301",
    "sg:province":"SC",
    "sg:tags":[
        "merchandise"
    ],
    "wof:name":"Jefco International",
    "wof:placetype":"venue"
},
  "geometry": {"coordinates":[-81.93887100000001,34.947035],"type":"Point"}
}