{
  "type": "Feature",
  "properties": {
    "iso:country":"US",
    "sg:address":"2260 Technical Pkwy",
    "sg:city":"North Charleston",
    "sg:classifiers":[
        {
            "category":"Home & Garden",
            "subcategory":"Building Materials",
            "type":"Retail Goods"
        }
    ],
    "sg:phone":"+1 843 884 8077",
    "sg:postcode":"29406",
    "sg:province":"SC",
    "sg:tags":[
        "door"
    ],
    "sg:website":"www.overheaddoor.com",
    "wof:name":"Overhead Door Corp",
    "wof:placetype":"venue"
},
  "geometry": {"coordinates":[-80.032376,32.911161],"type":"Point"}
}