{
  "type": "Feature",
  "properties": {
    "addr:full":"600 E Main St Seneca SC 29678",
    "addr:housenumber":"600",
    "addr:postcode":"29678",
    "addr:street":"E Main St",
    "iso:country":"US",
    "sg:address":"600 E Main St",
    "sg:city":"Seneca",
    "sg:classifiers":[
        {
            "category":"Autos & Motor Vehicles",
            "subcategory":"Automobile Sales",
            "type":"Retail Goods"
        }
    ],
    "sg:phone":"+1 864 882 6725",
    "sg:postcode":"29678",
    "sg:province":"SC",
    "sg:tags":[
        "car",
        "dealer"
    ],
    "wof:name":"Lipscombs Used Cars",
    "wof:placetype":"venue"
},
  "geometry": {"coordinates":[-82.945431,34.685614],"type":"Point"}
}