{
  "type": "Feature",
  "properties": {
    "iso:country":"US",
    "sg:address":"151 Dustin Dr",
    "sg:city":"Woodruff",
    "sg:classifiers":[
        {
            "category":"Real Estate",
            "subcategory":"Real Estate Operator",
            "type":"Services"
        }
    ],
    "sg:phone":"+1 864 433 9854",
    "sg:postcode":"29388",
    "sg:province":"SC",
    "sg:tags":[
        "mobile",
        "home",
        "site"
    ],
    "wof:name":"Moons Mobile Home Park",
    "wof:placetype":"venue"
},
  "geometry": {"coordinates":[-82.095827,34.872422],"type":"Point"}
}