{
  "type": "Feature",
  "properties": {
    "addr:full":"220 S Broad St Brevard SC 28712",
    "addr:housenumber":"220",
    "addr:postcode":"28712",
    "addr:street":"S Broad St",
    "iso:country":"US",
    "sg:address":"220 S Broad St",
    "sg:city":"Brevard",
    "sg:classifiers":[
        {
            "category":"Professional",
            "subcategory":"Business Services",
            "type":"Services"
        }
    ],
    "sg:phone":"+1 828 884 7889",
    "sg:postcode":"28712",
    "sg:province":"SC",
    "sg:tags":[
        "used",
        "merchandise"
    ],
    "sg:website":"www.jackeubanks.com",
    "wof:name":"Jack Eubanks Auctions",
    "wof:placetype":"venue"
},
  "geometry": {"coordinates":[-82.735629,35.231803],"type":"Point"}
}