{
  "type": "Feature",
  "properties": {
    "iso:country":"US",
    "sg:address":"111 W Main St",
    "sg:city":"Easley",
    "sg:classifiers":[
        {
            "category":"Shopping",
            "subcategory":"Hobbies, Toys, & Games",
            "type":"Retail Goods"
        }
    ],
    "sg:phone":"+1 864 855 0628",
    "sg:postcode":"29640",
    "sg:province":"SC",
    "sg:tags":[
        "craft",
        "supply"
    ],
    "wof:name":"Art Emporium",
    "wof:placetype":"venue"
},
  "geometry": {"coordinates":[-82.603708,34.83002],"type":"Point"}
}