{
  "type": "Feature",
  "properties": {
    "iso:country":"US",
    "sg:address":"129 River Song Rd",
    "sg:city":"Irmo",
    "sg:classifiers":[
        {
            "category":"Building & Trades",
            "subcategory":"Construction",
            "type":"Services"
        }
    ],
    "sg:phone":"+1 803 732 1508",
    "sg:postcode":"29063",
    "sg:province":"SC",
    "sg:tags":[
        "painter"
    ],
    "wof:name":"F Tait Painting Contractor",
    "wof:placetype":"venue"
},
  "geometry": {"coordinates":[-81.207067,34.102781],"type":"Point"}
}