{
  "type": "Feature",
  "properties": {
    "addr:full":"6325 Dorchester Rd North Charleston SC 29418",
    "addr:housenumber":"6325",
    "addr:postcode":"29418",
    "addr:street":"Dorchester Rd",
    "iso:country":"US",
    "sg:address":"6325 Dorchester Rd",
    "sg:city":"North Charleston",
    "sg:classifiers":[
        {
            "category":"Education",
            "subcategory":"Library",
            "type":"Public Place"
        }
    ],
    "sg:phone":"+1 843 552 6466",
    "sg:postcode":"29418",
    "sg:province":"SC",
    "wof:name":"Dorchester Road Library",
    "wof:placetype":"venue"
},
  "geometry": {"coordinates":[-80.058871,32.874511],"type":"Point"}
}