{
  "type": "Feature",
  "properties": {
    "iso:country":"US",
    "sg:address":"2512 River Rd",
    "sg:city":"Piedmont",
    "sg:classifiers":[
        {
            "category":"Building & Trades",
            "subcategory":"Equipment Rental",
            "type":"Services"
        }
    ],
    "sg:phone":"+1 864 269 3600",
    "sg:postcode":"29673",
    "sg:province":"SC",
    "sg:tags":[
        "contractor"
    ],
    "wof:name":"Jones-Calhoun Bobcat & Equip",
    "wof:placetype":"venue"
},
  "geometry": {"coordinates":[-82.475044,34.762541],"type":"Point"}
}