{
  "type": "Feature",
  "properties": {
    "iso:country":"US",
    "sg:address":"400 State St",
    "sg:city":"West Columbia",
    "sg:classifiers":[
        {
            "category":"Organizations",
            "subcategory":"Religious Organization",
            "type":"Services"
        }
    ],
    "sg:phone":"+1 803 794 1732",
    "sg:postcode":"29169",
    "sg:province":"SC",
    "wof:name":"Corazon De Jesus Heartjesus",
    "wof:placetype":"venue"
},
  "geometry": {"coordinates":[-81.05617599999999,33.990165],"type":"Point"}
}