{
  "type": "Feature",
  "properties": {
    "iso:country":"US",
    "sg:address":"2415 Fork Shoals Rd",
    "sg:city":"Piedmont",
    "sg:classifiers":[
        {
            "category":"Social Services",
            "subcategory":"Job Training",
            "type":"Services"
        }
    ],
    "sg:phone":"+1 864 299 0716",
    "sg:postcode":"29673",
    "sg:province":"SC",
    "sg:tags":[
        "rehabilitation"
    ],
    "wof:name":"Gregory's Community Care",
    "wof:placetype":"venue"
},
  "geometry": {"coordinates":[-82.338917,34.719502],"type":"Point"}
}