{
  "type": "Feature",
  "properties": {
    "addr:full":"250 Springtree Dr Columbia SC 29223",
    "addr:housenumber":"250",
    "addr:postcode":"29223",
    "addr:street":"Springtree Dr",
    "iso:country":"US",
    "sg:address":"250 Springtree Dr",
    "sg:city":"Columbia",
    "sg:classifiers":[
        {
            "category":"Real Estate",
            "subcategory":"Real Estate Operator",
            "type":"Services"
        }
    ],
    "sg:phone":"+1 803 741 0413",
    "sg:postcode":"29223",
    "sg:province":"SC",
    "sg:tags":[
        "apartment"
    ],
    "wof:name":"Springtree Apartments",
    "wof:placetype":"venue"
},
  "geometry": {"coordinates":[-80.963129,34.077144],"type":"Point"}
}