{
  "type": "Feature",
  "properties": {
    "iso:country":"US",
    "sg:address":"1504 S Murray Ave",
    "sg:city":"Anderson",
    "sg:classifiers":[
        {
            "category":"Personal",
            "subcategory":"Beauty Salon",
            "type":"Services"
        }
    ],
    "sg:phone":"+1 864 224 1570",
    "sg:postcode":"29624",
    "sg:province":"SC",
    "wof:name":"Ginny's Beauty Salon",
    "wof:placetype":"venue"
},
  "geometry": {"coordinates":[-82.654673,34.472696],"type":"Point"}
}