{
  "type": "Feature",
  "properties": {
    "iso:country":"US",
    "sg:address":"7 N Laurens St",
    "sg:city":"Greenville",
    "sg:classifiers":[
        {
            "category":"Real Estate",
            "subcategory":"Architect",
            "type":"Services"
        }
    ],
    "sg:phone":"+1 864 527 4700",
    "sg:postcode":"29601",
    "sg:province":"SC",
    "wof:name":"Betsch Associates",
    "wof:placetype":"venue"
},
  "geometry": {"coordinates":[-82.399649,34.851782],"type":"Point"}
}