{
  "type": "Feature",
  "properties": {
    "addr:full":"1616 Woodruff Rd Greenville SC 29607",
    "addr:housenumber":"1616",
    "addr:postcode":"29607",
    "addr:street":"Woodruff Rd",
    "iso:country":"US",
    "sg:address":"1616 Woodruff Rd",
    "sg:city":"Greenville",
    "sg:classifiers":[
        {
            "category":"Personal",
            "subcategory":"Beauty Salon",
            "type":"Services"
        }
    ],
    "sg:phone":"+1 864 331 3333",
    "sg:postcode":"29607",
    "sg:province":"SC",
    "sg:website":"www.wisteriasalonspa.com",
    "wof:name":"Wisteria Salon Spa",
    "wof:placetype":"venue"
},
  "geometry": {"coordinates":[-82.26824000000001,34.819896],"type":"Point"}
}