{
  "type": "Feature",
  "properties": {
    "iso:country":"US",
    "sg:address":"201 W McBee Ave",
    "sg:city":"Greenville",
    "sg:classifiers":[
        {
            "category":"Banks & Credit Unions",
            "subcategory":"Investment Brokerage",
            "type":"Services"
        }
    ],
    "sg:phone":"+1 864 242 6438",
    "sg:postcode":"29601",
    "sg:province":"SC",
    "wof:name":"Hughes Investments Piedmont",
    "wof:placetype":"venue"
},
  "geometry": {"coordinates":[-82.402252,34.850403],"type":"Point"}
}