{
  "type": "Feature",
  "properties": {
    "iso:country":"US",
    "sg:address":"909 Leesburg Rd",
    "sg:city":"Columbia",
    "sg:classifiers":[
        {
            "category":"Wholesale",
            "subcategory":"Auto Parts",
            "type":"Manufacturing & Wholesale Goods"
        }
    ],
    "sg:phone":"+1 803 783 7199",
    "sg:postcode":"29209",
    "sg:province":"SC",
    "sg:tags":[
        "supply"
    ],
    "wof:name":"Carquest Auto Parts",
    "wof:placetype":"venue"
},
  "geometry": {"coordinates":[-80.948358,33.975909],"type":"Point"}
}