{
  "type": "Feature",
  "properties": {
    "iso:country":"US",
    "sg:address":"6136 Bush River Rd",
    "sg:city":"Columbia",
    "sg:classifiers":[
        {
            "category":"Banks & Credit Unions",
            "subcategory":"Bank",
            "type":"Services"
        }
    ],
    "sg:phone":"+1 803 407 5276",
    "sg:postcode":"29212",
    "sg:province":"SC",
    "sg:tags":[
        "loan",
        "real estate"
    ],
    "wof:name":"Economic Solutions",
    "wof:placetype":"venue"
},
  "geometry": {"coordinates":[-81.21672100000001,34.062591],"type":"Point"}
}