{
  "type": "Feature",
  "properties": {
    "iso:country":"US",
    "sg:address":"835 S Main St",
    "sg:city":"Summerville",
    "sg:classifiers":[
        {
            "category":"Education",
            "subcategory":"School",
            "type":"Public Place"
        }
    ],
    "sg:phone":"+1 843 873 2372",
    "sg:postcode":"29483",
    "sg:province":"SC",
    "sg:website":"www.dorchester2.k12.sc.us",
    "wof:name":"Summerville Elementary School",
    "wof:placetype":"venue"
},
  "geometry": {"coordinates":[-80.18241,33.011004],"type":"Point"}
}