{
  "type": "Feature",
  "properties": {
    "iso:country":"US",
    "sg:address":"206 E McIntyre St",
    "sg:city":"Mullins",
    "sg:classifiers":[
        {
            "category":"Building & Trades",
            "subcategory":"Construction",
            "type":"Services"
        }
    ],
    "sg:phone":"+1 843 464 8770",
    "sg:postcode":"29574",
    "sg:province":"SC",
    "sg:tags":[
        "contractor"
    ],
    "wof:name":"Newton Builders",
    "wof:placetype":"venue"
},
  "geometry": {"coordinates":[-79.24331599999999,34.201311],"type":"Point"}
}