{
  "type": "Feature",
  "properties": {
    "iso:country":"US",
    "sg:address":"103 Old Dominion Dr",
    "sg:city":"Duncan",
    "sg:classifiers":[
        {
            "category":"Manufacturing",
            "subcategory":"Glass & Minerals",
            "type":"Manufacturing & Wholesale Goods"
        }
    ],
    "sg:phone":"+1 864 801 4020",
    "sg:postcode":"29334",
    "sg:province":"SC",
    "sg:tags":[
        "ready",
        "concrete",
        "mfg"
    ],
    "wof:name":"Piedmont Concrete Products",
    "wof:placetype":"venue"
},
  "geometry": {"coordinates":[-82.14819,34.890214],"type":"Point"}
}