{
  "type": "Feature",
  "properties": {
    "addr:full":"304 Rawl Rd Lexington SC 29072",
    "addr:housenumber":"304",
    "addr:postcode":"29072",
    "addr:street":"Rawl Rd",
    "iso:country":"US",
    "sg:address":"304 Rawl Rd",
    "sg:city":"Lexington",
    "sg:classifiers":[
        {
            "category":"Real Estate",
            "subcategory":"Real Estate Agent",
            "type":"Services"
        }
    ],
    "sg:phone":"+1 803 957 8200",
    "sg:postcode":"29072",
    "sg:province":"SC",
    "sg:tags":[
        "appraiser"
    ],
    "wof:name":"Sistare Appraisal Svc",
    "wof:placetype":"venue"
},
  "geometry": {"coordinates":[-81.27430099999999,33.962479],"type":"Point"}
}