{
  "type": "Feature",
  "properties": {
    "iso:country":"US",
    "sg:address":"113 Misty Oak Rd",
    "sg:city":"Columbia",
    "sg:classifiers":[
        {
            "category":"Farming",
            "subcategory":"Farm & Veterinary Services",
            "type":"Manufacturing & Wholesale Goods"
        }
    ],
    "sg:phone":"+1 803 466 9093",
    "sg:postcode":"29223",
    "sg:province":"SC",
    "sg:tags":[
        "grain",
        "cleaning"
    ],
    "wof:name":"Lady Y 2K Hair Styles & Dsgns",
    "wof:placetype":"venue"
},
  "geometry": {"coordinates":[-80.943841,34.061194],"type":"Point"}
}