{
  "type": "Feature",
  "properties": {
    "iso:country":"US",
    "sg:address":"1961 Mc Crays Mill Rd",
    "sg:city":"Sumter",
    "sg:classifiers":[
        {
            "category":"Restaurant",
            "type":"Food & Drink"
        }
    ],
    "sg:phone":"+1 803 773 2206",
    "sg:postcode":"29150",
    "sg:province":"SC",
    "sg:tags":[
        "barbecue",
        "eating"
    ],
    "wof:name":"Ward's Bar B Que",
    "wof:placetype":"venue"
},
  "geometry": {"coordinates":[-80.379119,33.904334],"type":"Point"}
}