{
  "type": "Feature",
  "properties": {
    "iso:country":"US",
    "sg:address":"2670 David H McLeod Blvd",
    "sg:city":"Florence",
    "sg:classifiers":[
        {
            "category":"Building & Trades",
            "subcategory":"Equipment Rental",
            "type":"Services"
        }
    ],
    "sg:phone":"+1 843 679 9499",
    "sg:postcode":"29501",
    "sg:province":"SC",
    "sg:tags":[
        "appliance"
    ],
    "wof:name":"Aaron's Plus",
    "wof:placetype":"venue"
},
  "geometry": {"coordinates":[-79.828036,34.188461],"type":"Point"}
}