{
  "type": "Feature",
  "properties": {
    "iso:country":"US",
    "sg:address":"1273 Wrenwood Dr",
    "sg:city":"Lancaster",
    "sg:classifiers":[
        {
            "category":"Building & Trades",
            "subcategory":"Construction",
            "type":"Services"
        }
    ],
    "sg:phone":"+1 803 283 8090",
    "sg:postcode":"29720",
    "sg:province":"SC",
    "sg:tags":[
        "home"
    ],
    "wof:name":"Baker Roger Home Repr & Rmdlg",
    "wof:placetype":"venue"
},
  "geometry": {"coordinates":[-80.76042,34.644631],"type":"Point"}
}