{
  "type": "Feature",
  "properties": {
    "iso:country":"US",
    "sg:address":"200 Lee Ave",
    "sg:city":"Hampton",
    "sg:classifiers":[
        {
            "category":"Manufacturing",
            "subcategory":"Printing",
            "type":"Manufacturing & Wholesale Goods"
        }
    ],
    "sg:phone":"+1 803 943 4645",
    "sg:postcode":"29924",
    "sg:province":"SC",
    "sg:tags":[
        "newspaper"
    ],
    "wof:name":"Hampton County Guardian",
    "wof:placetype":"venue"
},
  "geometry": {"coordinates":[-81.10767800000001,32.867796],"type":"Point"}
}