{
  "type": "Feature",
  "properties": {
    "iso:country":"US",
    "sg:address":"455 Milford Church Rd",
    "sg:city":"Taylors",
    "sg:classifiers":[
        {
            "category":"Real Estate",
            "subcategory":"Real Estate Operator",
            "type":"Services"
        }
    ],
    "sg:phone":"+1 864 895 2807",
    "sg:postcode":"29687",
    "sg:province":"SC",
    "sg:tags":[
        "mobile",
        "home",
        "site"
    ],
    "wof:name":"Milford Manor",
    "wof:placetype":"venue"
},
  "geometry": {"coordinates":[-82.31773099999999,34.979992],"type":"Point"}
}