{
  "type": "Feature",
  "properties": {
    "iso:country":"US",
    "sg:address":"129 Hornbuckle Dr",
    "sg:city":"Easley",
    "sg:classifiers":[
        {
            "category":"Shopping",
            "subcategory":"Pharmacy",
            "type":"Retail Goods"
        }
    ],
    "sg:phone":"+1 864 295 4827",
    "sg:postcode":"29642",
    "sg:province":"SC",
    "sg:tags":[
        "drug",
        "store"
    ],
    "wof:name":"Alexander Drug",
    "wof:placetype":"venue"
},
  "geometry": {"coordinates":[-82.51578499999999,34.771772],"type":"Point"}
}