{
  "type": "Feature",
  "properties": {
    "iso:country":"US",
    "sg:address":"1470 Ben Sawyer Blvd",
    "sg:city":"Mount Pleasant",
    "sg:classifiers":[
        {
            "category":"Building & Trades",
            "subcategory":"Construction",
            "type":"Services"
        }
    ],
    "sg:phone":"+1 843 856 5150",
    "sg:postcode":"29464",
    "sg:province":"SC",
    "sg:tags":[
        "industrial",
        "nonresidential"
    ],
    "wof:name":"Webb Clements Inc",
    "wof:placetype":"venue"
},
  "geometry": {"coordinates":[-79.85177899999999,32.789214],"type":"Point"}
}