{
  "type": "Feature",
  "properties": {
    "iso:country":"US",
    "sg:address":"4411 Devine St",
    "sg:city":"Columbia",
    "sg:classifiers":[
        {
            "category":"Restaurant",
            "type":"Food & Drink"
        }
    ],
    "sg:phone":"+1 803 782 9547",
    "sg:postcode":"29205",
    "sg:province":"SC",
    "sg:tags":[
        "barbeque"
    ],
    "wof:name":"Maurice's Gourmet Barbeque",
    "wof:placetype":"venue"
},
  "geometry": {"coordinates":[-80.97689800000001,33.991798],"type":"Point"}
}