{
  "type": "Feature",
  "properties": {
    "addr:full":"300 E Windsor St Westminster SC 29693",
    "addr:housenumber":"300",
    "addr:postcode":"29693",
    "addr:street":"E Windsor St",
    "iso:country":"US",
    "sg:address":"300 E Windsor St",
    "sg:city":"Westminster",
    "sg:classifiers":[
        {
            "category":"Retail",
            "subcategory":"Auto Repair",
            "type":"Services"
        }
    ],
    "sg:phone":"+1 864 647 9875",
    "sg:postcode":"29693",
    "sg:province":"SC",
    "sg:tags":[
        "repairing",
        "automobile"
    ],
    "wof:name":"M D Automotive",
    "wof:placetype":"venue"
},
  "geometry": {"coordinates":[-83.095488,34.664063],"type":"Point"}
}