{
  "type": "Feature",
  "properties": {
    "addr:full":"291 S Pine St Spartanburg SC 29302",
    "addr:housenumber":"291",
    "addr:postcode":"29302",
    "addr:street":"S Pine St",
    "iso:country":"US",
    "sg:address":"291 S Pine St",
    "sg:city":"Spartanburg",
    "sg:classifiers":[
        {
            "category":"Banks & Credit Unions",
            "subcategory":"Bank",
            "type":"Services"
        }
    ],
    "sg:phone":"+1 864 596 1468",
    "sg:postcode":"29302",
    "sg:province":"SC",
    "sg:tags":[
        "loan",
        "real estate"
    ],
    "sg:website":"www.fhhlc.com",
    "wof:name":"First Horizon Home Loan Corp",
    "wof:placetype":"venue"
},
  "geometry": {"coordinates":[-81.91652499999999,34.94873],"type":"Point"}
}