{
  "type": "Feature",
  "properties": {
    "iso:country":"US",
    "sg:address":"6 Bush River Ct",
    "sg:city":"Columbia",
    "sg:classifiers":[
        {
            "category":"Health Services",
            "subcategory":"Health Practitioner",
            "type":"Services"
        }
    ],
    "sg:phone":"+1 803 772 2231",
    "sg:postcode":"29210",
    "sg:province":"SC",
    "sg:tags":[
        "nurse",
        "registry"
    ],
    "wof:name":"Caring Inc",
    "wof:placetype":"venue"
},
  "geometry": {"coordinates":[-81.143382,34.042456],"type":"Point"}
}