{
  "type": "Feature",
  "properties": {
    "iso:country":"US",
    "sg:address":"2398 Cannons Campground Rd",
    "sg:city":"Spartanburg",
    "sg:classifiers":[
        {
            "category":"Manufacturing",
            "subcategory":"Tools & Machinery",
            "type":"Manufacturing & Wholesale Goods"
        }
    ],
    "sg:phone":"+1 864 579 2900",
    "sg:postcode":"29307",
    "sg:province":"SC",
    "sg:tags":[
        "textile",
        "parts"
    ],
    "sg:website":"www.consultexcorp.com",
    "wof:name":"Consultex Corp",
    "wof:placetype":"venue"
},
  "geometry": {"coordinates":[-81.87882999999999,34.992497],"type":"Point"}
}