{
  "type": "Feature",
  "properties": {
    "addr:full":"183 Burnett Rd Pauline SC 29374",
    "addr:housenumber":"183",
    "addr:postcode":"29374",
    "addr:street":"Burnett Rd",
    "iso:country":"US",
    "sg:address":"183 Burnett Rd",
    "sg:city":"Pauline",
    "sg:classifiers":[
        {
            "category":"Building & Trades",
            "subcategory":"Construction",
            "type":"Services"
        }
    ],
    "sg:phone":"+1 864 595 0960",
    "sg:postcode":"29374",
    "sg:province":"SC",
    "sg:tags":[
        "hanging",
        "contractor"
    ],
    "wof:name":"David Knox Painting Co",
    "wof:placetype":"venue"
},
  "geometry": {"coordinates":[-81.898715,34.79049],"type":"Point"}
}