{
  "type": "Feature",
  "properties": {
    "iso:country":"US",
    "sg:address":"143 E Pine Logging Rd",
    "sg:city":"Aiken",
    "sg:classifiers":[
        {
            "category":"Retail",
            "subcategory":"Auto Repair",
            "type":"Services"
        }
    ],
    "sg:phone":"+1 803 643 8863",
    "sg:postcode":"29803",
    "sg:province":"SC",
    "sg:tags":[
        "repairing",
        "automobile"
    ],
    "wof:name":"Precision Tune Auto Care",
    "wof:placetype":"venue"
},
  "geometry": {"coordinates":[-81.718328,33.524344],"type":"Point"}
}