{
  "type": "Feature",
  "properties": {
    "iso:country":"US",
    "sg:address":"1290 Peden Bridge Rd",
    "sg:city":"Chester",
    "sg:classifiers":[
        {
            "category":"Farming",
            "subcategory":"Farm",
            "type":"Manufacturing & Wholesale Goods"
        }
    ],
    "sg:phone":"+1 803 581 3769",
    "sg:postcode":"29706",
    "sg:province":"SC",
    "wof:name":"Chester Farms LLC",
    "wof:placetype":"venue"
},
  "geometry": {"coordinates":[-81.13088399999999,34.682621],"type":"Point"}
}