{
  "type": "Feature",
  "properties": {
    "iso:country":"US",
    "sg:address":"208 E Seven Pines St",
    "sg:city":"Hartsville",
    "sg:classifiers":[
        {
            "category":"Education",
            "subcategory":"School",
            "type":"Public Place"
        }
    ],
    "sg:phone":"+1 843 383 4029",
    "sg:postcode":"29550",
    "sg:province":"SC",
    "wof:name":"St John Head Start Ctr",
    "wof:placetype":"venue"
},
  "geometry": {"coordinates":[-80.065474,34.257565],"type":"Point"}
}