{
  "type": "Feature",
  "properties": {
    "addr:full":"49 Mill St Inman SC 29349",
    "addr:housenumber":"49",
    "addr:postcode":"29349",
    "addr:street":"Mill St",
    "iso:country":"US",
    "sg:address":"49 Mill St",
    "sg:city":"Inman",
    "sg:classifiers":[
        {
            "category":"Personal",
            "subcategory":"Beauty Salon",
            "type":"Services"
        }
    ],
    "sg:phone":"+1 864 472 9935",
    "sg:postcode":"29349",
    "sg:province":"SC",
    "wof:name":"Lisa's Styling Salon",
    "wof:placetype":"venue"
},
  "geometry": {"coordinates":[-82.094236,35.045263],"type":"Point"}
}