{
  "type": "Feature",
  "properties": {
    "addr:full":"901 Pinecroft Dr Taylors SC 29687",
    "addr:housenumber":"901",
    "addr:postcode":"29687",
    "addr:street":"Pinecroft Dr",
    "iso:country":"US",
    "sg:address":"901 Pinecroft Dr",
    "sg:city":"Taylors",
    "sg:classifiers":[
        {
            "category":"Building & Trades",
            "subcategory":"Construction",
            "type":"Services"
        }
    ],
    "sg:phone":"+1 864 449 4986",
    "sg:postcode":"29687",
    "sg:province":"SC",
    "sg:tags":[
        "house"
    ],
    "wof:name":"Abbott Builders",
    "wof:placetype":"venue"
},
  "geometry": {"coordinates":[-82.314753,34.92955],"type":"Point"}
}