{
  "type": "Feature",
  "properties": {
    "iso:country":"US",
    "sg:address":"104 Berkshire Ct",
    "sg:city":"Goose Creek",
    "sg:classifiers":[
        {
            "category":"Home & Garden",
            "subcategory":"Carpets & Floor Coverings",
            "type":"Retail Goods"
        }
    ],
    "sg:phone":"+1 843 797 0640",
    "sg:postcode":"29445",
    "sg:province":"SC",
    "wof:name":"Naples Floor Coverings",
    "wof:placetype":"venue"
},
  "geometry": {"coordinates":[-80.049638,33.020475],"type":"Point"}
}