{
  "type": "Feature",
  "properties": {
    "iso:country":"US",
    "sg:address":"6 Horton Dr",
    "sg:city":"Abbeville",
    "sg:classifiers":[
        {
            "category":"Social Services",
            "subcategory":"Child Care",
            "type":"Services"
        }
    ],
    "sg:phone":"+1 864 459 4343",
    "sg:postcode":"29620",
    "sg:province":"SC",
    "wof:name":"In His Hands Child Care Too",
    "wof:placetype":"venue"
},
  "geometry": {"coordinates":[-82.392003,34.157818],"type":"Point"}
}