{
  "type": "Feature",
  "properties": {
    "addr:full":"1101 E Main St Westminster SC 29693",
    "addr:housenumber":"1101",
    "addr:postcode":"29693",
    "addr:street":"E Main St",
    "iso:country":"US",
    "sg:address":"1101 E Main St",
    "sg:city":"Westminster",
    "sg:classifiers":[
        {
            "category":"Banks & Credit Unions",
            "subcategory":"Bank",
            "type":"Services"
        }
    ],
    "sg:phone":"+1 864 647 9554",
    "sg:postcode":"29693",
    "sg:province":"SC",
    "sg:tags":[
        "state",
        "commercial"
    ],
    "wof:name":"Community First Bank",
    "wof:placetype":"venue"
},
  "geometry": {"coordinates":[-83.082739,34.658687],"type":"Point"}
}