{
  "type": "Feature",
  "properties": {
    "iso:country":"US",
    "sg:address":"97 Forest Lake Dr",
    "sg:city":"Simpsonville",
    "sg:classifiers":[
        {
            "category":"Professional",
            "subcategory":"Management & Consulting",
            "type":"Services"
        }
    ],
    "sg:phone":"+1 864 675 9290",
    "sg:postcode":"29681",
    "sg:province":"SC",
    "sg:tags":[
        "consultant"
    ],
    "wof:name":"Jane Crawford Assoc LTD",
    "wof:placetype":"venue"
},
  "geometry": {"coordinates":[-82.26108000000001,34.817378],"type":"Point"}
}