{
  "type": "Feature",
  "properties": {
    "iso:country":"US",
    "sg:address":"708 Valhalla Dr",
    "sg:city":"Columbia",
    "sg:classifiers":[
        {
            "category":"Retail",
            "subcategory":"Repair Shop",
            "type":"Services"
        }
    ],
    "sg:phone":"+1 803 865 0715",
    "sg:postcode":"29229",
    "sg:province":"SC",
    "sg:tags":[
        "appliance"
    ],
    "wof:name":"Express Appliance & Repair",
    "wof:placetype":"venue"
},
  "geometry": {"coordinates":[-80.864362,34.113392],"type":"Point"}
}