{
  "type": "Feature",
  "properties": {
    "iso:country":"US",
    "sg:address":"1013 Old Hwy 52",
    "sg:city":"Moncks Corner",
    "sg:classifiers":[
        {
            "category":"Retail",
            "subcategory":"Self-service Laundry",
            "type":"Services"
        }
    ],
    "sg:phone":"+1 843 899 1316",
    "sg:postcode":"29461",
    "sg:province":"SC",
    "wof:name":"Laundry Center",
    "wof:placetype":"venue"
},
  "geometry": {"coordinates":[-80.00010899999999,33.186712],"type":"Point"}
}