{
  "type": "Feature",
  "properties": {
    "iso:country":"US",
    "sg:address":"576 Jerusalem Branch Rd",
    "sg:city":"Wagener",
    "sg:classifiers":[
        {
            "category":"Organizations",
            "subcategory":"Religious Organization",
            "type":"Services"
        }
    ],
    "sg:phone":"+1 803 564 3419",
    "sg:postcode":"29137",
    "sg:province":"SC",
    "sg:tags":[
        "church"
    ],
    "wof:name":"Jerusalem Branch Baptist Chr",
    "wof:placetype":"venue"
},
  "geometry": {"coordinates":[-81.333899,33.591952],"type":"Point"}
}