{
  "type": "Feature",
  "properties": {
    "addr:full":"1477 Lynwood Dr Lancaster SC 29720",
    "addr:housenumber":"1477",
    "addr:postcode":"29720",
    "addr:street":"Lynwood Dr",
    "iso:country":"US",
    "sg:address":"1477 Lynwood Dr",
    "sg:city":"Lancaster",
    "sg:classifiers":[
        {
            "category":"Personal",
            "subcategory":"Beauty Salon",
            "type":"Services"
        }
    ],
    "sg:phone":"+1 803 286 5209",
    "sg:postcode":"29720",
    "sg:province":"SC",
    "wof:name":"Strictly Business Barber",
    "wof:placetype":"venue"
},
  "geometry": {"coordinates":[-80.761461,34.675278],"type":"Point"}
}