{
  "type": "Feature",
  "properties": {
    "iso:country":"US",
    "sg:address":"273 State Hwy 61",
    "sg:city":"Ridgeville",
    "sg:classifiers":[
        {
            "category":"Education",
            "subcategory":"School",
            "type":"Public Place"
        }
    ],
    "sg:phone":"+1 843 873 7372",
    "sg:postcode":"29472",
    "sg:province":"SC",
    "wof:name":"Givhans Alternative",
    "wof:placetype":"venue"
},
  "geometry": {"coordinates":[-80.290983,32.964578],"type":"Point"}
}