{
  "type": "Feature",
  "properties": {
    "addr:full":"1040 E Lynches River Rd Lamar SC 29069",
    "addr:housenumber":"1040",
    "addr:postcode":"29069",
    "addr:street":"E Lynches River Rd",
    "iso:country":"US",
    "sg:address":"1040 E Lynches River Rd",
    "sg:city":"Lamar",
    "sg:classifiers":[
        {
            "category":"Farming",
            "subcategory":"Farm",
            "type":"Manufacturing & Wholesale Goods"
        }
    ],
    "sg:phone":"+1 843 326 5643",
    "sg:postcode":"29069",
    "sg:province":"SC",
    "sg:tags":[
        "crop",
        "general"
    ],
    "wof:name":"Robert & Kelly Windham Farm",
    "wof:placetype":"venue"
},
  "geometry": {"coordinates":[-80.08107699999999,34.114675],"type":"Point"}
}