{
  "type": "Feature",
  "properties": {
    "iso:country":"US",
    "sg:address":"465 E Main St",
    "sg:city":"Easley",
    "sg:classifiers":[
        {
            "category":"Bars & Pubs",
            "type":"Food & Drink"
        }
    ],
    "sg:phone":"+1 864 855 7002",
    "sg:postcode":"29640",
    "sg:province":"SC",
    "sg:tags":[
        "drinking"
    ],
    "wof:name":"Spot The",
    "wof:placetype":"venue"
},
  "geometry": {"coordinates":[-82.593088,34.831732],"type":"Point"}
}