{
  "type": "Feature",
  "properties": {
    "addr:full":"201 Magnolia St Spartanburg SC 29306",
    "addr:housenumber":"201",
    "addr:postcode":"29306",
    "addr:street":"Magnolia St",
    "iso:country":"US",
    "sg:address":"201 Magnolia St",
    "sg:city":"Spartanburg",
    "sg:classifiers":[
        {
            "category":"Government",
            "subcategory":"Office",
            "type":"Public Place"
        }
    ],
    "sg:phone":"+1 864 582 6422",
    "sg:postcode":"29306",
    "sg:province":"SC",
    "wof:name":"CONGRESSMAN Bob Inglis",
    "wof:placetype":"venue"
},
  "geometry": {"coordinates":[-81.934983,34.952456],"type":"Point"}
}