{
  "type": "Feature",
  "properties": {
    "addr:full":"2150 Dutch Fork Rd Chapin SC 29036",
    "addr:housenumber":"2150",
    "addr:postcode":"29036",
    "addr:street":"Dutch Fork Rd",
    "iso:country":"US",
    "sg:address":"2150 Dutch Fork Rd",
    "sg:city":"Chapin",
    "sg:classifiers":[
        {
            "category":"Recreation",
            "type":"Entertainment"
        }
    ],
    "sg:phone":"+1 803 798 2266",
    "sg:postcode":"29036",
    "sg:province":"SC",
    "sg:tags":[
        "boxing",
        "instruction"
    ],
    "wof:name":"White Rock Boxing",
    "wof:placetype":"venue"
},
  "geometry": {"coordinates":[-81.275752,34.144027],"type":"Point"}
}