{
  "type": "Feature",
  "properties": {
    "iso:country":"US",
    "sg:address":"711 Barfield Rd",
    "sg:city":"Elgin",
    "sg:classifiers":[
        {
            "category":"Building & Trades",
            "subcategory":"Construction",
            "type":"Services"
        }
    ],
    "sg:phone":"+1 803 438 5758",
    "sg:postcode":"29045",
    "sg:province":"SC",
    "sg:tags":[
        "contractor"
    ],
    "wof:name":"Wade H Brassell II",
    "wof:placetype":"venue"
},
  "geometry": {"coordinates":[-80.818939,34.229201],"type":"Point"}
}