{
  "type": "Feature",
  "properties": {
    "addr:full":"94 Main St Hilton Head Isle SC 29926",
    "addr:housenumber":"94",
    "addr:postcode":"29926",
    "addr:street":"Main St",
    "iso:country":"US",
    "sg:address":"94 Main St",
    "sg:city":"Hilton Head Isle",
    "sg:classifiers":[
        {
            "category":"Professional",
            "subcategory":"Lawyer & Legal Services",
            "type":"Services"
        }
    ],
    "sg:phone":"+1 843 842 2202",
    "sg:postcode":"29926",
    "sg:province":"SC",
    "sg:tags":[
        "attorney"
    ],
    "sg:website":"www.peterwolfattorney.com",
    "wof:name":"Peter L Wolf & Assoc",
    "wof:placetype":"venue"
},
  "geometry": {"coordinates":[-80.721172,32.21689],"type":"Point"}
}