{
  "type": "Feature",
  "properties": {
    "addr:full":"10 Hayne St Charleston SC 29401",
    "addr:housenumber":"10",
    "addr:postcode":"29401",
    "addr:street":"Hayne St",
    "iso:country":"US",
    "sg:address":"10 Hayne St",
    "sg:city":"Charleston",
    "sg:classifiers":[
        {
            "category":"Restaurant",
            "type":"Food & Drink"
        }
    ],
    "sg:menulink":"http://www.allmenus.com/sc/charleston-north-charleston/268039-hanks-seafood-restaurant/menu/",
    "sg:phone":"+1 843 723 3474",
    "sg:postcode":"29401",
    "sg:province":"SC",
    "sg:tags":[
        "seafood",
        "american"
    ],
    "wof:name":"Hank's Seafood Restaurant",
    "wof:placetype":"venue"
},
  "geometry": {"coordinates":[-79.929945,32.781885],"type":"Point"}
}