{
  "type": "Feature",
  "properties": {
    "addr:full":"185 Wire Rd Andrews SC 29532",
    "addr:housenumber":"185",
    "addr:postcode":"29532",
    "addr:street":"Wire Rd",
    "iso:country":"US",
    "sg:address":"185 Wire Rd",
    "sg:city":"Andrews",
    "sg:classifiers":[
        {
            "category":"Manufacturing",
            "subcategory":"Metals",
            "type":"Manufacturing & Wholesale Goods"
        }
    ],
    "sg:phone":"+1 843 264 5275",
    "sg:postcode":"29532",
    "sg:province":"SC",
    "sg:tags":[
        "product",
        "wire",
        "mfg"
    ],
    "wof:name":"Andrews Wire Company",
    "wof:placetype":"venue"
},
  "geometry": {"coordinates":[-79.895974,34.323801],"type":"Point"}
}