{
  "type": "Feature",
  "properties": {
    "iso:country":"US",
    "sg:address":"1214 Old Ebenezer Rd",
    "sg:city":"Latta",
    "sg:classifiers":[
        {
            "category":"Building & Trades",
            "subcategory":"Landscaping Services",
            "type":"Services"
        }
    ],
    "sg:phone":"+1 843 752 4000",
    "sg:postcode":"29565",
    "sg:province":"SC",
    "sg:tags":[
        "tree",
        "landscape"
    ],
    "wof:name":"County Line Tree Srvice",
    "wof:placetype":"venue"
},
  "geometry": {"coordinates":[-79.42123100000001,34.311882],"type":"Point"}
}