{
  "type": "Feature",
  "properties": {
    "iso:country":"US",
    "sg:address":"200 Ridge Medical Plaza Rd",
    "sg:city":"Edgefield",
    "sg:classifiers":[
        {
            "category":"Health Services",
            "subcategory":"Doctor",
            "type":"Services"
        }
    ],
    "sg:phone":"+1 803 637 3146",
    "sg:postcode":"29824",
    "sg:province":"SC",
    "sg:tags":[
        "physician",
        "surgeon"
    ],
    "wof:name":"Edgefield Medical Clinic",
    "wof:placetype":"venue"
},
  "geometry": {"coordinates":[-81.930392,33.77861],"type":"Point"}
}