{
  "type": "Feature",
  "properties": {
    "iso:country":"US",
    "sg:address":"2621 Kelleytown Rd",
    "sg:city":"Hartsville",
    "sg:classifiers":[
        {
            "category":"Wholesale",
            "subcategory":"Motor Vehicles",
            "type":"Manufacturing & Wholesale Goods"
        }
    ],
    "sg:phone":"+1 843 332 3379",
    "sg:postcode":"29550",
    "sg:province":"SC",
    "sg:tags":[
        "automobile",
        "used"
    ],
    "wof:name":"Melton Motor Company Inc",
    "wof:placetype":"venue"
},
  "geometry": {"coordinates":[-80.143828,34.349603],"type":"Point"}
}