{
  "type": "Feature",
  "properties": {
    "addr:full":"1117 48th Ave N Myrtle Beach SC 29577",
    "addr:housenumber":"1117",
    "addr:postcode":"29577",
    "addr:street":"48Th Ave N",
    "iso:country":"US",
    "sg:address":"1117 48th Ave N",
    "sg:city":"Myrtle Beach",
    "sg:classifiers":[
        {
            "category":"Professional",
            "subcategory":"Lawyer & Legal Services",
            "type":"Services"
        }
    ],
    "sg:phone":"+1 843 497 7000",
    "sg:postcode":"29577",
    "sg:province":"SC",
    "sg:tags":[
        "attorney"
    ],
    "wof:name":"Cox & Assoc",
    "wof:placetype":"venue"
},
  "geometry": {"coordinates":[-78.85942300000001,33.732974],"type":"Point"}
}