{
  "type": "Feature",
  "properties": {
    "iso:country":"US",
    "sg:address":"102 US Hwy 52",
    "sg:city":"Moncks Corner",
    "sg:classifiers":[
        {
            "category":"Travel",
            "subcategory":"Hotels & Motels",
            "type":"Entertainment"
        }
    ],
    "sg:phone":"+1 843 761 5401",
    "sg:postcode":"29461",
    "sg:province":"SC",
    "wof:name":"Swamp Fox Inn",
    "wof:placetype":"venue"
},
  "geometry": {"coordinates":[-79.996368,33.192319],"type":"Point"}
}