{
  "type": "Feature",
  "properties": {
    "iso:country":"US",
    "sg:address":"3841 Clement Rd",
    "sg:city":"Columbia",
    "sg:classifiers":[
        {
            "category":"Professional",
            "subcategory":"Lawyer & Legal Services",
            "type":"Services"
        }
    ],
    "sg:phone":"+1 803 254 0531",
    "sg:postcode":"29203",
    "sg:province":"SC",
    "wof:name":"Smalls Darryl D Atty",
    "wof:placetype":"venue"
},
  "geometry": {"coordinates":[-81.060097,34.0354],"type":"Point"}
}