{
  "type": "Feature",
  "properties": {
    "iso:country":"US",
    "sg:address":"6 Weldon St",
    "sg:city":"Greenville",
    "sg:classifiers":[
        {
            "category":"Wholesale",
            "subcategory":"Auto Parts",
            "type":"Manufacturing & Wholesale Goods"
        }
    ],
    "sg:phone":"+1 864 242 5555",
    "sg:postcode":"29609",
    "sg:province":"SC",
    "sg:tags":[
        "battery",
        "automotive",
        "industrial",
        "retail"
    ],
    "sg:website":"www.cipbattery.com",
    "wof:name":"Carolina Industrial Products",
    "wof:placetype":"venue"
},
  "geometry": {"coordinates":[-82.405934,34.881824],"type":"Point"}
}