{
  "type": "Feature",
  "properties": {
    "iso:country":"US",
    "sg:address":"1933 Mount Gallant Rd",
    "sg:city":"Rock Hill",
    "sg:classifiers":[
        {
            "category":"Home & Garden",
            "subcategory":"Garden Supply",
            "type":"Retail Goods"
        }
    ],
    "sg:phone":"+1 803 327 2323",
    "sg:postcode":"29732",
    "sg:province":"SC",
    "sg:tags":[
        "landscaping"
    ],
    "wof:name":"Palmetto Landscaping Supply",
    "wof:placetype":"venue"
},
  "geometry": {"coordinates":[-81.004447,34.976718],"type":"Point"}
}