{
  "type": "Feature",
  "properties": {
    "iso:country":"US",
    "sg:address":"151 N Spring St",
    "sg:city":"Spartanburg",
    "sg:classifiers":[
        {
            "category":"Government",
            "subcategory":"Office",
            "type":"Public Place"
        }
    ],
    "sg:phone":"+1 864 596 2300",
    "sg:postcode":"29306",
    "sg:province":"SC",
    "wof:name":"Spartanburg County Detox Ctr",
    "wof:placetype":"venue"
},
  "geometry": {"coordinates":[-81.93441,34.950394],"type":"Point"}
}