{
  "type": "Feature",
  "properties": {
    "iso:country":"US",
    "sg:address":"240 Waccamaw Bend Rd",
    "sg:city":"Conway",
    "sg:classifiers":[
        {
            "category":"Building & Trades",
            "subcategory":"Construction",
            "type":"Services"
        }
    ],
    "sg:phone":"+1 843 397 8113",
    "sg:postcode":"29527",
    "sg:province":"SC",
    "sg:tags":[
        "house",
        "local",
        "trucking"
    ],
    "wof:name":"Drw Construction Inc",
    "wof:placetype":"venue"
},
  "geometry": {"coordinates":[-79.073467,33.757612],"type":"Point"}
}