{
  "type": "Feature",
  "properties": {
    "addr:full":"1000 Hamar St Beaufort SC 29902",
    "addr:postcode":"1000;29902",
    "addr:street":"St",
    "iso:country":"US",
    "sg:address":"1000 Hamar St",
    "sg:city":"Beaufort",
    "sg:classifiers":[
        {
            "category":"Manufacturing",
            "subcategory":"Printing",
            "type":"Manufacturing & Wholesale Goods"
        }
    ],
    "sg:phone":"+1 843 525 9993",
    "sg:postcode":"29902",
    "sg:province":"SC",
    "sg:tags":[
        "printer"
    ],
    "wof:name":"Pinpoint",
    "wof:placetype":"venue"
},
  "geometry": {"coordinates":[-80.681753,32.438069],"type":"Point"}
}