{
  "type": "Feature",
  "properties": {
    "addr:full":"219 N Longstreet St Kingstree SC 29556",
    "addr:housenumber":"219",
    "addr:postcode":"29556",
    "addr:street":"N Longstreet St",
    "iso:country":"US",
    "sg:address":"219 N Longstreet St",
    "sg:city":"Kingstree",
    "sg:phone":"+1 843 355 6981",
    "sg:postcode":"29556",
    "sg:province":"SC",
    "sg:tags":[
        "oil"
    ],
    "wof:name":"Thomlinson & Mc White Oil Co",
    "wof:placetype":"venue"
},
  "geometry": {"coordinates":[-79.834249,33.665512],"type":"Point"}
}