{
  "type": "Feature",
  "properties": {
    "iso:country":"US",
    "sg:address":"99 Southport Rd",
    "sg:city":"Spartanburg",
    "sg:classifiers":[
        {
            "category":"Banks & Credit Unions",
            "subcategory":"Bank",
            "type":"Services"
        }
    ],
    "sg:phone":"+1 864 595 1101",
    "sg:postcode":"29306",
    "sg:province":"SC",
    "sg:tags":[
        "institution",
        "business"
    ],
    "wof:name":"Fast Cash Check Advance Inc",
    "wof:placetype":"venue"
},
  "geometry": {"coordinates":[-81.969735,34.919701],"type":"Point"}
}