{
  "type": "Feature",
  "properties": {
    "iso:country":"US",
    "sg:address":"864 Savannah Hwy",
    "sg:city":"Charleston",
    "sg:classifiers":[
        {
            "category":"Real Estate",
            "subcategory":"Surveying",
            "type":"Services"
        }
    ],
    "sg:phone":"+1 843 571 0900",
    "sg:postcode":"29407",
    "sg:province":"SC",
    "sg:tags":[
        "surveyor"
    ],
    "wof:name":"Anderson & Assoc Land Srvyng",
    "wof:placetype":"venue"
},
  "geometry": {"coordinates":[-79.9897,32.782626],"type":"Point"}
}