{
  "type": "Feature",
  "properties": {
    "addr:full":"212 S Ron McNair Blvd Lake City SC 29560",
    "addr:housenumber":"212",
    "addr:postcode":"29560",
    "addr:street":"S Ron Mcnair Blvd",
    "iso:country":"US",
    "sg:address":"212 S Ron McNair Blvd",
    "sg:city":"Lake City",
    "sg:classifiers":[
        {
            "category":"Autos & Motor Vehicles",
            "subcategory":"Automobile Sales",
            "type":"Retail Goods"
        }
    ],
    "sg:phone":"+1 843 394 5836",
    "sg:postcode":"29560",
    "sg:province":"SC",
    "sg:tags":[
        "used"
    ],
    "wof:name":"Cooks Auto Sales",
    "wof:placetype":"venue"
},
  "geometry": {"coordinates":[-79.76164300000001,33.870786],"type":"Point"}
}