{
  "type": "Feature",
  "properties": {
    "iso:country":"US",
    "sg:address":"1533 Augusta Rd",
    "sg:city":"West Columbia",
    "sg:classifiers":[
        {
            "category":"Home & Garden",
            "subcategory":"Carpets & Floor Coverings",
            "type":"Retail Goods"
        }
    ],
    "sg:phone":"+1 803 939 0045",
    "sg:postcode":"29169",
    "sg:province":"SC",
    "sg:tags":[
        "hardwood",
        "ceramic",
        "rug",
        "install",
        "ti",
        "dealer"
    ],
    "wof:name":"Floors By Design LLC",
    "wof:placetype":"venue"
},
  "geometry": {"coordinates":[-81.07867,33.986159],"type":"Point"}
}