{
  "type": "Feature",
  "properties": {
    "addr:full":"405 Pinckney St Mc Clellanville SC 29458",
    "addr:housenumber":"405",
    "addr:postcode":"29458",
    "addr:street":"Pinckney St",
    "iso:country":"US",
    "sg:address":"405 Pinckney St",
    "sg:city":"Mc Clellanville",
    "sg:classifiers":[
        {
            "category":"Museum",
            "type":"Entertainment"
        }
    ],
    "sg:phone":"+1 843 887 3030",
    "sg:postcode":"29458",
    "sg:province":"SC",
    "wof:name":"Village Museum",
    "wof:placetype":"venue"
},
  "geometry": {"coordinates":[-79.45893100000001,33.08037],"type":"Point"}
}