{
  "type": "Feature",
  "properties": {
    "iso:country":"US",
    "sg:address":"712 Antioch Church Rd",
    "sg:city":"Greenville",
    "sg:classifiers":[
        {
            "category":"Shopping",
            "subcategory":"Computers & Home Electronics",
            "type":"Retail Goods"
        }
    ],
    "sg:phone":"+1 864 350 0000",
    "sg:postcode":"29605",
    "sg:province":"SC",
    "sg:tags":[
        "software"
    ],
    "wof:name":"Upstate Net  LLC",
    "wof:placetype":"venue"
},
  "geometry": {"coordinates":[-82.348691,34.73688],"type":"Point"}
}