{
  "type": "Feature",
  "properties": {
    "iso:country":"US",
    "sg:address":"3714 Grandview Dr",
    "sg:city":"Simpsonville",
    "sg:classifiers":[
        {
            "category":"Organizations",
            "subcategory":"Religious Organization",
            "type":"Services"
        }
    ],
    "sg:phone":"+1 864 228 2056",
    "sg:postcode":"29680",
    "sg:province":"SC",
    "sg:tags":[
        "church"
    ],
    "wof:name":"Columbia Mission SC",
    "wof:placetype":"venue"
},
  "geometry": {"coordinates":[-82.25837,34.720198],"type":"Point"}
}