{
  "type": "Feature",
  "properties": {
    "iso:country":"US",
    "sg:address":"59 Woodmere Ct",
    "sg:city":"Williamston",
    "sg:classifiers":[
        {
            "category":"Government",
            "subcategory":"Office",
            "type":"Public Place"
        }
    ],
    "sg:phone":"+1 864 847 9373",
    "sg:postcode":"29697",
    "sg:province":"SC",
    "sg:tags":[
        "village"
    ],
    "wof:name":"Williamston Wastewater",
    "wof:placetype":"venue"
},
  "geometry": {"coordinates":[-82.471383,34.612663],"type":"Point"}
}