{
  "type": "Feature",
  "properties": {
    "iso:country":"US",
    "sg:address":"1332 N Lake Dr",
    "sg:city":"Lexington",
    "sg:classifiers":[
        {
            "category":"Recreation",
            "type":"Entertainment"
        }
    ],
    "sg:phone":"+1 803 356 5077",
    "sg:postcode":"29072",
    "sg:province":"SC",
    "sg:tags":[
        "broadcast",
        "station",
        "radio"
    ],
    "wof:name":"M C Kims Tae Kwon Do U S A",
    "wof:placetype":"venue"
},
  "geometry": {"coordinates":[-81.224144,34.013478],"type":"Point"}
}