{
  "type": "Feature",
  "properties": {
    "iso:country":"US",
    "sg:address":"411 W Washington St",
    "sg:city":"Hartsville",
    "sg:classifiers":[
        {
            "category":"Restaurant",
            "type":"Food & Drink"
        }
    ],
    "sg:phone":"+1 843 332 6733",
    "sg:postcode":"29550",
    "sg:province":"SC",
    "sg:tags":[
        "barbecue"
    ],
    "wof:name":"Piggy's Bar BQ",
    "wof:placetype":"venue"
},
  "geometry": {"coordinates":[-80.07716499999999,34.360745],"type":"Point"}
}