{
  "type": "Feature",
  "properties": {
    "addr:full":"241 Applewood Center Pl Seneca SC 29678",
    "addr:housenumber":"241",
    "addr:postcode":"29678",
    "addr:street":"Applewood Center Pl",
    "iso:country":"US",
    "sg:address":"241 Applewood Center Pl",
    "sg:city":"Seneca",
    "sg:classifiers":[
        {
            "category":"Shopping",
            "subcategory":"Beauty & Cosmetics",
            "type":"Retail Goods"
        }
    ],
    "sg:phone":"+1 864 886 0734",
    "sg:postcode":"29678",
    "sg:province":"SC",
    "sg:tags":[
        "personal",
        "product",
        "care"
    ],
    "sg:website":"www.bathandbodyworks.com",
    "wof:name":"Bath & Body Works Inc",
    "wof:placetype":"venue"
},
  "geometry": {"coordinates":[-82.98976999999999,34.690458],"type":"Point"}
}