{
  "type": "Feature",
  "properties": {
    "iso:country":"US",
    "sg:address":"473 Broughton St",
    "sg:city":"Orangeburg",
    "sg:classifiers":[
        {
            "category":"Organizations",
            "subcategory":"Religious Organization",
            "type":"Services"
        }
    ],
    "sg:phone":"+1 803 533 3410",
    "sg:postcode":"29115",
    "sg:province":"SC",
    "sg:tags":[
        "church"
    ],
    "wof:name":"Gospel Temple Of Deliverence",
    "wof:placetype":"venue"
},
  "geometry": {"coordinates":[-80.85733399999999,33.480819],"type":"Point"}
}