{
  "type": "Feature",
  "properties": {
    "addr:full":"711 16th Ave N Surfside Beach SC 29575",
    "addr:housenumber":"711",
    "addr:postcode":"29575",
    "addr:street":"16Th Ave N",
    "iso:country":"US",
    "sg:address":"711 16th Ave N",
    "sg:city":"Surfside Beach",
    "sg:classifiers":[
        {
            "category":"Social Services",
            "subcategory":"Child Care",
            "type":"Services"
        }
    ],
    "sg:phone":"+1 843 477 0328",
    "sg:postcode":"29575",
    "sg:province":"SC",
    "sg:tags":[
        "kindergarten",
        "academic",
        "school"
    ],
    "wof:name":"First Baptist Wee School",
    "wof:placetype":"venue"
},
  "geometry": {"coordinates":[-78.967642,33.622778],"type":"Point"}
}