{
  "type": "Feature",
  "properties": {
    "addr:full":"707 Rummell Rd Darlington SC 29532",
    "addr:housenumber":"707",
    "addr:postcode":"29532",
    "addr:street":"Rummell Rd",
    "iso:country":"US",
    "sg:address":"707 Rummell Rd",
    "sg:city":"Darlington",
    "sg:classifiers":[
        {
            "category":"Building & Trades",
            "subcategory":"Construction",
            "type":"Services"
        }
    ],
    "sg:phone":"+1 843 395 0756",
    "sg:postcode":"29532",
    "sg:province":"SC",
    "sg:tags":[
        "contractor"
    ],
    "wof:name":"North American Construction Co",
    "wof:placetype":"venue"
},
  "geometry": {"coordinates":[-79.77237100000001,34.319142],"type":"Point"}
}