{
  "type": "Feature",
  "properties": {
    "addr:full":"230 Moss Creek Dr Bluffton SC 29926",
    "addr:housenumber":"230",
    "addr:postcode":"29926",
    "addr:street":"Moss Creek Dr",
    "iso:country":"US",
    "sg:address":"230 Moss Creek Dr",
    "sg:city":"Bluffton",
    "sg:classifiers":[
        {
            "category":"Professional",
            "type":"Services"
        }
    ],
    "sg:phone":"+1 843 837 2046",
    "sg:postcode":"29926",
    "sg:province":"SC",
    "sg:tags":[
        "establishment"
    ],
    "wof:name":"Moss Creek Owners Assoc",
    "wof:placetype":"venue"
},
  "geometry": {"coordinates":[-80.809822,32.256999],"type":"Point"}
}