{
  "type": "Feature",
  "properties": {
    "addr:full":"605 Anderson St Piedmont SC 29673",
    "addr:housenumber":"605",
    "addr:postcode":"29673",
    "addr:street":"Anderson St",
    "iso:country":"US",
    "sg:address":"605 Anderson St",
    "sg:city":"Piedmont",
    "sg:classifiers":[
        {
            "category":"Restaurant",
            "type":"Food & Drink"
        }
    ],
    "sg:phone":"+1 864 845 7100",
    "sg:postcode":"29673",
    "sg:province":"SC",
    "wof:name":"Pearsonplace",
    "wof:placetype":"venue"
},
  "geometry": {"coordinates":[-82.471914,34.70033],"type":"Point"}
}