{
  "type": "Feature",
  "properties": {
    "iso:country":"US",
    "sg:address":"137 Chapin Rd",
    "sg:city":"Chapin",
    "sg:classifiers":[
        {
            "category":"Wholesale",
            "subcategory":"Construction Materials",
            "type":"Manufacturing & Wholesale Goods"
        }
    ],
    "sg:phone":"+1 803 345 1055",
    "sg:postcode":"29036",
    "sg:province":"SC",
    "sg:tags":[
        "sand",
        "gravel"
    ],
    "wof:name":"Chapin Rock & Sand",
    "wof:placetype":"venue"
},
  "geometry": {"coordinates":[-81.318581,34.139444],"type":"Point"}
}