{
  "type": "Feature",
  "properties": {
    "iso:country":"US",
    "sg:address":"3240 Ebenezer Rd",
    "sg:city":"Bennettsville",
    "sg:classifiers":[
        {
            "category":"Personal",
            "subcategory":"Beauty Salon",
            "type":"Services"
        }
    ],
    "sg:phone":"+1 843 479 3600",
    "sg:postcode":"29512",
    "sg:province":"SC",
    "wof:name":"Harrison Beauty Salon & Dudley",
    "wof:placetype":"venue"
},
  "geometry": {"coordinates":[-79.761994,34.714455],"type":"Point"}
}