{
  "type": "Feature",
  "properties": {
    "iso:country":"US",
    "sg:address":"2480 Sunset Meadow Ln",
    "sg:city":"Sharon",
    "sg:classifiers":[
        {
            "category":"Home & Garden",
            "subcategory":"Garden Supply",
            "type":"Retail Goods"
        }
    ],
    "sg:phone":"+1 803 927 7403",
    "sg:postcode":"29742",
    "sg:province":"SC",
    "sg:tags":[
        "nurseryman"
    ],
    "wof:name":"Sherer's Tree Farm",
    "wof:placetype":"venue"
},
  "geometry": {"coordinates":[-81.356222,34.897756],"type":"Point"}
}