{
  "type": "Feature",
  "properties": {
    "addr:full":"501 Taylor Street Columbia SC 29201",
    "addr:housenumber":"501",
    "addr:postcode":"29201",
    "addr:street":"Taylor Street",
    "iso:country":"US",
    "sg:address":"501 Taylor Street",
    "sg:city":"Columbia",
    "sg:classifiers":[
        {
            "category":"Travel",
            "subcategory":"Hotels & Motels",
            "type":"Entertainment"
        },
        {
            "category":"Retail",
            "subcategory":"Event Space",
            "type":"Services"
        }
    ],
    "sg:phone":"+1 803 744 4000",
    "sg:postcode":"29201",
    "sg:province":"SC",
    "sg:tags":[
        "venue"
    ],
    "sg:website":"www.holidayinnexpress.com",
    "wof:name":"Holiday Inn Express Hotel & Suites Columbia",
    "wof:placetype":"venue"
},
  "geometry": {"coordinates":[-81.047071,34.003637],"type":"Point"}
}