{
  "type": "Feature",
  "properties": {
    "iso:country":"US",
    "sg:address":"1998 Dave Lyle Blvd",
    "sg:city":"Rock Hill",
    "sg:classifiers":[
        {
            "category":"Restaurant",
            "type":"Food & Drink"
        }
    ],
    "sg:menulink":"http://www.allmenus.com/sc/rock-hill/200966-mcdonalds/menu/",
    "sg:postcode":"29730",
    "sg:province":"SC",
    "sg:tags":[
        "burger",
        "american"
    ],
    "wof:name":"McDonald's",
    "wof:placetype":"venue"
},
  "geometry": {"coordinates":[-80.97731,34.940416],"type":"Point"}
}