{
  "type": "Feature",
  "properties": {
    "iso:country":"US",
    "sg:address":"2547 Whiskey Rd",
    "sg:city":"Aiken",
    "sg:classifiers":[
        {
            "category":"Utilities",
            "subcategory":"Mobile Phone",
            "type":"Services"
        }
    ],
    "sg:phone":"+1 803 215 6800",
    "sg:postcode":"29803",
    "sg:province":"SC",
    "sg:tags":[
        "telephone",
        "cellular"
    ],
    "wof:name":"Sun Com",
    "wof:placetype":"venue"
},
  "geometry": {"coordinates":[-81.707005,33.502968],"type":"Point"}
}