{
  "type": "Feature",
  "properties": {
    "iso:country":"US",
    "sg:address":"1204 Orange St",
    "sg:city":"Hanahan",
    "sg:classifiers":[
        {
            "category":"Building & Trades",
            "subcategory":"Construction",
            "type":"Services"
        }
    ],
    "sg:phone":"+1 843 747 3000",
    "sg:postcode":"29410",
    "sg:province":"SC",
    "sg:tags":[
        "paving",
        "contractor"
    ],
    "wof:name":"A Asphalt Svc",
    "wof:placetype":"venue"
},
  "geometry": {"coordinates":[-80.013947,32.908171],"type":"Point"}
}