{
  "type": "Feature",
  "properties": {
    "addr:full":"7901 Garners Ferry Rd Columbia SC 29209",
    "addr:housenumber":"7901",
    "addr:postcode":"29209",
    "addr:street":"Garners Ferry Rd",
    "iso:country":"US",
    "sg:address":"7901 Garners Ferry Rd",
    "sg:city":"Columbia",
    "sg:classifiers":[
        {
            "category":"Food & Beverages",
            "subcategory":"Groceries & Convenience Stores",
            "type":"Retail Goods"
        }
    ],
    "sg:phone":"+1 803 783 7219",
    "sg:postcode":"29209",
    "sg:province":"SC",
    "sg:website":"www.circlek.com",
    "wof:name":"Circle K",
    "wof:placetype":"venue"
},
  "geometry": {"coordinates":[-80.923051,33.953655],"type":"Point"}
}