{
  "type": "Feature",
  "properties": {
    "iso:country":"US",
    "sg:address":"218 Main St",
    "sg:city":"North Myrtle Beach",
    "sg:classifiers":[
        {
            "category":"Utilities",
            "subcategory":"Telephone",
            "type":"Services"
        }
    ],
    "sg:phone":"+1 843 281 9688",
    "sg:postcode":"29582",
    "sg:province":"SC",
    "sg:tags":[
        "communications"
    ],
    "wof:name":"Vr Marketing Inc",
    "wof:placetype":"venue"
},
  "geometry": {"coordinates":[-78.673137,33.820341],"type":"Point"}
}