{
  "type": "Feature",
  "properties": {
    "addr:full":"1106 Hurley Dr Sumter SC 29150",
    "addr:housenumber":"1106",
    "addr:postcode":"29150",
    "addr:street":"Hurley Dr",
    "iso:country":"US",
    "sg:address":"1106 Hurley Dr",
    "sg:city":"Sumter",
    "sg:classifiers":[
        {
            "category":"Organizations",
            "subcategory":"Religious Organization",
            "type":"Services"
        }
    ],
    "sg:phone":"+1 803 775 6615",
    "sg:postcode":"29150",
    "sg:province":"SC",
    "sg:tags":[
        "church"
    ],
    "wof:name":"New Life Bible Church",
    "wof:placetype":"venue"
},
  "geometry": {"coordinates":[-80.339719,33.89039],"type":"Point"}
}