{
  "type": "Feature",
  "properties": {
    "addr:full":"146 Pepper Rd Easley SC 29642",
    "addr:housenumber":"146",
    "addr:postcode":"29642",
    "addr:street":"Pepper Rd",
    "iso:country":"US",
    "sg:address":"146 Pepper Rd",
    "sg:city":"Easley",
    "sg:classifiers":[
        {
            "category":"Home & Garden",
            "subcategory":"Garden Supply",
            "type":"Retail Goods"
        }
    ],
    "sg:phone":"+1 864 430 3113",
    "sg:postcode":"29642",
    "sg:province":"SC",
    "sg:tags":[
        "nurseryman"
    ],
    "wof:name":"Mill Pond Tree Farm",
    "wof:placetype":"venue"
},
  "geometry": {"coordinates":[-82.590278,34.734243],"type":"Point"}
}