{
  "type": "Feature",
  "properties": {
    "addr:full":"101 W Antrim Dr Greenville SC 29607",
    "addr:housenumber":"101",
    "addr:postcode":"29607",
    "addr:street":"W Antrim Dr",
    "iso:country":"US",
    "sg:address":"101 W Antrim Dr",
    "sg:city":"Greenville",
    "sg:classifiers":[
        {
            "category":"Professional",
            "subcategory":"Lawyer & Legal Services",
            "type":"Services"
        }
    ],
    "sg:phone":"+1 864 271 0220",
    "sg:postcode":"29607",
    "sg:province":"SC",
    "sg:tags":[
        "attorney"
    ],
    "wof:name":"Sullivan Law Firm",
    "wof:placetype":"venue"
},
  "geometry": {"coordinates":[-82.365291,34.84175],"type":"Point"}
}