{
  "type": "Feature",
  "properties": {
    "iso:country":"US",
    "sg:address":"1 Parkway E",
    "sg:city":"Greenville",
    "sg:classifiers":[
        {
            "category":"Personal",
            "type":"Services"
        }
    ],
    "sg:phone":"+1 864 329 1605",
    "sg:postcode":"29650",
    "sg:province":"SC",
    "sg:tags":[
        "therapist",
        "massage"
    ],
    "wof:name":"Revive Fitness & Massage",
    "wof:placetype":"venue"
},
  "geometry": {"coordinates":[-82.258375,34.864557],"type":"Point"}
}