{
  "type": "Feature",
  "properties": {
    "iso:country":"US",
    "sg:address":"135 Pearl St",
    "sg:city":"Darlington",
    "sg:classifiers":[
        {
            "category":"Restaurant",
            "type":"Food & Drink"
        }
    ],
    "sg:phone":"+1 843 393 6764",
    "sg:postcode":"29532",
    "sg:province":"SC",
    "sg:tags":[
        "eating"
    ],
    "wof:name":"Hometown Seafood",
    "wof:placetype":"venue"
},
  "geometry": {"coordinates":[-79.872417,34.301922],"type":"Point"}
}