{
  "type": "Feature",
  "properties": {
    "iso:country":"US",
    "sg:address":"2970 Old Furnace Rd",
    "sg:city":"Spartanburg",
    "sg:classifiers":[
        {
            "category":"Retail",
            "subcategory":"Auto Repair",
            "type":"Services"
        }
    ],
    "sg:phone":"+1 864 578 5447",
    "sg:postcode":"29316",
    "sg:province":"SC",
    "sg:tags":[
        "repairing",
        "automobile"
    ],
    "wof:name":"Cantrell Automotive",
    "wof:placetype":"venue"
},
  "geometry": {"coordinates":[-81.948075,35.057861],"type":"Point"}
}