{
  "type": "Feature",
  "properties": {
    "iso:country":"US",
    "sg:address":"107 W 8th North St",
    "sg:city":"Summerville",
    "sg:classifiers":[
        {
            "category":"Shopping",
            "subcategory":"Used Merchandise",
            "type":"Retail Goods"
        }
    ],
    "sg:phone":"+1 843 832 1877",
    "sg:postcode":"29483",
    "sg:province":"SC",
    "sg:tags":[
        "shop",
        "consignment"
    ],
    "wof:name":"Interiors 2 Consign",
    "wof:placetype":"venue"
},
  "geometry": {"coordinates":[-80.16876600000001,33.030689],"type":"Point"}
}