{
  "type": "Feature",
  "properties": {
    "iso:country":"US",
    "sg:address":"1515 Freedom Blvd",
    "sg:city":"Florence",
    "sg:classifiers":[
        {
            "category":"Recreation",
            "type":"Entertainment"
        }
    ],
    "sg:phone":"+1 843 667 0837",
    "sg:postcode":"29505",
    "sg:province":"SC",
    "sg:tags":[
        "amusement"
    ],
    "wof:name":"Florence County Recreation Dpt",
    "wof:placetype":"venue"
},
  "geometry": {"coordinates":[-79.753743,34.163541],"type":"Point"}
}