{
  "type": "Feature",
  "properties": {
    "iso:country":"US",
    "sg:address":"2820 Plymouth Rock Rd",
    "sg:city":"Columbia",
    "sg:classifiers":[
        {
            "category":"Retail",
            "subcategory":"Laundry & Dry Cleaning",
            "type":"Services"
        }
    ],
    "sg:phone":"+1 803 695 1884",
    "sg:postcode":"29209",
    "sg:province":"SC",
    "sg:tags":[
        "cleaners",
        "rug",
        "carpet"
    ],
    "wof:name":"Blue Ribbon Carpet Cleaning",
    "wof:placetype":"venue"
},
  "geometry": {"coordinates":[-80.903768,33.968366],"type":"Point"}
}