{
  "type": "Feature",
  "properties": {
    "iso:country":"US",
    "sg:address":"103 Quail Ridge Dr",
    "sg:city":"Simpsonville",
    "sg:classifiers":[
        {
            "category":"Building & Trades",
            "subcategory":"Construction",
            "type":"Services"
        }
    ],
    "sg:phone":"+1 864 967 9588",
    "sg:postcode":"29680",
    "sg:province":"SC",
    "sg:tags":[
        "general",
        "contractor"
    ],
    "wof:name":"Momentum Construction Svc",
    "wof:placetype":"venue"
},
  "geometry": {"coordinates":[-82.28075,34.705193],"type":"Point"}
}