{
  "type": "Feature",
  "properties": {
    "iso:country":"US",
    "sg:address":"1901 W Palmetto St",
    "sg:city":"Florence",
    "sg:classifiers":[
        {
            "category":"Shopping",
            "subcategory":"Shoes",
            "type":"Retail Goods"
        }
    ],
    "sg:phone":"+1 843 665 2223",
    "sg:postcode":"29501",
    "sg:province":"SC",
    "wof:name":"Payless Shoe Source",
    "wof:placetype":"venue"
},
  "geometry": {"coordinates":[-79.806826,34.188466],"type":"Point"}
}