{
  "type": "Feature",
  "properties": {
    "addr:full":"115 E Blackstock Rd Spartanburg SC 29301",
    "addr:housenumber":"115",
    "addr:postcode":"29301",
    "addr:street":"E Blackstock Rd",
    "iso:country":"US",
    "sg:address":"115 E Blackstock Rd",
    "sg:city":"Spartanburg",
    "sg:classifiers":[
        {
            "category":"Shopping",
            "subcategory":"Clothing, Apparel, & Fashions",
            "type":"Retail Goods"
        }
    ],
    "sg:phone":"+1 864 587 2160",
    "sg:postcode":"29301",
    "sg:province":"SC",
    "sg:tags":[
        "uniform"
    ],
    "wof:name":"Uniform Shoppe",
    "wof:placetype":"venue"
},
  "geometry": {"coordinates":[-81.986778,34.922042],"type":"Point"}
}