{
  "type": "Feature",
  "properties": {
    "iso:country":"US",
    "sg:address":"289 Daytona Rd",
    "sg:city":"Wagener",
    "sg:classifiers":[
        {
            "category":"Retail",
            "subcategory":"Auto Repair",
            "type":"Services"
        }
    ],
    "sg:phone":"+1 803 564 7195",
    "sg:postcode":"29164",
    "sg:province":"SC",
    "sg:tags":[
        "repairing",
        "automobile"
    ],
    "wof:name":"Quality Auto Ctr",
    "wof:placetype":"venue"
},
  "geometry": {"coordinates":[-81.414579,33.683556],"type":"Point"}
}