{
  "type": "Feature",
  "properties": {
    "iso:country":"US",
    "sg:address":"112 Sumter St",
    "sg:city":"Columbia",
    "sg:classifiers":[
        {
            "category":"Building & Trades",
            "subcategory":"Construction",
            "type":"Services"
        }
    ],
    "sg:phone":"+1 803 462 0610",
    "sg:postcode":"29225",
    "sg:province":"SC",
    "sg:tags":[
        "home",
        "builder"
    ],
    "wof:name":"Beazer Homes",
    "wof:placetype":"venue"
},
  "geometry": {"coordinates":[-81.025886,33.988104],"type":"Point"}
}