{
  "type": "Feature",
  "properties": {
    "addr:full":"241 King St Charleston SC 29401",
    "addr:housenumber":"241",
    "addr:postcode":"29401",
    "addr:street":"King St",
    "iso:country":"US",
    "sg:address":"241 King St",
    "sg:city":"Charleston",
    "sg:classifiers":[
        {
            "category":"Shopping",
            "subcategory":"Department Store",
            "type":"Retail Goods"
        }
    ],
    "sg:phone":"+1 843 723 4191",
    "sg:postcode":"29401",
    "sg:province":"SC",
    "wof:name":"Le Creuset of America Inc",
    "wof:placetype":"venue"
},
  "geometry": {"coordinates":[-79.933297,32.78065],"type":"Point"}
}