{
  "type": "Feature",
  "properties": {
    "iso:country":"US",
    "sg:address":"152 Grove St",
    "sg:city":"Spartanburg",
    "sg:classifiers":[
        {
            "category":"Building & Trades",
            "subcategory":"Electrical",
            "type":"Services"
        }
    ],
    "sg:phone":"+1 864 599 4063",
    "sg:postcode":"29353",
    "sg:province":"SC",
    "sg:tags":[
        "electrical",
        "contractor"
    ],
    "wof:name":"Westinghouse Electric Co LLC",
    "wof:placetype":"venue"
},
  "geometry": {"coordinates":[-81.688373,34.838256],"type":"Point"}
}