{
  "type": "Feature",
  "properties": {
    "iso:country":"US",
    "sg:address":"238 E Black St",
    "sg:city":"Rock Hill",
    "sg:classifiers":[
        {
            "category":"Retail",
            "subcategory":"Repair Shop",
            "type":"Services"
        }
    ],
    "sg:phone":"+1 803 327 5202",
    "sg:postcode":"29730",
    "sg:province":"SC",
    "sg:tags":[
        "instrument",
        "musical"
    ],
    "wof:name":"Grobusky Music Svc",
    "wof:placetype":"venue"
},
  "geometry": {"coordinates":[-81.025871,34.923475],"type":"Point"}
}