{
  "type": "Feature",
  "properties": {
    "addr:full":"1211 3rd Ave S Myrtle Beach SC 29577",
    "addr:housenumber":"1211",
    "addr:postcode":"29577",
    "addr:street":"3Rd Ave S Myrtle",
    "iso:country":"US",
    "sg:address":"1211 3rd Ave S",
    "sg:city":"Myrtle Beach",
    "sg:classifiers":[
        {
            "category":"Banks & Credit Unions",
            "subcategory":"Bank",
            "type":"Services"
        }
    ],
    "sg:phone":"+1 843 448 3065",
    "sg:postcode":"29577",
    "sg:province":"SC",
    "sg:tags":[
        "money",
        "transfer"
    ],
    "wof:name":"Hisbanoamerica",
    "wof:placetype":"venue"
},
  "geometry": {"coordinates":[-78.898774,33.696993],"type":"Point"}
}