{
  "type": "Feature",
  "properties": {
    "addr:full":"1900 North Ln Camden SC 29020",
    "addr:housenumber":"1900",
    "addr:postcode":"29020",
    "addr:street":"North Ln",
    "iso:country":"US",
    "sg:address":"1900 North Ln",
    "sg:city":"Camden",
    "sg:classifiers":[
        {
            "category":"Autos & Motor Vehicles",
            "subcategory":"Boat Sales",
            "type":"Retail Goods"
        }
    ],
    "sg:phone":"+1 803 432 4301",
    "sg:postcode":"29020",
    "sg:province":"SC",
    "wof:name":"Sailboats Parts Service",
    "wof:placetype":"venue"
},
  "geometry": {"coordinates":[-80.62970799999999,34.260583],"type":"Point"}
}