{
  "type": "Feature",
  "properties": {
    "iso:country":"US",
    "sg:address":"116 W Forest Dr",
    "sg:city":"Spartanburg",
    "sg:classifiers":[
        {
            "category":"Professional",
            "subcategory":"Business Services",
            "type":"Services"
        }
    ],
    "sg:phone":"+1 864 587 6975",
    "sg:postcode":"29301",
    "sg:province":"SC",
    "sg:tags":[
        "organizing"
    ],
    "wof:name":"Clear The Clutter",
    "wof:placetype":"venue"
},
  "geometry": {"coordinates":[-82.006445,34.922779],"type":"Point"}
}