{
  "type": "Feature",
  "properties": {
    "iso:country":"US",
    "sg:address":"127 Raddison Dr",
    "sg:city":"Cowpens",
    "sg:classifiers":[
        {
            "category":"Building & Trades",
            "subcategory":"Construction",
            "type":"Services"
        }
    ],
    "sg:phone":"+1 864 463 9181",
    "sg:postcode":"29330",
    "sg:province":"SC",
    "sg:tags":[
        "house"
    ],
    "wof:name":"Ce Scruggs & Sons LLC",
    "wof:placetype":"venue"
},
  "geometry": {"coordinates":[-81.771272,35.012486],"type":"Point"}
}