{
  "type": "Feature",
  "properties": {
    "addr:full":"2895 Main St Newberry SC 29108",
    "addr:housenumber":"2895",
    "addr:postcode":"29108",
    "addr:street":"Main St",
    "iso:country":"US",
    "sg:address":"2895 Main St",
    "sg:city":"Newberry",
    "sg:classifiers":[
        {
            "category":"Restaurant",
            "type":"Food & Drink"
        }
    ],
    "sg:phone":"+1 803 321 6221",
    "sg:postcode":"29108",
    "sg:province":"SC",
    "wof:name":"Mig's Of Newberry",
    "wof:placetype":"venue"
},
  "geometry": {"coordinates":[-81.59089299999999,34.282684],"type":"Point"}
}