{
  "type": "Feature",
  "properties": {
    "iso:country":"US",
    "sg:address":"1 S Piedmont Hwy",
    "sg:city":"Piedmont",
    "sg:classifiers":[
        {
            "category":"Food & Beverages",
            "subcategory":"Groceries & Convenience Stores",
            "type":"Retail Goods"
        }
    ],
    "sg:phone":"+1 864 845 4300",
    "sg:postcode":"29673",
    "sg:province":"SC",
    "wof:name":"Stop A Minit",
    "wof:placetype":"venue"
},
  "geometry": {"coordinates":[-82.45344900000001,34.704279],"type":"Point"}
}