{
  "type": "Feature",
  "properties": {
    "addr:full":"1318 Celebrity Cir Myrtle Beach SC 29577",
    "addr:housenumber":"1318",
    "addr:postcode":"29577",
    "addr:street":"Celebrity Cir",
    "iso:country":"US",
    "sg:address":"1318 Celebrity Cir",
    "sg:city":"Myrtle Beach",
    "sg:classifiers":[
        {
            "category":"Bars & Pubs",
            "type":"Food & Drink"
        }
    ],
    "sg:phone":"+1 843 444 8277",
    "sg:postcode":"29577",
    "sg:province":"SC",
    "sg:tags":[
        "club",
        "night"
    ],
    "wof:name":"Stool Pigeons Inc",
    "wof:placetype":"venue"
},
  "geometry": {"coordinates":[-78.87984899999999,33.719314],"type":"Point"}
}