{
  "type": "Feature",
  "properties": {
    "iso:country":"US",
    "sg:address":"1318 Celebrity Cir",
    "sg:city":"Myrtle Beach",
    "sg:classifiers":[
        {
            "category":"Bars & Pubs",
            "type":"Food & Drink"
        }
    ],
    "sg:phone":"+1 843 444 8277",
    "sg:postcode":"29577",
    "sg:province":"SC",
    "sg:tags":[
        "club",
        "night"
    ],
    "wof:name":"Stool Pigeons Inc",
    "wof:placetype":"venue"
},
  "geometry": {"coordinates":[-78.879849,33.719314],"type":"Point"}
}