{
  "type": "Feature",
  "properties": {
    "iso:country":"US",
    "sg:address":"241 Hillcrest Dr",
    "sg:city":"Laurens",
    "sg:classifiers":[
        {
            "category":"Food & Beverages",
            "subcategory":"Groceries & Convenience Stores",
            "type":"Retail Goods"
        }
    ],
    "sg:phone":"+1 864 984 2378",
    "sg:postcode":"29360",
    "sg:province":"SC",
    "sg:tags":[
        "grocer"
    ],
    "wof:name":"Food Lion",
    "wof:placetype":"venue"
},
  "geometry": {"coordinates":[-82.01277399999999,34.504916],"type":"Point"}
}