{
  "type": "Feature",
  "properties": {
    "addr:full":"415 Planters Dr Sumter SC 29154",
    "addr:housenumber":"415",
    "addr:postcode":"29154",
    "addr:street":"Planters Dr",
    "iso:country":"US",
    "sg:address":"415 Planters Dr",
    "sg:city":"Sumter",
    "sg:classifiers":[
        {
            "category":"Building & Trades",
            "subcategory":"Landscaping Services",
            "type":"Services"
        }
    ],
    "sg:phone":"+1 803 775 5003",
    "sg:postcode":"29154",
    "sg:province":"SC",
    "sg:tags":[
        "lawn",
        "maintenance",
        "grounds"
    ],
    "wof:name":"Lewis Lawn Svc",
    "wof:placetype":"venue"
},
  "geometry": {"coordinates":[-80.41694200000001,33.915147],"type":"Point"}
}