{
  "type": "Feature",
  "properties": {
    "addr:full":"210 W Main St Easley SC 29640",
    "addr:housenumber":"210",
    "addr:postcode":"29640",
    "addr:street":"W Main St",
    "iso:country":"US",
    "sg:address":"210 W Main St",
    "sg:city":"Easley",
    "sg:classifiers":[
        {
            "category":"Personal",
            "subcategory":"Beauty Salon",
            "type":"Services"
        }
    ],
    "sg:phone":"+1 864 855 2378",
    "sg:postcode":"29640",
    "sg:province":"SC",
    "sg:tags":[
        "manicuring"
    ],
    "wof:name":"Hollywood Nails",
    "wof:placetype":"venue"
},
  "geometry": {"coordinates":[-82.604829,34.829706],"type":"Point"}
}