{
  "type": "Feature",
  "properties": {
    "iso:country":"US",
    "sg:address":"3591 Northgate Rd",
    "sg:city":"Myrtle Beach",
    "sg:classifiers":[
        {
            "category":"Banks & Credit Unions",
            "subcategory":"Bank",
            "type":"Services"
        }
    ],
    "sg:phone":"+1 843 293 4422",
    "sg:postcode":"29581",
    "sg:province":"SC",
    "wof:name":"Conway National Bank",
    "wof:placetype":"venue"
},
  "geometry": {"coordinates":[-79.092658,34.118225],"type":"Point"}
}