{
  "type": "Feature",
  "properties": {
    "addr:full":"625 N Main St Heath Springs SC 29058",
    "addr:housenumber":"625",
    "addr:postcode":"29058",
    "addr:street":"N Main St Heath",
    "iso:country":"US",
    "sg:address":"625 N Main St",
    "sg:city":"Heath Springs",
    "sg:classifiers":[
        {
            "category":"Restaurant",
            "type":"Food & Drink"
        }
    ],
    "sg:phone":"+1 803 273 8301",
    "sg:postcode":"29058",
    "sg:province":"SC",
    "wof:name":"S & G Mini Mart",
    "wof:placetype":"venue"
},
  "geometry": {"coordinates":[-80.67952200000001,34.597121],"type":"Point"}
}