{
  "type": "Feature",
  "properties": {
    "iso:country":"US",
    "sg:address":"912 E Main St",
    "sg:city":"Spartanburg",
    "sg:classifiers":[
        {
            "category":"Professional",
            "subcategory":"Business Services",
            "type":"Services"
        }
    ],
    "sg:phone":"+1 864 583 3555",
    "sg:postcode":"29302",
    "sg:province":"SC",
    "sg:tags":[
        "embroidery"
    ],
    "wof:name":"Picket Fence",
    "wof:placetype":"venue"
},
  "geometry": {"coordinates":[-81.90880900000001,34.958657],"type":"Point"}
}