{
  "type": "Feature",
  "properties": {
    "addr:full":"763 E Main St Laurens SC 29360",
    "addr:housenumber":"763",
    "addr:postcode":"29360",
    "addr:street":"E Main St",
    "iso:country":"US",
    "sg:address":"763 E Main St",
    "sg:city":"Laurens",
    "sg:classifiers":[
        {
            "category":"Organizations",
            "subcategory":"Non-profit Organization",
            "type":"Services"
        }
    ],
    "sg:phone":"+1 864 984 5211",
    "sg:postcode":"29360",
    "sg:province":"SC",
    "wof:name":"Veterans Of Foreign Wars",
    "wof:placetype":"venue"
},
  "geometry": {"coordinates":[-81.992205,34.496607],"type":"Point"}
}