{
  "type": "Feature",
  "properties": {
    "addr:full":"1920 Sapling Dr Columbia SC 29210",
    "addr:housenumber":"1920",
    "addr:postcode":"29210",
    "addr:street":"Sapling Dr",
    "iso:country":"US",
    "sg:address":"1920 Sapling Dr",
    "sg:city":"Columbia",
    "sg:classifiers":[
        {
            "category":"Professional",
            "subcategory":"Management & Consulting",
            "type":"Services"
        },
        {
            "category":"Professional",
            "type":"Services"
        }
    ],
    "sg:phone":"+1 803 798 4001",
    "sg:postcode":"29210",
    "sg:province":"SC",
    "sg:tags":[
        "planning",
        "life",
        "coach",
        "event"
    ],
    "wof:name":"The Ideal Solution, LLC",
    "wof:placetype":"venue"
},
  "geometry": {"coordinates":[-81.08144900000001,34.050384],"type":"Point"}
}