{
  "type": "Feature",
  "properties": {
    "iso:country":"US",
    "sg:address":"8631 Valley Falls Rd",
    "sg:city":"Spartanburg",
    "sg:classifiers":[
        {
            "category":"Social Services",
            "subcategory":"Child Care",
            "type":"Services"
        }
    ],
    "sg:phone":"+1 864 578 1625",
    "sg:postcode":"29316",
    "sg:province":"SC",
    "wof:name":"Little Learners Skool",
    "wof:placetype":"venue"
},
  "geometry": {"coordinates":[-81.970698,35.027175],"type":"Point"}
}