{
  "type": "Feature",
  "properties": {
    "addr:full":"3481 Ladson Rd Ladson SC 29456",
    "addr:housenumber":"3481",
    "addr:postcode":"29456",
    "addr:street":"Ladson Rd",
    "iso:country":"US",
    "sg:address":"3481 Ladson Rd",
    "sg:city":"Ladson",
    "sg:classifiers":[
        {
            "category":"Local Transit",
            "type":"Transportation"
        }
    ],
    "sg:phone":"+1 843 747 1888",
    "sg:postcode":"29456",
    "sg:province":"SC",
    "sg:tags":[
        "passenger",
        "ambulance"
    ],
    "wof:name":"Rural Metro Ambulance Services",
    "wof:placetype":"venue"
},
  "geometry": {"coordinates":[-80.109758,32.985655],"type":"Point"}
}