{
  "type": "Feature",
  "properties": {
    "iso:country":"US",
    "sg:address":"155 Hightower Hill",
    "sg:city":"Seneca",
    "sg:classifiers":[
        {
            "category":"Wholesale",
            "subcategory":"Construction Materials",
            "type":"Manufacturing & Wholesale Goods"
        }
    ],
    "sg:phone":"+1 864 882 6394",
    "sg:postcode":"29672",
    "sg:province":"SC",
    "wof:name":"Luther & Scott Hightower Mason",
    "wof:placetype":"venue"
},
  "geometry": {"coordinates":[-82.966072,34.797174],"type":"Point"}
}