{
  "type": "Feature",
  "properties": {
    "iso:country":"US",
    "sg:address":"28 Martingale W",
    "sg:city":"Bluffton",
    "sg:classifiers":[
        {
            "category":"Building & Trades",
            "subcategory":"Construction",
            "type":"Services"
        }
    ],
    "sg:phone":"+1 843 683 0713",
    "sg:postcode":"29910",
    "sg:province":"SC",
    "sg:tags":[
        "house"
    ],
    "wof:name":"Barrett Builders Inc",
    "wof:placetype":"venue"
},
  "geometry": {"coordinates":[-80.884472,32.292267],"type":"Point"}
}