{
  "type": "Feature",
  "properties": {
    "iso:country":"US",
    "sg:address":"155 Osprey Ct",
    "sg:city":"Myrtle Beach",
    "sg:classifiers":[
        {
            "category":"Wholesale",
            "subcategory":"Construction Materials",
            "type":"Manufacturing & Wholesale Goods"
        }
    ],
    "sg:phone":"+1 843 650 9499",
    "sg:postcode":"29576",
    "sg:province":"SC",
    "sg:tags":[
        "fence"
    ],
    "wof:name":"Metro Fence & Supply",
    "wof:placetype":"venue"
},
  "geometry": {"coordinates":[-78.995261,33.587465],"type":"Point"}
}