{
  "type": "Feature",
  "properties": {
    "addr:full":"1440 N Schlitz Dr Florence SC 29501",
    "addr:housenumber":"1440",
    "addr:postcode":"29501",
    "addr:street":"N Schlitz Dr",
    "iso:country":"US",
    "sg:address":"1440 N Schlitz Dr",
    "sg:city":"Florence",
    "sg:classifiers":[
        {
            "category":"Food & Beverages",
            "subcategory":"Liquor & Beverages",
            "type":"Retail Goods"
        }
    ],
    "sg:phone":"+1 843 665 4748",
    "sg:postcode":"29501",
    "sg:province":"SC",
    "sg:tags":[
        "beer",
        "ale"
    ],
    "wof:name":"Yahnis Co",
    "wof:placetype":"venue"
},
  "geometry": {"coordinates":[-79.79362999999999,34.220201],"type":"Point"}
}