{
  "type": "Feature",
  "properties": {
    "iso:country":"US",
    "sg:address":"520 Davis Rd",
    "sg:city":"Greer",
    "sg:classifiers":[
        {
            "category":"Building & Trades",
            "subcategory":"Electrical",
            "type":"Services"
        }
    ],
    "sg:phone":"+1 864 968 0505",
    "sg:postcode":"29651",
    "sg:province":"SC",
    "sg:tags":[
        "electric",
        "contractor"
    ],
    "wof:name":"Eldeco Electric",
    "wof:placetype":"venue"
},
  "geometry": {"coordinates":[-82.178792,34.891389],"type":"Point"}
}