{
  "type": "Feature",
  "properties": {
    "iso:country":"US",
    "sg:address":"686 Lake Pt",
    "sg:city":"Mt Pleasant",
    "sg:classifiers":[
        {
            "category":"Wholesale",
            "subcategory":"Machinery & Supplies",
            "type":"Manufacturing & Wholesale Goods"
        }
    ],
    "sg:phone":"+1 843 881 1728",
    "sg:postcode":"29464",
    "sg:province":"SC",
    "sg:tags":[
        "equipment",
        "industrial"
    ],
    "wof:name":"Palmetto Sales & Svc",
    "wof:placetype":"venue"
},
  "geometry": {"coordinates":[-79.858508,32.826713],"type":"Point"}
}