{
  "type": "Feature",
  "properties": {
    "addr:full":"1015 Saint Andrews Blvd Charleston SC 29407",
    "addr:housenumber":"1015",
    "addr:postcode":"29407",
    "addr:street":"Saint Andrews Blvd",
    "iso:country":"US",
    "sg:address":"1015 Saint Andrews Blvd",
    "sg:city":"Charleston",
    "sg:classifiers":[
        {
            "category":"Arts & Performance",
            "subcategory":"Theater",
            "type":"Entertainment"
        }
    ],
    "sg:phone":"+1 843 556 6607",
    "sg:postcode":"29407",
    "sg:province":"SC",
    "sg:tags":[
        "entertainer"
    ],
    "wof:name":"Hokus Pokus Entertainment",
    "wof:placetype":"venue"
},
  "geometry": {"coordinates":[-79.992075,32.794415],"type":"Point"}
}