{
  "type": "Feature",
  "properties": {
    "addr:full":"6555 Southmount Rd Wadmalaw Island SC 29487",
    "addr:housenumber":"6555",
    "addr:postcode":"29487",
    "addr:street":"Southmount Rd",
    "iso:country":"US",
    "sg:address":"6555 Southmount Rd",
    "sg:city":"Wadmalaw Island",
    "sg:classifiers":[
        {
            "category":"Restaurant",
            "type":"Food & Drink"
        }
    ],
    "sg:phone":"+1 843 559 3642",
    "sg:postcode":"29487",
    "sg:province":"SC",
    "wof:name":"Lowcountry Tiramisu",
    "wof:placetype":"venue"
},
  "geometry": {"coordinates":[-80.17717500000001,32.626661],"type":"Point"}
}