{
  "type": "Feature",
  "properties": {
    "iso:country":"US",
    "sg:address":"1003 Wrenwood Rd",
    "sg:city":"Florence",
    "sg:classifiers":[
        {
            "category":"Building & Trades",
            "subcategory":"Landscaping Services",
            "type":"Services"
        }
    ],
    "sg:phone":"+1 843 292 9469",
    "sg:postcode":"29505",
    "sg:province":"SC",
    "sg:tags":[
        "lawn",
        "maintenance",
        "grounds"
    ],
    "wof:name":"Quality Lawn Svc Inc",
    "wof:placetype":"venue"
},
  "geometry": {"coordinates":[-79.781811,34.165067],"type":"Point"}
}