{
  "type": "Feature",
  "properties": {
    "iso:country":"US",
    "sg:address":"62 Brigade St",
    "sg:city":"Charleston",
    "sg:classifiers":[
        {
            "category":"Manufacturing",
            "subcategory":"Metals",
            "type":"Manufacturing & Wholesale Goods"
        }
    ],
    "sg:phone":"+1 843 722 2211",
    "sg:postcode":"29403",
    "sg:province":"SC",
    "sg:tags":[
        "product",
        "furnace",
        "works",
        "wire",
        "blast"
    ],
    "wof:name":"Palmetto Wire Products Inc",
    "wof:placetype":"venue"
},
  "geometry": {"coordinates":[-79.949034,32.810108],"type":"Point"}
}