{
  "type": "Feature",
  "properties": {
    "iso:country":"US",
    "sg:address":"2817 Sunset Forest Rd",
    "sg:city":"Anderson",
    "sg:classifiers":[
        {
            "category":"Building & Trades",
            "subcategory":"Construction",
            "type":"Services"
        }
    ],
    "sg:phone":"+1 864 226 5448",
    "sg:postcode":"29626",
    "sg:province":"SC",
    "sg:tags":[
        "contractor"
    ],
    "wof:name":"Lecroy Roofing Co",
    "wof:placetype":"venue"
},
  "geometry": {"coordinates":[-82.69530899999999,34.499761],"type":"Point"}
}