{
  "type": "Feature",
  "properties": {
    "addr:full":"7980 Haile Gold Mine Rd Kershaw SC 29067",
    "addr:housenumber":"7980",
    "addr:postcode":"29067",
    "addr:street":"Haile Gold Mine Rd",
    "iso:country":"US",
    "sg:address":"7980 Haile Gold Mine Rd",
    "sg:city":"Kershaw",
    "sg:classifiers":[
        {
            "category":"Organizations",
            "subcategory":"Religious Organization",
            "type":"Services"
        }
    ],
    "sg:phone":"+1 803 475 4242",
    "sg:postcode":"29067",
    "sg:province":"SC",
    "sg:tags":[
        "church"
    ],
    "wof:name":"Haile Gold Mine Baptist Church",
    "wof:placetype":"venue"
},
  "geometry": {"coordinates":[-80.510469,34.584112],"type":"Point"}
}