{
  "type": "Feature",
  "properties": {
    "addr:full":"2437 Willwood Dr Florence SC 29501",
    "addr:housenumber":"2437",
    "addr:postcode":"29501",
    "addr:street":"Willwood Dr",
    "iso:country":"US",
    "sg:address":"2437 Willwood Dr",
    "sg:city":"Florence",
    "sg:classifiers":[
        {
            "category":"Personal",
            "type":"Services"
        }
    ],
    "sg:phone":"+1 843 777 3200",
    "sg:postcode":"29501",
    "sg:province":"SC",
    "sg:tags":[
        "therapist",
        "massage"
    ],
    "wof:name":"Spa At Mcleod",
    "wof:placetype":"venue"
},
  "geometry": {"coordinates":[-79.818932,34.185439],"type":"Point"}
}