{
  "type": "Feature",
  "properties": {
    "addr:full":"405 Drayton Ct Summerville SC 29483",
    "addr:housenumber":"405",
    "addr:postcode":"29483",
    "addr:street":"Drayton Ct",
    "iso:country":"US",
    "sg:address":"405 Drayton Ct",
    "sg:city":"Summerville",
    "sg:classifiers":[
        {
            "category":"Professional",
            "subcategory":"Business Services",
            "type":"Services"
        }
    ],
    "sg:phone":"+1 843 695 0975",
    "sg:postcode":"29483",
    "sg:province":"SC",
    "sg:tags":[
        "process",
        "server"
    ],
    "wof:name":"Proserv",
    "wof:placetype":"venue"
},
  "geometry": {"coordinates":[-80.10607299999999,33.032393],"type":"Point"}
}