{
  "type": "Feature",
  "properties": {
    "addr:full":"249 Bird St Union SC 29379",
    "addr:housenumber":"249",
    "addr:postcode":"29379",
    "addr:street":"Bird St",
    "iso:country":"US",
    "sg:address":"249 Bird St",
    "sg:city":"Union",
    "sg:classifiers":[
        {
            "category":"Organizations",
            "subcategory":"Religious Organization",
            "type":"Services"
        }
    ],
    "sg:phone":"+1 864 427 0214",
    "sg:postcode":"29379",
    "sg:province":"SC",
    "sg:tags":[
        "church"
    ],
    "wof:name":"New Chapel AME Church",
    "wof:placetype":"venue"
},
  "geometry": {"coordinates":[-81.62384400000001,34.694252],"type":"Point"}
}