{
  "type": "Feature",
  "properties": {
    "iso:country":"US",
    "sg:address":"701 Cedar Lane Rd",
    "sg:city":"Greenville",
    "sg:classifiers":[
        {
            "category":"Autos & Motor Vehicles",
            "subcategory":"Fuel & Gas Station",
            "type":"Retail Goods"
        }
    ],
    "sg:phone":"+1 864 246 8297",
    "sg:postcode":"29617",
    "sg:province":"SC",
    "sg:tags":[
        "oil"
    ],
    "wof:name":"Spinx/Sunoco",
    "wof:placetype":"venue"
},
  "geometry": {"coordinates":[-82.430808,34.871037],"type":"Point"}
}