{
  "type": "Feature",
  "properties": {
    "addr:full":"91 Mathews Dr Hilton Head Island SC 29926",
    "addr:housenumber":"91",
    "addr:postcode":"29926",
    "addr:street":"Mathews Dr",
    "iso:country":"US",
    "sg:address":"91 Mathews Dr",
    "sg:city":"Hilton Head Island",
    "sg:classifiers":[
        {
            "category":"Banks & Credit Unions",
            "subcategory":"Bank",
            "type":"Services"
        }
    ],
    "sg:phone":"+1 843 689 2825",
    "sg:postcode":"29926",
    "sg:province":"SC",
    "sg:tags":[
        "consumer",
        "finance"
    ],
    "wof:name":"Citizens Finance Inc",
    "wof:placetype":"venue"
},
  "geometry": {"coordinates":[-80.702657,32.212781],"type":"Point"}
}