{
  "type": "Feature",
  "properties": {
    "iso:country":"US",
    "sg:address":"117 Vera Holliday Rd",
    "sg:city":"Six Mile",
    "sg:classifiers":[
        {
            "category":"Building & Trades",
            "subcategory":"Construction",
            "type":"Services"
        }
    ],
    "sg:phone":"+1 864 868 2127",
    "sg:postcode":"29682",
    "sg:province":"SC",
    "sg:tags":[
        "heavy"
    ],
    "wof:name":"William H Cochran Traffic",
    "wof:placetype":"venue"
},
  "geometry": {"coordinates":[-82.816174,34.844122],"type":"Point"}
}