{
  "type": "Feature",
  "properties": {
    "iso:country":"US",
    "sg:address":"1944 Davant Cir",
    "sg:city":"Mt Pleasant",
    "sg:classifiers":[
        {
            "category":"Professional",
            "subcategory":"Engineering",
            "type":"Services"
        }
    ],
    "sg:phone":"+1 843 856 9989",
    "sg:postcode":"29464",
    "sg:province":"SC",
    "sg:tags":[
        "engineer"
    ],
    "wof:name":"Campbell & Paris Engineers",
    "wof:placetype":"venue"
},
  "geometry": {"coordinates":[-79.835472,32.856395],"type":"Point"}
}