{
  "type": "Feature",
  "properties": {
    "iso:country":"US",
    "sg:address":"925 Magnolia Bluff Cir",
    "sg:city":"Beaufort",
    "sg:classifiers":[
        {
            "category":"Professional",
            "subcategory":"Art Services",
            "type":"Services"
        }
    ],
    "sg:phone":"+1 843 522 3413",
    "sg:postcode":"29902",
    "sg:province":"SC",
    "sg:tags":[
        "photographer"
    ],
    "wof:name":"Harold Boyd Photography",
    "wof:placetype":"venue"
},
  "geometry": {"coordinates":[-80.72924999999999,32.381551],"type":"Point"}
}