{
  "type": "Feature",
  "properties": {
    "iso:country":"US",
    "sg:address":"462 Triangle Rd",
    "sg:city":"Lexington",
    "sg:classifiers":[
        {
            "category":"Building & Trades",
            "subcategory":"Construction",
            "type":"Services"
        }
    ],
    "sg:phone":"+1 803 359 9306",
    "sg:postcode":"29072",
    "sg:province":"SC",
    "sg:tags":[
        "carpentry",
        "contractor"
    ],
    "wof:name":"Davids Cabinets & Interio",
    "wof:placetype":"venue"
},
  "geometry": {"coordinates":[-81.341345,33.963507],"type":"Point"}
}