{
  "type": "Feature",
  "properties": {
    "iso:country":"US",
    "sg:address":"390 Lakewood Dr",
    "sg:city":"Sumter",
    "sg:classifiers":[
        {
            "category":"Social Services",
            "type":"Services"
        }
    ],
    "sg:phone":"+1 803 478 5586",
    "sg:postcode":"29150",
    "sg:province":"SC",
    "sg:tags":[
        "mission"
    ],
    "wof:name":"Prayer House Mission",
    "wof:placetype":"venue"
},
  "geometry": {"coordinates":[-80.362966,33.845355],"type":"Point"}
}