{
  "type": "Feature",
  "properties": {
    "iso:country":"US",
    "sg:address":"902 Highmarket St",
    "sg:city":"Georgetown",
    "sg:classifiers":[
        {
            "category":"Professional",
            "type":"Services"
        }
    ],
    "sg:phone":"+1 843 546 8861",
    "sg:postcode":"29440",
    "sg:province":"SC",
    "sg:tags":[
        "establishment"
    ],
    "wof:name":"Positive Options Child Ctr",
    "wof:placetype":"venue"
},
  "geometry": {"coordinates":[-79.283697,33.370475],"type":"Point"}
}