{
  "type": "Feature",
  "properties": {
    "addr:full":"2812 W Palmetto St Florence SC 29501",
    "addr:housenumber":"2812",
    "addr:postcode":"29501",
    "addr:street":"W Palmetto St",
    "iso:country":"US",
    "sg:address":"2812 W Palmetto St",
    "sg:city":"Florence",
    "sg:classifiers":[
        {
            "category":"Organizations",
            "subcategory":"Religious Organization",
            "type":"Services"
        }
    ],
    "sg:phone":"+1 843 665 2463",
    "sg:postcode":"29501",
    "sg:province":"SC",
    "sg:tags":[
        "church"
    ],
    "wof:name":"First Church Of The Nazarene",
    "wof:placetype":"venue"
},
  "geometry": {"coordinates":[-79.831637,34.175557],"type":"Point"}
}