{
  "type": "Feature",
  "properties": {
    "addr:full":"104 W Georgia Rd Simpsonville SC 29681",
    "addr:housenumber":"104",
    "addr:postcode":"29681",
    "addr:street":"W Georgia Rd",
    "iso:country":"US",
    "sg:address":"104 W Georgia Rd",
    "sg:city":"Simpsonville",
    "sg:classifiers":[
        {
            "category":"Health Services",
            "subcategory":"Health Practitioner",
            "type":"Services"
        }
    ],
    "sg:phone":"+1 864 228 8222",
    "sg:postcode":"29681",
    "sg:province":"SC",
    "sg:tags":[
        "nutrition",
        "consultant"
    ],
    "wof:name":"Solutions In Healthcare",
    "wof:placetype":"venue"
},
  "geometry": {"coordinates":[-82.258368,34.739674],"type":"Point"}
}