{
  "type": "Feature",
  "properties": {
    "iso:country":"US",
    "sg:address":"1366 Amelia Ave",
    "sg:city":"Rock Hill",
    "sg:classifiers":[
        {
            "category":"Education",
            "subcategory":"Special Training",
            "type":"Public Place"
        }
    ],
    "sg:phone":"+1 803 366 1908",
    "sg:postcode":"29732",
    "sg:province":"SC",
    "sg:tags":[
        "tutoring"
    ],
    "wof:name":"Least Of These",
    "wof:placetype":"venue"
},
  "geometry": {"coordinates":[-81.021243,34.957616],"type":"Point"}
}