{
  "type": "Feature",
  "properties": {
    "iso:country":"US",
    "sg:address":"16 Berryhill Rd",
    "sg:city":"Columbia",
    "sg:classifiers":[
        {
            "category":"Professional",
            "subcategory":"Accounting & Tax Preparation",
            "type":"Services"
        }
    ],
    "sg:phone":"+1 803 798 8884",
    "sg:postcode":"29210",
    "sg:province":"SC",
    "sg:tags":[
        "accountant"
    ],
    "wof:name":"Tourville and Associates",
    "wof:placetype":"venue"
},
  "geometry": {"coordinates":[-81.118599,34.043999],"type":"Point"}
}