{
  "type": "Feature",
  "properties": {
    "iso:country":"US",
    "sg:address":"680 Serotina Ct",
    "sg:city":"Mount Pleasant",
    "sg:classifiers":[
        {
            "category":"Wholesale",
            "subcategory":"Plants",
            "type":"Manufacturing & Wholesale Goods"
        }
    ],
    "sg:phone":"+1 843 884 9021",
    "sg:postcode":"29464",
    "sg:province":"SC",
    "sg:tags":[
        "supply"
    ],
    "wof:name":"Roses Coming Up",
    "wof:placetype":"venue"
},
  "geometry": {"coordinates":[-79.85567,32.826304],"type":"Point"}
}