{
  "type": "Feature",
  "properties": {
    "iso:country":"US",
    "sg:address":"1306 Celebrity Cir",
    "sg:city":"Myrtle Beach",
    "sg:classifiers":[
        {
            "category":"Shopping",
            "subcategory":"Clothing, Apparel, & Fashions",
            "type":"Retail Goods"
        }
    ],
    "sg:phone":"+1 843 916 0412",
    "sg:postcode":"29577",
    "sg:province":"SC",
    "sg:website":"www.planethollywood.com",
    "wof:name":"Planet Hollywood Retail Store",
    "wof:placetype":"venue"
},
  "geometry": {"coordinates":[-78.880787,33.71951],"type":"Point"}
}