{
  "type": "Feature",
  "properties": {
    "iso:country":"US",
    "sg:address":"4317 McCombs Rd",
    "sg:city":"Ravenel",
    "sg:classifiers":[
        {
            "category":"Professional",
            "subcategory":"Accounting & Tax Preparation",
            "type":"Services"
        }
    ],
    "sg:phone":"+1 843 763 1333",
    "sg:postcode":"29470",
    "sg:province":"SC",
    "sg:tags":[
        "return",
        "filing"
    ],
    "wof:name":"Hollywood Income Tax Svc",
    "wof:placetype":"venue"
},
  "geometry": {"coordinates":[-80.149015,32.781418],"type":"Point"}
}