{
  "type": "Feature",
  "properties": {
    "addr:full":"1508 Highland Ave Camden SC 29020",
    "addr:housenumber":"1508",
    "addr:postcode":"29020",
    "addr:street":"Highland Ave",
    "iso:country":"US",
    "sg:address":"1508 Highland Ave",
    "sg:city":"Camden",
    "sg:classifiers":[
        {
            "category":"Home & Garden",
            "subcategory":"Hardware",
            "type":"Retail Goods"
        }
    ],
    "sg:phone":"+1 803 432 3248",
    "sg:postcode":"29020",
    "sg:province":"SC",
    "sg:tags":[
        "tool",
        "used"
    ],
    "wof:name":"Robinson Supply",
    "wof:placetype":"venue"
},
  "geometry": {"coordinates":[-80.60989499999999,34.25171],"type":"Point"}
}