{
  "type": "Feature",
  "properties": {
    "addr:full":"6686 Waxhaw Hwy Lancaster SC 29720",
    "addr:postcode":"6686;29720",
    "addr:street":"Waxhaw Hwy",
    "iso:country":"US",
    "sg:address":"6686 Waxhaw Hwy",
    "sg:city":"Lancaster",
    "sg:classifiers":[
        {
            "category":"Autos & Motor Vehicles",
            "subcategory":"Auto Supplies",
            "type":"Retail Goods"
        }
    ],
    "sg:phone":"+1 803 285 5332",
    "sg:postcode":"29720",
    "sg:province":"SC",
    "sg:tags":[
        "tire"
    ],
    "wof:name":"Five Twenty One Tire & Cycle",
    "wof:placetype":"venue"
},
  "geometry": {"coordinates":[-80.808587,34.909427],"type":"Point"}
}