{
  "type": "Feature",
  "properties": {
    "addr:full":"46 S Jacob Smart Blvd Ridgeland SC 29936",
    "addr:housenumber":"46",
    "addr:postcode":"29936",
    "addr:street":"S Jacob Smart Blvd",
    "iso:country":"US",
    "sg:address":"46 S Jacob Smart Blvd",
    "sg:city":"Ridgeland",
    "sg:classifiers":[
        {
            "category":"Home & Garden",
            "subcategory":"Building Materials",
            "type":"Retail Goods"
        }
    ],
    "sg:phone":"+1 843 684 0426",
    "sg:postcode":"29936",
    "sg:province":"SC",
    "sg:tags":[
        "glass",
        "window",
        "plate"
    ],
    "wof:name":"White Water Auto Glass Svc",
    "wof:placetype":"venue"
},
  "geometry": {"coordinates":[-80.98236199999999,32.476498],"type":"Point"}
}