{
  "type": "Feature",
  "properties": {
    "addr:full":"1326 E River St Anderson SC 29624",
    "addr:housenumber":"1326",
    "addr:postcode":"29624",
    "addr:street":"E River St",
    "iso:country":"US",
    "sg:address":"1326 E River St",
    "sg:city":"Anderson",
    "sg:classifiers":[
        {
            "category":"Wholesale",
            "subcategory":"Hardware",
            "type":"Manufacturing & Wholesale Goods"
        }
    ],
    "sg:phone":"+1 864 226 9131",
    "sg:postcode":"29624",
    "sg:province":"SC",
    "sg:tags":[
        "plumbing",
        "fixture",
        "supply"
    ],
    "wof:name":"Parnell-Martin-The Carolinas",
    "wof:placetype":"venue"
},
  "geometry": {"coordinates":[-82.632582,34.495719],"type":"Point"}
}