{
  "type": "Feature",
  "properties": {
    "iso:country":"US",
    "sg:address":"2006 Bear Village Ct",
    "sg:city":"Newberry",
    "sg:classifiers":[
        {
            "category":"Banks & Credit Unions",
            "subcategory":"Bank",
            "type":"Services"
        }
    ],
    "sg:phone":"+1 803 321 2325",
    "sg:postcode":"29108",
    "sg:province":"SC",
    "sg:tags":[
        "personal",
        "institution"
    ],
    "wof:name":"Advance America",
    "wof:placetype":"venue"
},
  "geometry": {"coordinates":[-81.60842700000001,34.296397],"type":"Point"}
}