{
  "type": "Feature",
  "properties": {
    "iso:country":"US",
    "sg:address":"125 Bull St",
    "sg:city":"Charleston",
    "sg:classifiers":[
        {
            "category":"Museum",
            "type":"Entertainment"
        }
    ],
    "sg:phone":"+1 843 953 7609",
    "sg:postcode":"29401",
    "sg:province":"SC",
    "sg:website":"www.cofc.edu",
    "wof:name":"Avery Research Ctr",
    "wof:placetype":"venue"
},
  "geometry": {"coordinates":[-79.94488800000001,32.780679],"type":"Point"}
}