{
  "type": "Feature",
  "properties": {
    "iso:country":"US",
    "sg:address":"2570 N Pleasantburg Dr",
    "sg:city":"Greenville",
    "sg:classifiers":[
        {
            "category":"Manufacturing",
            "subcategory":"Tools & Machinery",
            "type":"Manufacturing & Wholesale Goods"
        }
    ],
    "sg:phone":"+1 864 233 0052",
    "sg:postcode":"29609",
    "sg:province":"SC",
    "sg:tags":[
        "equipment",
        "janitor",
        "supply"
    ],
    "sg:website":"www.kicinc.com",
    "wof:name":"KIC Inc",
    "wof:placetype":"venue"
},
  "geometry": {"coordinates":[-82.378882,34.890949],"type":"Point"}
}