{
  "type": "Feature",
  "properties": {
    "iso:country":"US",
    "sg:address":"118 Hall St",
    "sg:city":"Saint Matthews",
    "sg:classifiers":[
        {
            "category":"Freight",
            "type":"Transportation"
        }
    ],
    "sg:phone":"+1 803 707 3449",
    "sg:postcode":"29135",
    "sg:province":"SC",
    "wof:name":"Denae Shane H Trnsporation LLC",
    "wof:placetype":"venue"
},
  "geometry": {"coordinates":[-80.788374,33.668799],"type":"Point"}
}