{
  "type": "Feature",
  "properties": {
    "iso:country":"US",
    "sg:address":"3713 Dorchester Rd",
    "sg:city":"Charleston",
    "sg:classifiers":[
        {
            "category":"Restaurant",
            "type":"Food & Drink"
        }
    ],
    "sg:phone":"+1 843 747 9198",
    "sg:postcode":"29405",
    "sg:province":"SC",
    "wof:name":"Alex's Restaurant",
    "wof:placetype":"venue"
},
  "geometry": {"coordinates":[-79.99045,32.853196],"type":"Point"}
}