{
  "type": "Feature",
  "properties": {
    "addr:full":"504 Hampton Ave Pickens SC 29671",
    "addr:housenumber":"504",
    "addr:postcode":"29671",
    "addr:street":"Hampton Ave",
    "iso:country":"US",
    "sg:address":"504 Hampton Ave",
    "sg:city":"Pickens",
    "sg:classifiers":[
        {
            "category":"Health Services",
            "subcategory":"Doctor",
            "type":"Services"
        }
    ],
    "sg:phone":"+1 864 878 7915",
    "sg:postcode":"29671",
    "sg:province":"SC",
    "sg:tags":[
        "dentist"
    ],
    "wof:name":"Pickens Dental Assoc",
    "wof:placetype":"venue"
},
  "geometry": {"coordinates":[-82.70183400000001,34.878478],"type":"Point"}
}