{
  "type": "Feature",
  "properties": {
    "iso:country":"US",
    "sg:address":"1201 McKibben St",
    "sg:city":"Newberry",
    "sg:classifiers":[
        {
            "category":"Arts & Performance",
            "subcategory":"Theater",
            "type":"Entertainment"
        }
    ],
    "sg:phone":"+1 803 276 6264",
    "sg:postcode":"29108",
    "sg:province":"SC",
    "wof:name":"Newberry Opera House-Box Ofc",
    "wof:placetype":"venue"
},
  "geometry": {"coordinates":[-81.620502,34.274478],"type":"Point"}
}