{
  "type": "Feature",
  "properties": {
    "iso:country":"US",
    "sg:address":"2198 Southport Rd",
    "sg:city":"Spartanburg",
    "sg:classifiers":[
        {
            "category":"Restaurant",
            "type":"Food & Drink"
        }
    ],
    "sg:menulink":"http://www.allmenus.com/sc/spartanburg/154842-hardees/menu/",
    "sg:phone":"+1 864 585 5528",
    "sg:postcode":"29306",
    "sg:province":"SC",
    "sg:tags":[
        "burger",
        "american"
    ],
    "wof:name":"Hardee's",
    "wof:placetype":"venue"
},
  "geometry": {"coordinates":[-81.88717699999999,34.92146],"type":"Point"}
}