{
  "type": "Feature",
  "properties": {
    "addr:full":"1256 Old Gilliard Rd Ridgeville SC 29472",
    "addr:housenumber":"1256",
    "addr:postcode":"29472",
    "addr:street":"Old Gilliard Rd",
    "iso:country":"US",
    "sg:address":"1256 Old Gilliard Rd",
    "sg:city":"Ridgeville",
    "sg:classifiers":[
        {
            "category":"Restaurant",
            "type":"Food & Drink"
        }
    ],
    "sg:phone":"+1 843 688 6000",
    "sg:postcode":"29472",
    "sg:province":"SC",
    "wof:name":"Sista's Soul Food",
    "wof:placetype":"venue"
},
  "geometry": {"coordinates":[-80.305695,33.154852],"type":"Point"}
}