{
  "type": "Feature",
  "properties": {
    "iso:country":"US",
    "sg:address":"125 W Stone Ave",
    "sg:city":"Greenville",
    "sg:classifiers":[
        {
            "category":"Shopping",
            "subcategory":"Hobbies, Toys, & Games",
            "type":"Retail Goods"
        }
    ],
    "sg:phone":"+1 864 233 1070",
    "sg:postcode":"29609",
    "sg:province":"SC",
    "sg:tags":[
        "merchandise"
    ],
    "wof:name":"Tempo Gallery & Art Supply",
    "wof:placetype":"venue"
},
  "geometry": {"coordinates":[-82.39798999999999,34.861805],"type":"Point"}
}