{
  "type": "Feature",
  "properties": {
    "iso:country":"US",
    "sg:address":"40 Saluda Ave",
    "sg:city":"Ware Shoals",
    "sg:classifiers":[
        {
            "category":"Manufacturing",
            "subcategory":"Rubber & Plastics",
            "type":"Manufacturing & Wholesale Goods"
        }
    ],
    "sg:phone":"+1 864 456 2727",
    "sg:postcode":"29692",
    "sg:province":"SC",
    "wof:name":"Quality Coating & Finishing",
    "wof:placetype":"venue"
},
  "geometry": {"coordinates":[-82.246404,34.399552],"type":"Point"}
}