{
  "type": "Feature",
  "properties": {
    "addr:full":"1000 Mill St Camden SC 29020",
    "addr:housenumber":"1000",
    "addr:postcode":"29020",
    "addr:street":"Mill St",
    "iso:country":"US",
    "sg:address":"1000 Mill St",
    "sg:city":"Camden",
    "sg:classifiers":[
        {
            "category":"Home & Garden",
            "subcategory":"Garden Supply",
            "type":"Retail Goods"
        }
    ],
    "sg:phone":"+1 803 432 3732",
    "sg:postcode":"29020",
    "sg:province":"SC",
    "sg:tags":[
        "landscaping",
        "equipment"
    ],
    "wof:name":"Garden Gazebo",
    "wof:placetype":"venue"
},
  "geometry": {"coordinates":[-80.59886299999999,34.246915],"type":"Point"}
}