{
  "type": "Feature",
  "properties": {
    "iso:country":"US",
    "sg:address":"7701 Augusta Rd",
    "sg:city":"Piedmont",
    "sg:classifiers":[
        {
            "category":"Food & Beverages",
            "subcategory":"Groceries & Convenience Stores",
            "type":"Retail Goods"
        }
    ],
    "sg:phone":"+1 864 277 7225",
    "sg:postcode":"29605",
    "sg:province":"SC",
    "sg:tags":[
        "grocer"
    ],
    "wof:name":"Coker's",
    "wof:placetype":"venue"
},
  "geometry": {"coordinates":[-82.390462,34.734986],"type":"Point"}
}