{
  "type": "Feature",
  "properties": {
    "iso:country":"US",
    "sg:address":"45 Derrick Rd",
    "sg:city":"Johnston",
    "sg:phone":"+1 803 275 2933",
    "sg:postcode":"29832",
    "sg:province":"SC",
    "sg:tags":[
        "farm",
        "soybean",
        "cotton"
    ],
    "wof:name":"Derrick Farm",
    "wof:placetype":"venue"
},
  "geometry": {"coordinates":[-81.75013800000001,33.755252],"type":"Point"}
}