{
  "type": "Feature",
  "properties": {
    "addr:full":"153 N Congress St Winnsboro SC 29180",
    "addr:housenumber":"153",
    "addr:postcode":"29180",
    "addr:street":"N Congress St",
    "iso:country":"US",
    "sg:address":"153 N Congress St",
    "sg:city":"Winnsboro",
    "sg:classifiers":[
        {
            "category":"Banks & Credit Unions",
            "subcategory":"Bank",
            "type":"Services"
        }
    ],
    "sg:phone":"+1 803 635 5238",
    "sg:postcode":"29180",
    "sg:province":"SC",
    "sg:tags":[
        "loan"
    ],
    "wof:name":"Regional Finance Corp",
    "wof:placetype":"venue"
},
  "geometry": {"coordinates":[-81.087001,34.381653],"type":"Point"}
}