{
  "type": "Feature",
  "properties": {
    "addr:full":"135 N Main St Bishopville SC 29010",
    "addr:housenumber":"135",
    "addr:postcode":"29010",
    "addr:street":"N Main St",
    "iso:country":"US",
    "sg:address":"135 N Main St",
    "sg:city":"Bishopville",
    "sg:classifiers":[
        {
            "category":"Banks & Credit Unions",
            "subcategory":"Bank",
            "type":"Services"
        }
    ],
    "sg:phone":"+1 803 484 4321",
    "sg:postcode":"29010",
    "sg:province":"SC",
    "sg:tags":[
        "personal",
        "institution"
    ],
    "wof:name":"World Finance",
    "wof:placetype":"venue"
},
  "geometry": {"coordinates":[-80.24789,34.218705],"type":"Point"}
}