{
  "type": "Feature",
  "properties": {
    "iso:country":"US",
    "sg:address":"25 Shaftesbury Rd",
    "sg:city":"Columbia",
    "sg:classifiers":[
        {
            "category":"Wholesale",
            "subcategory":"Non-durable Goods",
            "type":"Manufacturing & Wholesale Goods"
        }
    ],
    "sg:phone":"+1 803 776 2596",
    "sg:postcode":"29209",
    "sg:province":"SC",
    "wof:name":"Packman Collectibles",
    "wof:placetype":"venue"
},
  "geometry": {"coordinates":[-80.935498,33.979565],"type":"Point"}
}