{
  "type": "Feature",
  "properties": {
    "iso:country":"US",
    "sg:address":"7571 Rivers Ave",
    "sg:city":"North Charleston",
    "sg:classifiers":[
        {
            "category":"Restaurant",
            "type":"Food & Drink"
        }
    ],
    "sg:phone":"+1 843 824 1000",
    "sg:postcode":"29406",
    "sg:province":"SC",
    "wof:name":"Noisy Oyster",
    "wof:placetype":"venue"
},
  "geometry": {"coordinates":[-80.039813,32.93858],"type":"Point"}
}