{
  "type": "Feature",
  "properties": {
    "iso:country":"US",
    "sg:address":"1671 Springdale Dr",
    "sg:city":"Camden",
    "sg:classifiers":[
        {
            "category":"Restaurant",
            "type":"Food & Drink"
        }
    ],
    "sg:phone":"+1 803 713 8018",
    "sg:postcode":"29020",
    "sg:province":"SC",
    "wof:name":"Hong Kong Buffet",
    "wof:placetype":"venue"
},
  "geometry": {"coordinates":[-80.6413,34.255143],"type":"Point"}
}