{
  "type": "Feature",
  "properties": {
    "addr:full":"3510 Black River Rd Dalzell SC 29040",
    "addr:housenumber":"3510",
    "addr:postcode":"29040",
    "addr:street":"Black River Rd",
    "iso:country":"US",
    "sg:address":"3510 Black River Rd",
    "sg:city":"Dalzell",
    "sg:classifiers":[
        {
            "category":"Farming",
            "subcategory":"Livestock Farm",
            "type":"Manufacturing & Wholesale Goods"
        }
    ],
    "sg:phone":"+1 803 469 3742",
    "sg:postcode":"29040",
    "sg:province":"SC",
    "sg:tags":[
        "real",
        "beef",
        "lessor",
        "cattle",
        "property",
        "feedlot"
    ],
    "wof:name":"David C Ross Farm",
    "wof:placetype":"venue"
},
  "geometry": {"coordinates":[-80.428697,34.022673],"type":"Point"}
}