{
  "type": "Feature",
  "properties": {
    "iso:country":"US",
    "sg:address":"2101 Waterway Blvd",
    "sg:city":"Isle Of Palms",
    "sg:classifiers":[
        {
            "category":"Manufacturing",
            "subcategory":"Printing",
            "type":"Manufacturing & Wholesale Goods"
        }
    ],
    "sg:phone":"+1 843 886 6617",
    "sg:postcode":"29451",
    "sg:province":"SC",
    "sg:tags":[
        "cards",
        "commercial",
        "greeting",
        "mfg"
    ],
    "wof:name":"Spencer Studios",
    "wof:placetype":"venue"
},
  "geometry": {"coordinates":[-79.784364,32.793757],"type":"Point"}
}