{
  "type": "Feature",
  "properties": {
    "iso:country":"US",
    "sg:address":"215 Scotch Community Rd",
    "sg:city":"Mullins",
    "sg:classifiers":[
        {
            "category":"Social Services",
            "subcategory":"Child Care",
            "type":"Services"
        }
    ],
    "sg:phone":"+1 843 464 2611",
    "sg:postcode":"29574",
    "sg:province":"SC",
    "wof:name":"Mc Cray Tiny Tots",
    "wof:placetype":"venue"
},
  "geometry": {"coordinates":[-79.208371,34.199037],"type":"Point"}
}