{
  "type": "Feature",
  "properties": {
    "iso:country":"US",
    "sg:address":"480 E Bay St",
    "sg:city":"Charleston",
    "sg:classifiers":[
        {
            "category":"Real Estate",
            "subcategory":"Real Estate Agent",
            "type":"Services"
        }
    ],
    "sg:phone":"+1 843 577 4115",
    "sg:postcode":"29403",
    "sg:province":"SC",
    "wof:name":"Disher Hamrick & Myers Inc",
    "wof:placetype":"venue"
},
  "geometry": {"coordinates":[-79.929553,32.789092],"type":"Point"}
}