{
  "type": "Feature",
  "properties": {
    "addr:full":"2277 Sunset Blvd West Columbia SC 29169",
    "addr:housenumber":"2277",
    "addr:postcode":"29169",
    "addr:street":"Sunset Blvd",
    "iso:country":"US",
    "sg:address":"2277 Sunset Blvd",
    "sg:city":"West Columbia",
    "sg:classifiers":[
        {
            "category":"Retail",
            "subcategory":"Veterinary Services",
            "type":"Services"
        }
    ],
    "sg:phone":"+1 803 939 9061",
    "sg:postcode":"29169",
    "sg:province":"SC",
    "wof:name":"Kelly E Goodson",
    "wof:placetype":"venue"
},
  "geometry": {"coordinates":[-81.102737,34.001131],"type":"Point"}
}