{
  "type": "Feature",
  "properties": {
    "iso:country":"US",
    "sg:address":"1626 E North St",
    "sg:city":"Greenville",
    "sg:classifiers":[
        {
            "category":"Wholesale",
            "subcategory":"Groceries",
            "type":"Manufacturing & Wholesale Goods"
        }
    ],
    "sg:phone":"+1 864 242 1380",
    "sg:postcode":"29607",
    "sg:province":"SC",
    "sg:tags":[
        "baker"
    ],
    "wof:name":"Piece A Cake",
    "wof:placetype":"venue"
},
  "geometry": {"coordinates":[-82.37411899999999,34.860479],"type":"Point"}
}