{
  "type": "Feature",
  "properties": {
    "iso:country":"US",
    "sg:address":"7313 College St",
    "sg:city":"Irmo",
    "sg:classifiers":[
        {
            "category":"Insurance",
            "subcategory":"Insurance Agent",
            "type":"Services"
        }
    ],
    "sg:phone":"+1 803 732 7907",
    "sg:postcode":"29063",
    "sg:province":"SC",
    "wof:name":"Nationwide Insurance",
    "wof:placetype":"venue"
},
  "geometry": {"coordinates":[-81.174104,34.090531],"type":"Point"}
}