{
  "type": "Feature",
  "properties": {
    "addr:full":"4181 Ladson Rd Ladson SC 29456",
    "addr:housenumber":"4181",
    "addr:postcode":"29456",
    "addr:street":"Ladson Rd",
    "iso:country":"US",
    "sg:address":"4181 Ladson Rd",
    "sg:city":"Ladson",
    "sg:classifiers":[
        {
            "category":"Retail",
            "subcategory":"Auto Repair",
            "type":"Services"
        }
    ],
    "sg:phone":"+1 843 873 4071",
    "sg:postcode":"29456",
    "sg:province":"SC",
    "sg:tags":[
        "automobile",
        "customizing"
    ],
    "wof:name":"Show Zone",
    "wof:placetype":"venue"
},
  "geometry": {"coordinates":[-80.145011,32.969045],"type":"Point"}
}