{
  "type": "Feature",
  "properties": {
    "iso:country":"US",
    "sg:address":"520 S Lee St",
    "sg:city":"Bishopville",
    "sg:classifiers":[
        {
            "category":"Real Estate",
            "subcategory":"Real Estate Operator",
            "type":"Services"
        }
    ],
    "sg:phone":"+1 803 484 5753",
    "sg:postcode":"29010",
    "sg:province":"SC",
    "sg:tags":[
        "apartment"
    ],
    "wof:name":"Cloverleaf Apartments",
    "wof:placetype":"venue"
},
  "geometry": {"coordinates":[-80.25428599999999,34.208242],"type":"Point"}
}