{
  "type": "Feature",
  "properties": {
    "iso:country":"US",
    "sg:address":"341 Historic Ln",
    "sg:city":"Pawleys Island",
    "sg:classifiers":[
        {
            "category":"Professional",
            "subcategory":"Engineering",
            "type":"Services"
        }
    ],
    "sg:phone":"+1 843 237 7162",
    "sg:postcode":"29585",
    "sg:province":"SC",
    "sg:tags":[
        "engineer"
    ],
    "wof:name":"S J Consultants",
    "wof:placetype":"venue"
},
  "geometry": {"coordinates":[-79.11938600000001,33.482204],"type":"Point"}
}