{
  "type": "Feature",
  "properties": {
    "iso:country":"US",
    "sg:address":"1612 Craig Rd",
    "sg:city":"Rock Hill",
    "sg:classifiers":[
        {
            "category":"Building & Trades",
            "subcategory":"Construction",
            "type":"Services"
        }
    ],
    "sg:phone":"+1 803 327 3439",
    "sg:postcode":"29730",
    "sg:province":"SC",
    "sg:tags":[
        "house"
    ],
    "wof:name":"Dno Constr Services",
    "wof:placetype":"venue"
},
  "geometry": {"coordinates":[-81.05854100000001,34.861543],"type":"Point"}
}