{
  "type": "Feature",
  "properties": {
    "iso:country":"US",
    "sg:address":"1234 Sim Abrams Rd",
    "sg:city":"Newberry",
    "sg:classifiers":[
        {
            "category":"Professional",
            "subcategory":"Management & Consulting",
            "type":"Services"
        }
    ],
    "sg:phone":"+1 803 276 0717",
    "sg:postcode":"29108",
    "sg:province":"SC",
    "sg:tags":[
        "insurance"
    ],
    "wof:name":"Rickey O & Betsy W Chapman",
    "wof:placetype":"venue"
},
  "geometry": {"coordinates":[-81.782822,34.299397],"type":"Point"}
}