{
  "type": "Feature",
  "properties": {
    "iso:country":"US",
    "sg:address":"320 Bethany Rd",
    "sg:city":"Simpsonville",
    "sg:classifiers":[
        {
            "category":"Government",
            "subcategory":"Fire Station",
            "type":"Public Place"
        }
    ],
    "sg:phone":"+1 864 000 1111",
    "sg:postcode":"29681",
    "sg:province":"SC",
    "sg:tags":[
        "department"
    ],
    "wof:name":"East Simpsonville Fire Dept",
    "wof:placetype":"venue"
},
  "geometry": {"coordinates":[-82.191589,34.762165],"type":"Point"}
}