{
  "type": "Feature",
  "properties": {
    "iso:country":"US",
    "sg:address":"29 Pine Grove Rd",
    "sg:city":"Beaufort",
    "sg:classifiers":[
        {
            "category":"Organizations",
            "subcategory":"Religious Organization",
            "type":"Services"
        }
    ],
    "sg:phone":"+1 843 470 1796",
    "sg:postcode":"29906",
    "sg:province":"SC",
    "sg:tags":[
        "church"
    ],
    "wof:name":"St John Baptist Church",
    "wof:placetype":"venue"
},
  "geometry": {"coordinates":[-80.748544,32.443056],"type":"Point"}
}