{
  "type": "Feature",
  "properties": {
    "iso:country":"US",
    "sg:address":"148 Wateree Dr",
    "sg:city":"Santee",
    "sg:classifiers":[
        {
            "category":"Manufacturing",
            "subcategory":"Petroleum Products",
            "type":"Manufacturing & Wholesale Goods"
        }
    ],
    "sg:phone":"+1 803 854 2738",
    "sg:postcode":"29142",
    "sg:province":"SC",
    "sg:tags":[
        "treating",
        "lubricating",
        "oil",
        "mfg",
        "metal",
        "clean",
        "compound"
    ],
    "wof:name":"Metalube Inc",
    "wof:placetype":"venue"
},
  "geometry": {"coordinates":[-80.45124199999999,33.489488],"type":"Point"}
}