{
  "type": "Feature",
  "properties": {
    "iso:country":"US",
    "sg:address":"1509 State Hwy 246 N",
    "sg:city":"Greenwood",
    "sg:classifiers":[
        {
            "category":"Freight",
            "type":"Transportation"
        }
    ],
    "sg:phone":"+1 864 229 9796",
    "sg:postcode":"29649",
    "sg:province":"SC",
    "sg:tags":[
        "operator",
        "local",
        "trucking"
    ],
    "wof:name":"Quarles Trucking",
    "wof:placetype":"venue"
},
  "geometry": {"coordinates":[-82.133496,34.28021],"type":"Point"}
}