{
  "type": "Feature",
  "properties": {
    "iso:country":"US",
    "sg:address":"801 E Greenwood St",
    "sg:city":"Abbeville",
    "sg:classifiers":[
        {
            "category":"Travel",
            "subcategory":"Hotels & Motels",
            "type":"Entertainment"
        }
    ],
    "sg:phone":"+1 864 459 5041",
    "sg:postcode":"29620",
    "sg:province":"SC",
    "wof:name":"Abbevilla Motel",
    "wof:placetype":"venue"
},
  "geometry": {"coordinates":[-82.361695,34.180799],"type":"Point"}
}