{
  "type": "Feature",
  "properties": {
    "addr:full":"306 Graham St Florence SC 29501",
    "addr:housenumber":"306",
    "addr:postcode":"29501",
    "addr:street":"Graham St",
    "iso:country":"US",
    "sg:address":"306 Graham St",
    "sg:city":"Florence",
    "sg:classifiers":[
        {
            "category":"Health Services",
            "subcategory":"Nursing And Care Facility",
            "type":"Services"
        }
    ],
    "sg:phone":"+1 843 665 6674",
    "sg:postcode":"29501",
    "sg:province":"SC",
    "sg:tags":[
        "disabled",
        "independent",
        "for",
        "living"
    ],
    "wof:name":"Graham Street Community Res",
    "wof:placetype":"venue"
},
  "geometry": {"coordinates":[-79.77657499999999,34.191506],"type":"Point"}
}