{
  "type": "Feature",
  "properties": {
    "iso:country":"US",
    "sg:address":"1634 Sea Island Pkwy",
    "sg:city":"St Helena Island",
    "sg:classifiers":[
        {
            "category":"Restaurant",
            "type":"Food & Drink"
        }
    ],
    "sg:phone":"+1 843 838 5769",
    "sg:postcode":"29920",
    "sg:province":"SC",
    "wof:name":"Sand Dollar Tavern",
    "wof:placetype":"venue"
},
  "geometry": {"coordinates":[-80.508124,32.413034],"type":"Point"}
}