{
  "type": "Feature",
  "properties": {
    "iso:country":"US",
    "sg:address":"215 Park Ave SE",
    "sg:city":"Aiken",
    "sg:classifiers":[
        {
            "category":"Food & Beverages",
            "subcategory":"Liquor & Beverages",
            "type":"Retail Goods"
        }
    ],
    "sg:phone":"+1 803 649 9463",
    "sg:postcode":"29801",
    "sg:province":"SC",
    "sg:tags":[
        "alcoholic"
    ],
    "wof:name":"Wine Cellar",
    "wof:placetype":"venue"
},
  "geometry": {"coordinates":[-81.717666,33.557589],"type":"Point"}
}