{
  "type": "Feature",
  "properties": {
    "iso:country":"US",
    "sg:address":"2411 Savannah Hwy",
    "sg:city":"Charleston",
    "sg:classifiers":[
        {
            "category":"Professional",
            "subcategory":"Engineering",
            "type":"Services"
        }
    ],
    "sg:phone":"+1 843 556 4261",
    "sg:postcode":"29414",
    "sg:province":"SC",
    "sg:tags":[
        "engineer"
    ],
    "wof:name":"G Robert George & Assoc Inc",
    "wof:placetype":"venue"
},
  "geometry": {"coordinates":[-80.048019,32.792657],"type":"Point"}
}