{
  "type": "Feature",
  "properties": {
    "addr:full":"100 Church St Charleston SC 29401",
    "addr:housenumber":"100",
    "addr:postcode":"29401",
    "addr:street":"Church St",
    "iso:country":"US",
    "sg:address":"100 Church St",
    "sg:city":"Charleston",
    "sg:classifiers":[
        {
            "category":"Shopping",
            "subcategory":"Used Merchandise",
            "type":"Retail Goods"
        }
    ],
    "sg:phone":"+1 843 937 0808",
    "sg:postcode":"29401",
    "sg:province":"SC",
    "sg:tags":[
        "antique"
    ],
    "wof:name":"Church Street Galleries",
    "wof:placetype":"venue"
},
  "geometry": {"coordinates":[-79.92907099999999,32.774903],"type":"Point"}
}