{
  "type": "Feature",
  "properties": {
    "iso:country":"US",
    "sg:address":"320 Beechwood Dr",
    "sg:city":"Greer",
    "sg:classifiers":[
        {
            "category":"Professional",
            "type":"Services"
        }
    ],
    "sg:phone":"+1 864 879 8505",
    "sg:postcode":"29651",
    "sg:province":"SC",
    "sg:tags":[
        "establishment"
    ],
    "wof:name":"Phoenix Designs",
    "wof:placetype":"venue"
},
  "geometry": {"coordinates":[-82.296994,34.970622],"type":"Point"}
}