{
  "type": "Feature",
  "properties": {
    "addr:full":"170 Duck Pond Rd Walhalla SC 29691",
    "addr:housenumber":"170",
    "addr:postcode":"29691",
    "addr:street":"Duck Pond Rd",
    "iso:country":"US",
    "sg:address":"170 Duck Pond Rd",
    "sg:city":"Walhalla",
    "sg:classifiers":[
        {
            "category":"Autos & Motor Vehicles",
            "subcategory":"Automobile Sales",
            "type":"Retail Goods"
        }
    ],
    "sg:phone":"+1 864 718 0320",
    "sg:postcode":"29691",
    "sg:province":"SC",
    "sg:tags":[
        "aircraft"
    ],
    "wof:name":"Just Aircraft",
    "wof:placetype":"venue"
},
  "geometry": {"coordinates":[-83.082807,34.731098],"type":"Point"}
}