{
  "type": "Feature",
  "properties": {
    "iso:country":"US",
    "sg:address":"10 Derby Ct",
    "sg:city":"Bluffton",
    "sg:classifiers":[
        {
            "category":"Shopping",
            "subcategory":"Pharmacy",
            "type":"Retail Goods"
        }
    ],
    "sg:phone":"+1 843 836 1076",
    "sg:postcode":"29910",
    "sg:province":"SC",
    "wof:name":"Atlantic Healthcare",
    "wof:placetype":"venue"
},
  "geometry": {"coordinates":[-80.92109600000001,32.236474],"type":"Point"}
}