{
  "type": "Feature",
  "properties": {
    "addr:full":"308 E Butler Rd Mauldin SC 29662",
    "addr:housenumber":"308",
    "addr:postcode":"29662",
    "addr:street":"E Butler Rd",
    "iso:country":"US",
    "sg:address":"308 E Butler Rd",
    "sg:city":"Mauldin",
    "sg:classifiers":[
        {
            "category":"Personal",
            "subcategory":"Beauty Salon",
            "type":"Services"
        }
    ],
    "sg:phone":"+1 864 297 4237",
    "sg:postcode":"29662",
    "sg:province":"SC",
    "wof:name":"Scissors",
    "wof:placetype":"venue"
},
  "geometry": {"coordinates":[-82.30007500000001,34.782109],"type":"Point"}
}