{
  "type": "Feature",
  "properties": {
    "addr:full":"1015 5th Ave N Surfside Beach SC 29575",
    "addr:housenumber":"1015",
    "addr:postcode":"29575",
    "addr:street":"5Th Ave N",
    "iso:country":"US",
    "sg:address":"1015 5th Ave N",
    "sg:city":"Surfside Beach",
    "sg:classifiers":[
        {
            "category":"Building & Trades",
            "subcategory":"Plumbing",
            "type":"Services"
        }
    ],
    "sg:phone":"+1 843 238 4760",
    "sg:postcode":"29575",
    "sg:province":"SC",
    "sg:tags":[
        "plumbing",
        "contractor"
    ],
    "wof:name":"Mr Pipewrench",
    "wof:placetype":"venue"
},
  "geometry": {"coordinates":[-78.97866,33.616808],"type":"Point"}
}