{
  "type": "Feature",
  "properties": {
    "iso:country":"US",
    "sg:address":"150 Skull Shoals Rd",
    "sg:city":"Gaffney",
    "sg:classifiers":[
        {
            "category":"Food & Beverages",
            "subcategory":"Groceries & Convenience Stores",
            "type":"Retail Goods"
        }
    ],
    "sg:phone":"+1 864 488 2473",
    "sg:postcode":"29340",
    "sg:province":"SC",
    "wof:name":"Circle F Convenience Store",
    "wof:placetype":"venue"
},
  "geometry": {"coordinates":[-81.537655,34.894187],"type":"Point"}
}