{
  "type": "Feature",
  "properties": {
    "iso:country":"US",
    "sg:address":"620 Halton Rd",
    "sg:city":"Greenville",
    "sg:classifiers":[
        {
            "category":"Wholesale",
            "subcategory":"Durable Goods & Equipment",
            "type":"Manufacturing & Wholesale Goods"
        }
    ],
    "sg:phone":"+1 864 297 7298",
    "sg:postcode":"29607",
    "sg:province":"SC",
    "sg:tags":[
        "exporter"
    ],
    "wof:name":"Instant Photo Systems Inc",
    "wof:placetype":"venue"
},
  "geometry": {"coordinates":[-82.34083800000001,34.835636],"type":"Point"}
}