{
  "type": "Feature",
  "properties": {
    "iso:country":"US",
    "sg:address":"116 Capers St",
    "sg:city":"Greenville",
    "sg:classifiers":[
        {
            "category":"Building & Trades",
            "subcategory":"Construction",
            "type":"Services"
        }
    ],
    "sg:phone":"+1 864 232 3125",
    "sg:postcode":"29605",
    "sg:province":"SC",
    "sg:tags":[
        "home",
        "improvement"
    ],
    "wof:name":"Carter Co",
    "wof:placetype":"venue"
},
  "geometry": {"coordinates":[-82.398601,34.831222],"type":"Point"}
}