{
  "type": "Feature",
  "properties": {
    "addr:full":"436 N Duncan Byp Union SC 29379",
    "addr:housenumber":"436",
    "addr:postcode":"29379",
    "addr:street":"N Duncan Byp",
    "iso:country":"US",
    "sg:address":"436 N Duncan Byp",
    "sg:city":"Union",
    "sg:classifiers":[
        {
            "category":"Insurance",
            "subcategory":"Insurance Agent",
            "type":"Services"
        }
    ],
    "sg:phone":"+1 864 427 9274",
    "sg:postcode":"29379",
    "sg:province":"SC",
    "wof:name":"Allstate Insurance",
    "wof:placetype":"venue"
},
  "geometry": {"coordinates":[-81.63939000000001,34.720331],"type":"Point"}
}