{
  "type": "Feature",
  "properties": {
    "iso:country":"US",
    "sg:address":"3 S Park Cir",
    "sg:city":"Charleston",
    "sg:classifiers":[
        {
            "category":"Health Services",
            "subcategory":"Health Practitioner",
            "type":"Services"
        }
    ],
    "sg:phone":"+1 843 763 1799",
    "sg:postcode":"29407",
    "sg:province":"SC",
    "sg:tags":[
        "nutritionist"
    ],
    "wof:name":"T & T Tutor World Inc",
    "wof:placetype":"venue"
},
  "geometry": {"coordinates":[-80.030202,32.794048],"type":"Point"}
}