{
  "type": "Feature",
  "properties": {
    "iso:country":"US",
    "sg:address":"2142 Melbourne St",
    "sg:city":"Charleston",
    "sg:classifiers":[
        {
            "category":"Wholesale",
            "subcategory":"Groceries",
            "type":"Manufacturing & Wholesale Goods"
        }
    ],
    "sg:phone":"+1 843 744 3662",
    "sg:postcode":"29405",
    "sg:province":"SC",
    "sg:tags":[
        "grocer"
    ],
    "wof:name":"Cash & Carry Wholesale Grocery",
    "wof:placetype":"venue"
},
  "geometry": {"coordinates":[-79.991435,32.866549],"type":"Point"}
}