{
  "type": "Feature",
  "properties": {
    "iso:country":"US",
    "sg:address":"970 Gap Creek Rd",
    "sg:city":"Greer",
    "sg:classifiers":[
        {
            "category":"Personal",
            "subcategory":"Beauty Salon",
            "type":"Services"
        }
    ],
    "sg:phone":"+1 864 879 1104",
    "sg:postcode":"29365",
    "sg:province":"SC",
    "wof:name":"Sneak Preview Hair Salon",
    "wof:placetype":"venue"
},
  "geometry": {"coordinates":[-82.171178,34.955973],"type":"Point"}
}