{
  "type": "Feature",
  "properties": {
    "iso:country":"US",
    "sg:address":"480 Builders Rd",
    "sg:city":"Sumter",
    "sg:classifiers":[
        {
            "category":"Manufacturing",
            "subcategory":"Metals",
            "type":"Manufacturing & Wholesale Goods"
        }
    ],
    "sg:phone":"+1 803 506 2659",
    "sg:postcode":"29154",
    "sg:province":"SC",
    "sg:tags":[
        "tower"
    ],
    "wof:name":"Sba Towers Site Sc00356",
    "wof:placetype":"venue"
},
  "geometry": {"coordinates":[-80.412918,33.906745],"type":"Point"}
}