{
  "type": "Feature",
  "properties": {
    "iso:country":"US",
    "sg:address":"3251 N Pleasantburg Dr",
    "sg:city":"Greenville",
    "sg:classifiers":[
        {
            "category":"Shopping",
            "subcategory":"Clothing, Apparel, & Fashions",
            "type":"Retail Goods"
        }
    ],
    "sg:phone":"+1 864 232 0645",
    "sg:postcode":"29609",
    "sg:province":"SC",
    "sg:tags":[
        "family"
    ],
    "wof:name":"Old Navy",
    "wof:placetype":"venue"
},
  "geometry": {"coordinates":[-82.399838,34.889304],"type":"Point"}
}