{
  "type": "Feature",
  "properties": {
    "addr:full":"1861 Remount Rd North Charleston SC 29406",
    "addr:housenumber":"1861",
    "addr:postcode":"29406",
    "addr:street":"Remount Rd",
    "iso:country":"US",
    "sg:address":"1861 Remount Rd",
    "sg:city":"North Charleston",
    "sg:classifiers":[
        {
            "category":"Wholesale",
            "subcategory":"Machinery & Supplies",
            "type":"Manufacturing & Wholesale Goods"
        }
    ],
    "sg:phone":"+1 843 554 4115",
    "sg:postcode":"29406",
    "sg:province":"SC",
    "sg:tags":[
        "truck"
    ],
    "wof:name":"Dougherty Equipment Co Inc",
    "wof:placetype":"venue"
},
  "geometry": {"coordinates":[-80.00935800000001,32.900092],"type":"Point"}
}