{
  "type": "Feature",
  "properties": {
    "iso:country":"US",
    "sg:address":"641 Little Tony Ave",
    "sg:city":"Murrells Inlet",
    "sg:classifiers":[
        {
            "category":"Wholesale",
            "subcategory":"Machinery & Supplies",
            "type":"Manufacturing & Wholesale Goods"
        }
    ],
    "sg:phone":"+1 843 652 3112",
    "sg:postcode":"29576",
    "sg:province":"SC",
    "wof:name":"Granite Quarry Direct",
    "wof:placetype":"venue"
},
  "geometry": {"coordinates":[-79.046893,33.549655],"type":"Point"}
}