{
  "type": "Feature",
  "properties": {
    "addr:full":"3731 Oleander Dr Myrtle Beach SC 29577",
    "addr:housenumber":"3731",
    "addr:postcode":"29577",
    "addr:street":"Oleander Dr",
    "iso:country":"US",
    "sg:address":"3731 Oleander Dr",
    "sg:city":"Myrtle Beach",
    "sg:classifiers":[
        {
            "category":"Restaurant",
            "type":"Food & Drink"
        }
    ],
    "sg:menulink":"http://www.allmenus.com/sc/myrtle-beach/123058-quiznos-sub/menu/",
    "sg:phone":"+1 843 839 4782",
    "sg:postcode":"29577",
    "sg:province":"SC",
    "sg:tags":[
        "wrap",
        "american",
        "sandwich"
    ],
    "wof:name":"Quiznos Sub",
    "wof:placetype":"venue"
},
  "geometry": {"coordinates":[-78.86835000000001,33.726695],"type":"Point"}
}