{
  "type": "Feature",
  "properties": {
    "iso:country":"US",
    "sg:address":"3655 Hebron Dunbar Rd",
    "sg:city":"Clio",
    "sg:classifiers":[
        {
            "category":"Real Estate",
            "subcategory":"Real Estate Operator",
            "type":"Services"
        }
    ],
    "sg:phone":"+1 843 586 2659",
    "sg:postcode":"29525",
    "sg:province":"SC",
    "sg:tags":[
        "property",
        "lessor"
    ],
    "wof:name":"Lila Mumford",
    "wof:placetype":"venue"
},
  "geometry": {"coordinates":[-79.551088,34.533045],"type":"Point"}
}