{
  "type": "Feature",
  "properties": {
    "iso:country":"US",
    "sg:address":"115 E Blackstock Rd",
    "sg:city":"Spartanburg",
    "sg:classifiers":[
        {
            "category":"Professional",
            "subcategory":"Business Services",
            "type":"Services"
        }
    ],
    "sg:phone":"+1 864 279 9853",
    "sg:postcode":"29301",
    "sg:province":"SC",
    "sg:tags":[
        "embroidery"
    ],
    "wof:name":"Monograms Plus",
    "wof:placetype":"venue"
},
  "geometry": {"coordinates":[-81.986778,34.922042],"type":"Point"}
}