{
  "type": "Feature",
  "properties": {
    "iso:country":"US",
    "sg:address":"1115 Marion St",
    "sg:city":"Columbia",
    "sg:classifiers":[
        {
            "category":"Organizations",
            "subcategory":"Religious Organization",
            "type":"Services"
        }
    ],
    "sg:phone":"+1 803 771 7800",
    "sg:postcode":"29201",
    "sg:province":"SC",
    "sg:tags":[
        "church"
    ],
    "sg:website":"www.edusc.org",
    "wof:name":"Episcopal Diocese Of Upper Sc",
    "wof:placetype":"venue"
},
  "geometry": {"coordinates":[-81.0304,34.00222],"type":"Point"}
}