{
  "type": "Feature",
  "properties": {
    "iso:country":"US",
    "sg:address":"742 N Anderson Rd",
    "sg:city":"Rock Hill",
    "sg:classifiers":[
        {
            "category":"Shopping",
            "subcategory":"Books",
            "type":"Retail Goods"
        }
    ],
    "sg:phone":"+1 803 327 9028",
    "sg:postcode":"29730",
    "sg:province":"SC",
    "sg:tags":[
        "dealer"
    ],
    "sg:website":"www.crtsys.com",
    "wof:name":"Book Rack Of Rock Hill",
    "wof:placetype":"venue"
},
  "geometry": {"coordinates":[-80.99576,34.957009],"type":"Point"}
}