{
  "type": "Feature",
  "properties": {
    "iso:country":"US",
    "sg:address":"214 Pompton Ave",
    "sg:city":"Goose Creek",
    "sg:classifiers":[
        {
            "category":"Freight",
            "type":"Transportation"
        }
    ],
    "sg:phone":"+1 843 824 1565",
    "sg:postcode":"29445",
    "sg:province":"SC",
    "sg:tags":[
        "trucking"
    ],
    "wof:name":"Landstar Ligon Inc",
    "wof:placetype":"venue"
},
  "geometry": {"coordinates":[-80.00513599999999,32.988009],"type":"Point"}
}