{
  "type": "Feature",
  "properties": {
    "addr:full":"1931 Sumter St Columbia SC 29201",
    "addr:housenumber":"1931",
    "addr:postcode":"29201",
    "addr:street":"Sumter St",
    "iso:country":"US",
    "sg:address":"1931 Sumter St",
    "sg:city":"Columbia",
    "sg:classifiers":[
        {
            "category":"Arts & Performance",
            "subcategory":"Festival",
            "type":"Entertainment"
        }
    ],
    "sg:phone":"+1 803 252 6758",
    "sg:postcode":"29201",
    "sg:province":"SC",
    "sg:website":"www.columbiasgreekfestival.com/",
    "wof:name":"Columbia's Greek Festival",
    "wof:placetype":"venue"
},
  "geometry": {"coordinates":[-81.036326,34.011553],"type":"Point"}
}