{
  "type": "Feature",
  "properties": {
    "addr:full":"534 Broadway St Myrtle Beach SC 29577",
    "addr:housenumber":"534",
    "addr:postcode":"29577",
    "addr:street":"Broadway St",
    "iso:country":"US",
    "sg:address":"534 Broadway St",
    "sg:city":"Myrtle Beach",
    "sg:classifiers":[
        {
            "category":"Insurance",
            "subcategory":"Insurance Agent",
            "type":"Services"
        }
    ],
    "sg:phone":"+1 843 444 0851",
    "sg:postcode":"29577",
    "sg:province":"SC",
    "wof:name":"Farm Bureau Horry Myrtle Beach",
    "wof:placetype":"venue"
},
  "geometry": {"coordinates":[-78.888492,33.692536],"type":"Point"}
}