{
  "type": "Feature",
  "properties": {
    "iso:country":"US",
    "sg:address":"105 Hillcrest Dr",
    "sg:city":"Greer",
    "sg:classifiers":[
        {
            "category":"Retail",
            "subcategory":"Auto Repair",
            "type":"Services"
        }
    ],
    "sg:phone":"+1 864 848 0501",
    "sg:postcode":"29651",
    "sg:province":"SC",
    "sg:tags":[
        "truck"
    ],
    "wof:name":"Wayne's Truck & Auto Repair",
    "wof:placetype":"venue"
},
  "geometry": {"coordinates":[-82.269526,34.939026],"type":"Point"}
}