{
  "type": "Feature",
  "properties": {
    "addr:full":"314 E Shockley Ferry Rd Anderson SC 29624",
    "addr:housenumber":"314",
    "addr:postcode":"29624",
    "addr:street":"E Shockley Ferry Rd",
    "iso:country":"US",
    "sg:address":"314 E Shockley Ferry Rd",
    "sg:city":"Anderson",
    "sg:classifiers":[
        {
            "category":"Personal",
            "subcategory":"Beauty Salon",
            "type":"Services"
        }
    ],
    "sg:phone":"+1 864 375 0144",
    "sg:postcode":"29624",
    "sg:province":"SC",
    "sg:tags":[
        "hair",
        "stylist"
    ],
    "wof:name":"Hairnette's",
    "wof:placetype":"venue"
},
  "geometry": {"coordinates":[-82.641666,34.482039],"type":"Point"}
}