{
  "type": "Feature",
  "properties": {
    "iso:country":"US",
    "sg:address":"109 Wappoo Creek Dr",
    "sg:city":"Charleston",
    "sg:classifiers":[
        {
            "category":"Health Services",
            "subcategory":"Doctor",
            "type":"Services"
        }
    ],
    "sg:phone":"+1 843 723 9560",
    "sg:postcode":"29412",
    "sg:province":"SC",
    "sg:tags":[
        "dentist"
    ],
    "wof:name":"Low Country Oral Surgeons",
    "wof:placetype":"venue"
},
  "geometry": {"coordinates":[-79.975612,32.763754],"type":"Point"}
}