{
  "type": "Feature",
  "properties": {
    "addr:full":"5055 Old Buncombe Rd Greenville SC 29617",
    "addr:housenumber":"5055",
    "addr:postcode":"29617",
    "addr:street":"Old Buncombe Rd",
    "iso:country":"US",
    "sg:address":"5055 Old Buncombe Rd",
    "sg:city":"Greenville",
    "sg:classifiers":[
        {
            "category":"Food & Beverages",
            "subcategory":"Groceries & Convenience Stores",
            "type":"Retail Goods"
        }
    ],
    "sg:phone":"+1 864 246 7934",
    "sg:postcode":"29617",
    "sg:province":"SC",
    "wof:name":"Hickory Point",
    "wof:placetype":"venue"
},
  "geometry": {"coordinates":[-82.42907599999999,34.913392],"type":"Point"}
}