{
  "type": "Feature",
  "properties": {
    "addr:full":"4111 Main St Loris SC 29569",
    "addr:housenumber":"4111",
    "addr:postcode":"29569",
    "addr:street":"Main St",
    "iso:country":"US",
    "sg:address":"4111 Main St",
    "sg:city":"Loris",
    "sg:classifiers":[
        {
            "category":"Shopping",
            "subcategory":"Department Store",
            "type":"Retail Goods"
        }
    ],
    "sg:phone":"+1 843 756 5272",
    "sg:postcode":"29569",
    "sg:province":"SC",
    "wof:name":"Wolpert's Department Store Inc",
    "wof:placetype":"venue"
},
  "geometry": {"coordinates":[-78.890083,34.056426],"type":"Point"}
}