{
  "type": "Feature",
  "properties": {
    "iso:country":"US",
    "sg:address":"1217 Broughton Blvd",
    "sg:city":"Florence",
    "sg:classifiers":[
        {
            "category":"Wholesale",
            "subcategory":"Machinery & Supplies",
            "type":"Manufacturing & Wholesale Goods"
        }
    ],
    "sg:phone":"+1 843 629 0029",
    "sg:postcode":"29501",
    "sg:province":"SC",
    "sg:tags":[
        "equipment",
        "industrial"
    ],
    "wof:name":"S I E",
    "wof:placetype":"venue"
},
  "geometry": {"coordinates":[-79.801832,34.21449],"type":"Point"}
}