{
  "type": "Feature",
  "properties": {
    "iso:country":"US",
    "sg:address":"935 Brunson Spring Rd",
    "sg:city":"Galivants Ferry",
    "sg:classifiers":[
        {
            "category":"Building & Trades",
            "subcategory":"Construction",
            "type":"Services"
        }
    ],
    "sg:phone":"+1 843 365 1311",
    "sg:postcode":"29544",
    "sg:province":"SC",
    "sg:tags":[
        "hanging",
        "contractor"
    ],
    "wof:name":"Howard Jordan",
    "wof:placetype":"venue"
},
  "geometry": {"coordinates":[-79.176429,33.92062],"type":"Point"}
}