{
  "type": "Feature",
  "properties": {
    "iso:country":"US",
    "sg:address":"1118 Pleasant Ln",
    "sg:city":"Mt Pleasant",
    "sg:classifiers":[
        {
            "category":"Personal",
            "subcategory":"Beauty Salon",
            "type":"Services"
        }
    ],
    "sg:phone":"+1 843 388 2210",
    "sg:postcode":"29468",
    "sg:province":"SC",
    "wof:name":"Illusions Hair Studio",
    "wof:placetype":"venue"
},
  "geometry": {"coordinates":[-80.135035,33.42555],"type":"Point"}
}