{
  "type": "Feature",
  "properties": {
    "addr:full":"1314 Clarendon Ave Florence SC 29505",
    "addr:housenumber":"1314",
    "addr:postcode":"29505",
    "addr:street":"Clarendon Ave",
    "iso:country":"US",
    "sg:address":"1314 Clarendon Ave",
    "sg:city":"Florence",
    "sg:classifiers":[
        {
            "category":"Insurance",
            "subcategory":"Insurance Agent",
            "type":"Services"
        }
    ],
    "sg:phone":"+1 843 662 8165",
    "sg:postcode":"29505",
    "sg:province":"SC",
    "wof:name":"New York Life Insurance Co",
    "wof:placetype":"venue"
},
  "geometry": {"coordinates":[-79.79344500000001,34.162263],"type":"Point"}
}