{
  "type": "Feature",
  "properties": {
    "iso:country":"US",
    "sg:address":"1032 Lynch Rd",
    "sg:city":"Coward",
    "sg:classifiers":[
        {
            "category":"Personal",
            "subcategory":"Beauty Salon",
            "type":"Services"
        }
    ],
    "sg:phone":"+1 843 389 9570",
    "sg:postcode":"29530",
    "sg:province":"SC",
    "wof:name":"Betty's Beauty Salon",
    "wof:placetype":"venue"
},
  "geometry": {"coordinates":[-79.79016900000001,33.988092],"type":"Point"}
}