{
  "type": "Feature",
  "properties": {
    "addr:full":"127 E Main St Lake City SC 29560",
    "addr:housenumber":"127",
    "addr:postcode":"29560",
    "addr:street":"E Main St",
    "iso:country":"US",
    "sg:address":"127 E Main St",
    "sg:city":"Lake City",
    "sg:classifiers":[
        {
            "category":"Shopping",
            "subcategory":"Gifts & Souvenirs",
            "type":"Retail Goods"
        }
    ],
    "sg:phone":"+1 843 374 7300",
    "sg:postcode":"29560",
    "sg:province":"SC",
    "sg:tags":[
        "shop"
    ],
    "wof:name":"Holts Gift & China",
    "wof:placetype":"venue"
},
  "geometry": {"coordinates":[-79.754329,33.872567],"type":"Point"}
}