{
  "type": "Feature",
  "properties": {
    "addr:full":"133 Dogwood Blvd Travelers Rest SC 29690",
    "addr:housenumber":"133",
    "addr:postcode":"29690",
    "addr:street":"Dogwood Blvd",
    "iso:country":"US",
    "sg:address":"133 Dogwood Blvd",
    "sg:city":"Travelers Rest",
    "sg:classifiers":[
        {
            "category":"Building & Trades",
            "subcategory":"Construction",
            "type":"Services"
        }
    ],
    "sg:phone":"+1 864 895 9332",
    "sg:postcode":"29690",
    "sg:province":"SC",
    "sg:tags":[
        "maker",
        "cabinet"
    ],
    "wof:name":"Wood Creations",
    "wof:placetype":"venue"
},
  "geometry": {"coordinates":[-82.36733599999999,35.033447],"type":"Point"}
}