{
  "type": "Feature",
  "properties": {
    "iso:country":"US",
    "sg:address":"989 Old Georgia Rd",
    "sg:city":"Moore",
    "sg:classifiers":[
        {
            "category":"Recreation",
            "type":"Entertainment"
        }
    ],
    "sg:phone":"+1 864 576 8550",
    "sg:postcode":"29369",
    "sg:province":"SC",
    "sg:tags":[
        "skating",
        "rink"
    ],
    "wof:name":"Roebuck Family Skate Ctr",
    "wof:placetype":"venue"
},
  "geometry": {"coordinates":[-81.974548,34.888388],"type":"Point"}
}