{
  "type": "Feature",
  "properties": {
    "iso:country":"US",
    "sg:address":"1080 Morrison Dr",
    "sg:city":"Charleston",
    "sg:classifiers":[
        {
            "category":"Retail",
            "subcategory":"Auto Repair",
            "type":"Services"
        }
    ],
    "sg:phone":"+1 843 722 7666",
    "sg:postcode":"29403",
    "sg:province":"SC",
    "sg:tags":[
        "recreational",
        "vehicle"
    ],
    "wof:name":"Charleston Rv Svc",
    "wof:placetype":"venue"
},
  "geometry": {"coordinates":[-79.947182,32.810188],"type":"Point"}
}