{
  "type": "Feature",
  "properties": {
    "iso:country":"US",
    "sg:address":"301 Forest Park Dr",
    "sg:city":"Simpsonville",
    "sg:classifiers":[
        {
            "category":"Building & Trades",
            "subcategory":"Construction",
            "type":"Services"
        }
    ],
    "sg:phone":"+1 864 963 0910",
    "sg:postcode":"29681",
    "sg:province":"SC",
    "sg:tags":[
        "mobile",
        "home"
    ],
    "wof:name":"Miller Mobile Home Svc",
    "wof:placetype":"venue"
},
  "geometry": {"coordinates":[-82.255124,34.747603],"type":"Point"}
}