{
  "type": "Feature",
  "properties": {
    "iso:country":"US",
    "sg:address":"3212 W Blue Ridge Dr",
    "sg:city":"Greenville",
    "sg:classifiers":[
        {
            "category":"Retail",
            "subcategory":"Auto Repair",
            "type":"Services"
        }
    ],
    "sg:phone":"+1 864 295 0023",
    "sg:postcode":"29611",
    "sg:province":"SC",
    "sg:tags":[
        "repairing",
        "automobile"
    ],
    "wof:name":"Taller Ramirez",
    "wof:placetype":"venue"
},
  "geometry": {"coordinates":[-82.448286,34.853772],"type":"Point"}
}