{
  "type": "Feature",
  "properties": {
    "iso:country":"US",
    "sg:address":"100 Executive Center Dr",
    "sg:city":"Columbia",
    "sg:classifiers":[
        {
            "category":"Building & Trades",
            "subcategory":"Equipment Rental",
            "type":"Services"
        },
        {
            "category":"Banks & Credit Unions",
            "subcategory":"Bank",
            "type":"Services"
        }
    ],
    "sg:phone":"+1 803 750 4100",
    "sg:postcode":"29210",
    "sg:province":"SC",
    "sg:tags":[
        "company",
        "leasing",
        "finance"
    ],
    "wof:name":"Net Bank Business Finance",
    "wof:placetype":"venue"
},
  "geometry": {"coordinates":[-81.118487,34.03436],"type":"Point"}
}