{
  "type": "Feature",
  "properties": {
    "iso:country":"US",
    "sg:address":"66 Lenwood Blvd",
    "sg:city":"Charleston",
    "sg:classifiers":[
        {
            "category":"Banks & Credit Unions",
            "subcategory":"Financial Services",
            "type":"Services"
        }
    ],
    "sg:phone":"+1 843 853 5220",
    "sg:postcode":"29401",
    "sg:province":"SC",
    "sg:tags":[
        "investor"
    ],
    "wof:name":"David Trickey",
    "wof:placetype":"venue"
},
  "geometry": {"coordinates":[-79.935632,32.773361],"type":"Point"}
}