{
  "type": "Feature",
  "properties": {
    "addr:full":"586 Parris Island Gateway Beaufort SC 29906",
    "addr:housenumber":"586",
    "addr:postcode":"29906",
    "addr:street":"Parris Island",
    "iso:country":"US",
    "sg:address":"586 Parris Island Gateway",
    "sg:city":"Beaufort",
    "sg:classifiers":[
        {
            "category":"Insurance",
            "subcategory":"Insurance Agent",
            "type":"Services"
        }
    ],
    "sg:phone":"+1 843 522 0995",
    "sg:postcode":"29906",
    "sg:province":"SC",
    "wof:name":"Peoples Choice Insurance LLC",
    "wof:placetype":"venue"
},
  "geometry": {"coordinates":[-80.73996699999999,32.395131],"type":"Point"}
}