{
  "type": "Feature",
  "properties": {
    "iso:country":"US",
    "sg:address":"3008 Millwood Ave",
    "sg:city":"Columbia",
    "sg:classifiers":[
        {
            "category":"Health Services",
            "subcategory":"Health Practitioner",
            "type":"Services"
        }
    ],
    "sg:phone":"+1 803 252 5646",
    "sg:postcode":"29205",
    "sg:province":"SC",
    "sg:tags":[
        "pathologist",
        "speech"
    ],
    "wof:name":"South Carolina Speech Language",
    "wof:placetype":"venue"
},
  "geometry": {"coordinates":[-80.998224,34.001547],"type":"Point"}
}