{
  "type": "Feature",
  "properties": {
    "iso:country":"US",
    "sg:address":"111 Executive Park",
    "sg:city":"Lake City",
    "sg:classifiers":[
        {
            "category":"Insurance",
            "subcategory":"Insurance Agent",
            "type":"Services"
        }
    ],
    "sg:phone":"+1 843 374 3555",
    "sg:postcode":"29560",
    "sg:province":"SC",
    "wof:name":"Brown & Co",
    "wof:placetype":"venue"
},
  "geometry": {"coordinates":[-79.760318,33.8728],"type":"Point"}
}