{
  "type": "Feature",
  "properties": {
    "iso:country":"US",
    "sg:address":"121 Earls Mill Rd",
    "sg:city":"Seneca",
    "sg:classifiers":[
        {
            "category":"Building & Trades",
            "subcategory":"Cleaning & Sanitation",
            "type":"Services"
        }
    ],
    "sg:phone":"+1 864 972 2925",
    "sg:postcode":"29678",
    "sg:province":"SC",
    "sg:tags":[
        "sing",
        "maintenance"
    ],
    "wof:name":"Twins Services Inc",
    "wof:placetype":"venue"
},
  "geometry": {"coordinates":[-82.968029,34.583781],"type":"Point"}
}