{
  "type": "Feature",
  "properties": {
    "addr:full":"546 Hansford Dr Goose Creek SC 29445",
    "addr:housenumber":"546",
    "addr:postcode":"29445",
    "addr:street":"Hansford Dr",
    "iso:country":"US",
    "sg:address":"546 Hansford Dr",
    "sg:city":"Goose Creek",
    "sg:classifiers":[
        {
            "category":"Shopping",
            "subcategory":"Clothing, Apparel, & Fashions",
            "type":"Retail Goods"
        }
    ],
    "sg:phone":"+1 843 553 2155",
    "sg:postcode":"29445",
    "sg:province":"SC",
    "wof:name":"Cheryls Gladrags",
    "wof:placetype":"venue"
},
  "geometry": {"coordinates":[-80.02681699999999,33.028043],"type":"Point"}
}