{
  "type": "Feature",
  "properties": {
    "iso:country":"US",
    "sg:address":"3100 Broad St",
    "sg:city":"Sumter",
    "sg:classifiers":[
        {
            "category":"Home & Garden",
            "subcategory":"Mobile Homes",
            "type":"Retail Goods"
        }
    ],
    "sg:phone":"+1 803 494 4790",
    "sg:postcode":"29150",
    "sg:province":"SC",
    "wof:name":"Horton Homes Of Sumter",
    "wof:placetype":"venue"
},
  "geometry": {"coordinates":[-80.418036,33.963916],"type":"Point"}
}