{
  "type": "Feature",
  "properties": {
    "addr:full":"906 Maw Bridge Rd Central SC 29630",
    "addr:housenumber":"906",
    "addr:postcode":"29630",
    "addr:street":"Maw Bridge Rd",
    "iso:country":"US",
    "sg:address":"906 Maw Bridge Rd",
    "sg:city":"Central",
    "sg:classifiers":[
        {
            "category":"Retail",
            "subcategory":"Auto Repair",
            "type":"Services"
        }
    ],
    "sg:phone":"+1 864 639 2116",
    "sg:postcode":"29630",
    "sg:province":"SC",
    "sg:tags":[
        "wrecker"
    ],
    "wof:name":"Reid Wrecker Svc",
    "wof:placetype":"venue"
},
  "geometry": {"coordinates":[-82.790601,34.738858],"type":"Point"}
}