{
  "type": "Feature",
  "properties": {
    "iso:country":"US",
    "sg:address":"671 Hames Ridge Rd",
    "sg:city":"Mooresboro",
    "sg:classifiers":[
        {
            "category":"Banks & Credit Unions",
            "subcategory":"Financial Services",
            "type":"Services"
        }
    ],
    "sg:phone":"+1 828 657 9073",
    "sg:postcode":"28114",
    "sg:province":"SC",
    "sg:tags":[
        "company",
        "holding"
    ],
    "wof:name":"Pbg Holdings Corp",
    "wof:placetype":"venue"
},
  "geometry": {"coordinates":[-81.777286,35.242402],"type":"Point"}
}