{
  "type": "Feature",
  "properties": {
    "addr:full":"54 Lois Ave Greenville SC 29611",
    "addr:housenumber":"54",
    "addr:postcode":"29611",
    "addr:street":"Lois Ave",
    "iso:country":"US",
    "sg:address":"54 Lois Ave",
    "sg:city":"Greenville",
    "sg:classifiers":[
        {
            "category":"Restaurant",
            "type":"Food & Drink"
        }
    ],
    "sg:phone":"+1 864 370 7222",
    "sg:postcode":"29611",
    "sg:province":"SC",
    "wof:name":"Tuckers Soda Shop",
    "wof:placetype":"venue"
},
  "geometry": {"coordinates":[-82.430679,34.84888],"type":"Point"}
}