{
  "type": "Feature",
  "properties": {
    "iso:country":"US",
    "sg:address":"43 Jenkins Island Rd",
    "sg:city":"Hilton Head Isle",
    "sg:classifiers":[
        {
            "category":"Professional",
            "type":"Services"
        }
    ],
    "sg:phone":"+1 843 689 2197",
    "sg:postcode":"29926",
    "sg:province":"SC",
    "sg:tags":[
        "establishment"
    ],
    "wof:name":"BBM Inc",
    "wof:placetype":"venue"
},
  "geometry": {"coordinates":[-80.770836,32.223456],"type":"Point"}
}