{
  "type": "Feature",
  "properties": {
    "iso:country":"US",
    "sg:address":"179 Lott Ct",
    "sg:city":"West Columbia",
    "sg:classifiers":[
        {
            "category":"Professional",
            "subcategory":"Management & Consulting",
            "type":"Services"
        }
    ],
    "sg:phone":"+1 803 926 0018",
    "sg:postcode":"29169",
    "sg:province":"SC",
    "sg:tags":[
        "consultant",
        "lighting"
    ],
    "wof:name":"Nova Lighting",
    "wof:placetype":"venue"
},
  "geometry": {"coordinates":[-81.135161,34.009156],"type":"Point"}
}