{
  "type": "Feature",
  "properties": {
    "iso:country":"US",
    "sg:address":"1801 Columbia College Dr",
    "sg:city":"Columbia",
    "sg:classifiers":[
        {
            "category":"Food & Beverages",
            "subcategory":"Groceries & Convenience Stores",
            "type":"Retail Goods"
        }
    ],
    "sg:phone":"+1 803 714 1166",
    "sg:postcode":"29203",
    "sg:province":"SC",
    "wof:name":"Kings Open Air Market",
    "wof:placetype":"venue"
},
  "geometry": {"coordinates":[-81.02478600000001,34.040104],"type":"Point"}
}