{
  "type": "Feature",
  "properties": {
    "iso:country":"US",
    "sg:address":"400 SE Main St",
    "sg:city":"Simpsonville",
    "sg:classifiers":[
        {
            "category":"Real Estate",
            "subcategory":"Real Estate Agent",
            "type":"Services"
        }
    ],
    "sg:phone":"+1 864 963 3100",
    "sg:postcode":"29681",
    "sg:province":"SC",
    "wof:name":"W 3 Properties",
    "wof:placetype":"venue"
},
  "geometry": {"coordinates":[-82.25427000000001,34.728941],"type":"Point"}
}