{
  "type": "Feature",
  "properties": {
    "iso:country":"US",
    "sg:address":"151 Crown Point Rd",
    "sg:city":"Lexington",
    "sg:classifiers":[
        {
            "category":"Manufacturing",
            "subcategory":"Signs",
            "type":"Manufacturing & Wholesale Goods"
        }
    ],
    "sg:phone":"+1 803 356 0436",
    "sg:postcode":"29073",
    "sg:province":"SC",
    "sg:tags":[
        "mfg",
        "advertising",
        "specialty"
    ],
    "wof:name":"Ultimate Signs Inc",
    "wof:placetype":"venue"
},
  "geometry": {"coordinates":[-81.24466,33.929472],"type":"Point"}
}