{
  "type": "Feature",
  "properties": {
    "iso:country":"US",
    "sg:address":"283 Dorchester Manor Blvd",
    "sg:city":"Charleston",
    "sg:classifiers":[
        {
            "category":"Health Services",
            "subcategory":"Chiropractor",
            "type":"Services"
        }
    ],
    "sg:phone":"+1 843 207 9757",
    "sg:postcode":"29420",
    "sg:province":"SC",
    "wof:name":"Palmetto Rehab Of Charleston",
    "wof:placetype":"venue"
},
  "geometry": {"coordinates":[-80.09882,32.921847],"type":"Point"}
}