{
  "type": "Feature",
  "properties": {
    "addr:full":"2391 David H McLeod Blvd Florence SC 29501",
    "addr:housenumber":"2391",
    "addr:postcode":"29501",
    "addr:street":"David H Mcleod Blvd",
    "iso:country":"US",
    "sg:address":"2391 David H McLeod Blvd",
    "sg:city":"Florence",
    "sg:classifiers":[
        {
            "category":"Professional",
            "subcategory":"Lawyer & Legal Services",
            "type":"Services"
        }
    ],
    "sg:phone":"+1 843 669 1778",
    "sg:postcode":"29501",
    "sg:province":"SC",
    "sg:tags":[
        "attorney"
    ],
    "wof:name":"Mc Gowan Stewart Hiller",
    "wof:placetype":"venue"
},
  "geometry": {"coordinates":[-79.817348,34.18713],"type":"Point"}
}