{
  "type": "Feature",
  "properties": {
    "iso:country":"US",
    "sg:address":"220 Westgate Mall Dr",
    "sg:city":"Spartanburg",
    "sg:classifiers":[
        {
            "category":"Health Services",
            "subcategory":"Chiropractor",
            "type":"Services"
        }
    ],
    "sg:phone":"+1 864 587 9226",
    "sg:postcode":"29301",
    "sg:province":"SC",
    "wof:name":"G Mark Foster DC",
    "wof:placetype":"venue"
},
  "geometry": {"coordinates":[-81.988498,34.938619],"type":"Point"}
}