{
  "type": "Feature",
  "properties": {
    "iso:country":"US",
    "sg:address":"501 Greyback Rd",
    "sg:city":"Summerville",
    "sg:classifiers":[
        {
            "category":"Organizations",
            "subcategory":"Religious Organization",
            "type":"Services"
        }
    ],
    "sg:phone":"+1 843 875 4564",
    "sg:postcode":"29483",
    "sg:province":"SC",
    "sg:tags":[
        "church"
    ],
    "wof:name":"New Bethel Sounds Of Praise",
    "wof:placetype":"venue"
},
  "geometry": {"coordinates":[-80.26486199999999,33.058271],"type":"Point"}
}