{
  "type": "Feature",
  "properties": {
    "addr:full":"536 N Calhoun St Calhoun Falls SC 29628",
    "addr:housenumber":"536",
    "addr:postcode":"29628",
    "addr:street":"N Calhoun St",
    "iso:country":"US",
    "sg:address":"536 N Calhoun St",
    "sg:city":"Calhoun Falls",
    "sg:classifiers":[
        {
            "category":"Professional",
            "subcategory":"Accounting & Tax Preparation",
            "type":"Services"
        }
    ],
    "sg:phone":"+1 864 447 9091",
    "sg:postcode":"29628",
    "sg:province":"SC",
    "sg:tags":[
        "return",
        "filing"
    ],
    "wof:name":"Candace Tax Svc",
    "wof:placetype":"venue"
},
  "geometry": {"coordinates":[-82.598547,34.09727],"type":"Point"}
}