{
  "type": "Feature",
  "properties": {
    "iso:country":"US",
    "sg:address":"770 W Frontage Rd",
    "sg:city":"Campobello",
    "sg:classifiers":[
        {
            "category":"Manufacturing",
            "subcategory":"Buildings",
            "type":"Manufacturing & Wholesale Goods"
        }
    ],
    "sg:phone":"+1 864 457 2444",
    "sg:postcode":"29322",
    "sg:province":"SC",
    "sg:tags":[
        "co",
        "log",
        "mfg",
        "house",
        "prefabricated",
        "wood",
        "home",
        "cabin"
    ],
    "sg:website":"www.greenrivercabins.com",
    "wof:name":"Green River Cabins Inc",
    "wof:placetype":"venue"
},
  "geometry": {"coordinates":[-82.111569,35.146767],"type":"Point"}
}