{
  "type": "Feature",
  "properties": {
    "addr:full":"9091 Asheville Hwy Spartanburg SC 29316",
    "addr:housenumber":"9091",
    "addr:postcode":"29316",
    "addr:street":"Asheville Hwy",
    "iso:country":"US",
    "sg:address":"9091 Asheville Hwy",
    "sg:city":"Spartanburg",
    "sg:classifiers":[
        {
            "category":"Home & Garden",
            "subcategory":"Building Materials",
            "type":"Retail Goods"
        }
    ],
    "sg:phone":"+1 864 814 0070",
    "sg:postcode":"29316",
    "sg:province":"SC",
    "sg:tags":[
        "glass",
        "window",
        "plate"
    ],
    "wof:name":"Davenport Glass Svc Ctr Inc",
    "wof:placetype":"venue"
},
  "geometry": {"coordinates":[-82.01845,35.012954],"type":"Point"}
}