{
  "type": "Feature",
  "properties": {
    "iso:country":"US",
    "sg:address":"1905 Duke St",
    "sg:city":"Beaufort",
    "sg:classifiers":[
        {
            "category":"Shopping",
            "type":"Retail Goods"
        }
    ],
    "sg:phone":"+1 843 525 7404",
    "sg:postcode":"29902",
    "sg:province":"SC",
    "sg:tags":[
        "hearing",
        "equipment",
        "supply",
        "impaired"
    ],
    "wof:name":"Coastal Speech & Hearing Clnc",
    "wof:placetype":"venue"
},
  "geometry": {"coordinates":[-80.68398000000001,32.436296],"type":"Point"}
}