{
  "type": "Feature",
  "properties": {
    "addr:full":"142 Bunch Ford Rd Holly Hill SC 29059",
    "addr:housenumber":"142",
    "addr:postcode":"29059",
    "addr:street":"Bunch Ford Rd",
    "iso:country":"US",
    "sg:address":"142 Bunch Ford Rd",
    "sg:city":"Holly Hill",
    "sg:classifiers":[
        {
            "category":"Education",
            "subcategory":"School",
            "type":"Public Place"
        }
    ],
    "sg:phone":"+1 803 496 3243",
    "sg:postcode":"29059",
    "sg:province":"SC",
    "sg:website":"www.hollyhillacademy.org",
    "wof:name":"Holly Hill Academy",
    "wof:placetype":"venue"
},
  "geometry": {"coordinates":[-80.410546,33.336901],"type":"Point"}
}