{
  "type": "Feature",
  "properties": {
    "iso:country":"US",
    "sg:address":"2555 W Newcastle Rd",
    "sg:city":"Florence",
    "sg:classifiers":[
        {
            "category":"Building & Trades",
            "subcategory":"Plumbing",
            "type":"Services"
        }
    ],
    "sg:phone":"+1 843 669 9728",
    "sg:postcode":"29501",
    "sg:province":"SC",
    "sg:tags":[
        "heating",
        "contractor"
    ],
    "wof:name":"Stephens Refrigeration Svc",
    "wof:placetype":"venue"
},
  "geometry": {"coordinates":[-79.82051300000001,34.203072],"type":"Point"}
}