{
  "type": "Feature",
  "properties": {
    "iso:country":"US",
    "sg:address":"405 Kings Mountain St",
    "sg:city":"Clover",
    "sg:classifiers":[
        {
            "category":"Organizations",
            "subcategory":"Religious Organization",
            "type":"Services"
        }
    ],
    "sg:phone":"+1 803 222 5100",
    "sg:postcode":"29710",
    "sg:province":"SC",
    "sg:tags":[
        "church"
    ],
    "wof:name":"Clover Chapel United Methodist",
    "wof:placetype":"venue"
},
  "geometry": {"coordinates":[-81.231032,35.114593],"type":"Point"}
}