{
  "type": "Feature",
  "properties": {
    "iso:country":"US",
    "sg:address":"5326 Bush River Rd",
    "sg:city":"Columbia",
    "sg:classifiers":[
        {
            "category":"Home & Garden",
            "subcategory":"Building Materials",
            "type":"Retail Goods"
        }
    ],
    "sg:phone":"+1 803 796 3070",
    "sg:postcode":"29212",
    "sg:province":"SC",
    "sg:tags":[
        "glass",
        "window",
        "plate"
    ],
    "wof:name":"Century Glass Co",
    "wof:placetype":"venue"
},
  "geometry": {"coordinates":[-81.17250799999999,34.056248],"type":"Point"}
}