{
  "type": "Feature",
  "properties": {
    "addr:full":"263 Shop Rd Kershaw SC 29067",
    "addr:housenumber":"263",
    "addr:postcode":"29067",
    "addr:street":"Shop Rd",
    "iso:country":"US",
    "sg:address":"263 Shop Rd",
    "sg:city":"Kershaw",
    "sg:classifiers":[
        {
            "category":"Building & Trades",
            "subcategory":"Electrical",
            "type":"Services"
        }
    ],
    "sg:phone":"+1 803 475 2030",
    "sg:postcode":"29067",
    "sg:province":"SC",
    "sg:tags":[
        "electric",
        "contractor"
    ],
    "wof:name":"Truesdale Electric Inc",
    "wof:placetype":"venue"
},
  "geometry": {"coordinates":[-80.58185899999999,34.530595],"type":"Point"}
}