{
  "type": "Feature",
  "properties": {
    "iso:country":"US",
    "sg:address":"230 Colonial Dr",
    "sg:city":"Easley",
    "sg:classifiers":[
        {
            "category":"Autos & Motor Vehicles",
            "subcategory":"Automobile Sales",
            "type":"Retail Goods"
        }
    ],
    "sg:phone":"+1 864 859 8803",
    "sg:postcode":"29642",
    "sg:province":"SC",
    "sg:tags":[
        "car",
        "dealer"
    ],
    "wof:name":"Al's Auto Sales",
    "wof:placetype":"venue"
},
  "geometry": {"coordinates":[-82.552068,34.777356],"type":"Point"}
}