{
  "type": "Feature",
  "properties": {
    "iso:country":"US",
    "sg:address":"215 E Bay St",
    "sg:city":"Charleston",
    "sg:classifiers":[
        {
            "category":"Banks & Credit Unions",
            "subcategory":"Investment Brokerage",
            "type":"Services"
        }
    ],
    "sg:phone":"+1 843 722 0780",
    "sg:postcode":"29401",
    "sg:province":"SC",
    "wof:name":"FAS Investments",
    "wof:placetype":"venue"
},
  "geometry": {"coordinates":[-79.927235,32.780558],"type":"Point"}
}