{
  "type": "Feature",
  "properties": {
    "iso:country":"US",
    "sg:address":"5117 Baldwin Rd",
    "sg:city":"Columbia",
    "sg:classifiers":[
        {
            "category":"Building & Trades",
            "subcategory":"Construction",
            "type":"Services"
        }
    ],
    "sg:phone":"+1 803 754 7720",
    "sg:postcode":"29204",
    "sg:province":"SC",
    "sg:tags":[
        "home",
        "builder"
    ],
    "wof:name":"Jim Curry Construction Inc",
    "wof:placetype":"venue"
},
  "geometry": {"coordinates":[-80.99013600000001,34.045578],"type":"Point"}
}