{
  "type": "Feature",
  "properties": {
    "addr:full":"334 E Bay St Charleston SC 29401",
    "addr:housenumber":"334",
    "addr:postcode":"29401",
    "addr:street":"E Bay St",
    "iso:country":"US",
    "sg:address":"334 E Bay St",
    "sg:city":"Charleston",
    "sg:classifiers":[
        {
            "category":"Food & Beverages",
            "subcategory":"Specialty",
            "type":"Retail Goods"
        }
    ],
    "sg:phone":"+1 843 853 2776",
    "sg:postcode":"29401",
    "sg:province":"SC",
    "sg:tags":[
        "nutritional",
        "supplement",
        "health",
        "item"
    ],
    "wof:name":"GNC",
    "wof:placetype":"venue"
},
  "geometry": {"coordinates":[-79.929047,32.786267],"type":"Point"}
}