{
  "type": "Feature",
  "properties": {
    "iso:country":"US",
    "sg:address":"1570 State Hwy 61",
    "sg:city":"Ridgeville",
    "sg:classifiers":[
        {
            "category":"Food & Beverages",
            "subcategory":"Specialty",
            "type":"Retail Goods"
        }
    ],
    "sg:phone":"+1 843 873 3630",
    "sg:postcode":"29472",
    "sg:province":"SC",
    "wof:name":"Miller Enterprises",
    "wof:placetype":"venue"
},
  "geometry": {"coordinates":[-80.342037,33.014005],"type":"Point"}
}