{
  "type": "Feature",
  "properties": {
    "iso:country":"US",
    "sg:address":"4353 Cheviot Dr",
    "sg:city":"North Charleston",
    "sg:classifiers":[
        {
            "category":"Local Transit",
            "type":"Transportation"
        }
    ],
    "sg:phone":"+1 843 767 2646",
    "sg:postcode":"29418",
    "sg:province":"SC",
    "sg:tags":[
        "passenger"
    ],
    "wof:name":"Pete & Annette Limousine Svc",
    "wof:placetype":"venue"
},
  "geometry": {"coordinates":[-80.057762,32.869388],"type":"Point"}
}