{
  "type": "Feature",
  "properties": {
    "addr:full":"474 Monarch Rd Williston SC 29853",
    "addr:housenumber":"474",
    "addr:postcode":"29853",
    "addr:street":"Monarch Rd",
    "iso:country":"US",
    "sg:address":"474 Monarch Rd",
    "sg:city":"Williston",
    "sg:classifiers":[
        {
            "category":"Building & Trades",
            "subcategory":"Construction",
            "type":"Services"
        }
    ],
    "sg:phone":"+1 803 259 3454",
    "sg:postcode":"29853",
    "sg:province":"SC",
    "sg:tags":[
        "excavation",
        "contractor"
    ],
    "wof:name":"Bodiford Backhoe Services",
    "wof:placetype":"venue"
},
  "geometry": {"coordinates":[-81.3687,33.30791],"type":"Point"}
}