{
  "type": "Feature",
  "properties": {
    "iso:country":"US",
    "sg:address":"825 Surfside Dr",
    "sg:city":"Surfside Beach",
    "sg:classifiers":[
        {
            "category":"Professional",
            "subcategory":"Lawyer & Legal Services",
            "type":"Services"
        }
    ],
    "sg:phone":"+1 843 828 1137",
    "sg:postcode":"29575",
    "sg:province":"SC",
    "sg:tags":[
        "attorney"
    ],
    "wof:name":"Robert J Johnston",
    "wof:placetype":"venue"
},
  "geometry": {"coordinates":[-78.980875,33.61123],"type":"Point"}
}