{
  "type": "Feature",
  "properties": {
    "addr:full":"3771 N Hwy 17 Awendaw SC 29429",
    "addr:housenumber":"3771",
    "addr:postcode":"29429",
    "addr:street":"N Hwy 17",
    "iso:country":"US",
    "sg:address":"3771 N Hwy 17",
    "sg:city":"Awendaw",
    "sg:classifiers":[
        {
            "category":"Retail",
            "subcategory":"Auto Repair",
            "type":"Services"
        }
    ],
    "sg:phone":"+1 843 884 1141",
    "sg:postcode":"29429",
    "sg:province":"SC",
    "sg:tags":[
        "wrecker"
    ],
    "wof:name":"Parker Towing & Recovery",
    "wof:placetype":"venue"
},
  "geometry": {"coordinates":[-79.751397,32.883602],"type":"Point"}
}