{
  "type": "Feature",
  "properties": {
    "addr:full":"230 Tamwood Cir Cayce SC 29033",
    "addr:housenumber":"230",
    "addr:postcode":"29033",
    "addr:street":"Tamwood Cir",
    "iso:country":"US",
    "sg:address":"230 Tamwood Cir",
    "sg:city":"Cayce",
    "sg:classifiers":[
        {
            "category":"Building & Trades",
            "subcategory":"Construction",
            "type":"Services"
        }
    ],
    "sg:phone":"+1 803 794 1744",
    "sg:postcode":"29033",
    "sg:province":"SC",
    "sg:tags":[
        "house"
    ],
    "wof:name":"Christian Builders Inc",
    "wof:placetype":"venue"
},
  "geometry": {"coordinates":[-81.05914900000001,33.942798],"type":"Point"}
}