{
  "type": "Feature",
  "properties": {
    "iso:country":"US",
    "sg:address":"401 Orange St",
    "sg:city":"Abbeville",
    "sg:classifiers":[
        {
            "category":"Building & Trades",
            "subcategory":"Electrical",
            "type":"Services"
        }
    ],
    "sg:phone":"+1 864 366 2824",
    "sg:postcode":"29620",
    "sg:province":"SC",
    "sg:tags":[
        "electric",
        "contractor"
    ],
    "wof:name":"Mabry Electric & Plbg Cntrctng",
    "wof:placetype":"venue"
},
  "geometry": {"coordinates":[-82.387891,34.179704],"type":"Point"}
}