{
  "type": "Feature",
  "properties": {
    "iso:country":"US",
    "sg:address":"212 N Ocean Blvd",
    "sg:city":"Myrtle Beach",
    "sg:classifiers":[
        {
            "category":"Banks & Credit Unions",
            "subcategory":"Bank",
            "type":"Services"
        }
    ],
    "sg:phone":"+1 843 232 0656",
    "sg:postcode":"29575",
    "sg:province":"SC",
    "sg:tags":[
        "mortgage"
    ],
    "wof:name":"Mortgage Management LLC",
    "wof:placetype":"venue"
},
  "geometry": {"coordinates":[-78.970094,33.608199],"type":"Point"}
}