{
  "type": "Feature",
  "properties": {
    "iso:country":"US",
    "sg:address":"1332 State Hwy 14",
    "sg:city":"Simpsonville",
    "sg:classifiers":[
        {
            "category":"Retail",
            "subcategory":"Veterinary Services",
            "type":"Services"
        }
    ],
    "sg:phone":"+1 864 288 8908",
    "sg:postcode":"29681",
    "sg:province":"SC",
    "wof:name":"Holly Tree Animal Hospital",
    "wof:placetype":"venue"
},
  "geometry": {"coordinates":[-82.257952,34.789776],"type":"Point"}
}