{
  "type": "Feature",
  "properties": {
    "iso:country":"US",
    "sg:address":"258 N Suber Rd",
    "sg:city":"Greer",
    "sg:classifiers":[
        {
            "category":"Professional",
            "subcategory":"Management & Consulting",
            "type":"Services"
        }
    ],
    "sg:phone":"+1 864 989 0188",
    "sg:postcode":"29651",
    "sg:province":"SC",
    "sg:tags":[
        "retail",
        "direct",
        "sales"
    ],
    "wof:name":"Mark A Byars",
    "wof:placetype":"venue"
},
  "geometry": {"coordinates":[-82.274902,34.94178],"type":"Point"}
}