{
  "type": "Feature",
  "properties": {
    "iso:country":"US",
    "sg:address":"25 Thomas Griffin Rd",
    "sg:city":"Newberry",
    "sg:classifiers":[
        {
            "category":"Restaurant",
            "type":"Food & Drink"
        }
    ],
    "sg:menulink":"http://www.allmenus.com/sc/newberry/107764-waffle-house/menu/",
    "sg:phone":"+1 803 276 9022",
    "sg:postcode":"29108",
    "sg:province":"SC",
    "sg:tags":[
        "american"
    ],
    "wof:name":"Waffle House",
    "wof:placetype":"venue"
},
  "geometry": {"coordinates":[-81.57668700000001,34.309976],"type":"Point"}
}