{
  "type": "Feature",
  "properties": {
    "iso:country":"US",
    "sg:address":"2 Pine Trail Ct",
    "sg:city":"Greer",
    "sg:classifiers":[
        {
            "category":"Building & Trades",
            "subcategory":"Electrical",
            "type":"Services"
        }
    ],
    "sg:phone":"+1 864 877 8143",
    "sg:postcode":"29651",
    "sg:province":"SC",
    "sg:tags":[
        "electric",
        "contractor"
    ],
    "wof:name":"Newman Electrical",
    "wof:placetype":"venue"
},
  "geometry": {"coordinates":[-82.240392,34.965703],"type":"Point"}
}