{
  "type": "Feature",
  "properties": {
    "iso:country":"US",
    "sg:address":"127 Saint Philip St",
    "sg:city":"Charleston",
    "sg:classifiers":[
        {
            "category":"Organizations",
            "subcategory":"Religious Organization",
            "type":"Services"
        }
    ],
    "sg:phone":"+1 843 937 5993",
    "sg:postcode":"29403",
    "sg:province":"SC",
    "sg:tags":[
        "church"
    ],
    "wof:name":"Catholic Student Ministry",
    "wof:placetype":"venue"
},
  "geometry": {"coordinates":[-79.93930400000001,32.7877],"type":"Point"}
}