{
  "type": "Feature",
  "properties": {
    "addr:full":"6239 Savannah Hwy Ravenel SC 29470",
    "addr:housenumber":"6239",
    "addr:postcode":"29470",
    "addr:street":"Savannah Hwy",
    "iso:country":"US",
    "sg:address":"6239 Savannah Hwy",
    "sg:city":"Ravenel",
    "sg:classifiers":[
        {
            "category":"Government",
            "subcategory":"Post Office",
            "type":"Public Place"
        }
    ],
    "sg:phone":"+1 843 889 8990",
    "sg:postcode":"29470",
    "sg:province":"SC",
    "wof:name":"US Post Office",
    "wof:placetype":"venue"
},
  "geometry": {"coordinates":[-80.244348,32.776879],"type":"Point"}
}