{
  "type": "Feature",
  "properties": {
    "iso:country":"US",
    "sg:address":"121 Alexander Rd",
    "sg:city":"West Columbia",
    "sg:classifiers":[
        {
            "category":"Restaurant",
            "type":"Food & Drink"
        }
    ],
    "sg:menulink":"http://www.allmenus.com/sc/west-columbia-cayce/39548-new-orleans-river-front-restaurant/menu/",
    "sg:phone":"+1 803 794 5112",
    "sg:postcode":"29169",
    "sg:province":"SC",
    "sg:tags":[
        "american",
        "creole",
        "cajun"
    ],
    "wof:name":"New Orleans River Front Restaurant",
    "wof:placetype":"venue"
},
  "geometry": {"coordinates":[-81.05341900000001,33.994657],"type":"Point"}
}