{
  "type": "Feature",
  "properties": {
    "addr:full":"963 E Carolina Ave Hartsville SC 29550",
    "addr:housenumber":"963",
    "addr:postcode":"29550",
    "addr:street":"E Carolina Ave",
    "iso:country":"US",
    "sg:address":"963 E Carolina Ave",
    "sg:city":"Hartsville",
    "sg:classifiers":[
        {
            "category":"Professional",
            "subcategory":"Accounting & Tax Preparation",
            "type":"Services"
        }
    ],
    "sg:phone":"+1 843 339 5959",
    "sg:postcode":"29550",
    "sg:province":"SC",
    "sg:tags":[
        "return",
        "filing"
    ],
    "wof:name":"Derry's Bookkeeping & Tax Svc",
    "wof:placetype":"venue"
},
  "geometry": {"coordinates":[-80.053026,34.380848],"type":"Point"}
}