{
  "type": "Feature",
  "properties": {
    "addr:full":"216 Poinsett Hwy Greenville SC 29609",
    "addr:housenumber":"216",
    "addr:postcode":"29609",
    "addr:street":"Poinsett Hwy",
    "iso:country":"US",
    "sg:address":"216 Poinsett Hwy",
    "sg:city":"Greenville",
    "sg:classifiers":[
        {
            "category":"Restaurant",
            "type":"Food & Drink"
        }
    ],
    "sg:phone":"+1 864 834 2005",
    "sg:postcode":"29609",
    "sg:province":"SC",
    "sg:tags":[
        "drinking",
        "eating"
    ],
    "wof:name":"Blue Ridge Grille",
    "wof:placetype":"venue"
},
  "geometry": {"coordinates":[-82.404342,34.869899],"type":"Point"}
}