{
  "type": "Feature",
  "properties": {
    "iso:country":"US",
    "sg:address":"141-A Pelham Dr",
    "sg:city":"Columbia",
    "sg:classifiers":[
        {
            "category":"Restaurant",
            "type":"Food & Drink"
        }
    ],
    "sg:phone":"+1 803 776 8900",
    "sg:postcode":"29209",
    "sg:province":"SC",
    "sg:tags":[
        "buffet",
        "pizza"
    ],
    "sg:website":"www.cicispizza.com",
    "wof:name":"CiCi's Pizza Buffet",
    "wof:placetype":"venue"
},
  "geometry": {"coordinates":[-80.974861,33.978847],"type":"Point"}
}