{
  "type": "Feature",
  "properties": {
    "addr:full":"915 Folly Rd Charleston SC 29412",
    "addr:housenumber":"915",
    "addr:postcode":"29412",
    "addr:street":"Folly Rd",
    "iso:country":"US",
    "sg:address":"915 Folly Rd",
    "sg:city":"Charleston",
    "sg:classifiers":[
        {
            "category":"Shopping",
            "subcategory":"Music",
            "type":"Retail Goods"
        }
    ],
    "sg:phone":"+1 843 762 1120",
    "sg:postcode":"29412",
    "sg:province":"SC",
    "sg:tags":[
        "compact",
        "record",
        "disc",
        "tape"
    ],
    "wof:name":"Purple Music",
    "wof:placetype":"venue"
},
  "geometry": {"coordinates":[-79.968744,32.730216],"type":"Point"}
}