{
  "type": "Feature",
  "properties": {
    "iso:country":"US",
    "sg:address":"2107 Franklin St",
    "sg:city":"Rock Hill",
    "sg:classifiers":[
        {
            "category":"Building & Trades",
            "subcategory":"Construction",
            "type":"Services"
        }
    ],
    "sg:phone":"+1 803 329 6442",
    "sg:postcode":"29732",
    "sg:province":"SC",
    "sg:tags":[
        "painter"
    ],
    "wof:name":"Mc Neely's Painting & Wall",
    "wof:placetype":"venue"
},
  "geometry": {"coordinates":[-81.007314,34.974914],"type":"Point"}
}