{
  "type": "Feature",
  "properties": {
    "iso:country":"US",
    "sg:address":"101 S Main St",
    "sg:city":"Anderson",
    "sg:classifiers":[
        {
            "category":"Government",
            "subcategory":"Office",
            "type":"Public Place"
        }
    ],
    "sg:phone":"+1 864 260 1056",
    "sg:postcode":"29624",
    "sg:province":"SC",
    "sg:website":"www.andersoncountysc.org",
    "wof:name":"Anderson County Geographic",
    "wof:placetype":"venue"
},
  "geometry": {"coordinates":[-82.650094,34.502863],"type":"Point"}
}