{
  "type": "Feature",
  "properties": {
    "iso:country":"US",
    "sg:address":"2000 W Evans St",
    "sg:city":"Florence",
    "sg:classifiers":[
        {
            "category":"Restaurant",
            "type":"Food & Drink"
        }
    ],
    "sg:menulink":"http://www.allmenus.com/sc/florence/176680-kfc---kentucky-fried-chicken/menu/",
    "sg:phone":"+1 843 679 2870",
    "sg:postcode":"29501",
    "sg:province":"SC",
    "sg:tags":[
        "american",
        "chicken"
    ],
    "wof:name":"KFC - Kentucky Fried Chicken",
    "wof:placetype":"venue"
},
  "geometry": {"coordinates":[-79.80653700000001,34.194338],"type":"Point"}
}