{
  "type": "Feature",
  "properties": {
    "addr:full":"1028 Union Hill Rd Salley SC 29137",
    "addr:housenumber":"1028",
    "addr:postcode":"29137",
    "addr:street":"Union Hill Rd",
    "iso:country":"US",
    "sg:address":"1028 Union Hill Rd",
    "sg:city":"Salley",
    "sg:classifiers":[
        {
            "category":"Organizations",
            "subcategory":"Religious Organization",
            "type":"Services"
        }
    ],
    "sg:phone":"+1 803 564 3360",
    "sg:postcode":"29137",
    "sg:province":"SC",
    "sg:tags":[
        "church"
    ],
    "wof:name":"Union Hill Baptist Church",
    "wof:placetype":"venue"
},
  "geometry": {"coordinates":[-81.257445,33.64449],"type":"Point"}
}