{
  "type": "Feature",
  "properties": {
    "iso:country":"US",
    "sg:address":"4365 Headquarters Rd",
    "sg:city":"North Charleston",
    "sg:classifiers":[
        {
            "category":"Wholesale",
            "subcategory":"Motor Vehicles",
            "type":"Manufacturing & Wholesale Goods"
        }
    ],
    "sg:phone":"+1 843 744 8060",
    "sg:postcode":"29405",
    "sg:province":"SC",
    "sg:tags":[
        "auction",
        "automobile"
    ],
    "wof:name":"N Charleston Auto Auction Inc",
    "wof:placetype":"venue"
},
  "geometry": {"coordinates":[-80.00912099999999,32.851805],"type":"Point"}
}