{
  "type": "Feature",
  "properties": {
    "iso:country":"US",
    "sg:address":"835 S Jefferies Blvd",
    "sg:city":"Walterboro",
    "sg:classifiers":[
        {
            "category":"Freight",
            "type":"Transportation"
        }
    ],
    "sg:phone":"+1 843 549 1212",
    "sg:postcode":"29488",
    "sg:province":"SC",
    "sg:tags":[
        "general"
    ],
    "wof:name":"Warehouses Of Walterboro",
    "wof:placetype":"venue"
},
  "geometry": {"coordinates":[-80.67381399999999,32.895968],"type":"Point"}
}