{
  "type": "Feature",
  "properties": {
    "addr:full":"948 Wappoo Rd Charleston SC 29407",
    "addr:housenumber":"948",
    "addr:postcode":"29407",
    "addr:street":"Wappoo Rd",
    "iso:country":"US",
    "sg:address":"948 Wappoo Rd",
    "sg:city":"Charleston",
    "sg:classifiers":[
        {
            "category":"Real Estate",
            "subcategory":"Architect",
            "type":"Services"
        }
    ],
    "sg:phone":"+1 843 402 0101",
    "sg:postcode":"29407",
    "sg:province":"SC",
    "wof:name":"Constantine & Constantine Arch",
    "wof:placetype":"venue"
},
  "geometry": {"coordinates":[-80.016617,32.795446],"type":"Point"}
}