{
  "type": "Feature",
  "properties": {
    "addr:full":"1208 Texas Dr Ladson SC 29456",
    "addr:housenumber":"1208",
    "addr:postcode":"29456",
    "addr:street":"Texas Dr",
    "iso:country":"US",
    "sg:address":"1208 Texas Dr",
    "sg:city":"Ladson",
    "sg:classifiers":[
        {
            "category":"Retail",
            "subcategory":"Repair Shop",
            "type":"Services"
        }
    ],
    "sg:phone":"+1 843 884 9239",
    "sg:postcode":"29456",
    "sg:province":"SC",
    "sg:tags":[
        "refrigerator",
        "freezer"
    ],
    "wof:name":"James Jackson Appliance Repair",
    "wof:placetype":"venue"
},
  "geometry": {"coordinates":[-80.090045,33.022449],"type":"Point"}
}