{
  "type": "Feature",
  "properties": {
    "addr:full":"790 Charter Dr Longs SC 29568",
    "addr:housenumber":"790",
    "addr:postcode":"29568",
    "addr:street":"Charter Dr",
    "iso:country":"US",
    "sg:address":"790 Charter Dr",
    "sg:city":"Longs",
    "sg:classifiers":[
        {
            "category":"Professional",
            "subcategory":"Advertising",
            "type":"Services"
        }
    ],
    "sg:phone":"+1 843 399 4900",
    "sg:postcode":"29568",
    "sg:province":"SC",
    "sg:tags":[
        "counselor"
    ],
    "wof:name":"Momentum Marketing",
    "wof:placetype":"venue"
},
  "geometry": {"coordinates":[-78.682855,33.904211],"type":"Point"}
}