{
  "type": "Feature",
  "properties": {
    "addr:full":"118 Old Mill Rd Gaffney SC 29341",
    "addr:housenumber":"118",
    "addr:postcode":"29341",
    "addr:street":"Old Mill Rd",
    "iso:country":"US",
    "sg:address":"118 Old Mill Rd",
    "sg:city":"Gaffney",
    "sg:classifiers":[
        {
            "category":"Home & Garden",
            "subcategory":"Hardware",
            "type":"Retail Goods"
        }
    ],
    "sg:phone":"+1 864 489 2122",
    "sg:postcode":"29341",
    "sg:province":"SC",
    "wof:name":"Mc Craw Hardware",
    "wof:placetype":"venue"
},
  "geometry": {"coordinates":[-81.62386100000001,35.156808],"type":"Point"}
}