{
  "type": "Feature",
  "properties": {
    "iso:country":"US",
    "sg:address":"1007 Stockade Dr",
    "sg:city":"Florence",
    "sg:classifiers":[
        {
            "category":"Organizations",
            "subcategory":"Membership Organization",
            "type":"Services"
        }
    ],
    "sg:phone":"+1 843 669 2921",
    "sg:postcode":"29506",
    "sg:province":"SC",
    "sg:tags":[
        "society",
        "humane"
    ],
    "wof:name":"Humane Society",
    "wof:placetype":"venue"
},
  "geometry": {"coordinates":[-79.751484,34.182236],"type":"Point"}
}