{
  "type": "Feature",
  "properties": {
    "iso:country":"US",
    "sg:address":"2640 Beulah Cuttino Rd",
    "sg:city":"Sumter",
    "sg:classifiers":[
        {
            "category":"Manufacturing",
            "subcategory":"Toys & Sporting Goods",
            "type":"Manufacturing & Wholesale Goods"
        }
    ],
    "sg:phone":"+1 803 481 4553",
    "sg:postcode":"29150",
    "sg:province":"SC",
    "sg:tags":[
        "mfg"
    ],
    "wof:name":"Eargles Deer Stands LLC",
    "wof:placetype":"venue"
},
  "geometry": {"coordinates":[-80.330471,33.818414],"type":"Point"}
}