{
  "type": "Feature",
  "properties": {
    "addr:full":"410 US Hwy 17 (Bus) S Myrtle Beach SC 29575",
    "addr:housenumber":"410",
    "addr:postcode":"29575",
    "addr:street":"Us Hwy 17 Bus S Myrtle",
    "iso:country":"US",
    "sg:address":"410 US Hwy 17 (Bus) S",
    "sg:city":"Myrtle Beach",
    "sg:classifiers":[
        {
            "category":"Wholesale",
            "subcategory":"Non-durable Goods",
            "type":"Manufacturing & Wholesale Goods"
        }
    ],
    "sg:phone":"+1 843 238 5894",
    "sg:postcode":"29575",
    "sg:province":"SC",
    "wof:name":"Balloons Bountiful",
    "wof:placetype":"venue"
},
  "geometry": {"coordinates":[-78.983862,33.61034],"type":"Point"}
}