{
  "type": "Feature",
  "properties": {
    "addr:full":"1222 Charleston Hwy West Columbia SC 29169",
    "addr:housenumber":"1222",
    "addr:postcode":"29169",
    "addr:street":"Charleston Hwy",
    "iso:country":"US",
    "sg:address":"1222 Charleston Hwy",
    "sg:city":"West Columbia",
    "sg:classifiers":[
        {
            "category":"Restaurant",
            "type":"Food & Drink"
        }
    ],
    "sg:menulink":"http://www.allmenus.com/sc/west-columbia-cayce/39537-arbys/menu/",
    "sg:phone":"+1 803 794 7175",
    "sg:postcode":"29169",
    "sg:province":"SC",
    "sg:tags":[
        "wrap",
        "american",
        "sandwich"
    ],
    "wof:name":"Arby's",
    "wof:placetype":"venue"
},
  "geometry": {"coordinates":[-81.075034,33.978497],"type":"Point"}
}