{
  "type": "Feature",
  "properties": {
    "iso:country":"US",
    "sg:address":"1552 Richland Ave W",
    "sg:city":"Aiken",
    "sg:classifiers":[
        {
            "category":"Local Transit",
            "type":"Transportation"
        }
    ],
    "sg:phone":"+1 803 502 0075",
    "sg:postcode":"29801",
    "sg:province":"SC",
    "sg:tags":[
        "ambulance"
    ],
    "wof:name":"Palmetto Ambulance Svc",
    "wof:placetype":"venue"
},
  "geometry": {"coordinates":[-81.74080600000001,33.565498],"type":"Point"}
}