{
  "type": "Feature",
  "properties": {
    "addr:full":"1510 Cannon Bridge Rd Cordova SC 29039",
    "addr:housenumber":"1510",
    "addr:postcode":"29039",
    "addr:street":"Cannon Bridge Rd",
    "iso:country":"US",
    "sg:address":"1510 Cannon Bridge Rd",
    "sg:city":"Cordova",
    "sg:classifiers":[
        {
            "category":"Home & Garden",
            "subcategory":"Furniture",
            "type":"Retail Goods"
        }
    ],
    "sg:phone":"+1 803 516 8580",
    "sg:postcode":"29039",
    "sg:province":"SC",
    "wof:name":"Payless Variety",
    "wof:placetype":"venue"
},
  "geometry": {"coordinates":[-80.88355199999999,33.436827],"type":"Point"}
}