{
  "type": "Feature",
  "properties": {
    "iso:country":"US",
    "sg:address":"108 Boggs Dr",
    "sg:city":"Seneca",
    "sg:classifiers":[
        {
            "category":"Professional",
            "type":"Services"
        }
    ],
    "sg:phone":"+1 864 882 2102",
    "sg:postcode":"29678",
    "sg:province":"SC",
    "sg:tags":[
        "establishment"
    ],
    "wof:name":"Happy Trails Mobile Home Park",
    "wof:placetype":"venue"
},
  "geometry": {"coordinates":[-82.953763,34.671808],"type":"Point"}
}