{
  "type": "Feature",
  "properties": {
    "iso:country":"US",
    "sg:address":"2229 Taylor Rd",
    "sg:city":"Cayce",
    "sg:classifiers":[
        {
            "category":"Building & Trades",
            "subcategory":"Pest Control",
            "type":"Services"
        }
    ],
    "sg:phone":"+1 803 796 5588",
    "sg:postcode":"29033",
    "sg:province":"SC",
    "wof:name":"Cayce Exterminating Co Inc",
    "wof:placetype":"venue"
},
  "geometry": {"coordinates":[-81.071248,33.957178],"type":"Point"}
}