{
  "type": "Feature",
  "properties": {
    "iso:country":"US",
    "sg:address":"110 Marigold Ln",
    "sg:city":"Liberty",
    "sg:classifiers":[
        {
            "category":"Restaurant",
            "type":"Food & Drink"
        }
    ],
    "sg:phone":"+1 864 843 0401",
    "sg:postcode":"29657",
    "sg:province":"SC",
    "sg:tags":[
        "eating"
    ],
    "wof:name":"Crazy Daves Ice Cream",
    "wof:placetype":"venue"
},
  "geometry": {"coordinates":[-82.708398,34.776643],"type":"Point"}
}