{
  "type": "Feature",
  "properties": {
    "iso:country":"US",
    "sg:address":"1610 Pioneer Rd",
    "sg:city":"York",
    "sg:classifiers":[
        {
            "category":"Building & Trades",
            "subcategory":"Pest Control",
            "type":"Services"
        }
    ],
    "sg:phone":"+1 803 628 0003",
    "sg:postcode":"29745",
    "sg:province":"SC",
    "sg:tags":[
        "mothproofing"
    ],
    "sg:website":"http://www.pioneerservicespro.com",
    "wof:name":"Pioneer Services",
    "wof:placetype":"venue"
},
  "geometry": {"coordinates":[-81.210565,35.027642],"type":"Point"}
}