{
  "type": "Feature",
  "properties": {
    "iso:country":"US",
    "sg:address":"1501 S Murray Ave",
    "sg:city":"Anderson",
    "sg:classifiers":[
        {
            "category":"Autos & Motor Vehicles",
            "subcategory":"Automobile Sales",
            "type":"Retail Goods"
        }
    ],
    "sg:phone":"+1 864 375 9060",
    "sg:postcode":"29624",
    "sg:province":"SC",
    "sg:tags":[
        "car",
        "used",
        "dealer"
    ],
    "wof:name":"Trucks & More Inc",
    "wof:placetype":"venue"
},
  "geometry": {"coordinates":[-82.649926,34.490221],"type":"Point"}
}