{
  "type": "Feature",
  "properties": {
    "addr:full":"435 King St Charleston SC 29403",
    "addr:housenumber":"435",
    "addr:postcode":"29403",
    "addr:street":"King St",
    "iso:country":"US",
    "sg:address":"435 King St",
    "sg:city":"Charleston",
    "sg:classifiers":[
        {
            "category":"Food & Beverages",
            "subcategory":"Groceries & Convenience Stores",
            "type":"Retail Goods"
        }
    ],
    "sg:phone":"+1 843 958 8004",
    "sg:postcode":"29403",
    "sg:province":"SC",
    "sg:tags":[
        "grocer"
    ],
    "wof:name":"King Street Grocery",
    "wof:placetype":"venue"
},
  "geometry": {"coordinates":[-79.93842600000001,32.788847],"type":"Point"}
}