{
  "type": "Feature",
  "properties": {
    "iso:country":"US",
    "sg:address":"1836 Ranger Dr",
    "sg:city":"Cross",
    "sg:classifiers":[
        {
            "category":"Government",
            "subcategory":"Post Office",
            "type":"Public Place"
        }
    ],
    "sg:phone":"+1 843 753 2669",
    "sg:postcode":"29436",
    "sg:province":"SC",
    "wof:name":"US Post Office",
    "wof:placetype":"venue"
},
  "geometry": {"coordinates":[-80.162031,33.323202],"type":"Point"}
}