{
  "type": "Feature",
  "properties": {
    "iso:country":"US",
    "sg:address":"2407 Hwy 301 S",
    "sg:city":"Dillon",
    "sg:classifiers":[
        {
            "category":"Building & Trades",
            "subcategory":"Landscaping Services",
            "type":"Services"
        }
    ],
    "sg:phone":"+1 843 774 3888",
    "sg:postcode":"29536",
    "sg:province":"SC",
    "sg:tags":[
        "landscape",
        "contractor"
    ],
    "wof:name":"Lee's Landscaping Lawn Svc",
    "wof:placetype":"venue"
},
  "geometry": {"coordinates":[-79.399541,34.370505],"type":"Point"}
}