{
  "type": "Feature",
  "properties": {
    "iso:country":"US",
    "sg:address":"1175 Loring Mill Rd",
    "sg:city":"Sumter",
    "sg:classifiers":[
        {
            "category":"Food & Beverages",
            "subcategory":"Groceries & Convenience Stores",
            "type":"Retail Goods"
        }
    ],
    "sg:phone":"+1 803 469 3499",
    "sg:postcode":"29150",
    "sg:province":"SC",
    "wof:name":"Corner Pantry",
    "wof:placetype":"venue"
},
  "geometry": {"coordinates":[-80.417816,33.934019],"type":"Point"}
}