{
  "type": "Feature",
  "properties": {
    "iso:country":"US",
    "sg:address":"1594 Freedom Blvd",
    "sg:city":"Florence",
    "sg:classifiers":[
        {
            "category":"Health Services",
            "subcategory":"Doctor",
            "type":"Services"
        }
    ],
    "sg:phone":"+1 843 679 5135",
    "sg:postcode":"29505",
    "sg:province":"SC",
    "sg:tags":[
        "physician",
        "surgeon"
    ],
    "wof:name":"Florence Neurological Clinic",
    "wof:placetype":"venue"
},
  "geometry": {"coordinates":[-79.75513,34.162341],"type":"Point"}
}