{
  "type": "Feature",
  "properties": {
    "iso:country":"US",
    "sg:address":"477 S Georgetown Hwy",
    "sg:city":"Johnsonville",
    "sg:classifiers":[
        {
            "category":"Restaurant",
            "type":"Food & Drink"
        }
    ],
    "sg:phone":"+1 843 386 3667",
    "sg:postcode":"29555",
    "sg:province":"SC",
    "wof:name":"Shady Rest Family Restaurant",
    "wof:placetype":"venue"
},
  "geometry": {"coordinates":[-79.44258600000001,33.807666],"type":"Point"}
}