{
  "type": "Feature",
  "properties": {
    "iso:country":"US",
    "sg:address":"638 Kershaw Country Club Rd",
    "sg:city":"Kershaw",
    "sg:classifiers":[
        {
            "category":"Real Estate",
            "subcategory":"Real Estate Operator",
            "type":"Services"
        }
    ],
    "sg:phone":"+1 803 475 8804",
    "sg:postcode":"29067",
    "sg:province":"SC",
    "sg:tags":[
        "building",
        "apartment"
    ],
    "wof:name":"Foxwood Apartments",
    "wof:placetype":"venue"
},
  "geometry": {"coordinates":[-80.600854,34.53514],"type":"Point"}
}