{
  "type": "Feature",
  "properties": {
    "iso:country":"US",
    "sg:address":"700 Musgrove St",
    "sg:city":"Clinton",
    "sg:classifiers":[
        {
            "category":"Shopping",
            "subcategory":"Gifts & Souvenirs",
            "type":"Retail Goods"
        }
    ],
    "sg:phone":"+1 864 833 9580",
    "sg:postcode":"29325",
    "sg:province":"SC",
    "sg:tags":[
        "shop"
    ],
    "wof:name":"Unique Interiors Upholstry",
    "wof:placetype":"venue"
},
  "geometry": {"coordinates":[-81.87418099999999,34.483191],"type":"Point"}
}