{
  "type": "Feature",
  "properties": {
    "iso:country":"US",
    "sg:address":"2097 Calhoun Rd",
    "sg:city":"Greenwood",
    "sg:classifiers":[
        {
            "category":"Professional",
            "subcategory":"Accounting & Tax Preparation",
            "type":"Services"
        }
    ],
    "sg:phone":"+1 864 223 4478",
    "sg:postcode":"29649",
    "sg:province":"SC",
    "sg:tags":[
        "return",
        "filing"
    ],
    "wof:name":"Robert's Income Tax Svc",
    "wof:placetype":"venue"
},
  "geometry": {"coordinates":[-82.196586,34.22614],"type":"Point"}
}