{
  "type": "Feature",
  "properties": {
    "iso:country":"US",
    "sg:address":"807 Myrtle Ct",
    "sg:city":"North Myrtle Bch",
    "sg:classifiers":[
        {
            "category":"Real Estate",
            "subcategory":"Real Estate Agent",
            "type":"Services"
        }
    ],
    "sg:phone":"+1 843 249 6612",
    "sg:postcode":"29582",
    "sg:province":"SC",
    "sg:tags":[
        "management"
    ],
    "wof:name":"S & Z Properties & Mgmt",
    "wof:placetype":"venue"
},
  "geometry": {"coordinates":[-78.68927499999999,33.826143],"type":"Point"}
}