{
  "type": "Feature",
  "properties": {
    "iso:country":"US",
    "sg:address":"966 Old Furnace Rd",
    "sg:city":"Spartanburg",
    "sg:classifiers":[
        {
            "category":"Manufacturing",
            "subcategory":"Metals",
            "type":"Manufacturing & Wholesale Goods"
        }
    ],
    "sg:phone":"+1 864 814 3534",
    "sg:postcode":"29316",
    "sg:province":"SC",
    "sg:tags":[
        "product",
        "industrial",
        "fabricated",
        "mfg"
    ],
    "wof:name":"Southern Machine & Assembly",
    "wof:placetype":"venue"
},
  "geometry": {"coordinates":[-82.010264,35.037761],"type":"Point"}
}