{
  "type": "Feature",
  "properties": {
    "iso:country":"US",
    "sg:address":"379 Dennis Ridge Rd",
    "sg:city":"Bonneau",
    "sg:classifiers":[
        {
            "category":"Retail",
            "subcategory":"Auto Repair",
            "type":"Services"
        }
    ],
    "sg:phone":"+1 843 825 4376",
    "sg:postcode":"29431",
    "sg:province":"SC",
    "sg:tags":[
        "wrecker"
    ],
    "wof:name":"Middleton Towing Svc",
    "wof:placetype":"venue"
},
  "geometry": {"coordinates":[-79.956375,33.348069],"type":"Point"}
}