{
  "type": "Feature",
  "properties": {
    "addr:full":"1830 S 5th St Hartsville SC 29550",
    "addr:housenumber":"1830",
    "addr:postcode":"29550",
    "addr:street":"S 5Th St",
    "iso:country":"US",
    "sg:address":"1830 S 5th St",
    "sg:city":"Hartsville",
    "sg:classifiers":[
        {
            "category":"Wholesale",
            "subcategory":"Medical Equipment & Supplies",
            "type":"Manufacturing & Wholesale Goods"
        }
    ],
    "sg:phone":"+1 843 857 0636",
    "sg:postcode":"29550",
    "sg:province":"SC",
    "sg:tags":[
        "physician",
        "surgeon"
    ],
    "wof:name":"Advance Medical LLC",
    "wof:placetype":"venue"
},
  "geometry": {"coordinates":[-80.07167,34.338861],"type":"Point"}
}