{
  "type": "Feature",
  "properties": {
    "addr:full":"2402 N Kings Hwy Myrtle Beach SC 29577",
    "addr:housenumber":"2402",
    "addr:postcode":"29577",
    "addr:street":"N Kings Hwy",
    "iso:country":"US",
    "sg:address":"2402 N Kings Hwy",
    "sg:city":"Myrtle Beach",
    "sg:phone":"+1 843 444 9194",
    "sg:postcode":"29577",
    "sg:province":"SC",
    "sg:tags":[
        "product",
        "petroleum"
    ],
    "wof:name":"Seamart",
    "wof:placetype":"venue"
},
  "geometry": {"coordinates":[-78.867909,33.705773],"type":"Point"}
}