{
  "type": "Feature",
  "properties": {
    "addr:full":"4315 Kinlaw St Little River SC 29566",
    "addr:housenumber":"4315",
    "addr:postcode":"29566",
    "addr:street":"Kinlaw St",
    "iso:country":"US",
    "sg:address":"4315 Kinlaw St",
    "sg:city":"Little River",
    "sg:classifiers":[
        {
            "category":"Building & Trades",
            "subcategory":"Construction",
            "type":"Services"
        }
    ],
    "sg:phone":"+1 843 249 1881",
    "sg:postcode":"29566",
    "sg:province":"SC",
    "sg:tags":[
        "hanging",
        "contractor"
    ],
    "wof:name":"L & W Painting & Wallpapering",
    "wof:placetype":"venue"
},
  "geometry": {"coordinates":[-78.650136,33.861355],"type":"Point"}
}