{
  "type": "Feature",
  "properties": {
    "iso:country":"US",
    "sg:address":"2024 Nichols Hwy",
    "sg:city":"Nichols",
    "sg:phone":"+1 843 759 2237",
    "sg:postcode":"29581",
    "sg:province":"SC",
    "sg:tags":[
        "farm",
        "tobacco"
    ],
    "wof:name":"Russell Huggins",
    "wof:placetype":"venue"
},
  "geometry": {"coordinates":[-79.125158,34.16478],"type":"Point"}
}