{
  "type": "Feature",
  "properties": {
    "iso:country":"US",
    "sg:address":"936 Casselman Rd",
    "sg:city":"Scranton",
    "sg:classifiers":[
        {
            "category":"Organizations",
            "subcategory":"Religious Organization",
            "type":"Services"
        }
    ],
    "sg:phone":"+1 843 389 7622",
    "sg:postcode":"29591",
    "sg:province":"SC",
    "sg:tags":[
        "church"
    ],
    "wof:name":"Community PH Church",
    "wof:placetype":"venue"
},
  "geometry": {"coordinates":[-79.71006300000001,33.89171],"type":"Point"}
}