{
  "type": "Feature",
  "properties": {
    "iso:country":"US",
    "sg:address":"2600 Laurens Rd",
    "sg:city":"Greenville",
    "sg:classifiers":[
        {
            "category":"Food & Beverages",
            "subcategory":"Groceries & Convenience Stores",
            "type":"Retail Goods"
        }
    ],
    "sg:phone":"+1 864 234 6785",
    "sg:postcode":"29607",
    "sg:province":"SC",
    "wof:name":"Spinx Co Inc",
    "wof:placetype":"venue"
},
  "geometry": {"coordinates":[-82.34178,34.82148],"type":"Point"}
}