{
  "type": "Feature",
  "properties": {
    "iso:country":"US",
    "sg:address":"1015 Sumter St",
    "sg:city":"Columbia",
    "sg:classifiers":[
        {
            "category":"Government",
            "subcategory":"Office",
            "type":"Public Place"
        }
    ],
    "sg:phone":"+1 803 734 1965",
    "sg:postcode":"29201",
    "sg:province":"SC",
    "wof:name":"Commission On Judicial Conduct",
    "wof:placetype":"venue"
},
  "geometry": {"coordinates":[-81.031264,34.000086],"type":"Point"}
}