{
  "type": "Feature",
  "properties": {
    "iso:country":"US",
    "sg:address":"1600 Taylor St",
    "sg:city":"Columbia",
    "sg:classifiers":[
        {
            "category":"Health Services",
            "subcategory":"Optometrist",
            "type":"Services"
        },
        {
            "category":"Shopping",
            "subcategory":"Optician",
            "type":"Retail Goods"
        }
    ],
    "sg:phone":"+1 803 779 7783",
    "sg:postcode":"29201",
    "sg:province":"SC",
    "sg:tags":[
        "eyewear"
    ],
    "wof:name":"Folline Vision Centers",
    "wof:placetype":"venue"
},
  "geometry": {"coordinates":[-81.02941199999999,34.008419],"type":"Point"}
}