{
  "type": "Feature",
  "properties": {
    "iso:country":"US",
    "sg:address":"246 Kinard Rd",
    "sg:city":"Camden",
    "sg:classifiers":[
        {
            "category":"Home & Garden",
            "subcategory":"Building Materials",
            "type":"Retail Goods"
        }
    ],
    "sg:phone":"+1 803 432 2084",
    "sg:postcode":"29078",
    "sg:province":"SC",
    "sg:tags":[
        "mixed",
        "concrete"
    ],
    "wof:name":"Camden Concrete Co",
    "wof:placetype":"venue"
},
  "geometry": {"coordinates":[-80.68522,34.213432],"type":"Point"}
}