{
  "type": "Feature",
  "properties": {
    "iso:country":"US",
    "sg:address":"1215 Celebrity Cir",
    "sg:city":"Myrtle Beach",
    "sg:classifiers":[
        {
            "category":"Shopping",
            "subcategory":"Jewelry",
            "type":"Retail Goods"
        }
    ],
    "sg:phone":"+1 843 444 0119",
    "sg:postcode":"29577",
    "sg:province":"SC",
    "sg:tags":[
        "jeweler"
    ],
    "wof:name":"Silver Belles",
    "wof:placetype":"venue"
},
  "geometry": {"coordinates":[-78.885776,33.715613],"type":"Point"}
}