{
  "type": "Feature",
  "properties": {
    "addr:full":"110 Bennett St Leesville SC 29070",
    "addr:housenumber":"110",
    "addr:postcode":"29070",
    "addr:street":"Bennett St",
    "iso:country":"US",
    "sg:address":"110 Bennett St",
    "sg:city":"Leesville",
    "sg:classifiers":[
        {
            "category":"Personal",
            "subcategory":"Beauty Salon",
            "type":"Services"
        }
    ],
    "sg:phone":"+1 803 604 8507",
    "sg:postcode":"29070",
    "sg:province":"SC",
    "wof:name":"Robin's Hair Designs",
    "wof:placetype":"venue"
},
  "geometry": {"coordinates":[-81.510845,33.916911],"type":"Point"}
}