{
  "type": "Feature",
  "properties": {
    "iso:country":"US",
    "sg:address":"121 Bombay Dr",
    "sg:city":"Columbia",
    "sg:classifiers":[
        {
            "category":"Professional",
            "subcategory":"Engineering",
            "type":"Services"
        }
    ],
    "sg:phone":"+1 803 776 2000",
    "sg:postcode":"29209",
    "sg:province":"SC",
    "sg:tags":[
        "engineer"
    ],
    "wof:name":"Granie Engineering",
    "wof:placetype":"venue"
},
  "geometry": {"coordinates":[-80.966205,33.926854],"type":"Point"}
}