{
  "type": "Feature",
  "properties": {
    "iso:country":"US",
    "sg:address":"893 White Pond Rd",
    "sg:city":"Elgin",
    "sg:classifiers":[
        {
            "category":"Home & Garden",
            "subcategory":"Garden Supply",
            "type":"Retail Goods"
        }
    ],
    "sg:phone":"+1 803 438 4043",
    "sg:postcode":"29045",
    "sg:province":"SC",
    "sg:tags":[
        "fountain",
        "display"
    ],
    "wof:name":"Carolina Fountain",
    "wof:placetype":"venue"
},
  "geometry": {"coordinates":[-80.756398,34.146705],"type":"Point"}
}