{
  "type": "Feature",
  "properties": {
    "iso:country":"US",
    "sg:address":"2225 Richland Ave E",
    "sg:city":"Aiken",
    "sg:classifiers":[
        {
            "category":"Wholesale",
            "subcategory":"Beer",
            "type":"Manufacturing & Wholesale Goods"
        }
    ],
    "sg:phone":"+1 803 593 2846",
    "sg:postcode":"29801",
    "sg:province":"SC",
    "sg:tags":[
        "ale"
    ],
    "wof:name":"A B Beverage Co",
    "wof:placetype":"venue"
},
  "geometry": {"coordinates":[-81.686055,33.548636],"type":"Point"}
}