{
  "type": "Feature",
  "properties": {
    "addr:full":"219 Mill St Harleyville SC 29448",
    "addr:housenumber":"219",
    "addr:postcode":"29448",
    "addr:street":"Mill St",
    "iso:country":"US",
    "sg:address":"219 Mill St",
    "sg:city":"Harleyville",
    "sg:classifiers":[
        {
            "category":"Real Estate",
            "subcategory":"Real Estate Operator",
            "type":"Services"
        }
    ],
    "sg:phone":"+1 843 462 7700",
    "sg:postcode":"29448",
    "sg:province":"SC",
    "sg:tags":[
        "property",
        "lessor"
    ],
    "wof:name":"Harleyville Land Company LLC",
    "wof:placetype":"venue"
},
  "geometry": {"coordinates":[-80.446815,33.207087],"type":"Point"}
}