{
  "type": "Feature",
  "properties": {
    "iso:country":"US",
    "sg:address":"332 E Main St",
    "sg:city":"Kingstree",
    "sg:classifiers":[
        {
            "category":"Retail",
            "subcategory":"Funeral Services",
            "type":"Services"
        }
    ],
    "sg:phone":"+1 843 355 6262",
    "sg:postcode":"29556",
    "sg:province":"SC",
    "sg:tags":[
        "director"
    ],
    "wof:name":"Williamsburg Funeral Home",
    "wof:placetype":"venue"
},
  "geometry": {"coordinates":[-79.824038,33.665254],"type":"Point"}
}