{
  "type": "Feature",
  "properties": {
    "addr:full":"238 Pierce Rd Landrum SC 29356",
    "addr:housenumber":"238",
    "addr:postcode":"29356",
    "addr:street":"Pierce Rd",
    "iso:country":"US",
    "sg:address":"238 Pierce Rd",
    "sg:city":"Landrum",
    "sg:classifiers":[
        {
            "category":"Building & Trades",
            "subcategory":"Construction",
            "type":"Services"
        }
    ],
    "sg:phone":"+1 864 457 2983",
    "sg:postcode":"29356",
    "sg:province":"SC",
    "sg:tags":[
        "grading",
        "contractor"
    ],
    "wof:name":"Ben H Dobbins Grading & Haul",
    "wof:placetype":"venue"
},
  "geometry": {"coordinates":[-82.236389,35.155539],"type":"Point"}
}