{
  "type": "Feature",
  "properties": {
    "addr:full":"1400 Whiskey Rd Aiken SC 29803",
    "addr:housenumber":"1400",
    "addr:postcode":"29803",
    "addr:street":"Whiskey Rd",
    "iso:country":"US",
    "sg:address":"1400 Whiskey Rd",
    "sg:city":"Aiken",
    "sg:classifiers":[
        {
            "category":"Shopping",
            "subcategory":"Used Merchandise",
            "type":"Retail Goods"
        }
    ],
    "sg:phone":"+1 803 644 4601",
    "sg:postcode":"29803",
    "sg:province":"SC",
    "wof:name":"Goodwill Industries Emporium",
    "wof:placetype":"venue"
},
  "geometry": {"coordinates":[-81.723658,33.530137],"type":"Point"}
}