{
  "type": "Feature",
  "properties": {
    "iso:country":"US",
    "sg:address":"706 Pendleton St",
    "sg:city":"Greenville",
    "sg:classifiers":[
        {
            "category":"Social Services",
            "subcategory":"Job Training",
            "type":"Services"
        }
    ],
    "sg:phone":"+1 864 242 3531",
    "sg:postcode":"29601",
    "sg:province":"SC",
    "sg:tags":[
        "rehab",
        "government"
    ],
    "sg:website":"www.sces.org",
    "wof:name":"Employment Office-Job Svc",
    "wof:placetype":"venue"
},
  "geometry": {"coordinates":[-82.415848,34.84316],"type":"Point"}
}