{
  "type": "Feature",
  "properties": {
    "iso:country":"US",
    "sg:address":"1048 Oakland Ave",
    "sg:city":"Rock Hill",
    "sg:classifiers":[
        {
            "category":"Professional",
            "subcategory":"Lawyer & Legal Services",
            "type":"Services"
        }
    ],
    "sg:phone":"+1 803 985 1188",
    "sg:postcode":"29732",
    "sg:province":"SC",
    "sg:tags":[
        "attorney"
    ],
    "wof:name":"Ted A Greve & Assoc",
    "wof:placetype":"venue"
},
  "geometry": {"coordinates":[-81.03169699999999,34.944393],"type":"Point"}
}