{
  "type": "Feature",
  "properties": {
    "iso:country":"US",
    "sg:address":"217 Palmetto Bluff Rd",
    "sg:city":"Bluffton",
    "sg:classifiers":[
        {
            "category":"Home & Garden",
            "subcategory":"Furniture",
            "type":"Retail Goods"
        }
    ],
    "sg:phone":"+1 843 757 5041",
    "sg:postcode":"29910",
    "sg:province":"SC",
    "wof:name":"Alex Colleran",
    "wof:placetype":"venue"
},
  "geometry": {"coordinates":[-80.954554,32.218171],"type":"Point"}
}