{
  "type": "Feature",
  "properties": {
    "addr:full":"2810 Ashley Phosphate Rd North Charleston SC 29418",
    "addr:housenumber":"2810",
    "addr:postcode":"29418",
    "addr:street":"Ashley Phosphate Rd",
    "iso:country":"US",
    "sg:address":"2810 Ashley Phosphate Rd",
    "sg:city":"North Charleston",
    "sg:classifiers":[
        {
            "category":"Real Estate",
            "subcategory":"Real Estate Agent",
            "type":"Services"
        }
    ],
    "sg:phone":"+1 843 764 0237",
    "sg:postcode":"29418",
    "sg:province":"SC",
    "wof:name":"Brice Realty",
    "wof:placetype":"venue"
},
  "geometry": {"coordinates":[-80.055633,32.93223],"type":"Point"}
}