{
  "type": "Feature",
  "properties": {
    "iso:country":"US",
    "sg:address":"2109 W Evans St",
    "sg:city":"Florence",
    "sg:classifiers":[
        {
            "category":"Autos & Motor Vehicles",
            "subcategory":"Fuel & Gas Station",
            "type":"Retail Goods"
        }
    ],
    "sg:phone":"+1 843 662 7891",
    "sg:postcode":"29501",
    "sg:province":"SC",
    "sg:tags":[
        "station",
        "gasoline"
    ],
    "wof:name":"Exxon",
    "wof:placetype":"venue"
},
  "geometry": {"coordinates":[-79.811235,34.188435],"type":"Point"}
}