{
  "type": "Feature",
  "properties": {
    "addr:full":"210 N Springs Rd Columbia SC 29223",
    "addr:housenumber":"210",
    "addr:postcode":"29223",
    "addr:street":"N Springs Rd",
    "iso:country":"US",
    "sg:address":"210 N Springs Rd",
    "sg:city":"Columbia",
    "sg:classifiers":[
        {
            "category":"Building & Trades",
            "subcategory":"Landscaping Services",
            "type":"Services"
        }
    ],
    "sg:phone":"+1 803 419 0701",
    "sg:postcode":"29223",
    "sg:province":"SC",
    "sg:tags":[
        "landscape"
    ],
    "sg:website":"www.earthg.com",
    "wof:name":"Earth Graphics",
    "wof:placetype":"venue"
},
  "geometry": {"coordinates":[-80.893682,34.115346],"type":"Point"}
}