{
  "type": "Feature",
  "properties": {
    "iso:country":"US",
    "sg:address":"205 N Townville St",
    "sg:city":"Seneca",
    "sg:classifiers":[
        {
            "category":"Organizations",
            "subcategory":"Professional Association",
            "type":"Services"
        }
    ],
    "sg:phone":"+1 864 885 1515",
    "sg:postcode":"29678",
    "sg:province":"SC",
    "wof:name":"Seneca Lodge",
    "wof:placetype":"venue"
},
  "geometry": {"coordinates":[-82.953441,34.687009],"type":"Point"}
}