{
  "type": "Feature",
  "properties": {
    "iso:country":"US",
    "sg:address":"185 Montford Rd",
    "sg:city":"Georgetown",
    "sg:classifiers":[
        {
            "category":"Professional",
            "subcategory":"Accounting & Tax Preparation",
            "type":"Services"
        }
    ],
    "sg:phone":"+1 843 545 8914",
    "sg:postcode":"29440",
    "sg:province":"SC",
    "sg:tags":[
        "return",
        "filing"
    ],
    "wof:name":"Yolanda's Taxes",
    "wof:placetype":"venue"
},
  "geometry": {"coordinates":[-79.30575399999999,33.339382],"type":"Point"}
}