{
  "type": "Feature",
  "properties": {
    "iso:country":"US",
    "sg:address":"2300 Evans St",
    "sg:city":"Newberry",
    "sg:classifiers":[
        {
            "category":"Social Services",
            "subcategory":"Child Care",
            "type":"Services"
        }
    ],
    "sg:phone":"+1 803 276 3045",
    "sg:postcode":"29108",
    "sg:province":"SC",
    "wof:name":"Little Folk's Child Care Svc",
    "wof:placetype":"venue"
},
  "geometry": {"coordinates":[-81.610741,34.286809],"type":"Point"}
}