{
  "type": "Feature",
  "properties": {
    "iso:country":"US",
    "sg:address":"24 N Market St",
    "sg:city":"Charleston",
    "sg:classifiers":[
        {
            "category":"Health Services",
            "subcategory":"Doctor",
            "type":"Services"
        }
    ],
    "sg:phone":"+1 843 722 7077",
    "sg:postcode":"29401",
    "sg:province":"SC",
    "sg:tags":[
        "dentist"
    ],
    "wof:name":"Velocity Dental LLC",
    "wof:placetype":"venue"
},
  "geometry": {"coordinates":[-79.92588499999999,32.781337],"type":"Point"}
}