{
  "type": "Feature",
  "properties": {
    "iso:country":"US",
    "sg:address":"1002 S Main St",
    "sg:city":"Darlington",
    "sg:classifiers":[
        {
            "category":"Personal",
            "subcategory":"Beauty Salon",
            "type":"Services"
        }
    ],
    "sg:phone":"+1 843 393 1957",
    "sg:postcode":"29532",
    "sg:province":"SC",
    "wof:name":"Curl & Style Beauty Salon",
    "wof:placetype":"venue"
},
  "geometry": {"coordinates":[-79.86250099999999,34.290499],"type":"Point"}
}