{
  "type": "Feature",
  "properties": {
    "iso:country":"US",
    "sg:address":"109 N Buncombe Rd",
    "sg:city":"Greer",
    "sg:classifiers":[
        {
            "category":"Professional",
            "subcategory":"Lawyer & Legal Services",
            "type":"Services"
        }
    ],
    "sg:phone":"+1 864 848 9519",
    "sg:postcode":"29651",
    "sg:province":"SC",
    "sg:tags":[
        "attorney"
    ],
    "wof:name":"Temple Mann Briggs Hill",
    "wof:placetype":"venue"
},
  "geometry": {"coordinates":[-82.260633,34.945437],"type":"Point"}
}