{
  "type": "Feature",
  "properties": {
    "iso:country":"US",
    "sg:address":"1131 Louise Ter",
    "sg:city":"Mount Pleasant",
    "sg:classifiers":[
        {
            "category":"Travel",
            "subcategory":"Travel Agent",
            "type":"Entertainment"
        }
    ],
    "sg:phone":"+1 843 881 0996",
    "sg:postcode":"29464",
    "sg:province":"SC",
    "sg:tags":[
        "operator",
        "tour"
    ],
    "wof:name":"Lowcountry Excursions",
    "wof:placetype":"venue"
},
  "geometry": {"coordinates":[-79.84707899999999,32.812736],"type":"Point"}
}