{
  "type": "Feature",
  "properties": {
    "iso:country":"US",
    "sg:address":"131 Spring St",
    "sg:city":"Charleston",
    "sg:classifiers":[
        {
            "category":"Personal",
            "type":"Services"
        }
    ],
    "sg:phone":"+1 843 722 9333",
    "sg:postcode":"29403",
    "sg:province":"SC",
    "sg:tags":[
        "consultant",
        "wedding"
    ],
    "wof:name":"Weddings Elegantly Designed",
    "wof:placetype":"venue"
},
  "geometry": {"coordinates":[-79.94888899999999,32.789405],"type":"Point"}
}