{
  "type": "Feature",
  "properties": {
    "iso:country":"US",
    "sg:address":"903 Lakeside Dr",
    "sg:city":"Conway",
    "sg:classifiers":[
        {
            "category":"Real Estate",
            "subcategory":"Real Estate Agent",
            "type":"Services"
        }
    ],
    "sg:phone":"+1 843 248 9511",
    "sg:postcode":"29526",
    "sg:province":"SC",
    "wof:name":"Conway Real Estate Agency",
    "wof:placetype":"venue"
},
  "geometry": {"coordinates":[-79.048462,33.844563],"type":"Point"}
}