{
  "type": "Feature",
  "properties": {
    "iso:country":"US",
    "sg:address":"115 E Smith Ave",
    "sg:city":"Darlington",
    "sg:classifiers":[
        {
            "category":"Government",
            "subcategory":"Post Office",
            "type":"Public Place"
        }
    ],
    "sg:phone":"+1 843 393 3223",
    "sg:postcode":"29532",
    "sg:province":"SC",
    "wof:name":"US Post Office",
    "wof:placetype":"venue"
},
  "geometry": {"coordinates":[-79.88431300000001,34.316818],"type":"Point"}
}