{
  "type": "Feature",
  "properties": {
    "iso:country":"US",
    "sg:address":"1292 Broughton St",
    "sg:city":"Orangeburg",
    "sg:classifiers":[
        {
            "category":"Insurance",
            "subcategory":"Insurance Agent",
            "type":"Services"
        }
    ],
    "sg:phone":"+1 803 536 5353",
    "sg:postcode":"29115",
    "sg:province":"SC",
    "wof:name":"Keith A Hewitt Jr Insurance",
    "wof:placetype":"venue"
},
  "geometry": {"coordinates":[-80.866547,33.489866],"type":"Point"}
}