{
  "type": "Feature",
  "properties": {
    "iso:country":"US",
    "sg:address":"3550 S Live Oak Dr",
    "sg:city":"Moncks Corner",
    "sg:classifiers":[
        {
            "category":"Manufacturing",
            "subcategory":"Tools & Machinery",
            "type":"Manufacturing & Wholesale Goods"
        }
    ],
    "sg:phone":"+1 843 761 4456",
    "sg:postcode":"29461",
    "sg:province":"SC",
    "sg:tags":[
        "machine",
        "shop"
    ],
    "wof:name":"S & R Machine",
    "wof:placetype":"venue"
},
  "geometry": {"coordinates":[-80.08805700000001,33.070008],"type":"Point"}
}