{
  "type": "Feature",
  "properties": {
    "addr:full":"169 Baruch Ln Pawleys Island SC 29585",
    "addr:housenumber":"169",
    "addr:postcode":"29585",
    "addr:street":"Baruch Ln",
    "iso:country":"US",
    "sg:address":"169 Baruch Ln",
    "sg:city":"Pawleys Island",
    "sg:classifiers":[
        {
            "category":"Building & Trades",
            "subcategory":"Construction",
            "type":"Services"
        }
    ],
    "sg:phone":"+1 843 237 2423",
    "sg:postcode":"29585",
    "sg:province":"SC",
    "sg:tags":[
        "house",
        "contractor"
    ],
    "wof:name":"T Morris Construction",
    "wof:placetype":"venue"
},
  "geometry": {"coordinates":[-79.17782699999999,33.436317],"type":"Point"}
}