{
  "type": "Feature",
  "properties": {
    "iso:country":"US",
    "sg:address":"680 Edgefield Rd",
    "sg:city":"Cowpens",
    "sg:classifiers":[
        {
            "category":"Wholesale",
            "subcategory":"Machinery & Supplies",
            "type":"Manufacturing & Wholesale Goods"
        }
    ],
    "sg:phone":"+1 864 582 6161",
    "sg:postcode":"29330",
    "sg:province":"SC",
    "sg:tags":[
        "textile",
        "parts"
    ],
    "sg:website":"www.arcadiatextilemachinery.com",
    "wof:name":"Arcadia Textile Machinery",
    "wof:placetype":"venue"
},
  "geometry": {"coordinates":[-81.809811,35.046603],"type":"Point"}
}