{
  "type": "Feature",
  "properties": {
    "iso:country":"US",
    "sg:address":"909 Wesley Ct",
    "sg:city":"Spartanburg",
    "sg:classifiers":[
        {
            "category":"Shopping",
            "subcategory":"Computers & Home Electronics",
            "type":"Retail Goods"
        }
    ],
    "sg:phone":"+1 864 578 1038",
    "sg:postcode":"29316",
    "sg:province":"SC",
    "sg:tags":[
        "software"
    ],
    "sg:website":"www.pcssinc.com",
    "wof:name":"Professional Computer Software",
    "wof:placetype":"venue"
},
  "geometry": {"coordinates":[-81.972674,35.042514],"type":"Point"}
}