{
  "type": "Feature",
  "properties": {
    "iso:country":"US",
    "sg:address":"4709 Broad River Rd",
    "sg:city":"Columbia",
    "sg:classifiers":[
        {
            "category":"Retail",
            "subcategory":"Auto Repair",
            "type":"Services"
        }
    ],
    "sg:phone":"+1 803 772 7585",
    "sg:postcode":"29210",
    "sg:province":"SC",
    "sg:tags":[
        "repairing",
        "automobile"
    ],
    "wof:name":"Colony Station Auto Repair",
    "wof:placetype":"venue"
},
  "geometry": {"coordinates":[-81.119928,34.070376],"type":"Point"}
}