{
  "type": "Feature",
  "properties": {
    "addr:full":"182 E Queen St Pendleton SC 29670",
    "addr:housenumber":"182",
    "addr:postcode":"29670",
    "addr:street":"E Queen St",
    "iso:country":"US",
    "sg:address":"182 E Queen St",
    "sg:city":"Pendleton",
    "sg:classifiers":[
        {
            "category":"Banks & Credit Unions",
            "subcategory":"Bank",
            "type":"Services"
        }
    ],
    "sg:phone":"+1 864 646 3238",
    "sg:postcode":"29670",
    "sg:province":"SC",
    "sg:tags":[
        "national",
        "commercial"
    ],
    "wof:name":"Bank of America",
    "wof:placetype":"venue"
},
  "geometry": {"coordinates":[-82.783131,34.651689],"type":"Point"}
}