{
  "type": "Feature",
  "properties": {
    "iso:country":"US",
    "sg:address":"21 Morgan's Cove Dr",
    "sg:city":"Isle Of Palms",
    "sg:classifiers":[
        {
            "category":"Building & Trades",
            "subcategory":"Construction",
            "type":"Services"
        }
    ],
    "sg:phone":"+1 843 886 9003",
    "sg:postcode":"29451",
    "sg:province":"SC",
    "sg:tags":[
        "contractor"
    ],
    "wof:name":"Ans Interiors",
    "wof:placetype":"venue"
},
  "geometry": {"coordinates":[-79.756436,32.802467],"type":"Point"}
}