{
  "type": "Feature",
  "properties": {
    "addr:full":"21 Morgan's Cove Dr Isle Of Palms SC 29451",
    "addr:housenumber":"21",
    "addr:postcode":"29451",
    "addr:street":"Morgan'S Cove Dr",
    "iso:country":"US",
    "sg:address":"21 Morgan's Cove Dr",
    "sg:city":"Isle Of Palms",
    "sg:classifiers":[
        {
            "category":"Building & Trades",
            "subcategory":"Construction",
            "type":"Services"
        }
    ],
    "sg:phone":"+1 843 886 9003",
    "sg:postcode":"29451",
    "sg:province":"SC",
    "sg:tags":[
        "contractor"
    ],
    "wof:name":"Ans Interiors",
    "wof:placetype":"venue"
},
  "geometry": {"coordinates":[-79.75643599999999,32.802467],"type":"Point"}
}