{
  "type": "Feature",
  "properties": {
    "addr:full":"1037 Keithwood Ln Blythewood SC 29016",
    "addr:housenumber":"1037",
    "addr:postcode":"29016",
    "addr:street":"Keithwood Ln",
    "iso:country":"US",
    "sg:address":"1037 Keithwood Ln",
    "sg:city":"Blythewood",
    "sg:classifiers":[
        {
            "category":"Building & Trades",
            "subcategory":"Electrical",
            "type":"Services"
        }
    ],
    "sg:phone":"+1 803 754 8661",
    "sg:postcode":"29016",
    "sg:province":"SC",
    "sg:tags":[
        "electrical",
        "contractor"
    ],
    "wof:name":"BECO Electric Inc",
    "wof:placetype":"venue"
},
  "geometry": {"coordinates":[-80.978523,34.157713],"type":"Point"}
}