{
  "type": "Feature",
  "properties": {
    "addr:full":"400 Dozier St Georgetown SC 29440",
    "addr:housenumber":"400",
    "addr:postcode":"29440",
    "addr:street":"Dozier St",
    "iso:country":"US",
    "sg:address":"400 Dozier St",
    "sg:city":"Georgetown",
    "sg:classifiers":[
        {
            "category":"Recreation",
            "type":"Entertainment"
        }
    ],
    "sg:phone":"+1 843 545 3275",
    "sg:postcode":"29440",
    "sg:province":"SC",
    "sg:tags":[
        "parks"
    ],
    "wof:name":"Georgetown County Recreation",
    "wof:placetype":"venue"
},
  "geometry": {"coordinates":[-79.28707199999999,33.373042],"type":"Point"}
}