{
  "type": "Feature",
  "properties": {
    "addr:full":"5721 Salters Hill Rd Ravenel SC 29470",
    "addr:housenumber":"5721",
    "addr:postcode":"29470",
    "addr:street":"Salters Hill Rd",
    "iso:country":"US",
    "sg:address":"5721 Salters Hill Rd",
    "sg:city":"Ravenel",
    "sg:classifiers":[
        {
            "category":"Building & Trades",
            "subcategory":"Construction",
            "type":"Services"
        }
    ],
    "sg:phone":"+1 843 889 8235",
    "sg:postcode":"29470",
    "sg:province":"SC",
    "sg:tags":[
        "house"
    ],
    "wof:name":"Daniel Middleton Construc",
    "wof:placetype":"venue"
},
  "geometry": {"coordinates":[-80.218368,32.768725],"type":"Point"}
}