{
  "type": "Feature",
  "properties": {
    "addr:full":"206 King St Charleston SC 29401",
    "addr:housenumber":"206",
    "addr:postcode":"29401",
    "addr:street":"King St",
    "iso:country":"US",
    "sg:address":"206 King St",
    "sg:city":"Charleston",
    "sg:classifiers":[
        {
            "category":"Shopping",
            "subcategory":"Used Merchandise",
            "type":"Retail Goods"
        },
        {
            "category":"Wholesale",
            "subcategory":"Durable Goods & Equipment",
            "type":"Manufacturing & Wholesale Goods"
        }
    ],
    "sg:phone":"+1 843 723 8886",
    "sg:postcode":"29401",
    "sg:province":"SC",
    "sg:tags":[
        "antique"
    ],
    "wof:name":"Golden & Associate Antiques",
    "wof:placetype":"venue"
},
  "geometry": {"coordinates":[-79.93311,32.779719],"type":"Point"}
}