{
  "type": "Feature",
  "properties": {
    "iso:country":"US",
    "sg:address":"632 N Main St",
    "sg:city":"Greenville",
    "sg:classifiers":[
        {
            "category":"Wholesale",
            "subcategory":"Office Equipment",
            "type":"Manufacturing & Wholesale Goods"
        }
    ],
    "sg:phone":"+1 864 963 5453",
    "sg:postcode":"29601",
    "sg:province":"SC",
    "sg:tags":[
        "printing",
        "offset"
    ],
    "wof:name":"A B Dick Company Del",
    "wof:placetype":"venue"
},
  "geometry": {"coordinates":[-82.394599,34.860438],"type":"Point"}
}