{
  "type": "Feature",
  "properties": {
    "iso:country":"US",
    "sg:address":"1350 Commerce Pl",
    "sg:city":"Myrtle Beach",
    "sg:classifiers":[
        {
            "category":"Manufacturing",
            "subcategory":"Building Materials",
            "type":"Manufacturing & Wholesale Goods"
        }
    ],
    "sg:phone":"+1 843 626 9421",
    "sg:postcode":"29577",
    "sg:province":"SC",
    "sg:website":"www.coxmillwork.com",
    "wof:name":"Cox Millwork & Supply Inc",
    "wof:placetype":"venue"
},
  "geometry": {"coordinates":[-78.903694,33.704247],"type":"Point"}
}