{
  "type": "Feature",
  "properties": {
    "iso:country":"US",
    "sg:address":"311 N Cashua Dr",
    "sg:city":"Florence",
    "sg:classifiers":[
        {
            "category":"Autos & Motor Vehicles",
            "subcategory":"Automobile Sales",
            "type":"Retail Goods"
        }
    ],
    "sg:phone":"+1 843 661 4000",
    "sg:postcode":"29501",
    "sg:province":"SC",
    "sg:tags":[
        "car",
        "dealer"
    ],
    "sg:website":"www.auddiebrown.com",
    "wof:name":"Auddie Brown Auto Sales",
    "wof:placetype":"venue"
},
  "geometry": {"coordinates":[-79.801211,34.199283],"type":"Point"}
}