{
  "type": "Feature",
  "properties": {
    "iso:country":"US",
    "sg:address":"4136 Clemson Blvd",
    "sg:city":"Anderson",
    "sg:classifiers":[
        {
            "category":"Home & Garden",
            "subcategory":"Furniture",
            "type":"Retail Goods"
        }
    ],
    "sg:phone":"+1 864 231 0384",
    "sg:postcode":"29621",
    "sg:province":"SC",
    "sg:tags":[
        "equipment",
        "kitchen",
        "cabinet"
    ],
    "wof:name":"Stone Surfaces Unlimited",
    "wof:placetype":"venue"
},
  "geometry": {"coordinates":[-82.693822,34.560746],"type":"Point"}
}