{
  "type": "Feature",
  "properties": {
    "iso:country":"US",
    "sg:address":"239 N Jefferies Blvd",
    "sg:city":"Walterboro",
    "sg:classifiers":[
        {
            "category":"Organizations",
            "subcategory":"Non-profit Organization",
            "type":"Services"
        }
    ],
    "sg:phone":"+1 843 549 1079",
    "sg:postcode":"29488",
    "sg:province":"SC",
    "sg:website":"www.ricefestival.org",
    "wof:name":"Rice Festival",
    "wof:placetype":"venue"
},
  "geometry": {"coordinates":[-80.668028,32.912453],"type":"Point"}
}