{
  "type": "Feature",
  "properties": {
    "addr:full":"1519 Main St Hilton Head Isle SC 29926",
    "addr:housenumber":"1519",
    "addr:postcode":"29926",
    "addr:street":"Main St",
    "iso:country":"US",
    "sg:address":"1519 Main St",
    "sg:city":"Hilton Head Isle",
    "sg:classifiers":[
        {
            "category":"Professional",
            "subcategory":"Advertising",
            "type":"Services"
        }
    ],
    "sg:phone":"+1 843 689 6507",
    "sg:postcode":"29926",
    "sg:province":"SC",
    "sg:tags":[
        "mailing",
        "shipping"
    ],
    "wof:name":"UPS Store",
    "wof:placetype":"venue"
},
  "geometry": {"coordinates":[-80.72448300000001,32.214755],"type":"Point"}
}