{
  "type": "Feature",
  "properties": {
    "iso:country":"US",
    "sg:address":"2527 Devine St",
    "sg:city":"Columbia",
    "sg:classifiers":[
        {
            "category":"Food & Beverages",
            "subcategory":"Groceries & Convenience Stores",
            "type":"Retail Goods"
        }
    ],
    "sg:phone":"+1 803 771 6943",
    "sg:postcode":"29205",
    "sg:province":"SC",
    "wof:name":"Young's Food Stores",
    "wof:placetype":"venue"
},
  "geometry": {"coordinates":[-81.007691,33.998486],"type":"Point"}
}