{
  "type": "Feature",
  "properties": {
    "addr:full":"975 Savannah Hwy Charleston SC 29407",
    "addr:housenumber":"975",
    "addr:postcode":"29407",
    "addr:street":"Savannah Hwy",
    "iso:country":"US",
    "sg:address":"975 Savannah Hwy",
    "sg:city":"Charleston",
    "sg:classifiers":[
        {
            "category":"Shopping",
            "subcategory":"Department Store",
            "type":"Retail Goods"
        }
    ],
    "sg:phone":"+1 843 763 2444",
    "sg:postcode":"29407",
    "sg:province":"SC",
    "wof:name":"Stein Mart",
    "wof:placetype":"venue"
},
  "geometry": {"coordinates":[-79.99065400000001,32.78278],"type":"Point"}
}