{
  "type": "Feature",
  "properties": {
    "addr:full":"240 S Dargan St Florence SC 29506",
    "addr:housenumber":"240",
    "addr:postcode":"29506",
    "addr:street":"S Dargan St",
    "iso:country":"US",
    "sg:address":"240 S Dargan St",
    "sg:city":"Florence",
    "sg:classifiers":[
        {
            "category":"Education",
            "subcategory":"Special Training",
            "type":"Public Place"
        }
    ],
    "sg:phone":"+1 843 667 1908",
    "sg:postcode":"29506",
    "sg:province":"SC",
    "sg:tags":[
        "reading",
        "instruction",
        "improvement"
    ],
    "wof:name":"Florence Area Literacy Council",
    "wof:placetype":"venue"
},
  "geometry": {"coordinates":[-79.765817,34.194516],"type":"Point"}
}