{
  "type": "Feature",
  "properties": {
    "addr:full":"628 Orangeburg Rd Summerville SC 29483",
    "addr:housenumber":"628",
    "addr:postcode":"29483",
    "addr:street":"Orangeburg Rd",
    "iso:country":"US",
    "sg:address":"628 Orangeburg Rd",
    "sg:city":"Summerville",
    "sg:classifiers":[
        {
            "category":"Building & Trades",
            "subcategory":"Landscaping Services",
            "type":"Services"
        }
    ],
    "sg:phone":"+1 843 873 8939",
    "sg:postcode":"29483",
    "sg:province":"SC",
    "sg:tags":[
        "tree"
    ],
    "wof:name":"Russell Consulting LLC",
    "wof:placetype":"venue"
},
  "geometry": {"coordinates":[-80.239806,33.017186],"type":"Point"}
}