{
  "type": "Feature",
  "properties": {
    "iso:country":"US",
    "sg:address":"1116 Lancelot Ln",
    "sg:city":"Conway",
    "sg:classifiers":[
        {
            "category":"Social Services",
            "subcategory":"Adult Care",
            "type":"Services"
        }
    ],
    "sg:phone":"+1 843 234 0161",
    "sg:postcode":"29526",
    "sg:province":"SC",
    "sg:tags":[
        "home",
        "group"
    ],
    "wof:name":"Castlewood CTH",
    "wof:placetype":"venue"
},
  "geometry": {"coordinates":[-79.011465,33.759624],"type":"Point"}
}