{
  "type": "Feature",
  "properties": {
    "iso:country":"US",
    "sg:address":"573 Meeting St",
    "sg:city":"Charleston",
    "sg:classifiers":[
        {
            "category":"Social Services",
            "type":"Services"
        }
    ],
    "sg:phone":"+1 843 723 9477",
    "sg:postcode":"29403",
    "sg:province":"SC",
    "sg:tags":[
        "organization",
        "welfare"
    ],
    "wof:name":"Crisis Ministries",
    "wof:placetype":"venue"
},
  "geometry": {"coordinates":[-79.94348599999999,32.800855],"type":"Point"}
}