{
  "type": "Feature",
  "properties": {
    "iso:country":"US",
    "sg:address":"1745 Dixired Rd",
    "sg:city":"Leesville",
    "sg:classifiers":[
        {
            "category":"Building & Trades",
            "subcategory":"Construction",
            "type":"Services"
        }
    ],
    "sg:phone":"+1 803 532 0939",
    "sg:postcode":"29070",
    "sg:province":"SC",
    "sg:tags":[
        "contractor"
    ],
    "wof:name":"Malcolm Kopacz",
    "wof:placetype":"venue"
},
  "geometry": {"coordinates":[-81.47567100000001,33.881337],"type":"Point"}
}