{
  "type": "Feature",
  "properties": {
    "addr:full":"621 Airport Rd Greenville SC 29607",
    "addr:housenumber":"621",
    "addr:postcode":"29607",
    "addr:street":"Airport Rd",
    "iso:country":"US",
    "sg:address":"621 Airport Rd",
    "sg:city":"Greenville",
    "sg:classifiers":[
        {
            "category":"Bars & Pubs",
            "type":"Food & Drink"
        }
    ],
    "sg:phone":"+1 864 234 6767",
    "sg:postcode":"29607",
    "sg:province":"SC",
    "sg:tags":[
        "club",
        "night"
    ],
    "wof:name":"Club 621",
    "wof:placetype":"venue"
},
  "geometry": {"coordinates":[-82.345085,34.843356],"type":"Point"}
}