{
  "type": "Feature",
  "properties": {
    "addr:full":"11657 C R Koon Hwy Prosperity SC 29127",
    "addr:housenumber":"11657 c",
    "addr:postcode":"29127",
    "addr:street":"Koon Hwy",
    "iso:country":"US",
    "sg:address":"11657 C R Koon Hwy",
    "sg:city":"Prosperity",
    "sg:classifiers":[
        {
            "category":"Autos & Motor Vehicles",
            "subcategory":"Automobile Sales",
            "type":"Retail Goods"
        }
    ],
    "sg:phone":"+1 803 364 1343",
    "sg:postcode":"29127",
    "sg:province":"SC",
    "sg:tags":[
        "car",
        "dealer"
    ],
    "wof:name":"Jim's Auto Sales",
    "wof:placetype":"venue"
},
  "geometry": {"coordinates":[-81.542917,34.222489],"type":"Point"}
}