{
  "type": "Feature",
  "properties": {
    "iso:country":"US",
    "sg:address":"802 37th Ave S",
    "sg:city":"North Myrtle Bch",
    "sg:classifiers":[
        {
            "category":"Restaurant",
            "type":"Food & Drink"
        }
    ],
    "sg:phone":"+1 843 272 3351",
    "sg:postcode":"29582",
    "sg:province":"SC",
    "wof:name":"Horst Gast Haus",
    "wof:placetype":"venue"
},
  "geometry": {"coordinates":[-78.726101,33.802852],"type":"Point"}
}