{
  "type": "Feature",
  "properties": {
    "iso:country":"US",
    "sg:address":"1321 3rd Ave",
    "sg:city":"Conway",
    "sg:classifiers":[
        {
            "category":"Shopping",
            "subcategory":"Stationery & Office Supplies",
            "type":"Retail Goods"
        }
    ],
    "sg:phone":"+1 843 248 5364",
    "sg:postcode":"29526",
    "sg:province":"SC",
    "sg:tags":[
        "repair"
    ],
    "wof:name":"Coopers Typewriter Service",
    "wof:placetype":"venue"
},
  "geometry": {"coordinates":[-79.049789,33.833328],"type":"Point"}
}