{
  "type": "Feature",
  "properties": {
    "iso:country":"US",
    "sg:address":"2432 US Hwy 221",
    "sg:city":"Greenwood",
    "sg:classifiers":[
        {
            "category":"Wholesale",
            "subcategory":"Machinery & Supplies",
            "type":"Manufacturing & Wholesale Goods"
        }
    ],
    "sg:phone":"+1 864 229 4045",
    "sg:postcode":"29649",
    "sg:province":"SC",
    "sg:tags":[
        "bearing"
    ],
    "wof:name":"Bearing Distributors",
    "wof:placetype":"venue"
},
  "geometry": {"coordinates":[-82.109159,34.228976],"type":"Point"}
}