{
  "type": "Feature",
  "properties": {
    "iso:country":"US",
    "sg:address":"2609 Kelleytown Rd",
    "sg:city":"Hartsville",
    "sg:classifiers":[
        {
            "category":"Organizations",
            "subcategory":"Religious Organization",
            "type":"Services"
        }
    ],
    "sg:phone":"+1 843 332 8092",
    "sg:postcode":"29550",
    "sg:province":"SC",
    "sg:tags":[
        "church"
    ],
    "wof:name":"Kelleytown Baptist Church",
    "wof:placetype":"venue"
},
  "geometry": {"coordinates":[-80.143111,34.349678],"type":"Point"}
}