{
  "type": "Feature",
  "properties": {
    "iso:country":"US",
    "sg:address":"1750 Andrews Rd",
    "sg:city":"Columbia",
    "sg:classifiers":[
        {
            "category":"Wholesale",
            "subcategory":"Electrical",
            "type":"Manufacturing & Wholesale Goods"
        }
    ],
    "sg:phone":"+1 803 799 1500",
    "sg:postcode":"29201",
    "sg:province":"SC",
    "sg:tags":[
        "communication",
        "radio",
        "system"
    ],
    "wof:name":"Two Way Radio Of SC Inc",
    "wof:placetype":"venue"
},
  "geometry": {"coordinates":[-80.99775,33.9689],"type":"Point"}
}