{
  "type": "Feature",
  "properties": {
    "iso:country":"US",
    "sg:address":"2632 New Hope Rd",
    "sg:city":"Pomaria",
    "sg:classifiers":[
        {
            "category":"Restaurant",
            "type":"Food & Drink"
        }
    ],
    "sg:phone":"+1 803 276 0270",
    "sg:postcode":"29126",
    "sg:province":"SC",
    "sg:tags":[
        "eating"
    ],
    "wof:name":"Bos",
    "wof:placetype":"venue"
},
  "geometry": {"coordinates":[-81.42990500000001,34.312983],"type":"Point"}
}