{
  "type": "Feature",
  "properties": {
    "iso:country":"US",
    "sg:address":"1747 Knox Ave",
    "sg:city":"North Augusta",
    "sg:classifiers":[
        {
            "category":"Autos & Motor Vehicles",
            "subcategory":"Auto Supplies",
            "type":"Retail Goods"
        }
    ],
    "sg:phone":"+1 803 279 0369",
    "sg:postcode":"29841",
    "sg:province":"SC",
    "sg:tags":[
        "automobile",
        "parts"
    ],
    "wof:name":"O'Reilly Auto Parts",
    "wof:placetype":"venue"
},
  "geometry": {"coordinates":[-81.956056,33.5166],"type":"Point"}
}