{
  "type": "Feature",
  "properties": {
    "iso:country":"US",
    "sg:address":"4747 National Dr",
    "sg:city":"Myrtle Beach",
    "sg:classifiers":[
        {
            "category":"Education",
            "subcategory":"Special Training",
            "type":"Public Place"
        }
    ],
    "sg:phone":"+1 843 347 1965",
    "sg:postcode":"29578",
    "sg:province":"SC",
    "sg:tags":[
        "instruction",
        "music"
    ],
    "wof:name":"Piano Instruction-Dr Anderson",
    "wof:placetype":"venue"
},
  "geometry": {"coordinates":[-78.970433,33.781173],"type":"Point"}
}