{
  "type": "Feature",
  "properties": {
    "iso:country":"US",
    "sg:address":"1211 Central Ave",
    "sg:city":"Summerville",
    "sg:classifiers":[
        {
            "category":"Real Estate",
            "subcategory":"Real Estate Operator",
            "type":"Services"
        }
    ],
    "sg:phone":"+1 843 873 0731",
    "sg:postcode":"29483",
    "sg:province":"SC",
    "sg:tags":[
        "building",
        "apartment"
    ],
    "wof:name":"Altman Apartments",
    "wof:placetype":"venue"
},
  "geometry": {"coordinates":[-80.257925,32.995073],"type":"Point"}
}