{
  "type": "Feature",
  "properties": {
    "iso:country":"US",
    "sg:address":"311 Fleming Rd",
    "sg:city":"Charleston",
    "sg:classifiers":[
        {
            "category":"Shopping",
            "subcategory":"Beauty & Cosmetics",
            "type":"Retail Goods"
        }
    ],
    "sg:phone":"+1 843 762 1230",
    "sg:postcode":"29412",
    "sg:province":"SC",
    "sg:tags":[
        "merchandise"
    ],
    "wof:name":"Judotus Oils",
    "wof:placetype":"venue"
},
  "geometry": {"coordinates":[-79.98252599999999,32.759639],"type":"Point"}
}