{
  "type": "Feature",
  "properties": {
    "iso:country":"US",
    "sg:address":"550 Jefferson Davis Hwy",
    "sg:city":"Warrenville",
    "sg:classifiers":[
        {
            "category":"Autos & Motor Vehicles",
            "subcategory":"Automobile Sales",
            "type":"Retail Goods"
        }
    ],
    "sg:phone":"+1 803 663 3636",
    "sg:postcode":"29851",
    "sg:province":"SC",
    "sg:tags":[
        "car",
        "dealer"
    ],
    "sg:website":"www.hondacarsofaiken.com",
    "wof:name":"Honda Cars Of Aiken",
    "wof:placetype":"venue"
},
  "geometry": {"coordinates":[-81.791342,33.558766],"type":"Point"}
}