{
  "type": "Feature",
  "properties": {
    "addr:full":"119 Murray Dr Mauldin SC 29662",
    "addr:housenumber":"119",
    "addr:postcode":"29662",
    "addr:street":"Murray Dr",
    "iso:country":"US",
    "sg:address":"119 Murray Dr",
    "sg:city":"Mauldin",
    "sg:classifiers":[
        {
            "category":"Wholesale",
            "subcategory":"Machinery & Supplies",
            "type":"Manufacturing & Wholesale Goods"
        }
    ],
    "sg:phone":"+1 864 286 9835",
    "sg:postcode":"29662",
    "sg:province":"SC",
    "sg:tags":[
        "sprinkler"
    ],
    "wof:name":"Sentury Sprinkler Svc",
    "wof:placetype":"venue"
},
  "geometry": {"coordinates":[-82.310664,34.785963],"type":"Point"}
}