{
  "type": "Feature",
  "properties": {
    "addr:full":"1208 Geer Hwy Travelers Rest SC 29690",
    "addr:housenumber":"1208",
    "addr:postcode":"29690",
    "addr:street":"Geer Hwy",
    "iso:country":"US",
    "sg:address":"1208 Geer Hwy",
    "sg:city":"Travelers Rest",
    "sg:classifiers":[
        {
            "category":"Wholesale",
            "subcategory":"Apparel",
            "type":"Manufacturing & Wholesale Goods"
        }
    ],
    "sg:phone":"+1 864 834 8424",
    "sg:postcode":"29690",
    "sg:province":"SC",
    "sg:tags":[
        "textile",
        "broker"
    ],
    "wof:name":"Bella Embroidery",
    "wof:placetype":"venue"
},
  "geometry": {"coordinates":[-82.463418,34.983265],"type":"Point"}
}