{
  "type": "Feature",
  "properties": {
    "addr:full":"3600 Wade Hampton Blvd Taylors SC 29687",
    "addr:housenumber":"3600",
    "addr:postcode":"29687",
    "addr:street":"Wade Hampton Blvd",
    "iso:country":"US",
    "sg:address":"3600 Wade Hampton Blvd",
    "sg:city":"Taylors",
    "sg:classifiers":[
        {
            "category":"Shopping",
            "subcategory":"Used Merchandise",
            "type":"Retail Goods"
        }
    ],
    "sg:phone":"+1 864 609 9400",
    "sg:postcode":"29687",
    "sg:province":"SC",
    "wof:name":"Xponential Inc",
    "wof:placetype":"venue"
},
  "geometry": {"coordinates":[-82.302882,34.925619],"type":"Point"}
}