{
  "type": "Feature",
  "properties": {
    "iso:country":"US",
    "sg:address":"7523 Kershaw Camden Hwy",
    "sg:city":"Kershaw",
    "sg:classifiers":[
        {
            "category":"Recreation",
            "type":"Entertainment"
        }
    ],
    "sg:phone":"+1 803 475 5700",
    "sg:postcode":"29067",
    "sg:province":"SC",
    "sg:tags":[
        "martial",
        "arts",
        "instruction"
    ],
    "wof:name":"Waiters Martial Arts Studio",
    "wof:placetype":"venue"
},
  "geometry": {"coordinates":[-80.589072,34.565554],"type":"Point"}
}