{
  "type": "Feature",
  "properties": {
    "iso:country":"US",
    "sg:address":"1119 Woodlawn Ave",
    "sg:city":"Columbia",
    "sg:classifiers":[
        {
            "category":"Wholesale",
            "subcategory":"Electrical",
            "type":"Manufacturing & Wholesale Goods"
        }
    ],
    "sg:phone":"+1 803 776 8888",
    "sg:postcode":"29209",
    "sg:province":"SC",
    "sg:tags":[
        "alarm",
        "burglar",
        "system"
    ],
    "sg:website":"www.nationwidesecuritysystems.com",
    "wof:name":"Nationwide Security Systems",
    "wof:placetype":"venue"
},
  "geometry": {"coordinates":[-80.96232999999999,33.985021],"type":"Point"}
}