{
  "type": "Feature",
  "properties": {
    "iso:country":"US",
    "sg:address":"105 Highview Dr",
    "sg:city":"Greenville",
    "sg:classifiers":[
        {
            "category":"Building & Trades",
            "subcategory":"Construction",
            "type":"Services"
        }
    ],
    "sg:phone":"+1 864 292 3878",
    "sg:postcode":"29609",
    "sg:province":"SC",
    "sg:tags":[
        "hanging",
        "contractor"
    ],
    "wof:name":"A Change of Cover",
    "wof:placetype":"venue"
},
  "geometry": {"coordinates":[-82.360364,34.885821],"type":"Point"}
}