{
  "type": "Feature",
  "properties": {
    "iso:country":"US",
    "sg:address":"1751 Shivers Rd",
    "sg:city":"Columbia",
    "sg:classifiers":[
        {
            "category":"Government",
            "subcategory":"Jail",
            "type":"Public Place"
        }
    ],
    "sg:phone":"+1 803 896 9123",
    "sg:postcode":"29212",
    "sg:province":"SC",
    "sg:tags":[
        "govt",
        "state",
        "institution"
    ],
    "wof:name":"Juvenile Justice-New Direction",
    "wof:placetype":"venue"
},
  "geometry": {"coordinates":[-81.106331,34.054421],"type":"Point"}
}