{
  "type": "Feature",
  "properties": {
    "iso:country":"US",
    "sg:address":"1002 Jody Dr",
    "sg:city":"Seneca",
    "sg:classifiers":[
        {
            "category":"Real Estate",
            "subcategory":"Real Estate Agent",
            "type":"Services"
        }
    ],
    "sg:phone":"+1 864 882 2760",
    "sg:postcode":"29678",
    "sg:province":"SC",
    "wof:name":"Riverbirch Homes & Properties",
    "wof:placetype":"venue"
},
  "geometry": {"coordinates":[-82.995512,34.67378],"type":"Point"}
}