{
  "type": "Feature",
  "properties": {
    "addr:full":"1370 Remount Rd North Charleston SC 29406",
    "addr:housenumber":"1370",
    "addr:postcode":"29406",
    "addr:street":"Remount Rd",
    "iso:country":"US",
    "sg:address":"1370 Remount Rd",
    "sg:city":"North Charleston",
    "sg:classifiers":[
        {
            "category":"Health Services",
            "subcategory":"Doctor",
            "type":"Services"
        }
    ],
    "sg:phone":"+1 843 566 1200",
    "sg:postcode":"29406",
    "sg:province":"SC",
    "sg:tags":[
        "physician",
        "surgeon"
    ],
    "wof:name":"Ravenel Ob Gyn",
    "wof:placetype":"venue"
},
  "geometry": {"coordinates":[-79.99656299999999,32.901389],"type":"Point"}
}