{
  "type": "Feature",
  "properties": {
    "iso:country":"US",
    "sg:address":"5861 N Rhett Ave",
    "sg:city":"Charleston",
    "sg:classifiers":[
        {
            "category":"Bars & Pubs",
            "type":"Food & Drink"
        }
    ],
    "sg:phone":"+1 843 529 9911",
    "sg:postcode":"29406",
    "sg:province":"SC",
    "sg:tags":[
        "drinking"
    ],
    "wof:name":"Hanahan's Neighborhood Pub",
    "wof:placetype":"venue"
},
  "geometry": {"coordinates":[-79.992352,32.921461],"type":"Point"}
}