{
  "type": "Feature",
  "properties": {
    "addr:full":"400 Kent St Spartanburg SC 29301",
    "addr:housenumber":"400",
    "addr:postcode":"29301",
    "addr:street":"Kent St",
    "iso:country":"US",
    "sg:address":"400 Kent St",
    "sg:city":"Spartanburg",
    "sg:classifiers":[
        {
            "category":"Wholesale",
            "subcategory":"Machinery & Supplies",
            "type":"Manufacturing & Wholesale Goods"
        },
        {
            "category":"Professional",
            "subcategory":"Business Services",
            "type":"Services"
        }
    ],
    "sg:phone":"+1 864 439 8500",
    "sg:postcode":"29301",
    "sg:province":"SC",
    "sg:tags":[
        "sprinkler",
        "contractor"
    ],
    "wof:name":"Specialty Fire Protection LLC",
    "wof:placetype":"venue"
},
  "geometry": {"coordinates":[-82.044606,34.940208],"type":"Point"}
}