{
  "type": "Feature",
  "properties": {
    "iso:country":"US",
    "sg:address":"3720 S Irby St",
    "sg:city":"Florence",
    "sg:classifiers":[
        {
            "category":"Professional",
            "subcategory":"Business Services",
            "type":"Services"
        }
    ],
    "sg:phone":"+1 843 664 0500",
    "sg:postcode":"29505",
    "sg:province":"SC",
    "sg:tags":[
        "embroidery"
    ],
    "wof:name":"Academy Embroidery & Mngrmmng",
    "wof:placetype":"venue"
},
  "geometry": {"coordinates":[-79.782804,34.110276],"type":"Point"}
}