{
  "type": "Feature",
  "properties": {
    "iso:country":"US",
    "sg:address":"300 N Colonial Dr",
    "sg:city":"Timmonsville",
    "sg:classifiers":[
        {
            "category":"Building & Trades",
            "subcategory":"Construction",
            "type":"Services"
        }
    ],
    "sg:phone":"+1 843 346 2754",
    "sg:postcode":"29161",
    "sg:province":"SC",
    "sg:tags":[
        "masonry",
        "contractor"
    ],
    "wof:name":"Mc Allister Brick Masons",
    "wof:placetype":"venue"
},
  "geometry": {"coordinates":[-79.938727,34.141252],"type":"Point"}
}