{
  "type": "Feature",
  "properties": {
    "iso:country":"US",
    "sg:address":"731 N Main St",
    "sg:city":"Mauldin",
    "sg:classifiers":[
        {
            "category":"Retail",
            "subcategory":"Auto Repair",
            "type":"Services"
        }
    ],
    "sg:phone":"+1 864 281 1504",
    "sg:postcode":"29662",
    "sg:province":"SC",
    "sg:tags":[
        "repairing",
        "automobile"
    ],
    "wof:name":"Quality Automotive",
    "wof:placetype":"venue"
},
  "geometry": {"coordinates":[-82.313456,34.788063],"type":"Point"}
}