{
  "type": "Feature",
  "properties": {
    "iso:country":"US",
    "sg:address":"140 Beulah Rd",
    "sg:city":"Lake City",
    "sg:classifiers":[
        {
            "category":"Restaurant",
            "type":"Food & Drink"
        }
    ],
    "sg:phone":"+1 843 389 3965",
    "sg:postcode":"29560",
    "sg:province":"SC",
    "sg:tags":[
        "banquet",
        "rooms"
    ],
    "wof:name":"C B Askins Banquet Hall",
    "wof:placetype":"venue"
},
  "geometry": {"coordinates":[-79.733653,33.799868],"type":"Point"}
}