{
  "type": "Feature",
  "properties": {
    "addr:full":"737 Pine Ridge Dr West Columbia SC 29172",
    "addr:housenumber":"737",
    "addr:postcode":"29172",
    "addr:street":"Pine Ridge Dr",
    "iso:country":"US",
    "sg:address":"737 Pine Ridge Dr",
    "sg:city":"West Columbia",
    "sg:classifiers":[
        {
            "category":"Education",
            "subcategory":"School",
            "type":"Public Place"
        }
    ],
    "sg:phone":"+1 803 755 7420",
    "sg:postcode":"29172",
    "sg:province":"SC",
    "sg:tags":[
        "high",
        "middle",
        "elementary"
    ],
    "sg:website":"wood.lex2.groupfusion.net",
    "wof:name":"Lexington County School District Two",
    "wof:placetype":"venue"
},
  "geometry": {"coordinates":[-81.10717099999999,33.910186],"type":"Point"}
}