{
  "type": "Feature",
  "properties": {
    "iso:country":"US",
    "sg:address":"410 Baskin Rd",
    "sg:city":"Iva",
    "sg:classifiers":[
        {
            "category":"Shopping",
            "subcategory":"Computers & Home Electronics",
            "type":"Retail Goods"
        }
    ],
    "sg:phone":"+1 864 296 5230",
    "sg:postcode":"29655",
    "sg:province":"SC",
    "wof:name":"AVT",
    "wof:placetype":"venue"
},
  "geometry": {"coordinates":[-82.60534199999999,34.361766],"type":"Point"}
}