{
  "type": "Feature",
  "properties": {
    "addr:full":"306 S Main St Abbeville SC 29620",
    "addr:housenumber":"306",
    "addr:postcode":"29620",
    "addr:street":"S Main St",
    "iso:country":"US",
    "sg:address":"306 S Main St",
    "sg:city":"Abbeville",
    "sg:classifiers":[
        {
            "category":"Utilities",
            "subcategory":"Cable",
            "type":"Services"
        }
    ],
    "sg:phone":"+1 800 955 7766",
    "sg:postcode":"29620",
    "sg:province":"SC",
    "sg:tags":[
        "communications",
        "television",
        "telephone"
    ],
    "wof:name":"Charter Cmmnctons Holdings LLC",
    "wof:placetype":"venue"
},
  "geometry": {"coordinates":[-82.37682599999999,34.175401],"type":"Point"}
}