{
  "type": "Feature",
  "properties": {
    "iso:country":"US",
    "sg:address":"10 Peachtree St",
    "sg:city":"Charleston",
    "sg:classifiers":[
        {
            "category":"Building & Trades",
            "subcategory":"Cleaning & Sanitation",
            "type":"Services"
        }
    ],
    "sg:phone":"+1 843 723 1947",
    "sg:postcode":"29403",
    "sg:province":"SC",
    "sg:tags":[
        "janitor"
    ],
    "wof:name":"Carolina Contract Cleaners Inc",
    "wof:placetype":"venue"
},
  "geometry": {"coordinates":[-79.952779,32.809734],"type":"Point"}
}