{
  "type": "Feature",
  "properties": {
    "iso:country":"US",
    "sg:address":"308 79th Ave N",
    "sg:city":"Myrtle Beach",
    "sg:classifiers":[
        {
            "category":"Manufacturing",
            "subcategory":"Paper Products",
            "type":"Manufacturing & Wholesale Goods"
        }
    ],
    "sg:phone":"+1 843 497 8600",
    "sg:postcode":"29572",
    "sg:province":"SC",
    "sg:tags":[
        "bag"
    ],
    "wof:name":"Tbl Plastics",
    "wof:placetype":"venue"
},
  "geometry": {"coordinates":[-78.81450100000001,33.747806],"type":"Point"}
}