{
  "type": "Feature",
  "properties": {
    "iso:country":"US",
    "sg:address":"4435 Bluff Rd",
    "sg:city":"Columbia",
    "sg:classifiers":[
        {
            "category":"Insurance",
            "subcategory":"Hazard Insurance",
            "type":"Services"
        }
    ],
    "sg:phone":"+1 803 695 5333",
    "sg:postcode":"29209",
    "sg:province":"SC",
    "sg:tags":[
        "bond"
    ],
    "wof:name":"247 Bail Bond",
    "wof:placetype":"venue"
},
  "geometry": {"coordinates":[-80.97253600000001,33.934475],"type":"Point"}
}