{
  "type": "Feature",
  "properties": {
    "addr:full":"2334 Two Notch Rd Columbia SC 29204",
    "addr:housenumber":"2334",
    "addr:postcode":"29204",
    "addr:street":"Two Notch Rd",
    "iso:country":"US",
    "sg:address":"2334 Two Notch Rd",
    "sg:city":"Columbia",
    "sg:classifiers":[
        {
            "category":"Retail",
            "subcategory":"Car Wash",
            "type":"Services"
        }
    ],
    "sg:phone":"+1 803 256 7039",
    "sg:postcode":"29204",
    "sg:province":"SC",
    "wof:name":"McKenney's Car Wash",
    "wof:placetype":"venue"
},
  "geometry": {"coordinates":[-81.012001,34.024502],"type":"Point"}
}