{
  "type": "Feature",
  "properties": {
    "addr:full":"70 Romney St Charleston SC 29403",
    "addr:housenumber":"70",
    "addr:postcode":"29403",
    "addr:street":"Romney St",
    "iso:country":"US",
    "sg:address":"70 Romney St",
    "sg:city":"Charleston",
    "sg:classifiers":[
        {
            "category":"Building & Trades",
            "subcategory":"Construction",
            "type":"Services"
        }
    ],
    "sg:phone":"+1 843 577 7352",
    "sg:postcode":"29403",
    "sg:province":"SC",
    "sg:tags":[
        "woodworker"
    ],
    "wof:name":"JMO Woodworks",
    "wof:placetype":"venue"
},
  "geometry": {"coordinates":[-79.946102,32.80753],"type":"Point"}
}