{
  "type": "Feature",
  "properties": {
    "addr:full":"35 W Liberty St Sumter SC 29150",
    "addr:housenumber":"35",
    "addr:postcode":"29150",
    "addr:street":"W Liberty St",
    "iso:country":"US",
    "sg:address":"35 W Liberty St",
    "sg:city":"Sumter",
    "sg:classifiers":[
        {
            "category":"Shopping",
            "subcategory":"Pharmacy",
            "type":"Retail Goods"
        }
    ],
    "sg:phone":"+1 803 773 7283",
    "sg:postcode":"29150",
    "sg:province":"SC",
    "wof:name":"Siberts Drug Store",
    "wof:placetype":"venue"
},
  "geometry": {"coordinates":[-80.343204,33.920572],"type":"Point"}
}