{
  "type": "Feature",
  "properties": {
    "iso:country":"US",
    "sg:address":"605 Cypress Gardens Rd",
    "sg:city":"Moncks Corner",
    "sg:classifiers":[
        {
            "category":"Building & Trades",
            "subcategory":"Construction",
            "type":"Services"
        }
    ],
    "sg:phone":"+1 843 761 5630",
    "sg:postcode":"29461",
    "sg:province":"SC",
    "sg:tags":[
        "clearing",
        "land",
        "leveling"
    ],
    "wof:name":"DMT Landclearing Inc",
    "wof:placetype":"venue"
},
  "geometry": {"coordinates":[-80.063013,33.087336],"type":"Point"}
}