{
  "type": "Feature",
  "properties": {
    "iso:country":"US",
    "sg:address":"9731 N Kings Hwy",
    "sg:city":"Myrtle Beach",
    "sg:classifiers":[
        {
            "category":"Sports & Exercise",
            "subcategory":"Golf",
            "type":"Entertainment"
        }
    ],
    "sg:phone":"+1 843 449 6489",
    "sg:postcode":"29572",
    "sg:province":"SC",
    "sg:tags":[
        "course"
    ],
    "sg:website":"www.mbn.com",
    "wof:name":"Waterway Hills Golf Course",
    "wof:placetype":"venue"
},
  "geometry": {"coordinates":[-78.780153,33.785693],"type":"Point"}
}