{
  "type": "Feature",
  "properties": {
    "iso:country":"US",
    "sg:address":"314 Clement Rd",
    "sg:city":"Belton",
    "sg:classifiers":[
        {
            "category":"Autos & Motor Vehicles",
            "subcategory":"Motorcycle Sales",
            "type":"Retail Goods"
        }
    ],
    "sg:phone":"+1 864 338 7860",
    "sg:postcode":"29627",
    "sg:province":"SC",
    "sg:tags":[
        "metal",
        "fabrication",
        "structural"
    ],
    "wof:name":"Pete Miner Fabrications",
    "wof:placetype":"venue"
},
  "geometry": {"coordinates":[-82.454655,34.466083],"type":"Point"}
}