{
  "type": "Feature",
  "properties": {
    "iso:country":"US",
    "sg:address":"260 Galilee Rd",
    "sg:city":"Greenwood",
    "sg:classifiers":[
        {
            "category":"Building & Trades",
            "subcategory":"Construction",
            "type":"Services"
        }
    ],
    "sg:phone":"+1 864 227 8082",
    "sg:postcode":"29646",
    "sg:province":"SC",
    "sg:tags":[
        "residential"
    ],
    "wof:name":"Harrison Lee Roy Builders",
    "wof:placetype":"venue"
},
  "geometry": {"coordinates":[-82.163687,34.101857],"type":"Point"}
}