{
  "type": "Feature",
  "properties": {
    "iso:country":"US",
    "sg:address":"332 Hobcaw Dr",
    "sg:city":"Mt Pleasant",
    "sg:classifiers":[
        {
            "category":"Building & Trades",
            "subcategory":"Construction",
            "type":"Services"
        }
    ],
    "sg:phone":"+1 843 971 0155",
    "sg:postcode":"29464",
    "sg:province":"SC",
    "sg:tags":[
        "house",
        "builder",
        "home"
    ],
    "wof:name":"Edgewater Construction Inc",
    "wof:placetype":"venue"
},
  "geometry": {"coordinates":[-79.889219,32.817374],"type":"Point"}
}