{
  "type": "Feature",
  "properties": {
    "iso:country":"US",
    "sg:address":"1000 Main St",
    "sg:city":"Hilton Head Isle",
    "sg:classifiers":[
        {
            "category":"Insurance",
            "subcategory":"Insurance Agent",
            "type":"Services"
        }
    ],
    "sg:phone":"+1 843 689 3100",
    "sg:postcode":"29926",
    "sg:province":"SC",
    "wof:name":"Golden Age Insurance",
    "wof:placetype":"venue"
},
  "geometry": {"coordinates":[-80.724525,32.214969],"type":"Point"}
}