{
  "type": "Feature",
  "properties": {
    "addr:full":"420 Mead Ave Aiken SC 29801",
    "addr:housenumber":"420",
    "addr:postcode":"29801",
    "addr:street":"Mead Ave",
    "iso:country":"US",
    "sg:address":"420 Mead Ave",
    "sg:city":"Aiken",
    "sg:classifiers":[
        {
            "category":"Restaurant",
            "type":"Food & Drink"
        }
    ],
    "sg:phone":"+1 803 641 9628",
    "sg:postcode":"29801",
    "sg:province":"SC",
    "wof:name":"Track Kitchen",
    "wof:placetype":"venue"
},
  "geometry": {"coordinates":[-81.714536,33.546471],"type":"Point"}
}