{
  "type": "Feature",
  "properties": {
    "addr:full":"107 Nebo Valley Dr Westminster SC 29693",
    "addr:housenumber":"107",
    "addr:postcode":"29693",
    "addr:street":"Nebo Valley Dr",
    "iso:country":"US",
    "sg:address":"107 Nebo Valley Dr",
    "sg:city":"Westminster",
    "sg:classifiers":[
        {
            "category":"Place Of Worship",
            "subcategory":"Church",
            "type":"Public Place"
        },
        {
            "category":"Place Of Worship",
            "type":"Public Place"
        },
        {
            "category":"Organizations",
            "subcategory":"Religious Organization",
            "type":"Services"
        }
    ],
    "sg:phone":"+1 864 647 0529",
    "sg:postcode":"29693",
    "sg:province":"SC",
    "sg:tags":[
        "god",
        "churches-church",
        "churches-pentecostal"
    ],
    "wof:name":"Madison Church Of God",
    "wof:placetype":"venue"
},
  "geometry": {"coordinates":[-83.270854,34.651855],"type":"Point"}
}