{
  "type": "Feature",
  "properties": {
    "addr:full":"16 Berryhill Rd Columbia SC 29210",
    "addr:housenumber":"16",
    "addr:postcode":"29210",
    "addr:street":"Berryhill Rd",
    "iso:country":"US",
    "sg:address":"16 Berryhill Rd",
    "sg:city":"Columbia",
    "sg:classifiers":[
        {
            "category":"Professional",
            "subcategory":"Lawyer & Legal Services",
            "type":"Services"
        }
    ],
    "sg:phone":"+1 803 996 3777",
    "sg:postcode":"29210",
    "sg:province":"SC",
    "sg:tags":[
        "attorney"
    ],
    "wof:name":"Helton Law Firm",
    "wof:placetype":"venue"
},
  "geometry": {"coordinates":[-81.117918,34.043567],"type":"Point"}
}