{
  "type": "Feature",
  "properties": {
    "addr:full":"15 N Williamsburg County Hwy Kingstree SC 29556",
    "addr:housenumber":"15",
    "addr:postcode":"29556",
    "addr:street":"N Williamsburg County Hwy",
    "iso:country":"US",
    "sg:address":"15 N Williamsburg County Hwy",
    "sg:city":"Kingstree",
    "sg:classifiers":[
        {
            "category":"Food & Beverages",
            "subcategory":"Groceries & Convenience Stores",
            "type":"Retail Goods"
        }
    ],
    "sg:phone":"+1 843 354 9494",
    "sg:postcode":"29556",
    "sg:province":"SC",
    "sg:tags":[
        "grocer"
    ],
    "wof:name":"Food Lion",
    "wof:placetype":"venue"
},
  "geometry": {"coordinates":[-79.82310200000001,33.684257],"type":"Point"}
}