{
  "type": "Feature",
  "properties": {
    "iso:country":"US",
    "sg:address":"37 Maxie Ave",
    "sg:city":"Greenville",
    "sg:classifiers":[
        {
            "category":"Shopping",
            "subcategory":"Computers & Home Electronics",
            "type":"Retail Goods"
        }
    ],
    "sg:phone":"+1 864 269 3158",
    "sg:postcode":"29611",
    "sg:province":"SC",
    "sg:tags":[
        "equipment",
        "dealer"
    ],
    "wof:name":"Carolinas Computer Inc",
    "wof:placetype":"venue"
},
  "geometry": {"coordinates":[-82.44960399999999,34.814799],"type":"Point"}
}