{
  "type": "Feature",
  "properties": {
    "addr:full":"615 Poinsett Hwy Greenville SC 29609",
    "addr:housenumber":"615",
    "addr:postcode":"29609",
    "addr:street":"Poinsett Hwy",
    "iso:country":"US",
    "sg:address":"615 Poinsett Hwy",
    "sg:city":"Greenville",
    "sg:classifiers":[
        {
            "category":"Freight",
            "type":"Transportation"
        }
    ],
    "sg:phone":"+1 864 271 0707",
    "sg:postcode":"29609",
    "sg:province":"SC",
    "sg:tags":[
        "mover"
    ],
    "wof:name":"Allied Van Lines",
    "wof:placetype":"venue"
},
  "geometry": {"coordinates":[-82.40450300000001,34.877572],"type":"Point"}
}