{
  "type": "Feature",
  "properties": {
    "iso:country":"US",
    "sg:address":"1459 Old Dunbar Rd",
    "sg:city":"West Columbia",
    "sg:classifiers":[
        {
            "category":"Wholesale",
            "subcategory":"Auto Parts",
            "type":"Manufacturing & Wholesale Goods"
        }
    ],
    "sg:phone":"+1 803 755 9400",
    "sg:postcode":"29172",
    "sg:province":"SC",
    "sg:tags":[
        "exhaust",
        "system"
    ],
    "wof:name":"Northgate Muffler Distributors",
    "wof:placetype":"venue"
},
  "geometry": {"coordinates":[-81.11872200000001,33.925279],"type":"Point"}
}