{
  "type": "Feature",
  "properties": {
    "iso:country":"US",
    "sg:address":"112 Graytown Rd",
    "sg:city":"Mc Coll",
    "sg:classifiers":[
        {
            "category":"Organizations",
            "subcategory":"Religious Organization",
            "type":"Services"
        }
    ],
    "sg:phone":"+1 843 523 7035",
    "sg:postcode":"29570",
    "sg:province":"SC",
    "sg:tags":[
        "church"
    ],
    "wof:name":"Greater Rock Outreach Church",
    "wof:placetype":"venue"
},
  "geometry": {"coordinates":[-79.53368,34.665776],"type":"Point"}
}