{
  "type": "Feature",
  "properties": {
    "addr:full":"1936 Savannah Hwy Charleston SC 29407",
    "addr:housenumber":"1936",
    "addr:postcode":"29407",
    "addr:street":"Savannah Hwy",
    "iso:country":"US",
    "sg:address":"1936 Savannah Hwy",
    "sg:city":"Charleston",
    "sg:classifiers":[
        {
            "category":"Restaurant",
            "type":"Food & Drink"
        }
    ],
    "sg:menulink":"http://www.allmenus.com/sc/charleston-north-charleston/100898-captain-ds-seafood/menu/",
    "sg:phone":"+1 843 571 2308",
    "sg:postcode":"29407",
    "sg:province":"SC",
    "sg:tags":[
        "seafood",
        "american"
    ],
    "wof:name":"Captain D's Seafood",
    "wof:placetype":"venue"
},
  "geometry": {"coordinates":[-80.025299,32.788944],"type":"Point"}
}