{
  "type": "Feature",
  "properties": {
    "iso:country":"US",
    "sg:address":"2444 Overbrook Dr",
    "sg:city":"Gaffney",
    "sg:classifiers":[
        {
            "category":"Building & Trades",
            "subcategory":"Construction",
            "type":"Services"
        }
    ],
    "sg:phone":"+1 864 489 8020",
    "sg:postcode":"29341",
    "sg:province":"SC",
    "sg:tags":[
        "masonry",
        "contractor"
    ],
    "sg:website":"www.cherokeemasonry.com",
    "wof:name":"Cherokee Masonry Inc",
    "wof:placetype":"venue"
},
  "geometry": {"coordinates":[-81.726572,35.074785],"type":"Point"}
}