{
  "type": "Feature",
  "properties": {
    "addr:full":"1260 Chapin Rd Chapin SC 29036",
    "addr:housenumber":"1260",
    "addr:postcode":"29036",
    "addr:street":"Chapin Rd",
    "iso:country":"US",
    "sg:address":"1260 Chapin Rd",
    "sg:city":"Chapin",
    "sg:classifiers":[
        {
            "category":"Restaurant",
            "type":"Food & Drink"
        }
    ],
    "sg:phone":"+1 803 345 8884",
    "sg:postcode":"29036",
    "sg:province":"SC",
    "sg:tags":[
        "caterer"
    ],
    "wof:name":"Chapin Station",
    "wof:placetype":"venue"
},
  "geometry": {"coordinates":[-81.35821,34.16774],"type":"Point"}
}