{
  "type": "Feature",
  "properties": {
    "iso:country":"US",
    "sg:address":"32 Laurens St",
    "sg:city":"Charleston",
    "sg:classifiers":[
        {
            "category":"Manufacturing",
            "subcategory":"Lumber",
            "type":"Manufacturing & Wholesale Goods"
        }
    ],
    "sg:phone":"+1 843 884 5403",
    "sg:postcode":"29401",
    "sg:province":"SC",
    "sg:tags":[
        "forester"
    ],
    "wof:name":"Swanson Forestry & Real Estate",
    "wof:placetype":"venue"
},
  "geometry": {"coordinates":[-79.928721,32.786469],"type":"Point"}
}