{
  "type": "Feature",
  "properties": {
    "iso:country":"US",
    "sg:address":"11027 Anderson Rd",
    "sg:city":"Piedmont",
    "sg:classifiers":[
        {
            "category":"Professional",
            "subcategory":"Business Services",
            "type":"Services"
        },
        {
            "category":"Professional",
            "subcategory":"Printing & Photocopies",
            "type":"Services"
        },
        {
            "category":"Government",
            "subcategory":"Post Office",
            "type":"Public Place"
        },
        {
            "category":"Retail",
            "subcategory":"Storage",
            "type":"Services"
        }
    ],
    "sg:phone":"+1 864 269 4140",
    "sg:postcode":"29673",
    "sg:province":"SC",
    "sg:tags":[
        "services-commercial",
        "household",
        "commercial",
        "duplicating",
        "shipping",
        "copying",
        "mail"
    ],
    "sg:website":"http://www.alphaprints.com",
    "wof:name":"Alpha Printing",
    "wof:placetype":"venue"
},
  "geometry": {"coordinates":[-82.48286400000001,34.787762],"type":"Point"}
}