{
  "type": "Feature",
  "properties": {
    "addr:full":"1456 Kershaw Camden Hwy Lancaster SC 29720",
    "addr:housenumber":"1456",
    "addr:postcode":"29720",
    "addr:street":"Kershaw Camden Hwy",
    "iso:country":"US",
    "sg:address":"1456 Kershaw Camden Hwy",
    "sg:city":"Lancaster",
    "sg:classifiers":[
        {
            "category":"Building & Trades",
            "subcategory":"Construction",
            "type":"Services"
        }
    ],
    "sg:phone":"+1 803 283 8436",
    "sg:postcode":"29720",
    "sg:province":"SC",
    "sg:tags":[
        "paving",
        "contractor"
    ],
    "wof:name":"Jim Lineberger Constr Inc",
    "wof:placetype":"venue"
},
  "geometry": {"coordinates":[-80.752379,34.699486],"type":"Point"}
}