{
  "type": "Feature",
  "properties": {
    "addr:full":"839 Antioch Rd Blacksburg SC 29702",
    "addr:housenumber":"839",
    "addr:postcode":"29702",
    "addr:street":"Antioch Rd",
    "iso:country":"US",
    "sg:address":"839 Antioch Rd",
    "sg:city":"Blacksburg",
    "sg:classifiers":[
        {
            "category":"Organizations",
            "subcategory":"Religious Organization",
            "type":"Services"
        }
    ],
    "sg:phone":"+1 864 936 7726",
    "sg:postcode":"29702",
    "sg:province":"SC",
    "sg:tags":[
        "church"
    ],
    "wof:name":"Antioch Baptist Church",
    "wof:placetype":"venue"
},
  "geometry": {"coordinates":[-81.43261800000001,35.150535],"type":"Point"}
}