{
  "type": "Feature",
  "properties": {
    "iso:country":"US",
    "sg:address":"2095 Henry Teckenburg Dr",
    "sg:city":"Charleston",
    "sg:classifiers":[
        {
            "category":"Social Services",
            "type":"Services"
        }
    ],
    "sg:phone":"+1 843 402 1010",
    "sg:postcode":"29414",
    "sg:province":"SC",
    "sg:tags":[
        "organization",
        "welfare"
    ],
    "wof:name":"Women's & Infants' & Child Svc",
    "wof:placetype":"venue"
},
  "geometry": {"coordinates":[-80.043543,32.810969],"type":"Point"}
}