{
  "type": "Feature",
  "properties": {
    "addr:full":"4112 Chester Hwy Mc Connells SC 29726",
    "addr:housenumber":"4112",
    "addr:postcode":"29726",
    "addr:street":"Chester Hwy Mc",
    "iso:country":"US",
    "sg:address":"4112 Chester Hwy",
    "sg:city":"Mc Connells",
    "sg:classifiers":[
        {
            "category":"Communications",
            "subcategory":"Radio Station",
            "type":"Services"
        }
    ],
    "sg:phone":"+1 803 684 4241",
    "sg:postcode":"29726",
    "sg:province":"SC",
    "sg:tags":[
        "company",
        "broadcasting"
    ],
    "wof:name":"JEFCO Communications",
    "wof:placetype":"venue"
},
  "geometry": {"coordinates":[-81.21645100000001,34.882788],"type":"Point"}
}