{
  "type": "Feature",
  "properties": {
    "addr:full":"133 W Federal St Anderson SC 29625",
    "addr:housenumber":"133",
    "addr:postcode":"29625",
    "addr:street":"W Federal St",
    "iso:country":"US",
    "sg:address":"133 W Federal St",
    "sg:city":"Anderson",
    "sg:classifiers":[
        {
            "category":"Home & Garden",
            "subcategory":"Carpets & Floor Coverings",
            "type":"Retail Goods"
        }
    ],
    "sg:phone":"+1 864 375 1222",
    "sg:postcode":"29625",
    "sg:province":"SC",
    "sg:tags":[
        "dealer",
        "rug"
    ],
    "wof:name":"USA Floor Covering",
    "wof:placetype":"venue"
},
  "geometry": {"coordinates":[-82.65233000000001,34.505686],"type":"Point"}
}