{
  "type": "Feature",
  "properties": {
    "addr:full":"107 N Guerry St Florence SC 29501",
    "addr:housenumber":"107",
    "addr:postcode":"29501",
    "addr:street":"N Guerry St",
    "iso:country":"US",
    "sg:address":"107 N Guerry St",
    "sg:city":"Florence",
    "sg:classifiers":[
        {
            "category":"Education",
            "subcategory":"Special Training",
            "type":"Public Place"
        }
    ],
    "sg:phone":"+1 843 665 1030",
    "sg:postcode":"29501",
    "sg:province":"SC",
    "sg:tags":[
        "instruction",
        "driving"
    ],
    "wof:name":"Edward's Driving School",
    "wof:placetype":"venue"
},
  "geometry": {"coordinates":[-79.77866,34.19816],"type":"Point"}
}