{
  "type": "Feature",
  "properties": {
    "iso:country":"US",
    "sg:address":"130 Fairfield St",
    "sg:city":"Winnsboro",
    "sg:classifiers":[
        {
            "category":"Restaurant",
            "type":"Food & Drink"
        }
    ],
    "sg:menulink":"http://www.allmenus.com/sc/winnsboro-south/201008-mcdonalds/menu/",
    "sg:postcode":"29180",
    "sg:province":"SC",
    "sg:tags":[
        "burger",
        "american"
    ],
    "wof:name":"McDonald's",
    "wof:placetype":"venue"
},
  "geometry": {"coordinates":[-81.088431,34.384716],"type":"Point"}
}