{
  "type": "Feature",
  "properties": {
    "iso:country":"US",
    "sg:address":"235 Epting Ave",
    "sg:city":"Greenwood",
    "sg:classifiers":[
        {
            "category":"Retail",
            "subcategory":"Auto Repair",
            "type":"Services"
        }
    ],
    "sg:phone":"+1 864 227 3111",
    "sg:postcode":"29646",
    "sg:province":"SC",
    "sg:tags":[
        "repairing",
        "automobile"
    ],
    "wof:name":"Barr's Garage",
    "wof:placetype":"venue"
},
  "geometry": {"coordinates":[-82.15276,34.174127],"type":"Point"}
}