{
  "type": "Feature",
  "properties": {
    "iso:country":"US",
    "sg:address":"481 S Herlong Ave",
    "sg:city":"Rock Hill",
    "sg:classifiers":[
        {
            "category":"Social Services",
            "subcategory":"Child Care",
            "type":"Services"
        }
    ],
    "sg:phone":"+1 803 329 0500",
    "sg:postcode":"29732",
    "sg:province":"SC",
    "wof:name":"Sunshine House",
    "wof:placetype":"venue"
},
  "geometry": {"coordinates":[-81.059142,34.953848],"type":"Point"}
}