{
  "type": "Feature",
  "properties": {
    "iso:country":"US",
    "sg:address":"4665 Schirra Ct",
    "sg:city":"Spartanburg",
    "sg:classifiers":[
        {
            "category":"Building & Trades",
            "subcategory":"Construction",
            "type":"Services"
        }
    ],
    "sg:phone":"+1 864 574 0811",
    "sg:postcode":"29301",
    "sg:province":"SC",
    "sg:tags":[
        "house"
    ],
    "wof:name":"Lindseys Remodeling",
    "wof:placetype":"venue"
},
  "geometry": {"coordinates":[-81.996097,34.909516],"type":"Point"}
}