{
  "type": "Feature",
  "properties": {
    "iso:country":"US",
    "sg:address":"6804 N Ocean Blvd",
    "sg:city":"Myrtle Beach",
    "sg:classifiers":[
        {
            "category":"Travel",
            "subcategory":"Hotels & Motels",
            "type":"Entertainment"
        }
    ],
    "sg:phone":"+1 843 449 4833",
    "sg:postcode":"29572",
    "sg:province":"SC",
    "sg:tags":[
        "resort"
    ],
    "wof:name":"Monterey Bay Suites",
    "wof:placetype":"venue"
},
  "geometry": {"coordinates":[-78.821784,33.73879],"type":"Point"}
}