{
  "type": "Feature",
  "properties": {
    "addr:full":"412 Veterans Rd Columbia SC 29209",
    "addr:housenumber":"412",
    "addr:postcode":"29209",
    "addr:street":"Veterans Rd",
    "iso:country":"US",
    "sg:address":"412 Veterans Rd",
    "sg:city":"Columbia",
    "sg:classifiers":[
        {
            "category":"Professional",
            "subcategory":"Computer Services",
            "type":"Services"
        }
    ],
    "sg:phone":"+1 803 783 4444",
    "sg:postcode":"29209",
    "sg:province":"SC",
    "sg:tags":[
        "repair"
    ],
    "sg:website":"www.csssc.com",
    "wof:name":"C S & S Leasing Inc",
    "wof:placetype":"venue"
},
  "geometry": {"coordinates":[-80.959069,33.969368],"type":"Point"}
}