{
  "type": "Feature",
  "properties": {
    "iso:country":"US",
    "sg:address":"401 Dozier St",
    "sg:city":"Georgetown",
    "sg:classifiers":[
        {
            "category":"Insurance",
            "subcategory":"Insurance Agent",
            "type":"Services"
        }
    ],
    "sg:phone":"+1 843 527 1131",
    "sg:postcode":"29440",
    "sg:province":"SC",
    "wof:name":"Farm Bureau Insurance",
    "wof:placetype":"venue"
},
  "geometry": {"coordinates":[-79.28521000000001,33.37514],"type":"Point"}
}