{
  "type": "Feature",
  "properties": {
    "addr:full":"704 E McBee Ave Greenville SC 29601",
    "addr:housenumber":"704",
    "addr:postcode":"29601",
    "addr:street":"E Mcbee Ave",
    "iso:country":"US",
    "sg:address":"704 E McBee Ave",
    "sg:city":"Greenville",
    "sg:classifiers":[
        {
            "category":"Professional",
            "subcategory":"Lawyer & Legal Services",
            "type":"Services"
        }
    ],
    "sg:phone":"+1 864 242 4899",
    "sg:postcode":"29601",
    "sg:province":"SC",
    "sg:tags":[
        "attorney"
    ],
    "wof:name":"Kenison & Dudley",
    "wof:placetype":"venue"
},
  "geometry": {"coordinates":[-82.390477,34.847566],"type":"Point"}
}