{
  "type": "Feature",
  "properties": {
    "addr:full":"358 Augusta Rd North Augusta SC 29822",
    "addr:housenumber":"358",
    "addr:postcode":"29822",
    "addr:street":"Augusta Rd",
    "iso:country":"US",
    "sg:address":"358 Augusta Rd",
    "sg:city":"North Augusta",
    "sg:classifiers":[
        {
            "category":"Restaurant",
            "type":"Food & Drink"
        }
    ],
    "sg:phone":"+1 803 279 5664",
    "sg:postcode":"29822",
    "sg:province":"SC",
    "sg:website":"www.wingstop.com",
    "wof:name":"Wingstop",
    "wof:placetype":"venue"
},
  "geometry": {"coordinates":[-81.892143,33.496827],"type":"Point"}
}