{
  "type": "Feature",
  "properties": {
    "iso:country":"US",
    "sg:address":"1297 Professional Dr",
    "sg:city":"Myrtle Beach",
    "sg:classifiers":[
        {
            "category":"Health Services",
            "subcategory":"Clinic",
            "type":"Services"
        }
    ],
    "sg:phone":"+1 843 839 1536",
    "sg:postcode":"29577",
    "sg:province":"SC",
    "wof:name":"Natural Health Counseling",
    "wof:placetype":"venue"
},
  "geometry": {"coordinates":[-78.858771,33.731944],"type":"Point"}
}