{
  "type": "Feature",
  "properties": {
    "addr:full":"2971 Syrup Mill Rd Ridgeway SC 29130",
    "addr:housenumber":"2971",
    "addr:postcode":"29130",
    "addr:street":"Syrup Mill Rd",
    "iso:country":"US",
    "sg:address":"2971 Syrup Mill Rd",
    "sg:city":"Ridgeway",
    "sg:classifiers":[
        {
            "category":"Building & Trades",
            "subcategory":"Construction",
            "type":"Services"
        }
    ],
    "sg:phone":"+1 803 926 2433",
    "sg:postcode":"29130",
    "sg:province":"SC",
    "wof:name":"James Able & Son",
    "wof:placetype":"venue"
},
  "geometry": {"coordinates":[-81.040937,34.274722],"type":"Point"}
}