{
  "type": "Feature",
  "properties": {
    "addr:full":"806 US Hwy 501 E Conway SC 29526",
    "addr:housenumber":"806",
    "addr:postcode":"29526",
    "addr:street":"Us Hwy 501 E",
    "iso:country":"US",
    "sg:address":"806 US Hwy 501 E",
    "sg:city":"Conway",
    "sg:classifiers":[
        {
            "category":"Travel",
            "subcategory":"Hotels & Motels",
            "type":"Entertainment"
        }
    ],
    "sg:phone":"+1 843 234 1145",
    "sg:postcode":"29526",
    "sg:province":"SC",
    "sg:tags":[
        "resort"
    ],
    "wof:name":"Plantation Resort Properties",
    "wof:placetype":"venue"
},
  "geometry": {"coordinates":[-79.035355,33.813978],"type":"Point"}
}