{
  "type": "Feature",
  "properties": {
    "iso:country":"US",
    "sg:address":"1114 12th St",
    "sg:city":"Port Royal",
    "sg:classifiers":[
        {
            "category":"Building & Trades",
            "subcategory":"Construction",
            "type":"Services"
        }
    ],
    "sg:phone":"+1 843 525 0357",
    "sg:postcode":"29935",
    "sg:province":"SC",
    "sg:tags":[
        "roofing",
        "contractor"
    ],
    "wof:name":"Roof Doctor",
    "wof:placetype":"venue"
},
  "geometry": {"coordinates":[-80.696147,32.377526],"type":"Point"}
}