{
  "type": "Feature",
  "properties": {
    "iso:country":"US",
    "sg:address":"102 Brewster Way",
    "sg:city":"Aiken",
    "sg:classifiers":[
        {
            "category":"Building & Trades",
            "subcategory":"Construction",
            "type":"Services"
        }
    ],
    "sg:phone":"+1 803 648 5823",
    "sg:postcode":"29803",
    "sg:province":"SC",
    "sg:tags":[
        "contractor"
    ],
    "wof:name":"Minichella Construction",
    "wof:placetype":"venue"
},
  "geometry": {"coordinates":[-81.676855,33.471221],"type":"Point"}
}