{
  "type": "Feature",
  "properties": {
    "iso:country":"US",
    "sg:address":"1605 Madison Dr",
    "sg:city":"North Myrtle Bch",
    "sg:classifiers":[
        {
            "category":"Real Estate",
            "subcategory":"Real Estate Agent",
            "type":"Services"
        }
    ],
    "sg:phone":"+1 843 272 6115",
    "sg:postcode":"29582",
    "sg:province":"SC",
    "sg:website":"www.white-realty.com",
    "wof:name":"White Realty Co",
    "wof:placetype":"venue"
},
  "geometry": {"coordinates":[-78.701009,33.812574],"type":"Point"}
}