{
  "type": "Feature",
  "properties": {
    "iso:country":"US",
    "sg:address":"4000 Ashley Phosphate Rd",
    "sg:city":"Charleston",
    "sg:classifiers":[
        {
            "category":"Professional",
            "subcategory":"Lawyer & Legal Services",
            "type":"Services"
        }
    ],
    "sg:phone":"+1 843 552 3969",
    "sg:postcode":"29418",
    "sg:province":"SC",
    "sg:tags":[
        "attorney"
    ],
    "wof:name":"Maree Law Firm",
    "wof:placetype":"venue"
},
  "geometry": {"coordinates":[-80.087839,32.924144],"type":"Point"}
}