{
  "type": "Feature",
  "properties": {
    "addr:full":"245 Bridle Ridge Rd Lexington SC 29073",
    "addr:housenumber":"245",
    "addr:postcode":"29073",
    "addr:street":"Bridle Ridge Rd",
    "iso:country":"US",
    "sg:address":"245 Bridle Ridge Rd",
    "sg:city":"Lexington",
    "sg:classifiers":[
        {
            "category":"Building & Trades",
            "subcategory":"Construction",
            "type":"Services"
        }
    ],
    "sg:phone":"+1 803 356 5014",
    "sg:postcode":"29073",
    "sg:province":"SC",
    "sg:tags":[
        "hanging",
        "contractor"
    ],
    "wof:name":"Keith A Clayton",
    "wof:placetype":"venue"
},
  "geometry": {"coordinates":[-81.253969,33.888698],"type":"Point"}
}