{
  "type": "Feature",
  "properties": {
    "iso:country":"US",
    "sg:address":"82 Dungannon Hall",
    "sg:city":"Johns Island",
    "sg:classifiers":[
        {
            "category":"Wholesale",
            "subcategory":"Hardware",
            "type":"Manufacturing & Wholesale Goods"
        }
    ],
    "sg:phone":"+1 843 768 0048",
    "sg:postcode":"29455",
    "sg:province":"SC",
    "wof:name":"Clean Air of Carolina",
    "wof:placetype":"venue"
},
  "geometry": {"coordinates":[-80.076514,32.61505],"type":"Point"}
}