{
  "type": "Feature",
  "properties": {
    "iso:country":"US",
    "sg:address":"125 Amber Ln",
    "sg:city":"Conway",
    "sg:classifiers":[
        {
            "category":"Building & Trades",
            "subcategory":"Equipment Rental",
            "type":"Services"
        }
    ],
    "sg:phone":"+1 843 347 9044",
    "sg:postcode":"29526",
    "sg:province":"SC",
    "sg:tags":[
        "contractor"
    ],
    "wof:name":"United Rentals Aerial Equip",
    "wof:placetype":"venue"
},
  "geometry": {"coordinates":[-79.02868599999999,33.810991],"type":"Point"}
}