{
  "type": "Feature",
  "properties": {
    "iso:country":"US",
    "sg:address":"2130 N Boland Cir",
    "sg:city":"Charleston",
    "sg:classifiers":[
        {
            "category":"Airport",
            "type":"Transportation"
        }
    ],
    "sg:phone":"+1 843 871 3714",
    "sg:postcode":"29406",
    "sg:province":"SC",
    "sg:tags":[
        "aviation",
        "cleaning"
    ],
    "wof:name":"Maccs",
    "wof:placetype":"venue"
},
  "geometry": {"coordinates":[-80.017561,32.897793],"type":"Point"}
}