{
  "type": "Feature",
  "properties": {
    "iso:country":"US",
    "sg:address":"4683 Alma Rd",
    "sg:city":"Nichols",
    "sg:classifiers":[
        {
            "category":"Organizations",
            "subcategory":"Religious Organization",
            "type":"Services"
        }
    ],
    "sg:phone":"+1 843 392 1496",
    "sg:postcode":"29581",
    "sg:province":"SC",
    "sg:tags":[
        "church"
    ],
    "wof:name":"Piney Grove Missionary Baptist",
    "wof:placetype":"venue"
},
  "geometry": {"coordinates":[-79.023573,34.210135],"type":"Point"}
}