{
  "type": "Feature",
  "properties": {
    "iso:country":"US",
    "sg:address":"123 Nims Spring Dr",
    "sg:city":"Fort Mill",
    "sg:classifiers":[
        {
            "category":"Manufacturing",
            "subcategory":"Printing",
            "type":"Manufacturing & Wholesale Goods"
        }
    ],
    "sg:phone":"+1 803 547 1336",
    "sg:postcode":"29715",
    "sg:province":"SC",
    "sg:tags":[
        "mfg"
    ],
    "wof:name":"John H Harland Company",
    "wof:placetype":"venue"
},
  "geometry": {"coordinates":[-80.928973,34.990255],"type":"Point"}
}