{
  "type": "Feature",
  "properties": {
    "iso:country":"US",
    "sg:address":"17 US Hwy 17 Bus",
    "sg:city":"Surfside Beach",
    "sg:classifiers":[
        {
            "category":"Real Estate",
            "subcategory":"Real Estate Agent",
            "type":"Services"
        }
    ],
    "sg:phone":"+1 843 238 5464",
    "sg:postcode":"29575",
    "sg:province":"SC",
    "wof:name":"Harrison Realty Co",
    "wof:placetype":"venue"
},
  "geometry": {"coordinates":[-78.981816,33.611877],"type":"Point"}
}