{
  "type": "Feature",
  "properties": {
    "addr:full":"1400 Boiling Springs Rd Spartanburg SC 29303",
    "addr:housenumber":"1400",
    "addr:postcode":"29303",
    "addr:street":"Boiling Springs Rd",
    "iso:country":"US",
    "sg:address":"1400 Boiling Springs Rd",
    "sg:city":"Spartanburg",
    "sg:classifiers":[
        {
            "category":"Personal",
            "subcategory":"Beauty Salon",
            "type":"Services"
        }
    ],
    "sg:phone":"+1 864 599 0625",
    "sg:postcode":"29303",
    "sg:province":"SC",
    "wof:name":"Woodcreek Salon",
    "wof:placetype":"venue"
},
  "geometry": {"coordinates":[-81.94871500000001,35.000912],"type":"Point"}
}