{
  "type": "Feature",
  "properties": {
    "addr:full":"1 Mauney Ct Columbia SC 29201",
    "addr:housenumber":"1",
    "addr:postcode":"29201",
    "addr:street":"Mauney Ct",
    "iso:country":"US",
    "sg:address":"1 Mauney Ct",
    "sg:city":"Columbia",
    "sg:classifiers":[
        {
            "category":"Home & Garden",
            "subcategory":"Carpets & Floor Coverings",
            "type":"Retail Goods"
        }
    ],
    "sg:phone":"+1 803 765 9210",
    "sg:postcode":"29201",
    "sg:province":"SC",
    "wof:name":"E F Commercial Assoc",
    "wof:placetype":"venue"
},
  "geometry": {"coordinates":[-80.987422,33.960772],"type":"Point"}
}