{
  "type": "Feature",
  "properties": {
    "addr:full":"1904 Academy St Columbia SC 29203",
    "addr:housenumber":"1904",
    "addr:postcode":"29203",
    "addr:street":"Academy St",
    "iso:country":"US",
    "sg:address":"1904 Academy St",
    "sg:city":"Columbia",
    "sg:classifiers":[
        {
            "category":"Professional",
            "subcategory":"Management & Consulting",
            "type":"Services"
        }
    ],
    "sg:phone":"+1 803 400 1178",
    "sg:postcode":"29203",
    "sg:province":"SC",
    "sg:tags":[
        "consultant"
    ],
    "wof:name":"Comunicar Language & Consltng",
    "wof:placetype":"venue"
},
  "geometry": {"coordinates":[-81.030109,34.029766],"type":"Point"}
}