{
  "type": "Feature",
  "properties": {
    "iso:country":"US",
    "sg:address":"2 Echelon Rd",
    "sg:city":"Greenville",
    "sg:classifiers":[
        {
            "category":"Building & Trades",
            "subcategory":"Construction",
            "type":"Services"
        }
    ],
    "sg:phone":"+1 864 277 1422",
    "sg:postcode":"29605",
    "sg:province":"SC",
    "sg:tags":[
        "project"
    ],
    "wof:name":"Yeargin Potter Shackelford",
    "wof:placetype":"venue"
},
  "geometry": {"coordinates":[-82.382898,34.738682],"type":"Point"}
}