{
  "type": "Feature",
  "properties": {
    "iso:country":"US",
    "sg:address":"212 Knotty Pine Rd",
    "sg:city":"Darlington",
    "sg:classifiers":[
        {
            "category":"Government",
            "subcategory":"Office",
            "type":"Public Place"
        }
    ],
    "sg:phone":"+1 843 393 3041",
    "sg:postcode":"29532",
    "sg:province":"SC",
    "sg:tags":[
        "state",
        "program"
    ],
    "wof:name":"Education Dept",
    "wof:placetype":"venue"
},
  "geometry": {"coordinates":[-79.955512,34.294347],"type":"Point"}
}