{
  "type": "Feature",
  "properties": {
    "iso:country":"US",
    "sg:address":"108 N Maple St",
    "sg:city":"Pageland",
    "sg:classifiers":[
        {
            "category":"Utilities",
            "subcategory":"Cable",
            "type":"Services"
        }
    ],
    "sg:phone":"+1 843 672 5929",
    "sg:postcode":"29728",
    "sg:province":"SC",
    "sg:tags":[
        "television"
    ],
    "wof:name":"Falcon Cable TV",
    "wof:placetype":"venue"
},
  "geometry": {"coordinates":[-80.393067,34.772937],"type":"Point"}
}