{
  "type": "Feature",
  "properties": {
    "iso:country":"US",
    "sg:address":"9544 Commonwealth Blvd",
    "sg:city":"Columbia",
    "sg:classifiers":[
        {
            "category":"Airport",
            "type":"Transportation"
        }
    ],
    "sg:phone":"+1 803 348 0984",
    "sg:postcode":"29209",
    "sg:province":"SC",
    "sg:tags":[
        "support",
        "airline"
    ],
    "wof:name":"Gourmet Catering 33",
    "wof:placetype":"venue"
},
  "geometry": {"coordinates":[-80.902111,33.958647],"type":"Point"}
}