{
  "type": "Feature",
  "properties": {
    "iso:country":"US",
    "sg:address":"1029 Porter Rd",
    "sg:city":"Pendleton",
    "sg:classifiers":[
        {
            "category":"Building & Trades",
            "subcategory":"Landscaping Services",
            "type":"Services"
        }
    ],
    "sg:phone":"+1 864 646 7270",
    "sg:postcode":"29670",
    "sg:province":"SC",
    "wof:name":"Tommy Riggins",
    "wof:placetype":"venue"
},
  "geometry": {"coordinates":[-82.76024,34.671178],"type":"Point"}
}