{
  "type": "Feature",
  "properties": {
    "iso:country":"US",
    "sg:address":"1373 Ebenezer Rd",
    "sg:city":"Rock Hill",
    "sg:classifiers":[
        {
            "category":"Professional",
            "subcategory":"Lawyer & Legal Services",
            "type":"Services"
        }
    ],
    "sg:phone":"+1 803 980 2765",
    "sg:postcode":"29732",
    "sg:province":"SC",
    "sg:tags":[
        "attorney"
    ],
    "wof:name":"Lisa F Jarvis Law Office",
    "wof:placetype":"venue"
},
  "geometry": {"coordinates":[-81.039923,34.947704],"type":"Point"}
}