{
  "type": "Feature",
  "properties": {
    "iso:country":"US",
    "sg:address":"504 N Duncan Byp",
    "sg:city":"Union",
    "sg:classifiers":[
        {
            "category":"Restaurant",
            "type":"Food & Drink"
        }
    ],
    "sg:phone":"+1 864 429 3322",
    "sg:postcode":"29379",
    "sg:province":"SC",
    "wof:name":"Yellow Jacket Buffet",
    "wof:placetype":"venue"
},
  "geometry": {"coordinates":[-81.638845,34.725533],"type":"Point"}
}