{
  "type": "Feature",
  "properties": {
    "addr:full":"5616 State Hwy 185 Hodges SC 29653",
    "addr:housenumber":"5616",
    "addr:postcode":"29653",
    "addr:street":"State Hwy 185",
    "iso:country":"US",
    "sg:address":"5616 State Hwy 185",
    "sg:city":"Hodges",
    "sg:classifiers":[
        {
            "category":"Wholesale",
            "subcategory":"Machinery & Supplies",
            "type":"Manufacturing & Wholesale Goods"
        }
    ],
    "sg:phone":"+1 864 374 3555",
    "sg:postcode":"29653",
    "sg:province":"SC",
    "sg:tags":[
        "equipment",
        "industrial"
    ],
    "sg:website":"www.pumphouse.com",
    "wof:name":"Pump House",
    "wof:placetype":"venue"
},
  "geometry": {"coordinates":[-82.28054299999999,34.282641],"type":"Point"}
}