{
  "type": "Feature",
  "properties": {
    "iso:country":"US",
    "sg:address":"240 Wade Hampton Blvd",
    "sg:city":"Greenville",
    "sg:classifiers":[
        {
            "category":"Restaurant",
            "type":"Food & Drink"
        }
    ],
    "sg:phone":"+1 864 232 7774",
    "sg:postcode":"29609",
    "sg:province":"SC",
    "sg:tags":[
        "eating"
    ],
    "wof:name":"Henry's Smokehouse",
    "wof:placetype":"venue"
},
  "geometry": {"coordinates":[-82.38257,34.864281],"type":"Point"}
}