{
  "type": "Feature",
  "properties": {
    "iso:country":"US",
    "sg:address":"417 Kay Dr",
    "sg:city":"Easley",
    "sg:classifiers":[
        {
            "category":"Home & Garden",
            "subcategory":"Carpets & Floor Coverings",
            "type":"Retail Goods"
        }
    ],
    "sg:phone":"+1 864 855 6636",
    "sg:postcode":"29640",
    "sg:province":"SC",
    "sg:tags":[
        "laying",
        "contractor"
    ],
    "wof:name":"G & S Carpet",
    "wof:placetype":"venue"
},
  "geometry": {"coordinates":[-82.52786999999999,34.836206],"type":"Point"}
}