{
  "type": "Feature",
  "properties": {
    "iso:country":"US",
    "sg:address":"951 Shine Ave",
    "sg:city":"Myrtle Beach",
    "sg:classifiers":[
        {
            "category":"Organizations",
            "subcategory":"Non-profit Organization",
            "type":"Services"
        },
        {
            "category":"Real Estate",
            "subcategory":"Real Estate Agent",
            "type":"Services"
        }
    ],
    "sg:phone":"+1 843 626 3638",
    "sg:postcode":"29577",
    "sg:province":"SC",
    "sg:tags":[
        "assn",
        "business"
    ],
    "wof:name":"Coastal Carolinas Assn Realtor",
    "wof:placetype":"venue"
},
  "geometry": {"coordinates":[-78.935819,33.66718],"type":"Point"}
}