{
  "type": "Feature",
  "properties": {
    "iso:country":"US",
    "sg:address":"406 Trestle Rd",
    "sg:city":"Greenwood",
    "sg:classifiers":[
        {
            "category":"Real Estate",
            "subcategory":"Real Estate Agent",
            "type":"Services"
        }
    ],
    "sg:phone":"+1 864 229 7042",
    "sg:postcode":"29649",
    "sg:province":"SC",
    "wof:name":"All In One Realty Services LLC",
    "wof:placetype":"venue"
},
  "geometry": {"coordinates":[-82.074066,34.283652],"type":"Point"}
}