{
  "type": "Feature",
  "properties": {
    "iso:country":"US",
    "sg:address":"1106 N Anderson Rd",
    "sg:city":"Rock Hill",
    "sg:classifiers":[
        {
            "category":"Restaurant",
            "type":"Food & Drink"
        }
    ],
    "sg:phone":"+1 803 327 7222",
    "sg:postcode":"29730",
    "sg:province":"SC",
    "wof:name":"Tommy's Stage Right Food",
    "wof:placetype":"venue"
},
  "geometry": {"coordinates":[-80.992621,34.968458],"type":"Point"}
}