{
  "type": "Feature",
  "properties": {
    "iso:country":"US",
    "sg:address":"1881 Shivers Rd",
    "sg:city":"Columbia",
    "sg:classifiers":[
        {
            "category":"Education",
            "subcategory":"School",
            "type":"Public Place"
        }
    ],
    "sg:phone":"+1 803 896 9523",
    "sg:postcode":"29212",
    "sg:province":"SC",
    "wof:name":"New Directions School",
    "wof:placetype":"venue"
},
  "geometry": {"coordinates":[-81.106331,34.054421],"type":"Point"}
}