{
  "type": "Feature",
  "properties": {
    "iso:country":"US",
    "sg:address":"1022 Hickory Hill Rd",
    "sg:city":"Eastover",
    "sg:classifiers":[
        {
            "category":"Food & Beverages",
            "subcategory":"Groceries & Convenience Stores",
            "type":"Retail Goods"
        }
    ],
    "sg:phone":"+1 803 353 9697",
    "sg:postcode":"29044",
    "sg:province":"SC",
    "wof:name":"Hickory Hill Convienince Store",
    "wof:placetype":"venue"
},
  "geometry": {"coordinates":[-80.68134,33.873555],"type":"Point"}
}