{
  "type": "Feature",
  "properties": {
    "iso:country":"US",
    "sg:address":"2941 W Montague Ave",
    "sg:city":"North Charleston",
    "sg:classifiers":[
        {
            "category":"Food & Beverages",
            "subcategory":"Groceries & Convenience Stores",
            "type":"Retail Goods"
        }
    ],
    "sg:phone":"+1 843 554 3500",
    "sg:postcode":"29418",
    "sg:province":"SC",
    "wof:name":"Exxon",
    "wof:placetype":"venue"
},
  "geometry": {"coordinates":[-80.01259,32.868595],"type":"Point"}
}