{
  "type": "Feature",
  "properties": {
    "iso:country":"US",
    "sg:address":"1142 Walter Price Rd",
    "sg:city":"Cayce",
    "sg:classifiers":[
        {
            "category":"Organizations",
            "subcategory":"Religious Organization",
            "type":"Services"
        }
    ],
    "sg:phone":"+1 803 739 6654",
    "sg:postcode":"29033",
    "sg:province":"SC",
    "sg:tags":[
        "church"
    ],
    "wof:name":"Revealed Word Ministries",
    "wof:placetype":"venue"
},
  "geometry": {"coordinates":[-81.063034,33.971117],"type":"Point"}
}