{
  "type": "Feature",
  "properties": {
    "iso:country":"US",
    "sg:address":"1839 Springs Club Rd",
    "sg:city":"Lancaster",
    "sg:classifiers":[
        {
            "category":"Recreation",
            "type":"Entertainment"
        }
    ],
    "sg:phone":"+1 803 283 8330",
    "sg:postcode":"29720",
    "sg:province":"SC",
    "sg:tags":[
        "center"
    ],
    "wof:name":"Leroy Springs & Co",
    "wof:placetype":"venue"
},
  "geometry": {"coordinates":[-80.784194,34.685275],"type":"Point"}
}