{
  "type": "Feature",
  "properties": {
    "addr:full":"336 Harmon Rd Hopkins SC 29061",
    "addr:housenumber":"336",
    "addr:postcode":"29061",
    "addr:street":"Harmon Rd",
    "iso:country":"US",
    "sg:address":"336 Harmon Rd",
    "sg:city":"Hopkins",
    "sg:phone":"+1 803 776 8477",
    "sg:postcode":"29061",
    "sg:province":"SC",
    "sg:tags":[
        "irrigation",
        "system"
    ],
    "wof:name":"Rainmaker",
    "wof:placetype":"venue"
},
  "geometry": {"coordinates":[-80.803591,33.984487],"type":"Point"}
}