{
  "type": "Feature",
  "properties": {
    "addr:full":"30 Old Mill Rd Greenville SC 29607",
    "addr:housenumber":"30",
    "addr:postcode":"29607",
    "addr:street":"Old Mill Rd",
    "iso:country":"US",
    "sg:address":"30 Old Mill Rd",
    "sg:city":"Greenville",
    "sg:classifiers":[
        {
            "category":"Transit Center",
            "subcategory":"Freight",
            "type":"Transportation"
        }
    ],
    "sg:phone":"+1 864 297 7500",
    "sg:postcode":"29607",
    "sg:province":"SC",
    "sg:tags":[
        "forwarding"
    ],
    "wof:name":"Cross Country Shipper Association Inc",
    "wof:placetype":"venue"
},
  "geometry": {"coordinates":[-82.312027,34.79731],"type":"Point"}
}