{
  "type": "Feature",
  "properties": {
    "iso:country":"US",
    "sg:address":"2 Harbison Way",
    "sg:city":"Columbia",
    "sg:classifiers":[
        {
            "category":"Banks & Credit Unions",
            "subcategory":"Bank",
            "type":"Services"
        }
    ],
    "sg:phone":"+1 803 732 3153",
    "sg:postcode":"29212",
    "sg:province":"SC",
    "sg:tags":[
        "broker",
        "mortgage"
    ],
    "wof:name":"Capital City Mortgage Group",
    "wof:placetype":"venue"
},
  "geometry": {"coordinates":[-81.14622300000001,34.073275],"type":"Point"}
}