{
  "type": "Feature",
  "properties": {
    "addr:full":"490 State Hwy 121 Johnston SC 29832",
    "addr:housenumber":"490",
    "addr:postcode":"29832",
    "addr:street":"State Hwy 121",
    "iso:country":"US",
    "sg:address":"490 State Hwy 121",
    "sg:city":"Johnston",
    "sg:classifiers":[
        {
            "category":"Wholesale",
            "subcategory":"Scrap",
            "type":"Manufacturing & Wholesale Goods"
        }
    ],
    "sg:phone":"+1 803 275 5111",
    "sg:postcode":"29832",
    "sg:province":"SC",
    "sg:tags":[
        "recycling",
        "center"
    ],
    "wof:name":"Ridge Recyclers",
    "wof:placetype":"venue"
},
  "geometry": {"coordinates":[-81.832325,33.785805],"type":"Point"}
}