{
  "type": "Feature",
  "properties": {
    "iso:country":"US",
    "sg:address":"136 W Richardson Ave",
    "sg:city":"Summerville",
    "sg:classifiers":[
        {
            "category":"Professional",
            "subcategory":"Lawyer & Legal Services",
            "type":"Services"
        }
    ],
    "sg:phone":"+1 843 871 1000",
    "sg:postcode":"29483",
    "sg:province":"SC",
    "sg:tags":[
        "attorney"
    ],
    "wof:name":"Goodstein Law Firm",
    "wof:placetype":"venue"
},
  "geometry": {"coordinates":[-80.176698,33.019431],"type":"Point"}
}