{
  "type": "Feature",
  "properties": {
    "iso:country":"US",
    "sg:address":"2900 Taylor Rd",
    "sg:city":"Cayce",
    "sg:classifiers":[
        {
            "category":"Building & Trades",
            "subcategory":"Construction",
            "type":"Services"
        }
    ],
    "sg:phone":"+1 803 794 5200",
    "sg:postcode":"29033",
    "sg:province":"SC",
    "sg:tags":[
        "general",
        "contractor"
    ],
    "wof:name":"Sturkie Co",
    "wof:placetype":"venue"
},
  "geometry": {"coordinates":[-81.05246,33.954675],"type":"Point"}
}