{
  "type": "Feature",
  "properties": {
    "iso:country":"US",
    "sg:address":"1118 Boundary St",
    "sg:city":"Conway",
    "sg:classifiers":[
        {
            "category":"Real Estate",
            "subcategory":"Real Estate Operator",
            "type":"Services"
        }
    ],
    "sg:phone":"+1 843 248 4242",
    "sg:postcode":"29526",
    "sg:province":"SC",
    "sg:tags":[
        "apartment"
    ],
    "wof:name":"Moss Grove Apartments",
    "wof:placetype":"venue"
},
  "geometry": {"coordinates":[-79.061757,33.861385],"type":"Point"}
}