{
  "type": "Feature",
  "properties": {
    "addr:full":"563 US Hwy 52 Cheraw SC 29520",
    "addr:housenumber":"563",
    "addr:postcode":"29520",
    "addr:street":"Us Hwy 52",
    "iso:country":"US",
    "sg:address":"563 US Hwy 52",
    "sg:city":"Cheraw",
    "sg:classifiers":[
        {
            "category":"Insurance",
            "subcategory":"Insurance Agent",
            "type":"Services"
        }
    ],
    "sg:phone":"+1 843 537 3323",
    "sg:postcode":"29520",
    "sg:province":"SC",
    "wof:name":"Cheraw Insurance & Real Estate",
    "wof:placetype":"venue"
},
  "geometry": {"coordinates":[-79.889146,34.705198],"type":"Point"}
}