{
  "type": "Feature",
  "properties": {
    "iso:country":"US",
    "sg:address":"3501 Farrow Rd",
    "sg:city":"Columbia",
    "sg:classifiers":[
        {
            "category":"Shopping",
            "subcategory":"Clothing, Apparel, & Fashions",
            "type":"Retail Goods"
        }
    ],
    "sg:phone":"+1 803 252 1406",
    "sg:postcode":"29203",
    "sg:province":"SC",
    "sg:tags":[
        "lingerie"
    ],
    "wof:name":"Tobie's Sunshine Sales Co",
    "wof:placetype":"venue"
},
  "geometry": {"coordinates":[-81.02359800000001,34.033699],"type":"Point"}
}