{
  "type": "Feature",
  "properties": {
    "iso:country":"US",
    "sg:address":"4833 Calhoun Memorial Hwy",
    "sg:city":"Easley",
    "sg:classifiers":[
        {
            "category":"Home & Garden",
            "subcategory":"Mobile Homes",
            "type":"Retail Goods"
        }
    ],
    "sg:phone":"+1 864 855 8817",
    "sg:postcode":"29640",
    "sg:province":"SC",
    "wof:name":"South Star Homes",
    "wof:placetype":"venue"
},
  "geometry": {"coordinates":[-82.540758,34.826993],"type":"Point"}
}