{
  "type": "Feature",
  "properties": {
    "addr:full":"776 W Liberty St Sumter SC 29150",
    "addr:housenumber":"776",
    "addr:postcode":"29150",
    "addr:street":"W Liberty St",
    "iso:country":"US",
    "sg:address":"776 W Liberty St",
    "sg:city":"Sumter",
    "sg:classifiers":[
        {
            "category":"Banks & Credit Unions",
            "subcategory":"Investment Brokerage",
            "type":"Services"
        }
    ],
    "sg:phone":"+1 803 773 8373",
    "sg:postcode":"29150",
    "sg:province":"SC",
    "sg:tags":[
        "security"
    ],
    "wof:name":"Edward Jones Investments",
    "wof:placetype":"venue"
},
  "geometry": {"coordinates":[-80.36712,33.919389],"type":"Point"}
}