{
  "type": "Feature",
  "properties": {
    "iso:country":"US",
    "sg:address":"2113 Park St",
    "sg:city":"Columbia",
    "sg:classifiers":[
        {
            "category":"Professional",
            "subcategory":"Lawyer & Legal Services",
            "type":"Services"
        }
    ],
    "sg:phone":"+1 803 407 2209",
    "sg:postcode":"29201",
    "sg:province":"SC",
    "sg:tags":[
        "attorney"
    ],
    "wof:name":"Rutherford Law Firm",
    "wof:placetype":"venue"
},
  "geometry": {"coordinates":[-81.043363,34.013446],"type":"Point"}
}