{
  "type": "Feature",
  "properties": {
    "iso:country":"US",
    "sg:address":"403 E Washington St",
    "sg:city":"Walterboro",
    "sg:classifiers":[
        {
            "category":"Professional",
            "subcategory":"Business Services",
            "type":"Services"
        }
    ],
    "sg:phone":"+1 843 542 9700",
    "sg:postcode":"29488",
    "sg:province":"SC",
    "sg:tags":[
        "appraiser"
    ],
    "wof:name":"Dreamvestments LLC",
    "wof:placetype":"venue"
},
  "geometry": {"coordinates":[-80.66162,32.903466],"type":"Point"}
}