{
  "type": "Feature",
  "properties": {
    "addr:full":"481 Garlington Rd Greenville SC 29615",
    "addr:housenumber":"481",
    "addr:postcode":"29615",
    "addr:street":"Garlington Rd",
    "iso:country":"US",
    "sg:address":"481 Garlington Rd",
    "sg:city":"Greenville",
    "sg:classifiers":[
        {
            "category":"Professional",
            "subcategory":"Computer Services",
            "type":"Services"
        }
    ],
    "sg:phone":"+1 864 281 0682",
    "sg:postcode":"29615",
    "sg:province":"SC",
    "sg:tags":[
        "consultant",
        "designer"
    ],
    "wof:name":"Strategic Technologies",
    "wof:placetype":"venue"
},
  "geometry": {"coordinates":[-82.28701700000001,34.835686],"type":"Point"}
}