{
  "type": "Feature",
  "properties": {
    "iso:country":"US",
    "sg:address":"157 E Main St",
    "sg:city":"Rock Hill",
    "sg:classifiers":[
        {
            "category":"Insurance",
            "subcategory":"Insurance Agent",
            "type":"Services"
        }
    ],
    "sg:phone":"+1 803 366 8300",
    "sg:postcode":"29730",
    "sg:province":"SC",
    "sg:tags":[
        "accident"
    ],
    "wof:name":"Impro",
    "wof:placetype":"venue"
},
  "geometry": {"coordinates":[-81.027241,34.92569],"type":"Point"}
}