{
  "type": "Feature",
  "properties": {
    "iso:country":"US",
    "sg:address":"128 Red Bank Rd",
    "sg:city":"Goose Creek",
    "sg:classifiers":[
        {
            "category":"Organizations",
            "subcategory":"Religious Organization",
            "type":"Services"
        }
    ],
    "sg:phone":"+1 843 572 0151",
    "sg:postcode":"29445",
    "sg:province":"SC",
    "sg:tags":[
        "church"
    ],
    "wof:name":"Worship Center Church Of God",
    "wof:placetype":"venue"
},
  "geometry": {"coordinates":[-80.03541199999999,32.989953],"type":"Point"}
}