{
  "type": "Feature",
  "properties": {
    "iso:country":"US",
    "sg:address":"411 Poplar St",
    "sg:city":"Walterboro",
    "sg:classifiers":[
        {
            "category":"Shopping",
            "subcategory":"Clothing, Apparel, & Fashions",
            "type":"Retail Goods"
        }
    ],
    "sg:phone":"+1 843 217 0474",
    "sg:postcode":"29488",
    "sg:province":"SC",
    "wof:name":"Dixie Tee Shirt",
    "wof:placetype":"venue"
},
  "geometry": {"coordinates":[-80.638835,32.900483],"type":"Point"}
}