{
  "type": "Feature",
  "properties": {
    "addr:full":"410 W Liberty St Sumter SC 29150",
    "addr:housenumber":"410",
    "addr:postcode":"29150",
    "addr:street":"W Liberty St",
    "iso:country":"US",
    "sg:address":"410 W Liberty St",
    "sg:city":"Sumter",
    "sg:classifiers":[
        {
            "category":"Building & Trades",
            "subcategory":"Construction",
            "type":"Services"
        }
    ],
    "sg:phone":"+1 803 481 0703",
    "sg:postcode":"29150",
    "sg:province":"SC",
    "sg:tags":[
        "general",
        "contractor"
    ],
    "wof:name":"Edward Richardson Construction",
    "wof:placetype":"venue"
},
  "geometry": {"coordinates":[-80.350677,33.920514],"type":"Point"}
}