{
  "type": "Feature",
  "properties": {
    "iso:country":"US",
    "sg:address":"1172 N Pleasantburg Dr",
    "sg:city":"Greenville",
    "sg:classifiers":[
        {
            "category":"Home & Garden",
            "subcategory":"Building Materials",
            "type":"Retail Goods"
        }
    ],
    "sg:phone":"+1 864 268 6560",
    "sg:postcode":"29607",
    "sg:province":"SC",
    "sg:tags":[
        "paint"
    ],
    "wof:name":"Duron Paints & Wallcoverings",
    "wof:placetype":"venue"
},
  "geometry": {"coordinates":[-82.359122,34.872664],"type":"Point"}
}