{
  "type": "Feature",
  "properties": {
    "iso:country":"US",
    "sg:address":"9542 Dunes Gable Ct",
    "sg:city":"Myrtle Beach",
    "sg:classifiers":[
        {
            "category":"Real Estate",
            "subcategory":"Real Estate Agent",
            "type":"Services"
        }
    ],
    "sg:phone":"+1 843 692 9493",
    "sg:postcode":"29572",
    "sg:province":"SC",
    "wof:name":"Paradise Real Estate Inc",
    "wof:placetype":"venue"
},
  "geometry": {"coordinates":[-78.791516,33.765642],"type":"Point"}
}