{
  "type": "Feature",
  "properties": {
    "iso:country":"US",
    "sg:address":"390 Pine St",
    "sg:city":"Mc Bee",
    "sg:classifiers":[
        {
            "category":"Food & Beverages",
            "subcategory":"Groceries & Convenience Stores",
            "type":"Retail Goods"
        }
    ],
    "sg:phone":"+1 843 335 7403",
    "sg:postcode":"29102",
    "sg:province":"SC",
    "wof:name":"T & T Country Stop",
    "wof:placetype":"venue"
},
  "geometry": {"coordinates":[-80.212656,33.701914],"type":"Point"}
}