{
  "type": "Feature",
  "properties": {
    "addr:full":"20 Haywood Rd Greenville SC 29607",
    "addr:housenumber":"20",
    "addr:postcode":"29607",
    "addr:street":"Haywood Rd",
    "iso:country":"US",
    "sg:address":"20 Haywood Rd",
    "sg:city":"Greenville",
    "sg:classifiers":[
        {
            "category":"Manufacturing",
            "subcategory":"Printing",
            "type":"Manufacturing & Wholesale Goods"
        }
    ],
    "sg:phone":"+1 864 987 1011",
    "sg:postcode":"29607",
    "sg:province":"SC",
    "sg:tags":[
        "commercial"
    ],
    "wof:name":"Office Max Copy Services",
    "wof:placetype":"venue"
},
  "geometry": {"coordinates":[-82.346807,34.834826],"type":"Point"}
}