{
  "type": "Feature",
  "properties": {
    "iso:country":"US",
    "sg:address":"903 S Cashua Dr",
    "sg:city":"Florence",
    "sg:classifiers":[
        {
            "category":"Retail",
            "subcategory":"Repair Shop",
            "type":"Services"
        }
    ],
    "sg:phone":"+1 843 665 7165",
    "sg:postcode":"29501",
    "sg:province":"SC",
    "sg:tags":[
        "hardware",
        "equipment"
    ],
    "wof:name":"Mullins Tool Rental",
    "wof:placetype":"venue"
},
  "geometry": {"coordinates":[-79.81408399999999,34.173843],"type":"Point"}
}