{
  "type": "Feature",
  "properties": {
    "iso:country":"US",
    "sg:address":"1005 3rd Ave S",
    "sg:city":"Myrtle Beach",
    "sg:classifiers":[
        {
            "category":"Personal",
            "subcategory":"Tanning Parlor",
            "type":"Services"
        }
    ],
    "sg:phone":"+1 843 916 9596",
    "sg:postcode":"29577",
    "sg:province":"SC",
    "sg:tags":[
        "salon"
    ],
    "wof:name":"Strand Tans",
    "wof:placetype":"venue"
},
  "geometry": {"coordinates":[-78.89737700000001,33.693675],"type":"Point"}
}