{
  "type": "Feature",
  "properties": {
    "iso:country":"US",
    "sg:address":"233 Glenn Rd",
    "sg:city":"Anderson",
    "sg:classifiers":[
        {
            "category":"Home & Garden",
            "subcategory":"Building Materials",
            "type":"Retail Goods"
        }
    ],
    "sg:phone":"+1 864 224 5500",
    "sg:postcode":"29626",
    "sg:province":"SC",
    "sg:tags":[
        "downspouts",
        "gutter"
    ],
    "wof:name":"Blue Ridge Gutter Service Inc",
    "wof:placetype":"venue"
},
  "geometry": {"coordinates":[-82.759655,34.466795],"type":"Point"}
}