{
  "type": "Feature",
  "properties": {
    "iso:country":"US",
    "sg:address":"200 E Dunlap St",
    "sg:city":"Lancaster",
    "sg:classifiers":[
        {
            "category":"Government",
            "subcategory":"Office",
            "type":"Public Place"
        }
    ],
    "sg:phone":"+1 803 286 8208",
    "sg:postcode":"29720",
    "sg:province":"SC",
    "sg:tags":[
        "county",
        "program",
        "health"
    ],
    "wof:name":"Dept Health & Human Svc",
    "wof:placetype":"venue"
},
  "geometry": {"coordinates":[-80.768197,34.720984],"type":"Point"}
}