{
  "type": "Feature",
  "properties": {
    "iso:country":"US",
    "sg:address":"2495 Magnolia St",
    "sg:city":"Orangeburg",
    "sg:classifiers":[
        {
            "category":"Retail",
            "subcategory":"Auto Repair",
            "type":"Services"
        }
    ],
    "sg:phone":"+1 803 531 0140",
    "sg:postcode":"29115",
    "sg:province":"SC",
    "sg:tags":[
        "body",
        "automotive",
        "used",
        "painting",
        "automobile"
    ],
    "wof:name":"Automaxx Sales & Body Shop",
    "wof:placetype":"venue"
},
  "geometry": {"coordinates":[-80.848557,33.510387],"type":"Point"}
}