{
  "type": "Feature",
  "properties": {
    "addr:full":"2837 Rivers Ave North Charleston SC 29405",
    "addr:housenumber":"2837",
    "addr:postcode":"29405",
    "addr:street":"Rivers Ave",
    "iso:country":"US",
    "sg:address":"2837 Rivers Ave",
    "sg:city":"North Charleston",
    "sg:classifiers":[
        {
            "category":"Building & Trades",
            "subcategory":"Construction",
            "type":"Services"
        }
    ],
    "sg:phone":"+1 843 883 3938",
    "sg:postcode":"29405",
    "sg:province":"SC",
    "sg:tags":[
        "specializing",
        "contractor",
        "recreational",
        "facility"
    ],
    "wof:name":"Carolina Sports Surface Inc",
    "wof:placetype":"venue"
},
  "geometry": {"coordinates":[-79.968158,32.847042],"type":"Point"}
}