{
  "type": "Feature",
  "properties": {
    "iso:country":"US",
    "sg:address":"4101 Old Spartanburg Hwy",
    "sg:city":"Moore",
    "sg:classifiers":[
        {
            "category":"Building & Trades",
            "subcategory":"Construction",
            "type":"Services"
        }
    ],
    "sg:phone":"+1 864 576 3331",
    "sg:postcode":"29369",
    "sg:province":"SC",
    "sg:tags":[
        "contractor"
    ],
    "wof:name":"Sexton Construction",
    "wof:placetype":"venue"
},
  "geometry": {"coordinates":[-82.011045,34.832723],"type":"Point"}
}