{
  "type": "Feature",
  "properties": {
    "iso:country":"US",
    "sg:address":"138 Amicks Ferry Rd",
    "sg:city":"Chapin",
    "sg:classifiers":[
        {
            "category":"Retail",
            "subcategory":"Laundry & Dry Cleaning",
            "type":"Services"
        }
    ],
    "sg:phone":"+1 803 345 7714",
    "sg:postcode":"29036",
    "sg:province":"SC",
    "sg:tags":[
        "cleaners"
    ],
    "wof:name":"Breeze Dry Cleaning",
    "wof:placetype":"venue"
},
  "geometry": {"coordinates":[-81.355401,34.1629],"type":"Point"}
}