{
  "type": "Feature",
  "properties": {
    "addr:full":"8 Fraser St Beaufort SC 29907",
    "addr:housenumber":"8",
    "addr:postcode":"29907",
    "addr:street":"Fraser St",
    "iso:country":"US",
    "sg:address":"8 Fraser St",
    "sg:city":"Beaufort",
    "sg:classifiers":[
        {
            "category":"Shopping",
            "subcategory":"Gifts & Souvenirs",
            "type":"Retail Goods"
        },
        {
            "category":"Home & Garden",
            "subcategory":"Garden Supply",
            "type":"Retail Goods"
        }
    ],
    "sg:phone":"+1 843 322 0277",
    "sg:postcode":"29907",
    "sg:province":"SC",
    "sg:tags":[
        "center"
    ],
    "wof:name":"For The Birds N Garden",
    "wof:placetype":"venue"
},
  "geometry": {"coordinates":[-80.64257600000001,32.434265],"type":"Point"}
}