{
  "type": "Feature",
  "properties": {
    "iso:country":"US",
    "sg:address":"121 New Woodruff Rd",
    "sg:city":"Greer",
    "sg:classifiers":[
        {
            "category":"Organizations",
            "subcategory":"Religious Organization",
            "type":"Services"
        }
    ],
    "sg:phone":"+1 864 877 9686",
    "sg:postcode":"29651",
    "sg:province":"SC",
    "sg:tags":[
        "church"
    ],
    "wof:name":"Victor Baptist Church",
    "wof:placetype":"venue"
},
  "geometry": {"coordinates":[-82.22147,34.926174],"type":"Point"}
}