{
  "type": "Feature",
  "properties": {
    "addr:full":"2067 Great Falls Rd Lancaster SC 29720",
    "addr:housenumber":"2067",
    "addr:postcode":"29720",
    "addr:street":"Great Falls Rd",
    "iso:country":"US",
    "sg:address":"2067 Great Falls Rd",
    "sg:city":"Lancaster",
    "sg:classifiers":[
        {
            "category":"Retail",
            "subcategory":"Auto Rental",
            "type":"Services"
        }
    ],
    "sg:phone":"+1 803 285 6008",
    "sg:postcode":"29720",
    "sg:province":"SC",
    "sg:tags":[
        "renting",
        "truck",
        "leasing"
    ],
    "wof:name":"U-Haul Co",
    "wof:placetype":"venue"
},
  "geometry": {"coordinates":[-80.811575,34.663537],"type":"Point"}
}