{
  "type": "Feature",
  "properties": {
    "iso:country":"US",
    "sg:address":"117 Paul St",
    "sg:city":"Walterboro",
    "sg:classifiers":[
        {
            "category":"Retail",
            "subcategory":"Funeral Services",
            "type":"Services"
        }
    ],
    "sg:phone":"+1 843 549 5081",
    "sg:postcode":"29488",
    "sg:province":"SC",
    "sg:tags":[
        "director"
    ],
    "wof:name":"Parker Rhoden Funeral Home Inc",
    "wof:placetype":"venue"
},
  "geometry": {"coordinates":[-80.665746,32.906218],"type":"Point"}
}