{
  "type": "Feature",
  "properties": {
    "iso:country":"US",
    "sg:address":"12 Reeder Point Dr",
    "sg:city":"Columbia",
    "sg:classifiers":[
        {
            "category":"Organizations",
            "subcategory":"Religious Organization",
            "type":"Services"
        }
    ],
    "sg:phone":"+1 803 776 4450",
    "sg:postcode":"29209",
    "sg:province":"SC",
    "sg:tags":[
        "church"
    ],
    "wof:name":"Zion Chapel Baptist Church",
    "wof:placetype":"venue"
},
  "geometry": {"coordinates":[-80.96253,33.935301],"type":"Point"}
}