{
  "type": "Feature",
  "properties": {
    "iso:country":"US",
    "sg:address":"919 W Lucas St",
    "sg:city":"Florence",
    "sg:classifiers":[
        {
            "category":"Building & Trades",
            "subcategory":"Construction",
            "type":"Services"
        }
    ],
    "sg:phone":"+1 843 661 2191",
    "sg:postcode":"29501",
    "sg:province":"SC",
    "sg:tags":[
        "dry wall",
        "contractor"
    ],
    "wof:name":"Griffin Insulation & Drywall",
    "wof:placetype":"venue"
},
  "geometry": {"coordinates":[-79.77977199999999,34.213759],"type":"Point"}
}