{
  "type": "Feature",
  "properties": {
    "iso:country":"US",
    "sg:address":"459 Broad St",
    "sg:city":"Sumter",
    "sg:classifiers":[
        {
            "category":"Restaurant",
            "type":"Food & Drink"
        }
    ],
    "sg:phone":"+1 803 775 5941",
    "sg:postcode":"29150",
    "sg:province":"SC",
    "sg:tags":[
        "eating"
    ],
    "wof:name":"China Palace",
    "wof:placetype":"venue"
},
  "geometry": {"coordinates":[-80.360545,33.937769],"type":"Point"}
}