{
  "type": "Feature",
  "properties": {
    "iso:country":"US",
    "sg:address":"108 S Cleveland St",
    "sg:city":"Kershaw",
    "sg:classifiers":[
        {
            "category":"Health Services",
            "subcategory":"Doctor",
            "type":"Services"
        }
    ],
    "sg:phone":"+1 803 475 9440",
    "sg:postcode":"29067",
    "sg:province":"SC",
    "sg:tags":[
        "dentist"
    ],
    "wof:name":"Gabriel B Ingraham III DDS",
    "wof:placetype":"venue"
},
  "geometry": {"coordinates":[-80.583201,34.54776],"type":"Point"}
}