{
  "type": "Feature",
  "properties": {
    "iso:country":"US",
    "sg:address":"925 Munsen Spring Dr",
    "sg:city":"Columbia",
    "sg:classifiers":[
        {
            "category":"Building & Trades",
            "subcategory":"Construction",
            "type":"Services"
        }
    ],
    "sg:phone":"+1 803 776 7329",
    "sg:postcode":"29209",
    "sg:province":"SC",
    "sg:tags":[
        "hanging",
        "contractor"
    ],
    "wof:name":"A & S Enterprises Inc Columbia",
    "wof:placetype":"venue"
},
  "geometry": {"coordinates":[-80.96131,33.984565],"type":"Point"}
}