{
  "type": "Feature",
  "properties": {
    "iso:country":"US",
    "sg:address":"649 Jeter St",
    "sg:city":"Edgefield",
    "sg:classifiers":[
        {
            "category":"Food & Beverages",
            "subcategory":"Groceries & Convenience Stores",
            "type":"Retail Goods"
        }
    ],
    "sg:phone":"+1 803 637 6083",
    "sg:postcode":"29824",
    "sg:province":"SC",
    "sg:tags":[
        "grocer"
    ],
    "wof:name":"Hamm's Place",
    "wof:placetype":"venue"
},
  "geometry": {"coordinates":[-81.93570699999999,33.788618],"type":"Point"}
}