{
  "type": "Feature",
  "properties": {
    "iso:country":"US",
    "sg:address":"111 Lowman Dr",
    "sg:city":"Holly Hill",
    "sg:classifiers":[
        {
            "category":"Home & Garden",
            "subcategory":"Hardware",
            "type":"Retail Goods"
        },
        {
            "category":"Wholesale",
            "subcategory":"Hardware",
            "type":"Manufacturing & Wholesale Goods"
        }
    ],
    "sg:phone":"+1 803 496 9180",
    "sg:postcode":"29059",
    "sg:province":"SC",
    "sg:tags":[
        "tool",
        "parts",
        "sales"
    ],
    "wof:name":"Palmeto Procurement Company",
    "wof:placetype":"venue"
},
  "geometry": {"coordinates":[-80.379613,33.32351],"type":"Point"}
}