{
  "type": "Feature",
  "properties": {
    "addr:full":"7 Mullet St Bluffton SC 29910",
    "addr:housenumber":"7",
    "addr:postcode":"29910",
    "addr:street":"Mullet St",
    "iso:country":"US",
    "sg:address":"7 Mullet St",
    "sg:city":"Bluffton",
    "sg:classifiers":[
        {
            "category":"Health Services",
            "subcategory":"Doctor",
            "type":"Services"
        }
    ],
    "sg:phone":"+1 843 815 5066",
    "sg:postcode":"29910",
    "sg:province":"SC",
    "sg:tags":[
        "physician",
        "surgeon"
    ],
    "wof:name":"Harbourside Medical Assoc",
    "wof:placetype":"venue"
},
  "geometry": {"coordinates":[-80.84629099999999,32.216707],"type":"Point"}
}