{
  "type": "Feature",
  "properties": {
    "iso:country":"US",
    "sg:address":"1785 Reservation Rd",
    "sg:city":"Rock Hill",
    "sg:classifiers":[
        {
            "category":"Building & Trades",
            "subcategory":"Construction",
            "type":"Services"
        }
    ],
    "sg:phone":"+1 803 324 4777",
    "sg:postcode":"29730",
    "sg:province":"SC",
    "sg:tags":[
        "excavating",
        "contractor"
    ],
    "wof:name":"Kenny's Backhoe Svc",
    "wof:placetype":"venue"
},
  "geometry": {"coordinates":[-80.897241,34.899809],"type":"Point"}
}