{
  "type": "Feature",
  "properties": {
    "iso:country":"US",
    "sg:address":"102 Gantt St",
    "sg:city":"Lexington",
    "sg:classifiers":[
        {
            "category":"Professional",
            "type":"Services"
        },
        {
            "category":"Shopping",
            "type":"Retail Goods"
        }
    ],
    "sg:phone":"+1 803 359 7744",
    "sg:postcode":"29072",
    "sg:province":"SC",
    "sg:tags":[
        "repair",
        "arts",
        "merchandise",
        "artist"
    ],
    "wof:name":"Four Corner Art and Frame",
    "wof:placetype":"venue"
},
  "geometry": {"coordinates":[-81.235704,33.981792],"type":"Point"}
}