{
  "type": "Feature",
  "properties": {
    "addr:full":"1321 Celebrity Cir Myrtle Beach SC 29577",
    "addr:housenumber":"1321",
    "addr:postcode":"29577",
    "addr:street":"Celebrity Cir",
    "iso:country":"US",
    "sg:address":"1321 Celebrity Cir",
    "sg:city":"Myrtle Beach",
    "sg:classifiers":[
        {
            "category":"Shopping",
            "subcategory":"Used Merchandise",
            "type":"Retail Goods"
        }
    ],
    "sg:phone":"+1 843 916 9269",
    "sg:postcode":"29577",
    "sg:province":"SC",
    "sg:tags":[
        "book",
        "rare",
        "dealer"
    ],
    "wof:name":"ATM Now",
    "wof:placetype":"venue"
},
  "geometry": {"coordinates":[-78.87951200000001,33.719326],"type":"Point"}
}