{
  "type": "Feature",
  "properties": {
    "iso:country":"US",
    "sg:address":"3394 Young-Charles Dr",
    "sg:city":"Florence",
    "sg:classifiers":[
        {
            "category":"Building & Trades",
            "subcategory":"Construction",
            "type":"Services"
        }
    ],
    "sg:phone":"+1 843 667 4506",
    "sg:postcode":"29501",
    "sg:province":"SC",
    "sg:tags":[
        "house"
    ],
    "wof:name":"Gbm Construciton Co",
    "wof:placetype":"venue"
},
  "geometry": {"coordinates":[-79.839536,34.153007],"type":"Point"}
}