{
  "type": "Feature",
  "properties": {
    "addr:full":"2446 Laurens Rd Greenville SC 29607",
    "addr:housenumber":"2446",
    "addr:postcode":"29607",
    "addr:street":"Laurens Rd",
    "iso:country":"US",
    "sg:address":"2446 Laurens Rd",
    "sg:city":"Greenville",
    "sg:classifiers":[
        {
            "category":"Autos & Motor Vehicles",
            "subcategory":"Automobile Sales",
            "type":"Retail Goods"
        }
    ],
    "sg:phone":"+1 864 213 8000",
    "sg:postcode":"29607",
    "sg:province":"SC",
    "wof:name":"Carlton Motorcars Inc",
    "wof:placetype":"venue"
},
  "geometry": {"coordinates":[-82.346051,34.827247],"type":"Point"}
}