{
  "type": "Feature",
  "properties": {
    "iso:country":"US",
    "sg:address":"918 Shiloh Rd",
    "sg:city":"Seneca",
    "sg:classifiers":[
        {
            "category":"Retail",
            "subcategory":"Repair Shop",
            "type":"Services"
        }
    ],
    "sg:phone":"+1 864 882 9814",
    "sg:postcode":"29678",
    "sg:province":"SC",
    "sg:tags":[
        "upholsterer"
    ],
    "wof:name":"Alexander's Upholstery",
    "wof:placetype":"venue"
},
  "geometry": {"coordinates":[-82.90440099999999,34.680158],"type":"Point"}
}