{
  "type": "Feature",
  "properties": {
    "iso:country":"US",
    "sg:address":"4406 Forest Dr",
    "sg:city":"Columbia",
    "sg:classifiers":[
        {
            "category":"Insurance",
            "subcategory":"Insurance Agent",
            "type":"Services"
        }
    ],
    "sg:phone":"+1 803 743 0071",
    "sg:postcode":"29206",
    "sg:province":"SC",
    "sg:website":"www.libertylife.com",
    "wof:name":"RBC Liberty Insurance",
    "wof:placetype":"venue"
},
  "geometry": {"coordinates":[-80.973687,34.020981],"type":"Point"}
}