{
  "type": "Feature",
  "properties": {
    "addr:full":"4311 Hard Scrabble Rd Columbia SC 29223",
    "addr:postcode":"4311;29223",
    "addr:street":"Scrabble Rd",
    "iso:country":"US",
    "sg:address":"4311 Hard Scrabble Rd",
    "sg:city":"Columbia",
    "sg:classifiers":[
        {
            "category":"Health Services",
            "subcategory":"Doctor",
            "type":"Services"
        }
    ],
    "sg:phone":"+1 803 462 7000",
    "sg:postcode":"29223",
    "sg:province":"SC",
    "sg:tags":[
        "physician",
        "surgeon"
    ],
    "wof:name":"Carolina Physician Group",
    "wof:placetype":"venue"
},
  "geometry": {"coordinates":[-80.91383500000001,34.140343],"type":"Point"}
}