{
  "type": "Feature",
  "properties": {
    "iso:country":"US",
    "sg:address":"1648 Blue Johnson Rd",
    "sg:city":"Hopkins",
    "sg:classifiers":[
        {
            "category":"Building & Trades",
            "subcategory":"Electrical",
            "type":"Services"
        }
    ],
    "sg:phone":"+1 803 783 8952",
    "sg:postcode":"29061",
    "sg:province":"SC",
    "sg:tags":[
        "electric",
        "contractor"
    ],
    "wof:name":"Dixie Electric",
    "wof:placetype":"venue"
},
  "geometry": {"coordinates":[-80.821866,33.974378],"type":"Point"}
}