{
  "type": "Feature",
  "properties": {
    "iso:country":"US",
    "sg:address":"306 Sangaree Rd",
    "sg:city":"Summerville",
    "sg:classifiers":[
        {
            "category":"Professional",
            "subcategory":"Engineering",
            "type":"Services"
        }
    ],
    "sg:phone":"+1 843 873 9787",
    "sg:postcode":"29488",
    "sg:province":"SC",
    "sg:tags":[
        "engineer"
    ],
    "wof:name":"Ashley Engineering",
    "wof:placetype":"venue"
},
  "geometry": {"coordinates":[-80.670963,32.930775],"type":"Point"}
}