{
  "type": "Feature",
  "properties": {
    "iso:country":"US",
    "sg:address":"22 Stephanie Dr",
    "sg:city":"Pelzer",
    "sg:classifiers":[
        {
            "category":"Building & Trades",
            "subcategory":"Construction",
            "type":"Services"
        }
    ],
    "sg:phone":"+1 864 947 9876",
    "sg:postcode":"29669",
    "sg:province":"SC",
    "sg:tags":[
        "home",
        "improvement"
    ],
    "wof:name":"Beacham Inc",
    "wof:placetype":"venue"
},
  "geometry": {"coordinates":[-82.47898,34.646913],"type":"Point"}
}