{
  "type": "Feature",
  "properties": {
    "iso:country":"US",
    "sg:address":"207 Hillcrest Dr",
    "sg:city":"Laurens",
    "sg:classifiers":[
        {
            "category":"Food & Beverages",
            "subcategory":"Liquor & Beverages",
            "type":"Retail Goods"
        }
    ],
    "sg:phone":"+1 864 984 3023",
    "sg:postcode":"29360",
    "sg:province":"SC",
    "sg:tags":[
        "beer",
        "ale"
    ],
    "wof:name":"Palmetto Party Ctr",
    "wof:placetype":"venue"
},
  "geometry": {"coordinates":[-82.013728,34.505008],"type":"Point"}
}