{
  "type": "Feature",
  "properties": {
    "iso:country":"US",
    "sg:address":"325 State Hwy 72 Bus",
    "sg:city":"Greenwood",
    "sg:classifiers":[
        {
            "category":"Banks & Credit Unions",
            "subcategory":"Bank",
            "type":"Services"
        }
    ],
    "sg:phone":"+1 864 223 6111",
    "sg:postcode":"29649",
    "sg:province":"SC",
    "sg:tags":[
        "company",
        "commercial",
        "finance"
    ],
    "wof:name":"Quick Credit Corp",
    "wof:placetype":"venue"
},
  "geometry": {"coordinates":[-82.160412,34.199284],"type":"Point"}
}