{
  "type": "Feature",
  "properties": {
    "addr:full":"1400 29th Ave N Myrtle Beach SC 29577",
    "addr:housenumber":"1400",
    "addr:postcode":"29577",
    "addr:street":"29Th Ave N",
    "iso:country":"US",
    "sg:address":"1400 29th Ave N",
    "sg:city":"Myrtle Beach",
    "sg:classifiers":[
        {
            "category":"Shopping",
            "subcategory":"Shoes",
            "type":"Retail Goods"
        }
    ],
    "sg:phone":"+1 843 839 4653",
    "sg:postcode":"29577",
    "sg:province":"SC",
    "wof:name":"Martin's Golf & Tennis",
    "wof:placetype":"venue"
},
  "geometry": {"coordinates":[-78.875865,33.717475],"type":"Point"}
}