{
  "type": "Feature",
  "properties": {
    "iso:country":"US",
    "sg:address":"461 W Palmetto St",
    "sg:city":"Florence",
    "sg:classifiers":[
        {
            "category":"Health Services",
            "subcategory":"Doctor",
            "type":"Services"
        }
    ],
    "sg:phone":"+1 843 667 0286",
    "sg:postcode":"29501",
    "sg:province":"SC",
    "sg:tags":[
        "dentist"
    ],
    "wof:name":"Shealy Dental Clinic",
    "wof:placetype":"venue"
},
  "geometry": {"coordinates":[-79.774409,34.193427],"type":"Point"}
}