{
  "type": "Feature",
  "properties": {
    "addr:full":"122 Irene Cir Greenville SC 29617",
    "addr:housenumber":"122",
    "addr:postcode":"29617",
    "addr:street":"Irene Cir",
    "iso:country":"US",
    "sg:address":"122 Irene Cir",
    "sg:city":"Greenville",
    "sg:classifiers":[
        {
            "category":"Building & Trades",
            "subcategory":"Construction",
            "type":"Services"
        }
    ],
    "sg:phone":"+1 864 235 5576",
    "sg:postcode":"29617",
    "sg:province":"SC",
    "sg:tags":[
        "painting",
        "industrial",
        "commercial",
        "contractor"
    ],
    "wof:name":"B & T Contractors Inc",
    "wof:placetype":"venue"
},
  "geometry": {"coordinates":[-82.42738,34.886606],"type":"Point"}
}