{
  "type": "Feature",
  "properties": {
    "iso:country":"US",
    "sg:address":"513 Mill Stream Rd",
    "sg:city":"Lexington",
    "sg:classifiers":[
        {
            "category":"Shopping",
            "subcategory":"Stationery & Office Supplies",
            "type":"Retail Goods"
        }
    ],
    "sg:phone":"+1 803 957 9020",
    "sg:postcode":"29072",
    "sg:province":"SC",
    "sg:tags":[
        "printing",
        "commercial"
    ],
    "wof:name":"By Invitation Only",
    "wof:placetype":"venue"
},
  "geometry": {"coordinates":[-81.169075,34.031095],"type":"Point"}
}