{
  "type": "Feature",
  "properties": {
    "addr:full":"1017 W Main St Laurens SC 29360",
    "addr:housenumber":"1017",
    "addr:postcode":"29360",
    "addr:street":"W Main St",
    "iso:country":"US",
    "sg:address":"1017 W Main St",
    "sg:city":"Laurens",
    "sg:classifiers":[
        {
            "category":"Education",
            "subcategory":"Library",
            "type":"Public Place"
        }
    ],
    "sg:phone":"+1 864 984 0596",
    "sg:postcode":"29360",
    "sg:province":"SC",
    "sg:website":"www.lcpl.org",
    "wof:name":"Laurens County Library",
    "wof:placetype":"venue"
},
  "geometry": {"coordinates":[-82.03342499999999,34.493011],"type":"Point"}
}