{
  "type": "Feature",
  "properties": {
    "iso:country":"US",
    "sg:address":"14 Resolute Ln",
    "sg:city":"Mount Pleasant",
    "sg:classifiers":[
        {
            "category":"Shopping",
            "subcategory":"Florist",
            "type":"Retail Goods"
        }
    ],
    "sg:phone":"+1 843 388 8424",
    "sg:postcode":"29464",
    "sg:province":"SC",
    "wof:name":"Belles Fleurs",
    "wof:placetype":"venue"
},
  "geometry": {"coordinates":[-79.878986,32.812517],"type":"Point"}
}