{
  "type": "Feature",
  "properties": {
    "addr:full":"810 S Main St Mullins SC 29574",
    "addr:housenumber":"810",
    "addr:postcode":"29574",
    "addr:street":"S Main St",
    "iso:country":"US",
    "sg:address":"810 S Main St",
    "sg:city":"Mullins",
    "sg:classifiers":[
        {
            "category":"Building & Trades",
            "subcategory":"Electrical",
            "type":"Services"
        },
        {
            "category":"Shopping",
            "subcategory":"Computers & Home Electronics",
            "type":"Retail Goods"
        }
    ],
    "sg:phone":"+1 843 464 4006",
    "sg:postcode":"29574",
    "sg:province":"SC",
    "sg:tags":[
        "equipment",
        "satellite",
        "electrical",
        "system",
        "contractor"
    ],
    "wof:name":"Quality Satellite Service",
    "wof:placetype":"venue"
},
  "geometry": {"coordinates":[-79.25170300000001,34.193849],"type":"Point"}
}