{
  "type": "Feature",
  "properties": {
    "addr:full":"4804 Old Georgia Hwy Cowpens SC 29330",
    "addr:housenumber":"4804",
    "addr:postcode":"29330",
    "addr:street":"Old Georgia Hwy",
    "iso:country":"US",
    "sg:address":"4804 Old Georgia Hwy",
    "sg:city":"Cowpens",
    "sg:classifiers":[
        {
            "category":"Building & Trades",
            "subcategory":"Construction",
            "type":"Services"
        }
    ],
    "sg:phone":"+1 864 463 7140",
    "sg:postcode":"29330",
    "sg:province":"SC",
    "sg:tags":[
        "equipment",
        "installation"
    ],
    "wof:name":"Independant Riggers",
    "wof:placetype":"venue"
},
  "geometry": {"coordinates":[-81.772443,35.017551],"type":"Point"}
}