{
  "type": "Feature",
  "properties": {
    "iso:country":"US",
    "sg:address":"252 Trexler Ln",
    "sg:city":"Rock Hill",
    "sg:classifiers":[
        {
            "category":"Building & Trades",
            "subcategory":"Plumbing",
            "type":"Services"
        }
    ],
    "sg:phone":"+1 803 366 8006",
    "sg:postcode":"29732",
    "sg:province":"SC",
    "sg:tags":[
        "heating",
        "contractor"
    ],
    "wof:name":"B B & T Refrigaration Inc",
    "wof:placetype":"venue"
},
  "geometry": {"coordinates":[-81.052835,34.975269],"type":"Point"}
}