{
  "type": "Feature",
  "properties": {
    "iso:country":"US",
    "sg:address":"204 E Main St",
    "sg:city":"Taylors",
    "sg:classifiers":[
        {
            "category":"Recreation",
            "type":"Entertainment"
        }
    ],
    "sg:phone":"+1 864 268 7397",
    "sg:postcode":"29687",
    "sg:province":"SC",
    "sg:tags":[
        "skating",
        "rink"
    ],
    "wof:name":"Roller Sports Inc",
    "wof:placetype":"venue"
},
  "geometry": {"coordinates":[-82.293806,34.920844],"type":"Point"}
}