{
  "type": "Feature",
  "properties": {
    "addr:full":"119 Donald Dr Pelzer SC 29669",
    "addr:housenumber":"119",
    "addr:postcode":"29669",
    "addr:street":"Donald Dr",
    "iso:country":"US",
    "sg:address":"119 Donald Dr",
    "sg:city":"Pelzer",
    "sg:classifiers":[
        {
            "category":"Building & Trades",
            "subcategory":"Plumbing",
            "type":"Services"
        }
    ],
    "sg:phone":"+1 864 243 3347",
    "sg:postcode":"29669",
    "sg:province":"SC",
    "sg:tags":[
        "specializing",
        "contractor",
        "system",
        "septic",
        "grading"
    ],
    "wof:name":"Grading Nicholson & Hauling",
    "wof:placetype":"venue"
},
  "geometry": {"coordinates":[-82.374742,34.639921],"type":"Point"}
}