{
  "type": "Feature",
  "properties": {
    "iso:country":"US",
    "sg:address":"304 W Main St",
    "sg:city":"Dillon",
    "sg:classifiers":[
        {
            "category":"Insurance",
            "subcategory":"Insurance Agent",
            "type":"Services"
        }
    ],
    "sg:phone":"+1 843 774 5351",
    "sg:postcode":"29536",
    "sg:province":"SC",
    "wof:name":"Coleman Insurance",
    "wof:placetype":"venue"
},
  "geometry": {"coordinates":[-79.375606,34.418996],"type":"Point"}
}