{
  "type": "Feature",
  "properties": {
    "iso:country":"US",
    "sg:address":"1621 Savannah Hwy",
    "sg:city":"Charleston",
    "sg:classifiers":[
        {
            "category":"Autos & Motor Vehicles",
            "subcategory":"Automobile Sales",
            "type":"Retail Goods"
        }
    ],
    "sg:phone":"+1 843 725 7000",
    "sg:postcode":"29407",
    "sg:province":"SC",
    "sg:tags":[
        "car",
        "dealer"
    ],
    "sg:website":"www.sentrygm.com",
    "wof:name":"Harold Arnold's Sentry Buick",
    "wof:placetype":"venue"
},
  "geometry": {"coordinates":[-80.012049,32.786517],"type":"Point"}
}