{
  "type": "Feature",
  "properties": {
    "addr:full":"102 Rembert C Dennis Blvd Moncks Corner SC 29461",
    "addr:housenumber":"102;c",
    "addr:postcode":"29461",
    "addr:street":"Rembert;Dennis Blvd",
    "iso:country":"US",
    "sg:address":"102 Rembert C Dennis Blvd",
    "sg:city":"Moncks Corner",
    "sg:classifiers":[
        {
            "category":"Shopping",
            "subcategory":"Department Store",
            "type":"Retail Goods"
        }
    ],
    "sg:phone":"+1 843 899 5330",
    "sg:postcode":"29461",
    "sg:province":"SC",
    "wof:name":"Cato Fashion",
    "wof:placetype":"venue"
},
  "geometry": {"coordinates":[-79.99771699999999,33.187354],"type":"Point"}
}