{
  "type": "Feature",
  "properties": {
    "iso:country":"US",
    "sg:address":"255 Gibson Rd",
    "sg:city":"Lexington",
    "sg:classifiers":[
        {
            "category":"Utilities",
            "subcategory":"Telephone",
            "type":"Services"
        }
    ],
    "sg:phone":"+1 803 356 7605",
    "sg:postcode":"29072",
    "sg:province":"SC",
    "sg:tags":[
        "company"
    ],
    "wof:name":"MCIFAA",
    "wof:placetype":"venue"
},
  "geometry": {"coordinates":[-81.243533,33.970064],"type":"Point"}
}