{
  "type": "Feature",
  "properties": {
    "addr:full":"108 Buckeye Trl Anderson SC 29626",
    "addr:housenumber":"108",
    "addr:postcode":"29626",
    "addr:street":"Buckeye Trl",
    "iso:country":"US",
    "sg:address":"108 Buckeye Trl",
    "sg:city":"Anderson",
    "sg:classifiers":[
        {
            "category":"Food & Beverages",
            "subcategory":"Specialty",
            "type":"Retail Goods"
        }
    ],
    "sg:phone":"+1 864 231 0177",
    "sg:postcode":"29626",
    "sg:province":"SC",
    "sg:tags":[
        "vitamin"
    ],
    "wof:name":"Shaklee Distributor",
    "wof:placetype":"venue"
},
  "geometry": {"coordinates":[-82.83531000000001,34.440614],"type":"Point"}
}