{
  "type": "Feature",
  "properties": {
    "addr:full":"1412 Kingston Rd Columbia SC 29204",
    "addr:housenumber":"1412",
    "addr:postcode":"29204",
    "addr:street":"Kingston Rd",
    "iso:country":"US",
    "sg:address":"1412 Kingston Rd",
    "sg:city":"Columbia",
    "sg:classifiers":[
        {
            "category":"Organizations",
            "subcategory":"Religious Organization",
            "type":"Services"
        }
    ],
    "sg:phone":"+1 803 933 0904",
    "sg:postcode":"29204",
    "sg:province":"SC",
    "sg:tags":[
        "church"
    ],
    "wof:name":"Apostolic Church-Jesus Christ",
    "wof:placetype":"venue"
},
  "geometry": {"coordinates":[-81.00321599999999,34.030242],"type":"Point"}
}