{
  "type": "Feature",
  "properties": {
    "iso:country":"US",
    "sg:address":"614 Pondview Rd",
    "sg:city":"Johns Island",
    "sg:classifiers":[
        {
            "category":"Home & Garden",
            "subcategory":"Carpets & Floor Coverings",
            "type":"Retail Goods"
        }
    ],
    "sg:phone":"+1 843 559 2650",
    "sg:postcode":"29455",
    "sg:province":"SC",
    "wof:name":"Jayco Floor Covering",
    "wof:placetype":"venue"
},
  "geometry": {"coordinates":[-80.094247,32.771405],"type":"Point"}
}