{
  "type": "Feature",
  "properties": {
    "iso:country":"US",
    "sg:address":"1623 Casey Creek Rd",
    "sg:city":"Chesnee",
    "sg:classifiers":[
        {
            "category":"Autos & Motor Vehicles",
            "subcategory":"Automobile Sales",
            "type":"Retail Goods"
        }
    ],
    "sg:phone":"+1 864 814 0551",
    "sg:postcode":"29323",
    "sg:province":"SC",
    "sg:tags":[
        "used"
    ],
    "wof:name":"Steve Mitchells Quality Cars",
    "wof:placetype":"venue"
},
  "geometry": {"coordinates":[-81.89143,35.087904],"type":"Point"}
}