{
  "type": "Feature",
  "properties": {
    "addr:full":"1276 Ruddy Duck Rd Camden SC 29020",
    "addr:housenumber":"1276",
    "addr:postcode":"29020",
    "addr:street":"Ruddy Duck Rd",
    "iso:country":"US",
    "sg:address":"1276 Ruddy Duck Rd",
    "sg:city":"Camden",
    "sg:classifiers":[
        {
            "category":"Building & Trades",
            "subcategory":"Plumbing",
            "type":"Services"
        }
    ],
    "sg:phone":"+1 843 992 3348",
    "sg:postcode":"29020",
    "sg:province":"SC",
    "sg:tags":[
        "contractor"
    ],
    "wof:name":"Hans Plumbing Company",
    "wof:placetype":"venue"
},
  "geometry": {"coordinates":[-80.71658499999999,34.369705],"type":"Point"}
}