{
  "type": "Feature",
  "properties": {
    "iso:country":"US",
    "sg:address":"1 Penarth Dr",
    "sg:city":"Greenville",
    "sg:classifiers":[
        {
            "category":"Food & Beverages",
            "subcategory":"Groceries & Convenience Stores",
            "type":"Retail Goods"
        }
    ],
    "sg:phone":"+1 864 246 7678",
    "sg:postcode":"29617",
    "sg:province":"SC",
    "wof:name":"E C Solutions LLC",
    "wof:placetype":"venue"
},
  "geometry": {"coordinates":[-82.455804,34.871694],"type":"Point"}
}