{
  "type": "Feature",
  "properties": {
    "addr:full":"1860 Woodruff Rd Greenville SC 29607",
    "addr:housenumber":"1860",
    "addr:postcode":"29607",
    "addr:street":"Woodruff Rd",
    "iso:country":"US",
    "sg:address":"1860 Woodruff Rd",
    "sg:city":"Greenville",
    "sg:classifiers":[
        {
            "category":"Shopping",
            "subcategory":"Hobbies, Toys, & Games",
            "type":"Retail Goods"
        }
    ],
    "sg:phone":"+1 864 286 6777",
    "sg:postcode":"29607",
    "sg:province":"SC",
    "sg:tags":[
        "doll",
        "clothing",
        "accessory"
    ],
    "wof:name":"Unforgettables",
    "wof:placetype":"venue"
},
  "geometry": {"coordinates":[-82.272594,34.819445],"type":"Point"}
}