{
  "type": "Feature",
  "properties": {
    "iso:country":"US",
    "sg:address":"547 State Hwy 174",
    "sg:city":"Edisto Island",
    "sg:classifiers":[
        {
            "category":"Real Estate",
            "subcategory":"Real Estate Agent",
            "type":"Services"
        }
    ],
    "sg:phone":"+1 843 869 0100",
    "sg:postcode":"29438",
    "sg:province":"SC",
    "wof:name":"Egrets Pointe Townhouses Assn",
    "wof:placetype":"venue"
},
  "geometry": {"coordinates":[-80.299471,32.52388],"type":"Point"}
}