{
  "type": "Feature",
  "properties": {
    "iso:country":"US",
    "sg:address":"2780 Legion Rd",
    "sg:city":"Smyrna",
    "sg:classifiers":[
        {
            "category":"Manufacturing",
            "subcategory":"Lumber",
            "type":"Manufacturing & Wholesale Goods"
        }
    ],
    "sg:phone":"+1 803 925 0770",
    "sg:postcode":"29743",
    "sg:province":"SC",
    "sg:tags":[
        "logging",
        "contractor"
    ],
    "wof:name":"Benfield Michael I Wood Pdts",
    "wof:placetype":"venue"
},
  "geometry": {"coordinates":[-81.418502,35.038643],"type":"Point"}
}