{
  "type": "Feature",
  "properties": {
    "iso:country":"US",
    "sg:address":"205 Morris Rd",
    "sg:city":"Pickens",
    "sg:classifiers":[
        {
            "category":"Retail",
            "subcategory":"Auto Repair",
            "type":"Services"
        }
    ],
    "sg:phone":"+1 864 878 0713",
    "sg:postcode":"29671",
    "sg:province":"SC",
    "sg:tags":[
        "exchanging",
        "engine"
    ],
    "wof:name":"Miller's Small Engine",
    "wof:placetype":"venue"
},
  "geometry": {"coordinates":[-82.739028,34.890374],"type":"Point"}
}