{
  "type": "Feature",
  "properties": {
    "iso:country":"US",
    "sg:address":"421 E Calhoun Crossing Ct",
    "sg:city":"Spartanburg",
    "sg:classifiers":[
        {
            "category":"Real Estate",
            "subcategory":"Real Estate Operator",
            "type":"Services"
        }
    ],
    "sg:phone":"+1 864 579 1578",
    "sg:postcode":"29307",
    "sg:province":"SC",
    "sg:tags":[
        "building",
        "nonresidential"
    ],
    "wof:name":"FM Professional Park LLC",
    "wof:placetype":"venue"
},
  "geometry": {"coordinates":[-81.84752400000001,34.962054],"type":"Point"}
}