{
  "type": "Feature",
  "properties": {
    "addr:full":"1350 Ashley River Rd Charleston SC 29407",
    "addr:housenumber":"1350",
    "addr:postcode":"29407",
    "addr:street":"Ashley River Rd",
    "iso:country":"US",
    "sg:address":"1350 Ashley River Rd",
    "sg:city":"Charleston",
    "sg:classifiers":[
        {
            "category":"Real Estate",
            "subcategory":"Real Estate Agent",
            "type":"Services"
        }
    ],
    "sg:phone":"+1 843 852 2901",
    "sg:postcode":"29407",
    "sg:province":"SC",
    "sg:tags":[
        "investment"
    ],
    "wof:name":"Kava Properties Inc",
    "wof:placetype":"venue"
},
  "geometry": {"coordinates":[-80.000793,32.797714],"type":"Point"}
}