{
  "type": "Feature",
  "properties": {
    "iso:country":"US",
    "sg:address":"275 Harbison Blvd",
    "sg:city":"Columbia",
    "sg:classifiers":[
        {
            "category":"Restaurant",
            "type":"Food & Drink"
        }
    ],
    "sg:phone":"+1 803 407 7075",
    "sg:postcode":"29212",
    "sg:province":"SC",
    "wof:name":"Good Times",
    "wof:placetype":"venue"
},
  "geometry": {"coordinates":[-81.15681600000001,34.073674],"type":"Point"}
}