{
  "type": "Feature",
  "properties": {
    "iso:country":"US",
    "sg:address":"9714 N Kings Hwy",
    "sg:city":"Myrtle Beach",
    "sg:classifiers":[
        {
            "category":"Real Estate",
            "subcategory":"Real Estate Operator",
            "type":"Services"
        }
    ],
    "sg:phone":"+1 843 449 7685",
    "sg:postcode":"29572",
    "sg:province":"SC",
    "sg:tags":[
        "mall",
        "shopping",
        "center"
    ],
    "wof:name":"Magnolia Plaza Shopping Ctr",
    "wof:placetype":"venue"
},
  "geometry": {"coordinates":[-78.77967,33.785719],"type":"Point"}
}