{
  "type": "Feature",
  "properties": {
    "iso:country":"US",
    "sg:address":"119 Garmony Cir",
    "sg:city":"Columbia",
    "sg:classifiers":[
        {
            "category":"Real Estate",
            "subcategory":"Real Estate Services",
            "type":"Services"
        }
    ],
    "sg:phone":"+1 803 731 9687",
    "sg:postcode":"29212",
    "sg:province":"SC",
    "sg:tags":[
        "abstract",
        "title"
    ],
    "wof:name":"Abstract Title",
    "wof:placetype":"venue"
},
  "geometry": {"coordinates":[-81.158948,34.059266],"type":"Point"}
}