{
  "type": "Feature",
  "properties": {
    "iso:country":"US",
    "sg:address":"1201 NE Main St",
    "sg:city":"Simpsonville",
    "sg:classifiers":[
        {
            "category":"Autos & Motor Vehicles",
            "subcategory":"Auto Supplies",
            "type":"Retail Goods"
        }
    ],
    "sg:phone":"+1 864 963 3407",
    "sg:postcode":"29681",
    "sg:province":"SC",
    "sg:tags":[
        "tire"
    ],
    "wof:name":"Watson's Tires & Treds",
    "wof:placetype":"venue"
},
  "geometry": {"coordinates":[-82.27233,34.759231],"type":"Point"}
}