{
  "type": "Feature",
  "properties": {
    "iso:country":"US",
    "sg:address":"702 S Mechanic St",
    "sg:city":"Pendleton",
    "sg:classifiers":[
        {
            "category":"Autos & Motor Vehicles",
            "subcategory":"Auto Supplies",
            "type":"Retail Goods"
        }
    ],
    "sg:phone":"+1 864 646 8920",
    "sg:postcode":"29670",
    "sg:province":"SC",
    "sg:tags":[
        "equipment",
        "racing",
        "car",
        "automobile"
    ],
    "sg:website":"www.baumannengineering.com",
    "wof:name":"Baumann Engineering",
    "wof:placetype":"venue"
},
  "geometry": {"coordinates":[-82.78237,34.642748],"type":"Point"}
}