{
  "type": "Feature",
  "properties": {
    "addr:full":"516 E Main St Kingstree SC 29556",
    "addr:housenumber":"516",
    "addr:postcode":"29556",
    "addr:street":"E Main St",
    "iso:country":"US",
    "sg:address":"516 E Main St",
    "sg:city":"Kingstree",
    "sg:classifiers":[
        {
            "category":"Banks & Credit Unions",
            "subcategory":"Bank",
            "type":"Services"
        }
    ],
    "sg:phone":"+1 843 354 5585",
    "sg:postcode":"29556",
    "sg:province":"SC",
    "sg:tags":[
        "financing"
    ],
    "wof:name":"Washington Mutual Finance",
    "wof:placetype":"venue"
},
  "geometry": {"coordinates":[-79.821071,33.666014],"type":"Point"}
}