{
  "type": "Feature",
  "properties": {
    "iso:country":"US",
    "sg:address":"608 Moss Creek Dr",
    "sg:city":"Cayce",
    "sg:classifiers":[
        {
            "category":"Building & Trades",
            "subcategory":"Plumbing",
            "type":"Services"
        }
    ],
    "sg:phone":"+1 803 788 1023",
    "sg:postcode":"29033",
    "sg:province":"SC",
    "wof:name":"Aaron Plumbing",
    "wof:placetype":"venue"
},
  "geometry": {"coordinates":[-81.067066,33.942857],"type":"Point"}
}