{
  "type": "Feature",
  "properties": {
    "addr:full":"120 Marydale Ln Columbia SC 29210",
    "addr:housenumber":"120",
    "addr:postcode":"29210",
    "addr:street":"Marydale Ln",
    "iso:country":"US",
    "sg:address":"120 Marydale Ln",
    "sg:city":"Columbia",
    "sg:classifiers":[
        {
            "category":"Organizations",
            "subcategory":"Religious Organization",
            "type":"Services"
        }
    ],
    "sg:phone":"+1 803 772 7400",
    "sg:postcode":"29210",
    "sg:province":"SC",
    "sg:tags":[
        "church"
    ],
    "sg:website":"www.ourladyofthehillssc.org",
    "wof:name":"Our Lady Of The Hills Catholic",
    "wof:placetype":"venue"
},
  "geometry": {"coordinates":[-81.130966,34.034883],"type":"Point"}
}