{
  "type": "Feature",
  "properties": {
    "iso:country":"US",
    "sg:address":"2881 Tricom St",
    "sg:city":"North Charleston",
    "sg:classifiers":[
        {
            "category":"Health Services",
            "subcategory":"Health Practitioner",
            "type":"Services"
        }
    ],
    "sg:phone":"+1 843 824 2183",
    "sg:postcode":"29406",
    "sg:province":"SC",
    "sg:tags":[
        "therapist",
        "physical"
    ],
    "wof:name":"Rehabilitation Centers",
    "wof:placetype":"venue"
},
  "geometry": {"coordinates":[-80.069633,32.974647],"type":"Point"}
}