{
  "type": "Feature",
  "properties": {
    "addr:full":"231 Glenn Rd West Columbia SC 29172",
    "addr:housenumber":"231",
    "addr:postcode":"29172",
    "addr:street":"Glenn Rd",
    "iso:country":"US",
    "sg:address":"231 Glenn Rd",
    "sg:city":"West Columbia",
    "sg:classifiers":[
        {
            "category":"Building & Trades",
            "subcategory":"Construction",
            "type":"Services"
        }
    ],
    "sg:phone":"+1 803 791 0535",
    "sg:postcode":"29172",
    "sg:province":"SC",
    "sg:tags":[
        "grading",
        "contractor"
    ],
    "wof:name":"Phillip's Grading & Paving Co",
    "wof:placetype":"venue"
},
  "geometry": {"coordinates":[-81.065737,33.879431],"type":"Point"}
}