{
  "type": "Feature",
  "properties": {
    "addr:full":"115 Market St Cheraw SC 29520",
    "addr:housenumber":"115",
    "addr:postcode":"29520",
    "addr:street":"Market St",
    "iso:country":"US",
    "sg:address":"115 Market St",
    "sg:city":"Cheraw",
    "sg:classifiers":[
        {
            "category":"Shopping",
            "type":"Retail Goods"
        }
    ],
    "sg:phone":"+1 843 537 2600",
    "sg:postcode":"29520",
    "sg:province":"SC",
    "sg:tags":[
        "picture",
        "frame"
    ],
    "wof:name":"Frame Shop & Gallery",
    "wof:placetype":"venue"
},
  "geometry": {"coordinates":[-79.881613,34.698324],"type":"Point"}
}