{
  "type": "Feature",
  "properties": {
    "iso:country":"US",
    "sg:address":"25 Ray E Talley Ct",
    "sg:city":"Simpsonville",
    "sg:classifiers":[
        {
            "category":"Retail",
            "subcategory":"Car Wash",
            "type":"Services"
        }
    ],
    "sg:phone":"+1 864 228 9808",
    "sg:postcode":"29680",
    "sg:province":"SC",
    "sg:tags":[
        "automobile",
        "detail",
        "clean"
    ],
    "wof:name":"Automotive Excellence Inc",
    "wof:placetype":"venue"
},
  "geometry": {"coordinates":[-82.25536099999999,34.674668],"type":"Point"}
}