{
  "type": "Feature",
  "properties": {
    "addr:full":"947 Broad St Camden SC 29020",
    "addr:housenumber":"947",
    "addr:postcode":"29020",
    "addr:street":"Broad St",
    "iso:country":"US",
    "sg:address":"947 Broad St",
    "sg:city":"Camden",
    "sg:classifiers":[
        {
            "category":"Organizations",
            "subcategory":"Community Association",
            "type":"Services"
        }
    ],
    "sg:phone":"+1 803 432 5321",
    "sg:postcode":"29020",
    "sg:province":"SC",
    "sg:tags":[
        "fraternal"
    ],
    "wof:name":"Camden Tourist Elks Lodge",
    "wof:placetype":"venue"
},
  "geometry": {"coordinates":[-80.606972,34.244474],"type":"Point"}
}