{
  "type": "Feature",
  "properties": {
    "addr:full":"121 N Poinsett Hwy Travelers Rest SC 29690",
    "addr:housenumber":"121",
    "addr:postcode":"29690",
    "addr:street":"N Poinsett Hwy",
    "iso:country":"US",
    "sg:address":"121 N Poinsett Hwy",
    "sg:city":"Travelers Rest",
    "sg:classifiers":[
        {
            "category":"Organizations",
            "subcategory":"Religious Organization",
            "type":"Services"
        }
    ],
    "sg:phone":"+1 864 834 3331",
    "sg:postcode":"29690",
    "sg:province":"SC",
    "sg:tags":[
        "church"
    ],
    "wof:name":"Resurrection Power Ministries",
    "wof:placetype":"venue"
},
  "geometry": {"coordinates":[-82.43604000000001,34.97126],"type":"Point"}
}