{
  "type": "Feature",
  "properties": {
    "iso:country":"US",
    "sg:address":"2728 Depot Rd",
    "sg:city":"Beaufort",
    "sg:classifiers":[
        {
            "category":"Building & Trades",
            "subcategory":"Cleaning & Sanitation",
            "type":"Services"
        }
    ],
    "sg:phone":"+1 843 525 0201",
    "sg:postcode":"29902",
    "sg:province":"SC",
    "sg:tags":[
        "janitor"
    ],
    "wof:name":"Alpha Janitorial Svc",
    "wof:placetype":"venue"
},
  "geometry": {"coordinates":[-80.69259099999999,32.428014],"type":"Point"}
}