{
  "type": "Feature",
  "properties": {
    "addr:full":"101 Westminster Hwy Westminster SC 29693",
    "addr:housenumber":"101",
    "addr:postcode":"29693",
    "addr:street":"Westminster Hwy",
    "iso:country":"US",
    "sg:address":"101 Westminster Hwy",
    "sg:city":"Westminster",
    "sg:classifiers":[
        {
            "category":"Health Services",
            "subcategory":"Dentist",
            "type":"Services"
        }
    ],
    "sg:phone":"+1 864 647 2425",
    "sg:postcode":"29693",
    "sg:province":"SC",
    "sg:tags":[
        "implant",
        "dentistry",
        "dentists-cosmetic",
        "dentists-implantology"
    ],
    "sg:website":"http://www.realpagessites.com/westminsterdental",
    "wof:name":"Westminster Smiles",
    "wof:placetype":"venue"
},
  "geometry": {"coordinates":[-83.10037199999999,34.669064],"type":"Point"}
}