{
  "type": "Feature",
  "properties": {
    "iso:country":"US",
    "sg:address":"2423 Savannah Hwy",
    "sg:city":"Charleston",
    "sg:classifiers":[
        {
            "category":"Retail",
            "subcategory":"Auto Repair",
            "type":"Services"
        }
    ],
    "sg:phone":"+1 843 571 6840",
    "sg:postcode":"29414",
    "sg:province":"SC",
    "sg:tags":[
        "repairing",
        "automobile"
    ],
    "wof:name":"T S Industrial Repair",
    "wof:placetype":"venue"
},
  "geometry": {"coordinates":[-80.04712000000001,32.792552],"type":"Point"}
}