{
  "type": "Feature",
  "properties": {
    "iso:country":"US",
    "sg:address":"1937 W Palmetto St",
    "sg:city":"Florence",
    "sg:classifiers":[
        {
            "category":"Building & Trades",
            "subcategory":"Landscaping Services",
            "type":"Services"
        }
    ],
    "sg:phone":"+1 843 673 1970",
    "sg:postcode":"29501",
    "sg:province":"SC",
    "sg:tags":[
        "lawn",
        "maintenance",
        "grounds"
    ],
    "wof:name":"Lawn Doctor",
    "wof:placetype":"venue"
},
  "geometry": {"coordinates":[-79.804648,34.189398],"type":"Point"}
}