{
  "type": "Feature",
  "properties": {
    "iso:country":"US",
    "sg:address":"3045 Charleston Hwy",
    "sg:city":"West Columbia",
    "sg:classifiers":[
        {
            "category":"Bakery",
            "type":"Food & Drink"
        }
    ],
    "sg:phone":"+1 803 796 4514",
    "sg:postcode":"29172",
    "sg:province":"SC",
    "wof:name":"Sunbeam Bread & Cakes",
    "wof:placetype":"venue"
},
  "geometry": {"coordinates":[-81.07669799999999,33.928398],"type":"Point"}
}