{
  "type": "Feature",
  "properties": {
    "addr:full":"41 Sugaree Dr Bluffton SC 29910",
    "addr:housenumber":"41",
    "addr:postcode":"29910",
    "addr:street":"Sugaree Dr",
    "iso:country":"US",
    "sg:address":"41 Sugaree Dr",
    "sg:city":"Bluffton",
    "sg:classifiers":[
        {
            "category":"Manufacturing",
            "subcategory":"Tools & Machinery",
            "type":"Manufacturing & Wholesale Goods"
        }
    ],
    "sg:phone":"+1 843 706 2020",
    "sg:postcode":"29910",
    "sg:province":"SC",
    "wof:name":"Palmetto Tools Of South Caroli",
    "wof:placetype":"venue"
},
  "geometry": {"coordinates":[-80.874346,32.250167],"type":"Point"}
}