{
  "type": "Feature",
  "properties": {
    "addr:full":"1430 Ribaut Rd Port Royal SC 29935",
    "addr:housenumber":"1430",
    "addr:postcode":"29935",
    "addr:street":"Ribaut Rd",
    "iso:country":"US",
    "sg:address":"1430 Ribaut Rd",
    "sg:city":"Port Royal",
    "sg:classifiers":[
        {
            "category":"Restaurant",
            "type":"Food & Drink"
        }
    ],
    "sg:phone":"+1 843 525 0577",
    "sg:postcode":"29935",
    "sg:province":"SC",
    "sg:tags":[
        "eating"
    ],
    "wof:name":"Ranch Steakhouse Inc",
    "wof:placetype":"venue"
},
  "geometry": {"coordinates":[-80.685509,32.396575],"type":"Point"}
}