{
  "type": "Feature",
  "properties": {
    "iso:country":"US",
    "sg:address":"30 Hampton St",
    "sg:city":"Great Falls",
    "sg:classifiers":[
        {
            "category":"Organizations",
            "subcategory":"Religious Organization",
            "type":"Services"
        }
    ],
    "sg:phone":"+1 803 482 6755",
    "sg:postcode":"29055",
    "sg:province":"SC",
    "sg:tags":[
        "church"
    ],
    "wof:name":"St Peter's Episcopal Church",
    "wof:placetype":"venue"
},
  "geometry": {"coordinates":[-80.89419100000001,34.564476],"type":"Point"}
}