{
  "type": "Feature",
  "properties": {
    "iso:country":"US",
    "sg:address":"200 Commerce St",
    "sg:city":"Manning",
    "sg:classifiers":[
        {
            "category":"Home & Garden",
            "subcategory":"Building Materials",
            "type":"Retail Goods"
        }
    ],
    "sg:phone":"+1 803 435 5050",
    "sg:postcode":"29102",
    "sg:province":"SC",
    "sg:tags":[
        "glass",
        "window",
        "plate"
    ],
    "wof:name":"Turner's Custom Auto Glass",
    "wof:placetype":"venue"
},
  "geometry": {"coordinates":[-80.22323,33.69663],"type":"Point"}
}