{
  "type": "Feature",
  "properties": {
    "iso:country":"US",
    "sg:address":"5960 E Old Marion Hwy",
    "sg:city":"Florence",
    "sg:classifiers":[
        {
            "category":"Organizations",
            "subcategory":"Religious Organization",
            "type":"Services"
        }
    ],
    "sg:phone":"+1 843 669 0133",
    "sg:postcode":"29506",
    "sg:province":"SC",
    "sg:tags":[
        "church"
    ],
    "wof:name":"Bower's Chapel United Meth Chr",
    "wof:placetype":"venue"
},
  "geometry": {"coordinates":[-79.605689,34.208758],"type":"Point"}
}