{
  "type": "Feature",
  "properties": {
    "iso:country":"US",
    "sg:address":"119 Chipwood Ln",
    "sg:city":"Greenville",
    "sg:classifiers":[
        {
            "category":"Building & Trades",
            "subcategory":"Construction",
            "type":"Services"
        }
    ],
    "sg:phone":"+1 864 244 3985",
    "sg:postcode":"29615",
    "sg:province":"SC",
    "sg:tags":[
        "house",
        "builder",
        "operative"
    ],
    "wof:name":"Talley & Talley Builder",
    "wof:placetype":"venue"
},
  "geometry": {"coordinates":[-82.355034,34.880052],"type":"Point"}
}