{
  "type": "Feature",
  "properties": {
    "addr:full":"530 Mills Ave Greenville SC 29605",
    "addr:housenumber":"530",
    "addr:postcode":"29605",
    "addr:street":"Mills Ave",
    "iso:country":"US",
    "sg:address":"530 Mills Ave",
    "sg:city":"Greenville",
    "sg:classifiers":[
        {
            "category":"Professional",
            "subcategory":"Accounting & Tax Preparation",
            "type":"Services"
        }
    ],
    "sg:phone":"+1 864 271 7695",
    "sg:postcode":"29605",
    "sg:province":"SC",
    "sg:tags":[
        "return",
        "filing"
    ],
    "wof:name":"M & M Income Tax Svc",
    "wof:placetype":"venue"
},
  "geometry": {"coordinates":[-82.412778,34.824101],"type":"Point"}
}