{
  "type": "Feature",
  "properties": {
    "iso:country":"US",
    "sg:address":"4490 Boatshore Rd",
    "sg:city":"Rock Hill",
    "sg:classifiers":[
        {
            "category":"Recreation",
            "type":"Entertainment"
        }
    ],
    "sg:phone":"+1 803 366 6620",
    "sg:postcode":"29732",
    "sg:province":"SC",
    "sg:tags":[
        "parks"
    ],
    "wof:name":"Ebenezer Park",
    "wof:placetype":"venue"
},
  "geometry": {"coordinates":[-81.04280900000001,35.021141],"type":"Point"}
}