{
  "type": "Feature",
  "properties": {
    "iso:country":"US",
    "sg:address":"1009 Market St",
    "sg:city":"Camden",
    "sg:classifiers":[
        {
            "category":"Banks & Credit Unions",
            "subcategory":"Bank",
            "type":"Services"
        }
    ],
    "sg:phone":"+1 803 432 8411",
    "sg:postcode":"29020",
    "sg:province":"SC",
    "sg:tags":[
        "loan"
    ],
    "wof:name":"World Finance Corp Of Camden",
    "wof:placetype":"venue"
},
  "geometry": {"coordinates":[-80.60507800000001,34.24636],"type":"Point"}
}