{
  "type": "Feature",
  "properties": {
    "iso:country":"US",
    "sg:address":"162 Heber Ln",
    "sg:city":"Lexington",
    "sg:classifiers":[
        {
            "category":"Building & Trades",
            "subcategory":"Construction",
            "type":"Services"
        }
    ],
    "sg:phone":"+1 803 518 0991",
    "sg:postcode":"29072",
    "sg:province":"SC",
    "sg:tags":[
        "house"
    ],
    "wof:name":"Thornton Construction",
    "wof:placetype":"venue"
},
  "geometry": {"coordinates":[-81.312372,33.993265],"type":"Point"}
}