{
  "type": "Feature",
  "properties": {
    "addr:full":"541 John C Calhoun Dr Orangeburg SC 29115",
    "addr:housenumber":"541",
    "addr:postcode":"29115",
    "addr:street":"John C Calhoun Dr",
    "iso:country":"US",
    "sg:address":"541 John C Calhoun Dr",
    "sg:city":"Orangeburg",
    "sg:classifiers":[
        {
            "category":"Home & Garden",
            "subcategory":"Building Materials",
            "type":"Retail Goods"
        }
    ],
    "sg:phone":"+1 803 531 1172",
    "sg:postcode":"29115",
    "sg:province":"SC",
    "sg:tags":[
        "glass",
        "window",
        "plate"
    ],
    "wof:name":"Auto Glass Works",
    "wof:placetype":"venue"
},
  "geometry": {"coordinates":[-80.849912,33.490633],"type":"Point"}
}