{
  "type": "Feature",
  "properties": {
    "iso:country":"US",
    "sg:address":"113 W Main St",
    "sg:city":"Union",
    "sg:classifiers":[
        {
            "category":"Shopping",
            "subcategory":"Used Merchandise",
            "type":"Retail Goods"
        }
    ],
    "sg:phone":"+1 864 427 1605",
    "sg:postcode":"29379",
    "sg:province":"SC",
    "wof:name":"Reflections Boutique",
    "wof:placetype":"venue"
},
  "geometry": {"coordinates":[-81.624852,34.71507],"type":"Point"}
}