{
  "type": "Feature",
  "properties": {
    "addr:full":"2346 Oliver Rd Timmonsville SC 29161",
    "addr:housenumber":"2346",
    "addr:postcode":"29161",
    "addr:street":"Oliver Rd",
    "iso:country":"US",
    "sg:address":"2346 Oliver Rd",
    "sg:city":"Timmonsville",
    "sg:classifiers":[
        {
            "category":"Building & Trades",
            "subcategory":"Construction",
            "type":"Services"
        }
    ],
    "sg:phone":"+1 843 665 2816",
    "sg:postcode":"29161",
    "sg:province":"SC",
    "sg:tags":[
        "builder",
        "operative"
    ],
    "wof:name":"Teddy Dowling Construction",
    "wof:placetype":"venue"
},
  "geometry": {"coordinates":[-79.834834,34.148115],"type":"Point"}
}