{
  "type": "Feature",
  "properties": {
    "addr:full":"204 Evans St Westminster SC 29693",
    "addr:housenumber":"204",
    "addr:postcode":"29693",
    "addr:street":"Evans St",
    "iso:country":"US",
    "sg:address":"204 Evans St",
    "sg:city":"Westminster",
    "sg:classifiers":[
        {
            "category":"Manufacturing",
            "subcategory":"Retail Goods",
            "type":"Manufacturing & Wholesale Goods"
        }
    ],
    "sg:phone":"+1 864 647 8717",
    "sg:postcode":"29693",
    "sg:province":"SC",
    "sg:tags":[
        "product",
        "mfg"
    ],
    "wof:name":"WC Tidwell",
    "wof:placetype":"venue"
},
  "geometry": {"coordinates":[-83.105609,34.672651],"type":"Point"}
}