{
  "type": "Feature",
  "properties": {
    "iso:country":"US",
    "sg:address":"204 Evans St",
    "sg:city":"Westminster",
    "sg:classifiers":[
        {
            "category":"Manufacturing",
            "subcategory":"Retail Goods",
            "type":"Manufacturing & Wholesale Goods"
        }
    ],
    "sg:phone":"+1 864 647 8717",
    "sg:postcode":"29693",
    "sg:province":"SC",
    "sg:tags":[
        "product",
        "mfg"
    ],
    "wof:name":"WC Tidwell",
    "wof:placetype":"venue"
},
  "geometry": {"coordinates":[-83.105609,34.672651],"type":"Point"}
}