{
  "type": "Feature",
  "properties": {
    "addr:full":"102 E Shepard Ln Summerville SC 29483",
    "addr:housenumber":"102",
    "addr:postcode":"29483",
    "addr:street":"E Shepard Ln",
    "iso:country":"US",
    "sg:address":"102 E Shepard Ln",
    "sg:city":"Summerville",
    "sg:classifiers":[
        {
            "category":"Real Estate",
            "subcategory":"Real Estate Agent",
            "type":"Services"
        },
        {
            "category":"Real Estate",
            "subcategory":"Real Estate Operator",
            "type":"Services"
        }
    ],
    "sg:phone":"+1 843 871 1101",
    "sg:postcode":"29483",
    "sg:province":"SC",
    "sg:tags":[
        "building",
        "nonresidential"
    ],
    "wof:name":"Elite Southern Properties LLC",
    "wof:placetype":"venue"
},
  "geometry": {"coordinates":[-80.194579,32.99965],"type":"Point"}
}