{
  "type": "Feature",
  "properties": {
    "addr:full":"1 S Park Cir Charleston SC 29407",
    "addr:housenumber":"1",
    "addr:postcode":"29407",
    "addr:street":"S Park Cir",
    "iso:country":"US",
    "sg:address":"1 S Park Cir",
    "sg:city":"Charleston",
    "sg:classifiers":[
        {
            "category":"Insurance",
            "subcategory":"Life Insurance",
            "type":"Services"
        }
    ],
    "sg:phone":"+1 843 763 2500",
    "sg:postcode":"29407",
    "sg:province":"SC",
    "sg:tags":[
        "carrier"
    ],
    "wof:name":"MetLife",
    "wof:placetype":"venue"
},
  "geometry": {"coordinates":[-80.03027899999999,32.794063],"type":"Point"}
}