{
  "type": "Feature",
  "properties": {
    "addr:full":"2500 Kneece Rd Columbia SC 29223",
    "addr:housenumber":"2500",
    "addr:postcode":"29223",
    "addr:street":"Kneece Rd",
    "iso:country":"US",
    "sg:address":"2500 Kneece Rd",
    "sg:city":"Columbia",
    "sg:classifiers":[
        {
            "category":"Building & Trades",
            "subcategory":"Plumbing",
            "type":"Services"
        }
    ],
    "sg:phone":"+1 803 699 8903",
    "sg:postcode":"29223",
    "sg:province":"SC",
    "sg:tags":[
        "plumbing",
        "contractor"
    ],
    "wof:name":"Progressive Plumbing",
    "wof:placetype":"venue"
},
  "geometry": {"coordinates":[-80.94703199999999,34.059386],"type":"Point"}
}