{
  "type": "Feature",
  "properties": {
    "addr:full":"1489 Sumner Ave Charleston SC 29406",
    "addr:housenumber":"1489",
    "addr:postcode":"29406",
    "addr:street":"Sumner Ave",
    "iso:country":"US",
    "sg:address":"1489 Sumner Ave",
    "sg:city":"Charleston",
    "sg:classifiers":[
        {
            "category":"Food & Beverages",
            "subcategory":"Groceries & Convenience Stores",
            "type":"Retail Goods"
        }
    ],
    "sg:phone":"+1 843 745 9644",
    "sg:postcode":"29406",
    "sg:province":"SC",
    "wof:name":"North Corner",
    "wof:placetype":"venue"
},
  "geometry": {"coordinates":[-80.000793,32.897178],"type":"Point"}
}