{
  "type": "Feature",
  "properties": {
    "iso:country":"US",
    "sg:address":"330 Old Hunts Bridge Rd",
    "sg:city":"Greenville",
    "sg:classifiers":[
        {
            "category":"Building & Trades",
            "subcategory":"Construction",
            "type":"Services"
        }
    ],
    "sg:phone":"+1 864 246 3090",
    "sg:postcode":"29617",
    "sg:province":"SC",
    "sg:tags":[
        "cabinet",
        "finish",
        "maker",
        "carpentry"
    ],
    "wof:name":"K & L Cabinet Works",
    "wof:placetype":"venue"
},
  "geometry": {"coordinates":[-82.479673,34.920606],"type":"Point"}
}