{
  "type": "Feature",
  "properties": {
    "iso:country":"US",
    "sg:address":"118 Commerce Cir E",
    "sg:city":"Greenwood",
    "sg:classifiers":[
        {
            "category":"Home & Garden",
            "subcategory":"Furniture",
            "type":"Retail Goods"
        }
    ],
    "sg:phone":"+1 864 223 7300",
    "sg:postcode":"29646",
    "sg:province":"SC",
    "wof:name":"Furniture Discount Warehouse",
    "wof:placetype":"venue"
},
  "geometry": {"coordinates":[-82.13489199999999,34.206008],"type":"Point"}
}