{
  "type": "Feature",
  "properties": {
    "addr:full":"718 Wappoo Rd Charleston SC 29407",
    "addr:housenumber":"718",
    "addr:postcode":"29407",
    "addr:street":"Wappoo Rd",
    "iso:country":"US",
    "sg:address":"718 Wappoo Rd",
    "sg:city":"Charleston",
    "sg:classifiers":[
        {
            "category":"Professional",
            "subcategory":"Employment Agencies",
            "type":"Services"
        }
    ],
    "sg:phone":"+1 843 556 0303",
    "sg:postcode":"29407",
    "sg:province":"SC",
    "sg:tags":[
        "medical"
    ],
    "wof:name":"ATC Healthcare Svc",
    "wof:placetype":"venue"
},
  "geometry": {"coordinates":[-80.019549,32.79121],"type":"Point"}
}