{
  "type": "Feature",
  "properties": {
    "addr:full":"807 Gervais St Columbia SC 29201",
    "addr:housenumber":"807",
    "addr:postcode":"29201",
    "addr:street":"Gervais St",
    "iso:country":"US",
    "sg:address":"807 Gervais St",
    "sg:city":"Columbia",
    "sg:classifiers":[
        {
            "category":"Professional",
            "subcategory":"Management & Consulting",
            "type":"Services"
        }
    ],
    "sg:phone":"+1 803 771 0325",
    "sg:postcode":"29201",
    "sg:province":"SC",
    "sg:tags":[
        "counselor",
        "public",
        "relations"
    ],
    "sg:website":"www.sunrisepr.com",
    "wof:name":"Sunrise Enterprise Of Columbia",
    "wof:placetype":"venue"
},
  "geometry": {"coordinates":[-81.038661,33.999787],"type":"Point"}
}