{
  "type": "Feature",
  "properties": {
    "addr:full":"5616 Calhoun Memorial Hwy Easley SC 29640",
    "addr:housenumber":"5616",
    "addr:postcode":"29640",
    "addr:street":"Calhoun Memorial Hwy",
    "iso:country":"US",
    "sg:address":"5616 Calhoun Memorial Hwy",
    "sg:city":"Easley",
    "sg:classifiers":[
        {
            "category":"Restaurant",
            "type":"Food & Drink"
        }
    ],
    "sg:phone":"+1 864 855 3990",
    "sg:postcode":"29640",
    "sg:province":"SC",
    "sg:tags":[
        "pizza",
        "italian"
    ],
    "wof:name":"Fratelli's Pizza & Pasta",
    "wof:placetype":"venue"
},
  "geometry": {"coordinates":[-82.568307,34.826049],"type":"Point"}
}