{
  "type": "Feature",
  "properties": {
    "iso:country":"US",
    "sg:address":"419 S 5th St",
    "sg:city":"Hartsville",
    "sg:classifiers":[
        {
            "category":"Banks & Credit Unions",
            "subcategory":"Bank",
            "type":"Services"
        }
    ],
    "sg:phone":"+1 843 383 5610",
    "sg:postcode":"29550",
    "sg:province":"SC",
    "sg:tags":[
        "depository",
        "banking",
        "check",
        "cashing"
    ],
    "wof:name":"Commercial Check Cashings",
    "wof:placetype":"venue"
},
  "geometry": {"coordinates":[-80.068658,34.366203],"type":"Point"}
}