{
  "type": "Feature",
  "properties": {
    "iso:country":"US",
    "sg:address":"2335 Wilkinsville Hwy",
    "sg:city":"Gaffney",
    "sg:classifiers":[
        {
            "category":"Building & Trades",
            "subcategory":"Construction",
            "type":"Services"
        }
    ],
    "sg:phone":"+1 864 489 3630",
    "sg:postcode":"29340",
    "sg:province":"SC",
    "sg:tags":[
        "house"
    ],
    "wof:name":"Sam Cole Const",
    "wof:placetype":"venue"
},
  "geometry": {"coordinates":[-81.579132,35.027373],"type":"Point"}
}