{
  "type": "Feature",
  "properties": {
    "iso:country":"US",
    "sg:address":"6217 Monticello Rd",
    "sg:city":"Columbia",
    "sg:classifiers":[
        {
            "category":"Autos & Motor Vehicles",
            "subcategory":"Automobile Sales",
            "type":"Retail Goods"
        }
    ],
    "sg:phone":"+1 803 735 0149",
    "sg:postcode":"29203",
    "sg:province":"SC",
    "sg:tags":[
        "car",
        "dealer"
    ],
    "wof:name":"Newsome Chevrolet Parts Wrhse",
    "wof:placetype":"venue"
},
  "geometry": {"coordinates":[-81.05504999999999,34.068166],"type":"Point"}
}