{
  "type": "Feature",
  "properties": {
    "addr:full":"719 Bryant Rd Inman SC 29349",
    "addr:housenumber":"719",
    "addr:postcode":"29349",
    "addr:street":"Bryant Rd",
    "iso:country":"US",
    "sg:address":"719 Bryant Rd",
    "sg:city":"Inman",
    "sg:classifiers":[
        {
            "category":"Shopping",
            "subcategory":"Hobbies, Toys, & Games",
            "type":"Retail Goods"
        }
    ],
    "sg:phone":"+1 864 487 3777",
    "sg:postcode":"29349",
    "sg:province":"SC",
    "sg:tags":[
        "model",
        "supply"
    ],
    "wof:name":"Carolina Hobbies",
    "wof:placetype":"venue"
},
  "geometry": {"coordinates":[-82.04356799999999,35.032789],"type":"Point"}
}