{
  "type": "Feature",
  "properties": {
    "iso:country":"US",
    "sg:address":"1318 Donaldson Rd",
    "sg:city":"Greenville",
    "sg:classifiers":[
        {
            "category":"Retail",
            "subcategory":"Repair Shop",
            "type":"Services"
        }
    ],
    "sg:phone":"+1 864 299 0333",
    "sg:postcode":"29605",
    "sg:province":"SC",
    "sg:tags":[
        "ironwork"
    ],
    "wof:name":"Frank's Ornamental Iron Works",
    "wof:placetype":"venue"
},
  "geometry": {"coordinates":[-82.386887,34.753347],"type":"Point"}
}