{
  "type": "Feature",
  "properties": {
    "iso:country":"US",
    "sg:address":"389 E Henry St",
    "sg:city":"Spartanburg",
    "sg:classifiers":[
        {
            "category":"Insurance",
            "subcategory":"Insurance Agent",
            "type":"Services"
        }
    ],
    "sg:phone":"+1 864 585 0251",
    "sg:postcode":"29302",
    "sg:province":"SC",
    "wof:name":"Judy Agency",
    "wof:placetype":"venue"
},
  "geometry": {"coordinates":[-81.91921499999999,34.948565],"type":"Point"}
}