{
  "type": "Feature",
  "properties": {
    "iso:country":"US",
    "sg:address":"364 Calvary Rd",
    "sg:city":"Cheraw",
    "sg:classifiers":[
        {
            "category":"Organizations",
            "subcategory":"Religious Organization",
            "type":"Services"
        }
    ],
    "sg:phone":"+1 843 537 1100",
    "sg:postcode":"29520",
    "sg:province":"SC",
    "sg:tags":[
        "church"
    ],
    "sg:website":"www.cbc-cheraw.org",
    "wof:name":"Calvary Baptist Church",
    "wof:placetype":"venue"
},
  "geometry": {"coordinates":[-79.928605,34.693534],"type":"Point"}
}