{
  "type": "Feature",
  "properties": {
    "addr:full":"1410 N Waccamaw Dr Murrells Inlet SC 29576",
    "addr:housenumber":"1410",
    "addr:postcode":"29576",
    "addr:street":"N Waccamaw Dr",
    "iso:country":"US",
    "sg:address":"1410 N Waccamaw Dr",
    "sg:city":"Murrells Inlet",
    "sg:classifiers":[
        {
            "category":"Organizations",
            "subcategory":"Professional Association",
            "type":"Services"
        }
    ],
    "sg:phone":"+1 843 651 9265",
    "sg:postcode":"29576",
    "sg:province":"SC",
    "wof:name":"Portofino HOA",
    "wof:placetype":"venue"
},
  "geometry": {"coordinates":[-78.988967,33.587554],"type":"Point"}
}