{
  "type": "Feature",
  "properties": {
    "addr:full":"250 Handy Hill Dr Georgetown SC 29440",
    "addr:housenumber":"250",
    "addr:postcode":"29440",
    "addr:street":"Handy Hill Dr",
    "iso:country":"US",
    "sg:address":"250 Handy Hill Dr",
    "sg:city":"Georgetown",
    "sg:classifiers":[
        {
            "category":"Building & Trades",
            "subcategory":"Landscaping Services",
            "type":"Services"
        }
    ],
    "sg:phone":"+1 843 527 4065",
    "sg:postcode":"29440",
    "sg:province":"SC",
    "sg:tags":[
        "lawn",
        "care"
    ],
    "wof:name":"Rice Landscape",
    "wof:placetype":"venue"
},
  "geometry": {"coordinates":[-79.35589299999999,33.534766],"type":"Point"}
}