{
  "type": "Feature",
  "properties": {
    "addr:full":"210 Shuler Rd Columbia SC 29212",
    "addr:housenumber":"210",
    "addr:postcode":"29212",
    "addr:street":"Shuler Rd",
    "iso:country":"US",
    "sg:address":"210 Shuler Rd",
    "sg:city":"Columbia",
    "sg:classifiers":[
        {
            "category":"Manufacturing",
            "subcategory":"Metals",
            "type":"Manufacturing & Wholesale Goods"
        }
    ],
    "sg:phone":"+1 803 732 9445",
    "sg:postcode":"29212",
    "sg:province":"SC",
    "sg:tags":[
        "fiber",
        "optics",
        "system"
    ],
    "wof:name":"Fiber Link LLC",
    "wof:placetype":"venue"
},
  "geometry": {"coordinates":[-81.230009,34.06854],"type":"Point"}
}