{
  "type": "Feature",
  "properties": {
    "iso:country":"US",
    "sg:address":"402 N Cedar St",
    "sg:city":"Summerville",
    "sg:classifiers":[
        {
            "category":"Restaurant",
            "type":"Food & Drink"
        }
    ],
    "sg:phone":"+1 843 832 1717",
    "sg:postcode":"29483",
    "sg:province":"SC",
    "wof:name":"El Rosarito",
    "wof:placetype":"venue"
},
  "geometry": {"coordinates":[-80.172962,33.026119],"type":"Point"}
}