{
  "type": "Feature",
  "properties": {
    "iso:country":"US",
    "sg:address":"303 Twin Lakes Dr",
    "sg:city":"Summerville",
    "sg:classifiers":[
        {
            "category":"Home & Garden",
            "subcategory":"Building Materials",
            "type":"Retail Goods"
        }
    ],
    "sg:phone":"+1 843 832 4304",
    "sg:postcode":"29483",
    "sg:province":"SC",
    "sg:tags":[
        "door"
    ],
    "wof:name":"All About Garage Doors & Oper",
    "wof:placetype":"venue"
},
  "geometry": {"coordinates":[-80.270169,33.002042],"type":"Point"}
}