{
  "type": "Feature",
  "properties": {
    "addr:full":"110 Pisgah Church Rd Columbia SC 29203",
    "addr:housenumber":"110",
    "addr:postcode":"29203",
    "addr:street":"Pisgah Church Rd",
    "iso:country":"US",
    "sg:address":"110 Pisgah Church Rd",
    "sg:city":"Columbia",
    "sg:classifiers":[
        {
            "category":"Organizations",
            "subcategory":"Religious Organization",
            "type":"Services"
        }
    ],
    "sg:phone":"+1 803 699 9946",
    "sg:postcode":"29203",
    "sg:province":"SC",
    "sg:tags":[
        "church"
    ],
    "wof:name":"ADAMS Northeast AME Church",
    "wof:placetype":"venue"
},
  "geometry": {"coordinates":[-80.97195000000001,34.09484],"type":"Point"}
}