{
  "type": "Feature",
  "properties": {
    "iso:country":"US",
    "sg:address":"964 E Liberty St",
    "sg:city":"York",
    "sg:classifiers":[
        {
            "category":"Shopping",
            "subcategory":"Clothing, Apparel, & Fashions",
            "type":"Retail Goods"
        }
    ],
    "sg:phone":"+1 803 684 4997",
    "sg:postcode":"29745",
    "sg:province":"SC",
    "wof:name":"Cato",
    "wof:placetype":"venue"
},
  "geometry": {"coordinates":[-81.212913,34.985436],"type":"Point"}
}