{
  "type": "Feature",
  "properties": {
    "iso:country":"US",
    "sg:address":"1326 E Main St",
    "sg:city":"Rock Hill",
    "sg:classifiers":[
        {
            "category":"Professional",
            "subcategory":"Art Services",
            "type":"Services"
        }
    ],
    "sg:phone":"+1 803 327 9125",
    "sg:postcode":"29730",
    "sg:province":"SC",
    "sg:tags":[
        "photographer"
    ],
    "wof:name":"Roueche Photography Studio",
    "wof:placetype":"venue"
},
  "geometry": {"coordinates":[-81.00153,34.916165],"type":"Point"}
}