{
  "type": "Feature",
  "properties": {
    "iso:country":"US",
    "sg:address":"1160 Magnolia St",
    "sg:city":"Orangeburg",
    "sg:classifiers":[
        {
            "category":"Personal",
            "subcategory":"Beauty Salon",
            "type":"Services"
        }
    ],
    "sg:phone":"+1 803 536 0400",
    "sg:postcode":"29115",
    "sg:province":"SC",
    "wof:name":"Heaven's Touch Unisex Barber",
    "wof:placetype":"venue"
},
  "geometry": {"coordinates":[-80.85283,33.478709],"type":"Point"}
}