{
  "type": "Feature",
  "properties": {
    "addr:full":"101 Tyson Ave Bennettsville SC 29512",
    "addr:housenumber":"101",
    "addr:postcode":"29512",
    "addr:street":"Tyson Ave",
    "iso:country":"US",
    "sg:address":"101 Tyson Ave",
    "sg:city":"Bennettsville",
    "sg:classifiers":[
        {
            "category":"Farming",
            "subcategory":"Farm",
            "type":"Manufacturing & Wholesale Goods"
        }
    ],
    "sg:phone":"+1 843 523 6351",
    "sg:postcode":"29512",
    "sg:province":"SC",
    "sg:tags":[
        "crop",
        "general"
    ],
    "wof:name":"Hinson WA Farm",
    "wof:placetype":"venue"
},
  "geometry": {"coordinates":[-79.670677,34.622564],"type":"Point"}
}