{
  "type": "Feature",
  "properties": {
    "iso:country":"US",
    "sg:address":"839 Powdersville Rd",
    "sg:city":"Easley",
    "sg:classifiers":[
        {
            "category":"Retail",
            "subcategory":"Car Wash",
            "type":"Services"
        }
    ],
    "sg:phone":"+1 864 442 0081",
    "sg:postcode":"29642",
    "sg:province":"SC",
    "sg:tags":[
        "polishing",
        "washing"
    ],
    "wof:name":"Squeaky Clean Auto Wash",
    "wof:placetype":"venue"
},
  "geometry": {"coordinates":[-82.554358,34.817258],"type":"Point"}
}