{
  "type": "Feature",
  "properties": {
    "iso:country":"US",
    "sg:address":"3585 Boiling Springs Rd",
    "sg:city":"Spartanburg",
    "sg:classifiers":[
        {
            "category":"Freight",
            "type":"Transportation"
        }
    ],
    "sg:phone":"+1 864 578 6415",
    "sg:postcode":"29316",
    "sg:province":"SC",
    "sg:tags":[
        "trucking"
    ],
    "wof:name":"Lathan Brothers Trucking Co",
    "wof:placetype":"venue"
},
  "geometry": {"coordinates":[-81.98069099999999,35.044816],"type":"Point"}
}