{
  "type": "Feature",
  "properties": {
    "addr:full":"1416 Lagoon Park Cir Mount Pleasant SC 29466",
    "addr:housenumber":"1416",
    "addr:postcode":"29466",
    "addr:street":"Lagoon Park Cir",
    "iso:country":"US",
    "sg:address":"1416 Lagoon Park Cir",
    "sg:city":"Mount Pleasant",
    "sg:classifiers":[
        {
            "category":"Building & Trades",
            "subcategory":"Construction",
            "type":"Services"
        }
    ],
    "sg:phone":"+1 843 856 3658",
    "sg:postcode":"29466",
    "sg:province":"SC",
    "sg:tags":[
        "house"
    ],
    "wof:name":"GF Herrman Builders",
    "wof:placetype":"venue"
},
  "geometry": {"coordinates":[-79.779719,32.851608],"type":"Point"}
}