{
  "type": "Feature",
  "properties": {
    "addr:full":"2466 Wagener Rd Aiken SC 29801",
    "addr:housenumber":"2466",
    "addr:postcode":"29801",
    "addr:street":"Wagener Rd",
    "iso:country":"US",
    "sg:address":"2466 Wagener Rd",
    "sg:city":"Aiken",
    "sg:classifiers":[
        {
            "category":"Bars & Pubs",
            "type":"Food & Drink"
        }
    ],
    "sg:phone":"+1 803 649 5915",
    "sg:postcode":"29801",
    "sg:province":"SC",
    "sg:tags":[
        "lounge",
        "cocktail"
    ],
    "wof:name":"Ray's Tavern",
    "wof:placetype":"venue"
},
  "geometry": {"coordinates":[-81.679186,33.546411],"type":"Point"}
}