{
  "type": "Feature",
  "properties": {
    "addr:full":"148 Etiwan Park St Charleston SC 29492",
    "addr:housenumber":"148",
    "addr:postcode":"29492",
    "addr:street":"Etiwan Park St",
    "iso:country":"US",
    "sg:address":"148 Etiwan Park St",
    "sg:city":"Charleston",
    "sg:classifiers":[
        {
            "category":"Building & Trades",
            "subcategory":"Construction",
            "type":"Services"
        }
    ],
    "sg:phone":"+1 843 881 2212",
    "sg:postcode":"29492",
    "sg:province":"SC",
    "sg:tags":[
        "hanging",
        "contractor"
    ],
    "wof:name":"Koozer Painting",
    "wof:placetype":"venue"
},
  "geometry": {"coordinates":[-79.915176,32.858346],"type":"Point"}
}