{
  "type": "Feature",
  "properties": {
    "addr:full":"1621 Lake Murray Blvd Columbia SC 29212",
    "addr:housenumber":"1621",
    "addr:postcode":"29212",
    "addr:street":"Lake Murray Blvd",
    "iso:country":"US",
    "sg:address":"1621 Lake Murray Blvd",
    "sg:city":"Columbia",
    "sg:classifiers":[
        {
            "category":"Shopping",
            "subcategory":"Discount & Variety Stores",
            "type":"Retail Goods"
        }
    ],
    "sg:phone":"+1 803 732 5895",
    "sg:postcode":"29212",
    "sg:province":"SC",
    "sg:tags":[
        "merchandise",
        "general"
    ],
    "wof:name":"Schwan's Sales Enterprises",
    "wof:placetype":"venue"
},
  "geometry": {"coordinates":[-81.192814,34.082121],"type":"Point"}
}