{
  "type": "Feature",
  "properties": {
    "iso:country":"US",
    "sg:address":"221 Oakmont Dr",
    "sg:city":"Spartanburg",
    "sg:classifiers":[
        {
            "category":"Manufacturing",
            "subcategory":"Food",
            "type":"Manufacturing & Wholesale Goods"
        }
    ],
    "sg:phone":"+1 864 599 7862",
    "sg:postcode":"29316",
    "sg:province":"SC",
    "sg:tags":[
        "product",
        "mfg"
    ],
    "wof:name":"Best Foods Baking",
    "wof:placetype":"venue"
},
  "geometry": {"coordinates":[-81.999642,35.014234],"type":"Point"}
}