{
  "type": "Feature",
  "properties": {
    "addr:full":"210 S Main St Darlington SC 29532",
    "addr:housenumber":"210",
    "addr:postcode":"29532",
    "addr:street":"S Main St",
    "iso:country":"US",
    "sg:address":"210 S Main St",
    "sg:city":"Darlington",
    "sg:classifiers":[
        {
            "category":"Organizations",
            "subcategory":"Religious Organization",
            "type":"Services"
        }
    ],
    "sg:phone":"+1 843 393 4112",
    "sg:postcode":"29532",
    "sg:province":"SC",
    "sg:tags":[
        "church"
    ],
    "wof:name":"St Matthews Episcopal Church",
    "wof:placetype":"venue"
},
  "geometry": {"coordinates":[-79.869361,34.300489],"type":"Point"}
}