{
  "type": "Feature",
  "properties": {
    "addr:full":"690 Country Club Dr Conway SC 29526",
    "addr:housenumber":"690",
    "addr:postcode":"29526",
    "addr:street":"Country Club Dr",
    "iso:country":"US",
    "sg:address":"690 Country Club Dr",
    "sg:city":"Conway",
    "sg:classifiers":[
        {
            "category":"Professional",
            "subcategory":"Accounting & Tax Preparation",
            "type":"Services"
        }
    ],
    "sg:phone":"+1 843 488 5768",
    "sg:postcode":"29526",
    "sg:province":"SC",
    "sg:tags":[
        "bookkeeping",
        "general"
    ],
    "wof:name":"Benton & Tanner Bookkeeping",
    "wof:placetype":"venue"
},
  "geometry": {"coordinates":[-79.048907,33.866935],"type":"Point"}
}