{
  "type": "Feature",
  "properties": {
    "iso:country":"US",
    "sg:address":"942 Folly Rd",
    "sg:city":"Charleston",
    "sg:classifiers":[
        {
            "category":"Organizations",
            "subcategory":"Religious Organization",
            "type":"Services"
        }
    ],
    "sg:phone":"+1 843 762 1718",
    "sg:postcode":"29412",
    "sg:province":"SC",
    "sg:tags":[
        "church"
    ],
    "wof:name":"Calvary Baptist Church",
    "wof:placetype":"venue"
},
  "geometry": {"coordinates":[-79.968823,32.73117],"type":"Point"}
}