{
  "type": "Feature",
  "properties": {
    "iso:country":"US",
    "sg:address":"946 Atomic Rd",
    "sg:city":"North Augusta",
    "sg:classifiers":[
        {
            "category":"Autos & Motor Vehicles",
            "subcategory":"Automobile Sales",
            "type":"Retail Goods"
        },
        {
            "category":"Retail",
            "subcategory":"Auto Repair",
            "type":"Services"
        }
    ],
    "sg:phone":"+1 803 279 7887",
    "sg:postcode":"29841",
    "sg:province":"SC",
    "sg:tags":[
        "repairing",
        "used"
    ],
    "wof:name":"B & B Imported Cars Inc",
    "wof:placetype":"venue"
},
  "geometry": {"coordinates":[-81.939392,33.494295],"type":"Point"}
}