{
  "type": "Feature",
  "properties": {
    "iso:country":"US",
    "sg:address":"7360 Cross County Road Suite 103",
    "sg:city":"Charleston",
    "sg:classifiers":[
        {
            "category":"Professional",
            "subcategory":"Computer Services",
            "type":"Services"
        }
    ],
    "sg:phone":"+1 800 899 6272",
    "sg:postcode":"29418",
    "sg:province":"SC",
    "sg:tags":[
        "plastic-signs",
        "metal-sign",
        "outdoor-signage",
        "online-design",
        "custom-signs",
        "vinyl-signage",
        "wall-signs",
        "custom-banners",
        "real-estate-signs"
    ],
    "sg:website":"http://www.SignsUS.com",
    "wof:name":"SignsUS.com",
    "wof:placetype":"venue"
},
  "geometry": {"coordinates":[-80.07132300000001,32.925794],"type":"Point"}
}