{
  "type": "Feature",
  "properties": {
    "addr:full":"252 Rainbow Dr Salley SC 29137",
    "addr:housenumber":"252",
    "addr:postcode":"29137",
    "addr:street":"Rainbow Dr",
    "iso:country":"US",
    "sg:address":"252 Rainbow Dr",
    "sg:city":"Salley",
    "sg:classifiers":[
        {
            "category":"Organizations",
            "subcategory":"Religious Organization",
            "type":"Services"
        }
    ],
    "sg:phone":"+1 803 258 3042",
    "sg:postcode":"29137",
    "sg:province":"SC",
    "sg:tags":[
        "church"
    ],
    "wof:name":"Sardis Baptist Church",
    "wof:placetype":"venue"
},
  "geometry": {"coordinates":[-81.304332,33.650326],"type":"Point"}
}