{
  "type": "Feature",
  "properties": {
    "addr:full":"109 S Main St Woodruff SC 29388",
    "addr:housenumber":"109",
    "addr:postcode":"29388",
    "addr:street":"S Main St",
    "iso:country":"US",
    "sg:address":"109 S Main St",
    "sg:city":"Woodruff",
    "sg:classifiers":[
        {
            "category":"Personal",
            "type":"Services"
        }
    ],
    "sg:phone":"+1 864 476 2223",
    "sg:postcode":"29388",
    "sg:province":"SC",
    "sg:tags":[
        "therapist",
        "massage"
    ],
    "wof:name":"A Bodywise Choice Massage",
    "wof:placetype":"venue"
},
  "geometry": {"coordinates":[-82.03707799999999,34.739721],"type":"Point"}
}