{
  "type": "Feature",
  "properties": {
    "iso:country":"US",
    "sg:address":"967 Folly Rd",
    "sg:city":"Charleston",
    "sg:classifiers":[
        {
            "category":"Restaurant",
            "type":"Food & Drink"
        }
    ],
    "sg:menulink":"http://www.allmenus.com/sc/james-island/54132-juanita-greenbergs/menu/",
    "sg:phone":"+1 843 576 6224",
    "sg:postcode":"29412",
    "sg:province":"SC",
    "sg:tags":[
        "mexican"
    ],
    "wof:name":"Juanita Greenberg's",
    "wof:placetype":"venue"
},
  "geometry": {"coordinates":[-79.968891,32.731266],"type":"Point"}
}