{
  "type": "Feature",
  "properties": {
    "iso:country":"US",
    "sg:address":"428 Wilson Rd",
    "sg:city":"Newberry",
    "sg:classifiers":[
        {
            "category":"Personal",
            "subcategory":"Barber",
            "type":"Services"
        }
    ],
    "sg:phone":"+1 803 276 9098",
    "sg:postcode":"29108",
    "sg:province":"SC",
    "wof:name":"Cuttin Up Family Hair Cutting",
    "wof:placetype":"venue"
},
  "geometry": {"coordinates":[-81.589544,34.271058],"type":"Point"}
}