{
  "type": "Feature",
  "properties": {
    "addr:full":"6212 Ranch Rd Wadmalaw Island SC 29487",
    "addr:housenumber":"6212",
    "addr:postcode":"29487",
    "addr:street":"Ranch Rd",
    "iso:country":"US",
    "sg:address":"6212 Ranch Rd",
    "sg:city":"Wadmalaw Island",
    "sg:classifiers":[
        {
            "category":"Farming",
            "subcategory":"Farm",
            "type":"Manufacturing & Wholesale Goods"
        }
    ],
    "sg:phone":"+1 843 559 4437",
    "sg:postcode":"29487",
    "sg:province":"SC",
    "sg:tags":[
        "crop",
        "general"
    ],
    "wof:name":"Palmetto Point Farms",
    "wof:placetype":"venue"
},
  "geometry": {"coordinates":[-80.212902,32.648348],"type":"Point"}
}