{
  "type": "Feature",
  "properties": {
    "iso:country":"US",
    "sg:address":"1020 Hwy 52",
    "sg:city":"Moncks Corner",
    "sg:classifiers":[
        {
            "category":"Health Services",
            "subcategory":"Doctor",
            "type":"Services"
        }
    ],
    "sg:phone":"+1 843 761 8248",
    "sg:postcode":"29461",
    "sg:province":"SC",
    "sg:tags":[
        "physician",
        "surgeon"
    ],
    "wof:name":"Palmetto Primary Care",
    "wof:placetype":"venue"
},
  "geometry": {"coordinates":[-80.007692,33.185578],"type":"Point"}
}