{
  "type": "Feature",
  "properties": {
    "addr:full":"1020 Hwy 52 Moncks Corner SC 29461",
    "addr:housenumber":"1020",
    "addr:postcode":"29461",
    "addr:street":"Hwy 52",
    "iso:country":"US",
    "sg:address":"1020 Hwy 52",
    "sg:city":"Moncks Corner",
    "sg:classifiers":[
        {
            "category":"Health Services",
            "subcategory":"Doctor",
            "type":"Services"
        }
    ],
    "sg:phone":"+1 843 761 8248",
    "sg:postcode":"29461",
    "sg:province":"SC",
    "sg:tags":[
        "physician",
        "surgeon"
    ],
    "wof:name":"Palmetto Primary Care",
    "wof:placetype":"venue"
},
  "geometry": {"coordinates":[-80.00769200000001,33.185578],"type":"Point"}
}