{
  "type": "Feature",
  "properties": {
    "iso:country":"US",
    "sg:address":"901 US Hwy 378 W",
    "sg:city":"Lexington",
    "sg:classifiers":[
        {
            "category":"Freight",
            "type":"Transportation"
        }
    ],
    "sg:phone":"+1 803 957 2292",
    "sg:postcode":"29072",
    "sg:province":"SC",
    "sg:tags":[
        "operator",
        "construction",
        "local",
        "trucking"
    ],
    "wof:name":"Wessinger Construction Co",
    "wof:placetype":"venue"
},
  "geometry": {"coordinates":[-81.312288,33.994853],"type":"Point"}
}