{
  "type": "Feature",
  "properties": {
    "iso:country":"US",
    "sg:address":"1272 Asheville Hwy",
    "sg:city":"Spartanburg",
    "sg:classifiers":[
        {
            "category":"Food & Beverages",
            "subcategory":"Groceries & Convenience Stores",
            "type":"Retail Goods"
        }
    ],
    "sg:phone":"+1 864 598 0890",
    "sg:postcode":"29303",
    "sg:province":"SC",
    "wof:name":"Asian Grocery Store",
    "wof:placetype":"venue"
},
  "geometry": {"coordinates":[-81.958098,34.97464],"type":"Point"}
}