{
  "type": "Feature",
  "properties": {
    "iso:country":"US",
    "sg:address":"1083 Hwy 35",
    "sg:city":"St Stephen",
    "sg:classifiers":[
        {
            "category":"Organizations",
            "subcategory":"Religious Organization",
            "type":"Services"
        }
    ],
    "sg:phone":"+1 843 825 6354",
    "sg:postcode":"29479",
    "sg:province":"SC",
    "sg:tags":[
        "church"
    ],
    "wof:name":"Sumpter Chapel United Meth",
    "wof:placetype":"venue"
},
  "geometry": {"coordinates":[-79.964597,33.409525],"type":"Point"}
}