{
  "type": "Feature",
  "properties": {
    "iso:country":"US",
    "sg:address":"5909 Loftis Rd",
    "sg:city":"Hanahan",
    "sg:classifiers":[
        {
            "category":"Professional",
            "subcategory":"Computer Services",
            "type":"Services"
        }
    ],
    "sg:phone":"+1 843 554 4409",
    "sg:postcode":"29410",
    "sg:province":"SC",
    "sg:tags":[
        "repair"
    ],
    "wof:name":"Com-Tech Svc",
    "wof:placetype":"venue"
},
  "geometry": {"coordinates":[-80.010498,32.904155],"type":"Point"}
}