{
  "type": "Feature",
  "properties": {
    "iso:country":"US",
    "sg:address":"5032 Sunset Blvd",
    "sg:city":"Lexington",
    "sg:classifiers":[
        {
            "category":"Building & Trades",
            "subcategory":"Construction",
            "type":"Services"
        }
    ],
    "sg:phone":"+1 803 957 9757",
    "sg:postcode":"29072",
    "sg:province":"SC",
    "sg:tags":[
        "general",
        "contractor"
    ],
    "wof:name":"Carolina Systems-Built",
    "wof:placetype":"venue"
},
  "geometry": {"coordinates":[-81.19091400000001,34.009622],"type":"Point"}
}