{
  "type": "Feature",
  "properties": {
    "addr:full":"600 16th Ave N Myrtle Beach SC 29577",
    "addr:housenumber":"600",
    "addr:postcode":"29577",
    "addr:street":"16Th Ave N",
    "iso:country":"US",
    "sg:address":"600 16th Ave N",
    "sg:city":"Myrtle Beach",
    "sg:classifiers":[
        {
            "category":"Restaurant",
            "type":"Food & Drink"
        }
    ],
    "sg:phone":"+1 843 222 5899",
    "sg:postcode":"29577",
    "sg:province":"SC",
    "sg:tags":[
        "eating"
    ],
    "wof:name":"Chef Luckys Catering",
    "wof:placetype":"venue"
},
  "geometry": {"coordinates":[-78.878472,33.700635],"type":"Point"}
}