{
  "type": "Feature",
  "properties": {
    "iso:country":"US",
    "sg:address":"14 Fly Catcher Ln",
    "sg:city":"Beaufort",
    "sg:classifiers":[
        {
            "category":"Insurance",
            "subcategory":"Insurance Agent",
            "type":"Services"
        }
    ],
    "sg:phone":"+1 843 522 3835",
    "sg:postcode":"29907",
    "sg:province":"SC",
    "wof:name":"Allstate Insurance",
    "wof:placetype":"venue"
},
  "geometry": {"coordinates":[-80.644767,32.44348],"type":"Point"}
}