{
  "type": "Feature",
  "properties": {
    "iso:country":"US",
    "sg:address":"167 Berkshire Loop",
    "sg:city":"Pawleys Island",
    "sg:classifiers":[
        {
            "category":"Professional",
            "type":"Services"
        }
    ],
    "sg:phone":"+1 843 235 6592",
    "sg:postcode":"29585",
    "sg:province":"SC",
    "sg:tags":[
        "establishment"
    ],
    "wof:name":"Val Rosario",
    "wof:placetype":"venue"
},
  "geometry": {"coordinates":[-79.154993,33.444413],"type":"Point"}
}