{
  "type": "Feature",
  "properties": {
    "addr:full":"20 Burnt Church Rd Bluffton SC 29910",
    "addr:housenumber":"20",
    "addr:postcode":"29910",
    "addr:street":"Burnt Church Rd",
    "iso:country":"US",
    "sg:address":"20 Burnt Church Rd",
    "sg:city":"Bluffton",
    "sg:classifiers":[
        {
            "category":"Freight",
            "type":"Transportation"
        }
    ],
    "sg:phone":"+1 843 837 3313",
    "sg:postcode":"29910",
    "sg:province":"SC",
    "sg:tags":[
        "commercial",
        "storage"
    ],
    "wof:name":"Save More Mini Storage",
    "wof:placetype":"venue"
},
  "geometry": {"coordinates":[-80.844173,32.248768],"type":"Point"}
}