{
  "type": "Feature",
  "properties": {
    "iso:country":"US",
    "sg:address":"100 State Rd",
    "sg:city":"Cheraw",
    "sg:classifiers":[
        {
            "category":"Sports & Exercise",
            "subcategory":"Golf",
            "type":"Entertainment"
        }
    ],
    "sg:phone":"+1 843 537 6741",
    "sg:postcode":"29520",
    "sg:province":"SC",
    "sg:tags":[
        "course"
    ],
    "wof:name":"Cheraw Golf Course Maintenance",
    "wof:placetype":"venue"
},
  "geometry": {"coordinates":[-79.89519300000001,34.709353],"type":"Point"}
}