{
  "type": "Feature",
  "properties": {
    "addr:full":"1084 Boiling Springs Rd Spartanburg SC 29303",
    "addr:housenumber":"1084",
    "addr:postcode":"29303",
    "addr:street":"Boiling Springs Rd",
    "iso:country":"US",
    "sg:address":"1084 Boiling Springs Rd",
    "sg:city":"Spartanburg",
    "sg:classifiers":[
        {
            "category":"Professional",
            "subcategory":"Business Services",
            "type":"Services"
        }
    ],
    "sg:phone":"+1 864 234 1311",
    "sg:postcode":"29303",
    "sg:province":"SC",
    "sg:tags":[
        "real estate"
    ],
    "wof:name":"Jernigan Appraisal Group",
    "wof:placetype":"venue"
},
  "geometry": {"coordinates":[-81.942848,34.978131],"type":"Point"}
}