{
  "type": "Feature",
  "properties": {
    "addr:full":"6920 US Hwy 76 Nichols SC 29581",
    "addr:housenumber":"6920",
    "addr:postcode":"29581",
    "addr:street":"Us Hwy 76",
    "iso:country":"US",
    "sg:address":"6920 US Hwy 76",
    "sg:city":"Nichols",
    "sg:classifiers":[
        {
            "category":"Wholesale",
            "subcategory":"Petroleum",
            "type":"Manufacturing & Wholesale Goods"
        }
    ],
    "sg:phone":"+1 843 392 3362",
    "sg:postcode":"29581",
    "sg:province":"SC",
    "sg:tags":[
        "bulk",
        "product",
        "retail",
        "storage",
        "f"
    ],
    "wof:name":"Anderson Oil Co",
    "wof:placetype":"venue"
},
  "geometry": {"coordinates":[-79.03901399999999,34.260848],"type":"Point"}
}