{
  "type": "Feature",
  "properties": {
    "iso:country":"US",
    "sg:address":"82 Tanbark Ct",
    "sg:city":"Goose Creek",
    "sg:classifiers":[
        {
            "category":"Shopping",
            "subcategory":"Catalog Store",
            "type":"Retail Goods"
        }
    ],
    "sg:phone":"+1 843 553 9090",
    "sg:postcode":"29445",
    "sg:province":"SC",
    "wof:name":"Creative Pillow Etc",
    "wof:placetype":"venue"
},
  "geometry": {"coordinates":[-80.030001,33.037734],"type":"Point"}
}