{
  "type": "Feature",
  "properties": {
    "iso:country":"US",
    "sg:address":"1004 Carver St",
    "sg:city":"Myrtle Beach",
    "sg:classifiers":[
        {
            "category":"Local Transit",
            "type":"Transportation"
        }
    ],
    "sg:phone":"+1 843 626 7352",
    "sg:postcode":"29577",
    "sg:province":"SC",
    "sg:tags":[
        "squad",
        "rescue"
    ],
    "wof:name":"Myrtle Beach Volunteer Rescue",
    "wof:placetype":"venue"
},
  "geometry": {"coordinates":[-78.88208400000001,33.699505],"type":"Point"}
}