{
  "type": "Feature",
  "properties": {
    "addr:full":"3001 Meeting St Hilton Head Isle SC 29926",
    "addr:housenumber":"3001",
    "addr:postcode":"29926",
    "addr:street":"Meeting St;Head",
    "iso:country":"US",
    "sg:address":"3001 Meeting St",
    "sg:city":"Hilton Head Isle",
    "sg:classifiers":[
        {
            "category":"Social Services",
            "subcategory":"Child Care",
            "type":"Services"
        }
    ],
    "sg:phone":"+1 843 681 8671",
    "sg:postcode":"29926",
    "sg:province":"SC",
    "sg:tags":[
        "kindergarten",
        "academic",
        "school"
    ],
    "wof:name":"All Saints Episcopal Pre-Schl",
    "wof:placetype":"venue"
},
  "geometry": {"coordinates":[-80.73005999999999,32.215825],"type":"Point"}
}