{
  "type": "Feature",
  "properties": {
    "addr:full":"1757 Koulter Dr Columbia SC 29210",
    "addr:housenumber":"1757",
    "addr:postcode":"29210",
    "addr:street":"Koulter Dr",
    "iso:country":"US",
    "sg:address":"1757 Koulter Dr",
    "sg:city":"Columbia",
    "sg:classifiers":[
        {
            "category":"Building & Trades",
            "subcategory":"Construction",
            "type":"Services"
        }
    ],
    "sg:phone":"+1 803 551 5777",
    "sg:postcode":"29210",
    "sg:province":"SC",
    "sg:tags":[
        "general",
        "contractor"
    ],
    "sg:website":"www.artisanspecialties.com",
    "wof:name":"Artisan Specialties",
    "wof:placetype":"venue"
},
  "geometry": {"coordinates":[-81.075834,34.038213],"type":"Point"}
}