{
  "type": "Feature",
  "properties": {
    "iso:country":"US",
    "sg:address":"2025 Linwood St",
    "sg:city":"Sumter",
    "sg:classifiers":[
        {
            "category":"Building & Trades",
            "subcategory":"Construction",
            "type":"Services"
        }
    ],
    "sg:phone":"+1 803 905 7727",
    "sg:postcode":"29153",
    "sg:province":"SC",
    "sg:tags":[
        "contractor"
    ],
    "wof:name":"Apex Contracting",
    "wof:placetype":"venue"
},
  "geometry": {"coordinates":[-80.381405,33.963148],"type":"Point"}
}