{
  "type": "Feature",
  "properties": {
    "iso:country":"US",
    "sg:address":"3197 Whiskey Rd",
    "sg:city":"Aiken",
    "sg:classifiers":[
        {
            "category":"Professional",
            "subcategory":"Management & Consulting",
            "type":"Services"
        }
    ],
    "sg:phone":"+1 803 643 1715",
    "sg:postcode":"29803",
    "sg:province":"SC",
    "sg:tags":[
        "party",
        "planning"
    ],
    "wof:name":"Hole-N-One Miniature Golf",
    "wof:placetype":"venue"
},
  "geometry": {"coordinates":[-81.69856299999999,33.488172],"type":"Point"}
}