{
  "type": "Feature",
  "properties": {
    "iso:country":"US",
    "sg:address":"325 Evans Rd",
    "sg:city":"Johnsonville",
    "sg:classifiers":[
        {
            "category":"Food & Beverages",
            "subcategory":"Bakery",
            "type":"Retail Goods"
        }
    ],
    "sg:phone":"+1 843 493 2021",
    "sg:postcode":"29555",
    "sg:province":"SC",
    "wof:name":"Taste Sinsations",
    "wof:placetype":"venue"
},
  "geometry": {"coordinates":[-79.50845700000001,33.870801],"type":"Point"}
}