{
  "type": "Feature",
  "properties": {
    "iso:country":"US",
    "sg:address":"1602 Camelot Forest",
    "sg:city":"Belton",
    "sg:classifiers":[
        {
            "category":"Travel",
            "subcategory":"Travel Agent",
            "type":"Entertainment"
        }
    ],
    "sg:phone":"+1 864 338 0064",
    "sg:postcode":"29627",
    "sg:province":"SC",
    "sg:tags":[
        "tours",
        "promoter"
    ],
    "wof:name":"Happy Trails Tours Inc",
    "wof:placetype":"venue"
},
  "geometry": {"coordinates":[-82.478397,34.54866],"type":"Point"}
}