{
  "type": "Feature",
  "properties": {
    "addr:full":"205 Wattling Rd West Columbia SC 29170",
    "addr:housenumber":"205",
    "addr:postcode":"29170",
    "addr:street":"Wattling Rd",
    "iso:country":"US",
    "sg:address":"205 Wattling Rd",
    "sg:city":"West Columbia",
    "sg:classifiers":[
        {
            "category":"Shopping",
            "subcategory":"Antiques",
            "type":"Retail Goods"
        }
    ],
    "sg:phone":"+1 803 794 7197",
    "sg:postcode":"29170",
    "sg:province":"SC",
    "wof:name":"West Columbia Antique Mall",
    "wof:placetype":"venue"
},
  "geometry": {"coordinates":[-81.127602,33.976101],"type":"Point"}
}