{
  "type": "Feature",
  "properties": {
    "addr:full":"110 Carolina Rd Conway SC 29526",
    "addr:housenumber":"110",
    "addr:postcode":"29526",
    "addr:street":"Carolina Rd",
    "iso:country":"US",
    "sg:address":"110 Carolina Rd",
    "sg:city":"Conway",
    "sg:classifiers":[
        {
            "category":"Shopping",
            "subcategory":"Clothing, Apparel, & Fashions",
            "type":"Retail Goods"
        }
    ],
    "sg:phone":"+1 843 347 9378",
    "sg:postcode":"29526",
    "sg:province":"SC",
    "sg:tags":[
        "tack",
        "western"
    ],
    "wof:name":"Wild West",
    "wof:placetype":"venue"
},
  "geometry": {"coordinates":[-79.008449,33.802944],"type":"Point"}
}