{
  "type": "Feature",
  "properties": {
    "iso:country":"US",
    "sg:address":"208 N Friendfield Rd",
    "sg:city":"Scranton",
    "sg:phone":"+1 843 389 2831",
    "sg:postcode":"29591",
    "sg:province":"SC",
    "sg:tags":[
        "farm",
        "corn",
        "wheat",
        "tobacco",
        "soybean"
    ],
    "wof:name":"Rogers Farm",
    "wof:placetype":"venue"
},
  "geometry": {"coordinates":[-79.667483,33.977554],"type":"Point"}
}