{
  "type": "Feature",
  "properties": {
    "addr:full":"3226 Maybank Hwy Johns Island SC 29455",
    "addr:housenumber":"3226",
    "addr:postcode":"29455",
    "addr:street":"Maybank Hwy",
    "iso:country":"US",
    "sg:address":"3226 Maybank Hwy",
    "sg:city":"Johns Island",
    "sg:classifiers":[
        {
            "category":"Building & Trades",
            "subcategory":"Construction",
            "type":"Services"
        }
    ],
    "sg:phone":"+1 843 557 0111",
    "sg:postcode":"29455",
    "sg:province":"SC",
    "sg:tags":[
        "painter"
    ],
    "wof:name":"East Bay Workshop",
    "wof:placetype":"venue"
},
  "geometry": {"coordinates":[-80.06036400000001,32.731865],"type":"Point"}
}