{
  "type": "Feature",
  "properties": {
    "iso:country":"US",
    "sg:address":"2111 N Pleasantburg Dr",
    "sg:city":"Greenville",
    "sg:classifiers":[
        {
            "category":"Building & Trades",
            "subcategory":"Equipment Rental",
            "type":"Services"
        }
    ],
    "sg:phone":"+1 864 242 2196",
    "sg:postcode":"29609",
    "sg:province":"SC",
    "sg:tags":[
        "yard"
    ],
    "wof:name":"Rent-A-Center",
    "wof:placetype":"venue"
},
  "geometry": {"coordinates":[-82.37517200000001,34.889608],"type":"Point"}
}