{
  "type": "Feature",
  "properties": {
    "iso:country":"US",
    "sg:address":"6003 Temperance Hill Rd",
    "sg:city":"Marion",
    "sg:phone":"+1 843 423 4578",
    "sg:postcode":"29571",
    "sg:province":"SC",
    "sg:tags":[
        "farm",
        "tobacco"
    ],
    "wof:name":"Brigmans Farm",
    "wof:placetype":"venue"
},
  "geometry": {"coordinates":[-79.38227500000001,34.282697],"type":"Point"}
}