{
  "type": "Feature",
  "properties": {
    "iso:country":"US",
    "sg:address":"160 Elliot Dr",
    "sg:city":"Westminster",
    "sg:classifiers":[
        {
            "category":"Building & Trades",
            "subcategory":"Construction",
            "type":"Services"
        }
    ],
    "sg:phone":"+1 864 972 0000",
    "sg:postcode":"29693",
    "sg:province":"SC",
    "sg:tags":[
        "commercial",
        "renovation"
    ],
    "wof:name":"Elliott Group Inc",
    "wof:placetype":"venue"
},
  "geometry": {"coordinates":[-83.020493,34.594396],"type":"Point"}
}