{
  "type": "Feature",
  "properties": {
    "iso:country":"US",
    "sg:address":"207 New Market St",
    "sg:city":"Greenwood",
    "sg:classifiers":[
        {
            "category":"Building & Trades",
            "subcategory":"Plumbing",
            "type":"Services"
        }
    ],
    "sg:phone":"+1 864 223 4155",
    "sg:postcode":"29646",
    "sg:province":"SC",
    "sg:tags":[
        "plumbing",
        "contractor"
    ],
    "wof:name":"Ken Mc Donald Plumbing Svc",
    "wof:placetype":"venue"
},
  "geometry": {"coordinates":[-82.147042,34.19303],"type":"Point"}
}