{
  "type": "Feature",
  "properties": {
    "iso:country":"US",
    "sg:address":"48 Folly Rd",
    "sg:city":"Charleston",
    "sg:classifiers":[
        {
            "category":"Health Services",
            "subcategory":"Doctor",
            "type":"Services"
        }
    ],
    "sg:phone":"+1 843 769 2100",
    "sg:postcode":"29407",
    "sg:province":"SC",
    "sg:tags":[
        "physician",
        "surgeon"
    ],
    "wof:name":"James G Simpson MD",
    "wof:placetype":"venue"
},
  "geometry": {"coordinates":[-79.971771,32.778651],"type":"Point"}
}