{
  "type": "Feature",
  "properties": {
    "iso:country":"US",
    "sg:address":"1644 Main St",
    "sg:city":"Columbia",
    "sg:classifiers":[
        {
            "category":"Real Estate",
            "subcategory":"Real Estate Operator",
            "type":"Services"
        }
    ],
    "sg:phone":"+1 803 254 0593",
    "sg:postcode":"29201",
    "sg:province":"SC",
    "sg:tags":[
        "building",
        "parks"
    ],
    "wof:name":"Main Street Lofts",
    "wof:placetype":"venue"
},
  "geometry": {"coordinates":[-81.036189,34.007402],"type":"Point"}
}