{
  "type": "Feature",
  "properties": {
    "iso:country":"US",
    "sg:address":"253 W Ball Park Rd",
    "sg:city":"Gaston",
    "sg:classifiers":[
        {
            "category":"Building & Trades",
            "subcategory":"Construction",
            "type":"Services"
        }
    ],
    "sg:phone":"+1 803 791 9894",
    "sg:postcode":"29053",
    "sg:province":"SC",
    "sg:tags":[
        "carpentry",
        "contractor"
    ],
    "wof:name":"Kevin Beachum Framing",
    "wof:placetype":"venue"
},
  "geometry": {"coordinates":[-81.097528,33.82978],"type":"Point"}
}