{
  "type": "Feature",
  "properties": {
    "addr:full":"2475 Ashley River Rd Charleston SC 29414",
    "addr:housenumber":"2475",
    "addr:postcode":"29414",
    "addr:street":"Ashley River Rd",
    "iso:country":"US",
    "sg:address":"2475 Ashley River Rd",
    "sg:city":"Charleston",
    "sg:classifiers":[
        {
            "category":"Retail",
            "subcategory":"Laundry & Dry Cleaning",
            "type":"Services"
        }
    ],
    "sg:phone":"+1 843 763 5189",
    "sg:postcode":"29414",
    "sg:province":"SC",
    "sg:tags":[
        "cleaners",
        "rug",
        "carpet"
    ],
    "wof:name":"Ashley River Carpet Care",
    "wof:placetype":"venue"
},
  "geometry": {"coordinates":[-80.041738,32.828722],"type":"Point"}
}