{
  "type": "Feature",
  "properties": {
    "addr:full":"1110 Boonehill Rd Summerville SC 29483",
    "addr:housenumber":"1110",
    "addr:postcode":"29483",
    "addr:street":"Boonehill Rd",
    "iso:country":"US",
    "sg:address":"1110 Boonehill Rd",
    "sg:city":"Summerville",
    "sg:classifiers":[
        {
            "category":"Restaurant",
            "type":"Food & Drink"
        }
    ],
    "sg:phone":"+1 843 875 0690",
    "sg:postcode":"29483",
    "sg:province":"SC",
    "sg:tags":[
        "dairy",
        "parlor",
        "bar",
        "ice",
        "cream"
    ],
    "wof:name":"Tastee-Freez",
    "wof:placetype":"venue"
},
  "geometry": {"coordinates":[-80.213753,32.998763],"type":"Point"}
}