{
  "type": "Feature",
  "properties": {
    "iso:country":"US",
    "sg:address":"114 Blake St",
    "sg:city":"Greenwood",
    "sg:classifiers":[
        {
            "category":"Retail",
            "subcategory":"Portrait Studio",
            "type":"Services"
        }
    ],
    "sg:phone":"+1 864 223 9517",
    "sg:postcode":"29649",
    "sg:province":"SC",
    "sg:tags":[
        "photographer"
    ],
    "wof:name":"Bill Adams Studio",
    "wof:placetype":"venue"
},
  "geometry": {"coordinates":[-82.162958,34.197579],"type":"Point"}
}