{
  "type": "Feature",
  "properties": {
    "addr:full":"929 Front St Georgetown SC 29440",
    "addr:housenumber":"929",
    "addr:postcode":"29440",
    "addr:street":"Front St",
    "iso:country":"US",
    "sg:address":"929 Front St",
    "sg:city":"Georgetown",
    "sg:classifiers":[
        {
            "category":"Sports & Exercise",
            "subcategory":"Gym",
            "type":"Entertainment"
        }
    ],
    "sg:phone":"+1 843 546 1848",
    "sg:postcode":"29440",
    "sg:province":"SC",
    "sg:tags":[
        "club",
        "health",
        "studio",
        "gymnasium"
    ],
    "wof:name":"Winyah Fitness Ctr",
    "wof:placetype":"venue"
},
  "geometry": {"coordinates":[-79.287066,33.368913],"type":"Point"}
}