{
  "type": "Feature",
  "properties": {
    "addr:full":"4700 Palm Blvd Isle Of Palms SC 29451",
    "addr:housenumber":"4700",
    "addr:postcode":"29451",
    "addr:street":"Palm Blvd",
    "iso:country":"US",
    "sg:address":"4700 Palm Blvd",
    "sg:city":"Isle Of Palms",
    "sg:classifiers":[
        {
            "category":"Organizations",
            "subcategory":"Community Association",
            "type":"Services"
        }
    ],
    "sg:phone":"+1 843 886 6270",
    "sg:postcode":"29451",
    "sg:province":"SC",
    "sg:tags":[
        "club"
    ],
    "wof:name":"Citadel Beach Club",
    "wof:placetype":"venue"
},
  "geometry": {"coordinates":[-79.75157900000001,32.800464],"type":"Point"}
}