{
  "type": "Feature",
  "properties": {
    "iso:country":"US",
    "sg:address":"3810 Notch Rd",
    "sg:city":"Columbia",
    "sg:classifiers":[
        {
            "category":"Retail",
            "subcategory":"Auto Rental",
            "type":"Services"
        }
    ],
    "sg:phone":"+1 803 754 6650",
    "sg:postcode":"29204",
    "sg:province":"SC",
    "sg:tags":[
        "renting",
        "automobile"
    ],
    "wof:name":"Thrifty Car Rental",
    "wof:placetype":"venue"
},
  "geometry": {"coordinates":[-80.996576,34.040953],"type":"Point"}
}