{
  "type": "Feature",
  "properties": {
    "iso:country":"US",
    "sg:address":"204 Rock Creek Rd",
    "sg:city":"Anderson",
    "sg:classifiers":[
        {
            "category":"Retail",
            "subcategory":"Animal Services",
            "type":"Services"
        }
    ],
    "sg:phone":"+1 864 287 4529",
    "sg:postcode":"29625",
    "sg:province":"SC",
    "sg:tags":[
        "pet",
        "boarding",
        "sitting"
    ],
    "wof:name":"Paws Unlimited Pet Sitters",
    "wof:placetype":"venue"
},
  "geometry": {"coordinates":[-82.796809,34.546468],"type":"Point"}
}