{
  "type": "Feature",
  "properties": {
    "iso:country":"US",
    "sg:address":"1041 Creekview Dr",
    "sg:city":"Darlington",
    "sg:classifiers":[
        {
            "category":"Building & Trades",
            "subcategory":"Construction",
            "type":"Services"
        }
    ],
    "sg:phone":"+1 843 395 1518",
    "sg:postcode":"29540",
    "sg:province":"SC",
    "sg:tags":[
        "downspouts",
        "gutter"
    ],
    "wof:name":"Gutterguys",
    "wof:placetype":"venue"
},
  "geometry": {"coordinates":[-79.86374,34.335242],"type":"Point"}
}