{
  "type": "Feature",
  "properties": {
    "addr:full":"1703 Taylor St Columbia SC 29201",
    "addr:housenumber":"1703",
    "addr:postcode":"29201",
    "addr:street":"Taylor St",
    "iso:country":"US",
    "sg:address":"1703 Taylor St",
    "sg:city":"Columbia",
    "sg:classifiers":[
        {
            "category":"Arts & Performance",
            "subcategory":"Arts Center",
            "type":"Entertainment"
        },
        {
            "category":"Arts & Performance",
            "subcategory":"Music",
            "type":"Entertainment"
        }
    ],
    "sg:phone":"+1 803 252 2032",
    "sg:postcode":"29201",
    "sg:province":"SC",
    "sg:tags":[
        "performing",
        "venue"
    ],
    "sg:website":"www.thetownship.org/",
    "wof:name":"The Township Auditorium",
    "wof:placetype":"venue"
},
  "geometry": {"coordinates":[-81.02770200000001,34.0093],"type":"Point"}
}