{
  "type": "Feature",
  "properties": {
    "iso:country":"US",
    "sg:address":"2992 Reidville Rd",
    "sg:city":"Spartanburg",
    "sg:classifiers":[
        {
            "category":"Professional",
            "subcategory":"Lawyer & Legal Services",
            "type":"Services"
        }
    ],
    "sg:phone":"+1 864 574 8801",
    "sg:postcode":"29301",
    "sg:province":"SC",
    "sg:tags":[
        "attorney"
    ],
    "wof:name":"John D Hawkins",
    "wof:placetype":"venue"
},
  "geometry": {"coordinates":[-82.008323,34.915248],"type":"Point"}
}