{
  "type": "Feature",
  "properties": {
    "addr:full":"905 Greenville Dr Williamston SC 29697",
    "addr:housenumber":"905",
    "addr:postcode":"29697",
    "addr:street":"Greenville Dr",
    "iso:country":"US",
    "sg:address":"905 Greenville Dr",
    "sg:city":"Williamston",
    "sg:classifiers":[
        {
            "category":"Restaurant",
            "type":"Food & Drink"
        }
    ],
    "sg:menulink":"http://www.allmenus.com/sc/williamston-pelzer/215314-burger-king/menu/",
    "sg:phone":"+1 864 847 7887",
    "sg:postcode":"29697",
    "sg:province":"SC",
    "sg:tags":[
        "burger",
        "american"
    ],
    "wof:name":"Burger King",
    "wof:placetype":"venue"
},
  "geometry": {"coordinates":[-82.46903399999999,34.630022],"type":"Point"}
}