{
  "type": "Feature",
  "properties": {
    "addr:full":"31 Horizon St Aiken SC 29801",
    "addr:housenumber":"31",
    "addr:postcode":"29801",
    "addr:street":"Horizon St",
    "iso:country":"US",
    "sg:address":"31 Horizon St",
    "sg:city":"Aiken",
    "sg:classifiers":[
        {
            "category":"Personal",
            "subcategory":"Beauty Salon",
            "type":"Services"
        }
    ],
    "sg:phone":"+1 803 642 5052",
    "sg:postcode":"29801",
    "sg:province":"SC",
    "wof:name":"T's Beauty Shop",
    "wof:placetype":"venue"
},
  "geometry": {"coordinates":[-81.71973,33.611039],"type":"Point"}
}