{
  "type": "Feature",
  "properties": {
    "iso:country":"US",
    "sg:address":"802 Kelly St",
    "sg:city":"Anderson",
    "sg:classifiers":[
        {
            "category":"Personal",
            "subcategory":"Beauty Salon",
            "type":"Services"
        }
    ],
    "sg:phone":"+1 864 225 7100",
    "sg:postcode":"29625",
    "sg:province":"SC",
    "wof:name":"Agnes's",
    "wof:placetype":"venue"
},
  "geometry": {"coordinates":[-82.662578,34.509926],"type":"Point"}
}