{
  "type": "Feature",
  "properties": {
    "addr:full":"934 US Hwy 501 Myrtle Beach SC 29577",
    "addr:housenumber":"934",
    "addr:postcode":"29577",
    "addr:street":"Us Hwy 501",
    "iso:country":"US",
    "sg:address":"934 US Hwy 501",
    "sg:city":"Myrtle Beach",
    "sg:classifiers":[
        {
            "category":"Travel",
            "subcategory":"Hotels & Motels",
            "type":"Entertainment"
        }
    ],
    "sg:phone":"+1 843 448 3587",
    "sg:postcode":"29577",
    "sg:province":"SC",
    "wof:name":"Pams Corner",
    "wof:placetype":"venue"
},
  "geometry": {"coordinates":[-78.891198,33.695375],"type":"Point"}
}