{
  "type": "Feature",
  "properties": {
    "iso:country":"US",
    "sg:address":"1704 New Zion Rd",
    "sg:city":"Lake City",
    "sg:phone":"+1 843 389 2130",
    "sg:postcode":"29560",
    "sg:province":"SC",
    "sg:tags":[
        "farm",
        "tobacco"
    ],
    "wof:name":"Larry Springs",
    "wof:placetype":"venue"
},
  "geometry": {"coordinates":[-79.886634,33.846814],"type":"Point"}
}