{
  "type": "Feature",
  "properties": {
    "iso:country":"US",
    "sg:address":"13 S Hampden Ct",
    "sg:city":"Charleston",
    "sg:classifiers":[
        {
            "category":"Shopping",
            "subcategory":"Hobbies, Toys, & Games",
            "type":"Retail Goods"
        }
    ],
    "sg:phone":"+1 843 853 9517",
    "sg:postcode":"29403",
    "sg:province":"SC",
    "sg:tags":[
        "craft"
    ],
    "wof:name":"Floor It",
    "wof:placetype":"venue"
},
  "geometry": {"coordinates":[-79.936685,32.795326],"type":"Point"}
}