{
  "type": "Feature",
  "properties": {
    "iso:country":"US",
    "sg:address":"127 N Congress St",
    "sg:city":"Winnsboro",
    "sg:classifiers":[
        {
            "category":"Manufacturing",
            "subcategory":"Printing",
            "type":"Manufacturing & Wholesale Goods"
        }
    ],
    "sg:phone":"+1 803 635 4016",
    "sg:postcode":"29180",
    "sg:province":"SC",
    "sg:tags":[
        "newspaper"
    ],
    "wof:name":"Herald-Independent",
    "wof:placetype":"venue"
},
  "geometry": {"coordinates":[-81.087186,34.382299],"type":"Point"}
}