{
  "type": "Feature",
  "properties": {
    "addr:full":"1033 Sharon Rd York SC 29745",
    "addr:housenumber":"1033",
    "addr:postcode":"29745",
    "addr:street":"Sharon Rd",
    "iso:country":"US",
    "sg:address":"1033 Sharon Rd",
    "sg:city":"York",
    "sg:classifiers":[
        {
            "category":"Autos & Motor Vehicles",
            "subcategory":"Auto Supplies",
            "type":"Retail Goods"
        }
    ],
    "sg:phone":"+1 803 684 6870",
    "sg:postcode":"29745",
    "sg:province":"SC",
    "sg:tags":[
        "automotive"
    ],
    "wof:name":"Hi Way Junk Yard",
    "wof:placetype":"venue"
},
  "geometry": {"coordinates":[-81.257541,34.985325],"type":"Point"}
}