{
  "type": "Feature",
  "properties": {
    "addr:full":"486 Shipping Ln Mount Pleasant SC 29464",
    "addr:housenumber":"486",
    "addr:postcode":"29464",
    "addr:street":"Shipping Ln",
    "iso:country":"US",
    "sg:address":"486 Shipping Ln",
    "sg:city":"Mount Pleasant",
    "sg:classifiers":[
        {
            "category":"Freight",
            "type":"Transportation"
        }
    ],
    "sg:phone":"+1 843 849 6700",
    "sg:postcode":"29464",
    "sg:province":"SC",
    "sg:tags":[
        "distance",
        "storage",
        "long",
        "trucking"
    ],
    "wof:name":"Container Marketing Corp",
    "wof:placetype":"venue"
},
  "geometry": {"coordinates":[-79.87126499999999,32.839435],"type":"Point"}
}