{
  "type": "Feature",
  "properties": {
    "addr:full":"14 Shennecock Ct Aiken SC 29803",
    "addr:housenumber":"14",
    "addr:postcode":"29803",
    "addr:street":"Shennecock Ct",
    "iso:country":"US",
    "sg:address":"14 Shennecock Ct",
    "sg:city":"Aiken",
    "sg:classifiers":[
        {
            "category":"Manufacturing",
            "subcategory":"Watercraft",
            "type":"Manufacturing & Wholesale Goods"
        }
    ],
    "sg:phone":"+1 803 643 3007",
    "sg:postcode":"29803",
    "sg:province":"SC",
    "wof:name":"Custom Craft Builders",
    "wof:placetype":"venue"
},
  "geometry": {"coordinates":[-81.772231,33.466702],"type":"Point"}
}