{
  "type": "Feature",
  "properties": {
    "addr:full":"386 Bama Rd Gilbert SC 29054",
    "addr:housenumber":"386",
    "addr:postcode":"29054",
    "addr:street":"Bama Rd",
    "iso:country":"US",
    "sg:address":"386 Bama Rd",
    "sg:city":"Gilbert",
    "sg:classifiers":[
        {
            "category":"Shopping",
            "subcategory":"Hobbies, Toys, & Games",
            "type":"Retail Goods"
        }
    ],
    "sg:phone":"+1 803 892 3018",
    "sg:postcode":"29054",
    "sg:province":"SC",
    "sg:tags":[
        "craft"
    ],
    "wof:name":"A & A Rock & Crafts",
    "wof:placetype":"venue"
},
  "geometry": {"coordinates":[-81.42025099999999,33.963591],"type":"Point"}
}