{
  "type": "Feature",
  "properties": {
    "iso:country":"US",
    "sg:address":"69 Wentworth St",
    "sg:city":"Charleston",
    "sg:classifiers":[
        {
            "category":"Sports & Exercise",
            "subcategory":"Gym",
            "type":"Entertainment"
        }
    ],
    "sg:phone":"+1 843 723 4995",
    "sg:postcode":"29401",
    "sg:province":"SC",
    "sg:tags":[
        "club",
        "health",
        "studio",
        "gymnasium"
    ],
    "sg:website":"www.blueturtleyoga.com",
    "wof:name":"Eco Fitness & Blue Turtle Yoga",
    "wof:placetype":"venue"
},
  "geometry": {"coordinates":[-79.93224,32.783105],"type":"Point"}
}