{
  "type": "Feature",
  "properties": {
    "iso:country":"US",
    "sg:address":"499 Waters Rd",
    "sg:city":"Cowpens",
    "sg:classifiers":[
        {
            "category":"Manufacturing",
            "subcategory":"Tools & Machinery",
            "type":"Manufacturing & Wholesale Goods"
        }
    ],
    "sg:phone":"+1 864 463 0040",
    "sg:postcode":"29330",
    "sg:province":"SC",
    "sg:tags":[
        "machine",
        "shop"
    ],
    "wof:name":"Davis Machining & Fabricators",
    "wof:placetype":"venue"
},
  "geometry": {"coordinates":[-81.80586700000001,35.035753],"type":"Point"}
}