{
  "type": "Feature",
  "properties": {
    "iso:country":"US",
    "sg:address":"400 College Ave",
    "sg:city":"Clemson",
    "sg:classifiers":[
        {
            "category":"Personal",
            "subcategory":"Beauty Salon",
            "type":"Services"
        }
    ],
    "sg:phone":"+1 864 654 1140",
    "sg:postcode":"29631",
    "sg:province":"SC",
    "wof:name":"Platinum Salon",
    "wof:placetype":"venue"
},
  "geometry": {"coordinates":[-82.83515800000001,34.688216],"type":"Point"}
}