{
  "type": "Feature",
  "properties": {
    "iso:country":"US",
    "sg:address":"211 Medical Cir",
    "sg:city":"West Columbia",
    "sg:classifiers":[
        {
            "category":"Personal",
            "type":"Services"
        }
    ],
    "sg:phone":"+1 803 796 6100",
    "sg:postcode":"29169",
    "sg:province":"SC",
    "sg:tags":[
        "bureau"
    ],
    "wof:name":"Edu Care Publishing Inc",
    "wof:placetype":"venue"
},
  "geometry": {"coordinates":[-81.112314,34.00229],"type":"Point"}
}