{
  "type": "Feature",
  "properties": {
    "addr:full":"609 Laurens Rd Greenville SC 29607",
    "addr:housenumber":"609",
    "addr:postcode":"29607",
    "addr:street":"Laurens Rd",
    "iso:country":"US",
    "sg:address":"609 Laurens Rd",
    "sg:city":"Greenville",
    "sg:classifiers":[
        {
            "category":"Local Transit",
            "type":"Transportation"
        }
    ],
    "sg:phone":"+1 864 271 3127",
    "sg:postcode":"29607",
    "sg:province":"SC",
    "sg:tags":[
        "handicapped"
    ],
    "wof:name":"Wheelchair Getaways Inc",
    "wof:placetype":"venue"
},
  "geometry": {"coordinates":[-82.374989,34.850081],"type":"Point"}
}