{
  "type": "Feature",
  "properties": {
    "addr:full":"108 Anderson Cir Greenwood SC 29649",
    "addr:housenumber":"108",
    "addr:postcode":"29649",
    "addr:street":"Anderson Cir",
    "iso:country":"US",
    "sg:address":"108 Anderson Cir",
    "sg:city":"Greenwood",
    "sg:classifiers":[
        {
            "category":"Shopping",
            "subcategory":"Computers & Home Electronics",
            "type":"Retail Goods"
        }
    ],
    "sg:phone":"+1 864 229 0922",
    "sg:postcode":"29649",
    "sg:province":"SC",
    "wof:name":"Music Masters",
    "wof:placetype":"venue"
},
  "geometry": {"coordinates":[-82.20269399999999,34.208643],"type":"Point"}
}