{
  "type": "Feature",
  "properties": {
    "iso:country":"US",
    "sg:address":"3239 US Hwy 301 N",
    "sg:city":"Hamer",
    "sg:classifiers":[
        {
            "category":"Manufacturing",
            "subcategory":"Signs",
            "type":"Manufacturing & Wholesale Goods"
        }
    ],
    "sg:phone":"+1 843 774 6620",
    "sg:postcode":"29547",
    "sg:province":"SC",
    "sg:tags":[
        "advertising",
        "specialty"
    ],
    "wof:name":"Ace Hi Advertising Co Inc",
    "wof:placetype":"venue"
},
  "geometry": {"coordinates":[-79.31444500000001,34.493609],"type":"Point"}
}