{
  "type": "Feature",
  "properties": {
    "iso:country":"US",
    "sg:address":"1899 N Hobson Ave",
    "sg:city":"North Charleston",
    "sg:classifiers":[
        {
            "category":"Professional",
            "type":"Services"
        }
    ],
    "sg:phone":"+1 843 740 1911",
    "sg:postcode":"29405",
    "sg:province":"SC",
    "sg:tags":[
        "establishment"
    ],
    "wof:name":"S C Resarch Authority",
    "wof:placetype":"venue"
},
  "geometry": {"coordinates":[-79.970446,32.867767],"type":"Point"}
}