{
  "type": "Feature",
  "properties": {
    "iso:country":"US",
    "sg:address":"1270 Bower Pkwy",
    "sg:city":"Columbia",
    "sg:classifiers":[
        {
            "category":"Insurance",
            "subcategory":"Insurance Agent",
            "type":"Services"
        }
    ],
    "sg:phone":"+1 803 407 0072",
    "sg:postcode":"29212",
    "sg:province":"SC",
    "wof:name":"State Farm Insurance",
    "wof:placetype":"venue"
},
  "geometry": {"coordinates":[-81.15158700000001,34.070776],"type":"Point"}
}