{
  "type": "Feature",
  "properties": {
    "addr:full":"230 Cotton Dike Rd Frogmore SC 29920",
    "addr:housenumber":"230",
    "addr:postcode":"29920",
    "addr:street":"Cotton Dike Rd",
    "iso:country":"US",
    "sg:address":"230 Cotton Dike Rd",
    "sg:city":"Frogmore",
    "sg:classifiers":[
        {
            "category":"Real Estate",
            "subcategory":"Real Estate Operator",
            "type":"Services"
        }
    ],
    "sg:phone":"+1 843 838 5091",
    "sg:postcode":"29920",
    "sg:province":"SC",
    "sg:tags":[
        "building",
        "nonresidential"
    ],
    "wof:name":"Birch Grove Inc",
    "wof:placetype":"venue"
},
  "geometry": {"coordinates":[-80.588015,32.433003],"type":"Point"}
}