{
  "type": "Feature",
  "properties": {
    "addr:full":"135 Eagles Nest Dr Seneca SC 29678",
    "addr:housenumber":"135",
    "addr:postcode":"29678",
    "addr:street":"Eagles Nest Dr",
    "iso:country":"US",
    "sg:address":"135 Eagles Nest Dr",
    "sg:city":"Seneca",
    "sg:classifiers":[
        {
            "category":"Health Services",
            "subcategory":"Health Practitioner",
            "type":"Services"
        }
    ],
    "sg:phone":"+1 864 882 7965",
    "sg:postcode":"29678",
    "sg:province":"SC",
    "sg:tags":[
        "therapist",
        "physical"
    ],
    "wof:name":"Hummel Physical Therapy",
    "wof:placetype":"venue"
},
  "geometry": {"coordinates":[-82.950058,34.695881],"type":"Point"}
}