{
  "type": "Feature",
  "properties": {
    "iso:country":"US",
    "sg:address":"1345 Garner Ln",
    "sg:city":"Columbia",
    "sg:classifiers":[
        {
            "category":"Building & Trades",
            "subcategory":"Construction",
            "type":"Services"
        }
    ],
    "sg:phone":"+1 803 731 6500",
    "sg:postcode":"29210",
    "sg:province":"SC",
    "sg:tags":[
        "contractor"
    ],
    "wof:name":"Southern Home Exteriors",
    "wof:placetype":"venue"
},
  "geometry": {"coordinates":[-81.089321,34.040702],"type":"Point"}
}