{
  "type": "Feature",
  "properties": {
    "iso:country":"US",
    "sg:address":"556 McNeary St",
    "sg:city":"Prosperity",
    "sg:classifiers":[
        {
            "category":"Building & Trades",
            "subcategory":"Construction",
            "type":"Services"
        }
    ],
    "sg:phone":"+1 803 364 3245",
    "sg:postcode":"29127",
    "sg:province":"SC",
    "sg:tags":[
        "house"
    ],
    "wof:name":"Donald Amick Construction",
    "wof:placetype":"venue"
},
  "geometry": {"coordinates":[-81.530137,34.199255],"type":"Point"}
}