{
  "type": "Feature",
  "properties": {
    "iso:country":"US",
    "sg:address":"2771 Pleasant Rd",
    "sg:city":"Fort Mill",
    "sg:classifiers":[
        {
            "category":"Retail",
            "subcategory":"Repair Shop",
            "type":"Services"
        }
    ],
    "sg:phone":"+1 803 547 1917",
    "sg:postcode":"29708",
    "sg:province":"SC",
    "sg:tags":[
        "alarm",
        "system"
    ],
    "wof:name":"Charlies Lock & Key Inc",
    "wof:placetype":"venue"
},
  "geometry": {"coordinates":[-80.967513,35.058492],"type":"Point"}
}