{
  "type": "Feature",
  "properties": {
    "addr:full":"3687 Damascus Church Rd Westville SC 29175",
    "addr:housenumber":"3687",
    "addr:postcode":"29175",
    "addr:street":"Damascus Church Rd",
    "iso:country":"US",
    "sg:address":"3687 Damascus Church Rd",
    "sg:city":"Westville",
    "sg:classifiers":[
        {
            "category":"Building & Trades",
            "subcategory":"Construction",
            "type":"Services"
        }
    ],
    "sg:phone":"+1 803 425 5509",
    "sg:postcode":"29175",
    "sg:province":"SC",
    "sg:tags":[
        "contractor"
    ],
    "wof:name":"Truesdale Masonry",
    "wof:placetype":"venue"
},
  "geometry": {"coordinates":[-80.623777,34.430069],"type":"Point"}
}