{
  "type": "Feature",
  "properties": {
    "addr:full":"704 E Wade Hampton Blvd Greer SC 29651",
    "addr:housenumber":"704",
    "addr:postcode":"29651",
    "addr:street":"E Wade Hampton Blvd",
    "iso:country":"US",
    "sg:address":"704 E Wade Hampton Blvd",
    "sg:city":"Greer",
    "sg:classifiers":[
        {
            "category":"Restaurant",
            "type":"Food & Drink"
        }
    ],
    "sg:menulink":"http://www.allmenus.com/sc/greer/85093-applebees/menu/",
    "sg:phone":"+1 864 848 0073",
    "sg:postcode":"29651",
    "sg:province":"SC",
    "sg:tags":[
        "burger",
        "american",
        "sandwich",
        "soup"
    ],
    "wof:name":"Applebee's",
    "wof:placetype":"venue"
},
  "geometry": {"coordinates":[-82.213476,34.947478],"type":"Point"}
}