{
  "type": "Feature",
  "properties": {
    "iso:country":"US",
    "sg:address":"24 Brentwood Dr",
    "sg:city":"Greenville",
    "sg:classifiers":[
        {
            "category":"Freight",
            "type":"Transportation"
        }
    ],
    "sg:phone":"+1 864 271 7261",
    "sg:postcode":"29609",
    "sg:province":"SC",
    "sg:tags":[
        "operator",
        "local",
        "trucking"
    ],
    "wof:name":"Mike Mc Call",
    "wof:placetype":"venue"
},
  "geometry": {"coordinates":[-82.3807,34.885052],"type":"Point"}
}