{
  "type": "Feature",
  "properties": {
    "iso:country":"US",
    "sg:address":"2070 Sam Rittenberg Blvd",
    "sg:city":"Charleston",
    "sg:classifiers":[
        {
            "category":"Shopping",
            "subcategory":"Music",
            "type":"Retail Goods"
        }
    ],
    "sg:phone":"+1 843 556 5282",
    "sg:postcode":"29407",
    "sg:province":"SC",
    "sg:tags":[
        "compact",
        "record",
        "disc",
        "tape"
    ],
    "sg:website":"www.twec.com",
    "wof:name":"Fye",
    "wof:placetype":"venue"
},
  "geometry": {"coordinates":[-80.03057099999999,32.792449],"type":"Point"}
}