{
  "type": "Feature",
  "properties": {
    "iso:country":"US",
    "sg:address":"530 Knox Abbott Dr",
    "sg:city":"Cayce",
    "sg:classifiers":[
        {
            "category":"Professional",
            "subcategory":"Advertising",
            "type":"Services"
        }
    ],
    "sg:phone":"+1 803 739 6900",
    "sg:postcode":"29033",
    "sg:province":"SC",
    "sg:tags":[
        "guide"
    ],
    "wof:name":"Magnum Publications LLC",
    "wof:placetype":"venue"
},
  "geometry": {"coordinates":[-81.05959,33.983624],"type":"Point"}
}