{
  "type": "Feature",
  "properties": {
    "iso:country":"US",
    "sg:address":"119 N Townville St",
    "sg:city":"Seneca",
    "sg:classifiers":[
        {
            "category":"Professional",
            "subcategory":"Accounting & Tax Preparation",
            "type":"Services"
        }
    ],
    "sg:phone":"+1 864 882 7000",
    "sg:postcode":"29678",
    "sg:province":"SC",
    "sg:tags":[
        "return",
        "filing"
    ],
    "wof:name":"National Tax Svc",
    "wof:placetype":"venue"
},
  "geometry": {"coordinates":[-82.953124,34.684631],"type":"Point"}
}