{
  "type": "Feature",
  "properties": {
    "addr:full":"202 SW Railroad Ave Latta SC 29565",
    "addr:housenumber":"202",
    "addr:postcode":"29565",
    "addr:street":"Sw Railroad Ave",
    "iso:country":"US",
    "sg:address":"202 SW Railroad Ave",
    "sg:city":"Latta",
    "sg:classifiers":[
        {
            "category":"Wholesale",
            "subcategory":"Chemicals & Plastics",
            "type":"Manufacturing & Wholesale Goods"
        }
    ],
    "sg:phone":"+1 843 752 4337",
    "sg:postcode":"29565",
    "sg:province":"SC",
    "wof:name":"Palmetto AG Inc",
    "wof:placetype":"venue"
},
  "geometry": {"coordinates":[-79.433386,34.336927],"type":"Point"}
}