{
  "type": "Feature",
  "properties": {
    "iso:country":"US",
    "sg:address":"1106 Woodruff Rd",
    "sg:city":"Greenville",
    "sg:classifiers":[
        {
            "category":"Home & Garden",
            "subcategory":"Furniture",
            "type":"Retail Goods"
        }
    ],
    "sg:phone":"+1 864 329 1199",
    "sg:postcode":"29607",
    "sg:province":"SC",
    "sg:tags":[
        "mattress"
    ],
    "wof:name":"Mattress Source",
    "wof:placetype":"venue"
},
  "geometry": {"coordinates":[-82.30032,34.827508],"type":"Point"}
}