{
  "type": "Feature",
  "properties": {
    "iso:country":"US",
    "sg:address":"2 Old Dunham Bridge Rd",
    "sg:city":"Greenville",
    "sg:classifiers":[
        {
            "category":"Food & Beverages",
            "subcategory":"Groceries & Convenience Stores",
            "type":"Retail Goods"
        }
    ],
    "sg:phone":"+1 864 269 7669",
    "sg:postcode":"29611",
    "sg:province":"SC",
    "sg:tags":[
        "grocer"
    ],
    "wof:name":"Plez U Food Store",
    "wof:placetype":"venue"
},
  "geometry": {"coordinates":[-82.45974099999999,34.82053],"type":"Point"}
}