{
  "type": "Feature",
  "properties": {
    "iso:country":"US",
    "sg:address":"1721 Ebenezer Rd",
    "sg:city":"Rock Hill",
    "sg:classifiers":[
        {
            "category":"Health Services",
            "subcategory":"Doctor",
            "type":"Services"
        }
    ],
    "sg:phone":"+1 803 328 0175",
    "sg:postcode":"29732",
    "sg:province":"SC",
    "sg:tags":[
        "dentist"
    ],
    "wof:name":"Robert E Penny Pa",
    "wof:placetype":"venue"
},
  "geometry": {"coordinates":[-81.04785099999999,34.959247],"type":"Point"}
}