{
  "type": "Feature",
  "properties": {
    "iso:country":"US",
    "sg:address":"10 Alexander St",
    "sg:city":"Greenville",
    "sg:classifiers":[
        {
            "category":"Manufacturing",
            "subcategory":"Petroleum Products",
            "type":"Manufacturing & Wholesale Goods"
        }
    ],
    "sg:phone":"+1 864 232 5307",
    "sg:postcode":"29609",
    "sg:province":"SC",
    "sg:tags":[
        "oil"
    ],
    "wof:name":"Miiller/Scotland Fuels",
    "wof:placetype":"venue"
},
  "geometry": {"coordinates":[-82.412673,34.865213],"type":"Point"}
}