{
  "type": "Feature",
  "properties": {
    "iso:country":"US",
    "sg:address":"630 Skylark Dr",
    "sg:city":"Charleston",
    "sg:classifiers":[
        {
            "category":"Banks & Credit Unions",
            "subcategory":"Bank",
            "type":"Services"
        }
    ],
    "sg:phone":"+1 843 556 1818",
    "sg:postcode":"29407",
    "sg:province":"SC",
    "sg:tags":[
        "loan",
        "real estate"
    ],
    "wof:name":"Citi Financial",
    "wof:placetype":"venue"
},
  "geometry": {"coordinates":[-80.030186,32.791309],"type":"Point"}
}