{
  "type": "Feature",
  "properties": {
    "iso:country":"US",
    "sg:address":"518 College Ave",
    "sg:city":"Clemson",
    "sg:classifiers":[
        {
            "category":"Shopping",
            "subcategory":"Jewelry",
            "type":"Retail Goods"
        },
        {
            "category":"Wholesale",
            "subcategory":"Jewelry",
            "type":"Manufacturing & Wholesale Goods"
        }
    ],
    "sg:phone":"+1 864 624 9240",
    "sg:postcode":"29631",
    "sg:province":"SC",
    "sg:tags":[
        "beads"
    ],
    "wof:name":"Beaded Tiger",
    "wof:placetype":"venue"
},
  "geometry": {"coordinates":[-82.83480900000001,34.688917],"type":"Point"}
}