{
  "type": "Feature",
  "properties": {
    "iso:country":"US",
    "sg:address":"9652 N Kings Hwy",
    "sg:city":"Myrtle Beach",
    "sg:classifiers":[
        {
            "category":"Shopping",
            "subcategory":"Clothing, Apparel, & Fashions",
            "type":"Retail Goods"
        }
    ],
    "sg:phone":"+1 843 692 0220",
    "sg:postcode":"29572",
    "sg:province":"SC",
    "sg:tags":[
        "ready",
        "item",
        "boutique",
        "lady"
    ],
    "wof:name":"Cameron Diego Inc",
    "wof:placetype":"venue"
},
  "geometry": {"coordinates":[-78.777782,33.786339],"type":"Point"}
}