{
  "type": "Feature",
  "properties": {
    "addr:full":"313 London Pride Rd Irmo SC 29063",
    "addr:housenumber":"313",
    "addr:postcode":"29063",
    "addr:street":"London Pride Rd",
    "iso:country":"US",
    "sg:address":"313 London Pride Rd",
    "sg:city":"Irmo",
    "sg:classifiers":[
        {
            "category":"Freight",
            "type":"Transportation"
        }
    ],
    "sg:phone":"+1 803 407 1134",
    "sg:postcode":"29063",
    "sg:province":"SC",
    "wof:name":"Chris Able Transport LLC",
    "wof:placetype":"venue"
},
  "geometry": {"coordinates":[-81.19314900000001,34.100243],"type":"Point"}
}