{
  "type": "Feature",
  "properties": {
    "iso:country":"US",
    "sg:address":"2500 E River St",
    "sg:city":"Anderson",
    "sg:classifiers":[
        {
            "category":"Autos & Motor Vehicles",
            "subcategory":"Automobile Sales",
            "type":"Retail Goods"
        }
    ],
    "sg:phone":"+1 864 261 0718",
    "sg:postcode":"29621",
    "sg:province":"SC",
    "sg:tags":[
        "used"
    ],
    "wof:name":"Jonboys Used Cars",
    "wof:placetype":"venue"
},
  "geometry": {"coordinates":[-82.61077899999999,34.488977],"type":"Point"}
}