{
  "type": "Feature",
  "properties": {
    "iso:country":"US",
    "sg:address":"55 E Antrim Dr",
    "sg:city":"Greenville",
    "sg:classifiers":[
        {
            "category":"Manufacturing",
            "subcategory":"Chemicals & Compounds",
            "type":"Manufacturing & Wholesale Goods"
        }
    ],
    "sg:phone":"+1 864 242 6192",
    "sg:postcode":"29607",
    "sg:province":"SC",
    "sg:tags":[
        "paint"
    ],
    "wof:name":"ICI Dulux Paint",
    "wof:placetype":"venue"
},
  "geometry": {"coordinates":[-82.361932,34.840431],"type":"Point"}
}