{
  "type": "Feature",
  "properties": {
    "iso:country":"US",
    "sg:address":"5290 Burrows Rd",
    "sg:city":"Sumter",
    "sg:classifiers":[
        {
            "category":"Food & Beverages",
            "subcategory":"Groceries & Convenience Stores",
            "type":"Retail Goods"
        }
    ],
    "sg:phone":"+1 803 469 4843",
    "sg:postcode":"29153",
    "sg:province":"SC",
    "sg:tags":[
        "grocer"
    ],
    "wof:name":"Blanding Grocery Store",
    "wof:placetype":"venue"
},
  "geometry": {"coordinates":[-80.389417,34.070536],"type":"Point"}
}