{
  "type": "Feature",
  "properties": {
    "iso:country":"US",
    "sg:address":"2211 Hudson Rd",
    "sg:city":"Greer",
    "sg:classifiers":[
        {
            "category":"Banks & Credit Unions",
            "subcategory":"Bank",
            "type":"Services"
        }
    ],
    "sg:phone":"+1 864 609 0660",
    "sg:postcode":"29650",
    "sg:province":"SC",
    "sg:tags":[
        "money",
        "transfer"
    ],
    "wof:name":"Jom New Mexico Corp",
    "wof:placetype":"venue"
},
  "geometry": {"coordinates":[-82.290633,34.888173],"type":"Point"}
}