{
  "type": "Feature",
  "properties": {
    "iso:country":"US",
    "sg:address":"21 Wonder Farm Ave",
    "sg:city":"Nesmith",
    "sg:phone":"+1 843 382 2422",
    "sg:postcode":"29580",
    "sg:province":"SC",
    "sg:tags":[
        "farm",
        "corn",
        "animal",
        "general"
    ],
    "wof:name":"Harold Tisdale",
    "wof:placetype":"venue"
},
  "geometry": {"coordinates":[-79.571856,33.652656],"type":"Point"}
}