{
  "type": "Feature",
  "properties": {
    "iso:country":"US",
    "sg:address":"1812 Sam Rittenberg Blvd",
    "sg:city":"Charleston",
    "sg:classifiers":[
        {
            "category":"Restaurant",
            "type":"Food & Drink"
        }
    ],
    "sg:menulink":"http://www.allmenus.com/sc/charleston-north-charleston/89666-moes-southwest-grill/menu/",
    "sg:phone":"+1 843 225 6637",
    "sg:postcode":"29407",
    "sg:province":"SC",
    "sg:tags":[
        "mexican"
    ],
    "wof:name":"Moe's Southwest Grill",
    "wof:placetype":"venue"
},
  "geometry": {"coordinates":[-80.019412,32.801846],"type":"Point"}
}