{
  "type": "Feature",
  "properties": {
    "iso:country":"US",
    "sg:address":"1802 Airport Rd",
    "sg:city":"Lancaster",
    "sg:classifiers":[
        {
            "category":"Social Services",
            "subcategory":"Child Care",
            "type":"Services"
        }
    ],
    "sg:phone":"+1 803 285 8363",
    "sg:postcode":"29720",
    "sg:province":"SC",
    "wof:name":"Lois Barnes Child Care",
    "wof:placetype":"venue"
},
  "geometry": {"coordinates":[-80.78380300000001,34.68895],"type":"Point"}
}