{
  "type": "Feature",
  "properties": {
    "addr:full":"106 Cedar Ave Andrews SC 29510",
    "addr:housenumber":"106",
    "addr:postcode":"29510",
    "addr:street":"Cedar Ave",
    "iso:country":"US",
    "sg:address":"106 Cedar Ave",
    "sg:city":"Andrews",
    "sg:classifiers":[
        {
            "category":"Professional",
            "type":"Services"
        }
    ],
    "sg:phone":"+1 843 264 5903",
    "sg:postcode":"29510",
    "sg:province":"SC",
    "sg:tags":[
        "establishment"
    ],
    "wof:name":"Waccamaw Economic Opportunity",
    "wof:placetype":"venue"
},
  "geometry": {"coordinates":[-79.566041,33.454536],"type":"Point"}
}