{
  "type": "Feature",
  "properties": {
    "iso:country":"US",
    "sg:address":"29 Edinburgh Rd",
    "sg:city":"Charleston",
    "sg:classifiers":[
        {
            "category":"Shopping",
            "subcategory":"Used Merchandise",
            "type":"Retail Goods"
        }
    ],
    "sg:phone":"+1 843 556 4323",
    "sg:postcode":"29407",
    "sg:province":"SC",
    "sg:tags":[
        "antique"
    ],
    "wof:name":"Toler Edwards Antiques",
    "wof:placetype":"venue"
},
  "geometry": {"coordinates":[-79.996962,32.819482],"type":"Point"}
}