{
  "type": "Feature",
  "properties": {
    "iso:country":"US",
    "sg:address":"110 Clinton School Rd",
    "sg:city":"Lancaster",
    "sg:classifiers":[
        {
            "category":"Education",
            "subcategory":"School",
            "type":"Public Place"
        }
    ],
    "sg:phone":"+1 803 285 5395",
    "sg:postcode":"29720",
    "sg:province":"SC",
    "wof:name":"Clinton Elementary School",
    "wof:placetype":"venue"
},
  "geometry": {"coordinates":[-80.76706,34.724811],"type":"Point"}
}