{
  "type": "Feature",
  "properties": {
    "iso:country":"US",
    "sg:address":"1573 Folly Rd",
    "sg:city":"Charleston",
    "sg:classifiers":[
        {
            "category":"Shopping",
            "type":"Retail Goods"
        }
    ],
    "sg:phone":"+1 843 762 9283",
    "sg:postcode":"29412",
    "sg:province":"SC",
    "sg:tags":[
        "pet",
        "shop"
    ],
    "wof:name":"Pet Helpers Capital Campaign",
    "wof:placetype":"venue"
},
  "geometry": {"coordinates":[-79.966244,32.702867],"type":"Point"}
}