{
  "type": "Feature",
  "properties": {
    "iso:country":"US",
    "sg:address":"1040 US Hwy 17 N",
    "sg:city":"Surfside Beach",
    "sg:classifiers":[
        {
            "category":"Shopping",
            "subcategory":"Gifts & Souvenirs",
            "type":"Retail Goods"
        }
    ],
    "sg:phone":"+1 843 650 7474",
    "sg:postcode":"29575",
    "sg:province":"SC",
    "sg:tags":[
        "shop"
    ],
    "wof:name":"Gift's R4U",
    "wof:placetype":"venue"
},
  "geometry": {"coordinates":[-78.975003,33.618696],"type":"Point"}
}