{
  "type": "Feature",
  "properties": {
    "addr:full":"1801 Assembly St Columbia SC 29201",
    "addr:housenumber":"1801",
    "addr:postcode":"29201",
    "addr:street":"Assembly St",
    "iso:country":"US",
    "sg:address":"1801 Assembly St",
    "sg:city":"Columbia",
    "sg:classifiers":[
        {
            "category":"Banks & Credit Unions",
            "subcategory":"Bank",
            "type":"Services"
        }
    ],
    "sg:phone":"+1 803 252 1440",
    "sg:postcode":"29201",
    "sg:province":"SC",
    "sg:tags":[
        "federal"
    ],
    "wof:name":"Varo 3019 Federal Credit Union",
    "wof:placetype":"venue"
},
  "geometry": {"coordinates":[-81.039385,34.010094],"type":"Point"}
}