{
  "type": "Feature",
  "properties": {
    "iso:country":"US",
    "sg:address":"2099 Boiling Springs Rd",
    "sg:city":"Boiling Springs",
    "sg:classifiers":[
        {
            "category":"Ice Cream",
            "type":"Food & Drink"
        }
    ],
    "sg:menulink":"http://www.allmenus.com/sc/boiling-springs/220814-braums-ice-cream--dairy-stores/menu/",
    "sg:phone":"+1 864 578 5571",
    "sg:postcode":"29316",
    "sg:province":"SC",
    "sg:tags":[
        "american"
    ],
    "wof:name":"Braum's Ice Cream & Dairy Stores",
    "wof:placetype":"venue"
},
  "geometry": {"coordinates":[-81.963295,35.02014],"type":"Point"}
}