{
  "type": "Feature",
  "properties": {
    "iso:country":"US",
    "sg:address":"110 E Blackstock Rd",
    "sg:city":"Spartanburg",
    "sg:classifiers":[
        {
            "category":"Shopping",
            "subcategory":"Computers & Home Electronics",
            "type":"Retail Goods"
        }
    ],
    "sg:phone":"+1 864 574 3038",
    "sg:postcode":"29301",
    "sg:province":"SC",
    "sg:tags":[
        "equipment",
        "electronic",
        "supply"
    ],
    "wof:name":"Best Buy",
    "wof:placetype":"venue"
},
  "geometry": {"coordinates":[-81.98688,34.9221],"type":"Point"}
}