{
  "type": "Feature",
  "properties": {
    "iso:country":"US",
    "sg:address":"301 S Broad St",
    "sg:city":"Clinton",
    "sg:classifiers":[
        {
            "category":"Organizations",
            "subcategory":"Religious Organization",
            "type":"Services"
        }
    ],
    "sg:phone":"+1 864 833 2578",
    "sg:postcode":"29325",
    "sg:province":"SC",
    "sg:tags":[
        "church"
    ],
    "wof:name":"First Baptist Church",
    "wof:placetype":"venue"
},
  "geometry": {"coordinates":[-81.88065899999999,34.470284],"type":"Point"}
}