{
  "type": "Feature",
  "properties": {
    "addr:full":"6700 Garners Ferry Rd Columbia SC 29209",
    "addr:housenumber":"6700",
    "addr:postcode":"29209",
    "addr:street":"Garners Ferry Rd",
    "iso:country":"US",
    "sg:address":"6700 Garners Ferry Rd",
    "sg:city":"Columbia",
    "sg:classifiers":[
        {
            "category":"Banks & Credit Unions",
            "subcategory":"Bank",
            "type":"Services"
        }
    ],
    "sg:phone":"+1 803 776 1037",
    "sg:postcode":"29209",
    "sg:province":"SC",
    "wof:name":"Wachovia Bank",
    "wof:placetype":"venue"
},
  "geometry": {"coordinates":[-80.958969,33.977522],"type":"Point"}
}