{
  "type": "Feature",
  "properties": {
    "addr:full":"250 E Columbia Ave Leesville SC 29070",
    "addr:housenumber":"250",
    "addr:postcode":"29070",
    "addr:street":"E Columbia Ave",
    "iso:country":"US",
    "sg:address":"250 E Columbia Ave",
    "sg:city":"Leesville",
    "sg:classifiers":[
        {
            "category":"Home & Garden",
            "subcategory":"Furniture",
            "type":"Retail Goods"
        }
    ],
    "sg:phone":"+1 803 532 1080",
    "sg:postcode":"29070",
    "sg:province":"SC",
    "wof:name":"Farmers Furniture",
    "wof:placetype":"venue"
},
  "geometry": {"coordinates":[-81.51942099999999,33.913478],"type":"Point"}
}