{
  "type": "Feature",
  "properties": {
    "addr:full":"11830 US Hwy 17 Byp Murrells Inlet SC 29582",
    "addr:housenumber":"11830",
    "addr:postcode":"29582",
    "addr:street":"Us Hwy 17 Byp",
    "iso:country":"US",
    "sg:address":"11830 US Hwy 17 Byp",
    "sg:city":"Murrells Inlet",
    "sg:classifiers":[
        {
            "category":"Freight",
            "type":"Transportation"
        }
    ],
    "sg:phone":"+1 843 651 3555",
    "sg:postcode":"29582",
    "sg:province":"SC",
    "sg:tags":[
        "warehouse",
        "self",
        "storage"
    ],
    "wof:name":"Southern Storage Properties",
    "wof:placetype":"venue"
},
  "geometry": {"coordinates":[-79.02945099999999,33.575156],"type":"Point"}
}