{
  "type": "Feature",
  "properties": {
    "iso:country":"US",
    "sg:address":"538 Freemont Rd",
    "sg:city":"Longs",
    "sg:classifiers":[
        {
            "category":"Retail",
            "subcategory":"Auto Repair",
            "type":"Services"
        }
    ],
    "sg:phone":"+1 843 399 5707",
    "sg:postcode":"29568",
    "sg:province":"SC",
    "sg:tags":[
        "repairing",
        "automobile"
    ],
    "wof:name":"Wilson's Auto Svc",
    "wof:placetype":"venue"
},
  "geometry": {"coordinates":[-78.750277,33.935519],"type":"Point"}
}