{
  "type": "Feature",
  "properties": {
    "iso:country":"US",
    "sg:address":"2508 N Main St",
    "sg:city":"Anderson",
    "sg:classifiers":[
        {
            "category":"Freight",
            "type":"Transportation"
        }
    ],
    "sg:phone":"+1 864 226 1101",
    "sg:postcode":"29621",
    "sg:province":"SC",
    "sg:tags":[
        "operator",
        "local",
        "trucking"
    ],
    "wof:name":"Palmetto Moving & Storage",
    "wof:placetype":"venue"
},
  "geometry": {"coordinates":[-82.661124,34.52979],"type":"Point"}
}