{
  "type": "Feature",
  "properties": {
    "iso:country":"US",
    "sg:address":"711 W Wade Hampton Blvd",
    "sg:city":"Greer",
    "sg:classifiers":[
        {
            "category":"Professional",
            "subcategory":"Business Services",
            "type":"Services"
        }
    ],
    "sg:phone":"+1 864 879 2148",
    "sg:postcode":"29650",
    "sg:province":"SC",
    "sg:tags":[
        "interior",
        "consultant",
        "design",
        "decorator"
    ],
    "wof:name":"Gerald West Interiors",
    "wof:placetype":"venue"
},
  "geometry": {"coordinates":[-82.242703,34.947472],"type":"Point"}
}