{
  "type": "Feature",
  "properties": {
    "iso:country":"US",
    "sg:address":"6 Moody View Ct",
    "sg:city":"Columbia",
    "sg:classifiers":[
        {
            "category":"Building & Trades",
            "subcategory":"Landscaping Services",
            "type":"Services"
        }
    ],
    "sg:phone":"+1 803 865 8827",
    "sg:postcode":"29229",
    "sg:province":"SC",
    "sg:tags":[
        "lawn",
        "provides",
        "care"
    ],
    "wof:name":"M&M Landscaping & Lawn Maint",
    "wof:placetype":"venue"
},
  "geometry": {"coordinates":[-80.91296199999999,34.136807],"type":"Point"}
}