{
  "type": "Feature",
  "properties": {
    "addr:full":"1901 Cherokee Rd Williamston SC 29697",
    "addr:housenumber":"1901",
    "addr:postcode":"29697",
    "addr:street":"Cherokee Rd",
    "iso:country":"US",
    "sg:address":"1901 Cherokee Rd",
    "sg:city":"Williamston",
    "sg:classifiers":[
        {
            "category":"Wholesale",
            "subcategory":"Farm Supplies",
            "type":"Manufacturing & Wholesale Goods"
        }
    ],
    "sg:phone":"+1 864 226 9014",
    "sg:postcode":"29697",
    "sg:province":"SC",
    "sg:tags":[
        "auction",
        "livestock",
        "market"
    ],
    "wof:name":"Martin & Martin Cattle Inc",
    "wof:placetype":"venue"
},
  "geometry": {"coordinates":[-82.582768,34.652323],"type":"Point"}
}