{
  "type": "Feature",
  "properties": {
    "iso:country":"US",
    "sg:address":"795 Bobby Faucett Rd",
    "sg:city":"Jonesville",
    "sg:classifiers":[
        {
            "category":"Wholesale",
            "subcategory":"Machinery & Supplies",
            "type":"Manufacturing & Wholesale Goods"
        }
    ],
    "sg:phone":"+1 864 674 6421",
    "sg:postcode":"29353",
    "sg:province":"SC",
    "wof:name":"Gault's Small Engine",
    "wof:placetype":"venue"
},
  "geometry": {"coordinates":[-81.626877,34.840114],"type":"Point"}
}