{
  "type": "Feature",
  "properties": {
    "iso:country":"US",
    "sg:address":"47 Legare St",
    "sg:city":"Charleston",
    "sg:classifiers":[
        {
            "category":"Real Estate",
            "subcategory":"Developer",
            "type":"Services"
        },
        {
            "category":"Real Estate",
            "subcategory":"Real Estate Agent",
            "type":"Services"
        }
    ],
    "sg:phone":"+1 843 577 2670",
    "sg:postcode":"29401",
    "sg:province":"SC",
    "wof:name":"Tamsberg & Tamsberg LLC",
    "wof:placetype":"venue"
},
  "geometry": {"coordinates":[-79.934657,32.775561],"type":"Point"}
}