{
  "type": "Feature",
  "properties": {
    "addr:full":"576 Woodruff Rd Greenville SC 29607",
    "addr:housenumber":"576",
    "addr:postcode":"29607",
    "addr:street":"Woodruff Rd",
    "iso:country":"US",
    "sg:address":"576 Woodruff Rd",
    "sg:city":"Greenville",
    "sg:classifiers":[
        {
            "category":"Retail",
            "subcategory":"Portrait Studio",
            "type":"Services"
        }
    ],
    "sg:phone":"+1 864 987 5565",
    "sg:postcode":"29607",
    "sg:province":"SC",
    "sg:tags":[
        "photographer"
    ],
    "wof:name":"David Lawrence Photography",
    "wof:placetype":"venue"
},
  "geometry": {"coordinates":[-82.32753200000001,34.837259],"type":"Point"}
}