{
  "type": "Feature",
  "properties": {
    "addr:full":"3210 Hoffmeyer Rd Florence SC 29501",
    "addr:postcode":"3210;29501",
    "addr:street":"Hoffmeyer Rd",
    "iso:country":"US",
    "sg:address":"3210 Hoffmeyer Rd",
    "sg:city":"Florence",
    "sg:classifiers":[
        {
            "category":"Food & Beverages",
            "subcategory":"Groceries & Convenience Stores",
            "type":"Retail Goods"
        }
    ],
    "sg:phone":"+1 843 662 6068",
    "sg:postcode":"29501",
    "sg:province":"SC",
    "wof:name":"Neighborhood Grocery",
    "wof:placetype":"venue"
},
  "geometry": {"coordinates":[-79.84836199999999,34.208951],"type":"Point"}
}