{
  "type": "Feature",
  "properties": {
    "iso:country":"US",
    "sg:address":"216 S Pike W",
    "sg:city":"Sumter",
    "sg:classifiers":[
        {
            "category":"Restaurant",
            "type":"Food & Drink"
        }
    ],
    "sg:menulink":"http://www.allmenus.com/sc/sumter/100919-captain-ds-seafood/menu/",
    "sg:phone":"+1 803 775 7434",
    "sg:postcode":"29150",
    "sg:province":"SC",
    "sg:tags":[
        "seafood",
        "american"
    ],
    "wof:name":"Captain D's Seafood",
    "wof:placetype":"venue"
},
  "geometry": {"coordinates":[-80.349621,33.946338],"type":"Point"}
}