{
  "type": "Feature",
  "properties": {
    "iso:country":"US",
    "sg:address":"511 Palmetto Dr",
    "sg:city":"Simpsonville",
    "sg:classifiers":[
        {
            "category":"Freight",
            "type":"Transportation"
        }
    ],
    "sg:phone":"+1 864 963 9346",
    "sg:postcode":"29681",
    "sg:province":"SC",
    "sg:tags":[
        "commercial",
        "storage"
    ],
    "wof:name":"J & A Mini-Storage",
    "wof:placetype":"venue"
},
  "geometry": {"coordinates":[-82.291742,34.769161],"type":"Point"}
}