{
  "type": "Feature",
  "properties": {
    "addr:full":"2102 Old Spartanburg Rd Greer SC 29650",
    "addr:housenumber":"2102",
    "addr:postcode":"29650",
    "addr:street":"Old Spartanburg Rd",
    "iso:country":"US",
    "sg:address":"2102 Old Spartanburg Rd",
    "sg:city":"Greer",
    "sg:classifiers":[
        {
            "category":"Autos & Motor Vehicles",
            "subcategory":"Fuel & Gas Station",
            "type":"Retail Goods"
        }
    ],
    "sg:phone":"+1 864 244 7782",
    "sg:postcode":"29650",
    "sg:province":"SC",
    "sg:tags":[
        "oil"
    ],
    "wof:name":"Spinx Oil Co Inc",
    "wof:placetype":"venue"
},
  "geometry": {"coordinates":[-82.28996100000001,34.892443],"type":"Point"}
}