{
  "type": "Feature",
  "properties": {
    "iso:country":"US",
    "sg:address":"42 Grand Ave",
    "sg:city":"Greenville",
    "sg:classifiers":[
        {
            "category":"Utilities",
            "subcategory":"Electric",
            "type":"Services"
        }
    ],
    "sg:phone":"+1 864 271 7436",
    "sg:postcode":"29607",
    "sg:province":"SC",
    "sg:tags":[
        "company"
    ],
    "wof:name":"Davis Electric Co Inc",
    "wof:placetype":"venue"
},
  "geometry": {"coordinates":[-82.359467,34.853574],"type":"Point"}
}