{
  "type": "Feature",
  "properties": {
    "addr:full":"3346 Rivers Ave Charleston SC 29405",
    "addr:housenumber":"3346",
    "addr:postcode":"29405",
    "addr:street":"Rivers Ave",
    "iso:country":"US",
    "sg:address":"3346 Rivers Ave",
    "sg:city":"Charleston",
    "sg:classifiers":[
        {
            "category":"Social Services",
            "type":"Services"
        }
    ],
    "sg:phone":"+1 843 740 0750",
    "sg:postcode":"29405",
    "sg:province":"SC",
    "sg:tags":[
        "government"
    ],
    "wof:name":"Adoption & Birth Parent Svc",
    "wof:placetype":"venue"
},
  "geometry": {"coordinates":[-79.975159,32.854808],"type":"Point"}
}