{
  "type": "Feature",
  "properties": {
    "iso:country":"US",
    "sg:address":"30 Howard Creek Dr",
    "sg:city":"Fountain Inn",
    "sg:classifiers":[
        {
            "category":"Social Services",
            "subcategory":"Child Care",
            "type":"Services"
        }
    ],
    "sg:phone":"+1 864 862 5050",
    "sg:postcode":"29644",
    "sg:province":"SC",
    "wof:name":"Spike's After School",
    "wof:placetype":"venue"
},
  "geometry": {"coordinates":[-82.220284,34.70001],"type":"Point"}
}