{
  "type": "Feature",
  "properties": {
    "iso:country":"US",
    "sg:address":"1740 Ribaut Rd",
    "sg:city":"Port Royal",
    "sg:classifiers":[
        {
            "category":"Restaurant",
            "type":"Food & Drink"
        }
    ],
    "sg:phone":"+1 843 521 0701",
    "sg:postcode":"29935",
    "sg:province":"SC",
    "wof:name":"Ebeneser",
    "wof:placetype":"venue"
},
  "geometry": {"coordinates":[-80.695948,32.384063],"type":"Point"}
}