{
  "type": "Feature",
  "properties": {
    "iso:country":"US",
    "sg:address":"414 Maple Ave",
    "sg:city":"Johnsonville",
    "sg:classifiers":[
        {
            "category":"Education",
            "subcategory":"School",
            "type":"Public Place"
        }
    ],
    "sg:phone":"+1 843 386 2066",
    "sg:postcode":"29555",
    "sg:province":"SC",
    "wof:name":"Johnsonville Middle School",
    "wof:placetype":"venue"
},
  "geometry": {"coordinates":[-79.445734,33.807988],"type":"Point"}
}