{
  "type": "Feature",
  "properties": {
    "iso:country":"US",
    "sg:address":"633 Ross Hill Rd",
    "sg:city":"Gaffney",
    "sg:classifiers":[
        {
            "category":"Manufacturing",
            "subcategory":"Motor Vehicles & Parts",
            "type":"Manufacturing & Wholesale Goods"
        }
    ],
    "sg:phone":"+1 864 489 5168",
    "sg:postcode":"29341",
    "sg:province":"SC",
    "sg:tags":[
        "print",
        "apparel",
        "screen",
        "mfg"
    ],
    "wof:name":"Dixie Screen Printing",
    "wof:placetype":"venue"
},
  "geometry": {"coordinates":[-81.62808,35.160468],"type":"Point"}
}