{
  "type": "Feature",
  "properties": {
    "iso:country":"US",
    "sg:address":"208 President St",
    "sg:city":"Charleston",
    "sg:classifiers":[
        {
            "category":"Food & Beverages",
            "subcategory":"Groceries & Convenience Stores",
            "type":"Retail Goods"
        }
    ],
    "sg:phone":"+1 843 805 6400",
    "sg:postcode":"29403",
    "sg:province":"SC",
    "wof:name":"President Market",
    "wof:placetype":"venue"
},
  "geometry": {"coordinates":[-79.952404,32.791797],"type":"Point"}
}