{
  "type": "Feature",
  "properties": {
    "addr:full":"173 E Lacy St Chester SC 29706",
    "addr:housenumber":"173",
    "addr:postcode":"29706",
    "addr:street":"E Lacy St",
    "iso:country":"US",
    "sg:address":"173 E Lacy St",
    "sg:city":"Chester",
    "sg:classifiers":[
        {
            "category":"Insurance",
            "subcategory":"Insurance Agent",
            "type":"Services"
        }
    ],
    "sg:phone":"+1 803 581 0363",
    "sg:postcode":"29706",
    "sg:province":"SC",
    "wof:name":"Gene Boulware Insurance",
    "wof:placetype":"venue"
},
  "geometry": {"coordinates":[-81.199752,34.704142],"type":"Point"}
}