{
  "type": "Feature",
  "properties": {
    "addr:full":"444 King street Charleston SC 29403",
    "addr:housenumber":"444",
    "addr:postcode":"29403",
    "addr:street":"King Street",
    "iso:country":"US",
    "sg:address":"444 King street",
    "sg:city":"Charleston",
    "sg:classifiers":[
        {
            "category":"Professional",
            "subcategory":"Advertising",
            "type":"Services"
        }
    ],
    "sg:phone":"+1 843 225 7000",
    "sg:postcode":"29403",
    "sg:province":"SC",
    "sg:tags":[
        "seo",
        "sem",
        "ppc-management",
        "search-engine-optimization"
    ],
    "sg:website":"http://www.visiture.com",
    "wof:name":"Visiture",
    "wof:placetype":"venue"
},
  "geometry": {"coordinates":[-79.938536,32.789277],"type":"Point"}
}