{
  "type": "Feature",
  "properties": {
    "iso:country":"US",
    "sg:address":"104 Old Village Dr",
    "sg:city":"Anderson",
    "sg:classifiers":[
        {
            "category":"Manufacturing",
            "subcategory":"Retail Goods",
            "type":"Manufacturing & Wholesale Goods"
        }
    ],
    "sg:phone":"+1 864 225 2786",
    "sg:postcode":"29621",
    "sg:province":"SC",
    "sg:tags":[
        "product",
        "mfg"
    ],
    "wof:name":"Connie Williams",
    "wof:placetype":"venue"
},
  "geometry": {"coordinates":[-82.66329899999999,34.569018],"type":"Point"}
}