{
  "type": "Feature",
  "properties": {
    "addr:full":"137 Bethlehem Rd Batesburg SC 29006",
    "addr:housenumber":"137",
    "addr:postcode":"29006",
    "addr:street":"Bethlehem Rd",
    "iso:country":"US",
    "sg:address":"137 Bethlehem Rd",
    "sg:city":"Batesburg",
    "sg:classifiers":[
        {
            "category":"Farming",
            "subcategory":"Livestock Farm",
            "type":"Manufacturing & Wholesale Goods"
        }
    ],
    "sg:phone":"+1 803 532 5614",
    "sg:postcode":"29006",
    "sg:province":"SC",
    "sg:tags":[
        "beef",
        "corn",
        "general",
        "fa",
        "soybean",
        "cattle"
    ],
    "wof:name":"Dwight Davis",
    "wof:placetype":"venue"
},
  "geometry": {"coordinates":[-81.541037,33.881545],"type":"Point"}
}