{
  "type": "Feature",
  "properties": {
    "iso:country":"US",
    "sg:address":"7049 Dusk Trail Rd",
    "sg:city":"Ridge Spring",
    "sg:classifiers":[
        {
            "category":"Professional",
            "type":"Services"
        }
    ],
    "sg:phone":"+1 803 685 6305",
    "sg:postcode":"29129",
    "sg:province":"SC",
    "sg:tags":[
        "establishment"
    ],
    "wof:name":"Cumbee's Poultry",
    "wof:placetype":"venue"
},
  "geometry": {"coordinates":[-81.643769,33.790962],"type":"Point"}
}