{
  "type": "Feature",
  "properties": {
    "iso:country":"US",
    "sg:address":"1354 John Everall Rd",
    "sg:city":"Lancaster",
    "sg:classifiers":[
        {
            "category":"Retail",
            "subcategory":"Repair Shop",
            "type":"Services"
        }
    ],
    "sg:phone":"+1 803 283 4026",
    "sg:postcode":"29720",
    "sg:province":"SC",
    "sg:tags":[
        "appliance",
        "electrical",
        "contractor"
    ],
    "wof:name":"C & M Appliance Repair Inc",
    "wof:placetype":"venue"
},
  "geometry": {"coordinates":[-80.75957,34.752391],"type":"Point"}
}