{
  "type": "Feature",
  "properties": {
    "iso:country":"US",
    "sg:address":"204 Weimer St",
    "sg:city":"Bamberg",
    "sg:classifiers":[
        {
            "category":"Organizations",
            "subcategory":"Religious Organization",
            "type":"Services"
        }
    ],
    "sg:phone":"+1 803 245 7317",
    "sg:postcode":"29003",
    "sg:province":"SC",
    "sg:tags":[
        "church"
    ],
    "wof:name":"St John's Baptist Church",
    "wof:placetype":"venue"
},
  "geometry": {"coordinates":[-81.040521,33.293735],"type":"Point"}
}