{
  "type": "Feature",
  "properties": {
    "iso:country":"US",
    "sg:address":"907 Harness Trl",
    "sg:city":"Simpsonville",
    "sg:classifiers":[
        {
            "category":"Building & Trades",
            "subcategory":"Construction",
            "type":"Services"
        }
    ],
    "sg:phone":"+1 864 297 5426",
    "sg:postcode":"29681",
    "sg:province":"SC",
    "sg:tags":[
        "maintenance",
        "contractor"
    ],
    "wof:name":"L B Consulting",
    "wof:placetype":"venue"
},
  "geometry": {"coordinates":[-82.263077,34.814557],"type":"Point"}
}