{
  "type": "Feature",
  "properties": {
    "addr:full":"451 Old Conway Rd Marion SC 29571",
    "addr:housenumber":"451",
    "addr:postcode":"29571",
    "addr:street":"Old Conway Rd",
    "iso:country":"US",
    "sg:address":"451 Old Conway Rd",
    "sg:city":"Marion",
    "sg:classifiers":[
        {
            "category":"Shopping",
            "subcategory":"Florist",
            "type":"Retail Goods"
        }
    ],
    "sg:phone":"+1 843 423 9076",
    "sg:postcode":"29571",
    "sg:province":"SC",
    "wof:name":"Beths Flowers & Gifts",
    "wof:placetype":"venue"
},
  "geometry": {"coordinates":[-79.384395,34.150753],"type":"Point"}
}