{
  "type": "Feature",
  "properties": {
    "addr:full":"10850 Marlboro Ave Barnwell SC 29812",
    "addr:housenumber":"10850",
    "addr:postcode":"29812",
    "addr:street":"Marlboro Ave",
    "iso:country":"US",
    "sg:address":"10850 Marlboro Ave",
    "sg:city":"Barnwell",
    "sg:classifiers":[
        {
            "category":"Autos & Motor Vehicles",
            "subcategory":"Auto Supplies",
            "type":"Retail Goods"
        }
    ],
    "sg:phone":"+1 803 259 7051",
    "sg:postcode":"29812",
    "sg:province":"SC",
    "sg:tags":[
        "tire"
    ],
    "wof:name":"Barnwell Tire Co",
    "wof:placetype":"venue"
},
  "geometry": {"coordinates":[-81.35151,33.259632],"type":"Point"}
}