{
  "type": "Feature",
  "properties": {
    "iso:country":"US",
    "sg:address":"1227 Old Fort Rd",
    "sg:city":"Moncks Corner",
    "sg:classifiers":[
        {
            "category":"Shopping",
            "subcategory":"Catalog Store",
            "type":"Retail Goods"
        },
        {
            "category":"Building & Trades",
            "subcategory":"Construction",
            "type":"Services"
        }
    ],
    "sg:phone":"+1 843 899 7560",
    "sg:postcode":"29461",
    "sg:province":"SC",
    "sg:tags":[
        "house",
        "handyman",
        "mail"
    ],
    "wof:name":"J W Lowe & Co",
    "wof:placetype":"venue"
},
  "geometry": {"coordinates":[-79.99094700000001,33.18656],"type":"Point"}
}