{
  "type": "Feature",
  "properties": {
    "addr:full":"2867 Lesslie Hwy Rock Hill SC 29730",
    "addr:housenumber":"2867",
    "addr:postcode":"29730",
    "addr:street":"Lesslie Hwy",
    "iso:country":"US",
    "sg:address":"2867 Lesslie Hwy",
    "sg:city":"Rock Hill",
    "sg:classifiers":[
        {
            "category":"Education",
            "subcategory":"Special Training",
            "type":"Public Place"
        }
    ],
    "sg:phone":"+1 803 909 4050",
    "sg:postcode":"29730",
    "sg:province":"SC",
    "sg:tags":[
        "program"
    ],
    "sg:website":"www.abbyinc.com",
    "wof:name":"Abby Inc",
    "wof:placetype":"venue"
},
  "geometry": {"coordinates":[-80.964365,34.899186],"type":"Point"}
}