{
  "type": "Feature",
  "properties": {
    "iso:country":"US",
    "sg:address":"140 Stoneridge Dr",
    "sg:city":"Columbia",
    "sg:classifiers":[
        {
            "category":"Wholesale",
            "subcategory":"Stationery",
            "type":"Manufacturing & Wholesale Goods"
        }
    ],
    "sg:phone":"+1 803 256 0004",
    "sg:postcode":"29210",
    "sg:province":"SC",
    "sg:tags":[
        "business",
        "form",
        "system"
    ],
    "wof:name":"Standard Register Co",
    "wof:placetype":"venue"
},
  "geometry": {"coordinates":[-81.071324,34.014309],"type":"Point"}
}