{
  "type": "Feature",
  "properties": {
    "iso:country":"US",
    "sg:address":"601 Bay Branch Rd",
    "sg:city":"Lamar",
    "sg:classifiers":[
        {
            "category":"Utilities",
            "subcategory":"Refuse",
            "type":"Services"
        }
    ],
    "sg:phone":"+1 843 398 4800",
    "sg:postcode":"29069",
    "sg:province":"SC",
    "sg:tags":[
        "system"
    ],
    "wof:name":"Darlington County Recycling",
    "wof:placetype":"venue"
},
  "geometry": {"coordinates":[-80.056972,34.160913],"type":"Point"}
}