{
  "type": "Feature",
  "properties": {
    "addr:full":"100 Vanderbilt Ln Spartanburg SC 29301",
    "addr:housenumber":"100",
    "addr:postcode":"29301",
    "addr:street":"Vanderbilt Ln",
    "iso:country":"US",
    "sg:address":"100 Vanderbilt Ln",
    "sg:city":"Spartanburg",
    "sg:classifiers":[
        {
            "category":"Retail",
            "subcategory":"Portrait Studio",
            "type":"Services"
        }
    ],
    "sg:phone":"+1 864 574 5460",
    "sg:postcode":"29301",
    "sg:province":"SC",
    "sg:tags":[
        "photographer"
    ],
    "wof:name":"Olan Mills Portrait Studio",
    "wof:placetype":"venue"
},
  "geometry": {"coordinates":[-81.964044,34.944956],"type":"Point"}
}