{
  "type": "Feature",
  "properties": {
    "iso:country":"US",
    "sg:address":"385 Ridgeville Church Rd",
    "sg:city":"Inman",
    "sg:classifiers":[
        {
            "category":"Organizations",
            "subcategory":"Religious Organization",
            "type":"Services"
        }
    ],
    "sg:phone":"+1 864 578 0699",
    "sg:postcode":"29349",
    "sg:province":"SC",
    "sg:tags":[
        "church"
    ],
    "wof:name":"Ridgeville Baptist Church",
    "wof:placetype":"venue"
},
  "geometry": {"coordinates":[-82.030592,35.091953],"type":"Point"}
}