{
  "type": "Feature",
  "properties": {
    "iso:country":"US",
    "sg:address":"541 Flatnose Rd",
    "sg:city":"Darlington",
    "sg:classifiers":[
        {
            "category":"Farming",
            "subcategory":"Farm",
            "type":"Manufacturing & Wholesale Goods"
        }
    ],
    "sg:phone":"+1 843 393 5710",
    "sg:postcode":"29540",
    "sg:province":"SC",
    "sg:tags":[
        "crop",
        "general"
    ],
    "wof:name":"Charles Adams Farms",
    "wof:placetype":"venue"
},
  "geometry": {"coordinates":[-79.905903,34.417588],"type":"Point"}
}