{
  "type": "Feature",
  "properties": {
    "iso:country":"US",
    "sg:address":"4112 Hartford St",
    "sg:city":"Columbia",
    "sg:classifiers":[
        {
            "category":"Social Services",
            "subcategory":"Adult Care",
            "type":"Services"
        }
    ],
    "sg:phone":"+1 803 786 7411",
    "sg:postcode":"29204",
    "sg:province":"SC",
    "sg:tags":[
        "home",
        "residential"
    ],
    "wof:name":"Westside Residential Home Inc",
    "wof:placetype":"venue"
},
  "geometry": {"coordinates":[-80.993813,34.051793],"type":"Point"}
}