{
  "type": "Feature",
  "properties": {
    "addr:full":"138 Covey Hill Ln Greenville SC 29615",
    "addr:housenumber":"138",
    "addr:postcode":"29615",
    "addr:street":"Covey Hill Ln",
    "iso:country":"US",
    "sg:address":"138 Covey Hill Ln",
    "sg:city":"Greenville",
    "sg:classifiers":[
        {
            "category":"Shopping",
            "subcategory":"Clothing, Apparel, & Fashions",
            "type":"Retail Goods"
        }
    ],
    "sg:phone":"+1 864 370 9713",
    "sg:postcode":"29615",
    "sg:province":"SC",
    "wof:name":"Bk Unique Boutique",
    "wof:placetype":"venue"
},
  "geometry": {"coordinates":[-82.343396,34.860862],"type":"Point"}
}