{
  "type": "Feature",
  "properties": {
    "addr:full":"2341 Lide Springs Rd Darlington SC 29540",
    "addr:housenumber":"2341",
    "addr:postcode":"29540",
    "addr:street":"Lide Springs Rd",
    "iso:country":"US",
    "sg:address":"2341 Lide Springs Rd",
    "sg:city":"Darlington",
    "sg:classifiers":[
        {
            "category":"Building & Trades",
            "subcategory":"Construction",
            "type":"Services"
        }
    ],
    "sg:phone":"+1 843 398 0903",
    "sg:postcode":"29540",
    "sg:province":"SC",
    "sg:tags":[
        "railroad",
        "contractor"
    ],
    "wof:name":"Shane's Railwork Inc",
    "wof:placetype":"venue"
},
  "geometry": {"coordinates":[-79.822692,34.349536],"type":"Point"}
}