{
  "type": "Feature",
  "properties": {
    "iso:country":"US",
    "sg:address":"803 Lake Club Dr",
    "sg:city":"Rock Hill",
    "sg:classifiers":[
        {
            "category":"Real Estate",
            "subcategory":"Real Estate Agent",
            "type":"Services"
        }
    ],
    "sg:phone":"+1 803 328 6557",
    "sg:postcode":"29732",
    "sg:province":"SC",
    "wof:name":"Bagwell Family",
    "wof:placetype":"venue"
},
  "geometry": {"coordinates":[-81.04745200000001,35.023122],"type":"Point"}
}