{
  "type": "Feature",
  "properties": {
    "addr:full":"110 Cannery Rd Easley SC 29640",
    "addr:housenumber":"110",
    "addr:postcode":"29640",
    "addr:street":"Cannery Rd",
    "iso:country":"US",
    "sg:address":"110 Cannery Rd",
    "sg:city":"Easley",
    "sg:classifiers":[
        {
            "category":"Building & Trades",
            "subcategory":"Construction",
            "type":"Services"
        }
    ],
    "sg:phone":"+1 864 859 8521",
    "sg:postcode":"29640",
    "sg:province":"SC",
    "sg:tags":[
        "house"
    ],
    "wof:name":"Custom Home Wiring Inc",
    "wof:placetype":"venue"
},
  "geometry": {"coordinates":[-82.598139,34.88313],"type":"Point"}
}