{
  "type": "Feature",
  "properties": {
    "iso:country":"US",
    "sg:address":"9 Hardy St",
    "sg:city":"Williamston",
    "sg:classifiers":[
        {
            "category":"Building & Trades",
            "subcategory":"Construction",
            "type":"Services"
        }
    ],
    "sg:phone":"+1 864 847 9783",
    "sg:postcode":"29697",
    "sg:province":"SC",
    "sg:tags":[
        "carpentry",
        "contractor"
    ],
    "wof:name":"Rumsey & Son",
    "wof:placetype":"venue"
},
  "geometry": {"coordinates":[-82.49336099999999,34.618324],"type":"Point"}
}