{
  "type": "Feature",
  "properties": {
    "iso:country":"US",
    "sg:address":"202 N Main St",
    "sg:city":"Abbeville",
    "sg:classifiers":[
        {
            "category":"Restaurant",
            "type":"Food & Drink"
        }
    ],
    "sg:phone":"+1 864 459 9200",
    "sg:postcode":"29620",
    "sg:province":"SC",
    "sg:tags":[
        "parlor",
        "ice",
        "cream"
    ],
    "wof:name":"Abbeville's Ice Cream Parlor",
    "wof:placetype":"venue"
},
  "geometry": {"coordinates":[-82.381108,34.179958],"type":"Point"}
}