{
  "type": "Feature",
  "properties": {
    "iso:country":"US",
    "sg:address":"427 S Dave Lyle Blvd",
    "sg:city":"Rock Hill",
    "sg:classifiers":[
        {
            "category":"Health Services",
            "subcategory":"Doctor",
            "type":"Services"
        }
    ],
    "sg:phone":"+1 803 328 0858",
    "sg:postcode":"29730",
    "sg:province":"SC",
    "sg:tags":[
        "dentist"
    ],
    "wof:name":"D C Mc Duffie III DDS",
    "wof:placetype":"venue"
},
  "geometry": {"coordinates":[-81.031513,34.924738],"type":"Point"}
}