{
  "type": "Feature",
  "properties": {
    "addr:full":"24 Shelter Cove Ln Hilton Head Isle SC 29928",
    "addr:housenumber":"24",
    "addr:postcode":"29928",
    "addr:street":"Shelter Cove Ln",
    "iso:country":"US",
    "sg:address":"24 Shelter Cove Ln",
    "sg:city":"Hilton Head Isle",
    "sg:classifiers":[
        {
            "category":"Shopping",
            "subcategory":"Department Store",
            "type":"Retail Goods"
        }
    ],
    "sg:phone":"+1 843 341 2088",
    "sg:postcode":"29928",
    "sg:province":"SC",
    "wof:name":"Saks Fifth Avenue",
    "wof:placetype":"venue"
},
  "geometry": {"coordinates":[-80.723457,32.181857],"type":"Point"}
}