{
  "type": "Feature",
  "properties": {
    "iso:country":"US",
    "sg:address":"189 Fleming Ln",
    "sg:city":"Winnsboro",
    "sg:classifiers":[
        {
            "category":"Freight",
            "type":"Transportation"
        }
    ],
    "sg:phone":"+1 803 635 1696",
    "sg:postcode":"29180",
    "sg:province":"SC",
    "sg:tags":[
        "operator",
        "local",
        "trucking"
    ],
    "wof:name":"Mobley Trucking",
    "wof:placetype":"venue"
},
  "geometry": {"coordinates":[-81.151441,34.302991],"type":"Point"}
}