{
  "type": "Feature",
  "properties": {
    "iso:country":"US",
    "sg:address":"1480 US Hwy 221",
    "sg:city":"Greenwood",
    "sg:classifiers":[
        {
            "category":"Autos & Motor Vehicles",
            "subcategory":"Auto Supplies",
            "type":"Retail Goods"
        }
    ],
    "sg:phone":"+1 864 229 5506",
    "sg:postcode":"29649",
    "sg:province":"SC",
    "sg:tags":[
        "tire"
    ],
    "wof:name":"Harling's Discount Tire Market",
    "wof:placetype":"venue"
},
  "geometry": {"coordinates":[-82.14269400000001,34.210294],"type":"Point"}
}