{
  "type": "Feature",
  "properties": {
    "iso:country":"US",
    "sg:address":"126 Firehouse Ln",
    "sg:city":"Pineville",
    "sg:classifiers":[
        {
            "category":"Government",
            "subcategory":"Fire Station",
            "type":"Public Place"
        }
    ],
    "sg:phone":"+1 843 567 2219",
    "sg:postcode":"29468",
    "sg:province":"SC",
    "sg:tags":[
        "department"
    ],
    "wof:name":"Pineville-Russellville Fire",
    "wof:placetype":"venue"
},
  "geometry": {"coordinates":[-79.99142999999999,33.424133],"type":"Point"}
}