{
  "type": "Feature",
  "properties": {
    "iso:country":"US",
    "sg:address":"484 N Brooks St",
    "sg:city":"Manning",
    "sg:classifiers":[
        {
            "category":"Food & Beverages",
            "subcategory":"Groceries & Convenience Stores",
            "type":"Retail Goods"
        }
    ],
    "sg:phone":"+1 803 435 8111",
    "sg:postcode":"29102",
    "sg:province":"SC",
    "wof:name":"Thrifty Mart",
    "wof:placetype":"venue"
},
  "geometry": {"coordinates":[-80.209377,33.704298],"type":"Point"}
}