{
  "type": "Feature",
  "properties": {
    "iso:country":"US",
    "sg:address":"424 Gentry Memorial Hwy",
    "sg:city":"Easley",
    "sg:classifiers":[
        {
            "category":"Home & Garden",
            "subcategory":"Garden Supply",
            "type":"Retail Goods"
        }
    ],
    "sg:phone":"+1 864 855 3464",
    "sg:postcode":"29640",
    "sg:province":"SC",
    "sg:tags":[
        "center"
    ],
    "wof:name":"Plant N Pot Shop",
    "wof:placetype":"venue"
},
  "geometry": {"coordinates":[-82.62866699999999,34.837413],"type":"Point"}
}