{
  "type": "Feature",
  "properties": {
    "addr:full":"32 Partridge Cir Beaufort SC 29907",
    "addr:housenumber":"32",
    "addr:postcode":"29907",
    "addr:street":"Partridge Cir",
    "iso:country":"US",
    "sg:address":"32 Partridge Cir",
    "sg:city":"Beaufort",
    "sg:classifiers":[
        {
            "category":"Building & Trades",
            "subcategory":"Construction",
            "type":"Services"
        }
    ],
    "sg:phone":"+1 843 522 1276",
    "sg:postcode":"29907",
    "sg:province":"SC",
    "sg:tags":[
        "house"
    ],
    "wof:name":"North Star Construction",
    "wof:placetype":"venue"
},
  "geometry": {"coordinates":[-80.657678,32.460836],"type":"Point"}
}