{
  "type": "Feature",
  "properties": {
    "iso:country":"US",
    "sg:address":"4 S Brooks St",
    "sg:city":"Manning",
    "sg:classifiers":[
        {
            "category":"Manufacturing",
            "subcategory":"Printing",
            "type":"Manufacturing & Wholesale Goods"
        }
    ],
    "sg:phone":"+1 803 435 8422",
    "sg:postcode":"29102",
    "sg:province":"SC",
    "sg:tags":[
        "newspaper"
    ],
    "wof:name":"Manning Times",
    "wof:placetype":"venue"
},
  "geometry": {"coordinates":[-80.21060300000001,33.695137],"type":"Point"}
}