{
  "type": "Feature",
  "properties": {
    "iso:country":"US",
    "sg:address":"546 Springfield Rd",
    "sg:city":"Spartanburg",
    "sg:classifiers":[
        {
            "category":"Building & Trades",
            "subcategory":"Construction",
            "type":"Services"
        }
    ],
    "sg:phone":"+1 864 599 9260",
    "sg:postcode":"29303",
    "sg:province":"SC",
    "sg:tags":[
        "product",
        "asphalt"
    ],
    "wof:name":"Asphalt Associates Inc",
    "wof:placetype":"venue"
},
  "geometry": {"coordinates":[-82.006158,35.002539],"type":"Point"}
}