{
  "type": "Feature",
  "properties": {
    "addr:full":"1630 Heyward Brockington Rd Columbia SC 29203",
    "addr:housenumber":"1630",
    "addr:postcode":"29203",
    "addr:street":"Heyward Brockington Rd",
    "iso:country":"US",
    "sg:address":"1630 Heyward Brockington Rd",
    "sg:city":"Columbia",
    "sg:classifiers":[
        {
            "category":"Organizations",
            "subcategory":"Religious Organization",
            "type":"Services"
        }
    ],
    "sg:phone":"+1 803 754 0813",
    "sg:postcode":"29203",
    "sg:province":"SC",
    "sg:tags":[
        "church"
    ],
    "wof:name":"Way Of The Cross Church-Christ",
    "wof:placetype":"venue"
},
  "geometry": {"coordinates":[-81.05417199999999,34.102448],"type":"Point"}
}