{
  "type": "Feature",
  "properties": {
    "addr:full":"1419 Ellerbe St Columbia SC 29204",
    "addr:housenumber":"1419",
    "addr:postcode":"29204",
    "addr:street":"Ellerbe St",
    "iso:country":"US",
    "sg:address":"1419 Ellerbe St",
    "sg:city":"Columbia",
    "sg:classifiers":[
        {
            "category":"Building & Trades",
            "subcategory":"Construction",
            "type":"Services"
        }
    ],
    "sg:phone":"+1 803 754 9903",
    "sg:postcode":"29204",
    "sg:province":"SC",
    "sg:tags":[
        "contractor"
    ],
    "wof:name":"Custom Counter",
    "wof:placetype":"venue"
},
  "geometry": {"coordinates":[-80.99401899999999,34.039632],"type":"Point"}
}