{
  "type": "Feature",
  "properties": {
    "addr:full":"157 Columbia St Chester SC 29706",
    "addr:housenumber":"157",
    "addr:postcode":"29706",
    "addr:street":"Columbia St",
    "iso:country":"US",
    "sg:address":"157 Columbia St",
    "sg:city":"Chester",
    "sg:classifiers":[
        {
            "category":"Recreation",
            "type":"Entertainment"
        }
    ],
    "sg:phone":"+1 803 581 9622",
    "sg:postcode":"29706",
    "sg:province":"SC",
    "sg:tags":[
        "center"
    ],
    "wof:name":"Ymca Chester County Branch",
    "wof:placetype":"venue"
},
  "geometry": {"coordinates":[-81.21049600000001,34.700888],"type":"Point"}
}