{
  "type": "Feature",
  "properties": {
    "iso:country":"US",
    "sg:address":"933 Caledon Ct",
    "sg:city":"Greenville",
    "sg:classifiers":[
        {
            "category":"Professional",
            "subcategory":"Advertising",
            "type":"Services"
        }
    ],
    "sg:phone":"+1 864 298 1466",
    "sg:postcode":"29615",
    "sg:province":"SC",
    "wof:name":"Henderson Advertising",
    "wof:placetype":"venue"
},
  "geometry": {"coordinates":[-82.337949,34.862007],"type":"Point"}
}