{
  "type": "Feature",
  "properties": {
    "iso:country":"US",
    "sg:address":"132 Church St",
    "sg:city":"Graniteville",
    "sg:classifiers":[
        {
            "category":"Restaurant",
            "type":"Food & Drink"
        }
    ],
    "sg:phone":"+1 803 663 7952",
    "sg:postcode":"29829",
    "sg:province":"SC",
    "wof:name":"Village Restaurant & Deli",
    "wof:placetype":"venue"
},
  "geometry": {"coordinates":[-81.804563,33.557629],"type":"Point"}
}