{
  "type": "Feature",
  "properties": {
    "iso:country":"US",
    "sg:address":"1441 Main St Ste 775",
    "sg:city":"Columbia",
    "sg:classifiers":[
        {
            "category":"Banks & Credit Unions",
            "subcategory":"Bank",
            "type":"Services"
        }
    ],
    "sg:phone":"+1 803 212 7900",
    "sg:postcode":"29201",
    "sg:province":"SC",
    "sg:website":"www.usbank.com",
    "wof:name":"U S Bank",
    "wof:placetype":"venue"
},
  "geometry": {"coordinates":[-81.035129,34.004426],"type":"Point"}
}