{
  "type": "Feature",
  "properties": {
    "iso:country":"US",
    "sg:address":"475 N Main St",
    "sg:city":"Hemingway",
    "sg:classifiers":[
        {
            "category":"Sports & Exercise",
            "subcategory":"Gym",
            "type":"Entertainment"
        }
    ],
    "sg:phone":"+1 843 558 3545",
    "sg:postcode":"29554",
    "sg:province":"SC",
    "sg:tags":[
        "club",
        "health",
        "studio",
        "gymnasium"
    ],
    "wof:name":"Curves For Women",
    "wof:placetype":"venue"
},
  "geometry": {"coordinates":[-79.446144,33.765496],"type":"Point"}
}