{
  "type": "Feature",
  "properties": {
    "iso:country":"US",
    "sg:address":"110 Shamrock Ct",
    "sg:city":"Fort Mill",
    "sg:classifiers":[
        {
            "category":"Freight",
            "type":"Transportation"
        }
    ],
    "sg:phone":"+1 803 548 8096",
    "sg:postcode":"29715",
    "sg:province":"SC",
    "sg:tags":[
        "operator",
        "local",
        "trucking"
    ],
    "wof:name":"TNT of York County Inc",
    "wof:placetype":"venue"
},
  "geometry": {"coordinates":[-80.94772399999999,35.004507],"type":"Point"}
}