{
  "type": "Feature",
  "properties": {
    "iso:country":"US",
    "sg:address":"321 Pinehurst Dr",
    "sg:city":"Greenwood",
    "sg:classifiers":[
        {
            "category":"Real Estate",
            "subcategory":"Real Estate Agent",
            "type":"Services"
        }
    ],
    "sg:phone":"+1 864 229 7139",
    "sg:postcode":"29646",
    "sg:province":"SC",
    "wof:name":"Real Estate Inspctors Grenwood",
    "wof:placetype":"venue"
},
  "geometry": {"coordinates":[-82.063542,34.214541],"type":"Point"}
}