{
  "type": "Feature",
  "properties": {
    "iso:country":"US",
    "sg:address":"115 Beattie Park Rd",
    "sg:city":"Piedmont",
    "sg:classifiers":[
        {
            "category":"Health Services",
            "subcategory":"Doctor",
            "type":"Services"
        }
    ],
    "sg:phone":"+1 864 845 3331",
    "sg:postcode":"29673",
    "sg:province":"SC",
    "sg:tags":[
        "physician",
        "surgeon"
    ],
    "wof:name":"Piedmont Family Practice",
    "wof:placetype":"venue"
},
  "geometry": {"coordinates":[-82.470041,34.6987],"type":"Point"}
}