{
  "type": "Feature",
  "properties": {
    "addr:full":"1161 Parkway Dr Mt Pleasant SC 29464",
    "addr:housenumber":"1161",
    "addr:postcode":"29464",
    "addr:street":"Parkway Dr",
    "iso:country":"US",
    "sg:address":"1161 Parkway Dr",
    "sg:city":"Mt Pleasant",
    "sg:classifiers":[
        {
            "category":"Professional",
            "subcategory":"Management & Consulting",
            "type":"Services"
        }
    ],
    "sg:phone":"+1 843 881 3000",
    "sg:postcode":"29464",
    "sg:province":"SC",
    "sg:tags":[
        "consultant",
        "energy",
        "conservation"
    ],
    "sg:website":"www.herritage.com",
    "wof:name":"Energy Auditors Inc",
    "wof:placetype":"venue"
},
  "geometry": {"coordinates":[-79.820503,32.842228],"type":"Point"}
}