{
  "type": "Feature",
  "properties": {
    "iso:country":"US",
    "sg:address":"1219 Montague Ave Exd",
    "sg:city":"Greenwood",
    "sg:classifiers":[
        {
            "category":"Shopping",
            "subcategory":"Shoes",
            "type":"Retail Goods"
        }
    ],
    "sg:phone":"+1 864 229 2777",
    "sg:postcode":"29649",
    "sg:province":"SC",
    "wof:name":"Augusta Commons Stride Rite",
    "wof:placetype":"venue"
},
  "geometry": {"coordinates":[-82.178584,34.212128],"type":"Point"}
}