{
  "type": "Feature",
  "properties": {
    "iso:country":"US",
    "sg:address":"2216 Spring Hill Rd",
    "sg:city":"Gilbert",
    "sg:classifiers":[
        {
            "category":"Manufacturing",
            "subcategory":"Furniture",
            "type":"Manufacturing & Wholesale Goods"
        },
        {
            "category":"Home & Garden",
            "subcategory":"Furniture",
            "type":"Retail Goods"
        }
    ],
    "sg:phone":"+1 803 892 3787",
    "sg:postcode":"29054",
    "sg:province":"SC",
    "sg:tags":[
        "cabinet",
        "wood",
        "mfg"
    ],
    "wof:name":"Gilbert Cabinet & Millwork Co",
    "wof:placetype":"venue"
},
  "geometry": {"coordinates":[-81.388825,33.939801],"type":"Point"}
}