{
  "type": "Feature",
  "properties": {
    "iso:country":"US",
    "sg:address":"13975 Long Creek Hwy",
    "sg:city":"Long Creek",
    "sg:classifiers":[
        {
            "category":"Food & Beverages",
            "subcategory":"Specialty",
            "type":"Retail Goods"
        }
    ],
    "sg:phone":"+1 864 647 5112",
    "sg:postcode":"29658",
    "sg:province":"SC",
    "sg:tags":[
        "water",
        "bulk",
        "company"
    ],
    "wof:name":"Round Mountain Apple Orchard",
    "wof:placetype":"venue"
},
  "geometry": {"coordinates":[-83.27101399999999,34.798012],"type":"Point"}
}