{
  "type": "Feature",
  "properties": {
    "addr:full":"1441 Main St Columbia SC 29201",
    "addr:housenumber":"1441",
    "addr:postcode":"29201",
    "addr:street":"Main St",
    "iso:country":"US",
    "sg:address":"1441 Main St",
    "sg:city":"Columbia",
    "sg:classifiers":[
        {
            "category":"Professional",
            "subcategory":"Lawyer & Legal Services",
            "type":"Services"
        }
    ],
    "sg:phone":"+1 803 540 2129",
    "sg:postcode":"29201",
    "sg:province":"SC",
    "sg:tags":[
        "attorney"
    ],
    "wof:name":"Joan W Hartley",
    "wof:placetype":"venue"
},
  "geometry": {"coordinates":[-81.035167,34.004709],"type":"Point"}
}