{
  "type": "Feature",
  "properties": {
    "addr:full":"784 Friendship Church Rd Nesmith SC 29580",
    "addr:housenumber":"784",
    "addr:postcode":"29580",
    "addr:street":"Friendship Church Rd",
    "iso:country":"US",
    "sg:address":"784 Friendship Church Rd",
    "sg:city":"Nesmith",
    "sg:phone":"+1 843 382 2888",
    "sg:postcode":"29580",
    "sg:province":"SC",
    "sg:tags":[
        "farm",
        "soybean",
        "cotton"
    ],
    "wof:name":"Lakewood Plantation",
    "wof:placetype":"venue"
},
  "geometry": {"coordinates":[-79.57324699999999,33.694603],"type":"Point"}
}