{
  "type": "Feature",
  "properties": {
    "iso:country":"US",
    "sg:address":"35 Magnolia St",
    "sg:city":"York",
    "sg:classifiers":[
        {
            "category":"Shopping",
            "type":"Retail Goods"
        }
    ],
    "sg:phone":"+1 803 628 1838",
    "sg:postcode":"29745",
    "sg:province":"SC",
    "sg:tags":[
        "picture",
        "frame"
    ],
    "wof:name":"Frame Outlet",
    "wof:placetype":"venue"
},
  "geometry": {"coordinates":[-81.244586,35.002075],"type":"Point"}
}