{
  "type": "Feature",
  "properties": {
    "iso:country":"US",
    "sg:address":"225 S Limestone St",
    "sg:city":"Gaffney",
    "sg:classifiers":[
        {
            "category":"Organizations",
            "subcategory":"Professional Association",
            "type":"Services"
        }
    ],
    "sg:phone":"+1 864 489 5721",
    "sg:postcode":"29340",
    "sg:province":"SC",
    "sg:tags":[
        "chambers",
        "commerce"
    ],
    "sg:website":"www.cherokeechamber.org",
    "wof:name":"Cherokee County Chamber-Cmmrc",
    "wof:placetype":"venue"
},
  "geometry": {"coordinates":[-81.650742,35.071067],"type":"Point"}
}