{
  "type": "Feature",
  "properties": {
    "addr:full":"1605 Cedar Lane Rd Greenville SC 29617",
    "addr:housenumber":"1605",
    "addr:postcode":"29617",
    "addr:street":"Cedar Lane Rd",
    "iso:country":"US",
    "sg:address":"1605 Cedar Lane Rd",
    "sg:city":"Greenville",
    "sg:classifiers":[
        {
            "category":"Restaurant",
            "type":"Food & Drink"
        }
    ],
    "sg:phone":"+1 864 246 8880",
    "sg:postcode":"29617",
    "sg:province":"SC",
    "wof:name":"Westwood Restaurant",
    "wof:placetype":"venue"
},
  "geometry": {"coordinates":[-82.44713400000001,34.879178],"type":"Point"}
}