{
  "type": "Feature",
  "properties": {
    "iso:country":"US",
    "sg:address":"100 Augusta Dr",
    "sg:city":"Greenville",
    "sg:classifiers":[
        {
            "category":"Freight",
            "type":"Transportation"
        }
    ],
    "sg:phone":"+1 864 422 2588",
    "sg:postcode":"29605",
    "sg:province":"SC",
    "sg:website":"www.locketransportation.com",
    "wof:name":"Locke Transportation Inc",
    "wof:placetype":"venue"
},
  "geometry": {"coordinates":[-82.39420699999999,34.822803],"type":"Point"}
}