{
  "type": "Feature",
  "properties": {
    "iso:country":"US",
    "sg:address":"2407 S Irby St",
    "sg:city":"Florence",
    "sg:classifiers":[
        {
            "category":"Home & Garden",
            "subcategory":"Building Materials",
            "type":"Retail Goods"
        }
    ],
    "sg:phone":"+1 843 664 8877",
    "sg:postcode":"29505",
    "sg:province":"SC",
    "wof:name":"South Florence Building Supply",
    "wof:placetype":"venue"
},
  "geometry": {"coordinates":[-79.776939,34.127485],"type":"Point"}
}