{
  "type": "Feature",
  "properties": {
    "addr:full":"3595 US Hwy 15 Sumter SC 29153",
    "addr:housenumber":"3595",
    "addr:postcode":"29153",
    "addr:street":"Us Hwy 15",
    "iso:country":"US",
    "sg:address":"3595 US Hwy 15",
    "sg:city":"Sumter",
    "sg:classifiers":[
        {
            "category":"Real Estate",
            "subcategory":"Real Estate Operator",
            "type":"Services"
        }
    ],
    "sg:phone":"+1 803 469 0417",
    "sg:postcode":"29153",
    "sg:province":"SC",
    "sg:tags":[
        "building",
        "nonresidential"
    ],
    "wof:name":"Proworks Properties LLC",
    "wof:placetype":"venue"
},
  "geometry": {"coordinates":[-80.324642,34.019001],"type":"Point"}
}