{
  "type": "Feature",
  "properties": {
    "iso:country":"US",
    "sg:address":"419 79th Ave N",
    "sg:city":"Myrtle Beach",
    "sg:classifiers":[
        {
            "category":"Real Estate",
            "subcategory":"Real Estate Agent",
            "type":"Services"
        }
    ],
    "sg:phone":"+1 843 449 3948",
    "sg:postcode":"29572",
    "sg:province":"SC",
    "wof:name":"Exit Grand Strand Properties",
    "wof:placetype":"venue"
},
  "geometry": {"coordinates":[-78.815314,33.748245],"type":"Point"}
}