{
  "type": "Feature",
  "properties": {
    "iso:country":"US",
    "sg:address":"7505 Irmo Dr",
    "sg:city":"Columbia",
    "sg:classifiers":[
        {
            "category":"Professional",
            "subcategory":"Research",
            "type":"Services"
        }
    ],
    "sg:phone":"+1 803 732 5770",
    "sg:postcode":"29212",
    "sg:province":"SC",
    "sg:tags":[
        "environmental",
        "ecological"
    ],
    "wof:name":"Enviro-Test Svc",
    "wof:placetype":"venue"
},
  "geometry": {"coordinates":[-81.192401,34.088396],"type":"Point"}
}