{
  "type": "Feature",
  "properties": {
    "iso:country":"US",
    "sg:address":"3556 Earls Bridge Rd",
    "sg:city":"Easley",
    "sg:classifiers":[
        {
            "category":"Personal",
            "subcategory":"Beauty Salon",
            "type":"Services"
        }
    ],
    "sg:phone":"+1 864 836 3915",
    "sg:postcode":"29640",
    "sg:province":"SC",
    "wof:name":"Melodie's Hair Styling",
    "wof:placetype":"venue"
},
  "geometry": {"coordinates":[-82.551569,34.962752],"type":"Point"}
}