{
  "type": "Feature",
  "properties": {
    "addr:full":"205 Tribble St Anderson SC 29625",
    "addr:housenumber":"205",
    "addr:postcode":"29625",
    "addr:street":"Tribble St",
    "iso:country":"US",
    "sg:address":"205 Tribble St",
    "sg:city":"Anderson",
    "sg:classifiers":[
        {
            "category":"Retail",
            "subcategory":"Auto Repair",
            "type":"Services"
        }
    ],
    "sg:phone":"+1 864 716 0903",
    "sg:postcode":"29625",
    "sg:province":"SC",
    "sg:tags":[
        "repairing",
        "automobile"
    ],
    "wof:name":"Willie's Automotive",
    "wof:placetype":"venue"
},
  "geometry": {"coordinates":[-82.65494200000001,34.50671],"type":"Point"}
}