{
  "type": "Feature",
  "properties": {
    "addr:full":"730 S Pleasantburg Dr Greenville SC 29605",
    "addr:housenumber":"730",
    "addr:postcode":"29605",
    "addr:street":"S Pleasantburg Dr",
    "iso:country":"US",
    "sg:address":"730 S Pleasantburg Dr",
    "sg:city":"Greenville",
    "sg:classifiers":[
        {
            "category":"Education",
            "subcategory":"Vocational School",
            "type":"Public Place"
        }
    ],
    "sg:phone":"+1 864 467 0022",
    "sg:postcode":"29605",
    "sg:province":"SC",
    "wof:name":"Job Corps Admissions Office",
    "wof:placetype":"venue"
},
  "geometry": {"coordinates":[-82.36923,34.821698],"type":"Point"}
}