{
  "type": "Feature",
  "properties": {
    "iso:country":"US",
    "sg:address":"245 S Harvin St",
    "sg:city":"Sumter",
    "sg:classifiers":[
        {
            "category":"Shopping",
            "type":"Retail Goods"
        }
    ],
    "sg:phone":"+1 803 778 0264",
    "sg:postcode":"29150",
    "sg:province":"SC",
    "sg:tags":[
        "chemical"
    ],
    "wof:name":"Giant Resource Recovery",
    "wof:placetype":"venue"
},
  "geometry": {"coordinates":[-80.34044900000001,33.914458],"type":"Point"}
}