{
  "type": "Feature",
  "properties": {
    "iso:country":"US",
    "sg:address":"3855 Olivia St",
    "sg:city":"Myrtle Beach",
    "sg:classifiers":[
        {
            "category":"Professional",
            "subcategory":"Detective & Security Services",
            "type":"Services"
        }
    ],
    "sg:phone":"+1 843 236 0218",
    "sg:postcode":"29588",
    "sg:province":"SC",
    "sg:tags":[
        "guard",
        "patrol"
    ],
    "wof:name":"Top Guard Security",
    "wof:placetype":"venue"
},
  "geometry": {"coordinates":[-78.996905,33.697638],"type":"Point"}
}