{
  "type": "Feature",
  "properties": {
    "addr:full":"1106 Moorehead Pl Pendleton SC 29670",
    "addr:housenumber":"1106",
    "addr:postcode":"29670",
    "addr:street":"Moorehead Pl",
    "iso:country":"US",
    "sg:address":"1106 Moorehead Pl",
    "sg:city":"Pendleton",
    "sg:classifiers":[
        {
            "category":"Real Estate",
            "subcategory":"Developer",
            "type":"Services"
        }
    ],
    "sg:phone":"+1 864 261 8872",
    "sg:postcode":"29670",
    "sg:province":"SC",
    "wof:name":"Don Garrison",
    "wof:placetype":"venue"
},
  "geometry": {"coordinates":[-82.737233,34.603038],"type":"Point"}
}