{
  "type": "Feature",
  "properties": {
    "iso:country":"US",
    "sg:address":"206 29th Ave S",
    "sg:city":"Myrtle Beach",
    "sg:classifiers":[
        {
            "category":"Travel",
            "subcategory":"Hotels & Motels",
            "type":"Entertainment"
        }
    ],
    "sg:phone":"+1 843 448 3063",
    "sg:postcode":"29577",
    "sg:province":"SC",
    "sg:tags":[
        "breakfast",
        "accommodation",
        "bed"
    ],
    "wof:name":"Cain House Bed & Breakfast",
    "wof:placetype":"venue"
},
  "geometry": {"coordinates":[-78.916231,33.662761],"type":"Point"}
}