{
  "type": "Feature",
  "properties": {
    "iso:country":"US",
    "sg:address":"160 Bridwell Ct",
    "sg:city":"Six Mile",
    "sg:classifiers":[
        {
            "category":"Health Services",
            "subcategory":"Doctor",
            "type":"Services"
        }
    ],
    "sg:phone":"+1 864 868 6565",
    "sg:postcode":"29682",
    "sg:province":"SC",
    "sg:tags":[
        "clinic"
    ],
    "wof:name":"Adaptive Medical",
    "wof:placetype":"venue"
},
  "geometry": {"coordinates":[-82.82627100000001,34.818966],"type":"Point"}
}