{
  "type": "Feature",
  "properties": {
    "iso:country":"US",
    "sg:address":"1204 Main St",
    "sg:city":"Columbia",
    "sg:classifiers":[
        {
            "category":"Communications",
            "type":"Services"
        }
    ],
    "sg:phone":"+1 803 748 7171",
    "sg:postcode":"29201",
    "sg:province":"SC",
    "sg:tags":[
        "web",
        "design"
    ],
    "wof:name":"Web Site Co",
    "wof:placetype":"venue"
},
  "geometry": {"coordinates":[-81.033699,34.0019],"type":"Point"}
}