{
  "type": "Feature",
  "properties": {
    "addr:full":"1538 Cherokee Blvd Elgin SC 29045",
    "addr:housenumber":"1538",
    "addr:postcode":"29045",
    "addr:street":"Cherokee Blvd",
    "iso:country":"US",
    "sg:address":"1538 Cherokee Blvd",
    "sg:city":"Elgin",
    "sg:classifiers":[
        {
            "category":"Food & Beverages",
            "subcategory":"Groceries & Convenience Stores",
            "type":"Retail Goods"
        }
    ],
    "sg:phone":"+1 803 699 1999",
    "sg:postcode":"29045",
    "sg:province":"SC",
    "wof:name":"Cherokee Quik Stop",
    "wof:placetype":"venue"
},
  "geometry": {"coordinates":[-80.84578999999999,34.171411],"type":"Point"}
}