{
  "type": "Feature",
  "properties": {
    "iso:country":"US",
    "sg:address":"186 Saluda St",
    "sg:city":"Chester",
    "sg:classifiers":[
        {
            "category":"Manufacturing",
            "subcategory":"Tools & Machinery",
            "type":"Manufacturing & Wholesale Goods"
        }
    ],
    "sg:phone":"+1 803 377 8177",
    "sg:postcode":"29706",
    "sg:province":"SC",
    "sg:tags":[
        "equipment",
        "printing"
    ],
    "wof:name":"Textile Arts & Film",
    "wof:placetype":"venue"
},
  "geometry": {"coordinates":[-81.20180499999999,34.714148],"type":"Point"}
}