{
  "type": "Feature",
  "properties": {
    "addr:full":"100 E Coffee St Greenville SC 29601",
    "addr:housenumber":"100",
    "addr:postcode":"29601",
    "addr:street":"E Coffee St",
    "iso:country":"US",
    "sg:address":"100 E Coffee St",
    "sg:city":"Greenville",
    "sg:classifiers":[
        {
            "category":"Professional",
            "subcategory":"Lawyer & Legal Services",
            "type":"Services"
        }
    ],
    "sg:phone":"+1 864 242 6440",
    "sg:postcode":"29601",
    "sg:province":"SC",
    "sg:tags":[
        "attorney"
    ],
    "wof:name":"Alexander Hray",
    "wof:placetype":"venue"
},
  "geometry": {"coordinates":[-82.39694299999999,34.851058],"type":"Point"}
}