{
  "type": "Feature",
  "properties": {
    "iso:country":"US",
    "sg:address":"478 US Hwy 378 W",
    "sg:city":"Lexington",
    "sg:classifiers":[
        {
            "category":"Professional",
            "subcategory":"Engineering",
            "type":"Services"
        }
    ],
    "sg:phone":"+1 803 808 8020",
    "sg:postcode":"29072",
    "sg:province":"SC",
    "sg:tags":[
        "engineer"
    ],
    "wof:name":"K & P Engineering Inc",
    "wof:placetype":"venue"
},
  "geometry": {"coordinates":[-81.282592,33.990855],"type":"Point"}
}