{
  "type": "Feature",
  "properties": {
    "addr:full":"3020 Crest Haven Dr Dalzell SC 29040",
    "addr:housenumber":"3020",
    "addr:postcode":"29040",
    "addr:street":"Crest Haven Dr",
    "iso:country":"US",
    "sg:address":"3020 Crest Haven Dr",
    "sg:city":"Dalzell",
    "sg:classifiers":[
        {
            "category":"Building & Trades",
            "subcategory":"Construction",
            "type":"Services"
        }
    ],
    "sg:phone":"+1 803 499 3990",
    "sg:postcode":"29040",
    "sg:province":"SC",
    "sg:tags":[
        "contractor"
    ],
    "wof:name":"Scott Builders",
    "wof:placetype":"venue"
},
  "geometry": {"coordinates":[-80.41423500000001,34.067731],"type":"Point"}
}