{
  "type": "Feature",
  "properties": {
    "addr:full":"2478 Stribling Cir Lancaster SC 29720",
    "addr:postcode":"2478;29720",
    "addr:street":"Stribling Cir",
    "iso:country":"US",
    "sg:address":"2478 Stribling Cir",
    "sg:city":"Lancaster",
    "sg:classifiers":[
        {
            "category":"Building & Trades",
            "subcategory":"Construction",
            "type":"Services"
        }
    ],
    "sg:phone":"+1 803 285 7144",
    "sg:postcode":"29720",
    "sg:province":"SC",
    "sg:tags":[
        "house"
    ],
    "wof:name":"Ej S Home Improvements",
    "wof:placetype":"venue"
},
  "geometry": {"coordinates":[-80.84550400000001,34.712441],"type":"Point"}
}