{
  "type": "Feature",
  "properties": {
    "iso:country":"US",
    "sg:address":"2219 Hunter Creek Dr",
    "sg:city":"Charleston",
    "sg:classifiers":[
        {
            "category":"Building & Trades",
            "subcategory":"Construction",
            "type":"Services"
        }
    ],
    "sg:phone":"+1 843 556 7346",
    "sg:postcode":"29414",
    "sg:province":"SC",
    "sg:tags":[
        "hanging",
        "contractor"
    ],
    "wof:name":"Paul Grooms Painting",
    "wof:placetype":"venue"
},
  "geometry": {"coordinates":[-80.07685,32.838621],"type":"Point"}
}