{
  "type": "Feature",
  "properties": {
    "addr:full":"928 US Hwy 123 Seneca SC 29678",
    "addr:housenumber":"928",
    "addr:postcode":"29678",
    "addr:street":"Us Hwy 123",
    "iso:country":"US",
    "sg:address":"928 US Hwy 123",
    "sg:city":"Seneca",
    "sg:classifiers":[
        {
            "category":"Wholesale",
            "subcategory":"Electrical",
            "type":"Manufacturing & Wholesale Goods"
        }
    ],
    "sg:phone":"+1 864 885 0454",
    "sg:postcode":"29678",
    "sg:province":"SC",
    "sg:tags":[
        "computer",
        "electronic"
    ],
    "wof:name":"Advanced Electronics",
    "wof:placetype":"venue"
},
  "geometry": {"coordinates":[-82.976809,34.693236],"type":"Point"}
}