{
  "type": "Feature",
  "properties": {
    "iso:country":"US",
    "sg:address":"1310 Lady St",
    "sg:city":"Columbia",
    "sg:classifiers":[
        {
            "category":"Insurance",
            "subcategory":"Insurance Agent",
            "type":"Services"
        }
    ],
    "sg:phone":"+1 803 779 6133",
    "sg:postcode":"29201",
    "sg:province":"SC",
    "sg:tags":[
        "accident"
    ],
    "wof:name":"Twin Medical",
    "wof:placetype":"venue"
},
  "geometry": {"coordinates":[-81.031026,34.003486],"type":"Point"}
}