{
  "type": "Feature",
  "properties": {
    "iso:country":"US",
    "sg:address":"2 International Ct",
    "sg:city":"Greenville",
    "sg:classifiers":[
        {
            "category":"Wholesale",
            "subcategory":"Home Furnishings",
            "type":"Manufacturing & Wholesale Goods"
        }
    ],
    "sg:phone":"+1 864 234 0037",
    "sg:postcode":"29607",
    "sg:province":"SC",
    "wof:name":"Palmetto Framing Supplies",
    "wof:placetype":"venue"
},
  "geometry": {"coordinates":[-82.30814599999999,34.794893],"type":"Point"}
}