{
  "type": "Feature",
  "properties": {
    "addr:full":"605 S Ocean Blvd Myrtle Beach SC 29577",
    "addr:housenumber":"605",
    "addr:postcode":"29577",
    "addr:street":"S Ocean Blvd",
    "iso:country":"US",
    "sg:address":"605 S Ocean Blvd",
    "sg:city":"Myrtle Beach",
    "sg:classifiers":[
        {
            "category":"Travel",
            "subcategory":"Hotels & Motels",
            "type":"Entertainment"
        }
    ],
    "sg:phone":"+1 843 448 7007",
    "sg:postcode":"29577",
    "sg:province":"SC",
    "sg:website":"www.seadunesoceanfront.com",
    "wof:name":"Sea Dunes Ocean Front",
    "wof:placetype":"venue"
},
  "geometry": {"coordinates":[-78.89352700000001,33.679971],"type":"Point"}
}