{
  "type": "Feature",
  "properties": {
    "addr:full":"402 Old Trolley Rd Summerville SC 29485",
    "addr:housenumber":"402",
    "addr:postcode":"29485",
    "addr:street":"Old Trolley Rd",
    "iso:country":"US",
    "sg:address":"402 Old Trolley Rd",
    "sg:city":"Summerville",
    "sg:classifiers":[
        {
            "category":"Home & Garden",
            "subcategory":"Household Appliances",
            "type":"Retail Goods"
        }
    ],
    "sg:phone":"+1 843 875 4673",
    "sg:postcode":"29485",
    "sg:province":"SC",
    "wof:name":"Deltin Vacuum",
    "wof:placetype":"venue"
},
  "geometry": {"coordinates":[-80.179114,32.989765],"type":"Point"}
}