{
  "type": "Feature",
  "properties": {
    "addr:full":"3200 McCrays Mill Rd Sumter SC 29154",
    "addr:housenumber":"3200",
    "addr:postcode":"29154",
    "addr:street":"Mccrays Mill Rd",
    "iso:country":"US",
    "sg:address":"3200 McCrays Mill Rd",
    "sg:city":"Sumter",
    "sg:classifiers":[
        {
            "category":"Shopping",
            "subcategory":"Used Merchandise",
            "type":"Retail Goods"
        }
    ],
    "sg:phone":"+1 803 481 2995",
    "sg:postcode":"29154",
    "sg:province":"SC",
    "wof:name":"Primitive Cottage Antiques",
    "wof:placetype":"venue"
},
  "geometry": {"coordinates":[-80.419603,33.891072],"type":"Point"}
}