{
  "type": "Feature",
  "properties": {
    "iso:country":"US",
    "sg:address":"802 S Murray Ave",
    "sg:city":"Anderson",
    "sg:classifiers":[
        {
            "category":"Retail",
            "subcategory":"Auto Repair",
            "type":"Services"
        }
    ],
    "sg:phone":"+1 864 225 8481",
    "sg:postcode":"29626",
    "sg:province":"SC",
    "sg:tags":[
        "repairing",
        "automobile"
    ],
    "wof:name":"Battery & Electric Shop",
    "wof:placetype":"venue"
},
  "geometry": {"coordinates":[-82.651037,34.499169],"type":"Point"}
}