{
  "type": "Feature",
  "properties": {
    "iso:country":"US",
    "sg:address":"43 C Trotter Rd",
    "sg:city":"West Columbia",
    "sg:classifiers":[
        {
            "category":"Manufacturing",
            "subcategory":"Apparel",
            "type":"Manufacturing & Wholesale Goods"
        },
        {
            "category":"Home & Garden",
            "subcategory":"Home Furnishings",
            "type":"Retail Goods"
        }
    ],
    "sg:phone":"+1 803 796 1924",
    "sg:postcode":"29169",
    "sg:province":"SC",
    "sg:tags":[
        "made",
        "mfg",
        "covering",
        "window",
        "install",
        "curtain",
        "drapery"
    ],
    "wof:name":"Magruder Window Coverings Inc",
    "wof:placetype":"venue"
},
  "geometry": {"coordinates":[-81.129271,34.006406],"type":"Point"}
}