{
  "type": "Feature",
  "properties": {
    "iso:country":"US",
    "sg:address":"825 Herman Wise Rd",
    "sg:city":"Newberry",
    "sg:classifiers":[
        {
            "category":"Building & Trades",
            "subcategory":"Construction",
            "type":"Services"
        }
    ],
    "sg:phone":"+1 803 276 7807",
    "sg:postcode":"29108",
    "sg:province":"SC",
    "sg:tags":[
        "house"
    ],
    "wof:name":"Long & Bartley Builders",
    "wof:placetype":"venue"
},
  "geometry": {"coordinates":[-81.666827,34.302303],"type":"Point"}
}