{
  "type": "Feature",
  "properties": {
    "iso:country":"US",
    "sg:address":"120 Settle Rd",
    "sg:city":"Inman",
    "sg:classifiers":[
        {
            "category":"Shopping",
            "type":"Retail Goods"
        }
    ],
    "sg:phone":"+1 864 472 2017",
    "sg:postcode":"29349",
    "sg:province":"SC",
    "sg:tags":[
        "chemical"
    ],
    "wof:name":"Helena Chemical Co",
    "wof:placetype":"venue"
},
  "geometry": {"coordinates":[-82.042123,35.028649],"type":"Point"}
}