{
  "type": "Feature",
  "properties": {
    "iso:country":"US",
    "sg:address":"151 Oakland Ave",
    "sg:city":"Rock Hill",
    "sg:classifiers":[
        {
            "category":"Professional",
            "subcategory":"Accounting & Tax Preparation",
            "type":"Services"
        }
    ],
    "sg:phone":"+1 803 324 1190",
    "sg:postcode":"29730",
    "sg:province":"SC",
    "sg:tags":[
        "payroll"
    ],
    "wof:name":"Paychex Inc",
    "wof:placetype":"venue"
},
  "geometry": {"coordinates":[-81.02467,34.930975],"type":"Point"}
}