{
  "type": "Feature",
  "properties": {
    "iso:country":"US",
    "sg:address":"284 Fox Catcher Dr",
    "sg:city":"Myrtle Beach",
    "sg:classifiers":[
        {
            "category":"Building & Trades",
            "subcategory":"Landscaping Services",
            "type":"Services"
        }
    ],
    "sg:phone":"+1 843 241 4120",
    "sg:postcode":"29575",
    "sg:province":"SC",
    "sg:tags":[
        "landscape"
    ],
    "wof:name":"Ocean Front Landscapes Inc",
    "wof:placetype":"venue"
},
  "geometry": {"coordinates":[-79.007845,33.67654],"type":"Point"}
}