{
  "type": "Feature",
  "properties": {
    "addr:full":"25 Hugh St Barnwell SC 29812",
    "addr:housenumber":"25",
    "addr:postcode":"29812",
    "addr:street":"Hugh St",
    "iso:country":"US",
    "sg:address":"25 Hugh St",
    "sg:city":"Barnwell",
    "sg:classifiers":[
        {
            "category":"Health Services",
            "subcategory":"Hospital",
            "type":"Services"
        }
    ],
    "sg:phone":"+1 803 259 5946",
    "sg:postcode":"29812",
    "sg:province":"SC",
    "sg:tags":[
        "mental"
    ],
    "wof:name":"Aiken Barnwell Mental Health",
    "wof:placetype":"venue"
},
  "geometry": {"coordinates":[-81.37178299999999,33.246098],"type":"Point"}
}