{
  "type": "Feature",
  "properties": {
    "iso:country":"US",
    "sg:address":"3083 Charleston Hwy",
    "sg:city":"West Columbia",
    "sg:classifiers":[
        {
            "category":"Freight",
            "type":"Transportation"
        }
    ],
    "sg:phone":"+1 803 794 2600",
    "sg:postcode":"29172",
    "sg:province":"SC",
    "sg:tags":[
        "local",
        "except",
        "trucking"
    ],
    "sg:website":"www.overnite.com",
    "wof:name":"Overnite Transportation Co",
    "wof:placetype":"venue"
},
  "geometry": {"coordinates":[-81.07680999999999,33.928395],"type":"Point"}
}