{
  "type": "Feature",
  "properties": {
    "iso:country":"US",
    "sg:address":"5868 Friendship Ln",
    "sg:city":"Myrtle Beach",
    "sg:classifiers":[
        {
            "category":"Building & Trades",
            "subcategory":"Plumbing",
            "type":"Services"
        }
    ],
    "sg:phone":"+1 843 215 6532",
    "sg:postcode":"29588",
    "sg:province":"SC",
    "sg:tags":[
        "contractor"
    ],
    "wof:name":"Sullee Enterprises Inc",
    "wof:placetype":"venue"
},
  "geometry": {"coordinates":[-79.011804,33.652636],"type":"Point"}
}