{
  "type": "Feature",
  "properties": {
    "addr:full":"102 Lea Ct Spartanburg SC 29307",
    "addr:housenumber":"102",
    "addr:postcode":"29307",
    "addr:street":"Lea Ct",
    "iso:country":"US",
    "sg:address":"102 Lea Ct",
    "sg:city":"Spartanburg",
    "sg:classifiers":[
        {
            "category":"Food & Beverages",
            "subcategory":"Groceries & Convenience Stores",
            "type":"Retail Goods"
        }
    ],
    "sg:phone":"+1 864 936 7858",
    "sg:postcode":"29307",
    "sg:province":"SC",
    "wof:name":"Jeds Place",
    "wof:placetype":"venue"
},
  "geometry": {"coordinates":[-81.861012,35.014638],"type":"Point"}
}