{
  "type": "Feature",
  "properties": {
    "iso:country":"US",
    "sg:address":"119 S Lucas St",
    "sg:city":"Walterboro",
    "sg:classifiers":[
        {
            "category":"Organizations",
            "subcategory":"Religious Organization",
            "type":"Services"
        }
    ],
    "sg:phone":"+1 843 549 5441",
    "sg:postcode":"29488",
    "sg:province":"SC",
    "sg:tags":[
        "church"
    ],
    "wof:name":"United Methodist Church",
    "wof:placetype":"venue"
},
  "geometry": {"coordinates":[-80.66442600000001,32.901703],"type":"Point"}
}