{
  "type": "Feature",
  "properties": {
    "iso:country":"US",
    "sg:address":"394 Whittaker Pkwy",
    "sg:city":"Orangeburg",
    "sg:classifiers":[
        {
            "category":"Shopping",
            "subcategory":"Department Store",
            "type":"Retail Goods"
        }
    ],
    "sg:phone":"+1 803 535 3757",
    "sg:postcode":"29115",
    "sg:province":"SC",
    "wof:name":"Silverback Wholesale Co",
    "wof:placetype":"venue"
},
  "geometry": {"coordinates":[-80.83724,33.495715],"type":"Point"}
}