{
  "type": "Feature",
  "properties": {
    "iso:country":"US",
    "sg:address":"219 Oakland Ave",
    "sg:city":"Rock Hill",
    "sg:classifiers":[
        {
            "category":"Health Services",
            "subcategory":"Doctor",
            "type":"Services"
        }
    ],
    "sg:phone":"+1 803 328 2411",
    "sg:postcode":"29730",
    "sg:province":"SC",
    "sg:tags":[
        "dentist"
    ],
    "wof:name":"Wilson & Kirol",
    "wof:placetype":"venue"
},
  "geometry": {"coordinates":[-81.026108,34.933669],"type":"Point"}
}