{
  "type": "Feature",
  "properties": {
    "iso:country":"US",
    "sg:address":"311 N Magnolia St",
    "sg:city":"Summerville",
    "sg:classifiers":[
        {
            "category":"Professional",
            "subcategory":"Research",
            "type":"Services"
        }
    ],
    "sg:phone":"+1 843 871 5383",
    "sg:postcode":"29483",
    "sg:province":"SC",
    "sg:tags":[
        "environmental",
        "ecological"
    ],
    "sg:website":"www.sabinc.net",
    "wof:name":"Sabine & Waters Inc",
    "wof:placetype":"venue"
},
  "geometry": {"coordinates":[-80.171411,33.022085],"type":"Point"}
}