{
  "type": "Feature",
  "properties": {
    "addr:full":"533 Augusta Rd North Augusta SC 29822",
    "addr:housenumber":"533",
    "addr:postcode":"29822",
    "addr:street":"Augusta Rd",
    "iso:country":"US",
    "sg:address":"533 Augusta Rd",
    "sg:city":"North Augusta",
    "sg:classifiers":[
        {
            "category":"Banks & Credit Unions",
            "subcategory":"Bank",
            "type":"Services"
        }
    ],
    "sg:phone":"+1 803 613 1576",
    "sg:postcode":"29822",
    "sg:province":"SC",
    "sg:tags":[
        "loan",
        "real estate"
    ],
    "wof:name":"Douglas Mortgage Group",
    "wof:placetype":"venue"
},
  "geometry": {"coordinates":[-81.892043,33.496713],"type":"Point"}
}