{
  "type": "Feature",
  "properties": {
    "addr:full":"143 Mapletree Ln Spartanburg SC 29303",
    "addr:housenumber":"143",
    "addr:postcode":"29303",
    "addr:street":"Mapletree Ln",
    "iso:country":"US",
    "sg:address":"143 Mapletree Ln",
    "sg:city":"Spartanburg",
    "sg:classifiers":[
        {
            "category":"Building & Trades",
            "subcategory":"Cleaning & Sanitation",
            "type":"Services"
        }
    ],
    "sg:phone":"+1 864 585 6166",
    "sg:postcode":"29303",
    "sg:province":"SC",
    "sg:tags":[
        "janitor"
    ],
    "wof:name":"W & W Svc",
    "wof:placetype":"venue"
},
  "geometry": {"coordinates":[-81.92738,34.98076],"type":"Point"}
}