{
  "type": "Feature",
  "properties": {
    "iso:country":"US",
    "sg:address":"1618 Memorial Park Rd",
    "sg:city":"Lancaster",
    "sg:classifiers":[
        {
            "category":"Restaurant",
            "type":"Food & Drink"
        }
    ],
    "sg:phone":"+1 803 289 1234",
    "sg:postcode":"29720",
    "sg:province":"SC",
    "sg:tags":[
        "eating"
    ],
    "wof:name":"Bugsyss",
    "wof:placetype":"venue"
},
  "geometry": {"coordinates":[-80.792008,34.694876],"type":"Point"}
}