{
  "type": "Feature",
  "properties": {
    "addr:full":"501 19th Ave S Myrtle Beach SC 29577",
    "addr:housenumber":"501",
    "addr:postcode":"29577",
    "addr:street":"19Th Ave S Myrtle",
    "iso:country":"US",
    "sg:address":"501 19th Ave S",
    "sg:city":"Myrtle Beach",
    "sg:classifiers":[
        {
            "category":"Government",
            "subcategory":"Office",
            "type":"Public Place"
        }
    ],
    "sg:phone":"+1 843 444 5786",
    "sg:postcode":"29577",
    "sg:province":"SC",
    "sg:tags":[
        "armed",
        "force",
        "recruiting"
    ],
    "wof:name":"Army National Guard Recruiting",
    "wof:placetype":"venue"
},
  "geometry": {"coordinates":[-78.90819,33.674837],"type":"Point"}
}