{
  "type": "Feature",
  "properties": {
    "iso:country":"US",
    "sg:address":"1940 Highway 292",
    "sg:city":"Inman",
    "sg:classifiers":[
        {
            "category":"Restaurant",
            "type":"Food & Drink"
        }
    ],
    "sg:menulink":"http://www.allmenus.com/sc/inman/129225-subway/menu/",
    "sg:phone":"+1 864 472 8882",
    "sg:postcode":"29349",
    "sg:province":"SC",
    "sg:tags":[
        "american",
        "sandwich"
    ],
    "wof:name":"Subway",
    "wof:placetype":"venue"
},
  "geometry": {"coordinates":[-82.05974399999999,35.081996],"type":"Point"}
}