{
  "type": "Feature",
  "properties": {
    "addr:full":"1 Stoney Creek Rd Hilton Head Isle SC 29928",
    "addr:housenumber":"1",
    "addr:postcode":"29928",
    "addr:street":"Stoney Creek Rd",
    "iso:country":"US",
    "sg:address":"1 Stoney Creek Rd",
    "sg:city":"Hilton Head Isle",
    "sg:classifiers":[
        {
            "category":"Organizations",
            "subcategory":"Community Association",
            "type":"Services"
        }
    ],
    "sg:phone":"+1 843 363 4137",
    "sg:postcode":"29928",
    "sg:province":"SC",
    "sg:tags":[
        "club"
    ],
    "wof:name":"Sea Pines Beach Club Sales",
    "wof:placetype":"venue"
},
  "geometry": {"coordinates":[-80.806556,32.137673],"type":"Point"}
}