{
  "type": "Feature",
  "properties": {
    "iso:country":"US",
    "sg:address":"1310 N Fraser St",
    "sg:city":"Georgetown",
    "sg:classifiers":[
        {
            "category":"Restaurant",
            "type":"Food & Drink"
        }
    ],
    "sg:menulink":"http://www.allmenus.com/sc/georgetown/129181-subway/menu/",
    "sg:phone":"+1 843 545 9452",
    "sg:postcode":"29440",
    "sg:province":"SC",
    "sg:tags":[
        "american",
        "sandwich"
    ],
    "wof:name":"Subway",
    "wof:placetype":"venue"
},
  "geometry": {"coordinates":[-79.288999,33.390816],"type":"Point"}
}