{
  "type": "Feature",
  "properties": {
    "iso:country":"US",
    "sg:address":"3730 Pearl St",
    "sg:city":"Columbia",
    "sg:classifiers":[
        {
            "category":"Autos & Motor Vehicles",
            "subcategory":"Motorcycle Sales",
            "type":"Retail Goods"
        }
    ],
    "sg:phone":"+1 803 779 6780",
    "sg:postcode":"29203",
    "sg:province":"SC",
    "wof:name":"S & J Motorcycles",
    "wof:placetype":"venue"
},
  "geometry": {"coordinates":[-81.061237,34.028954],"type":"Point"}
}