{
  "type": "Feature",
  "properties": {
    "iso:country":"US",
    "sg:address":"13781 Asheville Hwy",
    "sg:city":"Inman",
    "sg:classifiers":[
        {
            "category":"Autos & Motor Vehicles",
            "subcategory":"Automobile Sales",
            "type":"Retail Goods"
        }
    ],
    "sg:phone":"+1 864 472 2728",
    "sg:postcode":"29349",
    "sg:province":"SC",
    "sg:tags":[
        "car",
        "dealer"
    ],
    "wof:name":"Craig Automotive",
    "wof:placetype":"venue"
},
  "geometry": {"coordinates":[-82.121691,35.058147],"type":"Point"}
}