{
  "type": "Feature",
  "properties": {
    "iso:country":"US",
    "sg:address":"20 Queen St",
    "sg:city":"Charleston",
    "sg:classifiers":[
        {
            "category":"Arts & Performance",
            "subcategory":"Theater",
            "type":"Entertainment"
        }
    ],
    "sg:phone":"+1 843 722 7521",
    "sg:postcode":"29401",
    "sg:province":"SC",
    "sg:website":"www.footlightplayers.net",
    "wof:name":"Footlight Players Inc",
    "wof:placetype":"venue"
},
  "geometry": {"coordinates":[-79.92804,32.778539],"type":"Point"}
}