{
  "type": "Feature",
  "properties": {
    "iso:country":"US",
    "sg:address":"920 Anderson Dr",
    "sg:city":"Liberty",
    "sg:classifiers":[
        {
            "category":"Organizations",
            "subcategory":"Religious Organization",
            "type":"Services"
        }
    ],
    "sg:phone":"+1 864 843 6481",
    "sg:postcode":"29657",
    "sg:province":"SC",
    "sg:tags":[
        "church"
    ],
    "wof:name":"Eastside Baptist Church",
    "wof:placetype":"venue"
},
  "geometry": {"coordinates":[-82.680762,34.782473],"type":"Point"}
}