{
  "type": "Feature",
  "properties": {
    "iso:country":"US",
    "sg:address":"1504 County Line Rd",
    "sg:city":"Bradley",
    "sg:classifiers":[
        {
            "category":"Wholesale",
            "subcategory":"Toys & Hobbies",
            "type":"Manufacturing & Wholesale Goods"
        }
    ],
    "sg:phone":"+1 864 227 9800",
    "sg:postcode":"29819",
    "sg:province":"SC",
    "sg:tags":[
        "ceramic"
    ],
    "wof:name":"Rounds Enterprises",
    "wof:placetype":"venue"
},
  "geometry": {"coordinates":[-82.139933,34.044751],"type":"Point"}
}