{
  "type": "Feature",
  "properties": {
    "iso:country":"US",
    "sg:address":"806 US Hwy 17 Bus",
    "sg:city":"Mount Pleasant",
    "sg:classifiers":[
        {
            "category":"Travel",
            "subcategory":"Travel Agent",
            "type":"Entertainment"
        }
    ],
    "sg:phone":"+1 843 881 1181",
    "sg:postcode":"29464",
    "sg:province":"SC",
    "sg:tags":[
        "agency"
    ],
    "wof:name":"Chitwood",
    "wof:placetype":"venue"
},
  "geometry": {"coordinates":[-79.863214,32.794247],"type":"Point"}
}