{
  "type": "Feature",
  "properties": {
    "addr:full":"3624 Fieldmaster Dr Timmonsville SC 29161",
    "addr:housenumber":"3624",
    "addr:postcode":"29161",
    "addr:street":"Fieldmaster Dr",
    "iso:country":"US",
    "sg:address":"3624 Fieldmaster Dr",
    "sg:city":"Timmonsville",
    "sg:classifiers":[
        {
            "category":"Organizations",
            "subcategory":"Religious Organization",
            "type":"Services"
        }
    ],
    "sg:phone":"+1 843 393 1060",
    "sg:postcode":"29161",
    "sg:province":"SC",
    "sg:tags":[
        "church"
    ],
    "wof:name":"Florence Christian Ctr",
    "wof:placetype":"venue"
},
  "geometry": {"coordinates":[-79.915734,34.186879],"type":"Point"}
}