{
  "type": "Feature",
  "properties": {
    "iso:country":"US",
    "sg:address":"336 Steeple Ct",
    "sg:city":"Lexington",
    "sg:classifiers":[
        {
            "category":"Building & Trades",
            "subcategory":"Construction",
            "type":"Services"
        }
    ],
    "sg:phone":"+1 803 957 9606",
    "sg:postcode":"29073",
    "sg:province":"SC",
    "sg:tags":[
        "carpentry",
        "contractor"
    ],
    "wof:name":"Mincey Carpentry Inc",
    "wof:placetype":"venue"
},
  "geometry": {"coordinates":[-81.248002,33.920952],"type":"Point"}
}