{
  "type": "Feature",
  "properties": {
    "iso:country":"US",
    "sg:address":"2065 Savannah Hwy",
    "sg:city":"Charleston",
    "sg:classifiers":[
        {
            "category":"Insurance",
            "subcategory":"Insurance Agent",
            "type":"Services"
        }
    ],
    "sg:phone":"+1 843 556 4221",
    "sg:postcode":"29407",
    "sg:province":"SC",
    "wof:name":"A Patch Insurance Agency Inc",
    "wof:placetype":"venue"
},
  "geometry": {"coordinates":[-80.03126399999999,32.789914],"type":"Point"}
}