{
  "type": "Feature",
  "properties": {
    "iso:country":"US",
    "sg:address":"1766 Rice Hollow Ct",
    "sg:city":"Charleston",
    "sg:classifiers":[
        {
            "category":"Shopping",
            "type":"Retail Goods"
        }
    ],
    "sg:phone":"+1 843 556 5036",
    "sg:postcode":"29407",
    "sg:province":"SC",
    "sg:tags":[
        "supply",
        "telephone",
        "contractor",
        "equipment",
        "electrical",
        "merchandise"
    ],
    "wof:name":"Caraviellos Communications",
    "wof:placetype":"venue"
},
  "geometry": {"coordinates":[-80.022752,32.81866],"type":"Point"}
}