{
  "type": "Feature",
  "properties": {
    "addr:full":"227 E Blackstock Rd Spartanburg SC 29301",
    "addr:housenumber":"227",
    "addr:postcode":"29301",
    "addr:street":"E Blackstock Rd",
    "iso:country":"US",
    "sg:address":"227 E Blackstock Rd",
    "sg:city":"Spartanburg",
    "sg:classifiers":[
        {
            "category":"Banks & Credit Unions",
            "subcategory":"Bank",
            "type":"Services"
        }
    ],
    "sg:phone":"+1 864 576 3224",
    "sg:postcode":"29301",
    "sg:province":"SC",
    "sg:tags":[
        "cashing",
        "check"
    ],
    "wof:name":"Check 'n Go",
    "wof:placetype":"venue"
},
  "geometry": {"coordinates":[-81.985375,34.916991],"type":"Point"}
}