{
  "type": "Feature",
  "properties": {
    "addr:full":"1013 Sea Gull Dr Mt Pleasant SC 29464",
    "addr:housenumber":"1013",
    "addr:postcode":"29464",
    "addr:street":"Sea Gull Dr",
    "iso:country":"US",
    "sg:address":"1013 Sea Gull Dr",
    "sg:city":"Mt Pleasant",
    "sg:classifiers":[
        {
            "category":"Professional",
            "type":"Services"
        }
    ],
    "sg:phone":"+1 843 849 8531",
    "sg:postcode":"29464",
    "sg:province":"SC",
    "wof:name":"Sunhead Projects",
    "wof:placetype":"venue"
},
  "geometry": {"coordinates":[-79.86103799999999,32.803626],"type":"Point"}
}