{
  "type": "Feature",
  "properties": {
    "addr:full":"515 N Cashua Dr Florence SC 29501",
    "addr:housenumber":"515",
    "addr:postcode":"29501",
    "addr:street":"N Cashua Dr",
    "iso:country":"US",
    "sg:address":"515 N Cashua Dr",
    "sg:city":"Florence",
    "sg:classifiers":[
        {
            "category":"Education",
            "subcategory":"School",
            "type":"Public Place"
        }
    ],
    "sg:phone":"+1 843 664 8156",
    "sg:postcode":"29501",
    "sg:province":"SC",
    "wof:name":"Carver Elementary School",
    "wof:placetype":"venue"
},
  "geometry": {"coordinates":[-79.799936,34.203326],"type":"Point"}
}