{
  "type": "Feature",
  "properties": {
    "iso:country":"US",
    "sg:address":"321 N Main St",
    "sg:city":"Saluda",
    "sg:classifiers":[
        {
            "category":"Building & Trades",
            "subcategory":"Electrical",
            "type":"Services"
        }
    ],
    "sg:phone":"+1 864 445 3784",
    "sg:postcode":"29138",
    "sg:province":"SC",
    "sg:tags":[
        "booth",
        "equipment",
        "telephone",
        "pay"
    ],
    "wof:name":"Equity Pay-Tel",
    "wof:placetype":"venue"
},
  "geometry": {"coordinates":[-81.772704,34.006073],"type":"Point"}
}