{
  "type": "Feature",
  "properties": {
    "iso:country":"US",
    "sg:address":"2270 White Horse Rd",
    "sg:city":"Greenville",
    "sg:classifiers":[
        {
            "category":"Professional",
            "subcategory":"Computer Services",
            "type":"Services"
        }
    ],
    "sg:phone":"+1 864 269 0705",
    "sg:postcode":"29605",
    "sg:province":"SC",
    "sg:tags":[
        "repair"
    ],
    "wof:name":"Whitt Enterprises",
    "wof:placetype":"venue"
},
  "geometry": {"coordinates":[-82.421369,34.797641],"type":"Point"}
}