{
  "type": "Feature",
  "properties": {
    "addr:full":"7540 Garners Ferry Rd Columbia SC 29209",
    "addr:housenumber":"7540",
    "addr:postcode":"29209",
    "addr:street":"Garners Ferry Rd",
    "iso:country":"US",
    "sg:address":"7540 Garners Ferry Rd",
    "sg:city":"Columbia",
    "sg:classifiers":[
        {
            "category":"Restaurant",
            "type":"Food & Drink"
        }
    ],
    "sg:phone":"+1 803 776 9633",
    "sg:postcode":"29209",
    "sg:province":"SC",
    "wof:name":"Popeyes Chicken & Biscuits",
    "wof:placetype":"venue"
},
  "geometry": {"coordinates":[-80.94077799999999,33.961537],"type":"Point"}
}