{
  "type": "Feature",
  "properties": {
    "iso:country":"US",
    "sg:address":"20416 Solomon Blatt Ave",
    "sg:city":"Blackville",
    "sg:classifiers":[
        {
            "category":"Autos & Motor Vehicles",
            "subcategory":"Fuel & Gas Station",
            "type":"Retail Goods"
        }
    ],
    "sg:phone":"+1 803 284 2971",
    "sg:postcode":"29817",
    "sg:province":"SC",
    "sg:tags":[
        "station",
        "gasoline"
    ],
    "wof:name":"Corner Stop 10",
    "wof:placetype":"venue"
},
  "geometry": {"coordinates":[-81.275035,33.38402],"type":"Point"}
}