{
  "type": "Feature",
  "properties": {
    "iso:country":"US",
    "sg:address":"108 Main St",
    "sg:city":"Leesville",
    "sg:classifiers":[
        {
            "category":"Restaurant",
            "type":"Food & Drink"
        },
        {
            "category":"Food & Beverages",
            "subcategory":"Bakery",
            "type":"Retail Goods"
        }
    ],
    "sg:phone":"+1 803 532 6455",
    "sg:postcode":"29070",
    "sg:province":"SC",
    "sg:tags":[
        "baker",
        "eating"
    ],
    "wof:name":"Henri's Bakery & Catering Svc",
    "wof:placetype":"venue"
},
  "geometry": {"coordinates":[-81.51183,33.916934],"type":"Point"}
}