{
  "type": "Feature",
  "properties": {
    "iso:country":"US",
    "sg:address":"5413 Rivers Ave",
    "sg:city":"North Charleston",
    "sg:classifiers":[
        {
            "category":"Retail",
            "subcategory":"Auto Repair",
            "type":"Services"
        }
    ],
    "sg:phone":"+1 843 747 6381",
    "sg:postcode":"29406",
    "sg:province":"SC",
    "sg:tags":[
        "muffler",
        "exhaust",
        "system"
    ],
    "wof:name":"Meineke Car Care Ctr",
    "wof:placetype":"venue"
},
  "geometry": {"coordinates":[-80.013555,32.892993],"type":"Point"}
}