{
  "type": "Feature",
  "properties": {
    "addr:full":"620 Long Point Rd Mount Pleasant SC 29464",
    "addr:housenumber":"620",
    "addr:postcode":"29464",
    "addr:street":"Long Point Rd",
    "iso:country":"US",
    "sg:address":"620 Long Point Rd",
    "sg:city":"Mount Pleasant",
    "sg:classifiers":[
        {
            "category":"Shopping",
            "type":"Retail Goods"
        }
    ],
    "sg:phone":"+1 843 971 8650",
    "sg:postcode":"29464",
    "sg:province":"SC",
    "sg:tags":[
        "merchandise"
    ],
    "wof:name":"Dolittles",
    "wof:placetype":"venue"
},
  "geometry": {"coordinates":[-79.856804,32.841201],"type":"Point"}
}