{
  "type": "Feature",
  "properties": {
    "addr:full":"43 S Market St Charleston SC 29401",
    "addr:housenumber":"43",
    "addr:postcode":"29401",
    "addr:street":"S Market St",
    "iso:country":"US",
    "sg:address":"43 S Market St",
    "sg:city":"Charleston",
    "sg:classifiers":[
        {
            "category":"Ice Cream",
            "type":"Food & Drink"
        }
    ],
    "sg:menulink":"http://www.allmenus.com/sc/charleston-north-charleston/232725-haagen-dazs-shop/menu/",
    "sg:phone":"+1 843 723 9326",
    "sg:postcode":"29401",
    "sg:province":"SC",
    "sg:tags":[
        "american"
    ],
    "wof:name":"Haagen-Dazs Shop",
    "wof:placetype":"venue"
},
  "geometry": {"coordinates":[-79.928476,32.780867],"type":"Point"}
}