{
  "type": "Feature",
  "properties": {
    "addr:full":"11 Easy St Taylors SC 29687",
    "addr:housenumber":"11",
    "addr:postcode":"29687",
    "addr:street":"Easy St",
    "iso:country":"US",
    "sg:address":"11 Easy St",
    "sg:city":"Taylors",
    "sg:classifiers":[
        {
            "category":"Shopping",
            "subcategory":"Computers & Home Electronics",
            "type":"Retail Goods"
        }
    ],
    "sg:phone":"+1 864 244 5005",
    "sg:postcode":"29687",
    "sg:province":"SC",
    "sg:tags":[
        "publishing"
    ],
    "wof:name":"Bethel Calvary Baptist Church",
    "wof:placetype":"venue"
},
  "geometry": {"coordinates":[-82.336262,34.923471],"type":"Point"}
}