{
  "type": "Feature",
  "properties": {
    "addr:full":"1945 W Palmetto St Florence SC 29501",
    "addr:housenumber":"1945",
    "addr:postcode":"29501",
    "addr:street":"W Palmetto St",
    "iso:country":"US",
    "sg:address":"1945 W Palmetto St",
    "sg:city":"Florence",
    "sg:classifiers":[
        {
            "category":"Shopping",
            "subcategory":"Books",
            "type":"Retail Goods"
        }
    ],
    "sg:phone":"+1 843 679 5376",
    "sg:postcode":"29501",
    "sg:province":"SC",
    "sg:tags":[
        "bookstore"
    ],
    "wof:name":"Books-A-Million",
    "wof:placetype":"venue"
},
  "geometry": {"coordinates":[-79.80698,34.18839],"type":"Point"}
}