{
  "type": "Feature",
  "properties": {
    "addr:full":"206 Henry St Bennettsville SC 29512",
    "addr:housenumber":"206",
    "addr:postcode":"29512",
    "addr:street":"Henry St",
    "iso:country":"US",
    "sg:address":"206 Henry St",
    "sg:city":"Bennettsville",
    "sg:classifiers":[
        {
            "category":"Organizations",
            "subcategory":"Religious Organization",
            "type":"Services"
        }
    ],
    "sg:phone":"+1 843 479 1189",
    "sg:postcode":"29512",
    "sg:province":"SC",
    "sg:tags":[
        "church"
    ],
    "wof:name":"St Mark Baptist Church",
    "wof:placetype":"venue"
},
  "geometry": {"coordinates":[-79.672955,34.613502],"type":"Point"}
}