{
  "type": "Feature",
  "properties": {
    "iso:country":"US",
    "sg:address":"2548 Main St",
    "sg:city":"Elgin",
    "sg:classifiers":[
        {
            "category":"Home & Garden",
            "subcategory":"Home Furnishings",
            "type":"Retail Goods"
        }
    ],
    "sg:phone":"+1 803 408 3008",
    "sg:postcode":"29045",
    "sg:province":"SC",
    "sg:tags":[
        "venetian",
        "blind"
    ],
    "wof:name":"Blind Spot",
    "wof:placetype":"venue"
},
  "geometry": {"coordinates":[-80.79949000000001,34.167203],"type":"Point"}
}