{
  "type": "Feature",
  "properties": {
    "iso:country":"US",
    "sg:address":"101 Catalpa Ct",
    "sg:city":"Goose Creek",
    "sg:classifiers":[
        {
            "category":"Farming",
            "subcategory":"Farm",
            "type":"Manufacturing & Wholesale Goods"
        }
    ],
    "sg:phone":"+1 843 797 2724",
    "sg:postcode":"29445",
    "sg:province":"SC",
    "sg:tags":[
        "crop",
        "general"
    ],
    "wof:name":"Jrj Farms Inc",
    "wof:placetype":"venue"
},
  "geometry": {"coordinates":[-80.071005,33.017809],"type":"Point"}
}