{
  "type": "Feature",
  "properties": {
    "addr:full":"205 W Blackstock Rd Spartanburg SC 29301",
    "addr:housenumber":"205",
    "addr:postcode":"29301",
    "addr:street":"W Blackstock Rd",
    "iso:country":"US",
    "sg:address":"205 W Blackstock Rd",
    "sg:city":"Spartanburg",
    "sg:classifiers":[
        {
            "category":"Personal",
            "subcategory":"Beauty Salon",
            "type":"Services"
        }
    ],
    "sg:phone":"+1 864 587 2588",
    "sg:postcode":"29301",
    "sg:province":"SC",
    "sg:website":"www.tradesecret.com",
    "wof:name":"Trade Secret",
    "wof:placetype":"venue"
},
  "geometry": {"coordinates":[-81.990667,34.936784],"type":"Point"}
}