{
  "type": "Feature",
  "properties": {
    "iso:country":"US",
    "sg:address":"1410 Blanding St",
    "sg:city":"Columbia",
    "sg:classifiers":[
        {
            "category":"Personal",
            "type":"Services"
        }
    ],
    "sg:phone":"+1 803 251 4425",
    "sg:postcode":"29201",
    "sg:province":"SC",
    "sg:tags":[
        "therapist",
        "massage"
    ],
    "wof:name":"Palmetto Massage Spec LLC",
    "wof:placetype":"venue"
},
  "geometry": {"coordinates":[-81.03181600000001,34.009303],"type":"Point"}
}