{
  "type": "Feature",
  "properties": {
    "addr:full":"1602 Klugh Rd Abbeville SC 29620",
    "addr:housenumber":"1602",
    "addr:postcode":"29620",
    "addr:street":"Klugh Rd",
    "iso:country":"US",
    "sg:address":"1602 Klugh Rd",
    "sg:city":"Abbeville",
    "sg:classifiers":[
        {
            "category":"Building & Trades",
            "subcategory":"Plumbing",
            "type":"Services"
        }
    ],
    "sg:phone":"+1 864 446 3232",
    "sg:postcode":"29620",
    "sg:province":"SC",
    "sg:tags":[
        "contractor"
    ],
    "wof:name":"Air Handler",
    "wof:placetype":"venue"
},
  "geometry": {"coordinates":[-82.27851099999999,34.235991],"type":"Point"}
}