{
  "type": "Feature",
  "properties": {
    "addr:full":"115 Carter Rd Seneca SC 29626",
    "addr:housenumber":"115",
    "addr:postcode":"29626",
    "addr:street":"Carter Rd",
    "iso:country":"US",
    "sg:address":"115 Carter Rd",
    "sg:city":"Seneca",
    "sg:classifiers":[
        {
            "category":"Health Services",
            "subcategory":"Hospital",
            "type":"Services"
        }
    ],
    "sg:phone":"+1 864 885 0157",
    "sg:postcode":"29626",
    "sg:province":"SC",
    "sg:tags":[
        "mental"
    ],
    "wof:name":"Oconee Mental Health Clinic",
    "wof:placetype":"venue"
},
  "geometry": {"coordinates":[-82.823774,34.448025],"type":"Point"}
}