{
  "type": "Feature",
  "properties": {
    "iso:country":"US",
    "sg:address":"509 W Butler Rd",
    "sg:city":"Greenville",
    "sg:classifiers":[
        {
            "category":"Banks & Credit Unions",
            "subcategory":"Bank",
            "type":"Services"
        }
    ],
    "sg:phone":"+1 864 277 2277",
    "sg:postcode":"29607",
    "sg:province":"SC",
    "sg:tags":[
        "loan"
    ],
    "wof:name":"RMC Central",
    "wof:placetype":"venue"
},
  "geometry": {"coordinates":[-82.320061,34.775332],"type":"Point"}
}