{
  "type": "Feature",
  "properties": {
    "iso:country":"US",
    "sg:address":"202 Kirksey Dr",
    "sg:city":"Summerville",
    "sg:classifiers":[
        {
            "category":"Building & Trades",
            "subcategory":"Construction",
            "type":"Services"
        }
    ],
    "sg:phone":"+1 843 821 4897",
    "sg:postcode":"29485",
    "sg:province":"SC",
    "sg:tags":[
        "floor",
        "laying",
        "contractor"
    ],
    "wof:name":"Runnerstrom CIT Inc",
    "wof:placetype":"venue"
},
  "geometry": {"coordinates":[-80.19466799999999,32.97065],"type":"Point"}
}