{
  "type": "Feature",
  "properties": {
    "addr:full":"15545 Wells Hwy Seneca SC 29678",
    "addr:housenumber":"15545",
    "addr:postcode":"29678",
    "addr:street":"Wells Hwy",
    "iso:country":"US",
    "sg:address":"15545 Wells Hwy",
    "sg:city":"Seneca",
    "sg:classifiers":[
        {
            "category":"Manufacturing",
            "subcategory":"Motor Vehicles & Parts",
            "type":"Manufacturing & Wholesale Goods"
        }
    ],
    "sg:phone":"+1 864 985 0568",
    "sg:postcode":"29678",
    "sg:province":"SC",
    "sg:tags":[
        "mfg"
    ],
    "wof:name":"Borgwrner Torqtransfer Systems",
    "wof:placetype":"venue"
},
  "geometry": {"coordinates":[-82.991781,34.688319],"type":"Point"}
}