{
  "type": "Feature",
  "properties": {
    "iso:country":"US",
    "sg:address":"567 N Main St",
    "sg:city":"Cross Hill",
    "sg:classifiers":[
        {
            "category":"Government",
            "subcategory":"Office",
            "type":"Public Place"
        }
    ],
    "sg:phone":"+1 864 998 4902",
    "sg:postcode":"29332",
    "sg:province":"SC",
    "wof:name":"Laurens County EMS Cross",
    "wof:placetype":"venue"
},
  "geometry": {"coordinates":[-81.988226,34.311431],"type":"Point"}
}