{
  "type": "Feature",
  "properties": {
    "iso:country":"US",
    "sg:address":"511 S Pleasantburg Dr",
    "sg:city":"Greenville",
    "sg:classifiers":[
        {
            "category":"Restaurant",
            "type":"Food & Drink"
        }
    ],
    "sg:phone":"+1 864 232 1800",
    "sg:postcode":"29607",
    "sg:province":"SC",
    "sg:tags":[
        "pizza"
    ],
    "sg:website":"www.frodospizza.com",
    "wof:name":"Frodo's Pizza",
    "wof:placetype":"venue"
},
  "geometry": {"coordinates":[-82.370051,34.828191],"type":"Point"}
}