{
  "type": "Feature",
  "properties": {
    "iso:country":"US",
    "sg:address":"1 Windy Bluff Dr",
    "sg:city":"Greenville",
    "sg:classifiers":[
        {
            "category":"Recreation",
            "type":"Entertainment"
        }
    ],
    "sg:phone":"+1 864 610 9981",
    "sg:postcode":"29617",
    "sg:province":"SC",
    "sg:tags":[
        "pool",
        "swimming"
    ],
    "wof:name":"Northcliff Pool",
    "wof:placetype":"venue"
},
  "geometry": {"coordinates":[-82.44868099999999,34.946385],"type":"Point"}
}