{
  "type": "Feature",
  "properties": {
    "iso:country":"US",
    "sg:address":"1801 Rutherford Rd",
    "sg:city":"Greenville",
    "sg:classifiers":[
        {
            "category":"Building & Trades",
            "subcategory":"Construction",
            "type":"Services"
        }
    ],
    "sg:phone":"+1 864 322 2693",
    "sg:postcode":"29609",
    "sg:province":"SC",
    "sg:tags":[
        "steel",
        "fabrication",
        "welding"
    ],
    "wof:name":"Steel Heddle",
    "wof:placetype":"venue"
},
  "geometry": {"coordinates":[-82.366356,34.89618],"type":"Point"}
}