{
  "type": "Feature",
  "properties": {
    "iso:country":"US",
    "sg:address":"941 N Logan St",
    "sg:city":"Gaffney",
    "sg:classifiers":[
        {
            "category":"Health Services",
            "subcategory":"Doctor",
            "type":"Services"
        }
    ],
    "sg:phone":"+1 864 489 9568",
    "sg:postcode":"29341",
    "sg:province":"SC",
    "sg:tags":[
        "dentist"
    ],
    "wof:name":"James M Carroll DDS",
    "wof:placetype":"venue"
},
  "geometry": {"coordinates":[-81.646125,35.080869],"type":"Point"}
}