{
  "type": "Feature",
  "properties": {
    "addr:full":"715 Augusta Rd Edgefield SC 29824",
    "addr:housenumber":"715",
    "addr:postcode":"29824",
    "addr:street":"Augusta Rd",
    "iso:country":"US",
    "sg:address":"715 Augusta Rd",
    "sg:city":"Edgefield",
    "sg:classifiers":[
        {
            "category":"Utilities",
            "subcategory":"Mobile Phone",
            "type":"Services"
        }
    ],
    "sg:phone":"+1 803 637 0044",
    "sg:postcode":"29824",
    "sg:province":"SC",
    "sg:tags":[
        "telephone",
        "cellular"
    ],
    "wof:name":"Radio Shack",
    "wof:placetype":"venue"
},
  "geometry": {"coordinates":[-81.911494,33.770685],"type":"Point"}
}