{
  "type": "Feature",
  "properties": {
    "addr:full":"936 Axtell Dr Cayce SC 29033",
    "addr:housenumber":"936",
    "addr:postcode":"29033",
    "addr:street":"Axtell Dr",
    "iso:country":"US",
    "sg:address":"936 Axtell Dr",
    "sg:city":"Cayce",
    "sg:classifiers":[
        {
            "category":"Restaurant",
            "type":"Food & Drink"
        }
    ],
    "sg:menulink":"http://www.allmenus.com/sc/west-columbia-cayce/40545-the-kingsman-restaurant/menu/",
    "sg:phone":"+1 803 796 8622",
    "sg:postcode":"29033",
    "sg:province":"SC",
    "sg:tags":[
        "american",
        "steakhouse"
    ],
    "wof:name":"The Kingsman Restaurant",
    "wof:placetype":"venue"
},
  "geometry": {"coordinates":[-81.05311500000001,33.986911],"type":"Point"}
}