{
  "type": "Feature",
  "properties": {
    "iso:country":"US",
    "sg:address":"2150 Northwoods Blvd",
    "sg:city":"Charleston",
    "sg:classifiers":[
        {
            "category":"Shopping",
            "subcategory":"Shoes",
            "type":"Retail Goods"
        }
    ],
    "sg:phone":"+1 843 863 9536",
    "sg:postcode":"29406",
    "sg:province":"SC",
    "wof:name":"Pacific Sunwear",
    "wof:placetype":"venue"
},
  "geometry": {"coordinates":[-80.04561099999999,32.942437],"type":"Point"}
}