{
  "type": "Feature",
  "properties": {
    "addr:full":"1677 Wayside Dr Bowman SC 29018",
    "addr:housenumber":"1677",
    "addr:postcode":"29018",
    "addr:street":"Wayside Dr",
    "iso:country":"US",
    "sg:address":"1677 Wayside Dr",
    "sg:city":"Bowman",
    "sg:phone":"+1 803 829 2362",
    "sg:postcode":"29018",
    "sg:province":"SC",
    "sg:tags":[
        "farm",
        "irish",
        "potato"
    ],
    "wof:name":"Ezra Westberry",
    "wof:placetype":"venue"
},
  "geometry": {"coordinates":[-80.66874199999999,33.280336],"type":"Point"}
}