{
  "type": "Feature",
  "properties": {
    "iso:country":"US",
    "sg:address":"28 Kitties Landing Rd",
    "sg:city":"Bluffton",
    "sg:classifiers":[
        {
            "category":"Home & Garden",
            "subcategory":"Carpets & Floor Coverings",
            "type":"Retail Goods"
        }
    ],
    "sg:phone":"+1 843 757 8080",
    "sg:postcode":"29910",
    "sg:province":"SC",
    "sg:tags":[
        "dealer",
        "rug"
    ],
    "wof:name":"Pars Oriental Rugs Inc",
    "wof:placetype":"venue"
},
  "geometry": {"coordinates":[-80.85421599999999,32.25273],"type":"Point"}
}