{
  "type": "Feature",
  "properties": {
    "addr:full":"309 Main St Greenwood SC 29646",
    "addr:housenumber":"309",
    "addr:postcode":"29646",
    "addr:street":"Main St",
    "iso:country":"US",
    "sg:address":"309 Main St",
    "sg:city":"Greenwood",
    "sg:classifiers":[
        {
            "category":"Professional",
            "subcategory":"Lawyer & Legal Services",
            "type":"Services"
        }
    ],
    "sg:phone":"+1 864 223 8333",
    "sg:postcode":"29646",
    "sg:province":"SC",
    "sg:tags":[
        "attorney"
    ],
    "wof:name":"Welch Law Firm",
    "wof:placetype":"venue"
},
  "geometry": {"coordinates":[-82.160389,34.190702],"type":"Point"}
}