{
  "type": "Feature",
  "properties": {
    "addr:full":"103 US Hwy 123 Seneca SC 29678",
    "addr:housenumber":"103",
    "addr:postcode":"29678",
    "addr:street":"Us Hwy 123",
    "iso:country":"US",
    "sg:address":"103 US Hwy 123",
    "sg:city":"Seneca",
    "sg:classifiers":[
        {
            "category":"Shopping",
            "subcategory":"Jewelry",
            "type":"Retail Goods"
        }
    ],
    "sg:phone":"+1 864 882 5747",
    "sg:postcode":"29678",
    "sg:province":"SC",
    "sg:tags":[
        "jeweler"
    ],
    "wof:name":"Bradley's Jewelers",
    "wof:placetype":"venue"
},
  "geometry": {"coordinates":[-82.93998999999999,34.699885],"type":"Point"}
}