{
  "type": "Feature",
  "properties": {
    "iso:country":"US",
    "sg:address":"2490 Charleston Hwy",
    "sg:city":"Cayce",
    "sg:classifiers":[
        {
            "category":"Home & Garden",
            "subcategory":"Garden Supply",
            "type":"Retail Goods"
        }
    ],
    "sg:phone":"+1 803 796 7907",
    "sg:postcode":"29033",
    "sg:province":"SC",
    "sg:tags":[
        "supp",
        "equipment",
        "repair"
    ],
    "wof:name":"Carolina Power Equipment Inc",
    "wof:placetype":"venue"
},
  "geometry": {"coordinates":[-81.078601,33.950373],"type":"Point"}
}