{
  "type": "Feature",
  "properties": {
    "addr:full":"2490 Charleston Hwy Cayce SC 29033",
    "addr:housenumber":"2490",
    "addr:postcode":"29033",
    "addr:street":"Charleston Hwy",
    "iso:country":"US",
    "sg:address":"2490 Charleston Hwy",
    "sg:city":"Cayce",
    "sg:classifiers":[
        {
            "category":"Home & Garden",
            "subcategory":"Garden Supply",
            "type":"Retail Goods"
        }
    ],
    "sg:phone":"+1 803 796 7907",
    "sg:postcode":"29033",
    "sg:province":"SC",
    "sg:tags":[
        "supp",
        "equipment",
        "repair"
    ],
    "wof:name":"Carolina Power Equipment Inc",
    "wof:placetype":"venue"
},
  "geometry": {"coordinates":[-81.07860100000001,33.950373],"type":"Point"}
}