{
  "type": "Feature",
  "properties": {
    "iso:country":"US",
    "sg:address":"2190 State Hwy 441",
    "sg:city":"Sumter",
    "sg:classifiers":[
        {
            "category":"Organizations",
            "subcategory":"Community Association",
            "type":"Services"
        }
    ],
    "sg:phone":"+1 803 499 5390",
    "sg:postcode":"29154",
    "sg:province":"SC",
    "sg:tags":[
        "military"
    ],
    "wof:name":"Amvets",
    "wof:placetype":"venue"
},
  "geometry": {"coordinates":[-80.48817200000001,33.981343],"type":"Point"}
}