{
  "type": "Feature",
  "properties": {
    "iso:country":"US",
    "sg:address":"2020 Gibbs Shoals Rd",
    "sg:city":"Greer",
    "sg:classifiers":[
        {
            "category":"Organizations",
            "subcategory":"Religious Organization",
            "type":"Services"
        }
    ],
    "sg:phone":"+1 864 877 3483",
    "sg:postcode":"29650",
    "sg:province":"SC",
    "sg:tags":[
        "church"
    ],
    "wof:name":"Providence Baptist Church",
    "wof:placetype":"venue"
},
  "geometry": {"coordinates":[-82.240031,34.876315],"type":"Point"}
}