{
  "type": "Feature",
  "properties": {
    "iso:country":"US",
    "sg:address":"396 2nd St",
    "sg:city":"Estill",
    "sg:classifiers":[
        {
            "category":"Professional",
            "subcategory":"Computer Services",
            "type":"Services"
        }
    ],
    "sg:phone":"+1 803 625 9357",
    "sg:postcode":"29918",
    "sg:province":"SC",
    "sg:tags":[
        "internet"
    ],
    "wof:name":"Internet Service-Low Country",
    "wof:placetype":"venue"
},
  "geometry": {"coordinates":[-81.23607800000001,32.752519],"type":"Point"}
}