{
  "type": "Feature",
  "properties": {
    "iso:country":"US",
    "sg:address":"105 Antigua Way",
    "sg:city":"Greer",
    "sg:classifiers":[
        {
            "category":"Professional",
            "subcategory":"Engineering",
            "type":"Services"
        }
    ],
    "sg:phone":"+1 864 234 4991",
    "sg:postcode":"29650",
    "sg:province":"SC",
    "sg:tags":[
        "engineer"
    ],
    "wof:name":"EPC Management Svc",
    "wof:placetype":"venue"
},
  "geometry": {"coordinates":[-82.269605,34.86798],"type":"Point"}
}