{
  "type": "Feature",
  "properties": {
    "iso:country":"US",
    "sg:address":"639 Avon Dr",
    "sg:city":"Spartanburg",
    "sg:classifiers":[
        {
            "category":"Wholesale",
            "subcategory":"Hardware",
            "type":"Manufacturing & Wholesale Goods"
        }
    ],
    "sg:phone":"+1 864 585 2280",
    "sg:postcode":"29303",
    "sg:province":"SC",
    "sg:tags":[
        "tool"
    ],
    "wof:name":"# 9 Salvage",
    "wof:placetype":"venue"
},
  "geometry": {"coordinates":[-81.937309,34.985374],"type":"Point"}
}