{
  "type": "Feature",
  "properties": {
    "addr:full":"3019 E Main St Exd Spartanburg SC 29307",
    "addr:housenumber":"3019",
    "addr:postcode":"29307",
    "addr:street":"E Main St Exd",
    "iso:country":"US",
    "sg:address":"3019 E Main St Exd",
    "sg:city":"Spartanburg",
    "sg:classifiers":[
        {
            "category":"Building & Trades",
            "subcategory":"Plumbing",
            "type":"Services"
        }
    ],
    "sg:phone":"+1 864 579 7559",
    "sg:postcode":"29307",
    "sg:province":"SC",
    "sg:tags":[
        "conditioning",
        "air",
        "system",
        "contractor"
    ],
    "wof:name":"Piedmont Heating & Air Cond",
    "wof:placetype":"venue"
},
  "geometry": {"coordinates":[-81.833006,34.993914],"type":"Point"}
}