{
  "type": "Feature",
  "properties": {
    "iso:country":"US",
    "sg:address":"650 River Rd",
    "sg:city":"Columbia",
    "sg:classifiers":[
        {
            "category":"Retail",
            "subcategory":"Auto Rental",
            "type":"Services"
        }
    ],
    "sg:phone":"+1 803 781 0588",
    "sg:postcode":"29212",
    "sg:province":"SC",
    "sg:tags":[
        "renting",
        "leasing",
        "trailer"
    ],
    "wof:name":"Palmetto Trailer Leasing Inc",
    "wof:placetype":"venue"
},
  "geometry": {"coordinates":[-81.254402,34.073349],"type":"Point"}
}