{
  "type": "Feature",
  "properties": {
    "iso:country":"US",
    "sg:address":"7089 Rivers Ave",
    "sg:city":"Charleston",
    "sg:classifiers":[
        {
            "category":"Real Estate",
            "subcategory":"Real Estate Agent",
            "type":"Services"
        }
    ],
    "sg:phone":"+1 843 553 1451",
    "sg:postcode":"29406",
    "sg:province":"SC",
    "wof:name":"Bulwinkle Real Estate Company",
    "wof:placetype":"venue"
},
  "geometry": {"coordinates":[-80.033716,32.927335],"type":"Point"}
}