{
  "type": "Feature",
  "properties": {
    "iso:country":"US",
    "sg:address":"1035 N Church St",
    "sg:city":"Spartanburg",
    "sg:classifiers":[
        {
            "category":"Autos & Motor Vehicles",
            "subcategory":"Automobile Sales",
            "type":"Retail Goods"
        }
    ],
    "sg:phone":"+1 864 580 2400",
    "sg:postcode":"29303",
    "sg:province":"SC",
    "sg:tags":[
        "car",
        "dealer"
    ],
    "wof:name":"Spartanburg Dodge",
    "wof:placetype":"venue"
},
  "geometry": {"coordinates":[-81.94170200000001,34.97209],"type":"Point"}
}