{
  "type": "Feature",
  "properties": {
    "iso:country":"US",
    "sg:address":"710 Pulaski St",
    "sg:city":"Columbia",
    "sg:classifiers":[
        {
            "category":"Banks & Credit Unions",
            "subcategory":"Bank",
            "type":"Services"
        }
    ],
    "sg:phone":"+1 803 227 5555",
    "sg:postcode":"29201",
    "sg:province":"SC",
    "wof:name":"Carolina Collegiate Federal Credit Union",
    "wof:placetype":"venue"
},
  "geometry": {"coordinates":[-81.040398,33.992001],"type":"Point"}
}