{
  "type": "Feature",
  "properties": {
    "addr:full":"1515 US Hwy 501 Myrtle Beach SC 29577",
    "addr:housenumber":"1515",
    "addr:postcode":"29577",
    "addr:street":"Us Hwy 501",
    "iso:country":"US",
    "sg:address":"1515 US Hwy 501",
    "sg:city":"Myrtle Beach",
    "sg:classifiers":[
        {
            "category":"Autos & Motor Vehicles",
            "subcategory":"Automobile Sales",
            "type":"Retail Goods"
        }
    ],
    "sg:phone":"+1 843 626 7433",
    "sg:postcode":"29577",
    "sg:province":"SC",
    "sg:tags":[
        "car",
        "dealer"
    ],
    "wof:name":"501 Auto Sales",
    "wof:placetype":"venue"
},
  "geometry": {"coordinates":[-78.90231799999999,33.700883],"type":"Point"}
}