{
  "type": "Feature",
  "properties": {
    "iso:country":"US",
    "sg:address":"901 N Lemacks St",
    "sg:city":"Walterboro",
    "sg:classifiers":[
        {
            "category":"Insurance",
            "subcategory":"Hazard Insurance",
            "type":"Services"
        }
    ],
    "sg:phone":"+1 843 549 1411",
    "sg:postcode":"29488",
    "sg:province":"SC",
    "sg:tags":[
        "bond"
    ],
    "wof:name":"Sam Brown Bonding",
    "wof:placetype":"venue"
},
  "geometry": {"coordinates":[-80.653661,32.910021],"type":"Point"}
}