{
  "type": "Feature",
  "properties": {
    "iso:country":"US",
    "sg:address":"1595 Mims Rd",
    "sg:city":"Sumter",
    "sg:classifiers":[
        {
            "category":"Building & Trades",
            "subcategory":"Construction",
            "type":"Services"
        }
    ],
    "sg:phone":"+1 803 495 2234",
    "sg:postcode":"29153",
    "sg:province":"SC",
    "sg:tags":[
        "painter"
    ],
    "wof:name":"Young Painting",
    "wof:placetype":"venue"
},
  "geometry": {"coordinates":[-80.281153,33.873601],"type":"Point"}
}