{
  "type": "Feature",
  "properties": {
    "iso:country":"US",
    "sg:address":"266 Black Oak Dr",
    "sg:city":"Windsor",
    "sg:classifiers":[
        {
            "category":"Building & Trades",
            "subcategory":"Landscaping Services",
            "type":"Services"
        }
    ],
    "sg:phone":"+1 803 641 2094",
    "sg:postcode":"29856",
    "sg:province":"SC",
    "wof:name":"Brocks Professional Services",
    "wof:placetype":"venue"
},
  "geometry": {"coordinates":[-81.548393,33.503614],"type":"Point"}
}