{
  "type": "Feature",
  "properties": {
    "addr:full":"400 N Parson St West Columbia SC 29169",
    "addr:housenumber":"400",
    "addr:postcode":"29169",
    "addr:street":"N Parson St",
    "iso:country":"US",
    "sg:address":"400 N Parson St",
    "sg:city":"West Columbia",
    "sg:classifiers":[
        {
            "category":"Wholesale",
            "subcategory":"Construction Materials",
            "type":"Manufacturing & Wholesale Goods"
        }
    ],
    "sg:phone":"+1 803 794 8005",
    "sg:postcode":"29169",
    "sg:province":"SC",
    "sg:tags":[
        "sand",
        "gravel"
    ],
    "wof:name":"H K Steele Inc",
    "wof:placetype":"venue"
},
  "geometry": {"coordinates":[-81.078824,33.99114],"type":"Point"}
}