{
  "type": "Feature",
  "properties": {
    "addr:full":"1482 Doar Pt Myrtle Beach SC 29577",
    "addr:housenumber":"1482",
    "addr:postcode":"29577",
    "addr:street":"Doar Pt",
    "iso:country":"US",
    "sg:address":"1482 Doar Pt",
    "sg:city":"Myrtle Beach",
    "sg:classifiers":[
        {
            "category":"Shopping",
            "subcategory":"Clothing, Apparel, & Fashions",
            "type":"Retail Goods"
        }
    ],
    "sg:phone":"+1 843 497 6180",
    "sg:postcode":"29577",
    "sg:province":"SC",
    "wof:name":"Ocean Breeze",
    "wof:placetype":"venue"
},
  "geometry": {"coordinates":[-78.88707100000001,33.728246],"type":"Point"}
}