{
  "type": "Feature",
  "properties": {
    "iso:country":"US",
    "sg:address":"105 Queen Pkwy",
    "sg:city":"West Columbia",
    "sg:classifiers":[
        {
            "category":"Home & Garden",
            "subcategory":"Building Materials",
            "type":"Retail Goods"
        }
    ],
    "sg:phone":"+1 803 791 8210",
    "sg:postcode":"29169",
    "sg:province":"SC",
    "sg:tags":[
        "equipment",
        "fixture",
        "lighting"
    ],
    "wof:name":"Standard Lighting Distributors Inc Columbia",
    "wof:placetype":"venue"
},
  "geometry": {"coordinates":[-81.10556200000001,33.985886],"type":"Point"}
}