{
  "type": "Feature",
  "properties": {
    "addr:full":"219 Simmons St Mt Pleasant SC 29464",
    "addr:housenumber":"219",
    "addr:postcode":"29464",
    "addr:street":"Simmons St",
    "iso:country":"US",
    "sg:address":"219 Simmons St",
    "sg:city":"Mt Pleasant",
    "sg:classifiers":[
        {
            "category":"Personal",
            "subcategory":"Beauty Salon",
            "type":"Services"
        }
    ],
    "sg:phone":"+1 843 881 6911",
    "sg:postcode":"29464",
    "sg:province":"SC",
    "sg:tags":[
        "spa",
        "day"
    ],
    "wof:name":"Garden Gate Day Spa & Salon",
    "wof:placetype":"venue"
},
  "geometry": {"coordinates":[-79.874712,32.791076],"type":"Point"}
}