{
  "type": "Feature",
  "properties": {
    "addr:full":"100 Norse Way Columbia SC 29229",
    "addr:housenumber":"100",
    "addr:postcode":"29229",
    "addr:street":"Norse Way",
    "iso:country":"US",
    "sg:address":"100 Norse Way",
    "sg:city":"Columbia",
    "sg:classifiers":[
        {
            "category":"Recreation",
            "type":"Entertainment"
        }
    ],
    "sg:phone":"+1 803 788 7771",
    "sg:postcode":"29229",
    "sg:province":"SC",
    "sg:tags":[
        "club",
        "personal",
        "membership",
        "sport",
        "public"
    ],
    "sg:website":"www.woodlandscc.com",
    "wof:name":"Woodlands Country Club",
    "wof:placetype":"venue"
},
  "geometry": {"coordinates":[-80.868352,34.109089],"type":"Point"}
}