{
  "type": "Feature",
  "properties": {
    "addr:full":"1440 S Live Oak Dr Moncks Corner SC 29461",
    "addr:housenumber":"1440",
    "addr:postcode":"29461",
    "addr:street":"S Live Oak Dr",
    "iso:country":"US",
    "sg:address":"1440 S Live Oak Dr",
    "sg:city":"Moncks Corner",
    "sg:classifiers":[
        {
            "category":"Restaurant",
            "type":"Food & Drink"
        }
    ],
    "sg:phone":"+1 843 899 5553",
    "sg:postcode":"29461",
    "sg:province":"SC",
    "wof:name":"Niko's Mediterranean Grill",
    "wof:placetype":"venue"
},
  "geometry": {"coordinates":[-80.05635599999999,33.159675],"type":"Point"}
}