{
  "type": "Feature",
  "properties": {
    "iso:country":"US",
    "sg:address":"1106 Waynick Dr",
    "sg:city":"Sumter",
    "sg:classifiers":[
        {
            "category":"Organizations",
            "subcategory":"Religious Organization",
            "type":"Services"
        }
    ],
    "sg:phone":"+1 803 775 2883",
    "sg:postcode":"29153",
    "sg:province":"SC",
    "sg:tags":[
        "church"
    ],
    "wof:name":"Boulevard Church Of Nazarene",
    "wof:placetype":"venue"
},
  "geometry": {"coordinates":[-80.311072,33.891397],"type":"Point"}
}