{
  "type": "Feature",
  "properties": {
    "iso:country":"US",
    "sg:address":"2792 Harristown Rd",
    "sg:city":"St Stephen",
    "sg:classifiers":[
        {
            "category":"Shopping",
            "subcategory":"Florist",
            "type":"Retail Goods"
        }
    ],
    "sg:phone":"+1 843 567 3126",
    "sg:postcode":"29479",
    "sg:province":"SC",
    "wof:name":"Humbert's Florist",
    "wof:placetype":"venue"
},
  "geometry": {"coordinates":[-79.906326,33.384284],"type":"Point"}
}