{
  "type": "Feature",
  "properties": {
    "iso:country":"US",
    "sg:address":"117 E Camden Ave",
    "sg:city":"Hartsville",
    "sg:classifiers":[
        {
            "category":"Bars & Pubs",
            "type":"Food & Drink"
        }
    ],
    "sg:phone":"+1 843 332 7555",
    "sg:postcode":"29550",
    "sg:province":"SC",
    "wof:name":"Mac's Too",
    "wof:placetype":"venue"
},
  "geometry": {"coordinates":[-80.070499,34.37008],"type":"Point"}
}