{
  "type": "Feature",
  "properties": {
    "addr:full":"707 Old Augusta Rd Greenville SC 29605",
    "addr:housenumber":"707",
    "addr:postcode":"29605",
    "addr:street":"Old Augusta Rd",
    "iso:country":"US",
    "sg:address":"707 Old Augusta Rd",
    "sg:city":"Greenville",
    "sg:classifiers":[
        {
            "category":"Freight",
            "type":"Transportation"
        }
    ],
    "sg:phone":"+1 864 299 4655",
    "sg:postcode":"29605",
    "sg:province":"SC",
    "sg:tags":[
        "consultant"
    ],
    "wof:name":"Schwab Logistics Solutions",
    "wof:placetype":"venue"
},
  "geometry": {"coordinates":[-82.38411600000001,34.800249],"type":"Point"}
}