{
  "type": "Feature",
  "properties": {
    "addr:full":"1649 Smyrna Rd Elgin SC 29045",
    "addr:housenumber":"1649",
    "addr:postcode":"29045",
    "addr:street":"Smyrna Rd",
    "iso:country":"US",
    "sg:address":"1649 Smyrna Rd",
    "sg:city":"Elgin",
    "sg:classifiers":[
        {
            "category":"Education",
            "subcategory":"School",
            "type":"Public Place"
        }
    ],
    "sg:phone":"+1 803 438 7414",
    "sg:postcode":"29045",
    "sg:province":"SC",
    "sg:website":"www.kershaw.k12.sc.us/stl",
    "wof:name":"Leslie M Stover School",
    "wof:placetype":"venue"
},
  "geometry": {"coordinates":[-80.788093,34.181509],"type":"Point"}
}