{
  "type": "Feature",
  "properties": {
    "iso:country":"US",
    "sg:address":"1028 1st Ave S",
    "sg:city":"North Myrtle Beach",
    "sg:classifiers":[
        {
            "category":"Building & Trades",
            "subcategory":"Construction",
            "type":"Services"
        }
    ],
    "sg:phone":"+1 843 280 6157",
    "sg:postcode":"29582",
    "sg:province":"SC",
    "wof:name":"Sam Horner Builder",
    "wof:placetype":"venue"
},
  "geometry": {"coordinates":[-78.683141,33.828133],"type":"Point"}
}