{
  "type": "Feature",
  "properties": {
    "iso:country":"US",
    "sg:address":"110 Skyuka Cir",
    "sg:city":"Landrum",
    "sg:classifiers":[
        {
            "category":"Wholesale",
            "subcategory":"Durable Goods & Equipment",
            "type":"Manufacturing & Wholesale Goods"
        }
    ],
    "sg:phone":"+1 864 457 3551",
    "sg:postcode":"29356",
    "sg:province":"SC",
    "wof:name":"Higgins Variety Store",
    "wof:placetype":"venue"
},
  "geometry": {"coordinates":[-82.179092,35.179893],"type":"Point"}
}