{
  "type": "Feature",
  "properties": {
    "addr:full":"900 S Kilbourne Rd Columbia SC 29205",
    "addr:housenumber":"900",
    "addr:postcode":"29205",
    "addr:street":"S Kilbourne Rd",
    "iso:country":"US",
    "sg:address":"900 S Kilbourne Rd",
    "sg:city":"Columbia",
    "sg:classifiers":[
        {
            "category":"Food & Beverages",
            "subcategory":"Groceries & Convenience Stores",
            "type":"Retail Goods"
        }
    ],
    "sg:phone":"+1 803 787 2832",
    "sg:postcode":"29205",
    "sg:province":"SC",
    "wof:name":"Mini-Mart No 1",
    "wof:placetype":"venue"
},
  "geometry": {"coordinates":[-80.989502,33.978901],"type":"Point"}
}