{
  "type": "Feature",
  "properties": {
    "addr:full":"1008 N Main St Anderson SC 29621",
    "addr:housenumber":"1008",
    "addr:postcode":"29621",
    "addr:street":"N Main St",
    "iso:country":"US",
    "sg:address":"1008 N Main St",
    "sg:city":"Anderson",
    "sg:classifiers":[
        {
            "category":"Real Estate",
            "subcategory":"Real Estate Agent",
            "type":"Services"
        }
    ],
    "sg:phone":"+1 864 225 3788",
    "sg:postcode":"29621",
    "sg:province":"SC",
    "sg:website":"www.cb-anderson.com",
    "wof:name":"Coldwell Banker",
    "wof:placetype":"venue"
},
  "geometry": {"coordinates":[-82.65237,34.512072],"type":"Point"}
}