{
  "type": "Feature",
  "properties": {
    "addr:full":"1403 E Main St Rock Hill SC 29730",
    "addr:housenumber":"1403",
    "addr:postcode":"29730",
    "addr:street":"E Main St",
    "iso:country":"US",
    "sg:address":"1403 E Main St",
    "sg:city":"Rock Hill",
    "sg:classifiers":[
        {
            "category":"Personal",
            "subcategory":"Beauty Salon",
            "type":"Services"
        }
    ],
    "sg:phone":"+1 803 329 1114",
    "sg:postcode":"29730",
    "sg:province":"SC",
    "sg:tags":[
        "manicuring"
    ],
    "wof:name":"L A Nails",
    "wof:placetype":"venue"
},
  "geometry": {"coordinates":[-80.999397,34.917289],"type":"Point"}
}