{
  "type": "Feature",
  "properties": {
    "iso:country":"US",
    "sg:address":"233 Wheatfield Dr",
    "sg:city":"Greenwood",
    "sg:classifiers":[
        {
            "category":"Wholesale",
            "subcategory":"Machinery & Supplies",
            "type":"Manufacturing & Wholesale Goods"
        }
    ],
    "sg:phone":"+1 864 223 9592",
    "sg:postcode":"29649",
    "sg:province":"SC",
    "sg:tags":[
        "pressure",
        "washing",
        "equipment"
    ],
    "wof:name":"J & J Cleaning Svc",
    "wof:placetype":"venue"
},
  "geometry": {"coordinates":[-82.109049,34.226724],"type":"Point"}
}