{
  "type": "Feature",
  "properties": {
    "addr:full":"1011 Anderson Hwy Easley SC 29642",
    "addr:housenumber":"1011",
    "addr:postcode":"29642",
    "addr:street":"Anderson Hwy",
    "iso:country":"US",
    "sg:address":"1011 Anderson Hwy",
    "sg:city":"Easley",
    "sg:classifiers":[
        {
            "category":"Shopping",
            "subcategory":"Used Merchandise",
            "type":"Retail Goods"
        }
    ],
    "sg:phone":"+1 864 269 0012",
    "sg:postcode":"29642",
    "sg:province":"SC",
    "wof:name":"Kidsville",
    "wof:placetype":"venue"
},
  "geometry": {"coordinates":[-82.620467,34.790049],"type":"Point"}
}