{
  "type": "Feature",
  "properties": {
    "iso:country":"US",
    "sg:address":"313 Jones Ave",
    "sg:city":"Greer",
    "sg:classifiers":[
        {
            "category":"Organizations",
            "subcategory":"Religious Organization",
            "type":"Services"
        }
    ],
    "sg:phone":"+1 864 877 4021",
    "sg:postcode":"29650",
    "sg:province":"SC",
    "sg:tags":[
        "church"
    ],
    "wof:name":"El Bethel Baptist Church",
    "wof:placetype":"venue"
},
  "geometry": {"coordinates":[-82.246144,34.932557],"type":"Point"}
}