{
  "type": "Feature",
  "properties": {
    "iso:country":"US",
    "sg:address":"3325 Wade Hampton Blvd",
    "sg:city":"Norris",
    "sg:classifiers":[
        {
            "category":"Autos & Motor Vehicles",
            "subcategory":"Auto Supplies",
            "type":"Retail Goods"
        },
        {
            "category":"Wholesale",
            "subcategory":"Auto Parts",
            "type":"Manufacturing & Wholesale Goods"
        }
    ],
    "sg:phone":"+1 864 268 9531",
    "sg:postcode":"29687",
    "sg:province":"SC",
    "sg:tags":[
        "automobile",
        "establishment"
    ],
    "wof:name":"Carquest Auto Parts",
    "wof:placetype":"venue"
},
  "geometry": {"coordinates":[-82.31501299999999,34.918196],"type":"Point"}
}