{
  "type": "Feature",
  "properties": {
    "addr:full":"454 Berryhill Rd Columbia SC 29210",
    "addr:housenumber":"454",
    "addr:postcode":"29210",
    "addr:street":"Berryhill Rd",
    "iso:country":"US",
    "sg:address":"454 Berryhill Rd",
    "sg:city":"Columbia",
    "sg:classifiers":[
        {
            "category":"Shopping",
            "subcategory":"Pharmacy",
            "type":"Retail Goods"
        }
    ],
    "sg:phone":"+1 803 256 4879",
    "sg:postcode":"29210",
    "sg:province":"SC",
    "sg:tags":[
        "drugstore"
    ],
    "wof:name":"Long Term Care IV",
    "wof:placetype":"venue"
},
  "geometry": {"coordinates":[-81.121101,34.032902],"type":"Point"}
}