{
  "type": "Feature",
  "properties": {
    "addr:full":"203 Old Salem Rd Seneca SC 29672",
    "addr:housenumber":"203",
    "addr:postcode":"29672",
    "addr:street":"Old Salem Rd",
    "iso:country":"US",
    "sg:address":"203 Old Salem Rd",
    "sg:city":"Seneca",
    "sg:classifiers":[
        {
            "category":"Real Estate",
            "subcategory":"Real Estate Operator",
            "type":"Services"
        }
    ],
    "sg:phone":"+1 864 882 0220",
    "sg:postcode":"29672",
    "sg:province":"SC",
    "sg:tags":[
        "apartment"
    ],
    "wof:name":"Porter Real Estate & Rentals",
    "wof:placetype":"venue"
},
  "geometry": {"coordinates":[-82.94126,34.700781],"type":"Point"}
}