{
  "type": "Feature",
  "properties": {
    "iso:country":"US",
    "sg:address":"2241 Ebenezer Rd",
    "sg:city":"Rock Hill",
    "sg:classifiers":[
        {
            "category":"Insurance",
            "subcategory":"Insurance Agent",
            "type":"Services"
        }
    ],
    "sg:phone":"+1 803 324 8774",
    "sg:postcode":"29732",
    "sg:province":"SC",
    "sg:website":"www.prudentialcarolinas.com",
    "wof:name":"Prudential Carolinas Realty",
    "wof:placetype":"venue"
},
  "geometry": {"coordinates":[-81.055126,34.972239],"type":"Point"}
}