{
  "type": "Feature",
  "properties": {
    "iso:country":"US",
    "sg:address":"91 Buck Island Rd",
    "sg:city":"Bluffton",
    "sg:classifiers":[
        {
            "category":"Restaurant",
            "type":"Food & Drink"
        }
    ],
    "sg:phone":"+1 843 757 8383",
    "sg:postcode":"29910",
    "sg:province":"SC",
    "sg:tags":[
        "eating"
    ],
    "wof:name":"Old Carolina Restaraunt",
    "wof:placetype":"venue"
},
  "geometry": {"coordinates":[-80.879209,32.269191],"type":"Point"}
}