{
  "type": "Feature",
  "properties": {
    "addr:full":"935 Ramblin Rd West Columbia SC 29170",
    "addr:housenumber":"935",
    "addr:postcode":"29170",
    "addr:street":"Ramblin Rd",
    "iso:country":"US",
    "sg:address":"935 Ramblin Rd",
    "sg:city":"West Columbia",
    "sg:classifiers":[
        {
            "category":"Wholesale",
            "subcategory":"Tobacco Products",
            "type":"Manufacturing & Wholesale Goods"
        }
    ],
    "sg:phone":"+1 803 755 2008",
    "sg:postcode":"29170",
    "sg:province":"SC",
    "sg:tags":[
        "equipment",
        "industrial"
    ],
    "wof:name":"MCT Wholesale",
    "wof:placetype":"venue"
},
  "geometry": {"coordinates":[-81.135679,33.910848],"type":"Point"}
}