{
  "type": "Feature",
  "properties": {
    "addr:full":"5050 Edmund Hwy West Columbia SC 29170",
    "addr:housenumber":"5050",
    "addr:postcode":"29170",
    "addr:street":"Edmund Hwy",
    "iso:country":"US",
    "sg:address":"5050 Edmund Hwy",
    "sg:city":"West Columbia",
    "sg:classifiers":[
        {
            "category":"Organizations",
            "subcategory":"Religious Organization",
            "type":"Services"
        }
    ],
    "sg:phone":"+1 803 955 3900",
    "sg:postcode":"29170",
    "sg:province":"SC",
    "sg:tags":[
        "church"
    ],
    "wof:name":"Gospel Time Bible Church",
    "wof:placetype":"venue"
},
  "geometry": {"coordinates":[-81.166489,33.88622],"type":"Point"}
}