{
  "type": "Feature",
  "properties": {
    "iso:country":"US",
    "sg:address":"66 Turner St",
    "sg:city":"Barnwell",
    "sg:classifiers":[
        {
            "category":"Shopping",
            "subcategory":"Clothing, Apparel, & Fashions",
            "type":"Retail Goods"
        }
    ],
    "sg:phone":"+1 803 259 3882",
    "sg:postcode":"29812",
    "sg:province":"SC",
    "wof:name":"Quest Tshirts & Transfer",
    "wof:placetype":"venue"
},
  "geometry": {"coordinates":[-81.363078,33.258016],"type":"Point"}
}