{
  "type": "Feature",
  "properties": {
    "iso:country":"US",
    "sg:address":"3592 Oates Hwy",
    "sg:city":"Lamar",
    "sg:classifiers":[
        {
            "category":"Professional",
            "subcategory":"Business Services",
            "type":"Services"
        }
    ],
    "sg:phone":"+1 843 332 7064",
    "sg:postcode":"29069",
    "sg:province":"SC",
    "sg:tags":[
        "inventory"
    ],
    "wof:name":"Stephens Inventory",
    "wof:placetype":"venue"
},
  "geometry": {"coordinates":[-80.073763,34.246534],"type":"Point"}
}