{
  "type": "Feature",
  "properties": {
    "iso:country":"US",
    "sg:address":"176 Trinity Church Rd",
    "sg:city":"Mooresboro",
    "sg:classifiers":[
        {
            "category":"Building & Trades",
            "subcategory":"Construction",
            "type":"Services"
        },
        {
            "category":"Building & Trades",
            "subcategory":"Landscaping Services",
            "type":"Services"
        }
    ],
    "sg:phone":"+1 828 657 5466",
    "sg:postcode":"28114",
    "sg:province":"SC",
    "sg:tags":[
        "heavy",
        "designer",
        "landscape"
    ],
    "wof:name":"Lail Grading Company",
    "wof:placetype":"venue"
},
  "geometry": {"coordinates":[-81.741658,35.265897],"type":"Point"}
}