{
  "type": "Feature",
  "properties": {
    "addr:full":"4128 US Hwy 78 Dorchester SC 29437",
    "addr:housenumber":"4128",
    "addr:postcode":"29437",
    "addr:street":"Us Hwy 78",
    "iso:country":"US",
    "sg:address":"4128 US Hwy 78",
    "sg:city":"Dorchester",
    "sg:classifiers":[
        {
            "category":"Education",
            "subcategory":"School",
            "type":"Public Place"
        }
    ],
    "sg:phone":"+1 843 563 5956",
    "sg:postcode":"29437",
    "sg:province":"SC",
    "wof:name":"Woodland High School",
    "wof:placetype":"venue"
},
  "geometry": {"coordinates":[-80.493724,33.166382],"type":"Point"}
}