{
  "type": "Feature",
  "properties": {
    "iso:country":"US",
    "sg:address":"4 Randolph St",
    "sg:city":"Greenville",
    "sg:classifiers":[
        {
            "category":"Organizations",
            "subcategory":"Religious Organization",
            "type":"Services"
        }
    ],
    "sg:phone":"+1 864 277 4550",
    "sg:postcode":"29605",
    "sg:province":"SC",
    "sg:tags":[
        "church"
    ],
    "wof:name":"New Covenant Life Ctr",
    "wof:placetype":"venue"
},
  "geometry": {"coordinates":[-82.389966,34.773358],"type":"Point"}
}