{
  "type": "Feature",
  "properties": {
    "iso:country":"US",
    "sg:address":"102 N Railroad Ave",
    "sg:city":"Hemingway",
    "sg:classifiers":[
        {
            "category":"Home & Garden",
            "subcategory":"Building Materials",
            "type":"Retail Goods"
        }
    ],
    "sg:phone":"+1 843 558 1177",
    "sg:postcode":"29554",
    "sg:province":"SC",
    "sg:tags":[
        "plumbing",
        "fixture",
        "supply"
    ],
    "wof:name":"Mc Kenzie's Kitchen",
    "wof:placetype":"venue"
},
  "geometry": {"coordinates":[-79.44895,33.754909],"type":"Point"}
}