{
  "type": "Feature",
  "properties": {
    "iso:country":"US",
    "sg:address":"3900 Augusta Rd",
    "sg:city":"West Columbia",
    "sg:classifiers":[
        {
            "category":"Recreation",
            "type":"Entertainment"
        }
    ],
    "sg:phone":"+1 803 796 8974",
    "sg:postcode":"29170",
    "sg:province":"SC",
    "sg:tags":[
        "psychic",
        "medium"
    ],
    "wof:name":"Ms Millie Psychic Reader",
    "wof:placetype":"venue"
},
  "geometry": {"coordinates":[-81.143808,33.971889],"type":"Point"}
}