{
  "type": "Feature",
  "properties": {
    "iso:country":"US",
    "sg:address":"1779 Woodruff Rd",
    "sg:city":"Greenville",
    "sg:classifiers":[
        {
            "category":"Retail",
            "subcategory":"Laundry & Dry Cleaning",
            "type":"Services"
        }
    ],
    "sg:phone":"+1 864 675 9004",
    "sg:postcode":"29607",
    "sg:province":"SC",
    "sg:tags":[
        "cleaners"
    ],
    "wof:name":"Park Cleaners",
    "wof:placetype":"venue"
},
  "geometry": {"coordinates":[-82.274601,34.819309],"type":"Point"}
}