{
  "type": "Feature",
  "properties": {
    "addr:full":"4107 Main St Loris SC 29569",
    "addr:housenumber":"4107",
    "addr:postcode":"29569",
    "addr:street":"Main St",
    "iso:country":"US",
    "sg:address":"4107 Main St",
    "sg:city":"Loris",
    "sg:classifiers":[
        {
            "category":"Shopping",
            "type":"Retail Goods"
        }
    ],
    "sg:phone":"+1 843 756 1547",
    "sg:postcode":"29569",
    "sg:province":"SC",
    "sg:tags":[
        "cosmetic",
        "perfume"
    ],
    "wof:name":"Merle Norman Cosmetics",
    "wof:placetype":"venue"
},
  "geometry": {"coordinates":[-78.890164,34.056455],"type":"Point"}
}