{
  "type": "Feature",
  "properties": {
    "iso:country":"US",
    "sg:address":"3359 Meeting Street Rd",
    "sg:city":"North Charleston",
    "sg:classifiers":[
        {
            "category":"Wholesale",
            "subcategory":"Hardware",
            "type":"Manufacturing & Wholesale Goods"
        }
    ],
    "sg:phone":"+1 843 566 0060",
    "sg:postcode":"29405",
    "sg:province":"SC",
    "sg:tags":[
        "nut",
        "bolt"
    ],
    "wof:name":"Metric Bolt & Nut Co Inc",
    "wof:placetype":"venue"
},
  "geometry": {"coordinates":[-79.976983,32.852285],"type":"Point"}
}