{
  "type": "Feature",
  "properties": {
    "addr:full":"2720 US Hwy 501 W Conway SC 29526",
    "addr:housenumber":"2720",
    "addr:postcode":"29526",
    "addr:street":"Us Hwy 501 W",
    "iso:country":"US",
    "sg:address":"2720 US Hwy 501 W",
    "sg:city":"Conway",
    "sg:classifiers":[
        {
            "category":"Building & Trades",
            "subcategory":"Construction",
            "type":"Services"
        }
    ],
    "sg:phone":"+1 843 365 1898",
    "sg:postcode":"29526",
    "sg:province":"SC",
    "wof:name":"Coastal Buildings & Truck Cvrs",
    "wof:placetype":"venue"
},
  "geometry": {"coordinates":[-79.09003199999999,33.860264],"type":"Point"}
}