{
  "type": "Feature",
  "properties": {
    "addr:full":"433 S Church St Lake City SC 29560",
    "addr:housenumber":"433",
    "addr:postcode":"29560",
    "addr:street":"S Church St",
    "iso:country":"US",
    "sg:address":"433 S Church St",
    "sg:city":"Lake City",
    "sg:classifiers":[
        {
            "category":"Freight",
            "type":"Transportation"
        }
    ],
    "sg:phone":"+1 843 722 4206",
    "sg:postcode":"29560",
    "sg:province":"SC",
    "sg:tags":[
        "trucking"
    ],
    "wof:name":"Quality Transport",
    "wof:placetype":"venue"
},
  "geometry": {"coordinates":[-79.759186,33.862265],"type":"Point"}
}