{
  "type": "Feature",
  "properties": {
    "iso:country":"US",
    "sg:address":"110 Wren St",
    "sg:city":"Barnwell",
    "sg:classifiers":[
        {
            "category":"Health Services",
            "subcategory":"Doctor",
            "type":"Services"
        }
    ],
    "sg:phone":"+1 803 259 3399",
    "sg:postcode":"29812",
    "sg:province":"SC",
    "sg:tags":[
        "physician",
        "surgeon"
    ],
    "wof:name":"Tri-County Family Medicine",
    "wof:placetype":"venue"
},
  "geometry": {"coordinates":[-81.362597,33.255208],"type":"Point"}
}