{
  "type": "Feature",
  "properties": {
    "addr:full":"1470 US Hwy 321 N Winnsboro SC 29180",
    "addr:housenumber":"1470",
    "addr:postcode":"29180",
    "addr:street":"Us Hwy 321 N",
    "iso:country":"US",
    "sg:address":"1470 US Hwy 321 N",
    "sg:city":"Winnsboro",
    "sg:classifiers":[
        {
            "category":"Retail",
            "subcategory":"Laundry & Dry Cleaning",
            "type":"Services"
        }
    ],
    "sg:phone":"+1 803 712 9888",
    "sg:postcode":"29180",
    "sg:province":"SC",
    "sg:tags":[
        "cleaners"
    ],
    "wof:name":"City Laundry & Cleaners Inc",
    "wof:placetype":"venue"
},
  "geometry": {"coordinates":[-81.10239900000001,34.404665],"type":"Point"}
}