{
  "type": "Feature",
  "properties": {
    "iso:country":"US",
    "sg:address":"600 N Harper St",
    "sg:city":"Laurens",
    "sg:classifiers":[
        {
            "category":"Professional",
            "subcategory":"Advertising",
            "type":"Services"
        }
    ],
    "sg:phone":"+1 864 984 5799",
    "sg:postcode":"29360",
    "sg:province":"SC",
    "wof:name":"Adams Outdoor Advertising",
    "wof:placetype":"venue"
},
  "geometry": {"coordinates":[-82.006684,34.509144],"type":"Point"}
}