{
  "type": "Feature",
  "properties": {
    "iso:country":"US",
    "sg:address":"45 E Dekalb St",
    "sg:city":"Camden",
    "sg:classifiers":[
        {
            "category":"Professional",
            "subcategory":"Computer Services",
            "type":"Services"
        }
    ],
    "sg:phone":"+1 803 713 0599",
    "sg:postcode":"29020",
    "sg:province":"SC",
    "sg:tags":[
        "repair"
    ],
    "wof:name":"Rip A Byte Computer Svc",
    "wof:placetype":"venue"
},
  "geometry": {"coordinates":[-80.592935,34.247213],"type":"Point"}
}