{
  "type": "Feature",
  "properties": {
    "addr:full":"130 Antique Dr West Columbia SC 29170",
    "addr:housenumber":"130",
    "addr:postcode":"29170",
    "addr:street":"Antique Dr",
    "iso:country":"US",
    "sg:address":"130 Antique Dr",
    "sg:city":"West Columbia",
    "sg:classifiers":[
        {
            "category":"Retail",
            "subcategory":"Portrait Studio",
            "type":"Services"
        }
    ],
    "sg:phone":"+1 803 755 8355",
    "sg:postcode":"29170",
    "sg:province":"SC",
    "sg:tags":[
        "photographer"
    ],
    "wof:name":"Hart Photography",
    "wof:placetype":"venue"
},
  "geometry": {"coordinates":[-81.157445,33.89168],"type":"Point"}
}