{
  "type": "Feature",
  "properties": {
    "iso:country":"US",
    "sg:address":"335 Midland Pkwy",
    "sg:city":"Summerville",
    "sg:classifiers":[
        {
            "category":"Social Services",
            "subcategory":"Adult Care",
            "type":"Services"
        }
    ],
    "sg:phone":"+1 843 821 4122",
    "sg:postcode":"29485",
    "sg:province":"SC",
    "sg:tags":[
        "home",
        "residential"
    ],
    "wof:name":"Magnolias Of Summerville",
    "wof:placetype":"venue"
},
  "geometry": {"coordinates":[-80.165295,32.965873],"type":"Point"}
}