{
  "type": "Feature",
  "properties": {
    "addr:full":"1679 Scott St Lake View SC 29563",
    "addr:housenumber":"1679",
    "addr:postcode":"29563",
    "addr:street":"Scott St",
    "iso:country":"US",
    "sg:address":"1679 Scott St",
    "sg:city":"Lake View",
    "sg:phone":"+1 843 759 2936",
    "sg:postcode":"29563",
    "sg:province":"SC",
    "sg:tags":[
        "hog",
        "tobacco",
        "farm",
        "chicken",
        "or",
        "feedlot"
    ],
    "wof:name":"Page Farm",
    "wof:placetype":"venue"
},
  "geometry": {"coordinates":[-79.16912499999999,34.326946],"type":"Point"}
}