{
  "type": "Feature",
  "properties": {
    "addr:full":"310 Cale Yarborough Hwy Timmonsville SC 29161",
    "addr:housenumber":"310",
    "addr:postcode":"29161",
    "addr:street":"Cale Yarborough Hwy",
    "iso:country":"US",
    "sg:address":"310 Cale Yarborough Hwy",
    "sg:city":"Timmonsville",
    "sg:classifiers":[
        {
            "category":"Retail",
            "subcategory":"Auto Repair",
            "type":"Services"
        }
    ],
    "sg:phone":"+1 843 346 7122",
    "sg:postcode":"29161",
    "sg:province":"SC",
    "sg:tags":[
        "wrecker"
    ],
    "wof:name":"W D Ard's Garage",
    "wof:placetype":"venue"
},
  "geometry": {"coordinates":[-79.959895,34.120291],"type":"Point"}
}