{
  "type": "Feature",
  "properties": {
    "iso:country":"US",
    "sg:address":"2750 Laurel St Ste 203",
    "sg:city":"Columbia",
    "sg:classifiers":[
        {
            "category":"Health Services",
            "subcategory":"Doctor",
            "type":"Services"
        }
    ],
    "sg:phone":"+1 803 256 7076",
    "sg:postcode":"29204",
    "sg:province":"SC",
    "sg:tags":[
        "throat",
        "surgeon",
        "ear",
        "cosmetic",
        "nose"
    ],
    "wof:name":"Palmetto Ear Nose & Throat Consultants PA",
    "wof:placetype":"venue"
},
  "geometry": {"coordinates":[-81.012299,34.015499],"type":"Point"}
}