{
  "type": "Feature",
  "properties": {
    "addr:full":"141 Gray Fox Run Chesnee SC 29323",
    "addr:housenumber":"141",
    "addr:postcode":"29323",
    "addr:street":"Gray Fox Run",
    "iso:country":"US",
    "sg:address":"141 Gray Fox Run",
    "sg:city":"Chesnee",
    "sg:classifiers":[
        {
            "category":"Wholesale",
            "subcategory":"Auto Parts",
            "type":"Manufacturing & Wholesale Goods"
        }
    ],
    "sg:phone":"+1 864 814 4369",
    "sg:postcode":"29323",
    "sg:province":"SC",
    "wof:name":"Reflections Auto Collision",
    "wof:placetype":"venue"
},
  "geometry": {"coordinates":[-81.924598,35.075422],"type":"Point"}
}