{
  "type": "Feature",
  "properties": {
    "addr:full":"746 Tallwood Rd Charleston SC 29412",
    "addr:housenumber":"746",
    "addr:postcode":"29412",
    "addr:street":"Tallwood Rd",
    "iso:country":"US",
    "sg:address":"746 Tallwood Rd",
    "sg:city":"Charleston",
    "sg:classifiers":[
        {
            "category":"Building & Trades",
            "subcategory":"Construction",
            "type":"Services"
        }
    ],
    "sg:phone":"+1 843 795 3161",
    "sg:postcode":"29412",
    "sg:province":"SC",
    "sg:tags":[
        "general"
    ],
    "wof:name":"B & C Construction Co",
    "wof:placetype":"venue"
},
  "geometry": {"coordinates":[-79.92213700000001,32.734027],"type":"Point"}
}