{
  "type": "Feature",
  "properties": {
    "iso:country":"US",
    "sg:address":"3657 Bay Rd",
    "sg:city":"Pamplico",
    "sg:classifiers":[
        {
            "category":"Manufacturing",
            "subcategory":"Lumber",
            "type":"Manufacturing & Wholesale Goods"
        }
    ],
    "sg:phone":"+1 843 493 5585",
    "sg:postcode":"29583",
    "sg:province":"SC",
    "sg:tags":[
        "logging",
        "contractor"
    ],
    "wof:name":"Engle Rental Co",
    "wof:placetype":"venue"
},
  "geometry": {"coordinates":[-79.576502,33.885351],"type":"Point"}
}