{
  "type": "Feature",
  "properties": {
    "addr:full":"107 N Goose Creek Blvd Goose Creek SC 29445",
    "addr:housenumber":"107",
    "addr:postcode":"29445",
    "addr:street":"N Goose Creek Blvd",
    "iso:country":"US",
    "sg:address":"107 N Goose Creek Blvd",
    "sg:city":"Goose Creek",
    "sg:classifiers":[
        {
            "category":"Restaurant",
            "type":"Food & Drink"
        }
    ],
    "sg:menulink":"http://www.allmenus.com/sc/goose-creek-hanahan/73242-pizza-hut/menu/",
    "sg:phone":"+1 843 797 7921",
    "sg:postcode":"29445",
    "sg:province":"SC",
    "sg:tags":[
        "american",
        "pizza"
    ],
    "wof:name":"Pizza Hut",
    "wof:placetype":"venue"
},
  "geometry": {"coordinates":[-80.039267,32.998559],"type":"Point"}
}