{
  "type": "Feature",
  "properties": {
    "iso:country":"US",
    "sg:address":"823 Caraway Dr",
    "sg:city":"Rock Hill",
    "sg:classifiers":[
        {
            "category":"Wholesale",
            "subcategory":"Construction Materials",
            "type":"Manufacturing & Wholesale Goods"
        }
    ],
    "sg:phone":"+1 803 328 1267",
    "sg:postcode":"29732",
    "sg:province":"SC",
    "sg:tags":[
        "fence"
    ],
    "wof:name":"Handyman Fence Co",
    "wof:placetype":"venue"
},
  "geometry": {"coordinates":[-81.103679,34.965993],"type":"Point"}
}