{
  "type": "Feature",
  "properties": {
    "iso:country":"US",
    "sg:address":"3517 Heatherwood Rd",
    "sg:city":"Columbia",
    "sg:classifiers":[
        {
            "category":"Real Estate",
            "subcategory":"Real Estate Operator",
            "type":"Services"
        }
    ],
    "sg:phone":"+1 803 799 4016",
    "sg:postcode":"29205",
    "sg:province":"SC",
    "sg:tags":[
        "property",
        "lessor"
    ],
    "wof:name":"Forest Center LLC",
    "wof:placetype":"venue"
},
  "geometry": {"coordinates":[-80.988242,34.003216],"type":"Point"}
}