{
  "type": "Feature",
  "properties": {
    "iso:country":"US",
    "sg:address":"301 N Railroad Ave",
    "sg:city":"Dillon",
    "sg:classifiers":[
        {
            "category":"Freight",
            "type":"Transportation"
        }
    ],
    "sg:phone":"+1 843 774 0091",
    "sg:postcode":"29536",
    "sg:province":"SC",
    "sg:tags":[
        "commercial",
        "storage"
    ],
    "wof:name":"Dillon Mini Storage",
    "wof:placetype":"venue"
},
  "geometry": {"coordinates":[-79.37046599999999,34.419953],"type":"Point"}
}