{
  "type": "Feature",
  "properties": {
    "iso:country":"US",
    "sg:address":"211 Ashford St",
    "sg:city":"Chester",
    "sg:classifiers":[
        {
            "category":"Organizations",
            "subcategory":"Religious Organization",
            "type":"Services"
        }
    ],
    "sg:phone":"+1 803 377 8443",
    "sg:postcode":"29706",
    "sg:province":"SC",
    "sg:tags":[
        "church"
    ],
    "wof:name":"Brooklyn AME Zion",
    "wof:placetype":"venue"
},
  "geometry": {"coordinates":[-81.212281,34.69948],"type":"Point"}
}