{
  "type": "Feature",
  "properties": {
    "iso:country":"US",
    "sg:address":"2204 Chesnee Hwy",
    "sg:city":"Spartanburg",
    "sg:classifiers":[
        {
            "category":"Food & Beverages",
            "subcategory":"Groceries & Convenience Stores",
            "type":"Retail Goods"
        }
    ],
    "sg:phone":"+1 864 542 0009",
    "sg:postcode":"29303",
    "sg:province":"SC",
    "wof:name":"Depot Food Store",
    "wof:placetype":"venue"
},
  "geometry": {"coordinates":[-81.89657,35.017993],"type":"Point"}
}