{
  "type": "Feature",
  "properties": {
    "iso:country":"US",
    "sg:address":"148 Rolling Hills Rd",
    "sg:city":"Aiken",
    "sg:classifiers":[
        {
            "category":"Professional",
            "subcategory":"Accounting & Tax Preparation",
            "type":"Services"
        }
    ],
    "sg:phone":"+1 803 652 2486",
    "sg:postcode":"29803",
    "sg:province":"SC",
    "sg:tags":[
        "bookkeeping",
        "general"
    ],
    "wof:name":"Bryant's Tax & Accounting",
    "wof:placetype":"venue"
},
  "geometry": {"coordinates":[-81.773216,33.413196],"type":"Point"}
}