{
  "type": "Feature",
  "properties": {
    "addr:full":"101 Edgefield Rd Greenville SC 29605",
    "addr:housenumber":"101",
    "addr:postcode":"29605",
    "addr:street":"Edgefield Rd",
    "iso:country":"US",
    "sg:address":"101 Edgefield Rd",
    "sg:city":"Greenville",
    "sg:classifiers":[
        {
            "category":"Organizations",
            "subcategory":"Religious Organization",
            "type":"Services"
        }
    ],
    "sg:phone":"+1 864 299 0861",
    "sg:postcode":"29605",
    "sg:province":"SC",
    "sg:tags":[
        "church"
    ],
    "wof:name":"Allen Memorial Baptist Church",
    "wof:placetype":"venue"
},
  "geometry": {"coordinates":[-82.390108,34.782388],"type":"Point"}
}