{
  "type": "Feature",
  "properties": {
    "addr:full":"521 Old Bridge Rd Mount Pleasant SC 29464",
    "addr:housenumber":"521",
    "addr:postcode":"29464",
    "addr:street":"Old Bridge Rd",
    "iso:country":"US",
    "sg:address":"521 Old Bridge Rd",
    "sg:city":"Mount Pleasant",
    "sg:classifiers":[
        {
            "category":"Communications",
            "subcategory":"Radio Station",
            "type":"Services"
        }
    ],
    "sg:phone":"+1 843 849 9090",
    "sg:postcode":"29464",
    "sg:province":"SC",
    "sg:tags":[
        "broadcast"
    ],
    "wof:name":"F M Rinker Production",
    "wof:placetype":"venue"
},
  "geometry": {"coordinates":[-79.86381900000001,32.778564],"type":"Point"}
}