{
  "type": "Feature",
  "properties": {
    "iso:country":"US",
    "sg:address":"210 Roberts Farm Rd",
    "sg:city":"Simpsonville",
    "sg:classifiers":[
        {
            "category":"Professional",
            "type":"Services"
        }
    ],
    "sg:phone":"+1 864 288 9085",
    "sg:postcode":"29681",
    "sg:province":"SC",
    "sg:tags":[
        "editorial"
    ],
    "wof:name":"Wordsmith",
    "wof:placetype":"venue"
},
  "geometry": {"coordinates":[-82.235518,34.796604],"type":"Point"}
}