{
  "type": "Feature",
  "properties": {
    "iso:country":"US",
    "sg:address":"4195 Edisto Rd",
    "sg:city":"Aiken",
    "sg:classifiers":[
        {
            "category":"Building & Trades",
            "subcategory":"Construction",
            "type":"Services"
        }
    ],
    "sg:phone":"+1 803 642 1260",
    "sg:postcode":"29129",
    "sg:province":"SC",
    "sg:tags":[
        "mobile",
        "home",
        "installation"
    ],
    "wof:name":"Danny C Sauls",
    "wof:placetype":"venue"
},
  "geometry": {"coordinates":[-81.650998,33.693677],"type":"Point"}
}