{
  "type": "Feature",
  "properties": {
    "iso:country":"US",
    "sg:address":"1275 Ebenezer Rd",
    "sg:city":"Rock Hill",
    "sg:classifiers":[
        {
            "category":"Banks & Credit Unions",
            "subcategory":"Bank",
            "type":"Services"
        }
    ],
    "sg:phone":"+1 803 324 2973",
    "sg:postcode":"29732",
    "sg:province":"SC",
    "sg:tags":[
        "loan",
        "real estate"
    ],
    "wof:name":"Eagle Financial Svc",
    "wof:placetype":"venue"
},
  "geometry": {"coordinates":[-81.038917,34.946853],"type":"Point"}
}