{
  "type": "Feature",
  "properties": {
    "iso:country":"US",
    "sg:address":"535 E Main St",
    "sg:city":"Liberty",
    "sg:classifiers":[
        {
            "category":"Organizations",
            "subcategory":"Religious Organization",
            "type":"Services"
        }
    ],
    "sg:phone":"+1 864 843 6839",
    "sg:postcode":"29657",
    "sg:province":"SC",
    "sg:tags":[
        "church"
    ],
    "wof:name":"Emmanuel Baptist Church",
    "wof:placetype":"venue"
},
  "geometry": {"coordinates":[-82.774036,34.649212],"type":"Point"}
}