{
  "type": "Feature",
  "properties": {
    "addr:full":"101 Eagle Ct Union SC 29379",
    "addr:housenumber":"101",
    "addr:postcode":"29379",
    "addr:street":"Eagle Ct",
    "iso:country":"US",
    "sg:address":"101 Eagle Ct",
    "sg:city":"Union",
    "sg:classifiers":[
        {
            "category":"Wholesale",
            "subcategory":"Apparel",
            "type":"Manufacturing & Wholesale Goods"
        }
    ],
    "sg:phone":"+1 864 427 6424",
    "sg:postcode":"29379",
    "sg:province":"SC",
    "sg:tags":[
        "textile",
        "broker"
    ],
    "wof:name":"Material Unlimited Inc",
    "wof:placetype":"venue"
},
  "geometry": {"coordinates":[-81.64593499999999,34.76791],"type":"Point"}
}