{
  "type": "Feature",
  "properties": {
    "iso:country":"US",
    "sg:address":"124 Felix Ln",
    "sg:city":"York",
    "sg:classifiers":[
        {
            "category":"Building & Trades",
            "subcategory":"Construction",
            "type":"Services"
        }
    ],
    "sg:phone":"+1 803 628 0648",
    "sg:postcode":"29745",
    "sg:province":"SC",
    "sg:tags":[
        "house"
    ],
    "wof:name":"Palmetto Custom Home Contg",
    "wof:placetype":"venue"
},
  "geometry": {"coordinates":[-81.14764,35.058766],"type":"Point"}
}