{
  "type": "Feature",
  "properties": {
    "iso:country":"US",
    "sg:address":"1631 E Myrtle Beach Hwy",
    "sg:city":"Scranton",
    "sg:classifiers":[
        {
            "category":"Autos & Motor Vehicles",
            "subcategory":"Automobile Sales",
            "type":"Retail Goods"
        }
    ],
    "sg:phone":"+1 843 389 4265",
    "sg:postcode":"29591",
    "sg:province":"SC",
    "sg:tags":[
        "car",
        "dealer"
    ],
    "wof:name":"James Used Cars",
    "wof:placetype":"venue"
},
  "geometry": {"coordinates":[-79.682587,33.920225],"type":"Point"}
}