{
  "type": "Feature",
  "properties": {
    "iso:country":"US",
    "sg:address":"2703 Azalea Dr",
    "sg:city":"Charleston",
    "sg:classifiers":[
        {
            "category":"Freight",
            "type":"Transportation"
        }
    ],
    "sg:phone":"+1 843 744 6618",
    "sg:postcode":"29405",
    "sg:province":"SC",
    "sg:tags":[
        "cargo",
        "containerized",
        "agent",
        "steamship"
    ],
    "wof:name":"B & R Agencies Inc",
    "wof:placetype":"venue"
},
  "geometry": {"coordinates":[-79.965308,32.841698],"type":"Point"}
}