{
  "type": "Feature",
  "properties": {
    "iso:country":"US",
    "sg:address":"2327 Hartnett Blvd",
    "sg:city":"Isle Of Palms",
    "sg:classifiers":[
        {
            "category":"Building & Trades",
            "subcategory":"Construction",
            "type":"Services"
        }
    ],
    "sg:phone":"+1 843 886 4016",
    "sg:postcode":"29451",
    "sg:province":"SC",
    "sg:tags":[
        "contractor"
    ],
    "wof:name":"Buckhannon Brothers Inc",
    "wof:placetype":"venue"
},
  "geometry": {"coordinates":[-79.780787,32.791882],"type":"Point"}
}