{
  "type": "Feature",
  "properties": {
    "iso:country":"US",
    "sg:address":"1919 Zion Rd",
    "sg:city":"Lancaster",
    "sg:classifiers":[
        {
            "category":"Real Estate",
            "subcategory":"Real Estate Operator",
            "type":"Services"
        }
    ],
    "sg:phone":"+1 803 285 9961",
    "sg:postcode":"29720",
    "sg:province":"SC",
    "sg:tags":[
        "mobile",
        "home",
        "site"
    ],
    "wof:name":"Zion Mobile Home Park",
    "wof:placetype":"venue"
},
  "geometry": {"coordinates":[-80.730677,34.780341],"type":"Point"}
}