{
  "type": "Feature",
  "properties": {
    "iso:country":"US",
    "sg:address":"4744 Broad St",
    "sg:city":"Loris",
    "sg:classifiers":[
        {
            "category":"Retail",
            "subcategory":"Auto Repair",
            "type":"Services"
        }
    ],
    "sg:phone":"+1 843 756 5442",
    "sg:postcode":"29569",
    "sg:province":"SC",
    "sg:tags":[
        "body",
        "automobile",
        "painting"
    ],
    "wof:name":"Mincey's Body Shop",
    "wof:placetype":"venue"
},
  "geometry": {"coordinates":[-78.885632,34.059558],"type":"Point"}
}