{
  "type": "Feature",
  "properties": {
    "addr:full":"274 Main Dr Aiken SC 29801",
    "addr:housenumber":"274",
    "addr:postcode":"29801",
    "addr:street":"Main Dr",
    "iso:country":"US",
    "sg:address":"274 Main Dr",
    "sg:city":"Aiken",
    "sg:classifiers":[
        {
            "category":"Food & Beverages",
            "subcategory":"Groceries & Convenience Stores",
            "type":"Retail Goods"
        }
    ],
    "sg:phone":"+1 803 643 8766",
    "sg:postcode":"29801",
    "sg:province":"SC",
    "wof:name":"Main Drive Stop & Shop",
    "wof:placetype":"venue"
},
  "geometry": {"coordinates":[-81.656533,33.553818],"type":"Point"}
}