{
  "type": "Feature",
  "properties": {
    "iso:country":"US",
    "sg:address":"905 Port Republic St",
    "sg:city":"Beaufort",
    "sg:classifiers":[
        {
            "category":"Shopping",
            "type":"Retail Goods"
        }
    ],
    "sg:phone":"+1 843 379 2222",
    "sg:postcode":"29902",
    "sg:province":"SC",
    "sg:tags":[
        "art",
        "gallery",
        "dealer"
    ],
    "wof:name":"Beaufort Art Assn",
    "wof:placetype":"venue"
},
  "geometry": {"coordinates":[-80.672909,32.431794],"type":"Point"}
}