{
  "type": "Feature",
  "properties": {
    "addr:full":"1701 White House Rd Georgetown SC 29440",
    "addr:housenumber":"1701",
    "addr:postcode":"29440",
    "addr:street":"White House Rd",
    "iso:country":"US",
    "sg:address":"1701 White House Rd",
    "sg:city":"Georgetown",
    "sg:classifiers":[
        {
            "category":"Farming",
            "subcategory":"Farm",
            "type":"Manufacturing & Wholesale Goods"
        }
    ],
    "sg:phone":"+1 843 546 7526",
    "sg:postcode":"29440",
    "sg:province":"SC",
    "sg:tags":[
        "crop",
        "general"
    ],
    "wof:name":"White House Plantation",
    "wof:placetype":"venue"
},
  "geometry": {"coordinates":[-79.22345300000001,33.4354],"type":"Point"}
}