{
  "type": "Feature",
  "properties": {
    "iso:country":"US",
    "sg:address":"402 E Main St",
    "sg:city":"Williamston",
    "sg:classifiers":[
        {
            "category":"Building & Trades",
            "subcategory":"Construction",
            "type":"Services"
        }
    ],
    "sg:phone":"+1 864 847 5584",
    "sg:postcode":"29697",
    "sg:province":"SC",
    "sg:tags":[
        "resurfacing",
        "laying",
        "refinishing",
        "floor"
    ],
    "wof:name":"PJL Custom Flooring",
    "wof:placetype":"venue"
},
  "geometry": {"coordinates":[-82.46956,34.621359],"type":"Point"}
}