{
  "type": "Feature",
  "properties": {
    "iso:country":"US",
    "sg:address":"1036 Park Dr",
    "sg:city":"Myrtle Beach",
    "sg:classifiers":[
        {
            "category":"Wholesale",
            "subcategory":"Auto Parts",
            "type":"Manufacturing & Wholesale Goods"
        }
    ],
    "sg:phone":"+1 843 626 9471",
    "sg:postcode":"29577",
    "sg:province":"SC",
    "wof:name":"Auto Parts World of Myrtle Bch",
    "wof:placetype":"venue"
},
  "geometry": {"coordinates":[-78.90377100000001,33.692287],"type":"Point"}
}