{
  "type": "Feature",
  "properties": {
    "iso:country":"US",
    "sg:address":"500 S Lake Dr",
    "sg:city":"Lexington",
    "sg:classifiers":[
        {
            "category":"Organizations",
            "subcategory":"Religious Organization",
            "type":"Services"
        }
    ],
    "sg:phone":"+1 803 359 3493",
    "sg:postcode":"29072",
    "sg:province":"SC",
    "sg:tags":[
        "church"
    ],
    "wof:name":"New Bethel AME Church",
    "wof:placetype":"venue"
},
  "geometry": {"coordinates":[-81.235612,33.974883],"type":"Point"}
}