{
  "type": "Feature",
  "properties": {
    "addr:full":"1850 Kershaw Camden Hwy Lancaster SC 29720",
    "addr:housenumber":"1850",
    "addr:postcode":"29720",
    "addr:street":"Kershaw Camden Hwy",
    "iso:country":"US",
    "sg:address":"1850 Kershaw Camden Hwy",
    "sg:city":"Lancaster",
    "sg:classifiers":[
        {
            "category":"Education",
            "subcategory":"School",
            "type":"Public Place"
        }
    ],
    "sg:phone":"+1 803 285 5565",
    "sg:postcode":"29720",
    "sg:province":"SC",
    "sg:website":"www.carolinachristian.org",
    "wof:name":"Carolina Christian Academy",
    "wof:placetype":"venue"
},
  "geometry": {"coordinates":[-80.739555,34.689894],"type":"Point"}
}