{
  "type": "Feature",
  "properties": {
    "addr:full":"116 Interstate Blvd Anderson SC 29615",
    "addr:housenumber":"116",
    "addr:postcode":"29615",
    "addr:street":"Interstate Blvd",
    "iso:country":"US",
    "sg:address":"116 Interstate Blvd",
    "sg:city":"Anderson",
    "sg:classifiers":[
        {
            "category":"Travel",
            "subcategory":"Hotels & Motels",
            "type":"Entertainment"
        }
    ],
    "sg:phone":"+1 864 622 2200",
    "sg:postcode":"29615",
    "sg:province":"SC",
    "wof:name":"Country Inn & Suites Anderson",
    "wof:placetype":"venue"
},
  "geometry": {"coordinates":[-82.239876,34.856149],"type":"Point"}
}