{
  "type": "Feature",
  "properties": {
    "addr:full":"78 Alexander St Charleston SC 29403",
    "addr:housenumber":"78",
    "addr:postcode":"29403",
    "addr:street":"Alexander St",
    "iso:country":"US",
    "sg:address":"78 Alexander St",
    "sg:city":"Charleston",
    "sg:classifiers":[
        {
            "category":"Shopping",
            "subcategory":"Clothing, Apparel, & Fashions",
            "type":"Retail Goods"
        }
    ],
    "sg:phone":"+1 843 723 7829",
    "sg:postcode":"29403",
    "sg:province":"SC",
    "sg:tags":[
        "sportswear"
    ],
    "sg:website":"www.ludensoutfitters.com",
    "wof:name":"Luden's",
    "wof:placetype":"venue"
},
  "geometry": {"coordinates":[-79.93065,32.789276],"type":"Point"}
}