{
  "type": "Feature",
  "properties": {
    "addr:full":"1620 Springstein Rd Rock Hill SC 29730",
    "addr:housenumber":"1620",
    "addr:postcode":"29730",
    "addr:street":"Springstein Rd",
    "iso:country":"US",
    "sg:address":"1620 Springstein Rd",
    "sg:city":"Rock Hill",
    "sg:classifiers":[
        {
            "category":"Home & Garden",
            "subcategory":"Garden Supply",
            "type":"Retail Goods"
        }
    ],
    "sg:phone":"+1 803 366 0313",
    "sg:postcode":"29730",
    "sg:province":"SC",
    "wof:name":"Ken Small Engine Repair",
    "wof:placetype":"venue"
},
  "geometry": {"coordinates":[-80.98376,34.932071],"type":"Point"}
}