{
  "type": "Feature",
  "properties": {
    "iso:country":"US",
    "sg:address":"315 Green Sea Rd N",
    "sg:city":"Loris",
    "sg:classifiers":[
        {
            "category":"Food & Beverages",
            "subcategory":"Groceries & Convenience Stores",
            "type":"Retail Goods"
        }
    ],
    "sg:phone":"+1 843 716 1500",
    "sg:postcode":"29569",
    "sg:province":"SC",
    "wof:name":"B's Convenience",
    "wof:placetype":"venue"
},
  "geometry": {"coordinates":[-78.978313,34.102191],"type":"Point"}
}