{
  "type": "Feature",
  "properties": {
    "iso:country":"US",
    "sg:address":"533 W Lucas St",
    "sg:city":"Florence",
    "sg:classifiers":[
        {
            "category":"Shopping",
            "subcategory":"Department Store",
            "type":"Retail Goods"
        }
    ],
    "sg:phone":"+1 843 667 8792",
    "sg:postcode":"29501",
    "sg:province":"SC",
    "sg:tags":[
        "shop"
    ],
    "wof:name":"Family Dollar Store",
    "wof:placetype":"venue"
},
  "geometry": {"coordinates":[-79.778051,34.212625],"type":"Point"}
}