{
  "type": "Feature",
  "properties": {
    "addr:full":"1213 S Ocean Blvd Myrtle Beach SC 29577",
    "addr:housenumber":"1213",
    "addr:postcode":"29577",
    "addr:street":"S Ocean Blvd",
    "iso:country":"US",
    "sg:address":"1213 S Ocean Blvd",
    "sg:city":"Myrtle Beach",
    "sg:classifiers":[
        {
            "category":"Building & Trades",
            "subcategory":"Electrical",
            "type":"Services"
        }
    ],
    "sg:phone":"+1 843 477 8060",
    "sg:postcode":"29577",
    "sg:province":"SC",
    "sg:tags":[
        "electric",
        "contractor"
    ],
    "wof:name":"M & M Electric Svc",
    "wof:placetype":"venue"
},
  "geometry": {"coordinates":[-78.898506,33.675949],"type":"Point"}
}