{
  "type": "Feature",
  "properties": {
    "addr:full":"4108 Dorchester Rd North Charleston SC 29405",
    "addr:housenumber":"4108",
    "addr:postcode":"29405",
    "addr:street":"Dorchester Rd",
    "iso:country":"US",
    "sg:address":"4108 Dorchester Rd",
    "sg:city":"North Charleston",
    "sg:classifiers":[
        {
            "category":"Wholesale",
            "subcategory":"Farm Supplies",
            "type":"Manufacturing & Wholesale Goods"
        }
    ],
    "sg:phone":"+1 843 745 0099",
    "sg:postcode":"29405",
    "sg:province":"SC",
    "wof:name":"Carolina Pco Supply",
    "wof:placetype":"venue"
},
  "geometry": {"coordinates":[-80.000136,32.853765],"type":"Point"}
}