{
  "type": "Feature",
  "properties": {
    "addr:full":"614 Fleming Rd Charleston SC 29412",
    "addr:housenumber":"614",
    "addr:postcode":"29412",
    "addr:street":"Fleming Rd",
    "iso:country":"US",
    "sg:address":"614 Fleming Rd",
    "sg:city":"Charleston",
    "sg:classifiers":[
        {
            "category":"Professional",
            "subcategory":"Management & Consulting",
            "type":"Services"
        }
    ],
    "sg:phone":"+1 843 225 6101",
    "sg:postcode":"29412",
    "sg:province":"SC",
    "sg:tags":[
        "logistics"
    ],
    "wof:name":"Cross Cutz Logistics",
    "wof:placetype":"venue"
},
  "geometry": {"coordinates":[-79.981443,32.745721],"type":"Point"}
}