{
  "type": "Feature",
  "properties": {
    "addr:full":"3680 Humbert Rd Johns Island SC 29455",
    "addr:postcode":"3680;29455",
    "addr:street":"Humbert Rd",
    "iso:country":"US",
    "sg:address":"3680 Humbert Rd",
    "sg:city":"Johns Island",
    "sg:classifiers":[
        {
            "category":"Building & Trades",
            "subcategory":"Cleaning & Sanitation",
            "type":"Services"
        }
    ],
    "sg:phone":"+1 843 557 0930",
    "sg:postcode":"29455",
    "sg:province":"SC",
    "sg:tags":[
        "janitor"
    ],
    "wof:name":"ABM Janitorial",
    "wof:placetype":"venue"
},
  "geometry": {"coordinates":[-80.112375,32.754526],"type":"Point"}
}