{
  "type": "Feature",
  "properties": {
    "iso:country":"US",
    "sg:address":"604 South St",
    "sg:city":"Simpsonville",
    "sg:classifiers":[
        {
            "category":"Organizations",
            "subcategory":"Religious Organization",
            "type":"Services"
        }
    ],
    "sg:phone":"+1 864 963 3372",
    "sg:postcode":"29681",
    "sg:province":"SC",
    "sg:tags":[
        "church"
    ],
    "wof:name":"Word-Life Deliverance Mnstrs",
    "wof:placetype":"venue"
},
  "geometry": {"coordinates":[-82.25813599999999,34.731103],"type":"Point"}
}