{
  "type": "Feature",
  "properties": {
    "iso:country":"US",
    "sg:address":"2 Nigh Oak Trce",
    "sg:city":"Greer",
    "sg:classifiers":[
        {
            "category":"Building & Trades",
            "subcategory":"Construction",
            "type":"Services"
        }
    ],
    "sg:phone":"+1 864 877 7478",
    "sg:postcode":"29651",
    "sg:province":"SC",
    "sg:tags":[
        "residential"
    ],
    "wof:name":"Benchmark Development Group LL",
    "wof:placetype":"venue"
},
  "geometry": {"coordinates":[-82.264887,34.969165],"type":"Point"}
}