{
  "type": "Feature",
  "properties": {
    "addr:full":"37 Harvest Ln Greenville SC 29601",
    "addr:housenumber":"37",
    "addr:postcode":"29601",
    "addr:street":"Harvest Ln",
    "iso:country":"US",
    "sg:address":"37 Harvest Ln",
    "sg:city":"Greenville",
    "sg:classifiers":[
        {
            "category":"Wholesale",
            "subcategory":"Machinery & Supplies",
            "type":"Manufacturing & Wholesale Goods"
        }
    ],
    "sg:phone":"+1 864 232 7987",
    "sg:postcode":"29601",
    "sg:province":"SC",
    "sg:tags":[
        "vacuum",
        "system",
        "cleaning"
    ],
    "wof:name":"Central Vacuums USA",
    "wof:placetype":"venue"
},
  "geometry": {"coordinates":[-82.383954,34.832104],"type":"Point"}
}