{
  "type": "Feature",
  "properties": {
    "iso:country":"US",
    "sg:address":"126 Fair Dr",
    "sg:city":"Clinton",
    "sg:classifiers":[
        {
            "category":"Manufacturing",
            "subcategory":"Tools & Machinery",
            "type":"Manufacturing & Wholesale Goods"
        }
    ],
    "sg:phone":"+1 864 833 9681",
    "sg:postcode":"29325",
    "sg:province":"SC",
    "sg:tags":[
        "equipment",
        "purifying",
        "cleaning",
        "air"
    ],
    "wof:name":"People's Choice",
    "wof:placetype":"venue"
},
  "geometry": {"coordinates":[-81.871016,34.450646],"type":"Point"}
}