{
  "type": "Feature",
  "properties": {
    "iso:country":"US",
    "sg:address":"1226 Pickens St Ste 202",
    "sg:city":"Columbia",
    "sg:classifiers":[
        {
            "category":"Shopping",
            "subcategory":"Computers & Home Electronics",
            "type":"Retail Goods"
        }
    ],
    "sg:phone":"+1 803 256 4500",
    "sg:postcode":"29201",
    "sg:province":"SC",
    "wof:name":"Garber Reporting Service & Video Conferencing",
    "wof:placetype":"venue"
},
  "geometry": {"coordinates":[-81.027298,34.0037],"type":"Point"}
}