{
  "type": "Feature",
  "properties": {
    "addr:full":"1500 Old Stage Rd Mauldin SC 29662",
    "addr:housenumber":"1500",
    "addr:postcode":"29662",
    "addr:street":"Old Stage Rd",
    "iso:country":"US",
    "sg:address":"1500 Old Stage Rd",
    "sg:city":"Mauldin",
    "sg:classifiers":[
        {
            "category":"Wholesale",
            "subcategory":"Chemicals & Plastics",
            "type":"Manufacturing & Wholesale Goods"
        }
    ],
    "sg:phone":"+1 864 963 4031",
    "sg:postcode":"29662",
    "sg:province":"SC",
    "sg:website":"www.cognis.com",
    "wof:name":"Cognis Corp",
    "wof:placetype":"venue"
},
  "geometry": {"coordinates":[-82.299463,34.770327],"type":"Point"}
}