{
  "type": "Feature",
  "properties": {
    "addr:full":"6003 N Kings Hwy Myrtle Beach SC 29577",
    "addr:housenumber":"6003",
    "addr:postcode":"29577",
    "addr:street":"N Kings Hwy",
    "iso:country":"US",
    "sg:address":"6003 N Kings Hwy",
    "sg:city":"Myrtle Beach",
    "sg:classifiers":[
        {
            "category":"Bars & Pubs",
            "type":"Food & Drink"
        }
    ],
    "sg:phone":"+1 843 497 5450",
    "sg:postcode":"29577",
    "sg:province":"SC",
    "sg:tags":[
        "grill",
        "bar"
    ],
    "wof:name":"Jimmagan's",
    "wof:placetype":"venue"
},
  "geometry": {"coordinates":[-78.832695,33.735447],"type":"Point"}
}