{
  "type": "Feature",
  "properties": {
    "addr:full":"116 N Congress St York SC 29745",
    "addr:housenumber":"116",
    "addr:postcode":"29745",
    "addr:street":"N Congress St",
    "iso:country":"US",
    "sg:address":"116 N Congress St",
    "sg:city":"York",
    "sg:classifiers":[
        {
            "category":"Government",
            "subcategory":"Office",
            "type":"Public Place"
        }
    ],
    "sg:phone":"+1 803 684 7004",
    "sg:postcode":"29745",
    "sg:province":"SC",
    "sg:tags":[
        "county",
        "program",
        "health"
    ],
    "wof:name":"York County Health Dept",
    "wof:placetype":"venue"
},
  "geometry": {"coordinates":[-81.238775,34.998397],"type":"Point"}
}