{
  "type": "Feature",
  "properties": {
    "addr:full":"2203 Bacons Bridge Rd Summerville SC 29485",
    "addr:housenumber":"2203",
    "addr:postcode":"29485",
    "addr:street":"Bacons Bridge Rd",
    "iso:country":"US",
    "sg:address":"2203 Bacons Bridge Rd",
    "sg:city":"Summerville",
    "sg:classifiers":[
        {
            "category":"Wholesale",
            "subcategory":"Farm Supplies",
            "type":"Manufacturing & Wholesale Goods"
        }
    ],
    "sg:phone":"+1 843 873 5934",
    "sg:postcode":"29485",
    "sg:province":"SC",
    "wof:name":"Mr Pinestraw",
    "wof:placetype":"venue"
},
  "geometry": {"coordinates":[-80.199541,32.969786],"type":"Point"}
}