{
  "type": "Feature",
  "properties": {
    "iso:country":"US",
    "sg:address":"1901 Assembly St",
    "sg:city":"Columbia",
    "sg:classifiers":[
        {
            "category":"Banks & Credit Unions",
            "subcategory":"Bank",
            "type":"Services"
        }
    ],
    "sg:phone":"+1 803 251 1300",
    "sg:postcode":"29201",
    "sg:province":"SC",
    "sg:website":"www.bbandt.com",
    "wof:name":"B B & T",
    "wof:placetype":"venue"
},
  "geometry": {"coordinates":[-81.03998799999999,34.011441],"type":"Point"}
}