{
  "type": "Feature",
  "properties": {
    "iso:country":"US",
    "sg:address":"614 12th St",
    "sg:city":"West Columbia",
    "sg:classifiers":[
        {
            "category":"Shopping",
            "subcategory":"Used Merchandise",
            "type":"Retail Goods"
        }
    ],
    "sg:phone":"+1 803 794 1221",
    "sg:postcode":"29169",
    "sg:province":"SC",
    "sg:tags":[
        "shop",
        "pawnbroker",
        "pawn"
    ],
    "wof:name":"Big John's Jewelry & Pawn",
    "wof:placetype":"venue"
},
  "geometry": {"coordinates":[-81.071899,33.985199],"type":"Point"}
}