{
  "type": "Feature",
  "properties": {
    "iso:country":"US",
    "sg:address":"2509 Ashley River Rd",
    "sg:city":"Charleston",
    "sg:classifiers":[
        {
            "category":"Shopping",
            "subcategory":"Florist",
            "type":"Retail Goods"
        }
    ],
    "sg:phone":"+1 843 852 0701",
    "sg:postcode":"29414",
    "sg:province":"SC",
    "wof:name":"Working With Nature Bonsai",
    "wof:placetype":"venue"
},
  "geometry": {"coordinates":[-80.043126,32.830587],"type":"Point"}
}