{
  "type": "Feature",
  "properties": {
    "iso:country":"US",
    "sg:address":"2482 Faber Rd",
    "sg:city":"Charleston",
    "sg:classifiers":[
        {
            "category":"Organizations",
            "subcategory":"Religious Organization",
            "type":"Services"
        }
    ],
    "sg:phone":"+1 843 225 8050",
    "sg:postcode":"29405",
    "sg:province":"SC",
    "sg:tags":[
        "church"
    ],
    "wof:name":"Joshua Baptist Church",
    "wof:placetype":"venue"
},
  "geometry": {"coordinates":[-80.014852,32.85314],"type":"Point"}
}