{
  "type": "Feature",
  "properties": {
    "addr:full":"3458 Beaver Dam Creek Rd Newberry SC 29108",
    "addr:housenumber":"3458",
    "addr:postcode":"29108",
    "addr:street":"Beaver Dam Creek Rd",
    "iso:country":"US",
    "sg:address":"3458 Beaver Dam Creek Rd",
    "sg:city":"Newberry",
    "sg:classifiers":[
        {
            "category":"Organizations",
            "subcategory":"Religious Organization",
            "type":"Services"
        }
    ],
    "sg:phone":"+1 803 276 0399",
    "sg:postcode":"29108",
    "sg:province":"SC",
    "sg:tags":[
        "church"
    ],
    "wof:name":"Old Beaver Dam Baptist Church",
    "wof:placetype":"venue"
},
  "geometry": {"coordinates":[-81.697165,34.329526],"type":"Point"}
}