{
  "type": "Feature",
  "properties": {
    "iso:country":"US",
    "sg:address":"75 Calhoun St",
    "sg:city":"Charleston",
    "sg:classifiers":[
        {
            "category":"Government",
            "subcategory":"Office",
            "type":"Public Place"
        }
    ],
    "sg:phone":"+1 843 724 3766",
    "sg:postcode":"29401",
    "sg:province":"SC",
    "sg:tags":[
        "village"
    ],
    "wof:name":"Charleston Housing & Comm Dev",
    "wof:placetype":"venue"
},
  "geometry": {"coordinates":[-79.930747,32.788212],"type":"Point"}
}