{
  "type": "Feature",
  "properties": {
    "iso:country":"US",
    "sg:address":"45 S Pointe Trce",
    "sg:city":"Bluffton",
    "sg:classifiers":[
        {
            "category":"Wholesale",
            "subcategory":"Non-durable Goods",
            "type":"Manufacturing & Wholesale Goods"
        }
    ],
    "sg:phone":"+1 843 757 8188",
    "sg:postcode":"29910",
    "sg:province":"SC",
    "sg:tags":[
        "advertising"
    ],
    "wof:name":"Palmer Enterprises",
    "wof:placetype":"venue"
},
  "geometry": {"coordinates":[-80.812254,32.233093],"type":"Point"}
}