{
  "type": "Feature",
  "properties": {
    "iso:country":"US",
    "sg:address":"414 Country Club Rd",
    "sg:city":"Newberry",
    "sg:classifiers":[
        {
            "category":"Organizations",
            "subcategory":"Community Association",
            "type":"Services"
        }
    ],
    "sg:phone":"+1 803 276 2385",
    "sg:postcode":"29108",
    "sg:province":"SC",
    "sg:tags":[
        "club"
    ],
    "wof:name":"Country Club Of Newberry",
    "wof:placetype":"venue"
},
  "geometry": {"coordinates":[-81.645495,34.303621],"type":"Point"}
}