{
  "type": "Feature",
  "properties": {
    "addr:full":"1810 E Poinsett St Exd Greer SC 29651",
    "addr:housenumber":"1810",
    "addr:postcode":"29651",
    "addr:street":"E Poinsett St Exd",
    "iso:country":"US",
    "sg:address":"1810 E Poinsett St Exd",
    "sg:city":"Greer",
    "sg:classifiers":[
        {
            "category":"Freight",
            "type":"Transportation"
        }
    ],
    "sg:phone":"+1 864 989 0210",
    "sg:postcode":"29651",
    "sg:province":"SC",
    "sg:tags":[
        "courier"
    ],
    "wof:name":"Stallion Express Courier",
    "wof:placetype":"venue"
},
  "geometry": {"coordinates":[-82.152857,34.939904],"type":"Point"}
}