{
  "type": "Feature",
  "properties": {
    "addr:full":"1257 N Old Pendleton Rd Easley SC 29642",
    "addr:housenumber":"1257",
    "addr:postcode":"29642",
    "addr:street":"N Old Pendleton Rd",
    "iso:country":"US",
    "sg:address":"1257 N Old Pendleton Rd",
    "sg:city":"Easley",
    "sg:classifiers":[
        {
            "category":"Building & Trades",
            "subcategory":"Construction",
            "type":"Services"
        }
    ],
    "sg:phone":"+1 864 855 5997",
    "sg:postcode":"29642",
    "sg:province":"SC",
    "sg:tags":[
        "contractor",
        "laying",
        "floor",
        "covering"
    ],
    "wof:name":"Carpet Coral",
    "wof:placetype":"venue"
},
  "geometry": {"coordinates":[-82.633596,34.78751],"type":"Point"}
}