{
  "type": "Feature",
  "properties": {
    "addr:full":"106 Beacon Hill Ct Easley SC 29640",
    "addr:housenumber":"106",
    "addr:postcode":"29640",
    "addr:street":"Beacon Hill Ct",
    "iso:country":"US",
    "sg:address":"106 Beacon Hill Ct",
    "sg:city":"Easley",
    "sg:classifiers":[
        {
            "category":"Recreation",
            "type":"Entertainment"
        }
    ],
    "sg:phone":"+1 864 269 2007",
    "sg:postcode":"29640",
    "sg:province":"SC",
    "sg:tags":[
        "instruction",
        "gymnastic"
    ],
    "wof:name":"Easley Gymnastics Academy",
    "wof:placetype":"venue"
},
  "geometry": {"coordinates":[-82.52012999999999,34.832356],"type":"Point"}
}