{
  "type": "Feature",
  "properties": {
    "iso:country":"US",
    "sg:address":"208 E Calhoun St",
    "sg:city":"Sumter",
    "sg:classifiers":[
        {
            "category":"Restaurant",
            "type":"Food & Drink"
        }
    ],
    "sg:menulink":"http://www.allmenus.com/sc/sumter/211013-burger-king/menu/",
    "sg:phone":"+1 803 775 3495",
    "sg:postcode":"29150",
    "sg:province":"SC",
    "sg:tags":[
        "burger",
        "american"
    ],
    "wof:name":"Burger King",
    "wof:placetype":"venue"
},
  "geometry": {"coordinates":[-80.333859,33.924363],"type":"Point"}
}