{
  "type": "Feature",
  "properties": {
    "iso:country":"US",
    "sg:address":"2601 Cobbs Way",
    "sg:city":"Anderson",
    "sg:classifiers":[
        {
            "category":"Insurance",
            "subcategory":"Insurance Agent",
            "type":"Services"
        }
    ],
    "sg:phone":"+1 864 224 3399",
    "sg:postcode":"29621",
    "sg:province":"SC",
    "sg:tags":[
        "accident"
    ],
    "wof:name":"AIS",
    "wof:placetype":"venue"
},
  "geometry": {"coordinates":[-82.596819,34.545282],"type":"Point"}
}