{
  "type": "Feature",
  "properties": {
    "iso:country":"US",
    "sg:address":"251 Spring St",
    "sg:city":"Spartanburg",
    "sg:classifiers":[
        {
            "category":"Building & Trades",
            "subcategory":"Landscaping Services",
            "type":"Services"
        }
    ],
    "sg:phone":"+1 864 578 1103",
    "sg:postcode":"29316",
    "sg:province":"SC",
    "wof:name":"Ray Owens Landscaping",
    "wof:placetype":"venue"
},
  "geometry": {"coordinates":[-82.0108,35.044191],"type":"Point"}
}