{
  "type": "Feature",
  "properties": {
    "addr:full":"432 Binnicker Bridge Rd Orangeburg SC 29115",
    "addr:housenumber":"432",
    "addr:postcode":"29115",
    "addr:street":"Binnicker Bridge Rd",
    "iso:country":"US",
    "sg:address":"432 Binnicker Bridge Rd",
    "sg:city":"Orangeburg",
    "sg:classifiers":[
        {
            "category":"Real Estate",
            "subcategory":"Real Estate Operator",
            "type":"Services"
        },
        {
            "category":"Retail",
            "subcategory":"Auto Rental",
            "type":"Services"
        }
    ],
    "sg:phone":"+1 803 531 2554",
    "sg:postcode":"29115",
    "sg:province":"SC",
    "sg:tags":[
        "mobile",
        "home",
        "leasing",
        "site"
    ],
    "wof:name":"Southgate Mobile Home Sales",
    "wof:placetype":"venue"
},
  "geometry": {"coordinates":[-80.95217599999999,33.450281],"type":"Point"}
}