{
  "type": "Feature",
  "properties": {
    "addr:full":"7705 US Hwy 76 Pendleton SC 29670",
    "addr:housenumber":"7705",
    "addr:postcode":"29670",
    "addr:street":"Us Hwy 76",
    "iso:country":"US",
    "sg:address":"7705 US Hwy 76",
    "sg:city":"Pendleton",
    "sg:classifiers":[
        {
            "category":"Home & Garden",
            "subcategory":"Furniture",
            "type":"Retail Goods"
        }
    ],
    "sg:phone":"+1 864 646 5705",
    "sg:postcode":"29670",
    "sg:province":"SC",
    "sg:tags":[
        "household",
        "appliance"
    ],
    "wof:name":"A Plus Rents Inc",
    "wof:placetype":"venue"
},
  "geometry": {"coordinates":[-82.784702,34.634833],"type":"Point"}
}