{
  "type": "Feature",
  "properties": {
    "addr:full":"1812 S 5th St Hartsville SC 29550",
    "addr:housenumber":"1812",
    "addr:postcode":"29550",
    "addr:street":"S 5Th St",
    "iso:country":"US",
    "sg:address":"1812 S 5th St",
    "sg:city":"Hartsville",
    "sg:classifiers":[
        {
            "category":"Retail",
            "subcategory":"Auto Repair",
            "type":"Services"
        }
    ],
    "sg:phone":"+1 843 332 2440",
    "sg:postcode":"29550",
    "sg:province":"SC",
    "sg:tags":[
        "automobile",
        "customizing"
    ],
    "wof:name":"Customs Plus",
    "wof:placetype":"venue"
},
  "geometry": {"coordinates":[-80.07147500000001,34.339082],"type":"Point"}
}