{
  "type": "Feature",
  "properties": {
    "iso:country":"US",
    "sg:address":"103 N Wingfield Rd",
    "sg:city":"Greer",
    "sg:classifiers":[
        {
            "category":"Wholesale",
            "subcategory":"Apparel",
            "type":"Manufacturing & Wholesale Goods"
        }
    ],
    "sg:phone":"+1 864 363 0570",
    "sg:postcode":"29650",
    "sg:province":"SC",
    "sg:tags":[
        "clothing"
    ],
    "wof:name":"Nu Charma",
    "wof:placetype":"venue"
},
  "geometry": {"coordinates":[-82.267326,34.882441],"type":"Point"}
}