{
  "type": "Feature",
  "properties": {
    "iso:country":"US",
    "sg:address":"3722 Clemson Blvd",
    "sg:city":"Anderson",
    "sg:classifiers":[
        {
            "category":"Banks & Credit Unions",
            "subcategory":"Bank",
            "type":"Services"
        }
    ],
    "sg:phone":"+1 864 226 5949",
    "sg:postcode":"29621",
    "sg:province":"SC",
    "sg:tags":[
        "loan"
    ],
    "wof:name":"Anderson Title Loans Inc",
    "wof:placetype":"venue"
},
  "geometry": {"coordinates":[-82.681137,34.55378],"type":"Point"}
}