{
  "type": "Feature",
  "properties": {
    "addr:full":"323 Jackson St Barnwell SC 29812",
    "addr:housenumber":"323",
    "addr:postcode":"29812",
    "addr:street":"Jackson St",
    "iso:country":"US",
    "sg:address":"323 Jackson St",
    "sg:city":"Barnwell",
    "sg:classifiers":[
        {
            "category":"Professional",
            "subcategory":"Lawyer & Legal Services",
            "type":"Services"
        }
    ],
    "sg:phone":"+1 803 541 7107",
    "sg:postcode":"29812",
    "sg:province":"SC",
    "sg:tags":[
        "attorney"
    ],
    "wof:name":"Koger Law Firm",
    "wof:placetype":"venue"
},
  "geometry": {"coordinates":[-81.36016100000001,33.226971],"type":"Point"}
}