{
  "type": "Feature",
  "properties": {
    "iso:country":"US",
    "sg:address":"1175 N Fraser St",
    "sg:city":"Georgetown",
    "sg:classifiers":[
        {
            "category":"Shopping",
            "subcategory":"Used Merchandise",
            "type":"Retail Goods"
        }
    ],
    "sg:phone":"+1 843 520 5885",
    "sg:postcode":"29440",
    "sg:province":"SC",
    "sg:tags":[
        "shop",
        "thrift"
    ],
    "wof:name":"Second Chance",
    "wof:placetype":"venue"
},
  "geometry": {"coordinates":[-79.28868900000001,33.386403],"type":"Point"}
}