{
  "type": "Feature",
  "properties": {
    "iso:country":"US",
    "sg:address":"707 Saluda Ave",
    "sg:city":"Columbia",
    "sg:classifiers":[
        {
            "category":"Shopping",
            "subcategory":"Shoes",
            "type":"Retail Goods"
        }
    ],
    "sg:phone":"+1 803 343 0730",
    "sg:postcode":"29205",
    "sg:province":"SC",
    "sg:tags":[
        "store"
    ],
    "wof:name":"Sophie Shoes",
    "wof:placetype":"venue"
},
  "geometry": {"coordinates":[-81.017684,33.998623],"type":"Point"}
}