{
  "type": "Feature",
  "properties": {
    "iso:country":"US",
    "sg:address":"536 Cheraw St",
    "sg:city":"Bennettsville",
    "sg:classifiers":[
        {
            "category":"Shopping",
            "subcategory":"Clothing, Apparel, & Fashions",
            "type":"Retail Goods"
        }
    ],
    "sg:phone":"+1 843 479 8159",
    "sg:postcode":"29512",
    "sg:province":"SC",
    "wof:name":"Knights Workout Center",
    "wof:placetype":"venue"
},
  "geometry": {"coordinates":[-79.690166,34.623406],"type":"Point"}
}