{
  "type": "Feature",
  "properties": {
    "iso:country":"US",
    "sg:address":"101 N Main St",
    "sg:city":"Sumter",
    "sg:classifiers":[
        {
            "category":"Personal",
            "subcategory":"Beauty Salon",
            "type":"Services"
        }
    ],
    "sg:phone":"+1 803 778 2213",
    "sg:postcode":"29150",
    "sg:province":"SC",
    "wof:name":"Beauty Palace",
    "wof:placetype":"venue"
},
  "geometry": {"coordinates":[-80.341493,33.922354],"type":"Point"}
}