{
  "type": "Feature",
  "properties": {
    "addr:full":"95 Governors Rd Hilton Head Island SC 29928",
    "addr:housenumber":"95",
    "addr:postcode":"29928",
    "addr:street":"Governors Rd",
    "iso:country":"US",
    "sg:address":"95 Governors Rd",
    "sg:city":"Hilton Head Island",
    "sg:classifiers":[
        {
            "category":"Real Estate",
            "subcategory":"Real Estate Agent",
            "type":"Services"
        }
    ],
    "sg:phone":"+1 843 301 4321",
    "sg:postcode":"29928",
    "sg:province":"SC",
    "wof:name":"Confetti",
    "wof:placetype":"venue"
},
  "geometry": {"coordinates":[-80.78652700000001,32.149456],"type":"Point"}
}