{
  "type": "Feature",
  "properties": {
    "addr:full":"199 Cedar Springs Rd Spartanburg SC 29302",
    "addr:housenumber":"199",
    "addr:postcode":"29302",
    "addr:street":"Cedar Springs Rd",
    "iso:country":"US",
    "sg:address":"199 Cedar Springs Rd",
    "sg:city":"Spartanburg",
    "sg:classifiers":[
        {
            "category":"Restaurant",
            "type":"Food & Drink"
        }
    ],
    "sg:menulink":"http://www.allmenus.com/sc/spartanburg/200980-mcdonalds/menu/",
    "sg:postcode":"29302",
    "sg:province":"SC",
    "sg:tags":[
        "burger",
        "american"
    ],
    "wof:name":"McDonald's",
    "wof:placetype":"venue"
},
  "geometry": {"coordinates":[-81.88634399999999,34.921095],"type":"Point"}
}