{
  "type": "Feature",
  "properties": {
    "addr:full":"1017 Pocket Rd Darlington SC 29532",
    "addr:housenumber":"1017",
    "addr:postcode":"29532",
    "addr:street":"Pocket Rd",
    "iso:country":"US",
    "sg:address":"1017 Pocket Rd",
    "sg:city":"Darlington",
    "sg:classifiers":[
        {
            "category":"Freight",
            "type":"Transportation"
        }
    ],
    "sg:phone":"+1 843 393 6148",
    "sg:postcode":"29532",
    "sg:province":"SC",
    "sg:tags":[
        "operator",
        "trucking"
    ],
    "wof:name":"Careys Auto Transport Inc",
    "wof:placetype":"venue"
},
  "geometry": {"coordinates":[-79.812275,34.302101],"type":"Point"}
}