{
  "type": "Feature",
  "properties": {
    "iso:country":"US",
    "sg:address":"102 Express Ln",
    "sg:city":"Darlington",
    "sg:classifiers":[
        {
            "category":"Shopping",
            "subcategory":"Pharmacy",
            "type":"Retail Goods"
        }
    ],
    "sg:phone":"+1 843 395 6448",
    "sg:postcode":"29532",
    "sg:province":"SC",
    "wof:name":"CVS Pharmacy",
    "wof:placetype":"venue"
},
  "geometry": {"coordinates":[-79.858232,34.283726],"type":"Point"}
}