{
  "type": "Feature",
  "properties": {
    "addr:full":"103 E College St Simpsonville SC 29681",
    "addr:housenumber":"103",
    "addr:postcode":"29681",
    "addr:street":"E College St",
    "iso:country":"US",
    "sg:address":"103 E College St",
    "sg:city":"Simpsonville",
    "sg:classifiers":[
        {
            "category":"Retail",
            "subcategory":"Auto Repair",
            "type":"Services"
        }
    ],
    "sg:phone":"+1 864 962 6712",
    "sg:postcode":"29681",
    "sg:province":"SC",
    "sg:tags":[
        "repairing",
        "automobile"
    ],
    "wof:name":"All Car",
    "wof:placetype":"venue"
},
  "geometry": {"coordinates":[-82.254739,34.739594],"type":"Point"}
}