{
  "type": "Feature",
  "properties": {
    "iso:country":"US",
    "sg:address":"32 Long St",
    "sg:city":"Spartanburg",
    "sg:classifiers":[
        {
            "category":"Building & Trades",
            "subcategory":"Construction",
            "type":"Services"
        }
    ],
    "sg:phone":"+1 864 585 7821",
    "sg:postcode":"29307",
    "sg:province":"SC",
    "sg:tags":[
        "contractor"
    ],
    "wof:name":"A One Fence",
    "wof:placetype":"venue"
},
  "geometry": {"coordinates":[-81.903301,34.983308],"type":"Point"}
}