{
  "type": "Feature",
  "properties": {
    "iso:country":"US",
    "sg:address":"75 Forest Ln",
    "sg:city":"Greenville",
    "sg:classifiers":[
        {
            "category":"Real Estate",
            "subcategory":"Real Estate Agent",
            "type":"Services"
        },
        {
            "category":"Banks & Credit Unions",
            "subcategory":"Financial Services",
            "type":"Services"
        }
    ],
    "sg:phone":"+1 864 271 6761",
    "sg:postcode":"29605",
    "sg:province":"SC",
    "sg:tags":[
        "company",
        "holding"
    ],
    "wof:name":"Fields Properties LLC",
    "wof:placetype":"venue"
},
  "geometry": {"coordinates":[-82.39792799999999,34.812977],"type":"Point"}
}