{
  "type": "Feature",
  "properties": {
    "addr:full":"113 Athena Ln Lexington SC 29072",
    "addr:housenumber":"113",
    "addr:postcode":"29072",
    "addr:street":"Athena Ln",
    "iso:country":"US",
    "sg:address":"113 Athena Ln",
    "sg:city":"Lexington",
    "sg:classifiers":[
        {
            "category":"Building & Trades",
            "subcategory":"Construction",
            "type":"Services"
        }
    ],
    "sg:phone":"+1 803 996 0378",
    "sg:postcode":"29072",
    "sg:province":"SC",
    "sg:tags":[
        "house"
    ],
    "wof:name":"Core Construction Co Inc",
    "wof:placetype":"venue"
},
  "geometry": {"coordinates":[-81.21266199999999,33.983054],"type":"Point"}
}