{
  "type": "Feature",
  "properties": {
    "iso:country":"US",
    "sg:address":"304 Huggins St",
    "sg:city":"Marion",
    "sg:classifiers":[
        {
            "category":"Social Services",
            "subcategory":"Child Care",
            "type":"Services"
        }
    ],
    "sg:phone":"+1 843 423 2077",
    "sg:postcode":"29571",
    "sg:province":"SC",
    "wof:name":"Agapeland Day Care Ctr",
    "wof:placetype":"venue"
},
  "geometry": {"coordinates":[-79.405315,34.168782],"type":"Point"}
}