{
  "type": "Feature",
  "properties": {
    "addr:full":"69 Barre St Charleston SC 29401",
    "addr:housenumber":"69",
    "addr:postcode":"29401",
    "addr:street":"Barre St",
    "iso:country":"US",
    "sg:address":"69 Barre St",
    "sg:city":"Charleston",
    "sg:classifiers":[
        {
            "category":"Health Services",
            "subcategory":"Clinic",
            "type":"Services"
        }
    ],
    "sg:phone":"+1 843 723 7771",
    "sg:postcode":"29401",
    "sg:province":"SC",
    "sg:tags":[
        "information",
        "program",
        "referral"
    ],
    "wof:name":"Susan G Komen Breast Cancer",
    "wof:placetype":"venue"
},
  "geometry": {"coordinates":[-79.94749400000001,32.782353],"type":"Point"}
}