{
  "type": "Feature",
  "properties": {
    "addr:full":"5458 State Hwy 34 Pomaria SC 29126",
    "addr:housenumber":"5458",
    "addr:postcode":"29126",
    "addr:street":"State Hwy 34",
    "iso:country":"US",
    "sg:address":"5458 State Hwy 34",
    "sg:city":"Pomaria",
    "sg:classifiers":[
        {
            "category":"Manufacturing",
            "subcategory":"Lumber",
            "type":"Manufacturing & Wholesale Goods"
        }
    ],
    "sg:phone":"+1 803 276 5123",
    "sg:postcode":"29126",
    "sg:province":"SC",
    "sg:tags":[
        "company",
        "logging"
    ],
    "wof:name":"Olin Lominick Timber Co",
    "wof:placetype":"venue"
},
  "geometry": {"coordinates":[-81.47557,34.353272],"type":"Point"}
}