{
  "type": "Feature",
  "properties": {
    "iso:country":"US",
    "sg:address":"10 Cutting Horse Ct",
    "sg:city":"Simpsonville",
    "sg:classifiers":[
        {
            "category":"Real Estate",
            "subcategory":"Real Estate Operator",
            "type":"Services"
        }
    ],
    "sg:phone":"+1 864 228 0078",
    "sg:postcode":"29680",
    "sg:province":"SC",
    "sg:tags":[
        "building",
        "nonresidential"
    ],
    "wof:name":"Glad Properties LLC",
    "wof:placetype":"venue"
},
  "geometry": {"coordinates":[-82.287559,34.703328],"type":"Point"}
}