{
  "type": "Feature",
  "properties": {
    "addr:full":"213 W Main St Dillon SC 29536",
    "addr:housenumber":"213",
    "addr:postcode":"29536",
    "addr:street":"W Main St",
    "iso:country":"US",
    "sg:address":"213 W Main St",
    "sg:city":"Dillon",
    "sg:classifiers":[
        {
            "category":"Shopping",
            "subcategory":"Optical Goods",
            "type":"Retail Goods"
        }
    ],
    "sg:phone":"+1 843 774 8112",
    "sg:postcode":"29536",
    "sg:province":"SC",
    "wof:name":"Vision Care PA",
    "wof:placetype":"venue"
},
  "geometry": {"coordinates":[-79.37457000000001,34.418279],"type":"Point"}
}