{
  "type": "Feature",
  "properties": {
    "iso:country":"US",
    "sg:address":"887 US Hwy 78",
    "sg:city":"Ridgeville",
    "sg:classifiers":[
        {
            "category":"Building & Trades",
            "subcategory":"Construction",
            "type":"Services"
        }
    ],
    "sg:phone":"+1 843 821 8340",
    "sg:postcode":"29483",
    "sg:province":"SC",
    "sg:tags":[
        "pavement",
        "marking"
    ],
    "wof:name":"Carolina Highway Svc",
    "wof:placetype":"venue"
},
  "geometry": {"coordinates":[-80.243303,33.062285],"type":"Point"}
}