{
  "type": "Feature",
  "properties": {
    "iso:country":"US",
    "sg:address":"2303 Harllees Bridge Rd",
    "sg:city":"Hamer",
    "sg:classifiers":[
        {
            "category":"Food & Beverages",
            "subcategory":"Groceries & Convenience Stores",
            "type":"Retail Goods"
        }
    ],
    "sg:phone":"+1 843 841 2575",
    "sg:postcode":"29547",
    "sg:province":"SC",
    "wof:name":"Harley's Store",
    "wof:placetype":"venue"
},
  "geometry": {"coordinates":[-79.361688,34.510623],"type":"Point"}
}