{
  "type": "Feature",
  "properties": {
    "iso:country":"US",
    "sg:address":"1168 Trojan Rd",
    "sg:city":"Cross",
    "sg:classifiers":[
        {
            "category":"Travel",
            "subcategory":"Campground",
            "type":"Entertainment"
        }
    ],
    "sg:phone":"+1 843 753 7720",
    "sg:postcode":"29436",
    "sg:province":"SC",
    "wof:name":"Eagle's Nest Campground & Rv",
    "wof:placetype":"venue"
},
  "geometry": {"coordinates":[-80.16099699999999,33.361461],"type":"Point"}
}