{
  "type": "Feature",
  "properties": {
    "iso:country":"US",
    "sg:address":"1207 Lakeside Dr",
    "sg:city":"Conway",
    "sg:classifiers":[
        {
            "category":"Health Services",
            "subcategory":"Doctor",
            "type":"Services"
        }
    ],
    "sg:phone":"+1 843 248 3919",
    "sg:postcode":"29526",
    "sg:province":"SC",
    "sg:tags":[
        "dentist"
    ],
    "wof:name":"Endicott Dental Care",
    "wof:placetype":"venue"
},
  "geometry": {"coordinates":[-79.049502,33.848512],"type":"Point"}
}