{
  "type": "Feature",
  "properties": {
    "iso:country":"US",
    "sg:address":"2406 Old Edisto Dr",
    "sg:city":"Orangeburg",
    "sg:classifiers":[
        {
            "category":"Shopping",
            "type":"Retail Goods"
        }
    ],
    "sg:phone":"+1 803 536 2519",
    "sg:postcode":"29115",
    "sg:province":"SC",
    "sg:tags":[
        "pet",
        "food",
        "supply"
    ],
    "wof:name":"Dog Food Ctr",
    "wof:placetype":"venue"
},
  "geometry": {"coordinates":[-80.895848,33.480823],"type":"Point"}
}