{
  "type": "Feature",
  "properties": {
    "iso:country":"US",
    "sg:address":"5 S Pacific Ave",
    "sg:city":"York",
    "sg:classifiers":[
        {
            "category":"Social Services",
            "subcategory":"Child Care",
            "type":"Services"
        }
    ],
    "sg:phone":"+1 803 684 6211",
    "sg:postcode":"29745",
    "sg:province":"SC",
    "wof:name":"Agape United Day Care",
    "wof:placetype":"venue"
},
  "geometry": {"coordinates":[-81.221913,34.986767],"type":"Point"}
}