{
  "type": "Feature",
  "properties": {
    "iso:country":"US",
    "sg:address":"102 Northwest Dr",
    "sg:city":"Anderson",
    "sg:classifiers":[
        {
            "category":"Insurance",
            "subcategory":"Insurance Agent",
            "type":"Services"
        }
    ],
    "sg:phone":"+1 864 224 4707",
    "sg:postcode":"29625",
    "sg:province":"SC",
    "wof:name":"Woodmen Of The World Insurance",
    "wof:placetype":"venue"
},
  "geometry": {"coordinates":[-82.687091,34.533884],"type":"Point"}
}