{
  "type": "Feature",
  "properties": {
    "addr:full":"301 Pine Hill Rd St Matthews SC 29135",
    "addr:housenumber":"301",
    "addr:postcode":"29135",
    "addr:street":"Pine Hill Rd",
    "iso:country":"US",
    "sg:address":"301 Pine Hill Rd",
    "sg:city":"St Matthews",
    "sg:classifiers":[
        {
            "category":"Shopping",
            "subcategory":"Jewelry",
            "type":"Retail Goods"
        }
    ],
    "sg:phone":"+1 803 655 5488",
    "sg:postcode":"29135",
    "sg:province":"SC",
    "sg:tags":[
        "jeweler"
    ],
    "wof:name":"Caroline's",
    "wof:placetype":"venue"
},
  "geometry": {"coordinates":[-80.773888,33.6579],"type":"Point"}
}