{
  "type": "Feature",
  "properties": {
    "iso:country":"US",
    "sg:address":"3275 N Pleasantburg Dr",
    "sg:city":"Greenville",
    "sg:classifiers":[
        {
            "category":"Personal",
            "subcategory":"Tanning Parlor",
            "type":"Services"
        }
    ],
    "sg:phone":"+1 864 232 1103",
    "sg:postcode":"29609",
    "sg:province":"SC",
    "sg:tags":[
        "salon"
    ],
    "sg:website":"www.ultratans.com",
    "wof:name":"Ultra Tan",
    "wof:placetype":"venue"
},
  "geometry": {"coordinates":[-82.399289,34.88892],"type":"Point"}
}