{
  "type": "Feature",
  "properties": {
    "iso:country":"US",
    "sg:address":"459 Riverside Dr SW",
    "sg:city":"Orangeburg",
    "sg:classifiers":[
        {
            "category":"Shopping",
            "subcategory":"Department Store",
            "type":"Retail Goods"
        }
    ],
    "sg:phone":"+1 803 534 4879",
    "sg:postcode":"29115",
    "sg:province":"SC",
    "sg:tags":[
        "shop"
    ],
    "wof:name":"Family Dollar Store",
    "wof:placetype":"venue"
},
  "geometry": {"coordinates":[-80.875384,33.489356],"type":"Point"}
}