{
  "type": "Feature",
  "properties": {
    "addr:full":"3775 Maybank Hwy Johns Island SC 29455",
    "addr:housenumber":"3775",
    "addr:postcode":"29455",
    "addr:street":"Maybank Hwy",
    "iso:country":"US",
    "sg:address":"3775 Maybank Hwy",
    "sg:city":"Johns Island",
    "sg:classifiers":[
        {
            "category":"Restaurant",
            "type":"Food & Drink"
        }
    ],
    "sg:phone":"+1 843 559 5206",
    "sg:postcode":"29455",
    "sg:province":"SC",
    "sg:tags":[
        "eating"
    ],
    "wof:name":"Peking Gourmet",
    "wof:placetype":"venue"
},
  "geometry": {"coordinates":[-80.086888,32.716963],"type":"Point"}
}