{
  "type": "Feature",
  "properties": {
    "iso:country":"US",
    "sg:address":"516 Epting Ave",
    "sg:city":"Greenwood",
    "sg:classifiers":[
        {
            "category":"Wholesale",
            "subcategory":"Medical Equipment & Supplies",
            "type":"Manufacturing & Wholesale Goods"
        },
        {
            "category":"Shopping",
            "type":"Retail Goods"
        }
    ],
    "sg:phone":"+1 864 223 4663",
    "sg:postcode":"29646",
    "sg:province":"SC",
    "sg:tags":[
        "physician",
        "durable",
        "surgeon",
        "lease"
    ],
    "wof:name":"Parrish Home Medical Inc",
    "wof:placetype":"venue"
},
  "geometry": {"coordinates":[-82.159705,34.171653],"type":"Point"}
}