{
  "type": "Feature",
  "properties": {
    "addr:full":"8251 Chisolm Plantation Rd Edisto Island SC 29438",
    "addr:housenumber":"8251",
    "addr:postcode":"29438",
    "addr:street":"Chisolm Plantation Rd",
    "iso:country":"US",
    "sg:address":"8251 Chisolm Plantation Rd",
    "sg:city":"Edisto Island",
    "sg:classifiers":[
        {
            "category":"Professional",
            "subcategory":"Engineering",
            "type":"Services"
        }
    ],
    "sg:phone":"+1 843 869 1690",
    "sg:postcode":"29438",
    "sg:province":"SC",
    "sg:tags":[
        "engineer"
    ],
    "wof:name":"Joseph Engineering & Sales",
    "wof:placetype":"venue"
},
  "geometry": {"coordinates":[-80.33326099999999,32.564124],"type":"Point"}
}