{
  "type": "Feature",
  "properties": {
    "iso:country":"US",
    "sg:address":"4342 Quail Dr",
    "sg:city":"Beaufort",
    "sg:classifiers":[
        {
            "category":"Home & Garden",
            "subcategory":"Carpets & Floor Coverings",
            "type":"Retail Goods"
        }
    ],
    "sg:phone":"+1 843 846 8924",
    "sg:postcode":"29906",
    "sg:province":"SC",
    "sg:tags":[
        "blind",
        "mini",
        "drapery",
        "clean"
    ],
    "wof:name":"J M Callaha Services",
    "wof:placetype":"venue"
},
  "geometry": {"coordinates":[-80.776172,32.463819],"type":"Point"}
}