{
  "type": "Feature",
  "properties": {
    "iso:country":"US",
    "sg:address":"1298 State Hwy 9 W",
    "sg:city":"Longs",
    "sg:classifiers":[
        {
            "category":"Organizations",
            "subcategory":"Religious Organization",
            "type":"Services"
        }
    ],
    "sg:phone":"+1 843 756 4360",
    "sg:postcode":"29568",
    "sg:province":"SC",
    "sg:tags":[
        "church"
    ],
    "wof:name":"Christian Church NMB",
    "wof:placetype":"venue"
},
  "geometry": {"coordinates":[-78.74069799999999,33.969921],"type":"Point"}
}